{
  "type": "Feature",
  "properties": {
    "iso:country":"US",
    "sg:address":"217 Wright Well Rd",
    "sg:city":"Pinon",
    "sg:classifiers":[
        {
            "category":"Farming",
            "subcategory":"Livestock Farm",
            "type":"Manufacturing & Wholesale Goods"
        }
    ],
    "sg:phone":"+1 505 687 3455",
    "sg:postcode":"88344",
    "sg:province":"NM",
    "sg:tags":[
        "ranch"
    ],
    "wof:name":"James R Everage Ranch",
    "wof:placetype":"venue"
},
  "geometry": {"coordinates":[-105.254514,32.646302],"type":"Point"}
}