{
  "type": "Feature",
  "properties": {
    "iso:country":"US",
    "sg:address":"505 W 18th St",
    "sg:city":"Portales",
    "sg:classifiers":[
        {
            "category":"Cinema",
            "subcategory":"Movie Rental",
            "type":"Entertainment"
        }
    ],
    "sg:phone":"+1 505 359 0039",
    "sg:postcode":"88130",
    "sg:province":"NM",
    "sg:tags":[
        "leasing",
        "video",
        "disc",
        "tape"
    ],
    "wof:name":"Video World",
    "wof:placetype":"venue"
},
  "geometry": {"coordinates":[-103.334992,34.171303],"type":"Point"}
}