{
  "type": "Feature",
  "properties": {
    "addr:full":"5021 Indian School Rd NE Albuquerque NM 87110",
    "addr:housenumber":"5021",
    "addr:postcode":"87110",
    "addr:street":"Indian School Rd Ne",
    "iso:country":"US",
    "sg:address":"5021 Indian School Rd NE",
    "sg:city":"Albuquerque",
    "sg:classifiers":[
        {
            "category":"Utilities",
            "subcategory":"Telephone",
            "type":"Services"
        },
        {
            "category":"Professional",
            "subcategory":"Computer Services",
            "type":"Services"
        }
    ],
    "sg:phone":"+1 505 232 7992",
    "sg:postcode":"87110",
    "sg:province":"NM",
    "sg:tags":[
        "provider",
        "internet"
    ],
    "sg:website":"www.swcp.com",
    "wof:name":"Southwest Cyberport Inc",
    "wof:placetype":"venue"
},
  "geometry": {"coordinates":[-106.587757,35.101981],"type":"Point"}
}