{
  "type": "Feature",
  "properties": {
    "iso:country":"US",
    "sg:address":"10 Cuesta Ln",
    "sg:city":"Santa Fe",
    "sg:classifiers":[
        {
            "category":"Retail",
            "subcategory":"Photofinishing",
            "type":"Services"
        }
    ],
    "sg:phone":"+1 505 466 8315",
    "sg:postcode":"87508",
    "sg:province":"NM",
    "sg:tags":[
        "laboratory"
    ],
    "wof:name":"Scott D Christpher Photography",
    "wof:placetype":"venue"
},
  "geometry": {"coordinates":[-105.912137,35.535211],"type":"Point"}
}