{
  "type": "Feature",
  "properties": {
    "iso:country":"US",
    "sg:address":"3531 State Hwy 528",
    "sg:city":"Albuquerque",
    "sg:classifiers":[
        {
            "category":"Restaurant",
            "type":"Food & Drink"
        }
    ],
    "sg:phone":"+1 505 890 0936",
    "sg:postcode":"87114",
    "sg:province":"NM",
    "sg:tags":[
        "eating"
    ],
    "sg:website":"www.whataburger.com",
    "wof:name":"Whataburger",
    "wof:placetype":"venue"
},
  "geometry": {"coordinates":[-106.651184,35.206396],"type":"Point"}
}