{
  "type": "Feature",
  "properties": {
    "iso:country":"US",
    "sg:address":"5300 Sequoia Rd NW",
    "sg:city":"Albuquerque",
    "sg:classifiers":[
        {
            "category":"Personal",
            "subcategory":"Beauty Salon",
            "type":"Services"
        }
    ],
    "sg:phone":"+1 505 710 0087",
    "sg:postcode":"87120",
    "sg:province":"NM",
    "wof:name":"Westside Hair Styles",
    "wof:placetype":"venue"
},
  "geometry": {"coordinates":[-106.69664299999999,35.122172],"type":"Point"}
}