{
  "type": "Feature",
  "properties": {
    "addr:full":"420 Coal Ave SE Albuquerque NM 87102",
    "addr:housenumber":"420",
    "addr:postcode":"87102",
    "addr:street":"Coal Ave Se",
    "iso:country":"US",
    "sg:address":"420 Coal Ave SE",
    "sg:city":"Albuquerque",
    "sg:classifiers":[
        {
            "category":"Organizations",
            "subcategory":"Non-profit Organization",
            "type":"Services"
        }
    ],
    "sg:phone":"+1 505 842 1078",
    "sg:postcode":"87102",
    "sg:province":"NM",
    "sg:tags":[
        "apartment",
        "human"
    ],
    "wof:name":"El Paseo Village Inc",
    "wof:placetype":"venue"
},
  "geometry": {"coordinates":[-106.64386500000001,35.079538],"type":"Point"}
}