{
  "type": "Feature",
  "properties": {
    "iso:country":"US",
    "sg:address":"3101 Old Pecos Trl",
    "sg:city":"Santa Fe",
    "sg:classifiers":[
        {
            "category":"Real Estate",
            "subcategory":"Real Estate Agent",
            "type":"Services"
        }
    ],
    "sg:phone":"+1 505 988 3210",
    "sg:postcode":"87505",
    "sg:province":"NM",
    "wof:name":"Templeton Properties",
    "wof:placetype":"venue"
},
  "geometry": {"coordinates":[-105.928839,35.63872],"type":"Point"}
}