{
  "type": "Feature",
  "properties": {
    "iso:country":"US",
    "sg:address":"1409 2nd St",
    "sg:city":"Santa Fe",
    "sg:classifiers":[
        {
            "category":"Social Services",
            "subcategory":"Child Care",
            "type":"Services"
        }
    ],
    "sg:phone":"+1 505 954 4601",
    "sg:postcode":"87505",
    "sg:province":"NM",
    "wof:name":"Presbyterian Medical Svc",
    "wof:placetype":"venue"
},
  "geometry": {"coordinates":[-105.968908,35.666309],"type":"Point"}
}