{
  "type": "Feature",
  "properties": {
    "iso:country":"US",
    "sg:address":"7 Saddle Ct",
    "sg:city":"Santa Fe",
    "sg:classifiers":[
        {
            "category":"Building & Trades",
            "subcategory":"Construction",
            "type":"Services"
        }
    ],
    "sg:phone":"+1 505 955 9663",
    "sg:postcode":"87508",
    "sg:province":"NM",
    "sg:tags":[
        "woodworker"
    ],
    "wof:name":"Mark Bressler's Dancing",
    "wof:placetype":"venue"
},
  "geometry": {"coordinates":[-105.90446,35.583698],"type":"Point"}
}