{
  "type": "Feature",
  "properties": {
    "iso:country":"US",
    "sg:address":"1400 Barbara Loop SE",
    "sg:city":"Rio Rancho",
    "sg:classifiers":[
        {
            "category":"Health Services",
            "subcategory":"Chiropractor",
            "type":"Services"
        }
    ],
    "sg:phone":"+1 505 891 2667",
    "sg:postcode":"87124",
    "sg:province":"NM",
    "wof:name":"B & B Chiropractic",
    "wof:placetype":"venue"
},
  "geometry": {"coordinates":[-106.653741,35.233844],"type":"Point"}
}