{
  "type": "Feature",
  "properties": {
    "iso:country":"US",
    "sg:address":"623 W Reinken Ave",
    "sg:city":"Belen",
    "sg:classifiers":[
        {
            "category":"Banks & Credit Unions",
            "subcategory":"Bank",
            "type":"Services"
        }
    ],
    "sg:phone":"+1 505 864 0010",
    "sg:postcode":"87002",
    "sg:province":"NM",
    "sg:tags":[
        "institution"
    ],
    "wof:name":"Your Credit",
    "wof:placetype":"venue"
},
  "geometry": {"coordinates":[-106.78143,34.663357],"type":"Point"}
}