{
  "type": "Feature",
  "properties": {
    "iso:country":"US",
    "sg:address":"1401 N Turner St",
    "sg:city":"Hobbs",
    "sg:classifiers":[
        {
            "category":"Shopping",
            "subcategory":"Bicycles & Sporting Goods",
            "type":"Retail Goods"
        }
    ],
    "sg:phone":"+1 505 393 0541",
    "sg:postcode":"88240",
    "sg:province":"NM",
    "wof:name":"Athletic Supply Inc",
    "wof:placetype":"venue"
},
  "geometry": {"coordinates":[-103.13875400000001,32.715716],"type":"Point"}
}