{
  "type": "Feature",
  "properties": {
    "iso:country":"US",
    "sg:address":"14305 Central Ave NW",
    "sg:city":"Albuquerque",
    "sg:classifiers":[
        {
            "category":"Utilities",
            "subcategory":"Fuel Oil & Lpg",
            "type":"Services"
        }
    ],
    "sg:phone":"+1 505 836 4772",
    "sg:postcode":"87121",
    "sg:province":"NM",
    "sg:tags":[
        "petroleum",
        "r",
        "gas",
        "liquid"
    ],
    "wof:name":"R&L Enterprises",
    "wof:placetype":"venue"
},
  "geometry": {"coordinates":[-106.781042,35.064112],"type":"Point"}
}