{
  "type": "Feature",
  "properties": {
    "iso:country":"US",
    "sg:address":"2511 N Telshor Blvd",
    "sg:city":"Las Cruces",
    "sg:classifiers":[
        {
            "category":"Building & Trades",
            "subcategory":"Construction",
            "type":"Services"
        }
    ],
    "sg:phone":"+1 505 521 4840",
    "sg:postcode":"88011",
    "sg:province":"NM",
    "sg:tags":[
        "general",
        "contractor"
    ],
    "sg:website":"www.johncurry.com",
    "wof:name":"John Curry Construction",
    "wof:placetype":"venue"
},
  "geometry": {"coordinates":[-106.765659,32.346538],"type":"Point"}
}