{
  "type": "Feature",
  "properties": {
    "iso:country":"US",
    "sg:address":"2320 Robles St",
    "sg:city":"Clovis",
    "sg:classifiers":[
        {
            "category":"Building & Trades",
            "subcategory":"Construction",
            "type":"Services"
        }
    ],
    "sg:phone":"+1 505 763 8757",
    "sg:postcode":"88101",
    "sg:province":"NM",
    "sg:tags":[
        "house"
    ],
    "wof:name":"Clovis Handyman",
    "wof:placetype":"venue"
},
  "geometry": {"coordinates":[-103.232718,34.402386],"type":"Point"}
}