{
  "type": "Feature",
  "properties": {
    "addr:full":"2114 Hendola Dr NE Albuquerque NM 87110",
    "addr:housenumber":"2114",
    "addr:postcode":"87110",
    "addr:street":"Hendola Dr Ne",
    "iso:country":"US",
    "sg:address":"2114 Hendola Dr NE",
    "sg:city":"Albuquerque",
    "sg:classifiers":[
        {
            "category":"Building & Trades",
            "subcategory":"Construction",
            "type":"Services"
        }
    ],
    "sg:phone":"+1 505 259 3420",
    "sg:postcode":"87110",
    "sg:province":"NM",
    "sg:tags":[
        "builder",
        "operative"
    ],
    "wof:name":"Golden Horn Corp",
    "wof:placetype":"venue"
},
  "geometry": {"coordinates":[-106.556892,35.104145],"type":"Point"}
}