{
  "type": "Feature",
  "properties": {
    "iso:country":"US",
    "sg:address":"4015 Clinton Blvd SW",
    "sg:city":"Albuquerque",
    "sg:classifiers":[
        {
            "category":"Shopping",
            "subcategory":"Florist",
            "type":"Retail Goods"
        }
    ],
    "sg:phone":"+1 505 877 0022",
    "sg:postcode":"87105",
    "sg:province":"NM",
    "wof:name":"Albuquerque Tropicals",
    "wof:placetype":"venue"
},
  "geometry": {"coordinates":[-106.68910700000001,35.021361],"type":"Point"}
}