{
  "type": "Feature",
  "properties": {
    "iso:country":"US",
    "sg:address":"7410 Montgomery Blvd NE",
    "sg:city":"Albuquerque",
    "sg:classifiers":[
        {
            "category":"Insurance",
            "subcategory":"Insurance Agent",
            "type":"Services"
        }
    ],
    "sg:phone":"+1 505 881 1235",
    "sg:postcode":"87109",
    "sg:province":"NM",
    "sg:tags":[
        "broker"
    ],
    "wof:name":"Insurance Marketing",
    "wof:placetype":"venue"
},
  "geometry": {"coordinates":[-106.563398,35.130669],"type":"Point"}
}