{
  "type": "Feature",
  "properties": {
    "iso:country":"US",
    "sg:address":"3840 Masthead St NE",
    "sg:city":"Albuquerque",
    "sg:classifiers":[
        {
            "category":"Insurance",
            "subcategory":"Insurance Agent",
            "type":"Services"
        },
        {
            "category":"Insurance",
            "subcategory":"Hazard Insurance",
            "type":"Services"
        },
        {
            "category":"Insurance",
            "subcategory":"Title Insurance",
            "type":"Services"
        },
        {
            "category":"Insurance",
            "subcategory":"Health Insurance",
            "type":"Services"
        },
        {
            "category":"Insurance",
            "subcategory":"Life Insurance",
            "type":"Services"
        }
    ],
    "sg:phone":"+1 505 766 9501",
    "sg:postcode":"87109",
    "sg:province":"NM",
    "sg:tags":[
        "business",
        "auto",
        "commercial",
        "homeowner",
        "benefit",
        "employee"
    ],
    "sg:website":"http://www.farmersagent.com/aflores",
    "wof:name":"Alexa Williamson-Flores - Farmers Insurance",
    "wof:placetype":"venue"
},
  "geometry": {"coordinates":[-106.600828,35.166409],"type":"Point"}
}