{
  "type": "Feature",
  "properties": {
    "iso:country":"US",
    "sg:address":"3201 N Kentucky Ave",
    "sg:city":"Roswell",
    "sg:classifiers":[
        {
            "category":"Real Estate",
            "subcategory":"Real Estate Operator",
            "type":"Services"
        }
    ],
    "sg:phone":"+1 505 623 7218",
    "sg:postcode":"88201",
    "sg:province":"NM",
    "sg:tags":[
        "mobile",
        "home",
        "site"
    ],
    "wof:name":"Coronado Mobile Home Park",
    "wof:placetype":"venue"
},
  "geometry": {"coordinates":[-104.52742,33.436099],"type":"Point"}
}