{
  "type": "Feature",
  "properties": {
    "addr:full":"855 W Castillo Ave Belen NM 87002",
    "addr:housenumber":"855",
    "addr:postcode":"87002",
    "addr:street":"W Castillo Ave",
    "iso:country":"US",
    "sg:address":"855 W Castillo Ave",
    "sg:city":"Belen",
    "sg:classifiers":[
        {
            "category":"Government",
            "subcategory":"Office",
            "type":"Public Place"
        }
    ],
    "sg:phone":"+1 505 864 7745",
    "sg:postcode":"87002",
    "sg:province":"NM",
    "sg:tags":[
        "state",
        "resource"
    ],
    "wof:name":"New Mexico WIC Program",
    "wof:placetype":"venue"
},
  "geometry": {"coordinates":[-106.778059,34.659909],"type":"Point"}
}