{
  "type": "Feature",
  "properties": {
    "iso:country":"US",
    "sg:address":"12210 San Bernardino Dr NE",
    "sg:city":"Albuquerque",
    "sg:classifiers":[
        {
            "category":"Building & Trades",
            "subcategory":"Construction",
            "type":"Services"
        }
    ],
    "sg:phone":"+1 505 550 0848",
    "sg:postcode":"87122",
    "sg:province":"NM",
    "sg:tags":[
        "general",
        "contractor"
    ],
    "wof:name":"Signature Custom Framing",
    "wof:placetype":"venue"
},
  "geometry": {"coordinates":[-106.50301,35.171143],"type":"Point"}
}