{
  "type": "Feature",
  "properties": {
    "addr:full":"221 Shelby St Santa Fe NM 87501",
    "addr:housenumber":"221",
    "addr:postcode":"87501",
    "addr:street":"Shelby St",
    "iso:country":"US",
    "sg:address":"221 Shelby St",
    "sg:city":"Santa Fe",
    "sg:classifiers":[
        {
            "category":"Restaurant",
            "type":"Food & Drink"
        }
    ],
    "sg:menulink":"http://www.allmenus.com/nm/santa-fe/269992-amavi-restaurant/menu/",
    "sg:phone":"+1 505 988 2355",
    "sg:postcode":"87501",
    "sg:province":"NM",
    "sg:tags":[
        "mediterranean"
    ],
    "wof:name":"Amavi Restaurant",
    "wof:placetype":"venue"
},
  "geometry": {"coordinates":[-105.938569,35.685427],"type":"Point"}
}