{
  "type": "Feature",
  "properties": {
    "iso:country":"US",
    "sg:address":"1001 N Solano Dr",
    "sg:city":"Las Cruces",
    "sg:classifiers":[
        {
            "category":"Health Services",
            "subcategory":"Health Practitioner",
            "type":"Services"
        }
    ],
    "sg:phone":"+1 505 523 2227",
    "sg:postcode":"88001",
    "sg:province":"NM",
    "wof:name":"Daniels Howard & Linda",
    "wof:placetype":"venue"
},
  "geometry": {"coordinates":[-106.771171,32.319988],"type":"Point"}
}