{
  "type": "Feature",
  "properties": {
    "iso:country":"US",
    "sg:address":"9825 Hannett Pl NE",
    "sg:city":"Albuquerque",
    "sg:classifiers":[
        {
            "category":"Shopping",
            "type":"Retail Goods"
        }
    ],
    "sg:phone":"+1 505 298 8003",
    "sg:postcode":"87112",
    "sg:province":"NM",
    "sg:tags":[
        "merchandise"
    ],
    "wof:name":"J & R Merchandise & Repair",
    "wof:placetype":"venue"
},
  "geometry": {"coordinates":[-106.534518,35.098403],"type":"Point"}
}