{
  "type": "Feature",
  "properties": {
    "iso:country":"US",
    "sg:address":"900 San Juan Blvd",
    "sg:city":"Farmington",
    "sg:classifiers":[
        {
            "category":"Manufacturing",
            "subcategory":"Tools & Machinery",
            "type":"Manufacturing & Wholesale Goods"
        }
    ],
    "sg:phone":"+1 505 327 5071",
    "sg:postcode":"87401",
    "sg:province":"NM",
    "sg:tags":[
        "fitting"
    ],
    "wof:name":"Precision Fitting & Gauge Co",
    "wof:placetype":"venue"
},
  "geometry": {"coordinates":[-108.188982,36.732868],"type":"Point"}
}