{
  "type": "Feature",
  "properties": {
    "iso:country":"US",
    "sg:address":"1710 W Aztec Blvd",
    "sg:city":"Aztec",
    "sg:classifiers":[
        {
            "category":"Retail",
            "subcategory":"Auto Repair",
            "type":"Services"
        }
    ],
    "sg:phone":"+1 505 333 2711",
    "sg:postcode":"87410",
    "sg:province":"NM",
    "sg:tags":[
        "body",
        "automobile",
        "painting"
    ],
    "wof:name":"Precision Collision",
    "wof:placetype":"venue"
},
  "geometry": {"coordinates":[-108.016577,36.826695],"type":"Point"}
}