{
  "type": "Feature",
  "properties": {
    "addr:full":"827 Cam del Monte Sol Santa Fe NM 87501",
    "addr:housenumber":"827",
    "addr:postcode":"87501",
    "addr:street":"Cam Del Monte Sol",
    "iso:country":"US",
    "sg:address":"827 Cam del Monte Sol",
    "sg:city":"Santa Fe",
    "sg:classifiers":[
        {
            "category":"Retail",
            "subcategory":"Auto Repair",
            "type":"Services"
        }
    ],
    "sg:phone":"+1 505 988 2346",
    "sg:postcode":"87501",
    "sg:province":"NM",
    "sg:tags":[
        "body",
        "automobile",
        "painting"
    ],
    "wof:name":"Capitol Paintworks & Collision",
    "wof:placetype":"venue"
},
  "geometry": {"coordinates":[-105.92226100000001,35.669988],"type":"Point"}
}