{
  "type": "Feature",
  "properties": {
    "addr:full":"130 Franklin St Hatch NM 87937",
    "addr:housenumber":"130",
    "addr:postcode":"87937",
    "addr:street":"Franklin St",
    "iso:country":"US",
    "sg:address":"130 Franklin St",
    "sg:city":"Hatch",
    "sg:classifiers":[
        {
            "category":"Banks & Credit Unions",
            "subcategory":"Bank",
            "type":"Services"
        }
    ],
    "sg:phone":"+1 505 267 3081",
    "sg:postcode":"87937",
    "sg:province":"NM",
    "wof:name":"Bank Of The West",
    "wof:placetype":"venue"
},
  "geometry": {"coordinates":[-107.15342699999999,32.665965],"type":"Point"}
}