{
  "type": "Feature",
  "properties": {
    "iso:country":"US",
    "sg:address":"101 Reese Dr",
    "sg:city":"Ruidoso",
    "sg:classifiers":[
        {
            "category":"Health Services",
            "subcategory":"Health Practitioner",
            "type":"Services"
        }
    ],
    "sg:phone":"+1 505 630 3739",
    "sg:postcode":"88345",
    "sg:province":"NM",
    "sg:tags":[
        "acupuncture"
    ],
    "wof:name":"Natural Health Care Complex",
    "wof:placetype":"venue"
},
  "geometry": {"coordinates":[-105.638081,33.323521],"type":"Point"}
}