{
  "type": "Feature",
  "properties": {
    "iso:country":"US",
    "sg:address":"822 5th St NW",
    "sg:city":"Albuquerque",
    "sg:classifiers":[
        {
            "category":"Professional",
            "subcategory":"Lawyer & Legal Services",
            "type":"Services"
        }
    ],
    "sg:phone":"+1 505 245 7063",
    "sg:postcode":"87102",
    "sg:province":"NM",
    "sg:tags":[
        "attorney"
    ],
    "wof:name":"Christina Argyres",
    "wof:placetype":"venue"
},
  "geometry": {"coordinates":[-106.65114699999999,35.093021],"type":"Point"}
}