{
  "type": "Feature",
  "properties": {
    "iso:country":"US",
    "sg:address":"8905 Washington St NE",
    "sg:city":"Albuquerque",
    "sg:classifiers":[
        {
            "category":"Professional",
            "subcategory":"Art Services",
            "type":"Services"
        }
    ],
    "sg:phone":"+1 505 858 1701",
    "sg:postcode":"87113",
    "sg:province":"NM",
    "sg:tags":[
        "artist"
    ],
    "wof:name":"Dream Weaver Design",
    "wof:placetype":"venue"
},
  "geometry": {"coordinates":[-106.594839,35.188428],"type":"Point"}
}