{
  "type": "Feature",
  "properties": {
    "iso:country":"US",
    "sg:address":"151 S Walnut St",
    "sg:city":"Las Cruces",
    "sg:classifiers":[
        {
            "category":"Professional",
            "subcategory":"Business Services",
            "type":"Services"
        }
    ],
    "sg:phone":"+1 505 523 5554",
    "sg:postcode":"88001",
    "sg:province":"NM",
    "sg:tags":[
        "interior",
        "consultant",
        "design",
        "decorator"
    ],
    "wof:name":"Kitchens Closets & Grge Mahal",
    "wof:placetype":"venue"
},
  "geometry": {"coordinates":[-106.756294,32.315062],"type":"Point"}
}