{
  "type": "Feature",
  "properties": {
    "iso:country":"US",
    "sg:address":"4201 Wyoming Blvd NE",
    "sg:city":"Albuquerque",
    "sg:classifiers":[
        {
            "category":"Banks & Credit Unions",
            "subcategory":"Bank",
            "type":"Services"
        }
    ],
    "sg:phone":"+1 505 855 0855",
    "sg:postcode":"87111",
    "sg:province":"NM",
    "wof:name":"Bank Of Albuquerque",
    "wof:placetype":"venue"
},
  "geometry": {"coordinates":[-106.551085,35.127755],"type":"Point"}
}