{
  "type": "Feature",
  "properties": {
    "addr:full":"4108 Old Cavern Hwy Carlsbad NM 88220",
    "addr:housenumber":"4108",
    "addr:postcode":"88220",
    "addr:street":"Old Cavern Hwy",
    "iso:country":"US",
    "sg:address":"4108 Old Cavern Hwy",
    "sg:city":"Carlsbad",
    "sg:classifiers":[
        {
            "category":"Building & Trades",
            "subcategory":"Construction",
            "type":"Services"
        }
    ],
    "sg:phone":"+1 505 885 1292",
    "sg:postcode":"88220",
    "sg:province":"NM",
    "sg:tags":[
        "general",
        "contractor"
    ],
    "wof:name":"W W Construction",
    "wof:placetype":"venue"
},
  "geometry": {"coordinates":[-104.22012700000001,32.369698],"type":"Point"}
}