{
  "type": "Feature",
  "properties": {
    "iso:country":"US",
    "sg:address":"5348 Pan American Fwy",
    "sg:city":"Albuquerque",
    "sg:classifiers":[
        {
            "category":"Shopping",
            "type":"Retail Goods"
        }
    ],
    "sg:phone":"+1 505 889 3011",
    "sg:postcode":"87109",
    "sg:province":"NM",
    "sg:tags":[
        "medical",
        "supply"
    ],
    "wof:name":"Kci",
    "wof:placetype":"venue"
},
  "geometry": {"coordinates":[-106.595592,35.141047],"type":"Point"}
}