{
  "type": "Feature",
  "properties": {
    "addr:full":"1601 Columbia Dr SE Albuquerque NM 87106",
    "addr:housenumber":"1601",
    "addr:postcode":"87106",
    "addr:street":"Columbia Dr Se",
    "iso:country":"US",
    "sg:address":"1601 Columbia Dr SE",
    "sg:city":"Albuquerque",
    "sg:classifiers":[
        {
            "category":"Education",
            "subcategory":"Special Training",
            "type":"Public Place"
        }
    ],
    "sg:phone":"+1 505 247 0862",
    "sg:postcode":"87106",
    "sg:province":"NM",
    "sg:tags":[
        "educational"
    ],
    "wof:name":"American Hispanic Pharmacy",
    "wof:placetype":"venue"
},
  "geometry": {"coordinates":[-106.616382,35.063279],"type":"Point"}
}