{
  "type": "Feature",
  "properties": {
    "iso:country":"US",
    "sg:address":"13 Kiva Pl",
    "sg:city":"Sandia Park",
    "sg:classifiers":[
        {
            "category":"Professional",
            "subcategory":"Management & Consulting",
            "type":"Services"
        }
    ],
    "sg:phone":"+1 505 286 0306",
    "sg:postcode":"87047",
    "sg:province":"NM",
    "sg:tags":[
        "consultant"
    ],
    "wof:name":"Cadre Design Consultant",
    "wof:placetype":"venue"
},
  "geometry": {"coordinates":[-106.33555200000001,35.192989],"type":"Point"}
}