{
  "type": "Feature",
  "properties": {
    "iso:country":"US",
    "sg:address":"9932 Bell Ave SE",
    "sg:city":"Albuquerque",
    "sg:classifiers":[
        {
            "category":"Wholesale",
            "subcategory":"Machinery & Supplies",
            "type":"Manufacturing & Wholesale Goods"
        }
    ],
    "sg:phone":"+1 505 296 6206",
    "sg:postcode":"87123",
    "sg:province":"NM",
    "sg:tags":[
        "vending"
    ],
    "wof:name":"F&M Vending",
    "wof:placetype":"venue"
},
  "geometry": {"coordinates":[-106.536833,35.069465],"type":"Point"}
}