{
  "type": "Feature",
  "properties": {
    "iso:country":"US",
    "sg:address":"10131 Coors Blvd NW",
    "sg:city":"Albuquerque",
    "sg:classifiers":[
        {
            "category":"Professional",
            "type":"Services"
        }
    ],
    "sg:phone":"+1 505 857 9731",
    "sg:postcode":"87114",
    "sg:province":"NM",
    "wof:name":"Valerie Jean",
    "wof:placetype":"venue"
},
  "geometry": {"coordinates":[-106.648961,35.201017],"type":"Point"}
}