{
  "type": "Feature",
  "properties": {
    "addr:full":"1699 Rio Bravo Blvd SW Albuquerque NM 87105",
    "addr:housenumber":"1699",
    "addr:postcode":"87105",
    "addr:street":"Rio Bravo Blvd Sw",
    "iso:country":"US",
    "sg:address":"1699 Rio Bravo Blvd SW",
    "sg:city":"Albuquerque",
    "sg:classifiers":[
        {
            "category":"Restaurant",
            "type":"Food & Drink"
        }
    ],
    "sg:menulink":"http://www.allmenus.com/nm/albuquerque/86231-little-caesars-pizza/menu/",
    "sg:phone":"+1 505 873 1300",
    "sg:postcode":"87105",
    "sg:province":"NM",
    "sg:tags":[
        "american",
        "pizza"
    ],
    "wof:name":"Little Caesar's Pizza",
    "wof:placetype":"venue"
},
  "geometry": {"coordinates":[-106.682886,35.026911],"type":"Point"}
}