{
  "type": "Feature",
  "properties": {
    "iso:country":"US",
    "sg:address":"828 Los Lovatos Rd",
    "sg:city":"Santa Fe",
    "sg:classifiers":[
        {
            "category":"Building & Trades",
            "subcategory":"Construction",
            "type":"Services"
        }
    ],
    "sg:phone":"+1 505 988 2448",
    "sg:postcode":"87501",
    "sg:province":"NM",
    "sg:tags":[
        "general",
        "contractor"
    ],
    "wof:name":"Tru Scale Builders Designer",
    "wof:placetype":"venue"
},
  "geometry": {"coordinates":[-105.941289,35.703603],"type":"Point"}
}