{
  "type": "Feature",
  "properties": {
    "iso:country":"US",
    "sg:address":"12200 Lomas Blvd NE",
    "sg:city":"Albuquerque",
    "sg:classifiers":[
        {
            "category":"Education",
            "subcategory":"School",
            "type":"Public Place"
        }
    ],
    "sg:phone":"+1 505 292 0090",
    "sg:postcode":"87112",
    "sg:province":"NM",
    "sg:tags":[
        "high",
        "k-",
        "private"
    ],
    "sg:website":"http://www.kanw.com",
    "wof:name":"Manzano High School",
    "wof:placetype":"venue"
},
  "geometry": {"coordinates":[-106.51287000000001,35.086615],"type":"Point"}
}