{
  "type": "Feature",
  "properties": {
    "iso:country":"US",
    "sg:address":"51 Bonanza Creek Rd",
    "sg:city":"Santa Fe",
    "sg:classifiers":[
        {
            "category":"Recreation",
            "type":"Entertainment"
        }
    ],
    "sg:phone":"+1 505 473 0581",
    "sg:postcode":"87508",
    "sg:province":"NM",
    "sg:tags":[
        "arts",
        "printing",
        "fine",
        "screen"
    ],
    "wof:name":"Arton Arts Inc",
    "wof:placetype":"venue"
},
  "geometry": {"coordinates":[-106.073812,35.493516],"type":"Point"}
}