{
  "type": "Feature",
  "properties": {
    "iso:country":"US",
    "sg:address":"200 Valley View Cir",
    "sg:city":"Ruidoso",
    "sg:classifiers":[
        {
            "category":"Education",
            "subcategory":"Special Training",
            "type":"Public Place"
        }
    ],
    "sg:phone":"+1 505 258 3976",
    "sg:postcode":"88345",
    "sg:province":"NM",
    "wof:name":"TLC Driving School Inc",
    "wof:placetype":"venue"
},
  "geometry": {"coordinates":[-105.663037,33.376892],"type":"Point"}
}