{
  "type": "Feature",
  "properties": {
    "iso:country":"US",
    "sg:address":"317 N Downtown Mall",
    "sg:city":"Las Cruces",
    "sg:classifiers":[
        {
            "category":"Professional",
            "subcategory":"Engineering",
            "type":"Services"
        }
    ],
    "sg:phone":"+1 505 527 6471",
    "sg:postcode":"88001",
    "sg:province":"NM",
    "sg:tags":[
        "engineer"
    ],
    "sg:website":"www.metroware.net",
    "wof:name":"Geo Stat",
    "wof:placetype":"venue"
},
  "geometry": {"coordinates":[-106.77902,32.311419],"type":"Point"}
}