{
  "type": "Feature",
  "properties": {
    "addr:full":"72 W Marcy St Santa Fe NM 87501",
    "addr:housenumber":"72",
    "addr:postcode":"87501",
    "addr:street":"W Marcy St",
    "iso:country":"US",
    "sg:address":"72 W Marcy St",
    "sg:city":"Santa Fe",
    "sg:classifiers":[
        {
            "category":"Restaurant",
            "type":"Food & Drink"
        }
    ],
    "sg:menulink":"http://www.allmenus.com/nm/santa-fe/275742-la-boca/menu/",
    "sg:phone":"+1 505 982 3433",
    "sg:postcode":"87501",
    "sg:province":"NM",
    "sg:tags":[
        "spanish"
    ],
    "wof:name":"LA Boca",
    "wof:placetype":"venue"
},
  "geometry": {"coordinates":[-105.937848,35.689322],"type":"Point"}
}