{
  "type": "Feature",
  "properties": {
    "iso:country":"US",
    "sg:address":"2629 Sudderth Dr",
    "sg:city":"Ruidoso",
    "sg:classifiers":[
        {
            "category":"Shopping",
            "type":"Retail Goods"
        }
    ],
    "sg:phone":"+1 505 257 9738",
    "sg:postcode":"88345",
    "sg:province":"NM",
    "sg:tags":[
        "used",
        "merchandise"
    ],
    "wof:name":"Fentons Gallery",
    "wof:placetype":"venue"
},
  "geometry": {"coordinates":[-105.673559,33.331746],"type":"Point"}
}