{
  "type": "Feature",
  "properties": {
    "iso:country":"US",
    "sg:address":"1991 State Hwy 602",
    "sg:city":"Gallup",
    "sg:classifiers":[
        {
            "category":"Autos & Motor Vehicles",
            "subcategory":"Motorcycle Sales",
            "type":"Retail Goods"
        }
    ],
    "sg:phone":"+1 505 722 0360",
    "sg:postcode":"87301",
    "sg:province":"NM",
    "wof:name":"Kawasaki Cycle City",
    "wof:placetype":"venue"
},
  "geometry": {"coordinates":[-108.740403,35.503404],"type":"Point"}
}