{
  "type": "Feature",
  "properties": {
    "iso:country":"US",
    "sg:address":"8814 2nd St NW",
    "sg:city":"Albuquerque",
    "sg:classifiers":[
        {
            "category":"Wholesale",
            "subcategory":"Machinery & Supplies",
            "type":"Manufacturing & Wholesale Goods"
        }
    ],
    "sg:phone":"+1 505 898 9199",
    "sg:postcode":"87114",
    "sg:province":"NM",
    "sg:tags":[
        "equipment",
        "irrigation",
        "system"
    ],
    "wof:name":"Territorial Landscape Co",
    "wof:placetype":"venue"
},
  "geometry": {"coordinates":[-106.619457,35.180438],"type":"Point"}
}