{
  "type": "Feature",
  "properties": {
    "addr:full":"4101 Menaul Blvd NE Albuquerque NM 87110",
    "addr:housenumber":"4101",
    "addr:postcode":"87110",
    "addr:street":"Menaul Blvd Ne",
    "iso:country":"US",
    "sg:address":"4101 Menaul Blvd NE",
    "sg:city":"Albuquerque",
    "sg:classifiers":[
        {
            "category":"Autos & Motor Vehicles",
            "subcategory":"Motorcycle Sales",
            "type":"Retail Goods"
        }
    ],
    "sg:phone":"+1 505 888 2484",
    "sg:postcode":"87110",
    "sg:province":"NM",
    "sg:tags":[
        "scooter"
    ],
    "wof:name":"Show Stoppers Unlimited",
    "wof:placetype":"venue"
},
  "geometry": {"coordinates":[-106.597059,35.109215],"type":"Point"}
}