{
  "type": "Feature",
  "properties": {
    "iso:country":"US",
    "sg:address":"4916 Homestead Trl NW",
    "sg:city":"Albuquerque",
    "sg:classifiers":[
        {
            "category":"Professional",
            "subcategory":"Accounting & Tax Preparation",
            "type":"Services"
        }
    ],
    "sg:phone":"+1 505 897 5096",
    "sg:postcode":"87120",
    "sg:province":"NM",
    "sg:tags":[
        "return"
    ],
    "wof:name":"Bulling Associates",
    "wof:placetype":"venue"
},
  "geometry": {"coordinates":[-106.693972,35.166512],"type":"Point"}
}