{
  "type": "Feature",
  "properties": {
    "iso:country":"US",
    "sg:address":"300 S 3rd St",
    "sg:city":"Tucumcari",
    "sg:classifiers":[
        {
            "category":"Building & Trades",
            "subcategory":"Construction",
            "type":"Services"
        }
    ],
    "sg:phone":"+1 505 461 3577",
    "sg:postcode":"88401",
    "sg:province":"NM",
    "sg:tags":[
        "grading",
        "contractor"
    ],
    "wof:name":"Quay County Road Dept",
    "wof:placetype":"venue"
},
  "geometry": {"coordinates":[-103.727388,35.176997],"type":"Point"}
}