{
  "type": "Feature",
  "properties": {
    "iso:country":"US",
    "sg:address":"827 W Meadowlark Ln",
    "sg:city":"Corrales",
    "sg:classifiers":[
        {
            "category":"Professional",
            "subcategory":"Lawyer & Legal Services",
            "type":"Services"
        }
    ],
    "sg:phone":"+1 505 922 0550",
    "sg:postcode":"87048",
    "sg:province":"NM",
    "sg:tags":[
        "attorney"
    ],
    "wof:name":"Chris King Attorney At Law",
    "wof:placetype":"venue"
},
  "geometry": {"coordinates":[-106.631733,35.220084],"type":"Point"}
}