{
  "type": "Feature",
  "properties": {
    "iso:country":"US",
    "sg:address":"5651 S Main St",
    "sg:city":"Mesilla Park",
    "sg:classifiers":[
        {
            "category":"Retail",
            "subcategory":"Auto Repair",
            "type":"Services"
        }
    ],
    "sg:phone":"+1 505 541 4995",
    "sg:postcode":"88047",
    "sg:province":"NM",
    "sg:tags":[
        "transmission"
    ],
    "wof:name":"Julio's Transmission",
    "wof:placetype":"venue"
},
  "geometry": {"coordinates":[-106.744921,32.241206],"type":"Point"}
}