{
  "type": "Feature",
  "properties": {
    "iso:country":"US",
    "sg:address":"353 Camino Azul NW Apt 5C",
    "sg:city":"Albuquerque",
    "sg:classifiers":[
        {
            "category":"Real Estate",
            "subcategory":"Real Estate Operator",
            "type":"Services"
        }
    ],
    "sg:phone":"+1 505 831 7014",
    "sg:postcode":"87121",
    "sg:province":"NM",
    "sg:tags":[
        "apartment"
    ],
    "wof:name":"Agua Azul Apartments",
    "wof:placetype":"venue"
},
  "geometry": {"coordinates":[-106.71205500000001,35.084791],"type":"Point"}
}