{
  "type": "Feature",
  "properties": {
    "addr:full":"8501 Hwy 4 Jemez Pueblo NM 87024",
    "addr:housenumber":"8501",
    "addr:postcode":"87024",
    "addr:street":"Hwy 4 Jemez",
    "iso:country":"US",
    "sg:address":"8501 Hwy 4",
    "sg:city":"Jemez Pueblo",
    "sg:classifiers":[
        {
            "category":"Education",
            "subcategory":"School",
            "type":"Public Place"
        }
    ],
    "sg:phone":"+1 505 834 7391",
    "sg:postcode":"87024",
    "sg:province":"NM",
    "sg:tags":[
        "district"
    ],
    "sg:website":"www.jvps.org",
    "wof:name":"Jemez Valley Public Schools",
    "wof:placetype":"venue"
},
  "geometry": {"coordinates":[-106.735786,35.656439],"type":"Point"}
}