{
  "type": "Feature",
  "properties": {
    "iso:country":"US",
    "sg:address":"6101 Iliff Rd NW",
    "sg:city":"Albuquerque",
    "sg:classifiers":[
        {
            "category":"Travel",
            "subcategory":"Hotels & Motels",
            "type":"Entertainment"
        }
    ],
    "sg:phone":"+1 505 839 1744",
    "sg:postcode":"87121",
    "sg:province":"NM",
    "sg:tags":[
        "operation"
    ],
    "wof:name":"LA Quinta Inn",
    "wof:placetype":"venue"
},
  "geometry": {"coordinates":[-106.707035,35.10347],"type":"Point"}
}