{
  "type": "Feature",
  "properties": {
    "iso:country":"US",
    "sg:address":"2033 Wyoming Blvd NE",
    "sg:city":"Albuquerque",
    "sg:classifiers":[
        {
            "category":"Banks & Credit Unions",
            "subcategory":"Bank",
            "type":"Services"
        }
    ],
    "sg:phone":"+1 505 243 7175",
    "sg:postcode":"87112",
    "sg:province":"NM",
    "sg:tags":[
        "loan",
        "real estate"
    ],
    "wof:name":"PGNF Home Lending",
    "wof:placetype":"venue"
},
  "geometry": {"coordinates":[-106.550933,35.105022],"type":"Point"}
}