{
  "type": "Feature",
  "properties": {
    "addr:full":"210 W Las Cruces Ave Las Cruces NM 88005",
    "addr:housenumber":"210",
    "addr:postcode":"88005",
    "addr:street":"W Las Cruces Ave",
    "iso:country":"US",
    "sg:address":"210 W Las Cruces Ave",
    "sg:city":"Las Cruces",
    "sg:classifiers":[
        {
            "category":"Professional",
            "type":"Services"
        }
    ],
    "sg:phone":"+1 505 496 8161",
    "sg:postcode":"88005",
    "sg:province":"NM",
    "sg:tags":[
        "establishment"
    ],
    "wof:name":"Oneill Amy Lac Dom",
    "wof:placetype":"venue"
},
  "geometry": {"coordinates":[-106.780537,32.31104],"type":"Point"}
}