{
  "type": "Feature",
  "properties": {
    "iso:country":"US",
    "sg:address":"1300 E Idaho Ave",
    "sg:city":"Las Cruces",
    "sg:classifiers":[
        {
            "category":"Banks & Credit Unions",
            "subcategory":"Bank",
            "type":"Services"
        }
    ],
    "sg:phone":"+1 505 527 4629",
    "sg:postcode":"88001",
    "sg:province":"NM",
    "sg:tags":[
        "executive",
        "institution",
        "business"
    ],
    "wof:name":"Tam Finance",
    "wof:placetype":"venue"
},
  "geometry": {"coordinates":[-106.76126,32.299509],"type":"Point"}
}