{
  "type": "Feature",
  "properties": {
    "iso:country":"US",
    "sg:address":"181 E Darby Rd",
    "sg:city":"Dexter",
    "sg:classifiers":[
        {
            "category":"Wholesale",
            "subcategory":"Machinery & Supplies",
            "type":"Manufacturing & Wholesale Goods"
        }
    ],
    "sg:phone":"+1 505 622 4959",
    "sg:postcode":"88230",
    "sg:province":"NM",
    "wof:name":"Tedros Dairy Supply",
    "wof:placetype":"venue"
},
  "geometry": {"coordinates":[-104.434777,33.285214],"type":"Point"}
}