{
  "type": "Feature",
  "properties": {
    "iso:country":"US",
    "sg:address":"210 Granado St",
    "sg:city":"Tularosa",
    "sg:classifiers":[
        {
            "category":"Shopping",
            "subcategory":"Used Merchandise",
            "type":"Retail Goods"
        }
    ],
    "sg:phone":"+1 505 585 9019",
    "sg:postcode":"88352",
    "sg:province":"NM",
    "wof:name":"LA Tienda Vieja",
    "wof:placetype":"venue"
},
  "geometry": {"coordinates":[-106.01573500000001,33.073183],"type":"Point"}
}