{
  "type": "Feature",
  "properties": {
    "addr:full":"3821 Menaul Blvd NE Albuquerque NM 87110",
    "addr:housenumber":"3821",
    "addr:postcode":"87110",
    "addr:street":"Menaul Blvd Ne",
    "iso:country":"US",
    "sg:address":"3821 Menaul Blvd NE",
    "sg:city":"Albuquerque",
    "sg:classifiers":[
        {
            "category":"Personal",
            "subcategory":"Beauty Salon",
            "type":"Services"
        }
    ],
    "sg:phone":"+1 505 884 8708",
    "sg:postcode":"87110",
    "sg:province":"NM",
    "sg:tags":[
        "shop"
    ],
    "wof:name":"No 1 Nails",
    "wof:placetype":"venue"
},
  "geometry": {"coordinates":[-106.599469,35.109295],"type":"Point"}
}