{
  "type": "Feature",
  "properties": {
    "addr:full":"5312 Jaguar Dr Santa Fe NM 87507",
    "addr:housenumber":"5312",
    "addr:postcode":"87507",
    "addr:street":"Jaguar Dr",
    "iso:country":"US",
    "sg:address":"5312 Jaguar Dr",
    "sg:city":"Santa Fe",
    "sg:classifiers":[
        {
            "category":"Health Services",
            "subcategory":"Hospital",
            "type":"Services"
        }
    ],
    "sg:phone":"+1 505 820 0262",
    "sg:postcode":"87507",
    "sg:province":"NM",
    "sg:tags":[
        "mental"
    ],
    "wof:name":"Zia Behavioral Health",
    "wof:placetype":"venue"
},
  "geometry": {"coordinates":[-106.033428,35.627847],"type":"Point"}
}