{
  "type": "Feature",
  "properties": {
    "addr:full":"827 Pso del Pueblo Sur Taos NM 87571",
    "addr:housenumber":"827",
    "addr:postcode":"87571",
    "addr:street":"Pso Del Pueblo Sur",
    "iso:country":"US",
    "sg:address":"827 Pso del Pueblo Sur",
    "sg:city":"Taos",
    "sg:classifiers":[
        {
            "category":"Real Estate",
            "subcategory":"Architect",
            "type":"Services"
        }
    ],
    "sg:phone":"+1 505 770 4412",
    "sg:postcode":"87571",
    "sg:province":"NM",
    "wof:name":"Nottingham Design Assoc",
    "wof:placetype":"venue"
},
  "geometry": {"coordinates":[-105.583555,36.38862],"type":"Point"}
}