{
  "type": "Feature",
  "properties": {
    "iso:country":"US",
    "sg:address":"712 Hutson Ave",
    "sg:city":"Texico",
    "sg:classifiers":[
        {
            "category":"Personal",
            "type":"Services"
        }
    ],
    "sg:phone":"+1 505 482 9544",
    "sg:postcode":"88135",
    "sg:province":"NM",
    "sg:tags":[
        "therapist",
        "massage"
    ],
    "wof:name":"Time Out Massage",
    "wof:placetype":"venue"
},
  "geometry": {"coordinates":[-103.050026,34.391822],"type":"Point"}
}