{
  "type": "Feature",
  "properties": {
    "addr:full":"40 E Via Plaza Nueva Santa Fe NM 87507",
    "addr:housenumber":"40",
    "addr:postcode":"87507",
    "addr:street":"E Via Plaza Nueva",
    "iso:country":"US",
    "sg:address":"40 E Via Plaza Nueva",
    "sg:city":"Santa Fe",
    "sg:classifiers":[
        {
            "category":"Manufacturing",
            "subcategory":"Printing",
            "type":"Manufacturing & Wholesale Goods"
        }
    ],
    "sg:phone":"+1 505 424 1515",
    "sg:postcode":"87507",
    "sg:province":"NM",
    "sg:tags":[
        "publisher"
    ],
    "wof:name":"Natural Awakenings Magazine",
    "wof:placetype":"venue"
},
  "geometry": {"coordinates":[-106.00891799999999,35.689325],"type":"Point"}
}