{
  "type": "Feature",
  "properties": {
    "addr:full":"700 W Jefferson Ave Lovington NM 88260",
    "addr:housenumber":"700",
    "addr:postcode":"88260",
    "addr:street":"W Jefferson Ave",
    "iso:country":"US",
    "sg:address":"700 W Jefferson Ave",
    "sg:city":"Lovington",
    "sg:classifiers":[
        {
            "category":"Education",
            "subcategory":"School",
            "type":"Public Place"
        }
    ],
    "sg:phone":"+1 505 396 4311",
    "sg:postcode":"88260",
    "sg:province":"NM",
    "wof:name":"Yarbro Elementary School",
    "wof:placetype":"venue"
},
  "geometry": {"coordinates":[-103.358138,32.951315],"type":"Point"}
}