{
  "type": "Feature",
  "properties": {
    "addr:full":"3530 Zafarano Dr Santa Fe NM 87507",
    "addr:housenumber":"3530",
    "addr:postcode":"87507",
    "addr:street":"Zafarano Dr",
    "iso:country":"US",
    "sg:address":"3530 Zafarano Dr",
    "sg:city":"Santa Fe",
    "sg:classifiers":[
        {
            "category":"Personal",
            "subcategory":"Beauty Salon",
            "type":"Services"
        }
    ],
    "sg:phone":"+1 505 424 9479",
    "sg:postcode":"87507",
    "sg:province":"NM",
    "sg:tags":[
        "shop",
        "manicuring"
    ],
    "wof:name":"Best Nails",
    "wof:placetype":"venue"
},
  "geometry": {"coordinates":[-106.01271699999999,35.642292],"type":"Point"}
}