{
  "type": "Feature",
  "properties": {
    "iso:country":"US",
    "sg:address":"34 Cam Tetzcoco",
    "sg:city":"Santa Fe",
    "sg:classifiers":[
        {
            "category":"Building & Trades",
            "subcategory":"Construction",
            "type":"Services"
        }
    ],
    "sg:phone":"+1 505 466 6788",
    "sg:postcode":"87508",
    "sg:province":"NM",
    "sg:tags":[
        "general",
        "contractor"
    ],
    "wof:name":"Renassiance Builders Inc",
    "wof:placetype":"venue"
},
  "geometry": {"coordinates":[-105.940038,35.58851],"type":"Point"}
}