{
  "type": "Feature",
  "properties": {
    "iso:country":"US",
    "sg:address":"4610 Eubank Blvd NE",
    "sg:city":"Albuquerque",
    "sg:classifiers":[
        {
            "category":"Shopping",
            "subcategory":"Gifts & Souvenirs",
            "type":"Retail Goods"
        }
    ],
    "sg:phone":"+1 505 257 9014",
    "sg:postcode":"87111",
    "sg:province":"NM",
    "wof:name":"All Fired Up",
    "wof:placetype":"venue"
},
  "geometry": {"coordinates":[-106.533252,35.131532],"type":"Point"}
}