{
  "type": "Feature",
  "properties": {
    "iso:country":"US",
    "sg:address":"1501 Cliffside Ct NW",
    "sg:city":"Albuquerque",
    "sg:classifiers":[
        {
            "category":"Building & Trades",
            "subcategory":"Construction",
            "type":"Services"
        }
    ],
    "sg:phone":"+1 505 836 6544",
    "sg:postcode":"87105",
    "sg:province":"NM",
    "sg:tags":[
        "home",
        "builder"
    ],
    "wof:name":"Alsan Homes C & R",
    "wof:placetype":"venue"
},
  "geometry": {"coordinates":[-106.697815,35.103266],"type":"Point"}
}