{
  "type": "Feature",
  "properties": {
    "iso:country":"US",
    "sg:address":"172 Vaquero Rd",
    "sg:city":"Santa Fe",
    "sg:classifiers":[
        {
            "category":"Wholesale",
            "subcategory":"Durable Goods & Equipment",
            "type":"Manufacturing & Wholesale Goods"
        }
    ],
    "sg:phone":"+1 505 466 9370",
    "sg:postcode":"87508",
    "sg:province":"NM",
    "wof:name":"New Earth Records",
    "wof:placetype":"venue"
},
  "geometry": {"coordinates":[-105.87206500000001,35.526891],"type":"Point"}
}