{
  "type": "Feature",
  "properties": {
    "iso:country":"US",
    "sg:address":"1755 Buildtek Ct",
    "sg:city":"Las Cruces",
    "sg:classifiers":[
        {
            "category":"Organizations",
            "subcategory":"Religious Organization",
            "type":"Services"
        }
    ],
    "sg:phone":"+1 505 526 6435",
    "sg:postcode":"88005",
    "sg:province":"NM",
    "sg:tags":[
        "church"
    ],
    "wof:name":"International Gospel Ctr",
    "wof:placetype":"venue"
},
  "geometry": {"coordinates":[-106.801505,32.310274],"type":"Point"}
}