{
  "type": "Feature",
  "properties": {
    "addr:full":"926 S San Pedro St Las Cruces NM 88001",
    "addr:housenumber":"926",
    "addr:postcode":"88001",
    "addr:street":"S San Pedro St",
    "iso:country":"US",
    "sg:address":"926 S San Pedro St",
    "sg:city":"Las Cruces",
    "sg:classifiers":[
        {
            "category":"Government",
            "subcategory":"Office",
            "type":"Public Place"
        }
    ],
    "sg:phone":"+1 505 528 2002",
    "sg:postcode":"88001",
    "sg:province":"NM",
    "sg:tags":[
        "village"
    ],
    "wof:name":"Las Cruces City Government",
    "wof:placetype":"venue"
},
  "geometry": {"coordinates":[-106.772997,32.302324],"type":"Point"}
}