{
  "type": "Feature",
  "properties": {
    "addr:full":"418 Cerrillos Rd Santa Fe NM 87501",
    "addr:housenumber":"418",
    "addr:postcode":"87501",
    "addr:street":"Cerrillos Rd",
    "iso:country":"US",
    "sg:address":"418 Cerrillos Rd",
    "sg:city":"Santa Fe",
    "sg:classifiers":[
        {
            "category":"Shopping",
            "type":"Retail Goods"
        },
        {
            "category":"Wholesale",
            "subcategory":"Non-durable Goods",
            "type":"Manufacturing & Wholesale Goods"
        }
    ],
    "sg:phone":"+1 505 983 1500",
    "sg:postcode":"87501",
    "sg:province":"NM",
    "sg:tags":[
        "interior",
        "merchandise"
    ],
    "wof:name":"Made In The Shade",
    "wof:placetype":"venue"
},
  "geometry": {"coordinates":[-105.944013,35.683319],"type":"Point"}
}