{
  "type": "Feature",
  "properties": {
    "addr:full":"102 Hospital Loop NE Albuquerque NM 87109",
    "addr:housenumber":"102",
    "addr:postcode":"87109",
    "addr:street":"Hospital Loop Ne",
    "iso:country":"US",
    "sg:address":"102 Hospital Loop NE",
    "sg:city":"Albuquerque",
    "sg:classifiers":[
        {
            "category":"Health Services",
            "subcategory":"Doctor",
            "type":"Services"
        }
    ],
    "sg:phone":"+1 505 559 5740",
    "sg:postcode":"87109",
    "sg:province":"NM",
    "wof:name":"Heights Mri Ctr",
    "wof:placetype":"venue"
},
  "geometry": {"coordinates":[-106.590897,35.134243],"type":"Point"}
}