{
  "type": "Feature",
  "properties": {
    "addr:full":"1133 Quincy St SE Albuquerque NM 87108",
    "addr:housenumber":"1133",
    "addr:postcode":"87108",
    "addr:street":"Quincy St Se",
    "iso:country":"US",
    "sg:address":"1133 Quincy St SE",
    "sg:city":"Albuquerque",
    "sg:classifiers":[
        {
            "category":"Real Estate",
            "subcategory":"Developer",
            "type":"Services"
        }
    ],
    "sg:phone":"+1 505 315 2938",
    "sg:postcode":"87108",
    "sg:province":"NM",
    "wof:name":"Standing Stones Inc",
    "wof:placetype":"venue"
},
  "geometry": {"coordinates":[-106.589547,35.064394],"type":"Point"}
}