{
  "type": "Feature",
  "properties": {
    "addr:full":"4 Bronco Rd Dexter NM 88230",
    "addr:housenumber":"4",
    "addr:postcode":"88230",
    "addr:street":"Bronco Rd",
    "iso:country":"US",
    "sg:address":"4 Bronco Rd",
    "sg:city":"Dexter",
    "sg:classifiers":[
        {
            "category":"Freight",
            "type":"Transportation"
        }
    ],
    "sg:phone":"+1 505 347 4166",
    "sg:postcode":"88230",
    "sg:province":"NM",
    "sg:tags":[
        "operator",
        "trucking"
    ],
    "wof:name":"Lawrence Gettler",
    "wof:placetype":"venue"
},
  "geometry": {"coordinates":[-104.484971,33.283125],"type":"Point"}
}