{
  "type": "Feature",
  "properties": {
    "iso:country":"US",
    "sg:address":"604 Legion Dr",
    "sg:city":"Las Vegas",
    "sg:classifiers":[
        {
            "category":"Government",
            "subcategory":"Fire Station",
            "type":"Public Place"
        }
    ],
    "sg:phone":"+1 505 425 6321",
    "sg:postcode":"87701",
    "sg:province":"NM",
    "sg:tags":[
        "department"
    ],
    "wof:name":"Las Vegas Fire Station",
    "wof:placetype":"venue"
},
  "geometry": {"coordinates":[-105.222429,35.618593],"type":"Point"}
}