{
  "type": "Feature",
  "properties": {
    "addr:full":"820 Pso de Peralta Santa Fe NM 87501",
    "addr:housenumber":"820",
    "addr:postcode":"87501",
    "addr:street":"Pso De Peralta",
    "iso:country":"US",
    "sg:address":"820 Pso de Peralta",
    "sg:city":"Santa Fe",
    "sg:classifiers":[
        {
            "category":"Health Services",
            "subcategory":"Doctor",
            "type":"Services"
        }
    ],
    "sg:phone":"+1 505 986 9633",
    "sg:postcode":"87501",
    "sg:province":"NM",
    "sg:tags":[
        "clinic"
    ],
    "wof:name":"Santa Fe Community Ctr",
    "wof:placetype":"venue"
},
  "geometry": {"coordinates":[-105.934045,35.684856],"type":"Point"}
}