{
  "type": "Feature",
  "properties": {
    "iso:country":"US",
    "sg:address":"603 San Juan de Rio Dr SE",
    "sg:city":"Rio Rancho",
    "sg:classifiers":[
        {
            "category":"Building & Trades",
            "subcategory":"Construction",
            "type":"Services"
        }
    ],
    "sg:phone":"+1 505 892 9367",
    "sg:postcode":"87124",
    "sg:province":"NM",
    "sg:tags":[
        "c",
        "nonresidential"
    ],
    "wof:name":"R Dowdican Assoc",
    "wof:placetype":"venue"
},
  "geometry": {"coordinates":[-106.648644,35.246112],"type":"Point"}
}