{
  "type": "Feature",
  "properties": {
    "addr:full":"2520 Madison St NE Albuquerque NM 87110",
    "addr:housenumber":"2520",
    "addr:postcode":"87110",
    "addr:street":"Madison St Ne",
    "iso:country":"US",
    "sg:address":"2520 Madison St NE",
    "sg:city":"Albuquerque",
    "sg:classifiers":[
        {
            "category":"Manufacturing",
            "subcategory":"Paper Products",
            "type":"Manufacturing & Wholesale Goods"
        }
    ],
    "sg:phone":"+1 505 875 1500",
    "sg:postcode":"87110",
    "sg:province":"NM",
    "sg:tags":[
        "bag",
        "mfg",
        "plastic"
    ],
    "wof:name":"Cycle Plastics",
    "wof:placetype":"venue"
},
  "geometry": {"coordinates":[-106.591948,35.108814],"type":"Point"}
}