{
  "type": "Feature",
  "properties": {
    "iso:country":"US",
    "sg:address":"1209 Apodaca St SW",
    "sg:city":"Albuquerque",
    "sg:classifiers":[
        {
            "category":"Real Estate",
            "subcategory":"Real Estate Agent",
            "type":"Services"
        }
    ],
    "sg:phone":"+1 505 831 1175",
    "sg:postcode":"87121",
    "sg:province":"NM",
    "wof:name":"Rl Encinio Construction",
    "wof:placetype":"venue"
},
  "geometry": {"coordinates":[-106.752484,35.053325],"type":"Point"}
}