{
  "type": "Feature",
  "properties": {
    "iso:country":"US",
    "sg:address":"12001 Pino Ave NE",
    "sg:city":"Albuquerque",
    "sg:classifiers":[
        {
            "category":"Professional",
            "type":"Services"
        }
    ],
    "sg:phone":"+1 505 797 4663",
    "sg:postcode":"87122",
    "sg:province":"NM",
    "wof:name":"2001 Corporation",
    "wof:placetype":"venue"
},
  "geometry": {"coordinates":[-106.502623,35.168421],"type":"Point"}
}