{
  "type": "Feature",
  "properties": {
    "iso:country":"US",
    "sg:address":"707 Galisteo St",
    "sg:city":"Santa Fe",
    "sg:classifiers":[
        {
            "category":"Building & Trades",
            "subcategory":"Construction",
            "type":"Services"
        }
    ],
    "sg:phone":"+1 505 988 1955",
    "sg:postcode":"87505",
    "sg:province":"NM",
    "sg:tags":[
        "house",
        "nonresidential"
    ],
    "wof:name":"Milagro Bldg Conspiracy",
    "wof:placetype":"venue"
},
  "geometry": {"coordinates":[-105.943871,35.677883],"type":"Point"}
}