{
  "type": "Feature",
  "properties": {
    "addr:full":"200 Las Mananitas St Santa Fe NM 87501",
    "addr:housenumber":"200",
    "addr:postcode":"87501",
    "addr:street":"Las Mananitas St",
    "iso:country":"US",
    "sg:address":"200 Las Mananitas St",
    "sg:city":"Santa Fe",
    "sg:classifiers":[
        {
            "category":"Building & Trades",
            "subcategory":"Construction",
            "type":"Services"
        }
    ],
    "sg:phone":"+1 505 983 3611",
    "sg:postcode":"87501",
    "sg:province":"NM",
    "sg:tags":[
        "home",
        "contractor",
        "general",
        "family",
        "custom"
    ],
    "wof:name":"Klein Design & Construction",
    "wof:placetype":"venue"
},
  "geometry": {"coordinates":[-105.95671,35.695996],"type":"Point"}
}