{
  "type": "Feature",
  "properties": {
    "iso:country":"US",
    "sg:address":"1941 Southern Blvd SE",
    "sg:city":"Rio Rancho",
    "sg:classifiers":[
        {
            "category":"Shopping",
            "subcategory":"Pharmacy",
            "type":"Retail Goods"
        }
    ],
    "sg:phone":"+1 505 891 8996",
    "sg:postcode":"87124",
    "sg:province":"NM",
    "sg:website":"www.walgreens.com",
    "wof:name":"Walgreens",
    "wof:placetype":"venue"
},
  "geometry": {"coordinates":[-106.697857,35.2416],"type":"Point"}
}