{
  "type": "Feature",
  "properties": {
    "iso:country":"US",
    "sg:address":"110 W College Blvd",
    "sg:city":"Roswell",
    "sg:classifiers":[
        {
            "category":"Real Estate",
            "subcategory":"Real Estate Services",
            "type":"Services"
        }
    ],
    "sg:phone":"+1 505 622 4331",
    "sg:postcode":"88201",
    "sg:province":"NM",
    "sg:tags":[
        "company",
        "title"
    ],
    "wof:name":"Lawyers Title Insurance Corp",
    "wof:placetype":"venue"
},
  "geometry": {"coordinates":[-104.52338899999999,33.408605],"type":"Point"}
}