{
  "type": "Feature",
  "properties": {
    "iso:country":"US",
    "sg:address":"9208 Hagerman Ave NE",
    "sg:city":"Albuquerque",
    "sg:classifiers":[
        {
            "category":"Personal",
            "type":"Services"
        },
        {
            "category":"Sports & Exercise",
            "subcategory":"Gym",
            "type":"Entertainment"
        }
    ],
    "sg:phone":"+1 505 821 5462",
    "sg:postcode":"87109",
    "sg:province":"NM",
    "sg:tags":[
        "trainer",
        "consultant",
        "program",
        "physical",
        "fitness"
    ],
    "wof:name":"Bodies Defined",
    "wof:placetype":"venue"
},
  "geometry": {"coordinates":[-106.53970700000001,35.170321],"type":"Point"}
}