{
  "type": "Feature",
  "properties": {
    "iso:country":"US",
    "sg:address":"310 E Mesa Ave",
    "sg:city":"Gallup",
    "sg:classifiers":[
        {
            "category":"Professional",
            "subcategory":"Lawyer & Legal Services",
            "type":"Services"
        }
    ],
    "sg:phone":"+1 505 722 2286",
    "sg:postcode":"87301",
    "sg:province":"NM",
    "sg:tags":[
        "attorney"
    ],
    "wof:name":"R David Pederson",
    "wof:placetype":"venue"
},
  "geometry": {"coordinates":[-108.73657900000001,35.525805],"type":"Point"}
}