{
  "type": "Feature",
  "properties": {
    "addr:full":"3400 Candelaria Rd NE Albuquerque NM 87107",
    "addr:postcode":"3400;87107",
    "addr:street":"Candelaria Rd Ne",
    "iso:country":"US",
    "sg:address":"3400 Candelaria Rd NE",
    "sg:city":"Albuquerque",
    "sg:classifiers":[
        {
            "category":"Wholesale",
            "subcategory":"Electrical",
            "type":"Manufacturing & Wholesale Goods"
        }
    ],
    "sg:phone":"+1 505 884 2600",
    "sg:postcode":"87107",
    "sg:province":"NM",
    "sg:tags":[
        "equipment",
        "electric",
        "supply"
    ],
    "sg:website":"www.rexelusa.com",
    "wof:name":"Rexel",
    "wof:placetype":"venue"
},
  "geometry": {"coordinates":[-106.60522,35.11653],"type":"Point"}
}