{
  "type": "Feature",
  "properties": {
    "iso:country":"US",
    "sg:address":"512 Sunrise Rd",
    "sg:city":"Roswell",
    "sg:classifiers":[
        {
            "category":"Professional",
            "subcategory":"Business Services",
            "type":"Services"
        }
    ],
    "sg:phone":"+1 505 910 9727",
    "sg:postcode":"88201",
    "sg:province":"NM",
    "sg:tags":[
        "process",
        "server"
    ],
    "wof:name":"Brink Process Svc",
    "wof:placetype":"venue"
},
  "geometry": {"coordinates":[-104.518092,33.442552],"type":"Point"}
}