{
  "type": "Feature",
  "properties": {
    "addr:full":"231 Muriel St NE Albuquerque NM 87123",
    "addr:housenumber":"231",
    "addr:postcode":"87123",
    "addr:street":"Muriel St Ne",
    "iso:country":"US",
    "sg:address":"231 Muriel St NE",
    "sg:city":"Albuquerque",
    "sg:classifiers":[
        {
            "category":"Building & Trades",
            "subcategory":"Construction",
            "type":"Services"
        }
    ],
    "sg:phone":"+1 505 304 0008",
    "sg:postcode":"87123",
    "sg:province":"NM",
    "sg:tags":[
        "project"
    ],
    "wof:name":"Robert Vallejos Construction",
    "wof:placetype":"venue"
},
  "geometry": {"coordinates":[-106.516407,35.072822],"type":"Point"}
}