{
  "type": "Feature",
  "properties": {
    "iso:country":"US",
    "sg:address":"6200 Jefferson St NE",
    "sg:city":"Albuquerque",
    "sg:classifiers":[
        {
            "category":"Professional",
            "type":"Services"
        }
    ],
    "sg:phone":"+1 505 343 9493",
    "sg:postcode":"87109",
    "sg:province":"NM",
    "sg:tags":[
        "establishment"
    ],
    "wof:name":"HPI-Gsa-1A",
    "wof:placetype":"venue"
},
  "geometry": {"coordinates":[-106.59379,35.149216],"type":"Point"}
}