{
  "type": "Feature",
  "properties": {
    "addr:full":"19337 State Hwy 314 Belen NM 87002",
    "addr:housenumber":"19337",
    "addr:postcode":"87002",
    "addr:street":"State Hwy 314",
    "iso:country":"US",
    "sg:address":"19337 State Hwy 314",
    "sg:city":"Belen",
    "sg:classifiers":[
        {
            "category":"Restaurant",
            "type":"Food & Drink"
        }
    ],
    "sg:phone":"+1 505 864 6740",
    "sg:postcode":"87002",
    "sg:province":"NM",
    "wof:name":"Burritos Alinstante",
    "wof:placetype":"venue"
},
  "geometry": {"coordinates":[-106.769533,34.681765],"type":"Point"}
}