{
  "type": "Feature",
  "properties": {
    "iso:country":"US",
    "sg:address":"303 San Mateo Blvd NE",
    "sg:city":"Albuquerque",
    "sg:classifiers":[
        {
            "category":"Manufacturing",
            "subcategory":"Electronics",
            "type":"Manufacturing & Wholesale Goods"
        }
    ],
    "sg:phone":"+1 505 265 6121",
    "sg:postcode":"87108",
    "sg:province":"NM",
    "sg:tags":[
        "publisher"
    ],
    "sg:website":"www.americanabooks.com",
    "wof:name":"Americana Publishing Inc",
    "wof:placetype":"venue"
},
  "geometry": {"coordinates":[-106.586271,35.078735],"type":"Point"}
}