{
  "type": "Feature",
  "properties": {
    "addr:full":"2508 N Prince St Clovis NM 88101",
    "addr:housenumber":"2508",
    "addr:postcode":"88101",
    "addr:street":"N Prince St",
    "iso:country":"US",
    "sg:address":"2508 N Prince St",
    "sg:city":"Clovis",
    "sg:classifiers":[
        {
            "category":"Building & Trades",
            "subcategory":"Construction",
            "type":"Services"
        }
    ],
    "sg:phone":"+1 505 763 7648",
    "sg:postcode":"88101",
    "sg:province":"NM",
    "sg:tags":[
        "general",
        "flooring",
        "contractor"
    ],
    "wof:name":"Best Floors & More",
    "wof:placetype":"venue"
},
  "geometry": {"coordinates":[-103.19658800000001,34.426329],"type":"Point"}
}