{
  "type": "Feature",
  "properties": {
    "addr:full":"6351 Quay Road Am Tucumcari NM 88401",
    "addr:housenumber":"6351",
    "addr:postcode":"88401",
    "addr:street":"Quay Road Am Tucumcari Nm",
    "iso:country":"US",
    "sg:address":"6351 Quay Road Am",
    "sg:city":"Tucumcari",
    "sg:classifiers":[
        {
            "category":"Retail",
            "subcategory":"Auto Repair",
            "type":"Services"
        }
    ],
    "sg:phone":"+1 505 461 6001",
    "sg:postcode":"88401",
    "sg:province":"NM",
    "sg:tags":[
        "wrecker"
    ],
    "wof:name":"Pinky's Towing",
    "wof:placetype":"venue"
},
  "geometry": {"coordinates":[-103.68436800000001,35.175539],"type":"Point"}
}