{
  "type": "Feature",
  "properties": {
    "iso:country":"US",
    "sg:address":"201 W Chaco St",
    "sg:city":"Aztec",
    "sg:classifiers":[
        {
            "category":"Government",
            "subcategory":"Office",
            "type":"Public Place"
        }
    ],
    "sg:phone":"+1 505 334 9456",
    "sg:postcode":"87410",
    "sg:province":"NM",
    "sg:tags":[
        "village"
    ],
    "wof:name":"Aztec Administrative Offices",
    "wof:placetype":"venue"
},
  "geometry": {"coordinates":[-107.99748,36.823147],"type":"Point"}
}