{
  "type": "Feature",
  "properties": {
    "addr:full":"4418 Central Ave SE Albuquerque NM 87108",
    "addr:housenumber":"4418",
    "addr:postcode":"87108",
    "addr:street":"Central Ave Se",
    "iso:country":"US",
    "sg:address":"4418 Central Ave SE",
    "sg:city":"Albuquerque",
    "sg:phone":"+1 505 255 8695",
    "sg:postcode":"87108",
    "sg:province":"NM",
    "wof:name":"Ron Peterson Firearms",
    "wof:placetype":"venue"
},
  "geometry": {"coordinates":[-106.595144,35.0787],"type":"Point"}
}