{
  "type": "Feature",
  "properties": {
    "iso:country":"US",
    "sg:address":"907 Country Club Dr SE",
    "sg:city":"Rio Rancho",
    "sg:classifiers":[
        {
            "category":"Real Estate",
            "subcategory":"Real Estate Operator",
            "type":"Services"
        }
    ],
    "sg:phone":"+1 505 892 0911",
    "sg:postcode":"87124",
    "sg:province":"NM",
    "sg:tags":[
        "condominium"
    ],
    "wof:name":"Fairways Condominium Assn",
    "wof:placetype":"venue"
},
  "geometry": {"coordinates":[-106.67319,35.243232],"type":"Point"}
}