{
  "type": "Feature",
  "properties": {
    "iso:country":"US",
    "sg:address":"111 W 3rd St",
    "sg:city":"Roswell",
    "sg:classifiers":[
        {
            "category":"Professional",
            "subcategory":"Lawyer & Legal Services",
            "type":"Services"
        }
    ],
    "sg:phone":"+1 505 625 2000",
    "sg:postcode":"88201",
    "sg:province":"NM",
    "sg:tags":[
        "attorney"
    ],
    "wof:name":"Kraft Law Firm",
    "wof:placetype":"venue"
},
  "geometry": {"coordinates":[-104.52425700000001,33.395453],"type":"Point"}
}