{
  "type": "Feature",
  "properties": {
    "iso:country":"US",
    "sg:address":"1710 E Aztec Ave",
    "sg:city":"Gallup",
    "sg:classifiers":[
        {
            "category":"Government",
            "subcategory":"Office",
            "type":"Public Place"
        }
    ],
    "sg:phone":"+1 505 863 3847",
    "sg:postcode":"87301",
    "sg:province":"NM",
    "sg:tags":[
        "transportation"
    ],
    "wof:name":"Motor Vehicle Division 13a",
    "wof:placetype":"venue"
},
  "geometry": {"coordinates":[-108.715799,35.528519],"type":"Point"}
}