{
  "type": "Feature",
  "properties": {
    "addr:full":"102 Barton St Truth Or Consequences NM 87901",
    "addr:housenumber":"102",
    "addr:postcode":"87901",
    "addr:street":"Barton St",
    "iso:country":"US",
    "sg:address":"102 Barton St",
    "sg:city":"Truth Or Consequences",
    "sg:classifiers":[
        {
            "category":"Government",
            "subcategory":"Office",
            "type":"Public Place"
        }
    ],
    "sg:phone":"+1 505 894 3011",
    "sg:postcode":"87901",
    "sg:province":"NM",
    "sg:tags":[
        "welfare"
    ],
    "wof:name":"Human Services New Mexico Dept",
    "wof:placetype":"venue"
},
  "geometry": {"coordinates":[-107.249686,33.143705],"type":"Point"}
}