{
  "type": "Feature",
  "properties": {
    "iso:country":"US",
    "sg:address":"1440 N Main St",
    "sg:city":"Clovis",
    "sg:classifiers":[
        {
            "category":"Manufacturing",
            "subcategory":"Metals",
            "type":"Manufacturing & Wholesale Goods"
        }
    ],
    "sg:phone":"+1 505 763 6915",
    "sg:postcode":"88101",
    "sg:province":"NM",
    "sg:tags":[
        "fabricator",
        "sheet"
    ],
    "wof:name":"Fitz Heating & Air Cond",
    "wof:placetype":"venue"
},
  "geometry": {"coordinates":[-103.20544700000001,34.412365],"type":"Point"}
}