{
  "type": "Feature",
  "properties": {
    "iso:country":"US",
    "sg:address":"426 Muscatel Ave NE",
    "sg:city":"Albuquerque",
    "sg:classifiers":[
        {
            "category":"Retail",
            "subcategory":"Animal Services",
            "type":"Services"
        }
    ],
    "sg:phone":"+1 505 345 3145",
    "sg:postcode":"87107",
    "sg:province":"NM",
    "sg:tags":[
        "pet",
        "grooming",
        "washing"
    ],
    "wof:name":"Animal Kingdom's Grooming",
    "wof:placetype":"venue"
},
  "geometry": {"coordinates":[-106.622225,35.139064],"type":"Point"}
}