{
  "type": "Feature",
  "properties": {
    "addr:full":"3332 Columbia Dr NE Albuquerque NM 87107",
    "addr:housenumber":"3332",
    "addr:postcode":"87107",
    "addr:street":"Columbia Dr Ne",
    "iso:country":"US",
    "sg:address":"3332 Columbia Dr NE",
    "sg:city":"Albuquerque",
    "sg:classifiers":[
        {
            "category":"Wholesale",
            "subcategory":"Fruits & Vegetables",
            "type":"Manufacturing & Wholesale Goods"
        }
    ],
    "sg:phone":"+1 505 884 1535",
    "sg:postcode":"87107",
    "sg:province":"NM",
    "wof:name":"Hacienda Produce LLC",
    "wof:placetype":"venue"
},
  "geometry": {"coordinates":[-106.621684,35.118594],"type":"Point"}
}