{
  "type": "Feature",
  "properties": {
    "addr:full":"2740 Wyoming Blvd NE Albuquerque NM 87111",
    "addr:housenumber":"2740",
    "addr:postcode":"87111",
    "addr:street":"Wyoming;Ne",
    "iso:country":"US",
    "sg:address":"2740 Wyoming Blvd NE",
    "sg:city":"Albuquerque",
    "sg:classifiers":[
        {
            "category":"Shopping",
            "subcategory":"Used Merchandise",
            "type":"Retail Goods"
        }
    ],
    "sg:phone":"+1 505 237 0022",
    "sg:postcode":"87111",
    "sg:province":"NM",
    "sg:tags":[
        "clothing"
    ],
    "wof:name":"Regeneration Consignment",
    "wof:placetype":"venue"
},
  "geometry": {"coordinates":[-106.550797,35.117596],"type":"Point"}
}