{
  "type": "Feature",
  "properties": {
    "iso:country":"US",
    "sg:address":"12920 Cll de Sandias NE",
    "sg:city":"Albuquerque",
    "sg:classifiers":[
        {
            "category":"Banks & Credit Unions",
            "subcategory":"Financial Services",
            "type":"Services"
        }
    ],
    "sg:phone":"+1 505 293 7876",
    "sg:postcode":"87111",
    "sg:province":"NM",
    "sg:tags":[
        "investor"
    ],
    "wof:name":"Seh Investment",
    "wof:placetype":"venue"
},
  "geometry": {"coordinates":[-106.494078,35.135805],"type":"Point"}
}