{
  "type": "Feature",
  "properties": {
    "iso:country":"US",
    "sg:address":"581 Eastlake Dr SE",
    "sg:city":"Rio Rancho",
    "sg:classifiers":[
        {
            "category":"Real Estate",
            "subcategory":"Real Estate Agent",
            "type":"Services"
        }
    ],
    "sg:phone":"+1 505 891 0325",
    "sg:postcode":"87124",
    "sg:province":"NM",
    "wof:name":"BHF LLC",
    "wof:placetype":"venue"
},
  "geometry": {"coordinates":[-106.659245,35.247786],"type":"Point"}
}