{
  "type": "Feature",
  "properties": {
    "iso:country":"US",
    "sg:address":"801 Schepps Blvd",
    "sg:city":"Clovis",
    "sg:classifiers":[
        {
            "category":"Building & Trades",
            "subcategory":"Construction",
            "type":"Services"
        }
    ],
    "sg:phone":"+1 505 769 2259",
    "sg:postcode":"88101",
    "sg:province":"NM",
    "sg:tags":[
        "general",
        "contractor"
    ],
    "wof:name":"White Sands Construction",
    "wof:placetype":"venue"
},
  "geometry": {"coordinates":[-103.16846200000001,34.403018],"type":"Point"}
}