{
  "type": "Feature",
  "properties": {
    "addr:full":"1402 Parkland Cir Aztec NM 87410",
    "addr:housenumber":"1402",
    "addr:postcode":"87410",
    "addr:street":"Parkland Cir",
    "iso:country":"US",
    "sg:address":"1402 Parkland Cir",
    "sg:city":"Aztec",
    "sg:classifiers":[
        {
            "category":"Retail",
            "subcategory":"Laundry & Dry Cleaning",
            "type":"Services"
        }
    ],
    "sg:phone":"+1 505 334 1819",
    "sg:postcode":"87410",
    "sg:province":"NM",
    "sg:tags":[
        "cleaners",
        "rug",
        "carpet"
    ],
    "wof:name":"Heaven's Best Carpet Cleaning",
    "wof:placetype":"venue"
},
  "geometry": {"coordinates":[-108.00738,36.832847],"type":"Point"}
}