{
  "type": "Feature",
  "properties": {
    "iso:country":"US",
    "sg:address":"4001 Office Ct",
    "sg:city":"Santa Fe",
    "sg:classifiers":[
        {
            "category":"Professional",
            "type":"Services"
        }
    ],
    "sg:phone":"+1 505 428 2100",
    "sg:postcode":"87507",
    "sg:province":"NM",
    "sg:tags":[
        "establishment"
    ],
    "wof:name":"Education Credit Management",
    "wof:placetype":"venue"
},
  "geometry": {"coordinates":[-106.015951,35.63296],"type":"Point"}
}