{
  "type": "Feature",
  "properties": {
    "iso:country":"US",
    "sg:address":"5300 Gable St NW",
    "sg:city":"Albuquerque",
    "sg:classifiers":[
        {
            "category":"Communications",
            "subcategory":"Film & Video Production",
            "type":"Services"
        }
    ],
    "sg:phone":"+1 505 898 5370",
    "sg:postcode":"87120",
    "sg:province":"NM",
    "sg:tags":[
        "motion"
    ],
    "wof:name":"Richard Kehl Jr",
    "wof:placetype":"venue"
},
  "geometry": {"coordinates":[-106.715772,35.14643],"type":"Point"}
}