{
  "type": "Feature",
  "properties": {
    "addr:full":"1612 Saint Michaels Dr Santa Fe NM 87505",
    "addr:housenumber":"1612",
    "addr:postcode":"87505",
    "addr:street":"Saint Michaels Dr",
    "iso:country":"US",
    "sg:address":"1612 Saint Michaels Dr",
    "sg:city":"Santa Fe",
    "sg:classifiers":[
        {
            "category":"Government",
            "subcategory":"Office",
            "type":"Public Place"
        }
    ],
    "sg:phone":"+1 505 471 7821",
    "sg:postcode":"87505",
    "sg:province":"NM",
    "sg:tags":[
        "armed",
        "force",
        "recruiting"
    ],
    "wof:name":"US Army Recruiting",
    "wof:placetype":"venue"
},
  "geometry": {"coordinates":[-105.974054,35.659539],"type":"Point"}
}