{
  "type": "Feature",
  "properties": {
    "iso:country":"US",
    "sg:address":"1200 E White St",
    "sg:city":"Hobbs",
    "sg:classifiers":[
        {
            "category":"Organizations",
            "subcategory":"Community Association",
            "type":"Services"
        }
    ],
    "sg:phone":"+1 505 393 6218",
    "sg:postcode":"88240",
    "sg:province":"NM",
    "sg:tags":[
        "fraternal"
    ],
    "wof:name":"Fraternal Order Of Eagles",
    "wof:placetype":"venue"
},
  "geometry": {"coordinates":[-103.123684,32.698849],"type":"Point"}
}