{
  "type": "Feature",
  "properties": {
    "iso:country":"US",
    "sg:address":"5809 Jefferson St NE",
    "sg:city":"Albuquerque",
    "sg:classifiers":[
        {
            "category":"Manufacturing",
            "subcategory":"Tools & Machinery",
            "type":"Manufacturing & Wholesale Goods"
        }
    ],
    "sg:phone":"+1 505 342 2943",
    "sg:postcode":"87109",
    "sg:province":"NM",
    "sg:tags":[
        "machine",
        "shop"
    ],
    "sg:website":"www.backerworks.com",
    "wof:name":"Backerworks Manufacturing",
    "wof:placetype":"venue"
},
  "geometry": {"coordinates":[-106.59548599999999,35.147051],"type":"Point"}
}