{
  "type": "Feature",
  "properties": {
    "iso:country":"US",
    "sg:address":"4015 Arkansas Ave",
    "sg:city":"Los Alamos",
    "sg:classifiers":[
        {
            "category":"Shopping",
            "subcategory":"Clothing, Apparel, & Fashions",
            "type":"Retail Goods"
        }
    ],
    "sg:phone":"+1 505 662 5053",
    "sg:postcode":"87544",
    "sg:province":"NM",
    "sg:tags":[
        "salvage",
        "surplus",
        "merchandise"
    ],
    "wof:name":"Black Hole/Los Alamos Sales Co",
    "wof:placetype":"venue"
},
  "geometry": {"coordinates":[-106.31936,35.899725],"type":"Point"}
}