{
  "type": "Feature",
  "properties": {
    "iso:country":"US",
    "sg:address":"5505 Cam Arbustos NE",
    "sg:city":"Albuquerque",
    "sg:classifiers":[
        {
            "category":"Professional",
            "type":"Services"
        }
    ],
    "sg:phone":"+1 505 293 8538",
    "sg:postcode":"87111",
    "sg:province":"NM",
    "sg:tags":[
        "establishment"
    ],
    "wof:name":"A J Precision Design",
    "wof:placetype":"venue"
},
  "geometry": {"coordinates":[-106.50172600000001,35.143735],"type":"Point"}
}