{
  "type": "Feature",
  "properties": {
    "iso:country":"US",
    "sg:address":"415 W Scharbauer St",
    "sg:city":"Hobbs",
    "sg:classifiers":[
        {
            "category":"Organizations",
            "subcategory":"Religious Organization",
            "type":"Services"
        }
    ],
    "sg:phone":"+1 505 397 4100",
    "sg:postcode":"88240",
    "sg:province":"NM",
    "sg:tags":[
        "church"
    ],
    "wof:name":"Scharbauer Street Church",
    "wof:placetype":"venue"
},
  "geometry": {"coordinates":[-103.141024,32.708084],"type":"Point"}
}