{
  "type": "Feature",
  "properties": {
    "iso:country":"US",
    "sg:address":"1455 Sunset Rd SE",
    "sg:city":"Rio Rancho",
    "sg:classifiers":[
        {
            "category":"Building & Trades",
            "subcategory":"Cleaning & Sanitation",
            "type":"Services"
        }
    ],
    "sg:phone":"+1 505 891 3052",
    "sg:postcode":"87124",
    "sg:province":"NM",
    "sg:tags":[
        "janitor",
        "maintenance"
    ],
    "wof:name":"K & L Cleaning Specialists LLC",
    "wof:placetype":"venue"
},
  "geometry": {"coordinates":[-106.706774,35.258416],"type":"Point"}
}