{
  "type": "Feature",
  "properties": {
    "iso:country":"US",
    "sg:address":"1600 Carlisle Blvd SE",
    "sg:city":"Albuquerque",
    "sg:classifiers":[
        {
            "category":"Food & Beverages",
            "subcategory":"Groceries & Convenience Stores",
            "type":"Retail Goods"
        }
    ],
    "sg:phone":"+1 505 254 3590",
    "sg:postcode":"87106",
    "sg:province":"NM",
    "wof:name":"Sami Food Mart",
    "wof:placetype":"venue"
},
  "geometry": {"coordinates":[-106.6043,35.058257],"type":"Point"}
}