{
  "type": "Feature",
  "properties": {
    "addr:full":"3612 San Pedro Dr NE Albuquerque NM 87110",
    "addr:housenumber":"3612",
    "addr:postcode":"87110",
    "addr:street":"San Pedro Dr Ne",
    "iso:country":"US",
    "sg:address":"3612 San Pedro Dr NE",
    "sg:city":"Albuquerque",
    "sg:classifiers":[
        {
            "category":"Professional",
            "subcategory":"Management & Consulting",
            "type":"Services"
        }
    ],
    "sg:phone":"+1 505 884 3877",
    "sg:postcode":"87110",
    "sg:province":"NM",
    "wof:name":"Diversified Solutions LLC",
    "wof:placetype":"venue"
},
  "geometry": {"coordinates":[-106.57701900000001,35.125834],"type":"Point"}
}