{
  "type": "Feature",
  "properties": {
    "iso:country":"US",
    "sg:address":"3121 San Pedro Dr NE",
    "sg:city":"Albuquerque",
    "sg:classifiers":[
        {
            "category":"Building & Trades",
            "subcategory":"Landscaping Services",
            "type":"Services"
        }
    ],
    "sg:phone":"+1 505 830 2449",
    "sg:postcode":"87110",
    "sg:province":"NM",
    "sg:tags":[
        "lawn",
        "maintenance",
        "grounds"
    ],
    "wof:name":"A Cut Above Lawn & Landscaping",
    "wof:placetype":"venue"
},
  "geometry": {"coordinates":[-106.577687,35.11931],"type":"Point"}
}