{
  "type": "Feature",
  "properties": {
    "iso:country":"US",
    "sg:address":"5716 N Lovington Hwy",
    "sg:city":"Hobbs",
    "sg:classifiers":[
        {
            "category":"Freight",
            "type":"Transportation"
        }
    ],
    "sg:phone":"+1 505 392 7466",
    "sg:postcode":"88240",
    "sg:province":"NM",
    "sg:tags":[
        "hauling",
        "trucking"
    ],
    "wof:name":"Coombes Trucking",
    "wof:placetype":"venue"
},
  "geometry": {"coordinates":[-103.185208,32.765233],"type":"Point"}
}