{
  "type": "Feature",
  "properties": {
    "addr:full":"1540 Juan Tabo Blvd NE Albuquerque NM 87112",
    "addr:housenumber":"1540",
    "addr:postcode":"87112",
    "addr:street":"Juan Tabo Blvd Ne",
    "iso:country":"US",
    "sg:address":"1540 Juan Tabo Blvd NE",
    "sg:city":"Albuquerque",
    "sg:classifiers":[
        {
            "category":"Personal",
            "subcategory":"Beauty Salon",
            "type":"Services"
        }
    ],
    "sg:phone":"+1 505 292 8700",
    "sg:postcode":"87112",
    "sg:province":"NM",
    "sg:tags":[
        "shop"
    ],
    "wof:name":"Studio One",
    "wof:placetype":"venue"
},
  "geometry": {"coordinates":[-106.515314,35.0991],"type":"Point"}
}