{
  "type": "Feature",
  "properties": {
    "iso:country":"US",
    "sg:address":"126 Yucca Dr",
    "sg:city":"Portales",
    "sg:classifiers":[
        {
            "category":"Farming",
            "subcategory":"Farm",
            "type":"Manufacturing & Wholesale Goods"
        }
    ],
    "sg:phone":"+1 505 359 6886",
    "sg:postcode":"88130",
    "sg:province":"NM",
    "sg:tags":[
        "crop",
        "general"
    ],
    "wof:name":"Nuckols Ranch Inc",
    "wof:placetype":"venue"
},
  "geometry": {"coordinates":[-103.340328,34.166933],"type":"Point"}
}