{
  "type": "Feature",
  "properties": {
    "iso:country":"US",
    "sg:address":"570 Western Mesa Rd",
    "sg:city":"Corrales",
    "sg:classifiers":[
        {
            "category":"Food & Beverages",
            "subcategory":"Liquor & Beverages",
            "type":"Retail Goods"
        }
    ],
    "sg:phone":"+1 505 890 3695",
    "sg:postcode":"87048",
    "sg:province":"NM",
    "sg:tags":[
        "wine"
    ],
    "wof:name":"Nm Wine Grwrs Assc",
    "wof:placetype":"venue"
},
  "geometry": {"coordinates":[-106.636351,35.228922],"type":"Point"}
}