{
  "type": "Feature",
  "properties": {
    "iso:country":"US",
    "sg:address":"1946 Cerrillos Rd",
    "sg:city":"Santa Fe",
    "sg:classifiers":[
        {
            "category":"Retail",
            "subcategory":"Auto Rental",
            "type":"Services"
        }
    ],
    "sg:phone":"+1 505 984 1096",
    "sg:postcode":"87505",
    "sg:province":"NM",
    "sg:tags":[
        "renting",
        "automobile"
    ],
    "wof:name":"Sears Car & Truck Rental",
    "wof:placetype":"venue"
},
  "geometry": {"coordinates":[-105.97447099999999,35.663986],"type":"Point"}
}