{
  "type": "Feature",
  "properties": {
    "addr:full":"993 Cam del Pueblo Bernalillo NM 87004",
    "addr:housenumber":"993",
    "addr:postcode":"87004",
    "addr:street":"Cam Del Pueblo",
    "iso:country":"US",
    "sg:address":"993 Cam del Pueblo",
    "sg:city":"Bernalillo",
    "sg:classifiers":[
        {
            "category":"Professional",
            "subcategory":"Management & Consulting",
            "type":"Services"
        }
    ],
    "sg:phone":"+1 505 239 0970",
    "sg:postcode":"87004",
    "sg:province":"NM",
    "sg:tags":[
        "marketing",
        "program"
    ],
    "wof:name":"CRC & Assoc",
    "wof:placetype":"venue"
},
  "geometry": {"coordinates":[-106.550664,35.3012],"type":"Point"}
}