{
  "type": "Feature",
  "properties": {
    "iso:country":"US",
    "sg:address":"720 Saint Michaels Dr",
    "sg:city":"Santa Fe",
    "sg:classifiers":[
        {
            "category":"Shopping",
            "type":"Retail Goods"
        }
    ],
    "sg:phone":"+1 505 989 3941",
    "sg:postcode":"87505",
    "sg:province":"NM",
    "sg:tags":[
        "art",
        "gallery",
        "dealer"
    ],
    "wof:name":"Cindia Harlan Fine Art",
    "wof:placetype":"venue"
},
  "geometry": {"coordinates":[-105.961209,35.659383],"type":"Point"}
}