{
  "type": "Feature",
  "properties": {
    "iso:country":"US",
    "sg:address":"78 Cities of Gold Rd",
    "sg:city":"Santa Fe",
    "sg:classifiers":[
        {
            "category":"Government",
            "subcategory":"Office",
            "type":"Public Place"
        }
    ],
    "sg:phone":"+1 505 455 1110",
    "sg:postcode":"87506",
    "sg:province":"NM",
    "sg:tags":[
        "educational",
        "program",
        "administrative"
    ],
    "wof:name":"Indian Vocational Education",
    "wof:placetype":"venue"
},
  "geometry": {"coordinates":[-106.01331,35.882573],"type":"Point"}
}