{
  "type": "Feature",
  "properties": {
    "addr:full":"1117 S 2nd St Raton NM 87740",
    "addr:housenumber":"1117",
    "addr:postcode":"87740",
    "addr:street":"S 2Nd St",
    "iso:country":"US",
    "sg:address":"1117 S 2nd St",
    "sg:city":"Raton",
    "sg:classifiers":[
        {
            "category":"Banks & Credit Unions",
            "subcategory":"Bank",
            "type":"Services"
        }
    ],
    "sg:phone":"+1 505 445 0300",
    "sg:postcode":"87740",
    "sg:province":"NM",
    "sg:tags":[
        "institution",
        "business"
    ],
    "wof:name":"AAA Title & Check Loan",
    "wof:placetype":"venue"
},
  "geometry": {"coordinates":[-104.440173,36.887826],"type":"Point"}
}