{
  "type": "Feature",
  "properties": {
    "iso:country":"US",
    "sg:address":"1102 E Fiesta Dr",
    "sg:city":"Carlsbad",
    "sg:classifiers":[
        {
            "category":"Retail",
            "subcategory":"Repair Shop",
            "type":"Services"
        }
    ],
    "sg:phone":"+1 505 885 7301",
    "sg:postcode":"88220",
    "sg:province":"NM",
    "sg:tags":[
        "taxidermist"
    ],
    "wof:name":"Artistic Wildlife Studio",
    "wof:placetype":"venue"
},
  "geometry": {"coordinates":[-104.205055,32.403871],"type":"Point"}
}