{
  "type": "Feature",
  "properties": {
    "iso:country":"US",
    "sg:address":"1112 10th St SE",
    "sg:city":"Rio Rancho",
    "sg:classifiers":[
        {
            "category":"Professional",
            "subcategory":"Accounting & Tax Preparation",
            "type":"Services"
        }
    ],
    "sg:phone":"+1 505 892 9852",
    "sg:postcode":"87124",
    "sg:province":"NM",
    "sg:tags":[
        "auditing"
    ],
    "wof:name":"P C Lecompte",
    "wof:placetype":"venue"
},
  "geometry": {"coordinates":[-106.716779,35.238581],"type":"Point"}
}