{
  "type": "Feature",
  "properties": {
    "addr:full":"415 Cedar St SE Albuquerque NM 87106",
    "addr:housenumber":"415",
    "addr:postcode":"87106",
    "addr:street":"Cedar St Se",
    "iso:country":"US",
    "sg:address":"415 Cedar St SE",
    "sg:city":"Albuquerque",
    "sg:classifiers":[
        {
            "category":"Health Services",
            "subcategory":"Health Practitioner",
            "type":"Services"
        }
    ],
    "sg:phone":"+1 505 224 7373",
    "sg:postcode":"87106",
    "sg:province":"NM",
    "sg:tags":[
        "audiologists"
    ],
    "wof:name":"Hearing Health Care Ctr",
    "wof:placetype":"venue"
},
  "geometry": {"coordinates":[-106.634663,35.078479],"type":"Point"}
}