{
  "type": "Feature",
  "properties": {
    "iso:country":"US",
    "sg:address":"911 S Texaco Rd",
    "sg:city":"Hobbs",
    "sg:classifiers":[
        {
            "category":"Mining & Drilling",
            "type":"Manufacturing & Wholesale Goods"
        }
    ],
    "sg:phone":"+1 505 393 7032",
    "sg:postcode":"88240",
    "sg:province":"NM",
    "sg:tags":[
        "field"
    ],
    "wof:name":"Norris Sucker Rods",
    "wof:placetype":"venue"
},
  "geometry": {"coordinates":[-103.162071,32.692664],"type":"Point"}
}