{
  "type": "Feature",
  "properties": {
    "addr:full":"3500 Cardenas Pl NE Albuquerque NM 87110",
    "addr:housenumber":"3500",
    "addr:postcode":"87110",
    "addr:street":"Cardenas Pl Ne",
    "iso:country":"US",
    "sg:address":"3500 Cardenas Pl NE",
    "sg:city":"Albuquerque",
    "sg:classifiers":[
        {
            "category":"Wholesale",
            "subcategory":"Chemicals & Plastics",
            "type":"Manufacturing & Wholesale Goods"
        }
    ],
    "sg:phone":"+1 505 463 8928",
    "sg:postcode":"87110",
    "sg:province":"NM",
    "sg:tags":[
        "product"
    ],
    "wof:name":"Faunus Tek Inc",
    "wof:placetype":"venue"
},
  "geometry": {"coordinates":[-106.578329,35.125591],"type":"Point"}
}