{
  "type": "Feature",
  "properties": {
    "iso:country":"US",
    "sg:address":"2419 Don Onofre Trl NW",
    "sg:city":"Albuquerque",
    "sg:classifiers":[
        {
            "category":"Manufacturing",
            "subcategory":"Jewelry",
            "type":"Manufacturing & Wholesale Goods"
        }
    ],
    "sg:phone":"+1 505 341 2457",
    "sg:postcode":"87107",
    "sg:province":"NM",
    "sg:tags":[
        "costume",
        "mfg"
    ],
    "wof:name":"Dalriada Handcrafts",
    "wof:placetype":"venue"
},
  "geometry": {"coordinates":[-106.673483,35.13354],"type":"Point"}
}