{
  "type": "Feature",
  "properties": {
    "addr:full":"7904 Hannett Ave NE Albuquerque NM 87110",
    "addr:housenumber":"7904",
    "addr:postcode":"87110",
    "addr:street":"Hannett Ave Ne",
    "iso:country":"US",
    "sg:address":"7904 Hannett Ave NE",
    "sg:city":"Albuquerque",
    "sg:classifiers":[
        {
            "category":"Health Services",
            "subcategory":"Nursing And Care Facility",
            "type":"Services"
        },
        {
            "category":"Health Services",
            "subcategory":"Health Practitioner",
            "type":"Services"
        }
    ],
    "sg:phone":"+1 505 332 2607",
    "sg:postcode":"87110",
    "sg:province":"NM",
    "sg:tags":[
        "physician",
        "nurse",
        "assistant"
    ],
    "wof:name":"Helen A. Sayers",
    "wof:placetype":"venue"
},
  "geometry": {"coordinates":[-106.556257,35.097826],"type":"Point"}
}