{
  "type": "Feature",
  "properties": {
    "addr:full":"9800 Menaul Blvd NE Albuquerque NM 87112",
    "addr:housenumber":"9800",
    "addr:postcode":"87112",
    "addr:street":"Menaul Blvd Ne",
    "iso:country":"US",
    "sg:address":"9800 Menaul Blvd NE",
    "sg:city":"Albuquerque",
    "sg:classifiers":[
        {
            "category":"Restaurant",
            "type":"Food & Drink"
        }
    ],
    "sg:phone":"+1 505 292 8877",
    "sg:postcode":"87112",
    "sg:province":"NM",
    "sg:website":"www.papafelipes.com",
    "wof:name":"Papa Felipe's Mexican Rstrnt",
    "wof:placetype":"venue"
},
  "geometry": {"coordinates":[-106.528248,35.108984],"type":"Point"}
}