{
  "type": "Feature",
  "properties": {
    "iso:country":"US",
    "sg:address":"11 Cll Medico",
    "sg:city":"Santa Fe",
    "sg:classifiers":[
        {
            "category":"Health Services",
            "subcategory":"Clinic",
            "type":"Services"
        }
    ],
    "sg:phone":"+1 505 983 8722",
    "sg:postcode":"87505",
    "sg:province":"NM",
    "sg:tags":[
        "colonic",
        "irrigation"
    ],
    "wof:name":"Martha G Flannery",
    "wof:placetype":"venue"
},
  "geometry": {"coordinates":[-105.941279,35.658208],"type":"Point"}
}