{
  "type": "Feature",
  "properties": {
    "iso:country":"US",
    "sg:address":"2800 Lawrence Blvd",
    "sg:city":"Alamogordo",
    "sg:classifiers":[
        {
            "category":"Real Estate",
            "subcategory":"Real Estate Operator",
            "type":"Services"
        }
    ],
    "sg:phone":"+1 505 437 1908",
    "sg:postcode":"88310",
    "sg:province":"NM",
    "sg:tags":[
        "mobile",
        "home",
        "site"
    ],
    "wof:name":"Oasis Mobile Home Park",
    "wof:placetype":"venue"
},
  "geometry": {"coordinates":[-105.958848,32.92177],"type":"Point"}
}