{
  "type": "Feature",
  "properties": {
    "iso:country":"US",
    "sg:address":"3908 Pso del Sol",
    "sg:city":"Santa Fe",
    "sg:classifiers":[
        {
            "category":"Social Services",
            "subcategory":"Child Care",
            "type":"Services"
        }
    ],
    "sg:phone":"+1 505 438 4165",
    "sg:postcode":"87507",
    "sg:province":"NM",
    "sg:tags":[
        "day"
    ],
    "wof:name":"Presbyterian Medical Services",
    "wof:placetype":"venue"
},
  "geometry": {"coordinates":[-106.043588,35.633365],"type":"Point"}
}