{
  "type": "Feature",
  "properties": {
    "iso:country":"US",
    "sg:address":"1776 N Turner St",
    "sg:city":"Hobbs",
    "sg:classifiers":[
        {
            "category":"Recreation",
            "type":"Entertainment"
        }
    ],
    "sg:phone":"+1 505 393 9201",
    "sg:postcode":"88240",
    "sg:province":"NM",
    "sg:tags":[
        "club",
        "membership",
        "sport"
    ],
    "wof:name":"Womans Club",
    "wof:placetype":"venue"
},
  "geometry": {"coordinates":[-103.140697,32.718336],"type":"Point"}
}