{
  "type": "Feature",
  "properties": {
    "iso:country":"US",
    "sg:address":"1209 Sudderth Dr",
    "sg:city":"Ruidoso",
    "sg:classifiers":[
        {
            "category":"Personal",
            "subcategory":"Beauty Salon",
            "type":"Services"
        }
    ],
    "sg:phone":"+1 505 257 2381",
    "sg:postcode":"88345",
    "sg:province":"NM",
    "sg:tags":[
        "shop"
    ],
    "wof:name":"Marthas Hair & Nails",
    "wof:placetype":"venue"
},
  "geometry": {"coordinates":[-105.659739,33.325975],"type":"Point"}
}