{
  "type": "Feature",
  "properties": {
    "addr:full":"4155 State Rte 68 Ranchos De Taos NM 87557",
    "addr:housenumber":"4155",
    "addr:postcode":"87557",
    "addr:street":"State Rte 68",
    "iso:country":"US",
    "sg:address":"4155 State Rte 68",
    "sg:city":"Ranchos De Taos",
    "sg:classifiers":[
        {
            "category":"Social Services",
            "type":"Services"
        }
    ],
    "sg:phone":"+1 505 737 5555",
    "sg:postcode":"87557",
    "sg:province":"NM",
    "wof:name":"Southwest Care Center",
    "wof:placetype":"venue"
},
  "geometry": {"coordinates":[-105.606357,36.36122],"type":"Point"}
}