{
  "type": "Feature",
  "properties": {
    "iso:country":"US",
    "sg:address":"1626 Agua Fria St",
    "sg:city":"Santa Fe",
    "sg:classifiers":[
        {
            "category":"Building & Trades",
            "subcategory":"Construction",
            "type":"Services"
        }
    ],
    "sg:phone":"+1 505 471 0805",
    "sg:postcode":"87505",
    "sg:province":"NM",
    "sg:tags":[
        "contractor"
    ],
    "wof:name":"Ornelas & Sons Roofing",
    "wof:placetype":"venue"
},
  "geometry": {"coordinates":[-105.971279,35.676641],"type":"Point"}
}