{
  "type": "Feature",
  "properties": {
    "addr:full":"6001 Carousal Ave NW Albuquerque NM 87120",
    "addr:housenumber":"6001",
    "addr:postcode":"87120",
    "addr:street":"Carousal Ave Nw",
    "iso:country":"US",
    "sg:address":"6001 Carousal Ave NW",
    "sg:city":"Albuquerque",
    "sg:classifiers":[
        {
            "category":"Arts & Performance",
            "subcategory":"Theater",
            "type":"Entertainment"
        }
    ],
    "sg:phone":"+1 505 888 1707",
    "sg:postcode":"87120",
    "sg:province":"NM",
    "sg:tags":[
        "group"
    ],
    "wof:name":"Too Hot To Stop",
    "wof:placetype":"venue"
},
  "geometry": {"coordinates":[-106.70669700000001,35.156348],"type":"Point"}
}