{
  "type": "Feature",
  "properties": {
    "addr:full":"505 S Main St Las Cruces NM 88001",
    "addr:housenumber":"505",
    "addr:postcode":"88001",
    "addr:street":"S Main St",
    "iso:country":"US",
    "sg:address":"505 S Main St",
    "sg:city":"Las Cruces",
    "sg:classifiers":[
        {
            "category":"Government",
            "subcategory":"Office",
            "type":"Public Place"
        }
    ],
    "sg:phone":"+1 505 528 1561",
    "sg:postcode":"88001",
    "sg:province":"NM",
    "wof:name":"US Pretrial Svc",
    "wof:placetype":"venue"
},
  "geometry": {"coordinates":[-106.77756100000001,32.305936],"type":"Point"}
}