{
  "type": "Feature",
  "properties": {
    "iso:country":"US",
    "sg:address":"2113 Oxford Ave SE",
    "sg:city":"Albuquerque",
    "sg:classifiers":[
        {
            "category":"Professional",
            "type":"Services"
        }
    ],
    "sg:phone":"+1 505 203 8244",
    "sg:postcode":"87106",
    "sg:province":"NM",
    "sg:tags":[
        "arts",
        "artist"
    ],
    "wof:name":"Mikoarts",
    "wof:placetype":"venue"
},
  "geometry": {"coordinates":[-106.622321,35.076087],"type":"Point"}
}