{
  "type": "Feature",
  "properties": {
    "addr:full":"4542 Yucca St Los Alamos NM 87544",
    "addr:housenumber":"4542",
    "addr:postcode":"87544",
    "addr:street":"Yucca St",
    "iso:country":"US",
    "sg:address":"4542 Yucca St",
    "sg:city":"Los Alamos",
    "sg:classifiers":[
        {
            "category":"Organizations",
            "subcategory":"Religious Organization",
            "type":"Services"
        }
    ],
    "sg:phone":"+1 505 662 0472",
    "sg:postcode":"87544",
    "sg:province":"NM",
    "sg:tags":[
        "church"
    ],
    "wof:name":"Kingdom Hall-Jehovah's Witness",
    "wof:placetype":"venue"
},
  "geometry": {"coordinates":[-106.325971,35.900405],"type":"Point"}
}