{
  "type": "Feature",
  "properties": {
    "addr:full":"1352 Peyton Rd Los Lunas NM 87031",
    "addr:housenumber":"1352",
    "addr:postcode":"87031",
    "addr:street":"Peyton Rd",
    "iso:country":"US",
    "sg:address":"1352 Peyton Rd",
    "sg:city":"Los Lunas",
    "sg:classifiers":[
        {
            "category":"Shopping",
            "subcategory":"Used Merchandise",
            "type":"Retail Goods"
        }
    ],
    "sg:phone":"+1 505 865 9869",
    "sg:postcode":"87031",
    "sg:province":"NM",
    "wof:name":"Nancy Dealy",
    "wof:placetype":"venue"
},
  "geometry": {"coordinates":[-106.76601700000001,34.75097],"type":"Point"}
}