{
  "type": "Feature",
  "properties": {
    "iso:country":"US",
    "sg:address":"301 Mechem Dr",
    "sg:city":"Ruidoso",
    "sg:classifiers":[
        {
            "category":"Travel",
            "subcategory":"Hotels & Motels",
            "type":"Entertainment"
        }
    ],
    "sg:phone":"+1 505 257 3131",
    "sg:postcode":"88345",
    "sg:province":"NM",
    "sg:tags":[
        "chalet",
        "rental",
        "cabin"
    ],
    "wof:name":"Bear Mountain Lodge",
    "wof:placetype":"venue"
},
  "geometry": {"coordinates":[-105.67962199999999,33.335487],"type":"Point"}
}