{
  "type": "Feature",
  "properties": {
    "iso:country":"US",
    "sg:address":"1152 de Vargas Ct",
    "sg:city":"Los Lunas",
    "sg:classifiers":[
        {
            "category":"Retail",
            "subcategory":"Repair Shop",
            "type":"Services"
        }
    ],
    "sg:phone":"+1 505 865 3505",
    "sg:postcode":"87031",
    "sg:province":"NM",
    "wof:name":"Johnny Trevino",
    "wof:placetype":"venue"
},
  "geometry": {"coordinates":[-106.725377,34.801121],"type":"Point"}
}