{
  "type": "Feature",
  "properties": {
    "iso:country":"US",
    "sg:address":"1820 S Industrial Dr",
    "sg:city":"Portales",
    "sg:classifiers":[
        {
            "category":"Manufacturing",
            "subcategory":"Food",
            "type":"Manufacturing & Wholesale Goods"
        }
    ],
    "sg:phone":"+1 505 359 2841",
    "sg:postcode":"88130",
    "sg:province":"NM",
    "sg:tags":[
        "fluid",
        "milk"
    ],
    "sg:website":"www.dfamilk.com",
    "wof:name":"Dairy Farmers Of America",
    "wof:placetype":"venue"
},
  "geometry": {"coordinates":[-103.369955,34.169622],"type":"Point"}
}