{
  "type": "Feature",
  "properties": {
    "iso:country":"US",
    "sg:address":"24 Lisbon Ave SE",
    "sg:city":"Rio Rancho",
    "sg:classifiers":[
        {
            "category":"Recreation",
            "type":"Entertainment"
        }
    ],
    "sg:phone":"+1 505 994 8335",
    "sg:postcode":"87124",
    "sg:province":"NM",
    "sg:tags":[
        "astrologer"
    ],
    "wof:name":"Amrita Astrological Services",
    "wof:placetype":"venue"
},
  "geometry": {"coordinates":[-106.704936,35.260411],"type":"Point"}
}