{
  "type": "Feature",
  "properties": {
    "iso:country":"US",
    "sg:address":"2117 N French Dr",
    "sg:city":"Hobbs",
    "sg:classifiers":[
        {
            "category":"Building & Trades",
            "subcategory":"Equipment Rental",
            "type":"Services"
        }
    ],
    "sg:phone":"+1 505 393 1717",
    "sg:postcode":"88240",
    "sg:province":"NM",
    "sg:tags":[
        "oil",
        "well",
        "supply"
    ],
    "wof:name":"Arrow Completion Systems",
    "wof:placetype":"venue"
},
  "geometry": {"coordinates":[-103.16211300000001,32.725428],"type":"Point"}
}