{
  "type": "Feature",
  "properties": {
    "addr:full":"201 E Blodgett St Carlsbad NM 88220",
    "addr:housenumber":"201",
    "addr:postcode":"88220",
    "addr:street":"E Blodgett St",
    "iso:country":"US",
    "sg:address":"201 E Blodgett St",
    "sg:city":"Carlsbad",
    "sg:classifiers":[
        {
            "category":"Home & Garden",
            "subcategory":"Building Materials",
            "type":"Retail Goods"
        }
    ],
    "sg:phone":"+1 505 887 7975",
    "sg:postcode":"88220",
    "sg:province":"NM",
    "sg:tags":[
        "type",
        "door"
    ],
    "wof:name":"Browning Garage Doors",
    "wof:placetype":"venue"
},
  "geometry": {"coordinates":[-104.224807,32.432108],"type":"Point"}
}