{
  "type": "Feature",
  "properties": {
    "addr:full":"5300 Homestead Rd NE Albuquerque NM 87110",
    "addr:housenumber":"5300",
    "addr:postcode":"87110",
    "addr:street":"Homestead Rd Ne",
    "iso:country":"US",
    "sg:address":"5300 Homestead Rd NE",
    "sg:city":"Albuquerque",
    "sg:classifiers":[
        {
            "category":"Government",
            "subcategory":"Office",
            "type":"Public Place"
        }
    ],
    "sg:phone":"+1 505 248 4526",
    "sg:postcode":"87110",
    "sg:province":"NM",
    "sg:tags":[
        "administrative",
        "program",
        "health"
    ],
    "wof:name":"Albuqerque Area Office Ihs",
    "wof:placetype":"venue"
},
  "geometry": {"coordinates":[-106.58573699999999,35.128978],"type":"Point"}
}