{
  "type": "Feature",
  "properties": {
    "iso:country":"US",
    "sg:address":"622 S Iron St",
    "sg:city":"Deming",
    "sg:classifiers":[
        {
            "category":"Professional",
            "subcategory":"Lawyer & Legal Services",
            "type":"Services"
        }
    ],
    "sg:phone":"+1 505 546 8406",
    "sg:postcode":"88030",
    "sg:province":"NM",
    "sg:tags":[
        "attorney"
    ],
    "wof:name":"Pierce Varela & Assoc",
    "wof:placetype":"venue"
},
  "geometry": {"coordinates":[-107.760384,32.262995],"type":"Point"}
}