{
  "type": "Feature",
  "properties": {
    "iso:country":"US",
    "sg:address":"901 Douglas Ave",
    "sg:city":"Las Vegas",
    "sg:classifiers":[
        {
            "category":"Education",
            "subcategory":"School",
            "type":"Public Place"
        }
    ],
    "sg:phone":"+1 505 425 6043",
    "sg:postcode":"87701",
    "sg:province":"NM",
    "sg:website":"www.cybercardinal.com",
    "wof:name":"Mike Mateo Sena Elementary",
    "wof:placetype":"venue"
},
  "geometry": {"coordinates":[-105.21865,35.59379],"type":"Point"}
}