{
  "type": "Feature",
  "properties": {
    "iso:country":"US",
    "sg:address":"30 Reata Rd",
    "sg:city":"Santa Fe",
    "sg:classifiers":[
        {
            "category":"Building & Trades",
            "subcategory":"Plumbing",
            "type":"Services"
        }
    ],
    "sg:phone":"+1 505 471 6169",
    "sg:postcode":"87507",
    "sg:province":"NM",
    "sg:tags":[
        "septic"
    ],
    "wof:name":"Pump Masters",
    "wof:placetype":"venue"
},
  "geometry": {"coordinates":[-106.04964200000001,35.601933],"type":"Point"}
}