{
  "type": "Feature",
  "properties": {
    "addr:full":"1895 Arrowhead Dr NW Deming NM 88030",
    "addr:housenumber":"1895",
    "addr:postcode":"88030",
    "addr:street":"Arrowhead Dr Nw",
    "iso:country":"US",
    "sg:address":"1895 Arrowhead Dr NW",
    "sg:city":"Deming",
    "sg:classifiers":[
        {
            "category":"Building & Trades",
            "subcategory":"Plumbing",
            "type":"Services"
        }
    ],
    "sg:phone":"+1 505 544 8780",
    "sg:postcode":"88030",
    "sg:province":"NM",
    "sg:tags":[
        "product",
        "management",
        "energy",
        "system"
    ],
    "sg:website":"www.dukeenergy.com",
    "wof:name":"Duke Energy",
    "wof:placetype":"venue"
},
  "geometry": {"coordinates":[-107.79862300000001,32.297845],"type":"Point"}
}