{
  "type": "Feature",
  "properties": {
    "iso:country":"US",
    "sg:address":"4314 Lost Feather",
    "sg:city":"Santa Fe",
    "sg:classifiers":[
        {
            "category":"Retail",
            "subcategory":"Animal Services",
            "type":"Services"
        }
    ],
    "sg:phone":"+1 505 424 9111",
    "sg:postcode":"87507",
    "sg:province":"NM",
    "sg:tags":[
        "pet",
        "boarding",
        "sitting"
    ],
    "wof:name":"Paws R Us",
    "wof:placetype":"venue"
},
  "geometry": {"coordinates":[-106.01304500000001,35.630672],"type":"Point"}
}