{
  "type": "Feature",
  "properties": {
    "iso:country":"US",
    "sg:address":"1324 N Chicago Ave",
    "sg:city":"Portales",
    "sg:classifiers":[
        {
            "category":"Retail",
            "subcategory":"Auto Repair",
            "type":"Services"
        }
    ],
    "sg:phone":"+1 505 226 0301",
    "sg:postcode":"88130",
    "sg:province":"NM",
    "sg:tags":[
        "repairing",
        "automobile"
    ],
    "wof:name":"PMS",
    "wof:placetype":"venue"
},
  "geometry": {"coordinates":[-103.33086400000001,34.192946],"type":"Point"}
}