{
  "type": "Feature",
  "properties": {
    "iso:country":"US",
    "sg:address":"5931 Office Blvd NE",
    "sg:city":"Albuquerque",
    "sg:classifiers":[
        {
            "category":"Organizations",
            "subcategory":"Professional Association",
            "type":"Services"
        }
    ],
    "sg:phone":"+1 505 344 3294",
    "sg:postcode":"87109",
    "sg:province":"NM",
    "sg:tags":[
        "business"
    ],
    "wof:name":"Remodelers Council",
    "wof:placetype":"venue"
},
  "geometry": {"coordinates":[-106.601083,35.147949],"type":"Point"}
}