{
  "type": "Feature",
  "properties": {
    "iso:country":"US",
    "sg:address":"539 Hillside Ave",
    "sg:city":"Santa Fe",
    "sg:classifiers":[
        {
            "category":"Professional",
            "subcategory":"Business Services",
            "type":"Services"
        }
    ],
    "sg:phone":"+1 505 982 0373",
    "sg:postcode":"87501",
    "sg:province":"NM",
    "sg:tags":[
        "event"
    ],
    "wof:name":"Events By Design",
    "wof:placetype":"venue"
},
  "geometry": {"coordinates":[-105.92796,35.6869],"type":"Point"}
}