{
  "type": "Feature",
  "properties": {
    "addr:full":"608 W Texas Ave Artesia NM 88210",
    "addr:housenumber":"608",
    "addr:postcode":"88210",
    "addr:street":"W Texas Ave",
    "iso:country":"US",
    "sg:address":"608 W Texas Ave",
    "sg:city":"Artesia",
    "sg:classifiers":[
        {
            "category":"Personal",
            "type":"Services"
        }
    ],
    "sg:phone":"+1 505 746 1222",
    "sg:postcode":"88210",
    "sg:province":"NM",
    "sg:tags":[
        "therapist",
        "massage"
    ],
    "wof:name":"Healing Touch Therapeutic",
    "wof:placetype":"venue"
},
  "geometry": {"coordinates":[-104.40471100000001,32.843367],"type":"Point"}
}