{
  "type": "Feature",
  "properties": {
    "addr:full":"535 Cerrillos Rd Santa Fe NM 87501",
    "addr:housenumber":"535",
    "addr:postcode":"87501",
    "addr:street":"Cerrillos Rd",
    "iso:country":"US",
    "sg:address":"535 Cerrillos Rd",
    "sg:city":"Santa Fe",
    "sg:classifiers":[
        {
            "category":"Organizations",
            "subcategory":"Professional Association",
            "type":"Services"
        }
    ],
    "sg:phone":"+1 505 820 2277",
    "sg:postcode":"87501",
    "sg:province":"NM",
    "sg:website":"www.aarp.org",
    "wof:name":"AARP",
    "wof:placetype":"venue"
},
  "geometry": {"coordinates":[-105.94427899999999,35.68311],"type":"Point"}
}