{
  "type": "Feature",
  "properties": {
    "addr:full":"2746 Jefferson St NE Albuquerque NM 87110",
    "addr:housenumber":"2746",
    "addr:postcode":"87110",
    "addr:street":"Jefferson St Ne",
    "iso:country":"US",
    "sg:address":"2746 Jefferson St NE",
    "sg:city":"Albuquerque",
    "sg:classifiers":[
        {
            "category":"Professional",
            "subcategory":"Computer Services",
            "type":"Services"
        }
    ],
    "sg:phone":"+1 505 888 4590",
    "sg:postcode":"87110",
    "sg:province":"NM",
    "sg:tags":[
        "datum"
    ],
    "wof:name":"Bsr Computer Services",
    "wof:placetype":"venue"
},
  "geometry": {"coordinates":[-106.592659,35.112015],"type":"Point"}
}