{
  "type": "Feature",
  "properties": {
    "iso:country":"US",
    "sg:address":"932 Sunset Rd SW",
    "sg:city":"Albuquerque",
    "sg:classifiers":[
        {
            "category":"Wholesale",
            "subcategory":"Auto Parts",
            "type":"Manufacturing & Wholesale Goods"
        }
    ],
    "sg:phone":"+1 505 243 2871",
    "sg:postcode":"87105",
    "sg:province":"NM",
    "sg:tags":[
        "supply"
    ],
    "wof:name":"NAPA Auto Parts",
    "wof:placetype":"venue"
},
  "geometry": {"coordinates":[-106.674533,35.067057],"type":"Point"}
}