{
  "type": "Feature",
  "properties": {
    "addr:full":"2659 Pan American Fwy Albuquerque NM 87107",
    "addr:housenumber":"2659",
    "addr:postcode":"87107",
    "addr:street":"Pan American Fwy",
    "iso:country":"US",
    "sg:address":"2659 Pan American Fwy",
    "sg:city":"Albuquerque",
    "sg:classifiers":[
        {
            "category":"Building & Trades",
            "subcategory":"Cleaning & Sanitation",
            "type":"Services"
        }
    ],
    "sg:phone":"+1 505 341 1070",
    "sg:postcode":"87107",
    "sg:province":"NM",
    "sg:tags":[
        "maintenance"
    ],
    "wof:name":"Jani-King",
    "wof:placetype":"venue"
},
  "geometry": {"coordinates":[-106.626182,35.112558],"type":"Point"}
}