{
  "type": "Feature",
  "properties": {
    "iso:country":"US",
    "sg:address":"1506 Redrock Dr",
    "sg:city":"Gallup",
    "sg:classifiers":[
        {
            "category":"Shopping",
            "subcategory":"Bicycles & Sporting Goods",
            "type":"Retail Goods"
        }
    ],
    "sg:phone":"+1 505 722 6077",
    "sg:postcode":"87301",
    "sg:province":"NM",
    "wof:name":"Scoreboard",
    "wof:placetype":"venue"
},
  "geometry": {"coordinates":[-108.726709,35.513332],"type":"Point"}
}