{
  "type": "Feature",
  "properties": {
    "addr:full":"200 W Marcy Ave Santa Fe NM 87501",
    "addr:housenumber":"200",
    "addr:postcode":"87501",
    "addr:street":"W Marcy Ave",
    "iso:country":"US",
    "sg:address":"200 W Marcy Ave",
    "sg:city":"Santa Fe",
    "sg:classifiers":[
        {
            "category":"Professional",
            "subcategory":"Lawyer & Legal Services",
            "type":"Services"
        }
    ],
    "sg:phone":"+1 505 982 4676",
    "sg:postcode":"87501",
    "sg:province":"NM",
    "sg:tags":[
        "attorney"
    ],
    "wof:name":"Sommer Udall Hardwick Ahern",
    "wof:placetype":"venue"
},
  "geometry": {"coordinates":[-105.94017700000001,35.689929],"type":"Point"}
}