{
  "type": "Feature",
  "properties": {
    "iso:country":"US",
    "sg:address":"1669 State Hwy 122",
    "sg:city":"Prewitt",
    "sg:classifiers":[
        {
            "category":"Government",
            "subcategory":"Fire Station",
            "type":"Public Place"
        }
    ],
    "sg:phone":"+1 505 876 2525",
    "sg:postcode":"87045",
    "sg:province":"NM",
    "sg:tags":[
        "department"
    ],
    "wof:name":"Prewitt Fire Dept",
    "wof:placetype":"venue"
},
  "geometry": {"coordinates":[-108.04398,35.364543],"type":"Point"}
}