{
  "type": "Feature",
  "properties": {
    "iso:country":"US",
    "sg:address":"340 N Railroad Ave",
    "sg:city":"Espanola",
    "sg:classifiers":[
        {
            "category":"Education",
            "subcategory":"School",
            "type":"Public Place"
        }
    ],
    "sg:phone":"+1 505 747 1456",
    "sg:postcode":"87532",
    "sg:province":"NM",
    "wof:name":"YDI Espanola Head Start",
    "wof:placetype":"venue"
},
  "geometry": {"coordinates":[-106.080151,35.994111],"type":"Point"}
}