{
  "type": "Feature",
  "properties": {
    "iso:country":"US",
    "sg:address":"1720 S Turner St",
    "sg:city":"Hobbs",
    "sg:classifiers":[
        {
            "category":"Organizations",
            "subcategory":"Religious Organization",
            "type":"Services"
        }
    ],
    "sg:phone":"+1 505 393 6855",
    "sg:postcode":"88240",
    "sg:province":"NM",
    "sg:tags":[
        "church"
    ],
    "wof:name":"Lamb-God Christian Fellowship",
    "wof:placetype":"venue"
},
  "geometry": {"coordinates":[-103.137578,32.683923],"type":"Point"}
}