{
  "type": "Feature",
  "properties": {
    "iso:country":"US",
    "sg:address":"2980 N Main St",
    "sg:city":"Las Cruces",
    "sg:classifiers":[
        {
            "category":"Health Services",
            "subcategory":"Doctor",
            "type":"Services"
        }
    ],
    "sg:phone":"+1 505 524 0044",
    "sg:postcode":"88001",
    "sg:province":"NM",
    "wof:name":"Anton F Milavec",
    "wof:placetype":"venue"
},
  "geometry": {"coordinates":[-106.775618,32.340786],"type":"Point"}
}