{
  "type": "Feature",
  "properties": {
    "iso:country":"US",
    "sg:address":"6221 Chappell Rd NE",
    "sg:city":"Albuquerque",
    "sg:classifiers":[
        {
            "category":"Building & Trades",
            "subcategory":"Construction",
            "type":"Services"
        },
        {
            "category":"Manufacturing",
            "subcategory":"Electronics",
            "type":"Manufacturing & Wholesale Goods"
        }
    ],
    "sg:phone":"+1 919 942 0262",
    "sg:postcode":"87113",
    "sg:province":"NM",
    "sg:tags":[
        "control",
        "installation",
        "signal",
        "sign",
        "traffic",
        "striping",
        "road"
    ],
    "sg:website":"www.highwaysupply.net",
    "wof:name":"Highway Supply  LLC",
    "wof:placetype":"venue"
},
  "geometry": {"coordinates":[-106.60641200000001,35.146809],"type":"Point"}
}