{
  "type": "Feature",
  "properties": {
    "iso:country":"US",
    "sg:address":"610 Grand Ave",
    "sg:city":"Las Vegas",
    "sg:classifiers":[
        {
            "category":"Autos & Motor Vehicles",
            "subcategory":"Automobile Sales",
            "type":"Retail Goods"
        }
    ],
    "sg:phone":"+1 505 425 6758",
    "sg:postcode":"87701",
    "sg:province":"NM",
    "sg:tags":[
        "car",
        "dealer"
    ],
    "wof:name":"Quality Motor Co",
    "wof:placetype":"venue"
},
  "geometry": {"coordinates":[-105.214021,35.595619],"type":"Point"}
}