{
  "type": "Feature",
  "properties": {
    "iso:country":"US",
    "sg:address":"615 Sudderth Dr",
    "sg:city":"Ruidoso",
    "sg:classifiers":[
        {
            "category":"Professional",
            "subcategory":"Business Services",
            "type":"Services"
        }
    ],
    "sg:phone":"+1 505 257 5101",
    "sg:postcode":"88345",
    "sg:province":"NM",
    "sg:tags":[
        "paging",
        "answering"
    ],
    "wof:name":"Office",
    "wof:placetype":"venue"
},
  "geometry": {"coordinates":[-105.64751,33.323483],"type":"Point"}
}