{
  "type": "Feature",
  "properties": {
    "iso:country":"US",
    "sg:address":"4819 Central Ave SE",
    "sg:city":"Albuquerque",
    "sg:classifiers":[
        {
            "category":"Professional",
            "subcategory":"Management & Consulting",
            "type":"Services"
        }
    ],
    "sg:phone":"+1 505 255 2182",
    "sg:postcode":"87108",
    "sg:province":"NM",
    "sg:tags":[
        "personnel",
        "consultant"
    ],
    "wof:name":"Q Staff",
    "wof:placetype":"venue"
},
  "geometry": {"coordinates":[-106.590456,35.07829],"type":"Point"}
}