{
  "type": "Feature",
  "properties": {
    "iso:country":"US",
    "sg:address":"640 N Riverside Dr",
    "sg:city":"Espanola",
    "sg:classifiers":[
        {
            "category":"Health Services",
            "subcategory":"Doctor",
            "type":"Services"
        }
    ],
    "sg:phone":"+1 505 753 9427",
    "sg:postcode":"87532",
    "sg:province":"NM",
    "sg:tags":[
        "clinic"
    ],
    "sg:website":"www.fmcna.com",
    "wof:name":"Espanola Dialysis",
    "wof:placetype":"venue"
},
  "geometry": {"coordinates":[-106.060802,35.988044],"type":"Point"}
}