{
  "type": "Feature",
  "properties": {
    "addr:full":"1405 S Ave A Portales NM 88130",
    "addr:housenumber":"1405",
    "addr:postcode":"88130",
    "addr:street":"S Ave A Portales",
    "iso:country":"US",
    "sg:address":"1405 S Ave A",
    "sg:city":"Portales",
    "sg:classifiers":[
        {
            "category":"Building & Trades",
            "subcategory":"Landscaping Services",
            "type":"Services"
        }
    ],
    "sg:phone":"+1 505 359 2267",
    "sg:postcode":"88130",
    "sg:province":"NM",
    "wof:name":"Joris Landscape Maint",
    "wof:placetype":"venue"
},
  "geometry": {"coordinates":[-103.33041299999999,34.177285],"type":"Point"}
}