{
  "type": "Feature",
  "properties": {
    "addr:full":"405 N Connelly St Clovis NM 88101",
    "addr:housenumber":"405",
    "addr:postcode":"88101",
    "addr:street":"N Connelly St",
    "iso:country":"US",
    "sg:address":"405 N Connelly St",
    "sg:city":"Clovis",
    "sg:classifiers":[
        {
            "category":"Organizations",
            "subcategory":"Religious Organization",
            "type":"Services"
        }
    ],
    "sg:phone":"+1 505 762 4510",
    "sg:postcode":"88101",
    "sg:province":"NM",
    "sg:tags":[
        "church"
    ],
    "wof:name":"Gospel Clovis Full Korean",
    "wof:placetype":"venue"
},
  "geometry": {"coordinates":[-103.207857,34.402823],"type":"Point"}
}