{
  "type": "Feature",
  "properties": {
    "iso:country":"US",
    "sg:address":"1701 S Houston St",
    "sg:city":"Hobbs",
    "sg:classifiers":[
        {
            "category":"Building & Trades",
            "subcategory":"Cleaning & Sanitation",
            "type":"Services"
        }
    ],
    "sg:phone":"+1 505 631 0787",
    "sg:postcode":"88240",
    "sg:province":"NM",
    "sg:tags":[
        "maintenance"
    ],
    "wof:name":"Mills Lot Maintenance",
    "wof:placetype":"venue"
},
  "geometry": {"coordinates":[-103.13129,32.683997],"type":"Point"}
}