{
  "type": "Feature",
  "properties": {
    "iso:country":"US",
    "sg:address":"4425 Shepard Rd NE",
    "sg:city":"Albuquerque",
    "sg:classifiers":[
        {
            "category":"Home & Garden",
            "subcategory":"Hardware",
            "type":"Retail Goods"
        }
    ],
    "sg:phone":"+1 505 681 9300",
    "sg:postcode":"87110",
    "sg:province":"NM",
    "wof:name":"Osborn Tools LLC",
    "wof:placetype":"venue"
},
  "geometry": {"coordinates":[-106.59545300000001,35.119583],"type":"Point"}
}