{
  "type": "Feature",
  "properties": {
    "iso:country":"US",
    "sg:address":"605 Caine St",
    "sg:city":"Socorro",
    "sg:classifiers":[
        {
            "category":"Wholesale",
            "subcategory":"Jewelry",
            "type":"Manufacturing & Wholesale Goods"
        }
    ],
    "sg:phone":"+1 505 835 2448",
    "sg:postcode":"87801",
    "sg:province":"NM",
    "sg:tags":[
        "stone"
    ],
    "wof:name":"Luna Falls",
    "wof:placetype":"venue"
},
  "geometry": {"coordinates":[-106.899581,34.063046],"type":"Point"}
}