{
  "type": "Feature",
  "properties": {
    "iso:country":"US",
    "sg:address":"206 E Charleston Rd",
    "sg:city":"Roswell",
    "sg:classifiers":[
        {
            "category":"Organizations",
            "subcategory":"Religious Organization",
            "type":"Services"
        }
    ],
    "sg:phone":"+1 505 622 1019",
    "sg:postcode":"88203",
    "sg:province":"NM",
    "sg:tags":[
        "church"
    ],
    "wof:name":"Mountain View Baptist Church",
    "wof:placetype":"venue"
},
  "geometry": {"coordinates":[-104.521987,33.336223],"type":"Point"}
}