{
  "type": "Feature",
  "properties": {
    "iso:country":"US",
    "sg:address":"7201B Montgomery Blvd NE",
    "sg:city":"Albuquerque",
    "sg:classifiers":[
        {
            "category":"Education",
            "subcategory":"Preschool",
            "type":"Public Place"
        },
        {
            "category":"Education",
            "subcategory":"School",
            "type":"Public Place"
        }
    ],
    "sg:phone":"+1 505 702 8767",
    "sg:postcode":"87109",
    "sg:province":"NM",
    "sg:tags":[
        "kindergarten",
        "high",
        "elementary",
        "middle"
    ],
    "sg:website":"http://www.albuquerquechristianschool.com",
    "wof:name":"Albuquerque Christian School",
    "wof:placetype":"venue"
},
  "geometry": {"coordinates":[-106.565398,35.13081],"type":"Point"}
}