{
  "type": "Feature",
  "properties": {
    "iso:country":"US",
    "sg:address":"201 12th St NW",
    "sg:city":"Albuquerque",
    "sg:classifiers":[
        {
            "category":"Professional",
            "subcategory":"Lawyer & Legal Services",
            "type":"Services"
        }
    ],
    "sg:phone":"+1 505 842 8177",
    "sg:postcode":"87102",
    "sg:province":"NM",
    "sg:tags":[
        "attorney"
    ],
    "wof:name":"Willima D Teel Atty At Law",
    "wof:placetype":"venue"
},
  "geometry": {"coordinates":[-106.66040599999999,35.089264],"type":"Point"}
}