{
  "type": "Feature",
  "properties": {
    "addr:full":"1401 N Canal St Carlsbad NM 88220",
    "addr:housenumber":"1401",
    "addr:postcode":"88220",
    "addr:street":"N Canal St",
    "iso:country":"US",
    "sg:address":"1401 N Canal St",
    "sg:city":"Carlsbad",
    "sg:classifiers":[
        {
            "category":"Autos & Motor Vehicles",
            "subcategory":"Fuel & Gas Station",
            "type":"Retail Goods"
        }
    ],
    "sg:phone":"+1 505 885 2700",
    "sg:postcode":"88220",
    "sg:province":"NM",
    "sg:tags":[
        "oil"
    ],
    "wof:name":"Chevron Allsup's Conv Store",
    "wof:placetype":"venue"
},
  "geometry": {"coordinates":[-104.22869,32.444333],"type":"Point"}
}