{
  "type": "Feature",
  "properties": {
    "iso:country":"US",
    "sg:address":"1589 San Mateo Ln",
    "sg:city":"Santa Fe",
    "sg:classifiers":[
        {
            "category":"Retail",
            "subcategory":"Auto Repair",
            "type":"Services"
        }
    ],
    "sg:phone":"+1 505 983 3481",
    "sg:postcode":"87505",
    "sg:province":"NM",
    "sg:tags":[
        "muffler",
        "automotive",
        "system",
        "exhaust"
    ],
    "wof:name":"All Custom X",
    "wof:placetype":"venue"
},
  "geometry": {"coordinates":[-105.961522,35.661498],"type":"Point"}
}