{
  "type": "Feature",
  "properties": {
    "iso:country":"US",
    "sg:address":"2210 Arno St SE",
    "sg:city":"Albuquerque",
    "sg:classifiers":[
        {
            "category":"Professional",
            "type":"Services"
        }
    ],
    "sg:phone":"+1 505 255 6099",
    "sg:postcode":"87102",
    "sg:province":"NM",
    "sg:tags":[
        "establishment"
    ],
    "wof:name":"Field & Frame",
    "wof:placetype":"venue"
},
  "geometry": {"coordinates":[-106.643918,35.059931],"type":"Point"}
}