{
  "type": "Feature",
  "properties": {
    "iso:country":"US",
    "sg:address":"2215 Santo Domingo Ave",
    "sg:city":"Las Cruces",
    "sg:classifiers":[
        {
            "category":"Building & Trades",
            "subcategory":"Construction",
            "type":"Services"
        }
    ],
    "sg:phone":"+1 505 521 0069",
    "sg:postcode":"88011",
    "sg:province":"NM",
    "sg:tags":[
        "house"
    ],
    "wof:name":"Spirit Home Builders Inc",
    "wof:placetype":"venue"
},
  "geometry": {"coordinates":[-106.750525,32.331204],"type":"Point"}
}