{
  "type": "Feature",
  "properties": {
    "iso:country":"US",
    "sg:address":"421 Schulte Rd NW",
    "sg:city":"Albuquerque",
    "sg:classifiers":[
        {
            "category":"Retail",
            "subcategory":"Repair Shop",
            "type":"Services"
        }
    ],
    "sg:phone":"+1 505 341 4933",
    "sg:postcode":"87107",
    "sg:province":"NM",
    "wof:name":"Flash Cycle",
    "wof:placetype":"venue"
},
  "geometry": {"coordinates":[-106.64365599999999,35.156616],"type":"Point"}
}