{
  "type": "Feature",
  "properties": {
    "iso:country":"US",
    "sg:address":"18424 S Hwy 28",
    "sg:city":"San Miguel",
    "sg:classifiers":[
        {
            "category":"Health Services",
            "subcategory":"Doctor",
            "type":"Services"
        }
    ],
    "sg:phone":"+1 505 233 3830",
    "sg:postcode":"88044",
    "sg:province":"NM",
    "sg:tags":[
        "clinic"
    ],
    "wof:name":"LA Clinica De Familia",
    "wof:placetype":"venue"
},
  "geometry": {"coordinates":[-106.72490000000001,32.14804],"type":"Point"}
}