{
  "type": "Feature",
  "properties": {
    "iso:country":"US",
    "sg:address":"2192 Ave de Mesilla",
    "sg:city":"Las Cruces",
    "sg:classifiers":[
        {
            "category":"Manufacturing",
            "subcategory":"Pottery",
            "type":"Manufacturing & Wholesale Goods"
        }
    ],
    "sg:phone":"+1 505 524 0538",
    "sg:postcode":"88005",
    "sg:province":"NM",
    "sg:tags":[
        "product",
        "mfg"
    ],
    "wof:name":"Flying South Pottery",
    "wof:placetype":"venue"
},
  "geometry": {"coordinates":[-106.795753,32.277108],"type":"Point"}
}