{
  "type": "Feature",
  "properties": {
    "iso:country":"US",
    "sg:address":"733 San Mateo Blvd NE",
    "sg:city":"Albuquerque",
    "sg:classifiers":[
        {
            "category":"Professional",
            "subcategory":"Lawyer & Legal Services",
            "type":"Services"
        }
    ],
    "sg:phone":"+1 505 266 9096",
    "sg:postcode":"87108",
    "sg:province":"NM",
    "sg:tags":[
        "attorney"
    ],
    "wof:name":"Smith Law Offices Pa Atty",
    "wof:placetype":"venue"
},
  "geometry": {"coordinates":[-106.586304,35.084241],"type":"Point"}
}