{
  "type": "Feature",
  "properties": {
    "addr:full":"2200 N Atkinson Ave Roswell NM 88201",
    "addr:housenumber":"2200",
    "addr:postcode":"88201",
    "addr:street":"N Atkinson Ave",
    "iso:country":"US",
    "sg:address":"2200 N Atkinson Ave",
    "sg:city":"Roswell",
    "sg:classifiers":[
        {
            "category":"Retail",
            "subcategory":"Auto Rental",
            "type":"Services"
        }
    ],
    "sg:phone":"+1 505 746 9459",
    "sg:postcode":"88201",
    "sg:province":"NM",
    "sg:tags":[
        "renting",
        "truck",
        "leasing"
    ],
    "wof:name":"Budget Truck Rental",
    "wof:placetype":"venue"
},
  "geometry": {"coordinates":[-104.50585599999999,33.416862],"type":"Point"}
}