{
  "type": "Feature",
  "properties": {
    "iso:country":"US",
    "sg:address":"77 Cedar St",
    "sg:city":"Truth Or Cnsqncs",
    "sg:classifiers":[
        {
            "category":"Recreation",
            "subcategory":"Marina",
            "type":"Entertainment"
        }
    ],
    "sg:phone":"+1 505 894 2073",
    "sg:postcode":"87901",
    "sg:province":"NM",
    "sg:website":"www.damsiteresort.com",
    "wof:name":"Dam Site Recreation Area",
    "wof:placetype":"venue"
},
  "geometry": {"coordinates":[-107.249239,33.130435],"type":"Point"}
}