{
  "type": "Feature",
  "properties": {
    "addr:full":"7416 Parkwood Dr NW Albuquerque NM 87120",
    "addr:housenumber":"7416",
    "addr:postcode":"87120",
    "addr:street":"Parkwood Dr Nw",
    "iso:country":"US",
    "sg:address":"7416 Parkwood Dr NW",
    "sg:city":"Albuquerque",
    "sg:classifiers":[
        {
            "category":"Shopping",
            "subcategory":"Gifts & Souvenirs",
            "type":"Retail Goods"
        }
    ],
    "sg:phone":"+1 505 507 4652",
    "sg:postcode":"87120",
    "sg:province":"NM",
    "sg:tags":[
        "shop"
    ],
    "wof:name":"Bumpersnickers",
    "wof:placetype":"venue"
},
  "geometry": {"coordinates":[-106.720263,35.102486],"type":"Point"}
}