{
  "type": "Feature",
  "properties": {
    "iso:country":"US",
    "sg:address":"1726 Solano Dr NE",
    "sg:city":"Albuquerque",
    "sg:classifiers":[
        {
            "category":"Professional",
            "subcategory":"Management & Consulting",
            "type":"Services"
        }
    ],
    "sg:phone":"+1 505 255 2598",
    "sg:postcode":"87110",
    "sg:province":"NM",
    "sg:tags":[
        "consultant"
    ],
    "wof:name":"J Welles & Assoc",
    "wof:placetype":"venue"
},
  "geometry": {"coordinates":[-106.602155,35.101612],"type":"Point"}
}