{
  "type": "Feature",
  "properties": {
    "addr:full":"4901 Rockaway Blvd NE Rio Rancho NM 87124",
    "addr:housenumber":"4901",
    "addr:postcode":"87124",
    "addr:street":"Rockaway Blvd Ne",
    "iso:country":"US",
    "sg:address":"4901 Rockaway Blvd NE",
    "sg:city":"Rio Rancho",
    "sg:classifiers":[
        {
            "category":"Professional",
            "subcategory":"Management & Consulting",
            "type":"Services"
        }
    ],
    "sg:phone":"+1 505 892 5272",
    "sg:postcode":"87124",
    "sg:province":"NM",
    "sg:tags":[
        "consultant",
        "business"
    ],
    "wof:name":"Aviation Certification",
    "wof:placetype":"venue"
},
  "geometry": {"coordinates":[-106.637349,35.260006],"type":"Point"}
}