{
  "type": "Feature",
  "properties": {
    "iso:country":"US",
    "sg:address":"615 Pinon St",
    "sg:city":"Las Cruces",
    "sg:classifiers":[
        {
            "category":"Building & Trades",
            "subcategory":"Construction",
            "type":"Services"
        }
    ],
    "sg:phone":"+1 505 382 9006",
    "sg:postcode":"88001",
    "sg:province":"NM",
    "sg:tags":[
        "general",
        "contractor"
    ],
    "wof:name":"Gilbert Provencio Const Co",
    "wof:placetype":"venue"
},
  "geometry": {"coordinates":[-106.774204,32.31807],"type":"Point"}
}