{
  "type": "Feature",
  "properties": {
    "iso:country":"US",
    "sg:address":"210 W Center St",
    "sg:city":"Tucumcari",
    "sg:classifiers":[
        {
            "category":"Organizations",
            "subcategory":"Non-profit Organization",
            "type":"Services"
        }
    ],
    "sg:phone":"+1 505 461 1914",
    "sg:postcode":"88401",
    "sg:province":"NM",
    "wof:name":"Eastern Plains CAA",
    "wof:placetype":"venue"
},
  "geometry": {"coordinates":[-103.728529,35.177946],"type":"Point"}
}