{
  "type": "Feature",
  "properties": {
    "iso:country":"US",
    "sg:address":"4710 Juan Tabo Blvd NE",
    "sg:city":"Albuquerque",
    "sg:classifiers":[
        {
            "category":"Organizations",
            "subcategory":"Religious Organization",
            "type":"Services"
        }
    ],
    "sg:phone":"+1 505 292 5444",
    "sg:postcode":"87111",
    "sg:province":"NM",
    "sg:tags":[
        "church"
    ],
    "sg:website":"www.hopeevfree.com",
    "wof:name":"Hope Evangelical Free Church",
    "wof:placetype":"venue"
},
  "geometry": {"coordinates":[-106.515601,35.136089],"type":"Point"}
}