{
  "type": "Feature",
  "properties": {
    "iso:country":"US",
    "sg:address":"11019 Cochiti Rd SE",
    "sg:city":"Albuquerque",
    "sg:classifiers":[
        {
            "category":"Wholesale",
            "subcategory":"Home Furnishings",
            "type":"Manufacturing & Wholesale Goods"
        }
    ],
    "sg:phone":"+1 505 296 2985",
    "sg:postcode":"87123",
    "sg:province":"NM",
    "sg:tags":[
        "closet",
        "accessory"
    ],
    "sg:website":"www.classyclosets.com",
    "wof:name":"Classy Closet",
    "wof:placetype":"venue"
},
  "geometry": {"coordinates":[-106.521973,35.06981],"type":"Point"}
}