{
  "type": "Feature",
  "properties": {
    "iso:country":"US",
    "sg:address":"623 Kit Carson Rd",
    "sg:city":"Taos",
    "sg:classifiers":[
        {
            "category":"Health Services",
            "subcategory":"Chiropractor",
            "type":"Services"
        }
    ],
    "sg:phone":"+1 505 737 9364",
    "sg:postcode":"87571",
    "sg:province":"NM",
    "wof:name":"Kama Rickett DC",
    "wof:placetype":"venue"
},
  "geometry": {"coordinates":[-105.56524,36.39547],"type":"Point"}
}