{
  "type": "Feature",
  "properties": {
    "iso:country":"US",
    "sg:address":"2450 Cam Capitan",
    "sg:city":"Santa Fe",
    "sg:classifiers":[
        {
            "category":"Professional",
            "subcategory":"Business Services",
            "type":"Services"
        }
    ],
    "sg:phone":"+1 505 473 9632",
    "sg:postcode":"87505",
    "sg:province":"NM",
    "wof:name":"Bioenergy Dev Group LLC",
    "wof:placetype":"venue"
},
  "geometry": {"coordinates":[-105.968137,35.640927],"type":"Point"}
}