{
  "type": "Feature",
  "properties": {
    "iso:country":"US",
    "sg:address":"4915 Watercress Dr NE",
    "sg:city":"Albuquerque",
    "sg:classifiers":[
        {
            "category":"Shopping",
            "subcategory":"Computers & Home Electronics",
            "type":"Retail Goods"
        }
    ],
    "sg:phone":"+1 505 857 0596",
    "sg:postcode":"87113",
    "sg:province":"NM",
    "sg:tags":[
        "equipment",
        "metal",
        "locating"
    ],
    "wof:name":"Caudill Enterprises/Tesoro",
    "wof:placetype":"venue"
},
  "geometry": {"coordinates":[-106.591528,35.18777],"type":"Point"}
}