{
  "type": "Feature",
  "properties": {
    "iso:country":"US",
    "sg:address":"800 Trinity Dr",
    "sg:city":"Los Alamos",
    "sg:classifiers":[
        {
            "category":"Government",
            "subcategory":"Office",
            "type":"Public Place"
        }
    ],
    "sg:phone":"+1 505 662 8105",
    "sg:postcode":"87544",
    "sg:province":"NM",
    "wof:name":"Los Alamos Chamber Of Commerce",
    "wof:placetype":"venue"
},
  "geometry": {"coordinates":[-106.294229,35.879781],"type":"Point"}
}