{
  "type": "Feature",
  "properties": {
    "iso:country":"US",
    "sg:address":"835 Spruce St",
    "sg:city":"Espanola",
    "sg:classifiers":[
        {
            "category":"Health Services",
            "subcategory":"Doctor",
            "type":"Services"
        }
    ],
    "sg:phone":"+1 505 747 1234",
    "sg:postcode":"87532",
    "sg:province":"NM",
    "sg:tags":[
        "physician",
        "surgeon"
    ],
    "wof:name":"New Mexico Heart Institute",
    "wof:placetype":"venue"
},
  "geometry": {"coordinates":[-106.084729,35.997268],"type":"Point"}
}