{
  "type": "Feature",
  "properties": {
    "addr:full":"1660 Old Pecos Trl Santa Fe NM 87505",
    "addr:housenumber":"1660",
    "addr:postcode":"87505",
    "addr:street":"Old Pecos Trl",
    "iso:country":"US",
    "sg:address":"1660 Old Pecos Trl",
    "sg:city":"Santa Fe",
    "sg:classifiers":[
        {
            "category":"Professional",
            "subcategory":"Lawyer & Legal Services",
            "type":"Services"
        }
    ],
    "sg:phone":"+1 505 988 2994",
    "sg:postcode":"87505",
    "sg:province":"NM",
    "sg:tags":[
        "attorney"
    ],
    "wof:name":"Bulman Shannon Broderick",
    "wof:placetype":"venue"
},
  "geometry": {"coordinates":[-105.938029,35.662353],"type":"Point"}
}