{
  "type": "Feature",
  "properties": {
    "iso:country":"US",
    "sg:address":"4910 E Main St",
    "sg:city":"Farmington",
    "sg:classifiers":[
        {
            "category":"Wholesale",
            "subcategory":"Machinery & Supplies",
            "type":"Manufacturing & Wholesale Goods"
        }
    ],
    "sg:phone":"+1 505 327 9624",
    "sg:postcode":"87402",
    "sg:province":"NM",
    "sg:tags":[
        "equipment",
        "oil",
        "gas"
    ],
    "sg:website":"www.ogequip.com",
    "wof:name":"Oil & Gas Equipment Corp",
    "wof:placetype":"venue"
},
  "geometry": {"coordinates":[-108.148454,36.767045],"type":"Point"}
}