{
  "type": "Feature",
  "properties": {
    "iso:country":"US",
    "sg:address":"519 E Canal St",
    "sg:city":"Alamogordo",
    "sg:classifiers":[
        {
            "category":"Retail",
            "subcategory":"Veterinary Services",
            "type":"Services"
        }
    ],
    "sg:phone":"+1 505 437 7085",
    "sg:postcode":"88310",
    "sg:province":"NM",
    "sg:tags":[
        "veterinarian"
    ],
    "wof:name":"Alamagordo Animal Hospital",
    "wof:placetype":"venue"
},
  "geometry": {"coordinates":[-105.954841,32.915865],"type":"Point"}
}