{
  "type": "Feature",
  "properties": {
    "addr:full":"729 Cam Porvenir Santa Fe NM 87505",
    "addr:housenumber":"729",
    "addr:postcode":"87505",
    "addr:street":"Cam Porvenir",
    "iso:country":"US",
    "sg:address":"729 Cam Porvenir",
    "sg:city":"Santa Fe",
    "sg:classifiers":[
        {
            "category":"Social Services",
            "type":"Services"
        }
    ],
    "sg:phone":"+1 505 820 6194",
    "sg:postcode":"87505",
    "sg:province":"NM",
    "sg:tags":[
        "organization",
        "welfare"
    ],
    "wof:name":"Community Options Inc",
    "wof:placetype":"venue"
},
  "geometry": {"coordinates":[-105.96487399999999,35.677085],"type":"Point"}
}