{
  "type": "Feature",
  "properties": {
    "iso:country":"US",
    "sg:address":"108 E Twilight Dr",
    "sg:city":"Farmington",
    "sg:classifiers":[
        {
            "category":"Building & Trades",
            "subcategory":"Construction",
            "type":"Services"
        }
    ],
    "sg:phone":"+1 505 327 1033",
    "sg:postcode":"87401",
    "sg:province":"NM",
    "sg:tags":[
        "general",
        "contractor"
    ],
    "wof:name":"Cammon Construction",
    "wof:placetype":"venue"
},
  "geometry": {"coordinates":[-108.202298,36.763246],"type":"Point"}
}