{
  "type": "Feature",
  "properties": {
    "addr:full":"703 Canyon Rd Santa Fe NM 87501",
    "addr:housenumber":"703",
    "addr:postcode":"87501",
    "addr:street":"Canyon Rd",
    "iso:country":"US",
    "sg:address":"703 Canyon Rd",
    "sg:city":"Santa Fe",
    "sg:classifiers":[
        {
            "category":"Shopping",
            "type":"Retail Goods"
        }
    ],
    "sg:phone":"+1 505 988 5300",
    "sg:postcode":"87501",
    "sg:province":"NM",
    "sg:tags":[
        "art",
        "gallery",
        "dealer"
    ],
    "wof:name":"Gallery Corazon",
    "wof:placetype":"venue"
},
  "geometry": {"coordinates":[-105.927431,35.68146],"type":"Point"}
}