{
  "type": "Feature",
  "properties": {
    "iso:country":"US",
    "sg:address":"1108 US Hwy 70",
    "sg:city":"Alamogordo",
    "sg:classifiers":[
        {
            "category":"Home & Garden",
            "subcategory":"Furniture",
            "type":"Retail Goods"
        }
    ],
    "sg:phone":"+1 505 443 1562",
    "sg:postcode":"88310",
    "sg:province":"NM",
    "wof:name":"C & R Furniture",
    "wof:placetype":"venue"
},
  "geometry": {"coordinates":[-105.984199,32.865292],"type":"Point"}
}