{
  "type": "Feature",
  "properties": {
    "addr:full":"1008 Pso del Pueblo Sur Taos NM 87571",
    "addr:housenumber":"1008",
    "addr:postcode":"87571",
    "addr:street":"Pso Del Pueblo Sur",
    "iso:country":"US",
    "sg:address":"1008 Pso del Pueblo Sur",
    "sg:city":"Taos",
    "sg:phone":"+1 505 758 8647",
    "sg:postcode":"87571",
    "sg:province":"NM",
    "sg:tags":[
        "communications",
        "postal",
        "business"
    ],
    "wof:name":"UPS Stores The",
    "wof:placetype":"venue"
},
  "geometry": {"coordinates":[-105.594931,36.372191],"type":"Point"}
}