{
  "type": "Feature",
  "properties": {
    "iso:country":"US",
    "sg:address":"1031 N Thomas St",
    "sg:city":"Carlsbad",
    "sg:classifiers":[
        {
            "category":"Health Services",
            "subcategory":"Doctor",
            "type":"Services"
        }
    ],
    "sg:phone":"+1 505 887 5542",
    "sg:postcode":"88220",
    "sg:province":"NM",
    "sg:tags":[
        "physician",
        "medical",
        "surgeon"
    ],
    "wof:name":"Sergio J Rybka MD P C",
    "wof:placetype":"venue"
},
  "geometry": {"coordinates":[-104.238962,32.434035],"type":"Point"}
}