{
  "type": "Feature",
  "properties": {
    "iso:country":"US",
    "sg:address":"5445 Edith Blvd NE",
    "sg:city":"Albuquerque",
    "sg:classifiers":[
        {
            "category":"Autos & Motor Vehicles",
            "subcategory":"Boat Sales",
            "type":"Retail Goods"
        }
    ],
    "sg:phone":"+1 505 341 1230",
    "sg:postcode":"87107",
    "sg:province":"NM",
    "sg:tags":[
        "dealer",
        "sales"
    ],
    "wof:name":"Young's Performance Marine",
    "wof:placetype":"venue"
},
  "geometry": {"coordinates":[-106.629375,35.134107],"type":"Point"}
}