{
  "type": "Feature",
  "properties": {
    "addr:full":"2100 Louisiana Blvd NE Albuquerque NM 87110",
    "addr:housenumber":"2100",
    "addr:postcode":"87110",
    "addr:street":"Louisiana Blvd Ne",
    "iso:country":"US",
    "sg:address":"2100 Louisiana Blvd NE",
    "sg:city":"Albuquerque",
    "sg:classifiers":[
        {
            "category":"Shopping",
            "subcategory":"Hobbies, Toys, & Games",
            "type":"Retail Goods"
        }
    ],
    "sg:phone":"+1 505 881 5371",
    "sg:postcode":"87110",
    "sg:province":"NM",
    "sg:tags":[
        "item"
    ],
    "wof:name":"Kb Toys",
    "wof:placetype":"venue"
},
  "geometry": {"coordinates":[-106.56875700000001,35.100638],"type":"Point"}
}