{
  "type": "Feature",
  "properties": {
    "iso:country":"US",
    "sg:address":"12601 Cloudview Ave NE",
    "sg:city":"Albuquerque",
    "sg:classifiers":[
        {
            "category":"Building & Trades",
            "subcategory":"Plumbing",
            "type":"Services"
        }
    ],
    "sg:phone":"+1 505 315 5064",
    "sg:postcode":"87123",
    "sg:province":"NM",
    "sg:tags":[
        "contractor"
    ],
    "wof:name":"Salvadors Plumbing",
    "wof:placetype":"venue"
},
  "geometry": {"coordinates":[-106.507085,35.07444],"type":"Point"}
}