{
  "type": "Feature",
  "properties": {
    "addr:full":"1747 Jay St Santa Fe NM 87505",
    "addr:housenumber":"1747",
    "addr:postcode":"87505",
    "addr:street":"Jay St",
    "iso:country":"US",
    "sg:address":"1747 Jay St",
    "sg:city":"Santa Fe",
    "sg:classifiers":[
        {
            "category":"Building & Trades",
            "subcategory":"Plumbing",
            "type":"Services"
        }
    ],
    "sg:phone":"+1 505 424 9191",
    "sg:postcode":"87505",
    "sg:province":"NM",
    "sg:tags":[
        "plumbing",
        "contractor"
    ],
    "wof:name":"Drain Works",
    "wof:placetype":"venue"
},
  "geometry": {"coordinates":[-105.969026,35.664405],"type":"Point"}
}