{
  "type": "Feature",
  "properties": {
    "addr:full":"72 Wild Turkey Way Santa Fe NM 87505",
    "addr:housenumber":"72",
    "addr:postcode":"87505",
    "addr:street":"Wild Turkey Way",
    "iso:country":"US",
    "sg:address":"72 Wild Turkey Way",
    "sg:city":"Santa Fe",
    "sg:classifiers":[
        {
            "category":"Professional",
            "subcategory":"Computer Services",
            "type":"Services"
        }
    ],
    "sg:phone":"+1 505 995 0627",
    "sg:postcode":"87505",
    "sg:province":"NM",
    "sg:tags":[
        "information",
        "retrieval"
    ],
    "wof:name":"Source Design",
    "wof:placetype":"venue"
},
  "geometry": {"coordinates":[-105.856329,35.579881],"type":"Point"}
}