{
  "type": "Feature",
  "properties": {
    "iso:country":"US",
    "sg:address":"1249 Futurity Dr",
    "sg:city":"Sunland Park",
    "sg:classifiers":[
        {
            "category":"Recreation",
            "subcategory":"Amusement Park",
            "type":"Entertainment"
        }
    ],
    "sg:phone":"+1 505 589 3410",
    "sg:postcode":"88063",
    "sg:province":"NM",
    "wof:name":"Western Playland",
    "wof:placetype":"venue"
},
  "geometry": {"coordinates":[-106.56503,31.805088],"type":"Point"}
}