{
  "type": "Feature",
  "properties": {
    "addr:full":"2120 Yale Blvd SE Albuquerque NM 87106",
    "addr:housenumber":"2120",
    "addr:postcode":"87106",
    "addr:street":"Yale Blvd Se",
    "iso:country":"US",
    "sg:address":"2120 Yale Blvd SE",
    "sg:city":"Albuquerque",
    "sg:classifiers":[
        {
            "category":"Restaurant",
            "type":"Food & Drink"
        }
    ],
    "sg:menulink":"http://www.allmenus.com/nm/albuquerque/92891-fuddruckers/menu/",
    "sg:phone":"+1 505 224 2841",
    "sg:postcode":"87106",
    "sg:province":"NM",
    "sg:tags":[
        "burger",
        "american"
    ],
    "wof:name":"Fuddruckers",
    "wof:placetype":"venue"
},
  "geometry": {"coordinates":[-106.62140599999999,35.057704],"type":"Point"}
}