{
  "type": "Feature",
  "properties": {
    "addr:full":"6 Horseshoe Loop Edgewood NM 87015",
    "addr:housenumber":"6",
    "addr:postcode":"87015",
    "addr:street":"Horseshoe Loop",
    "iso:country":"US",
    "sg:address":"6 Horseshoe Loop",
    "sg:city":"Edgewood",
    "sg:classifiers":[
        {
            "category":"Building & Trades",
            "subcategory":"Cleaning & Sanitation",
            "type":"Services"
        }
    ],
    "sg:phone":"+1 505 281 4607",
    "sg:postcode":"87015",
    "sg:province":"NM",
    "sg:tags":[
        "maintenance"
    ],
    "wof:name":"Bs Cleaning Services",
    "wof:placetype":"venue"
},
  "geometry": {"coordinates":[-106.243368,35.060317],"type":"Point"}
}