{
  "type": "Feature",
  "properties": {
    "iso:country":"US",
    "sg:address":"2501 San Pedro Dr NE",
    "sg:city":"Albuquerque",
    "sg:classifiers":[
        {
            "category":"Health Services",
            "subcategory":"Health Practitioner",
            "type":"Services"
        },
        {
            "category":"Communications",
            "type":"Services"
        }
    ],
    "sg:phone":"+1 505 323 1204",
    "sg:postcode":"87110",
    "sg:province":"NM",
    "sg:tags":[
        "pathologist",
        "speech-language",
        "myofunctional",
        "therapy"
    ],
    "wof:name":"Communication Partners Inc",
    "wof:placetype":"venue"
},
  "geometry": {"coordinates":[-106.57756,35.107239],"type":"Point"}
}