{
  "type": "Feature",
  "properties": {
    "iso:country":"US",
    "sg:address":"721 5th St",
    "sg:city":"Las Vegas",
    "sg:classifiers":[
        {
            "category":"Health Services",
            "subcategory":"Chiropractor",
            "type":"Services"
        }
    ],
    "sg:phone":"+1 505 425 5530",
    "sg:postcode":"87701",
    "sg:province":"NM",
    "wof:name":"Las Vegas Chiropractic Ctr",
    "wof:placetype":"venue"
},
  "geometry": {"coordinates":[-105.21517299999999,35.597213],"type":"Point"}
}