{
  "type": "Feature",
  "properties": {
    "iso:country":"US",
    "sg:address":"907 Gidding St",
    "sg:city":"Clovis",
    "sg:classifiers":[
        {
            "category":"Home & Garden",
            "subcategory":"Home Furnishings",
            "type":"Retail Goods"
        }
    ],
    "sg:phone":"+1 505 762 4155",
    "sg:postcode":"88101",
    "sg:province":"NM",
    "sg:tags":[
        "venetian",
        "blind"
    ],
    "wof:name":"Express Blinds",
    "wof:placetype":"venue"
},
  "geometry": {"coordinates":[-103.202684,34.407785],"type":"Point"}
}