{
  "type": "Feature",
  "properties": {
    "iso:country":"US",
    "sg:address":"9 Rd 5336",
    "sg:city":"Farmington",
    "sg:classifiers":[
        {
            "category":"Professional",
            "subcategory":"Secretarial Services",
            "type":"Services"
        }
    ],
    "sg:phone":"+1 505 327 2949",
    "sg:postcode":"87401",
    "sg:province":"NM",
    "sg:tags":[
        "reporting"
    ],
    "wof:name":"McKee Reporting Inc",
    "wof:placetype":"venue"
},
  "geometry": {"coordinates":[-108.060952,36.695017],"type":"Point"}
}