{
  "type": "Feature",
  "properties": {
    "iso:country":"US",
    "sg:address":"7206 Whippoorwill Ln NE",
    "sg:city":"Albuquerque",
    "sg:classifiers":[
        {
            "category":"Place Of Worship",
            "type":"Public Place"
        }
    ],
    "sg:phone":"+1 505 856 0660",
    "sg:postcode":"87109",
    "sg:province":"NM",
    "sg:tags":[
        "church"
    ],
    "wof:name":"Vineyard Church Of North Albuquerque",
    "wof:placetype":"venue"
},
  "geometry": {"coordinates":[-106.565309,35.171122],"type":"Point"}
}