{
  "type": "Feature",
  "properties": {
    "iso:country":"US",
    "sg:address":"7847 Tramway Blvd NE",
    "sg:city":"Albuquerque",
    "sg:classifiers":[
        {
            "category":"Professional",
            "subcategory":"Computer Services",
            "type":"Services"
        }
    ],
    "sg:phone":"+1 505 888 4387",
    "sg:postcode":"87122",
    "sg:province":"NM",
    "sg:tags":[
        "repair"
    ],
    "wof:name":"Help Desk Technical Svc",
    "wof:placetype":"venue"
},
  "geometry": {"coordinates":[-106.496393,35.172808],"type":"Point"}
}