{
  "type": "Feature",
  "properties": {
    "iso:country":"US",
    "sg:address":"758 Co Rd 6100",
    "sg:city":"Fruitland",
    "sg:classifiers":[
        {
            "category":"Utilities",
            "subcategory":"Natural Gas",
            "type":"Services"
        }
    ],
    "sg:phone":"+1 505 599 3374",
    "sg:postcode":"87416",
    "sg:province":"NM",
    "sg:tags":[
        "transmission"
    ],
    "wof:name":"El Paso Natural Gas Company",
    "wof:placetype":"venue"
},
  "geometry": {"coordinates":[-108.40382,36.747889],"type":"Point"}
}