{
  "type": "Feature",
  "properties": {
    "iso:country":"US",
    "sg:address":"226 N Guadalupe St",
    "sg:city":"Santa Fe",
    "sg:classifiers":[
        {
            "category":"Social Services",
            "type":"Services"
        }
    ],
    "sg:phone":"+1 505 955 1750",
    "sg:postcode":"87501",
    "sg:province":"NM",
    "sg:tags":[
        "youth",
        "organization",
        "center"
    ],
    "wof:name":"Youth Shelters & Family Svc",
    "wof:placetype":"venue"
},
  "geometry": {"coordinates":[-105.943668,35.689375],"type":"Point"}
}