{
  "type": "Feature",
  "properties": {
    "iso:country":"US",
    "sg:address":"2909 Yale Blvd SE",
    "sg:city":"Albuquerque",
    "sg:classifiers":[
        {
            "category":"Personal",
            "type":"Services"
        }
    ],
    "sg:phone":"+1 505 843 7634",
    "sg:postcode":"87106",
    "sg:province":"NM",
    "wof:name":"ABQ Valet",
    "wof:placetype":"venue"
},
  "geometry": {"coordinates":[-106.621959,35.049735],"type":"Point"}
}