{
  "type": "Feature",
  "properties": {
    "iso:country":"US",
    "sg:address":"7200 Montgomery Blvd NE",
    "sg:city":"Albuquerque",
    "sg:classifiers":[
        {
            "category":"Banks & Credit Unions",
            "subcategory":"Bank",
            "type":"Services"
        }
    ],
    "sg:phone":"+1 505 889 9900",
    "sg:postcode":"87109",
    "sg:province":"NM",
    "sg:tags":[
        "loan"
    ],
    "wof:name":"Ready Money",
    "wof:placetype":"venue"
},
  "geometry": {"coordinates":[-106.563849,35.130743],"type":"Point"}
}