{
  "type": "Feature",
  "properties": {
    "iso:country":"US",
    "sg:address":"45 Cam Torcido Lp",
    "sg:city":"Santa Fe",
    "sg:classifiers":[
        {
            "category":"Professional",
            "type":"Services"
        }
    ],
    "sg:phone":"+1 505 424 0674",
    "sg:postcode":"87507",
    "sg:province":"NM",
    "sg:tags":[
        "establishment"
    ],
    "wof:name":"Custom Canales",
    "wof:placetype":"venue"
},
  "geometry": {"coordinates":[-106.120746,35.596571],"type":"Point"}
}