{
  "type": "Feature",
  "properties": {
    "iso:country":"US",
    "sg:address":"12904 Sunrise Trail Pl NE",
    "sg:city":"Albuquerque",
    "sg:classifiers":[
        {
            "category":"Building & Trades",
            "subcategory":"Construction",
            "type":"Services"
        }
    ],
    "sg:phone":"+1 505 294 0354",
    "sg:postcode":"87111",
    "sg:province":"NM",
    "sg:tags":[
        "home",
        "builder"
    ],
    "wof:name":"Jenco Homes",
    "wof:placetype":"venue"
},
  "geometry": {"coordinates":[-106.49096400000001,35.155885],"type":"Point"}
}