{
  "type": "Feature",
  "properties": {
    "iso:country":"US",
    "sg:address":"401 W Fiesta Dr",
    "sg:city":"Carlsbad",
    "sg:classifiers":[
        {
            "category":"Cinema",
            "subcategory":"Movie Theater",
            "type":"Entertainment"
        }
    ],
    "sg:phone":"+1 505 885 4126",
    "sg:postcode":"88220",
    "sg:province":"NM",
    "wof:name":"Cavern City Cinemas",
    "wof:placetype":"venue"
},
  "geometry": {"coordinates":[-104.227667,32.40348],"type":"Point"}
}