{
  "type": "Feature",
  "properties": {
    "addr:full":"1915 N Swan St Silver City NM 88061",
    "addr:housenumber":"1915",
    "addr:postcode":"88061",
    "addr:street":"N Swan St",
    "iso:country":"US",
    "sg:address":"1915 N Swan St",
    "sg:city":"Silver City",
    "sg:classifiers":[
        {
            "category":"Organizations",
            "subcategory":"Religious Organization",
            "type":"Services"
        }
    ],
    "sg:phone":"+1 505 538 3513",
    "sg:postcode":"88061",
    "sg:province":"NM",
    "wof:name":"First Presbyterian Church",
    "wof:placetype":"venue"
},
  "geometry": {"coordinates":[-108.2696,32.784728],"type":"Point"}
}