{
  "type": "Feature",
  "properties": {
    "iso:country":"US",
    "sg:address":"303 W Rainbow Dr",
    "sg:city":"Hobbs",
    "sg:classifiers":[
        {
            "category":"Professional",
            "type":"Services"
        }
    ],
    "sg:phone":"+1 505 704 9644",
    "sg:postcode":"88240",
    "sg:province":"NM",
    "wof:name":"Riveros Paralegal Services",
    "wof:placetype":"venue"
},
  "geometry": {"coordinates":[-103.14128700000001,32.687998],"type":"Point"}
}