{
  "type": "Feature",
  "properties": {
    "iso:country":"US",
    "sg:address":"8201 Golf Course Rd NW",
    "sg:city":"Albuquerque",
    "sg:classifiers":[
        {
            "category":"Building & Trades",
            "subcategory":"Electrical",
            "type":"Services"
        }
    ],
    "sg:phone":"+1 505 281 0775",
    "sg:postcode":"87120",
    "sg:province":"NM",
    "sg:tags":[
        "electrical",
        "contractor"
    ],
    "wof:name":"Swaims Electric",
    "wof:placetype":"venue"
},
  "geometry": {"coordinates":[-106.687814,35.176978],"type":"Point"}
}