{
  "type": "Feature",
  "properties": {
    "iso:country":"US",
    "sg:address":"200 W Lea St",
    "sg:city":"Hobbs",
    "sg:classifiers":[
        {
            "category":"Professional",
            "subcategory":"Lawyer & Legal Services",
            "type":"Services"
        }
    ],
    "sg:phone":"+1 505 391 7477",
    "sg:postcode":"88240",
    "sg:province":"NM",
    "sg:tags":[
        "health"
    ],
    "wof:name":"Montgomery Health Offices",
    "wof:placetype":"venue"
},
  "geometry": {"coordinates":[-103.137473,32.70919],"type":"Point"}
}