{
  "type": "Feature",
  "properties": {
    "iso:country":"US",
    "sg:address":"1720 N Montana Ave",
    "sg:city":"Roswell",
    "sg:classifiers":[
        {
            "category":"Organizations",
            "subcategory":"Community Association",
            "type":"Services"
        }
    ],
    "sg:phone":"+1 505 622 1560",
    "sg:postcode":"88201",
    "sg:province":"NM",
    "sg:tags":[
        "fraternal"
    ],
    "wof:name":"Elks Lodge",
    "wof:placetype":"venue"
},
  "geometry": {"coordinates":[-104.540541,33.414774],"type":"Point"}
}