{
  "type": "Feature",
  "properties": {
    "iso:country":"US",
    "sg:address":"1028 Walnut Dr",
    "sg:city":"Farmington",
    "sg:classifiers":[
        {
            "category":"Freight",
            "type":"Transportation"
        }
    ],
    "sg:phone":"+1 505 325 3481",
    "sg:postcode":"87401",
    "sg:province":"NM",
    "sg:tags":[
        "commercial",
        "storage"
    ],
    "wof:name":"Jim-Co Self Storage",
    "wof:placetype":"venue"
},
  "geometry": {"coordinates":[-108.223144,36.733057],"type":"Point"}
}