{
  "type": "Feature",
  "properties": {
    "addr:full":"601 Gallegos St Logan NM 88426",
    "addr:housenumber":"601",
    "addr:postcode":"88426",
    "addr:street":"Gallegos St",
    "iso:country":"US",
    "sg:address":"601 Gallegos St",
    "sg:city":"Logan",
    "sg:classifiers":[
        {
            "category":"Personal",
            "subcategory":"Beauty Salon",
            "type":"Services"
        }
    ],
    "sg:phone":"+1 505 487 2117",
    "sg:postcode":"88426",
    "sg:province":"NM",
    "wof:name":"Shearly Shonda's",
    "wof:placetype":"venue"
},
  "geometry": {"coordinates":[-103.41646900000001,35.36664],"type":"Point"}
}