{
  "type": "Feature",
  "properties": {
    "iso:country":"US",
    "sg:address":"818 la Vega Ct SW",
    "sg:city":"Albuquerque",
    "sg:classifiers":[
        {
            "category":"Building & Trades",
            "subcategory":"Electrical",
            "type":"Services"
        }
    ],
    "sg:phone":"+1 505 873 6505",
    "sg:postcode":"87105",
    "sg:province":"NM",
    "sg:tags":[
        "electrician"
    ],
    "wof:name":"Lospinos Electric",
    "wof:placetype":"venue"
},
  "geometry": {"coordinates":[-106.666323,35.06017],"type":"Point"}
}