{
  "type": "Feature",
  "properties": {
    "iso:country":"US",
    "sg:address":"5915 Central Ave SE",
    "sg:city":"Albuquerque",
    "sg:classifiers":[
        {
            "category":"Banks & Credit Unions",
            "subcategory":"Bank",
            "type":"Services"
        }
    ],
    "sg:phone":"+1 505 255 3278",
    "sg:postcode":"87108",
    "sg:province":"NM",
    "sg:tags":[
        "loan"
    ],
    "wof:name":"Jr's Payday & Title Loans",
    "wof:placetype":"venue"
},
  "geometry": {"coordinates":[-106.580178,35.077204],"type":"Point"}
}