{
  "type": "Feature",
  "properties": {
    "iso:country":"US",
    "sg:address":"5 Balsa Rd",
    "sg:city":"Santa Fe",
    "sg:classifiers":[
        {
            "category":"Building & Trades",
            "subcategory":"Construction",
            "type":"Services"
        }
    ],
    "sg:phone":"+1 505 466 4925",
    "sg:postcode":"87508",
    "sg:province":"NM",
    "sg:tags":[
        "general",
        "contractor"
    ],
    "wof:name":"Cristo Construction Inc",
    "wof:placetype":"venue"
},
  "geometry": {"coordinates":[-105.94158400000001,35.536377],"type":"Point"}
}