{
  "type": "Feature",
  "properties": {
    "addr:full":"3106 E Greene St Carlsbad NM 88220",
    "addr:housenumber":"3106",
    "addr:postcode":"88220",
    "addr:street":"E Greene St",
    "iso:country":"US",
    "sg:address":"3106 E Greene St",
    "sg:city":"Carlsbad",
    "sg:classifiers":[
        {
            "category":"Professional",
            "subcategory":"Business Services",
            "type":"Services"
        }
    ],
    "sg:phone":"+1 505 885 5709",
    "sg:postcode":"88220",
    "sg:province":"NM",
    "sg:tags":[
        "water",
        "treatment"
    ],
    "wof:name":"Western Environmental Mgmt Inc",
    "wof:placetype":"venue"
},
  "geometry": {"coordinates":[-104.143694,32.459494],"type":"Point"}
}