{
  "type": "Feature",
  "properties": {
    "iso:country":"US",
    "sg:address":"3217 Morris St NE",
    "sg:city":"Albuquerque",
    "sg:classifiers":[
        {
            "category":"Building & Trades",
            "subcategory":"Cleaning & Sanitation",
            "type":"Services"
        }
    ],
    "sg:phone":"+1 505 712 0122",
    "sg:postcode":"87111",
    "sg:province":"NM",
    "sg:tags":[
        "window"
    ],
    "wof:name":"ABQ Spit Shine",
    "wof:placetype":"venue"
},
  "geometry": {"coordinates":[-106.52454400000001,35.118428],"type":"Point"}
}