{
  "type": "Feature",
  "properties": {
    "addr:full":"5711 Broadway Blvd SE Albuquerque NM 87105",
    "addr:housenumber":"5711",
    "addr:postcode":"87105",
    "addr:street":"Broadway Blvd Se",
    "iso:country":"US",
    "sg:address":"5711 Broadway Blvd SE",
    "sg:city":"Albuquerque",
    "sg:classifiers":[
        {
            "category":"Manufacturing",
            "subcategory":"Tools & Machinery",
            "type":"Manufacturing & Wholesale Goods"
        },
        {
            "category":"Wholesale",
            "subcategory":"Scrap",
            "type":"Manufacturing & Wholesale Goods"
        }
    ],
    "sg:phone":"+1 505 877 4615",
    "sg:postcode":"87105",
    "sg:province":"NM",
    "sg:tags":[
        "refuse",
        "center",
        "mfg",
        "industry",
        "recycling",
        "system"
    ],
    "wof:name":"Albuquerque Car Crushers Inc",
    "wof:placetype":"venue"
},
  "geometry": {"coordinates":[-106.654078,34.991926],"type":"Point"}
}