{
  "type": "Feature",
  "properties": {
    "addr:full":"300 N 3rd St Belen NM 87002",
    "addr:housenumber":"300",
    "addr:postcode":"87002",
    "addr:street":"N 3Rd St",
    "iso:country":"US",
    "sg:address":"300 N 3rd St",
    "sg:city":"Belen",
    "sg:classifiers":[
        {
            "category":"Social Services",
            "subcategory":"Child Care",
            "type":"Services"
        }
    ],
    "sg:phone":"+1 505 864 6095",
    "sg:postcode":"87002",
    "sg:province":"NM",
    "sg:tags":[
        "kindergarten",
        "academic",
        "school"
    ],
    "wof:name":"Watch Me Grow Preschool",
    "wof:placetype":"venue"
},
  "geometry": {"coordinates":[-106.769936,34.663112],"type":"Point"}
}