{
  "type": "Feature",
  "properties": {
    "iso:country":"US",
    "sg:address":"5115 Coors Blvd NW",
    "sg:city":"Albuquerque",
    "sg:classifiers":[
        {
            "category":"Health Services",
            "subcategory":"Doctor",
            "type":"Services"
        }
    ],
    "sg:phone":"+1 505 922 9511",
    "sg:postcode":"87120",
    "sg:province":"NM",
    "sg:tags":[
        "dentist"
    ],
    "wof:name":"Family Dentistry",
    "wof:placetype":"venue"
},
  "geometry": {"coordinates":[-106.693601,35.144558],"type":"Point"}
}