{
  "type": "Feature",
  "properties": {
    "iso:country":"US",
    "sg:address":"210 Ledoux St",
    "sg:city":"Taos",
    "sg:classifiers":[
        {
            "category":"Shopping",
            "type":"Retail Goods"
        }
    ],
    "sg:phone":"+1 505 758 3250",
    "sg:postcode":"87571",
    "sg:province":"NM",
    "sg:tags":[
        "art",
        "gallery",
        "dealer"
    ],
    "sg:website":"www.rcgormangallery.com",
    "wof:name":"Navajo Gallery",
    "wof:placetype":"venue"
},
  "geometry": {"coordinates":[-105.577652,36.406181],"type":"Point"}
}