{
  "type": "Feature",
  "properties": {
    "addr:full":"101 S Sycamore Ave Roswell NM 88203",
    "addr:housenumber":"101",
    "addr:postcode":"88203",
    "addr:street":"S Sycamore Ave",
    "iso:country":"US",
    "sg:address":"101 S Sycamore Ave",
    "sg:city":"Roswell",
    "sg:classifiers":[
        {
            "category":"Building & Trades",
            "subcategory":"Construction",
            "type":"Services"
        }
    ],
    "sg:phone":"+1 505 626 0874",
    "sg:postcode":"88203",
    "sg:province":"NM",
    "sg:tags":[
        "general",
        "contractor"
    ],
    "wof:name":"Shackelford Paint & Drywall",
    "wof:placetype":"venue"
},
  "geometry": {"coordinates":[-104.55908700000001,33.39414],"type":"Point"}
}