{
  "type": "Feature",
  "properties": {
    "iso:country":"US",
    "sg:address":"2400 Menaul Blvd NE Ste B",
    "sg:city":"Albuquerque",
    "sg:classifiers":[
        {
            "category":"Shopping",
            "subcategory":"Pets & Pet Supplies",
            "type":"Retail Goods"
        },
        {
            "category":"Museum",
            "subcategory":"Aquarium",
            "type":"Entertainment"
        }
    ],
    "sg:phone":"+1 505 884 0901",
    "sg:postcode":"87107",
    "sg:province":"NM",
    "sg:tags":[
        "furnishing",
        "dog",
        "store",
        "cat"
    ],
    "sg:website":"http://www.swreefco.com",
    "wof:name":"Southwest Reef Co",
    "wof:placetype":"venue"
},
  "geometry": {"coordinates":[-106.61685900000001,35.109138],"type":"Point"}
}