{
  "type": "Feature",
  "properties": {
    "iso:country":"US",
    "sg:address":"20 Mineral Hill Rd",
    "sg:city":"Las Vegas",
    "sg:classifiers":[
        {
            "category":"Professional",
            "subcategory":"Management & Consulting",
            "type":"Services"
        }
    ],
    "sg:phone":"+1 505 425 6738",
    "sg:postcode":"87701",
    "sg:province":"NM",
    "wof:name":"ABL Management Svc",
    "wof:placetype":"venue"
},
  "geometry": {"coordinates":[-105.43861699999999,35.644235],"type":"Point"}
}