{
  "type": "Feature",
  "properties": {
    "addr:full":"716 Mechem Dr Ruidoso NM 88345",
    "addr:housenumber":"716",
    "addr:postcode":"88345",
    "addr:street":"Mechem Dr",
    "iso:country":"US",
    "sg:address":"716 Mechem Dr",
    "sg:city":"Ruidoso",
    "sg:classifiers":[
        {
            "category":"Real Estate",
            "subcategory":"Real Estate Agent",
            "type":"Services"
        }
    ],
    "sg:phone":"+1 505 257 4274",
    "sg:postcode":"88345",
    "sg:province":"NM",
    "wof:name":"Starr Realty",
    "wof:placetype":"venue"
},
  "geometry": {"coordinates":[-105.674994,33.34786],"type":"Point"}
}