{
  "type": "Feature",
  "properties": {
    "iso:country":"US",
    "sg:address":"1308 Gusdorf Rd",
    "sg:city":"Taos",
    "sg:classifiers":[
        {
            "category":"Social Services",
            "type":"Services"
        }
    ],
    "sg:phone":"+1 505 758 3722",
    "sg:postcode":"87571",
    "sg:province":"NM",
    "sg:tags":[
        "probation"
    ],
    "wof:name":"Juvenile Probation & Parole",
    "wof:placetype":"venue"
},
  "geometry": {"coordinates":[-105.59063500000001,36.373307],"type":"Point"}
}