{
  "type": "Feature",
  "properties": {
    "addr:full":"8405 Monitor Dr NE Albuquerque NM 87109",
    "addr:housenumber":"8405",
    "addr:postcode":"87109",
    "addr:street":"Monitor Dr Ne",
    "iso:country":"US",
    "sg:address":"8405 Monitor Dr NE",
    "sg:city":"Albuquerque",
    "sg:classifiers":[
        {
            "category":"Retail",
            "subcategory":"Portrait Studio",
            "type":"Services"
        }
    ],
    "sg:phone":"+1 505 821 8537",
    "sg:postcode":"87109",
    "sg:province":"NM",
    "sg:tags":[
        "photographer"
    ],
    "wof:name":"Ron Behrmann Photography",
    "wof:placetype":"venue"
},
  "geometry": {"coordinates":[-106.548107,35.164751],"type":"Point"}
}