{
  "type": "Feature",
  "properties": {
    "iso:country":"US",
    "sg:address":"916 Lomas Blvd NW",
    "sg:city":"Albuquerque",
    "sg:classifiers":[
        {
            "category":"Real Estate",
            "subcategory":"Real Estate Agent",
            "type":"Services"
        }
    ],
    "sg:phone":"+1 505 842 6383",
    "sg:postcode":"87102",
    "sg:province":"NM",
    "wof:name":"Lebeck Co",
    "wof:placetype":"venue"
},
  "geometry": {"coordinates":[-106.65713100000001,35.091766],"type":"Point"}
}