{
  "type": "Feature",
  "properties": {
    "iso:country":"US",
    "sg:address":"23 Sombrillo Rd",
    "sg:city":"Espanola",
    "sg:classifiers":[
        {
            "category":"Shopping",
            "subcategory":"Jewelry",
            "type":"Retail Goods"
        }
    ],
    "sg:phone":"+1 505 753 4706",
    "sg:postcode":"87532",
    "sg:province":"NM",
    "wof:name":"Nacho Jewelry",
    "wof:placetype":"venue"
},
  "geometry": {"coordinates":[-106.035503,35.979457],"type":"Point"}
}