{
  "type": "Feature",
  "properties": {
    "iso:country":"US",
    "sg:address":"6600 Menaul Blvd NE",
    "sg:city":"Albuquerque",
    "sg:classifiers":[
        {
            "category":"Shopping",
            "subcategory":"Jewelry",
            "type":"Retail Goods"
        }
    ],
    "sg:phone":"+1 505 881 1307",
    "sg:postcode":"87110",
    "sg:province":"NM",
    "sg:tags":[
        "jeweler"
    ],
    "sg:website":"www.zales.com",
    "wof:name":"Zales The Diamond Store",
    "wof:placetype":"venue"
},
  "geometry": {"coordinates":[-106.56991,35.109124],"type":"Point"}
}