{
  "type": "Feature",
  "properties": {
    "addr:full":"14 David Dr Edgewood NM 87015",
    "addr:housenumber":"14",
    "addr:postcode":"87015",
    "addr:street":"David Dr",
    "iso:country":"US",
    "sg:address":"14 David Dr",
    "sg:city":"Edgewood",
    "sg:classifiers":[
        {
            "category":"Professional",
            "type":"Services"
        }
    ],
    "sg:phone":"+1 505 281 4221",
    "sg:postcode":"87015",
    "sg:province":"NM",
    "wof:name":"Marks Services",
    "wof:placetype":"venue"
},
  "geometry": {"coordinates":[-106.16429599999999,35.079394],"type":"Point"}
}