{
  "type": "Feature",
  "properties": {
    "iso:country":"US",
    "sg:address":"4303 Ellison St NE",
    "sg:city":"Albuquerque",
    "sg:classifiers":[
        {
            "category":"Professional",
            "subcategory":"Engineering",
            "type":"Services"
        },
        {
            "category":"Building & Trades",
            "subcategory":"Construction",
            "type":"Services"
        },
        {
            "category":"Wholesale",
            "subcategory":"Home Furnishings",
            "type":"Manufacturing & Wholesale Goods"
        }
    ],
    "sg:phone":"+1 505 345 8811",
    "sg:postcode":"87109",
    "sg:province":"NM",
    "sg:tags":[
        "system",
        "specialty",
        "fixture",
        "heating",
        "contractor",
        "equipment",
        "part",
        "plumbing",
        "supplies-wholesale",
        "air conditioning",
        "manufacturer"
    ],
    "wof:name":"Norman S Wright Company Manufacturers Representative",
    "wof:placetype":"venue"
},
  "geometry": {"coordinates":[-106.598303,35.160924],"type":"Point"}
}