{
  "type": "Feature",
  "properties": {
    "iso:country":"US",
    "sg:address":"2501 Ridgecrest Dr SE",
    "sg:city":"Albuquerque",
    "sg:classifiers":[
        {
            "category":"Wholesale",
            "subcategory":"Computers",
            "type":"Manufacturing & Wholesale Goods"
        }
    ],
    "sg:phone":"+1 505 896 8508",
    "sg:postcode":"87108",
    "sg:province":"NM",
    "wof:name":"Byteserve LLC",
    "wof:placetype":"venue"
},
  "geometry": {"coordinates":[-106.576757,35.055023],"type":"Point"}
}