{
  "type": "Feature",
  "properties": {
    "iso:country":"US",
    "sg:address":"1905 Siringo Rd",
    "sg:city":"Santa Fe",
    "sg:classifiers":[
        {
            "category":"Social Services",
            "type":"Services"
        }
    ],
    "sg:phone":"+1 505 438 3762",
    "sg:postcode":"87505",
    "sg:province":"NM",
    "sg:tags":[
        "youth",
        "organization",
        "center"
    ],
    "wof:name":"Youth Shelters & Family Svc",
    "wof:placetype":"venue"
},
  "geometry": {"coordinates":[-105.965932,35.652139],"type":"Point"}
}