{
  "type": "Feature",
  "properties": {
    "iso:country":"US",
    "sg:address":"1400 W Clayton Ave",
    "sg:city":"Lovington",
    "sg:classifiers":[
        {
            "category":"Wholesale",
            "subcategory":"Chemicals & Plastics",
            "type":"Manufacturing & Wholesale Goods"
        }
    ],
    "sg:phone":"+1 505 396 7581",
    "sg:postcode":"88260",
    "sg:province":"NM",
    "sg:tags":[
        "absorbent"
    ],
    "wof:name":"Hayes Oil Field Svc",
    "wof:placetype":"venue"
},
  "geometry": {"coordinates":[-103.36543,32.935358],"type":"Point"}
}