{
  "type": "Feature",
  "properties": {
    "iso:country":"US",
    "sg:address":"406 Fairgrounds Rd",
    "sg:city":"Alamogordo",
    "sg:classifiers":[
        {
            "category":"Autos & Motor Vehicles",
            "subcategory":"Automobile Sales",
            "type":"Retail Goods"
        }
    ],
    "sg:phone":"+1 505 439 5620",
    "sg:postcode":"88310",
    "sg:province":"NM",
    "sg:tags":[
        "car",
        "golf",
        "sales",
        "utility"
    ],
    "wof:name":"Apsco Club Car",
    "wof:placetype":"venue"
},
  "geometry": {"coordinates":[-105.95665,32.926626],"type":"Point"}
}