{
  "type": "Feature",
  "properties": {
    "iso:country":"US",
    "sg:address":"400 E 1st St",
    "sg:city":"Clovis",
    "sg:classifiers":[
        {
            "category":"Retail",
            "subcategory":"Repair Shop",
            "type":"Services"
        }
    ],
    "sg:phone":"+1 505 762 1781",
    "sg:postcode":"88101",
    "sg:province":"NM",
    "sg:tags":[
        "scooter",
        "motorcycle",
        "motor"
    ],
    "wof:name":"Clovis Cycle & Rv Sales",
    "wof:placetype":"venue"
},
  "geometry": {"coordinates":[-103.2015,34.398651],"type":"Point"}
}