{
  "type": "Feature",
  "properties": {
    "iso:country":"US",
    "sg:address":"904 1st St",
    "sg:city":"Grants",
    "sg:classifiers":[
        {
            "category":"Health Services",
            "subcategory":"Clinic",
            "type":"Services"
        }
    ],
    "sg:phone":"+1 505 287 5401",
    "sg:postcode":"87020",
    "sg:province":"NM",
    "sg:tags":[
        "home",
        "care"
    ],
    "wof:name":"Rmch Home Health",
    "wof:placetype":"venue"
},
  "geometry": {"coordinates":[-107.843066,35.1585],"type":"Point"}
}