{
  "type": "Feature",
  "properties": {
    "iso:country":"US",
    "sg:address":"239 Garfield Ave",
    "sg:city":"Socorro",
    "sg:classifiers":[
        {
            "category":"Education",
            "subcategory":"School",
            "type":"Public Place"
        }
    ],
    "sg:phone":"+1 505 835 8949",
    "sg:postcode":"87801",
    "sg:province":"NM",
    "wof:name":"Edward E Torres Elementary",
    "wof:placetype":"venue"
},
  "geometry": {"coordinates":[-106.895602,34.056433],"type":"Point"}
}