{
  "type": "Feature",
  "properties": {
    "iso:country":"US",
    "sg:address":"2428 Baylor Dr SE",
    "sg:city":"Albuquerque",
    "sg:classifiers":[
        {
            "category":"Real Estate",
            "subcategory":"Architect",
            "type":"Services"
        }
    ],
    "sg:phone":"+1 505 247 9955",
    "sg:postcode":"87106",
    "sg:province":"NM",
    "sg:tags":[
        "architectural"
    ],
    "sg:website":"www.vhga.net",
    "wof:name":"Van H Gilbert Architect P C",
    "wof:placetype":"venue"
},
  "geometry": {"coordinates":[-106.619376,35.05571],"type":"Point"}
}