{
  "type": "Feature",
  "properties": {
    "iso:country":"US",
    "sg:address":"622 Pso de la Loma",
    "sg:city":"Santa Fe",
    "sg:classifiers":[
        {
            "category":"Retail",
            "subcategory":"Portrait Studio",
            "type":"Services"
        }
    ],
    "sg:phone":"+1 505 989 4161",
    "sg:postcode":"87501",
    "sg:province":"NM",
    "sg:tags":[
        "photo"
    ],
    "wof:name":"Norman Mauskopf Photographer",
    "wof:placetype":"venue"
},
  "geometry": {"coordinates":[-105.93898,35.694954],"type":"Point"}
}