{
  "type": "Feature",
  "properties": {
    "iso:country":"US",
    "sg:address":"570 Lisbon Ave SE",
    "sg:city":"Rio Rancho",
    "sg:classifiers":[
        {
            "category":"Building & Trades",
            "subcategory":"Construction",
            "type":"Services"
        }
    ],
    "sg:phone":"+1 505 890 5624",
    "sg:postcode":"87124",
    "sg:province":"NM",
    "sg:tags":[
        "painter"
    ],
    "wof:name":"Bob The Painter",
    "wof:placetype":"venue"
},
  "geometry": {"coordinates":[-106.707226,35.252631],"type":"Point"}
}