{
  "type": "Feature",
  "properties": {
    "iso:country":"US",
    "sg:address":"422 San Felipe St NW",
    "sg:city":"Albuquerque",
    "sg:phone":"+1 505 244 3000",
    "sg:postcode":"87104",
    "sg:province":"NM",
    "wof:name":"Native Arts & Crafts",
    "wof:placetype":"venue"
},
  "geometry": {"coordinates":[-106.669402,35.097211],"type":"Point"}
}