{
  "type": "Feature",
  "properties": {
    "addr:full":"320 Osuna Rd NE Albuquerque NM 87107",
    "addr:housenumber":"320",
    "addr:postcode":"87107",
    "addr:street":"Osuna Rd Ne",
    "iso:country":"US",
    "sg:address":"320 Osuna Rd NE",
    "sg:city":"Albuquerque",
    "sg:classifiers":[
        {
            "category":"Organizations",
            "subcategory":"Non-profit Organization",
            "type":"Services"
        }
    ],
    "sg:phone":"+1 505 345 9033",
    "sg:postcode":"87107",
    "sg:province":"NM",
    "wof:name":"Enterprise Community",
    "wof:placetype":"venue"
},
  "geometry": {"coordinates":[-106.623423,35.1515],"type":"Point"}
}