{
  "type": "Feature",
  "properties": {
    "addr:full":"110 Amherst Dr SE Albuquerque NM 87106",
    "addr:housenumber":"110",
    "addr:postcode":"87106",
    "addr:street":"Amherst Dr Se",
    "iso:country":"US",
    "sg:address":"110 Amherst Dr SE",
    "sg:city":"Albuquerque",
    "sg:classifiers":[
        {
            "category":"Shopping",
            "subcategory":"Jewelry",
            "type":"Retail Goods"
        }
    ],
    "sg:phone":"+1 505 265 7170",
    "sg:postcode":"87106",
    "sg:province":"NM",
    "wof:name":"Ooh Aah Jewelry",
    "wof:placetype":"venue"
},
  "geometry": {"coordinates":[-106.605707,35.079157],"type":"Point"}
}