{
  "type": "Feature",
  "properties": {
    "addr:full":"904 Brazos Pl SE Albuquerque NM 87123",
    "addr:housenumber":"904",
    "addr:postcode":"87123",
    "addr:street":"Brazos Pl Se",
    "iso:country":"US",
    "sg:address":"904 Brazos Pl SE",
    "sg:city":"Albuquerque",
    "sg:classifiers":[
        {
            "category":"Professional",
            "subcategory":"Management & Consulting",
            "type":"Services"
        }
    ],
    "sg:phone":"+1 505 296 9287",
    "sg:postcode":"87123",
    "sg:province":"NM",
    "wof:name":"Joyce Godwin",
    "wof:placetype":"venue"
},
  "geometry": {"coordinates":[-106.50377,35.045418],"type":"Point"}
}