{
  "type": "Feature",
  "properties": {
    "addr:full":"821 E Pine St Deming NM 88030",
    "addr:housenumber":"821",
    "addr:postcode":"88030",
    "addr:street":"E Pine St",
    "iso:country":"US",
    "sg:address":"821 E Pine St",
    "sg:city":"Deming",
    "sg:classifiers":[
        {
            "category":"Restaurant",
            "type":"Food & Drink"
        }
    ],
    "sg:menulink":"http://www.allmenus.com/nm/deming-north/181799-wendys/menu/",
    "sg:phone":"+1 505 544 3028",
    "sg:postcode":"88030",
    "sg:province":"NM",
    "sg:tags":[
        "burger",
        "american",
        "soup"
    ],
    "wof:name":"Wendy's",
    "wof:placetype":"venue"
},
  "geometry": {"coordinates":[-107.747636,32.268773],"type":"Point"}
}