{
  "type": "Feature",
  "properties": {
    "iso:country":"US",
    "sg:address":"108 Industrial Park Loop NE",
    "sg:city":"Rio Rancho",
    "sg:classifiers":[
        {
            "category":"Retail",
            "subcategory":"Auto Repair",
            "type":"Services"
        }
    ],
    "sg:phone":"+1 505 896 9757",
    "sg:postcode":"87124",
    "sg:province":"NM",
    "sg:tags":[
        "wrecker"
    ],
    "wof:name":"ASAP Towing",
    "wof:placetype":"venue"
},
  "geometry": {"coordinates":[-106.631201,35.26038],"type":"Point"}
}