{
  "type": "Feature",
  "properties": {
    "iso:country":"US",
    "sg:address":"2712 N Main St",
    "sg:city":"Roswell",
    "sg:classifiers":[
        {
            "category":"Shopping",
            "subcategory":"Discount & Variety Stores",
            "type":"Retail Goods"
        }
    ],
    "sg:phone":"+1 505 627 3379",
    "sg:postcode":"88201",
    "sg:province":"NM",
    "wof:name":"Dollar General",
    "wof:placetype":"venue"
},
  "geometry": {"coordinates":[-104.523087,33.426581],"type":"Point"}
}