{
  "type": "Feature",
  "properties": {
    "addr:full":"3500 Trinity Dr Los Alamos NM 87544",
    "addr:housenumber":"3500",
    "addr:postcode":"87544",
    "addr:street":"Trinity Dr",
    "iso:country":"US",
    "sg:address":"3500 Trinity Dr",
    "sg:city":"Los Alamos",
    "sg:classifiers":[
        {
            "category":"Social Services",
            "type":"Services"
        }
    ],
    "sg:phone":"+1 505 662 2300",
    "sg:postcode":"87544",
    "sg:province":"NM",
    "sg:tags":[
        "pregnancy",
        "counseling",
        "information"
    ],
    "wof:name":"Hope Pregnancy Ctr",
    "wof:placetype":"venue"
},
  "geometry": {"coordinates":[-106.31421,35.882919],"type":"Point"}
}