{
  "type": "Feature",
  "properties": {
    "addr:full":"2008 W Broadway Ave Bloomfield NM 87413",
    "addr:housenumber":"2008",
    "addr:postcode":"87413",
    "addr:street":"W Broadway Ave",
    "iso:country":"US",
    "sg:address":"2008 W Broadway Ave",
    "sg:city":"Bloomfield",
    "sg:classifiers":[
        {
            "category":"Restaurant",
            "type":"Food & Drink"
        }
    ],
    "sg:phone":"+1 505 632 4514",
    "sg:postcode":"87413",
    "sg:province":"NM",
    "wof:name":"Bridges Cookin USA Rstrnt",
    "wof:placetype":"venue"
},
  "geometry": {"coordinates":[-108.00012700000001,36.711354],"type":"Point"}
}