{
  "type": "Feature",
  "properties": {
    "addr:full":"101 N Alameda Blvd Las Cruces NM 88005",
    "addr:housenumber":"101",
    "addr:postcode":"88005",
    "addr:street":"N Alameda Blvd",
    "iso:country":"US",
    "sg:address":"101 N Alameda Blvd",
    "sg:city":"Las Cruces",
    "sg:classifiers":[
        {
            "category":"Organizations",
            "subcategory":"Labor Organization",
            "type":"Services"
        }
    ],
    "sg:phone":"+1 505 526 7773",
    "sg:postcode":"88005",
    "sg:province":"NM",
    "wof:name":"APWU",
    "wof:placetype":"venue"
},
  "geometry": {"coordinates":[-106.78139,32.309779],"type":"Point"}
}