{
  "type": "Feature",
  "properties": {
    "addr:full":"3130 Vista Grande Dr NW Albuquerque NM 87120",
    "addr:housenumber":"3130",
    "addr:postcode":"87120",
    "addr:street":"Vista Grande Dr Nw",
    "iso:country":"US",
    "sg:address":"3130 Vista Grande Dr NW",
    "sg:city":"Albuquerque",
    "sg:classifiers":[
        {
            "category":"Community Center",
            "subcategory":"Senior",
            "type":"Public Place"
        }
    ],
    "sg:phone":"+1 505 839 1014",
    "sg:postcode":"87120",
    "sg:province":"NM",
    "sg:tags":[
        "citizen"
    ],
    "wof:name":"Preferred Assisted Living",
    "wof:placetype":"venue"
},
  "geometry": {"coordinates":[-106.696944,35.117173],"type":"Point"}
}