{
  "type": "Feature",
  "properties": {
    "addr:full":"2025 E Aztec Ave Gallup NM 87301",
    "addr:housenumber":"2025",
    "addr:postcode":"87301",
    "addr:street":"E Aztec Ave",
    "iso:country":"US",
    "sg:address":"2025 E Aztec Ave",
    "sg:city":"Gallup",
    "sg:classifiers":[
        {
            "category":"Health Services",
            "subcategory":"Doctor",
            "type":"Services"
        }
    ],
    "sg:phone":"+1 505 863 2847",
    "sg:postcode":"87301",
    "sg:province":"NM",
    "sg:tags":[
        "clinic"
    ],
    "wof:name":"Western New Mexico Medical",
    "wof:placetype":"venue"
},
  "geometry": {"coordinates":[-108.71127300000001,35.52818],"type":"Point"}
}