{
  "type": "Feature",
  "properties": {
    "iso:country":"US",
    "sg:address":"467 61st St NW",
    "sg:city":"Albuquerque",
    "sg:classifiers":[
        {
            "category":"Education",
            "subcategory":"Dance Studio",
            "type":"Public Place"
        }
    ],
    "sg:phone":"+1 505 831 4422",
    "sg:postcode":"87105",
    "sg:province":"NM",
    "wof:name":"Rodarte Pblo Schl Flmnco Spani",
    "wof:placetype":"venue"
},
  "geometry": {"coordinates":[-106.707766,35.087847],"type":"Point"}
}