{
  "type": "Feature",
  "properties": {
    "addr:full":"3400 Menaul Blvd NE 200 Albuquerque NM 87107",
    "addr:housenumber":"3400",
    "addr:postcode":"200;87107",
    "addr:street":"Menaul Blvd Ne",
    "iso:country":"US",
    "sg:address":"3400 Menaul Blvd NE 200",
    "sg:city":"Albuquerque",
    "sg:classifiers":[
        {
            "category":"Professional",
            "subcategory":"Engineering",
            "type":"Services"
        },
        {
            "category":"Professional",
            "subcategory":"Business Services",
            "type":"Services"
        },
        {
            "category":"Professional",
            "subcategory":"Computer Services",
            "type":"Services"
        }
    ],
    "sg:phone":"+1 505 798 0900",
    "sg:postcode":"87107",
    "sg:province":"NM",
    "sg:tags":[
        "coach",
        "consultant",
        "system",
        "integration",
        "designer",
        "engineer"
    ],
    "sg:website":"http://www.lhbis.com",
    "wof:name":"Lighthouse Business Information Solutions",
    "wof:placetype":"venue"
},
  "geometry": {"coordinates":[-106.60618100000001,35.109169],"type":"Point"}
}