{
  "type": "Feature",
  "properties": {
    "iso:country":"US",
    "sg:address":"211 S Cambridge Ave",
    "sg:city":"Hagerman",
    "sg:classifiers":[
        {
            "category":"Organizations",
            "subcategory":"Religious Organization",
            "type":"Services"
        }
    ],
    "sg:phone":"+1 505 752 3548",
    "sg:postcode":"88232",
    "sg:province":"NM",
    "sg:tags":[
        "church"
    ],
    "wof:name":"First Baptist Church",
    "wof:placetype":"venue"
},
  "geometry": {"coordinates":[-104.326308,33.112676],"type":"Point"}
}