{
  "type": "Feature",
  "properties": {
    "iso:country":"US",
    "sg:address":"3000 E Lohman Ave",
    "sg:city":"Las Cruces",
    "sg:classifiers":[
        {
            "category":"Banks & Credit Unions",
            "subcategory":"Bank",
            "type":"Services"
        }
    ],
    "sg:phone":"+1 505 556 3000",
    "sg:postcode":"88011",
    "sg:province":"NM",
    "wof:name":"First New Mexico Bank",
    "wof:placetype":"venue"
},
  "geometry": {"coordinates":[-106.74184,32.31648],"type":"Point"}
}