{
  "type": "Feature",
  "properties": {
    "iso:country":"US",
    "sg:address":"219 N Orchard Ave",
    "sg:city":"Farmington",
    "sg:classifiers":[
        {
            "category":"Organizations",
            "subcategory":"Religious Organization",
            "type":"Services"
        }
    ],
    "sg:phone":"+1 505 324 4688",
    "sg:postcode":"87401",
    "sg:province":"NM",
    "sg:tags":[
        "church"
    ],
    "wof:name":"San Juan Unitarian Fellowship",
    "wof:placetype":"venue"
},
  "geometry": {"coordinates":[-108.205352,36.731264],"type":"Point"}
}