{
  "type": "Feature",
  "properties": {
    "iso:country":"US",
    "sg:address":"7100 Menaul Blvd NE",
    "sg:city":"Albuquerque",
    "sg:classifiers":[
        {
            "category":"Personal",
            "type":"Services"
        }
    ],
    "sg:phone":"+1 505 269 3780",
    "sg:postcode":"87110",
    "sg:province":"NM",
    "sg:tags":[
        "therapist",
        "massage"
    ],
    "sg:website":"www.bodybenefits.net",
    "wof:name":"Body Benefits",
    "wof:placetype":"venue"
},
  "geometry": {"coordinates":[-106.564425,35.109156],"type":"Point"}
}