{
  "type": "Feature",
  "properties": {
    "iso:country":"US",
    "sg:address":"8509 Silverado Ave SW",
    "sg:city":"Albuquerque",
    "sg:classifiers":[
        {
            "category":"Retail",
            "subcategory":"Repair Shop",
            "type":"Services"
        }
    ],
    "sg:phone":"+1 505 352 2295",
    "sg:postcode":"87121",
    "sg:province":"NM",
    "wof:name":"Almanzas Cleaning House",
    "wof:placetype":"venue"
},
  "geometry": {"coordinates":[-106.731281,35.046388],"type":"Point"}
}