{
  "type": "Feature",
  "properties": {
    "addr:full":"1300 Tuyuna Trl Bernalillo NM 87004",
    "addr:housenumber":"1300",
    "addr:postcode":"87004",
    "addr:street":"Tuyuna Trl",
    "iso:country":"US",
    "sg:address":"1300 Tuyuna Trl",
    "sg:city":"Bernalillo",
    "sg:classifiers":[
        {
            "category":"Travel",
            "subcategory":"Hotels & Motels",
            "type":"Entertainment"
        }
    ],
    "sg:postcode":"87004",
    "sg:province":"NM",
    "sg:tags":[
        "lodging"
    ],
    "sg:website":"http://www.hyattregencytamaya.com?src=agn_tig_hhc_lk_2nd_ntnl_yellowpages_tamay",
    "wof:name":"Hyatt Regency Tamaya Resort and Spa",
    "wof:placetype":"venue"
},
  "geometry": {"coordinates":[-106.54718,35.35078],"type":"Point"}
}