{
  "type": "Feature",
  "properties": {
    "iso:country":"US",
    "sg:address":"10012 Coors Blvd NW",
    "sg:city":"Albuquerque",
    "sg:classifiers":[
        {
            "category":"Home & Garden",
            "subcategory":"Furniture",
            "type":"Retail Goods"
        }
    ],
    "sg:phone":"+1 505 890 6000",
    "sg:postcode":"87114",
    "sg:province":"NM",
    "sg:tags":[
        "equipment"
    ],
    "wof:name":"Academy Furniture Factory Outl",
    "wof:placetype":"venue"
},
  "geometry": {"coordinates":[-106.653818,35.194631],"type":"Point"}
}