{
  "type": "Feature",
  "properties": {
    "addr:full":"2113 Charlevoix St NW Albuquerque NM 87104",
    "addr:housenumber":"2113",
    "addr:postcode":"87104",
    "addr:street":"Charlevoix St Nw",
    "iso:country":"US",
    "sg:address":"2113 Charlevoix St NW",
    "sg:city":"Albuquerque",
    "sg:classifiers":[
        {
            "category":"Shopping",
            "type":"Retail Goods"
        }
    ],
    "sg:phone":"+1 505 242 2787",
    "sg:postcode":"87104",
    "sg:province":"NM",
    "sg:tags":[
        "art",
        "gallery",
        "dealer"
    ],
    "wof:name":"Charlevoix Street Gallery",
    "wof:placetype":"venue"
},
  "geometry": {"coordinates":[-106.67026799999999,35.098217],"type":"Point"}
}