{
  "type": "Feature",
  "properties": {
    "addr:full":"320 Lincoln St Anthony NM 88021",
    "addr:housenumber":"320",
    "addr:postcode":"88021",
    "addr:street":"Lincoln St",
    "iso:country":"US",
    "sg:address":"320 Lincoln St",
    "sg:city":"Anthony",
    "sg:classifiers":[
        {
            "category":"Insurance",
            "subcategory":"Insurance Agent",
            "type":"Services"
        }
    ],
    "sg:phone":"+1 505 882 5587",
    "sg:postcode":"88021",
    "sg:province":"NM",
    "wof:name":"Paul Jewell Insurance",
    "wof:placetype":"venue"
},
  "geometry": {"coordinates":[-106.603971,32.002095],"type":"Point"}
}