{
  "type": "Feature",
  "properties": {
    "addr:full":"814 W 7th St Clovis NM 88101",
    "addr:housenumber":"814",
    "addr:postcode":"88101",
    "addr:street":"W 7Th St",
    "iso:country":"US",
    "sg:address":"814 W 7th St",
    "sg:city":"Clovis",
    "sg:classifiers":[
        {
            "category":"Retail",
            "subcategory":"Auto Repair",
            "type":"Services"
        }
    ],
    "sg:phone":"+1 505 762 6925",
    "sg:postcode":"88101",
    "sg:province":"NM",
    "sg:tags":[
        "body",
        "automobile",
        "painting"
    ],
    "wof:name":"Walker's Body Shop",
    "wof:placetype":"venue"
},
  "geometry": {"coordinates":[-103.215276,34.404757],"type":"Point"}
}