{
  "type": "Feature",
  "properties": {
    "iso:country":"US",
    "sg:address":"310 E 3rd Ave",
    "sg:city":"Truth Or Cnsqncs",
    "sg:classifiers":[
        {
            "category":"Personal",
            "subcategory":"Barber",
            "type":"Services"
        }
    ],
    "sg:phone":"+1 505 894 1477",
    "sg:postcode":"87901",
    "sg:province":"NM",
    "sg:tags":[
        "shop"
    ],
    "wof:name":"Ivan International",
    "wof:placetype":"venue"
},
  "geometry": {"coordinates":[-107.248047,33.133224],"type":"Point"}
}