{
  "type": "Feature",
  "properties": {
    "iso:country":"US",
    "sg:address":"1524 Zuni Dr",
    "sg:city":"Farmington",
    "sg:classifiers":[
        {
            "category":"Retail",
            "subcategory":"Repair Shop",
            "type":"Services"
        }
    ],
    "sg:phone":"+1 505 326 4265",
    "sg:postcode":"87401",
    "sg:province":"NM",
    "sg:tags":[
        "repairing",
        "piano",
        "refinishing"
    ],
    "wof:name":"T-Ce Piano Tuning & Organ Rpr",
    "wof:placetype":"venue"
},
  "geometry": {"coordinates":[-108.190096,36.746973],"type":"Point"}
}