{
  "type": "Feature",
  "properties": {
    "addr:full":"9516 Mc Knight Ave NE Albuquerque NM 87112",
    "addr:housenumber":"9516",
    "addr:postcode":"87112",
    "addr:street":"Mc Knight Ave Ne",
    "iso:country":"US",
    "sg:address":"9516 Mc Knight Ave NE",
    "sg:city":"Albuquerque",
    "sg:classifiers":[
        {
            "category":"Home & Garden",
            "subcategory":"Household Appliances",
            "type":"Retail Goods"
        }
    ],
    "sg:phone":"+1 505 323 2114",
    "sg:postcode":"87112",
    "sg:province":"NM",
    "wof:name":"Hillside Car Wash",
    "wof:placetype":"venue"
},
  "geometry": {"coordinates":[-106.53753,35.100946],"type":"Point"}
}