{
  "type": "Feature",
  "properties": {
    "addr:full":"1190 E Foster Rd Las Cruces NM 88001",
    "addr:housenumber":"1190",
    "addr:postcode":"88001",
    "addr:street":"E Foster Rd",
    "iso:country":"US",
    "sg:address":"1190 E Foster Rd",
    "sg:city":"Las Cruces",
    "sg:classifiers":[
        {
            "category":"Building & Trades",
            "subcategory":"Electrical",
            "type":"Services"
        }
    ],
    "sg:phone":"+1 505 532 0115",
    "sg:postcode":"88001",
    "sg:province":"NM",
    "sg:tags":[
        "electrical",
        "contractor"
    ],
    "wof:name":"Cables Only",
    "wof:placetype":"venue"
},
  "geometry": {"coordinates":[-106.762862,32.297656],"type":"Point"}
}