{
  "type": "Feature",
  "properties": {
    "iso:country":"US",
    "sg:address":"509 Granado St",
    "sg:city":"Tularosa",
    "sg:classifiers":[
        {
            "category":"Restaurant",
            "type":"Food & Drink"
        }
    ],
    "sg:phone":"+1 505 585 2911",
    "sg:postcode":"88352",
    "sg:province":"NM",
    "wof:name":"Tulie Sidewalk Cafe",
    "wof:placetype":"venue"
},
  "geometry": {"coordinates":[-106.018629,33.071955],"type":"Point"}
}