{
  "type": "Feature",
  "properties": {
    "iso:country":"US",
    "sg:address":"1718 Saint Michaels Dr",
    "sg:city":"Santa Fe",
    "sg:classifiers":[
        {
            "category":"Restaurant",
            "type":"Food & Drink"
        }
    ],
    "sg:menulink":"http://www.allmenus.com/nm/santa-fe/152901-carrows/menu/",
    "sg:phone":"+1 505 471 7856",
    "sg:postcode":"87505",
    "sg:province":"NM",
    "sg:tags":[
        "sandwich",
        "salad",
        "burger",
        "dog",
        "soup",
        "hot",
        "wrap",
        "american"
    ],
    "wof:name":"Carrows",
    "wof:placetype":"venue"
},
  "geometry": {"coordinates":[-105.971667,35.659205],"type":"Point"}
}