{
  "type": "Feature",
  "properties": {
    "addr:full":"2515 Bosque Entrada Trl NW Albuquerque NM 87120",
    "addr:housenumber":"2515",
    "addr:postcode":"87120",
    "addr:street":"Bosque Entrada Trl Nw",
    "iso:country":"US",
    "sg:address":"2515 Bosque Entrada Trl NW",
    "sg:city":"Albuquerque",
    "sg:classifiers":[
        {
            "category":"Professional",
            "subcategory":"Engineering",
            "type":"Services"
        }
    ],
    "sg:phone":"+1 505 263 9195",
    "sg:postcode":"87120",
    "sg:province":"NM",
    "sg:tags":[
        "engineer"
    ],
    "wof:name":"PRSM Corp",
    "wof:placetype":"venue"
},
  "geometry": {"coordinates":[-106.663803,35.169834],"type":"Point"}
}