{
  "type": "Feature",
  "properties": {
    "addr:full":"919 N Valley Dr Las Cruces NM 88005",
    "addr:housenumber":"919",
    "addr:postcode":"88005",
    "addr:street":"N Valley Dr",
    "iso:country":"US",
    "sg:address":"919 N Valley Dr",
    "sg:city":"Las Cruces",
    "sg:classifiers":[
        {
            "category":"Shopping",
            "subcategory":"Musical Instruments",
            "type":"Retail Goods"
        }
    ],
    "sg:phone":"+1 505 526 8777",
    "sg:postcode":"88005",
    "sg:province":"NM",
    "wof:name":"Mesilla Valley Pro Music Sound",
    "wof:placetype":"venue"
},
  "geometry": {"coordinates":[-106.797178,32.313891],"type":"Point"}
}