{
  "type": "Feature",
  "properties": {
    "iso:country":"US",
    "sg:address":"26 Riovista Run",
    "sg:city":"Espanola",
    "sg:classifiers":[
        {
            "category":"Building & Trades",
            "subcategory":"Electrical",
            "type":"Services"
        }
    ],
    "sg:phone":"+1 505 927 1389",
    "sg:postcode":"87567",
    "sg:province":"NM",
    "sg:tags":[
        "electrical",
        "contractor"
    ],
    "wof:name":"Four Star Electric",
    "wof:placetype":"venue"
},
  "geometry": {"coordinates":[-105.994327,35.99572],"type":"Point"}
}