{
  "type": "Feature",
  "properties": {
    "iso:country":"US",
    "sg:address":"2415 Espanola St NE",
    "sg:city":"Albuquerque",
    "sg:classifiers":[
        {
            "category":"Building & Trades",
            "subcategory":"Cleaning & Sanitation",
            "type":"Services"
        },
        {
            "category":"Building & Trades",
            "subcategory":"Construction",
            "type":"Services"
        }
    ],
    "sg:phone":"+1 505 550 2300",
    "sg:postcode":"87110",
    "sg:province":"NM",
    "sg:tags":[
        "house"
    ],
    "wof:name":"Hammer Time Remodeling",
    "wof:placetype":"venue"
},
  "geometry": {"coordinates":[-106.563959,35.107252],"type":"Point"}
}