{
  "type": "Feature",
  "properties": {
    "addr:full":"324 S 6th St Socorro NM 87801",
    "addr:housenumber":"324",
    "addr:postcode":"87801",
    "addr:street":"S 6Th St",
    "iso:country":"US",
    "sg:address":"324 S 6th St",
    "sg:city":"Socorro",
    "sg:classifiers":[
        {
            "category":"Personal",
            "subcategory":"Barber",
            "type":"Services"
        }
    ],
    "sg:phone":"+1 505 838 0780",
    "sg:postcode":"87801",
    "sg:province":"NM",
    "wof:name":"Jeff's Barber Shop",
    "wof:placetype":"venue"
},
  "geometry": {"coordinates":[-106.89553100000001,34.052961],"type":"Point"}
}