{
  "type": "Feature",
  "properties": {
    "addr:full":"7201 Jefferson St NE Albuquerque NM 87109",
    "addr:housenumber":"7201",
    "addr:postcode":"87109",
    "addr:street":"Jefferson St Ne",
    "iso:country":"US",
    "sg:address":"7201 Jefferson St NE",
    "sg:city":"Albuquerque",
    "sg:classifiers":[
        {
            "category":"Professional",
            "subcategory":"Printing & Photocopies",
            "type":"Services"
        }
    ],
    "sg:phone":"+1 505 881 2821",
    "sg:postcode":"87109",
    "sg:province":"NM",
    "sg:tags":[
        "duplicating",
        "copying"
    ],
    "wof:name":"Spin Print",
    "wof:placetype":"venue"
},
  "geometry": {"coordinates":[-106.593323,35.1618],"type":"Point"}
}