{
  "type": "Feature",
  "properties": {
    "addr:full":"600 E Llano Estacado Blvd Clovis NM 88101",
    "addr:housenumber":"600",
    "addr:postcode":"88101",
    "addr:street":"E Llano Estacado Blvd",
    "iso:country":"US",
    "sg:address":"600 E Llano Estacado Blvd",
    "sg:city":"Clovis",
    "sg:classifiers":[
        {
            "category":"Autos & Motor Vehicles",
            "subcategory":"Fuel & Gas Station",
            "type":"Retail Goods"
        }
    ],
    "sg:phone":"+1 505 762 0022",
    "sg:postcode":"88101",
    "sg:province":"NM",
    "sg:tags":[
        "oil"
    ],
    "wof:name":"Llano Estacado Chevron",
    "wof:placetype":"venue"
},
  "geometry": {"coordinates":[-103.19893,34.434033],"type":"Point"}
}