{
  "type": "Feature",
  "properties": {
    "addr:full":"1000 W High St Grants NM 87020",
    "addr:housenumber":"1000",
    "addr:postcode":"87020",
    "addr:street":"W High St",
    "iso:country":"US",
    "sg:address":"1000 W High St",
    "sg:city":"Grants",
    "sg:classifiers":[
        {
            "category":"Real Estate",
            "subcategory":"Real Estate Agent",
            "type":"Services"
        }
    ],
    "sg:phone":"+1 505 285 6887",
    "sg:postcode":"87020",
    "sg:province":"NM",
    "wof:name":"Real Estate Corner",
    "wof:placetype":"venue"
},
  "geometry": {"coordinates":[-107.860203,35.155364],"type":"Point"}
}