{
  "type": "Feature",
  "properties": {
    "addr:full":"9722 Central Ave SW Albuquerque NM 87121",
    "addr:housenumber":"9722",
    "addr:postcode":"87121",
    "addr:street":"Central Ave Sw",
    "iso:country":"US",
    "sg:address":"9722 Central Ave SW",
    "sg:city":"Albuquerque",
    "sg:classifiers":[
        {
            "category":"Cinema",
            "subcategory":"Movie Rental",
            "type":"Entertainment"
        }
    ],
    "sg:phone":"+1 505 836 4146",
    "sg:postcode":"87121",
    "sg:province":"NM",
    "sg:tags":[
        "leasing",
        "video",
        "disc",
        "tape"
    ],
    "wof:name":"Route 66 Flicks",
    "wof:placetype":"venue"
},
  "geometry": {"coordinates":[-106.742255,35.072773],"type":"Point"}
}