{
  "type": "Feature",
  "properties": {
    "addr:full":"521 N Connelly St Clovis NM 88101",
    "addr:housenumber":"521",
    "addr:postcode":"88101",
    "addr:street":"N Connelly St",
    "iso:country":"US",
    "sg:address":"521 N Connelly St",
    "sg:city":"Clovis",
    "sg:classifiers":[
        {
            "category":"Retail",
            "subcategory":"Auto Repair",
            "type":"Services"
        }
    ],
    "sg:phone":"+1 575 742 2167",
    "sg:postcode":"88101",
    "sg:province":"NM",
    "sg:tags":[
        "body",
        "automobile",
        "painting",
        "repairing"
    ],
    "wof:name":"Clovis Clsc Customs",
    "wof:placetype":"venue"
},
  "geometry": {"coordinates":[-103.207916,34.40308],"type":"Point"}
}