{
  "type": "Feature",
  "properties": {
    "iso:country":"US",
    "sg:address":"4100 Monroe Rd",
    "sg:city":"Farmington",
    "sg:classifiers":[
        {
            "category":"Wholesale",
            "subcategory":"Construction Materials",
            "type":"Manufacturing & Wholesale Goods"
        }
    ],
    "sg:phone":"+1 505 860 9452",
    "sg:postcode":"87401",
    "sg:province":"NM",
    "sg:tags":[
        "marble"
    ],
    "wof:name":"Enchanted Marble & Glass Inc",
    "wof:placetype":"venue"
},
  "geometry": {"coordinates":[-108.150929,36.719086],"type":"Point"}
}