{
  "type": "Feature",
  "properties": {
    "iso:country":"US",
    "sg:address":"2237 Trinity Dr",
    "sg:city":"Los Alamos",
    "sg:classifiers":[
        {
            "category":"Professional",
            "subcategory":"Engineering",
            "type":"Services"
        }
    ],
    "sg:phone":"+1 505 662 3700",
    "sg:postcode":"87544",
    "sg:province":"NM",
    "sg:tags":[
        "environmental",
        "consulting"
    ],
    "wof:name":"Washington Group",
    "wof:placetype":"venue"
},
  "geometry": {"coordinates":[-106.303304,35.880016],"type":"Point"}
}