{
  "type": "Feature",
  "properties": {
    "iso:country":"US",
    "sg:address":"508 S California St",
    "sg:city":"Socorro",
    "sg:classifiers":[
        {
            "category":"Social Services",
            "subcategory":"Job Training",
            "type":"Services"
        }
    ],
    "sg:phone":"+1 505 835 4243",
    "sg:postcode":"87801",
    "sg:province":"NM",
    "sg:tags":[
        "rehab",
        "vocational",
        "ctr"
    ],
    "wof:name":"Area VI Vocational Rehab Ctr",
    "wof:placetype":"venue"
},
  "geometry": {"coordinates":[-106.89058799999999,34.053321],"type":"Point"}
}