{
  "type": "Feature",
  "properties": {
    "addr:full":"915 Sunset Rd SW Albuquerque NM 87105",
    "addr:housenumber":"915",
    "addr:postcode":"87105",
    "addr:street":"Sunset Rd Sw",
    "iso:country":"US",
    "sg:address":"915 Sunset Rd SW",
    "sg:city":"Albuquerque",
    "sg:classifiers":[
        {
            "category":"Home & Garden",
            "subcategory":"Furniture",
            "type":"Retail Goods"
        }
    ],
    "sg:phone":"+1 505 243 5861",
    "sg:postcode":"87105",
    "sg:province":"NM",
    "sg:tags":[
        "appliance"
    ],
    "wof:name":"Imperial Furniture Co",
    "wof:placetype":"venue"
},
  "geometry": {"coordinates":[-106.674666,35.066718],"type":"Point"}
}