{
  "type": "Feature",
  "properties": {
    "addr:full":"500 Commerce Way Clovis NM 88101",
    "addr:housenumber":"500",
    "addr:postcode":"88101",
    "addr:street":"Commerce Way",
    "iso:country":"US",
    "sg:address":"500 Commerce Way",
    "sg:city":"Clovis",
    "sg:classifiers":[
        {
            "category":"Retail",
            "subcategory":"Laundry & Dry Cleaning",
            "type":"Services"
        }
    ],
    "sg:phone":"+1 505 762 9202",
    "sg:postcode":"88101",
    "sg:province":"NM",
    "sg:tags":[
        "drycleaning",
        "plant",
        "cleaners"
    ],
    "wof:name":"Sparkle Cleaners Inc",
    "wof:placetype":"venue"
},
  "geometry": {"coordinates":[-103.19899700000001,34.416954],"type":"Point"}
}