{
  "type": "Feature",
  "properties": {
    "iso:country":"US",
    "sg:address":"3949 Corrales Rd NW",
    "sg:city":"Corrales",
    "sg:classifiers":[
        {
            "category":"Wholesale",
            "subcategory":"Medical Equipment & Supplies",
            "type":"Manufacturing & Wholesale Goods"
        }
    ],
    "sg:phone":"+1 505 922 1858",
    "sg:postcode":"87048",
    "sg:province":"NM",
    "sg:tags":[
        "physician",
        "surgeon"
    ],
    "wof:name":"Better Breathing Concepts LLC",
    "wof:placetype":"venue"
},
  "geometry": {"coordinates":[-106.623991,35.217689],"type":"Point"}
}