{
  "type": "Feature",
  "properties": {
    "iso:country":"US",
    "sg:address":"4900 Tramway Ridge Dr NE",
    "sg:city":"Albuquerque",
    "sg:classifiers":[
        {
            "category":"Social Services",
            "subcategory":"Adult Care",
            "type":"Services"
        }
    ],
    "sg:phone":"+1 505 271 4900",
    "sg:postcode":"87111",
    "sg:province":"NM",
    "sg:tags":[
        "living",
        "assisted"
    ],
    "wof:name":"Karrington At Stfrancis Place",
    "wof:placetype":"venue"
},
  "geometry": {"coordinates":[-106.499701,35.136266],"type":"Point"}
}