{
  "type": "Feature",
  "properties": {
    "addr:full":"11008 Montgomery Blvd NE Albuquerque NM 87111",
    "addr:housenumber":"11008",
    "addr:postcode":"87111",
    "addr:street":"Montgomery Blvd Ne",
    "iso:country":"US",
    "sg:address":"11008 Montgomery Blvd NE",
    "sg:city":"Albuquerque",
    "sg:classifiers":[
        {
            "category":"Shopping",
            "subcategory":"Computers & Home Electronics",
            "type":"Retail Goods"
        }
    ],
    "sg:phone":"+1 505 293 1718",
    "sg:postcode":"87111",
    "sg:province":"NM",
    "sg:tags":[
        "equipment",
        "electronic",
        "supply"
    ],
    "wof:name":"Radio Shack",
    "wof:placetype":"venue"
},
  "geometry": {"coordinates":[-106.516563,35.130593],"type":"Point"}
}