{
  "type": "Feature",
  "properties": {
    "iso:country":"US",
    "sg:address":"1160 Commerce Dr",
    "sg:city":"Las Cruces",
    "sg:classifiers":[
        {
            "category":"Health Services",
            "subcategory":"Health Practitioner",
            "type":"Services"
        }
    ],
    "sg:phone":"+1 505 525 2450",
    "sg:postcode":"88011",
    "sg:province":"NM",
    "sg:tags":[
        "therapist",
        "physical"
    ],
    "wof:name":"Atrium Physical Therapy",
    "wof:placetype":"venue"
},
  "geometry": {"coordinates":[-106.763562,32.347386],"type":"Point"}
}