{
  "type": "Feature",
  "properties": {
    "iso:country":"US",
    "sg:address":"4501 N Main St",
    "sg:city":"Roswell",
    "sg:classifiers":[
        {
            "category":"Shopping",
            "subcategory":"Clothing, Apparel, & Fashions",
            "type":"Retail Goods"
        }
    ],
    "sg:phone":"+1 505 622 9350",
    "sg:postcode":"88201",
    "sg:province":"NM",
    "wof:name":"Limited The",
    "wof:placetype":"venue"
},
  "geometry": {"coordinates":[-104.52314800000001,33.45034],"type":"Point"}
}