{
  "type": "Feature",
  "properties": {
    "iso:country":"US",
    "sg:address":"1116 Alameda Rd NW",
    "sg:city":"Albuquerque",
    "sg:classifiers":[
        {
            "category":"Social Services",
            "subcategory":"Child Care",
            "type":"Services"
        }
    ],
    "sg:phone":"+1 505 898 3553",
    "sg:postcode":"87114",
    "sg:province":"NM",
    "sg:tags":[
        "day"
    ],
    "wof:name":"Justen Jones Family Holdings",
    "wof:placetype":"venue"
},
  "geometry": {"coordinates":[-106.634101,35.199112],"type":"Point"}
}