{
  "type": "Feature",
  "properties": {
    "addr:full":"703 Memory Ln Socorro NM 87801",
    "addr:housenumber":"703",
    "addr:postcode":"87801",
    "addr:street":"Memory Ln",
    "iso:country":"US",
    "sg:address":"703 Memory Ln",
    "sg:city":"Socorro",
    "sg:classifiers":[
        {
            "category":"Education",
            "subcategory":"School",
            "type":"Public Place"
        }
    ],
    "sg:phone":"+1 505 838 1700",
    "sg:postcode":"87801",
    "sg:province":"NM",
    "wof:name":"Faith Christian School",
    "wof:placetype":"venue"
},
  "geometry": {"coordinates":[-106.886335,34.073077],"type":"Point"}
}