{
  "type": "Feature",
  "properties": {
    "addr:full":"360 Eubank Blvd NE Albuquerque NM 87123",
    "addr:housenumber":"360",
    "addr:postcode":"87123",
    "addr:street":"Eubank Blvd Ne",
    "iso:country":"US",
    "sg:address":"360 Eubank Blvd NE",
    "sg:city":"Albuquerque",
    "sg:classifiers":[
        {
            "category":"Shopping",
            "subcategory":"Shoes",
            "type":"Retail Goods"
        }
    ],
    "sg:phone":"+1 505 237 1443",
    "sg:postcode":"87123",
    "sg:province":"NM",
    "sg:tags":[
        "shoe",
        "store"
    ],
    "sg:website":"www.payless.com",
    "wof:name":"Payless Shoe Source",
    "wof:placetype":"venue"
},
  "geometry": {"coordinates":[-106.532258,35.078955],"type":"Point"}
}