{
  "type": "Feature",
  "properties": {
    "addr:full":"7535 Prairie Rd NE Albuquerque NM 87109",
    "addr:housenumber":"7535",
    "addr:postcode":"87109",
    "addr:street":"Prairie Rd Ne",
    "iso:country":"US",
    "sg:address":"7535 Prairie Rd NE",
    "sg:city":"Albuquerque",
    "sg:classifiers":[
        {
            "category":"Freight",
            "type":"Transportation"
        }
    ],
    "sg:phone":"+1 505 889 8988",
    "sg:postcode":"87109",
    "sg:province":"NM",
    "sg:tags":[
        "trucking"
    ],
    "wof:name":"Desert Diamond Transportation",
    "wof:placetype":"venue"
},
  "geometry": {"coordinates":[-106.560543,35.133489],"type":"Point"}
}