{
  "type": "Feature",
  "properties": {
    "addr:full":"2600 N Fairview Ave Farmington NM 87401",
    "addr:housenumber":"2600",
    "addr:postcode":"87401",
    "addr:street":"N Fairview Ave",
    "iso:country":"US",
    "sg:address":"2600 N Fairview Ave",
    "sg:city":"Farmington",
    "sg:classifiers":[
        {
            "category":"Social Services",
            "type":"Services"
        }
    ],
    "sg:phone":"+1 505 327 2532",
    "sg:postcode":"87401",
    "sg:province":"NM",
    "sg:tags":[
        "counselor",
        "marriage",
        "family"
    ],
    "wof:name":"New Horizon",
    "wof:placetype":"venue"
},
  "geometry": {"coordinates":[-108.17449499999999,36.753696],"type":"Point"}
}