{
  "type": "Feature",
  "properties": {
    "addr:full":"2901 Edith Blvd NE Albuquerque NM 87107",
    "addr:housenumber":"2901",
    "addr:postcode":"87107",
    "addr:street":"Edith Blvd Ne",
    "iso:country":"US",
    "sg:address":"2901 Edith Blvd NE",
    "sg:city":"Albuquerque",
    "sg:classifiers":[
        {
            "category":"Professional",
            "subcategory":"Computer Services",
            "type":"Services"
        }
    ],
    "sg:phone":"+1 505 463 1197",
    "sg:postcode":"87107",
    "sg:province":"NM",
    "sg:tags":[
        "repair"
    ],
    "wof:name":"4 U Svc",
    "wof:placetype":"venue"
},
  "geometry": {"coordinates":[-106.635293,35.115103],"type":"Point"}
}