{
  "type": "Feature",
  "properties": {
    "addr:full":"730 Canyon Rd Santa Fe NM 87501",
    "addr:housenumber":"730",
    "addr:postcode":"87501",
    "addr:street":"Canyon Rd",
    "iso:country":"US",
    "sg:address":"730 Canyon Rd",
    "sg:city":"Santa Fe",
    "sg:classifiers":[
        {
            "category":"Restaurant",
            "type":"Food & Drink"
        }
    ],
    "sg:phone":"+1 505 986 9023",
    "sg:postcode":"87501",
    "sg:province":"NM",
    "sg:website":"www.geronimo.com",
    "wof:name":"Geronimo Corporate Office",
    "wof:placetype":"venue"
},
  "geometry": {"coordinates":[-105.92625700000001,35.681022],"type":"Point"}
}