{
  "type": "Feature",
  "properties": {
    "addr:full":"1612 Roosevelt Rd Portales NM 88130",
    "addr:housenumber":"1612",
    "addr:postcode":"88130",
    "addr:street":"Roosevelt Rd",
    "iso:country":"US",
    "sg:address":"1612 Roosevelt Rd",
    "sg:city":"Portales",
    "sg:classifiers":[
        {
            "category":"Building & Trades",
            "subcategory":"Construction",
            "type":"Services"
        }
    ],
    "sg:phone":"+1 505 356 4965",
    "sg:postcode":"88130",
    "sg:province":"NM",
    "sg:tags":[
        "handyman"
    ],
    "wof:name":"Terles Mowing",
    "wof:placetype":"venue"
},
  "geometry": {"coordinates":[-103.289526,34.303145],"type":"Point"}
}