{
  "type": "Feature",
  "properties": {
    "iso:country":"US",
    "sg:address":"4300 San Mateo Blvd NE",
    "sg:city":"Albuquerque",
    "sg:classifiers":[
        {
            "category":"Insurance",
            "subcategory":"Insurance Agent",
            "type":"Services"
        }
    ],
    "sg:phone":"+1 505 884 2939",
    "sg:postcode":"87110",
    "sg:province":"NM",
    "sg:tags":[
        "consultant"
    ],
    "wof:name":"Matrix Absence Management Inc",
    "wof:placetype":"venue"
},
  "geometry": {"coordinates":[-106.586482,35.13093],"type":"Point"}
}