{
  "type": "Feature",
  "properties": {
    "addr:full":"100 Alto Rd Alto NM 88345",
    "addr:housenumber":"100",
    "addr:postcode":"88345",
    "addr:street":"Alto Rd",
    "iso:country":"US",
    "sg:address":"100 Alto Rd",
    "sg:city":"Alto",
    "sg:classifiers":[
        {
            "category":"Retail",
            "subcategory":"Repair Shop",
            "type":"Services"
        }
    ],
    "sg:phone":"+1 505 336 9997",
    "sg:postcode":"88345",
    "sg:province":"NM",
    "sg:tags":[
        "scooter",
        "motorcycle",
        "motor"
    ],
    "wof:name":"Alto Performance Cycle",
    "wof:placetype":"venue"
},
  "geometry": {"coordinates":[-105.681304,33.33428],"type":"Point"}
}