{
  "type": "Feature",
  "properties": {
    "addr:full":"4715 Glenn Ln Las Cruces NM 88007",
    "addr:housenumber":"4715",
    "addr:postcode":"88007",
    "addr:street":"Glenn Ln",
    "iso:country":"US",
    "sg:address":"4715 Glenn Ln",
    "sg:city":"Las Cruces",
    "sg:classifiers":[
        {
            "category":"Social Services",
            "subcategory":"Child Care",
            "type":"Services"
        }
    ],
    "sg:phone":"+1 505 523 6031",
    "sg:postcode":"88007",
    "sg:province":"NM",
    "sg:tags":[
        "day"
    ],
    "wof:name":"Wimbleys Day Care Center",
    "wof:placetype":"venue"
},
  "geometry": {"coordinates":[-106.79752999999999,32.375716],"type":"Point"}
}