{
  "type": "Feature",
  "properties": {
    "iso:country":"US",
    "sg:address":"5908 Central Ave SW",
    "sg:city":"Albuquerque",
    "sg:classifiers":[
        {
            "category":"Travel",
            "subcategory":"Hotels & Motels",
            "type":"Entertainment"
        }
    ],
    "sg:phone":"+1 505 836 3888",
    "sg:postcode":"87105",
    "sg:province":"NM",
    "wof:name":"Americana Motel",
    "wof:placetype":"venue"
},
  "geometry": {"coordinates":[-106.703112,35.081573],"type":"Point"}
}