{
  "type": "Feature",
  "properties": {
    "addr:full":"225 Wheatridge Dr Clovis NM 88101",
    "addr:housenumber":"225",
    "addr:postcode":"88101",
    "addr:street":"Wheatridge Dr",
    "iso:country":"US",
    "sg:address":"225 Wheatridge Dr",
    "sg:city":"Clovis",
    "sg:classifiers":[
        {
            "category":"Retail",
            "subcategory":"Repair Shop",
            "type":"Services"
        }
    ],
    "sg:phone":"+1 505 762 6779",
    "sg:postcode":"88101",
    "sg:province":"NM",
    "sg:tags":[
        "upholsterer"
    ],
    "wof:name":"Dunagan's Upholstery",
    "wof:placetype":"venue"
},
  "geometry": {"coordinates":[-103.266991,34.396679],"type":"Point"}
}