{
  "type": "Feature",
  "properties": {
    "addr:full":"500 E 18th St Farmington NM 87401",
    "addr:housenumber":"500",
    "addr:postcode":"87401",
    "addr:street":"E 18Th St",
    "iso:country":"US",
    "sg:address":"500 E 18th St",
    "sg:city":"Farmington",
    "sg:classifiers":[
        {
            "category":"Professional",
            "subcategory":"Computer Services",
            "type":"Services"
        }
    ],
    "sg:phone":"+1 505 327 7979",
    "sg:postcode":"87401",
    "sg:province":"NM",
    "sg:tags":[
        "internet"
    ],
    "wof:name":"HLS Internet",
    "wof:placetype":"venue"
},
  "geometry": {"coordinates":[-108.200171,36.746992],"type":"Point"}
}