{
  "type": "Feature",
  "properties": {
    "iso:country":"US",
    "sg:address":"219 N 4th St",
    "sg:city":"Belen",
    "sg:classifiers":[
        {
            "category":"Health Services",
            "subcategory":"Health Practitioner",
            "type":"Services"
        }
    ],
    "sg:phone":"+1 505 861 0332",
    "sg:postcode":"87002",
    "sg:province":"NM",
    "sg:tags":[
        "acupuncture"
    ],
    "wof:name":"Acupuncture-Herbology Ctr",
    "wof:placetype":"venue"
},
  "geometry": {"coordinates":[-106.771496,34.661906],"type":"Point"}
}