{
  "type": "Feature",
  "properties": {
    "addr:full":"130 Whittington Pl Anthony NM 88021",
    "addr:housenumber":"130",
    "addr:postcode":"88021",
    "addr:street":"Whittington Pl",
    "iso:country":"US",
    "sg:address":"130 Whittington Pl",
    "sg:city":"Anthony",
    "sg:classifiers":[
        {
            "category":"Professional",
            "subcategory":"Engineering",
            "type":"Services"
        }
    ],
    "sg:phone":"+1 505 589 5278",
    "sg:postcode":"88021",
    "sg:province":"NM",
    "wof:name":"Glaser Engineering",
    "wof:placetype":"venue"
},
  "geometry": {"coordinates":[-106.62523299999999,31.91515],"type":"Point"}
}