{
  "type": "Feature",
  "properties": {
    "iso:country":"US",
    "sg:address":"6220 San Mateo Blvd NE",
    "sg:city":"Albuquerque",
    "sg:classifiers":[
        {
            "category":"Professional",
            "subcategory":"Management & Consulting",
            "type":"Services"
        }
    ],
    "sg:phone":"+1 505 858 0708",
    "sg:postcode":"87109",
    "sg:province":"NM",
    "wof:name":"Peterschmidt & Assoc",
    "wof:placetype":"venue"
},
  "geometry": {"coordinates":[-106.586758,35.151503],"type":"Point"}
}