{
  "type": "Feature",
  "properties": {
    "iso:country":"US",
    "sg:address":"1021 Northern Blvd NE",
    "sg:city":"Rio Rancho",
    "sg:classifiers":[
        {
            "category":"Building & Trades",
            "subcategory":"Electrical",
            "type":"Services"
        }
    ],
    "sg:phone":"+1 505 892 3902",
    "sg:postcode":"87124",
    "sg:province":"NM",
    "sg:tags":[
        "electric",
        "contractor"
    ],
    "wof:name":"Design Electric",
    "wof:placetype":"venue"
},
  "geometry": {"coordinates":[-106.713416,35.274428],"type":"Point"}
}