{
  "type": "Feature",
  "properties": {
    "addr:full":"707 7th St Tularosa NM 88352",
    "addr:housenumber":"707",
    "addr:postcode":"88352",
    "addr:street":"7Th St",
    "iso:country":"US",
    "sg:address":"707 7th St",
    "sg:city":"Tularosa",
    "sg:classifiers":[
        {
            "category":"Professional",
            "subcategory":"Business Services",
            "type":"Services"
        }
    ],
    "sg:phone":"+1 505 585 0111",
    "sg:postcode":"88352",
    "sg:province":"NM",
    "wof:name":"Heacock Literary Agency Inc",
    "wof:placetype":"venue"
},
  "geometry": {"coordinates":[-106.02163299999999,33.072861],"type":"Point"}
}