{
  "type": "Feature",
  "properties": {
    "iso:country":"US",
    "sg:address":"499 Apache Loop SW",
    "sg:city":"Rio Rancho",
    "sg:classifiers":[
        {
            "category":"Building & Trades",
            "subcategory":"Landscaping Services",
            "type":"Services"
        }
    ],
    "sg:phone":"+1 505 892 4633",
    "sg:postcode":"87124",
    "sg:province":"NM",
    "sg:tags":[
        "lawn",
        "maintenance",
        "grounds"
    ],
    "wof:name":"Don Biggs Lawn Svc",
    "wof:placetype":"venue"
},
  "geometry": {"coordinates":[-106.746849,35.249407],"type":"Point"}
}