{
  "type": "Feature",
  "properties": {
    "iso:country":"US",
    "sg:address":"832 Frank Maes Ave",
    "sg:city":"Las Cruces",
    "sg:classifiers":[
        {
            "category":"Organizations",
            "subcategory":"Community Association",
            "type":"Services"
        }
    ],
    "sg:phone":"+1 505 524 6740",
    "sg:postcode":"88005",
    "sg:province":"NM",
    "wof:name":"Mesilla Valley Civitan",
    "wof:placetype":"venue"
},
  "geometry": {"coordinates":[-106.783261,32.340341],"type":"Point"}
}