{
  "type": "Feature",
  "properties": {
    "addr:full":"1207 Isleta Blvd SW Albuquerque NM 87105",
    "addr:housenumber":"1207",
    "addr:postcode":"87105",
    "addr:street":"Isleta Blvd Sw",
    "iso:country":"US",
    "sg:address":"1207 Isleta Blvd SW",
    "sg:city":"Albuquerque",
    "sg:classifiers":[
        {
            "category":"Organizations",
            "subcategory":"Religious Organization",
            "type":"Services"
        }
    ],
    "sg:phone":"+1 505 873 7997",
    "sg:postcode":"87105",
    "sg:province":"NM",
    "wof:name":"Ministries Mending Broken Hrt",
    "wof:placetype":"venue"
},
  "geometry": {"coordinates":[-106.67219900000001,35.055523],"type":"Point"}
}