{
  "type": "Feature",
  "properties": {
    "iso:country":"US",
    "sg:address":"310 Bridge Blvd SW",
    "sg:city":"Albuquerque",
    "sg:classifiers":[
        {
            "category":"Retail",
            "subcategory":"Auto Repair",
            "type":"Services"
        }
    ],
    "sg:phone":"+1 505 244 0117",
    "sg:postcode":"87102",
    "sg:province":"NM",
    "sg:tags":[
        "repairing",
        "automobile"
    ],
    "wof:name":"B & D Automotive",
    "wof:placetype":"venue"
},
  "geometry": {"coordinates":[-106.653572,35.069991],"type":"Point"}
}