{
  "type": "Feature",
  "properties": {
    "iso:country":"US",
    "sg:address":"1000 W University Ave",
    "sg:city":"Las Cruces",
    "sg:classifiers":[
        {
            "category":"Professional",
            "subcategory":"Art Services",
            "type":"Services"
        }
    ],
    "sg:phone":"+1 505 526 2583",
    "sg:postcode":"88005",
    "sg:province":"NM",
    "sg:tags":[
        "photography",
        "commercial"
    ],
    "wof:name":"L M Images",
    "wof:placetype":"venue"
},
  "geometry": {"coordinates":[-106.781561,32.275737],"type":"Point"}
}