{
  "type": "Feature",
  "properties": {
    "iso:country":"US",
    "sg:address":"3742 Jade Ave",
    "sg:city":"Las Cruces",
    "sg:classifiers":[
        {
            "category":"Health Services",
            "subcategory":"Clinic",
            "type":"Services"
        }
    ],
    "sg:phone":"+1 505 382 1919",
    "sg:postcode":"88012",
    "sg:province":"NM",
    "wof:name":"Mesilla Valley Practitioners",
    "wof:placetype":"venue"
},
  "geometry": {"coordinates":[-106.745822,32.374126],"type":"Point"}
}