{
  "type": "Feature",
  "properties": {
    "iso:country":"US",
    "sg:address":"1660 Old Pecos Trl",
    "sg:city":"Santa Fe",
    "sg:classifiers":[
        {
            "category":"Wholesale",
            "subcategory":"Machinery & Supplies",
            "type":"Manufacturing & Wholesale Goods"
        }
    ],
    "sg:phone":"+1 505 995 3142",
    "sg:postcode":"87505",
    "sg:province":"NM",
    "sg:tags":[
        "janitor"
    ],
    "wof:name":"Maintenancemart",
    "wof:placetype":"venue"
},
  "geometry": {"coordinates":[-105.938029,35.662353],"type":"Point"}
}