{
  "type": "Feature",
  "properties": {
    "iso:country":"US",
    "sg:address":"117 Bryn Mawr Dr SE",
    "sg:city":"Albuquerque",
    "sg:classifiers":[
        {
            "category":"Professional",
            "subcategory":"Lawyer & Legal Services",
            "type":"Services"
        }
    ],
    "sg:phone":"+1 505 268 8071",
    "sg:postcode":"87106",
    "sg:province":"NM",
    "sg:tags":[
        "attorney"
    ],
    "wof:name":"21st Century Law Office",
    "wof:placetype":"venue"
},
  "geometry": {"coordinates":[-106.609587,35.079297],"type":"Point"}
}