{
  "type": "Feature",
  "properties": {
    "addr:full":"910 E Main St Farmington NM 87401",
    "addr:housenumber":"910",
    "addr:postcode":"87401",
    "addr:street":"E Main St",
    "iso:country":"US",
    "sg:address":"910 E Main St",
    "sg:city":"Farmington",
    "sg:classifiers":[
        {
            "category":"Shopping",
            "subcategory":"Bicycles & Sporting Goods",
            "type":"Retail Goods"
        }
    ],
    "sg:phone":"+1 505 326 1805",
    "sg:postcode":"87401",
    "sg:province":"NM",
    "sg:website":"www.big5sportinggoods.com",
    "wof:name":"Big 5 Sporting Goods",
    "wof:placetype":"venue"
},
  "geometry": {"coordinates":[-108.19762,36.730579],"type":"Point"}
}