{
  "type": "Feature",
  "properties": {
    "iso:country":"US",
    "sg:address":"4501 N Main St",
    "sg:city":"Roswell",
    "sg:classifiers":[
        {
            "category":"Shopping",
            "subcategory":"Computers & Home Electronics",
            "type":"Retail Goods"
        }
    ],
    "sg:phone":"+1 505 622 9070",
    "sg:postcode":"88201",
    "sg:province":"NM",
    "sg:tags":[
        "equipment",
        "satellite",
        "system"
    ],
    "wof:name":"Cosmic Satellite Television",
    "wof:placetype":"venue"
},
  "geometry": {"coordinates":[-104.52314800000001,33.45034],"type":"Point"}
}