{
  "type": "Feature",
  "properties": {
    "iso:country":"US",
    "sg:address":"7442 Riverside Loop",
    "sg:city":"Santa Fe",
    "sg:classifiers":[
        {
            "category":"Wholesale",
            "subcategory":"Construction Materials",
            "type":"Manufacturing & Wholesale Goods"
        }
    ],
    "sg:phone":"+1 505 660 9377",
    "sg:postcode":"87507",
    "sg:province":"NM",
    "sg:tags":[
        "granite"
    ],
    "wof:name":"Rocky Top Stones",
    "wof:placetype":"venue"
},
  "geometry": {"coordinates":[-106.06315600000001,35.637023],"type":"Point"}
}