{
  "type": "Feature",
  "properties": {
    "addr:full":"8807 Cottonwood Rd NE Albuquerque NM 87111",
    "addr:housenumber":"8807",
    "addr:postcode":"87111",
    "addr:street":"Cottonwood Rd Ne",
    "iso:country":"US",
    "sg:address":"8807 Cottonwood Rd NE",
    "sg:city":"Albuquerque",
    "sg:classifiers":[
        {
            "category":"Health Services",
            "subcategory":"Doctor",
            "type":"Services"
        }
    ],
    "sg:phone":"+1 505 248 4000",
    "sg:postcode":"87111",
    "sg:province":"NM",
    "sg:tags":[
        "physician",
        "surgeon"
    ],
    "wof:name":"Indian Health Srv",
    "wof:placetype":"venue"
},
  "geometry": {"coordinates":[-106.54566199999999,35.118938],"type":"Point"}
}