{
  "type": "Feature",
  "properties": {
    "iso:country":"US",
    "sg:address":"2904 Wallace St",
    "sg:city":"Clovis",
    "sg:classifiers":[
        {
            "category":"Personal",
            "type":"Services"
        }
    ],
    "sg:phone":"+1 505 762 0392",
    "sg:postcode":"88101",
    "sg:province":"NM",
    "sg:tags":[
        "general",
        "contraction"
    ],
    "wof:name":"Herman Renovations",
    "wof:placetype":"venue"
},
  "geometry": {"coordinates":[-103.20037600000001,34.427663],"type":"Point"}
}