{
  "type": "Feature",
  "properties": {
    "addr:full":"12417 Placid Ave NE Albuquerque NM 87112",
    "addr:housenumber":"12417",
    "addr:postcode":"87112",
    "addr:street":"Placid Ave Ne",
    "iso:country":"US",
    "sg:address":"12417 Placid Ave NE",
    "sg:city":"Albuquerque",
    "sg:classifiers":[
        {
            "category":"Social Services",
            "subcategory":"Child Care",
            "type":"Services"
        }
    ],
    "sg:phone":"+1 505 298 1697",
    "sg:postcode":"87112",
    "sg:province":"NM",
    "sg:tags":[
        "day"
    ],
    "wof:name":"In Good Hands Home Preschool",
    "wof:placetype":"venue"
},
  "geometry": {"coordinates":[-106.503846,35.102566],"type":"Point"}
}