{
  "type": "Feature",
  "properties": {
    "addr:full":"8500 Menaul Blvd NE Albuquerque NM 87112",
    "addr:housenumber":"8500",
    "addr:postcode":"87112",
    "addr:street":"Menaul Blvd Ne",
    "iso:country":"US",
    "sg:address":"8500 Menaul Blvd NE",
    "sg:city":"Albuquerque",
    "sg:classifiers":[
        {
            "category":"Professional",
            "subcategory":"Accounting & Tax Preparation",
            "type":"Services"
        }
    ],
    "sg:phone":"+1 505 293 3322",
    "sg:postcode":"87112",
    "sg:province":"NM",
    "sg:tags":[
        "payroll"
    ],
    "sg:website":"www.paychex.com",
    "wof:name":"Paychex Inc",
    "wof:placetype":"venue"
},
  "geometry": {"coordinates":[-106.549418,35.109166],"type":"Point"}
}