{
  "type": "Feature",
  "properties": {
    "iso:country":"US",
    "sg:address":"9601 Trumbull Ave SE",
    "sg:city":"Albuquerque",
    "sg:classifiers":[
        {
            "category":"Manufacturing",
            "subcategory":"Retail Goods",
            "type":"Manufacturing & Wholesale Goods"
        }
    ],
    "sg:phone":"+1 505 271 1184",
    "sg:postcode":"87123",
    "sg:province":"NM",
    "sg:tags":[
        "manufacturer"
    ],
    "wof:name":"Your Mailsafe",
    "wof:placetype":"venue"
},
  "geometry": {"coordinates":[-106.53947100000001,35.068912],"type":"Point"}
}