{
  "type": "Feature",
  "properties": {
    "iso:country":"US",
    "sg:address":"3335 Columbus Rd",
    "sg:city":"Deming",
    "sg:classifiers":[
        {
            "category":"Wholesale",
            "subcategory":"Farm Supplies",
            "type":"Manufacturing & Wholesale Goods"
        }
    ],
    "sg:phone":"+1 505 544 3296",
    "sg:postcode":"88030",
    "sg:province":"NM",
    "sg:tags":[
        "equipment",
        "livestock"
    ],
    "wof:name":"J Bucket Tractors & Equipment",
    "wof:placetype":"venue"
},
  "geometry": {"coordinates":[-107.75138,32.233759],"type":"Point"}
}