{
  "type": "Feature",
  "properties": {
    "iso:country":"US",
    "sg:address":"586 Clayton Rd",
    "sg:city":"Raton",
    "sg:classifiers":[
        {
            "category":"Professional",
            "type":"Services"
        }
    ],
    "sg:phone":"+1 505 445 2471",
    "sg:postcode":"87740",
    "sg:province":"NM",
    "sg:tags":[
        "establishment"
    ],
    "wof:name":"Transceiver United",
    "wof:placetype":"venue"
},
  "geometry": {"coordinates":[-104.432547,36.88504],"type":"Point"}
}