{
  "type": "Feature",
  "properties": {
    "addr:full":"6116 Mossman Pl NE Albuquerque NM 87110",
    "addr:housenumber":"6116",
    "addr:postcode":"87110",
    "addr:street":"Mossman Pl Ne",
    "iso:country":"US",
    "sg:address":"6116 Mossman Pl NE",
    "sg:city":"Albuquerque",
    "sg:classifiers":[
        {
            "category":"Professional",
            "subcategory":"Lawyer & Legal Services",
            "type":"Services"
        }
    ],
    "sg:phone":"+1 505 830 1143",
    "sg:postcode":"87110",
    "sg:province":"NM",
    "sg:tags":[
        "business"
    ],
    "wof:name":"Tribble & Assoc",
    "wof:placetype":"venue"
},
  "geometry": {"coordinates":[-106.576183,35.125064],"type":"Point"}
}