{
  "type": "Feature",
  "properties": {
    "iso:country":"US",
    "sg:address":"1004 Ivydale Dr",
    "sg:city":"Las Cruces",
    "sg:classifiers":[
        {
            "category":"Arts & Performance",
            "subcategory":"Theater",
            "type":"Entertainment"
        }
    ],
    "sg:phone":"+1 505 649 3228",
    "sg:postcode":"88005",
    "sg:province":"NM",
    "sg:tags":[
        "live",
        "music"
    ],
    "wof:name":"Mobile Entertainment Systems",
    "wof:placetype":"venue"
},
  "geometry": {"coordinates":[-106.779655,32.348229],"type":"Point"}
}