{
  "type": "Feature",
  "properties": {
    "iso:country":"US",
    "sg:address":"4196 State Hwy 528 NE",
    "sg:city":"Rio Rancho",
    "sg:classifiers":[
        {
            "category":"Restaurant",
            "type":"Food & Drink"
        }
    ],
    "sg:phone":"+1 505 771 2020",
    "sg:postcode":"87144",
    "sg:province":"NM",
    "sg:tags":[
        "pizza"
    ],
    "wof:name":"Domino's Pizza",
    "wof:placetype":"venue"
},
  "geometry": {"coordinates":[-106.572208,35.328436],"type":"Point"}
}