{
  "type": "Feature",
  "properties": {
    "addr:full":"10501 Research Rd SE Albuquerque NM 87123",
    "addr:housenumber":"10501",
    "addr:postcode":"87123",
    "addr:street":"Research Rd Se",
    "iso:country":"US",
    "sg:address":"10501 Research Rd SE",
    "sg:city":"Albuquerque",
    "sg:classifiers":[
        {
            "category":"Professional",
            "type":"Services"
        }
    ],
    "sg:phone":"+1 505 923 1881",
    "sg:postcode":"87123",
    "sg:province":"NM",
    "sg:tags":[
        "scientist"
    ],
    "sg:website":"www.battelle.org",
    "wof:name":"Battelle Memorial Institute",
    "wof:placetype":"venue"
},
  "geometry": {"coordinates":[-106.53157299999999,35.055484],"type":"Point"}
}