{
  "type": "Feature",
  "properties": {
    "iso:country":"US",
    "sg:address":"4735 Quay Rd E",
    "sg:city":"Mc Alister",
    "sg:phone":"+1 505 458 6491",
    "sg:postcode":"88426",
    "sg:province":"NM",
    "sg:tags":[
        "farm",
        "ranch",
        "wheat",
        "cattle"
    ],
    "wof:name":"Akin & Akin Inc",
    "wof:placetype":"venue"
},
  "geometry": {"coordinates":[-103.095972,35.602816],"type":"Point"}
}