{
  "type": "Feature",
  "properties": {
    "iso:country":"US",
    "sg:address":"101 W Panther Ave",
    "sg:city":"Jal",
    "sg:classifiers":[
        {
            "category":"Health Services",
            "subcategory":"Doctor",
            "type":"Services"
        }
    ],
    "sg:phone":"+1 505 395 3400",
    "sg:postcode":"88252",
    "sg:province":"NM",
    "sg:tags":[
        "physician",
        "surgeon"
    ],
    "wof:name":"Jal Clinic",
    "wof:placetype":"venue"
},
  "geometry": {"coordinates":[-103.193896,32.110895],"type":"Point"}
}