{
  "type": "Feature",
  "properties": {
    "iso:country":"US",
    "sg:address":"514 Morris St NE",
    "sg:city":"Albuquerque",
    "sg:classifiers":[
        {
            "category":"Manufacturing",
            "subcategory":"Jewelry",
            "type":"Manufacturing & Wholesale Goods"
        }
    ],
    "sg:phone":"+1 505 294 3891",
    "sg:postcode":"87123",
    "sg:province":"NM",
    "sg:tags":[
        "costume",
        "mfg"
    ],
    "wof:name":"Zuni Custom Design",
    "wof:placetype":"venue"
},
  "geometry": {"coordinates":[-106.523748,35.076108],"type":"Point"}
}