{
  "type": "Feature",
  "properties": {
    "iso:country":"US",
    "sg:address":"725 Canyon Rd",
    "sg:city":"Santa Fe",
    "sg:classifiers":[
        {
            "category":"Shopping",
            "subcategory":"Luggage & Leather Goods",
            "type":"Retail Goods"
        }
    ],
    "sg:phone":"+1 505 982 9499",
    "sg:postcode":"87501",
    "sg:province":"NM",
    "wof:name":"Desert Son Leathersmiths",
    "wof:placetype":"venue"
},
  "geometry": {"coordinates":[-105.926897,35.681234],"type":"Point"}
}