{
  "type": "Feature",
  "properties": {
    "iso:country":"US",
    "sg:address":"1512 37th St SE",
    "sg:city":"Rio Rancho",
    "sg:classifiers":[
        {
            "category":"Professional",
            "subcategory":"Accounting & Tax Preparation",
            "type":"Services"
        }
    ],
    "sg:phone":"+1 505 892 0012",
    "sg:postcode":"87124",
    "sg:province":"NM",
    "sg:tags":[
        "return"
    ],
    "wof:name":"Financial Services Unlimited",
    "wof:placetype":"venue"
},
  "geometry": {"coordinates":[-106.663177,35.229969],"type":"Point"}
}