{
  "type": "Feature",
  "properties": {
    "iso:country":"US",
    "sg:address":"1489 S Main St",
    "sg:city":"Belen",
    "sg:classifiers":[
        {
            "category":"Retail",
            "subcategory":"Auto Repair",
            "type":"Services"
        }
    ],
    "sg:phone":"+1 505 864 7533",
    "sg:postcode":"87002",
    "sg:province":"NM",
    "wof:name":"Texaco",
    "wof:placetype":"venue"
},
  "geometry": {"coordinates":[-106.780783,34.638627],"type":"Point"}
}