{
  "type": "Feature",
  "properties": {
    "iso:country":"US",
    "sg:address":"510 Central Ave SE",
    "sg:city":"Albuquerque",
    "sg:classifiers":[
        {
            "category":"Bars & Pubs",
            "subcategory":"Wine Bar",
            "type":"Food & Drink"
        }
    ],
    "sg:menulink":"http://www.allmenus.com/nm/albuquerque/283394-farina-pizzeria--wine-bar/menu/",
    "sg:phone":"+1 505 243 0200",
    "sg:postcode":"87102",
    "sg:province":"NM",
    "sg:tags":[
        "american",
        "pizza"
    ],
    "wof:name":"Farina Pizzeria & Wine Bar",
    "wof:placetype":"venue"
},
  "geometry": {"coordinates":[-106.64188300000001,35.083126],"type":"Point"}
}