{
  "type": "Feature",
  "properties": {
    "addr:full":"13 Ave A Hachita NM 88040",
    "addr:postcode":"88040",
    "addr:street":"13 Ave A Hachita",
    "iso:country":"US",
    "sg:address":"13 Ave A",
    "sg:city":"Hachita",
    "sg:classifiers":[
        {
            "category":"Shopping",
            "type":"Retail Goods"
        }
    ],
    "sg:phone":"+1 505 436 2488",
    "sg:postcode":"88040",
    "sg:province":"NM",
    "sg:tags":[
        "lifting",
        "devices",
        "invalid"
    ],
    "wof:name":"Medical Lifting Devices Inc",
    "wof:placetype":"venue"
},
  "geometry": {"coordinates":[-108.319524,31.916802],"type":"Point"}
}