{
  "type": "Feature",
  "properties": {
    "addr:full":"8725 Broadway Blvd SE Albuquerque NM 87105",
    "addr:housenumber":"8725",
    "addr:postcode":"87105",
    "addr:street":"Broadway Blvd Se",
    "iso:country":"US",
    "sg:address":"8725 Broadway Blvd SE",
    "sg:city":"Albuquerque",
    "sg:classifiers":[
        {
            "category":"Freight",
            "type":"Transportation"
        }
    ],
    "sg:phone":"+1 505 873 4791",
    "sg:postcode":"87105",
    "sg:province":"NM",
    "sg:tags":[
        "operator",
        "trucking"
    ],
    "sg:website":"www.watkins.com",
    "wof:name":"Watkins Motor Lines Inc",
    "wof:placetype":"venue"
},
  "geometry": {"coordinates":[-106.66061500000001,34.961514],"type":"Point"}
}