{
  "type": "Feature",
  "properties": {
    "iso:country":"US",
    "sg:address":"606 Canyon Rd",
    "sg:city":"Santa Fe",
    "sg:classifiers":[
        {
            "category":"Education",
            "subcategory":"Dance Studio",
            "type":"Public Place"
        },
        {
            "category":"Professional",
            "type":"Services"
        }
    ],
    "sg:phone":"+1 505 989 8419",
    "sg:postcode":"87501",
    "sg:province":"NM",
    "sg:tags":[
        "arts",
        "artist"
    ],
    "wof:name":"Douglas Atwill Studio",
    "wof:placetype":"venue"
},
  "geometry": {"coordinates":[-105.929644,35.682012],"type":"Point"}
}