{
  "type": "Feature",
  "properties": {
    "iso:country":"US",
    "sg:address":"1304 Schofield Ln",
    "sg:city":"Farmington",
    "sg:classifiers":[
        {
            "category":"Professional",
            "subcategory":"Business Services",
            "type":"Services"
        }
    ],
    "sg:phone":"+1 505 325 2111",
    "sg:postcode":"87401",
    "sg:province":"NM",
    "wof:name":"C&S Sales & Service",
    "wof:placetype":"venue"
},
  "geometry": {"coordinates":[-108.181921,36.743078],"type":"Point"}
}