{
  "type": "Feature",
  "properties": {
    "addr:full":"1601 Pablo Ct NE Albuquerque NM 87112",
    "addr:housenumber":"1601",
    "addr:postcode":"87112",
    "addr:street":"Pablo Ct Ne",
    "iso:country":"US",
    "sg:address":"1601 Pablo Ct NE",
    "sg:city":"Albuquerque",
    "sg:classifiers":[
        {
            "category":"Communications",
            "type":"Services"
        }
    ],
    "sg:phone":"+1 505 247 3182",
    "sg:postcode":"87112",
    "sg:province":"NM",
    "wof:name":"Common Bond Communications Inc",
    "wof:placetype":"venue"
},
  "geometry": {"coordinates":[-106.49499400000001,35.097913],"type":"Point"}
}