{
  "type": "Feature",
  "properties": {
    "iso:country":"US",
    "sg:address":"11001 Spain Rd NE Ste A",
    "sg:city":"Albuquerque",
    "sg:classifiers":[
        {
            "category":"Health Services",
            "subcategory":"Doctor",
            "type":"Services"
        },
        {
            "category":"Health Services",
            "subcategory":"Dentist",
            "type":"Services"
        }
    ],
    "sg:phone":"+1 505 293 1687",
    "sg:postcode":"87111",
    "sg:province":"NM",
    "sg:tags":[
        "dentists-oral",
        "physician",
        "maxillofacial",
        "surgeons",
        "surgery",
        "oral"
    ],
    "sg:website":"http://www.pricelesssmiles.com",
    "wof:name":"Reuben A Jamharian",
    "wof:placetype":"venue"
},
  "geometry": {"coordinates":[-106.517349,35.141941],"type":"Point"}
}