{
  "type": "Feature",
  "properties": {
    "addr:full":"1200 New York Ave Alamogordo NM 88310",
    "addr:housenumber":"1200",
    "addr:postcode":"88310",
    "addr:street":"New York Ave",
    "iso:country":"US",
    "sg:address":"1200 New York Ave",
    "sg:city":"Alamogordo",
    "sg:classifiers":[
        {
            "category":"Banks & Credit Unions",
            "subcategory":"Investment Brokerage",
            "type":"Services"
        }
    ],
    "sg:phone":"+1 505 434 5850",
    "sg:postcode":"88310",
    "sg:province":"NM",
    "sg:tags":[
        "stock",
        "bond"
    ],
    "wof:name":"Edward Jones Co",
    "wof:placetype":"venue"
},
  "geometry": {"coordinates":[-105.959034,32.903487],"type":"Point"}
}