{
  "type": "Feature",
  "properties": {
    "iso:country":"US",
    "sg:address":"916 E Amador Ave",
    "sg:city":"Las Cruces",
    "sg:classifiers":[
        {
            "category":"Manufacturing",
            "subcategory":"Food",
            "type":"Manufacturing & Wholesale Goods"
        }
    ],
    "sg:phone":"+1 505 526 8351",
    "sg:postcode":"88001",
    "sg:province":"NM",
    "sg:tags":[
        "preparation",
        "mfg"
    ],
    "wof:name":"Robertos Mexican Food",
    "wof:placetype":"venue"
},
  "geometry": {"coordinates":[-106.76903299999999,32.308897],"type":"Point"}
}