{
  "type": "Feature",
  "properties": {
    "iso:country":"US",
    "sg:address":"501 Main St NW",
    "sg:city":"Albuquerque",
    "sg:classifiers":[
        {
            "category":"Social Services",
            "type":"Services"
        }
    ],
    "sg:phone":"+1 505 247 1553",
    "sg:postcode":"87104",
    "sg:province":"NM",
    "wof:name":"Boys Girls Clubs Albuquerque",
    "wof:placetype":"venue"
},
  "geometry": {"coordinates":[-106.67123100000001,35.098695],"type":"Point"}
}