{
  "type": "Feature",
  "properties": {
    "addr:full":"603 Barnett Dr Roswell NM 88203",
    "addr:housenumber":"603",
    "addr:postcode":"88203",
    "addr:street":"Barnett Dr",
    "iso:country":"US",
    "sg:address":"603 Barnett Dr",
    "sg:city":"Roswell",
    "sg:classifiers":[
        {
            "category":"Building & Trades",
            "subcategory":"Construction",
            "type":"Services"
        }
    ],
    "sg:phone":"+1 505 623 6126",
    "sg:postcode":"88203",
    "sg:province":"NM",
    "sg:tags":[
        "commercial",
        "sub",
        "contractor"
    ],
    "wof:name":"Nationwide Deck Applicator",
    "wof:placetype":"venue"
},
  "geometry": {"coordinates":[-104.530675,33.362373],"type":"Point"}
}