{
  "type": "Feature",
  "properties": {
    "addr:full":"2182 N Main St Las Cruces NM 88001",
    "addr:housenumber":"2182",
    "addr:postcode":"88001",
    "addr:street":"N Main St",
    "iso:country":"US",
    "sg:address":"2182 N Main St",
    "sg:city":"Las Cruces",
    "sg:classifiers":[
        {
            "category":"Personal",
            "type":"Services"
        },
        {
            "category":"Shopping",
            "subcategory":"Clothing, Apparel, & Fashions",
            "type":"Retail Goods"
        }
    ],
    "sg:phone":"+1 505 526 5096",
    "sg:postcode":"88001",
    "sg:province":"NM",
    "sg:tags":[
        "man",
        "wear",
        "formal"
    ],
    "wof:name":"S and H Mens Mart",
    "wof:placetype":"venue"
},
  "geometry": {"coordinates":[-106.78335800000001,32.326965],"type":"Point"}
}