{
  "type": "Feature",
  "properties": {
    "iso:country":"US",
    "sg:address":"410 S Sunset Ave",
    "sg:city":"Roswell",
    "sg:classifiers":[
        {
            "category":"Home & Garden",
            "subcategory":"Garden Supply",
            "type":"Retail Goods"
        }
    ],
    "sg:phone":"+1 505 624 2759",
    "sg:postcode":"88203",
    "sg:province":"NM",
    "wof:name":"C & J Nursery & Ldscpg Sups",
    "wof:placetype":"venue"
},
  "geometry": {"coordinates":[-104.541168,33.389743],"type":"Point"}
}