{
  "type": "Feature",
  "properties": {
    "addr:full":"5505 Lomas Blvd NE Albuquerque NM 87110",
    "addr:housenumber":"5505",
    "addr:postcode":"87110",
    "addr:street":"Lomas Blvd Ne",
    "iso:country":"US",
    "sg:address":"5505 Lomas Blvd NE",
    "sg:city":"Albuquerque",
    "sg:classifiers":[
        {
            "category":"Insurance",
            "subcategory":"Insurance Agent",
            "type":"Services"
        },
        {
            "category":"Insurance",
            "subcategory":"Hazard Insurance",
            "type":"Services"
        }
    ],
    "sg:phone":"+1 505 256 8158",
    "sg:postcode":"87110",
    "sg:province":"NM",
    "sg:tags":[
        "auto",
        "recreational",
        "motorcycle",
        "vehicle",
        "marine",
        "boat"
    ],
    "wof:name":"George Gandy Insurance",
    "wof:placetype":"venue"
},
  "geometry": {"coordinates":[-106.58354199999999,35.08746],"type":"Point"}
}