{
  "type": "Feature",
  "properties": {
    "iso:country":"US",
    "sg:address":"4701 Montano Rd NW",
    "sg:city":"Albuquerque",
    "sg:classifiers":[
        {
            "category":"Manufacturing",
            "subcategory":"Tools & Machinery",
            "type":"Manufacturing & Wholesale Goods"
        }
    ],
    "sg:phone":"+1 505 899 2156",
    "sg:postcode":"87120",
    "sg:province":"NM",
    "sg:tags":[
        "electrical",
        "mfg"
    ],
    "wof:name":"Carlberg & Associates",
    "wof:placetype":"venue"
},
  "geometry": {"coordinates":[-106.69160599999999,35.152206],"type":"Point"}
}