{
  "type": "Feature",
  "properties": {
    "iso:country":"US",
    "sg:address":"207 W Coal Ave",
    "sg:city":"Gallup",
    "sg:classifiers":[
        {
            "category":"Government",
            "subcategory":"Office",
            "type":"Public Place"
        }
    ],
    "sg:phone":"+1 505 726 0050",
    "sg:postcode":"87301",
    "sg:province":"NM",
    "sg:tags":[
        "village"
    ],
    "wof:name":"El Morro Theater",
    "wof:placetype":"venue"
},
  "geometry": {"coordinates":[-108.742383,35.527035],"type":"Point"}
}