{
  "type": "Feature",
  "properties": {
    "iso:country":"US",
    "sg:address":"9790 Coors Blvd NW",
    "sg:city":"Albuquerque",
    "sg:classifiers":[
        {
            "category":"Autos & Motor Vehicles",
            "subcategory":"Automobile Sales",
            "type":"Retail Goods"
        }
    ],
    "sg:phone":"+1 505 314 2020",
    "sg:postcode":"87114",
    "sg:province":"NM",
    "sg:tags":[
        "dealers-used",
        "car",
        "used",
        "cars-wholesale",
        "new"
    ],
    "sg:website":"http://www.crosscountryautosales.com",
    "wof:name":"Cross Country Auto Sales Westside",
    "wof:placetype":"venue"
},
  "geometry": {"coordinates":[-106.65740700000001,35.191005],"type":"Point"}
}