{
  "type": "Feature",
  "properties": {
    "iso:country":"US",
    "sg:address":"700 S Telshor Blvd",
    "sg:city":"Las Cruces",
    "sg:classifiers":[
        {
            "category":"Retail",
            "subcategory":"Portrait Studio",
            "type":"Services"
        }
    ],
    "sg:phone":"+1 505 522 1211",
    "sg:postcode":"88011",
    "sg:province":"NM",
    "sg:tags":[
        "photographer"
    ],
    "wof:name":"Star Image Shot",
    "wof:placetype":"venue"
},
  "geometry": {"coordinates":[-106.740977,32.310818],"type":"Point"}
}