{
  "type": "Feature",
  "properties": {
    "addr:full":"12512 Royal Ridge Ct NE Albuquerque NM 87111",
    "addr:housenumber":"12512",
    "addr:postcode":"87111",
    "addr:street":"Royal Ridge Ct Ne",
    "iso:country":"US",
    "sg:address":"12512 Royal Ridge Ct NE",
    "sg:city":"Albuquerque",
    "sg:classifiers":[
        {
            "category":"Education",
            "subcategory":"Special Training",
            "type":"Public Place"
        }
    ],
    "sg:phone":"+1 505 293 7734",
    "sg:postcode":"87111",
    "sg:province":"NM",
    "wof:name":"Janice Dane Huser Tutoring Svc",
    "wof:placetype":"venue"
},
  "geometry": {"coordinates":[-106.499437,35.142945],"type":"Point"}
}