{
  "type": "Feature",
  "properties": {
    "addr:full":"1814 Broadway Blvd SE Albuquerque NM 87102",
    "addr:housenumber":"1814",
    "addr:postcode":"87102",
    "addr:street":"Broadway Blvd Se",
    "iso:country":"US",
    "sg:address":"1814 Broadway Blvd SE",
    "sg:city":"Albuquerque",
    "sg:classifiers":[
        {
            "category":"Shopping",
            "type":"Retail Goods"
        }
    ],
    "sg:phone":"+1 505 842 8446",
    "sg:postcode":"87102",
    "sg:province":"NM",
    "sg:tags":[
        "art",
        "gallery",
        "dealer"
    ],
    "wof:name":"Curioso Obscura",
    "wof:placetype":"venue"
},
  "geometry": {"coordinates":[-106.645275,35.063082],"type":"Point"}
}