{
  "type": "Feature",
  "properties": {
    "iso:country":"US",
    "sg:address":"721 5th St",
    "sg:city":"Las Vegas",
    "sg:classifiers":[
        {
            "category":"Health Services",
            "subcategory":"Doctor",
            "type":"Services"
        }
    ],
    "sg:phone":"+1 505 425 1533",
    "sg:postcode":"87701",
    "sg:province":"NM",
    "sg:tags":[
        "physician",
        "surgeon"
    ],
    "wof:name":"Internal Medicine & Psychiatry",
    "wof:placetype":"venue"
},
  "geometry": {"coordinates":[-105.215173,35.597213],"type":"Point"}
}