{
  "type": "Feature",
  "properties": {
    "addr:full":"3956 State Rte 68 Ranchos De Taos NM 87557",
    "addr:housenumber":"3956",
    "addr:postcode":"87557",
    "addr:street":"State Rte 68",
    "iso:country":"US",
    "sg:address":"3956 State Rte 68",
    "sg:city":"Ranchos De Taos",
    "sg:classifiers":[
        {
            "category":"Manufacturing",
            "subcategory":"Musical Instruments",
            "type":"Manufacturing & Wholesale Goods"
        }
    ],
    "sg:phone":"+1 505 758 3796",
    "sg:postcode":"87557",
    "sg:province":"NM",
    "sg:website":"www.taosdrums.com",
    "wof:name":"Taos Drum Co",
    "wof:placetype":"venue"
},
  "geometry": {"coordinates":[-105.636196,36.347232],"type":"Point"}
}