{
  "type": "Feature",
  "properties": {
    "iso:country":"US",
    "sg:address":"737 Williams Dr",
    "sg:city":"Las Vegas",
    "sg:classifiers":[
        {
            "category":"Home & Garden",
            "subcategory":"Building Materials",
            "type":"Retail Goods"
        }
    ],
    "sg:phone":"+1 505 429 9596",
    "sg:postcode":"87701",
    "sg:province":"NM",
    "sg:tags":[
        "door"
    ],
    "wof:name":"A & C Garage Doors & Openers",
    "wof:placetype":"venue"
},
  "geometry": {"coordinates":[-105.233291,35.622783],"type":"Point"}
}