{
  "type": "Feature",
  "properties": {
    "iso:country":"US",
    "sg:address":"1380 Rio Rancho Dr SE",
    "sg:city":"Rio Rancho",
    "sg:classifiers":[
        {
            "category":"Organizations",
            "subcategory":"Political Organization",
            "type":"Services"
        }
    ],
    "sg:phone":"+1 505 891 4541",
    "sg:postcode":"87124",
    "sg:province":"NM",
    "wof:name":"Libertarion Party New Mexico",
    "wof:placetype":"venue"
},
  "geometry": {"coordinates":[-106.65723,35.236798],"type":"Point"}
}