{
  "type": "Feature",
  "properties": {
    "iso:country":"US",
    "sg:address":"1757 Allegheny Dr NE",
    "sg:city":"Rio Rancho",
    "sg:classifiers":[
        {
            "category":"Utilities",
            "type":"Services"
        }
    ],
    "sg:phone":"+1 505 344 8191",
    "sg:postcode":"87144",
    "sg:province":"NM",
    "sg:tags":[
        "sweeping"
    ],
    "wof:name":"Roadrunner Sweeping Inc",
    "wof:placetype":"venue"
},
  "geometry": {"coordinates":[-106.60088399999999,35.28946],"type":"Point"}
}