{
  "type": "Feature",
  "properties": {
    "iso:country":"US",
    "sg:address":"1721 Girard Blvd NE",
    "sg:city":"Albuquerque",
    "sg:classifiers":[
        {
            "category":"Banks & Credit Unions",
            "subcategory":"Bank",
            "type":"Services"
        }
    ],
    "sg:phone":"+1 505 262 1624",
    "sg:postcode":"87106",
    "sg:province":"NM",
    "sg:tags":[
        "escrow"
    ],
    "sg:website":"www.securityescrow.com",
    "wof:name":"Real Estate Law Associates",
    "wof:placetype":"venue"
},
  "geometry": {"coordinates":[-106.613952,35.10323],"type":"Point"}
}