{
  "type": "Feature",
  "properties": {
    "iso:country":"US",
    "sg:address":"3307 N Main St",
    "sg:city":"Roswell",
    "sg:classifiers":[
        {
            "category":"Travel",
            "subcategory":"Hotels & Motels",
            "type":"Entertainment"
        }
    ],
    "sg:phone":"+1 505 625 6666",
    "sg:postcode":"88201",
    "sg:province":"NM",
    "wof:name":"Motel 6",
    "wof:placetype":"venue"
},
  "geometry": {"coordinates":[-104.52315400000001,33.440907],"type":"Point"}
}