{
  "type": "Feature",
  "properties": {
    "addr:full":"4985 Airport Rd Santa Fe NM 87507",
    "addr:housenumber":"4985",
    "addr:postcode":"87507",
    "addr:street":"Airport Rd",
    "iso:country":"US",
    "sg:address":"4985 Airport Rd",
    "sg:city":"Santa Fe",
    "sg:classifiers":[
        {
            "category":"Social Services",
            "type":"Services"
        }
    ],
    "sg:phone":"+1 505 424 9789",
    "sg:postcode":"87507",
    "sg:province":"NM",
    "sg:tags":[
        "organization",
        "welfare"
    ],
    "wof:name":"Catholic Charities-Santa Fe",
    "wof:placetype":"venue"
},
  "geometry": {"coordinates":[-106.06497899999999,35.633095],"type":"Point"}
}