{
  "type": "Feature",
  "properties": {
    "iso:country":"US",
    "sg:address":"1009 W Apache St",
    "sg:city":"Farmington",
    "sg:classifiers":[
        {
            "category":"Home & Garden",
            "subcategory":"Building Materials",
            "type":"Retail Goods"
        }
    ],
    "sg:phone":"+1 505 327 6991",
    "sg:postcode":"87401",
    "sg:province":"NM",
    "sg:tags":[
        "door"
    ],
    "wof:name":"Beaver Overhead Door Co",
    "wof:placetype":"venue"
},
  "geometry": {"coordinates":[-108.222705,36.733842],"type":"Point"}
}