{
  "type": "Feature",
  "properties": {
    "addr:full":"3429 NW County Rd Hobbs NM 88240",
    "addr:housenumber":"3429",
    "addr:postcode":"88240",
    "addr:street":"Nw County Rd",
    "iso:country":"US",
    "sg:address":"3429 NW County Rd",
    "sg:city":"Hobbs",
    "sg:classifiers":[
        {
            "category":"Freight",
            "type":"Transportation"
        }
    ],
    "sg:phone":"+1 505 397 1449",
    "sg:postcode":"88240",
    "sg:province":"NM",
    "sg:tags":[
        "trucking"
    ],
    "wof:name":"Wilbanks Trucking Inc",
    "wof:placetype":"venue"
},
  "geometry": {"coordinates":[-103.170469,32.733965],"type":"Point"}
}