{
  "type": "Feature",
  "properties": {
    "addr:full":"2301 Northglen Dr Clovis NM 88101",
    "addr:housenumber":"2301",
    "addr:postcode":"88101",
    "addr:street":"Northglen Dr",
    "iso:country":"US",
    "sg:address":"2301 Northglen Dr",
    "sg:city":"Clovis",
    "sg:classifiers":[
        {
            "category":"Manufacturing",
            "subcategory":"Printing",
            "type":"Manufacturing & Wholesale Goods"
        }
    ],
    "sg:phone":"+1 505 742 2134",
    "sg:postcode":"88101",
    "sg:province":"NM",
    "sg:tags":[
        "publishing"
    ],
    "sg:website":"www.hear-hear.com",
    "wof:name":"Burch Media Inc",
    "wof:placetype":"venue"
},
  "geometry": {"coordinates":[-103.17287,34.428868],"type":"Point"}
}