{
  "type": "Feature",
  "properties": {
    "iso:country":"US",
    "sg:address":"901 W San Mateo Rd",
    "sg:city":"Santa Fe",
    "sg:classifiers":[
        {
            "category":"Manufacturing",
            "subcategory":"Food",
            "type":"Manufacturing & Wholesale Goods"
        }
    ],
    "sg:phone":"+1 505 989 4500",
    "sg:postcode":"87505",
    "sg:province":"NM",
    "sg:tags":[
        "product",
        "manufacturer"
    ],
    "wof:name":"Tamale Molly",
    "wof:placetype":"venue"
},
  "geometry": {"coordinates":[-105.964765,35.662221],"type":"Point"}
}