{
  "type": "Feature",
  "properties": {
    "iso:country":"US",
    "sg:address":"5010 Loma Alto Dr",
    "sg:city":"Farmington",
    "sg:classifiers":[
        {
            "category":"Building & Trades",
            "subcategory":"Construction",
            "type":"Services"
        }
    ],
    "sg:phone":"+1 505 327 5305",
    "sg:postcode":"87402",
    "sg:province":"NM",
    "sg:tags":[
        "carpentry",
        "contractor"
    ],
    "wof:name":"Kremp Quality Carpentry",
    "wof:placetype":"venue"
},
  "geometry": {"coordinates":[-108.146283,36.764573],"type":"Point"}
}