{
  "type": "Feature",
  "properties": {
    "addr:full":"710 N Turner St Hobbs NM 88240",
    "addr:housenumber":"710",
    "addr:postcode":"88240",
    "addr:street":"N Turner St",
    "iso:country":"US",
    "sg:address":"710 N Turner St",
    "sg:city":"Hobbs",
    "sg:classifiers":[
        {
            "category":"Personal",
            "subcategory":"Shoe Repair & Shine",
            "type":"Services"
        }
    ],
    "sg:phone":"+1 505 393 6583",
    "sg:postcode":"88240",
    "sg:province":"NM",
    "sg:tags":[
        "repairing",
        "parlor",
        "boot",
        "shoes"
    ],
    "wof:name":"Dean's Boot Shop",
    "wof:placetype":"venue"
},
  "geometry": {"coordinates":[-103.136143,32.708031],"type":"Point"}
}