{
  "type": "Feature",
  "properties": {
    "addr:full":"101 Bent St Taos NM 87571",
    "addr:housenumber":"101",
    "addr:postcode":"87571",
    "addr:street":"Bent St",
    "iso:country":"US",
    "sg:address":"101 Bent St",
    "sg:city":"Taos",
    "sg:classifiers":[
        {
            "category":"Shopping",
            "type":"Retail Goods"
        }
    ],
    "sg:phone":"+1 505 758 3561",
    "sg:postcode":"87571",
    "sg:province":"NM",
    "sg:tags":[
        "art",
        "gallery",
        "dealer"
    ],
    "wof:name":"Taos Blue",
    "wof:placetype":"venue"
},
  "geometry": {"coordinates":[-105.573196,36.408376],"type":"Point"}
}