{
  "type": "Feature",
  "properties": {
    "iso:country":"US",
    "sg:address":"1300 W Main St",
    "sg:city":"Farmington",
    "sg:classifiers":[
        {
            "category":"Home & Garden",
            "subcategory":"Building Materials",
            "type":"Retail Goods"
        }
    ],
    "sg:phone":"+1 505 324 8805",
    "sg:postcode":"87401",
    "sg:province":"NM",
    "wof:name":"Palm Harbor Village",
    "wof:placetype":"venue"
},
  "geometry": {"coordinates":[-108.224863,36.730226],"type":"Point"}
}