{
  "type": "Feature",
  "properties": {
    "iso:country":"US",
    "sg:address":"6149 Edith Blvd NE",
    "sg:city":"Albuquerque",
    "sg:classifiers":[
        {
            "category":"Building & Trades",
            "subcategory":"Construction",
            "type":"Services"
        }
    ],
    "sg:phone":"+1 505 345 4700",
    "sg:postcode":"87107",
    "sg:province":"NM",
    "sg:tags":[
        "roofing",
        "contractor"
    ],
    "wof:name":"High Country Roofing",
    "wof:placetype":"venue"
},
  "geometry": {"coordinates":[-106.625095,35.146863],"type":"Point"}
}