{
  "type": "Feature",
  "properties": {
    "iso:country":"US",
    "sg:address":"5817 Central Ave NW",
    "sg:city":"Albuquerque",
    "sg:classifiers":[
        {
            "category":"Health Services",
            "subcategory":"Clinic",
            "type":"Services"
        }
    ],
    "sg:phone":"+1 505 831 7815",
    "sg:postcode":"87105",
    "sg:province":"NM",
    "wof:name":"Health Care For The Homeless",
    "wof:placetype":"venue"
},
  "geometry": {"coordinates":[-106.702471,35.081857],"type":"Point"}
}