{
  "type": "Feature",
  "properties": {
    "iso:country":"US",
    "sg:address":"1504 N McCurdy Rd",
    "sg:city":"Espanola",
    "sg:classifiers":[
        {
            "category":"Building & Trades",
            "subcategory":"Electrical",
            "type":"Services"
        }
    ],
    "sg:phone":"+1 505 920 2180",
    "sg:postcode":"87532",
    "sg:province":"NM",
    "sg:tags":[
        "electrical",
        "electric",
        "contractor"
    ],
    "wof:name":"Northern Power & Lighting",
    "wof:placetype":"venue"
},
  "geometry": {"coordinates":[-106.057869,36.020196],"type":"Point"}
}