{
  "type": "Feature",
  "properties": {
    "addr:full":"1509 N Pso de Onate Espanola NM 87532",
    "addr:housenumber":"1509",
    "addr:postcode":"87532",
    "addr:street":"N Pso De Onate",
    "iso:country":"US",
    "sg:address":"1509 N Pso de Onate",
    "sg:city":"Espanola",
    "sg:classifiers":[
        {
            "category":"Retail",
            "subcategory":"Repair Shop",
            "type":"Services"
        }
    ],
    "sg:phone":"+1 505 753 5088",
    "sg:postcode":"87532",
    "sg:province":"NM",
    "sg:tags":[
        "taxidermist"
    ],
    "wof:name":"Sierra Taxidermy LLC",
    "wof:placetype":"venue"
},
  "geometry": {"coordinates":[-106.08970100000001,36.015451],"type":"Point"}
}