{
  "type": "Feature",
  "properties": {
    "addr:full":"2670 Coors Blvd SW Albuquerque NM 87121",
    "addr:housenumber":"2670",
    "addr:postcode":"87121",
    "addr:street":"Coors Blvd Sw",
    "iso:country":"US",
    "sg:address":"2670 Coors Blvd SW",
    "sg:city":"Albuquerque",
    "sg:classifiers":[
        {
            "category":"Restaurant",
            "type":"Food & Drink"
        }
    ],
    "sg:phone":"+1 505 352 2777",
    "sg:postcode":"87121",
    "sg:province":"NM",
    "sg:tags":[
        "eating"
    ],
    "wof:name":"Blimpie",
    "wof:placetype":"venue"
},
  "geometry": {"coordinates":[-106.71205999999999,35.037689],"type":"Point"}
}