{
  "type": "Feature",
  "properties": {
    "iso:country":"US",
    "sg:address":"104 S Plz",
    "sg:city":"Taos",
    "sg:classifiers":[
        {
            "category":"Shopping",
            "type":"Retail Goods"
        },
        {
            "category":"Shopping",
            "subcategory":"Optical Goods",
            "type":"Retail Goods"
        }
    ],
    "sg:phone":"+1 505 751 1565",
    "sg:postcode":"87571",
    "sg:province":"NM",
    "sg:tags":[
        "sun",
        "goggles",
        "sunglasses",
        "merchandise"
    ],
    "wof:name":"Sunshades of Taos",
    "wof:placetype":"venue"
},
  "geometry": {"coordinates":[-105.574051,36.406993],"type":"Point"}
}