{
  "type": "Feature",
  "properties": {
    "iso:country":"US",
    "sg:address":"500 Burro Ave",
    "sg:city":"Cloudcroft",
    "sg:classifiers":[
        {
            "category":"Real Estate",
            "subcategory":"Real Estate Agent",
            "type":"Services"
        }
    ],
    "sg:phone":"+1 505 682 2537",
    "sg:postcode":"88317",
    "sg:province":"NM",
    "sg:website":"www.greenmnt.com",
    "wof:name":"Green Mountain Real Estate Inc",
    "wof:placetype":"venue"
},
  "geometry": {"coordinates":[-105.74280400000001,32.958765],"type":"Point"}
}