{
  "type": "Feature",
  "properties": {
    "addr:full":"20 Rd 6400 Kirtland NM 87417",
    "addr:housenumber":"20",
    "addr:postcode":"6400;87417",
    "addr:street":"Rd",
    "iso:country":"US",
    "sg:address":"20 Rd 6400",
    "sg:city":"Kirtland",
    "sg:classifiers":[
        {
            "category":"Professional",
            "subcategory":"Lawyer & Legal Services",
            "type":"Services"
        }
    ],
    "sg:phone":"+1 505 598 9037",
    "sg:postcode":"87417",
    "sg:province":"NM",
    "sg:tags":[
        "attorney"
    ],
    "wof:name":"Todd M Ackley Atty",
    "wof:placetype":"venue"
},
  "geometry": {"coordinates":[-108.35982799999999,36.740217],"type":"Point"}
}