{
  "type": "Feature",
  "properties": {
    "iso:country":"US",
    "sg:address":"215 Fisher Ave",
    "sg:city":"Socorro",
    "sg:classifiers":[
        {
            "category":"Home & Garden",
            "subcategory":"Hardware",
            "type":"Retail Goods"
        }
    ],
    "sg:phone":"+1 505 835 0250",
    "sg:postcode":"87801",
    "sg:province":"NM",
    "wof:name":"Crabtree Builders Supply",
    "wof:placetype":"venue"
},
  "geometry": {"coordinates":[-106.895979,34.057432],"type":"Point"}
}