{
  "type": "Feature",
  "properties": {
    "iso:country":"US",
    "sg:address":"2401 Wyoming Blvd NE",
    "sg:city":"Albuquerque",
    "sg:classifiers":[
        {
            "category":"Retail",
            "subcategory":"Auto Repair",
            "type":"Services"
        }
    ],
    "sg:phone":"+1 505 299 3421",
    "sg:postcode":"87112",
    "sg:province":"NM",
    "sg:tags":[
        "repairing",
        "automobile"
    ],
    "wof:name":"Lee's Auto Svc",
    "wof:placetype":"venue"
},
  "geometry": {"coordinates":[-106.550866,35.112535],"type":"Point"}
}