{
  "type": "Feature",
  "properties": {
    "iso:country":"US",
    "sg:address":"1400 1st St SE",
    "sg:city":"Kirtland Afb",
    "sg:classifiers":[
        {
            "category":"Government",
            "subcategory":"Post Office",
            "type":"Public Place"
        }
    ],
    "sg:phone":"+1 505 000 1111",
    "sg:postcode":"87116",
    "sg:province":"NM",
    "wof:name":"US Post Office",
    "wof:placetype":"venue"
},
  "geometry": {"coordinates":[-106.553971,35.055319],"type":"Point"}
}