{
  "type": "Feature",
  "properties": {
    "iso:country":"US",
    "sg:address":"524 Haines Ave NW",
    "sg:city":"Albuquerque",
    "sg:classifiers":[
        {
            "category":"Manufacturing",
            "subcategory":"Rubber & Plastics",
            "type":"Manufacturing & Wholesale Goods"
        },
        {
            "category":"Shopping",
            "subcategory":"Department Store",
            "type":"Retail Goods"
        }
    ],
    "sg:phone":"+1 505 243 8331",
    "sg:postcode":"87102",
    "sg:province":"NM",
    "sg:tags":[
        "sponge",
        "product",
        "foam",
        "plastics-foam"
    ],
    "sg:website":"http://www.riograndefoam.com",
    "wof:name":"Rio Grande Foam Incorporated",
    "wof:placetype":"venue"
},
  "geometry": {"coordinates":[-106.649574,35.103126],"type":"Point"}
}