{
  "type": "Feature",
  "properties": {
    "addr:full":"1416 N Love St Lovington NM 88260",
    "addr:housenumber":"1416",
    "addr:postcode":"88260",
    "addr:street":"N Love St",
    "iso:country":"US",
    "sg:address":"1416 N Love St",
    "sg:city":"Lovington",
    "sg:classifiers":[
        {
            "category":"Retail",
            "subcategory":"Auto Repair",
            "type":"Services"
        }
    ],
    "sg:phone":"+1 505 396 3378",
    "sg:postcode":"88260",
    "sg:province":"NM",
    "sg:tags":[
        "body",
        "automobile",
        "painting"
    ],
    "wof:name":"Larry Mahan's Paint & Body Shp",
    "wof:placetype":"venue"
},
  "geometry": {"coordinates":[-103.34726499999999,32.960427],"type":"Point"}
}