{
  "type": "Feature",
  "properties": {
    "addr:full":"10500 N Dal Paso St Hobbs NM 88242",
    "addr:housenumber":"10500",
    "addr:postcode":"88242",
    "addr:street":"N Dal Paso St",
    "iso:country":"US",
    "sg:address":"10500 N Dal Paso St",
    "sg:city":"Hobbs",
    "sg:phone":"+1 505 392 2839",
    "sg:postcode":"88242",
    "sg:province":"NM",
    "sg:tags":[
        "farm"
    ],
    "wof:name":"Wilson Farms",
    "wof:placetype":"venue"
},
  "geometry": {"coordinates":[-103.127599,32.814155],"type":"Point"}
}