{
  "type": "Feature",
  "properties": {
    "iso:country":"US",
    "sg:address":"6000 San Francisco Rd NE",
    "sg:city":"Albuquerque",
    "sg:classifiers":[
        {
            "category":"Building & Trades",
            "subcategory":"Electrical",
            "type":"Services"
        }
    ],
    "sg:phone":"+1 505 828 0241",
    "sg:postcode":"87109",
    "sg:province":"NM",
    "sg:tags":[
        "electric",
        "contractor"
    ],
    "wof:name":"B Electric Inc",
    "wof:placetype":"venue"
},
  "geometry": {"coordinates":[-106.580849,35.166978],"type":"Point"}
}