{
  "type": "Feature",
  "properties": {
    "addr:full":"1204 Mechem Dr Ruidoso NM 88345",
    "addr:housenumber":"1204",
    "addr:postcode":"88345",
    "addr:street":"Mechem Dr",
    "iso:country":"US",
    "sg:address":"1204 Mechem Dr",
    "sg:city":"Ruidoso",
    "sg:classifiers":[
        {
            "category":"Restaurant",
            "type":"Food & Drink"
        }
    ],
    "sg:phone":"+1 505 258 4311",
    "sg:postcode":"88345",
    "sg:province":"NM",
    "sg:tags":[
        "eating"
    ],
    "wof:name":"Annes Market Place",
    "wof:placetype":"venue"
},
  "geometry": {"coordinates":[-105.66810099999999,33.369052],"type":"Point"}
}