{
  "type": "Feature",
  "properties": {
    "addr:full":"106 S Lincoln Rd Dexter NM 88230",
    "addr:housenumber":"106",
    "addr:postcode":"88230",
    "addr:street":"S Lincoln Rd",
    "iso:country":"US",
    "sg:address":"106 S Lincoln Rd",
    "sg:city":"Dexter",
    "sg:classifiers":[
        {
            "category":"Shopping",
            "subcategory":"Florist",
            "type":"Retail Goods"
        }
    ],
    "sg:phone":"+1 505 734 2229",
    "sg:postcode":"88230",
    "sg:province":"NM",
    "wof:name":"Abby's Flower Patch",
    "wof:placetype":"venue"
},
  "geometry": {"coordinates":[-104.371104,33.197682],"type":"Point"}
}