{
  "type": "Feature",
  "properties": {
    "iso:country":"US",
    "sg:address":"185 US Hwy 82",
    "sg:city":"Alamogordo",
    "sg:classifiers":[
        {
            "category":"Food & Beverages",
            "subcategory":"Groceries & Convenience Stores",
            "type":"Retail Goods"
        }
    ],
    "sg:phone":"+1 505 437 4077",
    "sg:postcode":"88310",
    "sg:province":"NM",
    "wof:name":"Stone Corner LLC",
    "wof:placetype":"venue"
},
  "geometry": {"coordinates":[-105.946479,32.957986],"type":"Point"}
}