{
  "type": "Feature",
  "properties": {
    "iso:country":"US",
    "sg:address":"4615 Menaul Blvd NE Ste A",
    "sg:city":"Albuquerque",
    "sg:classifiers":[
        {
            "category":"Health Services",
            "subcategory":"Doctor",
            "type":"Services"
        }
    ],
    "sg:phone":"+1 505 884 3860",
    "sg:postcode":"87110",
    "sg:province":"NM",
    "sg:tags":[
        "medicine",
        "physician",
        "surgeon",
        "internal",
        "surgeons"
    ],
    "wof:name":"Jennifer James 101",
    "wof:placetype":"venue"
},
  "geometry": {"coordinates":[-106.592003,35.109261],"type":"Point"}
}