{
  "type": "Feature",
  "properties": {
    "addr:full":"905 E 4th St Clovis NM 88101",
    "addr:housenumber":"905",
    "addr:postcode":"88101",
    "addr:street":"E 4Th St",
    "iso:country":"US",
    "sg:address":"905 E 4th St",
    "sg:city":"Clovis",
    "sg:classifiers":[
        {
            "category":"Building & Trades",
            "subcategory":"Construction",
            "type":"Services"
        }
    ],
    "sg:phone":"+1 575 791 3260",
    "sg:postcode":"88101",
    "sg:province":"NM",
    "sg:tags":[
        "industrial",
        "painting",
        "contractors-commercial",
        "contractor"
    ],
    "wof:name":"Raul's Painting",
    "wof:placetype":"venue"
},
  "geometry": {"coordinates":[-103.195177,34.401829],"type":"Point"}
}