{
  "type": "Feature",
  "properties": {
    "addr:full":"2121 S Triviz Dr Las Cruces NM 88001",
    "addr:housenumber":"2121",
    "addr:postcode":"88001",
    "addr:street":"S Triviz Dr",
    "iso:country":"US",
    "sg:address":"2121 S Triviz Dr",
    "sg:city":"Las Cruces",
    "sg:classifiers":[
        {
            "category":"Travel",
            "subcategory":"Hotels & Motels",
            "type":"Entertainment"
        }
    ],
    "sg:phone":"+1 505 522 1700",
    "sg:postcode":"88001",
    "sg:province":"NM",
    "sg:tags":[
        "operation"
    ],
    "wof:name":"Las Cruces Sleep Inn",
    "wof:placetype":"venue"
},
  "geometry": {"coordinates":[-106.74121599999999,32.293514],"type":"Point"}
}