{
  "type": "Feature",
  "properties": {
    "addr:full":"73 Alamo Canyon Rd Alamogordo NM 88310",
    "addr:housenumber":"73",
    "addr:postcode":"88310",
    "addr:street":"Alamo Canyon Rd",
    "iso:country":"US",
    "sg:address":"73 Alamo Canyon Rd",
    "sg:city":"Alamogordo",
    "sg:classifiers":[
        {
            "category":"Professional",
            "subcategory":"Business Services",
            "type":"Services"
        }
    ],
    "sg:phone":"+1 505 437 6449",
    "sg:postcode":"88310",
    "sg:province":"NM",
    "sg:tags":[
        "building",
        "inspection"
    ],
    "wof:name":"Hunt Building Inspections Inc",
    "wof:placetype":"venue"
},
  "geometry": {"coordinates":[-105.923643,32.868424],"type":"Point"}
}