{
  "type": "Feature",
  "properties": {
    "addr:full":"3379 State Rte 434 Angel Fire NM 87710",
    "addr:housenumber":"3379",
    "addr:postcode":"87710",
    "addr:street":"State Rte 434",
    "iso:country":"US",
    "sg:address":"3379 State Rte 434",
    "sg:city":"Angel Fire",
    "sg:classifiers":[
        {
            "category":"Professional",
            "subcategory":"Advertising",
            "type":"Services"
        },
        {
            "category":"Manufacturing",
            "subcategory":"Printing",
            "type":"Manufacturing & Wholesale Goods"
        }
    ],
    "sg:phone":"+1 505 377 3414",
    "sg:postcode":"87710",
    "sg:province":"NM",
    "sg:tags":[
        "multimedia"
    ],
    "wof:name":"Select Media",
    "wof:placetype":"venue"
},
  "geometry": {"coordinates":[-105.297039,36.421517],"type":"Point"}
}