{
  "type": "Feature",
  "properties": {
    "iso:country":"US",
    "sg:address":"207 Taylor Cir",
    "sg:city":"Carlsbad",
    "sg:classifiers":[
        {
            "category":"Wholesale",
            "subcategory":"Non-durable Goods",
            "type":"Manufacturing & Wholesale Goods"
        }
    ],
    "sg:phone":"+1 505 234 9161",
    "sg:postcode":"88220",
    "sg:province":"NM",
    "wof:name":"It Makes Scents",
    "wof:placetype":"venue"
},
  "geometry": {"coordinates":[-104.22087999999999,32.380936],"type":"Point"}
}