{
  "type": "Feature",
  "properties": {
    "iso:country":"US",
    "sg:address":"2630 Carlisle Blvd NE",
    "sg:city":"Albuquerque",
    "sg:classifiers":[
        {
            "category":"Shopping",
            "subcategory":"Optical Goods",
            "type":"Retail Goods"
        }
    ],
    "sg:phone":"+1 505 872 0214",
    "sg:postcode":"87110",
    "sg:province":"NM",
    "sg:website":"www.eyemartexpress.com",
    "wof:name":"Eyemart Express",
    "wof:placetype":"venue"
},
  "geometry": {"coordinates":[-106.604105,35.110526],"type":"Point"}
}