{
  "type": "Feature",
  "properties": {
    "iso:country":"US",
    "sg:address":"424 N Canal St",
    "sg:city":"Carlsbad",
    "sg:classifiers":[
        {
            "category":"Shopping",
            "subcategory":"Stationery & Office Supplies",
            "type":"Retail Goods"
        }
    ],
    "sg:phone":"+1 505 887 3535",
    "sg:postcode":"88220",
    "sg:province":"NM",
    "sg:tags":[
        "operates",
        "form",
        "furniture"
    ],
    "wof:name":"Connell's Office Products",
    "wof:placetype":"venue"
},
  "geometry": {"coordinates":[-104.228858,32.42477],"type":"Point"}
}