{
  "type": "Feature",
  "properties": {
    "iso:country":"US",
    "sg:address":"6900 Washington St NE",
    "sg:city":"Albuquerque",
    "sg:classifiers":[
        {
            "category":"Professional",
            "type":"Services"
        }
    ],
    "sg:phone":"+1 505 345 0156",
    "sg:postcode":"87109",
    "sg:province":"NM",
    "sg:tags":[
        "establishment"
    ],
    "wof:name":"ATS Inc",
    "wof:placetype":"venue"
},
  "geometry": {"coordinates":[-106.598435,35.159085],"type":"Point"}
}