{
  "type": "Feature",
  "properties": {
    "iso:country":"US",
    "sg:address":"630 Pso del Pueblo Sur",
    "sg:city":"Taos",
    "sg:classifiers":[
        {
            "category":"Professional",
            "subcategory":"Art Services",
            "type":"Services"
        }
    ],
    "sg:phone":"+1 505 758 3447",
    "sg:postcode":"87571",
    "sg:province":"NM",
    "sg:tags":[
        "graphic",
        "designer"
    ],
    "wof:name":"WEBB Design Studio",
    "wof:placetype":"venue"
},
  "geometry": {"coordinates":[-105.579494,36.395376],"type":"Point"}
}