{
  "type": "Feature",
  "properties": {
    "addr:full":"1928 Defiance Ave Las Cruces NM 88001",
    "addr:housenumber":"1928",
    "addr:postcode":"88001",
    "addr:street":"Defiance Ave",
    "iso:country":"US",
    "sg:address":"1928 Defiance Ave",
    "sg:city":"Las Cruces",
    "sg:classifiers":[
        {
            "category":"Building & Trades",
            "subcategory":"Pest Control",
            "type":"Services"
        }
    ],
    "sg:phone":"+1 505 621 1643",
    "sg:postcode":"88001",
    "sg:province":"NM",
    "wof:name":"Desert Oasis Pest Control",
    "wof:placetype":"venue"
},
  "geometry": {"coordinates":[-106.754485,32.322656],"type":"Point"}
}