{
  "type": "Feature",
  "properties": {
    "iso:country":"US",
    "sg:address":"1003 Main St SW",
    "sg:city":"Los Lunas",
    "sg:classifiers":[
        {
            "category":"Health Services",
            "subcategory":"Podiatrist",
            "type":"Services"
        }
    ],
    "sg:phone":"+1 505 565 1155",
    "sg:postcode":"87031",
    "sg:province":"NM",
    "wof:name":"Valencia Associated Poiadtrist",
    "wof:placetype":"venue"
},
  "geometry": {"coordinates":[-106.744376,34.812567],"type":"Point"}
}