{
  "type": "Feature",
  "properties": {
    "iso:country":"US",
    "sg:address":"1410 Wyoming Blvd NE",
    "sg:city":"Albuquerque",
    "sg:classifiers":[
        {
            "category":"Bars & Pubs",
            "type":"Food & Drink"
        }
    ],
    "sg:phone":"+1 505 292 2038",
    "sg:postcode":"87112",
    "sg:province":"NM",
    "wof:name":"Retro's Bar",
    "wof:placetype":"venue"
},
  "geometry": {"coordinates":[-106.550653,35.097051],"type":"Point"}
}