{
  "type": "Feature",
  "properties": {
    "iso:country":"US",
    "sg:address":"4317 San Pedro Dr NE",
    "sg:city":"Albuquerque",
    "sg:classifiers":[
        {
            "category":"Social Services",
            "subcategory":"Job Training",
            "type":"Services"
        }
    ],
    "sg:phone":"+1 505 883 0033",
    "sg:postcode":"87109",
    "sg:province":"NM",
    "wof:name":"Job Depot",
    "wof:placetype":"venue"
},
  "geometry": {"coordinates":[-106.577709,35.134301],"type":"Point"}
}