{
  "type": "Feature",
  "properties": {
    "iso:country":"US",
    "sg:address":"4350 Center Pl",
    "sg:city":"Santa Fe",
    "sg:classifiers":[
        {
            "category":"Retail",
            "subcategory":"Auto Repair",
            "type":"Services"
        }
    ],
    "sg:phone":"+1 505 474 8561",
    "sg:postcode":"87507",
    "sg:province":"NM",
    "sg:tags":[
        "repairing",
        "automobile"
    ],
    "wof:name":"B & G Automotive",
    "wof:placetype":"venue"
},
  "geometry": {"coordinates":[-106.024744,35.637324],"type":"Point"}
}