{
  "type": "Feature",
  "properties": {
    "iso:country":"US",
    "sg:address":"6300 Riverside Plaza Ln NW",
    "sg:city":"Albuquerque",
    "sg:classifiers":[
        {
            "category":"Education",
            "subcategory":"School",
            "type":"Public Place"
        }
    ],
    "sg:phone":"+1 505 792 4459",
    "sg:postcode":"87120",
    "sg:province":"NM",
    "wof:name":"Middle Beach Corp",
    "wof:placetype":"venue"
},
  "geometry": {"coordinates":[-106.67974700000001,35.15739],"type":"Point"}
}