{
  "type": "Feature",
  "properties": {
    "addr:full":"6101 Sequoia Rd NW Albuquerque NM 87120",
    "addr:housenumber":"6101",
    "addr:postcode":"87120",
    "addr:street":"Sequoia Rd Nw",
    "iso:country":"US",
    "sg:address":"6101 Sequoia Rd NW",
    "sg:city":"Albuquerque",
    "sg:classifiers":[
        {
            "category":"Real Estate",
            "subcategory":"Real Estate Operator",
            "type":"Services"
        }
    ],
    "sg:phone":"+1 505 836 5500",
    "sg:postcode":"87120",
    "sg:province":"NM",
    "sg:tags":[
        "apartment"
    ],
    "wof:name":"Broadstone Ladera Apartments",
    "wof:placetype":"venue"
},
  "geometry": {"coordinates":[-106.706813,35.121556],"type":"Point"}
}