{
  "type": "Feature",
  "properties": {
    "iso:country":"US",
    "sg:address":"2167 McNutt Rd",
    "sg:city":"Sunland Park",
    "sg:classifiers":[
        {
            "category":"Professional",
            "subcategory":"Accounting & Tax Preparation",
            "type":"Services"
        }
    ],
    "sg:phone":"+1 505 589 3200",
    "sg:postcode":"88063",
    "sg:province":"NM",
    "sg:tags":[
        "return",
        "filing"
    ],
    "wof:name":"James' Tax Svc",
    "wof:placetype":"venue"
},
  "geometry": {"coordinates":[-106.577539,31.79952],"type":"Point"}
}