{
  "type": "Feature",
  "properties": {
    "iso:country":"US",
    "sg:address":"4 Rd 2853",
    "sg:city":"Aztec",
    "sg:classifiers":[
        {
            "category":"Wholesale",
            "subcategory":"Construction Materials",
            "type":"Manufacturing & Wholesale Goods"
        }
    ],
    "sg:phone":"+1 505 334 2897",
    "sg:postcode":"87410",
    "sg:province":"NM",
    "sg:tags":[
        "fence"
    ],
    "wof:name":"Brother's Fencing",
    "wof:placetype":"venue"
},
  "geometry": {"coordinates":[-107.977808,36.859978],"type":"Point"}
}