{
  "type": "Feature",
  "properties": {
    "addr:full":"222 W Aztec Blvd Aztec NM 87410",
    "addr:housenumber":"222",
    "addr:postcode":"87410",
    "addr:street":"W Aztec Blvd",
    "iso:country":"US",
    "sg:address":"222 W Aztec Blvd",
    "sg:city":"Aztec",
    "sg:classifiers":[
        {
            "category":"Restaurant",
            "type":"Food & Drink"
        }
    ],
    "sg:menulink":"http://www.allmenus.com/nm/aztec/74871-pizza-hut/menu/",
    "sg:phone":"+1 505 334 7516",
    "sg:postcode":"87410",
    "sg:province":"NM",
    "sg:tags":[
        "american",
        "pizza"
    ],
    "wof:name":"Pizza Hut",
    "wof:placetype":"venue"
},
  "geometry": {"coordinates":[-107.994646,36.825866],"type":"Point"}
}