{
  "type": "Feature",
  "properties": {
    "iso:country":"US",
    "sg:address":"1114 Candelaria Rd NW",
    "sg:city":"Albuquerque",
    "sg:classifiers":[
        {
            "category":"Shopping",
            "subcategory":"Department Store",
            "type":"Retail Goods"
        }
    ],
    "sg:phone":"+1 505 341 3232",
    "sg:postcode":"87107",
    "sg:province":"NM",
    "wof:name":"Family Dollar Store",
    "wof:placetype":"venue"
},
  "geometry": {"coordinates":[-106.65479000000001,35.122561],"type":"Point"}
}