{
  "type": "Feature",
  "properties": {
    "iso:country":"US",
    "sg:address":"220 N Main Ave",
    "sg:city":"Aztec",
    "sg:classifiers":[
        {
            "category":"Personal",
            "subcategory":"Beauty Salon",
            "type":"Services"
        }
    ],
    "sg:phone":"+1 505 334 7214",
    "sg:postcode":"87410",
    "sg:province":"NM",
    "wof:name":"Southwest Styles",
    "wof:placetype":"venue"
},
  "geometry": {"coordinates":[-107.994344,36.823819],"type":"Point"}
}