{
  "type": "Feature",
  "properties": {
    "iso:country":"US",
    "sg:address":"1475 Central Ave",
    "sg:city":"Los Alamos",
    "sg:classifiers":[
        {
            "category":"Professional",
            "subcategory":"Lawyer & Legal Services",
            "type":"Services"
        }
    ],
    "sg:phone":"+1 505 662 5216",
    "sg:postcode":"87544",
    "sg:province":"NM",
    "sg:tags":[
        "attorney"
    ],
    "wof:name":"F Stephen Boone",
    "wof:placetype":"venue"
},
  "geometry": {"coordinates":[-106.29850999999999,35.881291],"type":"Point"}
}