{
  "type": "Feature",
  "properties": {
    "iso:country":"US",
    "sg:address":"113 Moore Dr",
    "sg:city":"Carlsbad",
    "sg:classifiers":[
        {
            "category":"Retail",
            "subcategory":"Repair Shop",
            "type":"Services"
        }
    ],
    "sg:phone":"+1 505 234 9029",
    "sg:postcode":"88220",
    "sg:province":"NM",
    "wof:name":"Seg Pumping",
    "wof:placetype":"venue"
},
  "geometry": {"coordinates":[-104.219926,32.420232],"type":"Point"}
}