{
  "type": "Feature",
  "properties": {
    "iso:country":"US",
    "sg:address":"2308 New York Ave SW",
    "sg:city":"Albuquerque",
    "sg:classifiers":[
        {
            "category":"Retail",
            "subcategory":"Car Wash",
            "type":"Services"
        }
    ],
    "sg:phone":"+1 505 934 0547",
    "sg:postcode":"87104",
    "sg:province":"NM",
    "sg:tags":[
        "carwash"
    ],
    "wof:name":"Alb Auto Jungle",
    "wof:placetype":"venue"
},
  "geometry": {"coordinates":[-106.677392,35.094389],"type":"Point"}
}