{
  "type": "Feature",
  "properties": {
    "iso:country":"US",
    "sg:address":"2255 Cll Cuesta",
    "sg:city":"Santa Fe",
    "sg:classifiers":[
        {
            "category":"Building & Trades",
            "subcategory":"Construction",
            "type":"Services"
        }
    ],
    "sg:phone":"+1 505 471 5818",
    "sg:postcode":"87505",
    "sg:province":"NM",
    "sg:tags":[
        "general",
        "contractor"
    ],
    "wof:name":"Caron Construction Co",
    "wof:placetype":"venue"
},
  "geometry": {"coordinates":[-105.981993,35.648541],"type":"Point"}
}