{
  "type": "Feature",
  "properties": {
    "iso:country":"US",
    "sg:address":"1650 Gabaldon Dr NW",
    "sg:city":"Albuquerque",
    "sg:classifiers":[
        {
            "category":"Social Services",
            "subcategory":"Child Care",
            "type":"Services"
        }
    ],
    "sg:phone":"+1 505 768 0878",
    "sg:postcode":"87104",
    "sg:province":"NM",
    "sg:tags":[
        "day"
    ],
    "wof:name":"Montessori Of The Rio Grande",
    "wof:placetype":"venue"
},
  "geometry": {"coordinates":[-106.68351199999999,35.111899],"type":"Point"}
}