{
  "type": "Feature",
  "properties": {
    "addr:full":"6801 4th St NW Albuquerque NM 87107",
    "addr:housenumber":"6801",
    "addr:postcode":"87107",
    "addr:street":"4Th St Nw",
    "iso:country":"US",
    "sg:address":"6801 4th St NW",
    "sg:city":"Albuquerque",
    "sg:classifiers":[
        {
            "category":"Travel",
            "subcategory":"Hotels & Motels",
            "type":"Entertainment"
        }
    ],
    "sg:phone":"+1 505 344 1606",
    "sg:postcode":"87107",
    "sg:province":"NM",
    "sg:tags":[
        "operation"
    ],
    "wof:name":"El Camino Motor Hotel",
    "wof:placetype":"venue"
},
  "geometry": {"coordinates":[-106.637006,35.160703],"type":"Point"}
}