{
  "type": "Feature",
  "properties": {
    "addr:full":"5010 4th St NW Albuquerque NM 87107",
    "addr:housenumber":"5010",
    "addr:postcode":"87107",
    "addr:street":"4Th St Nw",
    "iso:country":"US",
    "sg:address":"5010 4th St NW",
    "sg:city":"Albuquerque",
    "sg:classifiers":[
        {
            "category":"Communications",
            "subcategory":"Television Station",
            "type":"Services"
        }
    ],
    "sg:phone":"+1 505 345 1991",
    "sg:postcode":"87107",
    "sg:province":"NM",
    "sg:tags":[
        "broadcasting",
        "co"
    ],
    "sg:website":"www.kchf.com",
    "wof:name":"KCHF",
    "wof:placetype":"venue"
},
  "geometry": {"coordinates":[-106.642144,35.133639],"type":"Point"}
}