{
  "type": "Feature",
  "properties": {
    "iso:country":"US",
    "sg:address":"1334 Wyoming Blvd NE",
    "sg:city":"Albuquerque",
    "sg:classifiers":[
        {
            "category":"Health Services",
            "subcategory":"Health Practitioner",
            "type":"Services"
        }
    ],
    "sg:phone":"+1 505 292 3317",
    "sg:postcode":"87112",
    "sg:province":"NM",
    "sg:tags":[
        "therapist",
        "physical"
    ],
    "wof:name":"Southwest Orthopedic Physical",
    "wof:placetype":"venue"
},
  "geometry": {"coordinates":[-106.550635,35.093975],"type":"Point"}
}