{
  "type": "Feature",
  "properties": {
    "iso:country":"US",
    "sg:address":"845 Watson Ln",
    "sg:city":"Las Cruces",
    "sg:classifiers":[
        {
            "category":"Building & Trades",
            "subcategory":"Plumbing",
            "type":"Services"
        }
    ],
    "sg:phone":"+1 505 527 8217",
    "sg:postcode":"88005",
    "sg:province":"NM",
    "sg:tags":[
        "cooling",
        "heating",
        "fabrication",
        "contractor"
    ],
    "wof:name":"Sals Fabrication Htg & Coolg",
    "wof:placetype":"venue"
},
  "geometry": {"coordinates":[-106.780299,32.261636],"type":"Point"}
}