{
  "type": "Feature",
  "properties": {
    "addr:full":"16 Custie Ave Rodeo NM 88056",
    "addr:housenumber":"16",
    "addr:postcode":"88056",
    "addr:street":"Custie Ave",
    "iso:country":"US",
    "sg:address":"16 Custie Ave",
    "sg:city":"Rodeo",
    "sg:classifiers":[
        {
            "category":"Professional",
            "subcategory":"Business Services",
            "type":"Services"
        },
        {
            "category":"Government",
            "subcategory":"Post Office",
            "type":"Public Place"
        }
    ],
    "sg:phone":"+1 800 275 8777",
    "sg:postcode":"88056",
    "sg:province":"NM",
    "sg:tags":[
        "mail",
        "shipping"
    ],
    "sg:website":"http://www.usps.com",
    "wof:name":"USPS - United States Post Office - Rodeo Main Office",
    "wof:placetype":"venue"
},
  "geometry": {"coordinates":[-109.031818,31.83374],"type":"Point"}
}