{
  "type": "Feature",
  "properties": {
    "iso:country":"US",
    "sg:address":"920 Grand Ave",
    "sg:city":"Las Vegas",
    "sg:classifiers":[
        {
            "category":"Retail",
            "subcategory":"Repair Shop",
            "type":"Services"
        }
    ],
    "sg:phone":"+1 505 454 0103",
    "sg:postcode":"87701",
    "sg:province":"NM",
    "sg:tags":[
        "appliance",
        "electrical"
    ],
    "wof:name":"Bustamante Appliance Co",
    "wof:placetype":"venue"
},
  "geometry": {"coordinates":[-105.21276,35.600123],"type":"Point"}
}