{
  "type": "Feature",
  "properties": {
    "iso:country":"US",
    "sg:address":"611 Girard Blvd NE",
    "sg:city":"Albuquerque",
    "sg:classifiers":[
        {
            "category":"Professional",
            "subcategory":"Management & Consulting",
            "type":"Services"
        }
    ],
    "sg:phone":"+1 505 254 2255",
    "sg:postcode":"87106",
    "sg:province":"NM",
    "sg:tags":[
        "consultant"
    ],
    "wof:name":"Consultant",
    "wof:placetype":"venue"
},
  "geometry": {"coordinates":[-106.61323,35.087365],"type":"Point"}
}