{
  "type": "Feature",
  "properties": {
    "addr:full":"1010 N Dalmont St Hobbs NM 88240",
    "addr:housenumber":"1010",
    "addr:postcode":"88240",
    "addr:street":"N Dalmont St",
    "iso:country":"US",
    "sg:address":"1010 N Dalmont St",
    "sg:city":"Hobbs",
    "sg:classifiers":[
        {
            "category":"Health Services",
            "subcategory":"Chiropractor",
            "type":"Services"
        }
    ],
    "sg:phone":"+1 505 393 4636",
    "sg:postcode":"88240",
    "sg:province":"NM",
    "wof:name":"Family Wellness Chiropractic",
    "wof:placetype":"venue"
},
  "geometry": {"coordinates":[-103.13490299999999,32.711078],"type":"Point"}
}