{
  "type": "Feature",
  "properties": {
    "iso:country":"US",
    "sg:address":"7717 White St NE",
    "sg:city":"Albuquerque",
    "sg:classifiers":[
        {
            "category":"Social Services",
            "type":"Services"
        }
    ],
    "sg:phone":"+1 505 790 9079",
    "sg:postcode":"87109",
    "sg:province":"NM",
    "wof:name":"Stress Fx Inc",
    "wof:placetype":"venue"
},
  "geometry": {"coordinates":[-106.558456,35.169881],"type":"Point"}
}