{
  "type": "Feature",
  "properties": {
    "iso:country":"US",
    "sg:address":"1300 W Murray Dr",
    "sg:city":"Farmington",
    "sg:classifiers":[
        {
            "category":"Retail",
            "subcategory":"Auto Repair",
            "type":"Services"
        }
    ],
    "sg:phone":"+1 505 324 0610",
    "sg:postcode":"87401",
    "sg:province":"NM",
    "sg:tags":[
        "repairing",
        "automobile"
    ],
    "wof:name":"Wrench",
    "wof:placetype":"venue"
},
  "geometry": {"coordinates":[-108.22640699999999,36.727401],"type":"Point"}
}