{
  "type": "Feature",
  "properties": {
    "iso:country":"US",
    "sg:address":"200 N Marland Blvd",
    "sg:city":"Hobbs",
    "sg:classifiers":[
        {
            "category":"Travel",
            "subcategory":"Hotels & Motels",
            "type":"Entertainment"
        }
    ],
    "sg:phone":"+1 505 393 4101",
    "sg:postcode":"88240",
    "sg:province":"NM",
    "wof:name":"Roadway Inn",
    "wof:placetype":"venue"
},
  "geometry": {"coordinates":[-103.120172,32.702024],"type":"Point"}
}