{
  "type": "Feature",
  "properties": {
    "addr:full":"10004 Ashland St NW Albuquerque NM 87114",
    "addr:housenumber":"10004",
    "addr:postcode":"87114",
    "addr:street":"Ashland St Nw",
    "iso:country":"US",
    "sg:address":"10004 Ashland St NW",
    "sg:city":"Albuquerque",
    "sg:classifiers":[
        {
            "category":"Professional",
            "subcategory":"Accounting & Tax Preparation",
            "type":"Services"
        }
    ],
    "sg:phone":"+1 505 379 3446",
    "sg:postcode":"87114",
    "sg:province":"NM",
    "wof:name":"Sb Bookkeeping & Accounting",
    "wof:placetype":"venue"
},
  "geometry": {"coordinates":[-106.742598,35.19383],"type":"Point"}
}