{
  "type": "Feature",
  "properties": {
    "addr:full":"1375 Sara Rd SE Rio Rancho NM 87124",
    "addr:housenumber":"1375",
    "addr:postcode":"87124",
    "addr:street":"Sara Rd Se",
    "iso:country":"US",
    "sg:address":"1375 Sara Rd SE",
    "sg:city":"Rio Rancho",
    "sg:classifiers":[
        {
            "category":"Organizations",
            "subcategory":"Religious Organization",
            "type":"Services"
        }
    ],
    "sg:phone":"+1 505 896 0293",
    "sg:postcode":"87124",
    "sg:province":"NM",
    "wof:name":"New Church of High Desert",
    "wof:placetype":"venue"
},
  "geometry": {"coordinates":[-106.665616,35.234864],"type":"Point"}
}