{
  "type": "Feature",
  "properties": {
    "addr:full":"3229 Richards Ln Santa Fe NM 87507",
    "addr:housenumber":"3229",
    "addr:postcode":"87507",
    "addr:street":"Richards Ln",
    "iso:country":"US",
    "sg:address":"3229 Richards Ln",
    "sg:city":"Santa Fe",
    "sg:classifiers":[
        {
            "category":"Sports & Exercise",
            "subcategory":"Gym",
            "type":"Entertainment"
        }
    ],
    "sg:phone":"+1 505 316 0747",
    "sg:postcode":"87507",
    "sg:province":"NM",
    "sg:tags":[
        "club",
        "health",
        "studio",
        "gymnasium"
    ],
    "wof:name":"A B's Exclusive Fitness",
    "wof:placetype":"venue"
},
  "geometry": {"coordinates":[-106.000697,35.656701],"type":"Point"}
}