{
  "type": "Feature",
  "properties": {
    "iso:country":"US",
    "sg:address":"2800 Rosendo Garcia Rd SW",
    "sg:city":"Albuquerque",
    "sg:classifiers":[
        {
            "category":"Building & Trades",
            "subcategory":"Construction",
            "type":"Services"
        }
    ],
    "sg:phone":"+1 505 873 9272",
    "sg:postcode":"87105",
    "sg:province":"NM",
    "sg:tags":[
        "stucco",
        "contractor"
    ],
    "wof:name":"Rio Grande Lath & Plaster",
    "wof:placetype":"venue"
},
  "geometry": {"coordinates":[-106.703506,35.061237],"type":"Point"}
}