{
  "type": "Feature",
  "properties": {
    "iso:country":"US",
    "sg:address":"750 S Bosque Loop",
    "sg:city":"Bosque Farms",
    "sg:classifiers":[
        {
            "category":"Organizations",
            "subcategory":"Community Association",
            "type":"Services"
        }
    ],
    "sg:phone":"+1 505 869 3181",
    "sg:postcode":"87068",
    "sg:province":"NM",
    "wof:name":"Belen Area Radio Controll",
    "wof:placetype":"venue"
},
  "geometry": {"coordinates":[-106.700855,34.842669],"type":"Point"}
}