{
  "type": "Feature",
  "properties": {
    "iso:country":"US",
    "sg:address":"6381 N Main St",
    "sg:city":"Roswell",
    "sg:classifiers":[
        {
            "category":"Utilities",
            "subcategory":"Natural Gas",
            "type":"Services"
        }
    ],
    "sg:phone":"+1 505 623 2761",
    "sg:postcode":"88201",
    "sg:province":"NM",
    "sg:tags":[
        "transmission"
    ],
    "wof:name":"Cross Country Energy Svcs LLC",
    "wof:placetype":"venue"
},
  "geometry": {"coordinates":[-104.519137,33.488979],"type":"Point"}
}