{
  "type": "Feature",
  "properties": {
    "iso:country":"US",
    "sg:address":"508 Central Ave SW",
    "sg:city":"Albuquerque",
    "sg:classifiers":[
        {
            "category":"Professional",
            "subcategory":"Detective & Security Services",
            "type":"Services"
        }
    ],
    "sg:phone":"+1 505 242 1845",
    "sg:postcode":"87102",
    "sg:province":"NM",
    "sg:tags":[
        "guard",
        "patrol"
    ],
    "sg:website":"www.wackenhut.com",
    "wof:name":"Wackenhut Services Inc",
    "wof:placetype":"venue"
},
  "geometry": {"coordinates":[-106.65388900000001,35.084926],"type":"Point"}
}