{
  "type": "Feature",
  "properties": {
    "iso:country":"US",
    "sg:address":"1624 S 2nd St",
    "sg:city":"Gallup",
    "sg:classifiers":[
        {
            "category":"Shopping",
            "type":"Retail Goods"
        }
    ],
    "sg:phone":"+1 505 863 2161",
    "sg:postcode":"87301",
    "sg:province":"NM",
    "sg:tags":[
        "cosmetic",
        "perfume"
    ],
    "sg:website":"www.merlenorman.com",
    "wof:name":"Merle Norman Cosmetics",
    "wof:placetype":"venue"
},
  "geometry": {"coordinates":[-108.738592,35.512246],"type":"Point"}
}