{
  "type": "Feature",
  "properties": {
    "iso:country":"US",
    "sg:address":"860 Amethyst Dr NE",
    "sg:city":"Rio Rancho",
    "sg:classifiers":[
        {
            "category":"Professional",
            "subcategory":"Business Services",
            "type":"Services"
        }
    ],
    "sg:phone":"+1 505 896 9623",
    "sg:postcode":"87124",
    "sg:province":"NM",
    "wof:name":"JMJ Enterprises",
    "wof:placetype":"venue"
},
  "geometry": {"coordinates":[-106.640592,35.272654],"type":"Point"}
}