{
  "type": "Feature",
  "properties": {
    "iso:country":"US",
    "sg:address":"1332 Freeman Ave NW",
    "sg:city":"Albuquerque",
    "sg:classifiers":[
        {
            "category":"Manufacturing",
            "subcategory":"Tools & Machinery",
            "type":"Manufacturing & Wholesale Goods"
        }
    ],
    "sg:phone":"+1 505 342 9151",
    "sg:postcode":"87107",
    "sg:province":"NM",
    "sg:tags":[
        "lighting",
        "fixture"
    ],
    "wof:name":"Southwest Lights",
    "wof:placetype":"venue"
},
  "geometry": {"coordinates":[-106.656026,35.131173],"type":"Point"}
}