{
  "type": "Feature",
  "properties": {
    "iso:country":"US",
    "sg:address":"296 Russia Canyon Rd",
    "sg:city":"Cloudcroft",
    "sg:classifiers":[
        {
            "category":"Real Estate",
            "subcategory":"Real Estate Agent",
            "type":"Services"
        }
    ],
    "sg:phone":"+1 505 682 3717",
    "sg:postcode":"88317",
    "sg:province":"NM",
    "wof:name":"Log Cabin Realty",
    "wof:placetype":"venue"
},
  "geometry": {"coordinates":[-105.739222,32.897114],"type":"Point"}
}