{
  "type": "Feature",
  "properties": {
    "iso:country":"US",
    "sg:address":"1221 Gusdorf Rd",
    "sg:city":"Taos",
    "sg:classifiers":[
        {
            "category":"Manufacturing",
            "subcategory":"Paper Products",
            "type":"Manufacturing & Wholesale Goods"
        }
    ],
    "sg:phone":"+1 505 758 3587",
    "sg:postcode":"87571",
    "sg:province":"NM",
    "sg:tags":[
        "packaging",
        "material"
    ],
    "wof:name":"Taos Crating Co",
    "wof:placetype":"venue"
},
  "geometry": {"coordinates":[-105.587238,36.37801],"type":"Point"}
}