{
  "type": "Feature",
  "properties": {
    "iso:country":"US",
    "sg:address":"2596 S Broadway St",
    "sg:city":"Truth Or Cnsqncs",
    "sg:classifiers":[
        {
            "category":"Wholesale",
            "subcategory":"Farm Supplies",
            "type":"Manufacturing & Wholesale Goods"
        }
    ],
    "sg:phone":"+1 505 894 3994",
    "sg:postcode":"87901",
    "sg:province":"NM",
    "sg:tags":[
        "feed"
    ],
    "wof:name":"Sierra Feed & Mercantile",
    "wof:placetype":"venue"
},
  "geometry": {"coordinates":[-107.282173,33.120828],"type":"Point"}
}