{
  "type": "Feature",
  "properties": {
    "iso:country":"US",
    "sg:address":"1322 Pso de Peralta",
    "sg:city":"Santa Fe",
    "sg:classifiers":[
        {
            "category":"Professional",
            "subcategory":"Business Services",
            "type":"Services"
        }
    ],
    "sg:phone":"+1 505 989 5079",
    "sg:postcode":"87501",
    "sg:province":"NM",
    "sg:tags":[
        "arbitration"
    ],
    "wof:name":"Reese Fullerton Mediator",
    "wof:placetype":"venue"
},
  "geometry": {"coordinates":[-105.943157,35.681107],"type":"Point"}
}