{
  "type": "Feature",
  "properties": {
    "iso:country":"US",
    "sg:address":"2836 Valle Grande",
    "sg:city":"Mesilla",
    "sg:classifiers":[
        {
            "category":"Farming",
            "subcategory":"Farm",
            "type":"Manufacturing & Wholesale Goods"
        }
    ],
    "sg:phone":"+1 505 525 5636",
    "sg:postcode":"88005",
    "sg:province":"NM",
    "sg:tags":[
        "crop",
        "general"
    ],
    "wof:name":"Pentola Farms LLC",
    "wof:placetype":"venue"
},
  "geometry": {"coordinates":[-106.81055600000001,32.273144],"type":"Point"}
}