{
  "type": "Feature",
  "properties": {
    "addr:full":"30 Rainbow Blvd NE Albuquerque NM 87124",
    "addr:housenumber":"30",
    "addr:postcode":"87124",
    "addr:street":"Rainbow Blvd Ne",
    "iso:country":"US",
    "sg:address":"30 Rainbow Blvd NE",
    "sg:city":"Albuquerque",
    "sg:classifiers":[
        {
            "category":"Restaurant",
            "type":"Food & Drink"
        }
    ],
    "sg:phone":"+1 505 796 7788",
    "sg:postcode":"87124",
    "sg:province":"NM",
    "sg:tags":[
        "eating"
    ],
    "wof:name":"Tlur PA Lounge",
    "wof:placetype":"venue"
},
  "geometry": {"coordinates":[-106.736755,35.25912],"type":"Point"}
}