{
  "type": "Feature",
  "properties": {
    "addr:full":"1331 Juan Tabo Blvd NE Albuquerque NM 87112",
    "addr:housenumber":"1331",
    "addr:postcode":"87112",
    "addr:street":"Juan Tabo Blvd Ne",
    "iso:country":"US",
    "sg:address":"1331 Juan Tabo Blvd NE",
    "sg:city":"Albuquerque",
    "sg:classifiers":[
        {
            "category":"Banks & Credit Unions",
            "subcategory":"Bank",
            "type":"Services"
        }
    ],
    "sg:phone":"+1 505 271 9009",
    "sg:postcode":"87112",
    "sg:province":"NM",
    "sg:tags":[
        "cashing",
        "check"
    ],
    "sg:website":"www.acecashexpress.com",
    "wof:name":"ACE Cash Express",
    "wof:placetype":"venue"
},
  "geometry": {"coordinates":[-106.51540199999999,35.095969],"type":"Point"}
}