{
  "type": "Feature",
  "properties": {
    "iso:country":"US",
    "sg:address":"207 W Lea St",
    "sg:city":"Hobbs",
    "sg:classifiers":[
        {
            "category":"Retail",
            "subcategory":"Auto Repair",
            "type":"Services"
        }
    ],
    "sg:phone":"+1 505 393 6722",
    "sg:postcode":"88240",
    "sg:province":"NM",
    "sg:tags":[
        "general"
    ],
    "wof:name":"Tonys Auto Repair",
    "wof:placetype":"venue"
},
  "geometry": {"coordinates":[-103.13753699999999,32.709115],"type":"Point"}
}