{
  "type": "Feature",
  "properties": {
    "addr:full":"2504 Cam Entrada Santa Fe NM 87507",
    "addr:housenumber":"2504",
    "addr:postcode":"87507",
    "addr:street":"Cam Entrada",
    "iso:country":"US",
    "sg:address":"2504 Cam Entrada",
    "sg:city":"Santa Fe",
    "sg:classifiers":[
        {
            "category":"Social Services",
            "type":"Services"
        }
    ],
    "sg:phone":"+1 505 988 7621",
    "sg:postcode":"87507",
    "sg:province":"NM",
    "sg:tags":[
        "disabled",
        "care",
        "people"
    ],
    "sg:website":"www.challengenewmexico.com",
    "wof:name":"Challenge New Mexico",
    "wof:placetype":"venue"
},
  "geometry": {"coordinates":[-106.020155,35.636393],"type":"Point"}
}