{
  "type": "Feature",
  "properties": {
    "iso:country":"US",
    "sg:address":"254 Lower Las Colonias Rd",
    "sg:city":"El Prado",
    "sg:classifiers":[
        {
            "category":"Building & Trades",
            "subcategory":"Plumbing",
            "type":"Services"
        }
    ],
    "sg:phone":"+1 505 758 4206",
    "sg:postcode":"87529",
    "sg:province":"NM",
    "sg:tags":[
        "plumbing",
        "contractor"
    ],
    "wof:name":"Pipe-N-Hot Svc Co",
    "wof:placetype":"venue"
},
  "geometry": {"coordinates":[-105.624651,36.421943],"type":"Point"}
}