{
  "type": "Feature",
  "properties": {
    "iso:country":"US",
    "sg:address":"708 Sperry Dr",
    "sg:city":"Las Vegas",
    "sg:classifiers":[
        {
            "category":"Building & Trades",
            "subcategory":"Plumbing",
            "type":"Services"
        }
    ],
    "sg:phone":"+1 505 425 9252",
    "sg:postcode":"87701",
    "sg:province":"NM",
    "sg:tags":[
        "contractor"
    ],
    "wof:name":"S&E Plumbing",
    "wof:placetype":"venue"
},
  "geometry": {"coordinates":[-105.232505,35.619758],"type":"Point"}
}