{
  "type": "Feature",
  "properties": {
    "addr:full":"1504 W Riverside Dr Carlsbad NM 88220",
    "addr:housenumber":"1504",
    "addr:postcode":"88220",
    "addr:street":"W Riverside Dr",
    "iso:country":"US",
    "sg:address":"1504 W Riverside Dr",
    "sg:city":"Carlsbad",
    "sg:classifiers":[
        {
            "category":"Health Services",
            "subcategory":"Doctor",
            "type":"Services"
        }
    ],
    "sg:phone":"+1 505 234 1701",
    "sg:postcode":"88220",
    "sg:province":"NM",
    "sg:tags":[
        "medical"
    ],
    "wof:name":"Paul Bauer MD",
    "wof:placetype":"venue"
},
  "geometry": {"coordinates":[-104.246191,32.441277],"type":"Point"}
}