{
  "type": "Feature",
  "properties": {
    "iso:country":"US",
    "sg:address":"7301 Meridian Pl NW",
    "sg:city":"Albuquerque",
    "sg:classifiers":[
        {
            "category":"Wholesale",
            "subcategory":"Construction Materials",
            "type":"Manufacturing & Wholesale Goods"
        }
    ],
    "sg:phone":"+1 505 352 0202",
    "sg:postcode":"87121",
    "sg:province":"NM",
    "sg:tags":[
        "glass"
    ],
    "sg:website":"www.mygrantglass.com",
    "wof:name":"Mygrant Glass",
    "wof:placetype":"venue"
},
  "geometry": {"coordinates":[-106.719596,35.087009],"type":"Point"}
}