{
  "type": "Feature",
  "properties": {
    "iso:country":"US",
    "sg:address":"242 Los Pinos Rd",
    "sg:city":"Santa Fe",
    "sg:classifiers":[
        {
            "category":"Restaurant",
            "type":"Food & Drink"
        }
    ],
    "sg:phone":"+1 505 428 3600",
    "sg:postcode":"87507",
    "sg:province":"NM",
    "wof:name":"Blue Heron Restaurant",
    "wof:placetype":"venue"
},
  "geometry": {"coordinates":[-106.10261199999999,35.585466],"type":"Point"}
}