{
  "type": "Feature",
  "properties": {
    "addr:full":"4850 Pan American Fwy Albuquerque NM 87109",
    "addr:housenumber":"4850",
    "addr:postcode":"87109",
    "addr:street":"Pan American Fwy",
    "iso:country":"US",
    "sg:address":"4850 Pan American Fwy",
    "sg:city":"Albuquerque",
    "sg:classifiers":[
        {
            "category":"Autos & Motor Vehicles",
            "subcategory":"Motorcycle Sales",
            "type":"Retail Goods"
        }
    ],
    "sg:phone":"+1 505 822 0311",
    "sg:postcode":"87109",
    "sg:province":"NM",
    "sg:tags":[
        "scooter"
    ],
    "wof:name":"Desert Greens Equipment Inc",
    "wof:placetype":"venue"
},
  "geometry": {"coordinates":[-106.604392,35.135871],"type":"Point"}
}