{
  "type": "Feature",
  "properties": {
    "addr:full":"409 N Bullard St Silver City NM 88061",
    "addr:housenumber":"409",
    "addr:postcode":"88061",
    "addr:street":"N Bullard St",
    "iso:country":"US",
    "sg:address":"409 N Bullard St",
    "sg:city":"Silver City",
    "sg:classifiers":[
        {
            "category":"Shopping",
            "subcategory":"Hobbies, Toys, & Games",
            "type":"Retail Goods"
        }
    ],
    "sg:phone":"+1 505 534 0377",
    "sg:postcode":"88061",
    "sg:province":"NM",
    "wof:name":"Star Mountain Trading Co",
    "wof:placetype":"venue"
},
  "geometry": {"coordinates":[-108.276302,32.771733],"type":"Point"}
}