{
  "type": "Feature",
  "properties": {
    "addr:full":"4100 High Resort Blvd SE Rio Rancho NM 87124",
    "addr:housenumber":"4100",
    "addr:postcode":"87124",
    "addr:street":"High Resort Blvd Se",
    "iso:country":"US",
    "sg:address":"4100 High Resort Blvd SE",
    "sg:city":"Rio Rancho",
    "sg:classifiers":[
        {
            "category":"Health Services",
            "subcategory":"Medical Lab",
            "type":"Services"
        }
    ],
    "sg:phone":"+1 505 462 8839",
    "sg:postcode":"87124",
    "sg:province":"NM",
    "sg:tags":[
        "laboratory"
    ],
    "wof:name":"Tri Core Reference Labs",
    "wof:placetype":"venue"
},
  "geometry": {"coordinates":[-106.661196,35.25518],"type":"Point"}
}