{
  "type": "Feature",
  "properties": {
    "addr:full":"669 Cam del Pueblo Bernalillo NM 87004",
    "addr:housenumber":"669",
    "addr:postcode":"87004",
    "addr:street":"Cam Del Pueblo",
    "iso:country":"US",
    "sg:address":"669 Cam del Pueblo",
    "sg:city":"Bernalillo",
    "sg:classifiers":[
        {
            "category":"Government",
            "subcategory":"Office",
            "type":"Public Place"
        }
    ],
    "sg:phone":"+1 505 867 8170",
    "sg:postcode":"87004",
    "sg:province":"NM",
    "wof:name":"Sandoval County DWI Program",
    "wof:placetype":"venue"
},
  "geometry": {"coordinates":[-106.54769899999999,35.307126],"type":"Point"}
}