{
  "type": "Feature",
  "properties": {
    "iso:country":"US",
    "sg:address":"4210 2nd St NW",
    "sg:city":"Albuquerque",
    "sg:classifiers":[
        {
            "category":"Freight",
            "type":"Transportation"
        }
    ],
    "sg:phone":"+1 505 342 1000",
    "sg:postcode":"87107",
    "sg:province":"NM",
    "sg:tags":[
        "trucking"
    ],
    "wof:name":"Flying Star Transport",
    "wof:placetype":"venue"
},
  "geometry": {"coordinates":[-106.640157,35.126244],"type":"Point"}
}