{
  "type": "Feature",
  "properties": {
    "iso:country":"US",
    "sg:address":"1002 N Pate St",
    "sg:city":"Carlsbad",
    "sg:classifiers":[
        {
            "category":"Organizations",
            "subcategory":"Religious Organization",
            "type":"Services"
        }
    ],
    "sg:phone":"+1 505 885 3699",
    "sg:postcode":"88220",
    "sg:province":"NM",
    "sg:tags":[
        "church"
    ],
    "wof:name":"Temple Beth El",
    "wof:placetype":"venue"
},
  "geometry": {"coordinates":[-104.253676,32.435819],"type":"Point"}
}