{
  "type": "Feature",
  "properties": {
    "iso:country":"US",
    "sg:address":"2300 N White Sands Blvd",
    "sg:city":"Alamogordo",
    "sg:classifiers":[
        {
            "category":"Restaurant",
            "type":"Food & Drink"
        }
    ],
    "sg:phone":"+1 505 443 6102",
    "sg:postcode":"88310",
    "sg:province":"NM",
    "sg:tags":[
        "eating"
    ],
    "wof:name":"Maximinos",
    "wof:placetype":"venue"
},
  "geometry": {"coordinates":[-105.96048399999999,32.919134],"type":"Point"}
}