{
  "type": "Feature",
  "properties": {
    "iso:country":"US",
    "sg:address":"4909 Pso del Norte",
    "sg:city":"Albuquerque",
    "sg:classifiers":[
        {
            "category":"Professional",
            "type":"Services"
        }
    ],
    "sg:phone":"+1 505 856 5663",
    "sg:postcode":"87113",
    "sg:province":"NM",
    "sg:tags":[
        "establishment"
    ],
    "wof:name":"Wolfpack",
    "wof:placetype":"venue"
},
  "geometry": {"coordinates":[-106.60396,35.27905],"type":"Point"}
}