{
  "type": "Feature",
  "properties": {
    "iso:country":"US",
    "sg:address":"205 E Bender Blvd",
    "sg:city":"Hobbs",
    "sg:classifiers":[
        {
            "category":"Professional",
            "subcategory":"Lawyer & Legal Services",
            "type":"Services"
        }
    ],
    "sg:phone":"+1 505 393 0505",
    "sg:postcode":"88240",
    "sg:province":"NM",
    "sg:tags":[
        "attorney"
    ],
    "sg:website":"www.mandhlaw.com",
    "wof:name":"Maddox & Holloman",
    "wof:placetype":"venue"
},
  "geometry": {"coordinates":[-103.134989,32.725635],"type":"Point"}
}