{
  "type": "Feature",
  "properties": {
    "addr:full":"4186 US Hwy 64 Kirtland NM 87417",
    "addr:housenumber":"4186",
    "addr:postcode":"87417",
    "addr:street":"Us Hwy 64",
    "iso:country":"US",
    "sg:address":"4186 US Hwy 64",
    "sg:city":"Kirtland",
    "sg:classifiers":[
        {
            "category":"Shopping",
            "subcategory":"Department Store",
            "type":"Retail Goods"
        }
    ],
    "sg:phone":"+1 505 598 5768",
    "sg:postcode":"87417",
    "sg:province":"NM",
    "wof:name":"Dollar General",
    "wof:placetype":"venue"
},
  "geometry": {"coordinates":[-108.35976100000001,36.74318],"type":"Point"}
}