{
  "type": "Feature",
  "properties": {
    "addr:full":"2220 Lester Ave Las Cruces NM 88001",
    "addr:housenumber":"2220",
    "addr:postcode":"88001",
    "addr:street":"Lester Ave",
    "iso:country":"US",
    "sg:address":"2220 Lester Ave",
    "sg:city":"Las Cruces",
    "sg:classifiers":[
        {
            "category":"Government",
            "subcategory":"Office",
            "type":"Public Place"
        }
    ],
    "sg:phone":"+1 505 527 8695",
    "sg:postcode":"88001",
    "sg:province":"NM",
    "sg:tags":[
        "village"
    ],
    "wof:name":"Dona Ana County Head Start",
    "wof:placetype":"venue"
},
  "geometry": {"coordinates":[-106.74961999999999,32.30511],"type":"Point"}
}