{
  "type": "Feature",
  "properties": {
    "iso:country":"US",
    "sg:address":"8201 Golf Course Rd NW",
    "sg:city":"Albuquerque",
    "sg:classifiers":[
        {
            "category":"Restaurant",
            "type":"Food & Drink"
        }
    ],
    "sg:menulink":"http://www.allmenus.com/nm/albuquerque/256603-super-suppers/menu/",
    "sg:phone":"+1 505 898 9999",
    "sg:postcode":"87120",
    "sg:province":"NM",
    "sg:tags":[
        "new",
        "american"
    ],
    "wof:name":"Super Suppers",
    "wof:placetype":"venue"
},
  "geometry": {"coordinates":[-106.68785800000001,35.177941],"type":"Point"}
}