{
  "type": "Feature",
  "properties": {
    "addr:full":"630 S Dustin Rd Farmington NM 87401",
    "addr:housenumber":"630",
    "addr:postcode":"87401",
    "addr:street":"S Dustin Rd",
    "iso:country":"US",
    "sg:address":"630 S Dustin Rd",
    "sg:city":"Farmington",
    "sg:classifiers":[
        {
            "category":"Building & Trades",
            "subcategory":"Construction",
            "type":"Services"
        }
    ],
    "sg:phone":"+1 505 325 0770",
    "sg:postcode":"87401",
    "sg:province":"NM",
    "sg:tags":[
        "concrete",
        "pumping"
    ],
    "wof:name":"Cornerstone Concrete Pumping",
    "wof:placetype":"venue"
},
  "geometry": {"coordinates":[-108.175488,36.723528],"type":"Point"}
}