{
  "type": "Feature",
  "properties": {
    "iso:country":"US",
    "sg:address":"5651 Galaxy Dr",
    "sg:city":"Las Cruces",
    "sg:classifiers":[
        {
            "category":"Wholesale",
            "subcategory":"Scrap",
            "type":"Manufacturing & Wholesale Goods"
        }
    ],
    "sg:phone":"+1 505 525 0907",
    "sg:postcode":"88012",
    "sg:province":"NM",
    "sg:tags":[
        "recycling",
        "center"
    ],
    "wof:name":"Rios Enterprises",
    "wof:placetype":"venue"
},
  "geometry": {"coordinates":[-106.66095,32.405149],"type":"Point"}
}