{
  "type": "Feature",
  "properties": {
    "addr:full":"201 San Pedro Dr NE Albuquerque NM 87108",
    "addr:housenumber":"201",
    "addr:postcode":"87108",
    "addr:street":"San Pedro Dr Ne",
    "iso:country":"US",
    "sg:address":"201 San Pedro Dr NE",
    "sg:city":"Albuquerque",
    "sg:classifiers":[
        {
            "category":"Banks & Credit Unions",
            "subcategory":"Bank",
            "type":"Services"
        }
    ],
    "sg:phone":"+1 505 254 3746",
    "sg:postcode":"87108",
    "sg:province":"NM",
    "sg:tags":[
        "loan"
    ],
    "wof:name":"Check 'n Go",
    "wof:placetype":"venue"
},
  "geometry": {"coordinates":[-106.577456,35.079644],"type":"Point"}
}