{
  "type": "Feature",
  "properties": {
    "addr:full":"101 S Clark St Gallup NM 87301",
    "addr:housenumber":"101",
    "addr:postcode":"87301",
    "addr:street":"S Clark St",
    "iso:country":"US",
    "sg:address":"101 S Clark St",
    "sg:city":"Gallup",
    "sg:classifiers":[
        {
            "category":"Health Services",
            "subcategory":"Clinic",
            "type":"Services"
        }
    ],
    "sg:phone":"+1 505 863 9929",
    "sg:postcode":"87301",
    "sg:province":"NM",
    "wof:name":"Navajo Aids Network Inc",
    "wof:placetype":"venue"
},
  "geometry": {"coordinates":[-108.760955,35.522176],"type":"Point"}
}