{
  "type": "Feature",
  "properties": {
    "iso:country":"US",
    "sg:address":"201 Browning Pkwy",
    "sg:city":"Farmington",
    "sg:classifiers":[
        {
            "category":"Freight",
            "type":"Transportation"
        }
    ],
    "sg:phone":"+1 505 327 7211",
    "sg:postcode":"87401",
    "sg:province":"NM",
    "sg:tags":[
        "commercial",
        "storage"
    ],
    "wof:name":"Parkway Storage",
    "wof:placetype":"venue"
},
  "geometry": {"coordinates":[-108.16754,36.733388],"type":"Point"}
}