{
  "type": "Feature",
  "properties": {
    "iso:country":"US",
    "sg:address":"121 E Llano Estacado Blvd",
    "sg:city":"Clovis",
    "sg:classifiers":[
        {
            "category":"Health Services",
            "subcategory":"Doctor",
            "type":"Services"
        }
    ],
    "sg:phone":"+1 505 742 3100",
    "sg:postcode":"88101",
    "sg:province":"NM",
    "wof:name":"Powell Family Dentistry",
    "wof:placetype":"venue"
},
  "geometry": {"coordinates":[-103.205119,34.433912],"type":"Point"}
}