{
  "type": "Feature",
  "properties": {
    "addr:full":"8441 Wilson Hurley Pl NE Albuquerque NM 87122",
    "addr:housenumber":"8441",
    "addr:postcode":"87122",
    "addr:street":"Wilson Hurley Pl Ne",
    "iso:country":"US",
    "sg:address":"8441 Wilson Hurley Pl NE",
    "sg:city":"Albuquerque",
    "sg:classifiers":[
        {
            "category":"Airport",
            "type":"Transportation"
        }
    ],
    "sg:phone":"+1 505 856 0686",
    "sg:postcode":"87122",
    "sg:province":"NM",
    "wof:name":"High Desert Fliers L L C",
    "wof:placetype":"venue"
},
  "geometry": {"coordinates":[-106.553816,35.179264],"type":"Point"}
}