{
  "type": "Feature",
  "properties": {
    "addr:full":"202 W Broadway St Hobbs NM 88240",
    "addr:housenumber":"202",
    "addr:postcode":"88240",
    "addr:street":"W Broadway St",
    "iso:country":"US",
    "sg:address":"202 W Broadway St",
    "sg:city":"Hobbs",
    "sg:classifiers":[
        {
            "category":"Shopping",
            "subcategory":"Gifts & Souvenirs",
            "type":"Retail Goods"
        }
    ],
    "sg:phone":"+1 505 393 8711",
    "sg:postcode":"88240",
    "sg:province":"NM",
    "wof:name":"Mysotis Boutique",
    "wof:placetype":"venue"
},
  "geometry": {"coordinates":[-103.138679,32.700878],"type":"Point"}
}