{
  "type": "Feature",
  "properties": {
    "iso:country":"US",
    "sg:address":"2340 S Hwy 28",
    "sg:city":"Las Cruces",
    "sg:classifiers":[
        {
            "category":"Professional",
            "subcategory":"Business Services",
            "type":"Services"
        }
    ],
    "sg:phone":"+1 505 647 9698",
    "sg:postcode":"88005",
    "sg:province":"NM",
    "sg:tags":[
        "information",
        "referral"
    ],
    "wof:name":"Old Mesilla Visitors Ctr",
    "wof:placetype":"venue"
},
  "geometry": {"coordinates":[-106.79431,32.275212],"type":"Point"}
}