{
  "type": "Feature",
  "properties": {
    "iso:country":"US",
    "sg:address":"603 Candelaria Rd NW",
    "sg:city":"Albuquerque",
    "sg:classifiers":[
        {
            "category":"Building & Trades",
            "subcategory":"Construction",
            "type":"Services"
        }
    ],
    "sg:phone":"+1 505 344 8724",
    "sg:postcode":"87107",
    "sg:province":"NM",
    "sg:tags":[
        "general",
        "contractor"
    ],
    "wof:name":"Katewill Construction",
    "wof:placetype":"venue"
},
  "geometry": {"coordinates":[-106.64752900000001,35.120721],"type":"Point"}
}