{
  "type": "Feature",
  "properties": {
    "addr:full":"67 Condesa Rd Santa Fe NM 87508",
    "addr:housenumber":"67",
    "addr:postcode":"87508",
    "addr:street":"Condesa Rd",
    "iso:country":"US",
    "sg:address":"67 Condesa Rd",
    "sg:city":"Santa Fe",
    "sg:classifiers":[
        {
            "category":"Professional",
            "subcategory":"Computer Services",
            "type":"Services"
        }
    ],
    "sg:phone":"+1 505 466 3953",
    "sg:postcode":"87508",
    "sg:province":"NM",
    "sg:tags":[
        "development",
        "technology",
        "sales",
        "research"
    ],
    "wof:name":"Vista Photonics Inc",
    "wof:placetype":"venue"
},
  "geometry": {"coordinates":[-105.914444,35.518716],"type":"Point"}
}