{
  "type": "Feature",
  "properties": {
    "addr:full":"3308 W Hwy 66 Gallup NM 87301",
    "addr:housenumber":"3308",
    "addr:postcode":"87301",
    "addr:street":"W Hwy 66",
    "iso:country":"US",
    "sg:address":"3308 W Hwy 66",
    "sg:city":"Gallup",
    "sg:classifiers":[
        {
            "category":"Autos & Motor Vehicles",
            "subcategory":"Fuel & Gas Station",
            "type":"Retail Goods"
        }
    ],
    "sg:phone":"+1 505 722 4628",
    "sg:postcode":"87301",
    "sg:province":"NM",
    "sg:tags":[
        "oil"
    ],
    "wof:name":"Best Value Freeway Svc Ctr",
    "wof:placetype":"venue"
},
  "geometry": {"coordinates":[-108.827479,35.509014],"type":"Point"}
}