{
  "type": "Feature",
  "properties": {
    "addr:full":"909 N Date St Truth Or Cnsqncs NM 87901",
    "addr:housenumber":"909",
    "addr:postcode":"87901",
    "addr:street":"N Date St",
    "iso:country":"US",
    "sg:address":"909 N Date St",
    "sg:city":"Truth Or Cnsqncs",
    "sg:classifiers":[
        {
            "category":"Personal",
            "subcategory":"Beauty Salon",
            "type":"Services"
        }
    ],
    "sg:phone":"+1 505 894 0775",
    "sg:postcode":"87901",
    "sg:province":"NM",
    "sg:tags":[
        "manicuring"
    ],
    "wof:name":"Michele's Salon & Spa",
    "wof:placetype":"venue"
},
  "geometry": {"coordinates":[-107.25029000000001,33.140242],"type":"Point"}
}