{
  "type": "Feature",
  "properties": {
    "iso:country":"US",
    "sg:address":"7955 N Main St",
    "sg:city":"Las Cruces",
    "sg:classifiers":[
        {
            "category":"Building & Trades",
            "subcategory":"Plumbing",
            "type":"Services"
        }
    ],
    "sg:phone":"+1 505 541 9658",
    "sg:postcode":"88012",
    "sg:province":"NM",
    "sg:tags":[
        "contractor"
    ],
    "wof:name":"Fierro Mechanical",
    "wof:placetype":"venue"
},
  "geometry": {"coordinates":[-106.694299,32.392428],"type":"Point"}
}