{
  "type": "Feature",
  "properties": {
    "iso:country":"US",
    "sg:address":"1803 6th St NW",
    "sg:city":"Albuquerque",
    "sg:classifiers":[
        {
            "category":"Home & Garden",
            "subcategory":"Home Furnishings",
            "type":"Retail Goods"
        }
    ],
    "sg:phone":"+1 505 764 8466",
    "sg:postcode":"87102",
    "sg:province":"NM",
    "sg:tags":[
        "upholstery",
        "fabric"
    ],
    "wof:name":"Design Discount Ctr",
    "wof:placetype":"venue"
},
  "geometry": {"coordinates":[-106.650548,35.103222],"type":"Point"}
}