{
  "type": "Feature",
  "properties": {
    "iso:country":"US",
    "sg:address":"912 Broadway Blvd NE",
    "sg:city":"Albuquerque",
    "sg:classifiers":[
        {
            "category":"Wholesale",
            "subcategory":"Dairy",
            "type":"Manufacturing & Wholesale Goods"
        }
    ],
    "sg:phone":"+1 505 263 5264",
    "sg:postcode":"87102",
    "sg:province":"NM",
    "sg:tags":[
        "product"
    ],
    "wof:name":"Creamies of New Mexico",
    "wof:placetype":"venue"
},
  "geometry": {"coordinates":[-106.642814,35.09263],"type":"Point"}
}