{
  "type": "Feature",
  "properties": {
    "addr:full":"2713 Viola Dr SW Albuquerque NM 87105",
    "addr:housenumber":"2713",
    "addr:postcode":"87105",
    "addr:street":"Viola Dr Sw",
    "iso:country":"US",
    "sg:address":"2713 Viola Dr SW",
    "sg:city":"Albuquerque",
    "sg:classifiers":[
        {
            "category":"Real Estate",
            "subcategory":"Surveying",
            "type":"Services"
        }
    ],
    "sg:phone":"+1 505 842 6579",
    "sg:postcode":"87105",
    "sg:province":"NM",
    "sg:tags":[
        "surveyor"
    ],
    "wof:name":"Marquez Surveying Group",
    "wof:placetype":"venue"
},
  "geometry": {"coordinates":[-106.68745800000001,35.034132],"type":"Point"}
}