{
  "type": "Feature",
  "properties": {
    "iso:country":"US",
    "sg:address":"3801 Arkansas Ave",
    "sg:city":"Los Alamos",
    "sg:classifiers":[
        {
            "category":"Restaurant",
            "type":"Food & Drink"
        }
    ],
    "sg:phone":"+1 505 662 2324",
    "sg:postcode":"87544",
    "sg:province":"NM",
    "sg:tags":[
        "eating"
    ],
    "wof:name":"Tarpons Steak House",
    "wof:placetype":"venue"
},
  "geometry": {"coordinates":[-106.320891,35.900623],"type":"Point"}
}