{
  "type": "Feature",
  "properties": {
    "iso:country":"US",
    "sg:address":"10131 Coors Blvd NW",
    "sg:city":"Albuquerque",
    "sg:classifiers":[
        {
            "category":"Utilities",
            "subcategory":"Mobile Phone",
            "type":"Services"
        }
    ],
    "sg:phone":"+1 505 898 7646",
    "sg:postcode":"87114",
    "sg:province":"NM",
    "sg:tags":[
        "telephone",
        "cellular"
    ],
    "wof:name":"Verizon Wireless",
    "wof:placetype":"venue"
},
  "geometry": {"coordinates":[-106.648961,35.201017],"type":"Point"}
}