{
  "type": "Feature",
  "properties": {
    "addr:full":"300 Daniels St Truth Or Cnsqncs NM 87901",
    "addr:housenumber":"300",
    "addr:postcode":"87901",
    "addr:street":"Daniels St",
    "iso:country":"US",
    "sg:address":"300 Daniels St",
    "sg:city":"Truth Or Cnsqncs",
    "sg:classifiers":[
        {
            "category":"Government",
            "subcategory":"Office",
            "type":"Public Place"
        }
    ],
    "sg:phone":"+1 505 894 4979",
    "sg:postcode":"87901",
    "sg:province":"NM",
    "sg:tags":[
        "village"
    ],
    "wof:name":"Truth Or Consequences Youth",
    "wof:placetype":"venue"
},
  "geometry": {"coordinates":[-107.255645,33.129422],"type":"Point"}
}