{
  "type": "Feature",
  "properties": {
    "iso:country":"US",
    "sg:address":"2101 Trinity Dr",
    "sg:city":"Los Alamos",
    "sg:classifiers":[
        {
            "category":"Retail",
            "subcategory":"Repair Shop",
            "type":"Services"
        }
    ],
    "sg:phone":"+1 505 661 2554",
    "sg:postcode":"87544",
    "sg:province":"NM",
    "sg:tags":[
        "equipment",
        "electronic",
        "supply"
    ],
    "wof:name":"Xerox Corp",
    "wof:placetype":"venue"
},
  "geometry": {"coordinates":[-106.30201599999999,35.879786],"type":"Point"}
}