{
  "type": "Feature",
  "properties": {
    "addr:full":"4600 Mabry Dr Clovis NM 88101",
    "addr:postcode":"4600;88101",
    "addr:street":"Mabry Dr",
    "iso:country":"US",
    "sg:address":"4600 Mabry Dr",
    "sg:city":"Clovis",
    "sg:classifiers":[
        {
            "category":"Manufacturing",
            "subcategory":"Metals",
            "type":"Manufacturing & Wholesale Goods"
        }
    ],
    "sg:phone":"+1 505 763 4414",
    "sg:postcode":"88101",
    "sg:province":"NM",
    "sg:tags":[
        "steel"
    ],
    "wof:name":"Glenco Inc",
    "wof:placetype":"venue"
},
  "geometry": {"coordinates":[-103.150884,34.394533],"type":"Point"}
}