{
  "type": "Feature",
  "properties": {
    "iso:country":"US",
    "sg:address":"1126 Cam Delora",
    "sg:city":"Santa Fe",
    "sg:classifiers":[
        {
            "category":"Professional",
            "type":"Services"
        }
    ],
    "sg:phone":"+1 505 989 8419",
    "sg:postcode":"87505",
    "sg:province":"NM",
    "sg:tags":[
        "arts",
        "artist"
    ],
    "wof:name":"Douglas Atwill Studio",
    "wof:placetype":"venue"
},
  "geometry": {"coordinates":[-105.915873,35.676655],"type":"Point"}
}