{
  "type": "Feature",
  "properties": {
    "iso:country":"US",
    "sg:address":"219 E Maple St",
    "sg:city":"Deming",
    "sg:classifiers":[
        {
            "category":"Manufacturing",
            "subcategory":"Printing",
            "type":"Manufacturing & Wholesale Goods"
        }
    ],
    "sg:phone":"+1 505 546 2611",
    "sg:postcode":"88030",
    "sg:province":"NM",
    "sg:tags":[
        "newspaper"
    ],
    "sg:website":"www.demingheadlight.com",
    "wof:name":"Deming Headlight",
    "wof:placetype":"venue"
},
  "geometry": {"coordinates":[-107.755895,32.26597],"type":"Point"}
}