{
  "type": "Feature",
  "properties": {
    "iso:country":"US",
    "sg:address":"903 W Santa Fe Ave",
    "sg:city":"Grants",
    "sg:classifiers":[
        {
            "category":"Retail",
            "subcategory":"Repair Shop",
            "type":"Services"
        }
    ],
    "sg:phone":"+1 505 287 8664",
    "sg:postcode":"87020",
    "sg:province":"NM",
    "sg:tags":[
        "appliance"
    ],
    "wof:name":"JDS Stamps & Appliance",
    "wof:placetype":"venue"
},
  "geometry": {"coordinates":[-107.858492,35.153802],"type":"Point"}
}