{
  "type": "Feature",
  "properties": {
    "addr:full":"2500 N Valley Dr Las Cruces NM 88007",
    "addr:housenumber":"2500",
    "addr:postcode":"88007",
    "addr:street":"N Valley Dr",
    "iso:country":"US",
    "sg:address":"2500 N Valley Dr",
    "sg:city":"Las Cruces",
    "sg:classifiers":[
        {
            "category":"Food & Beverages",
            "subcategory":"Liquor & Beverages",
            "type":"Retail Goods"
        }
    ],
    "sg:phone":"+1 505 524 6926",
    "sg:postcode":"88007",
    "sg:province":"NM",
    "sg:tags":[
        "alcoholic"
    ],
    "wof:name":"Liquor Company 3",
    "wof:placetype":"venue"
},
  "geometry": {"coordinates":[-106.80895,32.33305],"type":"Point"}
}