{
  "type": "Feature",
  "properties": {
    "iso:country":"US",
    "sg:address":"5013 Heno Mine Rd",
    "sg:city":"Las Cruces",
    "sg:classifiers":[
        {
            "category":"Building & Trades",
            "subcategory":"Construction",
            "type":"Services"
        }
    ],
    "sg:phone":"+1 505 521 3311",
    "sg:postcode":"88011",
    "sg:province":"NM",
    "sg:tags":[
        "house"
    ],
    "wof:name":"Wylie Builders",
    "wof:placetype":"venue"
},
  "geometry": {"coordinates":[-106.63362499999999,32.293928],"type":"Point"}
}