{
  "type": "Feature",
  "properties": {
    "iso:country":"US",
    "sg:address":"223 Pso del Pueblo Sur",
    "sg:city":"Taos",
    "sg:classifiers":[
        {
            "category":"Shopping",
            "subcategory":"Gifts & Souvenirs",
            "type":"Retail Goods"
        }
    ],
    "sg:phone":"+1 505 758 4887",
    "sg:postcode":"87571",
    "sg:province":"NM",
    "sg:tags":[
        "cards",
        "greeting"
    ],
    "wof:name":"Celebrations Cards & Gifts",
    "wof:placetype":"venue"
},
  "geometry": {"coordinates":[-105.574138,36.404348],"type":"Point"}
}