{
  "type": "Feature",
  "properties": {
    "iso:country":"US",
    "sg:address":"10200 Corrales Rd NW",
    "sg:city":"Albuquerque",
    "sg:classifiers":[
        {
            "category":"Sports & Exercise",
            "subcategory":"Gym",
            "type":"Entertainment"
        }
    ],
    "sg:phone":"+1 505 264 9043",
    "sg:postcode":"87114",
    "sg:province":"NM",
    "sg:tags":[
        "club",
        "health",
        "studio",
        "gymnasium"
    ],
    "wof:name":"Why Weight Womens Fitness",
    "wof:placetype":"venue"
},
  "geometry": {"coordinates":[-106.645322,35.205644],"type":"Point"}
}