{
  "type": "Feature",
  "properties": {
    "iso:country":"US",
    "sg:address":"665 Harkle Rd",
    "sg:city":"Santa Fe",
    "sg:classifiers":[
        {
            "category":"Health Services",
            "subcategory":"Doctor",
            "type":"Services"
        }
    ],
    "sg:phone":"+1 505 983 7738",
    "sg:postcode":"87505",
    "sg:province":"NM",
    "sg:tags":[
        "physician",
        "surgeon"
    ],
    "wof:name":"Diabetic Limb Salvage",
    "wof:placetype":"venue"
},
  "geometry": {"coordinates":[-105.95114,35.659206],"type":"Point"}
}