{
  "type": "Feature",
  "properties": {
    "addr:full":"1435 Wyoming Blvd NE Albuquerque NM 87112",
    "addr:housenumber":"1435",
    "addr:postcode":"87112",
    "addr:street":"Wyoming;Ne",
    "iso:country":"US",
    "sg:address":"1435 Wyoming Blvd NE",
    "sg:city":"Albuquerque",
    "sg:classifiers":[
        {
            "category":"Retail",
            "subcategory":"Auto Repair",
            "type":"Services"
        }
    ],
    "sg:phone":"+1 505 271 1993",
    "sg:postcode":"87112",
    "sg:province":"NM",
    "sg:tags":[
        "glass",
        "insurance",
        "replacement"
    ],
    "sg:website":"www.exautoglass.com",
    "wof:name":"Express Auto Glass",
    "wof:placetype":"venue"
},
  "geometry": {"coordinates":[-106.55080100000001,35.096381],"type":"Point"}
}