{
  "type": "Feature",
  "properties": {
    "addr:full":"801 4th St Fort Sumner NM 88119",
    "addr:housenumber":"801",
    "addr:postcode":"88119",
    "addr:street":"4Th St",
    "iso:country":"US",
    "sg:address":"801 4th St",
    "sg:city":"Fort Sumner",
    "sg:classifiers":[
        {
            "category":"Manufacturing",
            "subcategory":"Tools & Machinery",
            "type":"Manufacturing & Wholesale Goods"
        }
    ],
    "sg:phone":"+1 505 355 2622",
    "sg:postcode":"88119",
    "sg:province":"NM",
    "sg:tags":[
        "windmill"
    ],
    "wof:name":"Mitchell's Windmill & Supl Inc",
    "wof:placetype":"venue"
},
  "geometry": {"coordinates":[-104.245446,34.474795],"type":"Point"}
}