{
  "type": "Feature",
  "properties": {
    "iso:country":"US",
    "sg:address":"2205 Sudderth Dr",
    "sg:city":"Ruidoso",
    "sg:classifiers":[
        {
            "category":"Shopping",
            "subcategory":"Bicycles & Sporting Goods",
            "type":"Retail Goods"
        }
    ],
    "sg:phone":"+1 505 630 0435",
    "sg:postcode":"88345",
    "sg:province":"NM",
    "sg:tags":[
        "equipment",
        "outdoor",
        "accessory"
    ],
    "wof:name":"Indoor Outdoor Decor",
    "wof:placetype":"venue"
},
  "geometry": {"coordinates":[-105.668071,33.330979],"type":"Point"}
}