{
  "type": "Feature",
  "properties": {
    "addr:full":"1882 Cam Manzana Los Alamos NM 87544",
    "addr:housenumber":"1882",
    "addr:postcode":"87544",
    "addr:street":"Cam Manzana",
    "iso:country":"US",
    "sg:address":"1882 Cam Manzana",
    "sg:city":"Los Alamos",
    "sg:classifiers":[
        {
            "category":"Professional",
            "subcategory":"Computer Services",
            "type":"Services"
        }
    ],
    "sg:phone":"+1 505 662 5622",
    "sg:postcode":"87544",
    "sg:province":"NM",
    "sg:tags":[
        "related"
    ],
    "wof:name":"Lynne Williams",
    "wof:placetype":"venue"
},
  "geometry": {"coordinates":[-106.293036,35.89138],"type":"Point"}
}