{
  "type": "Feature",
  "properties": {
    "iso:country":"US",
    "sg:address":"425 Oakmont Pl",
    "sg:city":"Alamogordo",
    "sg:classifiers":[
        {
            "category":"Building & Trades",
            "subcategory":"Construction",
            "type":"Services"
        }
    ],
    "sg:phone":"+1 505 437 4196",
    "sg:postcode":"88310",
    "sg:province":"NM",
    "sg:tags":[
        "residential",
        "general",
        "contractor"
    ],
    "wof:name":"R & V Construction",
    "wof:placetype":"venue"
},
  "geometry": {"coordinates":[-105.956463,32.856282],"type":"Point"}
}