{
  "type": "Feature",
  "properties": {
    "iso:country":"US",
    "sg:address":"1839 Wilmoore Dr SE",
    "sg:city":"Albuquerque",
    "sg:classifiers":[
        {
            "category":"Retail",
            "subcategory":"Auto Repair",
            "type":"Services"
        }
    ],
    "sg:phone":"+1 505 243 5820",
    "sg:postcode":"87106",
    "sg:province":"NM",
    "sg:tags":[
        "body"
    ],
    "wof:name":"Gilbert M Casaus",
    "wof:placetype":"venue"
},
  "geometry": {"coordinates":[-106.623282,35.060788],"type":"Point"}
}