{
  "type": "Feature",
  "properties": {
    "iso:country":"US",
    "sg:address":"3107 N Main St",
    "sg:city":"Roswell",
    "sg:classifiers":[
        {
            "category":"Professional",
            "subcategory":"Computer Services",
            "type":"Services"
        }
    ],
    "sg:phone":"+1 505 624 7700",
    "sg:postcode":"88201",
    "sg:province":"NM",
    "sg:tags":[
        "internet"
    ],
    "wof:name":"Plateau Long Distance",
    "wof:placetype":"venue"
},
  "geometry": {"coordinates":[-104.522952,33.433954],"type":"Point"}
}