{
  "type": "Feature",
  "properties": {
    "addr:full":"4204 Hahn Ct NE Albuquerque NM 87110",
    "addr:housenumber":"4204",
    "addr:postcode":"87110",
    "addr:street":"Hahn Ct Ne",
    "iso:country":"US",
    "sg:address":"4204 Hahn Ct NE",
    "sg:city":"Albuquerque",
    "sg:classifiers":[
        {
            "category":"Building & Trades",
            "subcategory":"Construction",
            "type":"Services"
        }
    ],
    "sg:phone":"+1 505 881 2332",
    "sg:postcode":"87110",
    "sg:province":"NM",
    "sg:tags":[
        "general"
    ],
    "wof:name":"Prairie Construction Co Inc",
    "wof:placetype":"venue"
},
  "geometry": {"coordinates":[-106.598685,35.128348],"type":"Point"}
}