{
  "type": "Feature",
  "properties": {
    "iso:country":"US",
    "sg:address":"1955 N Solano Dr",
    "sg:city":"Las Cruces",
    "sg:classifiers":[
        {
            "category":"Retail",
            "subcategory":"Auto Repair",
            "type":"Services"
        }
    ],
    "sg:phone":"+1 505 523 6068",
    "sg:postcode":"88001",
    "sg:province":"NM",
    "sg:tags":[
        "repairing",
        "automobile"
    ],
    "wof:name":"Gary's Auto Repair",
    "wof:placetype":"venue"
},
  "geometry": {"coordinates":[-106.77872600000001,32.327298],"type":"Point"}
}