{
  "type": "Feature",
  "properties": {
    "iso:country":"US",
    "sg:address":"97 E Frontage Rd",
    "sg:city":"Santa Fe",
    "sg:classifiers":[
        {
            "category":"Building & Trades",
            "subcategory":"Construction",
            "type":"Services"
        }
    ],
    "sg:phone":"+1 505 473 3897",
    "sg:postcode":"87508",
    "sg:province":"NM",
    "sg:tags":[
        "general",
        "contractor"
    ],
    "wof:name":"Summit Builders Inc",
    "wof:placetype":"venue"
},
  "geometry": {"coordinates":[-106.035706,35.599492],"type":"Point"}
}