{
  "type": "Feature",
  "properties": {
    "iso:country":"US",
    "sg:address":"215 W San Francisco St",
    "sg:city":"Santa Fe",
    "sg:classifiers":[
        {
            "category":"Professional",
            "subcategory":"Advertising",
            "type":"Services"
        }
    ],
    "sg:phone":"+1 505 986 3400",
    "sg:postcode":"87501",
    "sg:province":"NM",
    "sg:tags":[
        "counselor"
    ],
    "wof:name":"Circus Inc",
    "wof:placetype":"venue"
},
  "geometry": {"coordinates":[-105.942947,35.68823],"type":"Point"}
}