{
  "type": "Feature",
  "properties": {
    "iso:country":"US",
    "sg:address":"150 State Rd 344",
    "sg:city":"Edgewood",
    "sg:classifiers":[
        {
            "category":"Food & Beverages",
            "subcategory":"Groceries & Convenience Stores",
            "type":"Retail Goods"
        }
    ],
    "sg:phone":"+1 505 286 3800",
    "sg:postcode":"87015",
    "sg:province":"NM",
    "sg:tags":[
        "grocer"
    ],
    "wof:name":"John Brooks Value-Way",
    "wof:placetype":"venue"
},
  "geometry": {"coordinates":[-106.191416,35.08328],"type":"Point"}
}