{
  "type": "Feature",
  "properties": {
    "iso:country":"US",
    "sg:address":"115 Rodriquez St",
    "sg:city":"Santa Fe",
    "sg:classifiers":[
        {
            "category":"Professional",
            "subcategory":"Business Services",
            "type":"Services"
        }
    ],
    "sg:phone":"+1 505 983 3344",
    "sg:postcode":"87501",
    "sg:province":"NM",
    "wof:name":"Common Ground Mediation Svcs",
    "wof:placetype":"venue"
},
  "geometry": {"coordinates":[-105.92722000000001,35.686139],"type":"Point"}
}