{
  "type": "Feature",
  "properties": {
    "addr:full":"1700 S Gold Ave Deming NM 88030",
    "addr:housenumber":"1700",
    "addr:postcode":"88030",
    "addr:street":"S Gold Ave",
    "iso:country":"US",
    "sg:address":"1700 S Gold Ave",
    "sg:city":"Deming",
    "sg:classifiers":[
        {
            "category":"Communications",
            "subcategory":"Radio Station",
            "type":"Services"
        }
    ],
    "sg:phone":"+1 505 546 9011",
    "sg:postcode":"88030",
    "sg:province":"NM",
    "sg:tags":[
        "company",
        "broadcasting"
    ],
    "wof:name":"KDEM",
    "wof:placetype":"venue"
},
  "geometry": {"coordinates":[-107.75749,32.252029],"type":"Point"}
}