{
  "type": "Feature",
  "properties": {
    "addr:full":"205 E 7th St Roswell NM 88201",
    "addr:housenumber":"205",
    "addr:postcode":"88201",
    "addr:street":"E 7Th St",
    "iso:country":"US",
    "sg:address":"205 E 7th St",
    "sg:city":"Roswell",
    "sg:classifiers":[
        {
            "category":"Professional",
            "subcategory":"Business Services",
            "type":"Services"
        }
    ],
    "sg:phone":"+1 505 623 7355",
    "sg:postcode":"88201",
    "sg:province":"NM",
    "sg:tags":[
        "auctioneer"
    ],
    "wof:name":"Wild West Auctions",
    "wof:placetype":"venue"
},
  "geometry": {"coordinates":[-104.520332,33.400007],"type":"Point"}
}