{
  "type": "Feature",
  "properties": {
    "addr:full":"601 W 2nd St Roswell NM 88201",
    "addr:housenumber":"601",
    "addr:postcode":"88201",
    "addr:street":"W 2Nd St",
    "iso:country":"US",
    "sg:address":"601 W 2nd St",
    "sg:city":"Roswell",
    "sg:classifiers":[
        {
            "category":"Insurance",
            "subcategory":"Insurance Agent",
            "type":"Services"
        }
    ],
    "sg:phone":"+1 505 624 0404",
    "sg:postcode":"88201",
    "sg:province":"NM",
    "wof:name":"Brown & Brown Insurance",
    "wof:placetype":"venue"
},
  "geometry": {"coordinates":[-104.53178200000001,33.394247],"type":"Point"}
}