{
  "type": "Feature",
  "properties": {
    "iso:country":"US",
    "sg:address":"1350 Pso del Pueblo Sur",
    "sg:city":"Taos",
    "sg:classifiers":[
        {
            "category":"Shopping",
            "type":"Retail Goods"
        }
    ],
    "sg:phone":"+1 505 751 9327",
    "sg:postcode":"87571",
    "sg:province":"NM",
    "sg:tags":[
        "hearing",
        "equipment",
        "supply",
        "impaired"
    ],
    "wof:name":"Premier Hearing Ctr",
    "wof:placetype":"venue"
},
  "geometry": {"coordinates":[-105.595674,36.371346],"type":"Point"}
}