{
  "type": "Feature",
  "properties": {
    "iso:country":"US",
    "sg:address":"5115 Headingly Ave NE",
    "sg:city":"Albuquerque",
    "sg:classifiers":[
        {
            "category":"Shopping",
            "subcategory":"Department Store",
            "type":"Retail Goods"
        }
    ],
    "sg:phone":"+1 505 883 8068",
    "sg:postcode":"87110",
    "sg:province":"NM",
    "wof:name":"Pixie Inc",
    "wof:placetype":"venue"
},
  "geometry": {"coordinates":[-106.586544,35.12093],"type":"Point"}
}