{
  "type": "Feature",
  "properties": {
    "iso:country":"US",
    "sg:address":"901 N Tucker Ave",
    "sg:city":"Farmington",
    "sg:classifiers":[
        {
            "category":"Professional",
            "subcategory":"Accounting & Tax Preparation",
            "type":"Services"
        }
    ],
    "sg:phone":"+1 505 327 0266",
    "sg:postcode":"87401",
    "sg:province":"NM",
    "sg:tags":[
        "accountant"
    ],
    "wof:name":"Solga & Jakino",
    "wof:placetype":"venue"
},
  "geometry": {"coordinates":[-108.17758499999999,36.740108],"type":"Point"}
}