{
  "type": "Feature",
  "properties": {
    "iso:country":"US",
    "sg:address":"220 W Walnut St",
    "sg:city":"Deming",
    "sg:classifiers":[
        {
            "category":"Building & Trades",
            "subcategory":"Construction",
            "type":"Services"
        }
    ],
    "sg:phone":"+1 505 546 6761",
    "sg:postcode":"88030",
    "sg:province":"NM",
    "sg:tags":[
        "industrial",
        "commercial",
        "mechanical"
    ],
    "wof:name":"Crg International",
    "wof:placetype":"venue"
},
  "geometry": {"coordinates":[-107.759156,32.257014],"type":"Point"}
}