{
  "type": "Feature",
  "properties": {
    "addr:full":"8512 Rio Grande Blvd NW Albuquerque NM 87114",
    "addr:housenumber":"8512",
    "addr:postcode":"87114",
    "addr:street":"Rio Grande Blvd Nw",
    "iso:country":"US",
    "sg:address":"8512 Rio Grande Blvd NW",
    "sg:city":"Albuquerque",
    "sg:classifiers":[
        {
            "category":"Travel",
            "subcategory":"Travel Agent",
            "type":"Entertainment"
        }
    ],
    "sg:phone":"+1 505 293 2686",
    "sg:postcode":"87114",
    "sg:province":"NM",
    "sg:tags":[
        "agency"
    ],
    "wof:name":"Travel Club Of New Mexico",
    "wof:placetype":"venue"
},
  "geometry": {"coordinates":[-106.64421,35.179818],"type":"Point"}
}