{
  "type": "Feature",
  "properties": {
    "iso:country":"US",
    "sg:address":"2311 Edith Blvd SE",
    "sg:city":"Albuquerque",
    "sg:classifiers":[
        {
            "category":"Building & Trades",
            "subcategory":"Construction",
            "type":"Services"
        }
    ],
    "sg:phone":"+1 505 242 7799",
    "sg:postcode":"87102",
    "sg:province":"NM",
    "sg:tags":[
        "concrete",
        "contractor"
    ],
    "wof:name":"Associated Concrete Cutting",
    "wof:placetype":"venue"
},
  "geometry": {"coordinates":[-106.642769,35.058952],"type":"Point"}
}