{
  "type": "Feature",
  "properties": {
    "iso:country":"US",
    "sg:address":"2201 San Pedro Dr NE",
    "sg:city":"Albuquerque",
    "sg:classifiers":[
        {
            "category":"Professional",
            "subcategory":"Management & Consulting",
            "type":"Services"
        }
    ],
    "sg:phone":"+1 505 888 1939",
    "sg:postcode":"87110",
    "sg:province":"NM",
    "wof:name":"Barry Hatcher American Express",
    "wof:placetype":"venue"
},
  "geometry": {"coordinates":[-106.577568,35.100884],"type":"Point"}
}