{
  "type": "Feature",
  "properties": {
    "iso:country":"US",
    "sg:address":"2417 W Pierce St",
    "sg:city":"Carlsbad",
    "sg:classifiers":[
        {
            "category":"Food & Beverages",
            "subcategory":"Groceries & Convenience Stores",
            "type":"Retail Goods"
        }
    ],
    "sg:phone":"+1 505 885 1168",
    "sg:postcode":"88220",
    "sg:province":"NM",
    "sg:website":"www.allsups.com",
    "wof:name":"Allsup's Convenience Store",
    "wof:placetype":"venue"
},
  "geometry": {"coordinates":[-104.257368,32.440606],"type":"Point"}
}