{
  "type": "Feature",
  "properties": {
    "iso:country":"US",
    "sg:address":"805 Maria Ct SE",
    "sg:city":"Rio Rancho",
    "sg:classifiers":[
        {
            "category":"Professional",
            "type":"Services"
        }
    ],
    "sg:phone":"+1 505 892 1347",
    "sg:postcode":"87124",
    "sg:province":"NM",
    "wof:name":"Tammaro Home Services",
    "wof:placetype":"venue"
},
  "geometry": {"coordinates":[-106.646523,35.244142],"type":"Point"}
}