{
  "type": "Feature",
  "properties": {
    "iso:country":"US",
    "sg:address":"110 E Corbett St",
    "sg:city":"Hobbs",
    "sg:classifiers":[
        {
            "category":"Real Estate",
            "subcategory":"Real Estate Operator",
            "type":"Services"
        }
    ],
    "sg:phone":"+1 505 393 6875",
    "sg:postcode":"88240",
    "sg:province":"NM",
    "sg:tags":[
        "apartment"
    ],
    "wof:name":"Rex Arms Apartments",
    "wof:placetype":"venue"
},
  "geometry": {"coordinates":[-103.136115,32.71028],"type":"Point"}
}