{
  "type": "Feature",
  "properties": {
    "addr:full":"10211 San Luis Rey Pl NE Albuquerque NM 87111",
    "addr:housenumber":"10211",
    "addr:postcode":"87111",
    "addr:street":"San Luis Rey Pl Ne",
    "iso:country":"US",
    "sg:address":"10211 San Luis Rey Pl NE",
    "sg:city":"Albuquerque",
    "sg:classifiers":[
        {
            "category":"Real Estate",
            "subcategory":"Real Estate Agent",
            "type":"Services"
        }
    ],
    "sg:phone":"+1 505 292 4828",
    "sg:postcode":"87111",
    "sg:province":"NM",
    "sg:tags":[
        "broker"
    ],
    "wof:name":"Bill Posen Realty",
    "wof:placetype":"venue"
},
  "geometry": {"coordinates":[-106.525284,35.12655],"type":"Point"}
}