{
  "type": "Feature",
  "properties": {
    "iso:country":"US",
    "sg:address":"2020 Menaul Blvd NE",
    "sg:city":"Albuquerque",
    "sg:classifiers":[
        {
            "category":"Shopping",
            "subcategory":"Gifts & Souvenirs",
            "type":"Retail Goods"
        }
    ],
    "sg:phone":"+1 505 888 5893",
    "sg:postcode":"87107",
    "sg:province":"NM",
    "sg:tags":[
        "shop"
    ],
    "wof:name":"Vista Gift Shop",
    "wof:placetype":"venue"
},
  "geometry": {"coordinates":[-106.62216100000001,35.109085],"type":"Point"}
}