{
  "type": "Feature",
  "properties": {
    "addr:full":"5600 Wyoming Blvd NE Albuquerque NM 87109",
    "addr:housenumber":"5600",
    "addr:postcode":"87109",
    "addr:street":"Wyoming;Ne",
    "iso:country":"US",
    "sg:address":"5600 Wyoming Blvd NE",
    "sg:city":"Albuquerque",
    "sg:classifiers":[
        {
            "category":"Real Estate",
            "subcategory":"Real Estate Agent",
            "type":"Services"
        }
    ],
    "sg:phone":"+1 505 293 1156",
    "sg:postcode":"87109",
    "sg:province":"NM",
    "sg:tags":[
        "management"
    ],
    "wof:name":"Tecumseh Professional Assoc",
    "wof:placetype":"venue"
},
  "geometry": {"coordinates":[-106.553425,35.145519],"type":"Point"}
}