{
  "type": "Feature",
  "properties": {
    "iso:country":"US",
    "sg:address":"2089 Cll Lorca",
    "sg:city":"Santa Fe",
    "sg:classifiers":[
        {
            "category":"Banks & Credit Unions",
            "subcategory":"Bank",
            "type":"Services"
        }
    ],
    "sg:phone":"+1 505 474 3738",
    "sg:postcode":"87505",
    "sg:province":"NM",
    "sg:tags":[
        "mortgage"
    ],
    "wof:name":"Ben Cox",
    "wof:placetype":"venue"
},
  "geometry": {"coordinates":[-105.96390599999999,35.654396],"type":"Point"}
}