{
  "type": "Feature",
  "properties": {
    "addr:full":"2215 E Seminole Hwy Hobbs NM 88240",
    "addr:housenumber":"2215",
    "addr:postcode":"88240",
    "addr:street":"E Seminole Hwy",
    "iso:country":"US",
    "sg:address":"2215 E Seminole Hwy",
    "sg:city":"Hobbs",
    "sg:classifiers":[
        {
            "category":"Autos & Motor Vehicles",
            "subcategory":"Auto Supplies",
            "type":"Retail Goods"
        }
    ],
    "sg:phone":"+1 505 393 4572",
    "sg:postcode":"88240",
    "sg:province":"NM",
    "sg:tags":[
        "tire"
    ],
    "sg:website":"www.atoztire.com",
    "wof:name":"A To Z Tire & Battery Co",
    "wof:placetype":"venue"
},
  "geometry": {"coordinates":[-103.09727599999999,32.725381],"type":"Point"}
}