{
  "type": "Feature",
  "properties": {
    "iso:country":"US",
    "sg:address":"223 Chico Dr",
    "sg:city":"Las Vegas",
    "sg:classifiers":[
        {
            "category":"Building & Trades",
            "subcategory":"Construction",
            "type":"Services"
        }
    ],
    "sg:phone":"+1 505 425 8240",
    "sg:postcode":"87701",
    "sg:province":"NM",
    "sg:tags":[
        "general",
        "contractor"
    ],
    "wof:name":"L A Construction",
    "wof:placetype":"venue"
},
  "geometry": {"coordinates":[-105.21310200000001,35.625179],"type":"Point"}
}