{
  "type": "Feature",
  "properties": {
    "iso:country":"US",
    "sg:address":"10519 Portofino Dr NW",
    "sg:city":"Albuquerque",
    "sg:classifiers":[
        {
            "category":"Real Estate",
            "subcategory":"Real Estate Agent",
            "type":"Services"
        }
    ],
    "sg:phone":"+1 505 898 9000",
    "sg:postcode":"87114",
    "sg:province":"NM",
    "wof:name":"Home Authority",
    "wof:placetype":"venue"
},
  "geometry": {"coordinates":[-106.69081799999999,35.206918],"type":"Point"}
}