{
  "type": "Feature",
  "properties": {
    "iso:country":"US",
    "sg:address":"700 Coronado Ctr",
    "sg:city":"Albuquerque",
    "sg:classifiers":[
        {
            "category":"Shopping",
            "subcategory":"Department Store",
            "type":"Retail Goods"
        },
        {
            "category":"Shopping",
            "subcategory":"Beauty & Cosmetics",
            "type":"Retail Goods"
        },
        {
            "category":"Home & Garden",
            "subcategory":"Home Furnishings",
            "type":"Retail Goods"
        },
        {
            "category":"Shopping",
            "type":"Retail Goods"
        },
        {
            "category":"Shopping",
            "subcategory":"Catalog Store",
            "type":"Retail Goods"
        },
        {
            "category":"Professional",
            "subcategory":"Art Services",
            "type":"Services"
        },
        {
            "category":"Shopping",
            "subcategory":"Shoes",
            "type":"Retail Goods"
        },
        {
            "category":"Shopping",
            "subcategory":"Jewelry",
            "type":"Retail Goods"
        }
    ],
    "sg:phone":"+1 505 888 4668",
    "sg:postcode":"87110",
    "sg:province":"NM",
    "sg:tags":[
        "draperies",
        "designer",
        "vertical",
        "supply",
        "merchandise",
        "blinds-venetian",
        "jeweler",
        "equipment",
        "window",
        "interior",
        "treatment",
        "housewares",
        "curtain",
        "showroom",
        "decorator"
    ],
    "wof:name":"JCPenney Optical Center",
    "wof:placetype":"venue"
},
  "geometry": {"coordinates":[-106.574417,35.108879],"type":"Point"}
}