{
  "type": "Feature",
  "properties": {
    "iso:country":"US",
    "sg:address":"4200 Lomas Blvd NE",
    "sg:city":"Albuquerque",
    "sg:classifiers":[
        {
            "category":"Personal",
            "subcategory":"Beauty Salon",
            "type":"Services"
        }
    ],
    "sg:phone":"+1 505 228 3897",
    "sg:postcode":"87110",
    "sg:province":"NM",
    "sg:tags":[
        "nail",
        "shop"
    ],
    "wof:name":"Nails By Jahna",
    "wof:placetype":"venue"
},
  "geometry": {"coordinates":[-106.597967,35.087391],"type":"Point"}
}