{
  "type": "Feature",
  "properties": {
    "iso:country":"US",
    "sg:address":"7801 Tiburon St NE",
    "sg:city":"Albuquerque",
    "sg:classifiers":[
        {
            "category":"Wholesale",
            "subcategory":"Medical Equipment & Supplies",
            "type":"Manufacturing & Wholesale Goods"
        },
        {
            "category":"Home & Garden",
            "subcategory":"Building Materials",
            "type":"Retail Goods"
        },
        {
            "category":"Building & Trades",
            "subcategory":"Construction",
            "type":"Services"
        },
        {
            "category":"Home & Garden",
            "subcategory":"Carpets & Floor Coverings",
            "type":"Retail Goods"
        }
    ],
    "sg:phone":"+1 505 823 2700",
    "sg:postcode":"87109",
    "sg:province":"NM",
    "sg:tags":[
        "structure",
        "trusses-construction",
        "truss",
        "lumber-used",
        "roof"
    ],
    "sg:website":"http://www.probuild.com",
    "wof:name":"Probuild South",
    "wof:placetype":"venue"
},
  "geometry": {"coordinates":[-106.593476,35.171649],"type":"Point"}
}