{
  "type": "Feature",
  "properties": {
    "addr:full":"2804 Morton Rd SW Albuquerque NM 87105",
    "addr:housenumber":"2804",
    "addr:postcode":"87105",
    "addr:street":"Morton Rd Sw",
    "iso:country":"US",
    "sg:address":"2804 Morton Rd SW",
    "sg:city":"Albuquerque",
    "sg:classifiers":[
        {
            "category":"Building & Trades",
            "subcategory":"Pest Control",
            "type":"Services"
        }
    ],
    "sg:phone":"+1 505 873 0266",
    "sg:postcode":"87105",
    "sg:province":"NM",
    "wof:name":"Reliable Pest Control",
    "wof:placetype":"venue"
},
  "geometry": {"coordinates":[-106.711952,34.981353],"type":"Point"}
}