{
  "type": "Feature",
  "properties": {
    "addr:full":"3205 Central Ave SE Albuquerque NM 87106",
    "addr:housenumber":"3205",
    "addr:postcode":"87106",
    "addr:street":"Central Ave Se",
    "iso:country":"US",
    "sg:address":"3205 Central Ave SE",
    "sg:city":"Albuquerque",
    "sg:classifiers":[
        {
            "category":"Shopping",
            "subcategory":"Jewelry",
            "type":"Retail Goods"
        }
    ],
    "sg:phone":"+1 505 265 4147",
    "sg:postcode":"87106",
    "sg:province":"NM",
    "sg:tags":[
        "jeweler"
    ],
    "wof:name":"Lilly Barrack Jewelry & Gifts",
    "wof:placetype":"venue"
},
  "geometry": {"coordinates":[-106.608318,35.080378],"type":"Point"}
}