{
  "type": "Feature",
  "properties": {
    "iso:country":"US",
    "sg:address":"908 N Date St",
    "sg:city":"Truth Or Cnsqncs",
    "sg:classifiers":[
        {
            "category":"Wholesale",
            "subcategory":"Farm Supplies",
            "type":"Manufacturing & Wholesale Goods"
        }
    ],
    "sg:phone":"+1 505 894 6382",
    "sg:postcode":"87901",
    "sg:province":"NM",
    "sg:tags":[
        "feed"
    ],
    "wof:name":"H & O Tires & Feeds",
    "wof:placetype":"venue"
},
  "geometry": {"coordinates":[-107.250438,33.140265],"type":"Point"}
}