{
  "type": "Feature",
  "properties": {
    "iso:country":"US",
    "sg:address":"234 N Schwartz Ave",
    "sg:city":"Farmington",
    "sg:classifiers":[
        {
            "category":"Banks & Credit Unions",
            "subcategory":"Bank",
            "type":"Services"
        }
    ],
    "sg:phone":"+1 505 325 0040",
    "sg:postcode":"87401",
    "sg:province":"NM",
    "sg:tags":[
        "loan",
        "real estate"
    ],
    "wof:name":"San Juan Mortgage Inc",
    "wof:placetype":"venue"
},
  "geometry": {"coordinates":[-108.214052,36.730686],"type":"Point"}
}