{
  "type": "Feature",
  "properties": {
    "iso:country":"US",
    "sg:address":"3351 Candelaria Rd NE",
    "sg:city":"Albuquerque",
    "sg:classifiers":[
        {
            "category":"Wholesale",
            "subcategory":"Electrical",
            "type":"Manufacturing & Wholesale Goods"
        }
    ],
    "sg:phone":"+1 505 842 0553",
    "sg:postcode":"87107",
    "sg:province":"NM",
    "sg:tags":[
        "alarm",
        "burglar",
        "system"
    ],
    "wof:name":"Protection One Inc",
    "wof:placetype":"venue"
},
  "geometry": {"coordinates":[-106.609441,35.116619],"type":"Point"}
}