{
  "type": "Feature",
  "properties": {
    "iso:country":"US",
    "sg:address":"10108 Cochiti Rd SE",
    "sg:city":"Albuquerque",
    "sg:classifiers":[
        {
            "category":"Manufacturing",
            "subcategory":"Tools & Machinery",
            "type":"Manufacturing & Wholesale Goods"
        }
    ],
    "sg:phone":"+1 505 296 3425",
    "sg:postcode":"87123",
    "sg:province":"NM",
    "sg:tags":[
        "shop",
        "sheet",
        "work",
        "metal",
        "precision",
        "machine"
    ],
    "wof:name":"Precision Components Inc",
    "wof:placetype":"venue"
},
  "geometry": {"coordinates":[-106.532567,35.070737],"type":"Point"}
}