{
  "type": "Feature",
  "properties": {
    "addr:full":"2925 Huntington Dr Las Cruces NM 88011",
    "addr:housenumber":"2925",
    "addr:postcode":"88011",
    "addr:street":"Huntington Dr",
    "iso:country":"US",
    "sg:address":"2925 Huntington Dr",
    "sg:city":"Las Cruces",
    "sg:classifiers":[
        {
            "category":"Professional",
            "subcategory":"Lawyer & Legal Services",
            "type":"Services"
        }
    ],
    "sg:phone":"+1 505 522 0765",
    "sg:postcode":"88011",
    "sg:province":"NM",
    "sg:tags":[
        "attorney"
    ],
    "sg:website":"www.richgregory.com",
    "wof:name":"Richard B Gregory",
    "wof:placetype":"venue"
},
  "geometry": {"coordinates":[-106.73482300000001,32.297726],"type":"Point"}
}