{
  "type": "Feature",
  "properties": {
    "iso:country":"US",
    "sg:address":"904 Moore Ave",
    "sg:city":"Roswell",
    "sg:classifiers":[
        {
            "category":"Professional",
            "subcategory":"Management & Consulting",
            "type":"Services"
        }
    ],
    "sg:phone":"+1 505 626 4518",
    "sg:postcode":"88201",
    "sg:province":"NM",
    "sg:tags":[
        "investigation",
        "cite"
    ],
    "wof:name":"Geoscience Technologies",
    "wof:placetype":"venue"
},
  "geometry": {"coordinates":[-104.568175,33.402016],"type":"Point"}
}