{
  "type": "Feature",
  "properties": {
    "iso:country":"US",
    "sg:address":"1219 Luisa St",
    "sg:city":"Santa Fe",
    "sg:classifiers":[
        {
            "category":"Organizations",
            "subcategory":"Membership Organization",
            "type":"Services"
        }
    ],
    "sg:phone":"+1 505 986 0583",
    "sg:postcode":"87505",
    "sg:province":"NM",
    "wof:name":"Bienvenidos Outreach Program",
    "wof:placetype":"venue"
},
  "geometry": {"coordinates":[-105.950205,35.671457],"type":"Point"}
}