{
  "type": "Feature",
  "properties": {
    "addr:full":"435 S Telshor Blvd Las Cruces NM 88011",
    "addr:housenumber":"435",
    "addr:postcode":"88011",
    "addr:street":"S Telshor Blvd",
    "iso:country":"US",
    "sg:address":"435 S Telshor Blvd",
    "sg:city":"Las Cruces",
    "sg:classifiers":[
        {
            "category":"Restaurant",
            "type":"Food & Drink"
        }
    ],
    "sg:menulink":"http://www.allmenus.com/nm/las-cruces/183661-kfc---kentucky-fried-chicken/menu/",
    "sg:phone":"+1 505 522 8486",
    "sg:postcode":"88011",
    "sg:province":"NM",
    "sg:tags":[
        "american",
        "chicken"
    ],
    "wof:name":"KFC - Kentucky Fried Chicken",
    "wof:placetype":"venue"
},
  "geometry": {"coordinates":[-106.747196,32.316355],"type":"Point"}
}