{
  "type": "Feature",
  "properties": {
    "iso:country":"US",
    "sg:address":"4609 Norma Dr NE",
    "sg:city":"Albuquerque",
    "sg:classifiers":[
        {
            "category":"Education",
            "subcategory":"Vocational School",
            "type":"Public Place"
        }
    ],
    "sg:phone":"+1 505 272 0654",
    "sg:postcode":"87109",
    "sg:province":"NM",
    "sg:tags":[
        "on",
        "training",
        "database",
        "searching",
        "evidence",
        "professional"
    ],
    "wof:name":"Jonathan Eldredge",
    "wof:placetype":"venue"
},
  "geometry": {"coordinates":[-106.553117,35.131689],"type":"Point"}
}