{
  "type": "Feature",
  "properties": {
    "addr:full":"824 US Hwy 60 Socorro NM 87801",
    "addr:housenumber":"824",
    "addr:postcode":"87801",
    "addr:street":"Us Hwy 60",
    "iso:country":"US",
    "sg:address":"824 US Hwy 60",
    "sg:city":"Socorro",
    "sg:classifiers":[
        {
            "category":"Health Services",
            "subcategory":"Doctor",
            "type":"Services"
        }
    ],
    "sg:phone":"+1 505 835 2342",
    "sg:postcode":"87801",
    "sg:province":"NM",
    "sg:tags":[
        "dentist"
    ],
    "wof:name":"Caring Dental Ctr",
    "wof:placetype":"venue"
},
  "geometry": {"coordinates":[-106.90057400000001,34.052246],"type":"Point"}
}