{
  "type": "Feature",
  "properties": {
    "iso:country":"US",
    "sg:address":"824 US Hwy 60",
    "sg:city":"Socorro",
    "sg:classifiers":[
        {
            "category":"Health Services",
            "subcategory":"Doctor",
            "type":"Services"
        }
    ],
    "sg:phone":"+1 505 835 2342",
    "sg:postcode":"87801",
    "sg:province":"NM",
    "sg:tags":[
        "dentist"
    ],
    "wof:name":"Caring Dental Ctr",
    "wof:placetype":"venue"
},
  "geometry": {"coordinates":[-106.900574,34.052246],"type":"Point"}
}