{
  "type": "Feature",
  "properties": {
    "addr:full":"1040 Cypress Rd Bosque Farms NM 87068",
    "addr:housenumber":"1040",
    "addr:postcode":"87068",
    "addr:street":"Cypress Rd",
    "iso:country":"US",
    "sg:address":"1040 Cypress Rd",
    "sg:city":"Bosque Farms",
    "sg:classifiers":[
        {
            "category":"Building & Trades",
            "subcategory":"Electrical",
            "type":"Services"
        }
    ],
    "sg:phone":"+1 505 453 1213",
    "sg:postcode":"87068",
    "sg:province":"NM",
    "sg:tags":[
        "electric",
        "contractor"
    ],
    "wof:name":"SRS Electric",
    "wof:placetype":"venue"
},
  "geometry": {"coordinates":[-106.703064,34.836265],"type":"Point"}
}