{
  "type": "Feature",
  "properties": {
    "iso:country":"US",
    "sg:address":"44 Gilbert Pl",
    "sg:city":"Sandia Park",
    "sg:classifiers":[
        {
            "category":"Retail",
            "subcategory":"Repair Shop",
            "type":"Services"
        }
    ],
    "sg:phone":"+1 505 263 6018",
    "sg:postcode":"87047",
    "sg:province":"NM",
    "sg:tags":[
        "repairing",
        "equipment",
        "electric"
    ],
    "wof:name":"Consolidated Service Group LLC",
    "wof:placetype":"venue"
},
  "geometry": {"coordinates":[-106.301211,35.162146],"type":"Point"}
}