{
  "type": "Feature",
  "properties": {
    "iso:country":"US",
    "sg:address":"3705 Canyon Ridge Arc",
    "sg:city":"Las Cruces",
    "sg:classifiers":[
        {
            "category":"Professional",
            "subcategory":"Business Services",
            "type":"Services"
        }
    ],
    "sg:phone":"+1 505 522 2106",
    "sg:postcode":"88011",
    "sg:province":"NM",
    "wof:name":"Global Outpost Inc",
    "wof:placetype":"venue"
},
  "geometry": {"coordinates":[-106.723378,32.31657],"type":"Point"}
}