{
  "type": "Feature",
  "properties": {
    "iso:country":"US",
    "sg:address":"424 E Zia Dr",
    "sg:city":"Hobbs",
    "sg:classifiers":[
        {
            "category":"Professional",
            "subcategory":"Computer Services",
            "type":"Services"
        }
    ],
    "sg:phone":"+1 505 397 5084",
    "sg:postcode":"88240",
    "sg:province":"NM",
    "sg:tags":[
        "consultant",
        "designer"
    ],
    "wof:name":"Computerlink",
    "wof:placetype":"venue"
},
  "geometry": {"coordinates":[-103.13041699999999,32.721488],"type":"Point"}
}