{
  "type": "Feature",
  "properties": {
    "iso:country":"US",
    "sg:address":"633 W Taos St",
    "sg:city":"Hobbs",
    "sg:classifiers":[
        {
            "category":"Building & Trades",
            "subcategory":"Pest Control",
            "type":"Services"
        }
    ],
    "sg:phone":"+1 505 492 9403",
    "sg:postcode":"88240",
    "sg:province":"NM",
    "wof:name":"Mitchell Pest Control",
    "wof:placetype":"venue"
},
  "geometry": {"coordinates":[-103.144589,32.734928],"type":"Point"}
}