{
  "type": "Feature",
  "properties": {
    "iso:country":"US",
    "sg:address":"11701 Central Ave SE",
    "sg:city":"Albuquerque",
    "sg:classifiers":[
        {
            "category":"Autos & Motor Vehicles",
            "subcategory":"Recreational Vehicle Sales",
            "type":"Retail Goods"
        }
    ],
    "sg:phone":"+1 505 323 5503",
    "sg:postcode":"87123",
    "sg:province":"NM",
    "wof:name":"Enchantment Rv",
    "wof:placetype":"venue"
},
  "geometry": {"coordinates":[-106.516085,35.070265],"type":"Point"}
}