{
  "type": "Feature",
  "properties": {
    "iso:country":"US",
    "sg:address":"4900 Pan American Pl NE",
    "sg:city":"Albuquerque",
    "sg:classifiers":[
        {
            "category":"Home & Garden",
            "subcategory":"Furniture",
            "type":"Retail Goods"
        }
    ],
    "sg:phone":"+1 505 872 9550",
    "sg:postcode":"87109",
    "sg:province":"NM",
    "sg:tags":[
        "import",
        "household"
    ],
    "wof:name":"World Expressions Inc",
    "wof:placetype":"venue"
},
  "geometry": {"coordinates":[-106.589271,35.157351],"type":"Point"}
}