{
  "type": "Feature",
  "properties": {
    "iso:country":"US",
    "sg:address":"3227 el Toboso Dr NW",
    "sg:city":"Albuquerque",
    "sg:classifiers":[
        {
            "category":"Professional",
            "subcategory":"Lawyer & Legal Services",
            "type":"Services"
        }
    ],
    "sg:phone":"+1 505 255 9300",
    "sg:postcode":"87104",
    "sg:province":"NM",
    "sg:tags":[
        "attorney"
    ],
    "wof:name":"William Riordan Attorney",
    "wof:placetype":"venue"
},
  "geometry": {"coordinates":[-106.685311,35.118085],"type":"Point"}
}