{
  "type": "Feature",
  "properties": {
    "iso:country":"US",
    "sg:address":"3500 Airport Rd",
    "sg:city":"Alamogordo",
    "sg:classifiers":[
        {
            "category":"Government",
            "subcategory":"Office",
            "type":"Public Place"
        }
    ],
    "sg:phone":"+1 505 439 4110",
    "sg:postcode":"88310",
    "sg:province":"NM",
    "sg:tags":[
        "general"
    ],
    "wof:name":"Almogordo Mncpl Wht Snds Rgnl",
    "wof:placetype":"venue"
},
  "geometry": {"coordinates":[-105.996779,32.841096],"type":"Point"}
}