{
  "type": "Feature",
  "properties": {
    "iso:country":"US",
    "sg:address":"141 Mescalero Trl",
    "sg:city":"Ruidoso",
    "sg:classifiers":[
        {
            "category":"Real Estate",
            "subcategory":"Real Estate Services",
            "type":"Services"
        }
    ],
    "sg:phone":"+1 505 257 1475",
    "sg:postcode":"88345",
    "sg:province":"NM",
    "sg:tags":[
        "company",
        "title"
    ],
    "wof:name":"Attorney's Abstract",
    "wof:placetype":"venue"
},
  "geometry": {"coordinates":[-105.635779,33.322417],"type":"Point"}
}