{
  "type": "Feature",
  "properties": {
    "iso:country":"US",
    "sg:address":"1011 N Hudson St",
    "sg:city":"Silver City",
    "sg:classifiers":[
        {
            "category":"Government",
            "subcategory":"Police Station",
            "type":"Public Place"
        }
    ],
    "sg:phone":"+1 505 538 3723",
    "sg:postcode":"88061",
    "sg:province":"NM",
    "sg:tags":[
        "department",
        "protection"
    ],
    "wof:name":"Silver City Police Department",
    "wof:placetype":"venue"
},
  "geometry": {"coordinates":[-108.274371,32.775425],"type":"Point"}
}