{
  "type": "Feature",
  "properties": {
    "iso:country":"US",
    "sg:address":"12412 Pristine Dr NE",
    "sg:city":"Albuquerque",
    "sg:classifiers":[
        {
            "category":"Professional",
            "subcategory":"Business Services",
            "type":"Services"
        }
    ],
    "sg:phone":"+1 505 856 0555",
    "sg:postcode":"87122",
    "sg:province":"NM",
    "wof:name":"Cdo Enterprises",
    "wof:placetype":"venue"
},
  "geometry": {"coordinates":[-106.50586,35.180323],"type":"Point"}
}