{
  "type": "Feature",
  "properties": {
    "iso:country":"US",
    "sg:address":"1012 Marquez Pl",
    "sg:city":"Santa Fe",
    "sg:classifiers":[
        {
            "category":"Real Estate",
            "subcategory":"Real Estate Operator",
            "type":"Services"
        }
    ],
    "sg:phone":"+1 505 982 5638",
    "sg:postcode":"87505",
    "sg:province":"NM",
    "sg:tags":[
        "apartment"
    ],
    "wof:name":"Marquez Place Lofts LLC",
    "wof:placetype":"venue"
},
  "geometry": {"coordinates":[-105.949969,35.674592],"type":"Point"}
}