{
  "type": "Feature",
  "properties": {
    "addr:full":"6504 Mesa Antigua Pl NW Albuquerque NM 87120",
    "addr:housenumber":"6504",
    "addr:postcode":"87120",
    "addr:street":"Mesa Antigua Pl Nw",
    "iso:country":"US",
    "sg:address":"6504 Mesa Antigua Pl NW",
    "sg:city":"Albuquerque",
    "sg:classifiers":[
        {
            "category":"Professional",
            "subcategory":"Business Services",
            "type":"Services"
        }
    ],
    "sg:phone":"+1 505 899 3445",
    "sg:postcode":"87120",
    "sg:province":"NM",
    "wof:name":"Liquidators",
    "wof:placetype":"venue"
},
  "geometry": {"coordinates":[-106.691639,35.160587],"type":"Point"}
}