{
  "type": "Feature",
  "properties": {
    "addr:full":"622 Pso del Pueblo Sur Taos NM 87571",
    "addr:housenumber":"622",
    "addr:postcode":"87571",
    "addr:street":"Pso Del Pueblo Sur",
    "iso:country":"US",
    "sg:address":"622 Pso del Pueblo Sur",
    "sg:city":"Taos",
    "sg:classifiers":[
        {
            "category":"Shopping",
            "subcategory":"Jewelry",
            "type":"Retail Goods"
        }
    ],
    "sg:phone":"+1 505 758 9319",
    "sg:postcode":"87571",
    "sg:province":"NM",
    "sg:tags":[
        "jeweler"
    ],
    "wof:name":"Chavez Fine Jewelers",
    "wof:placetype":"venue"
},
  "geometry": {"coordinates":[-105.57938300000001,36.395621],"type":"Point"}
}