{
  "type": "Feature",
  "properties": {
    "iso:country":"US",
    "sg:address":"3600 Cerrillos Rd",
    "sg:city":"Santa Fe",
    "sg:classifiers":[
        {
            "category":"Health Services",
            "subcategory":"Chiropractor",
            "type":"Services"
        }
    ],
    "sg:phone":"+1 505 983 2218",
    "sg:postcode":"87507",
    "sg:province":"NM",
    "wof:name":"Diane B Carey DC",
    "wof:placetype":"venue"
},
  "geometry": {"coordinates":[-106.005223,35.646917],"type":"Point"}
}