{
  "type": "Feature",
  "properties": {
    "iso:country":"US",
    "sg:address":"201 Country Club Dr SE",
    "sg:city":"Rio Rancho",
    "sg:classifiers":[
        {
            "category":"Building & Trades",
            "subcategory":"Construction",
            "type":"Services"
        }
    ],
    "sg:phone":"+1 505 888 1531",
    "sg:postcode":"87124",
    "sg:province":"NM",
    "sg:tags":[
        "floor",
        "laying",
        "contractor"
    ],
    "wof:name":"Perfect Measure",
    "wof:placetype":"venue"
},
  "geometry": {"coordinates":[-106.671154,35.247671],"type":"Point"}
}