{
  "type": "Feature",
  "properties": {
    "addr:full":"111 Coors Blvd NW Ste 1 Albuquerque NM 87121",
    "addr:housenumber":"111",
    "addr:postcode":"87121",
    "addr:street":"Coors Blvd Nw Ste 1",
    "iso:country":"US",
    "sg:address":"111 Coors Blvd NW Ste 1",
    "sg:city":"Albuquerque",
    "sg:classifiers":[
        {
            "category":"Government",
            "subcategory":"Post Office",
            "type":"Public Place"
        }
    ],
    "sg:phone":"+1 505 346 0876",
    "sg:postcode":"87121",
    "sg:province":"NM",
    "sg:website":"http://www.usps.com",
    "wof:name":"USPS - United States Post Office",
    "wof:placetype":"venue"
},
  "geometry": {"coordinates":[-106.71073199999999,35.080477],"type":"Point"}
}