{
  "type": "Feature",
  "properties": {
    "iso:country":"US",
    "sg:address":"508 Escudero St",
    "sg:city":"Santa Fe",
    "sg:classifiers":[
        {
            "category":"Professional",
            "subcategory":"Business Services",
            "type":"Services"
        }
    ],
    "sg:phone":"+1 505 455 0802",
    "sg:postcode":"87505",
    "sg:province":"NM",
    "sg:tags":[
        "recording",
        "studio"
    ],
    "sg:website":"www.d7music.com",
    "wof:name":"D 7 Productions",
    "wof:placetype":"venue"
},
  "geometry": {"coordinates":[-105.967305,35.677291],"type":"Point"}
}