{
  "type": "Feature",
  "properties": {
    "iso:country":"US",
    "sg:address":"127 Bough Pl",
    "sg:city":"Jemez Springs",
    "sg:classifiers":[
        {
            "category":"Organizations",
            "subcategory":"Religious Organization",
            "type":"Services"
        }
    ],
    "sg:phone":"+1 505 829 4475",
    "sg:postcode":"87025",
    "sg:province":"NM",
    "sg:tags":[
        "church"
    ],
    "wof:name":"Jemez Mountain Baptist Church",
    "wof:placetype":"venue"
},
  "geometry": {"coordinates":[-106.645098,35.873514],"type":"Point"}
}