{
  "type": "Feature",
  "properties": {
    "iso:country":"US",
    "sg:address":"221 Canyon Rd",
    "sg:city":"Santa Fe",
    "sg:classifiers":[
        {
            "category":"Museum",
            "type":"Entertainment"
        }
    ],
    "sg:phone":"+1 505 955 0550",
    "sg:postcode":"87501",
    "sg:province":"NM",
    "sg:tags":[
        "gallery"
    ],
    "sg:website":"www.adobegallery.com",
    "wof:name":"Adobe Gallery",
    "wof:placetype":"venue"
},
  "geometry": {"coordinates":[-105.933278,35.683501],"type":"Point"}
}