{
  "type": "Feature",
  "properties": {
    "addr:full":"506 E Jemez St Hobbs NM 88240",
    "addr:housenumber":"506",
    "addr:postcode":"88240",
    "addr:street":"E Jemez St",
    "iso:country":"US",
    "sg:address":"506 E Jemez St",
    "sg:city":"Hobbs",
    "sg:classifiers":[
        {
            "category":"Professional",
            "type":"Services"
        }
    ],
    "sg:phone":"+1 505 393 0378",
    "sg:postcode":"88240",
    "sg:province":"NM",
    "wof:name":"Calidad Inc",
    "wof:placetype":"venue"
},
  "geometry": {"coordinates":[-103.13253400000001,32.722847],"type":"Point"}
}