{
  "type": "Feature",
  "properties": {
    "iso:country":"US",
    "sg:address":"901 Fairgrounds Rd",
    "sg:city":"Farmington",
    "sg:classifiers":[
        {
            "category":"Arts & Performance",
            "subcategory":"Theater",
            "type":"Entertainment"
        }
    ],
    "sg:phone":"+1 505 599 1407",
    "sg:postcode":"87401",
    "sg:province":"NM",
    "sg:tags":[
        "bureau"
    ],
    "sg:website":"www.farmington.nm.us",
    "wof:name":"Sandstone Productions",
    "wof:placetype":"venue"
},
  "geometry": {"coordinates":[-108.186638,36.737998],"type":"Point"}
}