{
  "type": "Feature",
  "properties": {
    "iso:country":"US",
    "sg:address":"1133 Lawrence Dr NE",
    "sg:city":"Albuquerque",
    "sg:classifiers":[
        {
            "category":"Building & Trades",
            "subcategory":"Construction",
            "type":"Services"
        }
    ],
    "sg:phone":"+1 505 293 9620",
    "sg:postcode":"87123",
    "sg:province":"NM",
    "sg:tags":[
        "plumbing",
        "general",
        "electrical",
        "contractor"
    ],
    "wof:name":"Runde Electric",
    "wof:placetype":"venue"
},
  "geometry": {"coordinates":[-106.490835,35.084909],"type":"Point"}
}