{
  "type": "Feature",
  "properties": {
    "iso:country":"US",
    "sg:address":"1005 S Telshor Blvd",
    "sg:city":"Las Cruces",
    "sg:classifiers":[
        {
            "category":"Building & Trades",
            "subcategory":"Construction",
            "type":"Services"
        }
    ],
    "sg:phone":"+1 505 524 2831",
    "sg:postcode":"88011",
    "sg:province":"NM",
    "sg:tags":[
        "house",
        "builder",
        "home"
    ],
    "wof:name":"Tarin Construction",
    "wof:placetype":"venue"
},
  "geometry": {"coordinates":[-106.73868,32.30635],"type":"Point"}
}