{
  "type": "Feature",
  "properties": {
    "iso:country":"US",
    "sg:address":"516 N Broadway St",
    "sg:city":"Truth Or Cnsqncs",
    "sg:classifiers":[
        {
            "category":"Insurance",
            "subcategory":"Insurance Agent",
            "type":"Services"
        }
    ],
    "sg:phone":"+1 505 894 2139",
    "sg:postcode":"87901",
    "sg:province":"NM",
    "wof:name":"Hot Springs Insurance Inc",
    "wof:placetype":"venue"
},
  "geometry": {"coordinates":[-107.255861,33.128445],"type":"Point"}
}