{
  "type": "Feature",
  "properties": {
    "iso:country":"US",
    "sg:address":"551 W Cordova Rd",
    "sg:city":"Santa Fe",
    "sg:classifiers":[
        {
            "category":"Shopping",
            "subcategory":"Clothing, Apparel, & Fashions",
            "type":"Retail Goods"
        }
    ],
    "sg:phone":"+1 505 983 6835",
    "sg:postcode":"87505",
    "sg:province":"NM",
    "wof:name":"Gong Hee Fot Choy",
    "wof:placetype":"venue"
},
  "geometry": {"coordinates":[-105.949597,35.672445],"type":"Point"}
}