{
  "type": "Feature",
  "properties": {
    "addr:full":"4617 Snapdragon Rd NW Albuquerque NM 87120",
    "addr:housenumber":"4617",
    "addr:postcode":"87120",
    "addr:street":"Snapdragon Rd Nw",
    "iso:country":"US",
    "sg:address":"4617 Snapdragon Rd NW",
    "sg:city":"Albuquerque",
    "sg:classifiers":[
        {
            "category":"Professional",
            "subcategory":"Management & Consulting",
            "type":"Services"
        }
    ],
    "sg:phone":"+1 505 246 0431",
    "sg:postcode":"87120",
    "sg:province":"NM",
    "sg:tags":[
        "policy",
        "public",
        "relations",
        "government"
    ],
    "wof:name":"Public Private Partnr The LLC",
    "wof:placetype":"venue"
},
  "geometry": {"coordinates":[-106.68773299999999,35.165422],"type":"Point"}
}