{
  "type": "Feature",
  "properties": {
    "iso:country":"US",
    "sg:address":"233 S New York Ave",
    "sg:city":"Alamogordo",
    "sg:classifiers":[
        {
            "category":"Personal",
            "subcategory":"Beauty Salon",
            "type":"Services"
        }
    ],
    "sg:phone":"+1 505 439 5189",
    "sg:postcode":"88310",
    "sg:province":"NM",
    "wof:name":"Smart Style Family Hair Salon",
    "wof:placetype":"venue"
},
  "geometry": {"coordinates":[-105.95948799999999,32.887645],"type":"Point"}
}