{
  "type": "Feature",
  "properties": {
    "iso:country":"US",
    "sg:address":"301 Commerce Rd",
    "sg:city":"Artesia",
    "sg:classifiers":[
        {
            "category":"Mining & Drilling",
            "type":"Manufacturing & Wholesale Goods"
        }
    ],
    "sg:phone":"+1 505 746 2217",
    "sg:postcode":"88210",
    "sg:province":"NM",
    "sg:tags":[
        "field",
        "oil"
    ],
    "sg:website":"www.gandltool.com",
    "wof:name":"G & L Tool Co",
    "wof:placetype":"venue"
},
  "geometry": {"coordinates":[-104.390997,32.874263],"type":"Point"}
}