{
  "type": "Feature",
  "properties": {
    "iso:country":"US",
    "sg:address":"217 Indiana St SE",
    "sg:city":"Albuquerque",
    "sg:classifiers":[
        {
            "category":"Retail",
            "subcategory":"Repair Shop",
            "type":"Services"
        },
        {
            "category":"Building & Trades",
            "subcategory":"Construction",
            "type":"Services"
        }
    ],
    "sg:phone":"+1 505 450 4027",
    "sg:postcode":"87108",
    "sg:province":"NM",
    "sg:tags":[
        "steel",
        "ironwork",
        "erection",
        "structural"
    ],
    "wof:name":"Say Iron Works",
    "wof:placetype":"venue"
},
  "geometry": {"coordinates":[-106.570819,35.074222],"type":"Point"}
}