{
  "type": "Feature",
  "properties": {
    "iso:country":"US",
    "sg:address":"10600 Central Ave SE",
    "sg:city":"Albuquerque",
    "sg:classifiers":[
        {
            "category":"Professional",
            "subcategory":"Management & Consulting",
            "type":"Services"
        }
    ],
    "sg:phone":"+1 505 480 6842",
    "sg:postcode":"87123",
    "sg:province":"NM",
    "sg:tags":[
        "consultant"
    ],
    "wof:name":"Baby Boy Media Consulting",
    "wof:placetype":"venue"
},
  "geometry": {"coordinates":[-106.530485,35.071706],"type":"Point"}
}