{
  "type": "Feature",
  "properties": {
    "iso:country":"US",
    "sg:address":"105 S Allen Ave",
    "sg:city":"Farmington",
    "sg:classifiers":[
        {
            "category":"Professional",
            "subcategory":"Research",
            "type":"Services"
        }
    ],
    "sg:phone":"+1 505 327 4600",
    "sg:postcode":"87401",
    "sg:province":"NM",
    "sg:tags":[
        "organization",
        "archaeologist",
        "noncommercial"
    ],
    "wof:name":"Animas Ceramic Consulting",
    "wof:placetype":"venue"
},
  "geometry": {"coordinates":[-108.206683,36.729027],"type":"Point"}
}