{
  "type": "Feature",
  "properties": {
    "iso:country":"US",
    "sg:address":"4204 Carlisle Blvd NE",
    "sg:city":"Albuquerque",
    "sg:classifiers":[
        {
            "category":"Professional",
            "subcategory":"Computer Services",
            "type":"Services"
        }
    ],
    "sg:phone":"+1 505 797 3400",
    "sg:postcode":"87107",
    "sg:province":"NM",
    "sg:tags":[
        "system",
        "cad"
    ],
    "wof:name":"Cad Store",
    "wof:placetype":"venue"
},
  "geometry": {"coordinates":[-106.60401,35.129819],"type":"Point"}
}