{
  "type": "Feature",
  "properties": {
    "addr:full":"4500 Chadwick Rd NW Albuquerque NM 87120",
    "addr:housenumber":"4500",
    "addr:postcode":"87120",
    "addr:street":"Chadwick Rd Nw",
    "iso:country":"US",
    "sg:address":"4500 Chadwick Rd NW",
    "sg:city":"Albuquerque",
    "sg:classifiers":[
        {
            "category":"Professional",
            "subcategory":"Detective & Security Services",
            "type":"Services"
        }
    ],
    "sg:phone":"+1 505 362 1502",
    "sg:postcode":"87120",
    "sg:province":"NM",
    "sg:tags":[
        "system"
    ],
    "wof:name":"Shield Security Services",
    "wof:placetype":"venue"
},
  "geometry": {"coordinates":[-106.68986200000001,35.156144],"type":"Point"}
}