{
  "type": "Feature",
  "properties": {
    "iso:country":"US",
    "sg:address":"903 S Solano Dr",
    "sg:city":"Las Cruces",
    "sg:classifiers":[
        {
            "category":"Insurance",
            "subcategory":"Insurance Agent",
            "type":"Services"
        }
    ],
    "sg:phone":"+1 505 523 5585",
    "sg:postcode":"88001",
    "sg:province":"NM",
    "wof:name":"American National Insurance Co",
    "wof:placetype":"venue"
},
  "geometry": {"coordinates":[-106.763283,32.303001],"type":"Point"}
}