{
  "type": "Feature",
  "properties": {
    "iso:country":"US",
    "sg:address":"5901 Indian School Rd NE",
    "sg:city":"Albuquerque",
    "sg:classifiers":[
        {
            "category":"Professional",
            "type":"Services"
        }
    ],
    "sg:phone":"+1 505 889 7000",
    "sg:postcode":"87110",
    "sg:province":"NM",
    "sg:tags":[
        "scientist"
    ],
    "sg:website":"www.itt.com",
    "wof:name":"ITT Industries Inc",
    "wof:placetype":"venue"
},
  "geometry": {"coordinates":[-106.580257,35.101803],"type":"Point"}
}