{
  "type": "Feature",
  "properties": {
    "iso:country":"US",
    "sg:address":"2649 Louisiana Blvd NE",
    "sg:city":"Albuquerque",
    "sg:classifiers":[
        {
            "category":"Shopping",
            "subcategory":"Clothing, Apparel, & Fashions",
            "type":"Retail Goods"
        }
    ],
    "sg:phone":"+1 505 888 2667",
    "sg:postcode":"87110",
    "sg:province":"NM",
    "wof:name":"Viola & Co",
    "wof:placetype":"venue"
},
  "geometry": {"coordinates":[-106.568929,35.110087],"type":"Point"}
}