{
  "type": "Feature",
  "properties": {
    "iso:country":"US",
    "sg:address":"1210 N Main St",
    "sg:city":"Roswell",
    "sg:classifiers":[
        {
            "category":"Real Estate",
            "subcategory":"Real Estate Agent",
            "type":"Services"
        }
    ],
    "sg:phone":"+1 505 622 2401",
    "sg:postcode":"88201",
    "sg:province":"NM",
    "sg:tags":[
        "finding",
        "apartment",
        "rental"
    ],
    "wof:name":"Ag Realty Rental",
    "wof:placetype":"venue"
},
  "geometry": {"coordinates":[-104.52285,33.4068],"type":"Point"}
}