{
  "type": "Feature",
  "properties": {
    "iso:country":"US",
    "sg:address":"926 Baca St",
    "sg:city":"Santa Fe",
    "sg:classifiers":[
        {
            "category":"Shopping",
            "type":"Retail Goods"
        }
    ],
    "sg:phone":"+1 505 820 2222",
    "sg:postcode":"87505",
    "sg:province":"NM",
    "sg:tags":[
        "art",
        "gallery",
        "dealer"
    ],
    "wof:name":"Baca Street Art District",
    "wof:placetype":"venue"
},
  "geometry": {"coordinates":[-105.963273,35.674712],"type":"Point"}
}