{
  "type": "Feature",
  "properties": {
    "iso:country":"US",
    "sg:address":"1441 Eubank Blvd NE",
    "sg:city":"Albuquerque",
    "sg:classifiers":[
        {
            "category":"Manufacturing",
            "subcategory":"Signs",
            "type":"Manufacturing & Wholesale Goods"
        }
    ],
    "sg:phone":"+1 505 293 5914",
    "sg:postcode":"87112",
    "sg:province":"NM",
    "sg:tags":[
        "retail",
        "specialty"
    ],
    "wof:name":"Marathon Signs P & R Inc",
    "wof:placetype":"venue"
},
  "geometry": {"coordinates":[-106.532816,35.095447],"type":"Point"}
}