{
  "type": "Feature",
  "properties": {
    "iso:country":"US",
    "sg:address":"278 Ojo de la Vaca Rd",
    "sg:city":"Santa Fe",
    "sg:classifiers":[
        {
            "category":"Building & Trades",
            "subcategory":"Plumbing",
            "type":"Services"
        }
    ],
    "sg:phone":"+1 505 466 0391",
    "sg:postcode":"87508",
    "sg:province":"NM",
    "sg:tags":[
        "septic"
    ],
    "wof:name":"Drake Construction",
    "wof:placetype":"venue"
},
  "geometry": {"coordinates":[-105.845786,35.531923],"type":"Point"}
}