{
  "type": "Feature",
  "properties": {
    "iso:country":"US",
    "sg:address":"11435 Montgomery Blvd NE",
    "sg:city":"Albuquerque",
    "sg:classifiers":[
        {
            "category":"Organizations",
            "subcategory":"Religious Organization",
            "type":"Services"
        }
    ],
    "sg:phone":"+1 505 293 1225",
    "sg:postcode":"87111",
    "sg:province":"NM",
    "sg:tags":[
        "church"
    ],
    "wof:name":"Holiday Park Community Church",
    "wof:placetype":"venue"
},
  "geometry": {"coordinates":[-106.50827099999999,35.130753],"type":"Point"}
}