{
  "type": "Feature",
  "properties": {
    "addr:full":"11300 Ridgeline Ave NE Albuquerque NM 87111",
    "addr:housenumber":"11300",
    "addr:postcode":"87111",
    "addr:street":"Ridgeline Ave Ne",
    "iso:country":"US",
    "sg:address":"11300 Ridgeline Ave NE",
    "sg:city":"Albuquerque",
    "sg:classifiers":[
        {
            "category":"Building & Trades",
            "subcategory":"Plumbing",
            "type":"Services"
        }
    ],
    "sg:phone":"+1 505 275 1035",
    "sg:postcode":"87111",
    "sg:province":"NM",
    "sg:tags":[
        "plumbing",
        "contractor"
    ],
    "wof:name":"J C Plumbing & Heating Co",
    "wof:placetype":"venue"
},
  "geometry": {"coordinates":[-106.513784,35.142708],"type":"Point"}
}