{
  "type": "Feature",
  "properties": {
    "iso:country":"US",
    "sg:address":"506 Ethel Ave",
    "sg:city":"Tularosa",
    "sg:classifiers":[
        {
            "category":"Manufacturing",
            "subcategory":"Tools & Machinery",
            "type":"Manufacturing & Wholesale Goods"
        }
    ],
    "sg:phone":"+1 505 585 8458",
    "sg:postcode":"88352",
    "sg:province":"NM",
    "sg:tags":[
        "installs",
        "pr",
        "mfg",
        "lightning",
        "surge"
    ],
    "wof:name":"Circuit Rider Electronics Inc",
    "wof:placetype":"venue"
},
  "geometry": {"coordinates":[-106.009596,33.075398],"type":"Point"}
}