{
  "type": "Feature",
  "properties": {
    "iso:country":"US",
    "sg:address":"1331 82nd St SW",
    "sg:city":"Albuquerque",
    "sg:classifiers":[
        {
            "category":"Food & Beverages",
            "subcategory":"Specialty",
            "type":"Retail Goods"
        }
    ],
    "sg:phone":"+1 505 831 0893",
    "sg:postcode":"87121",
    "sg:province":"NM",
    "wof:name":"Consuelo Trujillo",
    "wof:placetype":"venue"
},
  "geometry": {"coordinates":[-106.72519699999999,35.052793],"type":"Point"}
}