{
  "type": "Feature",
  "properties": {
    "addr:full":"9601 Lomas Blvd NE Albuquerque NM 87112",
    "addr:housenumber":"9601",
    "addr:postcode":"87112",
    "addr:street":"Lomas Blvd Ne",
    "iso:country":"US",
    "sg:address":"9601 Lomas Blvd NE",
    "sg:city":"Albuquerque",
    "sg:classifiers":[
        {
            "category":"Retail",
            "subcategory":"Driving School",
            "type":"Services"
        },
        {
            "category":"Autos & Motor Vehicles",
            "subcategory":"Motorcycle Sales",
            "type":"Retail Goods"
        }
    ],
    "sg:phone":"+1 505 292 6692",
    "sg:postcode":"87112",
    "sg:province":"NM",
    "sg:tags":[
        "instruction"
    ],
    "wof:name":"R & S Kawasaki",
    "wof:placetype":"venue"
},
  "geometry": {"coordinates":[-106.538708,35.087583],"type":"Point"}
}