{
  "type": "Feature",
  "properties": {
    "iso:country":"US",
    "sg:address":"222 Rodriquez St",
    "sg:city":"Santa Fe",
    "sg:classifiers":[
        {
            "category":"Organizations",
            "subcategory":"Non-profit Organization",
            "type":"Services"
        }
    ],
    "sg:phone":"+1 505 438 9684",
    "sg:postcode":"87501",
    "sg:province":"NM",
    "wof:name":"Loma Encantada Homeowners",
    "wof:placetype":"venue"
},
  "geometry": {"coordinates":[-105.927074,35.685477],"type":"Point"}
}