{
  "type": "Feature",
  "properties": {
    "addr:full":"83 Rd 5295 Farmington NM 87401",
    "addr:housenumber":"83",
    "addr:postcode":"87401",
    "addr:street":"Rd 5295",
    "iso:country":"US",
    "sg:address":"83 Rd 5295",
    "sg:city":"Farmington",
    "sg:classifiers":[
        {
            "category":"Building & Trades",
            "subcategory":"Cleaning & Sanitation",
            "type":"Services"
        }
    ],
    "sg:phone":"+1 505 632 2892",
    "sg:postcode":"87401",
    "sg:province":"NM",
    "sg:tags":[
        "maintenance"
    ],
    "wof:name":"Vista San Juan Estates",
    "wof:placetype":"venue"
},
  "geometry": {"coordinates":[-108.05597400000001,36.691717],"type":"Point"}
}