{
  "type": "Feature",
  "properties": {
    "iso:country":"US",
    "sg:address":"602 E Hines Ave",
    "sg:city":"Tucumcari",
    "sg:classifiers":[
        {
            "category":"Real Estate",
            "subcategory":"Real Estate Agent",
            "type":"Services"
        }
    ],
    "sg:phone":"+1 505 461 2013",
    "sg:postcode":"88401",
    "sg:province":"NM",
    "wof:name":"Smith San Jon Lands LLC",
    "wof:placetype":"venue"
},
  "geometry": {"coordinates":[-103.71976600000001,35.170719],"type":"Point"}
}