{
  "type": "Feature",
  "properties": {
    "iso:country":"US",
    "sg:address":"205 W Church St",
    "sg:city":"Carlsbad",
    "sg:classifiers":[
        {
            "category":"Shopping",
            "subcategory":"Optical Goods",
            "type":"Retail Goods"
        }
    ],
    "sg:phone":"+1 505 885 1257",
    "sg:postcode":"88220",
    "sg:province":"NM",
    "sg:tags":[
        "optician"
    ],
    "wof:name":"Fashion Eyeworks",
    "wof:placetype":"venue"
},
  "geometry": {"coordinates":[-104.228195,32.428518],"type":"Point"}
}