{
  "type": "Feature",
  "properties": {
    "addr:full":"1304 N Pennsylvania Ave Roswell NM 88201",
    "addr:housenumber":"1304",
    "addr:postcode":"88201",
    "addr:street":"N Pennsylvania Ave",
    "iso:country":"US",
    "sg:address":"1304 N Pennsylvania Ave",
    "sg:city":"Roswell",
    "sg:classifiers":[
        {
            "category":"Manufacturing",
            "subcategory":"Wood Products",
            "type":"Manufacturing & Wholesale Goods"
        }
    ],
    "sg:phone":"+1 505 624 2494",
    "sg:postcode":"88201",
    "sg:province":"NM",
    "sg:tags":[
        "mfg"
    ],
    "wof:name":"Frank & Maurines Creations",
    "wof:placetype":"venue"
},
  "geometry": {"coordinates":[-104.526146,33.408052],"type":"Point"}
}