{
  "type": "Feature",
  "properties": {
    "addr:full":"55 Old Santa Fe Trl Santa Fe NM 87501",
    "addr:housenumber":"55",
    "addr:postcode":"87501",
    "addr:street":"Old Santa Fe Trl",
    "iso:country":"US",
    "sg:address":"55 Old Santa Fe Trl",
    "sg:city":"Santa Fe",
    "sg:classifiers":[
        {
            "category":"Professional",
            "subcategory":"Lawyer & Legal Services",
            "type":"Services"
        }
    ],
    "sg:phone":"+1 505 988 8804",
    "sg:postcode":"87501",
    "sg:province":"NM",
    "sg:tags":[
        "attorney"
    ],
    "wof:name":"Mc Claugherty & Silver PC",
    "wof:placetype":"venue"
},
  "geometry": {"coordinates":[-105.937977,35.687282],"type":"Point"}
}