{
  "type": "Feature",
  "properties": {
    "addr:full":"2625 Halcon Pl SW Albuquerque NM 87105",
    "addr:housenumber":"2625",
    "addr:postcode":"87105",
    "addr:street":"Halcon Pl Sw",
    "iso:country":"US",
    "sg:address":"2625 Halcon Pl SW",
    "sg:city":"Albuquerque",
    "sg:classifiers":[
        {
            "category":"Manufacturing",
            "subcategory":"Buildings",
            "type":"Manufacturing & Wholesale Goods"
        },
        {
            "category":"Building & Trades",
            "subcategory":"Construction",
            "type":"Services"
        }
    ],
    "sg:phone":"+1 505 877 3441",
    "sg:postcode":"87105",
    "sg:province":"NM",
    "sg:tags":[
        "home",
        "builder",
        "industrial",
        "contractors-commercial",
        "contractor"
    ],
    "sg:website":"http://www.eclipseavation.com",
    "wof:name":"Rice Enterprise Construction",
    "wof:placetype":"venue"
},
  "geometry": {"coordinates":[-106.71226900000001,34.971335],"type":"Point"}
}