{
  "type": "Feature",
  "properties": {
    "iso:country":"US",
    "sg:address":"1100 Cam del Pueblo",
    "sg:city":"Bernalillo",
    "sg:classifiers":[
        {
            "category":"Shopping",
            "subcategory":"Used Merchandise",
            "type":"Retail Goods"
        }
    ],
    "sg:phone":"+1 505 867 7448",
    "sg:postcode":"87004",
    "sg:province":"NM",
    "sg:tags":[
        "antique"
    ],
    "wof:name":"Camino Real Antiques",
    "wof:placetype":"venue"
},
  "geometry": {"coordinates":[-106.551165,35.300112],"type":"Point"}
}