{
  "type": "Feature",
  "properties": {
    "addr:full":"410 Bayard St Santa Clara NM 88061",
    "addr:housenumber":"410",
    "addr:postcode":"88061",
    "addr:street":"Bayard St",
    "iso:country":"US",
    "sg:address":"410 Bayard St",
    "sg:city":"Santa Clara",
    "sg:classifiers":[
        {
            "category":"Government",
            "subcategory":"Office",
            "type":"Public Place"
        }
    ],
    "sg:phone":"+1 505 537 3106",
    "sg:postcode":"88061",
    "sg:province":"NM",
    "sg:tags":[
        "village"
    ],
    "wof:name":"Maintenance Shop",
    "wof:placetype":"venue"
},
  "geometry": {"coordinates":[-108.152956,32.772544],"type":"Point"}
}