{
  "type": "Feature",
  "properties": {
    "addr:full":"214 Old Santa Fe Trl Santa Fe NM 87501",
    "addr:housenumber":"214",
    "addr:postcode":"87501",
    "addr:street":"Old Santa Fe Trl",
    "iso:country":"US",
    "sg:address":"214 Old Santa Fe Trl",
    "sg:city":"Santa Fe",
    "sg:classifiers":[
        {
            "category":"Shopping",
            "subcategory":"Jewelry",
            "type":"Retail Goods"
        }
    ],
    "sg:phone":"+1 505 982 9759",
    "sg:postcode":"87501",
    "sg:province":"NM",
    "sg:tags":[
        "jeweler"
    ],
    "wof:name":"Santa Fe Jewels",
    "wof:placetype":"venue"
},
  "geometry": {"coordinates":[-105.937744,35.685012],"type":"Point"}
}