{
  "type": "Feature",
  "properties": {
    "iso:country":"US",
    "sg:address":"807 N Canal St",
    "sg:city":"Carlsbad",
    "sg:classifiers":[
        {
            "category":"Banks & Credit Unions",
            "subcategory":"Bank",
            "type":"Services"
        }
    ],
    "sg:phone":"+1 505 234 9192",
    "sg:postcode":"88220",
    "sg:province":"NM",
    "sg:tags":[
        "financing"
    ],
    "wof:name":"Crazy Sam's Car Title Loans",
    "wof:placetype":"venue"
},
  "geometry": {"coordinates":[-104.228944,32.430222],"type":"Point"}
}