{
  "type": "Feature",
  "properties": {
    "iso:country":"US",
    "sg:address":"602 2nd St NW",
    "sg:city":"Albuquerque",
    "sg:classifiers":[
        {
            "category":"Government",
            "subcategory":"Office",
            "type":"Public Place"
        }
    ],
    "sg:phone":"+1 505 924 3633",
    "sg:postcode":"87102",
    "sg:province":"NM",
    "sg:tags":[
        "village"
    ],
    "wof:name":"Albuquerque City Government",
    "wof:placetype":"venue"
},
  "geometry": {"coordinates":[-106.647897,35.090862],"type":"Point"}
}