{
  "type": "Feature",
  "properties": {
    "addr:full":"2300 Arenal Rd SW Albuquerque NM 87105",
    "addr:housenumber":"2300",
    "addr:postcode":"87105",
    "addr:street":"Arenal Rd Sw",
    "iso:country":"US",
    "sg:address":"2300 Arenal Rd SW",
    "sg:city":"Albuquerque",
    "sg:classifiers":[
        {
            "category":"Health Services",
            "subcategory":"Clinic",
            "type":"Services"
        }
    ],
    "sg:phone":"+1 505 873 0605",
    "sg:postcode":"87105",
    "sg:province":"NM",
    "wof:name":"First Choice Community Health",
    "wof:placetype":"venue"
},
  "geometry": {"coordinates":[-106.692127,35.051192],"type":"Point"}
}