{
  "type": "Feature",
  "properties": {
    "iso:country":"US",
    "sg:address":"1821 June St NE",
    "sg:city":"Albuquerque",
    "sg:classifiers":[
        {
            "category":"Health Services",
            "subcategory":"Clinic",
            "type":"Services"
        }
    ],
    "sg:phone":"+1 505 293 6004",
    "sg:postcode":"87112",
    "sg:province":"NM",
    "wof:name":"Vicky Horton Health Education",
    "wof:placetype":"venue"
},
  "geometry": {"coordinates":[-106.52257899999999,35.103491],"type":"Point"}
}