{
  "type": "Feature",
  "properties": {
    "addr:full":"234 Polaris St Las Cruces NM 88002",
    "addr:housenumber":"234",
    "addr:postcode":"88002",
    "addr:street":"Polaris St",
    "iso:country":"US",
    "sg:address":"234 Polaris St",
    "sg:city":"Las Cruces",
    "sg:classifiers":[
        {
            "category":"Professional",
            "subcategory":"Business Services",
            "type":"Services"
        }
    ],
    "sg:phone":"+1 505 678 0385",
    "sg:postcode":"88002",
    "sg:province":"NM",
    "wof:name":"Jennifer De John",
    "wof:placetype":"venue"
},
  "geometry": {"coordinates":[-106.49948500000001,32.380982],"type":"Point"}
}