{
  "type": "Feature",
  "properties": {
    "iso:country":"US",
    "sg:address":"1514 Lincoln Ave",
    "sg:city":"Alamogordo",
    "sg:classifiers":[
        {
            "category":"Retail",
            "subcategory":"Repair Shop",
            "type":"Services"
        }
    ],
    "sg:phone":"+1 505 434 3289",
    "sg:postcode":"88310",
    "sg:province":"NM",
    "sg:tags":[
        "scooter",
        "motorcycle",
        "motor"
    ],
    "wof:name":"Fat Bob's Motorcycles",
    "wof:placetype":"venue"
},
  "geometry": {"coordinates":[-105.94104900000001,32.90703],"type":"Point"}
}