{
  "type": "Feature",
  "properties": {
    "iso:country":"US",
    "sg:address":"1426 Schofield Ln",
    "sg:city":"Farmington",
    "sg:classifiers":[
        {
            "category":"Retail",
            "subcategory":"Portrait Studio",
            "type":"Services"
        }
    ],
    "sg:phone":"+1 505 327 4686",
    "sg:postcode":"87401",
    "sg:province":"NM",
    "sg:tags":[
        "laboratory",
        "photo",
        "photography",
        "photofinishing"
    ],
    "wof:name":"Photo Synthesis",
    "wof:placetype":"venue"
},
  "geometry": {"coordinates":[-108.1819,36.744107],"type":"Point"}
}