{
  "type": "Feature",
  "properties": {
    "iso:country":"US",
    "sg:address":"3128 Vis Sandia",
    "sg:city":"Santa Fe",
    "sg:classifiers":[
        {
            "category":"Professional",
            "subcategory":"Management & Consulting",
            "type":"Services"
        }
    ],
    "sg:phone":"+1 505 989 8157",
    "sg:postcode":"87506",
    "sg:province":"NM",
    "wof:name":"Store Enterprises",
    "wof:placetype":"venue"
},
  "geometry": {"coordinates":[-105.99324,35.713253],"type":"Point"}
}