{
  "type": "Feature",
  "properties": {
    "addr:full":"2600 Sullivan Ave Farmington NM 87401",
    "addr:housenumber":"2600",
    "addr:postcode":"87401",
    "addr:street":"Sullivan Ave",
    "iso:country":"US",
    "sg:address":"2600 Sullivan Ave",
    "sg:city":"Farmington",
    "sg:classifiers":[
        {
            "category":"Organizations",
            "subcategory":"Religious Organization",
            "type":"Services"
        }
    ],
    "sg:phone":"+1 505 325 2600",
    "sg:postcode":"87401",
    "sg:province":"NM",
    "sg:tags":[
        "church"
    ],
    "wof:name":"First Church Of The Nazarene",
    "wof:placetype":"venue"
},
  "geometry": {"coordinates":[-108.184158,36.753833],"type":"Point"}
}