{
  "type": "Feature",
  "properties": {
    "iso:country":"US",
    "sg:address":"1000 Airport Rd",
    "sg:city":"Lordsburg",
    "sg:classifiers":[
        {
            "category":"Airport",
            "type":"Transportation"
        }
    ],
    "sg:phone":"+1 505 542 3614",
    "sg:postcode":"88045",
    "sg:province":"NM",
    "wof:name":"Lordsburg Municipal Airport",
    "wof:placetype":"venue"
},
  "geometry": {"coordinates":[-108.70777099999999,32.340527],"type":"Point"}
}