{
  "type": "Feature",
  "properties": {
    "iso:country":"US",
    "sg:address":"617 1st St",
    "sg:city":"Grants",
    "sg:classifiers":[
        {
            "category":"Health Services",
            "subcategory":"Optometrist",
            "type":"Services"
        }
    ],
    "sg:phone":"+1 505 287 9438",
    "sg:postcode":"87020",
    "sg:province":"NM",
    "wof:name":"Dale Wickman Od",
    "wof:placetype":"venue"
},
  "geometry": {"coordinates":[-107.845107,35.156023],"type":"Point"}
}