{
  "type": "Feature",
  "properties": {
    "addr:full":"1037 Moon River Loop Las Cruces NM 88007",
    "addr:housenumber":"1037",
    "addr:postcode":"88007",
    "addr:street":"Moon River Loop",
    "iso:country":"US",
    "sg:address":"1037 Moon River Loop",
    "sg:city":"Las Cruces",
    "sg:classifiers":[
        {
            "category":"Health Services",
            "subcategory":"Medical Lab",
            "type":"Services"
        }
    ],
    "sg:phone":"+1 505 526 3070",
    "sg:postcode":"88007",
    "sg:province":"NM",
    "sg:tags":[
        "laboratory"
    ],
    "wof:name":"Figueroa Dental Studio",
    "wof:placetype":"venue"
},
  "geometry": {"coordinates":[-106.81314999999999,32.31297],"type":"Point"}
}