{
  "type": "Feature",
  "properties": {
    "addr:full":"949 Co Rd 23 Clovis NM 88101",
    "addr:housenumber":"949;23",
    "addr:postcode":"88101",
    "addr:street":"Co Rd",
    "iso:country":"US",
    "sg:address":"949 Co Rd 23",
    "sg:city":"Clovis",
    "sg:classifiers":[
        {
            "category":"Farming",
            "subcategory":"Dairy Farm",
            "type":"Manufacturing & Wholesale Goods"
        }
    ],
    "sg:phone":"+1 505 985 0190",
    "sg:postcode":"88101",
    "sg:province":"NM",
    "wof:name":"Starks & Sons",
    "wof:placetype":"venue"
},
  "geometry": {"coordinates":[-103.183994,34.594195],"type":"Point"}
}