{
  "type": "Feature",
  "properties": {
    "iso:country":"US",
    "sg:address":"5009 Industrial Park Loop NE",
    "sg:city":"Rio Rancho",
    "sg:classifiers":[
        {
            "category":"Retail",
            "subcategory":"Auto Repair",
            "type":"Services"
        }
    ],
    "sg:phone":"+1 505 892 5496",
    "sg:postcode":"87124",
    "sg:province":"NM",
    "sg:tags":[
        "transmission"
    ],
    "wof:name":"Auto Works Transmission",
    "wof:placetype":"venue"
},
  "geometry": {"coordinates":[-106.634947,35.259147],"type":"Point"}
}