{
  "type": "Feature",
  "properties": {
    "iso:country":"US",
    "sg:address":"2221 W Lea St",
    "sg:city":"Carlsbad",
    "sg:classifiers":[
        {
            "category":"Wholesale",
            "subcategory":"Toys & Hobbies",
            "type":"Manufacturing & Wholesale Goods"
        }
    ],
    "sg:phone":"+1 505 628 0479",
    "sg:postcode":"88220",
    "sg:province":"NM",
    "sg:tags":[
        "firework"
    ],
    "wof:name":"Mr W Fireworks Inc",
    "wof:placetype":"venue"
},
  "geometry": {"coordinates":[-104.255244,32.414538],"type":"Point"}
}