{
  "type": "Feature",
  "properties": {
    "addr:full":"2300 W 2nd St Roswell NM 88201",
    "addr:housenumber":"2300",
    "addr:postcode":"88201",
    "addr:street":"W 2Nd St",
    "iso:country":"US",
    "sg:address":"2300 W 2nd St",
    "sg:city":"Roswell",
    "sg:classifiers":[
        {
            "category":"Autos & Motor Vehicles",
            "subcategory":"Automobile Sales",
            "type":"Retail Goods"
        }
    ],
    "sg:phone":"+1 505 623 7500",
    "sg:postcode":"88201",
    "sg:province":"NM",
    "sg:tags":[
        "used"
    ],
    "wof:name":"Rods & Wheels",
    "wof:placetype":"venue"
},
  "geometry": {"coordinates":[-104.55605,33.39405],"type":"Point"}
}