{
  "type": "Feature",
  "properties": {
    "iso:country":"US",
    "sg:address":"403 Pso del Pueblo Sur",
    "sg:city":"Taos",
    "sg:classifiers":[
        {
            "category":"Shopping",
            "type":"Retail Goods"
        }
    ],
    "sg:phone":"+1 505 758 2475",
    "sg:postcode":"87571",
    "sg:province":"NM",
    "sg:tags":[
        "art",
        "gallery",
        "dealer"
    ],
    "wof:name":"Nichols Taos Fine Art Gallery",
    "wof:placetype":"venue"
},
  "geometry": {"coordinates":[-105.57589,36.400774],"type":"Point"}
}