{
  "type": "Feature",
  "properties": {
    "addr:full":"1620 Indian School Rd NE Albuquerque NM 87102",
    "addr:housenumber":"1620",
    "addr:postcode":"87102",
    "addr:street":"Indian School Rd Ne",
    "iso:country":"US",
    "sg:address":"1620 Indian School Rd NE",
    "sg:city":"Albuquerque",
    "sg:classifiers":[
        {
            "category":"Professional",
            "type":"Services"
        }
    ],
    "sg:phone":"+1 505 244 8729",
    "sg:postcode":"87102",
    "sg:province":"NM",
    "sg:tags":[
        "establishment"
    ],
    "wof:name":"Atrla Vista Del Rio",
    "wof:placetype":"venue"
},
  "geometry": {"coordinates":[-106.625381,35.100517],"type":"Point"}
}