{
  "type": "Feature",
  "properties": {
    "iso:country":"US",
    "sg:address":"2710 Alamosa Dr",
    "sg:city":"Santa Fe",
    "sg:classifiers":[
        {
            "category":"Real Estate",
            "subcategory":"Real Estate Agent",
            "type":"Services"
        }
    ],
    "sg:phone":"+1 505 474 3552",
    "sg:postcode":"87505",
    "sg:province":"NM",
    "wof:name":"Real Estate Consulting",
    "wof:placetype":"venue"
},
  "geometry": {"coordinates":[-105.98149600000001,35.650355],"type":"Point"}
}