{
  "type": "Feature",
  "properties": {
    "iso:country":"US",
    "sg:address":"5212 4th St NW",
    "sg:city":"Albuquerque",
    "sg:classifiers":[
        {
            "category":"Banks & Credit Unions",
            "subcategory":"Bank",
            "type":"Services"
        }
    ],
    "sg:phone":"+1 505 345 1453",
    "sg:postcode":"87107",
    "sg:province":"NM",
    "sg:tags":[
        "cashing",
        "check"
    ],
    "wof:name":"Advance America",
    "wof:placetype":"venue"
},
  "geometry": {"coordinates":[-106.64173599999999,35.135773],"type":"Point"}
}