{
  "type": "Feature",
  "properties": {
    "iso:country":"US",
    "sg:address":"7130 National Parks Hwy",
    "sg:city":"Carlsbad",
    "sg:classifiers":[
        {
            "category":"Manufacturing",
            "subcategory":"Electronics",
            "type":"Manufacturing & Wholesale Goods"
        }
    ],
    "sg:phone":"+1 505 887 6790",
    "sg:postcode":"88220",
    "sg:province":"NM",
    "sg:tags":[
        "home",
        "r",
        "mfg"
    ],
    "wof:name":"Edcor Electronics Corporation",
    "wof:placetype":"venue"
},
  "geometry": {"coordinates":[-104.26291399999999,32.322799],"type":"Point"}
}