{
  "type": "Feature",
  "properties": {
    "iso:country":"US",
    "sg:address":"2020 Cll Lorca",
    "sg:city":"Santa Fe",
    "sg:classifiers":[
        {
            "category":"Real Estate",
            "subcategory":"Real Estate Operator",
            "type":"Services"
        }
    ],
    "sg:phone":"+1 505 474 9260",
    "sg:postcode":"87505",
    "sg:province":"NM",
    "sg:tags":[
        "building",
        "apartment"
    ],
    "wof:name":"Evergreen Apartments",
    "wof:placetype":"venue"
},
  "geometry": {"coordinates":[-105.963817,35.657313],"type":"Point"}
}