{
  "type": "Feature",
  "properties": {
    "iso:country":"US",
    "sg:address":"502 W Cordova Rd",
    "sg:city":"Santa Fe",
    "sg:classifiers":[
        {
            "category":"Banks & Credit Unions",
            "subcategory":"Bank",
            "type":"Services"
        }
    ],
    "sg:phone":"+1 505 690 1029",
    "sg:postcode":"87505",
    "sg:province":"NM",
    "sg:tags":[
        "loan",
        "real estate"
    ],
    "sg:website":"www.loansantafe.com",
    "wof:name":"John Ruybalid",
    "wof:placetype":"venue"
},
  "geometry": {"coordinates":[-105.94805,35.672045],"type":"Point"}
}