{
  "type": "Feature",
  "properties": {
    "iso:country":"US",
    "sg:address":"133 Pso del Pueblo Sur",
    "sg:city":"Taos",
    "sg:classifiers":[
        {
            "category":"Shopping",
            "type":"Retail Goods"
        }
    ],
    "sg:phone":"+1 505 737 0500",
    "sg:postcode":"87571",
    "sg:province":"NM",
    "sg:tags":[
        "art",
        "gallery",
        "dealer"
    ],
    "wof:name":"Arte De Oaxaca",
    "wof:placetype":"venue"
},
  "geometry": {"coordinates":[-105.573699,36.406512],"type":"Point"}
}