{
  "type": "Feature",
  "properties": {
    "iso:country":"US",
    "sg:address":"3429 Gibson Blvd SE",
    "sg:city":"Albuquerque",
    "sg:classifiers":[
        {
            "category":"Professional",
            "type":"Services"
        }
    ],
    "sg:phone":"+1 505 255 4227",
    "sg:postcode":"87106",
    "sg:province":"NM",
    "sg:tags":[
        "establishment"
    ],
    "wof:name":"T & C Management",
    "wof:placetype":"venue"
},
  "geometry": {"coordinates":[-106.607878,35.058346],"type":"Point"}
}