{
  "type": "Feature",
  "properties": {
    "addr:full":"1000 Walkway Socorro NM 87801",
    "addr:housenumber":"1000",
    "addr:postcode":"87801",
    "addr:street":"Walkway Socorro",
    "iso:country":"US",
    "sg:address":"1000 Walkway",
    "sg:city":"Socorro",
    "sg:classifiers":[
        {
            "category":"Professional",
            "subcategory":"Art Services",
            "type":"Services"
        }
    ],
    "sg:phone":"+1 505 835 2007",
    "sg:postcode":"87801",
    "sg:province":"NM",
    "sg:tags":[
        "photofinishing",
        "photography",
        "commercial",
        "laboratory"
    ],
    "wof:name":"D Mar Company",
    "wof:placetype":"venue"
},
  "geometry": {"coordinates":[-106.90470999999999,34.070786],"type":"Point"}
}