{
  "type": "Feature",
  "properties": {
    "iso:country":"US",
    "sg:address":"403 Prospect Ave NE",
    "sg:city":"Albuquerque",
    "sg:classifiers":[
        {
            "category":"Wholesale",
            "subcategory":"Construction Materials",
            "type":"Manufacturing & Wholesale Goods"
        }
    ],
    "sg:phone":"+1 505 266 3800",
    "sg:postcode":"87102",
    "sg:province":"NM",
    "sg:tags":[
        "building",
        "product",
        "representative"
    ],
    "sg:website":"www.uplandteam.com",
    "wof:name":"Upland Corp",
    "wof:placetype":"venue"
},
  "geometry": {"coordinates":[-106.636573,35.107931],"type":"Point"}
}