{
  "type": "Feature",
  "properties": {
    "addr:full":"5451 Pinon Hills Blvd Farmington NM 87402",
    "addr:housenumber":"5451",
    "addr:postcode":"87402",
    "addr:street":"Pinon Hills Blvd",
    "iso:country":"US",
    "sg:address":"5451 Pinon Hills Blvd",
    "sg:city":"Farmington",
    "sg:classifiers":[
        {
            "category":"Building & Trades",
            "subcategory":"Construction",
            "type":"Services"
        }
    ],
    "sg:phone":"+1 505 599 0200",
    "sg:postcode":"87402",
    "sg:province":"NM",
    "sg:tags":[
        "home",
        "improvement"
    ],
    "wof:name":"Lowe's Of Farmington",
    "wof:placetype":"venue"
},
  "geometry": {"coordinates":[-108.13993600000001,36.772525],"type":"Point"}
}