{
  "type": "Feature",
  "properties": {
    "iso:country":"US",
    "sg:address":"116 Vermont St NE",
    "sg:city":"Albuquerque",
    "sg:classifiers":[
        {
            "category":"Retail",
            "subcategory":"Auto Repair",
            "type":"Services"
        }
    ],
    "sg:phone":"+1 505 256 9074",
    "sg:postcode":"87108",
    "sg:province":"NM",
    "sg:tags":[
        "general"
    ],
    "wof:name":"H & M Mobile Service",
    "wof:placetype":"venue"
},
  "geometry": {"coordinates":[-106.553688,35.076018],"type":"Point"}
}