{
  "type": "Feature",
  "properties": {
    "iso:country":"US",
    "sg:address":"350 Wind Chime Ln",
    "sg:city":"Las Cruces",
    "sg:classifiers":[
        {
            "category":"Building & Trades",
            "subcategory":"Plumbing",
            "type":"Services"
        }
    ],
    "sg:phone":"+1 505 647 3484",
    "sg:postcode":"88007",
    "sg:province":"NM",
    "sg:tags":[
        "septic"
    ],
    "wof:name":"Victor's Septic System",
    "wof:placetype":"venue"
},
  "geometry": {"coordinates":[-106.819022,32.382943],"type":"Point"}
}