{
  "type": "Feature",
  "properties": {
    "addr:full":"805 San Mateo Blvd NE Albuquerque NM 87108",
    "addr:housenumber":"805",
    "addr:postcode":"87108",
    "addr:street":"San Mateo Blvd Ne",
    "iso:country":"US",
    "sg:address":"805 San Mateo Blvd NE",
    "sg:city":"Albuquerque",
    "sg:classifiers":[
        {
            "category":"Shopping",
            "subcategory":"Florist",
            "type":"Retail Goods"
        }
    ],
    "sg:phone":"+1 505 750 9264",
    "sg:postcode":"87108",
    "sg:province":"NM",
    "sg:tags":[
        "basket",
        "gift"
    ],
    "sg:website":"http://www.mauldinsflowers.com",
    "wof:name":"Mauldin's Flowers Inc",
    "wof:placetype":"venue"
},
  "geometry": {"coordinates":[-106.586304,35.085432],"type":"Point"}
}