{
  "type": "Feature",
  "properties": {
    "iso:country":"US",
    "sg:address":"49 Cll Electra",
    "sg:city":"Santa Fe",
    "sg:classifiers":[
        {
            "category":"Retail",
            "subcategory":"Portrait Studio",
            "type":"Services"
        }
    ],
    "sg:phone":"+1 505 466 4284",
    "sg:postcode":"87508",
    "sg:province":"NM",
    "sg:tags":[
        "photographer"
    ],
    "wof:name":"Mary C Fredenburgh Phtgrphr",
    "wof:placetype":"venue"
},
  "geometry": {"coordinates":[-105.886395,35.546999],"type":"Point"}
}