{
  "type": "Feature",
  "properties": {
    "iso:country":"US",
    "sg:address":"304 S Pershing St",
    "sg:city":"Truth Or Cnsqncs",
    "sg:classifiers":[
        {
            "category":"Restaurant",
            "type":"Food & Drink"
        }
    ],
    "sg:phone":"+1 505 894 7687",
    "sg:postcode":"87901",
    "sg:province":"NM",
    "wof:name":"Pacific Grill",
    "wof:placetype":"venue"
},
  "geometry": {"coordinates":[-107.25221500000001,33.129092],"type":"Point"}
}