{
  "type": "Feature",
  "properties": {
    "addr:full":"730 Woodland Ave NW Albuquerque NM 87107",
    "addr:housenumber":"730",
    "addr:postcode":"87107",
    "addr:street":"Woodland Ave Nw",
    "iso:country":"US",
    "sg:address":"730 Woodland Ave NW",
    "sg:city":"Albuquerque",
    "sg:classifiers":[
        {
            "category":"Professional",
            "type":"Services"
        }
    ],
    "sg:phone":"+1 505 296 4445",
    "sg:postcode":"87107",
    "sg:province":"NM",
    "wof:name":"Transitionworks",
    "wof:placetype":"venue"
},
  "geometry": {"coordinates":[-106.65164,35.112395],"type":"Point"}
}