{
  "type": "Feature",
  "properties": {
    "addr:full":"5016 Cresta del Sur Ct NE Albuquerque NM 87111",
    "addr:housenumber":"5016",
    "addr:postcode":"87111",
    "addr:street":"Cresta Del Sur Ct Ne",
    "iso:country":"US",
    "sg:address":"5016 Cresta del Sur Ct NE",
    "sg:city":"Albuquerque",
    "sg:classifiers":[
        {
            "category":"Arts & Performance",
            "subcategory":"Theater",
            "type":"Entertainment"
        }
    ],
    "sg:phone":"+1 505 332 0811",
    "sg:postcode":"87111",
    "sg:province":"NM",
    "sg:tags":[
        "group"
    ],
    "wof:name":"Eleganza Music Co",
    "wof:placetype":"venue"
},
  "geometry": {"coordinates":[-106.484112,35.136658],"type":"Point"}
}