{
  "type": "Feature",
  "properties": {
    "iso:country":"US",
    "sg:address":"209 Richmond Dr SE",
    "sg:city":"Albuquerque",
    "sg:classifiers":[
        {
            "category":"Professional",
            "subcategory":"Business Services",
            "type":"Services"
        }
    ],
    "sg:phone":"+1 505 256 7380",
    "sg:postcode":"87106",
    "sg:province":"NM",
    "wof:name":"Karandi Bilmes Enterprises",
    "wof:placetype":"venue"
},
  "geometry": {"coordinates":[-106.610873,35.07743],"type":"Point"}
}