{
  "type": "Feature",
  "properties": {
    "iso:country":"US",
    "sg:address":"301 W Santa Fe Ave",
    "sg:city":"Grants",
    "sg:classifiers":[
        {
            "category":"Professional",
            "subcategory":"Business Services",
            "type":"Services"
        }
    ],
    "sg:phone":"+1 505 287 2445",
    "sg:postcode":"87020",
    "sg:province":"NM",
    "wof:name":"AAA Title Loans",
    "wof:placetype":"venue"
},
  "geometry": {"coordinates":[-107.852603,35.151972],"type":"Point"}
}