{
  "type": "Feature",
  "properties": {
    "iso:country":"US",
    "sg:address":"1102 S Platinum Ave",
    "sg:city":"Deming",
    "sg:classifiers":[
        {
            "category":"Food & Beverages",
            "subcategory":"Specialty",
            "type":"Retail Goods"
        }
    ],
    "sg:phone":"+1 505 544 8419",
    "sg:postcode":"88030",
    "sg:province":"NM",
    "wof:name":"Yamanouchi Consumer Inc",
    "wof:placetype":"venue"
},
  "geometry": {"coordinates":[-107.75494500000001,32.258089],"type":"Point"}
}