{
  "type": "Feature",
  "properties": {
    "iso:country":"US",
    "sg:address":"9132 4th St NW",
    "sg:city":"Albuquerque",
    "sg:classifiers":[
        {
            "category":"Professional",
            "subcategory":"Business Services",
            "type":"Services"
        },
        {
            "category":"Government",
            "subcategory":"Post Office",
            "type":"Public Place"
        }
    ],
    "sg:phone":"+1 800 275 8777",
    "sg:postcode":"87114",
    "sg:province":"NM",
    "sg:tags":[
        "mail",
        "shipping"
    ],
    "sg:website":"http://www.usps.com",
    "wof:name":"USPS - United States Post Office - Alameda Branch",
    "wof:placetype":"venue"
},
  "geometry": {"coordinates":[-106.620976,35.185213],"type":"Point"}
}