{
  "type": "Feature",
  "properties": {
    "iso:country":"US",
    "sg:address":"1409 Comer Dr",
    "sg:city":"Clovis",
    "sg:classifiers":[
        {
            "category":"Retail",
            "subcategory":"Animal Services",
            "type":"Services"
        }
    ],
    "sg:phone":"+1 505 763 0583",
    "sg:postcode":"88101",
    "sg:province":"NM",
    "sg:tags":[
        "pet"
    ],
    "wof:name":"Pooper Scooper",
    "wof:placetype":"venue"
},
  "geometry": {"coordinates":[-103.224327,34.430668],"type":"Point"}
}