{
  "type": "Feature",
  "properties": {
    "iso:country":"US",
    "sg:address":"5825 Mc Kinney Dr NE",
    "sg:city":"Albuquerque",
    "sg:classifiers":[
        {
            "category":"Freight",
            "type":"Transportation"
        }
    ],
    "sg:phone":"+1 505 821 4070",
    "sg:postcode":"87109",
    "sg:province":"NM",
    "sg:tags":[
        "commercial",
        "storage",
        "general"
    ],
    "wof:name":"Mc Kinney Mini Storage",
    "wof:placetype":"venue"
},
  "geometry": {"coordinates":[-106.579516,35.148402],"type":"Point"}
}