{
  "type": "Feature",
  "properties": {
    "iso:country":"US",
    "sg:address":"715 Dr Martin Luther King Jr Ave NE",
    "sg:city":"Albuquerque",
    "sg:classifiers":[
        {
            "category":"Health Services",
            "subcategory":"Doctor",
            "type":"Services"
        }
    ],
    "sg:phone":"+1 505 848 3700",
    "sg:postcode":"87102",
    "sg:province":"NM",
    "sg:tags":[
        "physician"
    ],
    "wof:name":"Pediatrick Chrlogy Assosciates",
    "wof:placetype":"venue"
},
  "geometry": {"coordinates":[-106.638257,35.085494],"type":"Point"}
}