{
  "type": "Feature",
  "properties": {
    "iso:country":"US",
    "sg:address":"1655 Cll Sotero",
    "sg:city":"Santa Fe",
    "sg:classifiers":[
        {
            "category":"Travel",
            "subcategory":"Travel Agent",
            "type":"Entertainment"
        }
    ],
    "sg:phone":"+1 505 983 1570",
    "sg:postcode":"87507",
    "sg:province":"NM",
    "sg:tags":[
        "tours",
        "promoter"
    ],
    "wof:name":"Fiesta Tours",
    "wof:placetype":"venue"
},
  "geometry": {"coordinates":[-105.987101,35.66214],"type":"Point"}
}