{
  "type": "Feature",
  "properties": {
    "iso:country":"US",
    "sg:address":"742 Cam del Pueblo",
    "sg:city":"Bernalillo",
    "sg:classifiers":[
        {
            "category":"Restaurant",
            "type":"Food & Drink"
        }
    ],
    "sg:phone":"+1 505 867 7228",
    "sg:postcode":"87004",
    "sg:province":"NM",
    "wof:name":"Fatwich Deli",
    "wof:placetype":"venue"
},
  "geometry": {"coordinates":[-106.548337,35.305918],"type":"Point"}
}