{
  "type": "Feature",
  "properties": {
    "addr:full":"37 Rd 3523 Flora Vista NM 87415",
    "addr:housenumber":"37;3523",
    "addr:postcode":"87415",
    "addr:street":"Rd;Flora Vista",
    "iso:country":"US",
    "sg:address":"37 Rd 3523",
    "sg:city":"Flora Vista",
    "sg:classifiers":[
        {
            "category":"Personal",
            "type":"Services"
        }
    ],
    "sg:phone":"+1 505 334 8149",
    "sg:postcode":"87415",
    "sg:province":"NM",
    "wof:name":"Marshall Mead",
    "wof:placetype":"venue"
},
  "geometry": {"coordinates":[-108.082909,36.789011],"type":"Point"}
}