{
  "type": "Feature",
  "properties": {
    "iso:country":"US",
    "sg:address":"311 N Downtown Mall",
    "sg:city":"Las Cruces",
    "sg:classifiers":[
        {
            "category":"Shopping",
            "type":"Retail Goods"
        }
    ],
    "sg:phone":"+1 505 523 2950",
    "sg:postcode":"88001",
    "sg:province":"NM",
    "sg:tags":[
        "art",
        "gallery",
        "dealer"
    ],
    "wof:name":"Blue Gate Gallery",
    "wof:placetype":"venue"
},
  "geometry": {"coordinates":[-106.77902,32.311423],"type":"Point"}
}