{
  "type": "Feature",
  "properties": {
    "addr:full":"3300 N Main St Roswell NM 88201",
    "addr:housenumber":"3300",
    "addr:postcode":"88201",
    "addr:street":"N Main St",
    "iso:country":"US",
    "sg:address":"3300 N Main St",
    "sg:city":"Roswell",
    "sg:classifiers":[
        {
            "category":"Food & Beverages",
            "subcategory":"Groceries & Convenience Stores",
            "type":"Retail Goods"
        }
    ],
    "sg:phone":"+1 505 624 1158",
    "sg:postcode":"88201",
    "sg:province":"NM",
    "wof:name":"K W Express",
    "wof:placetype":"venue"
},
  "geometry": {"coordinates":[-104.523236,33.440995],"type":"Point"}
}