{
  "type": "Feature",
  "properties": {
    "addr:full":"700 Wyoming Blvd NE Albuquerque NM 87123",
    "addr:housenumber":"700",
    "addr:postcode":"87123",
    "addr:street":"Ne",
    "iso:country":"US",
    "sg:address":"700 Wyoming Blvd NE",
    "sg:city":"Albuquerque",
    "sg:classifiers":[
        {
            "category":"Autos & Motor Vehicles",
            "subcategory":"Automobile Sales",
            "type":"Retail Goods"
        },
        {
            "category":"Banks & Credit Unions",
            "subcategory":"Financial Services",
            "type":"Services"
        }
    ],
    "sg:phone":"+1 505 349 3849",
    "sg:postcode":"87123",
    "sg:province":"NM",
    "sg:tags":[
        "car",
        "financing",
        "used",
        "truck"
    ],
    "sg:website":"https://www.drivetime.com/getapprovedppc/default.aspx?source=0A5AD7568164417D8DC2F5D8DE429FF2&campaign=bc",
    "wof:name":"DriveTime",
    "wof:placetype":"venue"
},
  "geometry": {"coordinates":[-106.55032300000001,35.08396],"type":"Point"}
}