{
  "type": "Feature",
  "properties": {
    "addr:full":"7439 Pan American West Fwy NE Albuquerque NM 87109",
    "addr:housenumber":"7439",
    "addr:postcode":"87109",
    "addr:street":"Pan American West Fwy Ne",
    "iso:country":"US",
    "sg:address":"7439 Pan American West Fwy NE",
    "sg:city":"Albuquerque",
    "sg:classifiers":[
        {
            "category":"Travel",
            "subcategory":"Hotels & Motels",
            "type":"Entertainment"
        }
    ],
    "sg:phone":"+1 505 345 7500",
    "sg:postcode":"87109",
    "sg:province":"NM",
    "sg:tags":[
        "corporate",
        "lodging"
    ],
    "sg:website":"http://redirect.searchignite.com/si/cm/tracking/DGTrackingRedirect.aspx?siclientid=2537&siredirect=http://www.lq.com/lq/properties/propertyProfile.do%3Fident%3DLQ4023%26IATA%3D99020726%26WT.srch%3D1&sisearchengine=155&siproduct=LQ+Albuquerque+Northwest",
    "wof:name":"La Quinta Inn & Suites Albuquerque - Northwest",
    "wof:placetype":"venue"
},
  "geometry": {"coordinates":[-106.586962,35.162539],"type":"Point"}
}