{
  "type": "Feature",
  "properties": {
    "iso:country":"US",
    "sg:address":"1314 Monte Largo Dr NE",
    "sg:city":"Albuquerque",
    "sg:classifiers":[
        {
            "category":"Home & Garden",
            "subcategory":"Home Furnishings",
            "type":"Retail Goods"
        }
    ],
    "sg:phone":"+1 505 489 4800",
    "sg:postcode":"87112",
    "sg:province":"NM",
    "sg:tags":[
        "beveled",
        "glass",
        "ornamental"
    ],
    "wof:name":"Fire Shop",
    "wof:placetype":"venue"
},
  "geometry": {"coordinates":[-106.492616,35.092226],"type":"Point"}
}