{
  "type": "Feature",
  "properties": {
    "iso:country":"US",
    "sg:address":"305 E Foster Rd",
    "sg:city":"Las Cruces",
    "sg:classifiers":[
        {
            "category":"Personal",
            "type":"Services"
        }
    ],
    "sg:phone":"+1 505 649 3327",
    "sg:postcode":"88005",
    "sg:province":"NM",
    "sg:tags":[
        "therapist",
        "massage"
    ],
    "wof:name":"Madrid Ilda",
    "wof:placetype":"venue"
},
  "geometry": {"coordinates":[-106.773629,32.295688],"type":"Point"}
}