{
  "type": "Feature",
  "properties": {
    "iso:country":"US",
    "sg:address":"1208 Silver Ave SW",
    "sg:city":"Albuquerque",
    "sg:classifiers":[
        {
            "category":"Professional",
            "subcategory":"Management & Consulting",
            "type":"Services"
        }
    ],
    "sg:phone":"+1 505 247 1917",
    "sg:postcode":"87102",
    "sg:province":"NM",
    "sg:tags":[
        "communication",
        "training",
        "intercultural"
    ],
    "wof:name":"Susan Rinderle Consulting",
    "wof:placetype":"venue"
},
  "geometry": {"coordinates":[-106.662601,35.083851],"type":"Point"}
}