{
  "type": "Feature",
  "properties": {
    "iso:country":"US",
    "sg:address":"701 E 11th St",
    "sg:city":"Clovis",
    "sg:classifiers":[
        {
            "category":"Organizations",
            "subcategory":"Religious Organization",
            "type":"Services"
        }
    ],
    "sg:phone":"+1 505 763 4110",
    "sg:postcode":"88101",
    "sg:province":"NM",
    "sg:tags":[
        "church"
    ],
    "wof:name":"Eastern Baptist Assn",
    "wof:placetype":"venue"
},
  "geometry": {"coordinates":[-103.197723,34.408894],"type":"Point"}
}