{
  "type": "Feature",
  "properties": {
    "iso:country":"US",
    "sg:address":"4630 Pan American Fwy",
    "sg:city":"Albuquerque",
    "sg:classifiers":[
        {
            "category":"Travel",
            "subcategory":"Hotels & Motels",
            "type":"Entertainment"
        }
    ],
    "sg:phone":"+1 505 830 0900",
    "sg:postcode":"87109",
    "sg:province":"NM",
    "sg:website":"www.bestwestern.com",
    "wof:name":"Best Western Inn",
    "wof:placetype":"venue"
},
  "geometry": {"coordinates":[-106.607465,35.133689],"type":"Point"}
}