{
  "type": "Feature",
  "properties": {
    "iso:country":"US",
    "sg:address":"502 S 1st St",
    "sg:city":"Tucumcari",
    "sg:classifiers":[
        {
            "category":"Insurance",
            "subcategory":"Insurance Agent",
            "type":"Services"
        }
    ],
    "sg:phone":"+1 505 461 2710",
    "sg:postcode":"88401",
    "sg:province":"NM",
    "wof:name":"Ronny B Sanders Insurance Inc",
    "wof:placetype":"venue"
},
  "geometry": {"coordinates":[-103.724825,35.174775],"type":"Point"}
}