{
  "type": "Feature",
  "properties": {
    "addr:full":"315 N Atkinson Ave Roswell NM 88201",
    "addr:housenumber":"315",
    "addr:postcode":"88201",
    "addr:street":"N Atkinson Ave",
    "iso:country":"US",
    "sg:address":"315 N Atkinson Ave",
    "sg:city":"Roswell",
    "sg:classifiers":[
        {
            "category":"Health Services",
            "subcategory":"Doctor",
            "type":"Services"
        }
    ],
    "sg:phone":"+1 505 625 9610",
    "sg:postcode":"88201",
    "sg:province":"NM",
    "sg:tags":[
        "medical",
        "clinic"
    ],
    "wof:name":"Continuing Care Concepts Inc",
    "wof:placetype":"venue"
},
  "geometry": {"coordinates":[-104.505419,33.396495],"type":"Point"}
}