{
  "type": "Feature",
  "properties": {
    "iso:country":"US",
    "sg:address":"2400 S 9th St",
    "sg:city":"Tucumcari",
    "sg:classifiers":[
        {
            "category":"Organizations",
            "subcategory":"Religious Organization",
            "type":"Services"
        }
    ],
    "sg:phone":"+1 505 461 9676",
    "sg:postcode":"88401",
    "sg:province":"NM",
    "sg:tags":[
        "church"
    ],
    "wof:name":"Church Of Jesus Christ Of Lds",
    "wof:placetype":"venue"
},
  "geometry": {"coordinates":[-103.73503100000001,35.155546],"type":"Point"}
}