{
  "type": "Feature",
  "properties": {
    "iso:country":"US",
    "sg:address":"431 Saint Michaels Dr",
    "sg:city":"Santa Fe",
    "sg:classifiers":[
        {
            "category":"Health Services",
            "subcategory":"Doctor",
            "type":"Services"
        }
    ],
    "sg:phone":"+1 505 954 9949",
    "sg:postcode":"87505",
    "sg:province":"NM",
    "sg:tags":[
        "physician",
        "surgeon"
    ],
    "wof:name":"On Call Immediate Medical Care",
    "wof:placetype":"venue"
},
  "geometry": {"coordinates":[-105.94380200000001,35.656645],"type":"Point"}
}