{
  "type": "Feature",
  "properties": {
    "addr:full":"4009 San Mateo Blvd NE Albuquerque NM 87110",
    "addr:housenumber":"4009",
    "addr:postcode":"87110",
    "addr:street":"San Mateo Blvd Ne",
    "iso:country":"US",
    "sg:address":"4009 San Mateo Blvd NE",
    "sg:city":"Albuquerque",
    "sg:classifiers":[
        {
            "category":"Bakery",
            "type":"Food & Drink"
        },
        {
            "category":"Coffee & Tea",
            "type":"Food & Drink"
        },
        {
            "category":"Bagels",
            "type":"Food & Drink"
        },
        {
            "category":"Donuts",
            "type":"Food & Drink"
        }
    ],
    "sg:menulink":"http://www.allmenus.com/nm/albuquerque/143928-dunkin-donuts/menu/",
    "sg:phone":"+1 505 881 9895",
    "sg:postcode":"87110",
    "sg:province":"NM",
    "sg:tags":[
        "american",
        "diner",
        "pastry"
    ],
    "wof:name":"Dunkin' Donuts",
    "wof:placetype":"venue"
},
  "geometry": {"coordinates":[-106.586533,35.12695],"type":"Point"}
}