{
  "type": "Feature",
  "properties": {
    "iso:country":"US",
    "sg:address":"3201 N Prince St",
    "sg:city":"Clovis",
    "sg:classifiers":[
        {
            "category":"Personal",
            "subcategory":"Barber",
            "type":"Services"
        }
    ],
    "sg:phone":"+1 505 749 5825",
    "sg:postcode":"88101",
    "sg:province":"NM",
    "wof:name":"B & J's Barber & Pro Shop",
    "wof:placetype":"venue"
},
  "geometry": {"coordinates":[-103.19642,34.431356],"type":"Point"}
}