{
  "type": "Feature",
  "properties": {
    "iso:country":"US",
    "sg:address":"106 Metz Dr",
    "sg:city":"Ruidoso",
    "sg:classifiers":[
        {
            "category":"Building & Trades",
            "subcategory":"Landscaping Services",
            "type":"Services"
        }
    ],
    "sg:phone":"+1 505 258 1000",
    "sg:postcode":"88345",
    "sg:province":"NM",
    "sg:website":"www.ziascapes.com",
    "wof:name":"Ziascapes",
    "wof:placetype":"venue"
},
  "geometry": {"coordinates":[-105.669881,33.352148],"type":"Point"}
}