{
  "type": "Feature",
  "properties": {
    "iso:country":"US",
    "sg:address":"4930 McLeod Rd NE",
    "sg:city":"Albuquerque",
    "sg:classifiers":[
        {
            "category":"Sports & Exercise",
            "subcategory":"Gym",
            "type":"Entertainment"
        }
    ],
    "sg:phone":"+1 505 888 7097",
    "sg:postcode":"87109",
    "sg:province":"NM",
    "sg:tags":[
        "fitness",
        "physical",
        "facility"
    ],
    "sg:website":"www.defined.com",
    "wof:name":"Defined Fitness",
    "wof:placetype":"venue"
},
  "geometry": {"coordinates":[-106.588469,35.1382],"type":"Point"}
}