{
  "type": "Feature",
  "properties": {
    "addr:full":"1730 Montano Rd NW Albuquerque NM 87107",
    "addr:housenumber":"1730",
    "addr:postcode":"87107",
    "addr:street":"Montano Rd Nw",
    "iso:country":"US",
    "sg:address":"1730 Montano Rd NW",
    "sg:city":"Albuquerque",
    "sg:classifiers":[
        {
            "category":"Utilities",
            "subcategory":"Telephone",
            "type":"Services"
        }
    ],
    "sg:phone":"+1 505 345 5535",
    "sg:postcode":"87107",
    "sg:province":"NM",
    "sg:tags":[
        "telecommunication"
    ],
    "wof:name":"Realize Communications",
    "wof:placetype":"venue"
},
  "geometry": {"coordinates":[-106.66291200000001,35.142346],"type":"Point"}
}