{
  "type": "Feature",
  "properties": {
    "addr:full":"78 Vis del Oro Cerrillos NM 87010",
    "addr:postcode":"87010",
    "addr:street":"Del Oro",
    "iso:country":"US",
    "sg:address":"78 Vis del Oro",
    "sg:city":"Cerrillos",
    "sg:classifiers":[
        {
            "category":"Travel",
            "subcategory":"Hotels & Motels",
            "type":"Entertainment"
        }
    ],
    "sg:phone":"+1 505 424 8995",
    "sg:postcode":"87010",
    "sg:province":"NM",
    "sg:tags":[
        "breakfast",
        "accommodation",
        "bed"
    ],
    "sg:website":"www.hdasantafe.com",
    "wof:name":"Hacienda Dona Andrea De Santa",
    "wof:placetype":"venue"
},
  "geometry": {"coordinates":[-106.127608,35.360983],"type":"Point"}
}