{
  "type": "Feature",
  "properties": {
    "iso:country":"US",
    "sg:address":"713 N Main St",
    "sg:city":"Belen",
    "sg:classifiers":[
        {
            "category":"Restaurant",
            "type":"Food & Drink"
        }
    ],
    "sg:phone":"+1 505 864 0110",
    "sg:postcode":"87002",
    "sg:province":"NM",
    "sg:tags":[
        "eating"
    ],
    "wof:name":"Sonic Drive-In",
    "wof:placetype":"venue"
},
  "geometry": {"coordinates":[-106.77457699999999,34.667563],"type":"Point"}
}