{
  "type": "Feature",
  "properties": {
    "iso:country":"US",
    "sg:address":"4902 Hawkins St NE",
    "sg:city":"Albuquerque",
    "sg:classifiers":[
        {
            "category":"Professional",
            "type":"Services"
        }
    ],
    "sg:phone":"+1 505 345 9623",
    "sg:postcode":"87109",
    "sg:province":"NM",
    "wof:name":"Custom Medical Solutions",
    "wof:placetype":"venue"
},
  "geometry": {"coordinates":[-106.590616,35.161909],"type":"Point"}
}