{
  "type": "Feature",
  "properties": {
    "addr:full":"200 W 1st St Roswell NM 88203",
    "addr:housenumber":"200",
    "addr:postcode":"88203",
    "addr:street":"W 1St St",
    "iso:country":"US",
    "sg:address":"200 W 1st St",
    "sg:city":"Roswell",
    "sg:classifiers":[
        {
            "category":"Health Services",
            "subcategory":"Health Practitioner",
            "type":"Services"
        }
    ],
    "sg:phone":"+1 505 623 1943",
    "sg:postcode":"88203",
    "sg:province":"NM",
    "sg:tags":[
        "psychologist"
    ],
    "wof:name":"Lynn B Daugherty PHD",
    "wof:placetype":"venue"
},
  "geometry": {"coordinates":[-104.526025,33.393102],"type":"Point"}
}