{
  "type": "Feature",
  "properties": {
    "iso:country":"US",
    "sg:address":"3301 Coors Blvd NW",
    "sg:city":"Albuquerque",
    "sg:classifiers":[
        {
            "category":"Shopping",
            "subcategory":"Computers & Home Electronics",
            "type":"Retail Goods"
        }
    ],
    "sg:phone":"+1 505 831 5946",
    "sg:postcode":"87120",
    "sg:province":"NM",
    "wof:name":"Radio Shack",
    "wof:placetype":"venue"
},
  "geometry": {"coordinates":[-106.701724,35.11934],"type":"Point"}
}