{
  "type": "Feature",
  "properties": {
    "iso:country":"US",
    "sg:address":"60 E San Francisco St",
    "sg:city":"Santa Fe",
    "sg:classifiers":[
        {
            "category":"Shopping",
            "subcategory":"Jewelry",
            "type":"Retail Goods"
        }
    ],
    "sg:phone":"+1 505 820 1399",
    "sg:postcode":"87501",
    "sg:province":"NM",
    "sg:tags":[
        "jeweler"
    ],
    "wof:name":"Amber Collections",
    "wof:placetype":"venue"
},
  "geometry": {"coordinates":[-105.938587,35.687061],"type":"Point"}
}