{
  "type": "Feature",
  "properties": {
    "addr:full":"2920 Los Lentes Rd SE Los Lunas NM 87031",
    "addr:housenumber":"2920",
    "addr:postcode":"87031",
    "addr:street":"Los Lentes Rd Se",
    "iso:country":"US",
    "sg:address":"2920 Los Lentes Rd SE",
    "sg:city":"Los Lunas",
    "sg:classifiers":[
        {
            "category":"Farming",
            "subcategory":"Farm & Veterinary Services",
            "type":"Manufacturing & Wholesale Goods"
        }
    ],
    "sg:phone":"+1 505 565 4469",
    "sg:postcode":"87031",
    "sg:province":"NM",
    "sg:tags":[
        "breeder",
        "livestock"
    ],
    "wof:name":"4 Daughters Land & Cattle Co",
    "wof:placetype":"venue"
},
  "geometry": {"coordinates":[-106.741365,34.776738],"type":"Point"}
}