{
  "type": "Feature",
  "properties": {
    "addr:full":"2882 Trades West Rd Santa Fe NM 87507",
    "addr:housenumber":"2882",
    "addr:postcode":"87507",
    "addr:street":"Trades West Rd",
    "iso:country":"US",
    "sg:address":"2882 Trades West Rd",
    "sg:city":"Santa Fe",
    "sg:classifiers":[
        {
            "category":"Manufacturing",
            "subcategory":"Signs",
            "type":"Manufacturing & Wholesale Goods"
        }
    ],
    "sg:phone":"+1 505 474 4746",
    "sg:postcode":"87507",
    "sg:province":"NM",
    "wof:name":"Arroyo Studio LLC",
    "wof:placetype":"venue"
},
  "geometry": {"coordinates":[-105.99176799999999,35.66143],"type":"Point"}
}