{
  "type": "Feature",
  "properties": {
    "iso:country":"US",
    "sg:address":"3001 State Hwy 90 S",
    "sg:city":"Silver City",
    "sg:classifiers":[
        {
            "category":"Organizations",
            "subcategory":"Religious Organization",
            "type":"Services"
        }
    ],
    "sg:phone":"+1 505 388 1031",
    "sg:postcode":"88065",
    "sg:province":"NM",
    "sg:tags":[
        "church"
    ],
    "sg:website":"www.calvarychapel.com/silvercity",
    "wof:name":"Calvary Chapel",
    "wof:placetype":"venue"
},
  "geometry": {"coordinates":[-108.341872,32.649031],"type":"Point"}
}