{
  "type": "Feature",
  "properties": {
    "addr:full":"8504 Spain Rd NE Albuquerque NM 87111",
    "addr:housenumber":"8504",
    "addr:postcode":"87111",
    "addr:street":"Spain Rd Ne",
    "iso:country":"US",
    "sg:address":"8504 Spain Rd NE",
    "sg:city":"Albuquerque",
    "sg:classifiers":[
        {
            "category":"Real Estate",
            "subcategory":"Architect",
            "type":"Services"
        }
    ],
    "sg:phone":"+1 505 821 5687",
    "sg:postcode":"87111",
    "sg:province":"NM",
    "sg:tags":[
        "architectural"
    ],
    "wof:name":"Miguel Trujillo & Associate",
    "wof:placetype":"venue"
},
  "geometry": {"coordinates":[-106.546024,35.139118],"type":"Point"}
}