{
  "type": "Feature",
  "properties": {
    "iso:country":"US",
    "sg:address":"5333 4th St NW",
    "sg:city":"Albuquerque",
    "sg:classifiers":[
        {
            "category":"Restaurant",
            "type":"Food & Drink"
        }
    ],
    "sg:menulink":"http://www.allmenus.com/nm/albuquerque/27316-tio-oscars-calderon/menu/",
    "sg:phone":"+1 505 342 1334",
    "sg:postcode":"87107",
    "sg:province":"NM",
    "sg:tags":[
        "mexican"
    ],
    "wof:name":"Tio Oscar's Calderon",
    "wof:placetype":"venue"
},
  "geometry": {"coordinates":[-106.641566,35.13707],"type":"Point"}
}