{
  "type": "Feature",
  "properties": {
    "iso:country":"US",
    "sg:address":"249 Old Church Rd",
    "sg:city":"Corrales",
    "sg:classifiers":[
        {
            "category":"Retail",
            "subcategory":"Repair Shop",
            "type":"Services"
        }
    ],
    "sg:phone":"+1 505 898 4539",
    "sg:postcode":"87048",
    "sg:province":"NM",
    "wof:name":"Demar Machines",
    "wof:placetype":"venue"
},
  "geometry": {"coordinates":[-106.62730000000001,35.229989],"type":"Point"}
}