{
  "type": "Feature",
  "properties": {
    "iso:country":"US",
    "sg:address":"10309 Manzanillo Ave NE",
    "sg:city":"Albuquerque",
    "sg:classifiers":[
        {
            "category":"Manufacturing",
            "subcategory":"Chemicals & Compounds",
            "type":"Manufacturing & Wholesale Goods"
        }
    ],
    "sg:phone":"+1 505 275 7774",
    "sg:postcode":"87111",
    "sg:province":"NM",
    "sg:tags":[
        "active",
        "surface",
        "agent",
        "mfg"
    ],
    "wof:name":"7 Eight 9",
    "wof:placetype":"venue"
},
  "geometry": {"coordinates":[-106.523589,35.144939],"type":"Point"}
}