{
  "type": "Feature",
  "properties": {
    "iso:country":"US",
    "sg:address":"301 E Marland St",
    "sg:city":"Hobbs",
    "sg:classifiers":[
        {
            "category":"Retail",
            "subcategory":"Auto Repair",
            "type":"Services"
        }
    ],
    "sg:phone":"+1 505 393 0661",
    "sg:postcode":"88240",
    "sg:province":"NM",
    "sg:tags":[
        "repairing",
        "tire"
    ],
    "wof:name":"Benny's Tire Repair",
    "wof:placetype":"venue"
},
  "geometry": {"coordinates":[-103.133743,32.696596],"type":"Point"}
}