{
  "type": "Feature",
  "properties": {
    "iso:country":"US",
    "sg:address":"4321 Fulcrum Way NE",
    "sg:city":"Rio Rancho",
    "sg:classifiers":[
        {
            "category":"Arts & Performance",
            "subcategory":"Theater",
            "type":"Entertainment"
        }
    ],
    "sg:phone":"+1 505 867 0660",
    "sg:postcode":"87144",
    "sg:province":"NM",
    "sg:tags":[
        "bureau"
    ],
    "wof:name":"Lions Gate Entertainment Inc",
    "wof:placetype":"venue"
},
  "geometry": {"coordinates":[-106.57715399999999,35.327315],"type":"Point"}
}