{
  "type": "Feature",
  "properties": {
    "iso:country":"US",
    "sg:address":"604 Alta Vista St",
    "sg:city":"Santa Fe",
    "sg:classifiers":[
        {
            "category":"Government",
            "subcategory":"Office",
            "type":"Public Place"
        }
    ],
    "sg:phone":"+1 505 983 1202",
    "sg:postcode":"87505",
    "sg:province":"NM",
    "sg:tags":[
        "village"
    ],
    "wof:name":"Santa Fe Traffic Signal Mntnc",
    "wof:placetype":"venue"
},
  "geometry": {"coordinates":[-105.951579,35.670112],"type":"Point"}
}