{
  "type": "Feature",
  "properties": {
    "addr:full":"1421 Luisa St Santa Fe NM 87505",
    "addr:housenumber":"1421",
    "addr:postcode":"87505",
    "addr:street":"Luisa St",
    "iso:country":"US",
    "sg:address":"1421 Luisa St",
    "sg:city":"Santa Fe",
    "sg:classifiers":[
        {
            "category":"Insurance",
            "subcategory":"Insurance Agent",
            "type":"Services"
        }
    ],
    "sg:phone":"+1 505 983 9587",
    "sg:postcode":"87505",
    "sg:province":"NM",
    "wof:name":"Northwestern Mutual Insurance",
    "wof:placetype":"venue"
},
  "geometry": {"coordinates":[-105.9515,35.66866],"type":"Point"}
}