{
  "type": "Feature",
  "properties": {
    "iso:country":"US",
    "sg:address":"214 Griffin St",
    "sg:city":"Santa Fe",
    "sg:classifiers":[
        {
            "category":"Shopping",
            "type":"Retail Goods"
        }
    ],
    "sg:phone":"+1 505 982 6881",
    "sg:postcode":"87501",
    "sg:province":"NM",
    "sg:tags":[
        "art",
        "gallery",
        "dealer"
    ],
    "wof:name":"Provenance",
    "wof:placetype":"venue"
},
  "geometry": {"coordinates":[-105.940648,35.689977],"type":"Point"}
}