{
  "type": "Feature",
  "properties": {
    "iso:country":"US",
    "sg:address":"3001 Louisiana Blvd NE",
    "sg:city":"Albuquerque",
    "sg:classifiers":[
        {
            "category":"Insurance",
            "subcategory":"Insurance Agent",
            "type":"Services"
        }
    ],
    "sg:phone":"+1 505 823 2130",
    "sg:postcode":"87110",
    "sg:province":"NM",
    "sg:tags":[
        "business"
    ],
    "wof:name":"Retirement Consultants LTD",
    "wof:placetype":"venue"
},
  "geometry": {"coordinates":[-106.56887,35.117312],"type":"Point"}
}