{
  "type": "Feature",
  "properties": {
    "iso:country":"US",
    "sg:address":"5312 Granite Ave NE",
    "sg:city":"Albuquerque",
    "sg:classifiers":[
        {
            "category":"Building & Trades",
            "subcategory":"Construction",
            "type":"Services"
        }
    ],
    "sg:phone":"+1 505 254 3814",
    "sg:postcode":"87110",
    "sg:province":"NM",
    "sg:tags":[
        "house"
    ],
    "wof:name":"Super Square Constructon",
    "wof:placetype":"venue"
},
  "geometry": {"coordinates":[-106.584952,35.090046],"type":"Point"}
}