{
  "type": "Feature",
  "properties": {
    "iso:country":"US",
    "sg:address":"3909 Juan Tabo Blvd NE",
    "sg:city":"Albuquerque",
    "sg:classifiers":[
        {
            "category":"Organizations",
            "subcategory":"Community Association",
            "type":"Services"
        }
    ],
    "sg:phone":"+1 505 883 8020",
    "sg:postcode":"87111",
    "sg:province":"NM",
    "wof:name":"New Mxco Coalition Sxl Asslt",
    "wof:placetype":"venue"
},
  "geometry": {"coordinates":[-106.515705,35.125491],"type":"Point"}
}