{
  "type": "Feature",
  "properties": {
    "iso:country":"US",
    "sg:address":"11412 Desert Classic Ln NE",
    "sg:city":"Albuquerque",
    "sg:classifiers":[
        {
            "category":"Shopping",
            "type":"Retail Goods"
        }
    ],
    "sg:phone":"+1 505 235 6115",
    "sg:postcode":"87111",
    "sg:province":"NM",
    "sg:tags":[
        "miscellaneous",
        "store"
    ],
    "wof:name":"Global Gems Supplier Inc",
    "wof:placetype":"venue"
},
  "geometry": {"coordinates":[-106.512979,35.154424],"type":"Point"}
}