{
  "type": "Feature",
  "properties": {
    "addr:full":"3600 E Tucumcari Blvd Tucumcari NM 88401",
    "addr:housenumber":"3600",
    "addr:postcode":"88401",
    "addr:street":"E Tucumcari Blvd",
    "iso:country":"US",
    "sg:address":"3600 E Tucumcari Blvd",
    "sg:city":"Tucumcari",
    "sg:classifiers":[
        {
            "category":"Autos & Motor Vehicles",
            "subcategory":"Fuel & Gas Station",
            "type":"Retail Goods"
        }
    ],
    "sg:phone":"+1 505 461 1184",
    "sg:postcode":"88401",
    "sg:province":"NM",
    "sg:tags":[
        "oil"
    ],
    "wof:name":"Holiday Gas & Tire",
    "wof:placetype":"venue"
},
  "geometry": {"coordinates":[-103.679951,35.171784],"type":"Point"}
}