{
  "type": "Feature",
  "properties": {
    "iso:country":"US",
    "sg:address":"3900 Pso del Sol",
    "sg:city":"Santa Fe",
    "sg:classifiers":[
        {
            "category":"Professional",
            "subcategory":"Management & Consulting",
            "type":"Services"
        }
    ],
    "sg:phone":"+1 505 474 6556",
    "sg:postcode":"87507",
    "sg:province":"NM",
    "sg:tags":[
        "development",
        "economic",
        "agency"
    ],
    "wof:name":"Wesstcorp",
    "wof:placetype":"venue"
},
  "geometry": {"coordinates":[-106.043719,35.634071],"type":"Point"}
}