{
  "type": "Feature",
  "properties": {
    "addr:full":"600 W Ave A Lovington NM 88260",
    "addr:housenumber":"600",
    "addr:postcode":"88260",
    "addr:street":"W Ave A",
    "iso:country":"US",
    "sg:address":"600 W Ave A",
    "sg:city":"Lovington",
    "sg:classifiers":[
        {
            "category":"Mining & Drilling",
            "type":"Manufacturing & Wholesale Goods"
        }
    ],
    "sg:phone":"+1 505 396 6024",
    "sg:postcode":"88260",
    "sg:province":"NM",
    "sg:tags":[
        "field",
        "oil"
    ],
    "wof:name":"Terra Southwest Inc",
    "wof:placetype":"venue"
},
  "geometry": {"coordinates":[-103.3562,32.947043],"type":"Point"}
}