{
  "type": "Feature",
  "properties": {
    "addr:full":"4348 S Roosevelt Rd W Milnesand NM 88125",
    "addr:housenumber":"4348",
    "addr:postcode":"88125",
    "addr:street":"S Roosevelt Rd W Milnesand",
    "iso:country":"US",
    "sg:address":"4348 S Roosevelt Rd W",
    "sg:city":"Milnesand",
    "sg:classifiers":[
        {
            "category":"Mining & Drilling",
            "type":"Manufacturing & Wholesale Goods"
        }
    ],
    "sg:phone":"+1 505 675 2311",
    "sg:postcode":"88125",
    "sg:province":"NM",
    "sg:tags":[
        "oil",
        "gas",
        "producer"
    ],
    "wof:name":"Targa Resources",
    "wof:placetype":"venue"
},
  "geometry": {"coordinates":[-103.426298,33.619255],"type":"Point"}
}