{
  "type": "Feature",
  "properties": {
    "addr:full":"406 W College Blvd Roswell NM 88201",
    "addr:housenumber":"406",
    "addr:postcode":"88201",
    "addr:street":"W College Blvd",
    "iso:country":"US",
    "sg:address":"406 W College Blvd",
    "sg:city":"Roswell",
    "sg:classifiers":[
        {
            "category":"Personal",
            "subcategory":"Beauty Salon",
            "type":"Services"
        }
    ],
    "sg:phone":"+1 505 623 9365",
    "sg:postcode":"88201",
    "sg:province":"NM",
    "wof:name":"Get Gorgeous Hair Salon",
    "wof:placetype":"venue"
},
  "geometry": {"coordinates":[-104.52887699999999,33.408642],"type":"Point"}
}