{
  "type": "Feature",
  "properties": {
    "iso:country":"US",
    "sg:address":"3211 Coors Blvd SW",
    "sg:city":"Albuquerque",
    "sg:classifiers":[
        {
            "category":"Professional",
            "subcategory":"Business Services",
            "type":"Services"
        }
    ],
    "sg:phone":"+1 505 452 8311",
    "sg:postcode":"87121",
    "sg:province":"NM",
    "sg:tags":[
        "license"
    ],
    "sg:website":"www.clsi.com",
    "wof:name":"Contractor's Licensing Svc Inc",
    "wof:placetype":"venue"
},
  "geometry": {"coordinates":[-106.713902,35.028499],"type":"Point"}
}