{
  "type": "Feature",
  "properties": {
    "iso:country":"US",
    "sg:address":"700 Dalies Ave",
    "sg:city":"Belen",
    "sg:classifiers":[
        {
            "category":"Restaurant",
            "type":"Food & Drink"
        }
    ],
    "sg:phone":"+1 505 864 2211",
    "sg:postcode":"87002",
    "sg:province":"NM",
    "wof:name":"Harla Mays Fat Boy Grill",
    "wof:placetype":"venue"
},
  "geometry": {"coordinates":[-106.775403,34.661001],"type":"Point"}
}