{
  "type": "Feature",
  "properties": {
    "iso:country":"US",
    "sg:address":"1400 Corriz Dr SW",
    "sg:city":"Albuquerque",
    "sg:classifiers":[
        {
            "category":"Education",
            "subcategory":"School",
            "type":"Public Place"
        }
    ],
    "sg:phone":"+1 505 836 0623",
    "sg:postcode":"87121",
    "sg:province":"NM",
    "wof:name":"Maryann Bnford Elementary Schl",
    "wof:placetype":"venue"
},
  "geometry": {"coordinates":[-106.726923,35.051931],"type":"Point"}
}