{
  "type": "Feature",
  "properties": {
    "iso:country":"US",
    "sg:address":"7539 Sanchez Rd SW",
    "sg:city":"Albuquerque",
    "sg:classifiers":[
        {
            "category":"Freight",
            "type":"Transportation"
        }
    ],
    "sg:phone":"+1 505 877 4777",
    "sg:postcode":"87105",
    "sg:province":"NM",
    "sg:tags":[
        "operator",
        "trucking"
    ],
    "wof:name":"Otero Trucking Inc",
    "wof:placetype":"venue"
},
  "geometry": {"coordinates":[-106.692587,34.953496],"type":"Point"}
}