{
  "type": "Feature",
  "properties": {
    "iso:country":"US",
    "sg:address":"4709 Lumber Ave NE",
    "sg:city":"Albuquerque",
    "sg:classifiers":[
        {
            "category":"Shopping",
            "subcategory":"Florist",
            "type":"Retail Goods"
        }
    ],
    "sg:phone":"+1 505 872 1221",
    "sg:postcode":"87109",
    "sg:province":"NM",
    "wof:name":"Emerald Florist",
    "wof:placetype":"venue"
},
  "geometry": {"coordinates":[-106.586649,35.135871],"type":"Point"}
}