{
  "type": "Feature",
  "properties": {
    "iso:country":"US",
    "sg:address":"2208 N Prince St",
    "sg:city":"Clovis",
    "sg:classifiers":[
        {
            "category":"Building & Trades",
            "subcategory":"Construction",
            "type":"Services"
        }
    ],
    "sg:phone":"+1 505 762 4088",
    "sg:postcode":"88101",
    "sg:province":"NM",
    "sg:tags":[
        "general",
        "contractor"
    ],
    "wof:name":"Kelley Construction Co",
    "wof:placetype":"venue"
},
  "geometry": {"coordinates":[-103.196618,34.420494],"type":"Point"}
}