{
  "type": "Feature",
  "properties": {
    "iso:country":"US",
    "sg:address":"1313 E 32nd St",
    "sg:city":"Silver City",
    "sg:classifiers":[
        {
            "category":"Health Services",
            "subcategory":"Doctor",
            "type":"Services"
        }
    ],
    "sg:phone":"+1 505 388 8024",
    "sg:postcode":"88061",
    "sg:province":"NM",
    "sg:tags":[
        "physician",
        "surgeon"
    ],
    "wof:name":"Southwest Radiology Assoc",
    "wof:placetype":"venue"
},
  "geometry": {"coordinates":[-108.262834,32.795635],"type":"Point"}
}