{
  "type": "Feature",
  "properties": {
    "iso:country":"US",
    "sg:address":"737 S Campo St",
    "sg:city":"Las Cruces",
    "sg:classifiers":[
        {
            "category":"Professional",
            "subcategory":"Accounting & Tax Preparation",
            "type":"Services"
        }
    ],
    "sg:phone":"+1 505 647 4843",
    "sg:postcode":"88001",
    "sg:province":"NM",
    "sg:tags":[
        "accountant"
    ],
    "wof:name":"Casa Moai",
    "wof:placetype":"venue"
},
  "geometry": {"coordinates":[-106.774811,32.304482],"type":"Point"}
}