{
  "type": "Feature",
  "properties": {
    "iso:country":"US",
    "sg:address":"7241 Old Santa Fe Trl",
    "sg:city":"Santa Fe",
    "sg:classifiers":[
        {
            "category":"Organizations",
            "subcategory":"Religious Organization",
            "type":"Services"
        }
    ],
    "sg:phone":"+1 505 988 4396",
    "sg:postcode":"87505",
    "sg:province":"NM",
    "sg:tags":[
        "church"
    ],
    "wof:name":"Mountain Cloud Zen Ctr",
    "wof:placetype":"venue"
},
  "geometry": {"coordinates":[-105.917027,35.628537],"type":"Point"}
}