{
  "type": "Feature",
  "properties": {
    "addr:full":"707 Broadway Blvd NE Albuquerque NM 87102",
    "addr:housenumber":"707",
    "addr:postcode":"87102",
    "addr:street":"Broadway Blvd Ne",
    "iso:country":"US",
    "sg:address":"707 Broadway Blvd NE",
    "sg:city":"Albuquerque",
    "sg:classifiers":[
        {
            "category":"Social Services",
            "type":"Services"
        }
    ],
    "sg:phone":"+1 505 841 8510",
    "sg:postcode":"87102",
    "sg:province":"NM",
    "sg:tags":[
        "family"
    ],
    "wof:name":"Bernalillo APS Adult Bureau",
    "wof:placetype":"venue"
},
  "geometry": {"coordinates":[-106.643255,35.091022],"type":"Point"}
}