{
  "type": "Feature",
  "properties": {
    "iso:country":"US",
    "sg:address":"11409 Cote Ave NE",
    "sg:city":"Albuquerque",
    "sg:classifiers":[
        {
            "category":"Professional",
            "subcategory":"Secretarial Services",
            "type":"Services"
        }
    ],
    "sg:phone":"+1 505 299 7089",
    "sg:postcode":"87123",
    "sg:province":"NM",
    "sg:tags":[
        "reporting"
    ],
    "wof:name":"Accustat Transcription",
    "wof:placetype":"venue"
},
  "geometry": {"coordinates":[-106.522757,35.084823],"type":"Point"}
}