{
  "type": "Feature",
  "properties": {
    "addr:full":"510 S 2nd St Gallup NM 87301",
    "addr:housenumber":"510",
    "addr:postcode":"87301",
    "addr:street":"S 2Nd St",
    "iso:country":"US",
    "sg:address":"510 S 2nd St",
    "sg:city":"Gallup",
    "sg:classifiers":[
        {
            "category":"Arts & Performance",
            "subcategory":"Theater",
            "type":"Entertainment"
        }
    ],
    "sg:phone":"+1 505 870 4334",
    "sg:postcode":"87301",
    "sg:province":"NM",
    "sg:tags":[
        "live",
        "music"
    ],
    "wof:name":"New Wave Mobile Sound",
    "wof:placetype":"venue"
},
  "geometry": {"coordinates":[-108.741039,35.52402],"type":"Point"}
}