{
  "type": "Feature",
  "properties": {
    "iso:country":"US",
    "sg:address":"2003 W 7th St",
    "sg:city":"Clovis",
    "sg:classifiers":[
        {
            "category":"Organizations",
            "subcategory":"Community Association",
            "type":"Services"
        }
    ],
    "sg:phone":"+1 505 762 9355",
    "sg:postcode":"88101",
    "sg:province":"NM",
    "sg:tags":[
        "fraternal"
    ],
    "wof:name":"Amvets Post 14",
    "wof:placetype":"venue"
},
  "geometry": {"coordinates":[-103.22958300000001,34.404607],"type":"Point"}
}