{
  "type": "Feature",
  "properties": {
    "iso:country":"US",
    "sg:address":"2102 E Historic Highway 66",
    "sg:city":"Gallup",
    "sg:classifiers":[
        {
            "category":"Restaurant",
            "type":"Food & Drink"
        }
    ],
    "sg:menulink":"http://www.allmenus.com/nm/gallup/81085-papa-johns-pizza/menu/",
    "sg:phone":"+1 505 722 2323",
    "sg:postcode":"87301",
    "sg:province":"NM",
    "sg:tags":[
        "american",
        "pizza"
    ],
    "wof:name":"Papa John's Pizza",
    "wof:placetype":"venue"
},
  "geometry": {"coordinates":[-108.711461,35.529416],"type":"Point"}
}