{
  "type": "Feature",
  "properties": {
    "iso:country":"US",
    "sg:address":"70 State Hwy 346",
    "sg:city":"Belen",
    "sg:classifiers":[
        {
            "category":"Retail",
            "subcategory":"Veterinary Services",
            "type":"Services"
        }
    ],
    "sg:phone":"+1 505 861 5321",
    "sg:postcode":"87006",
    "sg:province":"NM",
    "sg:tags":[
        "veterinarian"
    ],
    "wof:name":"Southwest Reproductive Svc",
    "wof:placetype":"venue"
},
  "geometry": {"coordinates":[-106.76884200000001,34.545407],"type":"Point"}
}