{
  "type": "Feature",
  "properties": {
    "iso:country":"US",
    "sg:address":"2000 Randolph Rd SE",
    "sg:city":"Albuquerque",
    "sg:classifiers":[
        {
            "category":"Professional",
            "subcategory":"Business Services",
            "type":"Services"
        }
    ],
    "sg:phone":"+1 505 265 4767",
    "sg:postcode":"87106",
    "sg:province":"NM",
    "sg:website":"www.unitech1.com",
    "wof:name":"Universal Systems & Technology",
    "wof:placetype":"venue"
},
  "geometry": {"coordinates":[-106.62208200000001,35.053708],"type":"Point"}
}