{
  "type": "Feature",
  "properties": {
    "iso:country":"US",
    "sg:address":"836 E Palace Ave",
    "sg:city":"Santa Fe",
    "sg:classifiers":[
        {
            "category":"Shopping",
            "subcategory":"Clothing, Apparel, & Fashions",
            "type":"Retail Goods"
        }
    ],
    "sg:phone":"+1 505 992 0122",
    "sg:postcode":"87501",
    "sg:province":"NM",
    "wof:name":"Coyote Moon",
    "wof:placetype":"venue"
},
  "geometry": {"coordinates":[-105.924881,35.683476],"type":"Point"}
}