{
  "type": "Feature",
  "properties": {
    "iso:country":"US",
    "sg:address":"1111 E 1st St",
    "sg:city":"Clovis",
    "sg:classifiers":[
        {
            "category":"Restaurant",
            "type":"Food & Drink"
        },
        {
            "category":"Ice Cream",
            "type":"Food & Drink"
        }
    ],
    "sg:menulink":"http://www.allmenus.com/nm/clovis/167850-dairy-queen/menu/",
    "sg:phone":"+1 505 763 1497",
    "sg:postcode":"88101",
    "sg:province":"NM",
    "sg:tags":[
        "burger",
        "american",
        "ice",
        "cream"
    ],
    "wof:name":"Dairy Queen",
    "wof:placetype":"venue"
},
  "geometry": {"coordinates":[-103.192555,34.398585],"type":"Point"}
}