{
  "type": "Feature",
  "properties": {
    "iso:country":"US",
    "sg:address":"8410 Washington St NE",
    "sg:city":"Albuquerque",
    "sg:classifiers":[
        {
            "category":"Wholesale",
            "subcategory":"Electrical",
            "type":"Manufacturing & Wholesale Goods"
        }
    ],
    "sg:phone":"+1 505 898 6968",
    "sg:postcode":"87113",
    "sg:province":"NM",
    "sg:tags":[
        "fire",
        "alarm",
        "system"
    ],
    "wof:name":"Great Western Specialty Systs",
    "wof:placetype":"venue"
},
  "geometry": {"coordinates":[-106.595214,35.179331],"type":"Point"}
}