{
  "type": "Feature",
  "properties": {
    "addr:full":"1326 Rufina Cir Santa Fe NM 87507",
    "addr:housenumber":"1326",
    "addr:postcode":"87507",
    "addr:street":"Rufina Cir",
    "iso:country":"US",
    "sg:address":"1326 Rufina Cir",
    "sg:city":"Santa Fe",
    "sg:classifiers":[
        {
            "category":"Manufacturing",
            "subcategory":"Chemicals & Compounds",
            "type":"Manufacturing & Wholesale Goods"
        }
    ],
    "sg:phone":"+1 505 438 0402",
    "sg:postcode":"87507",
    "sg:province":"NM",
    "sg:tags":[
        "aromatherapy",
        "oil",
        "essential",
        "mfg"
    ],
    "sg:website":"www.aromaland.com",
    "wof:name":"Aromaland Inc",
    "wof:placetype":"venue"
},
  "geometry": {"coordinates":[-105.995496,35.656639],"type":"Point"}
}