{
  "type": "Feature",
  "properties": {
    "iso:country":"US",
    "sg:address":"10308 Snow Heights Blvd NE",
    "sg:city":"Albuquerque",
    "sg:classifiers":[
        {
            "category":"Autos & Motor Vehicles",
            "subcategory":"Auto Supplies",
            "type":"Retail Goods"
        }
    ],
    "sg:phone":"+1 505 296 1322",
    "sg:postcode":"87112",
    "sg:province":"NM",
    "wof:name":"Ronald J Pratt",
    "wof:placetype":"venue"
},
  "geometry": {"coordinates":[-106.52797,35.104706],"type":"Point"}
}