{
  "type": "Feature",
  "properties": {
    "addr:full":"3500 Vis Alameda NE Albuquerque NM 87113",
    "addr:postcode":"3500;87113",
    "addr:street":"Alameda Ne",
    "iso:country":"US",
    "sg:address":"3500 Vis Alameda NE",
    "sg:city":"Albuquerque",
    "sg:classifiers":[
        {
            "category":"Building & Trades",
            "subcategory":"Construction",
            "type":"Services"
        }
    ],
    "sg:phone":"+1 505 792 1283",
    "sg:postcode":"87113",
    "sg:province":"NM",
    "sg:tags":[
        "dry wall",
        "contractor"
    ],
    "wof:name":"Rob Boyles Co",
    "wof:placetype":"venue"
},
  "geometry": {"coordinates":[-106.608166,35.179362],"type":"Point"}
}