{
  "type": "Feature",
  "properties": {
    "iso:country":"US",
    "sg:address":"704 Martinez St",
    "sg:city":"Logan",
    "sg:classifiers":[
        {
            "category":"Building & Trades",
            "subcategory":"Construction",
            "type":"Services"
        }
    ],
    "sg:phone":"+1 505 487 2560",
    "sg:postcode":"88426",
    "sg:province":"NM",
    "sg:tags":[
        "general",
        "contractor"
    ],
    "wof:name":"Usrey Enterprises",
    "wof:placetype":"venue"
},
  "geometry": {"coordinates":[-103.414433,35.365679],"type":"Point"}
}