{
  "type": "Feature",
  "properties": {
    "iso:country":"US",
    "sg:address":"8115 Oakdale Pl NW",
    "sg:city":"Albuquerque",
    "sg:classifiers":[
        {
            "category":"Building & Trades",
            "subcategory":"Electrical",
            "type":"Services"
        }
    ],
    "sg:phone":"+1 505 836 1132",
    "sg:postcode":"87120",
    "sg:province":"NM",
    "sg:tags":[
        "electrical",
        "contractor"
    ],
    "wof:name":"Elks Electric",
    "wof:placetype":"venue"
},
  "geometry": {"coordinates":[-106.734182,35.100597],"type":"Point"}
}