{
  "type": "Feature",
  "properties": {
    "iso:country":"US",
    "sg:address":"908 S Main St",
    "sg:city":"Belen",
    "sg:classifiers":[
        {
            "category":"Restaurant",
            "type":"Food & Drink"
        }
    ],
    "sg:phone":"+1 505 864 0425",
    "sg:postcode":"87002",
    "sg:province":"NM",
    "wof:name":"Frances Cafe",
    "wof:placetype":"venue"
},
  "geometry": {"coordinates":[-106.779518,34.651475],"type":"Point"}
}