{
  "type": "Feature",
  "properties": {
    "addr:full":"9019 Claremont Ave NE Albuquerque NM 87112",
    "addr:housenumber":"9019",
    "addr:postcode":"87112",
    "addr:street":"Claremont Ave Ne",
    "iso:country":"US",
    "sg:address":"9019 Claremont Ave NE",
    "sg:city":"Albuquerque",
    "sg:classifiers":[
        {
            "category":"Retail",
            "subcategory":"Photofinishing",
            "type":"Services"
        },
        {
            "category":"Retail",
            "subcategory":"Portrait Studio",
            "type":"Services"
        },
        {
            "category":"Professional",
            "subcategory":"Art Services",
            "type":"Services"
        }
    ],
    "sg:phone":"+1 505 298 4730",
    "sg:postcode":"87112",
    "sg:province":"NM",
    "sg:tags":[
        "rental",
        "photographers-portrait",
        "darkroom",
        "photo",
        "retouching",
        "restoration",
        "photographic"
    ],
    "wof:name":"Stephen S Photo Svc",
    "wof:placetype":"venue"
},
  "geometry": {"coordinates":[-106.544735,35.113076],"type":"Point"}
}