{
  "type": "Feature",
  "properties": {
    "iso:country":"US",
    "sg:address":"212 E Main St",
    "sg:city":"Tucumcari",
    "sg:classifiers":[
        {
            "category":"Shopping",
            "subcategory":"Stationery & Office Supplies",
            "type":"Retail Goods"
        }
    ],
    "sg:phone":"+1 505 461 2342",
    "sg:postcode":"88401",
    "sg:province":"NM",
    "wof:name":"Desertrose Crafts",
    "wof:placetype":"venue"
},
  "geometry": {"coordinates":[-103.72470800000001,35.178966],"type":"Point"}
}