{
  "type": "Feature",
  "properties": {
    "iso:country":"US",
    "sg:address":"6821 San Mateo Blvd NE",
    "sg:city":"Albuquerque",
    "sg:classifiers":[
        {
            "category":"Autos & Motor Vehicles",
            "subcategory":"Fuel & Gas Station",
            "type":"Retail Goods"
        }
    ],
    "sg:phone":"+1 505 883 6522",
    "sg:postcode":"87109",
    "sg:province":"NM",
    "sg:tags":[
        "convenience",
        "station",
        "gasoline",
        "store"
    ],
    "wof:name":"Texaco",
    "wof:placetype":"venue"
},
  "geometry": {"coordinates":[-106.586499,35.148094],"type":"Point"}
}