{
  "type": "Feature",
  "properties": {
    "iso:country":"US",
    "sg:address":"2703 Broadbent Pkwy NE",
    "sg:city":"Albuquerque",
    "sg:classifiers":[
        {
            "category":"Wholesale",
            "subcategory":"Electrical",
            "type":"Manufacturing & Wholesale Goods"
        }
    ],
    "sg:phone":"+1 505 830 0287",
    "sg:postcode":"87107",
    "sg:province":"NM",
    "sg:tags":[
        "control"
    ],
    "wof:name":"Phoenix Instrumentation",
    "wof:placetype":"venue"
},
  "geometry": {"coordinates":[-106.630173,35.11098],"type":"Point"}
}