{
  "type": "Feature",
  "properties": {
    "addr:full":"282 N Cam del Pueblo Bernalillo NM 87004",
    "addr:housenumber":"282",
    "addr:postcode":"87004",
    "addr:street":"N Cam Del Pueblo",
    "iso:country":"US",
    "sg:address":"282 N Cam del Pueblo",
    "sg:city":"Bernalillo",
    "sg:classifiers":[
        {
            "category":"Shopping",
            "type":"Retail Goods"
        }
    ],
    "sg:phone":"+1 505 771 8097",
    "sg:postcode":"87004",
    "sg:province":"NM",
    "sg:tags":[
        "art",
        "gallery",
        "dealer"
    ],
    "wof:name":"Arte Loca Gallery",
    "wof:placetype":"venue"
},
  "geometry": {"coordinates":[-106.54239200000001,35.322763],"type":"Point"}
}