{
  "type": "Feature",
  "properties": {
    "iso:country":"US",
    "sg:address":"36 Rd 4997",
    "sg:city":"Bloomfield",
    "sg:classifiers":[
        {
            "category":"Retail",
            "subcategory":"Auto Repair",
            "type":"Services"
        }
    ],
    "sg:phone":"+1 505 632 0950",
    "sg:postcode":"87413",
    "sg:province":"NM",
    "sg:tags":[
        "automotive",
        "mechanical"
    ],
    "wof:name":"Flash Repair Service",
    "wof:placetype":"venue"
},
  "geometry": {"coordinates":[-107.91522399999999,36.699068],"type":"Point"}
}