{
  "type": "Feature",
  "properties": {
    "iso:country":"US",
    "sg:address":"429 Hondo Seco Rd",
    "sg:city":"El Prado",
    "sg:classifiers":[
        {
            "category":"Professional",
            "type":"Services"
        }
    ],
    "sg:phone":"+1 505 776 2543",
    "sg:postcode":"87529",
    "sg:province":"NM",
    "wof:name":"Johnson Bortner Thomas & Lorri",
    "wof:placetype":"venue"
},
  "geometry": {"coordinates":[-105.602205,36.523782],"type":"Point"}
}