{
  "type": "Feature",
  "properties": {
    "iso:country":"US",
    "sg:address":"5112 Lomas Blvd NE",
    "sg:city":"Albuquerque",
    "sg:classifiers":[
        {
            "category":"Shopping",
            "subcategory":"Pharmacy",
            "type":"Retail Goods"
        }
    ],
    "sg:phone":"+1 505 265 6905",
    "sg:postcode":"87110",
    "sg:province":"NM",
    "wof:name":"Sav-On Drugs",
    "wof:placetype":"venue"
},
  "geometry": {"coordinates":[-106.58758899999999,35.087327],"type":"Point"}
}