{
  "type": "Feature",
  "properties": {
    "addr:full":"2029 Lakeview Rd SW Albuquerque NM 87105",
    "addr:housenumber":"2029",
    "addr:postcode":"87105",
    "addr:street":"Lakeview Rd Sw",
    "iso:country":"US",
    "sg:address":"2029 Lakeview Rd SW",
    "sg:city":"Albuquerque",
    "sg:classifiers":[
        {
            "category":"Building & Trades",
            "subcategory":"Construction",
            "type":"Services"
        }
    ],
    "sg:phone":"+1 505 873 1997",
    "sg:postcode":"87105",
    "sg:province":"NM",
    "sg:tags":[
        "excavation",
        "contractor"
    ],
    "wof:name":"D S Septic and Excavation",
    "wof:placetype":"venue"
},
  "geometry": {"coordinates":[-106.68899999999999,35.014496],"type":"Point"}
}