{
  "type": "Feature",
  "properties": {
    "iso:country":"US",
    "sg:address":"120 N Canal St",
    "sg:city":"Carlsbad",
    "sg:classifiers":[
        {
            "category":"Professional",
            "subcategory":"Engineering",
            "type":"Services"
        }
    ],
    "sg:phone":"+1 505 234 0028",
    "sg:postcode":"88220",
    "sg:province":"NM",
    "wof:name":"RE/Spec Inc",
    "wof:placetype":"venue"
},
  "geometry": {"coordinates":[-104.228895,32.421269],"type":"Point"}
}