{
  "type": "Feature",
  "properties": {
    "iso:country":"US",
    "sg:address":"8000 Louisiana Blvd NE",
    "sg:city":"Albuquerque",
    "sg:classifiers":[
        {
            "category":"Government",
            "subcategory":"Office",
            "type":"Public Place"
        }
    ],
    "sg:phone":"+1 505 856 4300",
    "sg:postcode":"87109",
    "sg:province":"NM",
    "sg:tags":[
        "federal"
    ],
    "wof:name":"Us Faa",
    "wof:placetype":"venue"
},
  "geometry": {"coordinates":[-106.568766,35.170601],"type":"Point"}
}