{
  "type": "Feature",
  "properties": {
    "iso:country":"US",
    "sg:address":"802 US Hwy 491",
    "sg:city":"Gallup",
    "sg:classifiers":[
        {
            "category":"Retail",
            "subcategory":"Laundry & Dry Cleaning",
            "type":"Services"
        }
    ],
    "sg:phone":"+1 505 863 2791",
    "sg:postcode":"87301",
    "sg:province":"NM",
    "wof:name":"G & G Laundry",
    "wof:placetype":"venue"
},
  "geometry": {"coordinates":[-108.758689,35.536932],"type":"Point"}
}