{
  "type": "Feature",
  "properties": {
    "iso:country":"US",
    "sg:address":"120 Louisiana Blvd NE",
    "sg:city":"Albuquerque",
    "sg:classifiers":[
        {
            "category":"Retail",
            "subcategory":"Car Wash",
            "type":"Services"
        }
    ],
    "sg:phone":"+1 505 265 1785",
    "sg:postcode":"87108",
    "sg:province":"NM",
    "sg:tags":[
        "polishing",
        "washing"
    ],
    "wof:name":"Circus Car Wash",
    "wof:placetype":"venue"
},
  "geometry": {"coordinates":[-106.568522,35.077691],"type":"Point"}
}