{
  "type": "Feature",
  "properties": {
    "addr:full":"901 Rio Grande Blvd NW Albuquerque NM 87104",
    "addr:housenumber":"901",
    "addr:postcode":"87104",
    "addr:street":"Rio Grande Blvd Nw",
    "iso:country":"US",
    "sg:address":"901 Rio Grande Blvd NW",
    "sg:city":"Albuquerque",
    "sg:classifiers":[
        {
            "category":"Insurance",
            "subcategory":"Insurance Agent",
            "type":"Services"
        }
    ],
    "sg:phone":"+1 505 242 5860",
    "sg:postcode":"87104",
    "sg:province":"NM",
    "wof:name":"Desert States Insurance",
    "wof:placetype":"venue"
},
  "geometry": {"coordinates":[-106.670748,35.103508],"type":"Point"}
}