{
  "type": "Feature",
  "properties": {
    "iso:country":"US",
    "sg:address":"805 Gavilan Canyon Rd",
    "sg:city":"Ruidoso",
    "sg:classifiers":[
        {
            "category":"Building & Trades",
            "subcategory":"Electrical",
            "type":"Services"
        }
    ],
    "sg:phone":"+1 505 258 5782",
    "sg:postcode":"88345",
    "sg:province":"NM",
    "sg:tags":[
        "electric",
        "contractor"
    ],
    "wof:name":"WRC Electric Co",
    "wof:placetype":"venue"
},
  "geometry": {"coordinates":[-105.64393200000001,33.351459],"type":"Point"}
}