{
  "type": "Feature",
  "properties": {
    "addr:full":"3500 Will Rogers Dr Santa Rosa NM 88435",
    "addr:housenumber":"3500",
    "addr:postcode":"88435",
    "addr:street":"Will Rogers Dr",
    "iso:country":"US",
    "sg:address":"3500 Will Rogers Dr",
    "sg:city":"Santa Rosa",
    "sg:classifiers":[
        {
            "category":"Restaurant",
            "type":"Food & Drink"
        }
    ],
    "sg:phone":"+1 505 472 5426",
    "sg:postcode":"88435",
    "sg:province":"NM",
    "sg:tags":[
        "parlor",
        "ice",
        "cream"
    ],
    "wof:name":"Dairy Queen",
    "wof:placetype":"venue"
},
  "geometry": {"coordinates":[-104.65212,34.9473],"type":"Point"}
}