{
  "type": "Feature",
  "properties": {
    "addr:full":"3800 Hawkins St NE Albuquerque NM 87109",
    "addr:housenumber":"3800",
    "addr:postcode":"87109",
    "addr:street":"Hawkins St Ne",
    "iso:country":"US",
    "sg:address":"3800 Hawkins St NE",
    "sg:city":"Albuquerque",
    "sg:classifiers":[
        {
            "category":"Manufacturing",
            "subcategory":"Signs",
            "type":"Manufacturing & Wholesale Goods"
        }
    ],
    "sg:phone":"+1 505 341 9210",
    "sg:postcode":"87109",
    "sg:province":"NM",
    "sg:tags":[
        "advertising",
        "specialty"
    ],
    "wof:name":"Clovis Sign Svc Inc",
    "wof:placetype":"venue"
},
  "geometry": {"coordinates":[-106.602115,35.162667],"type":"Point"}
}