{
  "type": "Feature",
  "properties": {
    "iso:country":"US",
    "sg:address":"115 E Plz",
    "sg:city":"Taos",
    "sg:classifiers":[
        {
            "category":"Shopping",
            "subcategory":"Clothing, Apparel, & Fashions",
            "type":"Retail Goods"
        }
    ],
    "sg:phone":"+1 505 758 8565",
    "sg:postcode":"87571",
    "sg:province":"NM",
    "sg:tags":[
        "t"
    ],
    "wof:name":"I Love Taos Co",
    "wof:placetype":"venue"
},
  "geometry": {"coordinates":[-105.574144,36.40713],"type":"Point"}
}