{
  "type": "Feature",
  "properties": {
    "iso:country":"US",
    "sg:address":"1009 W Lea St",
    "sg:city":"Carlsbad",
    "sg:classifiers":[
        {
            "category":"Personal",
            "subcategory":"Beauty Salon",
            "type":"Services"
        }
    ],
    "sg:phone":"+1 505 887 6798",
    "sg:postcode":"88220",
    "sg:province":"NM",
    "wof:name":"Mickee's Shop & Salon",
    "wof:placetype":"venue"
},
  "geometry": {"coordinates":[-104.238831,32.414429],"type":"Point"}
}