{
  "type": "Feature",
  "properties": {
    "iso:country":"US",
    "sg:address":"145 N Solano Dr",
    "sg:city":"Las Cruces",
    "sg:classifiers":[
        {
            "category":"Wholesale",
            "subcategory":"Hardware",
            "type":"Manufacturing & Wholesale Goods"
        },
        {
            "category":"Building & Trades",
            "subcategory":"Plumbing",
            "type":"Services"
        }
    ],
    "sg:phone":"+1 505 525 3805",
    "sg:postcode":"88001",
    "sg:province":"NM",
    "sg:tags":[
        "conditioning",
        "air",
        "system",
        "refrigerating",
        "contractor"
    ],
    "wof:name":"Complete Temperature Control",
    "wof:placetype":"venue"
},
  "geometry": {"coordinates":[-106.76518799999999,32.313286],"type":"Point"}
}