{
  "type": "Feature",
  "properties": {
    "iso:country":"US",
    "sg:address":"95 W Marcy St",
    "sg:city":"Santa Fe",
    "sg:classifiers":[
        {
            "category":"Restaurant",
            "type":"Food & Drink"
        }
    ],
    "sg:menulink":"http://www.allmenus.com/nm/santa-fe/3911-il-piatto/menu/",
    "sg:phone":"+1 505 984 1091",
    "sg:postcode":"87501",
    "sg:province":"NM",
    "sg:tags":[
        "italian"
    ],
    "wof:name":"Il Piatto",
    "wof:placetype":"venue"
},
  "geometry": {"coordinates":[-105.93809,35.689403],"type":"Point"}
}