{
  "type": "Feature",
  "properties": {
    "addr:full":"5555 Zuni Rd SE Albuquerque NM 87108",
    "addr:housenumber":"5555",
    "addr:postcode":"87108",
    "addr:street":"Zuni Rd Se",
    "iso:country":"US",
    "sg:address":"5555 Zuni Rd SE",
    "sg:city":"Albuquerque",
    "sg:classifiers":[
        {
            "category":"Restaurant",
            "type":"Food & Drink"
        }
    ],
    "sg:phone":"+1 505 266 8899",
    "sg:postcode":"87108",
    "sg:province":"NM",
    "sg:tags":[
        "eating"
    ],
    "wof:name":"Main Chinese Buffet",
    "wof:placetype":"venue"
},
  "geometry": {"coordinates":[-106.583827,35.072909],"type":"Point"}
}