{
  "type": "Feature",
  "properties": {
    "addr:full":"2847 Plz Amarilla Santa Fe NM 87507",
    "addr:postcode":"2847;87507",
    "addr:street":"Plz Amarilla",
    "iso:country":"US",
    "sg:address":"2847 Plz Amarilla",
    "sg:city":"Santa Fe",
    "sg:classifiers":[
        {
            "category":"Professional",
            "subcategory":"Management & Consulting",
            "type":"Services"
        }
    ],
    "sg:phone":"+1 505 424 8733",
    "sg:postcode":"87507",
    "sg:province":"NM",
    "sg:tags":[
        "public",
        "relations"
    ],
    "wof:name":"Marie Eaves",
    "wof:placetype":"venue"
},
  "geometry": {"coordinates":[-105.983679,35.637291],"type":"Point"}
}