{
  "type": "Feature",
  "properties": {
    "addr:full":"1370 State Hwy 371 Farmington NM 87401",
    "addr:housenumber":"1370",
    "addr:postcode":"87401",
    "addr:street":"State Hwy 371",
    "iso:country":"US",
    "sg:address":"1370 State Hwy 371",
    "sg:city":"Farmington",
    "sg:classifiers":[
        {
            "category":"Building & Trades",
            "subcategory":"Construction",
            "type":"Services"
        }
    ],
    "sg:phone":"+1 505 325 5720",
    "sg:postcode":"87401",
    "sg:province":"NM",
    "sg:tags":[
        "general",
        "contractor"
    ],
    "wof:name":"Eagle Nation",
    "wof:placetype":"venue"
},
  "geometry": {"coordinates":[-108.230367,36.720036],"type":"Point"}
}