{
  "type": "Feature",
  "properties": {
    "addr:full":"4201 Meadowlark Ln SE Rio Rancho NM 87124",
    "addr:housenumber":"4201",
    "addr:postcode":"87124",
    "addr:street":"Meadowlark Ln Se",
    "iso:country":"US",
    "sg:address":"4201 Meadowlark Ln SE",
    "sg:city":"Rio Rancho",
    "sg:classifiers":[
        {
            "category":"Real Estate",
            "subcategory":"Real Estate Operator",
            "type":"Services"
        }
    ],
    "sg:phone":"+1 505 892 6325",
    "sg:postcode":"87124",
    "sg:province":"NM",
    "sg:tags":[
        "building",
        "apartment"
    ],
    "wof:name":"Meadowlark Apts",
    "wof:placetype":"venue"
},
  "geometry": {"coordinates":[-106.65329800000001,35.240724],"type":"Point"}
}