{
  "type": "Feature",
  "properties": {
    "iso:country":"US",
    "sg:address":"981 Cll Carmelita",
    "sg:city":"Santa Fe",
    "sg:classifiers":[
        {
            "category":"Retail",
            "subcategory":"Portrait Studio",
            "type":"Services"
        }
    ],
    "sg:phone":"+1 505 473 4178",
    "sg:postcode":"87505",
    "sg:province":"NM",
    "sg:tags":[
        "photo"
    ],
    "wof:name":"Corrie Photography",
    "wof:placetype":"venue"
},
  "geometry": {"coordinates":[-105.984848,35.666949],"type":"Point"}
}