{
  "type": "Feature",
  "properties": {
    "addr:full":"5716 Menaul Blvd NE Albuquerque NM 87110",
    "addr:housenumber":"5716",
    "addr:postcode":"87110",
    "addr:street":"Menaul Blvd Ne",
    "iso:country":"US",
    "sg:address":"5716 Menaul Blvd NE",
    "sg:city":"Albuquerque",
    "sg:classifiers":[
        {
            "category":"Shopping",
            "subcategory":"Clothing, Apparel, & Fashions",
            "type":"Retail Goods"
        },
        {
            "category":"Shopping",
            "subcategory":"Bicycles & Sporting Goods",
            "type":"Retail Goods"
        }
    ],
    "sg:phone":"+1 505 814 6071",
    "sg:postcode":"87110",
    "sg:province":"NM",
    "sg:tags":[
        "clothing",
        "store"
    ],
    "sg:website":"http://www.cyclecave.com",
    "wof:name":"Cycle Cave Inc",
    "wof:placetype":"venue"
},
  "geometry": {"coordinates":[-106.580657,35.109057],"type":"Point"}
}