{
  "type": "Feature",
  "properties": {
    "addr:full":"123 Central Ave NW Albuquerque NM 87102",
    "addr:housenumber":"123",
    "addr:postcode":"87102",
    "addr:street":"Central Ave Nw",
    "iso:country":"US",
    "sg:address":"123 Central Ave NW",
    "sg:city":"Albuquerque",
    "sg:classifiers":[
        {
            "category":"Wholesale",
            "subcategory":"Electrical",
            "type":"Manufacturing & Wholesale Goods"
        }
    ],
    "sg:phone":"+1 505 764 6634",
    "sg:postcode":"87102",
    "sg:province":"NM",
    "sg:tags":[
        "telecommunication"
    ],
    "wof:name":"Brainstorm Industries",
    "wof:placetype":"venue"
},
  "geometry": {"coordinates":[-106.64905,35.08415],"type":"Point"}
}