{
  "type": "Feature",
  "properties": {
    "addr:full":"700 W Wilson Ave Gallup NM 87301",
    "addr:housenumber":"700",
    "addr:postcode":"87301",
    "addr:street":"W Wilson Ave",
    "iso:country":"US",
    "sg:address":"700 W Wilson Ave",
    "sg:city":"Gallup",
    "sg:classifiers":[
        {
            "category":"Education",
            "subcategory":"School",
            "type":"Public Place"
        }
    ],
    "sg:phone":"+1 505 863 3111",
    "sg:postcode":"87301",
    "sg:province":"NM",
    "wof:name":"Washington Elementary School",
    "wof:placetype":"venue"
},
  "geometry": {"coordinates":[-108.75205,35.529998],"type":"Point"}
}