{
  "type": "Feature",
  "properties": {
    "iso:country":"US",
    "sg:address":"8701 Oakcrest Pl NW",
    "sg:city":"Albuquerque",
    "sg:classifiers":[
        {
            "category":"Personal",
            "subcategory":"Beauty Salon",
            "type":"Services"
        }
    ],
    "sg:phone":"+1 505 899 4326",
    "sg:postcode":"87114",
    "sg:province":"NM",
    "sg:tags":[
        "shop"
    ],
    "wof:name":"Nailtek",
    "wof:placetype":"venue"
},
  "geometry": {"coordinates":[-106.683044,35.183827],"type":"Point"}
}