{
  "type": "Feature",
  "properties": {
    "iso:country":"US",
    "sg:address":"1571 Cerro Gordo Rd",
    "sg:city":"Santa Fe",
    "sg:classifiers":[
        {
            "category":"Building & Trades",
            "subcategory":"Construction",
            "type":"Services"
        }
    ],
    "sg:phone":"+1 505 820 6147",
    "sg:postcode":"87501",
    "sg:province":"NM",
    "sg:tags":[
        "contractor"
    ],
    "wof:name":"Olivas and Assoc",
    "wof:placetype":"venue"
},
  "geometry": {"coordinates":[-105.89954,35.686547],"type":"Point"}
}