{
  "type": "Feature",
  "properties": {
    "iso:country":"US",
    "sg:address":"8001 Wyoming Blvd NE",
    "sg:city":"Albuquerque",
    "sg:classifiers":[
        {
            "category":"Restaurant",
            "type":"Food & Drink"
        }
    ],
    "sg:phone":"+1 505 822 8802",
    "sg:postcode":"87113",
    "sg:province":"NM",
    "sg:tags":[
        "eating"
    ],
    "wof:name":"Jade Chinese Restaurant",
    "wof:placetype":"venue"
},
  "geometry": {"coordinates":[-106.55993599999999,35.174268],"type":"Point"}
}