{
  "type": "Feature",
  "properties": {
    "iso:country":"US",
    "sg:address":"1418 Luisa St",
    "sg:city":"Santa Fe",
    "sg:classifiers":[
        {
            "category":"Professional",
            "subcategory":"Accounting & Tax Preparation",
            "type":"Services"
        }
    ],
    "sg:phone":"+1 505 988 8835",
    "sg:postcode":"87505",
    "sg:province":"NM",
    "sg:tags":[
        "accountant"
    ],
    "wof:name":"Bishop & Loggains LLC",
    "wof:placetype":"venue"
},
  "geometry": {"coordinates":[-105.95169,35.668696],"type":"Point"}
}