{
  "type": "Feature",
  "properties": {
    "iso:country":"US",
    "sg:address":"3911 4th St NW",
    "sg:city":"Albuquerque",
    "sg:classifiers":[
        {
            "category":"Organizations",
            "subcategory":"Non-profit Organization",
            "type":"Services"
        }
    ],
    "sg:phone":"+1 505 345 6801",
    "sg:postcode":"87107",
    "sg:province":"NM",
    "sg:tags":[
        "info",
        "addiction",
        "abuse",
        "treatment",
        "drug"
    ],
    "wof:name":"Lifestyle Recovery",
    "wof:placetype":"venue"
},
  "geometry": {"coordinates":[-106.644175,35.123699],"type":"Point"}
}