{
  "type": "Feature",
  "properties": {
    "addr:full":"109 W Grand View Rd Capitan NM 88316",
    "addr:housenumber":"109",
    "addr:postcode":"88316",
    "addr:street":"W Grand View Rd",
    "iso:country":"US",
    "sg:address":"109 W Grand View Rd",
    "sg:city":"Capitan",
    "sg:classifiers":[
        {
            "category":"Retail",
            "subcategory":"Repair Shop",
            "type":"Services"
        }
    ],
    "sg:phone":"+1 505 354 8389",
    "sg:postcode":"88316",
    "sg:province":"NM",
    "sg:tags":[
        "upholsterer"
    ],
    "wof:name":"House Of Sewing",
    "wof:placetype":"venue"
},
  "geometry": {"coordinates":[-105.60480099999999,33.536667],"type":"Point"}
}