{
  "type": "Feature",
  "properties": {
    "addr:full":"518 E Griggs Ave Las Cruces NM 88001",
    "addr:housenumber":"518",
    "addr:postcode":"88001",
    "addr:street":"E Griggs Ave",
    "iso:country":"US",
    "sg:address":"518 E Griggs Ave",
    "sg:city":"Las Cruces",
    "sg:classifiers":[
        {
            "category":"Social Services",
            "subcategory":"Child Care",
            "type":"Services"
        }
    ],
    "sg:phone":"+1 505 526 8358",
    "sg:postcode":"88001",
    "sg:province":"NM",
    "sg:tags":[
        "day"
    ],
    "wof:name":"Connies Daycare",
    "wof:placetype":"venue"
},
  "geometry": {"coordinates":[-106.773433,32.310576],"type":"Point"}
}