{
  "type": "Feature",
  "properties": {
    "iso:country":"US",
    "sg:address":"6211 4th St NW",
    "sg:city":"Albuquerque",
    "sg:classifiers":[
        {
            "category":"Insurance",
            "subcategory":"Insurance Agent",
            "type":"Services"
        }
    ],
    "sg:phone":"+1 505 345 8757",
    "sg:postcode":"87107",
    "sg:province":"NM",
    "sg:tags":[
        "agency"
    ],
    "wof:name":"Chrzanowski Margaret",
    "wof:placetype":"venue"
},
  "geometry": {"coordinates":[-106.639892,35.146221],"type":"Point"}
}