{
  "type": "Feature",
  "properties": {
    "iso:country":"US",
    "sg:address":"12429 Towner Ave NE",
    "sg:city":"Albuquerque",
    "sg:classifiers":[
        {
            "category":"Professional",
            "type":"Services"
        }
    ],
    "sg:phone":"+1 505 293 2953",
    "sg:postcode":"87112",
    "sg:province":"NM",
    "wof:name":"Wyleas Services Inc",
    "wof:placetype":"venue"
},
  "geometry": {"coordinates":[-106.500603,35.108114],"type":"Point"}
}