{
  "type": "Feature",
  "properties": {
    "addr:full":"706 Cll Rivera Espanola NM 87532",
    "addr:housenumber":"706",
    "addr:postcode":"87532",
    "addr:street":"Cll Rivera",
    "iso:country":"US",
    "sg:address":"706 Cll Rivera",
    "sg:city":"Espanola",
    "sg:classifiers":[
        {
            "category":"Building & Trades",
            "subcategory":"Electrical",
            "type":"Services"
        }
    ],
    "sg:phone":"+1 505 753 6285",
    "sg:postcode":"87532",
    "sg:province":"NM",
    "sg:tags":[
        "electrical",
        "electric",
        "contractor"
    ],
    "wof:name":"Electric Connection LTD Co",
    "wof:placetype":"venue"
},
  "geometry": {"coordinates":[-106.060829,36.0185],"type":"Point"}
}