{
  "type": "Feature",
  "properties": {
    "iso:country":"US",
    "sg:address":"709 High St",
    "sg:city":"Lordsburg",
    "sg:classifiers":[
        {
            "category":"Health Services",
            "subcategory":"Chiropractor",
            "type":"Services"
        }
    ],
    "sg:phone":"+1 505 542 8806",
    "sg:postcode":"88045",
    "sg:province":"NM",
    "wof:name":"Carter Chiropractic Ctr",
    "wof:placetype":"venue"
},
  "geometry": {"coordinates":[-108.711776,32.345436],"type":"Point"}
}