{
  "type": "Feature",
  "properties": {
    "iso:country":"US",
    "sg:address":"2712 Carlisle Blvd NE",
    "sg:city":"Albuquerque",
    "sg:classifiers":[
        {
            "category":"Professional",
            "subcategory":"Detective & Security Services",
            "type":"Services"
        },
        {
            "category":"Manufacturing",
            "subcategory":"Electronics",
            "type":"Manufacturing & Wholesale Goods"
        }
    ],
    "sg:phone":"+1 505 988 9889",
    "sg:postcode":"87110",
    "sg:province":"NM",
    "sg:tags":[
        "control",
        "equipment-wholesale",
        "monitoring",
        "system",
        "manufacturer"
    ],
    "wof:name":"Tas Security Systems Inc",
    "wof:placetype":"venue"
},
  "geometry": {"coordinates":[-106.60408700000001,35.111293],"type":"Point"}
}