{
  "type": "Feature",
  "properties": {
    "iso:country":"US",
    "sg:address":"121 Cll del Presidente",
    "sg:city":"Bernalillo",
    "sg:classifiers":[
        {
            "category":"Health Services",
            "subcategory":"Doctor",
            "type":"Services"
        }
    ],
    "sg:phone":"+1 505 867 2324",
    "sg:postcode":"87004",
    "sg:province":"NM",
    "sg:tags":[
        "physician",
        "surgeon"
    ],
    "wof:name":"El Pueblo Health Svc",
    "wof:placetype":"venue"
},
  "geometry": {"coordinates":[-106.547127,35.305389],"type":"Point"}
}