{
  "type": "Feature",
  "properties": {
    "iso:country":"US",
    "sg:address":"4118 Central Ave SE",
    "sg:city":"Albuquerque",
    "sg:classifiers":[
        {
            "category":"Personal",
            "subcategory":"Beauty Salon",
            "type":"Services"
        }
    ],
    "sg:phone":"+1 505 268 9704",
    "sg:postcode":"87108",
    "sg:province":"NM",
    "wof:name":"Essence Beauty",
    "wof:placetype":"venue"
},
  "geometry": {"coordinates":[-106.597777,35.078944],"type":"Point"}
}