{
  "type": "Feature",
  "properties": {
    "iso:country":"US",
    "sg:address":"1101 W Broadway Ave",
    "sg:city":"Bloomfield",
    "sg:classifiers":[
        {
            "category":"Retail",
            "subcategory":"Repair Shop",
            "type":"Services"
        }
    ],
    "sg:phone":"+1 505 634 9953",
    "sg:postcode":"87413",
    "sg:province":"NM",
    "sg:tags":[
        "equipment",
        "welding"
    ],
    "wof:name":"Bad Bart's Welding Machine",
    "wof:placetype":"venue"
},
  "geometry": {"coordinates":[-107.991468,36.711209],"type":"Point"}
}