{
  "type": "Feature",
  "properties": {
    "iso:country":"US",
    "sg:address":"4410 Central Ave SW",
    "sg:city":"Albuquerque",
    "sg:classifiers":[
        {
            "category":"Shopping",
            "subcategory":"Hobbies, Toys, & Games",
            "type":"Retail Goods"
        },
        {
            "category":"Professional",
            "subcategory":"Management & Consulting",
            "type":"Services"
        }
    ],
    "sg:phone":"+1 505 831 6355",
    "sg:postcode":"87105",
    "sg:province":"NM",
    "sg:tags":[
        "direct",
        "sales"
    ],
    "wof:name":"J-1 Imports",
    "wof:placetype":"venue"
},
  "geometry": {"coordinates":[-106.685554,35.085529],"type":"Point"}
}