{
  "type": "Feature",
  "properties": {
    "addr:full":"2900 2nd St NW Albuquerque NM 87107",
    "addr:housenumber":"2900",
    "addr:postcode":"87107",
    "addr:street":"2Nd St Nw",
    "iso:country":"US",
    "sg:address":"2900 2nd St NW",
    "sg:city":"Albuquerque",
    "sg:classifiers":[
        {
            "category":"Retail",
            "subcategory":"Auto Repair",
            "type":"Services"
        }
    ],
    "sg:phone":"+1 505 344 3738",
    "sg:postcode":"87107",
    "sg:province":"NM",
    "sg:tags":[
        "repairing",
        "automobile"
    ],
    "wof:name":"Sheflones Auto",
    "wof:placetype":"venue"
},
  "geometry": {"coordinates":[-106.642886,35.115246],"type":"Point"}
}