{
  "type": "Feature",
  "properties": {
    "iso:country":"US",
    "sg:address":"423 4th St SW Ste C",
    "sg:city":"Albuquerque",
    "sg:phone":"+1 505 848 8002",
    "sg:postcode":"87102",
    "sg:province":"NM",
    "wof:name":"Heart & Soul",
    "wof:placetype":"venue"
},
  "geometry": {"coordinates":[-106.652173,35.081358],"type":"Point"}
}