{
  "type": "Feature",
  "properties": {
    "iso:country":"US",
    "sg:address":"400 San Felipe St NW",
    "sg:city":"Albuquerque",
    "sg:classifiers":[
        {
            "category":"Shopping",
            "subcategory":"Clothing, Apparel, & Fashions",
            "type":"Retail Goods"
        }
    ],
    "sg:phone":"+1 505 243 1960",
    "sg:postcode":"87104",
    "sg:province":"NM",
    "sg:tags":[
        "art",
        "jewelry"
    ],
    "wof:name":"South West Galleria",
    "wof:placetype":"venue"
},
  "geometry": {"coordinates":[-106.669342,35.098177],"type":"Point"}
}