{
  "type": "Feature",
  "properties": {
    "iso:country":"US",
    "sg:address":"733 Chihuahua Rd NE",
    "sg:city":"Rio Rancho",
    "sg:classifiers":[
        {
            "category":"Building & Trades",
            "subcategory":"Construction",
            "type":"Services"
        }
    ],
    "sg:phone":"+1 505 890 0859",
    "sg:postcode":"87144",
    "sg:province":"NM",
    "sg:tags":[
        "home",
        "builder"
    ],
    "wof:name":"Tre Taglio Homes",
    "wof:placetype":"venue"
},
  "geometry": {"coordinates":[-106.631058,35.269148],"type":"Point"}
}