{
  "type": "Feature",
  "properties": {
    "addr:full":"6800 Los Volcanoes Rd NW Albuquerque NM 87121",
    "addr:housenumber":"6800",
    "addr:postcode":"87121",
    "addr:street":"Los Volcanoes Rd Nw",
    "iso:country":"US",
    "sg:address":"6800 Los Volcanoes Rd NW",
    "sg:city":"Albuquerque",
    "sg:classifiers":[
        {
            "category":"Real Estate",
            "subcategory":"Real Estate Operator",
            "type":"Services"
        }
    ],
    "sg:phone":"+1 505 833 3799",
    "sg:postcode":"87121",
    "sg:province":"NM",
    "sg:tags":[
        "apartment"
    ],
    "wof:name":"Ahepa 501 Apartments Phase 1",
    "wof:placetype":"venue"
},
  "geometry": {"coordinates":[-106.711186,35.09107],"type":"Point"}
}