{
  "type": "Feature",
  "properties": {
    "addr:full":"501 E McGaffey St Roswell NM 88203",
    "addr:housenumber":"501",
    "addr:postcode":"88203",
    "addr:street":"E Mcgaffey St",
    "iso:country":"US",
    "sg:address":"501 E McGaffey St",
    "sg:city":"Roswell",
    "sg:classifiers":[
        {
            "category":"Government",
            "subcategory":"Fire Station",
            "type":"Public Place"
        }
    ],
    "sg:phone":"+1 505 624 6812",
    "sg:postcode":"88203",
    "sg:province":"NM",
    "sg:tags":[
        "department"
    ],
    "wof:name":"Roswell Fire Station",
    "wof:placetype":"venue"
},
  "geometry": {"coordinates":[-104.515424,33.379888],"type":"Point"}
}