{
  "type": "Feature",
  "properties": {
    "iso:country":"US",
    "sg:address":"2128 Central Ave SE",
    "sg:city":"Albuquerque",
    "sg:classifiers":[
        {
            "category":"Restaurant",
            "type":"Food & Drink"
        }
    ],
    "sg:phone":"+1 505 242 5366",
    "sg:postcode":"87106",
    "sg:province":"NM",
    "wof:name":"Bandito Hideout",
    "wof:placetype":"venue"
},
  "geometry": {"coordinates":[-106.622511,35.080916],"type":"Point"}
}