{
  "type": "Feature",
  "properties": {
    "iso:country":"US",
    "sg:address":"407 L Cassillas Blvd",
    "sg:city":"Clovis",
    "sg:classifiers":[
        {
            "category":"Social Services",
            "type":"Services"
        }
    ],
    "sg:phone":"+1 505 762 1933",
    "sg:postcode":"88101",
    "sg:province":"NM",
    "sg:tags":[
        "mission"
    ],
    "wof:name":"Lighthouse Mission",
    "wof:placetype":"venue"
},
  "geometry": {"coordinates":[-103.208871,34.39855],"type":"Point"}
}