{
  "type": "Feature",
  "properties": {
    "iso:country":"US",
    "sg:address":"5815 Wyoming Blvd NE",
    "sg:city":"Albuquerque",
    "sg:classifiers":[
        {
            "category":"Food & Beverages",
            "subcategory":"Groceries & Convenience Stores",
            "type":"Retail Goods"
        }
    ],
    "sg:phone":"+1 505 856 0474",
    "sg:postcode":"87109",
    "sg:province":"NM",
    "sg:website":"www.wholefoodsmarket.com",
    "wof:name":"Whole Foods Market",
    "wof:placetype":"venue"
},
  "geometry": {"coordinates":[-106.555067,35.14746],"type":"Point"}
}