{
  "type": "Feature",
  "properties": {
    "iso:country":"US",
    "sg:address":"407 S Guadalupe St",
    "sg:city":"Santa Fe",
    "sg:classifiers":[
        {
            "category":"Shopping",
            "type":"Retail Goods"
        }
    ],
    "sg:phone":"+1 505 995 9783",
    "sg:postcode":"87501",
    "sg:province":"NM",
    "sg:tags":[
        "art",
        "gallery",
        "dealer"
    ],
    "wof:name":"Ronnie Layden Fine Art Gallery",
    "wof:placetype":"venue"
},
  "geometry": {"coordinates":[-105.94584500000001,35.684335],"type":"Point"}
}