{
  "type": "Feature",
  "properties": {
    "iso:country":"US",
    "sg:address":"73 Sullivan Canyon Rd",
    "sg:city":"Cloudcroft",
    "sg:classifiers":[
        {
            "category":"Professional",
            "subcategory":"Accounting & Tax Preparation",
            "type":"Services"
        }
    ],
    "sg:phone":"+1 505 687 2444",
    "sg:postcode":"88317",
    "sg:province":"NM",
    "wof:name":"Mike Sherman Inc",
    "wof:placetype":"venue"
},
  "geometry": {"coordinates":[-105.650723,32.944309],"type":"Point"}
}