{
  "type": "Feature",
  "properties": {
    "addr:full":"541 Paisano St NE Ste B Albuquerque NM 87123",
    "addr:housenumber":"541",
    "addr:postcode":"87123",
    "addr:street":"Paisano St Ne Ste B",
    "iso:country":"US",
    "sg:address":"541 Paisano St NE Ste B",
    "sg:city":"Albuquerque",
    "sg:classifiers":[
        {
            "category":"Insurance",
            "subcategory":"Insurance Agent",
            "type":"Services"
        },
        {
            "category":"Insurance",
            "subcategory":"Hazard Insurance",
            "type":"Services"
        }
    ],
    "sg:phone":"+1 505 262 2236",
    "sg:postcode":"87123",
    "sg:province":"NM",
    "sg:tags":[
        "surety",
        "fidelity",
        "commercial",
        "business",
        "bond"
    ],
    "sg:website":"http://www.minickandcompany.com",
    "wof:name":"Minick & Company Inc.",
    "wof:placetype":"venue"
},
  "geometry": {"coordinates":[-106.51406,35.074526],"type":"Point"}
}