{
  "type": "Feature",
  "properties": {
    "addr:full":"3100 Sue Cir SE Rio Rancho NM 87124",
    "addr:housenumber":"3100",
    "addr:postcode":"87124",
    "addr:street":"Sue Cir Se",
    "iso:country":"US",
    "sg:address":"3100 Sue Cir SE",
    "sg:city":"Rio Rancho",
    "sg:classifiers":[
        {
            "category":"Building & Trades",
            "subcategory":"Construction",
            "type":"Services"
        }
    ],
    "sg:phone":"+1 505 892 7063",
    "sg:postcode":"87124",
    "sg:province":"NM",
    "sg:tags":[
        "general",
        "contractor"
    ],
    "wof:name":"Epic Jewelry Displays",
    "wof:placetype":"venue"
},
  "geometry": {"coordinates":[-106.67112299999999,35.236954],"type":"Point"}
}