{
  "type": "Feature",
  "properties": {
    "addr:full":"2901 Edith Blvd NE Albuquerque NM 87107",
    "addr:housenumber":"2901",
    "addr:postcode":"87107",
    "addr:street":"Edith Blvd Ne",
    "iso:country":"US",
    "sg:address":"2901 Edith Blvd NE",
    "sg:city":"Albuquerque",
    "sg:classifiers":[
        {
            "category":"Manufacturing",
            "subcategory":"Printing",
            "type":"Manufacturing & Wholesale Goods"
        }
    ],
    "sg:phone":"+1 505 345 2691",
    "sg:postcode":"87107",
    "sg:province":"NM",
    "sg:tags":[
        "commercial"
    ],
    "wof:name":"Diamond Press Inc",
    "wof:placetype":"venue"
},
  "geometry": {"coordinates":[-106.635293,35.115103],"type":"Point"}
}