{
  "type": "Feature",
  "properties": {
    "iso:country":"US",
    "sg:address":"201 E Washington Ave",
    "sg:city":"Lovington",
    "sg:classifiers":[
        {
            "category":"Health Services",
            "subcategory":"Hospital",
            "type":"Services"
        }
    ],
    "sg:phone":"+1 505 396 3972",
    "sg:postcode":"88260",
    "sg:province":"NM",
    "sg:tags":[
        "mental"
    ],
    "wof:name":"Zia Consulting Inc",
    "wof:placetype":"venue"
},
  "geometry": {"coordinates":[-103.346942,32.949157],"type":"Point"}
}