{
  "type": "Feature",
  "properties": {
    "iso:country":"US",
    "sg:address":"208 US Hwy 180 W",
    "sg:city":"Silver City",
    "sg:classifiers":[
        {
            "category":"Restaurant",
            "type":"Food & Drink"
        }
    ],
    "sg:phone":"+1 505 388 1128",
    "sg:postcode":"88061",
    "sg:province":"NM",
    "sg:tags":[
        "eating"
    ],
    "wof:name":"McDonalds",
    "wof:placetype":"venue"
},
  "geometry": {"coordinates":[-108.27564099999999,32.77997],"type":"Point"}
}