{
  "type": "Feature",
  "properties": {
    "iso:country":"US",
    "sg:address":"738 Meadow Lake Rd",
    "sg:city":"Los Lunas",
    "sg:classifiers":[
        {
            "category":"Utilities",
            "subcategory":"Water",
            "type":"Services"
        }
    ],
    "sg:phone":"+1 505 864 2218",
    "sg:postcode":"87031",
    "sg:province":"NM",
    "sg:tags":[
        "company",
        "sewage"
    ],
    "wof:name":"New Mexico Water Svc Co",
    "wof:placetype":"venue"
},
  "geometry": {"coordinates":[-106.54810000000001,34.805026],"type":"Point"}
}