{
  "type": "Feature",
  "properties": {
    "iso:country":"US",
    "sg:address":"901 N Prince St",
    "sg:city":"Clovis",
    "sg:classifiers":[
        {
            "category":"Autos & Motor Vehicles",
            "subcategory":"Fuel & Gas Station",
            "type":"Retail Goods"
        }
    ],
    "sg:phone":"+1 505 769 2291",
    "sg:postcode":"88101",
    "sg:province":"NM",
    "sg:tags":[
        "oil"
    ],
    "wof:name":"9th & Prince Chevron",
    "wof:placetype":"venue"
},
  "geometry": {"coordinates":[-103.196533,34.407837],"type":"Point"}
}