{
  "type": "Feature",
  "properties": {
    "addr:full":"3418 Central Ave SE Albuquerque NM 87106",
    "addr:housenumber":"3418",
    "addr:postcode":"87106",
    "addr:street":"Central Ave Se",
    "iso:country":"US",
    "sg:address":"3418 Central Ave SE",
    "sg:city":"Albuquerque",
    "sg:classifiers":[
        {
            "category":"Wholesale",
            "subcategory":"Non-durable Goods",
            "type":"Manufacturing & Wholesale Goods"
        }
    ],
    "sg:phone":"+1 505 246 8588",
    "sg:postcode":"87106",
    "sg:province":"NM",
    "wof:name":"Latino Inc",
    "wof:placetype":"venue"
},
  "geometry": {"coordinates":[-106.605985,35.07991],"type":"Point"}
}