{
  "type": "Feature",
  "properties": {
    "iso:country":"US",
    "sg:address":"715 1st St",
    "sg:city":"Grants",
    "sg:classifiers":[
        {
            "category":"Retail",
            "subcategory":"Laundry & Dry Cleaning",
            "type":"Services"
        }
    ],
    "sg:phone":"+1 505 287 2446",
    "sg:postcode":"87020",
    "sg:province":"NM",
    "sg:tags":[
        "cleaners",
        "plant",
        "coin",
        "drycleaning"
    ],
    "wof:name":"Holiday Cleaners & Laundry",
    "wof:placetype":"venue"
},
  "geometry": {"coordinates":[-107.844477,35.156859],"type":"Point"}
}