{
  "type": "Feature",
  "properties": {
    "iso:country":"US",
    "sg:address":"101 Park St",
    "sg:city":"Bayard",
    "sg:classifiers":[
        {
            "category":"Social Services",
            "type":"Services"
        }
    ],
    "sg:phone":"+1 505 537 2125",
    "sg:postcode":"88023",
    "sg:province":"NM",
    "sg:tags":[
        "youth",
        "organization",
        "center"
    ],
    "wof:name":"Copper Little League",
    "wof:placetype":"venue"
},
  "geometry": {"coordinates":[-108.133455,32.757658],"type":"Point"}
}