{
  "type": "Feature",
  "properties": {
    "addr:full":"309 Brady Canyon Rd Ruidoso NM 88345",
    "addr:housenumber":"309",
    "addr:postcode":"88345",
    "addr:street":"Brady Canyon Rd",
    "iso:country":"US",
    "sg:address":"309 Brady Canyon Rd",
    "sg:city":"Ruidoso",
    "sg:classifiers":[
        {
            "category":"Freight",
            "type":"Transportation"
        }
    ],
    "sg:phone":"+1 505 630 2055",
    "sg:postcode":"88345",
    "sg:province":"NM",
    "sg:tags":[
        "general"
    ],
    "wof:name":"Canyon Storage",
    "wof:placetype":"venue"
},
  "geometry": {"coordinates":[-105.690603,33.342754],"type":"Point"}
}