{
  "type": "Feature",
  "properties": {
    "iso:country":"US",
    "sg:address":"216 Pso del Pueblo Norte",
    "sg:city":"Taos",
    "sg:classifiers":[
        {
            "category":"Home & Garden",
            "subcategory":"Home Furnishings",
            "type":"Retail Goods"
        }
    ],
    "sg:phone":"+1 505 758 7801",
    "sg:postcode":"87571",
    "sg:province":"NM",
    "sg:tags":[
        "merchandise",
        "business"
    ],
    "wof:name":"Wabi Sabi",
    "wof:placetype":"venue"
},
  "geometry": {"coordinates":[-105.574279,36.404496],"type":"Point"}
}