{
  "type": "Feature",
  "properties": {
    "iso:country":"US",
    "sg:address":"811 Rankin Rd NE",
    "sg:city":"Albuquerque",
    "sg:classifiers":[
        {
            "category":"Home & Garden",
            "subcategory":"Garden Supply",
            "type":"Retail Goods"
        }
    ],
    "sg:phone":"+1 505 345 7847",
    "sg:postcode":"87107",
    "sg:province":"NM",
    "sg:tags":[
        "sprinkler"
    ],
    "wof:name":"Neumark Irrigation Supplies",
    "wof:placetype":"venue"
},
  "geometry": {"coordinates":[-106.627743,35.122761],"type":"Point"}
}