{
  "type": "Feature",
  "properties": {
    "iso:country":"US",
    "sg:address":"2221 Rio Rancho Dr SE",
    "sg:city":"Rio Rancho",
    "sg:classifiers":[
        {
            "category":"Travel",
            "subcategory":"Hotels & Motels",
            "type":"Entertainment"
        }
    ],
    "sg:phone":"+1 505 892 7900",
    "sg:postcode":"87124",
    "sg:province":"NM",
    "sg:website":"www.extendedstayamerica.com",
    "wof:name":"Extended Stay Inn & Suites Rio",
    "wof:placetype":"venue"
},
  "geometry": {"coordinates":[-106.661674,35.221327],"type":"Point"}
}