{
  "type": "Feature",
  "properties": {
    "addr:full":"700 Haines Ave NW Albuquerque NM 87102",
    "addr:housenumber":"700",
    "addr:postcode":"87102",
    "addr:street":"Haines Ave Nw",
    "iso:country":"US",
    "sg:address":"700 Haines Ave NW",
    "sg:city":"Albuquerque",
    "sg:classifiers":[
        {
            "category":"Professional",
            "subcategory":"Business Services",
            "type":"Services"
        }
    ],
    "sg:phone":"+1 505 878 9690",
    "sg:postcode":"87102",
    "sg:province":"NM",
    "sg:tags":[
        "barricade"
    ],
    "wof:name":"Action Safety Supply",
    "wof:placetype":"venue"
},
  "geometry": {"coordinates":[-106.654222,35.103741],"type":"Point"}
}