{
  "type": "Feature",
  "properties": {
    "iso:country":"US",
    "sg:address":"205 Rossmoor Rd SW",
    "sg:city":"Albuquerque",
    "sg:classifiers":[
        {
            "category":"Wholesale",
            "subcategory":"Machinery & Supplies",
            "type":"Manufacturing & Wholesale Goods"
        }
    ],
    "sg:phone":"+1 505 877 0287",
    "sg:postcode":"87105",
    "sg:province":"NM",
    "sg:tags":[
        "repair",
        "industrial",
        "e",
        "pumping",
        "equipment"
    ],
    "sg:website":"www.alphasw.com",
    "wof:name":"Alpha Southwest Inc",
    "wof:placetype":"venue"
},
  "geometry": {"coordinates":[-106.66201700000001,35.029839],"type":"Point"}
}