{
  "type": "Feature",
  "properties": {
    "addr:full":"67 Valle Hermosa Rd Sandia Park NM 87047",
    "addr:housenumber":"67",
    "addr:postcode":"87047",
    "addr:street":"Valle Hermosa Rd",
    "iso:country":"US",
    "sg:address":"67 Valle Hermosa Rd",
    "sg:city":"Sandia Park",
    "sg:classifiers":[
        {
            "category":"Autos & Motor Vehicles",
            "subcategory":"Motorcycle Sales",
            "type":"Retail Goods"
        }
    ],
    "sg:phone":"+1 505 281 9886",
    "sg:postcode":"87047",
    "sg:province":"NM",
    "wof:name":"Rider Valley Motorcycles LLC",
    "wof:placetype":"venue"
},
  "geometry": {"coordinates":[-106.318039,35.145706],"type":"Point"}
}