{
  "type": "Feature",
  "properties": {
    "iso:country":"US",
    "sg:address":"13125 Cedarbrook Ave NE",
    "sg:city":"Albuquerque",
    "sg:classifiers":[
        {
            "category":"Social Services",
            "subcategory":"Child Care",
            "type":"Services"
        }
    ],
    "sg:phone":"+1 505 296 9485",
    "sg:postcode":"87111",
    "sg:province":"NM",
    "sg:tags":[
        "day"
    ],
    "wof:name":"My Playschool Inc",
    "wof:placetype":"venue"
},
  "geometry": {"coordinates":[-106.491568,35.133973],"type":"Point"}
}