{
  "type": "Feature",
  "properties": {
    "addr:full":"865 Will Rogers Dr Santa Rosa NM 88435",
    "addr:housenumber":"865",
    "addr:postcode":"88435",
    "addr:street":"Will Rogers Dr",
    "iso:country":"US",
    "sg:address":"865 Will Rogers Dr",
    "sg:city":"Santa Rosa",
    "sg:classifiers":[
        {
            "category":"Restaurant",
            "type":"Food & Drink"
        }
    ],
    "sg:phone":"+1 505 472 3361",
    "sg:postcode":"88435",
    "sg:province":"NM",
    "sg:tags":[
        "eating"
    ],
    "wof:name":"Joseph's Restaurant",
    "wof:placetype":"venue"
},
  "geometry": {"coordinates":[-104.681681,34.94423],"type":"Point"}
}