{
  "type": "Feature",
  "properties": {
    "addr:full":"3831 Singer Blvd NE Albuquerque NM 87109",
    "addr:housenumber":"3831",
    "addr:postcode":"87109",
    "addr:street":"Singer Blvd Ne",
    "iso:country":"US",
    "sg:address":"3831 Singer Blvd NE",
    "sg:city":"Albuquerque",
    "sg:classifiers":[
        {
            "category":"Wholesale",
            "subcategory":"Stationery",
            "type":"Manufacturing & Wholesale Goods"
        }
    ],
    "sg:phone":"+1 505 345 3525",
    "sg:postcode":"87109",
    "sg:province":"NM",
    "sg:tags":[
        "supply",
        "furniture"
    ],
    "wof:name":"Boise Cascade",
    "wof:placetype":"venue"
},
  "geometry": {"coordinates":[-106.60172,35.144769],"type":"Point"}
}