{
  "type": "Feature",
  "properties": {
    "iso:country":"US",
    "sg:address":"2906 Edgecliff Pl",
    "sg:city":"Farmington",
    "sg:classifiers":[
        {
            "category":"Building & Trades",
            "subcategory":"Construction",
            "type":"Services"
        }
    ],
    "sg:phone":"+1 505 325 1239",
    "sg:postcode":"87402",
    "sg:province":"NM",
    "sg:tags":[
        "plastering",
        "contractor"
    ],
    "wof:name":"Ike's Plastering Inc",
    "wof:placetype":"venue"
},
  "geometry": {"coordinates":[-108.168529,36.756588],"type":"Point"}
}