{
  "type": "Feature",
  "properties": {
    "iso:country":"US",
    "sg:address":"133 Franklin St",
    "sg:city":"Hatch",
    "sg:classifiers":[
        {
            "category":"Government",
            "subcategory":"Office",
            "type":"Public Place"
        }
    ],
    "sg:phone":"+1 505 267 1686",
    "sg:postcode":"87937",
    "sg:province":"NM",
    "sg:tags":[
        "city",
        "program"
    ],
    "wof:name":"Hatch Motor Vehicles Dept",
    "wof:placetype":"venue"
},
  "geometry": {"coordinates":[-107.15327600000001,32.665953],"type":"Point"}
}