{
  "type": "Feature",
  "properties": {
    "iso:country":"US",
    "sg:address":"1572 Center Dr",
    "sg:city":"Santa Fe",
    "sg:classifiers":[
        {
            "category":"Utilities",
            "subcategory":"Mobile Phone",
            "type":"Services"
        }
    ],
    "sg:phone":"+1 505 474 3994",
    "sg:postcode":"87507",
    "sg:province":"NM",
    "sg:tags":[
        "communication",
        "radiotelephone"
    ],
    "wof:name":"Nextel",
    "wof:placetype":"venue"
},
  "geometry": {"coordinates":[-106.025116,35.635913],"type":"Point"}
}