{
  "type": "Feature",
  "properties": {
    "iso:country":"US",
    "sg:address":"4801 Alameda Blvd NE",
    "sg:city":"Albuquerque",
    "sg:classifiers":[
        {
            "category":"Home & Garden",
            "subcategory":"Building Materials",
            "type":"Retail Goods"
        }
    ],
    "sg:phone":"+1 505 345 3501",
    "sg:postcode":"87113",
    "sg:province":"NM",
    "sg:tags":[
        "windows"
    ],
    "sg:website":"www.pella.com",
    "wof:name":"Pella Window & Door Co",
    "wof:placetype":"venue"
},
  "geometry": {"coordinates":[-106.589676,35.184534],"type":"Point"}
}