{
  "type": "Feature",
  "properties": {
    "addr:full":"1801 S Canal St Carlsbad NM 88220",
    "addr:housenumber":"1801",
    "addr:postcode":"88220",
    "addr:street":"S Canal St",
    "iso:country":"US",
    "sg:address":"1801 S Canal St",
    "sg:city":"Carlsbad",
    "sg:classifiers":[
        {
            "category":"Restaurant",
            "type":"Food & Drink"
        }
    ],
    "sg:phone":"+1 505 234 2815",
    "sg:postcode":"88220",
    "sg:province":"NM",
    "sg:tags":[
        "eating"
    ],
    "wof:name":"No Whiner Diner",
    "wof:placetype":"venue"
},
  "geometry": {"coordinates":[-104.22390300000001,32.40363],"type":"Point"}
}