{
  "type": "Feature",
  "properties": {
    "addr:full":"5617 Menaul Blvd NE Albuquerque NM 87110",
    "addr:housenumber":"5617",
    "addr:postcode":"87110",
    "addr:street":"Menaul Blvd Ne",
    "iso:country":"US",
    "sg:address":"5617 Menaul Blvd NE",
    "sg:city":"Albuquerque",
    "sg:classifiers":[
        {
            "category":"Banks & Credit Unions",
            "subcategory":"Bank",
            "type":"Services"
        }
    ],
    "sg:phone":"+1 505 881 7004",
    "sg:postcode":"87110",
    "sg:province":"NM",
    "sg:tags":[
        "loan"
    ],
    "wof:name":"Western Finance",
    "wof:placetype":"venue"
},
  "geometry": {"coordinates":[-106.581012,35.109179],"type":"Point"}
}