{
  "type": "Feature",
  "properties": {
    "iso:country":"US",
    "sg:address":"6600 Menaul Blvd NE",
    "sg:city":"Albuquerque",
    "sg:classifiers":[
        {
            "category":"Food & Beverages",
            "subcategory":"Candy",
            "type":"Retail Goods"
        }
    ],
    "sg:phone":"+1 505 881 8384",
    "sg:postcode":"87110",
    "sg:province":"NM",
    "sg:website":"www.sweetfactory.com",
    "wof:name":"Sweet Factory",
    "wof:placetype":"venue"
},
  "geometry": {"coordinates":[-106.56990999999999,35.109124],"type":"Point"}
}