{
  "type": "Feature",
  "properties": {
    "iso:country":"US",
    "sg:address":"248 Muriel St NE",
    "sg:city":"Albuquerque",
    "sg:classifiers":[
        {
            "category":"Building & Trades",
            "subcategory":"Construction",
            "type":"Services"
        }
    ],
    "sg:phone":"+1 505 291 8372",
    "sg:postcode":"87123",
    "sg:province":"NM",
    "sg:tags":[
        "general",
        "contractor"
    ],
    "wof:name":"Lonnie Wright Construction",
    "wof:placetype":"venue"
},
  "geometry": {"coordinates":[-106.516254,35.072414],"type":"Point"}
}