{
  "type": "Feature",
  "properties": {
    "iso:country":"US",
    "sg:address":"1450 Bridge Blvd SW",
    "sg:city":"Albuquerque",
    "sg:classifiers":[
        {
            "category":"Real Estate",
            "subcategory":"Real Estate Operator",
            "type":"Services"
        }
    ],
    "sg:phone":"+1 505 244 3559",
    "sg:postcode":"87105",
    "sg:province":"NM",
    "sg:tags":[
        "apartment"
    ],
    "wof:name":"LA Villa Alegre Apartments",
    "wof:placetype":"venue"
},
  "geometry": {"coordinates":[-106.6742,35.066566],"type":"Point"}
}