{
  "type": "Feature",
  "properties": {
    "addr:full":"435 Saint Michaels Dr Santa Fe NM 87505",
    "addr:housenumber":"435",
    "addr:postcode":"87505",
    "addr:street":"Saint Michaels Dr",
    "iso:country":"US",
    "sg:address":"435 Saint Michaels Dr",
    "sg:city":"Santa Fe",
    "sg:classifiers":[
        {
            "category":"Social Services",
            "subcategory":"Job Training",
            "type":"Services"
        }
    ],
    "sg:phone":"+1 505 954 8500",
    "sg:postcode":"87505",
    "sg:province":"NM",
    "sg:tags":[
        "rehabilitation",
        "vocational",
        "center"
    ],
    "wof:name":"Vocatnal Rehabilitation Div NM",
    "wof:placetype":"venue"
},
  "geometry": {"coordinates":[-105.943349,35.656454],"type":"Point"}
}