{
  "type": "Feature",
  "properties": {
    "addr:full":"1476 Miracerros Loop N Santa Fe NM 87505",
    "addr:housenumber":"1476",
    "addr:postcode":"87505",
    "addr:street":"Miracerros Loop N",
    "iso:country":"US",
    "sg:address":"1476 Miracerros Loop N",
    "sg:city":"Santa Fe",
    "sg:classifiers":[
        {
            "category":"Travel",
            "subcategory":"Travel Agent",
            "type":"Entertainment"
        }
    ],
    "sg:phone":"+1 505 982 8829",
    "sg:postcode":"87505",
    "sg:province":"NM",
    "sg:tags":[
        "operator",
        "tour"
    ],
    "wof:name":"Lamy Shuttle & Tours",
    "wof:placetype":"venue"
},
  "geometry": {"coordinates":[-105.95005999999999,35.668498],"type":"Point"}
}