{
  "type": "Feature",
  "properties": {
    "addr:full":"215 Sierra Dr SE Albuquerque NM 87108",
    "addr:housenumber":"215",
    "addr:postcode":"87108",
    "addr:street":"Sierra Dr Se",
    "iso:country":"US",
    "sg:address":"215 Sierra Dr SE",
    "sg:city":"Albuquerque",
    "sg:classifiers":[
        {
            "category":"Professional",
            "subcategory":"Business Services",
            "type":"Services"
        }
    ],
    "sg:phone":"+1 505 262 0620",
    "sg:postcode":"87108",
    "sg:province":"NM",
    "wof:name":"Robert Gllgos Nativ Amercn Art",
    "wof:placetype":"venue"
},
  "geometry": {"coordinates":[-106.597899,35.07749],"type":"Point"}
}