{
  "type": "Feature",
  "properties": {
    "iso:country":"US",
    "sg:address":"418 Colorado Ave.",
    "sg:city":"Las Cruces",
    "sg:classifiers":[
        {
            "category":"Professional",
            "subcategory":"Management & Consulting",
            "type":"Services"
        }
    ],
    "sg:phone":"+1 575 647 2785",
    "sg:postcode":"88001-3613",
    "sg:province":"NM",
    "sg:tags":[
        "grand-unified-theory",
        "quantum-mechanics",
        "quantum-physics",
        "electrical-engineering",
        "chemical-engineering",
        "unified-physics-equations",
        "relativity",
        "atomic-model"
    ],
    "sg:website":"http://www.symmecon.com",
    "wof:name":"Symmecon Grand Unified Theory Marketing ",
    "wof:placetype":"venue"
},
  "geometry": {"coordinates":[-106.772448,32.303649],"type":"Point"}
}