{
  "type": "Feature",
  "properties": {
    "addr:full":"303 Washington St SE Albuquerque NM 87108",
    "addr:housenumber":"303",
    "addr:postcode":"87108",
    "addr:street":"Washington St Se",
    "iso:country":"US",
    "sg:address":"303 Washington St SE",
    "sg:city":"Albuquerque",
    "sg:classifiers":[
        {
            "category":"Building & Trades",
            "subcategory":"Pest Control",
            "type":"Services"
        }
    ],
    "sg:phone":"+1 505 826 9489",
    "sg:postcode":"87108",
    "sg:province":"NM",
    "wof:name":"Action Termite & Pest Control",
    "wof:placetype":"venue"
},
  "geometry": {"coordinates":[-106.595416,35.075727],"type":"Point"}
}