{
  "type": "Feature",
  "properties": {
    "iso:country":"US",
    "sg:address":"1426 W 2nd St",
    "sg:city":"Roswell",
    "sg:classifiers":[
        {
            "category":"Autos & Motor Vehicles",
            "subcategory":"Automobile Sales",
            "type":"Retail Goods"
        }
    ],
    "sg:phone":"+1 505 625 2415",
    "sg:postcode":"88201",
    "sg:province":"NM",
    "sg:tags":[
        "car",
        "dealer"
    ],
    "wof:name":"Abode Auto Plaza",
    "wof:placetype":"venue"
},
  "geometry": {"coordinates":[-104.543128,33.394117],"type":"Point"}
}