{
  "type": "Feature",
  "properties": {
    "addr:full":"702 Chrysler Dr Roswell NM 88201",
    "addr:housenumber":"702",
    "addr:postcode":"88201",
    "addr:street":"Chrysler Dr",
    "iso:country":"US",
    "sg:address":"702 Chrysler Dr",
    "sg:city":"Roswell",
    "sg:classifiers":[
        {
            "category":"Building & Trades",
            "subcategory":"Construction",
            "type":"Services"
        }
    ],
    "sg:phone":"+1 505 625 0774",
    "sg:postcode":"88201",
    "sg:province":"NM",
    "sg:tags":[
        "house"
    ],
    "wof:name":"Superior Homecrafters LLC",
    "wof:placetype":"venue"
},
  "geometry": {"coordinates":[-104.53178699999999,33.428428],"type":"Point"}
}