{
  "type": "Feature",
  "properties": {
    "iso:country":"US",
    "sg:address":"1802 Ave de Mesilla",
    "sg:city":"Las Cruces",
    "sg:classifiers":[
        {
            "category":"Manufacturing",
            "subcategory":"Wood Products",
            "type":"Manufacturing & Wholesale Goods"
        }
    ],
    "sg:phone":"+1 505 523 1362",
    "sg:postcode":"88005",
    "sg:province":"NM",
    "sg:tags":[
        "contractor",
        "carpentry",
        "trade",
        "mfg"
    ],
    "wof:name":"Mesilla Woodworks",
    "wof:placetype":"venue"
},
  "geometry": {"coordinates":[-106.79593,32.280119],"type":"Point"}
}