{
  "type": "Feature",
  "properties": {
    "iso:country":"US",
    "sg:address":"301 E 2nd St",
    "sg:city":"Clovis",
    "sg:classifiers":[
        {
            "category":"Shopping",
            "subcategory":"Used Merchandise",
            "type":"Retail Goods"
        }
    ],
    "sg:phone":"+1 505 762 3802",
    "sg:postcode":"88101",
    "sg:province":"NM",
    "wof:name":"Salvation Army Thrift Store",
    "wof:placetype":"venue"
},
  "geometry": {"coordinates":[-103.20272799999999,34.399688],"type":"Point"}
}