{
  "type": "Feature",
  "properties": {
    "iso:country":"US",
    "sg:address":"1065 S Main St",
    "sg:city":"Las Cruces",
    "sg:classifiers":[
        {
            "category":"Professional",
            "subcategory":"Management & Consulting",
            "type":"Services"
        }
    ],
    "sg:phone":"+1 505 647 0908",
    "sg:postcode":"88005",
    "sg:province":"NM",
    "sg:tags":[
        "consultant",
        "educational"
    ],
    "wof:name":"Corridor Inc",
    "wof:placetype":"venue"
},
  "geometry": {"coordinates":[-106.778631,32.300044],"type":"Point"}
}