{
  "type": "Feature",
  "properties": {
    "iso:country":"US",
    "sg:address":"110 Los Pandos Rd",
    "sg:city":"Taos",
    "sg:classifiers":[
        {
            "category":"Building & Trades",
            "subcategory":"Plumbing",
            "type":"Services"
        }
    ],
    "sg:phone":"+1 505 758 3227",
    "sg:postcode":"87571",
    "sg:province":"NM",
    "sg:tags":[
        "septic"
    ],
    "wof:name":"A & A Septic Svc",
    "wof:placetype":"venue"
},
  "geometry": {"coordinates":[-105.574704,36.402296],"type":"Point"}
}