{
  "type": "Feature",
  "properties": {
    "addr:full":"411 Saint Michaels Dr Santa Fe NM 87505",
    "addr:housenumber":"411",
    "addr:postcode":"87505",
    "addr:street":"Saint Michaels Dr",
    "iso:country":"US",
    "sg:address":"411 Saint Michaels Dr",
    "sg:city":"Santa Fe",
    "sg:classifiers":[
        {
            "category":"Professional",
            "subcategory":"Accounting & Tax Preparation",
            "type":"Services"
        }
    ],
    "sg:phone":"+1 505 984 3100",
    "sg:postcode":"87505",
    "sg:province":"NM",
    "sg:tags":[
        "accountant"
    ],
    "wof:name":"Houtman Accounting & Tax Svcs",
    "wof:placetype":"venue"
},
  "geometry": {"coordinates":[-105.941005,35.655748],"type":"Point"}
}