{
  "type": "Feature",
  "properties": {
    "addr:full":"4300 College Blvd Farmington NM 87402",
    "addr:housenumber":"4300",
    "addr:postcode":"87402",
    "addr:street":"College Blvd",
    "iso:country":"US",
    "sg:address":"4300 College Blvd",
    "sg:city":"Farmington",
    "sg:classifiers":[
        {
            "category":"Social Services",
            "subcategory":"Child Care",
            "type":"Services"
        }
    ],
    "sg:phone":"+1 505 325 0656",
    "sg:postcode":"87402",
    "sg:province":"NM",
    "sg:tags":[
        "center",
        "daycare"
    ],
    "wof:name":"Casa Montessori of Farmington",
    "wof:placetype":"venue"
},
  "geometry": {"coordinates":[-108.166033,36.762525],"type":"Point"}
}