{
  "type": "Feature",
  "properties": {
    "addr:full":"9901 Montgomery Blvd NE Albuquerque NM 87111",
    "addr:housenumber":"9901",
    "addr:postcode":"87111",
    "addr:street":"Montgomery Blvd Ne",
    "iso:country":"US",
    "sg:address":"9901 Montgomery Blvd NE",
    "sg:city":"Albuquerque",
    "sg:classifiers":[
        {
            "category":"Recreation",
            "type":"Entertainment"
        }
    ],
    "sg:phone":"+1 505 344 2500",
    "sg:postcode":"87111",
    "sg:province":"NM",
    "sg:tags":[
        "parks"
    ],
    "sg:website":"www.wrinm.org",
    "wof:name":"Wildlife Rescue Of New Mexico",
    "wof:placetype":"venue"
},
  "geometry": {"coordinates":[-106.52965,35.130728],"type":"Point"}
}