{
  "type": "Feature",
  "properties": {
    "addr:full":"212 W Main St Artesia NM 88210",
    "addr:housenumber":"212",
    "addr:postcode":"88210",
    "addr:street":"W Main St",
    "iso:country":"US",
    "sg:address":"212 W Main St",
    "sg:city":"Artesia",
    "sg:classifiers":[
        {
            "category":"Insurance",
            "subcategory":"Insurance Agent",
            "type":"Services"
        }
    ],
    "sg:phone":"+1 505 746 9897",
    "sg:postcode":"88210",
    "sg:province":"NM",
    "wof:name":"New York Life Insurance Co",
    "wof:placetype":"venue"
},
  "geometry": {"coordinates":[-104.39885599999999,32.842343],"type":"Point"}
}