{
  "type": "Feature",
  "properties": {
    "iso:country":"US",
    "sg:address":"813 4th St",
    "sg:city":"Las Vegas",
    "sg:classifiers":[
        {
            "category":"Health Services",
            "subcategory":"Clinic",
            "type":"Services"
        }
    ],
    "sg:phone":"+1 505 425 0044",
    "sg:postcode":"87701",
    "sg:province":"NM",
    "sg:tags":[
        "home"
    ],
    "wof:name":"Alegre Home Health",
    "wof:placetype":"venue"
},
  "geometry": {"coordinates":[-105.21478,35.598809],"type":"Point"}
}