{
  "type": "Feature",
  "properties": {
    "addr:full":"9 Mesa Vista Rd Cuba NM 87013",
    "addr:housenumber":"9",
    "addr:postcode":"87013",
    "addr:street":"Mesa Vista Rd",
    "iso:country":"US",
    "sg:address":"9 Mesa Vista Rd",
    "sg:city":"Cuba",
    "sg:classifiers":[
        {
            "category":"Utilities",
            "subcategory":"Natural Gas",
            "type":"Services"
        }
    ],
    "sg:phone":"+1 505 289 0151",
    "sg:postcode":"87013",
    "sg:province":"NM",
    "sg:tags":[
        "company"
    ],
    "wof:name":"Pnm Gas Svc",
    "wof:placetype":"venue"
},
  "geometry": {"coordinates":[-106.954722,36.020796],"type":"Point"}
}