{
  "type": "Feature",
  "properties": {
    "addr:full":"701 N Canal St Carlsbad NM 88220",
    "addr:housenumber":"701",
    "addr:postcode":"88220",
    "addr:street":"N Canal St",
    "iso:country":"US",
    "sg:address":"701 N Canal St",
    "sg:city":"Carlsbad",
    "sg:classifiers":[
        {
            "category":"Health Services",
            "subcategory":"Doctor",
            "type":"Services"
        }
    ],
    "sg:phone":"+1 505 234 1466",
    "sg:postcode":"88220",
    "sg:province":"NM",
    "sg:tags":[
        "physician",
        "surgeon"
    ],
    "wof:name":"Southern Nm Hematology & Onclg",
    "wof:placetype":"venue"
},
  "geometry": {"coordinates":[-104.228889,32.428601],"type":"Point"}
}