{
  "type": "Feature",
  "properties": {
    "iso:country":"US",
    "sg:address":"17520 Tierra Alta Dr",
    "sg:city":"Organ",
    "sg:classifiers":[
        {
            "category":"Retail",
            "subcategory":"Repair Shop",
            "type":"Services"
        }
    ],
    "sg:phone":"+1 505 382 7102",
    "sg:postcode":"88011",
    "sg:province":"NM",
    "wof:name":"Awl-Way",
    "wof:placetype":"venue"
},
  "geometry": {"coordinates":[-106.57837600000001,32.42846],"type":"Point"}
}