{
  "type": "Feature",
  "properties": {
    "iso:country":"US",
    "sg:address":"927 Los Lentes Rd NE",
    "sg:city":"Los Lunas",
    "sg:classifiers":[
        {
            "category":"Manufacturing",
            "subcategory":"Signs",
            "type":"Manufacturing & Wholesale Goods"
        }
    ],
    "sg:phone":"+1 505 865 4717",
    "sg:postcode":"87031",
    "sg:province":"NM",
    "wof:name":"Vialpando Signs",
    "wof:placetype":"venue"
},
  "geometry": {"coordinates":[-106.726567,34.814354],"type":"Point"}
}