{
  "type": "Feature",
  "properties": {
    "addr:full":"4420 W Rodeo Rd Santa Fe NM 87507",
    "addr:housenumber":"4420",
    "addr:postcode":"87507",
    "addr:street":"W Rodeo Rd",
    "iso:country":"US",
    "sg:address":"4420 W Rodeo Rd",
    "sg:city":"Santa Fe",
    "sg:classifiers":[
        {
            "category":"Retail",
            "subcategory":"Auto Repair",
            "type":"Services"
        }
    ],
    "sg:phone":"+1 505 438 6031",
    "sg:postcode":"87507",
    "sg:province":"NM",
    "sg:tags":[
        "general"
    ],
    "wof:name":"Meineke Discount Mufflers",
    "wof:placetype":"venue"
},
  "geometry": {"coordinates":[-106.01667,35.638524],"type":"Point"}
}