{
  "type": "Feature",
  "properties": {
    "iso:country":"US",
    "sg:address":"1016 Daskalos Dr NE",
    "sg:city":"Albuquerque",
    "sg:classifiers":[
        {
            "category":"Wholesale",
            "subcategory":"Computers",
            "type":"Manufacturing & Wholesale Goods"
        }
    ],
    "sg:phone":"+1 505 299 4381",
    "sg:postcode":"87123",
    "sg:province":"NM",
    "wof:name":"National Pos Systems of Nm",
    "wof:placetype":"venue"
},
  "geometry": {"coordinates":[-106.48547600000001,35.083417],"type":"Point"}
}