{
  "type": "Feature",
  "properties": {
    "addr:full":"6709 Prairie Rd NE Albuquerque NM 87109",
    "addr:housenumber":"6709",
    "addr:postcode":"87109",
    "addr:street":"Prairie Rd Ne",
    "iso:country":"US",
    "sg:address":"6709 Prairie Rd NE",
    "sg:city":"Albuquerque",
    "sg:classifiers":[
        {
            "category":"Real Estate",
            "subcategory":"Real Estate Services",
            "type":"Services"
        }
    ],
    "sg:phone":"+1 505 880 8787",
    "sg:postcode":"87109",
    "sg:province":"NM",
    "sg:tags":[
        "abstract",
        "title"
    ],
    "wof:name":"Red Mesa Title Service",
    "wof:placetype":"venue"
},
  "geometry": {"coordinates":[-106.56941500000001,35.13328],"type":"Point"}
}