{
  "type": "Feature",
  "properties": {
    "iso:country":"US",
    "sg:address":"1219 Gusdorf Rd",
    "sg:city":"Taos",
    "sg:classifiers":[
        {
            "category":"Arts & Performance",
            "subcategory":"Theater",
            "type":"Entertainment"
        }
    ],
    "sg:phone":"+1 505 758 0363",
    "sg:postcode":"87571",
    "sg:province":"NM",
    "sg:tags":[
        "dance",
        "company"
    ],
    "wof:name":"Khecari Dance Theatre",
    "wof:placetype":"venue"
},
  "geometry": {"coordinates":[-105.58735799999999,36.377947],"type":"Point"}
}