{
  "type": "Feature",
  "properties": {
    "addr:full":"111 Vermont St NE Albuquerque NM 87108",
    "addr:housenumber":"111",
    "addr:postcode":"87108",
    "addr:street":"Vermont St Ne",
    "iso:country":"US",
    "sg:address":"111 Vermont St NE",
    "sg:city":"Albuquerque",
    "sg:classifiers":[
        {
            "category":"Autos & Motor Vehicles",
            "subcategory":"Automobile Sales",
            "type":"Retail Goods"
        }
    ],
    "sg:phone":"+1 505 232 2125",
    "sg:postcode":"87108",
    "sg:province":"NM",
    "sg:tags":[
        "car",
        "dealer"
    ],
    "wof:name":"Car Co",
    "wof:placetype":"venue"
},
  "geometry": {"coordinates":[-106.55383500000001,35.07615],"type":"Point"}
}