{
  "type": "Feature",
  "properties": {
    "iso:country":"US",
    "sg:address":"5946 Agua Fria St",
    "sg:city":"Santa Fe",
    "sg:classifiers":[
        {
            "category":"Home & Garden",
            "subcategory":"Building Materials",
            "type":"Retail Goods"
        }
    ],
    "sg:phone":"+1 505 471 3491",
    "sg:postcode":"87507",
    "sg:province":"NM",
    "sg:website":"www.gmf.com",
    "wof:name":"Chaparral Materials Inc",
    "wof:placetype":"venue"
},
  "geometry": {"coordinates":[-106.05466699999999,35.638394],"type":"Point"}
}