{
  "type": "Feature",
  "properties": {
    "iso:country":"US",
    "sg:address":"423 E Pine St",
    "sg:city":"Deming",
    "sg:classifiers":[
        {
            "category":"Autos & Motor Vehicles",
            "subcategory":"Fuel & Gas Station",
            "type":"Retail Goods"
        }
    ],
    "sg:phone":"+1 505 546 3166",
    "sg:postcode":"88030",
    "sg:province":"NM",
    "sg:tags":[
        "station",
        "gasoline",
        "oil"
    ],
    "wof:name":"Pine Street Fina",
    "wof:placetype":"venue"
},
  "geometry": {"coordinates":[-107.753957,32.269346],"type":"Point"}
}