{
  "type": "Feature",
  "properties": {
    "addr:full":"19554 State Hwy 314 Belen NM 87002",
    "addr:housenumber":"19554",
    "addr:postcode":"87002",
    "addr:street":"State Hwy 314",
    "iso:country":"US",
    "sg:address":"19554 State Hwy 314",
    "sg:city":"Belen",
    "sg:classifiers":[
        {
            "category":"Shopping",
            "subcategory":"Department Store",
            "type":"Retail Goods"
        }
    ],
    "sg:phone":"+1 505 861 2345",
    "sg:postcode":"87002",
    "sg:province":"NM",
    "wof:name":"Sears Roebuck & Co",
    "wof:placetype":"venue"
},
  "geometry": {"coordinates":[-106.76060699999999,34.710117],"type":"Point"}
}