{
  "type": "Feature",
  "properties": {
    "iso:country":"US",
    "sg:address":"1001 Main St",
    "sg:city":"Lordsburg",
    "sg:classifiers":[
        {
            "category":"Autos & Motor Vehicles",
            "subcategory":"Fuel & Gas Station",
            "type":"Retail Goods"
        }
    ],
    "sg:phone":"+1 505 542 8032",
    "sg:postcode":"88045",
    "sg:province":"NM",
    "sg:tags":[
        "station",
        "gasoline"
    ],
    "wof:name":"Ernest J Short & Sons Inc",
    "wof:placetype":"venue"
},
  "geometry": {"coordinates":[-108.711851,32.343212],"type":"Point"}
}