{
  "type": "Feature",
  "properties": {
    "iso:country":"US",
    "sg:address":"2838 Cagua Dr NE",
    "sg:city":"Albuquerque",
    "sg:classifiers":[
        {
            "category":"Professional",
            "subcategory":"Business Services",
            "type":"Services"
        }
    ],
    "sg:phone":"+1 505 798 9000",
    "sg:postcode":"87110",
    "sg:province":"NM",
    "sg:tags":[
        "paging",
        "answering"
    ],
    "wof:name":"Business Network Ctr",
    "wof:placetype":"venue"
},
  "geometry": {"coordinates":[-106.578517,35.115654],"type":"Point"}
}