{
  "type": "Feature",
  "properties": {
    "iso:country":"US",
    "sg:address":"3347 Cerrillos Rd",
    "sg:city":"Santa Fe",
    "sg:classifiers":[
        {
            "category":"Travel",
            "subcategory":"Hotels & Motels",
            "type":"Entertainment"
        }
    ],
    "sg:phone":"+1 505 424 2453",
    "sg:postcode":"87507",
    "sg:province":"NM",
    "wof:name":"Courtyard By Marriott",
    "wof:placetype":"venue"
},
  "geometry": {"coordinates":[-106.001264,35.649522],"type":"Point"}
}