{
  "type": "Feature",
  "properties": {
    "addr:full":"3347 Cerrillos Rd Santa Fe NM 87507",
    "addr:housenumber":"3347",
    "addr:postcode":"87507",
    "addr:street":"Cerrillos Rd",
    "iso:country":"US",
    "sg:address":"3347 Cerrillos Rd",
    "sg:city":"Santa Fe",
    "sg:classifiers":[
        {
            "category":"Travel",
            "subcategory":"Hotels & Motels",
            "type":"Entertainment"
        }
    ],
    "sg:phone":"+1 505 424 2453",
    "sg:postcode":"87507",
    "sg:province":"NM",
    "wof:name":"Courtyard By Marriott",
    "wof:placetype":"venue"
},
  "geometry": {"coordinates":[-106.00126400000001,35.649522],"type":"Point"}
}