{
  "type": "Feature",
  "properties": {
    "addr:full":"1809 el Paseo Rd Las Cruces NM 88001",
    "addr:housenumber":"1809",
    "addr:postcode":"88001",
    "addr:street":"El Paseo Rd",
    "iso:country":"US",
    "sg:address":"1809 el Paseo Rd",
    "sg:city":"Las Cruces",
    "sg:classifiers":[
        {
            "category":"Organizations",
            "subcategory":"Religious Organization",
            "type":"Services"
        }
    ],
    "sg:phone":"+1 505 644 5025",
    "sg:postcode":"88001",
    "sg:province":"NM",
    "sg:tags":[
        "church"
    ],
    "wof:name":"Holy Family Old Catholic Chr",
    "wof:placetype":"venue"
},
  "geometry": {"coordinates":[-106.764312,32.290433],"type":"Point"}
}