{
  "type": "Feature",
  "properties": {
    "addr:full":"6211 4th St NW Albuquerque NM 87107",
    "addr:housenumber":"6211",
    "addr:postcode":"87107",
    "addr:street":"4Th St Nw",
    "iso:country":"US",
    "sg:address":"6211 4th St NW",
    "sg:city":"Albuquerque",
    "sg:classifiers":[
        {
            "category":"Personal",
            "subcategory":"Beauty Salon",
            "type":"Services"
        }
    ],
    "sg:phone":"+1 505 345 4666",
    "sg:postcode":"87107",
    "sg:province":"NM",
    "wof:name":"Style America",
    "wof:placetype":"venue"
},
  "geometry": {"coordinates":[-106.639892,35.146221],"type":"Point"}
}