{
  "type": "Feature",
  "properties": {
    "iso:country":"US",
    "sg:address":"4120 Cholla Rd",
    "sg:city":"Las Cruces",
    "sg:classifiers":[
        {
            "category":"Building & Trades",
            "subcategory":"Plumbing",
            "type":"Services"
        }
    ],
    "sg:phone":"+1 505 522 5995",
    "sg:postcode":"88011",
    "sg:province":"NM",
    "sg:tags":[
        "plumbing",
        "contractor"
    ],
    "wof:name":"Construction Plumbing",
    "wof:placetype":"venue"
},
  "geometry": {"coordinates":[-106.727272,32.270699],"type":"Point"}
}