{
  "type": "Feature",
  "properties": {
    "iso:country":"US",
    "sg:address":"108 N Spruce Ave",
    "sg:city":"Lovington",
    "sg:classifiers":[
        {
            "category":"Building & Trades",
            "subcategory":"Construction",
            "type":"Services"
        }
    ],
    "sg:phone":"+1 505 396 5221",
    "sg:postcode":"88201",
    "sg:province":"NM",
    "sg:tags":[
        "water",
        "well",
        "drilling"
    ],
    "wof:name":"Taylor Windmill & Submersible",
    "wof:placetype":"venue"
},
  "geometry": {"coordinates":[-104.55234900000001,33.394062],"type":"Point"}
}