{
  "type": "Feature",
  "properties": {
    "iso:country":"US",
    "sg:address":"76 Rincon Loop",
    "sg:city":"Tijeras",
    "sg:classifiers":[
        {
            "category":"Building & Trades",
            "subcategory":"Landscaping Services",
            "type":"Services"
        }
    ],
    "sg:phone":"+1 505 281 9609",
    "sg:postcode":"87059",
    "sg:province":"NM",
    "wof:name":"B & M Lawn Maintenance Inc",
    "wof:placetype":"venue"
},
  "geometry": {"coordinates":[-106.36608099999999,35.108664],"type":"Point"}
}