{
  "type": "Feature",
  "properties": {
    "iso:country":"US",
    "sg:address":"13632 Canada del Oso Pl NE",
    "sg:city":"Albuquerque",
    "sg:classifiers":[
        {
            "category":"Professional",
            "subcategory":"Employment Agencies",
            "type":"Services"
        }
    ],
    "sg:phone":"+1 505 249 9996",
    "sg:postcode":"87111",
    "sg:province":"NM",
    "sg:tags":[
        "help",
        "supply"
    ],
    "wof:name":"Dennis Bergman",
    "wof:placetype":"venue"
},
  "geometry": {"coordinates":[-106.478799,35.150729],"type":"Point"}
}