{
  "type": "Feature",
  "properties": {
    "iso:country":"US",
    "sg:address":"520 Mullen Rd NW",
    "sg:city":"Albuquerque",
    "sg:classifiers":[
        {
            "category":"Retail",
            "subcategory":"Repair Shop",
            "type":"Services"
        }
    ],
    "sg:phone":"+1 505 343 8113",
    "sg:postcode":"87107",
    "sg:province":"NM",
    "sg:tags":[
        "upholsterer"
    ],
    "wof:name":"Action Furniture",
    "wof:placetype":"venue"
},
  "geometry": {"coordinates":[-106.643354,35.151437],"type":"Point"}
}