{
  "type": "Feature",
  "properties": {
    "iso:country":"US",
    "sg:address":"151 S Solano Dr",
    "sg:city":"Las Cruces",
    "sg:classifiers":[
        {
            "category":"Organizations",
            "subcategory":"Non-profit Organization",
            "type":"Services"
        },
        {
            "category":"Social Services",
            "subcategory":"Job Training",
            "type":"Services"
        }
    ],
    "sg:phone":"+1 505 526 0903",
    "sg:postcode":"88001",
    "sg:province":"NM",
    "sg:tags":[
        "retardation",
        "disabled",
        "mental",
        "dev"
    ],
    "wof:name":"Families Plus Inc",
    "wof:placetype":"venue"
},
  "geometry": {"coordinates":[-106.764892,32.31237],"type":"Point"}
}