{
  "type": "Feature",
  "properties": {
    "iso:country":"US",
    "sg:address":"3320 2nd St NW",
    "sg:city":"Albuquerque",
    "sg:classifiers":[
        {
            "category":"Food & Beverages",
            "subcategory":"Bakery",
            "type":"Retail Goods"
        }
    ],
    "sg:phone":"+1 505 256 0752",
    "sg:postcode":"87107",
    "sg:province":"NM",
    "sg:tags":[
        "baker"
    ],
    "wof:name":"Union Baking Co",
    "wof:placetype":"venue"
},
  "geometry": {"coordinates":[-106.64248000000001,35.115706],"type":"Point"}
}