{
  "type": "Feature",
  "properties": {
    "iso:country":"US",
    "sg:address":"3604 Sierra Vista Dr",
    "sg:city":"Farmington",
    "sg:classifiers":[
        {
            "category":"Travel",
            "subcategory":"Campground",
            "type":"Entertainment"
        }
    ],
    "sg:phone":"+1 505 327 0933",
    "sg:postcode":"87402",
    "sg:province":"NM",
    "sg:tags":[
        "farm",
        "hay",
        "park",
        "trailer",
        "operates"
    ],
    "wof:name":"Martinez Enterprises",
    "wof:placetype":"venue"
},
  "geometry": {"coordinates":[-108.14384099999999,36.761006],"type":"Point"}
}