{
  "type": "Feature",
  "properties": {
    "iso:country":"US",
    "sg:address":"2820 Broadbent Pkwy NE",
    "sg:city":"Albuquerque",
    "sg:classifiers":[
        {
            "category":"Manufacturing",
            "subcategory":"Printing",
            "type":"Manufacturing & Wholesale Goods"
        }
    ],
    "sg:phone":"+1 505 343 9600",
    "sg:postcode":"87107",
    "sg:province":"NM",
    "sg:tags":[
        "multimedia"
    ],
    "wof:name":"Integrated Media Systems",
    "wof:placetype":"venue"
},
  "geometry": {"coordinates":[-106.628984,35.112538],"type":"Point"}
}