{
  "type": "Feature",
  "properties": {
    "iso:country":"US",
    "sg:address":"2407 Floral Rd NW",
    "sg:city":"Albuquerque",
    "sg:classifiers":[
        {
            "category":"Manufacturing",
            "subcategory":"Metals",
            "type":"Manufacturing & Wholesale Goods"
        }
    ],
    "sg:phone":"+1 505 242 2255",
    "sg:postcode":"87104",
    "sg:province":"NM",
    "sg:tags":[
        "ornamental",
        "work"
    ],
    "wof:name":"Custom Irons By Gallegos",
    "wof:placetype":"venue"
},
  "geometry": {"coordinates":[-106.673604,35.107068],"type":"Point"}
}