{
  "type": "Feature",
  "properties": {
    "iso:country":"US",
    "sg:address":"3111 Amherst Dr NE",
    "sg:city":"Albuquerque",
    "sg:classifiers":[
        {
            "category":"Manufacturing",
            "subcategory":"Furniture",
            "type":"Manufacturing & Wholesale Goods"
        }
    ],
    "sg:phone":"+1 505 385 5131",
    "sg:postcode":"87107",
    "sg:province":"NM",
    "sg:tags":[
        "wood",
        "mfg"
    ],
    "wof:name":"Tapworks",
    "wof:placetype":"venue"
},
  "geometry": {"coordinates":[-106.605289,35.117293],"type":"Point"}
}