{
  "type": "Feature",
  "properties": {
    "iso:country":"US",
    "sg:address":"1765 Ira Dr NE",
    "sg:city":"Rio Rancho",
    "sg:classifiers":[
        {
            "category":"Professional",
            "subcategory":"Accounting & Tax Preparation",
            "type":"Services"
        }
    ],
    "sg:phone":"+1 505 896 4968",
    "sg:postcode":"87144",
    "sg:province":"NM",
    "wof:name":"Richard Richard",
    "wof:placetype":"venue"
},
  "geometry": {"coordinates":[-106.7153,35.287276],"type":"Point"}
}