{
  "type": "Feature",
  "properties": {
    "iso:country":"US",
    "sg:address":"3356 Governor Miles Rd",
    "sg:city":"Santa Fe",
    "sg:classifiers":[
        {
            "category":"Building & Trades",
            "subcategory":"Cleaning & Sanitation",
            "type":"Services"
        }
    ],
    "sg:phone":"+1 505 474 9553",
    "sg:postcode":"87507",
    "sg:province":"NM",
    "sg:tags":[
        "janitor"
    ],
    "wof:name":"Mountain-Air Janitorial Clng",
    "wof:placetype":"venue"
},
  "geometry": {"coordinates":[-106.000389,35.627771],"type":"Point"}
}