{
  "type": "Feature",
  "properties": {
    "iso:country":"US",
    "sg:address":"415 N Cecil St",
    "sg:city":"Hobbs",
    "sg:classifiers":[
        {
            "category":"Shopping",
            "type":"Retail Goods"
        }
    ],
    "sg:phone":"+1 505 397 1972",
    "sg:postcode":"88240",
    "sg:province":"NM",
    "sg:tags":[
        "picture",
        "frame"
    ],
    "wof:name":"Frame House",
    "wof:placetype":"venue"
},
  "geometry": {"coordinates":[-103.148552,32.705918],"type":"Point"}
}