{
  "type": "Feature",
  "properties": {
    "iso:country":"US",
    "sg:address":"505 National Ave",
    "sg:city":"Las Vegas",
    "sg:phone":"+1 505 454 9494",
    "sg:postcode":"87701",
    "sg:province":"NM",
    "sg:tags":[
        "gas"
    ],
    "wof:name":"Yabrra Propane",
    "wof:placetype":"venue"
},
  "geometry": {"coordinates":[-105.215255,35.597374],"type":"Point"}
}