{
  "type": "Feature",
  "properties": {
    "iso:country":"US",
    "sg:address":"1315 S 8th St",
    "sg:city":"Deming",
    "sg:classifiers":[
        {
            "category":"Health Services",
            "subcategory":"Doctor",
            "type":"Services"
        }
    ],
    "sg:phone":"+1 505 546 6591",
    "sg:postcode":"88030",
    "sg:province":"NM",
    "sg:tags":[
        "dentist"
    ],
    "wof:name":"John L Gordon DDS",
    "wof:placetype":"venue"
},
  "geometry": {"coordinates":[-107.768685,32.255877],"type":"Point"}
}