{
  "type": "Feature",
  "properties": {
    "addr:full":"46 Dusty Trails Dr Placitas NM 87043",
    "addr:housenumber":"46",
    "addr:postcode":"87043",
    "addr:street":"Dusty Trails;Placitas",
    "iso:country":"US",
    "sg:address":"46 Dusty Trails Dr",
    "sg:city":"Placitas",
    "sg:classifiers":[
        {
            "category":"Building & Trades",
            "subcategory":"Construction",
            "type":"Services"
        }
    ],
    "sg:phone":"+1 505 771 2785",
    "sg:postcode":"87043",
    "sg:province":"NM",
    "sg:tags":[
        "company"
    ],
    "wof:name":"Zolnosky Construction Inc",
    "wof:placetype":"venue"
},
  "geometry": {"coordinates":[-106.497399,35.311139],"type":"Point"}
}