{
  "type": "Feature",
  "properties": {
    "iso:country":"US",
    "sg:address":"109 Lois Ln",
    "sg:city":"Sandia Park",
    "sg:classifiers":[
        {
            "category":"Building & Trades",
            "subcategory":"Construction",
            "type":"Services"
        }
    ],
    "sg:phone":"+1 505 286 8318",
    "sg:postcode":"87047",
    "sg:province":"NM",
    "sg:tags":[
        "utility",
        "contractor"
    ],
    "wof:name":"Western Utility Systems Inc",
    "wof:placetype":"venue"
},
  "geometry": {"coordinates":[-106.33472399999999,35.164328],"type":"Point"}
}