{
  "type": "Feature",
  "properties": {
    "iso:country":"US",
    "sg:address":"500 N Main St",
    "sg:city":"Roswell",
    "sg:classifiers":[
        {
            "category":"Education",
            "subcategory":"Vocational School",
            "type":"Public Place"
        }
    ],
    "sg:phone":"+1 505 627 0552",
    "sg:postcode":"88201",
    "sg:province":"NM",
    "wof:name":"Artesia Vocational Training",
    "wof:placetype":"venue"
},
  "geometry": {"coordinates":[-104.52274300000001,33.39879],"type":"Point"}
}