{
  "type": "Feature",
  "properties": {
    "addr:full":"2823 Industrial Rd Santa Fe NM 87507",
    "addr:housenumber":"2823",
    "addr:postcode":"87507",
    "addr:street":"Industrial Rd",
    "iso:country":"US",
    "sg:address":"2823 Industrial Rd",
    "sg:city":"Santa Fe",
    "sg:classifiers":[
        {
            "category":"Building & Trades",
            "subcategory":"Construction",
            "type":"Services"
        }
    ],
    "sg:phone":"+1 505 474 4836",
    "sg:postcode":"87507",
    "sg:province":"NM",
    "sg:tags":[
        "contractor"
    ],
    "wof:name":"Szantho Wood Works",
    "wof:placetype":"venue"
},
  "geometry": {"coordinates":[-105.99047400000001,35.662795],"type":"Point"}
}