{
  "type": "Feature",
  "properties": {
    "addr:full":"2617 Floral Rd NW Albuquerque NM 87104",
    "addr:housenumber":"2617",
    "addr:postcode":"87104",
    "addr:street":"Floral Rd Nw",
    "iso:country":"US",
    "sg:address":"2617 Floral Rd NW",
    "sg:city":"Albuquerque",
    "sg:classifiers":[
        {
            "category":"Professional",
            "type":"Services"
        }
    ],
    "sg:phone":"+1 505 842 6480",
    "sg:postcode":"87104",
    "sg:province":"NM",
    "wof:name":"Grant Right",
    "wof:placetype":"venue"
},
  "geometry": {"coordinates":[-106.67501,35.107036],"type":"Point"}
}