{
  "type": "Feature",
  "properties": {
    "iso:country":"US",
    "sg:address":"814 Cam del Monte Sol",
    "sg:city":"Santa Fe",
    "sg:classifiers":[
        {
            "category":"Building & Trades",
            "subcategory":"Landscaping Services",
            "type":"Services"
        }
    ],
    "sg:phone":"+1 505 474 5459",
    "sg:postcode":"87505",
    "sg:province":"NM",
    "sg:tags":[
        "landscape"
    ],
    "wof:name":"Chord Architecture",
    "wof:placetype":"venue"
},
  "geometry": {"coordinates":[-105.922428,35.671942],"type":"Point"}
}