{
  "type": "Feature",
  "properties": {
    "iso:country":"US",
    "sg:address":"3401 Ladera Dr NW",
    "sg:city":"Albuquerque",
    "sg:classifiers":[
        {
            "category":"Government",
            "subcategory":"Office",
            "type":"Public Place"
        }
    ],
    "sg:phone":"+1 505 836 8734",
    "sg:postcode":"87120",
    "sg:province":"NM",
    "sg:tags":[
        "township",
        "government-city",
        "village"
    ],
    "wof:name":"Albuquerque City Government",
    "wof:placetype":"venue"
},
  "geometry": {"coordinates":[-106.708389,35.121449],"type":"Point"}
}