{
  "type": "Feature",
  "properties": {
    "iso:country":"US",
    "sg:address":"1100 N Main St",
    "sg:city":"Las Cruces",
    "sg:classifiers":[
        {
            "category":"Professional",
            "subcategory":"Printing & Photocopies",
            "type":"Services"
        }
    ],
    "sg:phone":"+1 505 525 9400",
    "sg:postcode":"88001",
    "sg:province":"NM",
    "sg:tags":[
        "duplicating",
        "copying"
    ],
    "wof:name":"Complete Reprographics",
    "wof:placetype":"venue"
},
  "geometry": {"coordinates":[-106.78136000000001,32.3193],"type":"Point"}
}