{
  "type": "Feature",
  "properties": {
    "iso:country":"US",
    "sg:address":"10022 Rio Grande Blvd NW",
    "sg:city":"Albuquerque",
    "sg:classifiers":[
        {
            "category":"Professional",
            "subcategory":"Accounting & Tax Preparation",
            "type":"Services"
        }
    ],
    "sg:phone":"+1 505 833 5450",
    "sg:postcode":"87114",
    "sg:province":"NM",
    "sg:tags":[
        "accountant"
    ],
    "wof:name":"Fernandez Financial Svc",
    "wof:placetype":"venue"
},
  "geometry": {"coordinates":[-106.629434,35.199554],"type":"Point"}
}