{
  "type": "Feature",
  "properties": {
    "iso:country":"US",
    "sg:address":"3116 S Hwy 28",
    "sg:city":"Anthony",
    "sg:classifiers":[
        {
            "category":"Bars & Pubs",
            "type":"Food & Drink"
        }
    ],
    "sg:phone":"+1 505 874 2802",
    "sg:postcode":"88021",
    "sg:province":"NM",
    "wof:name":"Gallery 28",
    "wof:placetype":"venue"
},
  "geometry": {"coordinates":[-106.645078,31.955672],"type":"Point"}
}