{
  "type": "Feature",
  "properties": {
    "iso:country":"US",
    "sg:address":"241 Monte Alto Pl NE",
    "sg:city":"Albuquerque",
    "sg:classifiers":[
        {
            "category":"Professional",
            "subcategory":"Computer Services",
            "type":"Services"
        }
    ],
    "sg:phone":"+1 505 275 1502",
    "sg:postcode":"87123",
    "sg:province":"NM",
    "sg:tags":[
        "programing",
        "custom"
    ],
    "wof:name":"Makua Works Ltd",
    "wof:placetype":"venue"
},
  "geometry": {"coordinates":[-106.494701,35.0718],"type":"Point"}
}