{
  "type": "Feature",
  "properties": {
    "iso:country":"US",
    "sg:address":"7400 Krista Dr NE",
    "sg:city":"Albuquerque",
    "sg:classifiers":[
        {
            "category":"Professional",
            "subcategory":"Secretarial Services",
            "type":"Services"
        }
    ],
    "sg:phone":"+1 505 798 1507",
    "sg:postcode":"87109",
    "sg:province":"NM",
    "sg:tags":[
        "editing"
    ],
    "wof:name":"Heidi Reed",
    "wof:placetype":"venue"
},
  "geometry": {"coordinates":[-106.565083,35.160306],"type":"Point"}
}