{
  "type": "Feature",
  "properties": {
    "iso:country":"US",
    "sg:address":"3006 E Greene St",
    "sg:city":"Carlsbad",
    "sg:classifiers":[
        {
            "category":"Wholesale",
            "subcategory":"Machinery & Supplies",
            "type":"Manufacturing & Wholesale Goods"
        }
    ],
    "sg:phone":"+1 505 628 1619",
    "sg:postcode":"88220",
    "sg:province":"NM",
    "sg:tags":[
        "field",
        "oil"
    ],
    "wof:name":"Wilson",
    "wof:placetype":"venue"
},
  "geometry": {"coordinates":[-104.14808600000001,32.456234],"type":"Point"}
}