{
  "type": "Feature",
  "properties": {
    "addr:full":"85 Las Estrellas Santa Fe NM 87507",
    "addr:housenumber":"85",
    "addr:postcode":"87507",
    "addr:street":"Las Estrellas",
    "iso:country":"US",
    "sg:address":"85 Las Estrellas",
    "sg:city":"Santa Fe",
    "sg:classifiers":[
        {
            "category":"Professional",
            "type":"Services"
        }
    ],
    "sg:phone":"+1 505 471 4502",
    "sg:postcode":"87507",
    "sg:province":"NM",
    "sg:tags":[
        "studio"
    ],
    "wof:name":"Frank Andrews",
    "wof:placetype":"venue"
},
  "geometry": {"coordinates":[-106.080946,35.582298],"type":"Point"}
}