{
  "type": "Feature",
  "properties": {
    "iso:country":"US",
    "sg:address":"816 3rd St NW",
    "sg:city":"Albuquerque",
    "sg:classifiers":[
        {
            "category":"Recreation",
            "type":"Entertainment"
        }
    ],
    "sg:phone":"+1 505 243 7525",
    "sg:postcode":"87102",
    "sg:province":"NM",
    "wof:name":"Ra Support Services",
    "wof:placetype":"venue"
},
  "geometry": {"coordinates":[-106.648754,35.092765],"type":"Point"}
}