{
  "type": "Feature",
  "properties": {
    "iso:country":"US",
    "sg:address":"8704 Wisconsin Ct",
    "sg:city":"Clovis",
    "sg:classifiers":[
        {
            "category":"Professional",
            "subcategory":"Business Services",
            "type":"Services"
        }
    ],
    "sg:phone":"+1 505 784 9262",
    "sg:postcode":"88101",
    "sg:province":"NM",
    "sg:tags":[
        "embroidery"
    ],
    "wof:name":"B's Embroidery",
    "wof:placetype":"venue"
},
  "geometry": {"coordinates":[-103.333859,34.410525],"type":"Point"}
}