{
  "type": "Feature",
  "properties": {
    "iso:country":"US",
    "sg:address":"107 Mission Ridge Rd",
    "sg:city":"Corrales",
    "sg:classifiers":[
        {
            "category":"Building & Trades",
            "subcategory":"Construction",
            "type":"Services"
        }
    ],
    "sg:phone":"+1 505 899 1198",
    "sg:postcode":"87048",
    "sg:province":"NM",
    "sg:tags":[
        "home",
        "builder"
    ],
    "wof:name":"Builders West",
    "wof:placetype":"venue"
},
  "geometry": {"coordinates":[-106.636428,35.242117],"type":"Point"}
}