{
  "type": "Feature",
  "properties": {
    "iso:country":"US",
    "sg:address":"518 24th St",
    "sg:city":"Alamogordo",
    "sg:classifiers":[
        {
            "category":"Manufacturing",
            "subcategory":"Printing",
            "type":"Manufacturing & Wholesale Goods"
        }
    ],
    "sg:phone":"+1 505 437 7120",
    "sg:postcode":"88310",
    "sg:province":"NM",
    "sg:tags":[
        "newspaper"
    ],
    "sg:website":"www.alamogordonews.com",
    "wof:name":"Alamogordo Daily News",
    "wof:placetype":"venue"
},
  "geometry": {"coordinates":[-105.95667,32.919085],"type":"Point"}
}