{
  "type": "Feature",
  "properties": {
    "addr:full":"220 N White Sands Blvd Alamogordo NM 88310",
    "addr:housenumber":"220",
    "addr:postcode":"88310",
    "addr:street":"N White Sands Blvd",
    "iso:country":"US",
    "sg:address":"220 N White Sands Blvd",
    "sg:city":"Alamogordo",
    "sg:classifiers":[
        {
            "category":"Retail",
            "subcategory":"Auto Repair",
            "type":"Services"
        }
    ],
    "sg:phone":"+1 505 437 4112",
    "sg:postcode":"88310",
    "sg:province":"NM",
    "sg:tags":[
        "repairing",
        "automobile"
    ],
    "wof:name":"White Sands Automotive Ctr",
    "wof:placetype":"venue"
},
  "geometry": {"coordinates":[-105.96008999999999,32.892665],"type":"Point"}
}