{
  "type": "Feature",
  "properties": {
    "iso:country":"US",
    "sg:address":"1722 Quail Run Ct NE",
    "sg:city":"Albuquerque",
    "sg:classifiers":[
        {
            "category":"Professional",
            "subcategory":"Business Services",
            "type":"Services"
        }
    ],
    "sg:phone":"+1 505 856 1137",
    "sg:postcode":"87122",
    "sg:province":"NM",
    "wof:name":"Quail Run Medical Enterprizes",
    "wof:placetype":"venue"
},
  "geometry": {"coordinates":[-106.494321,35.162131],"type":"Point"}
}