{
  "type": "Feature",
  "properties": {
    "addr:full":"439 W San Francisco St Santa Fe NM 87501",
    "addr:housenumber":"439",
    "addr:postcode":"87501",
    "addr:street":"W San Francisco St",
    "iso:country":"US",
    "sg:address":"439 W San Francisco St",
    "sg:city":"Santa Fe",
    "sg:classifiers":[
        {
            "category":"Building & Trades",
            "subcategory":"Construction",
            "type":"Services"
        }
    ],
    "sg:phone":"+1 505 473 1670",
    "sg:postcode":"87501",
    "sg:province":"NM",
    "sg:tags":[
        "general",
        "commercial",
        "contractor"
    ],
    "wof:name":"Groundbreaking Inc",
    "wof:placetype":"venue"
},
  "geometry": {"coordinates":[-105.946254,35.689401],"type":"Point"}
}