{
  "type": "Feature",
  "properties": {
    "addr:full":"1624 McDonald Rd NW Albuquerque NM 87107",
    "addr:housenumber":"1624",
    "addr:postcode":"87107",
    "addr:street":"Mcdonald Rd Nw",
    "iso:country":"US",
    "sg:address":"1624 McDonald Rd NW",
    "sg:city":"Albuquerque",
    "sg:classifiers":[
        {
            "category":"Professional",
            "subcategory":"Management & Consulting",
            "type":"Services"
        }
    ],
    "sg:phone":"+1 505 344 8463",
    "sg:postcode":"87107",
    "sg:province":"NM",
    "sg:tags":[
        "business"
    ],
    "wof:name":"Consolidated Consulting Corp",
    "wof:placetype":"venue"
},
  "geometry": {"coordinates":[-106.66763,35.115705],"type":"Point"}
}