{
  "type": "Feature",
  "properties": {
    "iso:country":"US",
    "sg:address":"511 Nizhoni Blvd",
    "sg:city":"Gallup",
    "sg:classifiers":[
        {
            "category":"Local Transit",
            "type":"Transportation"
        }
    ],
    "sg:phone":"+1 505 722 7746",
    "sg:postcode":"87301",
    "sg:province":"NM",
    "sg:tags":[
        "ambulance"
    ],
    "wof:name":"Med Star Ambulance Svc",
    "wof:placetype":"venue"
},
  "geometry": {"coordinates":[-108.730349,35.508395],"type":"Point"}
}