{
  "type": "Feature",
  "properties": {
    "iso:country":"US",
    "sg:address":"737 Cagua Dr SE",
    "sg:city":"Albuquerque",
    "sg:classifiers":[
        {
            "category":"Real Estate",
            "subcategory":"Real Estate Agent",
            "type":"Services"
        },
        {
            "category":"Wholesale",
            "subcategory":"Durable Goods & Equipment",
            "type":"Manufacturing & Wholesale Goods"
        }
    ],
    "sg:phone":"+1 505 262 0100",
    "sg:postcode":"87108",
    "sg:province":"NM",
    "sg:tags":[
        "representative",
        "manufacturer"
    ],
    "wof:name":"Real Estate Connection Of Nm",
    "wof:placetype":"venue"
},
  "geometry": {"coordinates":[-106.57872399999999,35.068022],"type":"Point"}
}