{
  "type": "Feature",
  "properties": {
    "iso:country":"US",
    "sg:address":"299 4th St",
    "sg:city":"Chama",
    "sg:classifiers":[
        {
            "category":"Social Services",
            "type":"Services"
        }
    ],
    "sg:phone":"+1 505 756 2765",
    "sg:postcode":"87520",
    "sg:province":"NM",
    "sg:tags":[
        "senior",
        "citizen"
    ],
    "wof:name":"Rio Arriba County Senior Ctzns",
    "wof:placetype":"venue"
},
  "geometry": {"coordinates":[-106.58105500000001,36.904395],"type":"Point"}
}