{
  "type": "Feature",
  "properties": {
    "iso:country":"US",
    "sg:address":"610 N 4th St",
    "sg:city":"Belen",
    "sg:classifiers":[
        {
            "category":"Utilities",
            "subcategory":"Refuse",
            "type":"Services"
        }
    ],
    "sg:phone":"+1 505 261 8018",
    "sg:postcode":"87002",
    "sg:province":"NM",
    "sg:tags":[
        "garbage",
        "collection"
    ],
    "wof:name":"Small Equipment Svc",
    "wof:placetype":"venue"
},
  "geometry": {"coordinates":[-106.770274,34.666927],"type":"Point"}
}