{
  "type": "Feature",
  "properties": {
    "addr:full":"401 Central Ave Carrizozo NM 88310",
    "addr:housenumber":"401",
    "addr:postcode":"88310",
    "addr:street":"Central Ave",
    "iso:country":"US",
    "sg:address":"401 Central Ave",
    "sg:city":"Carrizozo",
    "sg:classifiers":[
        {
            "category":"Banks & Credit Unions",
            "subcategory":"Bank",
            "type":"Services"
        }
    ],
    "sg:phone":"+1 505 648 2377",
    "sg:postcode":"88310",
    "sg:province":"NM",
    "wof:name":"Wells Fargo Bank",
    "wof:placetype":"venue"
},
  "geometry": {"coordinates":[-105.87572900000001,33.64329],"type":"Point"}
}