{
  "type": "Feature",
  "properties": {
    "addr:full":"225 Kit Carson Rd Taos NM 87571",
    "addr:housenumber":"225",
    "addr:postcode":"87571",
    "addr:street":"Kit Carson Rd",
    "iso:country":"US",
    "sg:address":"225 Kit Carson Rd",
    "sg:city":"Taos",
    "sg:classifiers":[
        {
            "category":"Shopping",
            "type":"Retail Goods"
        }
    ],
    "sg:phone":"+1 505 737 9600",
    "sg:postcode":"87571",
    "sg:province":"NM",
    "sg:tags":[
        "art",
        "gallery",
        "dealer"
    ],
    "wof:name":"Jerry Mann Gallery",
    "wof:placetype":"venue"
},
  "geometry": {"coordinates":[-105.56908199999999,36.402935],"type":"Point"}
}