{
  "type": "Feature",
  "properties": {
    "addr:full":"463 Petree Rd Hagerman NM 88232",
    "addr:housenumber":"463",
    "addr:postcode":"88232",
    "addr:street":"Petree Rd",
    "iso:country":"US",
    "sg:address":"463 Petree Rd",
    "sg:city":"Hagerman",
    "sg:classifiers":[
        {
            "category":"Freight",
            "type":"Transportation"
        }
    ],
    "sg:phone":"+1 505 752 7770",
    "sg:postcode":"88232",
    "sg:province":"NM",
    "wof:name":"NNN Transportation Inc",
    "wof:placetype":"venue"
},
  "geometry": {"coordinates":[-104.35449300000001,33.088552],"type":"Point"}
}