{
  "type": "Feature",
  "properties": {
    "addr:full":"515 Ash St SE Albuquerque NM 87106",
    "addr:housenumber":"515",
    "addr:postcode":"87106",
    "addr:street":"Ash St Se",
    "iso:country":"US",
    "sg:address":"515 Ash St SE",
    "sg:city":"Albuquerque",
    "sg:classifiers":[
        {
            "category":"Place Of Worship",
            "subcategory":"Church",
            "type":"Public Place"
        },
        {
            "category":"Place Of Worship",
            "type":"Public Place"
        }
    ],
    "sg:phone":"+1 505 242 8928",
    "sg:postcode":"87106",
    "sg:province":"NM",
    "sg:tags":[
        "churches-baptist-general",
        "churches-baptist"
    ],
    "wof:name":"Fellowship Mssionary Baptst Ch",
    "wof:placetype":"venue"
},
  "geometry": {"coordinates":[-106.629935,35.077318],"type":"Point"}
}