{
  "type": "Feature",
  "properties": {
    "iso:country":"US",
    "sg:address":"1613 S Love St",
    "sg:city":"Lovington",
    "sg:classifiers":[
        {
            "category":"Organizations",
            "subcategory":"Religious Organization",
            "type":"Services"
        }
    ],
    "sg:phone":"+1 505 396 3959",
    "sg:postcode":"88260",
    "sg:province":"NM",
    "wof:name":"Revival Center Church",
    "wof:placetype":"venue"
},
  "geometry": {"coordinates":[-103.347267,32.932515],"type":"Point"}
}