{
  "type": "Feature",
  "properties": {
    "iso:country":"US",
    "sg:address":"1730 Lomas Blvd NW",
    "sg:city":"Albuquerque",
    "sg:classifiers":[
        {
            "category":"Education",
            "subcategory":"College",
            "type":"Public Place"
        }
    ],
    "sg:phone":"+1 505 277 6947",
    "sg:postcode":"87104",
    "sg:province":"NM",
    "sg:tags":[
        "academic",
        "school"
    ],
    "wof:name":"University-New Mexico Human Re",
    "wof:placetype":"venue"
},
  "geometry": {"coordinates":[-106.664967,35.092913],"type":"Point"}
}