{
  "type": "Feature",
  "properties": {
    "addr:full":"20967 US Hwy 84 Abiquiu NM 87510",
    "addr:postcode":"20967;87510",
    "addr:street":"Us Hwy 84",
    "iso:country":"US",
    "sg:address":"20967 US Hwy 84",
    "sg:city":"Abiquiu",
    "sg:classifiers":[
        {
            "category":"Food & Beverages",
            "subcategory":"Groceries & Convenience Stores",
            "type":"Retail Goods"
        }
    ],
    "sg:phone":"+1 505 685 4666",
    "sg:postcode":"87510",
    "sg:province":"NM",
    "wof:name":"Trujillos Store",
    "wof:placetype":"venue"
},
  "geometry": {"coordinates":[-106.299914,36.209064],"type":"Point"}
}