{
  "type": "Feature",
  "properties": {
    "iso:country":"US",
    "sg:address":"1148 W Marland St",
    "sg:city":"Hobbs",
    "sg:classifiers":[
        {
            "category":"Building & Trades",
            "subcategory":"Plumbing",
            "type":"Services"
        }
    ],
    "sg:phone":"+1 505 393 8833",
    "sg:postcode":"88240",
    "sg:province":"NM",
    "sg:tags":[
        "cooling",
        "tower"
    ],
    "wof:name":"Cooling Tower Maintenance",
    "wof:placetype":"venue"
},
  "geometry": {"coordinates":[-103.151422,32.696687],"type":"Point"}
}