{
  "type": "Feature",
  "properties": {
    "addr:full":"504 S Hull St Clovis NM 88101",
    "addr:housenumber":"504",
    "addr:postcode":"88101",
    "addr:street":"S Hull St",
    "iso:country":"US",
    "sg:address":"504 S Hull St",
    "sg:city":"Clovis",
    "sg:classifiers":[
        {
            "category":"Wholesale",
            "subcategory":"Farm Supplies",
            "type":"Manufacturing & Wholesale Goods"
        }
    ],
    "sg:phone":"+1 505 762 4422",
    "sg:postcode":"88101",
    "sg:province":"NM",
    "sg:tags":[
        "auction",
        "livestock",
        "market"
    ],
    "wof:name":"Clovis Livestock Auction Inc",
    "wof:placetype":"venue"
},
  "geometry": {"coordinates":[-103.22058699999999,34.392802],"type":"Point"}
}