{
  "type": "Feature",
  "properties": {
    "addr:full":"130 Louisiana Blvd NE Albuquerque NM 87108",
    "addr:housenumber":"130",
    "addr:postcode":"87108",
    "addr:street":"Louisiana Blvd Ne",
    "iso:country":"US",
    "sg:address":"130 Louisiana Blvd NE",
    "sg:city":"Albuquerque",
    "sg:classifiers":[
        {
            "category":"Wholesale",
            "subcategory":"Jewelry",
            "type":"Manufacturing & Wholesale Goods"
        }
    ],
    "sg:phone":"+1 505 266 2323",
    "sg:postcode":"87108",
    "sg:province":"NM",
    "sg:tags":[
        "stone"
    ],
    "wof:name":"Candice Jewelry",
    "wof:placetype":"venue"
},
  "geometry": {"coordinates":[-106.568522,35.07746],"type":"Point"}
}