{
  "type": "Feature",
  "properties": {
    "iso:country":"US",
    "sg:address":"1327 US Hwy 84",
    "sg:city":"Clovis",
    "sg:classifiers":[
        {
            "category":"Freight",
            "type":"Transportation"
        }
    ],
    "sg:phone":"+1 505 762 4531",
    "sg:postcode":"88101",
    "sg:province":"NM",
    "sg:tags":[
        "grain",
        "elevator"
    ],
    "wof:name":"Peavey Co",
    "wof:placetype":"venue"
},
  "geometry": {"coordinates":[-103.258366,34.404849],"type":"Point"}
}