{
  "type": "Feature",
  "properties": {
    "iso:country":"US",
    "sg:address":"9720 Mesa Arriba Ave NE",
    "sg:city":"Albuquerque",
    "sg:classifiers":[
        {
            "category":"Home & Garden",
            "subcategory":"Building Materials",
            "type":"Retail Goods"
        }
    ],
    "sg:phone":"+1 505 292 8349",
    "sg:postcode":"87111",
    "sg:province":"NM",
    "wof:name":"Clay Objects",
    "wof:placetype":"venue"
},
  "geometry": {"coordinates":[-106.529743,35.119299],"type":"Point"}
}