{
  "type": "Feature",
  "properties": {
    "iso:country":"US",
    "sg:address":"1099 State Rd 267",
    "sg:city":"Melrose",
    "sg:classifiers":[
        {
            "category":"Professional",
            "type":"Services"
        }
    ],
    "sg:phone":"+1 505 253 4381",
    "sg:postcode":"88124",
    "sg:province":"NM",
    "sg:tags":[
        "merchandise"
    ],
    "wof:name":"Bar X7 Brands",
    "wof:placetype":"venue"
},
  "geometry": {"coordinates":[-103.616951,34.402586],"type":"Point"}
}