{
  "type": "Feature",
  "properties": {
    "iso:country":"US",
    "sg:address":"9501 E US Hwy 70",
    "sg:city":"Las Cruces",
    "sg:classifiers":[
        {
            "category":"Building & Trades",
            "subcategory":"Construction",
            "type":"Services"
        }
    ],
    "sg:phone":"+1 505 382 1484",
    "sg:postcode":"88012",
    "sg:province":"NM",
    "sg:tags":[
        "project"
    ],
    "wof:name":"Mountain Top Enterprise",
    "wof:placetype":"venue"
},
  "geometry": {"coordinates":[-106.643573,32.409821],"type":"Point"}
}