{
  "type": "Feature",
  "properties": {
    "iso:country":"US",
    "sg:address":"3735 Arno St NE",
    "sg:city":"Albuquerque",
    "sg:classifiers":[
        {
            "category":"Professional",
            "subcategory":"Management & Consulting",
            "type":"Services"
        }
    ],
    "sg:phone":"+1 505 345 3404",
    "sg:postcode":"87107",
    "sg:province":"NM",
    "sg:tags":[
        "break",
        "coffee",
        "supply"
    ],
    "wof:name":"Aramark Refreshment Svc",
    "wof:placetype":"venue"
},
  "geometry": {"coordinates":[-106.63643,35.119342],"type":"Point"}
}