{
  "type": "Feature",
  "properties": {
    "iso:country":"US",
    "sg:address":"600 Rembert Trl SW",
    "sg:city":"Albuquerque",
    "sg:classifiers":[
        {
            "category":"Home & Garden",
            "subcategory":"Hardware",
            "type":"Retail Goods"
        },
        {
            "category":"Manufacturing",
            "subcategory":"Electronics",
            "type":"Manufacturing & Wholesale Goods"
        }
    ],
    "sg:phone":"+1 505 235 5613",
    "sg:postcode":"87121",
    "sg:province":"NM",
    "sg:tags":[
        "measuring",
        "instrument",
        "device",
        "electronic"
    ],
    "wof:name":"Aaa Calibration Equipment Specialist Inc.",
    "wof:placetype":"venue"
},
  "geometry": {"coordinates":[-106.724297,35.067219],"type":"Point"}
}