{
  "type": "Feature",
  "properties": {
    "iso:country":"US",
    "sg:address":"11 Chambon Rd",
    "sg:city":"Lemitar",
    "sg:classifiers":[
        {
            "category":"Restaurant",
            "type":"Food & Drink"
        }
    ],
    "sg:phone":"+1 505 838 2003",
    "sg:postcode":"87823",
    "sg:province":"NM",
    "sg:tags":[
        "shop",
        "coffee"
    ],
    "wof:name":"Moonspinners Coffee House",
    "wof:placetype":"venue"
},
  "geometry": {"coordinates":[-106.91235,34.160971],"type":"Point"}
}