{
  "type": "Feature",
  "properties": {
    "iso:country":"US",
    "sg:address":"4301 National Parks Hwy",
    "sg:city":"Carlsbad",
    "sg:classifiers":[
        {
            "category":"Travel",
            "subcategory":"Campground",
            "type":"Entertainment"
        }
    ],
    "sg:phone":"+1 505 885 6333",
    "sg:postcode":"88220",
    "sg:province":"NM",
    "wof:name":"Carlsbad Campgrounds",
    "wof:placetype":"venue"
},
  "geometry": {"coordinates":[-104.235383,32.365925],"type":"Point"}
}