{
  "type": "Feature",
  "properties": {
    "iso:country":"US",
    "sg:address":"2906 Juan Tabo Blvd NE",
    "sg:city":"Albuquerque",
    "sg:classifiers":[
        {
            "category":"Restaurant",
            "type":"Food & Drink"
        }
    ],
    "sg:menulink":"http://www.allmenus.com/nm/albuquerque/31562-king-tut-restaurant/menu/",
    "sg:phone":"+1 505 292 8100",
    "sg:postcode":"87112",
    "sg:province":"NM",
    "sg:tags":[
        "japanese",
        "asian"
    ],
    "wof:name":"King Tut Restaurant",
    "wof:placetype":"venue"
},
  "geometry": {"coordinates":[-106.51557200000001,35.115227],"type":"Point"}
}