{
  "type": "Feature",
  "properties": {
    "addr:full":"2821 N Telshor Blvd Las Cruces NM 88011",
    "addr:housenumber":"2821",
    "addr:postcode":"88011",
    "addr:street":"N Telshor Blvd",
    "iso:country":"US",
    "sg:address":"2821 N Telshor Blvd",
    "sg:city":"Las Cruces",
    "sg:classifiers":[
        {
            "category":"Personal",
            "subcategory":"Tanning Parlor",
            "type":"Services"
        }
    ],
    "sg:phone":"+1 505 521 7500",
    "sg:postcode":"88011",
    "sg:province":"NM",
    "sg:tags":[
        "salon"
    ],
    "wof:name":"Hot Pepper Tanning Co",
    "wof:placetype":"venue"
},
  "geometry": {"coordinates":[-106.763924,32.350338],"type":"Point"}
}