{
  "type": "Feature",
  "properties": {
    "iso:country":"US",
    "sg:address":"1415 S 1st St",
    "sg:city":"Clayton",
    "sg:classifiers":[
        {
            "category":"Government",
            "subcategory":"Fire Station",
            "type":"Public Place"
        }
    ],
    "sg:phone":"+1 505 374 0922",
    "sg:postcode":"88415",
    "sg:province":"NM",
    "sg:tags":[
        "department"
    ],
    "wof:name":"Rabbit Ear Fire Dept Non",
    "wof:placetype":"venue"
},
  "geometry": {"coordinates":[-103.176078,36.438214],"type":"Point"}
}