{
  "type": "Feature",
  "properties": {
    "iso:country":"US",
    "sg:address":"1620 Parkview Rd",
    "sg:city":"Las Vegas",
    "sg:classifiers":[
        {
            "category":"Insurance",
            "subcategory":"Life Insurance",
            "type":"Services"
        }
    ],
    "sg:phone":"+1 505 454 0641",
    "sg:postcode":"87701",
    "sg:province":"NM",
    "sg:tags":[
        "carrier"
    ],
    "wof:name":"Capital Choice Financial Svcs",
    "wof:placetype":"venue"
},
  "geometry": {"coordinates":[-105.222202,35.608028],"type":"Point"}
}