{
  "type": "Feature",
  "properties": {
    "iso:country":"US",
    "sg:address":"505 Richmond Dr SE",
    "sg:city":"Albuquerque",
    "sg:classifiers":[
        {
            "category":"Professional",
            "subcategory":"Computer Services",
            "type":"Services"
        }
    ],
    "sg:phone":"+1 505 266 2661",
    "sg:postcode":"87106",
    "sg:province":"NM",
    "sg:tags":[
        "datum"
    ],
    "wof:name":"Splork Web Design",
    "wof:placetype":"venue"
},
  "geometry": {"coordinates":[-106.61090299999999,35.073169],"type":"Point"}
}