{
  "type": "Feature",
  "properties": {
    "iso:country":"US",
    "sg:address":"9311 Coors Blvd NW",
    "sg:city":"Albuquerque",
    "sg:classifiers":[
        {
            "category":"Shopping",
            "subcategory":"Gifts & Souvenirs",
            "type":"Retail Goods"
        }
    ],
    "sg:phone":"+1 505 898 4808",
    "sg:postcode":"87114",
    "sg:province":"NM",
    "sg:tags":[
        "indian"
    ],
    "sg:website":"www.theenchantedsouthwest.com",
    "wof:name":"Enchanted Southwest",
    "wof:placetype":"venue"
},
  "geometry": {"coordinates":[-106.667511,35.18143],"type":"Point"}
}