{
  "type": "Feature",
  "properties": {
    "iso:country":"US",
    "sg:address":"909 N Alameda Blvd",
    "sg:city":"Las Cruces",
    "sg:classifiers":[
        {
            "category":"Communications",
            "type":"Services"
        }
    ],
    "sg:phone":"+1 505 524 2675",
    "sg:postcode":"88005",
    "sg:province":"NM",
    "sg:tags":[
        "internet"
    ],
    "sg:website":"www.eznett.net",
    "wof:name":"INTERNETSOLUTIONSINC.NET",
    "wof:placetype":"venue"
},
  "geometry": {"coordinates":[-106.784215,32.317735],"type":"Point"}
}