{
  "type": "Feature",
  "properties": {
    "iso:country":"US",
    "sg:address":"2306 Morris St NE",
    "sg:city":"Albuquerque",
    "sg:classifiers":[
        {
            "category":"Building & Trades",
            "subcategory":"Electrical",
            "type":"Services"
        }
    ],
    "sg:phone":"+1 505 299 4730",
    "sg:postcode":"87112",
    "sg:province":"NM",
    "sg:tags":[
        "electric",
        "contractor"
    ],
    "wof:name":"DAC",
    "wof:placetype":"venue"
},
  "geometry": {"coordinates":[-106.524418,35.108813],"type":"Point"}
}