{
  "type": "Feature",
  "properties": {
    "addr:full":"1500 Veranda Dr SE Albuquerque NM 87124",
    "addr:housenumber":"1500",
    "addr:postcode":"87124",
    "addr:street":"Veranda Dr Se",
    "iso:country":"US",
    "sg:address":"1500 Veranda Dr SE",
    "sg:city":"Albuquerque",
    "sg:classifiers":[
        {
            "category":"Education",
            "subcategory":"School",
            "type":"Public Place"
        }
    ],
    "sg:phone":"+1 505 994 0229",
    "sg:postcode":"87124",
    "sg:province":"NM",
    "sg:website":"www.rrps.com",
    "wof:name":"Cordoba Elementary School",
    "wof:placetype":"venue"
},
  "geometry": {"coordinates":[-106.697216,35.233394],"type":"Point"}
}