{
  "type": "Feature",
  "properties": {
    "addr:full":"1517 Aragon Rd SW Albuquerque NM 87105",
    "addr:housenumber":"1517",
    "addr:postcode":"87105",
    "addr:street":"Aragon Rd Sw",
    "iso:country":"US",
    "sg:address":"1517 Aragon Rd SW",
    "sg:city":"Albuquerque",
    "sg:classifiers":[
        {
            "category":"Building & Trades",
            "subcategory":"Cleaning & Sanitation",
            "type":"Services"
        }
    ],
    "sg:phone":"+1 505 873 3770",
    "sg:postcode":"87105",
    "sg:province":"NM",
    "sg:tags":[
        "maintenance"
    ],
    "wof:name":"C & M Cleaning Services Inc",
    "wof:placetype":"venue"
},
  "geometry": {"coordinates":[-106.697301,35.0564],"type":"Point"}
}