{
  "type": "Feature",
  "properties": {
    "iso:country":"US",
    "sg:address":"709 S Ohio Ave",
    "sg:city":"Roswell",
    "sg:classifiers":[
        {
            "category":"Building & Trades",
            "subcategory":"Plumbing",
            "type":"Services"
        }
    ],
    "sg:phone":"+1 505 623 1454",
    "sg:postcode":"88203",
    "sg:province":"NM",
    "sg:tags":[
        "plumbing",
        "contractor"
    ],
    "wof:name":"Leo's Plumbing & Heating",
    "wof:placetype":"venue"
},
  "geometry": {"coordinates":[-104.538892,33.386611],"type":"Point"}
}