{
  "type": "Feature",
  "properties": {
    "addr:full":"2701 2nd St NW Albuquerque NM 87107",
    "addr:housenumber":"2701",
    "addr:postcode":"87107",
    "addr:street":"2Nd St Nw",
    "iso:country":"US",
    "sg:address":"2701 2nd St NW",
    "sg:city":"Albuquerque",
    "sg:classifiers":[
        {
            "category":"Wholesale",
            "subcategory":"Scrap",
            "type":"Manufacturing & Wholesale Goods"
        }
    ],
    "sg:phone":"+1 505 345 8005",
    "sg:postcode":"87107",
    "sg:province":"NM",
    "sg:tags":[
        "recycling",
        "center"
    ],
    "wof:name":"Wise Recycling",
    "wof:placetype":"venue"
},
  "geometry": {"coordinates":[-106.643862,35.112468],"type":"Point"}
}