{
  "type": "Feature",
  "properties": {
    "addr:full":"29 Rd 5500 Bloomfield NM 87413",
    "addr:housenumber":"29",
    "addr:postcode":"5500;87413",
    "addr:street":"Rd",
    "iso:country":"US",
    "sg:address":"29 Rd 5500",
    "sg:city":"Bloomfield",
    "sg:classifiers":[
        {
            "category":"Government",
            "subcategory":"Fire Station",
            "type":"Public Place"
        }
    ],
    "sg:phone":"+1 505 632 8444",
    "sg:postcode":"87413",
    "sg:province":"NM",
    "sg:tags":[
        "county",
        "protection"
    ],
    "wof:name":"San Juan County Fire Dept",
    "wof:placetype":"venue"
},
  "geometry": {"coordinates":[-108.095733,36.697663],"type":"Point"}
}