{
  "type": "Feature",
  "properties": {
    "addr:full":"760 W Picacho Ave Las Cruces NM 88005",
    "addr:housenumber":"760",
    "addr:postcode":"88005",
    "addr:street":"W Picacho Ave",
    "iso:country":"US",
    "sg:address":"760 W Picacho Ave",
    "sg:city":"Las Cruces",
    "sg:classifiers":[
        {
            "category":"Organizations",
            "subcategory":"Professional Association",
            "type":"Services"
        }
    ],
    "sg:phone":"+1 505 524 1968",
    "sg:postcode":"88005",
    "sg:province":"NM",
    "sg:tags":[
        "chambers",
        "commerce"
    ],
    "wof:name":"Las Cruces Chamber Of Commerce",
    "wof:placetype":"venue"
},
  "geometry": {"coordinates":[-106.789106,32.315071],"type":"Point"}
}