{
  "type": "Feature",
  "properties": {
    "addr:full":"1229 Cll de Comercio Santa Fe NM 87507",
    "addr:housenumber":"1229",
    "addr:postcode":"87507",
    "addr:street":"Cll De Comercio",
    "iso:country":"US",
    "sg:address":"1229 Cll de Comercio",
    "sg:city":"Santa Fe",
    "sg:classifiers":[
        {
            "category":"Retail",
            "subcategory":"Auto Repair",
            "type":"Services"
        }
    ],
    "sg:phone":"+1 505 471 3399",
    "sg:postcode":"87507",
    "sg:province":"NM",
    "sg:tags":[
        "repairing",
        "automobile"
    ],
    "wof:name":"Bill's European Automotive Rpr",
    "wof:placetype":"venue"
},
  "geometry": {"coordinates":[-105.989396,35.661544],"type":"Point"}
}