{
  "type": "Feature",
  "properties": {
    "iso:country":"US",
    "sg:address":"5526 Compadre Ct NE",
    "sg:city":"Albuquerque",
    "sg:classifiers":[
        {
            "category":"Utilities",
            "subcategory":"Water",
            "type":"Services"
        }
    ],
    "sg:phone":"+1 505 822 0296",
    "sg:postcode":"87111",
    "sg:province":"NM",
    "sg:tags":[
        "supply"
    ],
    "wof:name":"Marywell Water Association",
    "wof:placetype":"venue"
},
  "geometry": {"coordinates":[-106.53171,35.145154],"type":"Point"}
}