{
  "type": "Feature",
  "properties": {
    "iso:country":"US",
    "sg:address":"312 W Broadway St",
    "sg:city":"Silver City",
    "sg:classifiers":[
        {
            "category":"Museum",
            "type":"Entertainment"
        }
    ],
    "sg:phone":"+1 505 388 5721",
    "sg:postcode":"88061",
    "sg:province":"NM",
    "sg:tags":[
        "gallery"
    ],
    "wof:name":"Silver City Museum Society",
    "wof:placetype":"venue"
},
  "geometry": {"coordinates":[-108.278612,32.770018],"type":"Point"}
}