{
  "type": "Feature",
  "properties": {
    "addr:city":"Silver City",
    "addr:full":"312 W Broadway Silver City, Nm 88061",
    "addr:house_number":"312",
    "addr:housenumber":"312",
    "addr:phone":"+1 575-538-5921",
    "addr:postcode":"88061",
    "addr:road":"W Broadway",
    "addr:state":"NM",
    "addr:street":"W Broadway St",
    "iso:country":"US",
    "sg:address":"312 W Broadway St",
    "sg:city":"Silver City",
    "sg:classifiers":[
        {
            "category":"Museum",
            "type":"Entertainment"
        }
    ],
    "sg:phone":"+1 505 388 5721",
    "sg:postcode":"88061",
    "sg:province":"NM",
    "sg:tags":[
        "gallery"
    ],
    "wof:name":"Silver City Museum",
    "wof:placetype":"venue"
},
  "geometry": {"coordinates":[-108.27795999999999,32.76997],"type":"Point"}
}