{
  "type": "Feature",
  "properties": {
    "iso:country":"US",
    "sg:address":"105 E Palace Ave",
    "sg:city":"Santa Fe",
    "sg:classifiers":[
        {
            "category":"Shopping",
            "subcategory":"Jewelry",
            "type":"Retail Goods"
        }
    ],
    "sg:phone":"+1 505 983 2657",
    "sg:postcode":"87501",
    "sg:province":"NM",
    "sg:tags":[
        "made",
        "custom"
    ],
    "wof:name":"Lewallen Ross Jewelry",
    "wof:placetype":"venue"
},
  "geometry": {"coordinates":[-105.93674,35.687403],"type":"Point"}
}