{
  "type": "Feature",
  "properties": {
    "addr:full":"5341 Wyoming Blvd NE Albuquerque NM 87109",
    "addr:housenumber":"5341",
    "addr:postcode":"87109",
    "addr:street":"Wyoming;Ne",
    "iso:country":"US",
    "sg:address":"5341 Wyoming Blvd NE",
    "sg:city":"Albuquerque",
    "sg:classifiers":[
        {
            "category":"Health Services",
            "subcategory":"Optometrist",
            "type":"Services"
        }
    ],
    "sg:phone":"+1 505 821 8333",
    "sg:postcode":"87109",
    "sg:province":"NM",
    "wof:name":"Eye Care For You PC",
    "wof:placetype":"venue"
},
  "geometry": {"coordinates":[-106.551147,35.140725],"type":"Point"}
}