{
  "type": "Feature",
  "properties": {
    "addr:full":"614 N Dustin Ave Farmington NM 87401",
    "addr:housenumber":"614",
    "addr:postcode":"87401",
    "addr:street":"N Dustin Ave",
    "iso:country":"US",
    "sg:address":"614 N Dustin Ave",
    "sg:city":"Farmington",
    "sg:classifiers":[
        {
            "category":"Freight",
            "type":"Transportation"
        }
    ],
    "sg:phone":"+1 505 324 0332",
    "sg:postcode":"87401",
    "sg:province":"NM",
    "sg:tags":[
        "field",
        "oil",
        "hauling"
    ],
    "wof:name":"Overright Trucking Inc",
    "wof:placetype":"venue"
},
  "geometry": {"coordinates":[-108.202325,36.73611],"type":"Point"}
}