{
  "type": "Feature",
  "properties": {
    "iso:country":"US",
    "sg:address":"301 Panorama Blvd",
    "sg:city":"Alamogordo",
    "sg:classifiers":[
        {
            "category":"Real Estate",
            "subcategory":"Real Estate Operator",
            "type":"Services"
        }
    ],
    "sg:phone":"+1 505 437 2300",
    "sg:postcode":"88310",
    "sg:province":"NM",
    "sg:tags":[
        "apartment"
    ],
    "wof:name":"Hunters Ridge Apts",
    "wof:placetype":"venue"
},
  "geometry": {"coordinates":[-105.956227,32.876103],"type":"Point"}
}