{
  "type": "Feature",
  "properties": {
    "iso:country":"US",
    "sg:address":"501 5th St NW",
    "sg:city":"Albuquerque",
    "sg:classifiers":[
        {
            "category":"Education",
            "subcategory":"Special Training",
            "type":"Public Place"
        }
    ],
    "sg:phone":"+1 505 244 1972",
    "sg:postcode":"87102",
    "sg:province":"NM",
    "sg:tags":[
        "instruction",
        "driving"
    ],
    "wof:name":"Teen USA Driving School",
    "wof:placetype":"venue"
},
  "geometry": {"coordinates":[-106.651778,35.090289],"type":"Point"}
}