{
  "type": "Feature",
  "properties": {
    "iso:country":"US",
    "sg:address":"3 Jemez Trl S",
    "sg:city":"Corrales",
    "sg:classifiers":[
        {
            "category":"Real Estate",
            "subcategory":"Real Estate Agent",
            "type":"Services"
        }
    ],
    "sg:phone":"+1 505 994 2294",
    "sg:postcode":"87048",
    "sg:province":"NM",
    "wof:name":"New Mexico Real Estate",
    "wof:placetype":"venue"
},
  "geometry": {"coordinates":[-106.650481,35.220327],"type":"Point"}
}