{
  "type": "Feature",
  "properties": {
    "iso:country":"US",
    "sg:address":"110 2nd St SW",
    "sg:city":"Albuquerque",
    "sg:classifiers":[
        {
            "category":"Professional",
            "subcategory":"Lawyer & Legal Services",
            "type":"Services"
        }
    ],
    "sg:phone":"+1 505 843 9635",
    "sg:postcode":"87102",
    "sg:province":"NM",
    "sg:tags":[
        "attorney"
    ],
    "wof:name":"David J Alderete Law Office",
    "wof:placetype":"venue"
},
  "geometry": {"coordinates":[-106.649342,35.083348],"type":"Point"}
}