{
  "type": "Feature",
  "properties": {
    "iso:country":"US",
    "sg:address":"42405 US Hwy 70",
    "sg:city":"Portales",
    "sg:classifiers":[
        {
            "category":"Banks & Credit Unions",
            "subcategory":"Bank",
            "type":"Services"
        }
    ],
    "sg:phone":"+1 505 359 2811",
    "sg:postcode":"88130",
    "sg:province":"NM",
    "sg:tags":[
        "loan"
    ],
    "wof:name":"A & A Title Loans",
    "wof:placetype":"venue"
},
  "geometry": {"coordinates":[-103.326086,34.196571],"type":"Point"}
}