{
  "type": "Feature",
  "properties": {
    "iso:country":"US",
    "sg:address":"3120 Bridge Blvd SW",
    "sg:city":"Albuquerque",
    "sg:classifiers":[
        {
            "category":"Manufacturing",
            "subcategory":"Signs",
            "type":"Manufacturing & Wholesale Goods"
        }
    ],
    "sg:phone":"+1 505 765 5656",
    "sg:postcode":"87121",
    "sg:province":"NM",
    "wof:name":"Affordable Signs",
    "wof:placetype":"venue"
},
  "geometry": {"coordinates":[-106.704342,35.068622],"type":"Point"}
}