{
  "type": "Feature",
  "properties": {
    "addr:full":"316 W Bender Blvd Hobbs NM 88240",
    "addr:housenumber":"316",
    "addr:postcode":"88240",
    "addr:street":"W Bender Blvd",
    "iso:country":"US",
    "sg:address":"316 W Bender Blvd",
    "sg:city":"Hobbs",
    "sg:classifiers":[
        {
            "category":"Retail",
            "subcategory":"Repair Shop",
            "type":"Services"
        },
        {
            "category":"Shopping",
            "subcategory":"Jewelry",
            "type":"Retail Goods"
        }
    ],
    "sg:phone":"+1 505 392 2020",
    "sg:postcode":"88240",
    "sg:province":"NM",
    "sg:tags":[
        "precious",
        "designer",
        "metal",
        "mfg"
    ],
    "wof:name":"Jerb's Custom Jewelry",
    "wof:placetype":"venue"
},
  "geometry": {"coordinates":[-103.13870900000001,32.725699],"type":"Point"}
}