{
  "type": "Feature",
  "properties": {
    "addr:full":"701 N Riverside Dr Espanola NM 87532",
    "addr:housenumber":"701",
    "addr:postcode":"87532",
    "addr:street":"N Riverside Dr",
    "iso:country":"US",
    "sg:address":"701 N Riverside Dr",
    "sg:city":"Espanola",
    "sg:classifiers":[
        {
            "category":"Restaurant",
            "type":"Food & Drink"
        }
    ],
    "sg:menulink":"http://www.allmenus.com/nm/santa-fe-north/169700-burger-king/menu/",
    "sg:phone":"+1 505 753 2970",
    "sg:postcode":"87532",
    "sg:province":"NM",
    "sg:tags":[
        "burger",
        "american"
    ],
    "wof:name":"Burger King",
    "wof:placetype":"venue"
},
  "geometry": {"coordinates":[-106.06458499999999,35.997013],"type":"Point"}
}