{
  "type": "Feature",
  "properties": {
    "addr:full":"228 S Chicago Ave Portales NM 88130",
    "addr:housenumber":"228",
    "addr:postcode":"88130",
    "addr:street":"S Chicago Ave",
    "iso:country":"US",
    "sg:address":"228 S Chicago Ave",
    "sg:city":"Portales",
    "sg:classifiers":[
        {
            "category":"Retail",
            "subcategory":"Auto Repair",
            "type":"Services"
        }
    ],
    "sg:phone":"+1 505 359 0404",
    "sg:postcode":"88130",
    "sg:province":"NM",
    "sg:tags":[
        "repairing",
        "automobile",
        "general"
    ],
    "wof:name":"Doug's Garage",
    "wof:placetype":"venue"
},
  "geometry": {"coordinates":[-103.331185,34.186579],"type":"Point"}
}