{
  "type": "Feature",
  "properties": {
    "iso:country":"US",
    "sg:address":"113 Lincoln Ave",
    "sg:city":"Santa Fe",
    "sg:classifiers":[
        {
            "category":"Museum",
            "type":"Entertainment"
        }
    ],
    "sg:phone":"+1 505 476 5060",
    "sg:postcode":"87501",
    "sg:province":"NM",
    "sg:website":"www.museumofnewmexico.org",
    "wof:name":"State Museum Admin Bldg",
    "wof:placetype":"venue"
},
  "geometry": {"coordinates":[-105.938295,35.688859],"type":"Point"}
}