{
  "type": "Feature",
  "properties": {
    "iso:country":"US",
    "sg:address":"2012 Quail Run Dr NE",
    "sg:city":"Albuquerque",
    "sg:classifiers":[
        {
            "category":"Manufacturing",
            "subcategory":"Apparel",
            "type":"Manufacturing & Wholesale Goods"
        }
    ],
    "sg:phone":"+1 505 856 0700",
    "sg:postcode":"87122",
    "sg:province":"NM",
    "sg:tags":[
        "clothing"
    ],
    "wof:name":"9 Below",
    "wof:placetype":"venue"
},
  "geometry": {"coordinates":[-106.49454299999999,35.168349],"type":"Point"}
}