{
  "type": "Feature",
  "properties": {
    "iso:country":"US",
    "sg:address":"101 Dp Rd",
    "sg:city":"Los Alamos",
    "sg:classifiers":[
        {
            "category":"Building & Trades",
            "subcategory":"Construction",
            "type":"Services"
        }
    ],
    "sg:phone":"+1 505 661 8336",
    "sg:postcode":"87544",
    "sg:province":"NM",
    "sg:tags":[
        "general",
        "contractor"
    ],
    "wof:name":"B & D Industries",
    "wof:placetype":"venue"
},
  "geometry": {"coordinates":[-106.270934,35.876695],"type":"Point"}
}