{
  "type": "Feature",
  "properties": {
    "iso:country":"US",
    "sg:address":"11811 Menaul Blvd NE",
    "sg:city":"Albuquerque",
    "sg:classifiers":[
        {
            "category":"Insurance",
            "subcategory":"Insurance Agent",
            "type":"Services"
        }
    ],
    "sg:phone":"+1 505 292 4814",
    "sg:postcode":"87112",
    "sg:province":"NM",
    "sg:website":"www.priamerica.com",
    "wof:name":"Primerica Financial Svc",
    "wof:placetype":"venue"
},
  "geometry": {"coordinates":[-106.50955,35.108811],"type":"Point"}
}