{
  "type": "Feature",
  "properties": {
    "iso:country":"US",
    "sg:address":"8032 Edith Blvd NE",
    "sg:city":"Albuquerque",
    "sg:classifiers":[
        {
            "category":"Building & Trades",
            "subcategory":"Construction",
            "type":"Services"
        }
    ],
    "sg:phone":"+1 505 898 0061",
    "sg:postcode":"87113",
    "sg:province":"NM",
    "sg:tags":[
        "fire",
        "restoration",
        "damage"
    ],
    "wof:name":"Mac Construction Inc",
    "wof:placetype":"venue"
},
  "geometry": {"coordinates":[-106.61517499999999,35.171684],"type":"Point"}
}