{
  "type": "Feature",
  "properties": {
    "addr:full":"5605 Fairoak Trl NE Albuquerque NM 87109",
    "addr:housenumber":"5605",
    "addr:postcode":"87109",
    "addr:street":"Fairoak Trl Ne",
    "iso:country":"US",
    "sg:address":"5605 Fairoak Trl NE",
    "sg:city":"Albuquerque",
    "sg:classifiers":[
        {
            "category":"Professional",
            "subcategory":"Detective & Security Services",
            "type":"Services"
        }
    ],
    "sg:phone":"+1 505 828 1024",
    "sg:postcode":"87109",
    "sg:province":"NM",
    "sg:tags":[
        "investigator"
    ],
    "sg:website":"www.bauerinvestigation.com",
    "wof:name":"Bauer Investigation",
    "wof:placetype":"venue"
},
  "geometry": {"coordinates":[-106.56082600000001,35.144723],"type":"Point"}
}