{
  "type": "Feature",
  "properties": {
    "addr:full":"602 W Argyle St Hagerman NM 88232",
    "addr:housenumber":"602",
    "addr:postcode":"88232",
    "addr:street":"W Argyle St",
    "iso:country":"US",
    "sg:address":"602 W Argyle St",
    "sg:city":"Hagerman",
    "sg:classifiers":[
        {
            "category":"Building & Trades",
            "subcategory":"Construction",
            "type":"Services"
        }
    ],
    "sg:phone":"+1 505 752 0263",
    "sg:postcode":"88232",
    "sg:province":"NM",
    "sg:tags":[
        "general",
        "contractor"
    ],
    "wof:name":"Munson Construction Co",
    "wof:placetype":"venue"
},
  "geometry": {"coordinates":[-104.33383600000001,33.113978],"type":"Point"}
}