{
  "type": "Feature",
  "properties": {
    "addr:full":"7624 Don Gaspar Dr NE Albuquerque NM 87109",
    "addr:housenumber":"7624",
    "addr:postcode":"87109",
    "addr:street":"Don Gaspar Dr Ne",
    "iso:country":"US",
    "sg:address":"7624 Don Gaspar Dr NE",
    "sg:city":"Albuquerque",
    "sg:classifiers":[
        {
            "category":"Wholesale",
            "subcategory":"Construction Materials",
            "type":"Manufacturing & Wholesale Goods"
        }
    ],
    "sg:phone":"+1 505 798 0662",
    "sg:postcode":"87109",
    "sg:province":"NM",
    "sg:tags":[
        "pipe",
        "article",
        "smoker"
    ],
    "wof:name":"Mighty Quinn",
    "wof:placetype":"venue"
},
  "geometry": {"coordinates":[-106.53704999999999,35.16625],"type":"Point"}
}