{
  "type": "Feature",
  "properties": {
    "iso:country":"US",
    "sg:address":"1313 Eubank Blvd NE",
    "sg:city":"Albuquerque",
    "sg:classifiers":[
        {
            "category":"Shopping",
            "subcategory":"Florist",
            "type":"Retail Goods"
        }
    ],
    "sg:phone":"+1 505 299 9509",
    "sg:postcode":"87112",
    "sg:province":"NM",
    "wof:name":"Savon Cash and Carry",
    "wof:placetype":"venue"
},
  "geometry": {"coordinates":[-106.53278400000001,35.094262],"type":"Point"}
}