{
  "type": "Feature",
  "properties": {
    "iso:country":"US",
    "sg:address":"6000 S Main St",
    "sg:city":"Mesilla Park",
    "sg:classifiers":[
        {
            "category":"Manufacturing",
            "subcategory":"Tools & Machinery",
            "type":"Manufacturing & Wholesale Goods"
        }
    ],
    "sg:phone":"+1 505 526 1411",
    "sg:postcode":"88047",
    "sg:province":"NM",
    "sg:tags":[
        "shop",
        "screw",
        "machined",
        "mills",
        "precision",
        "machine",
        "component"
    ],
    "sg:website":"www.lascrucesmachine.com",
    "wof:name":"Las Cruces Machine Co",
    "wof:placetype":"venue"
},
  "geometry": {"coordinates":[-106.74293,32.237726],"type":"Point"}
}