{
  "type": "Feature",
  "properties": {
    "addr:full":"3109 San Mateo Blvd NE Albuquerque NM 87110",
    "addr:housenumber":"3109",
    "addr:postcode":"87110",
    "addr:street":"San Mateo Blvd Ne",
    "iso:country":"US",
    "sg:address":"3109 San Mateo Blvd NE",
    "sg:city":"Albuquerque",
    "sg:classifiers":[
        {
            "category":"Restaurant",
            "type":"Food & Drink"
        }
    ],
    "sg:menulink":"http://www.allmenus.com/nm/albuquerque/67622-peter-pipers-pizza/menu/",
    "sg:phone":"+1 505 884 1616",
    "sg:postcode":"87110",
    "sg:province":"NM",
    "sg:tags":[
        "american",
        "pizza"
    ],
    "wof:name":"Peter Pipers Pizza",
    "wof:placetype":"venue"
},
  "geometry": {"coordinates":[-106.586494,35.1178],"type":"Point"}
}