{
  "type": "Feature",
  "properties": {
    "addr:full":"1508 N Dal Paso St Hobbs NM 88240",
    "addr:housenumber":"1508",
    "addr:postcode":"88240",
    "addr:street":"N Dal Paso St",
    "iso:country":"US",
    "sg:address":"1508 N Dal Paso St",
    "sg:city":"Hobbs",
    "sg:classifiers":[
        {
            "category":"Organizations",
            "subcategory":"Religious Organization",
            "type":"Services"
        }
    ],
    "sg:phone":"+1 505 397 7661",
    "sg:postcode":"88240",
    "sg:province":"NM",
    "wof:name":"Northside Baptist Church",
    "wof:placetype":"venue"
},
  "geometry": {"coordinates":[-103.12754200000001,32.716176],"type":"Point"}
}