{
  "type": "Feature",
  "properties": {
    "addr:full":"401 N White Sands Blvd Alamogordo NM 88310",
    "addr:housenumber":"401",
    "addr:postcode":"88310",
    "addr:street":"N White Sands Blvd",
    "iso:country":"US",
    "sg:address":"401 N White Sands Blvd",
    "sg:city":"Alamogordo",
    "sg:classifiers":[
        {
            "category":"Retail",
            "subcategory":"Laundry & Dry Cleaning",
            "type":"Services"
        }
    ],
    "sg:phone":"+1 505 434 2527",
    "sg:postcode":"88310",
    "sg:province":"NM",
    "sg:tags":[
        "launderer",
        "garment",
        "industrial",
        "drycleaning"
    ],
    "wof:name":"Comet Cleaners",
    "wof:placetype":"venue"
},
  "geometry": {"coordinates":[-105.96033199999999,32.894895],"type":"Point"}
}