{
  "type": "Feature",
  "properties": {
    "addr:full":"608 E Blanco St Aztec NM 87410",
    "addr:housenumber":"608",
    "addr:postcode":"87410",
    "addr:street":"E Blanco St",
    "iso:country":"US",
    "sg:address":"608 E Blanco St",
    "sg:city":"Aztec",
    "sg:classifiers":[
        {
            "category":"Manufacturing",
            "subcategory":"Tools & Machinery",
            "type":"Manufacturing & Wholesale Goods"
        }
    ],
    "sg:phone":"+1 505 333 2136",
    "sg:postcode":"87410",
    "sg:province":"NM",
    "sg:tags":[
        "clocks"
    ],
    "sg:website":"www.maverickcreations.com",
    "wof:name":"Maverick Creations",
    "wof:placetype":"venue"
},
  "geometry": {"coordinates":[-107.989023,36.821312],"type":"Point"}
}