{
  "type": "Feature",
  "properties": {
    "iso:country":"US",
    "sg:address":"1812 E 20th St",
    "sg:city":"Farmington",
    "sg:classifiers":[
        {
            "category":"Autos & Motor Vehicles",
            "subcategory":"Automobile Sales",
            "type":"Retail Goods"
        }
    ],
    "sg:phone":"+1 505 325 4496",
    "sg:postcode":"87401",
    "sg:province":"NM",
    "sg:tags":[
        "car",
        "used",
        "dealer"
    ],
    "wof:name":"High Desert Truck & Auto Inc",
    "wof:placetype":"venue"
},
  "geometry": {"coordinates":[-108.182136,36.748306],"type":"Point"}
}