{
  "type": "Feature",
  "properties": {
    "iso:country":"US",
    "sg:address":"2329 Wisconsin St NE",
    "sg:city":"Albuquerque",
    "sg:classifiers":[
        {
            "category":"Personal",
            "subcategory":"Beauty Salon",
            "type":"Services"
        }
    ],
    "sg:phone":"+1 505 400 7407",
    "sg:postcode":"87110",
    "sg:province":"NM",
    "wof:name":"Yvonne Rivers Legendary",
    "wof:placetype":"venue"
},
  "geometry": {"coordinates":[-106.552203,35.110514],"type":"Point"}
}