{
  "type": "Feature",
  "properties": {
    "addr:full":"609 Elora Dr Carlsbad NM 88220",
    "addr:housenumber":"609",
    "addr:postcode":"88220",
    "addr:street":"Elora Dr",
    "iso:country":"US",
    "sg:address":"609 Elora Dr",
    "sg:city":"Carlsbad",
    "sg:classifiers":[
        {
            "category":"Mining & Drilling",
            "type":"Manufacturing & Wholesale Goods"
        }
    ],
    "sg:phone":"+1 505 885 6870",
    "sg:postcode":"88220",
    "sg:province":"NM",
    "sg:tags":[
        "crude",
        "production",
        "gas"
    ],
    "wof:name":"Forrest Robert H Jr Oil LLC",
    "wof:placetype":"venue"
},
  "geometry": {"coordinates":[-104.233729,32.44019],"type":"Point"}
}