{
  "type": "Feature",
  "properties": {
    "addr:full":"3343 Will Rogers Dr Santa Rosa NM 88435",
    "addr:housenumber":"3343",
    "addr:postcode":"88435",
    "addr:street":"Will Rogers Dr",
    "iso:country":"US",
    "sg:address":"3343 Will Rogers Dr",
    "sg:city":"Santa Rosa",
    "sg:classifiers":[
        {
            "category":"Travel",
            "subcategory":"Hotels & Motels",
            "type":"Entertainment"
        }
    ],
    "sg:phone":"+1 505 472 5570",
    "sg:postcode":"88435",
    "sg:province":"NM",
    "sg:tags":[
        "operation"
    ],
    "wof:name":"Comfort Inn",
    "wof:placetype":"venue"
},
  "geometry": {"coordinates":[-104.656288,34.946521],"type":"Point"}
}