{
  "type": "Feature",
  "properties": {
    "iso:country":"US",
    "sg:address":"3428 State Hwy 47",
    "sg:city":"Los Lunas",
    "sg:classifiers":[
        {
            "category":"Banks & Credit Unions",
            "subcategory":"Bank",
            "type":"Services"
        }
    ],
    "sg:phone":"+1 505 866 5550",
    "sg:postcode":"87031",
    "sg:province":"NM",
    "sg:tags":[
        "loan",
        "real estate"
    ],
    "wof:name":"Frost Morgage Banking Corp",
    "wof:placetype":"venue"
},
  "geometry": {"coordinates":[-106.702411,34.806385],"type":"Point"}
}