{
  "type": "Feature",
  "properties": {
    "iso:country":"US",
    "sg:address":"5420 Territorial Rd NW",
    "sg:city":"Albuquerque",
    "sg:classifiers":[
        {
            "category":"Recreation",
            "type":"Entertainment"
        }
    ],
    "sg:phone":"+1 505 550 2677",
    "sg:postcode":"87120",
    "sg:province":"NM",
    "sg:tags":[
        "balloon"
    ],
    "wof:name":"Private Balloon Flights",
    "wof:placetype":"venue"
},
  "geometry": {"coordinates":[-106.69959799999999,35.162054],"type":"Point"}
}