{
  "type": "Feature",
  "properties": {
    "iso:country":"US",
    "sg:address":"5008 Holmes Dr",
    "sg:city":"Farmington",
    "sg:classifiers":[
        {
            "category":"Shopping",
            "subcategory":"Gifts & Souvenirs",
            "type":"Retail Goods"
        }
    ],
    "sg:phone":"+1 505 598 0380",
    "sg:postcode":"87402",
    "sg:province":"NM",
    "sg:tags":[
        "craft",
        "art",
        "indian"
    ],
    "wof:name":"Wade Foutz Indian Art",
    "wof:placetype":"venue"
},
  "geometry": {"coordinates":[-108.14512499999999,36.784617],"type":"Point"}
}