{
  "type": "Feature",
  "properties": {
    "iso:country":"US",
    "sg:address":"1409 Monterey Dr",
    "sg:city":"Santa Fe",
    "sg:classifiers":[
        {
            "category":"Education",
            "subcategory":"School",
            "type":"Public Place"
        }
    ],
    "sg:phone":"+1 505 989 5477",
    "sg:postcode":"87505",
    "sg:province":"NM",
    "wof:name":"Kaune Elementary",
    "wof:placetype":"venue"
},
  "geometry": {"coordinates":[-105.96172,35.667982],"type":"Point"}
}