{
  "type": "Feature",
  "properties": {
    "iso:country":"US",
    "sg:address":"1826 E Mojave St",
    "sg:city":"Farmington",
    "sg:classifiers":[
        {
            "category":"Manufacturing",
            "subcategory":"Printing",
            "type":"Manufacturing & Wholesale Goods"
        }
    ],
    "sg:phone":"+1 505 325 7889",
    "sg:postcode":"87401",
    "sg:province":"NM",
    "sg:tags":[
        "commercial"
    ],
    "wof:name":"American Signs",
    "wof:placetype":"venue"
},
  "geometry": {"coordinates":[-108.18411,36.738777],"type":"Point"}
}