{
  "type": "Feature",
  "properties": {
    "iso:country":"US",
    "sg:address":"9926 N Hwy 478",
    "sg:city":"Mesquite",
    "sg:classifiers":[
        {
            "category":"Professional",
            "type":"Services"
        }
    ],
    "sg:phone":"+1 505 233 3148",
    "sg:postcode":"88048",
    "sg:province":"NM",
    "sg:tags":[
        "establishment"
    ],
    "wof:name":"Cervantes Enterprises",
    "wof:placetype":"venue"
},
  "geometry": {"coordinates":[-106.67531099999999,32.131224],"type":"Point"}
}