{
  "type": "Feature",
  "properties": {
    "addr:full":"1100 New York Ave Alamogordo NM 88310",
    "addr:housenumber":"1100",
    "addr:postcode":"88310",
    "addr:street":"New York Ave",
    "iso:country":"US",
    "sg:address":"1100 New York Ave",
    "sg:city":"Alamogordo",
    "sg:classifiers":[
        {
            "category":"Banks & Credit Unions",
            "subcategory":"Financial Services",
            "type":"Services"
        }
    ],
    "sg:phone":"+1 505 437 2214",
    "sg:postcode":"88310",
    "sg:province":"NM",
    "sg:tags":[
        "company",
        "holding"
    ],
    "wof:name":"Griggs Holdings",
    "wof:placetype":"venue"
},
  "geometry": {"coordinates":[-105.959034,32.901975],"type":"Point"}
}