{
  "type": "Feature",
  "properties": {
    "addr:full":"1034 Agua Fria St Santa Fe NM 87501",
    "addr:housenumber":"1034",
    "addr:postcode":"87501",
    "addr:street":"Agua Fria St",
    "iso:country":"US",
    "sg:address":"1034 Agua Fria St",
    "sg:city":"Santa Fe",
    "sg:classifiers":[
        {
            "category":"Professional",
            "type":"Services"
        }
    ],
    "sg:phone":"+1 505 820 7909",
    "sg:postcode":"87501",
    "sg:province":"NM",
    "sg:tags":[
        "arts",
        "artist"
    ],
    "wof:name":"Ateliers Inc",
    "wof:placetype":"venue"
},
  "geometry": {"coordinates":[-105.957908,35.683358],"type":"Point"}
}