{
  "type": "Feature",
  "properties": {
    "iso:country":"US",
    "sg:address":"95 Vis del Oro",
    "sg:city":"Cerrillos",
    "sg:classifiers":[
        {
            "category":"Shopping",
            "subcategory":"Computers & Home Electronics",
            "type":"Retail Goods"
        }
    ],
    "sg:phone":"+1 505 424 9333",
    "sg:postcode":"87010",
    "sg:province":"NM",
    "sg:tags":[
        "high",
        "fidelity",
        "stereophonic"
    ],
    "wof:name":"Absolute Audio",
    "wof:placetype":"venue"
},
  "geometry": {"coordinates":[-106.134833,35.363408],"type":"Point"}
}