{
  "type": "Feature",
  "properties": {
    "addr:full":"2920 Stanford Dr NE Albuquerque NM 87107",
    "addr:housenumber":"2920",
    "addr:postcode":"87107",
    "addr:street":"Stanford Dr Ne",
    "iso:country":"US",
    "sg:address":"2920 Stanford Dr NE",
    "sg:city":"Albuquerque",
    "sg:classifiers":[
        {
            "category":"Building & Trades",
            "subcategory":"Plumbing",
            "type":"Services"
        }
    ],
    "sg:phone":"+1 505 833 4333",
    "sg:postcode":"87107",
    "sg:province":"NM",
    "sg:tags":[
        "plumbing",
        "contractor"
    ],
    "wof:name":"Elite Plumbing & Heating",
    "wof:placetype":"venue"
},
  "geometry": {"coordinates":[-106.617333,35.113925],"type":"Point"}
}