{
  "type": "Feature",
  "properties": {
    "addr:full":"57 Encantado Loop Santa Fe NM 87508",
    "addr:housenumber":"57",
    "addr:postcode":"87508",
    "addr:street":"Encantado Loop",
    "iso:country":"US",
    "sg:address":"57 Encantado Loop",
    "sg:city":"Santa Fe",
    "sg:classifiers":[
        {
            "category":"Professional",
            "type":"Services"
        }
    ],
    "sg:phone":"+1 505 466 6558",
    "sg:postcode":"87508",
    "sg:province":"NM",
    "sg:tags":[
        "establishment"
    ],
    "wof:name":"Dual Films",
    "wof:placetype":"venue"
},
  "geometry": {"coordinates":[-105.96489200000001,35.557352],"type":"Point"}
}