{
  "type": "Feature",
  "properties": {
    "iso:country":"US",
    "sg:address":"2213 Brothers Rd",
    "sg:city":"Santa Fe",
    "sg:classifiers":[
        {
            "category":"Banks & Credit Unions",
            "subcategory":"Bank",
            "type":"Services"
        }
    ],
    "sg:phone":"+1 505 471 6100",
    "sg:postcode":"87505",
    "sg:province":"NM",
    "sg:tags":[
        "escrow"
    ],
    "wof:name":"Investors Escrow Inc",
    "wof:placetype":"venue"
},
  "geometry": {"coordinates":[-105.952253,35.650994],"type":"Point"}
}