{
  "type": "Feature",
  "properties": {
    "iso:country":"US",
    "sg:address":"5310 Pan American East Fwy NE",
    "sg:city":"Albuquerque",
    "sg:classifiers":[
        {
            "category":"Restaurant",
            "type":"Food & Drink"
        }
    ],
    "sg:phone":"+1 505 881 2506",
    "sg:postcode":"87109",
    "sg:province":"NM",
    "sg:tags":[
        "pizza"
    ],
    "wof:name":"Dion's Pizza",
    "wof:placetype":"venue"
},
  "geometry": {"coordinates":[-106.59271,35.142674],"type":"Point"}
}