{
  "type": "Feature",
  "properties": {
    "iso:country":"US",
    "sg:address":"708 E 1st St",
    "sg:city":"Portales",
    "sg:classifiers":[
        {
            "category":"Restaurant",
            "type":"Food & Drink"
        }
    ],
    "sg:phone":"+1 505 356 6368",
    "sg:postcode":"88130",
    "sg:province":"NM",
    "sg:tags":[
        "eating"
    ],
    "wof:name":"J J S Jumbo Burgers",
    "wof:placetype":"venue"
},
  "geometry": {"coordinates":[-103.332386,34.188041],"type":"Point"}
}