{
  "type": "Feature",
  "properties": {
    "iso:country":"US",
    "sg:address":"10030 Contana Ct",
    "sg:city":"Las Cruces",
    "sg:classifiers":[
        {
            "category":"Professional",
            "subcategory":"Lawyer & Legal Services",
            "type":"Services"
        }
    ],
    "sg:phone":"+1 505 523 0090",
    "sg:postcode":"88007",
    "sg:province":"NM",
    "wof:name":"Ellins Law Firm",
    "wof:placetype":"venue"
},
  "geometry": {"coordinates":[-106.87161,32.307376],"type":"Point"}
}