{
  "type": "Feature",
  "properties": {
    "iso:country":"US",
    "sg:address":"83 Galloway",
    "sg:city":"Moriarty",
    "sg:classifiers":[
        {
            "category":"Government",
            "subcategory":"Office",
            "type":"Public Place"
        }
    ],
    "sg:phone":"+1 505 832 2043",
    "sg:postcode":"87035",
    "sg:province":"NM",
    "sg:tags":[
        "village"
    ],
    "wof:name":"Animal Control Ctr",
    "wof:placetype":"venue"
},
  "geometry": {"coordinates":[-105.998592,35.033398],"type":"Point"}
}