{
  "type": "Feature",
  "properties": {
    "iso:country":"US",
    "sg:address":"2677 Louisiana Blvd NE",
    "sg:city":"Albuquerque",
    "sg:classifiers":[
        {
            "category":"Restaurant",
            "type":"Food & Drink"
        }
    ],
    "sg:menulink":"http://www.allmenus.com/nm/albuquerque/256604-super-suppers/menu/",
    "sg:phone":"+1 505 872 3463",
    "sg:postcode":"87110",
    "sg:province":"NM",
    "sg:tags":[
        "new",
        "american"
    ],
    "wof:name":"Super Suppers",
    "wof:placetype":"venue"
},
  "geometry": {"coordinates":[-106.56889200000001,35.110553],"type":"Point"}
}