{
  "type": "Feature",
  "properties": {
    "addr:full":"6235 Montgomery Blvd NE Albuquerque NM 87109",
    "addr:housenumber":"6235",
    "addr:postcode":"87109",
    "addr:street":"Montgomery Blvd Ne",
    "iso:country":"US",
    "sg:address":"6235 Montgomery Blvd NE",
    "sg:city":"Albuquerque",
    "sg:classifiers":[
        {
            "category":"Retail",
            "subcategory":"Laundry & Dry Cleaning",
            "type":"Services"
        }
    ],
    "sg:phone":"+1 505 888 8903",
    "sg:postcode":"87109",
    "sg:province":"NM",
    "sg:tags":[
        "cleaners"
    ],
    "wof:name":"Eathens Quality Cleaners",
    "wof:placetype":"venue"
},
  "geometry": {"coordinates":[-106.57599999999999,35.130922],"type":"Point"}
}