{
  "type": "Feature",
  "properties": {
    "iso:country":"US",
    "sg:address":"3360 Scenic Dr",
    "sg:city":"Alamogordo",
    "sg:classifiers":[
        {
            "category":"Building & Trades",
            "subcategory":"Plumbing",
            "type":"Services"
        }
    ],
    "sg:phone":"+1 505 437 8868",
    "sg:postcode":"88310",
    "sg:province":"NM",
    "sg:tags":[
        "conditioning",
        "air",
        "system",
        "contractor"
    ],
    "wof:name":"Porky's Heating & Cooling",
    "wof:placetype":"venue"
},
  "geometry": {"coordinates":[-105.947885,32.938189],"type":"Point"}
}