{
  "type": "Feature",
  "properties": {
    "addr:full":"26 Cam Sanador Santa Fe NM 87505",
    "addr:housenumber":"26",
    "addr:postcode":"87505",
    "addr:street":"Cam Sanador",
    "iso:country":"US",
    "sg:address":"26 Cam Sanador",
    "sg:city":"Santa Fe",
    "sg:classifiers":[
        {
            "category":"Professional",
            "subcategory":"Research",
            "type":"Services"
        }
    ],
    "sg:phone":"+1 505 471 2023",
    "sg:postcode":"87505",
    "sg:province":"NM",
    "sg:tags":[
        "laboratory"
    ],
    "wof:name":"Indepth Water & Soil Sampling",
    "wof:placetype":"venue"
},
  "geometry": {"coordinates":[-105.916372,35.640986],"type":"Point"}
}