{
  "type": "Feature",
  "properties": {
    "addr:full":"1422 Pso de Peralta Santa Fe NM 87501",
    "addr:housenumber":"1422",
    "addr:postcode":"87501",
    "addr:street":"Pso De Peralta",
    "iso:country":"US",
    "sg:address":"1422 Pso de Peralta",
    "sg:city":"Santa Fe",
    "sg:classifiers":[
        {
            "category":"Professional",
            "subcategory":"Research",
            "type":"Services"
        }
    ],
    "sg:phone":"+1 505 992 0618",
    "sg:postcode":"87501",
    "sg:province":"NM",
    "sg:tags":[
        "foundation",
        "philanthropic"
    ],
    "wof:name":"PMS Foundation",
    "wof:placetype":"venue"
},
  "geometry": {"coordinates":[-105.944531,35.681368],"type":"Point"}
}