{
  "type": "Feature",
  "properties": {
    "iso:country":"US",
    "sg:address":"701 E McGaffey St",
    "sg:city":"Roswell",
    "sg:classifiers":[
        {
            "category":"Shopping",
            "subcategory":"Used Merchandise",
            "type":"Retail Goods"
        }
    ],
    "sg:phone":"+1 505 623 9210",
    "sg:postcode":"88203",
    "sg:province":"NM",
    "sg:tags":[
        "second",
        "store",
        "hand"
    ],
    "wof:name":"Humane Society Thrift Shop",
    "wof:placetype":"venue"
},
  "geometry": {"coordinates":[-104.512854,33.379876],"type":"Point"}
}