{
  "type": "Feature",
  "properties": {
    "iso:country":"US",
    "sg:address":"854 Swinging Spear Rd",
    "sg:city":"Roswell",
    "sg:classifiers":[
        {
            "category":"Building & Trades",
            "subcategory":"Construction",
            "type":"Services"
        }
    ],
    "sg:phone":"+1 505 622 6833",
    "sg:postcode":"88201",
    "sg:province":"NM",
    "sg:tags":[
        "general"
    ],
    "wof:name":"Hanson Construction",
    "wof:placetype":"venue"
},
  "geometry": {"coordinates":[-104.511515,33.441033],"type":"Point"}
}