{
  "type": "Feature",
  "properties": {
    "addr:full":"95 Chambon Rd Lemitar NM 87823",
    "addr:housenumber":"95",
    "addr:postcode":"87823",
    "addr:street":"Chambon Rd",
    "iso:country":"US",
    "sg:address":"95 Chambon Rd",
    "sg:city":"Lemitar",
    "sg:classifiers":[
        {
            "category":"Personal",
            "subcategory":"Beauty Salon",
            "type":"Services"
        }
    ],
    "sg:phone":"+1 505 838 4409",
    "sg:postcode":"87823",
    "sg:province":"NM",
    "sg:tags":[
        "shop"
    ],
    "wof:name":"Helen's Country Hairstyling",
    "wof:placetype":"venue"
},
  "geometry": {"coordinates":[-106.91567499999999,34.164325],"type":"Point"}
}