{
  "type": "Feature",
  "properties": {
    "iso:country":"US",
    "sg:address":"2001 Ave de Mesilla",
    "sg:city":"Las Cruces",
    "sg:classifiers":[
        {
            "category":"Professional",
            "type":"Services"
        }
    ],
    "sg:phone":"+1 505 523 5563",
    "sg:postcode":"88005",
    "sg:province":"NM",
    "sg:tags":[
        "establishment"
    ],
    "wof:name":"Stagestop",
    "wof:placetype":"venue"
},
  "geometry": {"coordinates":[-106.79593,32.277964],"type":"Point"}
}