{
  "type": "Feature",
  "properties": {
    "iso:country":"US",
    "sg:address":"495 Mockingbird Ln",
    "sg:city":"Corrales",
    "sg:classifiers":[
        {
            "category":"Manufacturing",
            "subcategory":"Tools & Machinery",
            "type":"Manufacturing & Wholesale Goods"
        }
    ],
    "sg:phone":"+1 505 898 1455",
    "sg:postcode":"87048",
    "sg:province":"NM",
    "sg:tags":[
        "communication",
        "mfg"
    ],
    "wof:name":"Burst Electronics Inc",
    "wof:placetype":"venue"
},
  "geometry": {"coordinates":[-106.606344,35.223548],"type":"Point"}
}