{
  "type": "Feature",
  "properties": {
    "iso:country":"US",
    "sg:address":"4770 Montgomery Blvd NE",
    "sg:city":"Albuquerque",
    "sg:classifiers":[
        {
            "category":"Professional",
            "subcategory":"Accounting & Tax Preparation",
            "type":"Services"
        }
    ],
    "sg:phone":"+1 505 883 2979",
    "sg:postcode":"87109",
    "sg:province":"NM",
    "sg:tags":[
        "return",
        "filing"
    ],
    "wof:name":"H & R Block",
    "wof:placetype":"venue"
},
  "geometry": {"coordinates":[-106.587015,35.130864],"type":"Point"}
}