{
  "type": "Feature",
  "properties": {
    "iso:country":"US",
    "sg:address":"1413 Paisano St NE",
    "sg:city":"Albuquerque",
    "sg:classifiers":[
        {
            "category":"Professional",
            "type":"Services"
        }
    ],
    "sg:phone":"+1 505 332 0865",
    "sg:postcode":"87112",
    "sg:province":"NM",
    "wof:name":"Southwest Super Bikes",
    "wof:placetype":"venue"
},
  "geometry": {"coordinates":[-106.51413,35.096392],"type":"Point"}
}