{
  "type": "Feature",
  "properties": {
    "addr:full":"3218 State Hwy 47 Los Lunas NM 87031",
    "addr:housenumber":"3218",
    "addr:postcode":"87031",
    "addr:street":"State Hwy 47",
    "iso:country":"US",
    "sg:address":"3218 State Hwy 47",
    "sg:city":"Los Lunas",
    "sg:classifiers":[
        {
            "category":"Autos & Motor Vehicles",
            "subcategory":"Automobile Sales",
            "type":"Retail Goods"
        }
    ],
    "sg:phone":"+1 505 866 1999",
    "sg:postcode":"87031",
    "sg:province":"NM",
    "sg:tags":[
        "car",
        "dealer"
    ],
    "wof:name":"Country Auto & Truck Corral",
    "wof:placetype":"venue"
},
  "geometry": {"coordinates":[-106.708371,34.776061],"type":"Point"}
}