{
  "type": "Feature",
  "properties": {
    "iso:country":"US",
    "sg:address":"6356 Calle Tesoro NW",
    "sg:city":"Albuquerque",
    "sg:classifiers":[
        {
            "category":"Professional",
            "subcategory":"Management & Consulting",
            "type":"Services"
        }
    ],
    "sg:phone":"+1 505 897 0218",
    "sg:postcode":"87114",
    "sg:province":"NM",
    "sg:tags":[
        "sound",
        "consultant",
        "system"
    ],
    "wof:name":"Big Boys Sound And Picture",
    "wof:placetype":"venue"
},
  "geometry": {"coordinates":[-106.724035,35.199034],"type":"Point"}
}