{
  "type": "Feature",
  "properties": {
    "addr:full":"3553 Zafarano Dr Santa Fe NM 87507",
    "addr:housenumber":"3553",
    "addr:postcode":"87507",
    "addr:street":"Zafarano Dr",
    "iso:country":"US",
    "sg:address":"3553 Zafarano Dr",
    "sg:city":"Santa Fe",
    "sg:classifiers":[
        {
            "category":"Shopping",
            "subcategory":"Clothing, Apparel, & Fashions",
            "type":"Retail Goods"
        }
    ],
    "sg:phone":"+1 505 471 6208",
    "sg:postcode":"87507",
    "sg:province":"NM",
    "sg:tags":[
        "western"
    ],
    "sg:website":"www.coralwest.com",
    "wof:name":"Corral West Ranchwear",
    "wof:placetype":"venue"
},
  "geometry": {"coordinates":[-106.01166000000001,35.638783],"type":"Point"}
}