{
  "type": "Feature",
  "properties": {
    "iso:country":"US",
    "sg:address":"6007 Paradise Blvd NW",
    "sg:city":"Albuquerque",
    "sg:classifiers":[
        {
            "category":"Organizations",
            "subcategory":"Religious Organization",
            "type":"Services"
        }
    ],
    "sg:phone":"+1 505 890 5633",
    "sg:postcode":"87114",
    "sg:province":"NM",
    "sg:tags":[
        "church"
    ],
    "wof:name":"New Covenant Worship Ctr",
    "wof:placetype":"venue"
},
  "geometry": {"coordinates":[-106.715936,35.193611],"type":"Point"}
}