{
  "type": "Feature",
  "properties": {
    "iso:country":"US",
    "sg:address":"12 Futurity Pl",
    "sg:city":"Tijeras",
    "sg:classifiers":[
        {
            "category":"Building & Trades",
            "subcategory":"Construction",
            "type":"Services"
        }
    ],
    "sg:phone":"+1 505 237 2880",
    "sg:postcode":"87059",
    "sg:province":"NM",
    "sg:tags":[
        "tile",
        "dealer"
    ],
    "wof:name":"Armstrong Tile & Stone",
    "wof:placetype":"venue"
},
  "geometry": {"coordinates":[-106.279751,35.087423],"type":"Point"}
}