{
  "type": "Feature",
  "properties": {
    "addr:full":"110 Morningside Rd Ruidoso NM 88345",
    "addr:housenumber":"110",
    "addr:postcode":"88345",
    "addr:street":"Morningside Rd",
    "iso:country":"US",
    "sg:address":"110 Morningside Rd",
    "sg:city":"Ruidoso",
    "sg:classifiers":[
        {
            "category":"Professional",
            "subcategory":"Management & Consulting",
            "type":"Services"
        }
    ],
    "sg:phone":"+1 505 257 4515",
    "sg:postcode":"88345",
    "sg:province":"NM",
    "wof:name":"High Country Marketing Inc",
    "wof:placetype":"venue"
},
  "geometry": {"coordinates":[-105.665091,33.348289],"type":"Point"}
}