{
  "type": "Feature",
  "properties": {
    "iso:country":"US",
    "sg:address":"13013 Glenwood Hills Ct NE",
    "sg:city":"Albuquerque",
    "sg:classifiers":[
        {
            "category":"Real Estate",
            "subcategory":"Architect",
            "type":"Services"
        }
    ],
    "sg:phone":"+1 505 298 3099",
    "sg:postcode":"87111",
    "sg:province":"NM",
    "wof:name":"Peter Butterfield Architecture",
    "wof:placetype":"venue"
},
  "geometry": {"coordinates":[-106.492197,35.127672],"type":"Point"}
}