{
  "type": "Feature",
  "properties": {
    "iso:country":"US",
    "sg:address":"16145 State Rte 28",
    "sg:city":"La Mesa",
    "sg:classifiers":[
        {
            "category":"Restaurant",
            "type":"Food & Drink"
        }
    ],
    "sg:phone":"+1 505 233 9976",
    "sg:postcode":"88044",
    "sg:province":"NM",
    "wof:name":"Chope's Bar & Cafe",
    "wof:placetype":"venue"
},
  "geometry": {"coordinates":[-106.706512,32.119935],"type":"Point"}
}