{
  "type": "Feature",
  "properties": {
    "iso:country":"US",
    "sg:address":"117 N Guadalupe St",
    "sg:city":"Santa Fe",
    "sg:classifiers":[
        {
            "category":"Professional",
            "subcategory":"Lawyer & Legal Services",
            "type":"Services"
        }
    ],
    "sg:phone":"+1 505 986 1131",
    "sg:postcode":"87501",
    "sg:province":"NM",
    "wof:name":"Christopher Carlsen",
    "wof:placetype":"venue"
},
  "geometry": {"coordinates":[-105.943394,35.689171],"type":"Point"}
}