{
  "type": "Feature",
  "properties": {
    "iso:country":"US",
    "sg:address":"801 W Maple St",
    "sg:city":"Farmington",
    "sg:classifiers":[
        {
            "category":"Health Services",
            "subcategory":"Doctor",
            "type":"Services"
        }
    ],
    "sg:phone":"+1 505 325 1229",
    "sg:postcode":"87401",
    "sg:province":"NM",
    "sg:tags":[
        "physician",
        "surgeon"
    ],
    "wof:name":"Four Corners Radiology Assoc",
    "wof:placetype":"venue"
},
  "geometry": {"coordinates":[-108.21831899999999,36.724864],"type":"Point"}
}