{
  "type": "Feature",
  "properties": {
    "iso:country":"US",
    "sg:address":"7009 Prospect Ave NE",
    "sg:city":"Albuquerque",
    "sg:classifiers":[
        {
            "category":"Food & Beverages",
            "subcategory":"Groceries & Convenience Stores",
            "type":"Retail Goods"
        },
        {
            "category":"Building & Trades",
            "subcategory":"Construction",
            "type":"Services"
        }
    ],
    "sg:phone":"+1 505 888 8411",
    "sg:postcode":"87110",
    "sg:province":"NM",
    "sg:tags":[
        "concrete",
        "contractor"
    ],
    "wof:name":"Perma-Curbs Of New Mexico",
    "wof:placetype":"venue"
},
  "geometry": {"coordinates":[-106.56447300000001,35.108202],"type":"Point"}
}