{
  "type": "Feature",
  "properties": {
    "iso:country":"US",
    "sg:address":"162 Crest View Rd",
    "sg:city":"Capitan",
    "sg:classifiers":[
        {
            "category":"Retail",
            "subcategory":"Animal Services",
            "type":"Services"
        }
    ],
    "sg:phone":"+1 505 354 2745",
    "sg:postcode":"88316",
    "sg:province":"NM",
    "sg:tags":[
        "pet",
        "grooming",
        "washing"
    ],
    "wof:name":"Laura's Grooming",
    "wof:placetype":"venue"
},
  "geometry": {"coordinates":[-105.59793999999999,33.540715],"type":"Point"}
}