{
  "type": "Feature",
  "properties": {
    "iso:country":"US",
    "sg:address":"5800 Harper Dr NE",
    "sg:city":"Albuquerque",
    "sg:classifiers":[
        {
            "category":"Restaurant",
            "type":"Food & Drink"
        }
    ],
    "sg:phone":"+1 505 804 1140",
    "sg:postcode":"87109",
    "sg:province":"NM",
    "sg:tags":[
        "caterer"
    ],
    "wof:name":"Tonys Catering Service",
    "wof:placetype":"venue"
},
  "geometry": {"coordinates":[-106.584023,35.152922],"type":"Point"}
}