{
  "type": "Feature",
  "properties": {
    "iso:country":"US",
    "sg:address":"5370 W Carlsbad Hwy",
    "sg:city":"Hobbs",
    "sg:classifiers":[
        {
            "category":"Freight",
            "type":"Transportation"
        }
    ],
    "sg:phone":"+1 505 391 8282",
    "sg:postcode":"88240",
    "sg:province":"NM",
    "sg:tags":[
        "trucking"
    ],
    "wof:name":"Mc Nabb Svc",
    "wof:placetype":"venue"
},
  "geometry": {"coordinates":[-103.211142,32.696691],"type":"Point"}
}