{
  "type": "Feature",
  "properties": {
    "iso:country":"US",
    "sg:address":"4908 Corrales Rd",
    "sg:city":"Corrales",
    "sg:classifiers":[
        {
            "category":"Manufacturing",
            "subcategory":"Pottery",
            "type":"Manufacturing & Wholesale Goods"
        }
    ],
    "sg:phone":"+1 505 897 0271",
    "sg:postcode":"87048",
    "sg:province":"NM",
    "sg:tags":[
        "product"
    ],
    "wof:name":"Hanselmann Pottery",
    "wof:placetype":"venue"
},
  "geometry": {"coordinates":[-106.612239,35.231076],"type":"Point"}
}