{
  "type": "Feature",
  "properties": {
    "iso:country":"US",
    "sg:address":"107 Goltz Dr",
    "sg:city":"Grants",
    "sg:classifiers":[
        {
            "category":"Building & Trades",
            "subcategory":"Plumbing",
            "type":"Services"
        }
    ],
    "sg:phone":"+1 505 876 4950",
    "sg:postcode":"87020",
    "sg:province":"NM",
    "sg:tags":[
        "conditioning",
        "air",
        "system",
        "contractor"
    ],
    "wof:name":"Air Care Heating & Cooling",
    "wof:placetype":"venue"
},
  "geometry": {"coordinates":[-107.83363300000001,35.163854],"type":"Point"}
}