{
  "type": "Feature",
  "properties": {
    "addr:full":"9104 Crestwood Ave NE Albuquerque NM 87112",
    "addr:housenumber":"9104",
    "addr:postcode":"87112",
    "addr:street":"Crestwood Ave Ne",
    "iso:country":"US",
    "sg:address":"9104 Crestwood Ave NE",
    "sg:city":"Albuquerque",
    "sg:classifiers":[
        {
            "category":"Shopping",
            "subcategory":"Computers & Home Electronics",
            "type":"Retail Goods"
        }
    ],
    "sg:phone":"+1 505 294 2323",
    "sg:postcode":"87112",
    "sg:province":"NM",
    "sg:tags":[
        "mail",
        "house"
    ],
    "wof:name":"Plum-C",
    "wof:placetype":"venue"
},
  "geometry": {"coordinates":[-106.543969,35.097782],"type":"Point"}
}