{
  "type": "Feature",
  "properties": {
    "addr:full":"1110 New York Ave Alamogordo NM 88310",
    "addr:housenumber":"1110",
    "addr:postcode":"88310",
    "addr:street":"New York Ave",
    "iso:country":"US",
    "sg:address":"1110 New York Ave",
    "sg:city":"Alamogordo",
    "sg:classifiers":[
        {
            "category":"Arts & Performance",
            "subcategory":"Theater",
            "type":"Entertainment"
        }
    ],
    "sg:phone":"+1 505 437 2202",
    "sg:postcode":"88310",
    "sg:province":"NM",
    "wof:name":"Flickinger Center-Performing",
    "wof:placetype":"venue"
},
  "geometry": {"coordinates":[-105.958957,32.901862],"type":"Point"}
}