{
  "type": "Feature",
  "properties": {
    "iso:country":"US",
    "sg:address":"201 E University Ave",
    "sg:city":"Las Cruces",
    "sg:classifiers":[
        {
            "category":"Restaurant",
            "type":"Food & Drink"
        }
    ],
    "sg:menulink":"http://www.allmenus.com/nm/las-cruces/5631-ramada-palms---sabor/menu/",
    "sg:phone":"+1 505 526 4411",
    "sg:postcode":"88005",
    "sg:province":"NM",
    "sg:tags":[
        "american"
    ],
    "wof:name":"Ramada Palms - Sabor",
    "wof:placetype":"venue"
},
  "geometry": {"coordinates":[-106.76775499999999,32.282012],"type":"Point"}
}