{
  "type": "Feature",
  "properties": {
    "iso:country":"US",
    "sg:address":"4800 Hawkins St NE",
    "sg:city":"Albuquerque",
    "sg:classifiers":[
        {
            "category":"Retail",
            "subcategory":"Auto Repair",
            "type":"Services"
        }
    ],
    "sg:phone":"+1 505 341 3711",
    "sg:postcode":"87109",
    "sg:province":"NM",
    "sg:tags":[
        "truck"
    ],
    "wof:name":"M & G Enterprises",
    "wof:placetype":"venue"
},
  "geometry": {"coordinates":[-106.590889,35.162692],"type":"Point"}
}