{
  "type": "Feature",
  "properties": {
    "addr:full":"124 Crusader Ct Clovis NM 88101",
    "addr:housenumber":"124",
    "addr:postcode":"88101",
    "addr:street":"Crusader Ct",
    "iso:country":"US",
    "sg:address":"124 Crusader Ct",
    "sg:city":"Clovis",
    "sg:classifiers":[
        {
            "category":"Education",
            "subcategory":"Special Training",
            "type":"Public Place"
        }
    ],
    "sg:phone":"+1 580 484 2201",
    "sg:postcode":"88101",
    "sg:province":"NM",
    "sg:tags":[
        "educational"
    ],
    "wof:name":"Sellers, Marico Octavis",
    "wof:placetype":"venue"
},
  "geometry": {"coordinates":[-103.176885,34.44523],"type":"Point"}
}