{
  "type": "Feature",
  "properties": {
    "iso:country":"US",
    "sg:address":"830 5th St NW",
    "sg:city":"Albuquerque",
    "sg:classifiers":[
        {
            "category":"Professional",
            "subcategory":"Lawyer & Legal Services",
            "type":"Services"
        }
    ],
    "sg:phone":"+1 505 244 0795",
    "sg:postcode":"87102",
    "sg:province":"NM",
    "wof:name":"Prosser Law Firm",
    "wof:placetype":"venue"
},
  "geometry": {"coordinates":[-106.65116,35.092942],"type":"Point"}
}