{
  "type": "Feature",
  "properties": {
    "iso:country":"US",
    "sg:address":"4903 Smith Ave",
    "sg:city":"Roswell",
    "sg:classifiers":[
        {
            "category":"Wholesale",
            "subcategory":"Auto Parts",
            "type":"Manufacturing & Wholesale Goods"
        }
    ],
    "sg:phone":"+1 505 622 7473",
    "sg:postcode":"88203",
    "sg:province":"NM",
    "wof:name":"Auto Parts & Accessories",
    "wof:placetype":"venue"
},
  "geometry": {"coordinates":[-104.520289,33.339844],"type":"Point"}
}