{
  "type": "Feature",
  "properties": {
    "addr:full":"3 Cll Medico Santa Fe NM 87505",
    "addr:housenumber":"3",
    "addr:postcode":"87505",
    "addr:street":"Cll Medico",
    "iso:country":"US",
    "sg:address":"3 Cll Medico",
    "sg:city":"Santa Fe",
    "sg:classifiers":[
        {
            "category":"Travel",
            "subcategory":"Hotels & Motels",
            "type":"Entertainment"
        }
    ],
    "sg:phone":"+1 505 984 8737",
    "sg:postcode":"87505",
    "sg:province":"NM",
    "sg:tags":[
        "resort",
        "center",
        "skiing"
    ],
    "wof:name":"Wolf Creek Ski Area",
    "wof:placetype":"venue"
},
  "geometry": {"coordinates":[-105.940636,35.657338],"type":"Point"}
}