{
  "type": "Feature",
  "properties": {
    "iso:country":"US",
    "sg:address":"525 Airport Rd",
    "sg:city":"Santa Fe",
    "sg:classifiers":[
        {
            "category":"Shopping",
            "subcategory":"Bicycles & Sporting Goods",
            "type":"Retail Goods"
        },
        {
            "category":"Shopping",
            "subcategory":"Clothing, Apparel, & Fashions",
            "type":"Retail Goods"
        }
    ],
    "sg:phone":"+1 505 474 7795",
    "sg:postcode":"87507",
    "sg:province":"NM",
    "sg:tags":[
        "equipment",
        "saddlery",
        "equestrian",
        "riding"
    ],
    "sg:website":"www.desertwindsaddlery.com",
    "wof:name":"Desert Wind Saddlery",
    "wof:placetype":"venue"
},
  "geometry": {"coordinates":[-106.031382,35.637654],"type":"Point"}
}