{
  "type": "Feature",
  "properties": {
    "addr:full":"6208 Montgomery Blvd NE Albuquerque NM 87109",
    "addr:housenumber":"6208",
    "addr:postcode":"87109",
    "addr:street":"Montgomery Blvd Ne",
    "iso:country":"US",
    "sg:address":"6208 Montgomery Blvd NE",
    "sg:city":"Albuquerque",
    "sg:classifiers":[
        {
            "category":"Health Services",
            "subcategory":"Health Practitioner",
            "type":"Services"
        }
    ],
    "sg:phone":"+1 505 610 7040",
    "sg:postcode":"87109",
    "sg:province":"NM",
    "sg:tags":[
        "psychotherapist"
    ],
    "wof:name":"Jan Koltonuk Psychotherapy",
    "wof:placetype":"venue"
},
  "geometry": {"coordinates":[-106.575795,35.13077],"type":"Point"}
}