{
  "type": "Feature",
  "properties": {
    "addr:full":"210 Herrera Rd Hatch NM 87937",
    "addr:housenumber":"210",
    "addr:postcode":"87937",
    "addr:street":"Herrera Rd",
    "iso:country":"US",
    "sg:address":"210 Herrera Rd",
    "sg:city":"Hatch",
    "sg:classifiers":[
        {
            "category":"Organizations",
            "subcategory":"Religious Organization",
            "type":"Services"
        }
    ],
    "sg:phone":"+1 505 267 3036",
    "sg:postcode":"87937",
    "sg:province":"NM",
    "sg:tags":[
        "church"
    ],
    "wof:name":"Church Of Jesus Christ Of Lds",
    "wof:placetype":"venue"
},
  "geometry": {"coordinates":[-107.15544800000001,32.670794],"type":"Point"}
}