{
  "type": "Feature",
  "properties": {
    "addr:full":"1100 Lomas Blvd NW Ste 1 Albuquerque NM 87102",
    "addr:housenumber":"1100",
    "addr:postcode":"87102",
    "addr:street":"Lomas Blvd Nw Ste 1",
    "iso:country":"US",
    "sg:address":"1100 Lomas Blvd NW Ste 1",
    "sg:city":"Albuquerque",
    "sg:classifiers":[
        {
            "category":"Health Services",
            "subcategory":"Chiropractor",
            "type":"Services"
        }
    ],
    "sg:phone":"+1 505 242 8400",
    "sg:postcode":"87102",
    "sg:province":"NM",
    "sg:tags":[
        "chiropractic"
    ],
    "wof:name":"Lehman, Thomas P Dr",
    "wof:placetype":"venue"
},
  "geometry": {"coordinates":[-106.658546,35.091949],"type":"Point"}
}