{
  "type": "Feature",
  "properties": {
    "addr:full":"15 Everest Ct Cedar Crest NM 87008",
    "addr:housenumber":"15",
    "addr:postcode":"87008",
    "addr:street":"Everest Ct",
    "iso:country":"US",
    "sg:address":"15 Everest Ct",
    "sg:city":"Cedar Crest",
    "sg:classifiers":[
        {
            "category":"Professional",
            "subcategory":"Art Services",
            "type":"Services"
        }
    ],
    "sg:phone":"+1 505 286 1022",
    "sg:postcode":"87008",
    "sg:province":"NM",
    "sg:tags":[
        "graphic",
        "designer"
    ],
    "wof:name":"Bonehead Studios",
    "wof:placetype":"venue"
},
  "geometry": {"coordinates":[-106.378732,35.089654],"type":"Point"}
}