{
  "type": "Feature",
  "properties": {
    "iso:country":"US",
    "sg:address":"2345 Southern Blvd SE",
    "sg:city":"Rio Rancho",
    "sg:classifiers":[
        {
            "category":"Retail",
            "subcategory":"Animal Services",
            "type":"Services"
        }
    ],
    "sg:phone":"+1 505 891 3269",
    "sg:postcode":"87124",
    "sg:province":"NM",
    "sg:tags":[
        "pet",
        "grooming",
        "washing",
        "merchandise"
    ],
    "wof:name":"Pet Palace Groomery",
    "wof:placetype":"venue"
},
  "geometry": {"coordinates":[-106.689758,35.241658],"type":"Point"}
}