{
  "type": "Feature",
  "properties": {
    "iso:country":"US",
    "sg:address":"1065 S Main St",
    "sg:city":"Las Cruces",
    "sg:classifiers":[
        {
            "category":"Building & Trades",
            "subcategory":"Construction",
            "type":"Services"
        }
    ],
    "sg:phone":"+1 505 647 3650",
    "sg:postcode":"88005",
    "sg:province":"NM",
    "sg:tags":[
        "house",
        "general",
        "contractor"
    ],
    "wof:name":"Charlos Homes LLC",
    "wof:placetype":"venue"
},
  "geometry": {"coordinates":[-106.778631,32.300044],"type":"Point"}
}