{
  "type": "Feature",
  "properties": {
    "addr:full":"1645 W Picacho Ave Las Cruces NM 88005",
    "addr:housenumber":"1645",
    "addr:postcode":"88005",
    "addr:street":"W Picacho Ave",
    "iso:country":"US",
    "sg:address":"1645 W Picacho Ave",
    "sg:city":"Las Cruces",
    "sg:classifiers":[
        {
            "category":"Home & Garden",
            "subcategory":"Building Materials",
            "type":"Retail Goods"
        }
    ],
    "sg:phone":"+1 505 523 5305",
    "sg:postcode":"88005",
    "sg:province":"NM",
    "wof:name":"Las Cruces Roofing Supply",
    "wof:placetype":"venue"
},
  "geometry": {"coordinates":[-106.802132,32.311853],"type":"Point"}
}