{
  "type": "Feature",
  "properties": {
    "addr:full":"109 Washington St SE Albuquerque NM 87108",
    "addr:housenumber":"109",
    "addr:postcode":"87108",
    "addr:street":"Washington St Se",
    "iso:country":"US",
    "sg:address":"109 Washington St SE",
    "sg:city":"Albuquerque",
    "sg:classifiers":[
        {
            "category":"Building & Trades",
            "subcategory":"Construction",
            "type":"Services"
        }
    ],
    "sg:phone":"+1 505 610 5945",
    "sg:postcode":"87108",
    "sg:province":"NM",
    "sg:tags":[
        "floor",
        "laying",
        "contractor"
    ],
    "wof:name":"Eriks Flooring",
    "wof:placetype":"venue"
},
  "geometry": {"coordinates":[-106.59542399999999,35.077876],"type":"Point"}
}