{
  "type": "Feature",
  "properties": {
    "addr:full":"1617 E 6th St Clovis NM 88101",
    "addr:housenumber":"1617",
    "addr:postcode":"88101",
    "addr:street":"E 6Th St",
    "iso:country":"US",
    "sg:address":"1617 E 6th St",
    "sg:city":"Clovis",
    "sg:classifiers":[
        {
            "category":"Retail",
            "subcategory":"Auto Repair",
            "type":"Services"
        }
    ],
    "sg:phone":"+1 575 763 6967",
    "sg:postcode":"88101",
    "sg:province":"NM",
    "sg:tags":[
        "body",
        "painting",
        "repairing",
        "automobile"
    ],
    "wof:name":"Jack Quaif",
    "wof:placetype":"venue"
},
  "geometry": {"coordinates":[-103.186211,34.403931],"type":"Point"}
}