{
  "type": "Feature",
  "properties": {
    "iso:country":"US",
    "sg:address":"4100 Pennsylvania St NE",
    "sg:city":"Albuquerque",
    "sg:classifiers":[
        {
            "category":"Autos & Motor Vehicles",
            "subcategory":"Auto Supplies",
            "type":"Retail Goods"
        },
        {
            "category":"Retail",
            "subcategory":"Auto Repair",
            "type":"Services"
        }
    ],
    "sg:phone":"+1 505 298 7115",
    "sg:postcode":"87109",
    "sg:province":"NM",
    "sg:tags":[
        "oil",
        "automotive",
        "automobile",
        "lube",
        "equipment-service",
        "air conditioning",
        "tune"
    ],
    "sg:website":"http://www.jiffylube.com",
    "wof:name":"Jiffy Lube",
    "wof:placetype":"venue"
},
  "geometry": {"coordinates":[-106.55983000000001,35.130829],"type":"Point"}
}