{
  "type": "Feature",
  "properties": {
    "addr:full":"5900 Jefferson St NE Albuquerque NM 87109",
    "addr:housenumber":"5900",
    "addr:postcode":"87109",
    "addr:street":"Jefferson St Ne",
    "iso:country":"US",
    "sg:address":"5900 Jefferson St NE",
    "sg:city":"Albuquerque",
    "sg:classifiers":[
        {
            "category":"Government",
            "subcategory":"Police Station",
            "type":"Public Place"
        }
    ],
    "sg:phone":"+1 505 344 9821",
    "sg:postcode":"87109",
    "sg:province":"NM",
    "sg:tags":[
        "department"
    ],
    "wof:name":"Albuquerque Police Officers'",
    "wof:placetype":"venue"
},
  "geometry": {"coordinates":[-106.595787,35.146091],"type":"Point"}
}