{
  "type": "Feature",
  "properties": {
    "addr:full":"840 Nogales Ave Chaparral NM 88081",
    "addr:housenumber":"840",
    "addr:postcode":"88081",
    "addr:street":"Nogales Ave",
    "iso:country":"US",
    "sg:address":"840 Nogales Ave",
    "sg:city":"Chaparral",
    "sg:classifiers":[
        {
            "category":"Building & Trades",
            "subcategory":"Construction",
            "type":"Services"
        }
    ],
    "sg:phone":"+1 915 820 3418",
    "sg:postcode":"88081",
    "sg:province":"NM",
    "sg:tags":[
        "repairing",
        "remodeling",
        "contractor"
    ],
    "wof:name":"Lorenzo's Roofing & Remodeling",
    "wof:placetype":"venue"
},
  "geometry": {"coordinates":[-106.364484,32.03215],"type":"Point"}
}