{
  "type": "Feature",
  "properties": {
    "iso:country":"US",
    "sg:address":"2013 Conita Real Ave SW",
    "sg:city":"Albuquerque",
    "sg:classifiers":[
        {
            "category":"Building & Trades",
            "subcategory":"Construction",
            "type":"Services"
        }
    ],
    "sg:phone":"+1 505 452 2500",
    "sg:postcode":"87105",
    "sg:province":"NM",
    "sg:tags":[
        "concrete",
        "contractor"
    ],
    "wof:name":"Artscapes",
    "wof:placetype":"venue"
},
  "geometry": {"coordinates":[-106.68411,35.057509],"type":"Point"}
}