{
  "type": "Feature",
  "properties": {
    "iso:country":"US",
    "sg:address":"1020 Lomas Blvd NW",
    "sg:city":"Albuquerque",
    "sg:classifiers":[
        {
            "category":"Banks & Credit Unions",
            "subcategory":"Bank",
            "type":"Services"
        }
    ],
    "sg:phone":"+1 505 242 2646",
    "sg:postcode":"87102",
    "sg:province":"NM",
    "sg:tags":[
        "personal",
        "institution"
    ],
    "wof:name":"Citifinancial",
    "wof:placetype":"venue"
},
  "geometry": {"coordinates":[-106.657295,35.091701],"type":"Point"}
}