{
  "type": "Feature",
  "properties": {
    "iso:country":"US",
    "sg:address":"915 New York Ave",
    "sg:city":"Alamogordo",
    "sg:classifiers":[
        {
            "category":"Food & Beverages",
            "subcategory":"Specialty",
            "type":"Retail Goods"
        }
    ],
    "sg:phone":"+1 505 434 1670",
    "sg:postcode":"88310",
    "sg:province":"NM",
    "wof:name":"Natures Pantry Health Foods",
    "wof:placetype":"venue"
},
  "geometry": {"coordinates":[-105.959299,32.899656],"type":"Point"}
}