{
  "type": "Feature",
  "properties": {
    "iso:country":"US",
    "sg:address":"3000 W Church St",
    "sg:city":"Carlsbad",
    "sg:classifiers":[
        {
            "category":"Education",
            "subcategory":"School",
            "type":"Public Place"
        }
    ],
    "sg:phone":"+1 505 234 3319",
    "sg:postcode":"88220",
    "sg:province":"NM",
    "sg:tags":[
        "secondary"
    ],
    "wof:name":"Carlsbad Senior High School",
    "wof:placetype":"venue"
},
  "geometry": {"coordinates":[-104.266513,32.428804],"type":"Point"}
}