{
  "type": "Feature",
  "properties": {
    "addr:full":"3211 Campus Blvd NE Albuquerque NM 87106",
    "addr:housenumber":"3211",
    "addr:postcode":"87106",
    "addr:street":"Campus Blvd Ne",
    "iso:country":"US",
    "sg:address":"3211 Campus Blvd NE",
    "sg:city":"Albuquerque",
    "sg:classifiers":[
        {
            "category":"Professional",
            "type":"Services"
        }
    ],
    "sg:phone":"+1 505 262 2213",
    "sg:postcode":"87106",
    "sg:province":"NM",
    "wof:name":"Barbara Ruzinsky & Associates",
    "wof:placetype":"venue"
},
  "geometry": {"coordinates":[-106.609662,35.083054],"type":"Point"}
}