{
  "type": "Feature",
  "properties": {
    "addr:full":"11012 Montgomery Blvd NE Albuquerque NM 87111",
    "addr:housenumber":"11012",
    "addr:postcode":"87111",
    "addr:street":"Montgomery Blvd Ne",
    "iso:country":"US",
    "sg:address":"11012 Montgomery Blvd NE",
    "sg:city":"Albuquerque",
    "sg:classifiers":[
        {
            "category":"Professional",
            "subcategory":"Art Services",
            "type":"Services"
        }
    ],
    "sg:phone":"+1 505 293 6304",
    "sg:postcode":"87111",
    "sg:province":"NM",
    "sg:tags":[
        "photography",
        "studio"
    ],
    "wof:name":"Kim Jew Photographer",
    "wof:placetype":"venue"
},
  "geometry": {"coordinates":[-106.51659600000001,35.130594],"type":"Point"}
}