{
  "type": "Feature",
  "properties": {
    "addr:full":"100 W Idaho Ave Jal NM 88252",
    "addr:housenumber":"100",
    "addr:postcode":"88252",
    "addr:street":"W Idaho Ave",
    "iso:country":"US",
    "sg:address":"100 W Idaho Ave",
    "sg:city":"Jal",
    "sg:classifiers":[
        {
            "category":"Organizations",
            "subcategory":"Professional Association",
            "type":"Services"
        }
    ],
    "sg:phone":"+1 505 395 2620",
    "sg:postcode":"88252",
    "sg:province":"NM",
    "sg:tags":[
        "chambers",
        "business",
        "commerce"
    ],
    "wof:name":"Chamber of Commerce",
    "wof:placetype":"venue"
},
  "geometry": {"coordinates":[-103.193364,32.114269],"type":"Point"}
}