{
  "type": "Feature",
  "properties": {
    "addr:full":"3404 Pimlico Pl SW Albuquerque NM 87105",
    "addr:housenumber":"3404",
    "addr:postcode":"87105",
    "addr:street":"Pimlico Pl Sw",
    "iso:country":"US",
    "sg:address":"3404 Pimlico Pl SW",
    "sg:city":"Albuquerque",
    "sg:classifiers":[
        {
            "category":"Home & Garden",
            "subcategory":"Building Materials",
            "type":"Retail Goods"
        }
    ],
    "sg:phone":"+1 505 821 8217",
    "sg:postcode":"87105",
    "sg:province":"NM",
    "sg:tags":[
        "windows"
    ],
    "wof:name":"Modern Construction Co",
    "wof:placetype":"venue"
},
  "geometry": {"coordinates":[-106.70990500000001,35.03812],"type":"Point"}
}