{
  "type": "Feature",
  "properties": {
    "addr:full":"278 Dp Rd Los Alamos NM 87544",
    "addr:postcode":"87544",
    "addr:street":"Dp Rd",
    "iso:country":"US",
    "sg:address":"278 Dp Rd",
    "sg:city":"Los Alamos",
    "sg:classifiers":[
        {
            "category":"Restaurant",
            "type":"Food & Drink"
        }
    ],
    "sg:phone":"+1 505 662 2233",
    "sg:postcode":"87544",
    "sg:province":"NM",
    "sg:tags":[
        "shop",
        "coffee"
    ],
    "wof:name":"Coffee Booth",
    "wof:placetype":"venue"
},
  "geometry": {"coordinates":[-106.27724499999999,35.877974],"type":"Point"}
}