{
  "type": "Feature",
  "properties": {
    "iso:country":"US",
    "sg:address":"8401 Jefferson St NE",
    "sg:city":"Albuquerque",
    "sg:classifiers":[
        {
            "category":"Building & Trades",
            "subcategory":"Plumbing",
            "type":"Services"
        }
    ],
    "sg:phone":"+1 505 468 1020",
    "sg:postcode":"87113",
    "sg:province":"NM",
    "sg:tags":[
        "plumbing",
        "contractor"
    ],
    "wof:name":"Coyote Plumbing Inc",
    "wof:placetype":"venue"
},
  "geometry": {"coordinates":[-106.592811,35.177911],"type":"Point"}
}