{
  "type": "Feature",
  "properties": {
    "iso:country":"US",
    "sg:address":"4851 Ellison St NE",
    "sg:city":"Albuquerque",
    "sg:classifiers":[
        {
            "category":"Retail",
            "subcategory":"Repair Shop",
            "type":"Services"
        },
        {
            "category":"Professional",
            "subcategory":"Management & Consulting",
            "type":"Services"
        }
    ],
    "sg:phone":"+1 505 344 0571",
    "sg:postcode":"87109",
    "sg:province":"NM",
    "sg:tags":[
        "coffee",
        "brewing",
        "electrical",
        "devices"
    ],
    "wof:name":"Hudson Repair",
    "wof:placetype":"venue"
},
  "geometry": {"coordinates":[-106.588457,35.160595],"type":"Point"}
}