{
  "type": "Feature",
  "properties": {
    "addr:full":"4614 Cairo Dr NE Albuquerque NM 87111",
    "addr:housenumber":"4614",
    "addr:postcode":"87111",
    "addr:street":"Cairo Dr Ne",
    "iso:country":"US",
    "sg:address":"4614 Cairo Dr NE",
    "sg:city":"Albuquerque",
    "sg:classifiers":[
        {
            "category":"Professional",
            "subcategory":"Accounting & Tax Preparation",
            "type":"Services"
        }
    ],
    "sg:phone":"+1 505 294 7991",
    "sg:postcode":"87111",
    "sg:province":"NM",
    "sg:tags":[
        "return"
    ],
    "wof:name":"National Assn Tax Prctitioners",
    "wof:placetype":"venue"
},
  "geometry": {"coordinates":[-106.511251,35.133648],"type":"Point"}
}