{
  "type": "Feature",
  "properties": {
    "addr:full":"76 Cities of Gold Rd Santa Fe NM 87506",
    "addr:housenumber":"76",
    "addr:postcode":"87506",
    "addr:street":"Rd",
    "iso:country":"US",
    "sg:address":"76 Cities of Gold Rd",
    "sg:city":"Santa Fe",
    "sg:classifiers":[
        {
            "category":"Government",
            "subcategory":"Police Station",
            "type":"Public Place"
        }
    ],
    "sg:phone":"+1 505 455 2295",
    "sg:postcode":"87506",
    "sg:province":"NM",
    "sg:tags":[
        "department"
    ],
    "wof:name":"Pojoaque Pueblo Police",
    "wof:placetype":"venue"
},
  "geometry": {"coordinates":[-106.013374,35.882804],"type":"Point"}
}