{
  "type": "Feature",
  "properties": {
    "iso:country":"US",
    "sg:address":"3619 Wyoming Blvd NE",
    "sg:city":"Albuquerque",
    "sg:classifiers":[
        {
            "category":"Personal",
            "subcategory":"Nail Salon",
            "type":"Services"
        }
    ],
    "sg:phone":"+1 505 275 6840",
    "sg:postcode":"87111",
    "sg:province":"NM",
    "wof:name":"Gorgeous Nails",
    "wof:placetype":"venue"
},
  "geometry": {"coordinates":[-106.551051,35.123854],"type":"Point"}
}