{
  "type": "Feature",
  "properties": {
    "addr:full":"3656 E Hobson Rd Roswell NM 88203",
    "addr:housenumber":"3656",
    "addr:postcode":"88203",
    "addr:street":"E Hobson Rd",
    "iso:country":"US",
    "sg:address":"3656 E Hobson Rd",
    "sg:city":"Roswell",
    "sg:phone":"+1 505 622 7289",
    "sg:postcode":"88203",
    "sg:province":"NM",
    "sg:tags":[
        "specializing",
        "a",
        "herb",
        "corn",
        "paprika",
        "hay",
        "spice",
        "or",
        "cotton"
    ],
    "wof:name":"Hobson Gardens",
    "wof:placetype":"venue"
},
  "geometry": {"coordinates":[-104.459748,33.320793],"type":"Point"}
}