{
  "type": "Feature",
  "properties": {
    "iso:country":"US",
    "sg:address":"2715 2nd St NW",
    "sg:city":"Albuquerque",
    "sg:classifiers":[
        {
            "category":"Professional",
            "type":"Services"
        }
    ],
    "sg:phone":"+1 505 345 3144",
    "sg:postcode":"87107",
    "sg:province":"NM",
    "sg:tags":[
        "establishment"
    ],
    "sg:website":"www.santafesaddleblanket.com",
    "wof:name":"Santa Fe Saddle Blanker",
    "wof:placetype":"venue"
},
  "geometry": {"coordinates":[-106.643956,35.112351],"type":"Point"}
}