{
  "type": "Feature",
  "properties": {
    "iso:country":"US",
    "sg:address":"1966 State Rte 21",
    "sg:city":"Miami",
    "sg:classifiers":[
        {
            "category":"Arts & Performance",
            "subcategory":"Theater",
            "type":"Entertainment"
        }
    ],
    "sg:phone":"+1 505 483 0042",
    "sg:postcode":"87729",
    "sg:province":"NM",
    "sg:tags":[
        "entertainer",
        "business"
    ],
    "wof:name":"Hampton Land & Lyrics",
    "wof:placetype":"venue"
},
  "geometry": {"coordinates":[-104.792259,36.348004],"type":"Point"}
}