{
  "type": "Feature",
  "properties": {
    "iso:country":"US",
    "sg:address":"511 Armijo St",
    "sg:city":"Santa Fe",
    "sg:classifiers":[
        {
            "category":"Banks & Credit Unions",
            "subcategory":"Financial Services",
            "type":"Services"
        },
        {
            "category":"Professional",
            "subcategory":"Research",
            "type":"Services"
        }
    ],
    "sg:phone":"+1 505 986 0208",
    "sg:postcode":"87501",
    "sg:province":"NM",
    "sg:tags":[
        "trust",
        "foundation",
        "nonprofit",
        "management",
        "philanthropic"
    ],
    "sg:website":"www.frostfound.org",
    "wof:name":"Frost Foundation Ltd",
    "wof:placetype":"venue"
},
  "geometry": {"coordinates":[-105.929743,35.686047],"type":"Point"}
}