{
  "type": "Feature",
  "properties": {
    "iso:country":"US",
    "sg:address":"670 Ranchitos Rd",
    "sg:city":"Corrales",
    "sg:classifiers":[
        {
            "category":"Building & Trades",
            "subcategory":"Construction",
            "type":"Services"
        }
    ],
    "sg:phone":"+1 505 898 8645",
    "sg:postcode":"87048",
    "sg:province":"NM",
    "sg:tags":[
        "general",
        "contractor"
    ],
    "wof:name":"Haddow Plumbing & Heating",
    "wof:placetype":"venue"
},
  "geometry": {"coordinates":[-106.63744699999999,35.22505],"type":"Point"}
}