{
  "type": "Feature",
  "properties": {
    "iso:country":"US",
    "sg:address":"1635 Isleta Blvd SW",
    "sg:city":"Albuquerque",
    "sg:classifiers":[
        {
            "category":"Shopping",
            "subcategory":"Department Store",
            "type":"Retail Goods"
        }
    ],
    "sg:phone":"+1 505 873 0577",
    "sg:postcode":"87105",
    "sg:province":"NM",
    "sg:tags":[
        "shop"
    ],
    "wof:name":"Family Dollar Store",
    "wof:placetype":"venue"
},
  "geometry": {"coordinates":[-106.677914,35.051601],"type":"Point"}
}