{
  "type": "Feature",
  "properties": {
    "addr:full":"2120 Northglen Dr Clovis NM 88101",
    "addr:housenumber":"2120",
    "addr:postcode":"88101",
    "addr:street":"Northglen Dr",
    "iso:country":"US",
    "sg:address":"2120 Northglen Dr",
    "sg:city":"Clovis",
    "sg:classifiers":[
        {
            "category":"Food & Beverages",
            "subcategory":"Bakery",
            "type":"Retail Goods"
        }
    ],
    "sg:phone":"+1 505 762 7308",
    "sg:postcode":"88101",
    "sg:province":"NM",
    "sg:tags":[
        "doughnut"
    ],
    "wof:name":"Gold Nugget Donuts",
    "wof:placetype":"venue"
},
  "geometry": {"coordinates":[-103.17636400000001,34.429704],"type":"Point"}
}