{
  "type": "Feature",
  "properties": {
    "addr:full":"210 Uracca St Raton NM 87740",
    "addr:housenumber":"210",
    "addr:postcode":"87740",
    "addr:street":"Uracca St",
    "iso:country":"US",
    "sg:address":"210 Uracca St",
    "sg:city":"Raton",
    "sg:classifiers":[
        {
            "category":"Restaurant",
            "type":"Food & Drink"
        }
    ],
    "sg:phone":"+1 505 445 9090",
    "sg:postcode":"87740",
    "sg:province":"NM",
    "sg:tags":[
        "eating"
    ],
    "wof:name":"Hot Dog Depot",
    "wof:placetype":"venue"
},
  "geometry": {"coordinates":[-104.438338,36.910248],"type":"Point"}
}