{
  "type": "Feature",
  "properties": {
    "addr:full":"1304 4th St NW Albuquerque NM 87102",
    "addr:housenumber":"1304",
    "addr:postcode":"87102",
    "addr:street":"4Th St Nw",
    "iso:country":"US",
    "sg:address":"1304 4th St NW",
    "sg:city":"Albuquerque",
    "sg:classifiers":[
        {
            "category":"Place Of Worship",
            "subcategory":"Church",
            "type":"Public Place"
        },
        {
            "category":"Place Of Worship",
            "type":"Public Place"
        }
    ],
    "sg:phone":"+1 505 247 7405",
    "sg:postcode":"87102",
    "sg:province":"NM",
    "sg:tags":[
        "covenant",
        "churches-evangelical",
        "churches-covenant",
        "christ",
        "churches-community"
    ],
    "wof:name":"Center City Evangelical Church",
    "wof:placetype":"venue"
},
  "geometry": {"coordinates":[-106.64920100000001,35.097101],"type":"Point"}
}