{
  "type": "Feature",
  "properties": {
    "addr:full":"50 Mills Ln New Laguna NM 87031",
    "addr:housenumber":"50",
    "addr:postcode":"87031",
    "addr:street":"Mills Ln",
    "iso:country":"US",
    "sg:address":"50 Mills Ln",
    "sg:city":"New Laguna",
    "sg:classifiers":[
        {
            "category":"Health Services",
            "subcategory":"Clinic",
            "type":"Services"
        }
    ],
    "sg:phone":"+1 505 552 6068",
    "sg:postcode":"87031",
    "sg:province":"NM",
    "wof:name":"Acoma Cnncito Lguna Wic Prgram",
    "wof:placetype":"venue"
},
  "geometry": {"coordinates":[-106.687381,34.801916],"type":"Point"}
}