{
  "type": "Feature",
  "properties": {
    "iso:country":"US",
    "sg:address":"601 86th St SW",
    "sg:city":"Albuquerque",
    "sg:classifiers":[
        {
            "category":"Organizations",
            "subcategory":"Religious Organization",
            "type":"Services"
        }
    ],
    "sg:phone":"+1 505 839 1063",
    "sg:postcode":"87121",
    "sg:province":"NM",
    "sg:tags":[
        "church"
    ],
    "wof:name":"Tower Road Baptist Church",
    "wof:placetype":"venue"
},
  "geometry": {"coordinates":[-106.730841,35.0669],"type":"Point"}
}