{
  "type": "Feature",
  "properties": {
    "addr:full":"125 Western Skies Dr SE Albuquerque NM 87123",
    "addr:housenumber":"125",
    "addr:postcode":"87123",
    "addr:street":"Western Skies Dr Se",
    "iso:country":"US",
    "sg:address":"125 Western Skies Dr SE",
    "sg:city":"Albuquerque",
    "sg:classifiers":[
        {
            "category":"Retail",
            "subcategory":"Self-service Laundry",
            "type":"Services"
        }
    ],
    "sg:phone":"+1 505 332 1300",
    "sg:postcode":"87123",
    "sg:province":"NM",
    "wof:name":"Happy Suds Laundry",
    "wof:placetype":"venue"
},
  "geometry": {"coordinates":[-106.509642,35.068281],"type":"Point"}
}