{
  "type": "Feature",
  "properties": {
    "iso:country":"US",
    "sg:address":"6101 Marble Ave NE",
    "sg:city":"Albuquerque",
    "sg:classifiers":[
        {
            "category":"Health Services",
            "subcategory":"Hospital",
            "type":"Services"
        }
    ],
    "sg:phone":"+1 505 323 3785",
    "sg:postcode":"87110",
    "sg:province":"NM",
    "sg:tags":[
        "mental"
    ],
    "wof:name":"Crisis Resolutions Inc",
    "wof:placetype":"venue"
},
  "geometry": {"coordinates":[-106.578609,35.089304],"type":"Point"}
}