{
  "type": "Feature",
  "properties": {
    "iso:country":"US",
    "sg:address":"620 Canyon Rd",
    "sg:city":"Santa Fe",
    "sg:classifiers":[
        {
            "category":"Shopping",
            "type":"Retail Goods"
        }
    ],
    "sg:phone":"+1 505 995 8600",
    "sg:postcode":"87501",
    "sg:province":"NM",
    "sg:tags":[
        "art",
        "gallery",
        "dealer"
    ],
    "wof:name":"New Mexico Originals",
    "wof:placetype":"venue"
},
  "geometry": {"coordinates":[-105.928601,35.681683],"type":"Point"}
}