{
  "type": "Feature",
  "properties": {
    "iso:country":"US",
    "sg:address":"2201 Miguel Chavez Rd",
    "sg:city":"Santa Fe",
    "sg:classifiers":[
        {
            "category":"Building & Trades",
            "subcategory":"Construction",
            "type":"Services"
        }
    ],
    "sg:phone":"+1 505 474 8674",
    "sg:postcode":"87505",
    "sg:province":"NM",
    "sg:tags":[
        "general",
        "contractor"
    ],
    "wof:name":"Diamond Custom Homes",
    "wof:placetype":"venue"
},
  "geometry": {"coordinates":[-105.953655,35.650774],"type":"Point"}
}