{
  "type": "Feature",
  "properties": {
    "iso:country":"US",
    "sg:address":"3210 San Mateo Blvd NE",
    "sg:city":"Albuquerque",
    "sg:classifiers":[
        {
            "category":"Shopping",
            "subcategory":"Bicycles & Sporting Goods",
            "type":"Retail Goods"
        }
    ],
    "sg:phone":"+1 505 881 1170",
    "sg:postcode":"87110",
    "sg:province":"NM",
    "sg:tags":[
        "equipment",
        "skateboard"
    ],
    "wof:name":"Duke City Skate Shop",
    "wof:placetype":"venue"
},
  "geometry": {"coordinates":[-106.586341,35.118381],"type":"Point"}
}