{
  "type": "Feature",
  "properties": {
    "iso:country":"US",
    "sg:address":"9200 Susan Ave SE",
    "sg:city":"Albuquerque",
    "sg:classifiers":[
        {
            "category":"Manufacturing",
            "subcategory":"Metals",
            "type":"Manufacturing & Wholesale Goods"
        }
    ],
    "sg:phone":"+1 505 271 2311",
    "sg:postcode":"87123",
    "sg:province":"NM",
    "sg:tags":[
        "metalwork",
        "architectural",
        "mfg"
    ],
    "wof:name":"High Desert Iron Works",
    "wof:placetype":"venue"
},
  "geometry": {"coordinates":[-106.544487,35.067747],"type":"Point"}
}