{
  "type": "Feature",
  "properties": {
    "iso:country":"US",
    "sg:address":"3929 Camino Alameda SW",
    "sg:city":"Albuquerque",
    "sg:classifiers":[
        {
            "category":"Shopping",
            "subcategory":"Bicycles & Sporting Goods",
            "type":"Retail Goods"
        },
        {
            "category":"Personal",
            "subcategory":"Sauna",
            "type":"Services"
        }
    ],
    "sg:phone":"+1 505 452 8441",
    "sg:postcode":"87105",
    "sg:province":"NM",
    "sg:tags":[
        "equipment",
        "swimming",
        "pool",
        "supply"
    ],
    "sg:website":"http://www.roybalpoolcovers.com",
    "wof:name":"Roybal Pool Covers",
    "wof:placetype":"venue"
},
  "geometry": {"coordinates":[-106.69222600000001,35.017645],"type":"Point"}
}