{
  "type": "Feature",
  "properties": {
    "iso:country":"US",
    "sg:address":"3306 W Hwy 66",
    "sg:city":"Gallup",
    "sg:classifiers":[
        {
            "category":"Travel",
            "subcategory":"Hotels & Motels",
            "type":"Entertainment"
        }
    ],
    "sg:phone":"+1 505 863 4492",
    "sg:postcode":"87301",
    "sg:province":"NM",
    "wof:name":"Motel 6",
    "wof:placetype":"venue"
},
  "geometry": {"coordinates":[-108.82745300000001,35.509048],"type":"Point"}
}