{
  "type": "Feature",
  "properties": {
    "iso:country":"US",
    "sg:address":"1504 Bridge Blvd SW",
    "sg:city":"Albuquerque",
    "sg:classifiers":[
        {
            "category":"Professional",
            "subcategory":"Lawyer & Legal Services",
            "type":"Services"
        }
    ],
    "sg:phone":"+1 505 247 8804",
    "sg:postcode":"87105",
    "sg:province":"NM",
    "sg:tags":[
        "attorney"
    ],
    "wof:name":"Sosa Law Firm PA",
    "wof:placetype":"venue"
},
  "geometry": {"coordinates":[-106.678572,35.065518],"type":"Point"}
}