{
  "type": "Feature",
  "properties": {
    "iso:country":"US",
    "sg:address":"11 Cll Medico",
    "sg:city":"Santa Fe",
    "sg:classifiers":[
        {
            "category":"Health Services",
            "subcategory":"Health Practitioner",
            "type":"Services"
        }
    ],
    "sg:phone":"+1 505 986 9123",
    "sg:postcode":"87505",
    "sg:province":"NM",
    "wof:name":"Sahlfeld C Bear",
    "wof:placetype":"venue"
},
  "geometry": {"coordinates":[-105.941279,35.658208],"type":"Point"}
}