{
  "type": "Feature",
  "properties": {
    "iso:country":"US",
    "sg:address":"38 Rd 3020",
    "sg:city":"Aztec",
    "sg:classifiers":[
        {
            "category":"Building & Trades",
            "subcategory":"Electrical",
            "type":"Services"
        }
    ],
    "sg:phone":"+1 505 334 8892",
    "sg:postcode":"87410",
    "sg:province":"NM",
    "sg:tags":[
        "electric",
        "contractor"
    ],
    "wof:name":"Townsend Electric Inc",
    "wof:placetype":"venue"
},
  "geometry": {"coordinates":[-108.025043,36.813161],"type":"Point"}
}