{
  "type": "Feature",
  "properties": {
    "addr:full":"1143 Montoya St NW Albuquerque NM 87104",
    "addr:housenumber":"1143",
    "addr:postcode":"87104",
    "addr:street":"Montoya St Nw",
    "iso:country":"US",
    "sg:address":"1143 Montoya St NW",
    "sg:city":"Albuquerque",
    "sg:classifiers":[
        {
            "category":"Building & Trades",
            "subcategory":"Cleaning & Sanitation",
            "type":"Services"
        }
    ],
    "sg:phone":"+1 505 843 8416",
    "sg:postcode":"87104",
    "sg:province":"NM",
    "sg:tags":[
        "maintenance"
    ],
    "wof:name":"Giselas House Cleaning",
    "wof:placetype":"venue"
},
  "geometry": {"coordinates":[-106.677021,35.105655],"type":"Point"}
}