{
  "type": "Feature",
  "properties": {
    "addr:full":"1645 N Grayson St Hobbs NM 88240",
    "addr:housenumber":"1645",
    "addr:postcode":"88240",
    "addr:street":"N Grayson St",
    "iso:country":"US",
    "sg:address":"1645 N Grayson St",
    "sg:city":"Hobbs",
    "sg:classifiers":[
        {
            "category":"Manufacturing",
            "subcategory":"Toys & Sporting Goods",
            "type":"Manufacturing & Wholesale Goods"
        }
    ],
    "sg:phone":"+1 505 397 7019",
    "sg:postcode":"88240",
    "sg:province":"NM",
    "sg:tags":[
        "stuffed",
        "doll"
    ],
    "wof:name":"Oh Baby",
    "wof:placetype":"venue"
},
  "geometry": {"coordinates":[-103.115354,32.71916],"type":"Point"}
}