{
  "type": "Feature",
  "properties": {
    "iso:country":"US",
    "sg:address":"5408 Chapel Dr NW",
    "sg:city":"Albuquerque",
    "sg:classifiers":[
        {
            "category":"Shopping",
            "subcategory":"Hobbies, Toys, & Games",
            "type":"Retail Goods"
        }
    ],
    "sg:phone":"+1 505 890 0618",
    "sg:postcode":"87114",
    "sg:province":"NM",
    "wof:name":"Mesa Arts",
    "wof:placetype":"venue"
},
  "geometry": {"coordinates":[-106.697713,35.201011],"type":"Point"}
}