{
  "type": "Feature",
  "properties": {
    "addr:full":"612 N Roselawn Ave Artesia NM 88210",
    "addr:housenumber":"612",
    "addr:postcode":"88210",
    "addr:street":"N Roselawn Ave",
    "iso:country":"US",
    "sg:address":"612 N Roselawn Ave",
    "sg:city":"Artesia",
    "sg:classifiers":[
        {
            "category":"Government",
            "subcategory":"Office",
            "type":"Public Place"
        }
    ],
    "sg:phone":"+1 505 746 9821",
    "sg:postcode":"88210",
    "sg:province":"NM",
    "sg:tags":[
        "village"
    ],
    "wof:name":"Artesia City Warehouse",
    "wof:placetype":"venue"
},
  "geometry": {"coordinates":[-104.399804,32.8484],"type":"Point"}
}