{
  "type": "Feature",
  "properties": {
    "iso:country":"US",
    "sg:address":"3612 Isleta Blvd SW",
    "sg:city":"Albuquerque",
    "sg:classifiers":[
        {
            "category":"Retail",
            "subcategory":"Auto Repair",
            "type":"Services"
        }
    ],
    "sg:phone":"+1 505 452 9133",
    "sg:postcode":"87105",
    "sg:province":"NM",
    "sg:tags":[
        "general"
    ],
    "wof:name":"J & G Auto & Truck Transm Repr",
    "wof:placetype":"venue"
},
  "geometry": {"coordinates":[-106.681531,35.02329],"type":"Point"}
}