{
  "type": "Feature",
  "properties": {
    "addr:full":"1106 N Main St Clovis NM 88101",
    "addr:housenumber":"1106",
    "addr:postcode":"88101",
    "addr:street":"N Main St",
    "iso:country":"US",
    "sg:address":"1106 N Main St",
    "sg:city":"Clovis",
    "sg:classifiers":[
        {
            "category":"Professional",
            "subcategory":"Computer Services",
            "type":"Services"
        }
    ],
    "sg:phone":"+1 505 763 4411",
    "sg:postcode":"88101",
    "sg:province":"NM",
    "sg:tags":[
        "internet"
    ],
    "wof:name":"Cox Communications",
    "wof:placetype":"venue"
},
  "geometry": {"coordinates":[-103.205443,34.409871],"type":"Point"}
}