{
  "type": "Feature",
  "properties": {
    "addr:full":"66 Rd 6050 Farmington NM 87401",
    "addr:housenumber":"66",
    "addr:postcode":"87401",
    "addr:street":"Rd 6050",
    "iso:country":"US",
    "sg:address":"66 Rd 6050",
    "sg:city":"Farmington",
    "sg:classifiers":[
        {
            "category":"Shopping",
            "type":"Retail Goods"
        }
    ],
    "sg:phone":"+1 505 598 6547",
    "sg:postcode":"87401",
    "sg:province":"NM",
    "sg:tags":[
        "cosmetic",
        "perfume"
    ],
    "wof:name":"Mary Kay Cosmetics",
    "wof:placetype":"venue"
},
  "geometry": {"coordinates":[-108.305409,36.728825],"type":"Point"}
}