{
  "type": "Feature",
  "properties": {
    "iso:country":"US",
    "sg:address":"4801 McMahon Blvd NW",
    "sg:city":"Albuquerque",
    "sg:classifiers":[
        {
            "category":"Health Services",
            "subcategory":"Health Practitioner",
            "type":"Services"
        }
    ],
    "sg:phone":"+1 505 727 2600",
    "sg:postcode":"87114",
    "sg:province":"NM",
    "wof:name":"Christine T Blaser Rn Cfnp",
    "wof:placetype":"venue"
},
  "geometry": {"coordinates":[-106.679016,35.207163],"type":"Point"}
}