{
  "type": "Feature",
  "properties": {
    "iso:country":"US",
    "sg:address":"4718 Hilltop Pl NE",
    "sg:city":"Albuquerque",
    "sg:classifiers":[
        {
            "category":"Professional",
            "type":"Services"
        }
    ],
    "sg:phone":"+1 505 323 1652",
    "sg:postcode":"87111",
    "sg:province":"NM",
    "sg:tags":[
        "establishment"
    ],
    "wof:name":"Home Savers Of Nm",
    "wof:placetype":"venue"
},
  "geometry": {"coordinates":[-106.494077,35.133024],"type":"Point"}
}