{
  "type": "Feature",
  "properties": {
    "iso:country":"US",
    "sg:address":"105 E Grand Ave",
    "sg:city":"Clovis",
    "sg:classifiers":[
        {
            "category":"Social Services",
            "type":"Services"
        }
    ],
    "sg:phone":"+1 505 742 3337",
    "sg:postcode":"88101",
    "sg:province":"NM",
    "sg:tags":[
        "organization",
        "welfare"
    ],
    "wof:name":"Big Brothers Big Sisters",
    "wof:placetype":"venue"
},
  "geometry": {"coordinates":[-103.205293,34.40067],"type":"Point"}
}