{
  "type": "Feature",
  "properties": {
    "iso:country":"US",
    "sg:address":"212 W Broadway St",
    "sg:city":"Silver City",
    "sg:classifiers":[
        {
            "category":"Shopping",
            "subcategory":"Used Merchandise",
            "type":"Retail Goods"
        }
    ],
    "sg:phone":"+1 505 538 4388",
    "sg:postcode":"88061",
    "sg:province":"NM",
    "sg:tags":[
        "antique"
    ],
    "wof:name":"Valencia Antiques",
    "wof:placetype":"venue"
},
  "geometry": {"coordinates":[-108.277833,32.769951],"type":"Point"}
}