{
  "type": "Feature",
  "properties": {
    "iso:country":"US",
    "sg:address":"130 N 2nd St",
    "sg:city":"Raton",
    "sg:classifiers":[
        {
            "category":"Professional",
            "subcategory":"Lawyer & Legal Services",
            "type":"Services"
        }
    ],
    "sg:phone":"+1 505 445 0000",
    "sg:postcode":"87740",
    "sg:province":"NM",
    "sg:tags":[
        "attorney"
    ],
    "wof:name":"Montoya Law Offices",
    "wof:placetype":"venue"
},
  "geometry": {"coordinates":[-104.439509,36.902607],"type":"Point"}
}