{
  "type": "Feature",
  "properties": {
    "iso:country":"US",
    "sg:address":"9221 Arvada Ave NE",
    "sg:city":"Albuquerque",
    "sg:classifiers":[
        {
            "category":"Professional",
            "subcategory":"Business Services",
            "type":"Services"
        }
    ],
    "sg:phone":"+1 505 299 9357",
    "sg:postcode":"87112",
    "sg:province":"NM",
    "wof:name":"Bonds Oil Co L L C",
    "wof:placetype":"venue"
},
  "geometry": {"coordinates":[-106.53776499999999,35.10473],"type":"Point"}
}