{
  "type": "Feature",
  "properties": {
    "iso:country":"US",
    "sg:address":"301 S 1st St",
    "sg:city":"Artesia",
    "sg:classifiers":[
        {
            "category":"Autos & Motor Vehicles",
            "subcategory":"Automobile Sales",
            "type":"Retail Goods"
        }
    ],
    "sg:phone":"+1 505 748 3665",
    "sg:postcode":"88210",
    "sg:province":"NM",
    "sg:tags":[
        "car",
        "dealer"
    ],
    "wof:name":"J & D's Auto Sales",
    "wof:placetype":"venue"
},
  "geometry": {"coordinates":[-104.397324,32.840184],"type":"Point"}
}