{
  "type": "Feature",
  "properties": {
    "iso:country":"US",
    "sg:address":"4432 Rio Trumperos Ct NW",
    "sg:city":"Albuquerque",
    "sg:classifiers":[
        {
            "category":"Social Services",
            "type":"Services"
        }
    ],
    "sg:phone":"+1 505 350 1815",
    "sg:postcode":"87120",
    "sg:province":"NM",
    "sg:tags":[
        "crisis",
        "intervention"
    ],
    "wof:name":"Frontline Crisis Intervention",
    "wof:placetype":"venue"
},
  "geometry": {"coordinates":[-106.686495,35.170007],"type":"Point"}
}