{
  "type": "Feature",
  "properties": {
    "iso:country":"US",
    "sg:address":"200 W Santa Fe Ave",
    "sg:city":"Grants",
    "sg:classifiers":[
        {
            "category":"Insurance",
            "subcategory":"Insurance Agent",
            "type":"Services"
        }
    ],
    "sg:phone":"+1 505 287 9449",
    "sg:postcode":"87020",
    "sg:province":"NM",
    "wof:name":"Farmers Insurance Group",
    "wof:placetype":"venue"
},
  "geometry": {"coordinates":[-107.85154199999999,35.15143],"type":"Point"}
}