{
  "type": "Feature",
  "properties": {
    "addr:full":"4600 Montgomery Blvd NE 101A Albuquerque NM 87109",
    "addr:housenumber":"4600;101a",
    "addr:postcode":"87109",
    "addr:street":"Montgomery Blvd Ne",
    "iso:country":"US",
    "sg:address":"4600 Montgomery Blvd NE 101A",
    "sg:city":"Albuquerque",
    "sg:classifiers":[
        {
            "category":"Health Services",
            "subcategory":"Doctor",
            "type":"Services"
        },
        {
            "category":"Health Services",
            "subcategory":"Clinic",
            "type":"Services"
        }
    ],
    "sg:phone":"+1 505 884 9687",
    "sg:postcode":"87109",
    "sg:province":"NM",
    "sg:tags":[
        "physician",
        "surgeon",
        "osteopathic"
    ],
    "wof:name":"Southwest Womens Sonography",
    "wof:placetype":"venue"
},
  "geometry": {"coordinates":[-106.59187300000001,35.130859],"type":"Point"}
}