{
  "type": "Feature",
  "properties": {
    "iso:country":"US",
    "sg:address":"313 E Jemez St",
    "sg:city":"Hobbs",
    "sg:classifiers":[
        {
            "category":"Real Estate",
            "subcategory":"Real Estate Agent",
            "type":"Services"
        }
    ],
    "sg:phone":"+1 505 397 4444",
    "sg:postcode":"88240",
    "sg:province":"NM",
    "wof:name":"Lovelady Gaylon Real Estate",
    "wof:placetype":"venue"
},
  "geometry": {"coordinates":[-103.134276,32.724264],"type":"Point"}
}