{
  "type": "Feature",
  "properties": {
    "iso:country":"US",
    "sg:address":"3801 Carlisle Blvd NE",
    "sg:city":"Albuquerque",
    "sg:classifiers":[
        {
            "category":"Communications",
            "subcategory":"Television Station",
            "type":"Services"
        }
    ],
    "sg:phone":"+1 505 884 7777",
    "sg:postcode":"87107",
    "sg:province":"NM",
    "sg:tags":[
        "broadcasting",
        "co"
    ],
    "wof:name":"Action 7 News",
    "wof:placetype":"venue"
},
  "geometry": {"coordinates":[-106.604113,35.124338],"type":"Point"}
}