{
  "type": "Feature",
  "properties": {
    "addr:full":"3500 Comanche Rd NE Albuquerque NM 87107",
    "addr:housenumber":"3500",
    "addr:postcode":"87107",
    "addr:street":"Comanche Rd Ne",
    "iso:country":"US",
    "sg:address":"3500 Comanche Rd NE",
    "sg:city":"Albuquerque",
    "sg:classifiers":[
        {
            "category":"Personal",
            "type":"Services"
        }
    ],
    "sg:phone":"+1 505 379 7830",
    "sg:postcode":"87107",
    "sg:province":"NM",
    "sg:tags":[
        "therapist",
        "massage"
    ],
    "wof:name":"Circle Of Grace",
    "wof:placetype":"venue"
},
  "geometry": {"coordinates":[-106.605183,35.12368],"type":"Point"}
}