{
  "type": "Feature",
  "properties": {
    "addr:full":"318 Buena Vista Dr Ruidoso NM 88346",
    "addr:housenumber":"318",
    "addr:postcode":"88346",
    "addr:street":"Buena Vista Dr",
    "iso:country":"US",
    "sg:address":"318 Buena Vista Dr",
    "sg:city":"Ruidoso",
    "sg:classifiers":[
        {
            "category":"Health Services",
            "subcategory":"Doctor",
            "type":"Services"
        }
    ],
    "sg:phone":"+1 505 336 7818",
    "sg:postcode":"88346",
    "sg:province":"NM",
    "sg:tags":[
        "physician",
        "surgeon"
    ],
    "wof:name":"Radiology Assoc Of Alb",
    "wof:placetype":"venue"
},
  "geometry": {"coordinates":[-105.656582,33.396537],"type":"Point"}
}