{
  "type": "Feature",
  "properties": {
    "iso:country":"US",
    "sg:address":"695 Bluebird Ln NE",
    "sg:city":"Albuquerque",
    "sg:classifiers":[
        {
            "category":"Professional",
            "subcategory":"Management & Consulting",
            "type":"Services"
        }
    ],
    "sg:phone":"+1 505 856 7330",
    "sg:postcode":"87122",
    "sg:province":"NM",
    "wof:name":"Advisors For Impact Inc",
    "wof:placetype":"venue"
},
  "geometry": {"coordinates":[-106.490245,35.183187],"type":"Point"}
}