{
  "type": "Feature",
  "properties": {
    "iso:country":"US",
    "sg:address":"322 E Yeso Dr",
    "sg:city":"Hobbs",
    "sg:classifiers":[
        {
            "category":"Professional",
            "type":"Services"
        }
    ],
    "sg:phone":"+1 505 391 7573",
    "sg:postcode":"88240",
    "sg:province":"NM",
    "wof:name":"JBC Svc",
    "wof:placetype":"venue"
},
  "geometry": {"coordinates":[-103.134032,32.714583],"type":"Point"}
}