{
  "type": "Feature",
  "properties": {
    "iso:country":"US",
    "sg:address":"610 Lamb St",
    "sg:city":"Silver City",
    "sg:classifiers":[
        {
            "category":"Building & Trades",
            "subcategory":"Construction",
            "type":"Services"
        }
    ],
    "sg:phone":"+1 505 534 4455",
    "sg:postcode":"88061",
    "sg:province":"NM",
    "sg:tags":[
        "plastering",
        "contractor"
    ],
    "wof:name":"G One Plastering",
    "wof:placetype":"venue"
},
  "geometry": {"coordinates":[-108.26897099999999,32.786508],"type":"Point"}
}