{
  "type": "Feature",
  "properties": {
    "iso:country":"US",
    "sg:address":"821 Beta St",
    "sg:city":"Clovis",
    "sg:classifiers":[
        {
            "category":"Real Estate",
            "subcategory":"Real Estate Operator",
            "type":"Services"
        }
    ],
    "sg:phone":"+1 505 763 7581",
    "sg:postcode":"88101",
    "sg:province":"NM",
    "sg:tags":[
        "apartment"
    ],
    "wof:name":"Sand & Sage Apartments",
    "wof:placetype":"venue"
},
  "geometry": {"coordinates":[-103.227242,34.404675],"type":"Point"}
}