{
  "type": "Feature",
  "properties": {
    "iso:country":"US",
    "sg:address":"2008 King Ct NE",
    "sg:city":"Albuquerque",
    "sg:classifiers":[
        {
            "category":"Professional",
            "subcategory":"Employment Agencies",
            "type":"Services"
        }
    ],
    "sg:phone":"+1 505 724 2071",
    "sg:postcode":"87112",
    "sg:province":"NM",
    "sg:tags":[
        "employer"
    ],
    "wof:name":"Association For Practitioners Of Infection Control And Epitemiology Of Nm",
    "wof:placetype":"venue"
},
  "geometry": {"coordinates":[-106.501456,35.105759],"type":"Point"}
}