{
  "type": "Feature",
  "properties": {
    "addr:full":"4704 Rincon Pl NW Albuquerque NM 87105",
    "addr:housenumber":"4704",
    "addr:postcode":"87105",
    "addr:street":"Rincon Pl Nw",
    "iso:country":"US",
    "sg:address":"4704 Rincon Pl NW",
    "sg:city":"Albuquerque",
    "sg:classifiers":[
        {
            "category":"Building & Trades",
            "subcategory":"Landscaping Services",
            "type":"Services"
        }
    ],
    "sg:phone":"+1 505 328 6211",
    "sg:postcode":"87105",
    "sg:province":"NM",
    "wof:name":"Rbb of Albuquerque",
    "wof:placetype":"venue"
},
  "geometry": {"coordinates":[-106.69182000000001,35.087748],"type":"Point"}
}