{
  "type": "Feature",
  "properties": {
    "iso:country":"US",
    "sg:address":"6401 Menaul Blvd NE",
    "sg:city":"Albuquerque",
    "sg:classifiers":[
        {
            "category":"Retail",
            "subcategory":"Veterinary Services",
            "type":"Services"
        }
    ],
    "sg:phone":"+1 505 881 3030",
    "sg:postcode":"87110",
    "sg:province":"NM",
    "wof:name":"Richard A Heise",
    "wof:placetype":"venue"
},
  "geometry": {"coordinates":[-106.57205,35.109105],"type":"Point"}
}