{
  "type": "Feature",
  "properties": {
    "iso:country":"US",
    "sg:address":"2007 E Aztec Ave",
    "sg:city":"Gallup",
    "sg:classifiers":[
        {
            "category":"Organizations",
            "subcategory":"Community Association",
            "type":"Services"
        }
    ],
    "sg:phone":"+1 505 722 8917",
    "sg:postcode":"87301",
    "sg:province":"NM",
    "sg:tags":[
        "club"
    ],
    "wof:name":"New Beginning Club",
    "wof:placetype":"venue"
},
  "geometry": {"coordinates":[-108.71179100000001,35.52821],"type":"Point"}
}