{
  "type": "Feature",
  "properties": {
    "iso:country":"US",
    "sg:address":"1310 W Spruce St",
    "sg:city":"Deming",
    "sg:classifiers":[
        {
            "category":"Restaurant",
            "type":"Food & Drink"
        }
    ],
    "sg:phone":"+1 505 546 2184",
    "sg:postcode":"88030",
    "sg:province":"NM",
    "wof:name":"USA Petroleum Corp",
    "wof:placetype":"venue"
},
  "geometry": {"coordinates":[-107.774816,32.266783],"type":"Point"}
}