{
  "type": "Feature",
  "properties": {
    "iso:country":"US",
    "sg:address":"3310 Sierra Dr NE",
    "sg:city":"Albuquerque",
    "sg:classifiers":[
        {
            "category":"Building & Trades",
            "subcategory":"Plumbing",
            "type":"Services"
        }
    ],
    "sg:phone":"+1 505 888 1688",
    "sg:postcode":"87110",
    "sg:province":"NM",
    "sg:tags":[
        "conditioning",
        "air",
        "system",
        "contractor"
    ],
    "wof:name":"C & L Mechanical Svc",
    "wof:placetype":"venue"
},
  "geometry": {"coordinates":[-106.596684,35.121367],"type":"Point"}
}