{
  "type": "Feature",
  "properties": {
    "addr:full":"1403 W James Ave Artesia NM 88210",
    "addr:housenumber":"1403",
    "addr:postcode":"88210",
    "addr:street":"W James Ave",
    "iso:country":"US",
    "sg:address":"1403 W James Ave",
    "sg:city":"Artesia",
    "sg:classifiers":[
        {
            "category":"Building & Trades",
            "subcategory":"Construction",
            "type":"Services"
        }
    ],
    "sg:phone":"+1 505 746 1347",
    "sg:postcode":"88210",
    "sg:province":"NM",
    "sg:tags":[
        "general",
        "contractor"
    ],
    "wof:name":"Catano Construction",
    "wof:placetype":"venue"
},
  "geometry": {"coordinates":[-104.41647399999999,32.848443],"type":"Point"}
}