{
  "type": "Feature",
  "properties": {
    "iso:country":"US",
    "sg:address":"8001 Rancho Dorado Ct NW",
    "sg:city":"Albuquerque",
    "sg:classifiers":[
        {
            "category":"Professional",
            "subcategory":"Art Services",
            "type":"Services"
        }
    ],
    "sg:phone":"+1 505 890 7755",
    "sg:postcode":"87120",
    "sg:province":"NM",
    "wof:name":"Media Matched Inc",
    "wof:placetype":"venue"
},
  "geometry": {"coordinates":[-106.68465,35.175293],"type":"Point"}
}