{
  "type": "Feature",
  "properties": {
    "iso:country":"US",
    "sg:address":"301 Carver Rd",
    "sg:city":"Las Cruces",
    "sg:classifiers":[
        {
            "category":"Retail",
            "subcategory":"Auto Repair",
            "type":"Services"
        }
    ],
    "sg:phone":"+1 505 524 6951",
    "sg:postcode":"88005",
    "sg:province":"NM",
    "sg:tags":[
        "automobile",
        "electric"
    ],
    "wof:name":"K & S Automotive Electric",
    "wof:placetype":"venue"
},
  "geometry": {"coordinates":[-106.760607,32.260213],"type":"Point"}
}