{
  "type": "Feature",
  "properties": {
    "iso:country":"US",
    "sg:address":"129 Westerfield Pl",
    "sg:city":"Clovis",
    "sg:classifiers":[
        {
            "category":"Retail",
            "subcategory":"Portrait Studio",
            "type":"Services"
        }
    ],
    "sg:phone":"+1 505 763 3368",
    "sg:postcode":"88101",
    "sg:province":"NM",
    "sg:tags":[
        "photographer"
    ],
    "wof:name":"Unique Photography",
    "wof:placetype":"venue"
},
  "geometry": {"coordinates":[-103.217965,34.425622],"type":"Point"}
}