{
  "type": "Feature",
  "properties": {
    "iso:country":"US",
    "sg:address":"201 E Lohman Ave",
    "sg:city":"Las Cruces",
    "sg:classifiers":[
        {
            "category":"Building & Trades",
            "subcategory":"Equipment Rental",
            "type":"Services"
        }
    ],
    "sg:phone":"+1 505 523 9700",
    "sg:postcode":"88001",
    "sg:province":"NM",
    "sg:tags":[
        "leasing"
    ],
    "wof:name":"Aarons F165",
    "wof:placetype":"venue"
},
  "geometry": {"coordinates":[-106.777097,32.306447],"type":"Point"}
}