{
  "type": "Feature",
  "properties": {
    "addr:full":"1208 Pile St Clovis NM 88101",
    "addr:housenumber":"1208",
    "addr:postcode":"88101",
    "addr:street":"Pile St",
    "iso:country":"US",
    "sg:address":"1208 Pile St",
    "sg:city":"Clovis",
    "sg:classifiers":[
        {
            "category":"Organizations",
            "subcategory":"Religious Organization",
            "type":"Services"
        }
    ],
    "sg:phone":"+1 505 769 1755",
    "sg:postcode":"88101",
    "sg:province":"NM",
    "sg:tags":[
        "church"
    ],
    "wof:name":"District Supt Methodist Church",
    "wof:placetype":"venue"
},
  "geometry": {"coordinates":[-103.20410800000001,34.410899],"type":"Point"}
}