{
  "type": "Feature",
  "properties": {
    "addr:full":"11317 Baja Dr NE Albuquerque NM 87111",
    "addr:housenumber":"11317",
    "addr:postcode":"87111",
    "addr:street":"Baja Dr Ne",
    "iso:country":"US",
    "sg:address":"11317 Baja Dr NE",
    "sg:city":"Albuquerque",
    "sg:classifiers":[
        {
            "category":"Building & Trades",
            "subcategory":"Construction",
            "type":"Services"
        }
    ],
    "sg:phone":"+1 505 304 6709",
    "sg:postcode":"87111",
    "sg:province":"NM",
    "sg:tags":[
        "repairing",
        "remodeling",
        "contractor"
    ],
    "wof:name":"J R Remodeling & Home Repair",
    "wof:placetype":"venue"
},
  "geometry": {"coordinates":[-106.51155900000001,35.134839],"type":"Point"}
}