{
  "type": "Feature",
  "properties": {
    "addr:full":"601 Espanola St NE Albuquerque NM 87108",
    "addr:housenumber":"601",
    "addr:postcode":"87108",
    "addr:street":"Espanola St Ne",
    "iso:country":"US",
    "sg:address":"601 Espanola St NE",
    "sg:city":"Albuquerque",
    "sg:classifiers":[
        {
            "category":"Social Services",
            "subcategory":"Child Care",
            "type":"Services"
        }
    ],
    "sg:phone":"+1 505 256 8401",
    "sg:postcode":"87108",
    "sg:province":"NM",
    "sg:tags":[
        "day"
    ],
    "wof:name":"Day Night Express",
    "wof:placetype":"venue"
},
  "geometry": {"coordinates":[-106.564165,35.085419],"type":"Point"}
}