{
  "type": "Feature",
  "properties": {
    "addr:full":"64 Yakima Rd Dexter NM 88230",
    "addr:housenumber":"64",
    "addr:postcode":"88230",
    "addr:street":"Yakima Rd",
    "iso:country":"US",
    "sg:address":"64 Yakima Rd",
    "sg:city":"Dexter",
    "sg:classifiers":[
        {
            "category":"Museum",
            "type":"Entertainment"
        }
    ],
    "sg:phone":"+1 505 347 2200",
    "sg:postcode":"88230",
    "sg:province":"NM",
    "wof:name":"UFO City",
    "wof:placetype":"venue"
},
  "geometry": {"coordinates":[-104.46186299999999,33.301142],"type":"Point"}
}