{
  "type": "Feature",
  "properties": {
    "iso:country":"US",
    "sg:address":"451 Cam del Monte Sol",
    "sg:city":"Santa Fe",
    "sg:classifiers":[
        {
            "category":"Health Services",
            "subcategory":"Clinic",
            "type":"Services"
        }
    ],
    "sg:phone":"+1 505 982 0036",
    "sg:postcode":"87505",
    "sg:province":"NM",
    "sg:tags":[
        "home",
        "care"
    ],
    "wof:name":"Santa Fe Forum",
    "wof:placetype":"venue"
},
  "geometry": {"coordinates":[-105.925358,35.67792],"type":"Point"}
}