{
  "type": "Feature",
  "properties": {
    "addr:full":"6458 Seven Rivers Hwy Artesia NM 88210",
    "addr:housenumber":"6458",
    "addr:postcode":"88210",
    "addr:street":"Seven Rivers Hwy",
    "iso:country":"US",
    "sg:address":"6458 Seven Rivers Hwy",
    "sg:city":"Artesia",
    "sg:classifiers":[
        {
            "category":"Farming",
            "subcategory":"Dairy Farm",
            "type":"Manufacturing & Wholesale Goods"
        }
    ],
    "sg:phone":"+1 505 748 2740",
    "sg:postcode":"88210",
    "sg:province":"NM",
    "wof:name":"Zia Dairy Inc",
    "wof:placetype":"venue"
},
  "geometry": {"coordinates":[-104.395554,32.779967],"type":"Point"}
}