{
  "type": "Feature",
  "properties": {
    "iso:country":"US",
    "sg:address":"4508 Waynesboro Rd NW",
    "sg:city":"Albuquerque",
    "sg:classifiers":[
        {
            "category":"Banks & Credit Unions",
            "subcategory":"Investment Brokerage",
            "type":"Services"
        }
    ],
    "sg:phone":"+1 505 883 1373",
    "sg:postcode":"87120",
    "sg:province":"NM",
    "sg:tags":[
        "advisory"
    ],
    "wof:name":"Invest Long & Prosper Ic",
    "wof:placetype":"venue"
},
  "geometry": {"coordinates":[-106.688465,35.175929],"type":"Point"}
}