{
  "type": "Feature",
  "properties": {
    "iso:country":"US",
    "sg:address":"6361 Weisner Rd",
    "sg:city":"Las Cruces",
    "sg:classifiers":[
        {
            "category":"Retail",
            "subcategory":"Auto Repair",
            "type":"Services"
        }
    ],
    "sg:phone":"+1 505 382 5055",
    "sg:postcode":"88012",
    "sg:province":"NM",
    "sg:tags":[
        "wrecker"
    ],
    "wof:name":"Atomic Towing",
    "wof:placetype":"venue"
},
  "geometry": {"coordinates":[-106.657298,32.416426],"type":"Point"}
}