{
  "type": "Feature",
  "properties": {
    "iso:country":"US",
    "sg:address":"23 Old Agua Fria Rd E",
    "sg:city":"Santa Fe",
    "sg:classifiers":[
        {
            "category":"Professional",
            "type":"Services"
        }
    ],
    "sg:phone":"+1 505 982 2368",
    "sg:postcode":"87508",
    "sg:province":"NM",
    "wof:name":"Evangeline Pacheco",
    "wof:placetype":"venue"
},
  "geometry": {"coordinates":[-105.920951,35.623014],"type":"Point"}
}