{
  "type": "Feature",
  "properties": {
    "iso:country":"US",
    "sg:address":"2501 Southern Blvd SE",
    "sg:city":"Rio Rancho",
    "sg:classifiers":[
        {
            "category":"Personal",
            "subcategory":"Tattoo Parlor",
            "type":"Services"
        }
    ],
    "sg:phone":"+1 505 896 0881",
    "sg:postcode":"87124",
    "sg:province":"NM",
    "sg:tags":[
        "tattooing"
    ],
    "wof:name":"Fear Not Tattoo & Piercing",
    "wof:placetype":"venue"
},
  "geometry": {"coordinates":[-106.686556,35.241583],"type":"Point"}
}