{
  "type": "Feature",
  "properties": {
    "iso:country":"US",
    "sg:address":"11608 Woodmar Ln NE",
    "sg:city":"Albuquerque",
    "sg:classifiers":[
        {
            "category":"Professional",
            "subcategory":"Advertising",
            "type":"Services"
        }
    ],
    "sg:phone":"+1 505 332 3116",
    "sg:postcode":"87111",
    "sg:province":"NM",
    "sg:tags":[
        "agency"
    ],
    "wof:name":"Karsh & Hagan Inc",
    "wof:placetype":"venue"
},
  "geometry": {"coordinates":[-106.510841,35.152073],"type":"Point"}
}