{
  "type": "Feature",
  "properties": {
    "iso:country":"US",
    "sg:address":"8671 Rio Grande Blvd NW",
    "sg:city":"Albuquerque",
    "sg:classifiers":[
        {
            "category":"Building & Trades",
            "subcategory":"Construction",
            "type":"Services"
        }
    ],
    "sg:phone":"+1 505 792 5566",
    "sg:postcode":"87114",
    "sg:province":"NM",
    "sg:tags":[
        "house"
    ],
    "wof:name":"Mrp Design & Construction Inc",
    "wof:placetype":"venue"
},
  "geometry": {"coordinates":[-106.642972,35.183695],"type":"Point"}
}