{
  "type": "Feature",
  "properties": {
    "iso:country":"US",
    "sg:address":"1717 Fairgrounds Rd",
    "sg:city":"Farmington",
    "sg:classifiers":[
        {
            "category":"Building & Trades",
            "subcategory":"Landscaping Services",
            "type":"Services"
        }
    ],
    "sg:phone":"+1 505 402 1383",
    "sg:postcode":"87401",
    "sg:province":"NM",
    "sg:tags":[
        "landscape",
        "contractor"
    ],
    "wof:name":"Stock & Son Solution Svc",
    "wof:placetype":"venue"
},
  "geometry": {"coordinates":[-108.185053,36.747026],"type":"Point"}
}