{
  "type": "Feature",
  "properties": {
    "iso:country":"US",
    "sg:address":"805 Hueco St",
    "sg:city":"Carlsbad",
    "sg:classifiers":[
        {
            "category":"Real Estate",
            "subcategory":"Real Estate Operator",
            "type":"Services"
        }
    ],
    "sg:phone":"+1 505 885 8204",
    "sg:postcode":"88220",
    "sg:province":"NM",
    "sg:tags":[
        "apartment"
    ],
    "wof:name":"Mission Apartments",
    "wof:placetype":"venue"
},
  "geometry": {"coordinates":[-104.236513,32.410316],"type":"Point"}
}