{
  "type": "Feature",
  "properties": {
    "addr:full":"4359 Waking Sky Santa Fe NM 87507",
    "addr:housenumber":"4359",
    "addr:postcode":"87507",
    "addr:street":"Waking Sky",
    "iso:country":"US",
    "sg:address":"4359 Waking Sky",
    "sg:city":"Santa Fe",
    "sg:classifiers":[
        {
            "category":"Communications",
            "subcategory":"Film & Video Production",
            "type":"Services"
        }
    ],
    "sg:phone":"+1 505 424 1501",
    "sg:postcode":"87507",
    "sg:province":"NM",
    "sg:tags":[
        "motion",
        "picture"
    ],
    "wof:name":"Screenwriting Conference",
    "wof:placetype":"venue"
},
  "geometry": {"coordinates":[-106.013289,35.629537],"type":"Point"}
}