{
  "type": "Feature",
  "properties": {
    "iso:country":"US",
    "sg:address":"1504 Michigan Ct NE",
    "sg:city":"Rio Rancho",
    "sg:classifiers":[
        {
            "category":"Professional",
            "subcategory":"Business Services",
            "type":"Services"
        }
    ],
    "sg:phone":"+1 505 994 4096",
    "sg:postcode":"87124",
    "sg:province":"NM",
    "wof:name":"Intelligent By Design",
    "wof:placetype":"venue"
},
  "geometry": {"coordinates":[-106.648078,35.282436],"type":"Point"}
}