{
  "type": "Feature",
  "properties": {
    "addr:full":"1901 Eubank Blvd NE Albuquerque NM 87112",
    "addr:housenumber":"1901",
    "addr:postcode":"87112",
    "addr:street":"Eubank Blvd Ne",
    "iso:country":"US",
    "sg:address":"1901 Eubank Blvd NE",
    "sg:city":"Albuquerque",
    "sg:classifiers":[
        {
            "category":"Retail",
            "subcategory":"Auto Rental",
            "type":"Services"
        }
    ],
    "sg:phone":"+1 505 293 1955",
    "sg:postcode":"87112",
    "sg:province":"NM",
    "sg:tags":[
        "truck",
        "trailer",
        "utility"
    ],
    "wof:name":"U-Haul",
    "wof:placetype":"venue"
},
  "geometry": {"coordinates":[-106.532973,35.103353],"type":"Point"}
}