{
  "type": "Feature",
  "properties": {
    "iso:country":"US",
    "sg:address":"2525 Alamo Ave SE",
    "sg:city":"Albuquerque",
    "sg:classifiers":[
        {
            "category":"Professional",
            "subcategory":"Detective & Security Services",
            "type":"Services"
        }
    ],
    "sg:phone":"+1 505 883 4916",
    "sg:postcode":"87106",
    "sg:province":"NM",
    "sg:tags":[
        "car"
    ],
    "wof:name":"Brinks Incorporated",
    "wof:placetype":"venue"
},
  "geometry": {"coordinates":[-106.618899,35.054595],"type":"Point"}
}