{
  "type": "Feature",
  "properties": {
    "iso:country":"US",
    "sg:address":"1401 S White Sands Blvd",
    "sg:city":"Alamogordo",
    "sg:classifiers":[
        {
            "category":"Restaurant",
            "type":"Food & Drink"
        }
    ],
    "sg:phone":"+1 505 437 8566",
    "sg:postcode":"88310",
    "sg:province":"NM",
    "sg:tags":[
        "eating"
    ],
    "wof:name":"Jose Maria Mexican Food",
    "wof:placetype":"venue"
},
  "geometry": {"coordinates":[-105.961127,32.876232],"type":"Point"}
}