{
  "type": "Feature",
  "properties": {
    "iso:country":"US",
    "sg:address":"4300 San Mateo Blvd NE",
    "sg:city":"Albuquerque",
    "sg:classifiers":[
        {
            "category":"Banks & Credit Unions",
            "subcategory":"Bank",
            "type":"Services"
        }
    ],
    "sg:phone":"+1 505 888 5080",
    "sg:postcode":"87110",
    "sg:province":"NM",
    "sg:tags":[
        "loan",
        "real estate"
    ],
    "wof:name":"Plaza Home Mortgage",
    "wof:placetype":"venue"
},
  "geometry": {"coordinates":[-106.586482,35.13093],"type":"Point"}
}