{
  "type": "Feature",
  "properties": {
    "addr:full":"316 Muriel St NE Albuquerque NM 87123",
    "addr:housenumber":"316",
    "addr:postcode":"87123",
    "addr:street":"Muriel St Ne",
    "iso:country":"US",
    "sg:address":"316 Muriel St NE",
    "sg:city":"Albuquerque",
    "sg:classifiers":[
        {
            "category":"Wholesale",
            "subcategory":"Electrical",
            "type":"Manufacturing & Wholesale Goods"
        }
    ],
    "sg:phone":"+1 505 293 3400",
    "sg:postcode":"87123",
    "sg:province":"NM",
    "sg:tags":[
        "sound",
        "equipment",
        "system"
    ],
    "wof:name":"Technical Support Consultants",
    "wof:placetype":"venue"
},
  "geometry": {"coordinates":[-106.516266,35.075099],"type":"Point"}
}