{
  "type": "Feature",
  "properties": {
    "addr:full":"5809 Menaul Blvd NE Albuquerque NM 87110",
    "addr:housenumber":"5809",
    "addr:postcode":"87110",
    "addr:street":"Menaul Blvd Ne",
    "iso:country":"US",
    "sg:address":"5809 Menaul Blvd NE",
    "sg:city":"Albuquerque",
    "sg:classifiers":[
        {
            "category":"Banks & Credit Unions",
            "subcategory":"Financial Services",
            "type":"Services"
        }
    ],
    "sg:phone":"+1 505 884 4100",
    "sg:postcode":"87110",
    "sg:province":"NM",
    "sg:tags":[
        "payday",
        "loan"
    ],
    "wof:name":"Easy Payday Lones",
    "wof:placetype":"venue"
},
  "geometry": {"coordinates":[-106.579662,35.109191],"type":"Point"}
}