{
  "type": "Feature",
  "properties": {
    "iso:country":"US",
    "sg:address":"10300 Menaul Blvd NE",
    "sg:city":"Albuquerque",
    "sg:classifiers":[
        {
            "category":"Organizations",
            "subcategory":"Community Association",
            "type":"Services"
        }
    ],
    "sg:phone":"+1 505 323 2222",
    "sg:postcode":"87112",
    "sg:province":"NM",
    "sg:tags":[
        "club"
    ],
    "wof:name":"Dallas Cowboys Fan Club",
    "wof:placetype":"venue"
},
  "geometry": {"coordinates":[-106.525471,35.108894],"type":"Point"}
}