{
  "type": "Feature",
  "properties": {
    "iso:country":"US",
    "sg:address":"322 Pinos Verdes St",
    "sg:city":"Santa Fe",
    "sg:classifiers":[
        {
            "category":"Shopping",
            "subcategory":"Books",
            "type":"Retail Goods"
        }
    ],
    "sg:phone":"+1 505 989 1577",
    "sg:postcode":"87501",
    "sg:province":"NM",
    "sg:tags":[
        "bookstore"
    ],
    "wof:name":"Good Books",
    "wof:placetype":"venue"
},
  "geometry": {"coordinates":[-105.931546,35.71781],"type":"Point"}
}