{
  "type": "Feature",
  "properties": {
    "iso:country":"US",
    "sg:address":"6700 Jefferson St NE",
    "sg:city":"Albuquerque",
    "sg:classifiers":[
        {
            "category":"Professional",
            "subcategory":"Lawyer & Legal Services",
            "type":"Services"
        }
    ],
    "sg:phone":"+1 505 468 0518",
    "sg:postcode":"87109",
    "sg:province":"NM",
    "sg:tags":[
        "attorney"
    ],
    "wof:name":"Mays & Fain",
    "wof:placetype":"venue"
},
  "geometry": {"coordinates":[-106.593254,35.159355],"type":"Point"}
}