{
  "type": "Feature",
  "properties": {
    "addr:full":"428 Sandoval St Santa Fe NM 87501",
    "addr:housenumber":"428",
    "addr:postcode":"87501",
    "addr:street":"Sandoval St",
    "iso:country":"US",
    "sg:address":"428 Sandoval St",
    "sg:city":"Santa Fe",
    "sg:classifiers":[
        {
            "category":"Real Estate",
            "subcategory":"Real Estate Agent",
            "type":"Services"
        }
    ],
    "sg:phone":"+1 505 984 1766",
    "sg:postcode":"87501",
    "sg:province":"NM",
    "wof:name":"Yates Drilling Co",
    "wof:placetype":"venue"
},
  "geometry": {"coordinates":[-105.944722,35.683381],"type":"Point"}
}