{
  "type": "Feature",
  "properties": {
    "iso:country":"US",
    "sg:address":"703 Linda Ledesma Rd",
    "sg:city":"Anthony",
    "sg:classifiers":[
        {
            "category":"Retail",
            "subcategory":"Auto Repair",
            "type":"Services"
        }
    ],
    "sg:phone":"+1 505 882 4180",
    "sg:postcode":"88021",
    "sg:province":"NM",
    "sg:tags":[
        "tire"
    ],
    "wof:name":"J C Tire & Welding",
    "wof:placetype":"venue"
},
  "geometry": {"coordinates":[-106.603816,32.022085],"type":"Point"}
}