{
  "type": "Feature",
  "properties": {
    "addr:full":"505 Burro Ave Cloudcroft NM 88317",
    "addr:housenumber":"505",
    "addr:postcode":"88317",
    "addr:street":"Burro Ave",
    "iso:country":"US",
    "sg:address":"505 Burro Ave",
    "sg:city":"Cloudcroft",
    "sg:classifiers":[
        {
            "category":"Shopping",
            "subcategory":"Jewelry",
            "type":"Retail Goods"
        }
    ],
    "sg:phone":"+1 505 682 4414",
    "sg:postcode":"88317",
    "sg:province":"NM",
    "sg:tags":[
        "jeweler"
    ],
    "wof:name":"Julienne Jewelry",
    "wof:placetype":"venue"
},
  "geometry": {"coordinates":[-105.742818,32.958687],"type":"Point"}
}