{
  "type": "Feature",
  "properties": {
    "iso:country":"US",
    "sg:address":"6462 SE Main St",
    "sg:city":"Dexter",
    "sg:classifiers":[
        {
            "category":"Retail",
            "subcategory":"Repair Shop",
            "type":"Services"
        }
    ],
    "sg:phone":"+1 505 626 4026",
    "sg:postcode":"88230",
    "sg:province":"NM",
    "sg:tags":[
        "welding"
    ],
    "wof:name":"RDF Enterprises Inc",
    "wof:placetype":"venue"
},
  "geometry": {"coordinates":[-104.466464,33.290278],"type":"Point"}
}