{
  "type": "Feature",
  "properties": {
    "iso:country":"US",
    "sg:address":"2917 Quincy St NE",
    "sg:city":"Albuquerque",
    "sg:classifiers":[
        {
            "category":"Building & Trades",
            "subcategory":"Landscaping Services",
            "type":"Services"
        }
    ],
    "sg:phone":"+1 505 363 8267",
    "sg:postcode":"87110",
    "sg:province":"NM",
    "sg:tags":[
        "landscape",
        "contractor"
    ],
    "wof:name":"Southwst Enchanted Landscaping",
    "wof:placetype":"venue"
},
  "geometry": {"coordinates":[-106.58965000000001,35.116184],"type":"Point"}
}