{
  "type": "Feature",
  "properties": {
    "iso:country":"US",
    "sg:address":"304 Pso del Pueblo Sur",
    "sg:city":"Taos",
    "sg:classifiers":[
        {
            "category":"Wholesale",
            "subcategory":"Durable Goods & Equipment",
            "type":"Manufacturing & Wholesale Goods"
        }
    ],
    "sg:phone":"+1 505 751 4210",
    "sg:postcode":"87571",
    "sg:province":"NM",
    "sg:tags":[
        "importer"
    ],
    "wof:name":"Camino Real Imports-Plaza",
    "wof:placetype":"venue"
},
  "geometry": {"coordinates":[-105.574911,36.402542],"type":"Point"}
}