{
  "type": "Feature",
  "properties": {
    "iso:country":"US",
    "sg:address":"485 Llano St",
    "sg:city":"Aztec",
    "sg:classifiers":[
        {
            "category":"Freight",
            "type":"Transportation"
        },
        {
            "category":"Recreation",
            "subcategory":"Marina",
            "type":"Entertainment"
        }
    ],
    "sg:phone":"+1 505 334 0403",
    "sg:postcode":"87410",
    "sg:province":"NM",
    "sg:tags":[
        "commercial",
        "operation",
        "storage"
    ],
    "wof:name":"Cottonwood Mini Storage & Rv",
    "wof:placetype":"venue"
},
  "geometry": {"coordinates":[-108.00064999999999,36.819626],"type":"Point"}
}