{
  "type": "Feature",
  "properties": {
    "iso:country":"US",
    "sg:address":"610 N Canal St",
    "sg:city":"Carlsbad",
    "sg:classifiers":[
        {
            "category":"Personal",
            "type":"Services"
        }
    ],
    "sg:phone":"+1 505 887 8593",
    "sg:postcode":"88220",
    "sg:province":"NM",
    "wof:name":"Mariess Weddings & Receptions",
    "wof:placetype":"venue"
},
  "geometry": {"coordinates":[-104.228827,32.427314],"type":"Point"}
}