{
  "type": "Feature",
  "properties": {
    "addr:full":"5801 Osuna Rd NE Albuquerque NM 87109",
    "addr:housenumber":"5801",
    "addr:postcode":"87109",
    "addr:street":"Osuna Rd Ne",
    "iso:country":"US",
    "sg:address":"5801 Osuna Rd NE",
    "sg:city":"Albuquerque",
    "sg:classifiers":[
        {
            "category":"Professional",
            "type":"Services"
        }
    ],
    "sg:phone":"+1 505 837 1181",
    "sg:postcode":"87109",
    "sg:province":"NM",
    "sg:tags":[
        "establishment"
    ],
    "wof:name":"Adamas",
    "wof:placetype":"venue"
},
  "geometry": {"coordinates":[-106.580271,35.144335],"type":"Point"}
}