{
  "type": "Feature",
  "properties": {
    "iso:country":"US",
    "sg:address":"1940 S Espina St",
    "sg:city":"Las Cruces",
    "sg:classifiers":[
        {
            "category":"Shopping",
            "subcategory":"Tobacco",
            "type":"Retail Goods"
        }
    ],
    "sg:phone":"+1 505 527 9930",
    "sg:postcode":"88001",
    "sg:province":"NM",
    "sg:tags":[
        "product"
    ],
    "wof:name":"Smoke House",
    "wof:placetype":"venue"
},
  "geometry": {"coordinates":[-106.761043,32.291863],"type":"Point"}
}