{
  "type": "Feature",
  "properties": {
    "iso:country":"US",
    "sg:address":"3295 Cerrillos Rd",
    "sg:city":"Santa Fe",
    "sg:classifiers":[
        {
            "category":"Restaurant",
            "type":"Food & Drink"
        }
    ],
    "sg:menulink":"http://www.allmenus.com/nm/santa-fe/183676-kfc---kentucky-fried-chicken/menu/",
    "sg:phone":"+1 505 471 7042",
    "sg:postcode":"87507",
    "sg:province":"NM",
    "sg:tags":[
        "american",
        "chicken"
    ],
    "wof:name":"KFC - Kentucky Fried Chicken",
    "wof:placetype":"venue"
},
  "geometry": {"coordinates":[-105.99768400000001,35.651707],"type":"Point"}
}