{
  "type": "Feature",
  "properties": {
    "addr:full":"132 Romero St Santa Fe NM 87501",
    "addr:housenumber":"132",
    "addr:postcode":"87501",
    "addr:street":"Romero St",
    "iso:country":"US",
    "sg:address":"132 Romero St",
    "sg:city":"Santa Fe",
    "sg:classifiers":[
        {
            "category":"Professional",
            "type":"Services"
        }
    ],
    "sg:phone":"+1 505 955 0690",
    "sg:postcode":"87501",
    "sg:province":"NM",
    "wof:name":"Feng Shui-Mary Layne",
    "wof:placetype":"venue"
},
  "geometry": {"coordinates":[-105.94915399999999,35.685756],"type":"Point"}
}