{
  "type": "Feature",
  "properties": {
    "addr:full":"2274 Cll Pulido Santa Fe NM 87505",
    "addr:housenumber":"2274",
    "addr:postcode":"87505",
    "addr:street":"Cll Pulido",
    "iso:country":"US",
    "sg:address":"2274 Cll Pulido",
    "sg:city":"Santa Fe",
    "sg:classifiers":[
        {
            "category":"Health Services",
            "subcategory":"Chiropractor",
            "type":"Services"
        }
    ],
    "sg:phone":"+1 505 474 4815",
    "sg:postcode":"87505",
    "sg:province":"NM",
    "wof:name":"Life Enhancement Chiropractic",
    "wof:placetype":"venue"
},
  "geometry": {"coordinates":[-105.980369,35.648117],"type":"Point"}
}