{
  "type": "Feature",
  "properties": {
    "iso:country":"US",
    "sg:address":"101 S Clark St",
    "sg:city":"Gallup",
    "sg:classifiers":[
        {
            "category":"Social Services",
            "type":"Services"
        }
    ],
    "sg:phone":"+1 505 722 9756",
    "sg:postcode":"87301",
    "sg:province":"NM",
    "sg:tags":[
        "organization",
        "welfare"
    ],
    "wof:name":"New Mexico Advocates-Children",
    "wof:placetype":"venue"
},
  "geometry": {"coordinates":[-108.760955,35.522176],"type":"Point"}
}