{
  "type": "Feature",
  "properties": {
    "iso:country":"US",
    "sg:address":"1804 Arroyo Chamiso",
    "sg:city":"Santa Fe",
    "sg:classifiers":[
        {
            "category":"Social Services",
            "subcategory":"Child Care",
            "type":"Services"
        }
    ],
    "sg:phone":"+1 505 983 8924",
    "sg:postcode":"87505",
    "sg:province":"NM",
    "sg:tags":[
        "kindergarten",
        "academic",
        "school",
        "day"
    ],
    "wof:name":"Childrens School Inc",
    "wof:placetype":"venue"
},
  "geometry": {"coordinates":[-105.94244999999999,35.65488],"type":"Point"}
}