{
  "type": "Feature",
  "properties": {
    "iso:country":"US",
    "sg:address":"1012 Don Diego Ave",
    "sg:city":"Santa Fe",
    "sg:classifiers":[
        {
            "category":"Travel",
            "subcategory":"Travel Agent",
            "type":"Entertainment"
        }
    ],
    "sg:phone":"+1 505 989 5072",
    "sg:postcode":"87505",
    "sg:province":"NM",
    "sg:tags":[
        "operator",
        "tour"
    ],
    "wof:name":"Tour Service Cstm Trvl Experts",
    "wof:placetype":"venue"
},
  "geometry": {"coordinates":[-105.948489,35.674961],"type":"Point"}
}