{
  "type": "Feature",
  "properties": {
    "iso:country":"US",
    "sg:address":"1050 Old Pecos Trl",
    "sg:city":"Santa Fe",
    "sg:classifiers":[
        {
            "category":"Cinema",
            "subcategory":"Movie Theater",
            "type":"Entertainment"
        }
    ],
    "sg:phone":"+1 505 982 1338",
    "sg:postcode":"87505",
    "sg:province":"NM",
    "sg:website":"www.ccasantafe.org",
    "wof:name":"Center For Contemporary Arts",
    "wof:placetype":"venue"
},
  "geometry": {"coordinates":[-105.936593,35.673437],"type":"Point"}
}