{
  "type": "Feature",
  "properties": {
    "iso:country":"US",
    "sg:address":"11865 US Hwy 180 E",
    "sg:city":"Arenas Valley",
    "sg:classifiers":[
        {
            "category":"Retail",
            "subcategory":"Veterinary Services",
            "type":"Services"
        }
    ],
    "sg:phone":"+1 505 388 1993",
    "sg:postcode":"88022",
    "sg:province":"NM",
    "sg:tags":[
        "veterinarian"
    ],
    "wof:name":"Arenas Valley Animal Clinic",
    "wof:placetype":"venue"
},
  "geometry": {"coordinates":[-108.183737,32.779786],"type":"Point"}
}