{
  "type": "Feature",
  "properties": {
    "iso:country":"US",
    "sg:address":"704 N Bullard St",
    "sg:city":"Silver City",
    "sg:classifiers":[
        {
            "category":"Shopping",
            "subcategory":"Clothing, Apparel, & Fashions",
            "type":"Retail Goods"
        }
    ],
    "sg:phone":"+1 505 388 2474",
    "sg:postcode":"88061",
    "sg:province":"NM",
    "wof:name":"A LA Mode Fine Fashions Etc",
    "wof:placetype":"venue"
},
  "geometry": {"coordinates":[-108.275851,32.773761],"type":"Point"}
}