{
  "type": "Feature",
  "properties": {
    "addr:full":"204 S Green Ave Tatum NM 88267",
    "addr:housenumber":"204",
    "addr:postcode":"88267",
    "addr:street":"S Green Ave",
    "iso:country":"US",
    "sg:address":"204 S Green Ave",
    "sg:city":"Tatum",
    "sg:classifiers":[
        {
            "category":"Mining & Drilling",
            "type":"Manufacturing & Wholesale Goods"
        }
    ],
    "sg:phone":"+1 505 398 4833",
    "sg:postcode":"88267",
    "sg:province":"NM",
    "sg:tags":[
        "field",
        "oil"
    ],
    "wof:name":"Liberty Maintenance Svc",
    "wof:placetype":"venue"
},
  "geometry": {"coordinates":[-103.30904700000001,33.254837],"type":"Point"}
}