{
  "type": "Feature",
  "properties": {
    "addr:full":"1511 Golf Course Rd SE Rio Rancho NM 87124",
    "addr:housenumber":"1511",
    "addr:postcode":"87124",
    "addr:street":"Golf Course Rd Se",
    "iso:country":"US",
    "sg:address":"1511 Golf Course Rd SE",
    "sg:city":"Rio Rancho",
    "sg:classifiers":[
        {
            "category":"Building & Trades",
            "subcategory":"Plumbing",
            "type":"Services"
        }
    ],
    "sg:phone":"+1 505 954 4200",
    "sg:postcode":"87124",
    "sg:province":"NM",
    "sg:tags":[
        "plumbing",
        "contractor"
    ],
    "wof:name":"Mr Plumber",
    "wof:placetype":"venue"
},
  "geometry": {"coordinates":[-106.677177,35.233314],"type":"Point"}
}