{
  "type": "Feature",
  "properties": {
    "iso:country":"US",
    "sg:address":"557 W Cordova Rd",
    "sg:city":"Santa Fe",
    "sg:classifiers":[
        {
            "category":"Shopping",
            "type":"Retail Goods"
        }
    ],
    "sg:phone":"+1 505 983 1154",
    "sg:postcode":"87505",
    "sg:province":"NM",
    "sg:tags":[
        "merchandise"
    ],
    "wof:name":"Artservices of Santa Fe Inc",
    "wof:placetype":"venue"
},
  "geometry": {"coordinates":[-105.949534,35.672431],"type":"Point"}
}