{
  "type": "Feature",
  "properties": {
    "addr:full":"4200 Wyoming Blvd NE Albuquerque NM 87111",
    "addr:housenumber":"4200",
    "addr:postcode":"87111",
    "addr:street":"Wyoming;Ne",
    "iso:country":"US",
    "sg:address":"4200 Wyoming Blvd NE",
    "sg:city":"Albuquerque",
    "sg:classifiers":[
        {
            "category":"Shopping",
            "subcategory":"Bicycles & Sporting Goods",
            "type":"Retail Goods"
        }
    ],
    "sg:phone":"+1 505 296 5866",
    "sg:postcode":"87111",
    "sg:province":"NM",
    "sg:tags":[
        "equipment",
        "golf",
        "supply"
    ],
    "sg:website":"www.golfmartabq.com",
    "wof:name":"Golf Mart",
    "wof:placetype":"venue"
},
  "geometry": {"coordinates":[-106.550935,35.127752],"type":"Point"}
}