{
  "type": "Feature",
  "properties": {
    "iso:country":"US",
    "sg:address":"215 E Central Ave",
    "sg:city":"Lovington",
    "sg:classifiers":[
        {
            "category":"Government",
            "subcategory":"Police Station",
            "type":"Public Place"
        }
    ],
    "sg:phone":"+1 505 396 3611",
    "sg:postcode":"88260",
    "sg:province":"NM",
    "sg:tags":[
        "department"
    ],
    "wof:name":"Sheriffs Department",
    "wof:placetype":"venue"
},
  "geometry": {"coordinates":[-103.346931,32.948099],"type":"Point"}
}