{
  "type": "Feature",
  "properties": {
    "addr:full":"36 Agua Rd Angel Fire NM 87710",
    "addr:housenumber":"36",
    "addr:postcode":"87710",
    "addr:street":"Agua Rd",
    "iso:country":"US",
    "sg:address":"36 Agua Rd",
    "sg:city":"Angel Fire",
    "sg:classifiers":[
        {
            "category":"Building & Trades",
            "subcategory":"Construction",
            "type":"Services"
        }
    ],
    "sg:phone":"+1 505 377 5924",
    "sg:postcode":"87710",
    "sg:province":"NM",
    "sg:tags":[
        "excavating",
        "contractor"
    ],
    "wof:name":"Piedra Lumbre Excavation Inc",
    "wof:placetype":"venue"
},
  "geometry": {"coordinates":[-105.304697,36.419547],"type":"Point"}
}