{
  "type": "Feature",
  "properties": {
    "addr:full":"1212 W 2nd St Roswell NM 88201",
    "addr:housenumber":"1212",
    "addr:postcode":"88201",
    "addr:street":"W 2Nd St",
    "iso:country":"US",
    "sg:address":"1212 W 2nd St",
    "sg:city":"Roswell",
    "sg:classifiers":[
        {
            "category":"Travel",
            "subcategory":"Hotels & Motels",
            "type":"Entertainment"
        }
    ],
    "sg:phone":"+1 505 623 1293",
    "sg:postcode":"88201",
    "sg:province":"NM",
    "wof:name":"Crane Motel",
    "wof:placetype":"venue"
},
  "geometry": {"coordinates":[-104.540251,33.394123],"type":"Point"}
}