{
  "type": "Feature",
  "properties": {
    "iso:country":"US",
    "sg:address":"437 W Broadway",
    "sg:city":"Farmington",
    "sg:classifiers":[
        {
            "category":"Retail",
            "subcategory":"Repair Shop",
            "type":"Services"
        }
    ],
    "sg:phone":"+1 505 327 2477",
    "sg:postcode":"87401",
    "sg:province":"NM",
    "wof:name":"City T V & V C R Service",
    "wof:placetype":"venue"
},
  "geometry": {"coordinates":[-108.20974,36.727977],"type":"Point"}
}