{
  "type": "Feature",
  "properties": {
    "addr:full":"63 Yakima Rd Dexter NM 88230",
    "addr:housenumber":"63",
    "addr:postcode":"88230",
    "addr:street":"Yakima Rd",
    "iso:country":"US",
    "sg:address":"63 Yakima Rd",
    "sg:city":"Dexter",
    "sg:classifiers":[
        {
            "category":"Organizations",
            "subcategory":"Religious Organization",
            "type":"Services"
        }
    ],
    "sg:phone":"+1 505 347 5309",
    "sg:postcode":"88230",
    "sg:province":"NM",
    "sg:tags":[
        "church"
    ],
    "wof:name":"Midway Assembly Of God Church",
    "wof:placetype":"venue"
},
  "geometry": {"coordinates":[-104.461901,33.301354],"type":"Point"}
}