{
  "type": "Feature",
  "properties": {
    "addr:full":"7101 Hensch Ave NE Albuquerque NM 87109",
    "addr:housenumber":"7101",
    "addr:postcode":"87109",
    "addr:street":"Hensch Ave Ne",
    "iso:country":"US",
    "sg:address":"7101 Hensch Ave NE",
    "sg:city":"Albuquerque",
    "sg:classifiers":[
        {
            "category":"Banks & Credit Unions",
            "subcategory":"Financial Services",
            "type":"Services"
        }
    ],
    "sg:phone":"+1 505 821 6535",
    "sg:postcode":"87109",
    "sg:province":"NM",
    "sg:tags":[
        "trust",
        "management"
    ],
    "wof:name":"Health Winds Trust",
    "wof:placetype":"venue"
},
  "geometry": {"coordinates":[-106.568344,35.148697],"type":"Point"}
}