{
  "type": "Feature",
  "properties": {
    "iso:country":"US",
    "sg:address":"1719 S Ave D",
    "sg:city":"Portales",
    "sg:classifiers":[
        {
            "category":"Shopping",
            "subcategory":"Pharmacy",
            "type":"Retail Goods"
        }
    ],
    "sg:phone":"+1 505 356 8555",
    "sg:postcode":"88130",
    "sg:province":"NM",
    "sg:website":"www.villagerx.com",
    "wof:name":"Village Pharmacy",
    "wof:placetype":"venue"
},
  "geometry": {"coordinates":[-103.334687,34.17269],"type":"Point"}
}