{
  "type": "Feature",
  "properties": {
    "iso:country":"US",
    "sg:address":"3018 Aliso Dr NE",
    "sg:city":"Albuquerque",
    "sg:classifiers":[
        {
            "category":"Freight",
            "type":"Transportation"
        }
    ],
    "sg:phone":"+1 505 881 6214",
    "sg:postcode":"87110",
    "sg:province":"NM",
    "sg:tags":[
        "operator",
        "local",
        "hauling",
        "trucking"
    ],
    "wof:name":"Montenegro's Trucking",
    "wof:placetype":"venue"
},
  "geometry": {"coordinates":[-106.601575,35.118551],"type":"Point"}
}