{
  "type": "Feature",
  "properties": {
    "iso:country":"US",
    "sg:address":"227 E Darby Rd",
    "sg:city":"Dexter",
    "sg:classifiers":[
        {
            "category":"Wholesale",
            "subcategory":"Toys & Hobbies",
            "type":"Manufacturing & Wholesale Goods"
        }
    ],
    "sg:phone":"+1 505 625 8707",
    "sg:postcode":"88230",
    "sg:province":"NM",
    "sg:tags":[
        "firework"
    ],
    "wof:name":"Amy's Fireworks",
    "wof:placetype":"venue"
},
  "geometry": {"coordinates":[-104.427835,33.285154],"type":"Point"}
}