{
  "type": "Feature",
  "properties": {
    "iso:country":"US",
    "sg:address":"6317 Elm St NE",
    "sg:city":"Albuquerque",
    "sg:classifiers":[
        {
            "category":"Wholesale",
            "subcategory":"Construction Materials",
            "type":"Manufacturing & Wholesale Goods"
        }
    ],
    "sg:phone":"+1 505 620 0334",
    "sg:postcode":"87113",
    "sg:province":"NM",
    "sg:tags":[
        "fence"
    ],
    "wof:name":"J R & Sons Fencing Co",
    "wof:placetype":"venue"
},
  "geometry": {"coordinates":[-106.620706,35.147065],"type":"Point"}
}