{
  "type": "Feature",
  "properties": {
    "iso:country":"US",
    "sg:address":"316 N Norris St",
    "sg:city":"Clovis",
    "sg:classifiers":[
        {
            "category":"Building & Trades",
            "subcategory":"Plumbing",
            "type":"Services"
        }
    ],
    "sg:phone":"+1 505 762 4001",
    "sg:postcode":"88101",
    "sg:province":"NM",
    "sg:tags":[
        "plumbing",
        "contractor"
    ],
    "wof:name":"W T Denton Mechanical Inc",
    "wof:placetype":"venue"
},
  "geometry": {"coordinates":[-103.17890800000001,34.401685],"type":"Point"}
}