{
  "type": "Feature",
  "properties": {
    "addr:full":"1200 16th St Eunice NM 88231",
    "addr:housenumber":"1200",
    "addr:postcode":"88231",
    "addr:street":"16Th St",
    "iso:country":"US",
    "sg:address":"1200 16th St",
    "sg:city":"Eunice",
    "sg:classifiers":[
        {
            "category":"Education",
            "subcategory":"School",
            "type":"Public Place"
        }
    ],
    "sg:phone":"+1 505 394 2440",
    "sg:postcode":"88231",
    "sg:province":"NM",
    "sg:website":"www.eunice.org",
    "wof:name":"Mettie Jordan Elementary Schl",
    "wof:placetype":"venue"
},
  "geometry": {"coordinates":[-103.162969,32.440629],"type":"Point"}
}