{
  "type": "Feature",
  "properties": {
    "iso:country":"US",
    "sg:address":"8100 Wyoming Blvd NE",
    "sg:city":"Albuquerque",
    "sg:classifiers":[
        {
            "category":"Home & Garden",
            "subcategory":"Furniture",
            "type":"Retail Goods"
        }
    ],
    "sg:phone":"+1 505 797 0749",
    "sg:postcode":"87113",
    "sg:province":"NM",
    "wof:name":"Sleep-N-Aire",
    "wof:placetype":"venue"
},
  "geometry": {"coordinates":[-106.55995799999999,35.175751],"type":"Point"}
}