{
  "type": "Feature",
  "properties": {
    "addr:full":"1524 Central Ave SE Albuquerque NM 87106",
    "addr:housenumber":"1524",
    "addr:postcode":"87106",
    "addr:street":"Central Ave Se",
    "iso:country":"US",
    "sg:address":"1524 Central Ave SE",
    "sg:city":"Albuquerque",
    "sg:classifiers":[
        {
            "category":"Real Estate",
            "subcategory":"Real Estate Services",
            "type":"Services"
        },
        {
            "category":"Real Estate",
            "subcategory":"Developer",
            "type":"Services"
        },
        {
            "category":"Real Estate",
            "subcategory":"Real Estate Agent",
            "type":"Services"
        }
    ],
    "sg:phone":"+1 505 247 4377",
    "sg:postcode":"87106",
    "sg:province":"NM",
    "sg:tags":[
        "investing",
        "buyer",
        "broker"
    ],
    "wof:name":"Ben Chavez Realty",
    "wof:placetype":"venue"
},
  "geometry": {"coordinates":[-106.63002299999999,35.081751],"type":"Point"}
}