{
  "type": "Feature",
  "properties": {
    "addr:full":"400 Tijeras Ave NW Albuquerque NM 87102",
    "addr:housenumber":"400",
    "addr:postcode":"87102",
    "addr:street":"Tijeras Ave Nw",
    "iso:country":"US",
    "sg:address":"400 Tijeras Ave NW",
    "sg:city":"Albuquerque",
    "sg:classifiers":[
        {
            "category":"Utilities",
            "subcategory":"Telephone",
            "type":"Services"
        }
    ],
    "sg:phone":"+1 505 245 7335",
    "sg:postcode":"87102",
    "sg:province":"NM",
    "sg:tags":[
        "communications",
        "radiotelephone",
        "communication"
    ],
    "wof:name":"Qwest",
    "wof:placetype":"venue"
},
  "geometry": {"coordinates":[-106.6524,35.086912],"type":"Point"}
}