{
  "type": "Feature",
  "properties": {
    "addr:full":"1928 7th St NW Albuquerque NM 87102",
    "addr:housenumber":"1928",
    "addr:postcode":"87102",
    "addr:street":"7Th St Nw",
    "iso:country":"US",
    "sg:address":"1928 7th St NW",
    "sg:city":"Albuquerque",
    "sg:classifiers":[
        {
            "category":"Manufacturing",
            "subcategory":"Metals",
            "type":"Manufacturing & Wholesale Goods"
        }
    ],
    "sg:phone":"+1 505 296 9600",
    "sg:postcode":"87102",
    "sg:province":"NM",
    "sg:tags":[
        "steel"
    ],
    "sg:website":"www.southwestironworkinc.com",
    "wof:name":"Southwest Ironwork Inc",
    "wof:placetype":"venue"
},
  "geometry": {"coordinates":[-106.652812,35.104014],"type":"Point"}
}