{
  "type": "Feature",
  "properties": {
    "iso:country":"US",
    "sg:address":"2525 S Telshor Blvd",
    "sg:city":"Las Cruces",
    "sg:classifiers":[
        {
            "category":"Professional",
            "subcategory":"Research",
            "type":"Services"
        }
    ],
    "sg:phone":"+1 505 521 4477",
    "sg:postcode":"88011",
    "sg:province":"NM",
    "sg:tags":[
        "commercial",
        "physical"
    ],
    "wof:name":"Lovelace Respiratory RES Inst",
    "wof:placetype":"venue"
},
  "geometry": {"coordinates":[-106.7349,32.291421],"type":"Point"}
}