{
  "type": "Feature",
  "properties": {
    "addr:full":"1765 Chaparro St Las Cruces NM 88001",
    "addr:housenumber":"1765",
    "addr:postcode":"88001",
    "addr:street":"Chaparro St",
    "iso:country":"US",
    "sg:address":"1765 Chaparro St",
    "sg:city":"Las Cruces",
    "sg:classifiers":[
        {
            "category":"Professional",
            "type":"Services"
        }
    ],
    "sg:phone":"+1 505 526 2111",
    "sg:postcode":"88001",
    "sg:province":"NM",
    "sg:tags":[
        "geographer"
    ],
    "wof:name":"Geostat",
    "wof:placetype":"venue"
},
  "geometry": {"coordinates":[-106.76015700000001,32.294538],"type":"Point"}
}