{
  "type": "Feature",
  "properties": {
    "iso:country":"US",
    "sg:address":"328 Alamos Rd",
    "sg:city":"Corrales",
    "sg:classifiers":[
        {
            "category":"Building & Trades",
            "subcategory":"Construction",
            "type":"Services"
        }
    ],
    "sg:phone":"+1 505 897 3520",
    "sg:postcode":"87048",
    "sg:province":"NM",
    "sg:tags":[
        "general",
        "contractor"
    ],
    "wof:name":"Limited Edition Homes",
    "wof:placetype":"venue"
},
  "geometry": {"coordinates":[-106.62950600000001,35.225032],"type":"Point"}
}