{
  "type": "Feature",
  "properties": {
    "addr:full":"120 Carlito Rd NW Albuquerque NM 87107",
    "addr:housenumber":"120",
    "addr:postcode":"87107",
    "addr:street":"Carlito Rd Nw",
    "iso:country":"US",
    "sg:address":"120 Carlito Rd NW",
    "sg:city":"Albuquerque",
    "sg:classifiers":[
        {
            "category":"Building & Trades",
            "subcategory":"Pest Control",
            "type":"Services"
        }
    ],
    "sg:phone":"+1 505 345 6677",
    "sg:postcode":"87107",
    "sg:province":"NM",
    "sg:tags":[
        "farm",
        "supply"
    ],
    "wof:name":"Craig Pest Control",
    "wof:placetype":"venue"
},
  "geometry": {"coordinates":[-106.62943,35.15631],"type":"Point"}
}