{
  "type": "Feature",
  "properties": {
    "iso:country":"US",
    "sg:address":"3824 Corrales Rd",
    "sg:city":"Corrales",
    "sg:classifiers":[
        {
            "category":"Personal",
            "subcategory":"Beauty Salon",
            "type":"Services"
        }
    ],
    "sg:phone":"+1 505 899 5707",
    "sg:postcode":"87048",
    "sg:province":"NM",
    "sg:tags":[
        "spa",
        "day"
    ],
    "sg:website":"www.serenitygardensnm.com",
    "wof:name":"Day Spa At Serenity Gardens",
    "wof:placetype":"venue"
},
  "geometry": {"coordinates":[-106.622709,35.217932],"type":"Point"}
}