{
  "type": "Feature",
  "properties": {
    "iso:country":"US",
    "sg:address":"4801 Ellison St NE",
    "sg:city":"Albuquerque",
    "sg:classifiers":[
        {
            "category":"Manufacturing",
            "subcategory":"Rubber & Plastics",
            "type":"Manufacturing & Wholesale Goods"
        }
    ],
    "sg:phone":"+1 505 341 4702",
    "sg:postcode":"87109",
    "sg:province":"NM",
    "wof:name":"Custom Fabricators Inc",
    "wof:placetype":"venue"
},
  "geometry": {"coordinates":[-106.58823599999999,35.160474],"type":"Point"}
}