{
  "type": "Feature",
  "properties": {
    "iso:country":"US",
    "sg:address":"1002 Ferndale Dr",
    "sg:city":"Las Cruces",
    "sg:classifiers":[
        {
            "category":"Building & Trades",
            "subcategory":"Cleaning & Sanitation",
            "type":"Services"
        }
    ],
    "sg:phone":"+1 505 382 0736",
    "sg:postcode":"88005",
    "sg:province":"NM",
    "sg:tags":[
        "maintenance"
    ],
    "wof:name":"Reliable Maintenance Service",
    "wof:placetype":"venue"
},
  "geometry": {"coordinates":[-106.778846,32.346862],"type":"Point"}
}