{
  "type": "Feature",
  "properties": {
    "addr:full":"2015 Knudsen Ave Farmington NM 87401",
    "addr:housenumber":"2015",
    "addr:postcode":"87401",
    "addr:street":"Knudsen Ave",
    "iso:country":"US",
    "sg:address":"2015 Knudsen Ave",
    "sg:city":"Farmington",
    "sg:classifiers":[
        {
            "category":"Professional",
            "subcategory":"Business Services",
            "type":"Services"
        }
    ],
    "sg:phone":"+1 505 326 5545",
    "sg:postcode":"87401",
    "sg:province":"NM",
    "sg:tags":[
        "paging",
        "answering"
    ],
    "wof:name":"Advanced Communications Inc",
    "wof:placetype":"venue"
},
  "geometry": {"coordinates":[-108.188666,36.749741],"type":"Point"}
}