{
  "type": "Feature",
  "properties": {
    "addr:full":"800 Quail Hill Trl Pena Blanca NM 87041",
    "addr:housenumber":"800",
    "addr:postcode":"87041",
    "addr:street":"Quail Hill Trl",
    "iso:country":"US",
    "sg:address":"800 Quail Hill Trl",
    "sg:city":"Pena Blanca",
    "sg:classifiers":[
        {
            "category":"Education",
            "subcategory":"School",
            "type":"Public Place"
        }
    ],
    "sg:phone":"+1 505 867 5547",
    "sg:postcode":"87041",
    "sg:province":"NM",
    "wof:name":"Cochiti Elementary School",
    "wof:placetype":"venue"
},
  "geometry": {"coordinates":[-106.323123,35.581652],"type":"Point"}
}