{
  "type": "Feature",
  "properties": {
    "iso:country":"US",
    "sg:address":"3 Monte Vista Ct",
    "sg:city":"Placitas",
    "sg:classifiers":[
        {
            "category":"Professional",
            "subcategory":"Management & Consulting",
            "type":"Services"
        }
    ],
    "sg:phone":"+1 505 771 8858",
    "sg:postcode":"87043",
    "sg:province":"NM",
    "sg:tags":[
        "engineering"
    ],
    "wof:name":"Utility Development Consulting",
    "wof:placetype":"venue"
},
  "geometry": {"coordinates":[-106.40998399999999,35.300051],"type":"Point"}
}