{
  "type": "Feature",
  "properties": {
    "iso:country":"US",
    "sg:address":"1101 E Taylor Rd",
    "sg:city":"Las Cruces",
    "sg:classifiers":[
        {
            "category":"Building & Trades",
            "subcategory":"Construction",
            "type":"Services"
        }
    ],
    "sg:phone":"+1 505 523 8802",
    "sg:postcode":"88005",
    "sg:province":"NM",
    "sg:tags":[
        "h",
        "contractor"
    ],
    "wof:name":"Frietze Tile",
    "wof:placetype":"venue"
},
  "geometry": {"coordinates":[-106.79747,32.37479],"type":"Point"}
}