{
  "type": "Feature",
  "properties": {
    "iso:country":"US",
    "sg:address":"621 Old Santa Fe Trl",
    "sg:city":"Santa Fe",
    "sg:classifiers":[
        {
            "category":"Professional",
            "subcategory":"Engineering",
            "type":"Services"
        }
    ],
    "sg:phone":"+1 505 983 2053",
    "sg:postcode":"87505",
    "sg:province":"NM",
    "wof:name":"Malcolm Worby Designs",
    "wof:placetype":"venue"
},
  "geometry": {"coordinates":[-105.937433,35.679336],"type":"Point"}
}