{
  "type": "Feature",
  "properties": {
    "addr:full":"249 N Armory Rd Las Cruces NM 88007",
    "addr:housenumber":"249",
    "addr:postcode":"88007",
    "addr:street":"N Armory Rd",
    "iso:country":"US",
    "sg:address":"249 N Armory Rd",
    "sg:city":"Las Cruces",
    "sg:classifiers":[
        {
            "category":"Government",
            "subcategory":"Office",
            "type":"Public Place"
        }
    ],
    "sg:phone":"+1 505 524 7444",
    "sg:postcode":"88007",
    "sg:province":"NM",
    "sg:tags":[
        "national",
        "security"
    ],
    "wof:name":"New Mexico Army Ntnl Grd Ofce",
    "wof:placetype":"venue"
},
  "geometry": {"coordinates":[-106.93682,32.273869],"type":"Point"}
}