{
  "type": "Feature",
  "properties": {
    "iso:country":"US",
    "sg:address":"101 S Orchard Ave",
    "sg:city":"Farmington",
    "sg:classifiers":[
        {
            "category":"Banks & Credit Unions",
            "subcategory":"Bank",
            "type":"Services"
        }
    ],
    "sg:phone":"+1 505 325 0734",
    "sg:postcode":"87401",
    "sg:province":"NM",
    "sg:tags":[
        "loan",
        "real estate"
    ],
    "wof:name":"Quest Financial Solutions Inc",
    "wof:placetype":"venue"
},
  "geometry": {"coordinates":[-108.20548700000001,36.729093],"type":"Point"}
}