{
  "type": "Feature",
  "properties": {
    "iso:country":"US",
    "sg:address":"518 W Pueblo Dr",
    "sg:city":"Espanola",
    "sg:classifiers":[
        {
            "category":"Health Services",
            "subcategory":"Health Practitioner",
            "type":"Services"
        }
    ],
    "sg:phone":"+1 505 747 3333",
    "sg:postcode":"87532",
    "sg:province":"NM",
    "wof:name":"Rocky Mountain Orthopedics",
    "wof:placetype":"venue"
},
  "geometry": {"coordinates":[-106.06576200000001,36.00201],"type":"Point"}
}