{
  "type": "Feature",
  "properties": {
    "iso:country":"US",
    "sg:address":"1 N White Sands Blvd",
    "sg:city":"Alamogordo",
    "sg:classifiers":[
        {
            "category":"Retail",
            "subcategory":"Repair Shop",
            "type":"Services"
        }
    ],
    "sg:phone":"+1 505 443 1777",
    "sg:postcode":"88310",
    "sg:province":"NM",
    "sg:tags":[
        "lock",
        "locksmith"
    ],
    "wof:name":"Alamogordo Lock & Key",
    "wof:placetype":"venue"
},
  "geometry": {"coordinates":[-105.966296,32.940488],"type":"Point"}
}