{
  "type": "Feature",
  "properties": {
    "iso:country":"US",
    "sg:address":"405 N Broadway St",
    "sg:city":"Truth Or Cnsqncs",
    "sg:classifiers":[
        {
            "category":"Health Services",
            "subcategory":"Chiropractor",
            "type":"Services"
        }
    ],
    "sg:phone":"+1 505 894 2002",
    "sg:postcode":"87901",
    "sg:province":"NM",
    "wof:name":"Rio Grande Chiropractic Ctr",
    "wof:placetype":"venue"
},
  "geometry": {"coordinates":[-107.255613,33.128595],"type":"Point"}
}