{
  "type": "Feature",
  "properties": {
    "iso:country":"US",
    "sg:address":"133 Cook Ave",
    "sg:city":"Raton",
    "sg:classifiers":[
        {
            "category":"Bars & Pubs",
            "type":"Food & Drink"
        }
    ],
    "sg:phone":"+1 505 445 9992",
    "sg:postcode":"87740",
    "sg:province":"NM",
    "sg:tags":[
        "bar"
    ],
    "wof:name":"White House Saloon",
    "wof:placetype":"venue"
},
  "geometry": {"coordinates":[-104.438776,36.900985],"type":"Point"}
}