{
  "type": "Feature",
  "properties": {
    "addr:full":"410 W Broadway St Silver City NM 88061",
    "addr:housenumber":"410",
    "addr:postcode":"88061",
    "addr:street":"W Broadway St",
    "iso:country":"US",
    "sg:address":"410 W Broadway St",
    "sg:city":"Silver City",
    "sg:classifiers":[
        {
            "category":"Government",
            "subcategory":"Office",
            "type":"Public Place"
        }
    ],
    "sg:phone":"+1 505 538 3737",
    "sg:postcode":"88061",
    "sg:province":"NM",
    "sg:tags":[
        "career",
        "center"
    ],
    "wof:name":"Silver Cy One Stop Career Ctr",
    "wof:placetype":"venue"
},
  "geometry": {"coordinates":[-108.27939000000001,32.770093],"type":"Point"}
}