{
  "type": "Feature",
  "properties": {
    "addr:full":"9223 Central Ave NE Albuquerque NM 87123",
    "addr:housenumber":"9223",
    "addr:postcode":"87123",
    "addr:street":"Central Ave Ne",
    "iso:country":"US",
    "sg:address":"9223 Central Ave NE",
    "sg:city":"Albuquerque",
    "sg:classifiers":[
        {
            "category":"Autos & Motor Vehicles",
            "subcategory":"Recreational Vehicle Sales",
            "type":"Retail Goods"
        }
    ],
    "sg:phone":"+1 505 559 4981",
    "sg:postcode":"87123",
    "sg:province":"NM",
    "sg:tags":[
        "home",
        "camper"
    ],
    "sg:website":"http://www.desertrvsales.com",
    "wof:name":"Desert RV Sales",
    "wof:placetype":"venue"
},
  "geometry": {"coordinates":[-106.545216,35.073405],"type":"Point"}
}