{
  "type": "Feature",
  "properties": {
    "iso:country":"US",
    "sg:address":"2485 Bosque Farms Blvd",
    "sg:city":"Bosque Farms",
    "sg:classifiers":[
        {
            "category":"Professional",
            "subcategory":"Business Services",
            "type":"Services"
        }
    ],
    "sg:phone":"+1 505 869 9190",
    "sg:postcode":"87068",
    "sg:province":"NM",
    "sg:tags":[
        "embroidery"
    ],
    "wof:name":"Lasting Impressions Laser",
    "wof:placetype":"venue"
},
  "geometry": {"coordinates":[-106.69143,34.839254],"type":"Point"}
}