{
  "type": "Feature",
  "properties": {
    "iso:country":"US",
    "sg:address":"138 Park Ave",
    "sg:city":"Santa Fe",
    "sg:classifiers":[
        {
            "category":"Travel",
            "subcategory":"Hotels & Motels",
            "type":"Entertainment"
        }
    ],
    "sg:phone":"+1 505 988 4455",
    "sg:postcode":"87501",
    "sg:province":"NM",
    "sg:website":"www.eldoradohotel.com",
    "wof:name":"Casa Pueblo",
    "wof:placetype":"venue"
},
  "geometry": {"coordinates":[-105.945177,35.690127],"type":"Point"}
}