{
  "type": "Feature",
  "properties": {
    "addr:full":"15 Willa Cather Rd Lamy NM 87540",
    "addr:housenumber":"15",
    "addr:postcode":"87540",
    "addr:street":"Willa Cather Rd",
    "iso:country":"US",
    "sg:address":"15 Willa Cather Rd",
    "sg:city":"Lamy",
    "sg:classifiers":[
        {
            "category":"Professional",
            "subcategory":"Management & Consulting",
            "type":"Services"
        }
    ],
    "sg:phone":"+1 505 466 3656",
    "sg:postcode":"87540",
    "sg:province":"NM",
    "wof:name":"James Hellerman",
    "wof:placetype":"venue"
},
  "geometry": {"coordinates":[-105.88057000000001,35.505401],"type":"Point"}
}