{
  "type": "Feature",
  "properties": {
    "addr:full":"8401 Florence Ave NE Albuquerque NM 87122",
    "addr:housenumber":"8401",
    "addr:postcode":"87122",
    "addr:street":"Florence Ave Ne",
    "iso:country":"US",
    "sg:address":"8401 Florence Ave NE",
    "sg:city":"Albuquerque",
    "sg:classifiers":[
        {
            "category":"Building & Trades",
            "subcategory":"Construction",
            "type":"Services"
        }
    ],
    "sg:phone":"+1 505 856 6514",
    "sg:postcode":"87122",
    "sg:province":"NM",
    "sg:tags":[
        "general",
        "contractor"
    ],
    "wof:name":"Pioneer Construction Co",
    "wof:placetype":"venue"
},
  "geometry": {"coordinates":[-106.551097,35.191599],"type":"Point"}
}