{
  "type": "Feature",
  "properties": {
    "addr:full":"2111 Sudderth Dr Ruidoso NM 88345",
    "addr:housenumber":"2111",
    "addr:postcode":"88345",
    "addr:street":"Sudderth Dr",
    "iso:country":"US",
    "sg:address":"2111 Sudderth Dr",
    "sg:city":"Ruidoso",
    "sg:classifiers":[
        {
            "category":"Shopping",
            "subcategory":"Clothing, Apparel, & Fashions",
            "type":"Retail Goods"
        }
    ],
    "sg:phone":"+1 505 257 1065",
    "sg:postcode":"88345",
    "sg:province":"NM",
    "wof:name":"Susie's Closet",
    "wof:placetype":"venue"
},
  "geometry": {"coordinates":[-105.66738599999999,33.330688],"type":"Point"}
}