{
  "type": "Feature",
  "properties": {
    "addr:full":"4515 Columbus Rd Deming NM 88030",
    "addr:housenumber":"4515",
    "addr:postcode":"88030",
    "addr:street":"Columbus Rd",
    "iso:country":"US",
    "sg:address":"4515 Columbus Rd",
    "sg:city":"Deming",
    "sg:classifiers":[
        {
            "category":"Building & Trades",
            "subcategory":"Construction",
            "type":"Services"
        }
    ],
    "sg:phone":"+1 505 546 7583",
    "sg:postcode":"88030",
    "sg:province":"NM",
    "sg:tags":[
        "house"
    ],
    "wof:name":"Richard W Gilmore Inc",
    "wof:placetype":"venue"
},
  "geometry": {"coordinates":[-107.751203,32.217741],"type":"Point"}
}