{
  "type": "Feature",
  "properties": {
    "iso:country":"US",
    "sg:address":"1855 Golden Dr",
    "sg:city":"Las Cruces",
    "sg:classifiers":[
        {
            "category":"Building & Trades",
            "subcategory":"Electrical",
            "type":"Services"
        }
    ],
    "sg:phone":"+1 505 524 9294",
    "sg:postcode":"88005",
    "sg:province":"NM",
    "sg:tags":[
        "electric",
        "contractor"
    ],
    "wof:name":"Double E Electric Co",
    "wof:placetype":"venue"
},
  "geometry": {"coordinates":[-106.793532,32.323624],"type":"Point"}
}