{
  "type": "Feature",
  "properties": {
    "iso:country":"US",
    "sg:address":"515 W High St",
    "sg:city":"Grants",
    "sg:classifiers":[
        {
            "category":"Government",
            "subcategory":"Office",
            "type":"Public Place"
        }
    ],
    "sg:phone":"+1 505 285 2522",
    "sg:postcode":"87020",
    "sg:province":"NM",
    "sg:tags":[
        "county",
        "taxation"
    ],
    "wof:name":"Cibola County Treasurer",
    "wof:placetype":"venue"
},
  "geometry": {"coordinates":[-107.85476,35.153884],"type":"Point"}
}