{
  "type": "Feature",
  "properties": {
    "iso:country":"US",
    "sg:address":"2518 del Sur Dr SW",
    "sg:city":"Albuquerque",
    "sg:classifiers":[
        {
            "category":"Building & Trades",
            "subcategory":"Construction",
            "type":"Services"
        }
    ],
    "sg:phone":"+1 505 440 6930",
    "sg:postcode":"87105",
    "sg:province":"NM",
    "sg:tags":[
        "general",
        "contractor"
    ],
    "wof:name":"B R S Construction Company",
    "wof:placetype":"venue"
},
  "geometry": {"coordinates":[-106.698301,35.025886],"type":"Point"}
}