{
  "type": "Feature",
  "properties": {
    "addr:full":"229 Shangri la Ct NW Albuquerque NM 87107",
    "addr:housenumber":"229",
    "addr:postcode":"87107",
    "addr:street":"Shangri La Ct Nw",
    "iso:country":"US",
    "sg:address":"229 Shangri la Ct NW",
    "sg:city":"Albuquerque",
    "sg:classifiers":[
        {
            "category":"Building & Trades",
            "subcategory":"Construction",
            "type":"Services"
        }
    ],
    "sg:phone":"+1 505 345 7578",
    "sg:postcode":"87107",
    "sg:province":"NM",
    "sg:tags":[
        "altering",
        "house",
        "siding",
        "remodeling",
        "contractor"
    ],
    "wof:name":"White Way Home Improvement Co Inc",
    "wof:placetype":"venue"
},
  "geometry": {"coordinates":[-106.64009299999999,35.131968],"type":"Point"}
}