{
  "type": "Feature",
  "properties": {
    "iso:country":"US",
    "sg:address":"1007 Marron Cir NE",
    "sg:city":"Albuquerque",
    "sg:classifiers":[
        {
            "category":"Real Estate",
            "subcategory":"Real Estate Agent",
            "type":"Services"
        },
        {
            "category":"Real Estate",
            "subcategory":"Real Estate Operator",
            "type":"Services"
        }
    ],
    "sg:phone":"+1 505 298 1510",
    "sg:postcode":"87112",
    "sg:province":"NM",
    "sg:tags":[
        "building",
        "apartment"
    ],
    "wof:name":"Marron Park Apartments",
    "wof:placetype":"venue"
},
  "geometry": {"coordinates":[-106.546089,35.089738],"type":"Point"}
}