{
  "type": "Feature",
  "properties": {
    "iso:country":"US",
    "sg:address":"6806 Deerbourne Rd NW",
    "sg:city":"Albuquerque",
    "sg:classifiers":[
        {
            "category":"Professional",
            "subcategory":"Computer Services",
            "type":"Services"
        }
    ],
    "sg:phone":"+1 505 400 0341",
    "sg:postcode":"87114",
    "sg:province":"NM",
    "sg:tags":[
        "development",
        "software",
        "database"
    ],
    "wof:name":"Specialty Software",
    "wof:placetype":"venue"
},
  "geometry": {"coordinates":[-106.731931,35.198792],"type":"Point"}
}