{
  "type": "Feature",
  "properties": {
    "iso:country":"US",
    "sg:address":"400 Marquette Ave NW",
    "sg:city":"Albuquerque",
    "sg:classifiers":[
        {
            "category":"Government",
            "subcategory":"Office",
            "type":"Public Place"
        }
    ],
    "sg:phone":"+1 505 768 3700",
    "sg:postcode":"87102",
    "sg:province":"NM",
    "sg:tags":[
        "village"
    ],
    "wof:name":"Albuquerque Human Resources",
    "wof:placetype":"venue"
},
  "geometry": {"coordinates":[-106.652135,35.088324],"type":"Point"}
}