{
  "type": "Feature",
  "properties": {
    "addr:full":"5621 Palomino Dr NW Albuquerque NM 87120",
    "addr:housenumber":"5621",
    "addr:postcode":"87120",
    "addr:street":"Palomino Dr Nw",
    "iso:country":"US",
    "sg:address":"5621 Palomino Dr NW",
    "sg:city":"Albuquerque",
    "sg:classifiers":[
        {
            "category":"Health Services",
            "subcategory":"Medical Lab",
            "type":"Services"
        }
    ],
    "sg:phone":"+1 505 899 1447",
    "sg:postcode":"87120",
    "sg:province":"NM",
    "sg:tags":[
        "laboratory"
    ],
    "wof:name":"Sonography Service",
    "wof:placetype":"venue"
},
  "geometry": {"coordinates":[-106.704857,35.14886],"type":"Point"}
}