{
  "type": "Feature",
  "properties": {
    "iso:country":"US",
    "sg:address":"524 Gerald Chavez Ln",
    "sg:city":"Los Lunas",
    "sg:classifiers":[
        {
            "category":"Real Estate",
            "subcategory":"Real Estate Operator",
            "type":"Services"
        }
    ],
    "sg:phone":"+1 505 865 5182",
    "sg:postcode":"87031",
    "sg:province":"NM",
    "sg:tags":[
        "apartment"
    ],
    "wof:name":"Gerald Chavez Apartments",
    "wof:placetype":"venue"
},
  "geometry": {"coordinates":[-106.729734,34.811581],"type":"Point"}
}