{
  "type": "Feature",
  "properties": {
    "addr:full":"1201 E Amador Ave Las Cruces NM 88001",
    "addr:housenumber":"1201",
    "addr:postcode":"88001",
    "addr:street":"E Amador Ave",
    "iso:country":"US",
    "sg:address":"1201 E Amador Ave",
    "sg:city":"Las Cruces",
    "sg:classifiers":[
        {
            "category":"Sports & Exercise",
            "subcategory":"Bowling",
            "type":"Entertainment"
        }
    ],
    "sg:phone":"+1 505 526 8855",
    "sg:postcode":"88001",
    "sg:province":"NM",
    "sg:tags":[
        "center"
    ],
    "wof:name":"Sun Bowl Inc",
    "wof:placetype":"venue"
},
  "geometry": {"coordinates":[-106.76599,32.309599],"type":"Point"}
}