{
  "type": "Feature",
  "properties": {
    "iso:country":"US",
    "sg:address":"702 Canyon Rd",
    "sg:city":"Santa Fe",
    "sg:classifiers":[
        {
            "category":"Professional",
            "subcategory":"Business Services",
            "type":"Services"
        }
    ],
    "sg:phone":"+1 505 983 2654",
    "sg:postcode":"87501",
    "sg:province":"NM",
    "wof:name":"David Brighton Engraver",
    "wof:placetype":"venue"
},
  "geometry": {"coordinates":[-105.924886,35.680397],"type":"Point"}
}