{
  "type": "Feature",
  "properties": {
    "addr:full":"1300 S Country Club Rd Deming NM 88030",
    "addr:housenumber":"1300",
    "addr:postcode":"88030",
    "addr:street":"S Country Club Rd",
    "iso:country":"US",
    "sg:address":"1300 S Country Club Rd",
    "sg:city":"Deming",
    "sg:classifiers":[
        {
            "category":"Sports & Exercise",
            "subcategory":"Gym",
            "type":"Entertainment"
        }
    ],
    "sg:phone":"+1 505 589 0191",
    "sg:postcode":"88030",
    "sg:province":"NM",
    "sg:tags":[
        "club",
        "health",
        "studio",
        "gymnasium"
    ],
    "wof:name":"Curves",
    "wof:placetype":"venue"
},
  "geometry": {"coordinates":[-107.73434,32.255499],"type":"Point"}
}