{
  "type": "Feature",
  "properties": {
    "iso:country":"US",
    "sg:address":"613 7th St",
    "sg:city":"Cimarron",
    "sg:classifiers":[
        {
            "category":"Wholesale",
            "subcategory":"Durable Goods & Equipment",
            "type":"Manufacturing & Wholesale Goods"
        }
    ],
    "sg:phone":"+1 505 376 6626",
    "sg:postcode":"87714",
    "sg:province":"NM",
    "sg:tags":[
        "bedding",
        "wood",
        "animal",
        "shaving"
    ],
    "wof:name":"Silver Dollar Racg & Shavings",
    "wof:placetype":"venue"
},
  "geometry": {"coordinates":[-104.90935899999999,36.513097],"type":"Point"}
}