{
  "type": "Feature",
  "properties": {
    "iso:country":"US",
    "sg:address":"1221 N Prince St",
    "sg:city":"Clovis",
    "sg:classifiers":[
        {
            "category":"Shopping",
            "subcategory":"Clothing, Apparel, & Fashions",
            "type":"Retail Goods"
        }
    ],
    "sg:phone":"+1 505 762 0650",
    "sg:postcode":"88101",
    "sg:province":"NM",
    "sg:tags":[
        "shop",
        "bridal"
    ],
    "wof:name":"Blanca's",
    "wof:placetype":"venue"
},
  "geometry": {"coordinates":[-103.19646,34.410767],"type":"Point"}
}