{
  "type": "Feature",
  "properties": {
    "addr:full":"6001 Indian School Rd NE Albuquerque NM 87110",
    "addr:housenumber":"6001",
    "addr:postcode":"87110",
    "addr:street":"Indian School Rd Ne",
    "iso:country":"US",
    "sg:address":"6001 Indian School Rd NE",
    "sg:city":"Albuquerque",
    "sg:classifiers":[
        {
            "category":"Professional",
            "subcategory":"Engineering",
            "type":"Services"
        }
    ],
    "sg:phone":"+1 505 884 5600",
    "sg:postcode":"87110",
    "sg:province":"NM",
    "sg:tags":[
        "firm",
        "consulting"
    ],
    "wof:name":"CH2M Hill",
    "wof:placetype":"venue"
},
  "geometry": {"coordinates":[-106.575717,35.102651],"type":"Point"}
}