{
  "type": "Feature",
  "properties": {
    "addr:full":"300 N 2nd St Raton NM 87740",
    "addr:housenumber":"300",
    "addr:postcode":"87740",
    "addr:street":"N 2Nd St",
    "iso:country":"US",
    "sg:address":"300 N 2nd St",
    "sg:city":"Raton",
    "sg:classifiers":[
        {
            "category":"Autos & Motor Vehicles",
            "subcategory":"Automobile Sales",
            "type":"Retail Goods"
        }
    ],
    "sg:phone":"+1 505 445 8819",
    "sg:postcode":"87740",
    "sg:province":"NM",
    "sg:tags":[
        "sport",
        "trailer",
        "utility"
    ],
    "wof:name":"H & L Trailers",
    "wof:placetype":"venue"
},
  "geometry": {"coordinates":[-104.439065,36.904434],"type":"Point"}
}