{
  "type": "Feature",
  "properties": {
    "addr:full":"118 W 2nd St Clovis NM 88101",
    "addr:housenumber":"118",
    "addr:postcode":"88101",
    "addr:street":"W 2Nd St",
    "iso:country":"US",
    "sg:address":"118 W 2nd St",
    "sg:city":"Clovis",
    "sg:classifiers":[
        {
            "category":"Home & Garden",
            "subcategory":"Furniture",
            "type":"Retail Goods"
        }
    ],
    "sg:phone":"+1 505 763 3005",
    "sg:postcode":"88101",
    "sg:province":"NM",
    "sg:tags":[
        "business"
    ],
    "wof:name":"Kens Auction Service",
    "wof:placetype":"venue"
},
  "geometry": {"coordinates":[-103.206425,34.39976],"type":"Point"}
}