{
  "type": "Feature",
  "properties": {
    "iso:country":"US",
    "sg:address":"7101 Jefferson St NE",
    "sg:city":"Albuquerque",
    "sg:classifiers":[
        {
            "category":"Shopping",
            "subcategory":"Computers & Home Electronics",
            "type":"Retail Goods"
        }
    ],
    "sg:phone":"+1 505 344 2126",
    "sg:postcode":"87109",
    "sg:province":"NM",
    "wof:name":"Medical Managment West Inc",
    "wof:placetype":"venue"
},
  "geometry": {"coordinates":[-106.593323,35.159753],"type":"Point"}
}