{
  "type": "Feature",
  "properties": {
    "iso:country":"US",
    "sg:address":"6751 Chamisa Ln",
    "sg:city":"Farmington",
    "sg:classifiers":[
        {
            "category":"Shopping",
            "subcategory":"Gifts & Souvenirs",
            "type":"Retail Goods"
        }
    ],
    "sg:phone":"+1 505 326 0590",
    "sg:postcode":"87402",
    "sg:province":"NM",
    "sg:tags":[
        "shop"
    ],
    "wof:name":"Scarlet Feather",
    "wof:placetype":"venue"
},
  "geometry": {"coordinates":[-108.132424,36.791902],"type":"Point"}
}