{
  "type": "Feature",
  "properties": {
    "iso:country":"US",
    "sg:address":"100 SE Pittman St",
    "sg:city":"Seminole",
    "sg:classifiers":[
        {
            "category":"Building & Trades",
            "subcategory":"Construction",
            "type":"Services"
        }
    ],
    "sg:phone":"+1 432 758 9899",
    "sg:postcode":"79360",
    "sg:province":"NM",
    "wof:name":"AWR Construction",
    "wof:placetype":"venue"
},
  "geometry": {"coordinates":[-102.640064,32.71208],"type":"Point"}
}