{
  "type": "Feature",
  "properties": {
    "addr:full":"111 E 6th St Clovis NM 88101",
    "addr:housenumber":"111",
    "addr:postcode":"88101",
    "addr:street":"E 6Th St",
    "iso:country":"US",
    "sg:address":"111 E 6th St",
    "sg:city":"Clovis",
    "sg:classifiers":[
        {
            "category":"Wholesale",
            "subcategory":"Farm Supplies",
            "type":"Manufacturing & Wholesale Goods"
        }
    ],
    "sg:phone":"+1 505 763 5055",
    "sg:postcode":"88101",
    "sg:province":"NM",
    "sg:tags":[
        "feed"
    ],
    "wof:name":"505 Resources Inc",
    "wof:placetype":"venue"
},
  "geometry": {"coordinates":[-103.204137,34.403833],"type":"Point"}
}