{
  "type": "Feature",
  "properties": {
    "iso:country":"US",
    "sg:address":"3803 Riverview Pl NW",
    "sg:city":"Albuquerque",
    "sg:classifiers":[
        {
            "category":"Professional",
            "subcategory":"Management & Consulting",
            "type":"Services"
        }
    ],
    "sg:phone":"+1 505 831 6475",
    "sg:postcode":"87105",
    "sg:province":"NM",
    "sg:tags":[
        "safety",
        "hazard",
        "analysis"
    ],
    "wof:name":"Enregs Inc",
    "wof:placetype":"venue"
},
  "geometry": {"coordinates":[-106.696444,35.097826],"type":"Point"}
}