{
  "type": "Feature",
  "properties": {
    "addr:full":"400 W Coal Ave Gallup NM 87301",
    "addr:housenumber":"400",
    "addr:postcode":"87301",
    "addr:street":"W Coal Ave",
    "iso:country":"US",
    "sg:address":"400 W Coal Ave",
    "sg:city":"Gallup",
    "sg:classifiers":[
        {
            "category":"Autos & Motor Vehicles",
            "subcategory":"Auto Supplies",
            "type":"Retail Goods"
        }
    ],
    "sg:phone":"+1 505 863 6819",
    "sg:postcode":"87301",
    "sg:province":"NM",
    "sg:tags":[
        "tire"
    ],
    "wof:name":"Firestone Tire & Auto Ctr",
    "wof:placetype":"venue"
},
  "geometry": {"coordinates":[-108.74489699999999,35.526313],"type":"Point"}
}