{
  "type": "Feature",
  "properties": {
    "addr:full":"4300 E Pine St Deming NM 88030",
    "addr:housenumber":"4300",
    "addr:postcode":"88030",
    "addr:street":"E Pine St",
    "iso:country":"US",
    "sg:address":"4300 E Pine St",
    "sg:city":"Deming",
    "sg:classifiers":[
        {
            "category":"Travel",
            "subcategory":"Hotels & Motels",
            "type":"Entertainment"
        }
    ],
    "sg:phone":"+1 505 544 7254",
    "sg:postcode":"88030",
    "sg:province":"NM",
    "wof:name":"LA Quinta Inn & Suites",
    "wof:placetype":"venue"
},
  "geometry": {"coordinates":[-107.703439,32.268732],"type":"Point"}
}