{
  "type": "Feature",
  "properties": {
    "addr:full":"814 W 21st St Clovis NM 88101",
    "addr:housenumber":"814",
    "addr:postcode":"88101",
    "addr:street":"W 21St St",
    "iso:country":"US",
    "sg:address":"814 W 21st St",
    "sg:city":"Clovis",
    "sg:classifiers":[
        {
            "category":"Health Services",
            "subcategory":"Doctor",
            "type":"Services"
        }
    ],
    "sg:phone":"+1 575 769 2674",
    "sg:postcode":"88101",
    "sg:province":"NM",
    "sg:tags":[
        "physician",
        "family",
        "practice",
        "surgeons",
        "medicine",
        "surgeon"
    ],
    "wof:name":"Oswald C Graham Md",
    "wof:placetype":"venue"
},
  "geometry": {"coordinates":[-103.216481,34.419312],"type":"Point"}
}