{
  "type": "Feature",
  "properties": {
    "iso:country":"US",
    "sg:address":"4 Molino Viejo",
    "sg:city":"Santa Fe",
    "sg:classifiers":[
        {
            "category":"Building & Trades",
            "subcategory":"Construction",
            "type":"Services"
        }
    ],
    "sg:phone":"+1 505 455 7758",
    "sg:postcode":"87506",
    "sg:province":"NM",
    "sg:tags":[
        "well",
        "drilling"
    ],
    "wof:name":"Romero's Pump Svc",
    "wof:placetype":"venue"
},
  "geometry": {"coordinates":[-105.974288,35.889998],"type":"Point"}
}