{
  "type": "Feature",
  "properties": {
    "iso:country":"US",
    "sg:address":"410 W Hall St",
    "sg:city":"Hatch",
    "sg:classifiers":[
        {
            "category":"Food & Beverages",
            "subcategory":"Groceries & Convenience Stores",
            "type":"Retail Goods"
        }
    ],
    "sg:phone":"+1 505 267 3000",
    "sg:postcode":"87937",
    "sg:province":"NM",
    "wof:name":"B & M Minimart",
    "wof:placetype":"venue"
},
  "geometry": {"coordinates":[-107.157868,32.665598],"type":"Point"}
}