{
  "type": "Feature",
  "properties": {
    "addr:full":"3301 Coors Blvd NW Albuquerque NM 87120",
    "addr:housenumber":"3301",
    "addr:postcode":"87120",
    "addr:street":"Coors Blvd Nw",
    "iso:country":"US",
    "sg:address":"3301 Coors Blvd NW",
    "sg:city":"Albuquerque",
    "sg:classifiers":[
        {
            "category":"Restaurant",
            "type":"Food & Drink"
        }
    ],
    "sg:phone":"+1 505 831 1039",
    "sg:postcode":"87120",
    "sg:province":"NM",
    "sg:tags":[
        "eating"
    ],
    "wof:name":"Burger King",
    "wof:placetype":"venue"
},
  "geometry": {"coordinates":[-106.701724,35.11934],"type":"Point"}
}