{
  "type": "Feature",
  "properties": {
    "addr:full":"71 N Fork Walnut Creek Rd Silver City NM 88061",
    "addr:housenumber":"71",
    "addr:postcode":"88061",
    "addr:street":"N Fork Walnut Creek Rd",
    "iso:country":"US",
    "sg:address":"71 N Fork Walnut Creek Rd",
    "sg:city":"Silver City",
    "sg:classifiers":[
        {
            "category":"Real Estate",
            "subcategory":"Real Estate Agent",
            "type":"Services"
        }
    ],
    "sg:phone":"+1 505 534 9624",
    "sg:postcode":"88061",
    "sg:province":"NM",
    "sg:tags":[
        "rental",
        "vacation"
    ],
    "wof:name":"Walnut Creek Cottages",
    "wof:placetype":"venue"
},
  "geometry": {"coordinates":[-108.327258,32.877196],"type":"Point"}
}