{
  "type": "Feature",
  "properties": {
    "iso:country":"US",
    "sg:address":"2204 Lester Dr NE",
    "sg:city":"Albuquerque",
    "sg:classifiers":[
        {
            "category":"Building & Trades",
            "subcategory":"Construction",
            "type":"Services"
        }
    ],
    "sg:phone":"+1 505 271 5030",
    "sg:postcode":"87112",
    "sg:province":"NM",
    "sg:tags":[
        "house"
    ],
    "wof:name":"Myers Construction",
    "wof:placetype":"venue"
},
  "geometry": {"coordinates":[-106.547146,35.108819],"type":"Point"}
}