{
  "type": "Feature",
  "properties": {
    "addr:full":"236 S 3rd St Raton NM 87740",
    "addr:housenumber":"236",
    "addr:postcode":"87740",
    "addr:street":"S 3Rd St",
    "iso:country":"US",
    "sg:address":"236 S 3rd St",
    "sg:city":"Raton",
    "sg:classifiers":[
        {
            "category":"Organizations",
            "subcategory":"Religious Organization",
            "type":"Services"
        }
    ],
    "sg:phone":"+1 505 445 3571",
    "sg:postcode":"87740",
    "sg:province":"NM",
    "sg:tags":[
        "church"
    ],
    "sg:website":"www.fbcraton.org",
    "wof:name":"First Baptist Church",
    "wof:placetype":"venue"
},
  "geometry": {"coordinates":[-104.441278,36.900696],"type":"Point"}
}