{
  "type": "Feature",
  "properties": {
    "iso:country":"US",
    "sg:address":"1117 Stanford Dr NE",
    "sg:city":"Albuquerque",
    "sg:classifiers":[
        {
            "category":"Education",
            "subcategory":"College",
            "type":"Public Place"
        }
    ],
    "sg:phone":"+1 505 277 4700",
    "sg:postcode":"87106",
    "sg:province":"NM",
    "sg:tags":[
        "legal"
    ],
    "wof:name":"School of Law",
    "wof:placetype":"venue"
},
  "geometry": {"coordinates":[-106.617637,35.094376],"type":"Point"}
}