{
  "type": "Feature",
  "properties": {
    "iso:country":"US",
    "sg:address":"84 E San Francisco St",
    "sg:city":"Santa Fe",
    "sg:classifiers":[
        {
            "category":"Shopping",
            "subcategory":"Jewelry",
            "type":"Retail Goods"
        }
    ],
    "sg:phone":"+1 505 954 4800",
    "sg:postcode":"87501",
    "sg:province":"NM",
    "sg:tags":[
        "jeweler"
    ],
    "wof:name":"Golden Bear",
    "wof:placetype":"venue"
},
  "geometry": {"coordinates":[-105.93892099999999,35.687125],"type":"Point"}
}