{
  "type": "Feature",
  "properties": {
    "iso:country":"US",
    "sg:address":"817 N Canal St",
    "sg:city":"Carlsbad",
    "sg:classifiers":[
        {
            "category":"Restaurant",
            "type":"Food & Drink"
        }
    ],
    "sg:phone":"+1 505 885 8744",
    "sg:postcode":"88220",
    "sg:province":"NM",
    "wof:name":"Red Chimney Pit Bar-B-Q",
    "wof:placetype":"venue"
},
  "geometry": {"coordinates":[-104.228946,32.430046],"type":"Point"}
}