{
  "type": "Feature",
  "properties": {
    "iso:country":"US",
    "sg:address":"103 E Ute St",
    "sg:city":"Farmington",
    "sg:classifiers":[
        {
            "category":"Retail",
            "subcategory":"Funeral Services",
            "type":"Services"
        }
    ],
    "sg:phone":"+1 505 326 9189",
    "sg:postcode":"87401",
    "sg:province":"NM",
    "sg:website":"www.brewerleelarkin.com",
    "wof:name":"Farmington Cremation Society",
    "wof:placetype":"venue"
},
  "geometry": {"coordinates":[-108.203452,36.741134],"type":"Point"}
}