{
  "type": "Feature",
  "properties": {
    "addr:full":"9809 Candelaria Rd NE Albuquerque NM 87112",
    "addr:housenumber":"9809",
    "addr:postcode":"87112",
    "addr:street":"Candelaria Rd Ne",
    "iso:country":"US",
    "sg:address":"9809 Candelaria Rd NE",
    "sg:city":"Albuquerque",
    "sg:classifiers":[
        {
            "category":"Personal",
            "subcategory":"Beauty Salon",
            "type":"Services"
        }
    ],
    "sg:phone":"+1 505 275 0963",
    "sg:postcode":"87112",
    "sg:province":"NM",
    "wof:name":"Head To Toe",
    "wof:placetype":"venue"
},
  "geometry": {"coordinates":[-106.532257,35.116251],"type":"Point"}
}