{
  "type": "Feature",
  "properties": {
    "iso:country":"US",
    "sg:address":"2113 Warner St",
    "sg:city":"Santa Fe",
    "sg:classifiers":[
        {
            "category":"Government",
            "subcategory":"Office",
            "type":"Public Place"
        }
    ],
    "sg:phone":"+1 505 827 3500",
    "sg:postcode":"87505",
    "sg:province":"NM",
    "sg:tags":[
        "state",
        "auditor"
    ],
    "wof:name":"Auditor New Mexico State",
    "wof:placetype":"venue"
},
  "geometry": {"coordinates":[-105.96866799999999,35.659425],"type":"Point"}
}