{
  "type": "Feature",
  "properties": {
    "addr:full":"7 Loma Manzanita Santa Fe NM 87506",
    "addr:housenumber":"7",
    "addr:postcode":"87506",
    "addr:street":"Loma Manzanita",
    "iso:country":"US",
    "sg:address":"7 Loma Manzanita",
    "sg:city":"Santa Fe",
    "sg:classifiers":[
        {
            "category":"Real Estate",
            "subcategory":"Real Estate Agent",
            "type":"Services"
        }
    ],
    "sg:phone":"+1 505 983 1114",
    "sg:postcode":"87506",
    "sg:province":"NM",
    "wof:name":"Norma Marino-Baca",
    "wof:placetype":"venue"
},
  "geometry": {"coordinates":[-106.008396,35.898801],"type":"Point"}
}