{
  "type": "Feature",
  "properties": {
    "iso:country":"US",
    "sg:address":"1001 E University Ave",
    "sg:city":"Las Cruces",
    "sg:classifiers":[
        {
            "category":"Restaurant",
            "type":"Food & Drink"
        }
    ],
    "sg:menulink":"http://www.allmenus.com/nm/las-cruces/6494-great-american-pizza/menu/",
    "sg:phone":"+1 505 522 5775",
    "sg:postcode":"88001",
    "sg:province":"NM",
    "sg:tags":[
        "american",
        "pizza"
    ],
    "wof:name":"Great American Pizza",
    "wof:placetype":"venue"
},
  "geometry": {"coordinates":[-106.75632899999999,32.284099],"type":"Point"}
}