{
  "type": "Feature",
  "properties": {
    "addr:full":"9 Autumnwood Ct Edgewood NM 87015",
    "addr:housenumber":"9",
    "addr:postcode":"87015",
    "addr:street":"Autumnwood Ct",
    "iso:country":"US",
    "sg:address":"9 Autumnwood Ct",
    "sg:city":"Edgewood",
    "sg:classifiers":[
        {
            "category":"Shopping",
            "subcategory":"Catalog Store",
            "type":"Retail Goods"
        }
    ],
    "sg:phone":"+1 505 286 1771",
    "sg:postcode":"87015",
    "sg:province":"NM",
    "sg:tags":[
        "house",
        "mail"
    ],
    "wof:name":"Classic Century",
    "wof:placetype":"venue"
},
  "geometry": {"coordinates":[-106.260136,35.074384],"type":"Point"}
}