{
  "type": "Feature",
  "properties": {
    "iso:country":"US",
    "sg:address":"115 E Alicante Rd",
    "sg:city":"Santa Fe",
    "sg:classifiers":[
        {
            "category":"Professional",
            "subcategory":"Engineering",
            "type":"Services"
        }
    ],
    "sg:phone":"+1 505 983 4366",
    "sg:postcode":"87505",
    "sg:province":"NM",
    "sg:tags":[
        "engineer"
    ],
    "wof:name":"Dennis R Cooper",
    "wof:placetype":"venue"
},
  "geometry": {"coordinates":[-105.941215,35.665401],"type":"Point"}
}