{
  "type": "Feature",
  "properties": {
    "iso:country":"US",
    "sg:address":"3320 Cerrillos Rd",
    "sg:city":"Santa Fe",
    "sg:classifiers":[
        {
            "category":"Home & Garden",
            "subcategory":"Home Furnishings",
            "type":"Retail Goods"
        }
    ],
    "sg:phone":"+1 505 471 3388",
    "sg:postcode":"87507",
    "sg:province":"NM",
    "sg:tags":[
        "housewares"
    ],
    "wof:name":"Bed Bath & Beyond",
    "wof:placetype":"venue"
},
  "geometry": {"coordinates":[-106.001814,35.649028],"type":"Point"}
}