{
  "type": "Feature",
  "properties": {
    "addr:full":"2615 Graceland Dr NE Albuquerque NM 87110",
    "addr:housenumber":"2615",
    "addr:postcode":"87110",
    "addr:street":"Graceland Dr Ne",
    "iso:country":"US",
    "sg:address":"2615 Graceland Dr NE",
    "sg:city":"Albuquerque",
    "sg:classifiers":[
        {
            "category":"Home & Garden",
            "subcategory":"Carpets & Floor Coverings",
            "type":"Retail Goods"
        }
    ],
    "sg:phone":"+1 505 883 4439",
    "sg:postcode":"87110",
    "sg:province":"NM",
    "wof:name":"Mgs Carpet",
    "wof:placetype":"venue"
},
  "geometry": {"coordinates":[-106.59713499999999,35.110823],"type":"Point"}
}