{
  "type": "Feature",
  "properties": {
    "iso:country":"US",
    "sg:address":"821 Canyon Rd",
    "sg:city":"Santa Fe",
    "sg:classifiers":[
        {
            "category":"Shopping",
            "type":"Retail Goods"
        }
    ],
    "sg:phone":"+1 505 983 2640",
    "sg:postcode":"87501",
    "sg:province":"NM",
    "sg:tags":[
        "merchandise"
    ],
    "wof:name":"Ortiz Gallery",
    "wof:placetype":"venue"
},
  "geometry": {"coordinates":[-105.92442,35.680284],"type":"Point"}
}