{
  "type": "Feature",
  "properties": {
    "addr:full":"1501 Lomas Blvd NW Albuquerque NM 87104",
    "addr:housenumber":"1501",
    "addr:postcode":"87104",
    "addr:street":"Lomas Blvd Nw",
    "iso:country":"US",
    "sg:address":"1501 Lomas Blvd NW",
    "sg:city":"Albuquerque",
    "sg:classifiers":[
        {
            "category":"Shopping",
            "subcategory":"Jewelry",
            "type":"Retail Goods"
        },
        {
            "category":"Wholesale",
            "subcategory":"Jewelry",
            "type":"Manufacturing & Wholesale Goods"
        }
    ],
    "sg:phone":"+1 505 247 4442",
    "sg:postcode":"87104",
    "sg:province":"NM",
    "sg:tags":[
        "store",
        "jeweler"
    ],
    "sg:website":"www.gertrudezachary.com",
    "wof:name":"Gertrude Zachary Jewelry Mfg",
    "wof:placetype":"venue"
},
  "geometry": {"coordinates":[-106.66391400000001,35.092834],"type":"Point"}
}