{
  "type": "Feature",
  "properties": {
    "iso:country":"US",
    "sg:address":"7325 4th St NW",
    "sg:city":"Albuquerque",
    "sg:classifiers":[
        {
            "category":"Health Services",
            "subcategory":"Doctor",
            "type":"Services"
        }
    ],
    "sg:phone":"+1 505 898 4360",
    "sg:postcode":"87107",
    "sg:province":"NM",
    "sg:tags":[
        "physician",
        "surgeon"
    ],
    "wof:name":"Arthur S Wershaw MD",
    "wof:placetype":"venue"
},
  "geometry": {"coordinates":[-106.635831,35.167058],"type":"Point"}
}