{
  "type": "Feature",
  "properties": {
    "iso:country":"US",
    "sg:address":"5315 Silver Ave SE",
    "sg:city":"Albuquerque",
    "sg:classifiers":[
        {
            "category":"Autos & Motor Vehicles",
            "subcategory":"Automobile Sales",
            "type":"Retail Goods"
        }
    ],
    "sg:phone":"+1 505 268 6040",
    "sg:postcode":"87108",
    "sg:province":"NM",
    "wof:name":"Sunburst Kar Kleen Sales",
    "wof:placetype":"venue"
},
  "geometry": {"coordinates":[-106.58453,35.076557],"type":"Point"}
}