{
  "type": "Feature",
  "properties": {
    "iso:country":"US",
    "sg:address":"101 Hospital Loop NE",
    "sg:city":"Albuquerque",
    "sg:classifiers":[
        {
            "category":"Health Services",
            "subcategory":"Doctor",
            "type":"Services"
        }
    ],
    "sg:phone":"+1 505 848 3773",
    "sg:postcode":"87109",
    "sg:province":"NM",
    "sg:tags":[
        "nutrition",
        "surgeon",
        "surgeons",
        "physician"
    ],
    "wof:name":"G Michael Dempsey Md",
    "wof:placetype":"venue"
},
  "geometry": {"coordinates":[-106.59256,35.132759],"type":"Point"}
}