{
  "type": "Feature",
  "properties": {
    "iso:country":"US",
    "sg:address":"1327 Ortiz Dr SE",
    "sg:city":"Albuquerque",
    "sg:classifiers":[
        {
            "category":"Wholesale",
            "subcategory":"Jewelry",
            "type":"Manufacturing & Wholesale Goods"
        }
    ],
    "sg:phone":"+1 505 268 6986",
    "sg:postcode":"87108",
    "sg:province":"NM",
    "sg:tags":[
        "stone"
    ],
    "wof:name":"Cheri Clay Designs",
    "wof:placetype":"venue"
},
  "geometry": {"coordinates":[-106.585433,35.060654],"type":"Point"}
}