{
  "type": "Feature",
  "properties": {
    "iso:country":"US",
    "sg:address":"3813 Hawkins St NE",
    "sg:city":"Albuquerque",
    "sg:classifiers":[
        {
            "category":"Manufacturing",
            "subcategory":"Signs",
            "type":"Manufacturing & Wholesale Goods"
        }
    ],
    "sg:phone":"+1 505 797 3076",
    "sg:postcode":"87109",
    "sg:province":"NM",
    "sg:tags":[
        "advertising",
        "mfg"
    ],
    "sg:website":"www.signarama.com",
    "wof:name":"Sign-A-Rama",
    "wof:placetype":"venue"
},
  "geometry": {"coordinates":[-106.602009,35.162818],"type":"Point"}
}