{
  "type": "Feature",
  "properties": {
    "addr:full":"3554 Agua Fria St Santa Fe NM 87507",
    "addr:housenumber":"3554",
    "addr:postcode":"87507",
    "addr:street":"Agua Fria St",
    "iso:country":"US",
    "sg:address":"3554 Agua Fria St",
    "sg:city":"Santa Fe",
    "sg:classifiers":[
        {
            "category":"Wholesale",
            "subcategory":"Machinery & Supplies",
            "type":"Manufacturing & Wholesale Goods"
        }
    ],
    "sg:phone":"+1 505 471 5180",
    "sg:postcode":"87507",
    "sg:province":"NM",
    "wof:name":"Earth & Water Inc",
    "wof:placetype":"venue"
},
  "geometry": {"coordinates":[-106.01063600000001,35.658862],"type":"Point"}
}