{
  "type": "Feature",
  "properties": {
    "iso:country":"US",
    "sg:address":"108 W Apache St",
    "sg:city":"Farmington",
    "sg:classifiers":[
        {
            "category":"Professional",
            "type":"Services"
        }
    ],
    "sg:phone":"+1 505 325 6078",
    "sg:postcode":"87401",
    "sg:province":"NM",
    "sg:tags":[
        "establishment"
    ],
    "wof:name":"Drake JA Well Servicing Co",
    "wof:placetype":"venue"
},
  "geometry": {"coordinates":[-108.206253,36.734037],"type":"Point"}
}