{
  "type": "Feature",
  "properties": {
    "addr:full":"1100 San Mateo Blvd NE Albuquerque NM 87110",
    "addr:housenumber":"1100",
    "addr:postcode":"87110",
    "addr:street":"San Mateo Blvd Ne",
    "iso:country":"US",
    "sg:address":"1100 San Mateo Blvd NE",
    "sg:city":"Albuquerque",
    "sg:classifiers":[
        {
            "category":"Autos & Motor Vehicles",
            "subcategory":"Automobile Sales",
            "type":"Retail Goods"
        }
    ],
    "sg:phone":"+1 505 255 7800",
    "sg:postcode":"87110",
    "sg:province":"NM",
    "sg:tags":[
        "car",
        "dealer"
    ],
    "sg:website":"www.motorworldnm.com",
    "wof:name":"Motorworld",
    "wof:placetype":"venue"
},
  "geometry": {"coordinates":[-106.58614900000001,35.088336],"type":"Point"}
}