{
  "type": "Feature",
  "properties": {
    "iso:country":"US",
    "sg:address":"400 Lake Dr",
    "sg:city":"Santa Rosa",
    "sg:classifiers":[
        {
            "category":"Building & Trades",
            "subcategory":"Landscaping Services",
            "type":"Services"
        }
    ],
    "sg:phone":"+1 505 472 5955",
    "sg:postcode":"88435",
    "sg:province":"NM",
    "sg:tags":[
        "maintenance"
    ],
    "wof:name":"Bill Montoya Lawn & Maint",
    "wof:placetype":"venue"
},
  "geometry": {"coordinates":[-104.6795,34.94146],"type":"Point"}
}