{
  "type": "Feature",
  "properties": {
    "iso:country":"US",
    "sg:address":"5643 4th St NW",
    "sg:city":"Albuquerque",
    "sg:classifiers":[
        {
            "category":"Shopping",
            "subcategory":"Used Merchandise",
            "type":"Retail Goods"
        }
    ],
    "sg:phone":"+1 505 345 9097",
    "sg:postcode":"87107",
    "sg:province":"NM",
    "sg:tags":[
        "shop",
        "jewelry",
        "pawn",
        "pawnbroker",
        "mail",
        "order"
    ],
    "wof:name":"Pawn City Inc",
    "wof:placetype":"venue"
},
  "geometry": {"coordinates":[-106.64120699999999,35.139336],"type":"Point"}
}