{
  "type": "Feature",
  "properties": {
    "iso:country":"US",
    "sg:address":"7405 Dulce Rd",
    "sg:city":"Carlsbad",
    "sg:classifiers":[
        {
            "category":"Recreation",
            "subcategory":"Arcade",
            "type":"Entertainment"
        },
        {
            "category":"Building & Trades",
            "subcategory":"Equipment Rental",
            "type":"Services"
        }
    ],
    "sg:phone":"+1 505 885 0009",
    "sg:postcode":"88220",
    "sg:province":"NM",
    "sg:tags":[
        "amusement",
        "devices"
    ],
    "wof:name":"Tony's Rentals",
    "wof:placetype":"venue"
},
  "geometry": {"coordinates":[-104.226136,32.31565],"type":"Point"}
}