{
  "type": "Feature",
  "properties": {
    "iso:country":"US",
    "sg:address":"1221 W Pierce St",
    "sg:city":"Carlsbad",
    "sg:classifiers":[
        {
            "category":"Retail",
            "subcategory":"Auto Repair",
            "type":"Services"
        }
    ],
    "sg:phone":"+1 505 885 8713",
    "sg:postcode":"88220",
    "sg:province":"NM",
    "sg:tags":[
        "repairing",
        "automobile"
    ],
    "wof:name":"Master Lube",
    "wof:placetype":"venue"
},
  "geometry": {"coordinates":[-104.243359,32.435766],"type":"Point"}
}