{
  "type": "Feature",
  "properties": {
    "iso:country":"US",
    "sg:address":"3561 Zafarano Dr",
    "sg:city":"Santa Fe",
    "sg:classifiers":[
        {
            "category":"Shopping",
            "type":"Retail Goods"
        }
    ],
    "sg:phone":"+1 505 471 5255",
    "sg:postcode":"87507",
    "sg:province":"NM",
    "sg:tags":[
        "pet",
        "shop"
    ],
    "wof:name":"Petsmart",
    "wof:placetype":"venue"
},
  "geometry": {"coordinates":[-106.011488,35.63979],"type":"Point"}
}