{
  "type": "Feature",
  "properties": {
    "iso:country":"US",
    "sg:address":"2900 Barcelona Rd SW",
    "sg:city":"Albuquerque",
    "sg:classifiers":[
        {
            "category":"Building & Trades",
            "subcategory":"Construction",
            "type":"Services"
        }
    ],
    "sg:phone":"+1 505 720 0927",
    "sg:postcode":"87105",
    "sg:province":"NM",
    "sg:tags":[
        "house"
    ],
    "wof:name":"Aj Renovation",
    "wof:placetype":"venue"
},
  "geometry": {"coordinates":[-106.702253,35.030561],"type":"Point"}
}