{
  "type": "Feature",
  "properties": {
    "addr:full":"422 Texas St NE Albuquerque NM 87108",
    "addr:housenumber":"422",
    "addr:postcode":"87108",
    "addr:street":"Texas St Ne",
    "iso:country":"US",
    "sg:address":"422 Texas St NE",
    "sg:city":"Albuquerque",
    "sg:classifiers":[
        {
            "category":"Building & Trades",
            "subcategory":"Construction",
            "type":"Services"
        }
    ],
    "sg:phone":"+1 505 401 0003",
    "sg:postcode":"87108",
    "sg:province":"NM",
    "sg:tags":[
        "handyman"
    ],
    "wof:name":"Wiley Coyote",
    "wof:placetype":"venue"
},
  "geometry": {"coordinates":[-106.555701,35.083272],"type":"Point"}
}