{
  "type": "Feature",
  "properties": {
    "addr:full":"601 4th St SW Albuquerque NM 87102",
    "addr:housenumber":"601",
    "addr:postcode":"87102",
    "addr:street":"4Th St Sw",
    "iso:country":"US",
    "sg:address":"601 4th St SW",
    "sg:city":"Albuquerque",
    "sg:classifiers":[
        {
            "category":"Education",
            "subcategory":"School",
            "type":"Public Place"
        }
    ],
    "sg:phone":"+1 505 247 1012",
    "sg:postcode":"87102",
    "sg:province":"NM",
    "wof:name":"Coronado Complex Special Ed",
    "wof:placetype":"venue"
},
  "geometry": {"coordinates":[-106.65273999999999,35.078668],"type":"Point"}
}