{
  "type": "Feature",
  "properties": {
    "iso:country":"US",
    "sg:address":"2701 7th St",
    "sg:city":"Las Vegas",
    "sg:classifiers":[
        {
            "category":"Building & Trades",
            "subcategory":"Construction",
            "type":"Services"
        }
    ],
    "sg:phone":"+1 505 425 5837",
    "sg:postcode":"87701",
    "sg:province":"NM",
    "sg:tags":[
        "general",
        "contractor"
    ],
    "wof:name":"Carlson Construction Co",
    "wof:placetype":"venue"
},
  "geometry": {"coordinates":[-105.22556,35.621469],"type":"Point"}
}