{
  "type": "Feature",
  "properties": {
    "iso:country":"US",
    "sg:address":"1607 Silver Ave SE",
    "sg:city":"Albuquerque",
    "sg:classifiers":[
        {
            "category":"Health Services",
            "subcategory":"Doctor",
            "type":"Services"
        }
    ],
    "sg:phone":"+1 505 247 9539",
    "sg:postcode":"87106",
    "sg:province":"NM",
    "sg:tags":[
        "medical"
    ],
    "wof:name":"Shy Drager Syndrome Support Gr",
    "wof:placetype":"venue"
},
  "geometry": {"coordinates":[-106.62835099999999,35.079582],"type":"Point"}
}