{
  "type": "Feature",
  "properties": {
    "iso:country":"US",
    "sg:address":"905 W Conway Ave",
    "sg:city":"Las Cruces",
    "sg:classifiers":[
        {
            "category":"Wholesale",
            "subcategory":"Books, Periodicals, & Newspapers",
            "type":"Manufacturing & Wholesale Goods"
        }
    ],
    "sg:phone":"+1 505 541 5680",
    "sg:postcode":"88005",
    "sg:province":"NM",
    "wof:name":"Bioguide Press",
    "wof:placetype":"venue"
},
  "geometry": {"coordinates":[-106.777962,32.272561],"type":"Point"}
}