{
  "type": "Feature",
  "properties": {
    "iso:country":"US",
    "sg:address":"1501 Mountain Rd NW",
    "sg:city":"Albuquerque",
    "sg:classifiers":[
        {
            "category":"Personal",
            "subcategory":"Beauty Salon",
            "type":"Services"
        }
    ],
    "sg:phone":"+1 505 244 9104",
    "sg:postcode":"87104",
    "sg:province":"NM",
    "wof:name":"Kamaria Creations Hair & Skin",
    "wof:placetype":"venue"
},
  "geometry": {"coordinates":[-106.663399,35.096745],"type":"Point"}
}