{
  "type": "Feature",
  "properties": {
    "addr:full":"8 Ladera Rd Los Lunas NM 87002",
    "addr:housenumber":"8",
    "addr:postcode":"87002",
    "addr:street":"Ladera Rd",
    "iso:country":"US",
    "sg:address":"8 Ladera Rd",
    "sg:city":"Los Lunas",
    "sg:classifiers":[
        {
            "category":"Real Estate",
            "subcategory":"Developer",
            "type":"Services"
        },
        {
            "category":"Real Estate",
            "subcategory":"Real Estate Operator",
            "type":"Services"
        }
    ],
    "sg:phone":"+1 505 865 7985",
    "sg:postcode":"87002",
    "sg:province":"NM",
    "sg:tags":[
        "mobile",
        "home",
        "site"
    ],
    "wof:name":"D & J Mobile Home Park",
    "wof:placetype":"venue"
},
  "geometry": {"coordinates":[-106.784115,34.729267],"type":"Point"}
}