{
  "type": "Feature",
  "properties": {
    "addr:full":"16 Valley Rd Santa Fe NM 87557",
    "addr:housenumber":"16",
    "addr:postcode":"87557",
    "addr:street":"Valley Rd",
    "iso:country":"US",
    "sg:address":"16 Valley Rd",
    "sg:city":"Santa Fe",
    "sg:classifiers":[
        {
            "category":"Building & Trades",
            "subcategory":"Cleaning & Sanitation",
            "type":"Services"
        }
    ],
    "sg:phone":"+1 505 471 0800",
    "sg:postcode":"87557",
    "sg:province":"NM",
    "sg:tags":[
        "maintenance"
    ],
    "wof:name":"Kic Janitorial Svc",
    "wof:placetype":"venue"
},
  "geometry": {"coordinates":[-105.610849,36.346557],"type":"Point"}
}