{
  "type": "Feature",
  "properties": {
    "iso:country":"US",
    "sg:address":"802 Pinehurst Rd SE",
    "sg:city":"Rio Rancho",
    "sg:classifiers":[
        {
            "category":"Professional",
            "type":"Services"
        }
    ],
    "sg:phone":"+1 505 891 3542",
    "sg:postcode":"87124",
    "sg:province":"NM",
    "sg:tags":[
        "establishment"
    ],
    "wof:name":"Collatz Inc",
    "wof:placetype":"venue"
},
  "geometry": {"coordinates":[-106.658096,35.243576],"type":"Point"}
}