{
  "type": "Feature",
  "properties": {
    "iso:country":"US",
    "sg:address":"4198 US Hwy 64",
    "sg:city":"Kirtland",
    "sg:classifiers":[
        {
            "category":"Restaurant",
            "type":"Food & Drink"
        }
    ],
    "sg:phone":"+1 505 598 1228",
    "sg:postcode":"87417",
    "sg:province":"NM",
    "wof:name":"KFC",
    "wof:placetype":"venue"
},
  "geometry": {"coordinates":[-108.357555,36.742548],"type":"Point"}
}