{
  "type": "Feature",
  "properties": {
    "addr:full":"604 W Broadway St Hobbs NM 88240",
    "addr:housenumber":"604",
    "addr:postcode":"88240",
    "addr:street":"W Broadway St",
    "iso:country":"US",
    "sg:address":"604 W Broadway St",
    "sg:city":"Hobbs",
    "sg:classifiers":[
        {
            "category":"Organizations",
            "subcategory":"Political Organization",
            "type":"Services"
        }
    ],
    "sg:phone":"+1 505 393 1336",
    "sg:postcode":"88240",
    "sg:province":"NM",
    "wof:name":"Democratics Headquarters",
    "wof:placetype":"venue"
},
  "geometry": {"coordinates":[-103.14246300000001,32.700892],"type":"Point"}
}