{
  "type": "Feature",
  "properties": {
    "addr:full":"2408 Cam del Oso Santa Fe NM 87501",
    "addr:housenumber":"2408",
    "addr:postcode":"87501",
    "addr:street":"Cam Del Oso",
    "iso:country":"US",
    "sg:address":"2408 Cam del Oso",
    "sg:city":"Santa Fe",
    "sg:phone":"+1 505 982 5900",
    "sg:postcode":"87501",
    "sg:province":"NM",
    "sg:tags":[
        "farm",
        "cotton"
    ],
    "wof:name":"Hall Farms",
    "wof:placetype":"venue"
},
  "geometry": {"coordinates":[-105.88961999999999,35.720376],"type":"Point"}
}