{
  "type": "Feature",
  "properties": {
    "iso:country":"US",
    "sg:address":"1484 Columbia Ave",
    "sg:city":"Alamogordo",
    "sg:classifiers":[
        {
            "category":"Organizations",
            "subcategory":"Religious Organization",
            "type":"Services"
        }
    ],
    "sg:phone":"+1 505 437 6028",
    "sg:postcode":"88310",
    "sg:province":"NM",
    "wof:name":"Community Bptst Chrch Almgordo",
    "wof:placetype":"venue"
},
  "geometry": {"coordinates":[-105.99681699999999,32.859583],"type":"Point"}
}