{
  "type": "Feature",
  "properties": {
    "iso:country":"US",
    "sg:address":"4480 Overlook Ln",
    "sg:city":"Las Cruces",
    "sg:classifiers":[
        {
            "category":"Shopping",
            "subcategory":"Gifts & Souvenirs",
            "type":"Retail Goods"
        }
    ],
    "sg:phone":"+1 505 647 3658",
    "sg:postcode":"88007",
    "sg:province":"NM",
    "sg:tags":[
        "interior",
        "decorating"
    ],
    "wof:name":"Sweet William",
    "wof:placetype":"venue"
},
  "geometry": {"coordinates":[-106.830448,32.348489],"type":"Point"}
}