{
  "type": "Feature",
  "properties": {
    "iso:country":"US",
    "sg:address":"1203 Cll Luna",
    "sg:city":"Santa Fe",
    "sg:classifiers":[
        {
            "category":"Personal",
            "type":"Services"
        }
    ],
    "sg:phone":"+1 505 820 1203",
    "sg:postcode":"87501",
    "sg:province":"NM",
    "wof:name":"Feng Shui Santa Fe",
    "wof:placetype":"venue"
},
  "geometry": {"coordinates":[-105.916606,35.691494],"type":"Point"}
}