{
  "type": "Feature",
  "properties": {
    "iso:country":"US",
    "sg:address":"1749 State Hwy 17",
    "sg:city":"Chama",
    "sg:classifiers":[
        {
            "category":"Restaurant",
            "type":"Food & Drink"
        }
    ],
    "sg:phone":"+1 505 756 2989",
    "sg:postcode":"87520",
    "sg:province":"NM",
    "wof:name":"Bar-B-Que Place",
    "wof:placetype":"venue"
},
  "geometry": {"coordinates":[-106.58185899999999,36.894095],"type":"Point"}
}