{
  "type": "Feature",
  "properties": {
    "iso:country":"US",
    "sg:address":"154 Caldwell Ave",
    "sg:city":"Belen",
    "sg:classifiers":[
        {
            "category":"Cinema",
            "subcategory":"Movie Rental",
            "type":"Entertainment"
        }
    ],
    "sg:phone":"+1 505 864 3399",
    "sg:postcode":"87002",
    "sg:province":"NM",
    "sg:tags":[
        "video",
        "game",
        "leasing"
    ],
    "wof:name":"Sunset Video Inc",
    "wof:placetype":"venue"
},
  "geometry": {"coordinates":[-106.760444,34.659622],"type":"Point"}
}