{
  "type": "Feature",
  "properties": {
    "addr:full":"200 N Main St Roswell NM 88201",
    "addr:housenumber":"200",
    "addr:postcode":"88201",
    "addr:street":"N Main St",
    "iso:country":"US",
    "sg:address":"200 N Main St",
    "sg:city":"Roswell",
    "sg:classifiers":[
        {
            "category":"Restaurant",
            "type":"Food & Drink"
        }
    ],
    "sg:phone":"+1 505 623 5377",
    "sg:postcode":"88201",
    "sg:province":"NM",
    "wof:name":"Denny's",
    "wof:placetype":"venue"
},
  "geometry": {"coordinates":[-104.522751,33.395384],"type":"Point"}
}