{
  "type": "Feature",
  "properties": {
    "iso:country":"US",
    "sg:address":"609 San Mateo Blvd NE",
    "sg:city":"Albuquerque",
    "sg:classifiers":[
        {
            "category":"Travel",
            "subcategory":"Travel Agent",
            "type":"Entertainment"
        }
    ],
    "sg:phone":"+1 505 255 8234",
    "sg:postcode":"87108",
    "sg:province":"NM",
    "sg:tags":[
        "agency"
    ],
    "wof:name":"International Travel Assoc",
    "wof:placetype":"venue"
},
  "geometry": {"coordinates":[-106.586268,35.083595],"type":"Point"}
}