{
  "type": "Feature",
  "properties": {
    "iso:country":"US",
    "sg:address":"2 N Lake Rd",
    "sg:city":"Artesia",
    "sg:classifiers":[
        {
            "category":"Retail",
            "subcategory":"Auto Repair",
            "type":"Services"
        }
    ],
    "sg:phone":"+1 505 746 4084",
    "sg:postcode":"88210",
    "sg:province":"NM",
    "sg:tags":[
        "body",
        "special",
        "mfg"
    ],
    "wof:name":"SRU Graphics & Customizing",
    "wof:placetype":"venue"
},
  "geometry": {"coordinates":[-104.37825599999999,32.76974],"type":"Point"}
}