{
  "type": "Feature",
  "properties": {
    "iso:country":"US",
    "sg:address":"2809 N Prince St",
    "sg:city":"Clovis",
    "sg:classifiers":[
        {
            "category":"Government",
            "subcategory":"Office",
            "type":"Public Place"
        }
    ],
    "sg:phone":"+1 505 769 2851",
    "sg:postcode":"88101",
    "sg:province":"NM",
    "sg:tags":[
        "armed",
        "force",
        "recruiting"
    ],
    "wof:name":"US Army Recruiting",
    "wof:placetype":"venue"
},
  "geometry": {"coordinates":[-103.19645199999999,34.423314],"type":"Point"}
}