{
  "type": "Feature",
  "properties": {
    "addr:full":"805 Charles St Grants NM 87020",
    "addr:housenumber":"805",
    "addr:postcode":"87020",
    "addr:street":"Charles St",
    "iso:country":"US",
    "sg:address":"805 Charles St",
    "sg:city":"Grants",
    "sg:classifiers":[
        {
            "category":"Organizations",
            "subcategory":"Community Association",
            "type":"Services"
        }
    ],
    "sg:phone":"+1 505 287 3885",
    "sg:postcode":"87020",
    "sg:province":"NM",
    "sg:tags":[
        "fraternal"
    ],
    "wof:name":"Elks Lodge",
    "wof:placetype":"venue"
},
  "geometry": {"coordinates":[-107.840035,35.155658],"type":"Point"}
}