{
  "type": "Feature",
  "properties": {
    "iso:country":"US",
    "sg:address":"530 Harkle Rd",
    "sg:city":"Santa Fe",
    "sg:classifiers":[
        {
            "category":"Professional",
            "subcategory":"Lawyer & Legal Services",
            "type":"Services"
        }
    ],
    "sg:phone":"+1 505 989 1434",
    "sg:postcode":"87505",
    "sg:province":"NM",
    "sg:tags":[
        "attorney"
    ],
    "wof:name":"Cassutt Hays & Friedman PA",
    "wof:placetype":"venue"
},
  "geometry": {"coordinates":[-105.948871,35.660031],"type":"Point"}
}