{
  "type": "Feature",
  "properties": {
    "iso:country":"US",
    "sg:address":"5601 Midway Park Pl NE",
    "sg:city":"Albuquerque",
    "sg:classifiers":[
        {
            "category":"Utilities",
            "subcategory":"Water",
            "type":"Services"
        }
    ],
    "sg:phone":"+1 505 595 1509",
    "sg:postcode":"87109",
    "sg:province":"NM",
    "sg:tags":[
        "merchandise",
        "supply"
    ],
    "wof:name":"United States Filter Corp",
    "wof:placetype":"venue"
},
  "geometry": {"coordinates":[-106.60410899999999,35.142534],"type":"Point"}
}