{
  "type": "Feature",
  "properties": {
    "addr:full":"5600 Rinconada St Farmington NM 87402",
    "addr:postcode":"5600;87402",
    "addr:street":"Rinconada St",
    "iso:country":"US",
    "sg:address":"5600 Rinconada St",
    "sg:city":"Farmington",
    "sg:classifiers":[
        {
            "category":"Mining & Drilling",
            "type":"Manufacturing & Wholesale Goods"
        }
    ],
    "sg:phone":"+1 505 326 3192",
    "sg:postcode":"87402",
    "sg:province":"NM",
    "sg:tags":[
        "field",
        "oil"
    ],
    "wof:name":"Protocom Consulting Inc",
    "wof:placetype":"venue"
},
  "geometry": {"coordinates":[-108.136833,36.791429],"type":"Point"}
}