{
  "type": "Feature",
  "properties": {
    "iso:country":"US",
    "sg:address":"11000 Central Ave SE",
    "sg:city":"Albuquerque",
    "sg:classifiers":[
        {
            "category":"Shopping",
            "type":"Retail Goods"
        },
        {
            "category":"Home & Garden",
            "subcategory":"Mobile Homes",
            "type":"Retail Goods"
        }
    ],
    "sg:phone":"+1 505 292 3131",
    "sg:postcode":"87123",
    "sg:province":"NM",
    "sg:tags":[
        "material",
        "commercial",
        "unit",
        "merchandise"
    ],
    "sg:website":"www.morganusa.com",
    "wof:name":"Morgan Buildings Pools & Spas",
    "wof:placetype":"venue"
},
  "geometry": {"coordinates":[-106.521647,35.070755],"type":"Point"}
}