{
  "type": "Feature",
  "properties": {
    "iso:country":"US",
    "sg:address":"1720 Juan Tabo Blvd NE",
    "sg:city":"Albuquerque",
    "sg:classifiers":[
        {
            "category":"Banks & Credit Unions",
            "subcategory":"Bank",
            "type":"Services"
        }
    ],
    "sg:phone":"+1 505 823 6622",
    "sg:postcode":"87112",
    "sg:province":"NM",
    "sg:tags":[
        "loan",
        "real estate"
    ],
    "wof:name":"Canyon Mortgage Bankers",
    "wof:placetype":"venue"
},
  "geometry": {"coordinates":[-106.515355,35.101095],"type":"Point"}
}