{
  "type": "Feature",
  "properties": {
    "iso:country":"US",
    "sg:address":"225 E Idaho Ave",
    "sg:city":"Las Cruces",
    "sg:classifiers":[
        {
            "category":"Health Services",
            "subcategory":"Doctor",
            "type":"Services"
        }
    ],
    "sg:phone":"+1 505 647 9047",
    "sg:postcode":"88005",
    "sg:province":"NM",
    "sg:tags":[
        "dentist"
    ],
    "wof:name":"A 1 Dental",
    "wof:placetype":"venue"
},
  "geometry": {"coordinates":[-106.776984,32.296122],"type":"Point"}
}