{
  "type": "Feature",
  "properties": {
    "iso:country":"US",
    "sg:address":"6900 Zuni Rd SE",
    "sg:city":"Albuquerque",
    "sg:classifiers":[
        {
            "category":"Food & Beverages",
            "subcategory":"Groceries & Convenience Stores",
            "type":"Retail Goods"
        }
    ],
    "sg:phone":"+1 505 268 8122",
    "sg:postcode":"87108",
    "sg:province":"NM",
    "sg:website":"www.allsups.com",
    "wof:name":"Allsup's Convenience Store",
    "wof:placetype":"venue"
},
  "geometry": {"coordinates":[-106.569705,35.072668],"type":"Point"}
}