{
  "type": "Feature",
  "properties": {
    "iso:country":"US",
    "sg:address":"611 Lead Ave SW",
    "sg:city":"Albuquerque",
    "sg:classifiers":[
        {
            "category":"Professional",
            "type":"Services"
        }
    ],
    "sg:phone":"+1 505 842 8738",
    "sg:postcode":"87102",
    "sg:province":"NM",
    "wof:name":"Shields Vm Inc",
    "wof:placetype":"venue"
},
  "geometry": {"coordinates":[-106.65563,35.082117],"type":"Point"}
}