{
  "type": "Feature",
  "properties": {
    "iso:country":"US",
    "sg:address":"7605 Cutler Ave NE",
    "sg:city":"Albuquerque",
    "sg:classifiers":[
        {
            "category":"Building & Trades",
            "subcategory":"Construction",
            "type":"Services"
        }
    ],
    "sg:phone":"+1 505 830 0338",
    "sg:postcode":"87110",
    "sg:province":"NM",
    "sg:tags":[
        "residential"
    ],
    "wof:name":"Duke City Construction",
    "wof:placetype":"venue"
},
  "geometry": {"coordinates":[-106.559979,35.107137],"type":"Point"}
}