{
  "type": "Feature",
  "properties": {
    "iso:country":"US",
    "sg:address":"32 Ivy Ln",
    "sg:city":"La Luz",
    "sg:classifiers":[
        {
            "category":"Building & Trades",
            "subcategory":"Construction",
            "type":"Services"
        }
    ],
    "sg:phone":"+1 505 437 7769",
    "sg:postcode":"88337",
    "sg:province":"NM",
    "sg:tags":[
        "general",
        "contractor"
    ],
    "wof:name":"Williamson Construction Inc",
    "wof:placetype":"venue"
},
  "geometry": {"coordinates":[-105.975168,32.992762],"type":"Point"}
}