{
  "type": "Feature",
  "properties": {
    "iso:country":"US",
    "sg:address":"6176 Hwy 64",
    "sg:city":"Bloomfield",
    "sg:classifiers":[
        {
            "category":"Autos & Motor Vehicles",
            "subcategory":"Fuel & Gas Station",
            "type":"Retail Goods"
        }
    ],
    "sg:phone":"+1 505 632 2975",
    "sg:postcode":"87413",
    "sg:province":"NM",
    "sg:tags":[
        "oil"
    ],
    "wof:name":"Amigo Marts",
    "wof:placetype":"venue"
},
  "geometry": {"coordinates":[-108.020853,36.706086],"type":"Point"}
}