{
  "type": "Feature",
  "properties": {
    "addr:full":"1505 W Pierce St Carlsbad NM 88220",
    "addr:housenumber":"1505",
    "addr:postcode":"88220",
    "addr:street":"W Pierce St",
    "iso:country":"US",
    "sg:address":"1505 W Pierce St",
    "sg:city":"Carlsbad",
    "sg:classifiers":[
        {
            "category":"Shopping",
            "subcategory":"Discount & Variety Stores",
            "type":"Retail Goods"
        }
    ],
    "sg:phone":"+1 505 885 3527",
    "sg:postcode":"88220",
    "sg:province":"NM",
    "wof:name":"Dollar Store",
    "wof:placetype":"venue"
},
  "geometry": {"coordinates":[-104.24864100000001,32.436627],"type":"Point"}
}