{
  "type": "Feature",
  "properties": {
    "iso:country":"US",
    "sg:address":"8816 Democracy Rd NE",
    "sg:city":"Albuquerque",
    "sg:classifiers":[
        {
            "category":"Wholesale",
            "subcategory":"Non-durable Goods",
            "type":"Manufacturing & Wholesale Goods"
        }
    ],
    "sg:phone":"+1 505 858 0035",
    "sg:postcode":"87109",
    "sg:province":"NM",
    "wof:name":"Rowan Trading Company",
    "wof:placetype":"venue"
},
  "geometry": {"coordinates":[-106.545782,35.171259],"type":"Point"}
}