{
  "type": "Feature",
  "properties": {
    "iso:country":"US",
    "sg:address":"4910 Cutler Ave NE",
    "sg:city":"Albuquerque",
    "sg:classifiers":[
        {
            "category":"Shopping",
            "subcategory":"Shoes",
            "type":"Retail Goods"
        }
    ],
    "sg:phone":"+1 505 872 8600",
    "sg:postcode":"87110",
    "sg:province":"NM",
    "wof:name":"Good Feet Store",
    "wof:placetype":"venue"
},
  "geometry": {"coordinates":[-106.590447,35.105489],"type":"Point"}
}