{
  "type": "Feature",
  "properties": {
    "addr:full":"263 Francis Ave Raton NM 87740",
    "addr:housenumber":"263",
    "addr:postcode":"87740",
    "addr:street":"Francis Ave",
    "iso:country":"US",
    "sg:address":"263 Francis Ave",
    "sg:city":"Raton",
    "sg:classifiers":[
        {
            "category":"Organizations",
            "subcategory":"Religious Organization",
            "type":"Services"
        }
    ],
    "sg:phone":"+1 505 445 2255",
    "sg:postcode":"87740",
    "sg:province":"NM",
    "wof:name":"Johnson Mesa Church Assn",
    "wof:placetype":"venue"
},
  "geometry": {"coordinates":[-104.444908,36.909988],"type":"Point"}
}