{
  "type": "Feature",
  "properties": {
    "iso:country":"US",
    "sg:address":"3900 Pso del Sol",
    "sg:city":"Santa Fe",
    "sg:classifiers":[
        {
            "category":"Organizations",
            "subcategory":"Professional Association",
            "type":"Services"
        }
    ],
    "sg:phone":"+1 505 473 1004",
    "sg:postcode":"87507",
    "sg:province":"NM",
    "wof:name":"Farm To Table",
    "wof:placetype":"venue"
},
  "geometry": {"coordinates":[-106.043719,35.634071],"type":"Point"}
}