{
  "type": "Feature",
  "properties": {
    "iso:country":"US",
    "sg:address":"9988 2nd St NW",
    "sg:city":"Albuquerque",
    "sg:classifiers":[
        {
            "category":"Building & Trades",
            "subcategory":"Plumbing",
            "type":"Services"
        }
    ],
    "sg:phone":"+1 505 899 2939",
    "sg:postcode":"87114",
    "sg:province":"NM",
    "sg:tags":[
        "sheet",
        "work",
        "metal",
        "contractor"
    ],
    "wof:name":"Four Winds Mechanical Heat",
    "wof:placetype":"venue"
},
  "geometry": {"coordinates":[-106.612071,35.193307],"type":"Point"}
}