{
  "type": "Feature",
  "properties": {
    "addr:full":"6815 Marigot Rd NW Albuquerque NM 87120",
    "addr:housenumber":"6815",
    "addr:postcode":"87120",
    "addr:street":"Marigot Rd Nw",
    "iso:country":"US",
    "sg:address":"6815 Marigot Rd NW",
    "sg:city":"Albuquerque",
    "sg:classifiers":[
        {
            "category":"Retail",
            "subcategory":"Portrait Studio",
            "type":"Services"
        }
    ],
    "sg:phone":"+1 505 352 1752",
    "sg:postcode":"87120",
    "sg:province":"NM",
    "sg:tags":[
        "photo"
    ],
    "wof:name":"Goodmans Fine Art Photography",
    "wof:placetype":"venue"
},
  "geometry": {"coordinates":[-106.71465000000001,35.106826],"type":"Point"}
}