{
  "type": "Feature",
  "properties": {
    "iso:country":"US",
    "sg:address":"6815 Marigot Rd NW",
    "sg:city":"Albuquerque",
    "sg:classifiers":[
        {
            "category":"Retail",
            "subcategory":"Portrait Studio",
            "type":"Services"
        }
    ],
    "sg:phone":"+1 505 352 1752",
    "sg:postcode":"87120",
    "sg:province":"NM",
    "sg:tags":[
        "photo"
    ],
    "wof:name":"Goodmans Fine Art Photography",
    "wof:placetype":"venue"
},
  "geometry": {"coordinates":[-106.71465,35.106826],"type":"Point"}
}