{
  "type": "Feature",
  "properties": {
    "iso:country":"US",
    "sg:address":"140 Mesa Vista St",
    "sg:city":"Santa Fe",
    "sg:classifiers":[
        {
            "category":"Social Services",
            "type":"Services"
        }
    ],
    "sg:phone":"+1 505 820 2433",
    "sg:postcode":"87501",
    "sg:province":"NM",
    "sg:tags":[
        "counselor",
        "marriage",
        "family"
    ],
    "wof:name":"Listening Sage Assoc",
    "wof:placetype":"venue"
},
  "geometry": {"coordinates":[-105.966394,35.686147],"type":"Point"}
}