{
  "type": "Feature",
  "properties": {
    "iso:country":"US",
    "sg:address":"3201 4th St NW",
    "sg:city":"Albuquerque",
    "sg:classifiers":[
        {
            "category":"Shopping",
            "subcategory":"Computers & Home Electronics",
            "type":"Retail Goods"
        }
    ],
    "sg:phone":"+1 505 344 3233",
    "sg:postcode":"87107",
    "sg:province":"NM",
    "sg:tags":[
        "programing",
        "custom"
    ],
    "wof:name":"Jeskell Incorporated",
    "wof:placetype":"venue"
},
  "geometry": {"coordinates":[-106.64560400000001,35.11599],"type":"Point"}
}