{
  "type": "Feature",
  "properties": {
    "iso:country":"US",
    "sg:address":"724 W Animas St",
    "sg:city":"Farmington",
    "sg:classifiers":[
        {
            "category":"Government",
            "subcategory":"Office",
            "type":"Public Place"
        }
    ],
    "sg:phone":"+1 505 325 2458",
    "sg:postcode":"87401",
    "sg:province":"NM",
    "wof:name":"Underground Storage Tank Bur",
    "wof:placetype":"venue"
},
  "geometry": {"coordinates":[-108.215259,36.727168],"type":"Point"}
}