{
  "type": "Feature",
  "properties": {
    "addr:full":"335 Los Ranchos Rd NW Albuquerque NM 87107",
    "addr:housenumber":"335",
    "addr:postcode":"87107",
    "addr:street":"Los Ranchos Rd Nw",
    "iso:country":"US",
    "sg:address":"335 Los Ranchos Rd NW",
    "sg:city":"Albuquerque",
    "sg:classifiers":[
        {
            "category":"Building & Trades",
            "subcategory":"Landscaping Services",
            "type":"Services"
        }
    ],
    "sg:phone":"+1 505 345 9099",
    "sg:postcode":"87107",
    "sg:province":"NM",
    "sg:tags":[
        "heavy",
        "equipment",
        "electrical",
        "co"
    ],
    "sg:website":"www.steveshelly.com",
    "wof:name":"Steve Shelly Landscapes",
    "wof:placetype":"venue"
},
  "geometry": {"coordinates":[-106.63479100000001,35.170409],"type":"Point"}
}