{
  "type": "Feature",
  "properties": {
    "addr:full":"400 Gold Ave SW Albuquerque NM 87102",
    "addr:housenumber":"400",
    "addr:postcode":"87102",
    "addr:street":"Gold Ave Sw",
    "iso:country":"US",
    "sg:address":"400 Gold Ave SW",
    "sg:city":"Albuquerque",
    "sg:classifiers":[
        {
            "category":"Professional",
            "subcategory":"Computer Services",
            "type":"Services"
        }
    ],
    "sg:phone":"+1 505 241 3900",
    "sg:postcode":"87102",
    "sg:province":"NM",
    "sg:tags":[
        "custom",
        "datum",
        "programing",
        "internet"
    ],
    "sg:website":"www.inter800.com",
    "wof:name":"Internet 800 Directory",
    "wof:placetype":"venue"
},
  "geometry": {"coordinates":[-106.652993,35.083701],"type":"Point"}
}