{
  "type": "Feature",
  "properties": {
    "iso:country":"US",
    "sg:address":"3601 2nd St SW",
    "sg:city":"Albuquerque",
    "sg:classifiers":[
        {
            "category":"Building & Trades",
            "subcategory":"Electrical",
            "type":"Services"
        }
    ],
    "sg:phone":"+1 505 877 8500",
    "sg:postcode":"87105",
    "sg:province":"NM",
    "sg:tags":[
        "electric",
        "contractor"
    ],
    "sg:website":"www.drbelectric.com",
    "wof:name":"Drb Electric Inc",
    "wof:placetype":"venue"
},
  "geometry": {"coordinates":[-106.658202,35.027161],"type":"Point"}
}