{
  "type": "Feature",
  "properties": {
    "iso:country":"US",
    "sg:address":"1925 Aspen Dr",
    "sg:city":"Santa Fe",
    "sg:classifiers":[
        {
            "category":"Insurance",
            "subcategory":"Insurance Agent",
            "type":"Services"
        }
    ],
    "sg:phone":"+1 505 983 1077",
    "sg:postcode":"87505",
    "sg:province":"NM",
    "wof:name":"Franklin Life Insurance",
    "wof:placetype":"venue"
},
  "geometry": {"coordinates":[-105.970689,35.655309],"type":"Point"}
}