{
  "type": "Feature",
  "properties": {
    "iso:country":"US",
    "sg:address":"1202 Mechem Dr",
    "sg:city":"Ruidoso",
    "sg:classifiers":[
        {
            "category":"Sports & Exercise",
            "subcategory":"Bowling",
            "type":"Entertainment"
        }
    ],
    "sg:phone":"+1 505 258 3557",
    "sg:postcode":"88345",
    "sg:province":"NM",
    "sg:tags":[
        "drinking",
        "center"
    ],
    "wof:name":"Ruidoso Bowling Center",
    "wof:placetype":"venue"
},
  "geometry": {"coordinates":[-105.668186,33.369181],"type":"Point"}
}