{
  "type": "Feature",
  "properties": {
    "addr:full":"814 Ash Loop Espanola NM 87532",
    "addr:housenumber":"814",
    "addr:postcode":"87532",
    "addr:street":"Ash Loop",
    "iso:country":"US",
    "sg:address":"814 Ash Loop",
    "sg:city":"Espanola",
    "sg:classifiers":[
        {
            "category":"Professional",
            "subcategory":"Accounting & Tax Preparation",
            "type":"Services"
        }
    ],
    "sg:phone":"+1 505 753 3811",
    "sg:postcode":"87532",
    "sg:province":"NM",
    "sg:tags":[
        "return"
    ],
    "wof:name":"Loren Pacheo Tax Service",
    "wof:placetype":"venue"
},
  "geometry": {"coordinates":[-106.058138,36.002234],"type":"Point"}
}