{
  "type": "Feature",
  "properties": {
    "iso:country":"US",
    "sg:address":"201 Oak Grove Pl",
    "sg:city":"Ruidoso",
    "sg:classifiers":[
        {
            "category":"Manufacturing",
            "subcategory":"Printing",
            "type":"Manufacturing & Wholesale Goods"
        }
    ],
    "sg:phone":"+1 505 257 6171",
    "sg:postcode":"88345",
    "sg:province":"NM",
    "sg:tags":[
        "graphic",
        "agency"
    ],
    "wof:name":"Grindstone Graphics Mktg Svcs",
    "wof:placetype":"venue"
},
  "geometry": {"coordinates":[-105.68385499999999,33.328396],"type":"Point"}
}