{
  "type": "Feature",
  "properties": {
    "iso:country":"US",
    "sg:address":"500 W National St",
    "sg:city":"Las Vegas",
    "sg:classifiers":[
        {
            "category":"Government",
            "subcategory":"Office",
            "type":"Public Place"
        }
    ],
    "sg:phone":"+1 505 425 9376",
    "sg:postcode":"87701",
    "sg:province":"NM",
    "sg:tags":[
        "county",
        "taxation"
    ],
    "wof:name":"San Miguel County Treasurers",
    "wof:placetype":"venue"
},
  "geometry": {"coordinates":[-105.22931,35.59155],"type":"Point"}
}