{
  "type": "Feature",
  "properties": {
    "iso:country":"US",
    "sg:address":"300 E Broadway St",
    "sg:city":"Tatum",
    "sg:classifiers":[
        {
            "category":"Government",
            "subcategory":"Police Station",
            "type":"Public Place"
        }
    ],
    "sg:phone":"+1 505 398 4444",
    "sg:postcode":"88267",
    "sg:province":"NM",
    "sg:tags":[
        "department"
    ],
    "wof:name":"Tatum City Police Dept",
    "wof:placetype":"venue"
},
  "geometry": {"coordinates":[-103.31393,33.256972],"type":"Point"}
}