{
  "type": "Feature",
  "properties": {
    "iso:country":"US",
    "sg:address":"217 E McGaffey St",
    "sg:city":"Roswell",
    "sg:classifiers":[
        {
            "category":"Building & Trades",
            "subcategory":"Plumbing",
            "type":"Services"
        }
    ],
    "sg:phone":"+1 505 623 2011",
    "sg:postcode":"88203",
    "sg:province":"NM",
    "sg:tags":[
        "plumbing",
        "contractor"
    ],
    "sg:website":"www.creading.com",
    "wof:name":"C Reading Inc",
    "wof:placetype":"venue"
},
  "geometry": {"coordinates":[-104.518827,33.379881],"type":"Point"}
}