{
  "type": "Feature",
  "properties": {
    "iso:country":"US",
    "sg:address":"2201 N Main St",
    "sg:city":"Las Cruces",
    "sg:classifiers":[
        {
            "category":"Shopping",
            "subcategory":"Florist",
            "type":"Retail Goods"
        }
    ],
    "sg:phone":"+1 505 524 7358",
    "sg:postcode":"88001",
    "sg:province":"NM",
    "wof:name":"Your Florist",
    "wof:placetype":"venue"
},
  "geometry": {"coordinates":[-106.78316,32.33104],"type":"Point"}
}