{
  "type": "Feature",
  "properties": {
    "addr:full":"2713 Girard Blvd NE Albuquerque NM 87107",
    "addr:housenumber":"2713",
    "addr:postcode":"87107",
    "addr:street":"Girard Blvd Ne",
    "iso:country":"US",
    "sg:address":"2713 Girard Blvd NE",
    "sg:city":"Albuquerque",
    "sg:classifiers":[
        {
            "category":"Manufacturing",
            "subcategory":"Retail Goods",
            "type":"Manufacturing & Wholesale Goods"
        }
    ],
    "sg:phone":"+1 505 888 8830",
    "sg:postcode":"87107",
    "sg:province":"NM",
    "sg:tags":[
        "marking",
        "devices",
        "mfg"
    ],
    "wof:name":"Rubber Stamps Tomorrow",
    "wof:placetype":"venue"
},
  "geometry": {"coordinates":[-106.613868,35.113085],"type":"Point"}
}