{
  "type": "Feature",
  "properties": {
    "addr:full":"620 S 11th St Belen NM 87002",
    "addr:housenumber":"620",
    "addr:postcode":"87002",
    "addr:street":"S 11Th St",
    "iso:country":"US",
    "sg:address":"620 S 11th St",
    "sg:city":"Belen",
    "sg:classifiers":[
        {
            "category":"Professional",
            "subcategory":"Business Services",
            "type":"Services"
        }
    ],
    "sg:phone":"+1 505 861 2918",
    "sg:postcode":"87002",
    "sg:province":"NM",
    "wof:name":"Information Research Services",
    "wof:placetype":"venue"
},
  "geometry": {"coordinates":[-106.782752,34.655091],"type":"Point"}
}