{
  "type": "Feature",
  "properties": {
    "iso:country":"US",
    "sg:address":"4220 Broadway Blvd SE",
    "sg:city":"Albuquerque",
    "sg:classifiers":[
        {
            "category":"Wholesale",
            "subcategory":"Auto Parts",
            "type":"Manufacturing & Wholesale Goods"
        }
    ],
    "sg:phone":"+1 505 877 5929",
    "sg:postcode":"87105",
    "sg:province":"NM",
    "sg:tags":[
        "body",
        "used"
    ],
    "wof:name":"Olguins Body Shop",
    "wof:placetype":"venue"
},
  "geometry": {"coordinates":[-106.647368,35.017841],"type":"Point"}
}