{
  "type": "Feature",
  "properties": {
    "iso:country":"US",
    "sg:address":"500 Douglas Ave",
    "sg:city":"Las Vegas",
    "sg:classifiers":[
        {
            "category":"Personal",
            "type":"Services"
        }
    ],
    "sg:phone":"+1 505 454 0008",
    "sg:postcode":"87701",
    "sg:province":"NM",
    "sg:tags":[
        "therapist",
        "massage"
    ],
    "wof:name":"Haiya's Massage Therapy",
    "wof:placetype":"venue"
},
  "geometry": {"coordinates":[-105.21422,35.595189],"type":"Point"}
}