{
  "type": "Feature",
  "properties": {
    "addr:full":"1101 Brilliant St Raton NM 87740",
    "addr:housenumber":"1101",
    "addr:postcode":"87740",
    "addr:street":"Brilliant St",
    "iso:country":"US",
    "sg:address":"1101 Brilliant St",
    "sg:city":"Raton",
    "sg:classifiers":[
        {
            "category":"Organizations",
            "subcategory":"Religious Organization",
            "type":"Services"
        }
    ],
    "sg:phone":"+1 505 445 2695",
    "sg:postcode":"87740",
    "sg:province":"NM",
    "sg:tags":[
        "church"
    ],
    "wof:name":"Raton Church Of Christ",
    "wof:placetype":"venue"
},
  "geometry": {"coordinates":[-104.44490999999999,36.884948],"type":"Point"}
}