{
  "type": "Feature",
  "properties": {
    "iso:country":"US",
    "sg:address":"6220 San Mateo Blvd NE",
    "sg:city":"Albuquerque",
    "sg:phone":"+1 505 294 0602",
    "sg:postcode":"87109",
    "sg:province":"NM",
    "wof:name":"Salon Chrishawn",
    "wof:placetype":"venue"
},
  "geometry": {"coordinates":[-106.586344,35.147162],"type":"Point"}
}