{
  "type": "Feature",
  "properties": {
    "addr:full":"1101 N Norris St Clovis NM 88101",
    "addr:housenumber":"1101",
    "addr:postcode":"88101",
    "addr:street":"N Norris St",
    "iso:country":"US",
    "sg:address":"1101 N Norris St",
    "sg:city":"Clovis",
    "sg:classifiers":[
        {
            "category":"Professional",
            "subcategory":"Accounting & Tax Preparation",
            "type":"Services"
        }
    ],
    "sg:phone":"+1 505 769 3778",
    "sg:postcode":"88101",
    "sg:province":"NM",
    "wof:name":"Pate Janet M Rpa",
    "wof:placetype":"venue"
},
  "geometry": {"coordinates":[-103.178833,34.410171],"type":"Point"}
}