{
  "type": "Feature",
  "properties": {
    "iso:country":"US",
    "sg:address":"225 San Pedro Dr NE",
    "sg:city":"Albuquerque",
    "sg:classifiers":[
        {
            "category":"Building & Trades",
            "subcategory":"Construction",
            "type":"Services"
        }
    ],
    "sg:phone":"+1 505 262 9838",
    "sg:postcode":"87108",
    "sg:province":"NM",
    "sg:tags":[
        "company"
    ],
    "wof:name":"Blackmon Construction",
    "wof:placetype":"venue"
},
  "geometry": {"coordinates":[-106.577529,35.07891],"type":"Point"}
}