{
  "type": "Feature",
  "properties": {
    "iso:country":"US",
    "sg:address":"2105 Aztec Rd NE",
    "sg:city":"Albuquerque",
    "sg:classifiers":[
        {
            "category":"Professional",
            "subcategory":"Computer Services",
            "type":"Services"
        }
    ],
    "sg:phone":"+1 505 232 0176",
    "sg:postcode":"87107",
    "sg:province":"NM",
    "sg:tags":[
        "hardware",
        "software",
        "integration",
        "system"
    ],
    "wof:name":"Cimarron Computer Engineering",
    "wof:placetype":"venue"
},
  "geometry": {"coordinates":[-106.617373,35.120244],"type":"Point"}
}