{
  "type": "Feature",
  "properties": {
    "iso:country":"US",
    "sg:address":"1616 N Main St",
    "sg:city":"Clovis",
    "sg:classifiers":[
        {
            "category":"Shopping",
            "type":"Retail Goods"
        }
    ],
    "sg:phone":"+1 505 769 7770",
    "sg:postcode":"88101",
    "sg:province":"NM",
    "sg:tags":[
        "direct",
        "merchandise",
        "sales"
    ],
    "wof:name":"Southwest Water Treatment",
    "wof:placetype":"venue"
},
  "geometry": {"coordinates":[-103.205462,34.413837],"type":"Point"}
}