{
  "type": "Feature",
  "properties": {
    "iso:country":"US",
    "sg:address":"13913 Indian School Rd NE",
    "sg:city":"Albuquerque",
    "sg:classifiers":[
        {
            "category":"Health Services",
            "subcategory":"Doctor",
            "type":"Services"
        }
    ],
    "sg:phone":"+1 505 299 6894",
    "sg:postcode":"87112",
    "sg:province":"NM",
    "sg:tags":[
        "medical"
    ],
    "wof:name":"Roger P Hirst MD PC",
    "wof:placetype":"venue"
},
  "geometry": {"coordinates":[-106.481761,35.098848],"type":"Point"}
}