{
  "type": "Feature",
  "properties": {
    "iso:country":"US",
    "sg:address":"4217 San Mateo Blvd NE",
    "sg:city":"Albuquerque",
    "sg:classifiers":[
        {
            "category":"Wholesale",
            "subcategory":"Jewelry",
            "type":"Manufacturing & Wholesale Goods"
        }
    ],
    "sg:phone":"+1 505 884 8911",
    "sg:postcode":"87110",
    "sg:province":"NM",
    "sg:tags":[
        "turquoise"
    ],
    "wof:name":"China Mountain Turquoise",
    "wof:placetype":"venue"
},
  "geometry": {"coordinates":[-106.58654799999999,35.12835],"type":"Point"}
}