{
  "type": "Feature",
  "properties": {
    "addr:full":"201 Dale Scott Ave Alamogordo NM 88310",
    "addr:housenumber":"201",
    "addr:postcode":"88310",
    "addr:street":"Dale Scott Ave",
    "iso:country":"US",
    "sg:address":"201 Dale Scott Ave",
    "sg:city":"Alamogordo",
    "sg:classifiers":[
        {
            "category":"Education",
            "subcategory":"Dance Studio",
            "type":"Public Place"
        }
    ],
    "sg:phone":"+1 505 434 3223",
    "sg:postcode":"88310",
    "sg:province":"NM",
    "sg:tags":[
        "instruction",
        "dancing"
    ],
    "wof:name":"Showtime Studio",
    "wof:placetype":"venue"
},
  "geometry": {"coordinates":[-105.94055299999999,32.891111],"type":"Point"}
}