{
  "type": "Feature",
  "properties": {
    "iso:country":"US",
    "sg:address":"1916 Central Ave SE",
    "sg:city":"Albuquerque",
    "sg:classifiers":[
        {
            "category":"Restaurant",
            "type":"Food & Drink"
        }
    ],
    "sg:phone":"+1 505 842 0030",
    "sg:postcode":"87106",
    "sg:province":"NM",
    "sg:tags":[
        "eating"
    ],
    "wof:name":"Burger King",
    "wof:placetype":"venue"
},
  "geometry": {"coordinates":[-106.624548,35.081064],"type":"Point"}
}