{
  "type": "Feature",
  "properties": {
    "iso:country":"US",
    "sg:address":"6821 Montgomery Blvd NE",
    "sg:city":"Albuquerque",
    "sg:classifiers":[
        {
            "category":"Restaurant",
            "type":"Food & Drink"
        }
    ],
    "sg:phone":"+1 505 256 5141",
    "sg:postcode":"87109",
    "sg:province":"NM",
    "wof:name":"Net Ministries",
    "wof:placetype":"venue"
},
  "geometry": {"coordinates":[-106.57100800000001,35.130854],"type":"Point"}
}