{
  "type": "Feature",
  "properties": {
    "addr:full":"4308 Tulane Dr NE Albuquerque NM 87107",
    "addr:housenumber":"4308",
    "addr:postcode":"87107",
    "addr:street":"Tulane Dr Ne",
    "iso:country":"US",
    "sg:address":"4308 Tulane Dr NE",
    "sg:city":"Albuquerque",
    "sg:classifiers":[
        {
            "category":"Social Services",
            "subcategory":"Adult Care",
            "type":"Services"
        }
    ],
    "sg:phone":"+1 505 884 1341",
    "sg:postcode":"87107",
    "sg:province":"NM",
    "sg:tags":[
        "home",
        "residential"
    ],
    "wof:name":"Tender Heart Assisted Living",
    "wof:placetype":"venue"
},
  "geometry": {"coordinates":[-106.606753,35.129944],"type":"Point"}
}