{
  "type": "Feature",
  "properties": {
    "iso:country":"US",
    "sg:address":"831 Echo Ln",
    "sg:city":"Farmington",
    "sg:classifiers":[
        {
            "category":"Personal",
            "type":"Services"
        }
    ],
    "sg:phone":"+1 505 327 2015",
    "sg:postcode":"87401",
    "sg:province":"NM",
    "sg:tags":[
        "welcoming",
        "newcomer",
        "for"
    ],
    "wof:name":"Farmington Welcome Svc",
    "wof:placetype":"venue"
},
  "geometry": {"coordinates":[-108.217878,36.745414],"type":"Point"}
}