{
  "type": "Feature",
  "properties": {
    "iso:country":"US",
    "sg:address":"111 Smokey Bear Blvd",
    "sg:city":"Capitan",
    "sg:classifiers":[
        {
            "category":"Shopping",
            "subcategory":"Gifts & Souvenirs",
            "type":"Retail Goods"
        }
    ],
    "sg:phone":"+1 505 354 4251",
    "sg:postcode":"88316",
    "sg:province":"NM",
    "sg:tags":[
        "shop"
    ],
    "wof:name":"Smokey's Hometown Shop",
    "wof:placetype":"venue"
},
  "geometry": {"coordinates":[-105.57204900000001,33.545503],"type":"Point"}
}