{
  "type": "Feature",
  "properties": {
    "iso:country":"US",
    "sg:address":"1302 Barelas Rd SW",
    "sg:city":"Albuquerque",
    "sg:classifiers":[
        {
            "category":"Building & Trades",
            "subcategory":"Electrical",
            "type":"Services"
        }
    ],
    "sg:phone":"+1 505 247 1289",
    "sg:postcode":"87102",
    "sg:province":"NM",
    "sg:tags":[
        "industrial",
        "electrician",
        "electric",
        "contractors-commercial"
    ],
    "wof:name":"Professional Constructive Services",
    "wof:placetype":"venue"
},
  "geometry": {"coordinates":[-106.655114,35.073054],"type":"Point"}
}