{
  "type": "Feature",
  "properties": {
    "iso:country":"US",
    "sg:address":"76 E San Francisco St",
    "sg:city":"Santa Fe",
    "sg:classifiers":[
        {
            "category":"Shopping",
            "type":"Retail Goods"
        }
    ],
    "sg:phone":"+1 505 982 6244",
    "sg:postcode":"87501",
    "sg:province":"NM",
    "sg:tags":[
        "fine",
        "art"
    ],
    "wof:name":"Owings Dewey Fine Art",
    "wof:placetype":"venue"
},
  "geometry": {"coordinates":[-105.938742,35.687104],"type":"Point"}
}