{
  "type": "Feature",
  "properties": {
    "iso:country":"US",
    "sg:address":"112 US Hwy 54",
    "sg:city":"Logan",
    "sg:classifiers":[
        {
            "category":"Retail",
            "subcategory":"Auto Repair",
            "type":"Services"
        }
    ],
    "sg:phone":"+1 505 487 2963",
    "sg:postcode":"88426",
    "sg:province":"NM",
    "sg:tags":[
        "repairing",
        "automobile"
    ],
    "wof:name":"Logan Auto Clinic & Towing",
    "wof:placetype":"venue"
},
  "geometry": {"coordinates":[-103.10325400000001,35.605571],"type":"Point"}
}