{
  "type": "Feature",
  "properties": {
    "iso:country":"US",
    "sg:address":"621 Ortiz Dr NE",
    "sg:city":"Albuquerque",
    "sg:classifiers":[
        {
            "category":"Personal",
            "subcategory":"Beauty Salon",
            "type":"Services"
        }
    ],
    "sg:phone":"+1 505 730 6080",
    "sg:postcode":"87108",
    "sg:province":"NM",
    "sg:tags":[
        "manicuring"
    ],
    "wof:name":"Studio 621",
    "wof:placetype":"venue"
},
  "geometry": {"coordinates":[-106.58535999999999,35.083477],"type":"Point"}
}