{
  "type": "Feature",
  "properties": {
    "addr:full":"321 W Historic Hwy 66 Church Rock NM 87301",
    "addr:housenumber":"321",
    "addr:postcode":"87301",
    "addr:street":"W Historic Hwy 66",
    "iso:country":"US",
    "sg:address":"321 W Historic Hwy 66",
    "sg:city":"Church Rock",
    "sg:classifiers":[
        {
            "category":"Manufacturing",
            "subcategory":"Building Materials",
            "type":"Manufacturing & Wholesale Goods"
        }
    ],
    "sg:phone":"+1 505 726 0826",
    "sg:postcode":"87301",
    "sg:province":"NM",
    "sg:tags":[
        "cabinet"
    ],
    "wof:name":"Cabinets Southwest Inc",
    "wof:placetype":"venue"
},
  "geometry": {"coordinates":[-108.744466,35.527471],"type":"Point"}
}