{
  "type": "Feature",
  "properties": {
    "addr:full":"2200 Candelaria Rd NE Albuquerque NM 87107",
    "addr:housenumber":"2200",
    "addr:postcode":"87107",
    "addr:street":"Candelaria Rd Ne",
    "iso:country":"US",
    "sg:address":"2200 Candelaria Rd NE",
    "sg:city":"Albuquerque",
    "sg:classifiers":[
        {
            "category":"Freight",
            "type":"Transportation"
        }
    ],
    "sg:phone":"+1 505 884 4844",
    "sg:postcode":"87107",
    "sg:province":"NM",
    "sg:tags":[
        "commercial",
        "storage"
    ],
    "wof:name":"AAA U-Lock-It Self Storage",
    "wof:placetype":"venue"
},
  "geometry": {"coordinates":[-106.618217,35.11507],"type":"Point"}
}