{
  "type": "Feature",
  "properties": {
    "iso:country":"US",
    "sg:address":"3144 el Camino Real",
    "sg:city":"Las Cruces",
    "sg:classifiers":[
        {
            "category":"Professional",
            "subcategory":"Computer Services",
            "type":"Services"
        }
    ],
    "sg:phone":"+1 505 644 6913",
    "sg:postcode":"88007",
    "sg:province":"NM",
    "sg:tags":[
        "repair"
    ],
    "wof:name":"A-1 Computer Svc",
    "wof:placetype":"venue"
},
  "geometry": {"coordinates":[-106.792522,32.339729],"type":"Point"}
}