{
  "type": "Feature",
  "properties": {
    "iso:country":"US",
    "sg:address":"1016 W Pierce St",
    "sg:city":"Carlsbad",
    "sg:classifiers":[
        {
            "category":"Professional",
            "type":"Services"
        }
    ],
    "sg:phone":"+1 505 887 6966",
    "sg:postcode":"88220",
    "sg:province":"NM",
    "sg:tags":[
        "establishment"
    ],
    "wof:name":"Stroud & Assoc Evenings Call",
    "wof:placetype":"venue"
},
  "geometry": {"coordinates":[-104.23873500000001,32.435825],"type":"Point"}
}