{
  "type": "Feature",
  "properties": {
    "addr:full":"3435 US Hwy 64 Waterflow NM 87421",
    "addr:housenumber":"3435",
    "addr:postcode":"87421",
    "addr:street":"Us Hwy 64",
    "iso:country":"US",
    "sg:address":"3435 US Hwy 64",
    "sg:city":"Waterflow",
    "sg:classifiers":[
        {
            "category":"Wholesale",
            "subcategory":"Farm Supplies",
            "type":"Manufacturing & Wholesale Goods"
        }
    ],
    "sg:phone":"+1 505 598 5133",
    "sg:postcode":"87421",
    "sg:province":"NM",
    "sg:tags":[
        "feed"
    ],
    "wof:name":"Valley Trading Co",
    "wof:placetype":"venue"
},
  "geometry": {"coordinates":[-108.49195400000001,36.760214],"type":"Point"}
}