{
  "type": "Feature",
  "properties": {
    "iso:country":"US",
    "sg:address":"2029 San Juan Blvd",
    "sg:city":"Farmington",
    "sg:classifiers":[
        {
            "category":"Home & Garden",
            "subcategory":"Hardware",
            "type":"Retail Goods"
        }
    ],
    "sg:phone":"+1 505 327 4773",
    "sg:postcode":"87401",
    "sg:province":"NM",
    "sg:tags":[
        "tool",
        "used"
    ],
    "wof:name":"Southwest Power Tools",
    "wof:placetype":"venue"
},
  "geometry": {"coordinates":[-108.180864,36.736107],"type":"Point"}
}