{
  "type": "Feature",
  "properties": {
    "addr:full":"2508 Utah St NE Albuquerque NM 87110",
    "addr:housenumber":"2508",
    "addr:postcode":"87110",
    "addr:street":"Utah St Ne",
    "iso:country":"US",
    "sg:address":"2508 Utah St NE",
    "sg:city":"Albuquerque",
    "sg:classifiers":[
        {
            "category":"Autos & Motor Vehicles",
            "subcategory":"Automobile Sales",
            "type":"Retail Goods"
        }
    ],
    "sg:phone":"+1 505 296 8709",
    "sg:postcode":"87110",
    "sg:province":"NM",
    "sg:tags":[
        "car",
        "dealer"
    ],
    "wof:name":"Hometown Auto Recon",
    "wof:placetype":"venue"
},
  "geometry": {"coordinates":[-106.555353,35.110881],"type":"Point"}
}