{
  "type": "Feature",
  "properties": {
    "iso:country":"US",
    "sg:address":"715 Alta Vista St",
    "sg:city":"Santa Fe",
    "sg:classifiers":[
        {
            "category":"Government",
            "subcategory":"Office",
            "type":"Public Place"
        }
    ],
    "sg:phone":"+1 505 476 2150",
    "sg:postcode":"87505",
    "sg:province":"NM",
    "sg:tags":[
        "state"
    ],
    "wof:name":"New Mexico State Government",
    "wof:placetype":"venue"
},
  "geometry": {"coordinates":[-105.955158,35.671057],"type":"Point"}
}