{
  "type": "Feature",
  "properties": {
    "addr:full":"10200 Acoma Rd SE Albuquerque NM 87123",
    "addr:housenumber":"10200",
    "addr:postcode":"87123",
    "addr:street":"Acoma Rd Se",
    "iso:country":"US",
    "sg:address":"10200 Acoma Rd SE",
    "sg:city":"Albuquerque",
    "sg:classifiers":[
        {
            "category":"Shopping",
            "subcategory":"Tobacco",
            "type":"Retail Goods"
        }
    ],
    "sg:phone":"+1 505 292 3926",
    "sg:postcode":"87123",
    "sg:province":"NM",
    "sg:tags":[
        "cigarette",
        "product",
        "cigar",
        "dealer"
    ],
    "wof:name":"Cigarette Outlet Eubank",
    "wof:placetype":"venue"
},
  "geometry": {"coordinates":[-106.533309,35.069954],"type":"Point"}
}