{
  "type": "Feature",
  "properties": {
    "addr:full":"101 Clover Dr Ruidoso NM 88345",
    "addr:housenumber":"101",
    "addr:postcode":"88345",
    "addr:street":"Clover Dr",
    "iso:country":"US",
    "sg:address":"101 Clover Dr",
    "sg:city":"Ruidoso",
    "sg:classifiers":[
        {
            "category":"Arts & Performance",
            "subcategory":"Theater",
            "type":"Entertainment"
        }
    ],
    "sg:phone":"+1 505 257 4846",
    "sg:postcode":"88345",
    "sg:province":"NM",
    "sg:tags":[
        "group"
    ],
    "wof:name":"Ruidoso Party Rental",
    "wof:placetype":"venue"
},
  "geometry": {"coordinates":[-105.676922,33.330016],"type":"Point"}
}