{
  "type": "Feature",
  "properties": {
    "iso:country":"US",
    "sg:address":"527 N Tornillo St",
    "sg:city":"Las Cruces",
    "sg:classifiers":[
        {
            "category":"Professional",
            "subcategory":"Art Services",
            "type":"Services"
        }
    ],
    "sg:phone":"+1 505 526 9264",
    "sg:postcode":"88001",
    "sg:province":"NM",
    "sg:tags":[
        "photography",
        "commercial"
    ],
    "wof:name":"Magic Photo",
    "wof:placetype":"venue"
},
  "geometry": {"coordinates":[-106.774459,32.314401],"type":"Point"}
}