{
  "type": "Feature",
  "properties": {
    "addr:full":"23 Pia Mesa Rd Zuni NM 87327",
    "addr:housenumber":"23",
    "addr:postcode":"87327",
    "addr:street":"Pia Mesa Rd",
    "iso:country":"US",
    "sg:address":"23 Pia Mesa Rd",
    "sg:city":"Zuni",
    "sg:classifiers":[
        {
            "category":"Travel",
            "subcategory":"Hotels & Motels",
            "type":"Entertainment"
        }
    ],
    "sg:phone":"+1 505 782 4547",
    "sg:postcode":"87327",
    "sg:province":"NM",
    "sg:tags":[
        "breakfast",
        "accommodation",
        "bed"
    ],
    "wof:name":"Inn At Halona",
    "wof:placetype":"venue"
},
  "geometry": {"coordinates":[-108.85124399999999,35.065576],"type":"Point"}
}