{
  "type": "Feature",
  "properties": {
    "iso:country":"US",
    "sg:address":"10613 Clyburn Park Dr NE",
    "sg:city":"Albuquerque",
    "sg:classifiers":[
        {
            "category":"Manufacturing",
            "subcategory":"Electronics",
            "type":"Manufacturing & Wholesale Goods"
        }
    ],
    "sg:phone":"+1 505 681 7600",
    "sg:postcode":"87123",
    "sg:province":"NM",
    "sg:tags":[
        "duplication",
        "tape"
    ],
    "wof:name":"Master Sound Audio",
    "wof:placetype":"venue"
},
  "geometry": {"coordinates":[-106.52646900000001,35.076047],"type":"Point"}
}