{
  "type": "Feature",
  "properties": {
    "addr:full":"1330 el Paseo Rd Las Cruces NM 88001",
    "addr:housenumber":"1330",
    "addr:postcode":"88001",
    "addr:street":"El Paseo Rd",
    "iso:country":"US",
    "sg:address":"1330 el Paseo Rd",
    "sg:city":"Las Cruces",
    "sg:classifiers":[
        {
            "category":"Retail",
            "subcategory":"Auto Repair",
            "type":"Services"
        }
    ],
    "sg:phone":"+1 505 524 3548",
    "sg:postcode":"88001",
    "sg:province":"NM",
    "sg:tags":[
        "general",
        "supply"
    ],
    "wof:name":"Big O Tires",
    "wof:placetype":"venue"
},
  "geometry": {"coordinates":[-106.77139200000001,32.297171],"type":"Point"}
}