{
  "type": "Feature",
  "properties": {
    "iso:country":"US",
    "sg:address":"1591 E Lohman Ave",
    "sg:city":"Las Cruces",
    "sg:classifiers":[
        {
            "category":"Insurance",
            "subcategory":"Insurance Agent",
            "type":"Services"
        }
    ],
    "sg:phone":"+1 505 525 1177",
    "sg:postcode":"88001",
    "sg:province":"NM",
    "wof:name":"Allstate Insurance Co",
    "wof:placetype":"venue"
},
  "geometry": {"coordinates":[-106.762128,32.309443],"type":"Point"}
}