{
  "type": "Feature",
  "properties": {
    "iso:country":"US",
    "sg:address":"700 S Hull St",
    "sg:city":"Clovis",
    "sg:classifiers":[
        {
            "category":"Freight",
            "type":"Transportation"
        }
    ],
    "sg:phone":"+1 505 762 4343",
    "sg:postcode":"88101",
    "sg:province":"NM",
    "sg:tags":[
        "packing",
        "crating"
    ],
    "wof:name":"H & B Packing",
    "wof:placetype":"venue"
},
  "geometry": {"coordinates":[-103.220512,34.39082],"type":"Point"}
}