{
  "type": "Feature",
  "properties": {
    "iso:country":"US",
    "sg:address":"3100 E Aztec Ave",
    "sg:city":"Gallup",
    "sg:classifiers":[
        {
            "category":"Building & Trades",
            "subcategory":"Electrical",
            "type":"Services"
        }
    ],
    "sg:phone":"+1 505 488 6542",
    "sg:postcode":"87301",
    "sg:province":"NM",
    "sg:tags":[
        "electrical",
        "electric",
        "contractor"
    ],
    "wof:name":"Spur Electric",
    "wof:placetype":"venue"
},
  "geometry": {"coordinates":[-108.693628,35.527706],"type":"Point"}
}