{
  "type": "Feature",
  "properties": {
    "iso:country":"US",
    "sg:address":"904 Colonial Pkwy",
    "sg:city":"Clovis",
    "sg:classifiers":[
        {
            "category":"Real Estate",
            "subcategory":"Real Estate Agent",
            "type":"Services"
        }
    ],
    "sg:phone":"+1 505 762 3388",
    "sg:postcode":"88101",
    "sg:province":"NM",
    "wof:name":"Bennett Land Co",
    "wof:placetype":"venue"
},
  "geometry": {"coordinates":[-103.196305,34.439335],"type":"Point"}
}