{
  "type": "Feature",
  "properties": {
    "iso:country":"US",
    "sg:address":"907 S Solano Dr",
    "sg:city":"Las Cruces",
    "sg:classifiers":[
        {
            "category":"Professional",
            "subcategory":"Business Services",
            "type":"Services"
        }
    ],
    "sg:phone":"+1 505 523 1631",
    "sg:postcode":"88001",
    "sg:province":"NM",
    "sg:tags":[
        "repossessing"
    ],
    "wof:name":"G & S Repo & Collection Svc",
    "wof:placetype":"venue"
},
  "geometry": {"coordinates":[-106.763294,32.303048],"type":"Point"}
}