{
  "type": "Feature",
  "properties": {
    "iso:country":"US",
    "sg:address":"4141 Barcelona Rd SW",
    "sg:city":"Albuquerque",
    "sg:classifiers":[
        {
            "category":"Building & Trades",
            "subcategory":"Construction",
            "type":"Services"
        }
    ],
    "sg:phone":"+1 505 304 7410",
    "sg:postcode":"87121",
    "sg:province":"NM",
    "sg:tags":[
        "layer",
        "carpet"
    ],
    "wof:name":"Hector Mendoza Zubiate Carpet",
    "wof:placetype":"venue"
},
  "geometry": {"coordinates":[-106.720894,35.030583],"type":"Point"}
}