{
  "type": "Feature",
  "properties": {
    "iso:country":"US",
    "sg:address":"11500 Menaul Blvd NE",
    "sg:city":"Albuquerque",
    "sg:classifiers":[
        {
            "category":"Insurance",
            "subcategory":"Insurance Agent",
            "type":"Services"
        }
    ],
    "sg:phone":"+1 505 292 0838",
    "sg:postcode":"87112",
    "sg:province":"NM",
    "wof:name":"Titan Auto Insurance",
    "wof:placetype":"venue"
},
  "geometry": {"coordinates":[-106.51205400000001,35.108743],"type":"Point"}
}