{
  "type": "Feature",
  "properties": {
    "iso:country":"US",
    "sg:address":"2601 Wyoming Blvd NE",
    "sg:city":"Albuquerque",
    "sg:classifiers":[
        {
            "category":"Professional",
            "subcategory":"Lawyer & Legal Services",
            "type":"Services"
        }
    ],
    "sg:phone":"+1 505 293 4911",
    "sg:postcode":"87112",
    "sg:province":"NM",
    "wof:name":"McIlwain Stephen Atty At Law",
    "wof:placetype":"venue"
},
  "geometry": {"coordinates":[-106.55094800000001,35.114202],"type":"Point"}
}