{
  "type": "Feature",
  "properties": {
    "addr:full":"5601 Wilshire Ave NE Albuquerque NM 87113",
    "addr:housenumber":"5601",
    "addr:postcode":"87113",
    "addr:street":"Wilshire Ave Ne",
    "iso:country":"US",
    "sg:address":"5601 Wilshire Ave NE",
    "sg:city":"Albuquerque",
    "sg:classifiers":[
        {
            "category":"Retail",
            "subcategory":"Auto Repair",
            "type":"Services"
        }
    ],
    "sg:phone":"+1 505 821 1666",
    "sg:postcode":"87113",
    "sg:province":"NM",
    "sg:tags":[
        "body",
        "automobile",
        "painting"
    ],
    "sg:website":"www.finchammobilestorage.com",
    "wof:name":"Fincham Enterprises Body Shop",
    "wof:placetype":"venue"
},
  "geometry": {"coordinates":[-106.583961,35.18168],"type":"Point"}
}