{
  "type": "Feature",
  "properties": {
    "addr:full":"223 Montano Rd NW Albuquerque NM 87107",
    "addr:housenumber":"223",
    "addr:postcode":"87107",
    "addr:street":"Montano Rd Nw",
    "iso:country":"US",
    "sg:address":"223 Montano Rd NW",
    "sg:city":"Albuquerque",
    "sg:classifiers":[
        {
            "category":"Personal",
            "subcategory":"Beauty Salon",
            "type":"Services"
        }
    ],
    "sg:phone":"+1 505 296 6000",
    "sg:postcode":"87107",
    "sg:province":"NM",
    "wof:name":"Estevan's",
    "wof:placetype":"venue"
},
  "geometry": {"coordinates":[-106.63691,35.138322],"type":"Point"}
}