{
  "type": "Feature",
  "properties": {
    "iso:country":"US",
    "sg:address":"11209 Hume Ave NE",
    "sg:city":"Albuquerque",
    "sg:classifiers":[
        {
            "category":"Shopping",
            "subcategory":"Clothing, Apparel, & Fashions",
            "type":"Retail Goods"
        }
    ],
    "sg:phone":"+1 505 307 0075",
    "sg:postcode":"87112",
    "sg:province":"NM",
    "sg:tags":[
        "alteration"
    ],
    "wof:name":"Custom Alterations Tailoring",
    "wof:placetype":"venue"
},
  "geometry": {"coordinates":[-106.52321999999999,35.099507],"type":"Point"}
}