{
  "type": "Feature",
  "properties": {
    "iso:country":"US",
    "sg:address":"1313 Wellesley Dr SE",
    "sg:city":"Albuquerque",
    "sg:classifiers":[
        {
            "category":"Professional",
            "type":"Services"
        }
    ],
    "sg:phone":"+1 505 256 7748",
    "sg:postcode":"87106",
    "sg:province":"NM",
    "sg:tags":[
        "establishment"
    ],
    "wof:name":"Albuquerque Mental Health Hsng",
    "wof:placetype":"venue"
},
  "geometry": {"coordinates":[-106.608748,35.064842],"type":"Point"}
}