{
  "type": "Feature",
  "properties": {
    "iso:country":"US",
    "sg:address":"980 N Main St",
    "sg:city":"Las Cruces",
    "sg:classifiers":[
        {
            "category":"Professional",
            "subcategory":"Lawyer & Legal Services",
            "type":"Services"
        }
    ],
    "sg:phone":"+1 505 527 2131",
    "sg:postcode":"88001",
    "sg:province":"NM",
    "wof:name":"John B Leyba Esq Attorney",
    "wof:placetype":"venue"
},
  "geometry": {"coordinates":[-106.780613,32.316912],"type":"Point"}
}