{
  "type": "Feature",
  "properties": {
    "iso:country":"US",
    "sg:address":"4901 Central Ave SE",
    "sg:city":"Albuquerque",
    "sg:classifiers":[
        {
            "category":"Banks & Credit Unions",
            "subcategory":"Bank",
            "type":"Services"
        }
    ],
    "sg:phone":"+1 505 855 0855",
    "sg:postcode":"87108",
    "sg:province":"NM",
    "wof:name":"Bank Of Albuquerque",
    "wof:placetype":"venue"
},
  "geometry": {"coordinates":[-106.589327,35.078089],"type":"Point"}
}