{
  "type": "Feature",
  "properties": {
    "addr:full":"1306 W College Blvd Roswell NM 88201",
    "addr:housenumber":"1306",
    "addr:postcode":"88201",
    "addr:street":"W College Blvd",
    "iso:country":"US",
    "sg:address":"1306 W College Blvd",
    "sg:city":"Roswell",
    "sg:classifiers":[
        {
            "category":"Social Services",
            "subcategory":"Adult Care",
            "type":"Services"
        }
    ],
    "sg:phone":"+1 505 627 8361",
    "sg:postcode":"88201",
    "sg:province":"NM",
    "sg:tags":[
        "home",
        "sheltered"
    ],
    "wof:name":"Refuge Shelter For Battered",
    "wof:placetype":"venue"
},
  "geometry": {"coordinates":[-104.53946999999999,33.408586],"type":"Point"}
}