{
  "type": "Feature",
  "properties": {
    "addr:full":"4130 Cutler Ave NE Albuquerque NM 87110",
    "addr:housenumber":"4130",
    "addr:postcode":"87110",
    "addr:street":"Cutler Ave Ne",
    "iso:country":"US",
    "sg:address":"4130 Cutler Ave NE",
    "sg:city":"Albuquerque",
    "sg:classifiers":[
        {
            "category":"Sports & Exercise",
            "subcategory":"Gym",
            "type":"Entertainment"
        }
    ],
    "sg:phone":"+1 505 855 7722",
    "sg:postcode":"87110",
    "sg:province":"NM",
    "sg:tags":[
        "fitness",
        "physical",
        "merchandise",
        "facility"
    ],
    "wof:name":"Spa & Billiard World",
    "wof:placetype":"venue"
},
  "geometry": {"coordinates":[-106.598404,35.105505],"type":"Point"}
}