{
  "type": "Feature",
  "properties": {
    "iso:country":"US",
    "sg:address":"8801 Horizon Blvd",
    "sg:city":"Albuquerque",
    "sg:classifiers":[
        {
            "category":"Banks & Credit Unions",
            "subcategory":"Investment Brokerage",
            "type":"Services"
        }
    ],
    "sg:phone":"+1 505 798 3000",
    "sg:postcode":"87113",
    "sg:province":"NM",
    "sg:tags":[
        "consultant",
        "planning",
        "financial"
    ],
    "wof:name":"John Hancock Signature Svc",
    "wof:placetype":"venue"
},
  "geometry": {"coordinates":[-106.600939,35.184565],"type":"Point"}
}