{
  "type": "Feature",
  "properties": {
    "iso:country":"US",
    "sg:address":"9174 Signal Ave NE",
    "sg:city":"Albuquerque",
    "sg:classifiers":[
        {
            "category":"Banks & Credit Unions",
            "subcategory":"Financial Services",
            "type":"Services"
        }
    ],
    "sg:phone":"+1 505 858 0508",
    "sg:postcode":"87122",
    "sg:province":"NM",
    "sg:tags":[
        "company",
        "holding"
    ],
    "wof:name":"Deveraux Holdings Company LLC",
    "wof:placetype":"venue"
},
  "geometry": {"coordinates":[-106.541,35.182916],"type":"Point"}
}