{
  "type": "Feature",
  "properties": {
    "iso:country":"US",
    "sg:address":"5150 Journal Center Blvd NE",
    "sg:city":"Albuquerque",
    "sg:classifiers":[
        {
            "category":"Shopping",
            "subcategory":"Pharmacy",
            "type":"Retail Goods"
        },
        {
            "category":"Community Center",
            "type":"Public Place"
        }
    ],
    "sg:phone":"+1 505 262 3365",
    "sg:postcode":"87109",
    "sg:province":"NM",
    "sg:tags":[
        "medical"
    ],
    "sg:website":"http://www.lovelace.com",
    "wof:name":"Lovelace Pharmacy - Jurnl Ctr",
    "wof:placetype":"venue"
},
  "geometry": {"coordinates":[-106.585356,35.170062],"type":"Point"}
}