{
  "type": "Feature",
  "properties": {
    "addr:full":"202 E Pinon St Farmington NM 87402",
    "addr:housenumber":"202",
    "addr:postcode":"87402",
    "addr:street":"E Pinon St",
    "iso:country":"US",
    "sg:address":"202 E Pinon St",
    "sg:city":"Farmington",
    "sg:classifiers":[
        {
            "category":"Travel",
            "subcategory":"Campground",
            "type":"Entertainment"
        }
    ],
    "sg:phone":"+1 505 564 2222",
    "sg:postcode":"87402",
    "sg:province":"NM",
    "sg:tags":[
        "recreational",
        "parks",
        "vehicle"
    ],
    "wof:name":"Dad's Rv Park",
    "wof:placetype":"venue"
},
  "geometry": {"coordinates":[-108.204065,36.723209],"type":"Point"}
}