{
  "type": "Feature",
  "properties": {
    "iso:country":"US",
    "sg:address":"6900 Los Volcanoes Rd NW",
    "sg:city":"Albuquerque",
    "sg:classifiers":[
        {
            "category":"Organizations",
            "subcategory":"Religious Organization",
            "type":"Services"
        }
    ],
    "sg:phone":"+1 505 401 1088",
    "sg:postcode":"87121",
    "sg:province":"NM",
    "wof:name":"Nlbc Womens Aux",
    "wof:placetype":"venue"
},
  "geometry": {"coordinates":[-106.719251,35.089836],"type":"Point"}
}