{
  "type": "Feature",
  "properties": {
    "iso:country":"US",
    "sg:address":"2390 North Rd",
    "sg:city":"Los Alamos",
    "sg:classifiers":[
        {
            "category":"Organizations",
            "subcategory":"Religious Organization",
            "type":"Services"
        }
    ],
    "sg:phone":"+1 505 662 5151",
    "sg:postcode":"87544",
    "sg:province":"NM",
    "sg:tags":[
        "church"
    ],
    "sg:website":"www.bethluth.com",
    "wof:name":"Bethlehem Evangelical Lutheran",
    "wof:placetype":"venue"
},
  "geometry": {"coordinates":[-106.32456000000001,35.899848],"type":"Point"}
}