{
  "type": "Feature",
  "properties": {
    "addr:full":"801 W Main St Farmington NM 87401",
    "addr:housenumber":"801",
    "addr:postcode":"87401",
    "addr:street":"W Main St",
    "iso:country":"US",
    "sg:address":"801 W Main St",
    "sg:city":"Farmington",
    "sg:classifiers":[
        {
            "category":"Banks & Credit Unions",
            "subcategory":"Bank",
            "type":"Services"
        }
    ],
    "sg:phone":"+1 505 564 3229",
    "sg:postcode":"87401",
    "sg:province":"NM",
    "sg:tags":[
        "loan"
    ],
    "wof:name":"Gold Star Finance",
    "wof:placetype":"venue"
},
  "geometry": {"coordinates":[-108.21823500000001,36.729081],"type":"Point"}
}