{
  "type": "Feature",
  "properties": {
    "iso:country":"US",
    "sg:address":"813 Saint Michaels Dr",
    "sg:city":"Santa Fe",
    "sg:classifiers":[
        {
            "category":"Banks & Credit Unions",
            "subcategory":"Bank",
            "type":"Services"
        }
    ],
    "sg:phone":"+1 505 983 7328",
    "sg:postcode":"87505",
    "sg:province":"NM",
    "sg:tags":[
        "state",
        "chartered"
    ],
    "sg:website":"www.secunm.org",
    "wof:name":"State Employees Credit Union",
    "wof:placetype":"venue"
},
  "geometry": {"coordinates":[-105.963135,35.659558],"type":"Point"}
}