{
  "type": "Feature",
  "properties": {
    "iso:country":"US",
    "sg:address":"904 New York Ave",
    "sg:city":"Alamogordo",
    "sg:classifiers":[
        {
            "category":"Restaurant",
            "type":"Food & Drink"
        }
    ],
    "sg:phone":"+1 505 437 9600",
    "sg:postcode":"88310",
    "sg:province":"NM",
    "sg:tags":[
        "tea",
        "rooms"
    ],
    "wof:name":"Nelleke's Small Piece-Europe",
    "wof:placetype":"venue"
},
  "geometry": {"coordinates":[-105.959149,32.899742],"type":"Point"}
}