{
  "type": "Feature",
  "properties": {
    "addr:full":"107 Sierra Vista Dr Los Alamos NM 87544",
    "addr:housenumber":"107",
    "addr:postcode":"87544",
    "addr:street":"Sierra Vista Dr",
    "iso:country":"US",
    "sg:address":"107 Sierra Vista Dr",
    "sg:city":"Los Alamos",
    "sg:classifiers":[
        {
            "category":"Professional",
            "subcategory":"Computer Services",
            "type":"Services"
        }
    ],
    "sg:phone":"+1 505 672 1095",
    "sg:postcode":"87544",
    "sg:province":"NM",
    "sg:tags":[
        "repair"
    ],
    "wof:name":"Dr Mac Computer Support",
    "wof:placetype":"venue"
},
  "geometry": {"coordinates":[-106.215132,35.822853],"type":"Point"}
}