{
  "type": "Feature",
  "properties": {
    "addr:full":"4815 Hawkins St NE Albuquerque NM 87109",
    "addr:housenumber":"4815",
    "addr:postcode":"87109",
    "addr:street":"Hawkins St Ne",
    "iso:country":"US",
    "sg:address":"4815 Hawkins St NE",
    "sg:city":"Albuquerque",
    "sg:classifiers":[
        {
            "category":"Building & Trades",
            "subcategory":"Construction",
            "type":"Services"
        }
    ],
    "sg:phone":"+1 505 821 8025",
    "sg:postcode":"87109",
    "sg:province":"NM",
    "sg:tags":[
        "dry wall",
        "contractor"
    ],
    "wof:name":"Unique Drywall",
    "wof:placetype":"venue"
},
  "geometry": {"coordinates":[-106.59066900000001,35.162791],"type":"Point"}
}