{
  "type": "Feature",
  "properties": {
    "iso:country":"US",
    "sg:address":"820 N Edwards St",
    "sg:city":"Clovis",
    "sg:classifiers":[
        {
            "category":"Professional",
            "subcategory":"Accounting & Tax Preparation",
            "type":"Services"
        }
    ],
    "sg:phone":"+1 505 763 3968",
    "sg:postcode":"88101",
    "sg:province":"NM",
    "sg:tags":[
        "return",
        "filing"
    ],
    "wof:name":"Marin Income Tax Svc",
    "wof:placetype":"venue"
},
  "geometry": {"coordinates":[-103.218051,34.406583],"type":"Point"}
}