{
  "type": "Feature",
  "properties": {
    "addr:full":"3150 Carlisle Blvd NE Albuquerque NM 87110",
    "addr:housenumber":"3150",
    "addr:postcode":"87110",
    "addr:street":"Carlisle Blvd Ne",
    "iso:country":"US",
    "sg:address":"3150 Carlisle Blvd NE",
    "sg:city":"Albuquerque",
    "sg:classifiers":[
        {
            "category":"Professional",
            "subcategory":"Engineering",
            "type":"Services"
        }
    ],
    "sg:phone":"+1 505 889 4525",
    "sg:postcode":"87110",
    "sg:province":"NM",
    "sg:tags":[
        "consulting"
    ],
    "wof:name":"Parsons Engineering Science",
    "wof:placetype":"venue"
},
  "geometry": {"coordinates":[-106.604033,35.117834],"type":"Point"}
}