{
  "type": "Feature",
  "properties": {
    "iso:country":"US",
    "sg:address":"3700 Osuna Rd NE",
    "sg:city":"Albuquerque",
    "sg:classifiers":[
        {
            "category":"Building & Trades",
            "subcategory":"Equipment Rental",
            "type":"Services"
        }
    ],
    "sg:phone":"+1 505 345 3687",
    "sg:postcode":"87109",
    "sg:province":"NM",
    "sg:tags":[
        "heavy",
        "construction"
    ],
    "wof:name":"Jack Beaty and Assicoates",
    "wof:placetype":"venue"
},
  "geometry": {"coordinates":[-106.604613,35.153545],"type":"Point"}
}