{
  "type": "Feature",
  "properties": {
    "iso:country":"US",
    "sg:address":"12513 Phoenix Ave NE",
    "sg:city":"Albuquerque",
    "sg:classifiers":[
        {
            "category":"Banks & Credit Unions",
            "subcategory":"Investment Brokerage",
            "type":"Services"
        }
    ],
    "sg:phone":"+1 505 293 0461",
    "sg:postcode":"87112",
    "sg:province":"NM",
    "sg:tags":[
        "advisory",
        "consulting",
        "management"
    ],
    "wof:name":"MGM",
    "wof:placetype":"venue"
},
  "geometry": {"coordinates":[-106.499014,35.110981],"type":"Point"}
}