{
  "type": "Feature",
  "properties": {
    "iso:country":"US",
    "sg:address":"10205 Southern Blvd SE",
    "sg:city":"Albuquerque",
    "sg:classifiers":[
        {
            "category":"Manufacturing",
            "subcategory":"Motor Vehicles & Parts",
            "type":"Manufacturing & Wholesale Goods"
        }
    ],
    "sg:phone":"+1 505 292 8018",
    "sg:postcode":"87123",
    "sg:province":"NM",
    "sg:tags":[
        "body",
        "equipment",
        "truck",
        "mfg"
    ],
    "wof:name":"Construction Support Equipment",
    "wof:placetype":"venue"
},
  "geometry": {"coordinates":[-106.53337500000001,35.067436],"type":"Point"}
}