{
  "type": "Feature",
  "properties": {
    "iso:country":"US",
    "sg:address":"15 Terry Dr",
    "sg:city":"Los Lunas",
    "sg:classifiers":[
        {
            "category":"Building & Trades",
            "subcategory":"Cleaning & Sanitation",
            "type":"Services"
        }
    ],
    "sg:phone":"+1 505 891 2424",
    "sg:postcode":"87031",
    "sg:province":"NM",
    "sg:tags":[
        "commercial"
    ],
    "wof:name":"Jet Kleen",
    "wof:placetype":"venue"
},
  "geometry": {"coordinates":[-106.68108599999999,34.798792],"type":"Point"}
}