{
  "type": "Feature",
  "properties": {
    "iso:country":"US",
    "sg:address":"1009 Franklin St",
    "sg:city":"Anthony",
    "sg:classifiers":[
        {
            "category":"Shopping",
            "subcategory":"Florist",
            "type":"Retail Goods"
        }
    ],
    "sg:phone":"+1 915 886 3232",
    "sg:postcode":"79821",
    "sg:province":"NM",
    "wof:name":"Monica's Flowers",
    "wof:placetype":"venue"
},
  "geometry": {"coordinates":[-106.594815,31.998506],"type":"Point"}
}