{
  "type": "Feature",
  "properties": {
    "iso:country":"US",
    "sg:address":"900 Atlantic Ave SW",
    "sg:city":"Albuquerque",
    "sg:classifiers":[
        {
            "category":"Education",
            "subcategory":"School",
            "type":"Public Place"
        }
    ],
    "sg:phone":"+1 505 242 5131",
    "sg:postcode":"87102",
    "sg:province":"NM",
    "wof:name":"Albuquerque Pub Sch Cafeteria",
    "wof:placetype":"venue"
},
  "geometry": {"coordinates":[-106.65976000000001,35.07703],"type":"Point"}
}