{
  "type": "Feature",
  "properties": {
    "iso:country":"US",
    "sg:address":"3416 Old Cavern Hwy",
    "sg:city":"Carlsbad",
    "sg:classifiers":[
        {
            "category":"Freight",
            "type":"Transportation"
        }
    ],
    "sg:phone":"+1 505 887 6663",
    "sg:postcode":"88220",
    "sg:province":"NM",
    "sg:tags":[
        "operator",
        "local",
        "trucking"
    ],
    "wof:name":"Bc Hauling & Hot Shot Service",
    "wof:placetype":"venue"
},
  "geometry": {"coordinates":[-104.220146,32.381532],"type":"Point"}
}