{
  "type": "Feature",
  "properties": {
    "addr:full":"3852 Ladera Dr NW Albuquerque NM 87120",
    "addr:housenumber":"3852",
    "addr:postcode":"87120",
    "addr:street":"Ladera Dr Nw",
    "iso:country":"US",
    "sg:address":"3852 Ladera Dr NW",
    "sg:city":"Albuquerque",
    "sg:classifiers":[
        {
            "category":"Building & Trades",
            "subcategory":"Construction",
            "type":"Services"
        }
    ],
    "sg:phone":"+1 505 831 7301",
    "sg:postcode":"87120",
    "sg:province":"NM",
    "sg:tags":[
        "general",
        "contractor"
    ],
    "wof:name":"Donald R Reynolds",
    "wof:placetype":"venue"
},
  "geometry": {"coordinates":[-106.710264,35.12589],"type":"Point"}
}