{
  "type": "Feature",
  "properties": {
    "addr:full":"1731 Central Ave Los Alamos NM 87544",
    "addr:housenumber":"1731",
    "addr:postcode":"87544",
    "addr:street":"Central Ave",
    "iso:country":"US",
    "sg:address":"1731 Central Ave",
    "sg:city":"Los Alamos",
    "sg:classifiers":[
        {
            "category":"Manufacturing",
            "subcategory":"Furniture",
            "type":"Manufacturing & Wholesale Goods"
        }
    ],
    "sg:phone":"+1 505 662 1978",
    "sg:postcode":"87544",
    "sg:province":"NM",
    "sg:tags":[
        "mfg",
        "wood",
        "sewing",
        "cabinet"
    ],
    "wof:name":"Vacuum Store",
    "wof:placetype":"venue"
},
  "geometry": {"coordinates":[-106.301118,35.88142],"type":"Point"}
}