{
  "type": "Feature",
  "properties": {
    "addr:full":"340 N Water St Las Cruces NM 88001",
    "addr:housenumber":"340",
    "addr:postcode":"88001",
    "addr:street":"N Water St",
    "iso:country":"US",
    "sg:address":"340 N Water St",
    "sg:city":"Las Cruces",
    "sg:classifiers":[
        {
            "category":"Banks & Credit Unions",
            "subcategory":"Investment Brokerage",
            "type":"Services"
        }
    ],
    "sg:phone":"+1 505 541 6501",
    "sg:postcode":"88001",
    "sg:province":"NM",
    "sg:tags":[
        "consultant",
        "planning",
        "financial"
    ],
    "sg:website":"www.ameriprise.com",
    "wof:name":"Ameriprise Financial",
    "wof:placetype":"venue"
},
  "geometry": {"coordinates":[-106.78012200000001,32.31158],"type":"Point"}
}