{
  "type": "Feature",
  "properties": {
    "addr:full":"111 Eagle Dr Raton NM 87740",
    "addr:housenumber":"111",
    "addr:postcode":"87740",
    "addr:street":"Eagle Dr",
    "iso:country":"US",
    "sg:address":"111 Eagle Dr",
    "sg:city":"Raton",
    "sg:classifiers":[
        {
            "category":"Building & Trades",
            "subcategory":"Construction",
            "type":"Services"
        }
    ],
    "sg:phone":"+1 505 445 8429",
    "sg:postcode":"87740",
    "sg:province":"NM",
    "sg:tags":[
        "repairing",
        "remodeling",
        "contractor"
    ],
    "wof:name":"David Parker Builders Inc",
    "wof:placetype":"venue"
},
  "geometry": {"coordinates":[-104.46186400000001,36.890225],"type":"Point"}
}