{
  "type": "Feature",
  "properties": {
    "iso:country":"US",
    "sg:address":"2205 Carolina St",
    "sg:city":"Clovis",
    "sg:classifiers":[
        {
            "category":"Building & Trades",
            "subcategory":"Construction",
            "type":"Services"
        }
    ],
    "sg:phone":"+1 505 763 5894",
    "sg:postcode":"88101",
    "sg:province":"NM",
    "sg:tags":[
        "painter"
    ],
    "wof:name":"AA-1 Painting & Remodeling",
    "wof:placetype":"venue"
},
  "geometry": {"coordinates":[-103.204339,34.373413],"type":"Point"}
}