{
  "type": "Feature",
  "properties": {
    "addr:full":"501 N Main St Roswell NM 88201",
    "addr:housenumber":"501",
    "addr:postcode":"88201",
    "addr:street":"N Main St",
    "iso:country":"US",
    "sg:address":"501 N Main St",
    "sg:city":"Roswell",
    "sg:classifiers":[
        {
            "category":"Real Estate",
            "subcategory":"Real Estate Agent",
            "type":"Services"
        }
    ],
    "sg:phone":"+1 505 624 2262",
    "sg:postcode":"88201",
    "sg:province":"NM",
    "sg:website":"www.realestateroswell.com",
    "wof:name":"Grieves Group Realtors",
    "wof:placetype":"venue"
},
  "geometry": {"coordinates":[-104.52274300000001,33.39879],"type":"Point"}
}