{
  "type": "Feature",
  "properties": {
    "iso:country":"US",
    "sg:address":"3316 Lafayette Dr NE",
    "sg:city":"Albuquerque",
    "sg:classifiers":[
        {
            "category":"Manufacturing",
            "subcategory":"Musical Instruments",
            "type":"Manufacturing & Wholesale Goods"
        }
    ],
    "sg:phone":"+1 505 884 1669",
    "sg:postcode":"87107",
    "sg:province":"NM",
    "sg:tags":[
        "guitar",
        "mfg"
    ],
    "wof:name":"Pimentel Guitar",
    "wof:placetype":"venue"
},
  "geometry": {"coordinates":[-106.60847,35.119713],"type":"Point"}
}