{
  "type": "Feature",
  "properties": {
    "iso:country":"US",
    "sg:address":"1222 State Hwy 53",
    "sg:city":"Zuni",
    "sg:classifiers":[
        {
            "category":"Professional",
            "subcategory":"Business Services",
            "type":"Services"
        }
    ],
    "sg:phone":"+1 505 782 2466",
    "sg:postcode":"87327",
    "sg:province":"NM",
    "wof:name":"Ashiwi Awan Business Dev Corp",
    "wof:placetype":"venue"
},
  "geometry": {"coordinates":[-108.84483899999999,35.070141],"type":"Point"}
}