{
  "type": "Feature",
  "properties": {
    "iso:country":"US",
    "sg:address":"4200 SE Main St",
    "sg:city":"Roswell",
    "sg:classifiers":[
        {
            "category":"Building & Trades",
            "subcategory":"Construction",
            "type":"Services"
        }
    ],
    "sg:phone":"+1 505 622 8106",
    "sg:postcode":"88203",
    "sg:province":"NM",
    "sg:tags":[
        "roofing",
        "contractor"
    ],
    "sg:website":"www.allen-roofing.com",
    "wof:name":"Allen Roofing Co",
    "wof:placetype":"venue"
},
  "geometry": {"coordinates":[-104.504412,33.33048],"type":"Point"}
}