{
  "type": "Feature",
  "properties": {
    "addr:full":"162 Bridge St Las Vegas NM 87701",
    "addr:housenumber":"162",
    "addr:postcode":"87701",
    "addr:street":"Bridge St",
    "iso:country":"US",
    "sg:address":"162 Bridge St",
    "sg:city":"Las Vegas",
    "sg:classifiers":[
        {
            "category":"Personal",
            "type":"Services"
        },
        {
            "category":"Personal",
            "subcategory":"Tattoo Parlor",
            "type":"Services"
        }
    ],
    "sg:phone":"+1 505 454 7391",
    "sg:postcode":"87701",
    "sg:province":"NM",
    "sg:tags":[
        "tattooing"
    ],
    "wof:name":"Razors Custom Tattoos",
    "wof:placetype":"venue"
},
  "geometry": {"coordinates":[-105.225166,35.593315],"type":"Point"}
}