{
  "type": "Feature",
  "properties": {
    "iso:country":"US",
    "sg:address":"1065 S Main St",
    "sg:city":"Las Cruces",
    "sg:classifiers":[
        {
            "category":"Insurance",
            "subcategory":"Insurance Agent",
            "type":"Services"
        }
    ],
    "sg:phone":"+1 505 524 0570",
    "sg:postcode":"88005",
    "sg:province":"NM",
    "wof:name":"Allstate Insurance Co",
    "wof:placetype":"venue"
},
  "geometry": {"coordinates":[-106.778631,32.300044],"type":"Point"}
}