{
  "type": "Feature",
  "properties": {
    "addr:full":"3122 Spur Ct NW Albuquerque NM 87104",
    "addr:housenumber":"3122",
    "addr:postcode":"87104",
    "addr:street":"Spur Ct Nw",
    "iso:country":"US",
    "sg:address":"3122 Spur Ct NW",
    "sg:city":"Albuquerque",
    "sg:classifiers":[
        {
            "category":"Banks & Credit Unions",
            "subcategory":"Investment Brokerage",
            "type":"Services"
        },
        {
            "category":"Real Estate",
            "subcategory":"Developer",
            "type":"Services"
        }
    ],
    "sg:phone":"+1 505 843 8373",
    "sg:postcode":"87104",
    "sg:province":"NM",
    "sg:tags":[
        "investing"
    ],
    "wof:name":"Mmg Inc",
    "wof:placetype":"venue"
},
  "geometry": {"coordinates":[-106.683886,35.101522],"type":"Point"}
}