{
  "type": "Feature",
  "properties": {
    "iso:country":"US",
    "sg:address":"1090 US Hwy 70",
    "sg:city":"Alamogordo",
    "sg:classifiers":[
        {
            "category":"Real Estate",
            "subcategory":"Real Estate Operator",
            "type":"Services"
        }
    ],
    "sg:phone":"+1 505 434 2266",
    "sg:postcode":"88310",
    "sg:province":"NM",
    "sg:tags":[
        "mobile",
        "home",
        "site"
    ],
    "wof:name":"Desert Paradise Mobile Home",
    "wof:placetype":"venue"
},
  "geometry": {"coordinates":[-105.960161,32.899856],"type":"Point"}
}