{
  "type": "Feature",
  "properties": {
    "iso:country":"US",
    "sg:address":"325 Canyonview Dr",
    "sg:city":"Farmington",
    "sg:classifiers":[
        {
            "category":"Building & Trades",
            "subcategory":"Construction",
            "type":"Services"
        }
    ],
    "sg:phone":"+1 505 327 5502",
    "sg:postcode":"87401",
    "sg:province":"NM",
    "sg:tags":[
        "general",
        "contractor"
    ],
    "wof:name":"Liessmann Construction",
    "wof:placetype":"venue"
},
  "geometry": {"coordinates":[-108.201159,36.772106],"type":"Point"}
}