{
  "type": "Feature",
  "properties": {
    "iso:country":"US",
    "sg:address":"205 N Main Ave",
    "sg:city":"Lovington",
    "sg:classifiers":[
        {
            "category":"Shopping",
            "subcategory":"Gifts & Souvenirs",
            "type":"Retail Goods"
        }
    ],
    "sg:phone":"+1 505 396 1654",
    "sg:postcode":"88260",
    "sg:province":"NM",
    "sg:tags":[
        "personal",
        "party",
        "supply"
    ],
    "wof:name":"Paper and Party Emporium",
    "wof:placetype":"venue"
},
  "geometry": {"coordinates":[-103.348659,32.949694],"type":"Point"}
}