{
  "type": "Feature",
  "properties": {
    "iso:country":"US",
    "sg:address":"140 Wagner Ln",
    "sg:city":"Corrales",
    "sg:classifiers":[
        {
            "category":"Professional",
            "subcategory":"Computer Services",
            "type":"Services"
        }
    ],
    "sg:phone":"+1 505 897 4769",
    "sg:postcode":"87048",
    "sg:province":"NM",
    "sg:tags":[
        "website",
        "design"
    ],
    "sg:website":"www.cre8fx.com",
    "wof:name":"Creative Effects Software",
    "wof:placetype":"venue"
},
  "geometry": {"coordinates":[-106.606759,35.230749],"type":"Point"}
}