{
  "type": "Feature",
  "properties": {
    "iso:country":"US",
    "sg:address":"2801 W Rodeo Rd",
    "sg:city":"Santa Fe",
    "sg:classifiers":[
        {
            "category":"Retail",
            "subcategory":"Laundry & Dry Cleaning",
            "type":"Services"
        }
    ],
    "sg:phone":"+1 505 473 4396",
    "sg:postcode":"87507",
    "sg:province":"NM",
    "sg:tags":[
        "drycleaning",
        "plant"
    ],
    "wof:name":"Santa Fe One Hour Martinizing",
    "wof:placetype":"venue"
},
  "geometry": {"coordinates":[-105.982136,35.638429],"type":"Point"}
}