{
  "type": "Feature",
  "properties": {
    "iso:country":"US",
    "sg:address":"411 E Church St",
    "sg:city":"Carlsbad",
    "sg:classifiers":[
        {
            "category":"Personal",
            "type":"Services"
        }
    ],
    "sg:phone":"+1 505 628 3905",
    "sg:postcode":"88220",
    "sg:province":"NM",
    "wof:name":"3 TS Tanning LLC",
    "wof:placetype":"venue"
},
  "geometry": {"coordinates":[-104.22199,32.428465],"type":"Point"}
}