{
  "type": "Feature",
  "properties": {
    "iso:country":"US",
    "sg:address":"1000 Cerrillos Rd",
    "sg:city":"Santa Fe",
    "sg:classifiers":[
        {
            "category":"Home & Garden",
            "subcategory":"Carpets & Floor Coverings",
            "type":"Retail Goods"
        }
    ],
    "sg:phone":"+1 505 988 3022",
    "sg:postcode":"87505",
    "sg:province":"NM",
    "sg:tags":[
        "dealer",
        "rug"
    ],
    "wof:name":"Carpet One Dominguez",
    "wof:placetype":"venue"
},
  "geometry": {"coordinates":[-105.95811999999999,35.674962],"type":"Point"}
}