{
  "type": "Feature",
  "properties": {
    "addr:full":"7204 Old Aspen Rd SW Albuquerque NM 87121",
    "addr:housenumber":"7204",
    "addr:postcode":"87121",
    "addr:street":"Old Aspen Rd Sw",
    "iso:country":"US",
    "sg:address":"7204 Old Aspen Rd SW",
    "sg:city":"Albuquerque",
    "sg:classifiers":[
        {
            "category":"Shopping",
            "subcategory":"Bicycles & Sporting Goods",
            "type":"Retail Goods"
        }
    ],
    "sg:phone":"+1 505 831 3509",
    "sg:postcode":"87121",
    "sg:province":"NM",
    "wof:name":"Leos Candies Bike",
    "wof:placetype":"venue"
},
  "geometry": {"coordinates":[-106.715802,35.052895],"type":"Point"}
}