{
  "type": "Feature",
  "properties": {
    "addr:full":"215 W Broadway St Hobbs NM 88240",
    "addr:housenumber":"215",
    "addr:postcode":"88240",
    "addr:street":"W Broadway St",
    "iso:country":"US",
    "sg:address":"215 W Broadway St",
    "sg:city":"Hobbs",
    "sg:classifiers":[
        {
            "category":"Shopping",
            "subcategory":"Computers & Home Electronics",
            "type":"Retail Goods"
        }
    ],
    "sg:phone":"+1 505 393 7226",
    "sg:postcode":"88240",
    "sg:province":"NM",
    "sg:tags":[
        "equipment",
        "dealer"
    ],
    "wof:name":"Precision Computer's",
    "wof:placetype":"venue"
},
  "geometry": {"coordinates":[-103.138552,32.700728],"type":"Point"}
}