{
  "type": "Feature",
  "properties": {
    "iso:country":"US",
    "sg:address":"4300 Prairie Hill Pl NW",
    "sg:city":"Albuquerque",
    "sg:classifiers":[
        {
            "category":"Building & Trades",
            "subcategory":"Construction",
            "type":"Services"
        }
    ],
    "sg:phone":"+1 505 440 2406",
    "sg:postcode":"87114",
    "sg:province":"NM",
    "sg:tags":[
        "system",
        "contractor",
        "air conditioning"
    ],
    "sg:website":"http://mountainairconditioningandheatingsvc.com",
    "wof:name":"Moutain Air Conditioning and Heating Service",
    "wof:placetype":"venue"
},
  "geometry": {"coordinates":[-106.66687,35.19466],"type":"Point"}
}