{
  "type": "Feature",
  "properties": {
    "iso:country":"US",
    "sg:address":"7800 Central Ave SE",
    "sg:city":"Albuquerque",
    "sg:classifiers":[
        {
            "category":"Autos & Motor Vehicles",
            "subcategory":"Automobile Sales",
            "type":"Retail Goods"
        }
    ],
    "sg:phone":"+1 505 268 6932",
    "sg:postcode":"87108",
    "sg:province":"NM",
    "sg:tags":[
        "new",
        "used"
    ],
    "sg:website":"www.fultonmotors.com",
    "wof:name":"Fulton Motors Truck Sales",
    "wof:placetype":"venue"
},
  "geometry": {"coordinates":[-106.560133,35.074973],"type":"Point"}
}