{
  "type": "Feature",
  "properties": {
    "addr:full":"1014 W High St Grants NM 87020",
    "addr:housenumber":"1014",
    "addr:postcode":"87020",
    "addr:street":"W High St",
    "iso:country":"US",
    "sg:address":"1014 W High St",
    "sg:city":"Grants",
    "sg:classifiers":[
        {
            "category":"Government",
            "subcategory":"Office",
            "type":"Public Place"
        }
    ],
    "sg:phone":"+1 505 285 6673",
    "sg:postcode":"87020",
    "sg:province":"NM",
    "sg:tags":[
        "program",
        "administrative"
    ],
    "wof:name":"Child Care Bureau Region 1",
    "wof:placetype":"venue"
},
  "geometry": {"coordinates":[-107.860123,35.155414],"type":"Point"}
}