{
  "type": "Feature",
  "properties": {
    "addr:full":"4501 Indian School Rd NE Albuquerque NM 87110",
    "addr:housenumber":"4501",
    "addr:postcode":"87110",
    "addr:street":"Indian School Rd Ne",
    "iso:country":"US",
    "sg:address":"4501 Indian School Rd NE",
    "sg:city":"Albuquerque",
    "sg:classifiers":[
        {
            "category":"Professional",
            "subcategory":"Lawyer & Legal Services",
            "type":"Services"
        }
    ],
    "sg:phone":"+1 505 254 7767",
    "sg:postcode":"87110",
    "sg:province":"NM",
    "sg:tags":[
        "attorney"
    ],
    "wof:name":"Susan C Little & Assoc",
    "wof:placetype":"venue"
},
  "geometry": {"coordinates":[-106.592314,35.101929],"type":"Point"}
}