{
  "type": "Feature",
  "properties": {
    "iso:country":"US",
    "sg:address":"3905 SE Main St",
    "sg:city":"Roswell",
    "sg:classifiers":[
        {
            "category":"Bars & Pubs",
            "type":"Food & Drink"
        }
    ],
    "sg:phone":"+1 505 623 7627",
    "sg:postcode":"88203",
    "sg:province":"NM",
    "sg:tags":[
        "lounge",
        "cocktail"
    ],
    "wof:name":"Town & Country Nightclub",
    "wof:placetype":"venue"
},
  "geometry": {"coordinates":[-104.50597399999999,33.336375],"type":"Point"}
}