{
  "type": "Feature",
  "properties": {
    "iso:country":"US",
    "sg:address":"5717 Edith Blvd NE",
    "sg:city":"Albuquerque",
    "sg:classifiers":[
        {
            "category":"Personal",
            "subcategory":"Beauty Salon",
            "type":"Services"
        }
    ],
    "sg:phone":"+1 505 344 6585",
    "sg:postcode":"87107",
    "sg:province":"NM",
    "wof:name":"Kat's Kuts Hair Design",
    "wof:placetype":"venue"
},
  "geometry": {"coordinates":[-106.62800300000001,35.137612],"type":"Point"}
}