{
  "type": "Feature",
  "properties": {
    "iso:country":"US",
    "sg:address":"33 Rd 6299",
    "sg:city":"Kirtland",
    "sg:classifiers":[
        {
            "category":"Building & Trades",
            "subcategory":"Construction",
            "type":"Services"
        },
        {
            "category":"Shopping",
            "subcategory":"Computers & Home Electronics",
            "type":"Retail Goods"
        }
    ],
    "sg:phone":"+1 505 598 9984",
    "sg:postcode":"87417",
    "sg:province":"NM",
    "sg:tags":[
        "equipment",
        "dredging",
        "metal",
        "locating"
    ],
    "wof:name":"Star Outdoors",
    "wof:placetype":"venue"
},
  "geometry": {"coordinates":[-108.341998,36.736801],"type":"Point"}
}