{
  "type": "Feature",
  "properties": {
    "iso:country":"US",
    "sg:address":"4401 McLeod Rd NE",
    "sg:city":"Albuquerque",
    "sg:classifiers":[
        {
            "category":"Wholesale",
            "subcategory":"Medical Equipment & Supplies",
            "type":"Manufacturing & Wholesale Goods"
        },
        {
            "category":"Health Services",
            "subcategory":"Clinic",
            "type":"Services"
        }
    ],
    "sg:phone":"+1 505 881 9111",
    "sg:postcode":"87109",
    "sg:province":"NM",
    "sg:tags":[
        "home"
    ],
    "sg:website":"www.apria.com",
    "wof:name":"Apria Healthcare Inc",
    "wof:placetype":"venue"
},
  "geometry": {"coordinates":[-106.593513,35.137484],"type":"Point"}
}