{
  "type": "Feature",
  "properties": {
    "addr:full":"115 S Silver Ave Deming NM 88030",
    "addr:housenumber":"115",
    "addr:postcode":"88030",
    "addr:street":"S Silver Ave",
    "iso:country":"US",
    "sg:address":"115 S Silver Ave",
    "sg:city":"Deming",
    "sg:classifiers":[
        {
            "category":"Home & Garden",
            "subcategory":"Carpets & Floor Coverings",
            "type":"Retail Goods"
        }
    ],
    "sg:phone":"+1 505 546 4077",
    "sg:postcode":"88030",
    "sg:province":"NM",
    "sg:tags":[
        "dealer",
        "rug"
    ],
    "wof:name":"LA Frontera Carpet & Tile",
    "wof:placetype":"venue"
},
  "geometry": {"coordinates":[-107.757373,32.268707],"type":"Point"}
}