{
  "type": "Feature",
  "properties": {
    "addr:full":"521 Candelaria Rd NE Albuquerque NM 87107",
    "addr:housenumber":"521",
    "addr:postcode":"87107",
    "addr:street":"Candelaria Rd Ne",
    "iso:country":"US",
    "sg:address":"521 Candelaria Rd NE",
    "sg:city":"Albuquerque",
    "sg:classifiers":[
        {
            "category":"Building & Trades",
            "subcategory":"Construction",
            "type":"Services"
        }
    ],
    "sg:phone":"+1 505 343 0722",
    "sg:postcode":"87107",
    "sg:province":"NM",
    "sg:tags":[
        "painter"
    ],
    "wof:name":"Kaehr Corp Paint Shop",
    "wof:placetype":"venue"
},
  "geometry": {"coordinates":[-106.63394700000001,35.116526],"type":"Point"}
}