{
  "type": "Feature",
  "properties": {
    "addr:full":"3216 Richards Ln Santa Fe NM 87507",
    "addr:housenumber":"3216",
    "addr:postcode":"87507",
    "addr:street":"Richards Ln",
    "iso:country":"US",
    "sg:address":"3216 Richards Ln",
    "sg:city":"Santa Fe",
    "sg:classifiers":[
        {
            "category":"Professional",
            "subcategory":"Research",
            "type":"Services"
        }
    ],
    "sg:phone":"+1 505 474 3500",
    "sg:postcode":"87507",
    "sg:province":"NM",
    "sg:tags":[
        "development"
    ],
    "wof:name":"Santa Fe Science & Technology",
    "wof:placetype":"venue"
},
  "geometry": {"coordinates":[-106.00021,35.65673],"type":"Point"}
}