{
  "type": "Feature",
  "properties": {
    "addr:full":"23 Rd 2685 Aztec NM 87410",
    "addr:housenumber":"23",
    "addr:postcode":"2685;87410",
    "addr:street":"Rd",
    "iso:country":"US",
    "sg:address":"23 Rd 2685",
    "sg:city":"Aztec",
    "sg:classifiers":[
        {
            "category":"Manufacturing",
            "subcategory":"Metals",
            "type":"Manufacturing & Wholesale Goods"
        }
    ],
    "sg:phone":"+1 505 334 3849",
    "sg:postcode":"87410",
    "sg:province":"NM",
    "sg:tags":[
        "coating"
    ],
    "wof:name":"Line-X Spray On Bedliners",
    "wof:placetype":"venue"
},
  "geometry": {"coordinates":[-107.944143,36.884704],"type":"Point"}
}