{
  "type": "Feature",
  "properties": {
    "addr:full":"8080 Academy Rd NE Albuquerque NM 87111",
    "addr:housenumber":"8080",
    "addr:postcode":"87111",
    "addr:street":"Academy Rd Ne",
    "iso:country":"US",
    "sg:address":"8080 Academy Rd NE",
    "sg:city":"Albuquerque",
    "sg:classifiers":[
        {
            "category":"Health Services",
            "subcategory":"Doctor",
            "type":"Services"
        }
    ],
    "sg:phone":"+1 505 727 3400",
    "sg:postcode":"87111",
    "sg:province":"NM",
    "sg:tags":[
        "physician",
        "surgeon"
    ],
    "wof:name":"Academy Family Healthcare Ctr",
    "wof:placetype":"venue"
},
  "geometry": {"coordinates":[-106.548592,35.148207],"type":"Point"}
}