{
  "type": "Feature",
  "properties": {
    "addr:full":"820 Sagebrush Dr Corrales NM 87048",
    "addr:housenumber":"820",
    "addr:postcode":"87048",
    "addr:street":"Sagebrush Dr",
    "iso:country":"US",
    "sg:address":"820 Sagebrush Dr",
    "sg:city":"Corrales",
    "sg:classifiers":[
        {
            "category":"Real Estate",
            "subcategory":"Real Estate Agent",
            "type":"Services"
        }
    ],
    "sg:phone":"+1 505 792 8115",
    "sg:postcode":"87048",
    "sg:province":"NM",
    "wof:name":"New Dawn Realty",
    "wof:placetype":"venue"
},
  "geometry": {"coordinates":[-106.623637,35.245444],"type":"Point"}
}