{
  "type": "Feature",
  "properties": {
    "addr:full":"1605 Sheldon St Clovis NM 88101",
    "addr:housenumber":"1605",
    "addr:postcode":"88101",
    "addr:street":"Sheldon St",
    "iso:country":"US",
    "sg:address":"1605 Sheldon St",
    "sg:city":"Clovis",
    "sg:classifiers":[
        {
            "category":"Social Services",
            "subcategory":"Child Care",
            "type":"Services"
        }
    ],
    "sg:phone":"+1 505 762 8972",
    "sg:postcode":"88101",
    "sg:province":"NM",
    "wof:name":"Hawkins Preschool & Daycare",
    "wof:placetype":"venue"
},
  "geometry": {"coordinates":[-103.19893,34.414218],"type":"Point"}
}