{
  "type": "Feature",
  "properties": {
    "addr:full":"208 Dp Rd Los Alamos NM 87544",
    "addr:postcode":"87544",
    "addr:street":"Dp Rd",
    "iso:country":"US",
    "sg:address":"208 Dp Rd",
    "sg:city":"Los Alamos",
    "sg:classifiers":[
        {
            "category":"Retail",
            "subcategory":"Auto Repair",
            "type":"Services"
        }
    ],
    "sg:phone":"+1 505 662 7647",
    "sg:postcode":"87544",
    "sg:province":"NM",
    "sg:tags":[
        "repairing",
        "automobile",
        "parts",
        "general"
    ],
    "wof:name":"Glover's Auto Parts & Repair",
    "wof:placetype":"venue"
},
  "geometry": {"coordinates":[-106.274832,35.876796],"type":"Point"}
}