{
  "type": "Feature",
  "properties": {
    "addr:full":"3424 Montreal St NE Albuquerque NM 87111",
    "addr:housenumber":"3424",
    "addr:postcode":"87111",
    "addr:street":"Montreal St Ne",
    "iso:country":"US",
    "sg:address":"3424 Montreal St NE",
    "sg:city":"Albuquerque",
    "sg:classifiers":[
        {
            "category":"Professional",
            "subcategory":"Management & Consulting",
            "type":"Services"
        }
    ],
    "sg:phone":"+1 505 259 9114",
    "sg:postcode":"87111",
    "sg:province":"NM",
    "sg:tags":[
        "public",
        "relations"
    ],
    "wof:name":"Bob Cleavall Consulting",
    "wof:placetype":"venue"
},
  "geometry": {"coordinates":[-106.505039,35.119376],"type":"Point"}
}