{
  "type": "Feature",
  "properties": {
    "addr:full":"80 Saddle Spur Trl Edgewood NM 87015",
    "addr:housenumber":"80",
    "addr:postcode":"87015",
    "addr:street":"Saddle Spur Trl",
    "iso:country":"US",
    "sg:address":"80 Saddle Spur Trl",
    "sg:city":"Edgewood",
    "sg:classifiers":[
        {
            "category":"Building & Trades",
            "subcategory":"Construction",
            "type":"Services"
        }
    ],
    "sg:phone":"+1 505 281 1150",
    "sg:postcode":"87015",
    "sg:province":"NM",
    "sg:tags":[
        "contractor"
    ],
    "wof:name":"Gates Construction Co Inc",
    "wof:placetype":"venue"
},
  "geometry": {"coordinates":[-106.257683,35.069716],"type":"Point"}
}