{
  "type": "Feature",
  "properties": {
    "addr:full":"1000 Riverview Dr SE Rio Rancho NM 87124",
    "addr:housenumber":"1000",
    "addr:postcode":"87124",
    "addr:street":"Riverview Dr Se",
    "iso:country":"US",
    "sg:address":"1000 Riverview Dr SE",
    "sg:city":"Rio Rancho",
    "sg:classifiers":[
        {
            "category":"Health Services",
            "subcategory":"Nursing And Care Facility",
            "type":"Services"
        }
    ],
    "sg:phone":"+1 505 892 8400",
    "sg:postcode":"87124",
    "sg:province":"NM",
    "sg:tags":[
        "intermediate"
    ],
    "wof:name":"Sandia Springs",
    "wof:placetype":"venue"
},
  "geometry": {"coordinates":[-106.645303,35.238603],"type":"Point"}
}