{
  "type": "Feature",
  "properties": {
    "iso:country":"US",
    "sg:address":"2155 Louisiana Blvd NE",
    "sg:city":"Albuquerque",
    "sg:classifiers":[
        {
            "category":"Health Services",
            "subcategory":"Clinic",
            "type":"Services"
        }
    ],
    "sg:phone":"+1 505 298 7771",
    "sg:postcode":"87110",
    "sg:province":"NM",
    "sg:tags":[
        "home"
    ],
    "wof:name":"Maxim Healthcare Svc",
    "wof:placetype":"venue"
},
  "geometry": {"coordinates":[-106.56883500000001,35.101641],"type":"Point"}
}