{
  "type": "Feature",
  "properties": {
    "addr:full":"333 Lagunitas Rd SW Albuquerque NM 87105",
    "addr:housenumber":"333",
    "addr:postcode":"87105",
    "addr:street":"Lagunitas Rd Sw",
    "iso:country":"US",
    "sg:address":"333 Lagunitas Rd SW",
    "sg:city":"Albuquerque",
    "sg:classifiers":[
        {
            "category":"Building & Trades",
            "subcategory":"Construction",
            "type":"Services"
        }
    ],
    "sg:phone":"+1 505 873 4289",
    "sg:postcode":"87105",
    "sg:province":"NM",
    "sg:tags":[
        "house"
    ],
    "wof:name":"Bella Vista Builders Inc",
    "wof:placetype":"venue"
},
  "geometry": {"coordinates":[-106.672359,34.989525],"type":"Point"}
}