{
  "type": "Feature",
  "properties": {
    "iso:country":"US",
    "sg:address":"10508 Chapala Pl NE",
    "sg:city":"Albuquerque",
    "sg:classifiers":[
        {
            "category":"Personal",
            "type":"Services"
        }
    ],
    "sg:phone":"+1 505 293 0477",
    "sg:postcode":"87111",
    "sg:province":"NM",
    "wof:name":"Athletic Touch",
    "wof:placetype":"venue"
},
  "geometry": {"coordinates":[-106.52072699999999,35.122954],"type":"Point"}
}