{
  "type": "Feature",
  "properties": {
    "iso:country":"US",
    "sg:address":"5500 Johnson Ter",
    "sg:city":"Farmington",
    "sg:classifiers":[
        {
            "category":"Wholesale",
            "subcategory":"Sporting Goods",
            "type":"Manufacturing & Wholesale Goods"
        }
    ],
    "sg:phone":"+1 505 327 0993",
    "sg:postcode":"87402",
    "sg:province":"NM",
    "sg:tags":[
        "mfg"
    ],
    "wof:name":"Road Apple Rally Ltd",
    "wof:placetype":"venue"
},
  "geometry": {"coordinates":[-108.139917,36.792428],"type":"Point"}
}