{
  "type": "Feature",
  "properties": {
    "addr:full":"301 Summit Ave Springer NM 87747",
    "addr:housenumber":"301",
    "addr:postcode":"87747",
    "addr:street":"Summit Ave",
    "iso:country":"US",
    "sg:address":"301 Summit Ave",
    "sg:city":"Springer",
    "sg:classifiers":[
        {
            "category":"Organizations",
            "subcategory":"Religious Organization",
            "type":"Services"
        }
    ],
    "sg:phone":"+1 505 483 2254",
    "sg:postcode":"87747",
    "sg:province":"NM",
    "sg:tags":[
        "church"
    ],
    "wof:name":"Immanuel Lutheran Church",
    "wof:placetype":"venue"
},
  "geometry": {"coordinates":[-104.591607,36.361056],"type":"Point"}
}