{
  "type": "Feature",
  "properties": {
    "addr:full":"2003 Southern Blvd SE Rio Rancho NM 87124",
    "addr:housenumber":"2003",
    "addr:postcode":"87124",
    "addr:street":"Southern Blvd Se",
    "iso:country":"US",
    "sg:address":"2003 Southern Blvd SE",
    "sg:city":"Rio Rancho",
    "sg:classifiers":[
        {
            "category":"Organizations",
            "subcategory":"Religious Organization",
            "type":"Services"
        }
    ],
    "sg:phone":"+1 505 792 7999",
    "sg:postcode":"87124",
    "sg:province":"NM",
    "sg:website":"www.mydestinynow.com",
    "wof:name":"Destiny Center",
    "wof:placetype":"venue"
},
  "geometry": {"coordinates":[-106.696832,35.241612],"type":"Point"}
}