{
  "type": "Feature",
  "properties": {
    "iso:country":"US",
    "sg:address":"600 N Union Ave",
    "sg:city":"Roswell",
    "sg:classifiers":[
        {
            "category":"Health Services",
            "subcategory":"Doctor",
            "type":"Services"
        }
    ],
    "sg:phone":"+1 505 624 9801",
    "sg:postcode":"88201",
    "sg:province":"NM",
    "sg:tags":[
        "physician",
        "surgeon"
    ],
    "wof:name":"High Plains Urology Group",
    "wof:placetype":"venue"
},
  "geometry": {"coordinates":[-104.536116,33.398958],"type":"Point"}
}