{
  "type": "Feature",
  "properties": {
    "iso:country":"US",
    "sg:address":"66 Old School Rd",
    "sg:city":"Chamisal",
    "sg:classifiers":[
        {
            "category":"Health Services",
            "subcategory":"Clinic",
            "type":"Services"
        }
    ],
    "sg:phone":"+1 505 587 2685",
    "sg:postcode":"87521",
    "sg:province":"NM",
    "wof:name":"White Crane Clinic",
    "wof:placetype":"venue"
},
  "geometry": {"coordinates":[-105.742645,36.177115],"type":"Point"}
}