{
  "type": "Feature",
  "properties": {
    "iso:country":"US",
    "sg:address":"2109 White Cloud St NE",
    "sg:city":"Albuquerque",
    "sg:classifiers":[
        {
            "category":"Professional",
            "subcategory":"Management & Consulting",
            "type":"Services"
        }
    ],
    "sg:phone":"+1 505 299 1048",
    "sg:postcode":"87112",
    "sg:province":"NM",
    "wof:name":"Human Resources Mgt Consulting",
    "wof:placetype":"venue"
},
  "geometry": {"coordinates":[-106.495529,35.104915],"type":"Point"}
}