{
  "type": "Feature",
  "properties": {
    "iso:country":"US",
    "sg:address":"4205 Stowe Rd NW",
    "sg:city":"Albuquerque",
    "sg:classifiers":[
        {
            "category":"Professional",
            "type":"Services"
        }
    ],
    "sg:phone":"+1 505 890 3057",
    "sg:postcode":"87114",
    "sg:province":"NM",
    "wof:name":"Joseph N Dimarco",
    "wof:placetype":"venue"
},
  "geometry": {"coordinates":[-106.66692,35.214771],"type":"Point"}
}