{
  "type": "Feature",
  "properties": {
    "iso:country":"US",
    "sg:address":"10198 US Hwy 180 W",
    "sg:city":"Silver City",
    "sg:classifiers":[
        {
            "category":"Real Estate",
            "subcategory":"Developer",
            "type":"Services"
        }
    ],
    "sg:phone":"+1 505 535 2463",
    "sg:postcode":"88061",
    "sg:province":"NM",
    "sg:tags":[
        "mobile",
        "home"
    ],
    "wof:name":"Mangas Terrace Mobile Home Prk",
    "wof:placetype":"venue"
},
  "geometry": {"coordinates":[-108.457501,32.779057],"type":"Point"}
}