{
  "type": "Feature",
  "properties": {
    "iso:country":"US",
    "sg:address":"2859 Cerrillos Rd",
    "sg:city":"Santa Fe",
    "sg:classifiers":[
        {
            "category":"Wholesale",
            "subcategory":"Office Equipment",
            "type":"Manufacturing & Wholesale Goods"
        }
    ],
    "sg:phone":"+1 505 473 1196",
    "sg:postcode":"87507",
    "sg:province":"NM",
    "sg:tags":[
        "machine",
        "duplicating",
        "copying"
    ],
    "wof:name":"Advanced Copy Systems",
    "wof:placetype":"venue"
},
  "geometry": {"coordinates":[-105.98801899999999,35.657263],"type":"Point"}
}