{
  "type": "Feature",
  "properties": {
    "addr:full":"1170 N Solano Dr Las Cruces NM 88001",
    "addr:housenumber":"1170",
    "addr:postcode":"88001",
    "addr:street":"N Solano Dr",
    "iso:country":"US",
    "sg:address":"1170 N Solano Dr",
    "sg:city":"Las Cruces",
    "sg:classifiers":[
        {
            "category":"Government",
            "subcategory":"Office",
            "type":"Public Place"
        }
    ],
    "sg:phone":"+1 505 528 5180",
    "sg:postcode":"88001",
    "sg:province":"NM",
    "sg:tags":[
        "administrative",
        "program",
        "health"
    ],
    "wof:name":"Long Term Svc-SW Regional",
    "wof:placetype":"venue"
},
  "geometry": {"coordinates":[-106.771322,32.320134],"type":"Point"}
}