{
  "type": "Feature",
  "properties": {
    "iso:country":"US",
    "sg:address":"11 Sobradora Dr",
    "sg:city":"Santa Fe",
    "sg:classifiers":[
        {
            "category":"Government",
            "subcategory":"Office",
            "type":"Public Place"
        }
    ],
    "sg:phone":"+1 512 426 1980",
    "sg:postcode":"87508",
    "sg:province":"NM",
    "sg:tags":[
        "consulting"
    ],
    "wof:name":"Aventa Group LLC",
    "wof:placetype":"venue"
},
  "geometry": {"coordinates":[-105.99475200000001,35.59401],"type":"Point"}
}