{
  "type": "Feature",
  "properties": {
    "iso:country":"US",
    "sg:address":"2324 N Kingsley Dr",
    "sg:city":"Hobbs",
    "sg:classifiers":[
        {
            "category":"Social Services",
            "subcategory":"Child Care",
            "type":"Services"
        }
    ],
    "sg:phone":"+1 505 392 5940",
    "sg:postcode":"88240",
    "sg:province":"NM",
    "sg:tags":[
        "kindergarten",
        "academic",
        "school"
    ],
    "wof:name":"Jarrett & Jarrett",
    "wof:placetype":"venue"
},
  "geometry": {"coordinates":[-103.14165800000001,32.725808],"type":"Point"}
}