{
  "type": "Feature",
  "properties": {
    "iso:country":"US",
    "sg:address":"3845 Cedarvale Rd",
    "sg:city":"Roswell",
    "sg:classifiers":[
        {
            "category":"Wholesale",
            "subcategory":"Meat",
            "type":"Manufacturing & Wholesale Goods"
        }
    ],
    "sg:phone":"+1 505 622 1214",
    "sg:postcode":"88203",
    "sg:province":"NM",
    "sg:tags":[
        "plant",
        "packing"
    ],
    "wof:name":"Pecos Valley Meat",
    "wof:placetype":"venue"
},
  "geometry": {"coordinates":[-104.42872800000001,33.363065],"type":"Point"}
}