{
  "type": "Feature",
  "properties": {
    "addr:full":"924 E Tucumcari Blvd Tucumcari NM 88401",
    "addr:housenumber":"924",
    "addr:postcode":"88401",
    "addr:street":"E Tucumcari Blvd",
    "iso:country":"US",
    "sg:address":"924 E Tucumcari Blvd",
    "sg:city":"Tucumcari",
    "sg:classifiers":[
        {
            "category":"Shopping",
            "subcategory":"Gifts & Souvenirs",
            "type":"Retail Goods"
        }
    ],
    "sg:phone":"+1 505 461 3773",
    "sg:postcode":"88401",
    "sg:province":"NM",
    "sg:tags":[
        "shop"
    ],
    "wof:name":"Tee Pee",
    "wof:placetype":"venue"
},
  "geometry": {"coordinates":[-103.715619,35.171642],"type":"Point"}
}