{
  "type": "Feature",
  "properties": {
    "addr:full":"17 Tramway Ln NE Albuquerque NM 87122",
    "addr:housenumber":"17",
    "addr:postcode":"87122",
    "addr:street":"Tramway Ln Ne",
    "iso:country":"US",
    "sg:address":"17 Tramway Ln NE",
    "sg:city":"Albuquerque",
    "sg:classifiers":[
        {
            "category":"Building & Trades",
            "subcategory":"Construction",
            "type":"Services"
        }
    ],
    "sg:phone":"+1 505 856 6957",
    "sg:postcode":"87122",
    "sg:province":"NM",
    "sg:tags":[
        "general",
        "contractor"
    ],
    "wof:name":"Meehan Brothers-General Contrs",
    "wof:placetype":"venue"
},
  "geometry": {"coordinates":[-106.493556,35.185535],"type":"Point"}
}