{
  "type": "Feature",
  "properties": {
    "iso:country":"US",
    "sg:address":"310 N Tornillo St",
    "sg:city":"Las Cruces",
    "sg:classifiers":[
        {
            "category":"Social Services",
            "type":"Services"
        }
    ],
    "sg:phone":"+1 505 524 1632",
    "sg:postcode":"88001",
    "sg:province":"NM",
    "sg:tags":[
        "senior",
        "citizen"
    ],
    "wof:name":"Eastside Senior Ctr",
    "wof:placetype":"venue"
},
  "geometry": {"coordinates":[-106.773927,32.31306],"type":"Point"}
}