{
  "type": "Feature",
  "properties": {
    "iso:country":"US",
    "sg:address":"4421 Prospect Ave NE",
    "sg:city":"Albuquerque",
    "sg:classifiers":[
        {
            "category":"Manufacturing",
            "subcategory":"Signs",
            "type":"Manufacturing & Wholesale Goods"
        }
    ],
    "sg:phone":"+1 505 888 5444",
    "sg:postcode":"87110",
    "sg:province":"NM",
    "wof:name":"American Sign Frame Co",
    "wof:placetype":"venue"
},
  "geometry": {"coordinates":[-106.595304,35.107454],"type":"Point"}
}