{
  "type": "Feature",
  "properties": {
    "iso:country":"US",
    "sg:address":"4501 Blake Rd SW",
    "sg:city":"Albuquerque",
    "sg:classifiers":[
        {
            "category":"Real Estate",
            "subcategory":"Real Estate Operator",
            "type":"Services"
        }
    ],
    "sg:phone":"+1 505 877 7997",
    "sg:postcode":"87121",
    "sg:province":"NM",
    "sg:tags":[
        "apartment"
    ],
    "wof:name":"Vista Del Sol",
    "wof:placetype":"venue"
},
  "geometry": {"coordinates":[-106.73091100000001,35.038955],"type":"Point"}
}