{
  "type": "Feature",
  "properties": {
    "iso:country":"US",
    "sg:address":"1532 Pso de Peralta",
    "sg:city":"Santa Fe",
    "sg:classifiers":[
        {
            "category":"Professional",
            "subcategory":"Art Services",
            "type":"Services"
        }
    ],
    "sg:phone":"+1 505 989 8460",
    "sg:postcode":"87501",
    "sg:province":"NM",
    "sg:tags":[
        "commercial",
        "design"
    ],
    "wof:name":"Swell Design Inc",
    "wof:placetype":"venue"
},
  "geometry": {"coordinates":[-105.94771799999999,35.681876],"type":"Point"}
}