{
  "type": "Feature",
  "properties": {
    "iso:country":"US",
    "sg:address":"4137 Foxwood Trl SE",
    "sg:city":"Rio Rancho",
    "sg:classifiers":[
        {
            "category":"Professional",
            "subcategory":"Accounting & Tax Preparation",
            "type":"Services"
        }
    ],
    "sg:phone":"+1 505 891 9596",
    "sg:postcode":"87124",
    "sg:province":"NM",
    "sg:tags":[
        "accountant"
    ],
    "wof:name":"Brenda Gnerich CPA",
    "wof:placetype":"venue"
},
  "geometry": {"coordinates":[-106.657493,35.252325],"type":"Point"}
}