{
  "type": "Feature",
  "properties": {
    "iso:country":"US",
    "sg:address":"613 Amherst Dr NE",
    "sg:city":"Albuquerque",
    "sg:classifiers":[
        {
            "category":"Social Services",
            "subcategory":"Child Care",
            "type":"Services"
        }
    ],
    "sg:phone":"+1 505 255 7340",
    "sg:postcode":"87106",
    "sg:province":"NM",
    "wof:name":"Sweetheart Nursery & Kndrgrtn",
    "wof:placetype":"venue"
},
  "geometry": {"coordinates":[-106.605563,35.087368],"type":"Point"}
}