{
  "type": "Feature",
  "properties": {
    "iso:country":"US",
    "sg:address":"400 Bell Ave",
    "sg:city":"Mesilla Park",
    "sg:classifiers":[
        {
            "category":"Education",
            "subcategory":"School",
            "type":"Public Place"
        }
    ],
    "sg:phone":"+1 505 527 6059",
    "sg:postcode":"88001",
    "sg:province":"NM",
    "wof:name":"Mesilla Valley Training Center",
    "wof:placetype":"venue"
},
  "geometry": {"coordinates":[-106.76647199999999,32.276014],"type":"Point"}
}