{
  "type": "Feature",
  "properties": {
    "iso:country":"US",
    "sg:address":"2 Rd 3499",
    "sg:city":"Flora Vista",
    "sg:classifiers":[
        {
            "category":"Insurance",
            "subcategory":"Insurance Agent",
            "type":"Services"
        }
    ],
    "sg:phone":"+1 505 334 9900",
    "sg:postcode":"87415",
    "sg:province":"NM",
    "wof:name":"Hallock Insurance",
    "wof:placetype":"venue"
},
  "geometry": {"coordinates":[-108.084622,36.807939],"type":"Point"}
}