{
  "type": "Feature",
  "properties": {
    "iso:country":"US",
    "sg:address":"6208 Montgomery Blvd NE Ste D",
    "sg:city":"Albuquerque",
    "sg:classifiers":[
        {
            "category":"Health Services",
            "subcategory":"Doctor",
            "type":"Services"
        },
        {
            "category":"Health Services",
            "subcategory":"Dentist",
            "type":"Services"
        }
    ],
    "sg:phone":"+1 505 830 9081",
    "sg:postcode":"87109",
    "sg:province":"NM",
    "sg:tags":[
        "dentists-oral",
        "physician",
        "maxillofacial",
        "surgeons",
        "surgery",
        "oral"
    ],
    "wof:name":"Lynch Thomas J",
    "wof:placetype":"venue"
},
  "geometry": {"coordinates":[-106.577409,35.130779],"type":"Point"}
}