{
  "type": "Feature",
  "properties": {
    "iso:country":"US",
    "sg:address":"125 Kit Carson Rd",
    "sg:city":"Taos",
    "sg:classifiers":[
        {
            "category":"Home & Garden",
            "subcategory":"Home Furnishings",
            "type":"Retail Goods"
        }
    ],
    "sg:phone":"+1 505 758 3195",
    "sg:postcode":"87571",
    "sg:province":"NM",
    "sg:tags":[
        "pottery"
    ],
    "wof:name":"Market Contemporary Crafts",
    "wof:placetype":"venue"
},
  "geometry": {"coordinates":[-105.572872,36.407163],"type":"Point"}
}