{
  "type": "Feature",
  "properties": {
    "addr:full":"901 Rio Grande Blvd NW Albuquerque NM 87104",
    "addr:housenumber":"901",
    "addr:postcode":"87104",
    "addr:street":"Rio Grande Blvd Nw",
    "iso:country":"US",
    "sg:address":"901 Rio Grande Blvd NW",
    "sg:city":"Albuquerque",
    "sg:classifiers":[
        {
            "category":"Shopping",
            "subcategory":"Clothing, Apparel, & Fashions",
            "type":"Retail Goods"
        }
    ],
    "sg:phone":"+1 505 766 9393",
    "sg:postcode":"87104",
    "sg:province":"NM",
    "sg:tags":[
        "s"
    ],
    "wof:name":"Exclusively Yours Boutique",
    "wof:placetype":"venue"
},
  "geometry": {"coordinates":[-106.670748,35.103508],"type":"Point"}
}