{
  "type": "Feature",
  "properties": {
    "iso:country":"US",
    "sg:address":"14520 Encantado Rd NE",
    "sg:city":"Albuquerque",
    "sg:classifiers":[
        {
            "category":"Real Estate",
            "subcategory":"Real Estate Agent",
            "type":"Services"
        }
    ],
    "sg:phone":"+1 505 292 1245",
    "sg:postcode":"87123",
    "sg:province":"NM",
    "sg:tags":[
        "appraiser"
    ],
    "wof:name":"Residential Appraisals Inc",
    "wof:placetype":"venue"
},
  "geometry": {"coordinates":[-106.48636999999999,35.075037],"type":"Point"}
}