{
  "type": "Feature",
  "properties": {
    "iso:country":"US",
    "sg:address":"613 Mesilla St SE",
    "sg:city":"Albuquerque",
    "sg:classifiers":[
        {
            "category":"Real Estate",
            "subcategory":"Real Estate Operator",
            "type":"Services"
        }
    ],
    "sg:phone":"+1 505 265 4265",
    "sg:postcode":"87108",
    "sg:province":"NM",
    "sg:tags":[
        "building",
        "apartment"
    ],
    "wof:name":"Casa Mesilla Apartments",
    "wof:placetype":"venue"
},
  "geometry": {"coordinates":[-106.565505,35.067432],"type":"Point"}
}