{
  "type": "Feature",
  "properties": {
    "addr:full":"80 Jemez St Jemez Springs NM 87035",
    "addr:housenumber":"80",
    "addr:postcode":"87035",
    "addr:street":"Jemez St",
    "iso:country":"US",
    "sg:address":"80 Jemez St",
    "sg:city":"Jemez Springs",
    "sg:classifiers":[
        {
            "category":"Government",
            "subcategory":"Court House",
            "type":"Public Place"
        }
    ],
    "sg:phone":"+1 505 829 3858",
    "sg:postcode":"87035",
    "sg:province":"NM",
    "sg:tags":[
        "city"
    ],
    "wof:name":"Jemez Springs Municipal Court",
    "wof:placetype":"venue"
},
  "geometry": {"coordinates":[-106.068527,35.028539],"type":"Point"}
}