{
  "type": "Feature",
  "properties": {
    "iso:country":"US",
    "sg:address":"3520 Cam Jalisco",
    "sg:city":"Santa Fe",
    "sg:classifiers":[
        {
            "category":"Social Services",
            "subcategory":"Adult Care",
            "type":"Services"
        },
        {
            "category":"Professional",
            "type":"Services"
        }
    ],
    "sg:phone":"+1 505 438 2666",
    "sg:postcode":"87507",
    "sg:province":"NM",
    "sg:tags":[
        "residential",
        "establishment"
    ],
    "wof:name":"Casa De Su Vida",
    "wof:placetype":"venue"
},
  "geometry": {"coordinates":[-106.00416300000001,35.632554],"type":"Point"}
}