{
  "type": "Feature",
  "properties": {
    "iso:country":"US",
    "sg:address":"125 E Palace Ave",
    "sg:city":"Santa Fe",
    "sg:classifiers":[
        {
            "category":"Banks & Credit Unions",
            "subcategory":"Bank",
            "type":"Services"
        }
    ],
    "sg:phone":"+1 505 983 1206",
    "sg:postcode":"87501",
    "sg:province":"NM",
    "sg:tags":[
        "loan",
        "real estate"
    ],
    "sg:website":"www.regal-mortgage.com",
    "wof:name":"REGAL-Mortgage.Com",
    "wof:placetype":"venue"
},
  "geometry": {"coordinates":[-105.937456,35.687593],"type":"Point"}
}