{
  "type": "Feature",
  "properties": {
    "iso:country":"US",
    "sg:address":"2428 San Mateo Pl NE",
    "sg:city":"Albuquerque",
    "sg:classifiers":[
        {
            "category":"Manufacturing",
            "subcategory":"Printing",
            "type":"Manufacturing & Wholesale Goods"
        }
    ],
    "sg:phone":"+1 505 830 1500",
    "sg:postcode":"87110",
    "sg:province":"NM",
    "sg:tags":[
        "commercial"
    ],
    "wof:name":"G S I",
    "wof:placetype":"venue"
},
  "geometry": {"coordinates":[-106.586331,35.106409],"type":"Point"}
}