{
  "type": "Feature",
  "properties": {
    "iso:country":"US",
    "sg:address":"845 el Paseo Rd",
    "sg:city":"Las Cruces",
    "sg:classifiers":[
        {
            "category":"Home & Garden",
            "subcategory":"Building Materials",
            "type":"Retail Goods"
        }
    ],
    "sg:phone":"+1 505 527 1055",
    "sg:postcode":"88001",
    "sg:province":"NM",
    "sg:website":"www.sutherlands.com",
    "wof:name":"Sutherlands Lumber Co",
    "wof:placetype":"venue"
},
  "geometry": {"coordinates":[-106.775802,32.301324],"type":"Point"}
}