{
  "type": "Feature",
  "properties": {
    "iso:country":"US",
    "sg:address":"86 Verano Loop",
    "sg:city":"Santa Fe",
    "sg:classifiers":[
        {
            "category":"Education",
            "subcategory":"Special Training",
            "type":"Public Place"
        }
    ],
    "sg:phone":"+1 505 466 1497",
    "sg:postcode":"87508",
    "sg:province":"NM",
    "wof:name":"Educational Services Intl",
    "wof:placetype":"venue"
},
  "geometry": {"coordinates":[-105.92407799999999,35.548085],"type":"Point"}
}