{
  "type": "Feature",
  "properties": {
    "iso:country":"US",
    "sg:address":"517 US Hwy 60",
    "sg:city":"Socorro",
    "sg:classifiers":[
        {
            "category":"Organizations",
            "subcategory":"Community Association",
            "type":"Services"
        }
    ],
    "sg:phone":"+1 505 835 1852",
    "sg:postcode":"87801",
    "sg:province":"NM",
    "sg:tags":[
        "fraternal"
    ],
    "wof:name":"Knights Of Columbus",
    "wof:placetype":"venue"
},
  "geometry": {"coordinates":[-106.891366,34.053034],"type":"Point"}
}