{
  "type": "Feature",
  "properties": {
    "iso:country":"US",
    "sg:address":"6417 Lomas Blvd NE",
    "sg:city":"Albuquerque",
    "sg:classifiers":[
        {
            "category":"Home & Garden",
            "subcategory":"Building Materials",
            "type":"Retail Goods"
        }
    ],
    "sg:phone":"+1 505 262 1775",
    "sg:postcode":"87110",
    "sg:province":"NM",
    "sg:tags":[
        "wall",
        "paint",
        "covering"
    ],
    "wof:name":"Custom Paint Center Inc",
    "wof:placetype":"venue"
},
  "geometry": {"coordinates":[-106.575306,35.087389],"type":"Point"}
}