{
  "type": "Feature",
  "properties": {
    "iso:country":"US",
    "sg:address":"400 Tharp Ave",
    "sg:city":"Clovis",
    "sg:classifiers":[
        {
            "category":"Wholesale",
            "subcategory":"Construction Materials",
            "type":"Manufacturing & Wholesale Goods"
        }
    ],
    "sg:phone":"+1 505 762 9852",
    "sg:postcode":"88101",
    "sg:province":"NM",
    "sg:tags":[
        "sand",
        "gravel"
    ],
    "wof:name":"Sam Sanders Materials Inc",
    "wof:placetype":"venue"
},
  "geometry": {"coordinates":[-103.236707,34.403667],"type":"Point"}
}