{
  "type": "Feature",
  "properties": {
    "iso:country":"US",
    "sg:address":"4229 Packaway Rd NW",
    "sg:city":"Albuquerque",
    "sg:classifiers":[
        {
            "category":"Banks & Credit Unions",
            "subcategory":"Investment Brokerage",
            "type":"Services"
        }
    ],
    "sg:phone":"+1 505 228 2052",
    "sg:postcode":"87114",
    "sg:province":"NM",
    "sg:tags":[
        "advisory",
        "financial"
    ],
    "wof:name":"Marathon Financial Svc",
    "wof:placetype":"venue"
},
  "geometry": {"coordinates":[-106.667866,35.204517],"type":"Point"}
}