{
  "type": "Feature",
  "properties": {
    "iso:country":"US",
    "sg:address":"219 State Hwy 314 NW",
    "sg:city":"Los Lunas",
    "sg:classifiers":[
        {
            "category":"Real Estate",
            "subcategory":"Real Estate Agent",
            "type":"Services"
        }
    ],
    "sg:phone":"+1 505 565 8888",
    "sg:postcode":"87031",
    "sg:province":"NM",
    "wof:name":"Hightech Realty",
    "wof:placetype":"venue"
},
  "geometry": {"coordinates":[-106.735869,34.807595],"type":"Point"}
}