{
  "type": "Feature",
  "properties": {
    "iso:country":"US",
    "sg:address":"562 Atrisco Dr SW",
    "sg:city":"Albuquerque",
    "sg:classifiers":[
        {
            "category":"Government",
            "subcategory":"Office",
            "type":"Public Place"
        }
    ],
    "sg:phone":"+1 505 843 7695",
    "sg:postcode":"87105",
    "sg:province":"NM",
    "sg:tags":[
        "village"
    ],
    "wof:name":"Senior Citizen Meal Sites",
    "wof:placetype":"venue"
},
  "geometry": {"coordinates":[-106.687258,35.075407],"type":"Point"}
}