{
  "type": "Feature",
  "properties": {
    "iso:country":"US",
    "sg:address":"111 Coors Blvd NW Ste C13",
    "sg:city":"Albuquerque",
    "sg:classifiers":[
        {
            "category":"Personal",
            "subcategory":"Nail Salon",
            "type":"Services"
        }
    ],
    "sg:phone":"+1 505 833 5140",
    "sg:postcode":"87121",
    "sg:province":"NM",
    "wof:name":"Beauty Nails",
    "wof:placetype":"venue"
},
  "geometry": {"coordinates":[-106.710732,35.080477],"type":"Point"}
}