{
  "type": "Feature",
  "properties": {
    "iso:country":"US",
    "sg:address":"823 W Railroad Blvd",
    "sg:city":"Deming",
    "sg:classifiers":[
        {
            "category":"Manufacturing",
            "subcategory":"Glass & Minerals",
            "type":"Manufacturing & Wholesale Goods"
        }
    ],
    "sg:phone":"+1 505 546 2647",
    "sg:postcode":"88030",
    "sg:province":"NM",
    "sg:tags":[
        "ready",
        "concrete",
        "mfg"
    ],
    "wof:name":"Southwest Concrete and Paving",
    "wof:placetype":"venue"
},
  "geometry": {"coordinates":[-107.767877,32.269325],"type":"Point"}
}