{
  "type": "Feature",
  "properties": {
    "addr:full":"6 Ruta Sin Nombre Santa Fe NM 87507",
    "addr:housenumber":"6",
    "addr:postcode":"87507",
    "addr:street":"Ruta Sin Nombre",
    "iso:country":"US",
    "sg:address":"6 Ruta Sin Nombre",
    "sg:city":"Santa Fe",
    "sg:classifiers":[
        {
            "category":"Real Estate",
            "subcategory":"Real Estate Agent",
            "type":"Services"
        }
    ],
    "sg:phone":"+1 505 982 2877",
    "sg:postcode":"87507",
    "sg:province":"NM",
    "sg:tags":[
        "consultant"
    ],
    "wof:name":"Gallegos Agency",
    "wof:placetype":"venue"
},
  "geometry": {"coordinates":[-105.986287,35.688603],"type":"Point"}
}