{
  "type": "Feature",
  "properties": {
    "addr:full":"3204 Richards Ln Santa Fe NM 87507",
    "addr:housenumber":"3204",
    "addr:postcode":"87507",
    "addr:street":"Richards Ln",
    "iso:country":"US",
    "sg:address":"3204 Richards Ln",
    "sg:city":"Santa Fe",
    "sg:classifiers":[
        {
            "category":"Professional",
            "subcategory":"Engineering",
            "type":"Services"
        }
    ],
    "sg:phone":"+1 505 471 1101",
    "sg:postcode":"87507",
    "sg:province":"NM",
    "sg:tags":[
        "consultant"
    ],
    "wof:name":"Geo-Test Inc",
    "wof:placetype":"venue"
},
  "geometry": {"coordinates":[-105.999075,35.657179],"type":"Point"}
}