{
  "type": "Feature",
  "properties": {
    "addr:full":"3901 Indian School Rd NE Albuquerque NM 87110",
    "addr:housenumber":"3901",
    "addr:postcode":"87110",
    "addr:street":"Indian School Rd Ne",
    "iso:country":"US",
    "sg:address":"3901 Indian School Rd NE",
    "sg:city":"Albuquerque",
    "sg:classifiers":[
        {
            "category":"Real Estate",
            "subcategory":"Real Estate Operator",
            "type":"Services"
        }
    ],
    "sg:phone":"+1 505 262 1759",
    "sg:postcode":"87110",
    "sg:province":"NM",
    "sg:tags":[
        "building",
        "apartment"
    ],
    "wof:name":"Summit Apts",
    "wof:placetype":"venue"
},
  "geometry": {"coordinates":[-106.600292,35.101993],"type":"Point"}
}