{
  "type": "Feature",
  "properties": {
    "addr:full":"10601 Lomas Blvd NE Albuquerque NM 87112",
    "addr:housenumber":"10601",
    "addr:postcode":"87112",
    "addr:street":"Lomas Blvd Ne",
    "iso:country":"US",
    "sg:address":"10601 Lomas Blvd NE",
    "sg:city":"Albuquerque",
    "sg:classifiers":[
        {
            "category":"Professional",
            "subcategory":"Computer Services",
            "type":"Services"
        }
    ],
    "sg:phone":"+1 505 883 1113",
    "sg:postcode":"87112",
    "sg:province":"NM",
    "sg:tags":[
        "prepackaged",
        "software"
    ],
    "wof:name":"Professional Computer Services",
    "wof:placetype":"venue"
},
  "geometry": {"coordinates":[-106.528374,35.0871],"type":"Point"}
}