{
  "type": "Feature",
  "properties": {
    "iso:country":"US",
    "sg:address":"520 E 1st St",
    "sg:city":"Clovis",
    "sg:classifiers":[
        {
            "category":"Autos & Motor Vehicles",
            "subcategory":"Auto Supplies",
            "type":"Retail Goods"
        }
    ],
    "sg:phone":"+1 505 769 2871",
    "sg:postcode":"88101",
    "sg:province":"NM",
    "sg:tags":[
        "repair",
        "tire"
    ],
    "wof:name":"Big O Tires",
    "wof:placetype":"venue"
},
  "geometry": {"coordinates":[-103.199989,34.398731],"type":"Point"}
}