{
  "type": "Feature",
  "properties": {
    "addr:full":"421 Delgado Ln Santa Fe NM 87505",
    "addr:housenumber":"421",
    "addr:postcode":"87505",
    "addr:street":"Delgado Ln",
    "iso:country":"US",
    "sg:address":"421 Delgado Ln",
    "sg:city":"Santa Fe",
    "sg:classifiers":[
        {
            "category":"Professional",
            "subcategory":"Management & Consulting",
            "type":"Services"
        }
    ],
    "sg:phone":"+1 505 955 0681",
    "sg:postcode":"87505",
    "sg:province":"NM",
    "wof:name":"Maio and Company Inc",
    "wof:placetype":"venue"
},
  "geometry": {"coordinates":[-105.93201999999999,35.679356],"type":"Point"}
}