{
  "type": "Feature",
  "properties": {
    "addr:full":"223 Wyoming Blvd NE Albuquerque NM 87123",
    "addr:housenumber":"223",
    "addr:postcode":"87123",
    "addr:street":"Ne",
    "iso:country":"US",
    "sg:address":"223 Wyoming Blvd NE",
    "sg:city":"Albuquerque",
    "sg:classifiers":[
        {
            "category":"Autos & Motor Vehicles",
            "subcategory":"Automobile Sales",
            "type":"Retail Goods"
        }
    ],
    "sg:phone":"+1 505 265 6652",
    "sg:postcode":"87123",
    "sg:province":"NM",
    "sg:tags":[
        "used"
    ],
    "wof:name":"Wyoming Motors",
    "wof:placetype":"venue"
},
  "geometry": {"coordinates":[-106.55045699999999,35.077765],"type":"Point"}
}