{
  "type": "Feature",
  "properties": {
    "addr:full":"7517 Tammaron Pl NE Albuquerque NM 87109",
    "addr:housenumber":"7517",
    "addr:postcode":"87109",
    "addr:street":"Tammaron Pl Ne",
    "iso:country":"US",
    "sg:address":"7517 Tammaron Pl NE",
    "sg:city":"Albuquerque",
    "sg:classifiers":[
        {
            "category":"Shopping",
            "subcategory":"Catalog Store",
            "type":"Retail Goods"
        }
    ],
    "sg:phone":"+1 505 235 6464",
    "sg:postcode":"87109",
    "sg:province":"NM",
    "sg:tags":[
        "mail",
        "order"
    ],
    "wof:name":"Aztec Industries",
    "wof:placetype":"venue"
},
  "geometry": {"coordinates":[-106.560832,35.151001],"type":"Point"}
}