{
  "type": "Feature",
  "properties": {
    "addr:full":"2302 W Pierce St Carlsbad NM 88220",
    "addr:housenumber":"2302",
    "addr:postcode":"88220",
    "addr:street":"W Pierce St",
    "iso:country":"US",
    "sg:address":"2302 W Pierce St",
    "sg:city":"Carlsbad",
    "sg:classifiers":[
        {
            "category":"Personal",
            "subcategory":"Beauty Salon",
            "type":"Services"
        }
    ],
    "sg:phone":"+1 505 885 1823",
    "sg:postcode":"88220",
    "sg:province":"NM",
    "sg:tags":[
        "manicuring"
    ],
    "wof:name":"LA Nails",
    "wof:placetype":"venue"
},
  "geometry": {"coordinates":[-104.25411800000001,32.438848],"type":"Point"}
}