{
  "type": "Feature",
  "properties": {
    "addr:full":"19 W Ave D Lovington NM 88260",
    "addr:housenumber":"19",
    "addr:postcode":"88260",
    "addr:street":"W Ave D",
    "iso:country":"US",
    "sg:address":"19 W Ave D",
    "sg:city":"Lovington",
    "sg:classifiers":[
        {
            "category":"Shopping",
            "subcategory":"Music",
            "type":"Retail Goods"
        }
    ],
    "sg:phone":"+1 505 396 1425",
    "sg:postcode":"88260",
    "sg:province":"NM",
    "sg:tags":[
        "video",
        "disc",
        "tape",
        "cassette"
    ],
    "sg:website":"www.moviegallery.com",
    "wof:name":"Movie Gallery",
    "wof:placetype":"venue"
},
  "geometry": {"coordinates":[-103.349281,32.943906],"type":"Point"}
}