{
  "type": "Feature",
  "properties": {
    "iso:country":"US",
    "sg:address":"3311 Columbia Dr NE",
    "sg:city":"Albuquerque",
    "sg:classifiers":[
        {
            "category":"Building & Trades",
            "subcategory":"Construction",
            "type":"Services"
        }
    ],
    "sg:phone":"+1 505 881 7651",
    "sg:postcode":"87107",
    "sg:province":"NM",
    "sg:tags":[
        "excavation",
        "contractor"
    ],
    "wof:name":"J & D Excavation Inc",
    "wof:placetype":"venue"
},
  "geometry": {"coordinates":[-106.621797,35.118872],"type":"Point"}
}