{
  "type": "Feature",
  "properties": {
    "addr:full":"6001 Lomas Blvd NE Albuquerque NM 87110",
    "addr:housenumber":"6001",
    "addr:postcode":"87110",
    "addr:street":"Lomas Blvd Ne",
    "iso:country":"US",
    "sg:address":"6001 Lomas Blvd NE",
    "sg:city":"Albuquerque",
    "sg:classifiers":[
        {
            "category":"Personal",
            "subcategory":"Beauty Salon",
            "type":"Services"
        }
    ],
    "sg:phone":"+1 505 260 0646",
    "sg:postcode":"87110",
    "sg:province":"NM",
    "sg:tags":[
        "manicuring"
    ],
    "wof:name":"Top Nails",
    "wof:placetype":"venue"
},
  "geometry": {"coordinates":[-106.579195,35.087332],"type":"Point"}
}