{
  "type": "Feature",
  "properties": {
    "addr:full":"502 Carmony Rd NE Albuquerque NM 87107",
    "addr:housenumber":"502",
    "addr:postcode":"87107",
    "addr:street":"Carmony Rd Ne",
    "iso:country":"US",
    "sg:address":"502 Carmony Rd NE",
    "sg:city":"Albuquerque",
    "sg:classifiers":[
        {
            "category":"Retail",
            "subcategory":"Repair Shop",
            "type":"Services"
        },
        {
            "category":"Utilities",
            "subcategory":"Refuse",
            "type":"Services"
        }
    ],
    "sg:phone":"+1 505 344 0177",
    "sg:postcode":"87107",
    "sg:province":"NM",
    "sg:tags":[
        "liquid",
        "waste",
        "trap",
        "grease",
        "removal"
    ],
    "wof:name":"American Waste Removal Inc",
    "wof:placetype":"venue"
},
  "geometry": {"coordinates":[-106.627707,35.12869],"type":"Point"}
}