{
  "type": "Feature",
  "properties": {
    "iso:country":"US",
    "sg:address":"4000 Southern Blvd SE",
    "sg:city":"Rio Rancho",
    "sg:classifiers":[
        {
            "category":"Real Estate",
            "subcategory":"Real Estate Agent",
            "type":"Services"
        }
    ],
    "sg:phone":"+1 505 892 1000",
    "sg:postcode":"87124",
    "sg:province":"NM",
    "sg:website":"www.cblegacynm.com",
    "wof:name":"Coldwell Banker",
    "wof:placetype":"venue"
},
  "geometry": {"coordinates":[-106.656363,35.241274],"type":"Point"}
}