{
  "type": "Feature",
  "properties": {
    "iso:country":"US",
    "sg:address":"1505 Cornell Dr NE",
    "sg:city":"Albuquerque",
    "sg:classifiers":[
        {
            "category":"Professional",
            "subcategory":"Lawyer & Legal Services",
            "type":"Services"
        }
    ],
    "sg:phone":"+1 505 277 4737",
    "sg:postcode":"87106",
    "sg:province":"NM",
    "wof:name":"Hart Frdrick M Attrney At Law",
    "wof:placetype":"venue"
},
  "geometry": {"coordinates":[-106.620034,35.100682],"type":"Point"}
}