{
  "type": "Feature",
  "properties": {
    "addr:full":"1911 N Freeman Ave Artesia NM 88210",
    "addr:housenumber":"1911",
    "addr:postcode":"88210",
    "addr:street":"N Freeman Ave",
    "iso:country":"US",
    "sg:address":"1911 N Freeman Ave",
    "sg:city":"Artesia",
    "sg:classifiers":[
        {
            "category":"Organizations",
            "subcategory":"Religious Organization",
            "type":"Services"
        }
    ],
    "sg:phone":"+1 505 746 4446",
    "sg:postcode":"88210",
    "sg:province":"NM",
    "sg:tags":[
        "church"
    ],
    "wof:name":"Victory Life Fellowship",
    "wof:placetype":"venue"
},
  "geometry": {"coordinates":[-104.39550800000001,32.861981],"type":"Point"}
}