{
  "type": "Feature",
  "properties": {
    "iso:country":"US",
    "sg:address":"1818 Coal Pl SE",
    "sg:city":"Albuquerque",
    "sg:classifiers":[
        {
            "category":"Organizations",
            "subcategory":"Religious Organization",
            "type":"Services"
        }
    ],
    "sg:phone":"+1 505 242 2251",
    "sg:postcode":"87106",
    "sg:province":"NM",
    "wof:name":"Blessed Sacrament Fathers",
    "wof:placetype":"venue"
},
  "geometry": {"coordinates":[-106.626492,35.077215],"type":"Point"}
}