{
  "type": "Feature",
  "properties": {
    "addr:full":"1554 Cam Amado Santa Fe NM 87505",
    "addr:housenumber":"1554",
    "addr:postcode":"87505",
    "addr:street":"Cam Amado",
    "iso:country":"US",
    "sg:address":"1554 Cam Amado",
    "sg:city":"Santa Fe",
    "sg:classifiers":[
        {
            "category":"Professional",
            "subcategory":"Accounting & Tax Preparation",
            "type":"Services"
        }
    ],
    "sg:phone":"+1 505 986 8608",
    "sg:postcode":"87505",
    "sg:province":"NM",
    "wof:name":"Jeanne Milholand PC",
    "wof:placetype":"venue"
},
  "geometry": {"coordinates":[-105.94346299999999,35.660562],"type":"Point"}
}