{
  "type": "Feature",
  "properties": {
    "iso:country":"US",
    "sg:address":"6913 Natalie Ave NE",
    "sg:city":"Albuquerque",
    "sg:classifiers":[
        {
            "category":"Education",
            "subcategory":"Dance Studio",
            "type":"Public Place"
        }
    ],
    "sg:phone":"+1 505 888 1054",
    "sg:postcode":"87110",
    "sg:province":"NM",
    "sg:website":"www.btnm.org",
    "wof:name":"Ballet Theater Of New Mexico",
    "wof:placetype":"venue"
},
  "geometry": {"coordinates":[-106.568895,35.128984],"type":"Point"}
}