{
  "type": "Feature",
  "properties": {
    "addr:full":"8404 Central Ave SE Albuquerque NM 87108",
    "addr:housenumber":"8404",
    "addr:postcode":"87108",
    "addr:street":"Central Ave Se",
    "iso:country":"US",
    "sg:address":"8404 Central Ave SE",
    "sg:city":"Albuquerque",
    "sg:classifiers":[
        {
            "category":"Home & Garden",
            "subcategory":"Building Materials",
            "type":"Retail Goods"
        }
    ],
    "sg:phone":"+1 505 232 2352",
    "sg:postcode":"87108",
    "sg:province":"NM",
    "wof:name":"Riveras Catering Truck 84",
    "wof:placetype":"venue"
},
  "geometry": {"coordinates":[-106.552739,35.074036],"type":"Point"}
}