{
  "type": "Feature",
  "properties": {
    "iso:country":"US",
    "sg:address":"4216 Roadrunner Ln",
    "sg:city":"Santa Fe",
    "sg:classifiers":[
        {
            "category":"Freight",
            "type":"Transportation"
        }
    ],
    "sg:phone":"+1 505 438 1819",
    "sg:postcode":"87507",
    "sg:province":"NM",
    "sg:tags":[
        "delivery"
    ],
    "wof:name":"Rio Grande Deliveries Inc",
    "wof:placetype":"venue"
},
  "geometry": {"coordinates":[-106.061735,35.629234],"type":"Point"}
}