{
  "type": "Feature",
  "properties": {
    "iso:country":"US",
    "sg:address":"16 Schmittle Rd",
    "sg:city":"Socorro",
    "sg:classifiers":[
        {
            "category":"Building & Trades",
            "subcategory":"Construction",
            "type":"Services"
        }
    ],
    "sg:phone":"+1 505 835 2551",
    "sg:postcode":"87823",
    "sg:province":"NM",
    "sg:tags":[
        "general",
        "contractor"
    ],
    "wof:name":"Lar Co Construction",
    "wof:placetype":"venue"
},
  "geometry": {"coordinates":[-106.902709,34.136538],"type":"Point"}
}