{
  "type": "Feature",
  "properties": {
    "addr:full":"10 Bataan Blvd Santa Fe NM 87508",
    "addr:housenumber":"10",
    "addr:postcode":"87508",
    "addr:street":"Bataan Blvd",
    "iso:country":"US",
    "sg:address":"10 Bataan Blvd",
    "sg:city":"Santa Fe",
    "sg:classifiers":[
        {
            "category":"Government",
            "subcategory":"Office",
            "type":"Public Place"
        }
    ],
    "sg:phone":"+1 505 474 1880",
    "sg:postcode":"87508",
    "sg:province":"NM",
    "sg:tags":[
        "national",
        "security"
    ],
    "wof:name":"Directorate of Eng/Nmarng",
    "wof:placetype":"venue"
},
  "geometry": {"coordinates":[-106.088488,35.570916],"type":"Point"}
}