{
  "type": "Feature",
  "properties": {
    "iso:country":"US",
    "sg:address":"1425 el Camino Real St",
    "sg:city":"Socorro",
    "sg:classifiers":[
        {
            "category":"Freight",
            "type":"Transportation"
        }
    ],
    "sg:phone":"+1 505 835 0333",
    "sg:postcode":"87801",
    "sg:province":"NM",
    "wof:name":"Public Schools Transportation",
    "wof:placetype":"venue"
},
  "geometry": {"coordinates":[-106.899021,34.081086],"type":"Point"}
}