{
  "type": "Feature",
  "properties": {
    "addr:full":"309 Central Ave Carrizozo NM 88301",
    "addr:housenumber":"309",
    "addr:postcode":"88301",
    "addr:street":"Central Ave",
    "iso:country":"US",
    "sg:address":"309 Central Ave",
    "sg:city":"Carrizozo",
    "sg:classifiers":[
        {
            "category":"Manufacturing",
            "subcategory":"Printing",
            "type":"Manufacturing & Wholesale Goods"
        }
    ],
    "sg:phone":"+1 505 648 2333",
    "sg:postcode":"88301",
    "sg:province":"NM",
    "sg:tags":[
        "newspaper"
    ],
    "wof:name":"Lincoln County News",
    "wof:placetype":"venue"
},
  "geometry": {"coordinates":[-105.874573,33.643929],"type":"Point"}
}