{
  "type": "Feature",
  "properties": {
    "iso:country":"US",
    "sg:address":"306 S Main St",
    "sg:city":"Elida",
    "sg:classifiers":[
        {
            "category":"Organizations",
            "subcategory":"Religious Organization",
            "type":"Services"
        }
    ],
    "sg:phone":"+1 505 274 6371",
    "sg:postcode":"88116",
    "sg:province":"NM",
    "sg:tags":[
        "church"
    ],
    "wof:name":"First Baptist Church-Elida",
    "wof:placetype":"venue"
},
  "geometry": {"coordinates":[-103.65688900000001,33.944734],"type":"Point"}
}