{
  "type": "Feature",
  "properties": {
    "iso:country":"US",
    "sg:address":"4506 Broadway Blvd SE",
    "sg:city":"Albuquerque",
    "sg:classifiers":[
        {
            "category":"Building & Trades",
            "subcategory":"Plumbing",
            "type":"Services"
        }
    ],
    "sg:phone":"+1 505 873 4898",
    "sg:postcode":"87105",
    "sg:province":"NM",
    "sg:tags":[
        "fire",
        "system",
        "automatic",
        "sprinkler",
        "contractor"
    ],
    "wof:name":"Rio Grande Fire Prtctn Systms",
    "wof:placetype":"venue"
},
  "geometry": {"coordinates":[-106.649944,35.007862],"type":"Point"}
}