{
  "type": "Feature",
  "properties": {
    "iso:country":"US",
    "sg:address":"904 Pso de la Cuma",
    "sg:city":"Santa Fe",
    "sg:classifiers":[
        {
            "category":"Professional",
            "subcategory":"Business Services",
            "type":"Services"
        }
    ],
    "sg:phone":"+1 505 982 6826",
    "sg:postcode":"87501",
    "sg:province":"NM",
    "wof:name":"Slb Systems Inc",
    "wof:placetype":"venue"
},
  "geometry": {"coordinates":[-105.93833600000001,35.701957],"type":"Point"}
}