{
  "type": "Feature",
  "properties": {
    "iso:country":"US",
    "sg:address":"333 E Main St",
    "sg:city":"Farmington",
    "sg:classifiers":[
        {
            "category":"Social Services",
            "type":"Services"
        }
    ],
    "sg:phone":"+1 505 327 0505",
    "sg:postcode":"87401",
    "sg:province":"NM",
    "wof:name":"Andreas Novak Lisw",
    "wof:placetype":"venue"
},
  "geometry": {"coordinates":[-108.202235,36.729023],"type":"Point"}
}