{
  "type": "Feature",
  "properties": {
    "iso:country":"US",
    "sg:address":"610 W Mesa Ave",
    "sg:city":"Gallup",
    "sg:classifiers":[
        {
            "category":"Restaurant",
            "type":"Food & Drink"
        }
    ],
    "sg:phone":"+1 505 722 7000",
    "sg:postcode":"87301",
    "sg:province":"NM",
    "wof:name":"El Metate",
    "wof:placetype":"venue"
},
  "geometry": {"coordinates":[-108.746279,35.523001],"type":"Point"}
}