{
  "type": "Feature",
  "properties": {
    "addr:full":"1639 Pso del Pueblo Norte El Prado NM 87529",
    "addr:housenumber":"1639",
    "addr:postcode":"87529",
    "addr:street":"Pso Del Pueblo Norte",
    "iso:country":"US",
    "sg:address":"1639 Pso del Pueblo Norte",
    "sg:city":"El Prado",
    "sg:classifiers":[
        {
            "category":"Restaurant",
            "type":"Food & Drink"
        }
    ],
    "sg:phone":"+1 505 751 4431",
    "sg:postcode":"87529",
    "sg:province":"NM",
    "wof:name":"Rita's",
    "wof:placetype":"venue"
},
  "geometry": {"coordinates":[-105.59397300000001,36.455608],"type":"Point"}
}