{
  "type": "Feature",
  "properties": {
    "iso:country":"US",
    "sg:address":"2285 E Lohman Ave",
    "sg:city":"Las Cruces",
    "sg:classifiers":[
        {
            "category":"Retail",
            "subcategory":"Auto Rental",
            "type":"Services"
        }
    ],
    "sg:phone":"+1 505 523 5351",
    "sg:postcode":"88001",
    "sg:province":"NM",
    "sg:tags":[
        "renting",
        "automobile"
    ],
    "wof:name":"Enterprise Rent A Car",
    "wof:placetype":"venue"
},
  "geometry": {"coordinates":[-106.75177100000001,32.312962],"type":"Point"}
}