{
  "type": "Feature",
  "properties": {
    "addr:full":"6505 Louise Pl NE Albuquerque NM 87109",
    "addr:housenumber":"6505",
    "addr:postcode":"87109",
    "addr:street":"Louise Pl Ne",
    "iso:country":"US",
    "sg:address":"6505 Louise Pl NE",
    "sg:city":"Albuquerque",
    "sg:classifiers":[
        {
            "category":"Professional",
            "subcategory":"Management & Consulting",
            "type":"Services"
        }
    ],
    "sg:phone":"+1 505 828 0179",
    "sg:postcode":"87109",
    "sg:province":"NM",
    "sg:tags":[
        "retail",
        "direct",
        "sales"
    ],
    "wof:name":"Carol Sharp",
    "wof:placetype":"venue"
},
  "geometry": {"coordinates":[-106.57652299999999,35.148858],"type":"Point"}
}