{
  "type": "Feature",
  "properties": {
    "iso:country":"US",
    "sg:address":"5504 Menaul Blvd NE",
    "sg:city":"Albuquerque",
    "sg:classifiers":[
        {
            "category":"Shopping",
            "type":"Retail Goods"
        }
    ],
    "sg:phone":"+1 505 881 3222",
    "sg:postcode":"87110",
    "sg:province":"NM",
    "sg:tags":[
        "spa",
        "hot",
        "tub"
    ],
    "wof:name":"Cal Spas",
    "wof:placetype":"venue"
},
  "geometry": {"coordinates":[-106.582013,35.109046],"type":"Point"}
}