{
  "type": "Feature",
  "properties": {
    "iso:country":"US",
    "sg:address":"575 S Alameda Blvd",
    "sg:city":"Las Cruces",
    "sg:classifiers":[
        {
            "category":"Social Services",
            "subcategory":"Job Training",
            "type":"Services"
        }
    ],
    "sg:phone":"+1 505 528 3177",
    "sg:postcode":"88005",
    "sg:province":"NM",
    "sg:tags":[
        "rehab",
        "government"
    ],
    "wof:name":"Las Cruces Home Rehabilitation",
    "wof:placetype":"venue"
},
  "geometry": {"coordinates":[-106.780131,32.305586],"type":"Point"}
}