{
  "type": "Feature",
  "properties": {
    "iso:country":"US",
    "sg:address":"24930 US Hwy 64",
    "sg:city":"Taos",
    "sg:classifiers":[
        {
            "category":"Manufacturing",
            "subcategory":"Lumber",
            "type":"Manufacturing & Wholesale Goods"
        }
    ],
    "sg:phone":"+1 505 758 1506",
    "sg:postcode":"87571",
    "sg:province":"NM",
    "sg:tags":[
        "planing",
        "mills",
        "sawmill"
    ],
    "wof:name":"Olguin Sawmill & Firewood",
    "wof:placetype":"venue"
},
  "geometry": {"coordinates":[-105.611645,36.456993],"type":"Point"}
}