{
  "type": "Feature",
  "properties": {
    "iso:country":"US",
    "sg:address":"909 Virginia St NE",
    "sg:city":"Albuquerque",
    "sg:classifiers":[
        {
            "category":"Professional",
            "subcategory":"Accounting & Tax Preparation",
            "type":"Services"
        }
    ],
    "sg:phone":"+1 505 232 3134",
    "sg:postcode":"87108",
    "sg:province":"NM",
    "sg:tags":[
        "accountant"
    ],
    "wof:name":"Apple Accounting & Bus Svc",
    "wof:placetype":"venue"
},
  "geometry": {"coordinates":[-106.55255,35.086334],"type":"Point"}
}