{
  "type": "Feature",
  "properties": {
    "iso:country":"US",
    "sg:address":"815 S Gold Ave",
    "sg:city":"Deming",
    "sg:classifiers":[
        {
            "category":"Organizations",
            "subcategory":"Non-profit Organization",
            "type":"Services"
        }
    ],
    "sg:phone":"+1 505 546 6107",
    "sg:postcode":"88030",
    "sg:province":"NM",
    "wof:name":"Independent Order-Odd Fellows",
    "wof:placetype":"venue"
},
  "geometry": {"coordinates":[-107.75744,32.261041],"type":"Point"}
}