{
  "type": "Feature",
  "properties": {
    "iso:country":"US",
    "sg:address":"1633 8th St",
    "sg:city":"Las Vegas",
    "sg:classifiers":[
        {
            "category":"Shopping",
            "type":"Retail Goods"
        }
    ],
    "sg:phone":"+1 505 425 8827",
    "sg:postcode":"87701",
    "sg:province":"NM",
    "sg:tags":[
        "ice"
    ],
    "wof:name":"Las Vegas Ice Co",
    "wof:placetype":"venue"
},
  "geometry": {"coordinates":[-105.22491599999999,35.605374],"type":"Point"}
}