{
  "type": "Feature",
  "properties": {
    "iso:country":"US",
    "sg:address":"305 E San Mateo Rd",
    "sg:city":"Santa Fe",
    "sg:classifiers":[
        {
            "category":"Professional",
            "subcategory":"Management & Consulting",
            "type":"Services"
        }
    ],
    "sg:phone":"+1 505 982 5223",
    "sg:postcode":"87505",
    "sg:province":"NM",
    "wof:name":"Closson Enterprises LLC",
    "wof:placetype":"venue"
},
  "geometry": {"coordinates":[-105.936832,35.664334],"type":"Point"}
}