{
  "type": "Feature",
  "properties": {
    "iso:country":"US",
    "sg:address":"925 Bridge Blvd SW",
    "sg:city":"Albuquerque",
    "sg:classifiers":[
        {
            "category":"Retail",
            "subcategory":"Auto Repair",
            "type":"Services"
        }
    ],
    "sg:phone":"+1 505 248 1931",
    "sg:postcode":"87105",
    "sg:province":"NM",
    "sg:tags":[
        "transmission"
    ],
    "wof:name":"Price Transmissions",
    "wof:placetype":"venue"
},
  "geometry": {"coordinates":[-106.666014,35.068702],"type":"Point"}
}