{
  "type": "Feature",
  "properties": {
    "iso:country":"US",
    "sg:address":"4601 E Main St",
    "sg:city":"Farmington",
    "sg:classifiers":[
        {
            "category":"Shopping",
            "subcategory":"Department Store",
            "type":"Retail Goods"
        }
    ],
    "sg:phone":"+1 505 326 2681",
    "sg:postcode":"87402",
    "sg:province":"NM",
    "wof:name":"Dillards 923",
    "wof:placetype":"venue"
},
  "geometry": {"coordinates":[-108.153049,36.764578],"type":"Point"}
}