{
  "type": "Feature",
  "properties": {
    "addr:full":"8804 Washington St NE Albuquerque NM 87113",
    "addr:housenumber":"8804",
    "addr:postcode":"87113",
    "addr:street":"Washington St Ne",
    "iso:country":"US",
    "sg:address":"8804 Washington St NE",
    "sg:city":"Albuquerque",
    "sg:classifiers":[
        {
            "category":"Insurance",
            "subcategory":"Insurance Agent",
            "type":"Services"
        }
    ],
    "sg:phone":"+1 505 797 4370",
    "sg:postcode":"87113",
    "sg:province":"NM",
    "sg:tags":[
        "adjuster"
    ],
    "wof:name":"GAB Robins",
    "wof:placetype":"venue"
},
  "geometry": {"coordinates":[-106.596637,35.186053],"type":"Point"}
}