{
  "type": "Feature",
  "properties": {
    "iso:country":"US",
    "sg:address":"1655 S Main St",
    "sg:city":"Las Cruces",
    "sg:classifiers":[
        {
            "category":"Travel",
            "subcategory":"Hotels & Motels",
            "type":"Entertainment"
        }
    ],
    "sg:phone":"+1 505 524 7791",
    "sg:postcode":"88005",
    "sg:province":"NM",
    "wof:name":"Sands Motel",
    "wof:placetype":"venue"
},
  "geometry": {"coordinates":[-106.779723,32.296054],"type":"Point"}
}