{
  "type": "Feature",
  "properties": {
    "addr:full":"6615 Lomas Blvd NE Albuquerque NM 87110",
    "addr:housenumber":"6615",
    "addr:postcode":"87110",
    "addr:street":"Lomas Blvd Ne",
    "iso:country":"US",
    "sg:address":"6615 Lomas Blvd NE",
    "sg:city":"Albuquerque",
    "sg:classifiers":[
        {
            "category":"Home & Garden",
            "subcategory":"Building Materials",
            "type":"Retail Goods"
        },
        {
            "category":"Building & Trades",
            "subcategory":"Construction",
            "type":"Services"
        }
    ],
    "sg:phone":"+1 505 268 2738",
    "sg:postcode":"87110",
    "sg:province":"NM",
    "sg:tags":[
        "windows",
        "house",
        "nonresidential"
    ],
    "wof:name":"Cardinal Construction Inc",
    "wof:placetype":"venue"
},
  "geometry": {"coordinates":[-106.573177,35.087399],"type":"Point"}
}