{
  "type": "Feature",
  "properties": {
    "iso:country":"US",
    "sg:address":"2221 N Main St",
    "sg:city":"Clovis",
    "sg:classifiers":[
        {
            "category":"Ice Cream",
            "type":"Food & Drink"
        }
    ],
    "sg:menulink":"http://www.allmenus.com/nm/clovis/167849-dairy-queen/menu/",
    "sg:phone":"+1 505 763 4676",
    "sg:postcode":"88101",
    "sg:province":"NM",
    "sg:tags":[
        "burger",
        "american"
    ],
    "wof:name":"Dairy Queen",
    "wof:placetype":"venue"
},
  "geometry": {"coordinates":[-103.20541299999999,34.421541],"type":"Point"}
}