{
  "type": "Feature",
  "properties": {
    "iso:country":"US",
    "sg:address":"100 N Canal St",
    "sg:city":"Carlsbad",
    "sg:classifiers":[
        {
            "category":"Government",
            "subcategory":"Court House",
            "type":"Public Place"
        }
    ],
    "sg:phone":"+1 505 887 7101",
    "sg:postcode":"88220",
    "sg:province":"NM",
    "sg:tags":[
        "county"
    ],
    "wof:name":"District Judge",
    "wof:placetype":"venue"
},
  "geometry": {"coordinates":[-104.22896900000001,32.42151],"type":"Point"}
}