{
  "type": "Feature",
  "properties": {
    "iso:country":"US",
    "sg:address":"1410 Old Mescalero Rd",
    "sg:city":"Tularosa",
    "sg:classifiers":[
        {
            "category":"Museum",
            "type":"Entertainment"
        }
    ],
    "sg:phone":"+1 505 585 4722",
    "sg:postcode":"88352",
    "sg:province":"NM",
    "sg:tags":[
        "gallery"
    ],
    "wof:name":"Studio Normand",
    "wof:placetype":"venue"
},
  "geometry": {"coordinates":[-105.997899,33.076677],"type":"Point"}
}