{
  "type": "Feature",
  "properties": {
    "addr:full":"2208 Lester Dr NE Albuquerque NM 87112",
    "addr:housenumber":"2208",
    "addr:postcode":"87112",
    "addr:street":"Lester Dr Ne",
    "iso:country":"US",
    "sg:address":"2208 Lester Dr NE",
    "sg:city":"Albuquerque",
    "sg:classifiers":[
        {
            "category":"Personal",
            "subcategory":"Beauty Salon",
            "type":"Services"
        }
    ],
    "sg:phone":"+1 505 298 5038",
    "sg:postcode":"87112",
    "sg:province":"NM",
    "sg:tags":[
        "shop"
    ],
    "wof:name":"Three Fountains Beauty Salon",
    "wof:placetype":"venue"
},
  "geometry": {"coordinates":[-106.547145,35.108773],"type":"Point"}
}