{
  "type": "Feature",
  "properties": {
    "addr:full":"6001 Central Ave NW Albuquerque NM 87105",
    "addr:housenumber":"6001",
    "addr:postcode":"87105",
    "addr:street":"Central Ave Nw",
    "iso:country":"US",
    "sg:address":"6001 Central Ave NW",
    "sg:city":"Albuquerque",
    "sg:classifiers":[
        {
            "category":"Insurance",
            "subcategory":"Insurance Agent",
            "type":"Services"
        }
    ],
    "sg:phone":"+1 505 836 2964",
    "sg:postcode":"87105",
    "sg:province":"NM",
    "wof:name":"Chaney Agency",
    "wof:placetype":"venue"
},
  "geometry": {"coordinates":[-106.70482199999999,35.081219],"type":"Point"}
}