{
  "type": "Feature",
  "properties": {
    "iso:country":"US",
    "sg:address":"3005 Northridge Dr",
    "sg:city":"Farmington",
    "sg:classifiers":[
        {
            "category":"Health Services",
            "subcategory":"Doctor",
            "type":"Services"
        }
    ],
    "sg:phone":"+1 505 326 2273",
    "sg:postcode":"87401",
    "sg:province":"NM",
    "sg:tags":[
        "clinic",
        "medical",
        "outpatient",
        "specialty"
    ],
    "wof:name":"Marc Irwin PHD PA",
    "wof:placetype":"venue"
},
  "geometry": {"coordinates":[-108.193804,36.756117],"type":"Point"}
}