{
  "type": "Feature",
  "properties": {
    "addr:full":"2120 N Alto Dr Hobbs NM 88240",
    "addr:housenumber":"2120",
    "addr:postcode":"88240",
    "addr:street":"N Alto Dr",
    "iso:country":"US",
    "sg:address":"2120 N Alto Dr",
    "sg:city":"Hobbs",
    "sg:classifiers":[
        {
            "category":"Government",
            "subcategory":"Office",
            "type":"Public Place"
        }
    ],
    "sg:phone":"+1 505 397 5290",
    "sg:postcode":"88240",
    "sg:province":"NM",
    "sg:tags":[
        "admin",
        "affairs",
        "state"
    ],
    "wof:name":"Veteran's Service",
    "wof:placetype":"venue"
},
  "geometry": {"coordinates":[-103.129166,32.72403],"type":"Point"}
}