{
  "type": "Feature",
  "properties": {
    "addr:full":"1329 W Taos St Hobbs NM 88240",
    "addr:housenumber":"1329",
    "addr:postcode":"88240",
    "addr:street":"W Taos St",
    "iso:country":"US",
    "sg:address":"1329 W Taos St",
    "sg:city":"Hobbs",
    "sg:classifiers":[
        {
            "category":"Health Services",
            "subcategory":"Clinic",
            "type":"Services"
        }
    ],
    "sg:phone":"+1 505 392 7360",
    "sg:postcode":"88240",
    "sg:province":"NM",
    "wof:name":"Kristy Snow",
    "wof:placetype":"venue"
},
  "geometry": {"coordinates":[-103.150896,32.735423],"type":"Point"}
}