{
  "type": "Feature",
  "properties": {
    "iso:country":"US",
    "sg:address":"700 Camelot Blvd SW",
    "sg:city":"Los Lunas",
    "sg:classifiers":[
        {
            "category":"Organizations",
            "subcategory":"Religious Organization",
            "type":"Services"
        }
    ],
    "sg:phone":"+1 505 865 9226",
    "sg:postcode":"87031",
    "sg:province":"NM",
    "sg:tags":[
        "church"
    ],
    "wof:name":"Christ The King Lutheran Chr",
    "wof:placetype":"venue"
},
  "geometry": {"coordinates":[-106.761024,34.806473],"type":"Point"}
}