{
  "type": "Feature",
  "properties": {
    "addr:full":"615 Wyoming Blvd SE Albuquerque NM 87123",
    "addr:housenumber":"615",
    "addr:postcode":"87123",
    "addr:street":"Blvd Se",
    "iso:country":"US",
    "sg:address":"615 Wyoming Blvd SE",
    "sg:city":"Albuquerque",
    "sg:classifiers":[
        {
            "category":"Retail",
            "subcategory":"Laundry & Dry Cleaning",
            "type":"Services"
        },
        {
            "category":"Shopping",
            "subcategory":"Clothing, Apparel, & Fashions",
            "type":"Retail Goods"
        }
    ],
    "sg:phone":"+1 505 255 4614",
    "sg:postcode":"87123",
    "sg:province":"NM",
    "sg:tags":[
        "alteration"
    ],
    "wof:name":"Tuye's Alterations",
    "wof:placetype":"venue"
},
  "geometry": {"coordinates":[-106.55059300000001,35.065076],"type":"Point"}
}