{
  "type": "Feature",
  "properties": {
    "iso:country":"US",
    "sg:address":"8 Moore Ave",
    "sg:city":"Alamogordo",
    "sg:classifiers":[
        {
            "category":"Building & Trades",
            "subcategory":"Construction",
            "type":"Services"
        }
    ],
    "sg:phone":"+1 505 439 8677",
    "sg:postcode":"88310",
    "sg:province":"NM",
    "sg:tags":[
        "roofing",
        "contractor"
    ],
    "wof:name":"Ruiz Roofing",
    "wof:placetype":"venue"
},
  "geometry": {"coordinates":[-105.983771,32.895043],"type":"Point"}
}