{
  "type": "Feature",
  "properties": {
    "iso:country":"US",
    "sg:address":"200 Inverness Dr SE",
    "sg:city":"Rio Rancho",
    "sg:classifiers":[
        {
            "category":"Real Estate",
            "subcategory":"Real Estate Operator",
            "type":"Services"
        }
    ],
    "sg:phone":"+1 505 994 0393",
    "sg:postcode":"87124",
    "sg:province":"NM",
    "sg:tags":[
        "building",
        "nonresidential"
    ],
    "wof:name":"Don Haven Properties",
    "wof:placetype":"venue"
},
  "geometry": {"coordinates":[-106.675087,35.256427],"type":"Point"}
}