{
  "type": "Feature",
  "properties": {
    "iso:country":"US",
    "sg:address":"1609 Columbus Rd",
    "sg:city":"Deming",
    "sg:classifiers":[
        {
            "category":"Autos & Motor Vehicles",
            "subcategory":"Fuel & Gas Station",
            "type":"Retail Goods"
        }
    ],
    "sg:phone":"+1 505 544 0212",
    "sg:postcode":"88030",
    "sg:province":"NM",
    "sg:tags":[
        "oil"
    ],
    "wof:name":"Pepper Chevron Food Mart",
    "wof:placetype":"venue"
},
  "geometry": {"coordinates":[-107.75147,32.252931],"type":"Point"}
}