{
  "type": "Feature",
  "properties": {
    "iso:country":"US",
    "sg:address":"23273 US Hwy 70",
    "sg:city":"Tularosa",
    "sg:classifiers":[
        {
            "category":"Farming",
            "subcategory":"Livestock Farm",
            "type":"Manufacturing & Wholesale Goods"
        }
    ],
    "sg:phone":"+1 505 585 2776",
    "sg:postcode":"88352",
    "sg:province":"NM",
    "sg:tags":[
        "photography",
        "commercial",
        "equine"
    ],
    "wof:name":"Cottonwood Springs Ranch",
    "wof:placetype":"venue"
},
  "geometry": {"coordinates":[-105.94731,33.103163],"type":"Point"}
}