{
  "type": "Feature",
  "properties": {
    "addr:full":"1874 US Hwy 180 E Silver City NM 88061",
    "addr:housenumber":"1874",
    "addr:postcode":"88061",
    "addr:street":"Us Hwy 180 E",
    "iso:country":"US",
    "sg:address":"1874 US Hwy 180 E",
    "sg:city":"Silver City",
    "sg:classifiers":[
        {
            "category":"Personal",
            "subcategory":"Beauty Salon",
            "type":"Services"
        }
    ],
    "sg:phone":"+1 505 538 5860",
    "sg:postcode":"88061",
    "sg:province":"NM",
    "sg:tags":[
        "shop"
    ],
    "wof:name":"Merle Norman Cosmetics",
    "wof:placetype":"venue"
},
  "geometry": {"coordinates":[-108.259283,32.785914],"type":"Point"}
}