{
  "type": "Feature",
  "properties": {
    "iso:country":"US",
    "sg:address":"8201 Golf Course Rd NW",
    "sg:city":"Albuquerque",
    "sg:classifiers":[
        {
            "category":"Professional",
            "subcategory":"Management & Consulting",
            "type":"Services"
        }
    ],
    "sg:phone":"+1 505 899 1448",
    "sg:postcode":"87120",
    "sg:province":"NM",
    "sg:tags":[
        "business"
    ],
    "wof:name":"Protect Your Rights",
    "wof:placetype":"venue"
},
  "geometry": {"coordinates":[-106.687814,35.176978],"type":"Point"}
}