{
  "type": "Feature",
  "properties": {
    "addr:full":"11 Ladera Rd Santa Fe NM 87508",
    "addr:housenumber":"11",
    "addr:postcode":"87508",
    "addr:street":"Ladera Rd",
    "iso:country":"US",
    "sg:address":"11 Ladera Rd",
    "sg:city":"Santa Fe",
    "sg:classifiers":[
        {
            "category":"Professional",
            "subcategory":"Management & Consulting",
            "type":"Services"
        }
    ],
    "sg:phone":"+1 505 466 0222",
    "sg:postcode":"87508",
    "sg:province":"NM",
    "sg:tags":[
        "consultant",
        "business"
    ],
    "wof:name":"Professional Consulting & Res",
    "wof:placetype":"venue"
},
  "geometry": {"coordinates":[-105.960714,35.530347],"type":"Point"}
}