{
  "type": "Feature",
  "properties": {
    "iso:country":"US",
    "sg:address":"6400 Uptown Blvd NE Ste 2",
    "sg:city":"Albuquerque",
    "sg:classifiers":[
        {
            "category":"Education",
            "subcategory":"School",
            "type":"Public Place"
        }
    ],
    "sg:phone":"+1 505 247 1012",
    "sg:postcode":"87110",
    "sg:province":"NM",
    "sg:tags":[
        "k-",
        "private"
    ],
    "wof:name":"Albuquerque Sch Dist South Reg",
    "wof:placetype":"venue"
},
  "geometry": {"coordinates":[-106.57325,35.103699],"type":"Point"}
}