{
  "type": "Feature",
  "properties": {
    "iso:country":"US",
    "sg:address":"400 Gold Ave SW Ste 1060",
    "sg:city":"Albuquerque",
    "sg:classifiers":[
        {
            "category":"Professional",
            "subcategory":"Management & Consulting",
            "type":"Services"
        },
        {
            "category":"Professional",
            "subcategory":"Lawyer & Legal Services",
            "type":"Services"
        },
        {
            "category":"Banks & Credit Unions",
            "subcategory":"Financial Services",
            "type":"Services"
        }
    ],
    "sg:phone":"+1 505 243 7222",
    "sg:postcode":"87102",
    "sg:province":"NM",
    "sg:tags":[
        "financing",
        "retirement",
        "sharing",
        "estate",
        "profit",
        "annuity",
        "wills",
        "attorney",
        "planning",
        "plan",
        "consultant",
        "trust",
        "insurance",
        "pension"
    ],
    "sg:website":"http://www.abacus401k.com",
    "wof:name":"Abacus Retirement Solutions",
    "wof:placetype":"venue"
},
  "geometry": {"coordinates":[-106.651787,35.083591],"type":"Point"}
}