{
  "type": "Feature",
  "properties": {
    "addr:full":"523 S Main St Belen NM 87002",
    "addr:housenumber":"523",
    "addr:postcode":"87002",
    "addr:street":"S Main St",
    "iso:country":"US",
    "sg:address":"523 S Main St",
    "sg:city":"Belen",
    "sg:classifiers":[
        {
            "category":"Restaurant",
            "type":"Food & Drink"
        }
    ],
    "sg:phone":"+1 505 864 4135",
    "sg:postcode":"87002",
    "sg:province":"NM",
    "wof:name":"Circle T Drive-In",
    "wof:placetype":"venue"
},
  "geometry": {"coordinates":[-106.778227,34.65707],"type":"Point"}
}