{
  "type": "Feature",
  "properties": {
    "iso:country":"US",
    "sg:address":"714 W Main St",
    "sg:city":"Farmington",
    "sg:classifiers":[
        {
            "category":"Cinema",
            "subcategory":"Movie Rental",
            "type":"Entertainment"
        }
    ],
    "sg:phone":"+1 505 327 1600",
    "sg:postcode":"87401",
    "sg:province":"NM",
    "sg:tags":[
        "leasing",
        "video",
        "disc",
        "tape"
    ],
    "wof:name":"Front Row Seat",
    "wof:placetype":"venue"
},
  "geometry": {"coordinates":[-108.21486,36.729129],"type":"Point"}
}