{
  "type": "Feature",
  "properties": {
    "addr:full":"663 N Roosevelt Road 3 Clovis NM 88101",
    "addr:housenumber":"663",
    "addr:postcode":"88101",
    "addr:street":"N Roosevelt Road 3",
    "iso:country":"US",
    "sg:address":"663 N Roosevelt Road 3",
    "sg:city":"Clovis",
    "sg:classifiers":[
        {
            "category":"Professional",
            "type":"Services"
        }
    ],
    "sg:phone":"+1 505 683 0041",
    "sg:postcode":"88101",
    "sg:province":"NM",
    "sg:tags":[
        "establishment"
    ],
    "wof:name":"Herdsman OFFICE-Cld",
    "wof:placetype":"venue"
},
  "geometry": {"coordinates":[-103.137286,34.302866],"type":"Point"}
}