{
  "type": "Feature",
  "properties": {
    "iso:country":"US",
    "sg:address":"3251 Cerrillos Rd",
    "sg:city":"Santa Fe",
    "sg:classifiers":[
        {
            "category":"Professional",
            "subcategory":"Accounting & Tax Preparation",
            "type":"Services"
        }
    ],
    "sg:phone":"+1 505 471 1576",
    "sg:postcode":"87507",
    "sg:province":"NM",
    "sg:tags":[
        "return",
        "filing"
    ],
    "wof:name":"H & R Block",
    "wof:placetype":"venue"
},
  "geometry": {"coordinates":[-105.99857299999999,35.651285],"type":"Point"}
}