{
  "type": "Feature",
  "properties": {
    "iso:country":"US",
    "sg:address":"6767 Academy Rd NE",
    "sg:city":"Albuquerque",
    "sg:classifiers":[
        {
            "category":"Banks & Credit Unions",
            "subcategory":"Bank",
            "type":"Services"
        }
    ],
    "sg:phone":"+1 505 857 2218",
    "sg:postcode":"87109",
    "sg:province":"NM",
    "sg:tags":[
        "mortgage"
    ],
    "wof:name":"Desert Mountain Mortgage",
    "wof:placetype":"venue"
},
  "geometry": {"coordinates":[-106.57265,35.14542],"type":"Point"}
}