{
  "type": "Feature",
  "properties": {
    "addr:full":"1611 Pso de Peralta Santa Fe NM 87501",
    "addr:housenumber":"1611",
    "addr:postcode":"87501",
    "addr:street":"Pso De Peralta",
    "iso:country":"US",
    "sg:address":"1611 Pso de Peralta",
    "sg:city":"Santa Fe",
    "sg:classifiers":[
        {
            "category":"Arts & Performance",
            "subcategory":"Theater",
            "type":"Entertainment"
        }
    ],
    "sg:phone":"+1 505 982 8309",
    "sg:postcode":"87501",
    "sg:province":"NM",
    "sg:tags":[
        "theatrical"
    ],
    "wof:name":"Railyard Performance Center",
    "wof:placetype":"venue"
},
  "geometry": {"coordinates":[-105.948559,35.681847],"type":"Point"}
}