{
  "type": "Feature",
  "properties": {
    "addr:full":"1501 Paseo De Peralta Santa Fe NM 87501",
    "addr:housenumber":"1501",
    "addr:postcode":"87501",
    "addr:street":"Paseo De Peralta",
    "iso:country":"US",
    "sg:address":"1501 Paseo De Peralta",
    "sg:city":"Santa Fe",
    "sg:classifiers":[
        {
            "category":"Restaurant",
            "type":"Food & Drink"
        }
    ],
    "sg:menulink":"http://www.allmenus.com/nm/santa-fe/3900-amaya/menu/",
    "sg:phone":"+1 505 982 1200",
    "sg:postcode":"87501",
    "sg:province":"NM",
    "sg:tags":[
        "wrap",
        "seafood",
        "sandwich",
        "american"
    ],
    "wof:name":"Amaya",
    "wof:placetype":"venue"
},
  "geometry": {"coordinates":[-105.946106,35.681601],"type":"Point"}
}