{
  "type": "Feature",
  "properties": {
    "iso:country":"US",
    "sg:address":"1610 W Washington Ave",
    "sg:city":"Artesia",
    "sg:classifiers":[
        {
            "category":"Building & Trades",
            "subcategory":"Pest Control",
            "type":"Services"
        }
    ],
    "sg:phone":"+1 505 746 6483",
    "sg:postcode":"88210",
    "sg:province":"NM",
    "wof:name":"Prescription Pest Control",
    "wof:placetype":"venue"
},
  "geometry": {"coordinates":[-104.416907,32.835881],"type":"Point"}
}