{
  "type": "Feature",
  "properties": {
    "addr:full":"8316 Corona Loop NE Albuquerque NM 87113",
    "addr:housenumber":"8316",
    "addr:postcode":"87113",
    "addr:street":"Corona Loop Ne",
    "iso:country":"US",
    "sg:address":"8316 Corona Loop NE",
    "sg:city":"Albuquerque",
    "sg:classifiers":[
        {
            "category":"Communications",
            "type":"Services"
        }
    ],
    "sg:phone":"+1 505 877 2100",
    "sg:postcode":"87113",
    "sg:province":"NM",
    "wof:name":"Broken Arrow Comm",
    "wof:placetype":"venue"
},
  "geometry": {"coordinates":[-106.598494,35.179689],"type":"Point"}
}