{
  "type": "Feature",
  "properties": {
    "iso:country":"US",
    "sg:address":"3109 N Swan St",
    "sg:city":"Silver City",
    "sg:classifiers":[
        {
            "category":"Farming",
            "subcategory":"Farm & Veterinary Services",
            "type":"Manufacturing & Wholesale Goods"
        }
    ],
    "sg:phone":"+1 505 538 2048",
    "sg:postcode":"88061",
    "sg:province":"NM",
    "sg:tags":[
        "livestock"
    ],
    "wof:name":"Bagby Ranch Inc",
    "wof:placetype":"venue"
},
  "geometry": {"coordinates":[-108.269621,32.795333],"type":"Point"}
}