{
  "type": "Feature",
  "properties": {
    "iso:country":"US",
    "sg:address":"11260 Lovington Hwy",
    "sg:city":"Artesia",
    "sg:classifiers":[
        {
            "category":"Building & Trades",
            "subcategory":"Construction",
            "type":"Services"
        }
    ],
    "sg:phone":"+1 505 746 6406",
    "sg:postcode":"88210",
    "sg:province":"NM",
    "sg:tags":[
        "road",
        "contractor"
    ],
    "wof:name":"Reiman Corp",
    "wof:placetype":"venue"
},
  "geometry": {"coordinates":[-104.310403,32.836252],"type":"Point"}
}