{
  "type": "Feature",
  "properties": {
    "iso:country":"US",
    "sg:address":"236 Dolores Rd",
    "sg:city":"Los Lunas",
    "sg:classifiers":[
        {
            "category":"Professional",
            "subcategory":"Business Services",
            "type":"Services"
        }
    ],
    "sg:phone":"+1 505 565 2590",
    "sg:postcode":"87031",
    "sg:province":"NM",
    "wof:name":"Tj Enterprises",
    "wof:placetype":"venue"
},
  "geometry": {"coordinates":[-106.752904,34.752761],"type":"Point"}
}