{
  "type": "Feature",
  "properties": {
    "iso:country":"US",
    "sg:address":"8528 Lomas Blvd NE",
    "sg:city":"Albuquerque",
    "sg:classifiers":[
        {
            "category":"Autos & Motor Vehicles",
            "subcategory":"Automobile Sales",
            "type":"Retail Goods"
        }
    ],
    "sg:phone":"+1 505 262 1111",
    "sg:postcode":"87110",
    "sg:province":"NM",
    "sg:tags":[
        "car",
        "dealer"
    ],
    "wof:name":"Zangara Dodge",
    "wof:placetype":"venue"
},
  "geometry": {"coordinates":[-106.5509,35.087274],"type":"Point"}
}