{
  "type": "Feature",
  "properties": {
    "iso:country":"US",
    "sg:address":"3401 Pitt St NE",
    "sg:city":"Albuquerque",
    "sg:classifiers":[
        {
            "category":"Freight",
            "type":"Transportation"
        }
    ],
    "sg:phone":"+1 505 875 9020",
    "sg:postcode":"87111",
    "sg:province":"NM",
    "sg:tags":[
        "warehouse",
        "confectionery",
        "facility"
    ],
    "wof:name":"Mr CS Snack Foods",
    "wof:placetype":"venue"
},
  "geometry": {"coordinates":[-106.529369,35.121682],"type":"Point"}
}