{
  "type": "Feature",
  "properties": {
    "iso:country":"US",
    "sg:address":"819 Gavilan Canyon Rd",
    "sg:city":"Ruidoso",
    "sg:classifiers":[
        {
            "category":"Education",
            "subcategory":"School",
            "type":"Public Place"
        }
    ],
    "sg:phone":"+1 505 258 5707",
    "sg:postcode":"88345",
    "sg:province":"NM",
    "wof:name":"Gavilan Canyon School",
    "wof:placetype":"venue"
},
  "geometry": {"coordinates":[-105.64393200000001,33.351459],"type":"Point"}
}