{
  "type": "Feature",
  "properties": {
    "iso:country":"US",
    "sg:address":"12540 State Highway 14 N",
    "sg:city":"Sandia Park",
    "sg:classifiers":[
        {
            "category":"Bakery",
            "type":"Food & Drink"
        }
    ],
    "sg:phone":"+1 505 286 2691",
    "sg:postcode":"87047",
    "sg:province":"NM",
    "wof:name":"Kokopelli's Restaurant and Cantina",
    "wof:placetype":"venue"
},
  "geometry": {"coordinates":[-106.346001,35.164501],"type":"Point"}
}