{
  "type": "Feature",
  "properties": {
    "addr:full":"41 Likely Rd Santa Fe NM 87508",
    "addr:housenumber":"41",
    "addr:postcode":"87508",
    "addr:street":"Likely Rd",
    "iso:country":"US",
    "sg:address":"41 Likely Rd",
    "sg:city":"Santa Fe",
    "sg:classifiers":[
        {
            "category":"Professional",
            "subcategory":"Management & Consulting",
            "type":"Services"
        }
    ],
    "sg:phone":"+1 505 986 0001",
    "sg:postcode":"87508",
    "sg:province":"NM",
    "wof:name":"Reider Assoc Inc",
    "wof:placetype":"venue"
},
  "geometry": {"coordinates":[-105.941518,35.597554],"type":"Point"}
}