{
  "type": "Feature",
  "properties": {
    "iso:country":"US",
    "sg:address":"1301 S Ave F",
    "sg:city":"Portales",
    "sg:classifiers":[
        {
            "category":"Professional",
            "subcategory":"Business Services",
            "type":"Services"
        }
    ],
    "sg:phone":"+1 505 356 5058",
    "sg:postcode":"88130",
    "sg:province":"NM",
    "sg:tags":[
        "notary"
    ],
    "wof:name":"Rosemary Mathews",
    "wof:placetype":"venue"
},
  "geometry": {"coordinates":[-103.33841,34.178736],"type":"Point"}
}