{
  "type": "Feature",
  "properties": {
    "iso:country":"US",
    "sg:address":"1022 Pso del Pueblo Sur",
    "sg:city":"Taos",
    "sg:classifiers":[
        {
            "category":"Autos & Motor Vehicles",
            "subcategory":"Auto Supplies",
            "type":"Retail Goods"
        }
    ],
    "sg:phone":"+1 505 758 8846",
    "sg:postcode":"87571",
    "sg:province":"NM",
    "sg:tags":[
        "automobile",
        "parts"
    ],
    "wof:name":"E & F Auto Supply",
    "wof:placetype":"venue"
},
  "geometry": {"coordinates":[-105.594949,36.372158],"type":"Point"}
}