{
  "type": "Feature",
  "properties": {
    "iso:country":"US",
    "sg:address":"801 Nikanda Rd NE",
    "sg:city":"Albuquerque",
    "sg:classifiers":[
        {
            "category":"Retail",
            "subcategory":"Auto Repair",
            "type":"Services"
        }
    ],
    "sg:phone":"+1 505 293 2811",
    "sg:postcode":"87107",
    "sg:province":"NM",
    "sg:tags":[
        "truck"
    ],
    "wof:name":"DDL Svc",
    "wof:placetype":"venue"
},
  "geometry": {"coordinates":[-106.625429,35.131448],"type":"Point"}
}