{
  "type": "Feature",
  "properties": {
    "iso:country":"US",
    "sg:address":"2425 Ridgecrest Dr SE",
    "sg:city":"Albuquerque",
    "sg:classifiers":[
        {
            "category":"Professional",
            "subcategory":"Business Services",
            "type":"Services"
        }
    ],
    "sg:phone":"+1 505 262 7531",
    "sg:postcode":"87108",
    "sg:province":"NM",
    "wof:name":"Business Technology Group",
    "wof:placetype":"venue"
},
  "geometry": {"coordinates":[-106.578041,35.055535],"type":"Point"}
}