{
  "type": "Feature",
  "properties": {
    "iso:country":"US",
    "sg:address":"7 Ave Vista Grande",
    "sg:city":"Santa Fe",
    "sg:classifiers":[
        {
            "category":"Health Services",
            "subcategory":"Health Practitioner",
            "type":"Services"
        }
    ],
    "sg:phone":"+1 505 989 8578",
    "sg:postcode":"87508",
    "sg:province":"NM",
    "sg:tags":[
        "organization",
        "religious"
    ],
    "wof:name":"Alaya",
    "wof:placetype":"venue"
},
  "geometry": {"coordinates":[-105.886952,35.536815],"type":"Point"}
}