{
  "type": "Feature",
  "properties": {
    "iso:country":"US",
    "sg:address":"414 Rd 4990",
    "sg:city":"Bloomfield",
    "sg:classifiers":[
        {
            "category":"Professional",
            "subcategory":"Research",
            "type":"Services"
        }
    ],
    "sg:phone":"+1 505 634 0600",
    "sg:postcode":"87413",
    "sg:province":"NM",
    "sg:tags":[
        "environmental",
        "ecological"
    ],
    "wof:name":"Patrick J Murin Environmental",
    "wof:placetype":"venue"
},
  "geometry": {"coordinates":[-107.91933299999999,36.697205],"type":"Point"}
}