{
  "type": "Feature",
  "properties": {
    "iso:country":"US",
    "sg:address":"3107 Eubank Blvd NE",
    "sg:city":"Albuquerque",
    "sg:classifiers":[
        {
            "category":"Personal",
            "subcategory":"Barber",
            "type":"Services"
        }
    ],
    "sg:phone":"+1 505 299 0276",
    "sg:postcode":"87111",
    "sg:province":"NM",
    "sg:tags":[
        "shop",
        "beauty"
    ],
    "wof:name":"Larry's Hair Styling",
    "wof:placetype":"venue"
},
  "geometry": {"coordinates":[-106.533362,35.11846],"type":"Point"}
}