{
  "type": "Feature",
  "properties": {
    "addr:full":"2606 Wyoming Blvd NE Albuquerque NM 87112",
    "addr:housenumber":"2606",
    "addr:postcode":"87112",
    "addr:street":"Wyoming;Ne",
    "iso:country":"US",
    "sg:address":"2606 Wyoming Blvd NE",
    "sg:city":"Albuquerque",
    "sg:classifiers":[
        {
            "category":"Health Services",
            "subcategory":"Nursing And Care Facility",
            "type":"Services"
        }
    ],
    "sg:phone":"+1 505 271 5000",
    "sg:postcode":"87112",
    "sg:province":"NM",
    "wof:name":"Hofmantown Alzheimers Care",
    "wof:placetype":"venue"
},
  "geometry": {"coordinates":[-106.550798,35.114117],"type":"Point"}
}