{
  "type": "Feature",
  "properties": {
    "iso:country":"US",
    "sg:address":"12 W Central Ave",
    "sg:city":"Lovington",
    "sg:classifiers":[
        {
            "category":"Retail",
            "subcategory":"Portrait Studio",
            "type":"Services"
        }
    ],
    "sg:phone":"+1 505 396 9956",
    "sg:postcode":"88260",
    "sg:province":"NM",
    "sg:tags":[
        "photo"
    ],
    "wof:name":"Photojenics",
    "wof:placetype":"venue"
},
  "geometry": {"coordinates":[-103.349405,32.948174],"type":"Point"}
}