{
  "type": "Feature",
  "properties": {
    "iso:country":"US",
    "sg:address":"1404 Eastridge Dr",
    "sg:city":"Clovis",
    "sg:classifiers":[
        {
            "category":"Professional",
            "subcategory":"Business Services",
            "type":"Services"
        }
    ],
    "sg:phone":"+1 505 762 4056",
    "sg:postcode":"88101",
    "sg:province":"NM",
    "wof:name":"Amateur Athletic Union of",
    "wof:placetype":"venue"
},
  "geometry": {"coordinates":[-103.190073,34.416531],"type":"Point"}
}