{
  "type": "Feature",
  "properties": {
    "iso:country":"US",
    "sg:address":"7 Arroyo Vis N",
    "sg:city":"Santa Fe",
    "sg:classifiers":[
        {
            "category":"Shopping",
            "subcategory":"Books",
            "type":"Retail Goods"
        }
    ],
    "sg:phone":"+1 505 986 0362",
    "sg:postcode":"87505",
    "sg:province":"NM",
    "wof:name":"Body Inc",
    "wof:placetype":"venue"
},
  "geometry": {"coordinates":[-105.919554,35.636936],"type":"Point"}
}