{
  "type": "Feature",
  "properties": {
    "addr:full":"310 W High St Grants NM 87020",
    "addr:housenumber":"310",
    "addr:postcode":"87020",
    "addr:street":"W High St",
    "iso:country":"US",
    "sg:address":"310 W High St",
    "sg:city":"Grants",
    "sg:classifiers":[
        {
            "category":"Government",
            "subcategory":"Office",
            "type":"Public Place"
        }
    ],
    "sg:phone":"+1 505 287 7941",
    "sg:postcode":"87020",
    "sg:province":"NM",
    "sg:tags":[
        "federal",
        "planning",
        "dev"
    ],
    "wof:name":"USDA Rural Development",
    "wof:placetype":"venue"
},
  "geometry": {"coordinates":[-107.851789,35.152873],"type":"Point"}
}