{
  "type": "Feature",
  "properties": {
    "iso:country":"US",
    "sg:address":"2000 Sudderth Dr",
    "sg:city":"Ruidoso",
    "sg:classifiers":[
        {
            "category":"Travel",
            "subcategory":"Hotels & Motels",
            "type":"Entertainment"
        }
    ],
    "sg:phone":"+1 505 257 0571",
    "sg:postcode":"88345",
    "sg:province":"NM",
    "sg:tags":[
        "resort"
    ],
    "wof:name":"Resort Promotions Inc",
    "wof:placetype":"venue"
},
  "geometry": {"coordinates":[-105.666341,33.329963],"type":"Point"}
}