{
  "type": "Feature",
  "properties": {
    "iso:country":"US",
    "sg:address":"5301 Menaul Blvd NE",
    "sg:city":"Albuquerque",
    "sg:classifiers":[
        {
            "category":"Home & Garden",
            "subcategory":"Household Appliances",
            "type":"Retail Goods"
        }
    ],
    "sg:phone":"+1 505 883 7511",
    "sg:postcode":"87110",
    "sg:province":"NM",
    "sg:website":"www.baillios.com",
    "wof:name":"Baillio's Electronics & Appl",
    "wof:placetype":"venue"
},
  "geometry": {"coordinates":[-106.584177,35.109148],"type":"Point"}
}