{
  "type": "Feature",
  "properties": {
    "addr:full":"113 W Broadway Farmington NM 87401",
    "addr:housenumber":"113",
    "addr:postcode":"87401",
    "addr:street":"W Broadway",
    "iso:country":"US",
    "sg:address":"113 W Broadway",
    "sg:city":"Farmington",
    "sg:classifiers":[
        {
            "category":"Shopping",
            "subcategory":"Optical Goods",
            "type":"Retail Goods"
        }
    ],
    "sg:phone":"+1 505 326 2020",
    "sg:postcode":"87401",
    "sg:province":"NM",
    "wof:name":"Cutler Jim Dr",
    "wof:placetype":"venue"
},
  "geometry": {"coordinates":[-108.206462,36.728004],"type":"Point"}
}