{
  "type": "Feature",
  "properties": {
    "addr:full":"311 N Date St Truth Or Consequences NM 87901",
    "addr:housenumber":"311",
    "addr:postcode":"87901",
    "addr:street":"N Date St",
    "iso:country":"US",
    "sg:address":"311 N Date St",
    "sg:city":"Truth Or Consequences",
    "sg:classifiers":[
        {
            "category":"Government",
            "subcategory":"Court House",
            "type":"Public Place"
        }
    ],
    "sg:phone":"+1 505 894 9033",
    "sg:postcode":"87901",
    "sg:province":"NM",
    "sg:tags":[
        "legal"
    ],
    "wof:name":"Office of District Attorney",
    "wof:placetype":"venue"
},
  "geometry": {"coordinates":[-107.25031300000001,33.133245],"type":"Point"}
}