{
  "type": "Feature",
  "properties": {
    "addr:full":"800 E Denby Ave Melrose NM 88124",
    "addr:housenumber":"800",
    "addr:postcode":"88124",
    "addr:street":"E Denby Ave",
    "iso:country":"US",
    "sg:address":"800 E Denby Ave",
    "sg:city":"Melrose",
    "sg:classifiers":[
        {
            "category":"Building & Trades",
            "subcategory":"Construction",
            "type":"Services"
        }
    ],
    "sg:phone":"+1 505 253 4439",
    "sg:postcode":"88124",
    "sg:province":"NM",
    "sg:tags":[
        "contractor"
    ],
    "wof:name":"Southwest Construction Company",
    "wof:placetype":"venue"
},
  "geometry": {"coordinates":[-103.62352,34.424437],"type":"Point"}
}