{
  "type": "Feature",
  "properties": {
    "iso:country":"US",
    "sg:address":"550 Dekalb Rd",
    "sg:city":"Farmington",
    "sg:classifiers":[
        {
            "category":"Building & Trades",
            "subcategory":"Cleaning & Sanitation",
            "type":"Services"
        }
    ],
    "sg:phone":"+1 505 722 7373",
    "sg:postcode":"87401",
    "sg:province":"NM",
    "sg:tags":[
        "janitor"
    ],
    "wof:name":"Velvet Glove Carpet Care",
    "wof:placetype":"venue"
},
  "geometry": {"coordinates":[-108.184496,36.726012],"type":"Point"}
}