{
  "type": "Feature",
  "properties": {
    "addr:full":"9525 Cargo Ave NE Albuquerque NM 87109",
    "addr:housenumber":"9525",
    "addr:postcode":"87109",
    "addr:street":"Cargo Ave Ne",
    "iso:country":"US",
    "sg:address":"9525 Cargo Ave NE",
    "sg:city":"Albuquerque",
    "sg:classifiers":[
        {
            "category":"Professional",
            "subcategory":"Engineering",
            "type":"Services"
        }
    ],
    "sg:phone":"+1 505 400 1776",
    "sg:postcode":"87109",
    "sg:province":"NM",
    "sg:tags":[
        "engineer"
    ],
    "wof:name":"Go For It",
    "wof:placetype":"venue"
},
  "geometry": {"coordinates":[-106.535284,35.167752],"type":"Point"}
}