{
  "type": "Feature",
  "properties": {
    "iso:country":"US",
    "sg:address":"2835 Pan American Fwy",
    "sg:city":"Albuquerque",
    "sg:classifiers":[
        {
            "category":"Professional",
            "type":"Services"
        }
    ],
    "sg:phone":"+1 505 341 0090",
    "sg:postcode":"87107",
    "sg:province":"NM",
    "sg:tags":[
        "establishment"
    ],
    "wof:name":"Wirestar Liberty",
    "wof:placetype":"venue"
},
  "geometry": {"coordinates":[-106.626937,35.111292],"type":"Point"}
}