{
  "type": "Feature",
  "properties": {
    "addr:full":"2025 Cam de Chavez Bosque Farms NM 87068",
    "addr:housenumber":"2025",
    "addr:postcode":"87068",
    "addr:street":"Cam De Chavez",
    "iso:country":"US",
    "sg:address":"2025 Cam de Chavez",
    "sg:city":"Bosque Farms",
    "sg:classifiers":[
        {
            "category":"Farming",
            "subcategory":"Dairy Farm",
            "type":"Manufacturing & Wholesale Goods"
        }
    ],
    "sg:phone":"+1 505 869 0837",
    "sg:postcode":"87068",
    "sg:province":"NM",
    "wof:name":"Vanderploeg Inc",
    "wof:placetype":"venue"
},
  "geometry": {"coordinates":[-106.699258,34.843115],"type":"Point"}
}