{
  "type": "Feature",
  "properties": {
    "iso:country":"US",
    "sg:address":"407 Galisteo St",
    "sg:city":"Santa Fe",
    "sg:classifiers":[
        {
            "category":"Government",
            "subcategory":"Office",
            "type":"Public Place"
        }
    ],
    "sg:phone":"+1 505 827 3640",
    "sg:postcode":"87501",
    "sg:province":"NM",
    "sg:tags":[
        "state",
        "taxation"
    ],
    "wof:name":"Budget Division",
    "wof:placetype":"venue"
},
  "geometry": {"coordinates":[-105.94277,35.682209],"type":"Point"}
}