{
  "type": "Feature",
  "properties": {
    "iso:country":"US",
    "sg:address":"21 Cielo del Rey",
    "sg:city":"Anthony",
    "sg:classifiers":[
        {
            "category":"Home & Garden",
            "subcategory":"Hardware",
            "type":"Retail Goods"
        }
    ],
    "sg:phone":"+1 505 589 9015",
    "sg:postcode":"88021",
    "sg:province":"NM",
    "wof:name":"True Value",
    "wof:placetype":"venue"
},
  "geometry": {"coordinates":[-106.645324,31.905165],"type":"Point"}
}