{
  "type": "Feature",
  "properties": {
    "addr:full":"2420 W Pierce St Carlsbad NM 88220",
    "addr:housenumber":"2420",
    "addr:postcode":"88220",
    "addr:street":"W Pierce St",
    "iso:country":"US",
    "sg:address":"2420 W Pierce St",
    "sg:city":"Carlsbad",
    "sg:classifiers":[
        {
            "category":"Health Services",
            "subcategory":"Doctor",
            "type":"Services"
        }
    ],
    "sg:phone":"+1 505 628 0598",
    "sg:postcode":"88220",
    "sg:province":"NM",
    "sg:tags":[
        "physician",
        "surgeon"
    ],
    "wof:name":"Julio C Munoz MD",
    "wof:placetype":"venue"
},
  "geometry": {"coordinates":[-104.259355,32.442318],"type":"Point"}
}