{
  "type": "Feature",
  "properties": {
    "iso:country":"US",
    "sg:address":"3401 Comanche Rd NE",
    "sg:city":"Albuquerque",
    "sg:classifiers":[
        {
            "category":"Health Services",
            "subcategory":"Dentist",
            "type":"Services"
        }
    ],
    "sg:phone":"+1 505 883 6279",
    "sg:postcode":"87107",
    "sg:province":"NM",
    "sg:tags":[
        "dentists-endodontists"
    ],
    "sg:website":"http://drnieto.com",
    "wof:name":"DR ANTHONY NIETO",
    "wof:placetype":"venue"
},
  "geometry": {"coordinates":[-106.606911,35.123705],"type":"Point"}
}