{
  "type": "Feature",
  "properties": {
    "iso:country":"US",
    "sg:address":"2133 N French Dr",
    "sg:city":"Hobbs",
    "sg:classifiers":[
        {
            "category":"Mining & Drilling",
            "type":"Manufacturing & Wholesale Goods"
        }
    ],
    "sg:phone":"+1 505 393 2609",
    "sg:postcode":"88240",
    "sg:province":"NM",
    "sg:tags":[
        "oil",
        "well"
    ],
    "wof:name":"Bio Tech Inc",
    "wof:placetype":"venue"
},
  "geometry": {"coordinates":[-103.162111,32.72518],"type":"Point"}
}