{
  "type": "Feature",
  "properties": {
    "addr:full":"16 Joe Nestor Rd Edgewood NM 87015",
    "addr:housenumber":"16",
    "addr:postcode":"87015",
    "addr:street":"Joe Nestor Rd",
    "iso:country":"US",
    "sg:address":"16 Joe Nestor Rd",
    "sg:city":"Edgewood",
    "sg:classifiers":[
        {
            "category":"Health Services",
            "subcategory":"Doctor",
            "type":"Services"
        }
    ],
    "sg:phone":"+1 505 286 1193",
    "sg:postcode":"87015",
    "sg:province":"NM",
    "wof:name":"East Mountain Optomechanical",
    "wof:placetype":"venue"
},
  "geometry": {"coordinates":[-106.25309,35.098275],"type":"Point"}
}