{
  "type": "Feature",
  "properties": {
    "iso:country":"US",
    "sg:address":"181 Pearl Dr NE",
    "sg:city":"Rio Rancho",
    "sg:classifiers":[
        {
            "category":"Professional",
            "subcategory":"Art Services",
            "type":"Services"
        }
    ],
    "sg:phone":"+1 505 892 6468",
    "sg:postcode":"87124",
    "sg:province":"NM",
    "sg:tags":[
        "photographer"
    ],
    "wof:name":"Pro-Vision",
    "wof:placetype":"venue"
},
  "geometry": {"coordinates":[-106.641058,35.261044],"type":"Point"}
}