{
  "type": "Feature",
  "properties": {
    "iso:country":"US",
    "sg:address":"11426 Prospect Ave NE",
    "sg:city":"Albuquerque",
    "sg:classifiers":[
        {
            "category":"Personal",
            "subcategory":"Beauty Salon",
            "type":"Services"
        }
    ],
    "sg:phone":"+1 505 238 4842",
    "sg:postcode":"87112",
    "sg:province":"NM",
    "wof:name":"Mystic Nails",
    "wof:placetype":"venue"
},
  "geometry": {"coordinates":[-106.513756,35.106998],"type":"Point"}
}