{
  "type": "Feature",
  "properties": {
    "iso:country":"US",
    "sg:address":"439 Cam del Monte Sol",
    "sg:city":"Santa Fe",
    "sg:classifiers":[
        {
            "category":"Shopping",
            "type":"Retail Goods"
        },
        {
            "category":"Museum",
            "type":"Entertainment"
        }
    ],
    "sg:phone":"+1 505 992 0711",
    "sg:postcode":"87505",
    "sg:province":"NM",
    "sg:tags":[
        "art",
        "gallery",
        "dealer"
    ],
    "sg:website":"www.chiaroscurosantafe.com",
    "wof:name":"Chiaroscuro Gallery LLC",
    "wof:placetype":"venue"
},
  "geometry": {"coordinates":[-105.92537,35.677695],"type":"Point"}
}