{
  "type": "Feature",
  "properties": {
    "iso:country":"US",
    "sg:address":"1405 Pso del Pueblo Sur",
    "sg:city":"Taos",
    "sg:classifiers":[
        {
            "category":"Personal",
            "subcategory":"Beauty Salon",
            "type":"Services"
        }
    ],
    "sg:phone":"+1 505 737 0979",
    "sg:postcode":"87571",
    "sg:province":"NM",
    "wof:name":"Jon Somes Salon",
    "wof:placetype":"venue"
},
  "geometry": {"coordinates":[-105.59554,36.371279],"type":"Point"}
}