{
  "type": "Feature",
  "properties": {
    "iso:country":"US",
    "sg:address":"1306 Broadway Blvd SE",
    "sg:city":"Albuquerque",
    "sg:classifiers":[
        {
            "category":"Food & Beverages",
            "subcategory":"Liquor & Beverages",
            "type":"Retail Goods"
        }
    ],
    "sg:phone":"+1 505 242 8542",
    "sg:postcode":"87102",
    "sg:province":"NM",
    "sg:tags":[
        "alcoholic"
    ],
    "wof:name":"Stadium Package Liquors",
    "wof:placetype":"venue"
},
  "geometry": {"coordinates":[-106.64550699999999,35.069733],"type":"Point"}
}