{
  "type": "Feature",
  "properties": {
    "iso:country":"US",
    "sg:address":"1811 Lafayette Dr NE",
    "sg:city":"Albuquerque",
    "sg:classifiers":[
        {
            "category":"Shopping",
            "subcategory":"Hobbies, Toys, & Games",
            "type":"Retail Goods"
        }
    ],
    "sg:phone":"+1 505 265 9161",
    "sg:postcode":"87106",
    "sg:province":"NM",
    "sg:tags":[
        "product",
        "ceramic"
    ],
    "wof:name":"Yhwh's Ceramics",
    "wof:placetype":"venue"
},
  "geometry": {"coordinates":[-106.60937,35.103547],"type":"Point"}
}