{
  "type": "Feature",
  "properties": {
    "iso:country":"US",
    "sg:address":"5636 State Rte 41",
    "sg:city":"Lamy",
    "sg:classifiers":[
        {
            "category":"Shopping",
            "type":"Retail Goods"
        }
    ],
    "sg:phone":"+1 505 466 2664",
    "sg:postcode":"87540",
    "sg:province":"NM",
    "sg:tags":[
        "merchandise"
    ],
    "wof:name":"Gwyn & Gwyn Arts Inc",
    "wof:placetype":"venue"
},
  "geometry": {"coordinates":[-105.946309,35.398381],"type":"Point"}
}