{
  "type": "Feature",
  "properties": {
    "addr:full":"11508 Constitution Ave NE Albuquerque NM 87112",
    "addr:housenumber":"11508",
    "addr:postcode":"87112",
    "addr:street":"Constitution Ave Ne",
    "iso:country":"US",
    "sg:address":"11508 Constitution Ave NE",
    "sg:city":"Albuquerque",
    "sg:classifiers":[
        {
            "category":"Shopping",
            "subcategory":"Gifts & Souvenirs",
            "type":"Retail Goods"
        }
    ],
    "sg:phone":"+1 505 332 9039",
    "sg:postcode":"87112",
    "sg:province":"NM",
    "wof:name":"BP Super Store Gifts & More",
    "wof:placetype":"venue"
},
  "geometry": {"coordinates":[-106.519746,35.094207],"type":"Point"}
}