{
  "type": "Feature",
  "properties": {
    "iso:country":"US",
    "sg:address":"416 Sudderth Dr",
    "sg:city":"Ruidoso",
    "sg:classifiers":[
        {
            "category":"Restaurant",
            "type":"Food & Drink"
        }
    ],
    "sg:phone":"+1 505 257 0845",
    "sg:postcode":"88345",
    "sg:province":"NM",
    "wof:name":"Santa Fe Grill",
    "wof:placetype":"venue"
},
  "geometry": {"coordinates":[-105.63856,33.322843],"type":"Point"}
}