{
  "type": "Feature",
  "properties": {
    "iso:country":"US",
    "sg:address":"708 Silver Heights Blvd",
    "sg:city":"Silver City",
    "sg:classifiers":[
        {
            "category":"Restaurant",
            "type":"Food & Drink"
        }
    ],
    "sg:phone":"+1 505 538 5666",
    "sg:postcode":"88061",
    "sg:province":"NM",
    "sg:tags":[
        "drinking",
        "eating"
    ],
    "wof:name":"Red Barn Family Steakhouse The",
    "wof:placetype":"venue"
},
  "geometry": {"coordinates":[-108.267932,32.7829],"type":"Point"}
}