{
  "type": "Feature",
  "properties": {
    "addr:full":"824 E Yeso Dr Hobbs NM 88240",
    "addr:housenumber":"824",
    "addr:postcode":"88240",
    "addr:street":"E Yeso Dr",
    "iso:country":"US",
    "sg:address":"824 E Yeso Dr",
    "sg:city":"Hobbs",
    "sg:classifiers":[
        {
            "category":"Personal",
            "subcategory":"Beauty Salon",
            "type":"Services"
        }
    ],
    "sg:phone":"+1 505 433 0447",
    "sg:postcode":"88240",
    "sg:province":"NM",
    "wof:name":"WYLD Hair Station",
    "wof:placetype":"venue"
},
  "geometry": {"coordinates":[-103.12355100000001,32.716707],"type":"Point"}
}