{
  "type": "Feature",
  "properties": {
    "iso:country":"US",
    "sg:address":"2300 Princeton Dr NE",
    "sg:city":"Albuquerque",
    "sg:classifiers":[
        {
            "category":"Professional",
            "subcategory":"Management & Consulting",
            "type":"Services"
        }
    ],
    "sg:phone":"+1 505 345 2700",
    "sg:postcode":"87106",
    "sg:province":"NM",
    "wof:name":"Pinnacle Marketing Inc",
    "wof:placetype":"venue"
},
  "geometry": {"coordinates":[-106.620406,35.109183],"type":"Point"}
}