{
  "type": "Feature",
  "properties": {
    "iso:country":"US",
    "sg:address":"204 San Mateo Blvd SE",
    "sg:city":"Albuquerque",
    "sg:classifiers":[
        {
            "category":"Shopping",
            "subcategory":"Used Merchandise",
            "type":"Retail Goods"
        }
    ],
    "sg:phone":"+1 505 217 0130",
    "sg:postcode":"87108",
    "sg:province":"NM",
    "sg:tags":[
        "building",
        "material"
    ],
    "wof:name":"Restore-Greater Abq Habitat",
    "wof:placetype":"venue"
},
  "geometry": {"coordinates":[-106.586163,35.075738],"type":"Point"}
}