{
  "type": "Feature",
  "properties": {
    "addr:full":"12 Palomas Rd Los Lunas NM 87031",
    "addr:housenumber":"12",
    "addr:postcode":"87031",
    "addr:street":"Palomas Rd",
    "iso:country":"US",
    "sg:address":"12 Palomas Rd",
    "sg:city":"Los Lunas",
    "sg:classifiers":[
        {
            "category":"Autos & Motor Vehicles",
            "subcategory":"Automobile Sales",
            "type":"Retail Goods"
        }
    ],
    "sg:phone":"+1 505 866 7201",
    "sg:postcode":"87031",
    "sg:province":"NM",
    "sg:tags":[
        "used"
    ],
    "wof:name":"ABC Trailer Sales",
    "wof:placetype":"venue"
},
  "geometry": {"coordinates":[-106.676705,34.807159],"type":"Point"}
}