{
  "type": "Feature",
  "properties": {
    "iso:country":"US",
    "sg:address":"500 11th St NW",
    "sg:city":"Albuquerque",
    "sg:classifiers":[
        {
            "category":"Building & Trades",
            "subcategory":"Electrical",
            "type":"Services"
        }
    ],
    "sg:phone":"+1 505 244 9490",
    "sg:postcode":"87102",
    "sg:province":"NM",
    "sg:tags":[
        "electrician"
    ],
    "wof:name":"Baird Electric",
    "wof:placetype":"venue"
},
  "geometry": {"coordinates":[-106.659019,35.089981],"type":"Point"}
}