{
  "type": "Feature",
  "properties": {
    "iso:country":"US",
    "sg:address":"2921 Carlisle Blvd NE",
    "sg:city":"Albuquerque",
    "sg:classifiers":[
        {
            "category":"Social Services",
            "type":"Services"
        }
    ],
    "sg:phone":"+1 505 266 0288",
    "sg:postcode":"87110",
    "sg:province":"NM",
    "sg:tags":[
        "counselor",
        "marriage",
        "family"
    ],
    "wof:name":"Susan Sabini",
    "wof:placetype":"venue"
},
  "geometry": {"coordinates":[-106.60420499999999,35.116158],"type":"Point"}
}