{
  "type": "Feature",
  "properties": {
    "iso:country":"US",
    "sg:address":"7500 Bluewater Rd NW",
    "sg:city":"Albuquerque",
    "sg:classifiers":[
        {
            "category":"Professional",
            "subcategory":"Management & Consulting",
            "type":"Services"
        }
    ],
    "sg:phone":"+1 505 839 3000",
    "sg:postcode":"87121",
    "sg:province":"NM",
    "sg:tags":[
        "marketing",
        "program"
    ],
    "sg:website":"www.riogrande.com",
    "wof:name":"Rio Grande Jewelers' Supply",
    "wof:placetype":"venue"
},
  "geometry": {"coordinates":[-106.71727199999999,35.085366],"type":"Point"}
}