{
  "type": "Feature",
  "properties": {
    "iso:country":"US",
    "sg:address":"900 4th St SW",
    "sg:city":"Albuquerque",
    "sg:classifiers":[
        {
            "category":"Wholesale",
            "subcategory":"Durable Goods & Equipment",
            "type":"Manufacturing & Wholesale Goods"
        }
    ],
    "sg:phone":"+1 505 247 8484",
    "sg:postcode":"87102",
    "sg:province":"NM",
    "wof:name":"Cristy Records",
    "wof:placetype":"venue"
},
  "geometry": {"coordinates":[-106.653296,35.075762],"type":"Point"}
}