{
  "type": "Feature",
  "properties": {
    "iso:country":"US",
    "sg:address":"29 Rodeo Rd",
    "sg:city":"Silver City",
    "sg:classifiers":[
        {
            "category":"Utilities",
            "subcategory":"Refuse",
            "type":"Services"
        }
    ],
    "sg:phone":"+1 505 538 2388",
    "sg:postcode":"88061",
    "sg:province":"NM",
    "sg:tags":[
        "system"
    ],
    "wof:name":"Grant County Sanitation Svc",
    "wof:placetype":"venue"
},
  "geometry": {"coordinates":[-108.244428,32.776662],"type":"Point"}
}