{
  "type": "Feature",
  "properties": {
    "iso:country":"US",
    "sg:address":"3790 Luna de Miel",
    "sg:city":"Santa Fe",
    "sg:classifiers":[
        {
            "category":"Building & Trades",
            "subcategory":"Construction",
            "type":"Services"
        }
    ],
    "sg:phone":"+1 505 474 7701",
    "sg:postcode":"87507",
    "sg:province":"NM",
    "sg:tags":[
        "roofing",
        "contractor"
    ],
    "wof:name":"Salcido's Roofing Co",
    "wof:placetype":"venue"
},
  "geometry": {"coordinates":[-106.046617,35.637422],"type":"Point"}
}