{
  "type": "Feature",
  "properties": {
    "iso:country":"US",
    "sg:address":"1621 S Prince St",
    "sg:city":"Clovis",
    "sg:classifiers":[
        {
            "category":"Professional",
            "subcategory":"Research",
            "type":"Services"
        }
    ],
    "sg:phone":"+1 505 762 1956",
    "sg:postcode":"88101",
    "sg:province":"NM",
    "sg:tags":[
        "environmental",
        "ecological"
    ],
    "wof:name":"GMC Environmental Svc",
    "wof:placetype":"venue"
},
  "geometry": {"coordinates":[-103.19630600000001,34.381106],"type":"Point"}
}