{
  "type": "Feature",
  "properties": {
    "iso:country":"US",
    "sg:address":"7336 Triana Pl NW",
    "sg:city":"Albuquerque",
    "sg:classifiers":[
        {
            "category":"Shopping",
            "subcategory":"Department Store",
            "type":"Retail Goods"
        }
    ],
    "sg:phone":"+1 505 922 9559",
    "sg:postcode":"87114",
    "sg:province":"NM",
    "wof:name":"Hookahkingscom",
    "wof:placetype":"venue"
},
  "geometry": {"coordinates":[-106.73704499999999,35.192187],"type":"Point"}
}