{
  "type": "Feature",
  "properties": {
    "addr:full":"612 E Murray Dr Farmington NM 87401",
    "addr:housenumber":"612",
    "addr:postcode":"87401",
    "addr:street":"E Murray Dr",
    "iso:country":"US",
    "sg:address":"612 E Murray Dr",
    "sg:city":"Farmington",
    "sg:classifiers":[
        {
            "category":"Professional",
            "subcategory":"Engineering",
            "type":"Services"
        }
    ],
    "sg:phone":"+1 505 325 5667",
    "sg:postcode":"87401",
    "sg:province":"NM",
    "sg:tags":[
        "engineer"
    ],
    "wof:name":"On Site Technologies",
    "wof:placetype":"venue"
},
  "geometry": {"coordinates":[-108.199054,36.719603],"type":"Point"}
}