{
  "type": "Feature",
  "properties": {
    "iso:country":"US",
    "sg:address":"15 Shasta Ct",
    "sg:city":"Bluewater",
    "sg:classifiers":[
        {
            "category":"Education",
            "subcategory":"School",
            "type":"Public Place"
        }
    ],
    "sg:phone":"+1 505 876 2522",
    "sg:postcode":"87008",
    "sg:province":"NM",
    "wof:name":"Bluewater Elementary School",
    "wof:placetype":"venue"
},
  "geometry": {"coordinates":[-106.37911,35.099791],"type":"Point"}
}