{
  "type": "Feature",
  "properties": {
    "iso:country":"US",
    "sg:address":"2543 Morningside Dr NE",
    "sg:city":"Albuquerque",
    "sg:classifiers":[
        {
            "category":"Personal",
            "subcategory":"Beauty Salon",
            "type":"Services"
        }
    ],
    "sg:phone":"+1 505 837 1313",
    "sg:postcode":"87110",
    "sg:province":"NM",
    "sg:tags":[
        "manicuring"
    ],
    "wof:name":"Personails",
    "wof:placetype":"venue"
},
  "geometry": {"coordinates":[-106.599321,35.107671],"type":"Point"}
}