{
  "type": "Feature",
  "properties": {
    "addr:full":"2668 Hot Peppers Rd Anthony NM 88081",
    "addr:housenumber":"2668",
    "addr:postcode":"88081",
    "addr:street":"Hot Peppers Rd",
    "iso:country":"US",
    "sg:address":"2668 Hot Peppers Rd",
    "sg:city":"Anthony",
    "sg:classifiers":[
        {
            "category":"Freight",
            "type":"Transportation"
        }
    ],
    "sg:phone":"+1 505 824 3090",
    "sg:postcode":"88081",
    "sg:province":"NM",
    "sg:tags":[
        "arrangement"
    ],
    "wof:name":"Summit International",
    "wof:placetype":"venue"
},
  "geometry": {"coordinates":[-106.47554,32.067333],"type":"Point"}
}