{
  "type": "Feature",
  "properties": {
    "iso:country":"US",
    "sg:address":"6025 Coronado Ave NE",
    "sg:city":"Albuquerque",
    "sg:classifiers":[
        {
            "category":"Building & Trades",
            "subcategory":"Electrical",
            "type":"Services"
        }
    ],
    "sg:phone":"+1 505 828 1213",
    "sg:postcode":"87109",
    "sg:province":"NM",
    "sg:tags":[
        "electrical",
        "electric",
        "contractor"
    ],
    "wof:name":"Laben Electric Company",
    "wof:placetype":"venue"
},
  "geometry": {"coordinates":[-106.58065999999999,35.165725],"type":"Point"}
}