{
  "type": "Feature",
  "properties": {
    "addr:full":"12 Berm St NW Albuquerque NM 87120",
    "addr:housenumber":"12",
    "addr:postcode":"87120",
    "addr:street":"Berm St Nw",
    "iso:country":"US",
    "sg:address":"12 Berm St NW",
    "sg:city":"Albuquerque",
    "sg:classifiers":[
        {
            "category":"Professional",
            "subcategory":"Business Services",
            "type":"Services"
        }
    ],
    "sg:phone":"+1 505 898 4695",
    "sg:postcode":"87120",
    "sg:province":"NM",
    "wof:name":"Asid",
    "wof:placetype":"venue"
},
  "geometry": {"coordinates":[-106.69616600000001,35.140442],"type":"Point"}
}