{
  "type": "Feature",
  "properties": {
    "iso:country":"US",
    "sg:address":"12 Berm St NW",
    "sg:city":"Albuquerque",
    "sg:classifiers":[
        {
            "category":"Professional",
            "subcategory":"Business Services",
            "type":"Services"
        }
    ],
    "sg:phone":"+1 505 898 4695",
    "sg:postcode":"87120",
    "sg:province":"NM",
    "wof:name":"Asid",
    "wof:placetype":"venue"
},
  "geometry": {"coordinates":[-106.696166,35.140442],"type":"Point"}
}