{
  "type": "Feature",
  "properties": {
    "iso:country":"US",
    "sg:address":"2107 Cerrillos Rd",
    "sg:city":"Santa Fe",
    "sg:classifiers":[
        {
            "category":"Shopping",
            "subcategory":"Books",
            "type":"Retail Goods"
        }
    ],
    "sg:phone":"+1 505 438 2792",
    "sg:postcode":"87505",
    "sg:province":"NM",
    "sg:tags":[
        "comic"
    ],
    "wof:name":"Good Times Toons & Tunes",
    "wof:placetype":"venue"
},
  "geometry": {"coordinates":[-105.97741000000001,35.662633],"type":"Point"}
}