{
  "type": "Feature",
  "properties": {
    "iso:country":"US",
    "sg:address":"1305 8th St",
    "sg:city":"Tularosa",
    "sg:classifiers":[
        {
            "category":"Education",
            "subcategory":"School",
            "type":"Public Place"
        }
    ],
    "sg:phone":"+1 505 585 8876",
    "sg:postcode":"88352",
    "sg:province":"NM",
    "wof:name":"Tularosa Municipal Swimmng Pl",
    "wof:placetype":"venue"
},
  "geometry": {"coordinates":[-106.024542,33.075384],"type":"Point"}
}