{
  "type": "Feature",
  "properties": {
    "iso:country":"US",
    "sg:address":"1103 San Mateo Blvd SE",
    "sg:city":"Albuquerque",
    "sg:classifiers":[
        {
            "category":"Retail",
            "subcategory":"Auto Repair",
            "type":"Services"
        }
    ],
    "sg:phone":"+1 505 265 1095",
    "sg:postcode":"87108",
    "sg:province":"NM",
    "sg:tags":[
        "general"
    ],
    "wof:name":"Ridgecrest Automotive",
    "wof:placetype":"venue"
},
  "geometry": {"coordinates":[-106.58645,35.063838],"type":"Point"}
}