{
  "type": "Feature",
  "properties": {
    "addr:full":"529 Price Ranch Rd Elida NM 88116",
    "addr:housenumber":"529",
    "addr:postcode":"88116",
    "addr:street":"Price Ranch Rd",
    "iso:country":"US",
    "sg:address":"529 Price Ranch Rd",
    "sg:city":"Elida",
    "sg:classifiers":[
        {
            "category":"Farming",
            "subcategory":"Livestock Farm",
            "type":"Manufacturing & Wholesale Goods"
        }
    ],
    "sg:phone":"+1 505 478 2471",
    "sg:postcode":"88116",
    "sg:province":"NM",
    "sg:tags":[
        "ranch"
    ],
    "wof:name":"Mesa Ranch Inc",
    "wof:placetype":"venue"
},
  "geometry": {"coordinates":[-103.77507,34.180906],"type":"Point"}
}