{
  "type": "Feature",
  "properties": {
    "iso:country":"US",
    "sg:address":"2069 Clearwater Loop NE",
    "sg:city":"Rio Rancho",
    "sg:classifiers":[
        {
            "category":"Professional",
            "subcategory":"Management & Consulting",
            "type":"Services"
        }
    ],
    "sg:phone":"+1 505 867 9585",
    "sg:postcode":"87144",
    "sg:province":"NM",
    "sg:tags":[
        "consultant"
    ],
    "wof:name":"Wildflower Consulting",
    "wof:placetype":"venue"
},
  "geometry": {"coordinates":[-106.59291899999999,35.293587],"type":"Point"}
}