{
  "type": "Feature",
  "properties": {
    "iso:country":"US",
    "sg:address":"1572 Center Dr",
    "sg:city":"Santa Fe",
    "sg:classifiers":[
        {
            "category":"Retail",
            "subcategory":"Repair Shop",
            "type":"Services"
        }
    ],
    "sg:phone":"+1 505 473 1280",
    "sg:postcode":"87507",
    "sg:province":"NM",
    "wof:name":"Furniture Shop",
    "wof:placetype":"venue"
},
  "geometry": {"coordinates":[-106.025116,35.635913],"type":"Point"}
}