{
  "type": "Feature",
  "properties": {
    "addr:full":"1400 Pile St Clovis NM 88101",
    "addr:housenumber":"1400",
    "addr:postcode":"88101",
    "addr:street":"Pile St",
    "iso:country":"US",
    "sg:address":"1400 Pile St",
    "sg:city":"Clovis",
    "sg:classifiers":[
        {
            "category":"Professional",
            "subcategory":"Accounting & Tax Preparation",
            "type":"Services"
        }
    ],
    "sg:phone":"+1 505 769 1944",
    "sg:postcode":"88101",
    "sg:province":"NM",
    "sg:tags":[
        "accountant"
    ],
    "wof:name":"Turner & Seefeld",
    "wof:placetype":"venue"
},
  "geometry": {"coordinates":[-103.20414700000001,34.413879],"type":"Point"}
}