{
  "type": "Feature",
  "properties": {
    "addr:full":"1019 Claudine St NE Albuquerque NM 87112",
    "addr:housenumber":"1019",
    "addr:postcode":"87112",
    "addr:street":"Claudine St Ne",
    "iso:country":"US",
    "sg:address":"1019 Claudine St NE",
    "sg:city":"Albuquerque",
    "sg:classifiers":[
        {
            "category":"Building & Trades",
            "subcategory":"Construction",
            "type":"Services"
        }
    ],
    "sg:phone":"+1 505 293 4061",
    "sg:postcode":"87112",
    "sg:province":"NM",
    "sg:tags":[
        "house"
    ],
    "wof:name":"Residential Maintenance Svc",
    "wof:placetype":"venue"
},
  "geometry": {"coordinates":[-106.51991599999999,35.090003],"type":"Point"}
}