{
  "type": "Feature",
  "properties": {
    "addr:full":"6201 Karlson Dr NE Albuquerque NM 87113",
    "addr:housenumber":"6201",
    "addr:postcode":"87113",
    "addr:street":"Karlson Dr Ne",
    "iso:country":"US",
    "sg:address":"6201 Karlson Dr NE",
    "sg:city":"Albuquerque",
    "sg:classifiers":[
        {
            "category":"Building & Trades",
            "subcategory":"Landscaping Services",
            "type":"Services"
        }
    ],
    "sg:phone":"+1 505 823 9845",
    "sg:postcode":"87113",
    "sg:province":"NM",
    "wof:name":"Chavez Landscaping",
    "wof:placetype":"venue"
},
  "geometry": {"coordinates":[-106.578389,35.179691],"type":"Point"}
}