{
  "type": "Feature",
  "properties": {
    "iso:country":"US",
    "sg:address":"411 N Bayard St",
    "sg:city":"Silver City",
    "sg:classifiers":[
        {
            "category":"Bars & Pubs",
            "type":"Food & Drink"
        }
    ],
    "sg:phone":"+1 505 537 2782",
    "sg:postcode":"88061",
    "sg:province":"NM",
    "wof:name":"Brown Derby Niteclub",
    "wof:placetype":"venue"
},
  "geometry": {"coordinates":[-108.27928,32.771991],"type":"Point"}
}