{
  "type": "Feature",
  "properties": {
    "iso:country":"US",
    "sg:address":"11915 Hopi Rd NE",
    "sg:city":"Albuquerque",
    "sg:classifiers":[
        {
            "category":"Professional",
            "subcategory":"Accounting & Tax Preparation",
            "type":"Services"
        }
    ],
    "sg:phone":"+1 505 294 1580",
    "sg:postcode":"87123",
    "sg:province":"NM",
    "sg:tags":[
        "return",
        "filing"
    ],
    "wof:name":"John Love Tax Svc",
    "wof:placetype":"venue"
},
  "geometry": {"coordinates":[-106.514124,35.073167],"type":"Point"}
}