{
  "type": "Feature",
  "properties": {
    "iso:country":"US",
    "sg:address":"4 Lost Canyon",
    "sg:city":"Edgewood",
    "sg:classifiers":[
        {
            "category":"Building & Trades",
            "subcategory":"Electrical",
            "type":"Services"
        }
    ],
    "sg:phone":"+1 505 286 6318",
    "sg:postcode":"87059",
    "sg:province":"NM",
    "sg:tags":[
        "electrical",
        "contractor"
    ],
    "wof:name":"A & L Electric",
    "wof:placetype":"venue"
},
  "geometry": {"coordinates":[-106.20996599999999,35.033592],"type":"Point"}
}