{
  "type": "Feature",
  "properties": {
    "iso:country":"US",
    "sg:address":"4610 Eubank Blvd NE",
    "sg:city":"Albuquerque",
    "sg:classifiers":[
        {
            "category":"Shopping",
            "type":"Retail Goods"
        }
    ],
    "sg:phone":"+1 505 323 1180",
    "sg:postcode":"87111",
    "sg:province":"NM",
    "sg:tags":[
        "art",
        "gallery",
        "dealer"
    ],
    "wof:name":"Homart",
    "wof:placetype":"venue"
},
  "geometry": {"coordinates":[-106.533252,35.131532],"type":"Point"}
}