{
  "type": "Feature",
  "properties": {
    "addr:full":"31130 US Hwy 64 Cimarron NM 87714",
    "addr:postcode":"31130;87714",
    "addr:street":"Us Hwy 64",
    "iso:country":"US",
    "sg:address":"31130 US Hwy 64",
    "sg:city":"Cimarron",
    "sg:classifiers":[
        {
            "category":"Travel",
            "subcategory":"Campground",
            "type":"Entertainment"
        }
    ],
    "sg:phone":"+1 505 376 2343",
    "sg:postcode":"87714",
    "sg:province":"NM",
    "sg:tags":[
        "camp"
    ],
    "wof:name":"Ponil Camp Grounds",
    "wof:placetype":"venue"
},
  "geometry": {"coordinates":[-104.901268,36.517289],"type":"Point"}
}