{
  "type": "Feature",
  "properties": {
    "iso:country":"US",
    "sg:address":"115 Don Gaspar Ave",
    "sg:city":"Santa Fe",
    "sg:classifiers":[
        {
            "category":"Shopping",
            "subcategory":"Jewelry",
            "type":"Retail Goods"
        }
    ],
    "sg:phone":"+1 505 984 0040",
    "sg:postcode":"87501",
    "sg:province":"NM",
    "wof:name":"Golden Eye",
    "wof:placetype":"venue"
},
  "geometry": {"coordinates":[-105.93965,35.686612],"type":"Point"}
}