{
  "type": "Feature",
  "properties": {
    "addr:full":"3916 Futura Dr Roswell NM 88201",
    "addr:housenumber":"3916",
    "addr:postcode":"88201",
    "addr:street":"Futura Dr",
    "iso:country":"US",
    "sg:address":"3916 Futura Dr",
    "sg:city":"Roswell",
    "sg:classifiers":[
        {
            "category":"Building & Trades",
            "subcategory":"Construction",
            "type":"Services"
        }
    ],
    "sg:phone":"+1 505 623 8312",
    "sg:postcode":"88201",
    "sg:province":"NM",
    "sg:tags":[
        "interior",
        "residential",
        "remodeling",
        "contractor"
    ],
    "wof:name":"A G Construction Company",
    "wof:placetype":"venue"
},
  "geometry": {"coordinates":[-104.515608,33.445831],"type":"Point"}
}