{
  "type": "Feature",
  "properties": {
    "addr:full":"908 N Orchard Ave Farmington NM 87401",
    "addr:housenumber":"908",
    "addr:postcode":"87401",
    "addr:street":"N Orchard Ave",
    "iso:country":"US",
    "sg:address":"908 N Orchard Ave",
    "sg:city":"Farmington",
    "sg:classifiers":[
        {
            "category":"Professional",
            "subcategory":"Secretarial Services",
            "type":"Services"
        }
    ],
    "sg:phone":"+1 505 327 0910",
    "sg:postcode":"87401",
    "sg:province":"NM",
    "sg:tags":[
        "reporting"
    ],
    "wof:name":"Professional Office Associates",
    "wof:placetype":"venue"
},
  "geometry": {"coordinates":[-108.20508599999999,36.738573],"type":"Point"}
}