{
  "type": "Feature",
  "properties": {
    "iso:country":"US",
    "sg:address":"6205 Peachtree Pl NE",
    "sg:city":"Albuquerque",
    "sg:classifiers":[
        {
            "category":"Utilities",
            "subcategory":"Telephone",
            "type":"Services"
        }
    ],
    "sg:phone":"+1 505 980 9809",
    "sg:postcode":"87111",
    "sg:province":"NM",
    "sg:tags":[
        "communications"
    ],
    "wof:name":"E- Steam Ventures",
    "wof:placetype":"venue"
},
  "geometry": {"coordinates":[-106.506415,35.150719],"type":"Point"}
}