{
  "type": "Feature",
  "properties": {
    "iso:country":"US",
    "sg:address":"1104 E Manana Blvd",
    "sg:city":"Clovis",
    "sg:classifiers":[
        {
            "category":"Real Estate",
            "subcategory":"Real Estate Agent",
            "type":"Services"
        }
    ],
    "sg:phone":"+1 505 769 2663",
    "sg:postcode":"88101",
    "sg:province":"NM",
    "wof:name":"Kenneth Realty",
    "wof:placetype":"venue"
},
  "geometry": {"coordinates":[-103.19537,34.426787],"type":"Point"}
}