{
  "type": "Feature",
  "properties": {
    "iso:country":"US",
    "sg:address":"1925 Aspen Dr",
    "sg:city":"Santa Fe",
    "sg:classifiers":[
        {
            "category":"Professional",
            "subcategory":"Management & Consulting",
            "type":"Services"
        }
    ],
    "sg:phone":"+1 505 471 3681",
    "sg:postcode":"87505",
    "sg:province":"NM",
    "sg:tags":[
        "consultant",
        "business"
    ],
    "wof:name":"Peaseprofessional Services",
    "wof:placetype":"venue"
},
  "geometry": {"coordinates":[-105.97068899999999,35.655309],"type":"Point"}
}