{
  "type": "Feature",
  "properties": {
    "iso:country":"US",
    "sg:address":"724 Silver Ave SW",
    "sg:city":"Albuquerque",
    "sg:classifiers":[
        {
            "category":"Government",
            "subcategory":"Fire Station",
            "type":"Public Place"
        }
    ],
    "sg:phone":"+1 505 768 3473",
    "sg:postcode":"87102",
    "sg:province":"NM",
    "sg:tags":[
        "department"
    ],
    "wof:name":"Fire Dept Employment Info",
    "wof:placetype":"venue"
},
  "geometry": {"coordinates":[-106.65651699999999,35.08308],"type":"Point"}
}