{
  "type": "Feature",
  "properties": {
    "iso:country":"US",
    "sg:address":"820 E Bender Blvd",
    "sg:city":"Hobbs",
    "sg:classifiers":[
        {
            "category":"Building & Trades",
            "subcategory":"Plumbing",
            "type":"Services"
        }
    ],
    "sg:phone":"+1 505 393 1340",
    "sg:postcode":"88240",
    "sg:province":"NM",
    "sg:tags":[
        "heating",
        "contractor"
    ],
    "wof:name":"A G Custom Sheet METAL & AC",
    "wof:placetype":"venue"
},
  "geometry": {"coordinates":[-103.127386,32.725786],"type":"Point"}
}