{
  "type": "Feature",
  "properties": {
    "iso:country":"US",
    "sg:address":"2006 Dark Canyon Rd",
    "sg:city":"Carlsbad",
    "sg:classifiers":[
        {
            "category":"Farming",
            "subcategory":"Livestock Farm",
            "type":"Manufacturing & Wholesale Goods"
        }
    ],
    "sg:phone":"+1 505 981 2443",
    "sg:postcode":"88220",
    "sg:province":"NM",
    "sg:tags":[
        "ranch"
    ],
    "wof:name":"Davidson Ranch Two",
    "wof:placetype":"venue"
},
  "geometry": {"coordinates":[-104.55907999999999,32.30215],"type":"Point"}
}