{
  "type": "Feature",
  "properties": {
    "iso:country":"US",
    "sg:address":"780 Hwy 22",
    "sg:city":"Pena Blanca",
    "sg:classifiers":[
        {
            "category":"Building & Trades",
            "subcategory":"Construction",
            "type":"Services"
        }
    ],
    "sg:phone":"+1 505 465 0341",
    "sg:postcode":"87041",
    "sg:province":"NM",
    "sg:tags":[
        "general",
        "contractor"
    ],
    "wof:name":"William H Hall Construction",
    "wof:placetype":"venue"
},
  "geometry": {"coordinates":[-106.338493,35.568143],"type":"Point"}
}