{
  "type": "Feature",
  "properties": {
    "addr:full":"1322 Frontage Rd Belen NM 87002",
    "addr:housenumber":"1322",
    "addr:postcode":"87002",
    "addr:street":"Frontage Rd",
    "iso:country":"US",
    "sg:address":"1322 Frontage Rd",
    "sg:city":"Belen",
    "sg:classifiers":[
        {
            "category":"Food & Beverages",
            "subcategory":"Bakery",
            "type":"Retail Goods"
        }
    ],
    "sg:phone":"+1 505 864 4784",
    "sg:postcode":"87002",
    "sg:province":"NM",
    "wof:name":"Donut King",
    "wof:placetype":"venue"
},
  "geometry": {"coordinates":[-106.766566,34.690451],"type":"Point"}
}