{
  "type": "Feature",
  "properties": {
    "addr:full":"200 N Grimes St Hobbs NM 88240",
    "addr:housenumber":"200",
    "addr:postcode":"88240",
    "addr:street":"N Grimes St",
    "iso:country":"US",
    "sg:address":"200 N Grimes St",
    "sg:city":"Hobbs",
    "sg:classifiers":[
        {
            "category":"Mining & Drilling",
            "type":"Manufacturing & Wholesale Goods"
        }
    ],
    "sg:phone":"+1 505 393 5133",
    "sg:postcode":"88240",
    "sg:province":"NM",
    "sg:tags":[
        "field",
        "oil"
    ],
    "wof:name":"Wilson Supply",
    "wof:placetype":"venue"
},
  "geometry": {"coordinates":[-103.14483,32.703485],"type":"Point"}
}