{
  "type": "Feature",
  "properties": {
    "addr:full":"301 E Lohman Ave Las Cruces NM 88001",
    "addr:housenumber":"301",
    "addr:postcode":"88001",
    "addr:street":"E Lohman Ave",
    "iso:country":"US",
    "sg:address":"301 E Lohman Ave",
    "sg:city":"Las Cruces",
    "sg:classifiers":[
        {
            "category":"Health Services",
            "subcategory":"Doctor",
            "type":"Services"
        }
    ],
    "sg:phone":"+1 505 524 4900",
    "sg:postcode":"88001",
    "sg:province":"NM",
    "sg:tags":[
        "dentist"
    ],
    "wof:name":"Emergency & Family Dental PC",
    "wof:placetype":"venue"
},
  "geometry": {"coordinates":[-106.77442000000001,32.306849],"type":"Point"}
}