{
  "type": "Feature",
  "properties": {
    "iso:country":"US",
    "sg:address":"111 Central Ave",
    "sg:city":"Carrizozo",
    "sg:classifiers":[
        {
            "category":"Restaurant",
            "type":"Food & Drink"
        }
    ],
    "sg:phone":"+1 505 648 2964",
    "sg:postcode":"88301",
    "sg:province":"NM",
    "wof:name":"Four Winds Restaurant & Lounge",
    "wof:placetype":"venue"
},
  "geometry": {"coordinates":[-105.872325,33.645386],"type":"Point"}
}