{
  "type": "Feature",
  "properties": {
    "iso:country":"US",
    "sg:address":"1682 Tierra del Rio NW",
    "sg:city":"Albuquerque",
    "sg:classifiers":[
        {
            "category":"Social Services",
            "type":"Services"
        }
    ],
    "sg:phone":"+1 505 228 1848",
    "sg:postcode":"87107",
    "sg:province":"NM",
    "wof:name":"Blackwood Counceling Serv",
    "wof:placetype":"venue"
},
  "geometry": {"coordinates":[-106.656206,35.139704],"type":"Point"}
}