{
  "type": "Feature",
  "properties": {
    "addr:full":"684 Lisbon Ave SE Rio Rancho NM 87124",
    "addr:housenumber":"684",
    "addr:postcode":"87124",
    "addr:street":"Lisbon Ave Se",
    "iso:country":"US",
    "sg:address":"684 Lisbon Ave SE",
    "sg:city":"Rio Rancho",
    "sg:classifiers":[
        {
            "category":"Professional",
            "subcategory":"Computer Services",
            "type":"Services"
        }
    ],
    "sg:phone":"+1 505 892 6361",
    "sg:postcode":"87124",
    "sg:province":"NM",
    "sg:tags":[
        "graphics"
    ],
    "wof:name":"Plasma Storm Graphics",
    "wof:placetype":"venue"
},
  "geometry": {"coordinates":[-106.710582,35.248374],"type":"Point"}
}