{
  "type": "Feature",
  "properties": {
    "addr:full":"709 Haines Ave NW Albuquerque NM 87102",
    "addr:housenumber":"709",
    "addr:postcode":"87102",
    "addr:street":"Haines Ave Nw",
    "iso:country":"US",
    "sg:address":"709 Haines Ave NW",
    "sg:city":"Albuquerque",
    "sg:classifiers":[
        {
            "category":"Manufacturing",
            "subcategory":"Building Materials",
            "type":"Manufacturing & Wholesale Goods"
        },
        {
            "category":"Home & Garden",
            "subcategory":"Furniture",
            "type":"Retail Goods"
        }
    ],
    "sg:phone":"+1 505 872 2067",
    "sg:postcode":"87102",
    "sg:province":"NM",
    "sg:tags":[
        "manufacture",
        "cabinet"
    ],
    "wof:name":"Casework Technologies Ltd",
    "wof:placetype":"venue"
},
  "geometry": {"coordinates":[-106.654127,35.103801],"type":"Point"}
}