{
  "type": "Feature",
  "properties": {
    "addr:full":"1427 Ave de Las America Santa Fe NM 87507",
    "addr:housenumber":"1427",
    "addr:postcode":"87507",
    "addr:street":"Ave De Las America",
    "iso:country":"US",
    "sg:address":"1427 Ave de Las America",
    "sg:city":"Santa Fe",
    "sg:classifiers":[
        {
            "category":"Home & Garden",
            "subcategory":"Furniture",
            "type":"Retail Goods"
        }
    ],
    "sg:phone":"+1 505 474 9398",
    "sg:postcode":"87507",
    "sg:province":"NM",
    "sg:tags":[
        "mattress"
    ],
    "wof:name":"Denver Mattress Co",
    "wof:placetype":"venue"
},
  "geometry": {"coordinates":[-106.00246199999999,35.646643],"type":"Point"}
}