{
  "type": "Feature",
  "properties": {
    "addr:full":"126 General Somervell St NE Albuquerque NM 87123",
    "addr:housenumber":"126",
    "addr:postcode":"87123",
    "addr:street":"General Somervell St Ne",
    "iso:country":"US",
    "sg:address":"126 General Somervell St NE",
    "sg:city":"Albuquerque",
    "sg:classifiers":[
        {
            "category":"Building & Trades",
            "subcategory":"Plumbing",
            "type":"Services"
        }
    ],
    "sg:phone":"+1 505 332 9734",
    "sg:postcode":"87123",
    "sg:province":"NM",
    "sg:tags":[
        "contractor"
    ],
    "wof:name":"AC Services",
    "wof:placetype":"venue"
},
  "geometry": {"coordinates":[-106.54235300000001,35.074163],"type":"Point"}
}