{
  "type": "Feature",
  "properties": {
    "iso:country":"US",
    "sg:address":"12524 Piru Blvd SE",
    "sg:city":"Albuquerque",
    "sg:classifiers":[
        {
            "category":"Shopping",
            "subcategory":"Computers & Home Electronics",
            "type":"Retail Goods"
        }
    ],
    "sg:phone":"+1 505 228 9242",
    "sg:postcode":"87123",
    "sg:province":"NM",
    "sg:tags":[
        "sales"
    ],
    "wof:name":"Omni Tek Inc",
    "wof:placetype":"venue"
},
  "geometry": {"coordinates":[-106.505004,35.061272],"type":"Point"}
}