{
  "type": "Feature",
  "properties": {
    "iso:country":"US",
    "sg:address":"1501 Alfredo Garcia Ct NW",
    "sg:city":"Albuquerque",
    "sg:classifiers":[
        {
            "category":"Food & Beverages",
            "subcategory":"Candy",
            "type":"Retail Goods"
        }
    ],
    "sg:phone":"+1 505 342 0941",
    "sg:postcode":"87107",
    "sg:province":"NM",
    "sg:tags":[
        "nut"
    ],
    "wof:name":"Paradox",
    "wof:placetype":"venue"
},
  "geometry": {"coordinates":[-106.65998399999999,35.158048],"type":"Point"}
}