{
  "type": "Feature",
  "properties": {
    "iso:country":"US",
    "sg:address":"1600 N Main Ave",
    "sg:city":"Lovington",
    "sg:classifiers":[
        {
            "category":"Health Services",
            "subcategory":"Doctor",
            "type":"Services"
        }
    ],
    "sg:phone":"+1 505 396 3529",
    "sg:postcode":"88260",
    "sg:province":"NM",
    "sg:tags":[
        "medical"
    ],
    "wof:name":"Amar Bains MD",
    "wof:placetype":"venue"
},
  "geometry": {"coordinates":[-103.34812,32.962891],"type":"Point"}
}