{
  "type": "Feature",
  "properties": {
    "iso:country":"US",
    "sg:address":"208 Grant Ave",
    "sg:city":"Santa Fe",
    "sg:classifiers":[
        {
            "category":"Social Services",
            "subcategory":"Child Care",
            "type":"Services"
        }
    ],
    "sg:phone":"+1 505 982 8919",
    "sg:postcode":"87501",
    "sg:province":"NM",
    "wof:name":"First Presbyterian Preschool",
    "wof:placetype":"venue"
},
  "geometry": {"coordinates":[-105.940177,35.689929],"type":"Point"}
}