{
  "type": "Feature",
  "properties": {
    "addr:full":"9201 San Mateo Blvd NE Albuquerque NM 87113",
    "addr:housenumber":"9201",
    "addr:postcode":"87113",
    "addr:street":"San Mateo Blvd Ne",
    "iso:country":"US",
    "sg:address":"9201 San Mateo Blvd NE",
    "sg:city":"Albuquerque",
    "sg:classifiers":[
        {
            "category":"Government",
            "subcategory":"Office",
            "type":"Public Place"
        }
    ],
    "sg:phone":"+1 505 828 7690",
    "sg:postcode":"87113",
    "sg:province":"NM",
    "sg:tags":[
        "federal",
        "security"
    ],
    "wof:name":"US Defense Contract Audit",
    "wof:placetype":"venue"
},
  "geometry": {"coordinates":[-106.58655,35.188528],"type":"Point"}
}