{
  "type": "Feature",
  "properties": {
    "iso:country":"US",
    "sg:address":"3004 Horn Ave",
    "sg:city":"Clovis",
    "sg:classifiers":[
        {
            "category":"Building & Trades",
            "subcategory":"Landscaping Services",
            "type":"Services"
        }
    ],
    "sg:phone":"+1 505 749 9280",
    "sg:postcode":"88101",
    "sg:province":"NM",
    "sg:tags":[
        "lawn",
        "maintenance",
        "grounds"
    ],
    "wof:name":"Custom Lawn Care & Landscaping",
    "wof:placetype":"venue"
},
  "geometry": {"coordinates":[-103.213216,34.429841],"type":"Point"}
}