{
  "type": "Feature",
  "properties": {
    "iso:country":"US",
    "sg:address":"1901 University Blvd SE",
    "sg:city":"Albuquerque",
    "sg:classifiers":[
        {
            "category":"Travel",
            "subcategory":"Hotels & Motels",
            "type":"Entertainment"
        }
    ],
    "sg:phone":"+1 505 247 0512",
    "sg:postcode":"87106",
    "sg:province":"NM",
    "sg:tags":[
        "operation",
        "eating",
        "drinking"
    ],
    "wof:name":"Radisson Inn",
    "wof:placetype":"venue"
},
  "geometry": {"coordinates":[-106.63167,35.063625],"type":"Point"}
}