{
  "type": "Feature",
  "properties": {
    "iso:country":"US",
    "sg:address":"3020 Commercial St NE",
    "sg:city":"Albuquerque",
    "sg:classifiers":[
        {
            "category":"Professional",
            "subcategory":"Advertising",
            "type":"Services"
        }
    ],
    "sg:phone":"+1 505 342 2626",
    "sg:postcode":"87107",
    "sg:province":"NM",
    "sg:tags":[
        "consulting",
        "management",
        "agency"
    ],
    "wof:name":"Gutierrez & Associates Inc",
    "wof:placetype":"venue"
},
  "geometry": {"coordinates":[-106.638337,35.117635],"type":"Point"}
}