{
  "type": "Feature",
  "properties": {
    "addr:full":"16 W Cordova St Cuba NM 87013",
    "addr:housenumber":"16",
    "addr:postcode":"87013",
    "addr:street":"W Cordova St",
    "iso:country":"US",
    "sg:address":"16 W Cordova St",
    "sg:city":"Cuba",
    "sg:classifiers":[
        {
            "category":"Government",
            "subcategory":"Office",
            "type":"Public Place"
        }
    ],
    "sg:phone":"+1 505 289 2166",
    "sg:postcode":"87013",
    "sg:province":"NM",
    "sg:tags":[
        "city",
        "program"
    ],
    "wof:name":"Cuba Transportation Program",
    "wof:placetype":"venue"
},
  "geometry": {"coordinates":[-106.965361,36.015897],"type":"Point"}
}