{
  "type": "Feature",
  "properties": {
    "iso:country":"US",
    "sg:address":"4000 Edith Blvd NE",
    "sg:city":"Albuquerque",
    "sg:classifiers":[
        {
            "category":"Government",
            "subcategory":"Jail",
            "type":"Public Place"
        }
    ],
    "sg:phone":"+1 505 841 2400",
    "sg:postcode":"87107",
    "sg:province":"NM",
    "sg:tags":[
        "correctional",
        "facility"
    ],
    "wof:name":"Youth Diagnostic & Dev Ctr",
    "wof:placetype":"venue"
},
  "geometry": {"coordinates":[-106.633313,35.122166],"type":"Point"}
}