{
  "type": "Feature",
  "properties": {
    "iso:country":"US",
    "sg:address":"4816 Wellsburg Ave NW",
    "sg:city":"Albuquerque",
    "sg:classifiers":[
        {
            "category":"Professional",
            "subcategory":"Business Services",
            "type":"Services"
        }
    ],
    "sg:phone":"+1 505 925 0742",
    "sg:postcode":"87120",
    "sg:province":"NM",
    "sg:tags":[
        "distributor",
        "import"
    ],
    "wof:name":"Innovative Tech Int LLC",
    "wof:placetype":"venue"
},
  "geometry": {"coordinates":[-106.692627,35.174807],"type":"Point"}
}