{
  "type": "Feature",
  "properties": {
    "iso:country":"US",
    "sg:address":"8735 Tierra Alegra Dr NE",
    "sg:city":"Albuquerque",
    "sg:classifiers":[
        {
            "category":"Professional",
            "subcategory":"Management & Consulting",
            "type":"Services"
        }
    ],
    "sg:phone":"+1 505 797 7783",
    "sg:postcode":"87122",
    "sg:province":"NM",
    "wof:name":"Michael OKeefe",
    "wof:placetype":"venue"
},
  "geometry": {"coordinates":[-106.552971,35.18382],"type":"Point"}
}