{
  "type": "Feature",
  "properties": {
    "iso:country":"US",
    "sg:address":"403 W Aztec Ave",
    "sg:city":"Gallup",
    "sg:classifiers":[
        {
            "category":"Building & Trades",
            "subcategory":"Construction",
            "type":"Services"
        }
    ],
    "sg:phone":"+1 505 863 4855",
    "sg:postcode":"87301",
    "sg:province":"NM",
    "sg:tags":[
        "home",
        "improvement"
    ],
    "wof:name":"Lowe's Market",
    "wof:placetype":"venue"
},
  "geometry": {"coordinates":[-108.74458199999999,35.525502],"type":"Point"}
}