{
  "type": "Feature",
  "properties": {
    "addr:full":"10801 Holly Ave NE Albuquerque NM 87122",
    "addr:housenumber":"10801",
    "addr:postcode":"87122",
    "addr:street":"Holly Ave Ne",
    "iso:country":"US",
    "sg:address":"10801 Holly Ave NE",
    "sg:city":"Albuquerque",
    "sg:classifiers":[
        {
            "category":"Building & Trades",
            "subcategory":"Construction",
            "type":"Services"
        }
    ],
    "sg:phone":"+1 505 828 3608",
    "sg:postcode":"87122",
    "sg:province":"NM",
    "sg:tags":[
        "company"
    ],
    "wof:name":"Beaty Construction",
    "wof:placetype":"venue"
},
  "geometry": {"coordinates":[-106.520698,35.175716],"type":"Point"}
}