{
  "type": "Feature",
  "properties": {
    "addr:full":"404 N Armijo St Las Cruces NM 88005",
    "addr:housenumber":"404",
    "addr:postcode":"88005",
    "addr:street":"N Armijo St",
    "iso:country":"US",
    "sg:address":"404 N Armijo St",
    "sg:city":"Las Cruces",
    "sg:classifiers":[
        {
            "category":"Real Estate",
            "subcategory":"Real Estate Agent",
            "type":"Services"
        }
    ],
    "sg:phone":"+1 505 524 7653",
    "sg:postcode":"88005",
    "sg:province":"NM",
    "wof:name":"Coss Real Estate LC",
    "wof:placetype":"venue"
},
  "geometry": {"coordinates":[-106.78337500000001,32.312281],"type":"Point"}
}