{
  "type": "Feature",
  "properties": {
    "iso:country":"US",
    "sg:address":"3095 W Historic Highway 66",
    "sg:city":"Gallup",
    "sg:classifiers":[
        {
            "category":"Fast Food",
            "type":"Food & Drink"
        },
        {
            "category":"Restaurant",
            "type":"Food & Drink"
        }
    ],
    "sg:phone":"+1 505 722 7612",
    "sg:postcode":"87301",
    "sg:province":"NM",
    "sg:tags":[
        "mexican"
    ],
    "sg:website":"http://www.tacobell.com",
    "wof:name":"Taco Bell",
    "wof:placetype":"venue"
},
  "geometry": {"coordinates":[-108.811775,35.508927],"type":"Point"}
}