{
  "type": "Feature",
  "properties": {
    "iso:country":"US",
    "sg:address":"816 E Motel Dr",
    "sg:city":"Lordsburg",
    "sg:classifiers":[
        {
            "category":"Travel",
            "subcategory":"Hotels & Motels",
            "type":"Entertainment"
        }
    ],
    "sg:phone":"+1 505 542 3567",
    "sg:postcode":"88045",
    "sg:province":"NM",
    "wof:name":"Budget Motel",
    "wof:placetype":"venue"
},
  "geometry": {"coordinates":[-108.699501,32.347714],"type":"Point"}
}