{
  "type": "Feature",
  "properties": {
    "iso:country":"US",
    "sg:address":"1407 W 2nd St",
    "sg:city":"Roswell",
    "sg:classifiers":[
        {
            "category":"Shopping",
            "subcategory":"Jewelry",
            "type":"Retail Goods"
        }
    ],
    "sg:phone":"+1 505 622 2707",
    "sg:postcode":"88201",
    "sg:province":"NM",
    "wof:name":"Chaves County Pawn",
    "wof:placetype":"venue"
},
  "geometry": {"coordinates":[-104.543583,33.394245],"type":"Point"}
}