{
  "type": "Feature",
  "properties": {
    "addr:full":"10822 Claremont Ave NE Albuquerque NM 87112",
    "addr:housenumber":"10822",
    "addr:postcode":"87112",
    "addr:street":"Claremont Ave Ne",
    "iso:country":"US",
    "sg:address":"10822 Claremont Ave NE",
    "sg:city":"Albuquerque",
    "sg:classifiers":[
        {
            "category":"Building & Trades",
            "subcategory":"Construction",
            "type":"Services"
        }
    ],
    "sg:phone":"+1 505 299 0380",
    "sg:postcode":"87112",
    "sg:province":"NM",
    "sg:tags":[
        "house"
    ],
    "wof:name":"Hello Handyman Services",
    "wof:placetype":"venue"
},
  "geometry": {"coordinates":[-106.51961,35.112853],"type":"Point"}
}