{
  "type": "Feature",
  "properties": {
    "addr:full":"2133 E Main St Farmington NM 87401",
    "addr:housenumber":"2133",
    "addr:postcode":"87401",
    "addr:street":"E Main St",
    "iso:country":"US",
    "sg:address":"2133 E Main St",
    "sg:city":"Farmington",
    "sg:classifiers":[
        {
            "category":"Restaurant",
            "type":"Food & Drink"
        }
    ],
    "sg:phone":"+1 505 326 5580",
    "sg:postcode":"87401",
    "sg:province":"NM",
    "sg:tags":[
        "eating"
    ],
    "wof:name":"Hometown Hamburgers",
    "wof:placetype":"venue"
},
  "geometry": {"coordinates":[-108.179517,36.738447],"type":"Point"}
}