{
  "type": "Feature",
  "properties": {
    "iso:country":"US",
    "sg:address":"4351 E Lohman Ave",
    "sg:city":"Las Cruces",
    "sg:classifiers":[
        {
            "category":"Professional",
            "subcategory":"Management & Consulting",
            "type":"Services"
        }
    ],
    "sg:phone":"+1 505 521 9965",
    "sg:postcode":"88011",
    "sg:province":"NM",
    "sg:tags":[
        "consultant",
        "business"
    ],
    "wof:name":"Firstvalley Management",
    "wof:placetype":"venue"
},
  "geometry": {"coordinates":[-106.735907,32.318516],"type":"Point"}
}