{
  "type": "Feature",
  "properties": {
    "iso:country":"US",
    "sg:address":"4035 Cerrillos Rd",
    "sg:city":"Santa Fe",
    "sg:classifiers":[
        {
            "category":"Retail",
            "subcategory":"Repair Shop",
            "type":"Services"
        }
    ],
    "sg:phone":"+1 505 473 7982",
    "sg:postcode":"87507",
    "sg:province":"NM",
    "sg:tags":[
        "welding"
    ],
    "wof:name":"Fab Shop",
    "wof:placetype":"venue"
},
  "geometry": {"coordinates":[-106.00610399999999,35.646452],"type":"Point"}
}