{
  "type": "Feature",
  "properties": {
    "iso:country":"US",
    "sg:address":"3140 Coors Blvd NW",
    "sg:city":"Albuquerque",
    "sg:classifiers":[
        {
            "category":"Shopping",
            "subcategory":"Bicycles & Sporting Goods",
            "type":"Retail Goods"
        }
    ],
    "sg:phone":"+1 505 836 6555",
    "sg:postcode":"87120",
    "sg:province":"NM",
    "sg:website":"www.big5sportinggoods.com",
    "wof:name":"Big 5 Sporting Goods",
    "wof:placetype":"venue"
},
  "geometry": {"coordinates":[-106.70156299999999,35.120923],"type":"Point"}
}