{
  "type": "Feature",
  "properties": {
    "iso:country":"US",
    "sg:address":"2850 Rufina St",
    "sg:city":"Santa Fe",
    "sg:classifiers":[
        {
            "category":"Building & Trades",
            "subcategory":"Electrical",
            "type":"Services"
        }
    ],
    "sg:phone":"+1 505 421 3383",
    "sg:postcode":"87507",
    "sg:province":"NM",
    "sg:tags":[
        "house",
        "electrical",
        "contractor"
    ],
    "wof:name":"Karma Works LLC",
    "wof:placetype":"venue"
},
  "geometry": {"coordinates":[-105.989582,35.659168],"type":"Point"}
}