{
  "type": "Feature",
  "properties": {
    "iso:country":"US",
    "sg:address":"500 Brionne Dr",
    "sg:city":"Clovis",
    "sg:classifiers":[
        {
            "category":"Retail",
            "subcategory":"Repair Shop",
            "type":"Services"
        }
    ],
    "sg:phone":"+1 505 742 1583",
    "sg:postcode":"88101",
    "sg:province":"NM",
    "sg:tags":[
        "welding"
    ],
    "wof:name":"Trevino Tree Triming",
    "wof:placetype":"venue"
},
  "geometry": {"coordinates":[-103.251625,34.392345],"type":"Point"}
}