{
  "type": "Feature",
  "properties": {
    "iso:country":"US",
    "sg:address":"10084 Menaul Blvd NE",
    "sg:city":"Albuquerque",
    "sg:classifiers":[
        {
            "category":"Professional",
            "subcategory":"Art Services",
            "type":"Services"
        }
    ],
    "sg:phone":"+1 505 275 2806",
    "sg:postcode":"87112",
    "sg:province":"NM",
    "sg:tags":[
        "commercial",
        "design"
    ],
    "wof:name":"Distinct Designs",
    "wof:placetype":"venue"
},
  "geometry": {"coordinates":[-106.530788,35.108864],"type":"Point"}
}