{
  "type": "Feature",
  "properties": {
    "iso:country":"US",
    "sg:address":"108 N Delaware Ave",
    "sg:city":"Roswell",
    "sg:classifiers":[
        {
            "category":"Personal",
            "subcategory":"Beauty Salon",
            "type":"Services"
        }
    ],
    "sg:phone":"+1 505 625 1627",
    "sg:postcode":"88203",
    "sg:province":"NM",
    "sg:tags":[
        "shop"
    ],
    "wof:name":"Head To Toe Hair Wolff Tan Ctr",
    "wof:placetype":"venue"
},
  "geometry": {"coordinates":[-104.537639,33.394117],"type":"Point"}
}