{
  "type": "Feature",
  "properties": {
    "iso:country":"US",
    "sg:address":"200 S Florida Ave",
    "sg:city":"Alamogordo",
    "sg:classifiers":[
        {
            "category":"Manufacturing",
            "subcategory":"Glass & Minerals",
            "type":"Manufacturing & Wholesale Goods"
        }
    ],
    "sg:phone":"+1 505 439 0394",
    "sg:postcode":"88310",
    "sg:province":"NM",
    "sg:tags":[
        "engraver"
    ],
    "wof:name":"Espiritu Custom Awards",
    "wof:placetype":"venue"
},
  "geometry": {"coordinates":[-105.952223,32.887505],"type":"Point"}
}