{
  "type": "Feature",
  "properties": {
    "iso:country":"US",
    "sg:address":"1909 E 20th St",
    "sg:city":"Farmington",
    "sg:classifiers":[
        {
            "category":"Banks & Credit Unions",
            "subcategory":"Investment Brokerage",
            "type":"Services"
        }
    ],
    "sg:phone":"+1 505 325 6644",
    "sg:postcode":"87401",
    "sg:province":"NM",
    "sg:tags":[
        "security"
    ],
    "wof:name":"Raymond James Financial Svc",
    "wof:placetype":"venue"
},
  "geometry": {"coordinates":[-108.181842,36.748153],"type":"Point"}
}