{
  "type": "Feature",
  "properties": {
    "iso:country":"US",
    "sg:address":"425 Locust St SE",
    "sg:city":"Albuquerque",
    "sg:classifiers":[
        {
            "category":"Autos & Motor Vehicles",
            "subcategory":"Fuel & Gas Station",
            "type":"Retail Goods"
        }
    ],
    "sg:phone":"+1 505 242 2275",
    "sg:postcode":"87102",
    "sg:province":"NM",
    "sg:tags":[
        "oil"
    ],
    "wof:name":"Alex Chevron",
    "wof:placetype":"venue"
},
  "geometry": {"coordinates":[-106.638208,35.079056],"type":"Point"}
}