{
  "type": "Feature",
  "properties": {
    "iso:country":"US",
    "sg:address":"7217 Foxford Ave NW",
    "sg:city":"Albuquerque",
    "sg:classifiers":[
        {
            "category":"Autos & Motor Vehicles",
            "subcategory":"Motorcycle Sales",
            "type":"Retail Goods"
        }
    ],
    "sg:phone":"+1 505 897 1278",
    "sg:postcode":"87120",
    "sg:province":"NM",
    "sg:tags":[
        "scooter"
    ],
    "wof:name":"Aragon's TNTATV",
    "wof:placetype":"venue"
},
  "geometry": {"coordinates":[-106.719899,35.147011],"type":"Point"}
}