{
  "type": "Feature",
  "properties": {
    "iso:country":"US",
    "sg:address":"708 Marquette Ave NW",
    "sg:city":"Albuquerque",
    "sg:classifiers":[
        {
            "category":"Professional",
            "subcategory":"Lawyer & Legal Services",
            "type":"Services"
        }
    ],
    "sg:phone":"+1 505 254 0000",
    "sg:postcode":"87102",
    "sg:province":"NM",
    "sg:tags":[
        "attorney"
    ],
    "wof:name":"Harvey Law Firm LLC",
    "wof:placetype":"venue"
},
  "geometry": {"coordinates":[-106.655279,35.088456],"type":"Point"}
}