{
  "type": "Feature",
  "properties": {
    "iso:country":"US",
    "sg:address":"10700 Lagrima de Oro Rd NE",
    "sg:city":"Albuquerque",
    "sg:classifiers":[
        {
            "category":"Recreation",
            "type":"Entertainment"
        }
    ],
    "sg:phone":"+1 505 299 9702",
    "sg:postcode":"87111",
    "sg:province":"NM",
    "sg:tags":[
        "club",
        "baseball"
    ],
    "wof:name":"Roadrunner Little League",
    "wof:placetype":"venue"
},
  "geometry": {"coordinates":[-106.517889,35.133311],"type":"Point"}
}