{
  "type": "Feature",
  "properties": {
    "iso:country":"US",
    "sg:address":"723 N Main St",
    "sg:city":"Roswell",
    "sg:classifiers":[
        {
            "category":"Banks & Credit Unions",
            "subcategory":"Investment Brokerage",
            "type":"Services"
        }
    ],
    "sg:phone":"+1 505 622 7163",
    "sg:postcode":"88201",
    "sg:province":"NM",
    "wof:name":"Holsum Inc",
    "wof:placetype":"venue"
},
  "geometry": {"coordinates":[-104.522681,33.40079],"type":"Point"}
}