{
  "type": "Feature",
  "properties": {
    "iso:country":"US",
    "sg:address":"700 Co Rd 6100",
    "sg:city":"Fruitland",
    "sg:classifiers":[
        {
            "category":"Food & Beverages",
            "subcategory":"Groceries & Convenience Stores",
            "type":"Retail Goods"
        }
    ],
    "sg:phone":"+1 505 598 5940",
    "sg:postcode":"87416",
    "sg:province":"NM",
    "sg:tags":[
        "grocer"
    ],
    "wof:name":"Golden's Food Store",
    "wof:placetype":"venue"
},
  "geometry": {"coordinates":[-108.396646,36.740464],"type":"Point"}
}