{
  "type": "Feature",
  "properties": {
    "iso:country":"US",
    "sg:address":"3202 Carrasco Rd",
    "sg:city":"Carlsbad",
    "sg:classifiers":[
        {
            "category":"Professional",
            "subcategory":"Business Services",
            "type":"Services"
        }
    ],
    "sg:phone":"+1 505 236 6515",
    "sg:postcode":"88220",
    "sg:province":"NM",
    "wof:name":"Tully Cavender",
    "wof:placetype":"venue"
},
  "geometry": {"coordinates":[-104.154618,32.312685],"type":"Point"}
}