{
  "type": "Feature",
  "properties": {
    "addr:full":"500 S Anthony Dr Anthony NM 88021",
    "addr:housenumber":"500",
    "addr:postcode":"88021",
    "addr:street":"S Anthony Dr",
    "iso:country":"US",
    "sg:address":"500 S Anthony Dr",
    "sg:city":"Anthony",
    "sg:classifiers":[
        {
            "category":"Insurance",
            "subcategory":"Insurance Agent",
            "type":"Services"
        }
    ],
    "sg:phone":"+1 505 882 5317",
    "sg:postcode":"88021",
    "sg:province":"NM",
    "wof:name":"Fred Loya Insurance",
    "wof:placetype":"venue"
},
  "geometry": {"coordinates":[-106.606374,32.003771],"type":"Point"}
}