{
  "type": "Feature",
  "properties": {
    "iso:country":"US",
    "sg:address":"313 Ll Davis Dr",
    "sg:city":"Ruidoso",
    "sg:classifiers":[
        {
            "category":"Building & Trades",
            "subcategory":"Construction",
            "type":"Services"
        }
    ],
    "sg:phone":"+1 505 258 2615",
    "sg:postcode":"88345",
    "sg:province":"NM",
    "sg:tags":[
        "house"
    ],
    "wof:name":"St John Custom Homes Inc",
    "wof:placetype":"venue"
},
  "geometry": {"coordinates":[-105.656248,33.3664],"type":"Point"}
}