{
  "type": "Feature",
  "properties": {
    "addr:full":"305 Big Horn Ridge Pl NE Albuquerque NM 87122",
    "addr:housenumber":"305",
    "addr:postcode":"87122",
    "addr:street":"Big Horn Ridge Pl Ne",
    "iso:country":"US",
    "sg:address":"305 Big Horn Ridge Pl NE",
    "sg:city":"Albuquerque",
    "sg:classifiers":[
        {
            "category":"Freight",
            "type":"Transportation"
        }
    ],
    "sg:phone":"+1 505 856 6914",
    "sg:postcode":"87122",
    "sg:province":"NM",
    "wof:name":"Northern Trnsp Systems",
    "wof:placetype":"venue"
},
  "geometry": {"coordinates":[-106.48144000000001,35.177171],"type":"Point"}
}