{
  "type": "Feature",
  "properties": {
    "iso:country":"US",
    "sg:address":"1494 Catalonia St",
    "sg:city":"Bernalillo",
    "sg:classifiers":[
        {
            "category":"Building & Trades",
            "subcategory":"Construction",
            "type":"Services"
        }
    ],
    "sg:phone":"+1 505 867 5082",
    "sg:postcode":"87004",
    "sg:province":"NM",
    "sg:tags":[
        "boring",
        "drilling",
        "contractor"
    ],
    "wof:name":"C J Drilling & Driving",
    "wof:placetype":"venue"
},
  "geometry": {"coordinates":[-106.548928,35.29208],"type":"Point"}
}