{
  "type": "Feature",
  "properties": {
    "iso:country":"US",
    "sg:address":"204 Industrial Park Loop NE",
    "sg:city":"Rio Rancho",
    "sg:classifiers":[
        {
            "category":"Home & Garden",
            "subcategory":"Building Materials",
            "type":"Retail Goods"
        }
    ],
    "sg:phone":"+1 505 892 8869",
    "sg:postcode":"87124",
    "sg:province":"NM",
    "sg:tags":[
        "mixed",
        "concrete"
    ],
    "wof:name":"Rio Rancho Cart Away Concrete",
    "wof:placetype":"venue"
},
  "geometry": {"coordinates":[-106.630599,35.261713],"type":"Point"}
}