{
  "type": "Feature",
  "properties": {
    "iso:country":"US",
    "sg:address":"1017 Oregon Ave",
    "sg:city":"Alamogordo",
    "sg:classifiers":[
        {
            "category":"Organizations",
            "subcategory":"Non-profit Organization",
            "type":"Services"
        }
    ],
    "sg:phone":"+1 505 434 3773",
    "sg:postcode":"88310",
    "sg:province":"NM",
    "sg:tags":[
        "information",
        "alcoholism",
        "treatment"
    ],
    "wof:name":"Alliance Behavioral Health Svc",
    "wof:placetype":"venue"
},
  "geometry": {"coordinates":[-105.94463399999999,32.90185],"type":"Point"}
}