{
  "type": "Feature",
  "properties": {
    "iso:country":"US",
    "sg:address":"3031 Topley Ave",
    "sg:city":"Las Cruces",
    "sg:classifiers":[
        {
            "category":"Building & Trades",
            "subcategory":"Plumbing",
            "type":"Services"
        }
    ],
    "sg:phone":"+1 505 525 3969",
    "sg:postcode":"88005",
    "sg:province":"NM",
    "sg:tags":[
        "conditioning",
        "air",
        "heating",
        "contractor"
    ],
    "wof:name":"Lanpher Air Conditioning & Htg",
    "wof:placetype":"venue"
},
  "geometry": {"coordinates":[-106.781859,32.343727],"type":"Point"}
}