{
  "type": "Feature",
  "properties": {
    "iso:country":"US",
    "sg:address":"1220 Marquette Pl NE",
    "sg:city":"Albuquerque",
    "sg:classifiers":[
        {
            "category":"Shopping",
            "subcategory":"Hobbies, Toys, & Games",
            "type":"Retail Goods"
        }
    ],
    "sg:phone":"+1 505 764 0447",
    "sg:postcode":"87106",
    "sg:province":"NM",
    "wof:name":"Seven Oaks",
    "wof:placetype":"venue"
},
  "geometry": {"coordinates":[-106.631778,35.086003],"type":"Point"}
}