{
  "type": "Feature",
  "properties": {
    "addr:full":"624 2nd St SW Albuquerque NM 87102",
    "addr:housenumber":"624",
    "addr:postcode":"87102",
    "addr:street":"2Nd St Sw",
    "iso:country":"US",
    "sg:address":"624 2nd St SW",
    "sg:city":"Albuquerque",
    "sg:classifiers":[
        {
            "category":"Retail",
            "subcategory":"Auto Repair",
            "type":"Services"
        }
    ],
    "sg:phone":"+1 505 247 8488",
    "sg:postcode":"87102",
    "sg:province":"NM",
    "sg:tags":[
        "repairing",
        "automobile",
        "automotive"
    ],
    "wof:name":"Amador Brothers Wheel Algnmnt",
    "wof:placetype":"venue"
},
  "geometry": {"coordinates":[-106.650257,35.078589],"type":"Point"}
}