{
  "type": "Feature",
  "properties": {
    "addr:full":"6300 San Mateo Blvd NE Albuquerque NM 87109",
    "addr:housenumber":"6300",
    "addr:postcode":"87109",
    "addr:street":"San Mateo Blvd Ne",
    "iso:country":"US",
    "sg:address":"6300 San Mateo Blvd NE",
    "sg:city":"Albuquerque",
    "sg:classifiers":[
        {
            "category":"Shopping",
            "subcategory":"Gifts & Souvenirs",
            "type":"Retail Goods"
        }
    ],
    "sg:phone":"+1 505 798 1516",
    "sg:postcode":"87109",
    "sg:province":"NM",
    "sg:tags":[
        "shop"
    ],
    "wof:name":"Tuesday Morning",
    "wof:placetype":"venue"
},
  "geometry": {"coordinates":[-106.586626,35.151073],"type":"Point"}
}