{
  "type": "Feature",
  "properties": {
    "iso:country":"US",
    "sg:address":"123 Wellesley Dr SE",
    "sg:city":"Albuquerque",
    "sg:classifiers":[
        {
            "category":"Health Services",
            "subcategory":"Health Practitioner",
            "type":"Services"
        }
    ],
    "sg:phone":"+1 505 266 5762",
    "sg:postcode":"87106",
    "sg:province":"NM",
    "sg:tags":[
        "midwife"
    ],
    "wof:name":"Gentle Birth",
    "wof:placetype":"venue"
},
  "geometry": {"coordinates":[-106.608334,35.079347],"type":"Point"}
}