{
  "type": "Feature",
  "properties": {
    "iso:country":"US",
    "sg:address":"5816 Isleta Blvd SW",
    "sg:city":"Albuquerque",
    "sg:classifiers":[
        {
            "category":"Education",
            "subcategory":"College",
            "type":"Public Place"
        }
    ],
    "sg:phone":"+1 505 224 5010",
    "sg:postcode":"87105",
    "sg:province":"NM",
    "sg:tags":[
        "academic",
        "school"
    ],
    "wof:name":"South Valley Campus",
    "wof:placetype":"venue"
},
  "geometry": {"coordinates":[-106.693828,34.995205],"type":"Point"}
}