{
  "type": "Feature",
  "properties": {
    "iso:country":"US",
    "sg:address":"2801 Missouri Ave",
    "sg:city":"Las Cruces",
    "sg:classifiers":[
        {
            "category":"Professional",
            "subcategory":"Computer Services",
            "type":"Services"
        }
    ],
    "sg:phone":"+1 505 644 2987",
    "sg:postcode":"88011",
    "sg:province":"NM",
    "sg:tags":[
        "design",
        "system"
    ],
    "wof:name":"Customized Micro Solution",
    "wof:placetype":"venue"
},
  "geometry": {"coordinates":[-106.737858,32.299816],"type":"Point"}
}