{
  "type": "Feature",
  "properties": {
    "iso:country":"US",
    "sg:address":"3101 Old Pecos Trl",
    "sg:city":"Santa Fe",
    "sg:classifiers":[
        {
            "category":"Professional",
            "subcategory":"Art Services",
            "type":"Services"
        }
    ],
    "sg:phone":"+1 505 988 5904",
    "sg:postcode":"87505",
    "sg:province":"NM",
    "sg:tags":[
        "graphic",
        "designer"
    ],
    "wof:name":"Larry Kerbs Studios",
    "wof:placetype":"venue"
},
  "geometry": {"coordinates":[-105.928839,35.63872],"type":"Point"}
}