{
  "type": "Feature",
  "properties": {
    "iso:country":"US",
    "sg:address":"4409 Skyline Ct NE",
    "sg:city":"Albuquerque",
    "sg:classifiers":[
        {
            "category":"Professional",
            "subcategory":"Management & Consulting",
            "type":"Services"
        }
    ],
    "sg:phone":"+1 505 299 0733",
    "sg:postcode":"87111",
    "sg:province":"NM",
    "wof:name":"Black Forrest Holding Co Inc",
    "wof:placetype":"venue"
},
  "geometry": {"coordinates":[-106.484191,35.12997],"type":"Point"}
}