{
  "type": "Feature",
  "properties": {
    "addr:full":"3410 Indian School Rd NE Albuquerque NM 87106",
    "addr:housenumber":"3410",
    "addr:postcode":"87106",
    "addr:street":"Indian School Rd Ne",
    "iso:country":"US",
    "sg:address":"3410 Indian School Rd NE",
    "sg:city":"Albuquerque",
    "sg:classifiers":[
        {
            "category":"Health Services",
            "subcategory":"Doctor",
            "type":"Services"
        }
    ],
    "sg:phone":"+1 505 265 6921",
    "sg:postcode":"87106",
    "sg:province":"NM",
    "sg:tags":[
        "dentist"
    ],
    "wof:name":"Harry B Bastian DDS PC",
    "wof:placetype":"venue"
},
  "geometry": {"coordinates":[-106.60457,35.101938],"type":"Point"}
}