{
  "type": "Feature",
  "properties": {
    "iso:country":"US",
    "sg:address":"1923 Alvarado Dr NE",
    "sg:city":"Albuquerque",
    "sg:classifiers":[
        {
            "category":"Organizations",
            "subcategory":"Non-profit Organization",
            "type":"Services"
        }
    ],
    "sg:phone":"+1 505 262 2177",
    "sg:postcode":"87110",
    "sg:province":"NM",
    "sg:tags":[
        "hospital",
        "specialty",
        "social"
    ],
    "wof:name":"Al-Anon Information Service",
    "wof:placetype":"venue"
},
  "geometry": {"coordinates":[-106.582048,35.097928],"type":"Point"}
}