{
  "type": "Feature",
  "properties": {
    "iso:country":"US",
    "sg:address":"1357 Pso del Pueblo Sur",
    "sg:city":"Taos",
    "sg:classifiers":[
        {
            "category":"Restaurant",
            "type":"Food & Drink"
        }
    ],
    "sg:phone":"+1 505 758 1735",
    "sg:postcode":"87571",
    "sg:province":"NM",
    "wof:name":"Sonic Drive-In",
    "wof:placetype":"venue"
},
  "geometry": {"coordinates":[-105.595473,36.371387],"type":"Point"}
}