{
  "type": "Feature",
  "properties": {
    "addr:full":"11436 Woodmar Ln NE Albuquerque NM 87111",
    "addr:postcode":"11436;87111",
    "addr:street":"Woodmar Ln Ne",
    "iso:country":"US",
    "sg:address":"11436 Woodmar Ln NE",
    "sg:city":"Albuquerque",
    "sg:classifiers":[
        {
            "category":"Building & Trades",
            "subcategory":"Construction",
            "type":"Services"
        }
    ],
    "sg:phone":"+1 505 293 6155",
    "sg:postcode":"87111",
    "sg:province":"NM",
    "sg:tags":[
        "roofing",
        "contractor"
    ],
    "wof:name":"Mc Kelly Roofing Svc",
    "wof:placetype":"venue"
},
  "geometry": {"coordinates":[-106.51178400000001,35.151973],"type":"Point"}
}