{
  "type": "Feature",
  "properties": {
    "addr:full":"216 Dartmouth Dr SE Albuquerque NM 87106",
    "addr:housenumber":"216",
    "addr:postcode":"87106",
    "addr:street":"Dartmouth Dr Se",
    "iso:country":"US",
    "sg:address":"216 Dartmouth Dr SE",
    "sg:city":"Albuquerque",
    "sg:classifiers":[
        {
            "category":"Real Estate",
            "subcategory":"Real Estate Agent",
            "type":"Services"
        }
    ],
    "sg:phone":"+1 505 265 3497",
    "sg:postcode":"87106",
    "sg:province":"NM",
    "wof:name":"Denker Enterprises",
    "wof:placetype":"venue"
},
  "geometry": {"coordinates":[-106.61196099999999,35.077589],"type":"Point"}
}