{
  "type": "Feature",
  "properties": {
    "addr:full":"714 US Hwy 85 Socorro NM 87801",
    "addr:housenumber":"714",
    "addr:postcode":"87801",
    "addr:street":"Us Hwy 85",
    "iso:country":"US",
    "sg:address":"714 US Hwy 85",
    "sg:city":"Socorro",
    "sg:classifiers":[
        {
            "category":"Manufacturing",
            "subcategory":"Furniture",
            "type":"Manufacturing & Wholesale Goods"
        }
    ],
    "sg:phone":"+1 505 835 3231",
    "sg:postcode":"87801",
    "sg:province":"NM",
    "sg:tags":[
        "woodworking"
    ],
    "wof:name":"Harolds Furniture & Cstm Wdwrk",
    "wof:placetype":"venue"
},
  "geometry": {"coordinates":[-106.891552,34.050012],"type":"Point"}
}