{
  "type": "Feature",
  "properties": {
    "addr:full":"8500 Menaul Blvd NE Albuquerque NM 87112",
    "addr:housenumber":"8500",
    "addr:postcode":"87112",
    "addr:street":"Menaul Blvd Ne",
    "iso:country":"US",
    "sg:address":"8500 Menaul Blvd NE",
    "sg:city":"Albuquerque",
    "sg:classifiers":[
        {
            "category":"Restaurant",
            "type":"Food & Drink"
        }
    ],
    "sg:phone":"+1 505 345 4401",
    "sg:postcode":"87112",
    "sg:province":"NM",
    "sg:tags":[
        "eating"
    ],
    "wof:name":"West Mesa Subway",
    "wof:placetype":"venue"
},
  "geometry": {"coordinates":[-106.549418,35.109166],"type":"Point"}
}