{
  "type": "Feature",
  "properties": {
    "iso:country":"US",
    "sg:address":"2104 Snow Dr",
    "sg:city":"Alamogordo",
    "sg:classifiers":[
        {
            "category":"Insurance",
            "subcategory":"Insurance Agent",
            "type":"Services"
        }
    ],
    "sg:phone":"+1 505 437 2514",
    "sg:postcode":"88310",
    "sg:province":"NM",
    "wof:name":"Joe J Caron",
    "wof:placetype":"venue"
},
  "geometry": {"coordinates":[-105.937086,32.913106],"type":"Point"}
}