{
  "type": "Feature",
  "properties": {
    "addr:full":"1203 W 2nd St Roswell NM 88201",
    "addr:housenumber":"1203",
    "addr:postcode":"88201",
    "addr:street":"W 2Nd St",
    "iso:country":"US",
    "sg:address":"1203 W 2nd St",
    "sg:city":"Roswell",
    "sg:classifiers":[
        {
            "category":"Restaurant",
            "type":"Food & Drink"
        }
    ],
    "sg:menulink":"http://www.allmenus.com/nm/roswell/74849-pizza-hut/menu/",
    "sg:phone":"+1 505 623 8380",
    "sg:postcode":"88201",
    "sg:province":"NM",
    "sg:tags":[
        "american",
        "pizza"
    ],
    "wof:name":"Pizza Hut",
    "wof:placetype":"venue"
},
  "geometry": {"coordinates":[-104.539022,33.394218],"type":"Point"}
}