{
  "type": "Feature",
  "properties": {
    "iso:country":"US",
    "sg:address":"1100 S Main St",
    "sg:city":"Las Cruces",
    "sg:classifiers":[
        {
            "category":"Organizations",
            "subcategory":"Non-profit Organization",
            "type":"Services"
        }
    ],
    "sg:phone":"+1 505 647 8737",
    "sg:postcode":"88005",
    "sg:province":"NM",
    "sg:tags":[
        "disability"
    ],
    "wof:name":"Campo Behavioral Health LLC",
    "wof:placetype":"venue"
},
  "geometry": {"coordinates":[-106.77979000000001,32.298519],"type":"Point"}
}