{
  "type": "Feature",
  "properties": {
    "iso:country":"US",
    "sg:address":"6218 Cottontop Rd",
    "sg:city":"Carlsbad",
    "sg:classifiers":[
        {
            "category":"Building & Trades",
            "subcategory":"Plumbing",
            "type":"Services"
        }
    ],
    "sg:phone":"+1 505 885 3596",
    "sg:postcode":"88220",
    "sg:province":"NM",
    "sg:tags":[
        "plumbing",
        "contractor"
    ],
    "wof:name":"Wayne Brazeal Mechanical",
    "wof:placetype":"venue"
},
  "geometry": {"coordinates":[-104.18626,32.374573],"type":"Point"}
}