{
  "type": "Feature",
  "properties": {
    "iso:country":"US",
    "sg:address":"102 Richmond Dr NE",
    "sg:city":"Albuquerque",
    "sg:classifiers":[
        {
            "category":"Social Services",
            "type":"Services"
        }
    ],
    "sg:phone":"+1 505 265 2930",
    "sg:postcode":"87106",
    "sg:province":"NM",
    "sg:tags":[
        "organization",
        "welfare"
    ],
    "wof:name":"Community Clotheshorse",
    "wof:placetype":"venue"
},
  "geometry": {"coordinates":[-106.610958,35.081855],"type":"Point"}
}