{
  "type": "Feature",
  "properties": {
    "iso:country":"US",
    "sg:address":"1702 Watchpoint",
    "sg:city":"Santa Fe",
    "sg:classifiers":[
        {
            "category":"Professional",
            "type":"Services"
        }
    ],
    "sg:phone":"+1 505 954 4091",
    "sg:postcode":"87507",
    "sg:province":"NM",
    "sg:tags":[
        "technical",
        "marketing",
        "publication"
    ],
    "wof:name":"Mary Skriba",
    "wof:placetype":"venue"
},
  "geometry": {"coordinates":[-105.982378,35.680569],"type":"Point"}
}