{
  "type": "Feature",
  "properties": {
    "addr:full":"4770 Montgomery Blvd NE Albuquerque NM 87109",
    "addr:housenumber":"4770",
    "addr:postcode":"87109",
    "addr:street":"Montgomery Blvd Ne",
    "iso:country":"US",
    "sg:address":"4770 Montgomery Blvd NE",
    "sg:city":"Albuquerque",
    "sg:classifiers":[
        {
            "category":"Personal",
            "type":"Services"
        }
    ],
    "sg:phone":"+1 505 888 1368",
    "sg:postcode":"87109",
    "sg:province":"NM",
    "sg:tags":[
        "control",
        "weight"
    ],
    "wof:name":"Jenny Craig Weight Loss Ctr",
    "wof:placetype":"venue"
},
  "geometry": {"coordinates":[-106.58701499999999,35.130864],"type":"Point"}
}