{
  "type": "Feature",
  "properties": {
    "addr:full":"422 S Main Ave Portales NM 88130",
    "addr:housenumber":"422",
    "addr:postcode":"88130",
    "addr:street":"S Main Ave",
    "iso:country":"US",
    "sg:address":"422 S Main Ave",
    "sg:city":"Portales",
    "sg:classifiers":[
        {
            "category":"Shopping",
            "subcategory":"Used Merchandise",
            "type":"Retail Goods"
        }
    ],
    "sg:phone":"+1 505 359 1974",
    "sg:postcode":"88130",
    "sg:province":"NM",
    "wof:name":"Main Exchange The",
    "wof:placetype":"venue"
},
  "geometry": {"coordinates":[-103.334811,34.184193],"type":"Point"}
}