{
  "type": "Feature",
  "properties": {
    "addr:full":"6812 Cherry Blossom Ln NE Albuquerque NM 87111",
    "addr:housenumber":"6812",
    "addr:postcode":"87111",
    "addr:street":"Cherry Blossom Ln Ne",
    "iso:country":"US",
    "sg:address":"6812 Cherry Blossom Ln NE",
    "sg:city":"Albuquerque",
    "sg:classifiers":[
        {
            "category":"Utilities",
            "subcategory":"Telephone",
            "type":"Services"
        }
    ],
    "sg:phone":"+1 505 821 6912",
    "sg:postcode":"87111",
    "sg:province":"NM",
    "sg:tags":[
        "communications"
    ],
    "wof:name":"Pocket PC Passion Inc",
    "wof:placetype":"venue"
},
  "geometry": {"coordinates":[-106.547248,35.157084],"type":"Point"}
}