{
  "type": "Feature",
  "properties": {
    "iso:country":"US",
    "sg:address":"1411 Pso de Peralta",
    "sg:city":"Santa Fe",
    "sg:classifiers":[
        {
            "category":"Real Estate",
            "subcategory":"Real Estate Agent",
            "type":"Services"
        }
    ],
    "sg:phone":"+1 505 982 1700",
    "sg:postcode":"87501",
    "sg:province":"NM",
    "sg:website":"www.margocutler.com",
    "wof:name":"Margo Cutler LTD Real Estate",
    "wof:placetype":"venue"
},
  "geometry": {"coordinates":[-105.944945,35.681268],"type":"Point"}
}