{
  "type": "Feature",
  "properties": {
    "addr:full":"717 Canyon Rd Santa Fe NM 87501",
    "addr:housenumber":"717",
    "addr:postcode":"87501",
    "addr:street":"Canyon Rd",
    "iso:country":"US",
    "sg:address":"717 Canyon Rd",
    "sg:city":"Santa Fe",
    "sg:classifiers":[
        {
            "category":"Shopping",
            "type":"Retail Goods"
        }
    ],
    "sg:phone":"+1 505 988 2179",
    "sg:postcode":"87501",
    "sg:province":"NM",
    "sg:tags":[
        "wholesale",
        "art",
        "supply"
    ],
    "wof:name":"Artisan/Santa Fe",
    "wof:placetype":"venue"
},
  "geometry": {"coordinates":[-105.92667899999999,35.681165],"type":"Point"}
}