{
  "type": "Feature",
  "properties": {
    "iso:country":"US",
    "sg:address":"513 W Cedar St",
    "sg:city":"Loving",
    "sg:classifiers":[
        {
            "category":"Organizations",
            "subcategory":"Religious Organization",
            "type":"Services"
        }
    ],
    "sg:phone":"+1 505 745 2981",
    "sg:postcode":"88256",
    "sg:province":"NM",
    "sg:tags":[
        "church"
    ],
    "wof:name":"Loving Baptist Church",
    "wof:placetype":"venue"
},
  "geometry": {"coordinates":[-104.09836,32.285856],"type":"Point"}
}