{
  "type": "Feature",
  "properties": {
    "iso:country":"US",
    "sg:address":"4139 Blackhawk Rd",
    "sg:city":"Silver City",
    "sg:classifiers":[
        {
            "category":"Freight",
            "type":"Transportation"
        }
    ],
    "sg:phone":"+1 505 388 9259",
    "sg:postcode":"88061",
    "sg:province":"NM",
    "sg:tags":[
        "operator",
        "trucking"
    ],
    "wof:name":"Gerhardt Vincent Ltd Liab",
    "wof:placetype":"venue"
},
  "geometry": {"coordinates":[-108.275448,32.807035],"type":"Point"}
}