{
  "type": "Feature",
  "properties": {
    "iso:country":"US",
    "sg:address":"1801 W Main St",
    "sg:city":"Artesia",
    "sg:classifiers":[
        {
            "category":"Home & Garden",
            "subcategory":"Building Materials",
            "type":"Retail Goods"
        }
    ],
    "sg:phone":"+1 505 746 3576",
    "sg:postcode":"88210",
    "sg:province":"NM",
    "sg:tags":[
        "hardware",
        "lumber"
    ],
    "wof:name":"Artesia Do It Center",
    "wof:placetype":"venue"
},
  "geometry": {"coordinates":[-104.419991,32.84218],"type":"Point"}
}