{
  "type": "Feature",
  "properties": {
    "iso:country":"US",
    "sg:address":"117 Little Cloud Rd",
    "sg:city":"Moriarty",
    "sg:classifiers":[
        {
            "category":"Retail",
            "subcategory":"Repair Shop",
            "type":"Services"
        }
    ],
    "sg:phone":"+1 505 832 0864",
    "sg:postcode":"87035",
    "sg:province":"NM",
    "sg:tags":[
        "electrical"
    ],
    "wof:name":"Action Appliance Repair",
    "wof:placetype":"venue"
},
  "geometry": {"coordinates":[-106.125438,34.990987],"type":"Point"}
}