{
  "type": "Feature",
  "properties": {
    "iso:country":"US",
    "sg:address":"69 Edmundo Rd",
    "sg:city":"Belen",
    "sg:classifiers":[
        {
            "category":"Shopping",
            "subcategory":"Clothing, Apparel, & Fashions",
            "type":"Retail Goods"
        }
    ],
    "sg:phone":"+1 505 864 6121",
    "sg:postcode":"87002",
    "sg:province":"NM",
    "wof:name":"Jane A Pouch Fashion Coordinat",
    "wof:placetype":"venue"
},
  "geometry": {"coordinates":[-106.77442499999999,34.712207],"type":"Point"}
}