{
  "type": "Feature",
  "properties": {
    "addr:full":"213 Las Colinas Ln NE Albuquerque NM 87113",
    "addr:housenumber":"213",
    "addr:postcode":"87113",
    "addr:street":"Las Colinas Ln Ne",
    "iso:country":"US",
    "sg:address":"213 Las Colinas Ln NE",
    "sg:city":"Albuquerque",
    "sg:classifiers":[
        {
            "category":"Retail",
            "subcategory":"Repair Shop",
            "type":"Services"
        }
    ],
    "sg:phone":"+1 505 345 0134",
    "sg:postcode":"87113",
    "sg:province":"NM",
    "wof:name":"New Mexico Piano Service",
    "wof:placetype":"venue"
},
  "geometry": {"coordinates":[-106.619668,35.161113],"type":"Point"}
}