{
  "type": "Feature",
  "properties": {
    "iso:country":"US",
    "sg:address":"10601 Apache Ave NE",
    "sg:city":"Albuquerque",
    "sg:classifiers":[
        {
            "category":"Organizations",
            "subcategory":"Membership Organization",
            "type":"Services"
        }
    ],
    "sg:phone":"+1 505 298 6507",
    "sg:postcode":"87112",
    "sg:province":"NM",
    "wof:name":"Lasemilla Institute",
    "wof:placetype":"venue"
},
  "geometry": {"coordinates":[-106.526252,35.106125],"type":"Point"}
}