{
  "type": "Feature",
  "properties": {
    "addr:full":"1201 Lafayette Dr NE Albuquerque NM 87106",
    "addr:housenumber":"1201",
    "addr:postcode":"87106",
    "addr:street":"Lafayette Dr Ne",
    "iso:country":"US",
    "sg:address":"1201 Lafayette Dr NE",
    "sg:city":"Albuquerque",
    "sg:classifiers":[
        {
            "category":"Building & Trades",
            "subcategory":"Construction",
            "type":"Services"
        }
    ],
    "sg:phone":"+1 505 266 0116",
    "sg:postcode":"87106",
    "sg:province":"NM",
    "sg:tags":[
        "house"
    ],
    "wof:name":"Jack M Payne General Contr",
    "wof:placetype":"venue"
},
  "geometry": {"coordinates":[-106.608649,35.096531],"type":"Point"}
}