{
  "type": "Feature",
  "properties": {
    "iso:country":"US",
    "sg:address":"4700 Tramway Blvd NE",
    "sg:city":"Albuquerque",
    "sg:classifiers":[
        {
            "category":"Food & Beverages",
            "subcategory":"Groceries & Convenience Stores",
            "type":"Retail Goods"
        }
    ],
    "sg:phone":"+1 505 292 5888",
    "sg:postcode":"87111",
    "sg:province":"NM",
    "sg:tags":[
        "grocer"
    ],
    "wof:name":"Smith's Food & Drug Ctr",
    "wof:placetype":"venue"
},
  "geometry": {"coordinates":[-106.49807300000001,35.131907],"type":"Point"}
}