{
  "type": "Feature",
  "properties": {
    "iso:country":"US",
    "sg:address":"860 N Telshor Blvd",
    "sg:city":"Las Cruces",
    "sg:classifiers":[
        {
            "category":"Autos & Motor Vehicles",
            "subcategory":"Automobile Sales",
            "type":"Retail Goods"
        }
    ],
    "sg:phone":"+1 505 521 1900",
    "sg:postcode":"88011",
    "sg:province":"NM",
    "sg:tags":[
        "car",
        "dealer"
    ],
    "sg:website":"www.saturnoflascruces.com",
    "wof:name":"Saturn Of Las Cruces",
    "wof:placetype":"venue"
},
  "geometry": {"coordinates":[-106.750143,32.320806],"type":"Point"}
}