{
  "type": "Feature",
  "properties": {
    "iso:country":"US",
    "sg:address":"1092 N Canal St",
    "sg:city":"Carlsbad",
    "sg:classifiers":[
        {
            "category":"Utilities",
            "subcategory":"Cable",
            "type":"Services"
        }
    ],
    "sg:phone":"+1 505 885 4147",
    "sg:postcode":"88220",
    "sg:province":"NM",
    "sg:tags":[
        "television"
    ],
    "wof:name":"U S Cable Of Carlsbad",
    "wof:placetype":"venue"
},
  "geometry": {"coordinates":[-104.228825,32.434128],"type":"Point"}
}