{
  "type": "Feature",
  "properties": {
    "iso:country":"US",
    "sg:address":"89 Moya Rd",
    "sg:city":"Santa Fe",
    "sg:classifiers":[
        {
            "category":"Travel",
            "subcategory":"Travel Agent",
            "type":"Entertainment"
        }
    ],
    "sg:phone":"+1 505 466 0665",
    "sg:postcode":"87508",
    "sg:province":"NM",
    "sg:tags":[
        "art",
        "tours"
    ],
    "wof:name":"Walkabout Tours",
    "wof:placetype":"venue"
},
  "geometry": {"coordinates":[-105.911645,35.543698],"type":"Point"}
}