{
  "type": "Feature",
  "properties": {
    "iso:country":"US",
    "sg:address":"23 Arroyo Griego Rd",
    "sg:city":"Santa Fe",
    "sg:classifiers":[
        {
            "category":"Real Estate",
            "subcategory":"Architect",
            "type":"Services"
        }
    ],
    "sg:phone":"+1 505 982 4173",
    "sg:postcode":"87506",
    "sg:province":"NM",
    "wof:name":"Woodmetalconcrete Architecture",
    "wof:placetype":"venue"
},
  "geometry": {"coordinates":[-105.928535,35.761966],"type":"Point"}
}