{
  "type": "Feature",
  "properties": {
    "iso:country":"US",
    "sg:address":"7252 Chickadee Ln NE",
    "sg:city":"Albuquerque",
    "sg:classifiers":[
        {
            "category":"Banks & Credit Unions",
            "subcategory":"Bank",
            "type":"Services"
        }
    ],
    "sg:phone":"+1 505 296 4520",
    "sg:postcode":"87109",
    "sg:province":"NM",
    "sg:tags":[
        "other",
        "plan",
        "card"
    ],
    "wof:name":"Merchant Service",
    "wof:placetype":"venue"
},
  "geometry": {"coordinates":[-106.56464099999999,35.171502],"type":"Point"}
}