{
  "type": "Feature",
  "properties": {
    "addr:full":"700 E 4th St Raton NM 87740",
    "addr:housenumber":"700",
    "addr:postcode":"87740",
    "addr:street":"E 4Th St",
    "iso:country":"US",
    "sg:address":"700 E 4th St",
    "sg:city":"Raton",
    "sg:classifiers":[
        {
            "category":"Social Services",
            "subcategory":"Child Care",
            "type":"Services"
        }
    ],
    "sg:phone":"+1 505 445 0308",
    "sg:postcode":"87740",
    "sg:province":"NM",
    "sg:tags":[
        "day"
    ],
    "wof:name":"Raton Head Start",
    "wof:placetype":"venue"
},
  "geometry": {"coordinates":[-104.432311,36.897764],"type":"Point"}
}