{
  "type": "Feature",
  "properties": {
    "iso:country":"US",
    "sg:address":"1118 National Ave",
    "sg:city":"Las Vegas",
    "sg:classifiers":[
        {
            "category":"Health Services",
            "subcategory":"Clinic",
            "type":"Services"
        }
    ],
    "sg:phone":"+1 505 425 1538",
    "sg:postcode":"87701",
    "sg:province":"NM",
    "sg:tags":[
        "home"
    ],
    "wof:name":"Alternative Home Health Care",
    "wof:placetype":"venue"
},
  "geometry": {"coordinates":[-105.221385,35.59481],"type":"Point"}
}