{
  "type": "Feature",
  "properties": {
    "addr:full":"9530 Tramway Blvd NE Albuquerque NM 87122",
    "addr:housenumber":"9530",
    "addr:postcode":"87122",
    "addr:street":"Tramway Blvd Ne",
    "iso:country":"US",
    "sg:address":"9530 Tramway Blvd NE",
    "sg:city":"Albuquerque",
    "sg:classifiers":[
        {
            "category":"Recreation",
            "type":"Entertainment"
        }
    ],
    "sg:phone":"+1 505 797 7825",
    "sg:postcode":"87122",
    "sg:province":"NM",
    "sg:tags":[
        "club",
        "hockey"
    ],
    "wof:name":"N M Ice Hockey Foundation",
    "wof:placetype":"venue"
},
  "geometry": {"coordinates":[-106.496239,35.189694],"type":"Point"}
}