{
  "type": "Feature",
  "properties": {
    "iso:country":"US",
    "sg:address":"23 Freeform Way",
    "sg:city":"Placitas",
    "sg:classifiers":[
        {
            "category":"Professional",
            "subcategory":"Management & Consulting",
            "type":"Services"
        }
    ],
    "sg:phone":"+1 505 867 2403",
    "sg:postcode":"87043",
    "sg:province":"NM",
    "wof:name":"Design Training Collaborative",
    "wof:placetype":"venue"
},
  "geometry": {"coordinates":[-106.506898,35.30502],"type":"Point"}
}