{
  "type": "Feature",
  "properties": {
    "addr:full":"86 Sun Valley Rd Tularosa NM 88352",
    "addr:housenumber":"86",
    "addr:postcode":"88352",
    "addr:street":"Sun Valley Rd",
    "iso:country":"US",
    "sg:address":"86 Sun Valley Rd",
    "sg:city":"Tularosa",
    "sg:classifiers":[
        {
            "category":"Building & Trades",
            "subcategory":"Construction",
            "type":"Services"
        }
    ],
    "sg:phone":"+1 505 439 7650",
    "sg:postcode":"88352",
    "sg:province":"NM",
    "sg:tags":[
        "hanging",
        "contractor"
    ],
    "wof:name":"Spotted Horse Painting",
    "wof:placetype":"venue"
},
  "geometry": {"coordinates":[-105.99458300000001,33.0438],"type":"Point"}
}