{
  "type": "Feature",
  "properties": {
    "addr:full":"629 Amherst Dr NE Albuquerque NM 87106",
    "addr:housenumber":"629",
    "addr:postcode":"87106",
    "addr:street":"Amherst Dr Ne",
    "iso:country":"US",
    "sg:address":"629 Amherst Dr NE",
    "sg:city":"Albuquerque",
    "sg:classifiers":[
        {
            "category":"Personal",
            "subcategory":"Barber",
            "type":"Services"
        }
    ],
    "sg:phone":"+1 505 268 9292",
    "sg:postcode":"87106",
    "sg:province":"NM",
    "sg:tags":[
        "shop"
    ],
    "wof:name":"Parkview Barber Shop",
    "wof:placetype":"venue"
},
  "geometry": {"coordinates":[-106.605557,35.087166],"type":"Point"}
}