{
  "type": "Feature",
  "properties": {
    "addr:full":"4400 Anaheim Ave NE Albuquerque NM 87113",
    "addr:housenumber":"4400",
    "addr:postcode":"87113",
    "addr:street":"Anaheim Ave Ne",
    "iso:country":"US",
    "sg:address":"4400 Anaheim Ave NE",
    "sg:city":"Albuquerque",
    "sg:classifiers":[
        {
            "category":"Professional",
            "subcategory":"Research",
            "type":"Services"
        }
    ],
    "sg:phone":"+1 505 342 2024",
    "sg:postcode":"87113",
    "sg:province":"NM",
    "sg:tags":[
        "environmental",
        "ecological"
    ],
    "wof:name":"D & H Pump Svc",
    "wof:placetype":"venue"
},
  "geometry": {"coordinates":[-106.59648199999999,35.177937],"type":"Point"}
}