{
  "type": "Feature",
  "properties": {
    "iso:country":"US",
    "sg:address":"301 Gold Ave SW",
    "sg:city":"Albuquerque",
    "sg:classifiers":[
        {
            "category":"Professional",
            "subcategory":"Research",
            "type":"Services"
        }
    ],
    "sg:phone":"+1 505 843 9006",
    "sg:postcode":"87102",
    "sg:province":"NM",
    "sg:tags":[
        "development",
        "economic"
    ],
    "wof:name":"Next Generation Economy Inc",
    "wof:placetype":"venue"
},
  "geometry": {"coordinates":[-106.651797,35.083562],"type":"Point"}
}