{
  "type": "Feature",
  "properties": {
    "addr:full":"4035 Cerrillos Rd Santa Fe NM 87507",
    "addr:housenumber":"4035",
    "addr:postcode":"87507",
    "addr:street":"Cerrillos Rd",
    "iso:country":"US",
    "sg:address":"4035 Cerrillos Rd",
    "sg:city":"Santa Fe",
    "sg:classifiers":[
        {
            "category":"Retail",
            "subcategory":"Auto Rental",
            "type":"Services"
        }
    ],
    "sg:phone":"+1 505 473 5487",
    "sg:postcode":"87507",
    "sg:province":"NM",
    "sg:tags":[
        "truck"
    ],
    "wof:name":"U-Haul",
    "wof:placetype":"venue"
},
  "geometry": {"coordinates":[-106.00610399999999,35.646452],"type":"Point"}
}