{
  "type": "Feature",
  "properties": {
    "iso:country":"US",
    "sg:address":"3109 N Carlton Ave",
    "sg:city":"Farmington",
    "sg:classifiers":[
        {
            "category":"Shopping",
            "subcategory":"Crafts & Fabrics",
            "type":"Retail Goods"
        }
    ],
    "sg:phone":"+1 505 320 5206",
    "sg:postcode":"87401",
    "sg:province":"NM",
    "sg:tags":[
        "sewing"
    ],
    "wof:name":"Quilt Garden",
    "wof:placetype":"venue"
},
  "geometry": {"coordinates":[-108.18923599999999,36.757015],"type":"Point"}
}