{
  "type": "Feature",
  "properties": {
    "iso:country":"US",
    "sg:address":"830 Main St NE",
    "sg:city":"Los Lunas",
    "sg:classifiers":[
        {
            "category":"Retail",
            "subcategory":"Auto Rental",
            "type":"Services"
        }
    ],
    "sg:phone":"+1 505 864 1936",
    "sg:postcode":"87031",
    "sg:province":"NM",
    "sg:tags":[
        "passenger",
        "car"
    ],
    "wof:name":"Enterprise Lsg Company-West",
    "wof:placetype":"venue"
},
  "geometry": {"coordinates":[-106.726435,34.805476],"type":"Point"}
}