{
  "type": "Feature",
  "properties": {
    "iso:country":"US",
    "sg:address":"1217 Pso de Peralta",
    "sg:city":"Santa Fe",
    "sg:classifiers":[
        {
            "category":"Shopping",
            "type":"Retail Goods"
        }
    ],
    "sg:phone":"+1 505 984 1808",
    "sg:postcode":"87501",
    "sg:province":"NM",
    "sg:tags":[
        "art",
        "gallery",
        "dealer"
    ],
    "wof:name":"Clarke & Clarke Tribal Arts",
    "wof:placetype":"venue"
},
  "geometry": {"coordinates":[-105.939078,35.681557],"type":"Point"}
}