{
  "type": "Feature",
  "properties": {
    "addr:full":"1319 W Picacho Ave Las Cruces NM 88005",
    "addr:housenumber":"1319",
    "addr:postcode":"88005",
    "addr:street":"W Picacho Ave",
    "iso:country":"US",
    "sg:address":"1319 W Picacho Ave",
    "sg:city":"Las Cruces",
    "sg:classifiers":[
        {
            "category":"Retail",
            "subcategory":"Auto Repair",
            "type":"Services"
        }
    ],
    "sg:phone":"+1 505 524 0740",
    "sg:postcode":"88005",
    "sg:province":"NM",
    "sg:tags":[
        "automobile",
        "electric"
    ],
    "wof:name":"S & A Auto Electric Svc",
    "wof:placetype":"venue"
},
  "geometry": {"coordinates":[-106.79629,32.313214],"type":"Point"}
}