{
  "type": "Feature",
  "properties": {
    "iso:country":"US",
    "sg:address":"414 Silver Ave SW",
    "sg:city":"Albuquerque",
    "sg:classifiers":[
        {
            "category":"Professional",
            "subcategory":"Lawyer & Legal Services",
            "type":"Services"
        }
    ],
    "sg:phone":"+1 505 346 4646",
    "sg:postcode":"87102",
    "sg:province":"NM",
    "sg:tags":[
        "attorney"
    ],
    "wof:name":"Clyde F Worthen",
    "wof:placetype":"venue"
},
  "geometry": {"coordinates":[-106.653053,35.082647],"type":"Point"}
}