{
  "type": "Feature",
  "properties": {
    "iso:country":"US",
    "sg:address":"2432 Claremont Ave NE",
    "sg:city":"Albuquerque",
    "sg:classifiers":[
        {
            "category":"Wholesale",
            "subcategory":"Hardware",
            "type":"Manufacturing & Wholesale Goods"
        }
    ],
    "sg:phone":"+1 505 884 0133",
    "sg:postcode":"87107",
    "sg:province":"NM",
    "sg:tags":[
        "plumbing",
        "fixtures",
        "part",
        "fixture",
        "supply"
    ],
    "sg:website":"http://www.bgsi-plumbing.com",
    "wof:name":"Bob Garrecht Supply, Inc.",
    "wof:placetype":"venue"
},
  "geometry": {"coordinates":[-106.61592400000001,35.112937],"type":"Point"}
}