{
  "type": "Feature",
  "properties": {
    "iso:country":"US",
    "sg:address":"824 Sperry Dr",
    "sg:city":"Las Vegas",
    "sg:classifiers":[
        {
            "category":"Social Services",
            "subcategory":"Child Care",
            "type":"Services"
        }
    ],
    "sg:phone":"+1 505 425 8179",
    "sg:postcode":"87701",
    "sg:province":"NM",
    "sg:tags":[
        "day"
    ],
    "wof:name":"Tiny Tots Daycare",
    "wof:placetype":"venue"
},
  "geometry": {"coordinates":[-105.23509,35.618578],"type":"Point"}
}