{
  "type": "Feature",
  "properties": {
    "iso:country":"US",
    "sg:address":"1304 W Ponderosa Dr",
    "sg:city":"Hobbs",
    "sg:classifiers":[
        {
            "category":"Wholesale",
            "subcategory":"Auto Parts",
            "type":"Manufacturing & Wholesale Goods"
        }
    ],
    "sg:phone":"+1 505 392 2215",
    "sg:postcode":"88242",
    "sg:province":"NM",
    "wof:name":"Dependable Parts Service",
    "wof:placetype":"venue"
},
  "geometry": {"coordinates":[-103.149096,32.77214],"type":"Point"}
}