{
  "type": "Feature",
  "properties": {
    "iso:country":"US",
    "sg:address":"169 Rd 3100",
    "sg:city":"Aztec",
    "sg:classifiers":[
        {
            "category":"Mining & Drilling",
            "type":"Manufacturing & Wholesale Goods"
        }
    ],
    "sg:phone":"+1 505 334 3850",
    "sg:postcode":"87410",
    "sg:province":"NM",
    "sg:tags":[
        "field",
        "oil"
    ],
    "wof:name":"Double S Hot Shot",
    "wof:placetype":"venue"
},
  "geometry": {"coordinates":[-108.043419,36.779136],"type":"Point"}
}