{
  "type": "Feature",
  "properties": {
    "iso:country":"US",
    "sg:address":"1163 Cam San Acacio",
    "sg:city":"Santa Fe",
    "sg:classifiers":[
        {
            "category":"Home & Garden",
            "subcategory":"Carpets & Floor Coverings",
            "type":"Retail Goods"
        }
    ],
    "sg:phone":"+1 505 988 3411",
    "sg:postcode":"87505",
    "sg:province":"NM",
    "sg:tags":[
        "rug",
        "tapestry"
    ],
    "wof:name":"Mahaim Pierre Rugs & Antiques",
    "wof:placetype":"venue"
},
  "geometry": {"coordinates":[-105.916904,35.677959],"type":"Point"}
}