{
  "type": "Feature",
  "properties": {
    "addr:full":"9190 Coors Blvd NW Albuquerque NM 87120",
    "addr:housenumber":"9190",
    "addr:postcode":"87120",
    "addr:street":"Coors Blvd Nw",
    "iso:country":"US",
    "sg:address":"9190 Coors Blvd NW",
    "sg:city":"Albuquerque",
    "sg:classifiers":[
        {
            "category":"Recreation",
            "type":"Entertainment"
        }
    ],
    "sg:phone":"+1 505 897 3716",
    "sg:postcode":"87120",
    "sg:province":"NM",
    "sg:tags":[
        "club",
        "membership",
        "physical",
        "fitness"
    ],
    "wof:name":"River Point Sports & Welllness",
    "wof:placetype":"venue"
},
  "geometry": {"coordinates":[-106.66935599999999,35.179597],"type":"Point"}
}