{
  "type": "Feature",
  "properties": {
    "iso:country":"US",
    "sg:address":"1420 W 7th St",
    "sg:city":"Clovis",
    "sg:classifiers":[
        {
            "category":"Food & Beverages",
            "subcategory":"Groceries & Convenience Stores",
            "type":"Retail Goods"
        }
    ],
    "sg:phone":"+1 505 769 0707",
    "sg:postcode":"88101",
    "sg:province":"NM",
    "sg:tags":[
        "product"
    ],
    "wof:name":"Velma's Soul Foods",
    "wof:placetype":"venue"
},
  "geometry": {"coordinates":[-103.222696,34.404767],"type":"Point"}
}