{
  "type": "Feature",
  "properties": {
    "iso:country":"US",
    "sg:address":"7112 Pan American Fwy",
    "sg:city":"Albuquerque",
    "sg:classifiers":[
        {
            "category":"Professional",
            "subcategory":"Engineering",
            "type":"Services"
        }
    ],
    "sg:phone":"+1 505 867 5022",
    "sg:postcode":"87109",
    "sg:province":"NM",
    "sg:tags":[
        "engineer"
    ],
    "wof:name":"Cft Inc",
    "wof:placetype":"venue"
},
  "geometry": {"coordinates":[-106.58674000000001,35.160721],"type":"Point"}
}