{
  "type": "Feature",
  "properties": {
    "addr:full":"2812 Campbell Rd NW Albuquerque NM 87104",
    "addr:housenumber":"2812",
    "addr:postcode":"87104",
    "addr:street":"Campbell Rd Nw",
    "iso:country":"US",
    "sg:address":"2812 Campbell Rd NW",
    "sg:city":"Albuquerque",
    "sg:classifiers":[
        {
            "category":"Professional",
            "subcategory":"Management & Consulting",
            "type":"Services"
        }
    ],
    "sg:phone":"+1 505 345 5715",
    "sg:postcode":"87104",
    "sg:province":"NM",
    "sg:tags":[
        "business"
    ],
    "wof:name":"Weller Consulting Inc",
    "wof:placetype":"venue"
},
  "geometry": {"coordinates":[-106.682889,35.122629],"type":"Point"}
}