{
  "type": "Feature",
  "properties": {
    "iso:country":"US",
    "sg:address":"2444 Juan Tabo Blvd NE",
    "sg:city":"Albuquerque",
    "sg:classifiers":[
        {
            "category":"Personal",
            "subcategory":"Beauty Salon",
            "type":"Services"
        }
    ],
    "sg:phone":"+1 505 298 1821",
    "sg:postcode":"87112",
    "sg:province":"NM",
    "sg:tags":[
        "shop"
    ],
    "wof:name":"Blue Dolphin Hair Studio",
    "wof:placetype":"venue"
},
  "geometry": {"coordinates":[-106.515501,35.110213],"type":"Point"}
}