{
  "type": "Feature",
  "properties": {
    "iso:country":"US",
    "sg:address":"955 S Auburn Ave",
    "sg:city":"Farmington",
    "sg:classifiers":[
        {
            "category":"Home & Garden",
            "subcategory":"Mobile Homes",
            "type":"Retail Goods"
        }
    ],
    "sg:phone":"+1 505 564 3264",
    "sg:postcode":"87401",
    "sg:province":"NM",
    "sg:tags":[
        "parts"
    ],
    "wof:name":"Complete Mobile Home Parts Svc",
    "wof:placetype":"venue"
},
  "geometry": {"coordinates":[-108.211529,36.721465],"type":"Point"}
}