{
  "type": "Feature",
  "properties": {
    "addr:full":"308 Harvard Dr SE Albuquerque NM 87106",
    "addr:housenumber":"308",
    "addr:postcode":"87106",
    "addr:street":"Harvard Dr Se",
    "iso:country":"US",
    "sg:address":"308 Harvard Dr SE",
    "sg:city":"Albuquerque",
    "sg:classifiers":[
        {
            "category":"Professional",
            "subcategory":"Management & Consulting",
            "type":"Services"
        }
    ],
    "sg:phone":"+1 505 254 7716",
    "sg:postcode":"87106",
    "sg:province":"NM",
    "sg:tags":[
        "consultant",
        "educational"
    ],
    "wof:name":"Stephen Michael Tumolo Edctn",
    "wof:placetype":"venue"
},
  "geometry": {"coordinates":[-106.620728,35.075631],"type":"Point"}
}