{
  "type": "Feature",
  "properties": {
    "iso:country":"US",
    "sg:address":"564 N Guadalupe St",
    "sg:city":"Santa Fe",
    "sg:classifiers":[
        {
            "category":"Shopping",
            "subcategory":"Department Store",
            "type":"Retail Goods"
        }
    ],
    "sg:phone":"+1 505 982 2655",
    "sg:postcode":"87501",
    "sg:province":"NM",
    "sg:website":"www.devargascenter.com",
    "wof:name":"De Vargas Ctr",
    "wof:placetype":"venue"
},
  "geometry": {"coordinates":[-105.94921600000001,35.693586],"type":"Point"}
}