{
  "type": "Feature",
  "properties": {
    "iso:country":"US",
    "sg:address":"1724 S 2nd St",
    "sg:city":"Gallup",
    "sg:classifiers":[
        {
            "category":"Home & Garden",
            "subcategory":"Building Materials",
            "type":"Retail Goods"
        }
    ],
    "sg:phone":"+1 505 863 4475",
    "sg:postcode":"87301",
    "sg:province":"NM",
    "sg:tags":[
        "hardware",
        "center"
    ],
    "wof:name":"Gallup Lumber & Supply Co",
    "wof:placetype":"venue"
},
  "geometry": {"coordinates":[-108.738592,35.510057],"type":"Point"}
}