{
  "type": "Feature",
  "properties": {
    "addr:full":"195 State Hwy 75 Dixon NM 87527",
    "addr:housenumber":"195",
    "addr:postcode":"87527",
    "addr:street":"State Hwy 75",
    "iso:country":"US",
    "sg:address":"195 State Hwy 75",
    "sg:city":"Dixon",
    "sg:classifiers":[
        {
            "category":"Social Services",
            "type":"Services"
        }
    ],
    "sg:phone":"+1 505 579 9176",
    "sg:postcode":"87527",
    "sg:province":"NM",
    "sg:tags":[
        "senior",
        "citizen"
    ],
    "wof:name":"Rio Arriba County Senior Ctzns",
    "wof:placetype":"venue"
},
  "geometry": {"coordinates":[-105.886899,36.197369],"type":"Point"}
}