{
  "type": "Feature",
  "properties": {
    "iso:country":"US",
    "sg:address":"2105 Delk Dr",
    "sg:city":"Silver City",
    "sg:classifiers":[
        {
            "category":"Professional",
            "subcategory":"Business Services",
            "type":"Services"
        }
    ],
    "sg:phone":"+1 505 538 7318",
    "sg:postcode":"88061",
    "sg:province":"NM",
    "wof:name":"Madrid Bail Bonds",
    "wof:placetype":"venue"
},
  "geometry": {"coordinates":[-108.23169799999999,32.789572],"type":"Point"}
}