{
  "type": "Feature",
  "properties": {
    "iso:country":"US",
    "sg:address":"200 W 1st St",
    "sg:city":"Roswell",
    "sg:classifiers":[
        {
            "category":"Government",
            "subcategory":"Office",
            "type":"Public Place"
        }
    ],
    "sg:phone":"+1 505 624 6077",
    "sg:postcode":"88203",
    "sg:province":"NM",
    "sg:tags":[
        "human"
    ],
    "wof:name":"Office of Inspector General",
    "wof:placetype":"venue"
},
  "geometry": {"coordinates":[-104.526025,33.393102],"type":"Point"}
}