{
  "type": "Feature",
  "properties": {
    "addr:full":"1100 S Main St Las Cruces NM 88005",
    "addr:housenumber":"1100",
    "addr:postcode":"88005",
    "addr:street":"S Main St",
    "iso:country":"US",
    "sg:address":"1100 S Main St",
    "sg:city":"Las Cruces",
    "sg:classifiers":[
        {
            "category":"Insurance",
            "subcategory":"Health Insurance",
            "type":"Services"
        },
        {
            "category":"Insurance",
            "subcategory":"Insurance Agent",
            "type":"Services"
        }
    ],
    "sg:phone":"+1 505 525 1148",
    "sg:postcode":"88005",
    "sg:province":"NM",
    "sg:tags":[
        "carrier"
    ],
    "wof:name":"AFLAC",
    "wof:placetype":"venue"
},
  "geometry": {"coordinates":[-106.77979000000001,32.298519],"type":"Point"}
}