{
  "type": "Feature",
  "properties": {
    "addr:full":"1508 Bishops Lodge Rd Santa Fe NM 87506",
    "addr:housenumber":"1508",
    "addr:postcode":"87506",
    "addr:street":"Bishops Lodge Rd",
    "iso:country":"US",
    "sg:address":"1508 Bishops Lodge Rd",
    "sg:city":"Santa Fe",
    "sg:classifiers":[
        {
            "category":"Shopping",
            "type":"Retail Goods"
        }
    ],
    "sg:phone":"+1 505 988 8001",
    "sg:postcode":"87506",
    "sg:province":"NM",
    "sg:tags":[
        "art",
        "gallery",
        "dealer"
    ],
    "wof:name":"Shidoni Arts",
    "wof:placetype":"venue"
},
  "geometry": {"coordinates":[-105.92733200000001,35.757445],"type":"Point"}
}