{
  "type": "Feature",
  "properties": {
    "iso:country":"US",
    "sg:address":"1765 Argus Ct SE",
    "sg:city":"Rio Rancho",
    "sg:classifiers":[
        {
            "category":"Building & Trades",
            "subcategory":"Plumbing",
            "type":"Services"
        }
    ],
    "sg:phone":"+1 505 896 0210",
    "sg:postcode":"87124",
    "sg:province":"NM",
    "sg:tags":[
        "contractor"
    ],
    "wof:name":"Accent Pool & Plumbing",
    "wof:placetype":"venue"
},
  "geometry": {"coordinates":[-106.701782,35.24595],"type":"Point"}
}