{
  "type": "Feature",
  "properties": {
    "iso:country":"US",
    "sg:address":"60 Rd 3950",
    "sg:city":"Farmington",
    "sg:classifiers":[
        {
            "category":"Real Estate",
            "subcategory":"Real Estate Agent",
            "type":"Services"
        }
    ],
    "sg:phone":"+1 505 324 9734",
    "sg:postcode":"87401",
    "sg:province":"NM",
    "wof:name":"Jackson Real Estate Svc Inc",
    "wof:placetype":"venue"
},
  "geometry": {"coordinates":[-108.137941,36.742205],"type":"Point"}
}