{
  "type": "Feature",
  "properties": {
    "iso:country":"US",
    "sg:address":"1621 Virginia St NE",
    "sg:city":"Albuquerque",
    "sg:classifiers":[
        {
            "category":"Insurance",
            "subcategory":"Insurance Agent",
            "type":"Services"
        }
    ],
    "sg:phone":"+1 505 293 9629",
    "sg:postcode":"87110",
    "sg:province":"NM",
    "wof:name":"McQuarrie Robert E & Assoc",
    "wof:placetype":"venue"
},
  "geometry": {"coordinates":[-106.552858,35.101722],"type":"Point"}
}