{
  "type": "Feature",
  "properties": {
    "iso:country":"US",
    "sg:address":"500 N Richardson Ave",
    "sg:city":"Roswell",
    "sg:classifiers":[
        {
            "category":"Government",
            "subcategory":"Office",
            "type":"Public Place"
        }
    ],
    "sg:phone":"+1 505 623 3310",
    "sg:postcode":"88201",
    "sg:province":"NM",
    "sg:tags":[
        "control",
        "damage",
        "animal"
    ],
    "wof:name":"Animal Damage Control Office",
    "wof:placetype":"venue"
},
  "geometry": {"coordinates":[-104.524409,33.39879],"type":"Point"}
}