{
  "type": "Feature",
  "properties": {
    "addr:full":"1305 Colonial Pkwy Clovis NM 88101",
    "addr:housenumber":"1305",
    "addr:postcode":"88101",
    "addr:street":"Colonial Pkwy",
    "iso:country":"US",
    "sg:address":"1305 Colonial Pkwy",
    "sg:city":"Clovis",
    "sg:classifiers":[
        {
            "category":"Health Services",
            "subcategory":"Clinic",
            "type":"Services"
        }
    ],
    "sg:phone":"+1 505 763 4179",
    "sg:postcode":"88101",
    "sg:province":"NM",
    "wof:name":"Community Health Group",
    "wof:placetype":"venue"
},
  "geometry": {"coordinates":[-103.19201700000001,34.441124],"type":"Point"}
}