{
  "type": "Feature",
  "properties": {
    "iso:country":"US",
    "sg:address":"5501 Palomino Dr NW",
    "sg:city":"Albuquerque",
    "sg:classifiers":[
        {
            "category":"Wholesale",
            "subcategory":"Durable Goods & Equipment",
            "type":"Manufacturing & Wholesale Goods"
        }
    ],
    "sg:phone":"+1 505 899 5464",
    "sg:postcode":"87120",
    "sg:province":"NM",
    "sg:tags":[
        "importer"
    ],
    "wof:name":"Sheherazade Imports",
    "wof:placetype":"venue"
},
  "geometry": {"coordinates":[-106.705041,35.150242],"type":"Point"}
}