{
  "type": "Feature",
  "properties": {
    "addr:full":"6475 E Main St Farmington NM 87402",
    "addr:housenumber":"6475",
    "addr:postcode":"87402",
    "addr:street":"E Main St",
    "iso:country":"US",
    "sg:address":"6475 E Main St",
    "sg:city":"Farmington",
    "sg:classifiers":[
        {
            "category":"Shopping",
            "type":"Retail Goods"
        }
    ],
    "sg:phone":"+1 505 327 0558",
    "sg:postcode":"87402",
    "sg:province":"NM",
    "sg:tags":[
        "merchandise"
    ],
    "wof:name":"Family Craft Memorials",
    "wof:placetype":"venue"
},
  "geometry": {"coordinates":[-108.125613,36.778123],"type":"Point"}
}