{
  "type": "Feature",
  "properties": {
    "iso:country":"US",
    "sg:address":"12 Estambre Rd",
    "sg:city":"Santa Fe",
    "sg:classifiers":[
        {
            "category":"Restaurant",
            "type":"Food & Drink"
        }
    ],
    "sg:phone":"+1 505 469 6006",
    "sg:postcode":"87508",
    "sg:province":"NM",
    "sg:tags":[
        "eating"
    ],
    "wof:name":"Kiffin Entprs Inc",
    "wof:placetype":"venue"
},
  "geometry": {"coordinates":[-105.94458,35.52834],"type":"Point"}
}