{
  "type": "Feature",
  "properties": {
    "addr:full":"11320 Campo del Oso Ave NE Albuquerque NM 87123",
    "addr:housenumber":"11320",
    "addr:postcode":"87123",
    "addr:street":"Campo Del Oso Ave Ne",
    "iso:country":"US",
    "sg:address":"11320 Campo del Oso Ave NE",
    "sg:city":"Albuquerque",
    "sg:classifiers":[
        {
            "category":"Professional",
            "subcategory":"Management & Consulting",
            "type":"Services"
        }
    ],
    "sg:phone":"+1 505 291 8505",
    "sg:postcode":"87123",
    "sg:province":"NM",
    "sg:tags":[
        "business"
    ],
    "wof:name":"OGorman Consulting",
    "wof:placetype":"venue"
},
  "geometry": {"coordinates":[-106.524593,35.085567],"type":"Point"}
}