{
  "type": "Feature",
  "properties": {
    "iso:country":"US",
    "sg:address":"8444 Spain Rd NE",
    "sg:city":"Albuquerque",
    "sg:classifiers":[
        {
            "category":"Building & Trades",
            "subcategory":"Landscaping Services",
            "type":"Services"
        }
    ],
    "sg:phone":"+1 505 821 7900",
    "sg:postcode":"87111",
    "sg:province":"NM",
    "sg:tags":[
        "landscape",
        "contractor"
    ],
    "wof:name":"A & J Landscaping",
    "wof:placetype":"venue"
},
  "geometry": {"coordinates":[-106.547068,35.139698],"type":"Point"}
}