{
  "type": "Feature",
  "properties": {
    "addr:full":"500 Copper Ave NW # 1B Albuquerque NM 87102",
    "addr:housenumber":"500",
    "addr:postcode":"87102",
    "addr:street":"Copper Ave Nw # 1B",
    "iso:country":"US",
    "sg:address":"500 Copper Ave NW # 1B",
    "sg:city":"Albuquerque",
    "sg:classifiers":[
        {
            "category":"Personal",
            "subcategory":"Beauty Salon",
            "type":"Services"
        }
    ],
    "sg:phone":"+1 505 839 1885",
    "sg:postcode":"87102",
    "sg:province":"NM",
    "wof:name":"Axis Salon & Spa",
    "wof:placetype":"venue"
},
  "geometry": {"coordinates":[-106.65261099999999,35.08569],"type":"Point"}
}