{
  "type": "Feature",
  "properties": {
    "iso:country":"US",
    "sg:address":"711 S 2nd St",
    "sg:city":"Gallup",
    "sg:classifiers":[
        {
            "category":"Home & Garden",
            "subcategory":"Building Materials",
            "type":"Retail Goods"
        }
    ],
    "sg:phone":"+1 505 722 9373",
    "sg:postcode":"87301",
    "sg:province":"NM",
    "sg:tags":[
        "glass",
        "window",
        "plate"
    ],
    "wof:name":"Rosales Construction Co",
    "wof:placetype":"venue"
},
  "geometry": {"coordinates":[-108.74044499999999,35.523011],"type":"Point"}
}