{
  "type": "Feature",
  "properties": {
    "iso:country":"US",
    "sg:address":"4012 2nd St NW",
    "sg:city":"Albuquerque",
    "sg:classifiers":[
        {
            "category":"Organizations",
            "subcategory":"Religious Organization",
            "type":"Services"
        }
    ],
    "sg:phone":"+1 505 345 0076",
    "sg:postcode":"87107",
    "sg:province":"NM",
    "sg:tags":[
        "church"
    ],
    "wof:name":"United Bible Fellowship Church",
    "wof:placetype":"venue"
},
  "geometry": {"coordinates":[-106.640555,35.124142],"type":"Point"}
}