{
  "type": "Feature",
  "properties": {
    "iso:country":"US",
    "sg:address":"10000 Calabacillas Ct NW",
    "sg:city":"Albuquerque",
    "sg:classifiers":[
        {
            "category":"Sports & Exercise",
            "subcategory":"Sports Center",
            "type":"Entertainment"
        }
    ],
    "sg:phone":"+1 505 660 0483",
    "sg:postcode":"87114",
    "sg:province":"NM",
    "sg:tags":[
        "manager",
        "promoter"
    ],
    "wof:name":"Right Action Management Inc",
    "wof:placetype":"venue"
},
  "geometry": {"coordinates":[-106.662949,35.196381],"type":"Point"}
}