{
  "type": "Feature",
  "properties": {
    "iso:country":"US",
    "sg:address":"1312 Elfego Baca Dr SW",
    "sg:city":"Albuquerque",
    "sg:classifiers":[
        {
            "category":"Arts & Performance",
            "subcategory":"Theater",
            "type":"Entertainment"
        }
    ],
    "sg:phone":"+1 505 250 4581",
    "sg:postcode":"87121",
    "sg:province":"NM",
    "sg:tags":[
        "group"
    ],
    "wof:name":"Johnnys Sound In Motion",
    "wof:placetype":"venue"
},
  "geometry": {"coordinates":[-106.753846,35.050225],"type":"Point"}
}