{
  "type": "Feature",
  "properties": {
    "iso:country":"US",
    "sg:address":"821 Canyon Rd",
    "sg:city":"Santa Fe",
    "sg:classifiers":[
        {
            "category":"Wholesale",
            "subcategory":"Home Furnishings",
            "type":"Manufacturing & Wholesale Goods"
        }
    ],
    "sg:phone":"+1 505 983 9426",
    "sg:postcode":"87501",
    "sg:province":"NM",
    "wof:name":"Canyon Road Pottery",
    "wof:placetype":"venue"
},
  "geometry": {"coordinates":[-105.92442,35.680284],"type":"Point"}
}