{
  "type": "Feature",
  "properties": {
    "iso:country":"US",
    "sg:address":"150 E Madrid Ave",
    "sg:city":"Las Cruces",
    "sg:classifiers":[
        {
            "category":"Food & Beverages",
            "subcategory":"Liquor & Beverages",
            "type":"Retail Goods"
        }
    ],
    "sg:phone":"+1 505 525 2102",
    "sg:postcode":"88001",
    "sg:province":"NM",
    "sg:tags":[
        "alcoholic"
    ],
    "wof:name":"Liquor Co 1",
    "wof:placetype":"venue"
},
  "geometry": {"coordinates":[-106.78197,32.328089],"type":"Point"}
}