{
  "type": "Feature",
  "properties": {
    "addr:full":"1605 Antonio Dr NE Albuquerque NM 87112",
    "addr:housenumber":"1605",
    "addr:postcode":"87112",
    "addr:street":"Antonio Dr Ne",
    "iso:country":"US",
    "sg:address":"1605 Antonio Dr NE",
    "sg:city":"Albuquerque",
    "sg:classifiers":[
        {
            "category":"Travel",
            "subcategory":"Travel Agent",
            "type":"Entertainment"
        }
    ],
    "sg:phone":"+1 505 292 4238",
    "sg:postcode":"87112",
    "sg:province":"NM",
    "sg:tags":[
        "agency",
        "services-commercial"
    ],
    "wof:name":"Premium Travel Planners",
    "wof:placetype":"venue"
},
  "geometry": {"coordinates":[-106.484131,35.097318],"type":"Point"}
}