{
  "type": "Feature",
  "properties": {
    "addr:full":"26 Erica Santa Fe NM 87507",
    "addr:housenumber":"26",
    "addr:postcode":"87507",
    "addr:street":"Erica",
    "iso:country":"US",
    "sg:address":"26 Erica",
    "sg:city":"Santa Fe",
    "sg:classifiers":[
        {
            "category":"Building & Trades",
            "subcategory":"Construction",
            "type":"Services"
        }
    ],
    "sg:phone":"+1 505 474 3122",
    "sg:postcode":"87507",
    "sg:province":"NM",
    "sg:tags":[
        "contractor",
        "metal",
        "fabrication",
        "structural"
    ],
    "wof:name":"Joels Portable Welding Service",
    "wof:placetype":"venue"
},
  "geometry": {"coordinates":[-106.06931400000001,35.59435],"type":"Point"}
}