{
  "type": "Feature",
  "properties": {
    "iso:country":"US",
    "sg:address":"1925 Highland Ave",
    "sg:city":"Las Cruces",
    "sg:classifiers":[
        {
            "category":"Retail",
            "subcategory":"Laundry & Dry Cleaning",
            "type":"Services"
        }
    ],
    "sg:phone":"+1 505 524 1078",
    "sg:postcode":"88005",
    "sg:province":"NM",
    "sg:tags":[
        "cleaners",
        "upholstery",
        "rug",
        "carpet"
    ],
    "wof:name":"Steam Genie-Carpet Steam Clng",
    "wof:placetype":"venue"
},
  "geometry": {"coordinates":[-106.792744,32.326916],"type":"Point"}
}