{
  "type": "Feature",
  "properties": {
    "iso:country":"US",
    "sg:address":"2306 N Davis Ave",
    "sg:city":"Roswell",
    "sg:classifiers":[
        {
            "category":"Building & Trades",
            "subcategory":"Construction",
            "type":"Services"
        }
    ],
    "sg:phone":"+1 505 627 5739",
    "sg:postcode":"88201",
    "sg:province":"NM",
    "sg:tags":[
        "general"
    ],
    "wof:name":"Dick Harp Construction",
    "wof:placetype":"venue"
},
  "geometry": {"coordinates":[-104.518245,33.421137],"type":"Point"}
}