{
  "type": "Feature",
  "properties": {
    "iso:country":"US",
    "sg:address":"801 Mitchell St",
    "sg:city":"Clovis",
    "sg:classifiers":[
        {
            "category":"Professional",
            "subcategory":"Management & Consulting",
            "type":"Services"
        }
    ],
    "sg:phone":"+1 505 762 9143",
    "sg:postcode":"88101",
    "sg:province":"NM",
    "sg:tags":[
        "food"
    ],
    "wof:name":"Aramark Corp",
    "wof:placetype":"venue"
},
  "geometry": {"coordinates":[-103.20665,34.406811],"type":"Point"}
}