{
  "type": "Feature",
  "properties": {
    "iso:country":"US",
    "sg:address":"502 Hst Rte 66",
    "sg:city":"Gallup",
    "sg:classifiers":[
        {
            "category":"Banks & Credit Unions",
            "subcategory":"Bank",
            "type":"Services"
        }
    ],
    "sg:phone":"+1 505 722 3912",
    "sg:postcode":"87301",
    "sg:province":"NM",
    "sg:tags":[
        "loan"
    ],
    "wof:name":"Metro Finance",
    "wof:placetype":"venue"
},
  "geometry": {"coordinates":[-108.735632,35.530107],"type":"Point"}
}