{
  "type": "Feature",
  "properties": {
    "iso:country":"US",
    "sg:address":"1116 Titleist Dr NE",
    "sg:city":"Albuquerque",
    "sg:classifiers":[
        {
            "category":"Insurance",
            "subcategory":"Insurance Agent",
            "type":"Services"
        }
    ],
    "sg:phone":"+1 505 323 5470",
    "sg:postcode":"87112",
    "sg:province":"NM",
    "wof:name":"National Assoc For Self-Employ",
    "wof:placetype":"venue"
},
  "geometry": {"coordinates":[-106.486946,35.090231],"type":"Point"}
}