{
  "type": "Feature",
  "properties": {
    "iso:country":"US",
    "sg:address":"663 Bishops Lodge Rd",
    "sg:city":"Santa Fe",
    "sg:classifiers":[
        {
            "category":"Building & Trades",
            "subcategory":"Electrical",
            "type":"Services"
        }
    ],
    "sg:phone":"+1 505 699 4915",
    "sg:postcode":"87501",
    "sg:province":"NM",
    "sg:tags":[
        "electric",
        "contractor"
    ],
    "wof:name":"Desert Design Electric",
    "wof:placetype":"venue"
},
  "geometry": {"coordinates":[-105.93141300000001,35.695983],"type":"Point"}
}