{
  "type": "Feature",
  "properties": {
    "addr:full":"1115 Ave I Eunice NM 88231",
    "addr:housenumber":"1115",
    "addr:postcode":"88231",
    "addr:street":"Ave I",
    "iso:country":"US",
    "sg:address":"1115 Ave I",
    "sg:city":"Eunice",
    "sg:classifiers":[
        {
            "category":"Recreation",
            "type":"Entertainment"
        }
    ],
    "sg:phone":"+1 505 394 4021",
    "sg:postcode":"88231",
    "sg:province":"NM",
    "sg:tags":[
        "hall",
        "auditorium"
    ],
    "wof:name":"Eunice Community Ctr",
    "wof:placetype":"venue"
},
  "geometry": {"coordinates":[-103.157332,32.436259],"type":"Point"}
}