{
  "type": "Feature",
  "properties": {
    "iso:country":"US",
    "sg:address":"605 San Mateo Blvd NE",
    "sg:city":"Albuquerque",
    "sg:classifiers":[
        {
            "category":"Wholesale",
            "subcategory":"Medical Equipment & Supplies",
            "type":"Manufacturing & Wholesale Goods"
        },
        {
            "category":"Health Services",
            "subcategory":"Hospital",
            "type":"Services"
        },
        {
            "category":"Shopping",
            "subcategory":"Pharmacy",
            "type":"Retail Goods"
        }
    ],
    "sg:phone":"+1 505 232 0272",
    "sg:postcode":"87108",
    "sg:province":"NM",
    "sg:tags":[
        "physician",
        "refinishing",
        "home",
        "surgeon",
        "equipment-repairing",
        "care"
    ],
    "sg:website":"http://www.righttrackmobility.com",
    "wof:name":"Right Track Mobility",
    "wof:placetype":"venue"
},
  "geometry": {"coordinates":[-106.586307,35.082748],"type":"Point"}
}