{
  "type": "Feature",
  "properties": {
    "iso:country":"US",
    "sg:address":"317 N Leech St",
    "sg:city":"Hobbs",
    "sg:classifiers":[
        {
            "category":"Manufacturing",
            "subcategory":"Petroleum Products",
            "type":"Manufacturing & Wholesale Goods"
        }
    ],
    "sg:phone":"+1 505 393 2013",
    "sg:postcode":"88240",
    "sg:province":"NM",
    "wof:name":"Phillips Petroleum",
    "wof:placetype":"venue"
},
  "geometry": {"coordinates":[-103.142468,32.703803],"type":"Point"}
}