{
  "type": "Feature",
  "properties": {
    "iso:country":"US",
    "sg:address":"3230 Matthew Ave NE",
    "sg:city":"Albuquerque",
    "sg:classifiers":[
        {
            "category":"Manufacturing",
            "subcategory":"Metals",
            "type":"Manufacturing & Wholesale Goods"
        },
        {
            "category":"Home & Garden",
            "subcategory":"Hardware",
            "type":"Retail Goods"
        },
        {
            "category":"Building & Trades",
            "subcategory":"Construction",
            "type":"Services"
        },
        {
            "category":"Manufacturing",
            "subcategory":"Building Materials",
            "type":"Manufacturing & Wholesale Goods"
        }
    ],
    "sg:phone":"+1 505 837 1112",
    "sg:postcode":"87107",
    "sg:province":"NM",
    "sg:tags":[
        "steel",
        "roofing",
        "industrial",
        "sheet",
        "work",
        "contractor",
        "warehouse",
        "contractors-commercial",
        "distributor",
        "fabricator",
        "mill",
        "store"
    ],
    "sg:website":"http://www.condeck.com",
    "wof:name":"Condeck Corporation",
    "wof:placetype":"venue"
},
  "geometry": {"coordinates":[-106.610329,35.115315],"type":"Point"}
}