{
  "type": "Feature",
  "properties": {
    "addr:full":"12408 Scarlet Gem Ave NE Albuquerque NM 87122",
    "addr:housenumber":"12408",
    "addr:postcode":"87122",
    "addr:street":"Scarlet Gem Ave Ne",
    "iso:country":"US",
    "sg:address":"12408 Scarlet Gem Ave NE",
    "sg:city":"Albuquerque",
    "sg:classifiers":[
        {
            "category":"Wholesale",
            "subcategory":"Groceries",
            "type":"Manufacturing & Wholesale Goods"
        }
    ],
    "sg:phone":"+1 505 385 8961",
    "sg:postcode":"87122",
    "sg:province":"NM",
    "sg:tags":[
        "nut",
        "processing"
    ],
    "wof:name":"We'Re Nutts",
    "wof:placetype":"venue"
},
  "geometry": {"coordinates":[-106.50567100000001,35.180921],"type":"Point"}
}