{
  "type": "Feature",
  "properties": {
    "iso:country":"US",
    "sg:address":"171 US Hwy 66",
    "sg:city":"Albuquerque",
    "sg:classifiers":[
        {
            "category":"Building & Trades",
            "subcategory":"Construction",
            "type":"Services"
        }
    ],
    "sg:phone":"+1 505 293 0099",
    "sg:postcode":"87123",
    "sg:province":"NM",
    "sg:tags":[
        "house"
    ],
    "wof:name":"Klp Construction/Remodeling",
    "wof:placetype":"venue"
},
  "geometry": {"coordinates":[-106.438686,35.063425],"type":"Point"}
}