{
  "type": "Feature",
  "properties": {
    "addr:full":"3814 Bonnie Ann Ct NE Albuquerque NM 87111",
    "addr:housenumber":"3814",
    "addr:postcode":"87111",
    "addr:street":"Bonnie Ann Ct Ne",
    "iso:country":"US",
    "sg:address":"3814 Bonnie Ann Ct NE",
    "sg:city":"Albuquerque",
    "sg:classifiers":[
        {
            "category":"Professional",
            "subcategory":"Business Services",
            "type":"Services"
        }
    ],
    "sg:phone":"+1 505 252 1746",
    "sg:postcode":"87111",
    "sg:province":"NM",
    "wof:name":"Albuquerque Pool Care",
    "wof:placetype":"venue"
},
  "geometry": {"coordinates":[-106.546927,35.128185],"type":"Point"}
}