{
  "type": "Feature",
  "properties": {
    "addr:full":"1917 Ridgecrest Dr SE Albuquerque NM 87108",
    "addr:housenumber":"1917",
    "addr:postcode":"87108",
    "addr:street":"Ridgecrest Dr Se",
    "iso:country":"US",
    "sg:address":"1917 Ridgecrest Dr SE",
    "sg:city":"Albuquerque",
    "sg:classifiers":[
        {
            "category":"Real Estate",
            "subcategory":"Real Estate Operator",
            "type":"Services"
        }
    ],
    "sg:phone":"+1 505 255 9139",
    "sg:postcode":"87108",
    "sg:province":"NM",
    "sg:tags":[
        "apartment"
    ],
    "wof:name":"Acorn Apartments",
    "wof:placetype":"venue"
},
  "geometry": {"coordinates":[-106.588464,35.059699],"type":"Point"}
}