{
  "type": "Feature",
  "properties": {
    "addr:full":"513 Hamlin Ave Texico NM 88135",
    "addr:housenumber":"513",
    "addr:postcode":"88135",
    "addr:street":"Hamlin Ave",
    "iso:country":"US",
    "sg:address":"513 Hamlin Ave",
    "sg:city":"Texico",
    "sg:classifiers":[
        {
            "category":"Organizations",
            "subcategory":"Religious Organization",
            "type":"Services"
        }
    ],
    "sg:phone":"+1 505 482 9002",
    "sg:postcode":"88135",
    "sg:province":"NM",
    "sg:tags":[
        "church"
    ],
    "wof:name":"United Pentecostal Church",
    "wof:placetype":"venue"
},
  "geometry": {"coordinates":[-103.048241,34.390759],"type":"Point"}
}