{
  "type": "Feature",
  "properties": {
    "iso:country":"US",
    "sg:address":"1570 Pacheco St",
    "sg:city":"Santa Fe",
    "sg:classifiers":[
        {
            "category":"Professional",
            "type":"Services"
        }
    ],
    "sg:phone":"+1 505 983 2528",
    "sg:postcode":"87505",
    "sg:province":"NM",
    "sg:tags":[
        "art",
        "restoring"
    ],
    "wof:name":"Steven Prins & Company",
    "wof:placetype":"venue"
},
  "geometry": {"coordinates":[-105.95999500000001,35.663339],"type":"Point"}
}