{
  "type": "Feature",
  "properties": {
    "iso:country":"US",
    "sg:address":"900 W 2nd St",
    "sg:city":"Roswell",
    "sg:classifiers":[
        {
            "category":"Food & Beverages",
            "subcategory":"Groceries & Convenience Stores",
            "type":"Retail Goods"
        }
    ],
    "sg:phone":"+1 505 623 6100",
    "sg:postcode":"88201",
    "sg:province":"NM",
    "sg:tags":[
        "grocer"
    ],
    "wof:name":"Lawrence Bros IGA",
    "wof:placetype":"venue"
},
  "geometry": {"coordinates":[-104.536092,33.394216],"type":"Point"}
}