{
  "type": "Feature",
  "properties": {
    "addr:full":"4808 N Michigan Ave Roswell NM 88201",
    "addr:housenumber":"4808",
    "addr:postcode":"88201",
    "addr:street":"N Michigan Ave",
    "iso:country":"US",
    "sg:address":"4808 N Michigan Ave",
    "sg:city":"Roswell",
    "sg:classifiers":[
        {
            "category":"Mining & Drilling",
            "type":"Manufacturing & Wholesale Goods"
        }
    ],
    "sg:phone":"+1 505 622 9874",
    "sg:postcode":"88201",
    "sg:province":"NM",
    "sg:tags":[
        "field",
        "oil"
    ],
    "wof:name":"Precision Gas Measurement Inc",
    "wof:placetype":"venue"
},
  "geometry": {"coordinates":[-104.534312,33.457406],"type":"Point"}
}