{
  "type": "Feature",
  "properties": {
    "iso:country":"US",
    "sg:address":"8313 Central Ave SE",
    "sg:city":"Albuquerque",
    "sg:classifiers":[
        {
            "category":"Retail",
            "subcategory":"Portrait Studio",
            "type":"Services"
        }
    ],
    "sg:phone":"+1 505 265 8028",
    "sg:postcode":"87108",
    "sg:province":"NM",
    "sg:tags":[
        "photographer"
    ],
    "wof:name":"Delgado's Creative Photography",
    "wof:placetype":"venue"
},
  "geometry": {"coordinates":[-106.553909,35.074353],"type":"Point"}
}