{
  "type": "Feature",
  "properties": {
    "iso:country":"US",
    "sg:address":"811 Don Gaspar Ave",
    "sg:city":"Santa Fe",
    "sg:classifiers":[
        {
            "category":"Professional",
            "subcategory":"Accounting & Tax Preparation",
            "type":"Services"
        }
    ],
    "sg:phone":"+1 505 986 9182",
    "sg:postcode":"87505",
    "sg:province":"NM",
    "wof:name":"Paula Baron",
    "wof:placetype":"venue"
},
  "geometry": {"coordinates":[-105.942041,35.676328],"type":"Point"}
}