{
  "type": "Feature",
  "properties": {
    "iso:country":"US",
    "sg:address":"2935 Monte Vista Blvd NE",
    "sg:city":"Albuquerque",
    "sg:classifiers":[
        {
            "category":"Manufacturing",
            "subcategory":"Signs",
            "type":"Manufacturing & Wholesale Goods"
        }
    ],
    "sg:phone":"+1 505 232 2112",
    "sg:postcode":"87106",
    "sg:province":"NM",
    "sg:tags":[
        "vinyl"
    ],
    "wof:name":"Sign & Image Factory",
    "wof:placetype":"venue"
},
  "geometry": {"coordinates":[-106.612359,35.081402],"type":"Point"}
}