{
  "type": "Feature",
  "properties": {
    "iso:country":"US",
    "sg:address":"4011 Mesa Verde Ave NE",
    "sg:city":"Albuquerque",
    "sg:classifiers":[
        {
            "category":"Professional",
            "subcategory":"Engineering",
            "type":"Services"
        }
    ],
    "sg:phone":"+1 505 266 2500",
    "sg:postcode":"87110",
    "sg:province":"NM",
    "sg:tags":[
        "mining",
        "engineer"
    ],
    "wof:name":"CU Flat LLC",
    "wof:placetype":"venue"
},
  "geometry": {"coordinates":[-106.598304,35.088516],"type":"Point"}
}