{
  "type": "Feature",
  "properties": {
    "iso:country":"US",
    "sg:address":"5105 Budding Ln",
    "sg:city":"Farmington",
    "sg:classifiers":[
        {
            "category":"Arts & Performance",
            "subcategory":"Theater",
            "type":"Entertainment"
        }
    ],
    "sg:phone":"+1 505 325 6655",
    "sg:postcode":"87402",
    "sg:province":"NM",
    "sg:tags":[
        "live",
        "music"
    ],
    "sg:website":"www.southwestdj.com",
    "wof:name":"Southwest DJ Svc",
    "wof:placetype":"venue"
},
  "geometry": {"coordinates":[-108.137328,36.776875],"type":"Point"}
}