{
  "type": "Feature",
  "properties": {
    "iso:country":"US",
    "sg:address":"4710 Central Ave SE",
    "sg:city":"Albuquerque",
    "sg:classifiers":[
        {
            "category":"Shopping",
            "subcategory":"Used Merchandise",
            "type":"Retail Goods"
        }
    ],
    "sg:phone":"+1 505 268 1313",
    "sg:postcode":"87108",
    "sg:province":"NM",
    "sg:tags":[
        "antique"
    ],
    "wof:name":"Antiques & Things",
    "wof:placetype":"venue"
},
  "geometry": {"coordinates":[-106.591407,35.078242],"type":"Point"}
}