{
  "type": "Feature",
  "properties": {
    "iso:country":"US",
    "sg:address":"8053 US Hwy 54",
    "sg:city":"Tularosa",
    "sg:classifiers":[
        {
            "category":"Home & Garden",
            "subcategory":"Garden Supply",
            "type":"Retail Goods"
        }
    ],
    "sg:phone":"+1 505 585 2684",
    "sg:postcode":"88352",
    "sg:province":"NM",
    "sg:tags":[
        "nurseryman"
    ],
    "wof:name":"M-T Tree Farm",
    "wof:placetype":"venue"
},
  "geometry": {"coordinates":[-106.030249,33.093449],"type":"Point"}
}