{
  "type": "Feature",
  "properties": {
    "addr:full":"8618 Menaul Blvd NE Albuquerque NM 87112",
    "addr:housenumber":"8618",
    "addr:postcode":"87112",
    "addr:street":"Menaul Blvd Ne",
    "iso:country":"US",
    "sg:address":"8618 Menaul Blvd NE",
    "sg:city":"Albuquerque",
    "sg:classifiers":[
        {
            "category":"Health Services",
            "subcategory":"Clinic",
            "type":"Services"
        }
    ],
    "sg:phone":"+1 505 363 3152",
    "sg:postcode":"87112",
    "sg:province":"NM",
    "sg:tags":[
        "holistic",
        "practitioner"
    ],
    "wof:name":"Whole Body Wellness",
    "wof:placetype":"venue"
},
  "geometry": {"coordinates":[-106.546052,35.10918],"type":"Point"}
}