{
  "type": "Feature",
  "properties": {
    "addr:full":"2918 Washington St NE Albuquerque NM 87110",
    "addr:housenumber":"2918",
    "addr:postcode":"87110",
    "addr:street":"Washington St Ne",
    "iso:country":"US",
    "sg:address":"2918 Washington St NE",
    "sg:city":"Albuquerque",
    "sg:classifiers":[
        {
            "category":"Professional",
            "subcategory":"Employment Agencies",
            "type":"Services"
        }
    ],
    "sg:phone":"+1 505 875 0316",
    "sg:postcode":"87110",
    "sg:province":"NM",
    "wof:name":"Bcd Services",
    "wof:placetype":"venue"
},
  "geometry": {"coordinates":[-106.59473,35.116178],"type":"Point"}
}