{
  "type": "Feature",
  "properties": {
    "iso:country":"US",
    "sg:address":"5905 Prenda de Oro Dr NW",
    "sg:city":"Albuquerque",
    "sg:classifiers":[
        {
            "category":"Freight",
            "type":"Transportation"
        }
    ],
    "sg:phone":"+1 505 352 5052",
    "sg:postcode":"87120",
    "sg:province":"NM",
    "sg:tags":[
        "operator",
        "mover",
        "local",
        "trucking"
    ],
    "wof:name":"Duke City Movers Inc",
    "wof:placetype":"venue"
},
  "geometry": {"coordinates":[-106.706191,35.115653],"type":"Point"}
}