{
  "type": "Feature",
  "properties": {
    "iso:country":"US",
    "sg:address":"3501 Haines Ave NE",
    "sg:city":"Albuquerque",
    "sg:classifiers":[
        {
            "category":"Professional",
            "subcategory":"Advertising",
            "type":"Services"
        }
    ],
    "sg:phone":"+1 505 268 7747",
    "sg:postcode":"87106",
    "sg:province":"NM",
    "sg:tags":[
        "agency"
    ],
    "wof:name":"G T Advertising",
    "wof:placetype":"venue"
},
  "geometry": {"coordinates":[-106.606604,35.099916],"type":"Point"}
}