{
  "type": "Feature",
  "properties": {
    "iso:country":"US",
    "sg:address":"7509 Rio Grande Blvd NW",
    "sg:city":"Albuquerque",
    "sg:classifiers":[
        {
            "category":"Recreation",
            "type":"Entertainment"
        }
    ],
    "sg:phone":"+1 505 898 0910",
    "sg:postcode":"87107",
    "sg:province":"NM",
    "sg:tags":[
        "stable"
    ],
    "sg:website":"www.hunter-jumper.com",
    "wof:name":"Top Notch Farm",
    "wof:placetype":"venue"
},
  "geometry": {"coordinates":[-106.64846300000001,35.172088],"type":"Point"}
}