{
  "type": "Feature",
  "properties": {
    "iso:country":"US",
    "sg:address":"10228 State Rte 104",
    "sg:city":"Tucumcari",
    "sg:classifiers":[
        {
            "category":"Home & Garden",
            "subcategory":"Home Furnishings",
            "type":"Retail Goods"
        }
    ],
    "sg:phone":"+1 505 461 3868",
    "sg:postcode":"88401",
    "sg:province":"NM",
    "sg:tags":[
        "pottery"
    ],
    "wof:name":"Red Earth Studio",
    "wof:placetype":"venue"
},
  "geometry": {"coordinates":[-103.762861,35.226408],"type":"Point"}
}