{
  "type": "Feature",
  "properties": {
    "iso:country":"US",
    "sg:address":"533 Washington St NE",
    "sg:city":"Albuquerque",
    "sg:classifiers":[
        {
            "category":"Health Services",
            "subcategory":"Health Practitioner",
            "type":"Services"
        }
    ],
    "sg:phone":"+1 505 262 2090",
    "sg:postcode":"87108",
    "sg:province":"NM",
    "wof:name":"Cao Joy Lac Dom",
    "wof:placetype":"venue"
},
  "geometry": {"coordinates":[-106.595392,35.0874],"type":"Point"}
}