{
  "type": "Feature",
  "properties": {
    "iso:country":"US",
    "sg:address":"1632 Mc Ewen Ct SW",
    "sg:city":"Albuquerque",
    "sg:classifiers":[
        {
            "category":"Retail",
            "subcategory":"Auto Repair",
            "type":"Services"
        }
    ],
    "sg:phone":"+1 505 873 3900",
    "sg:postcode":"87105",
    "sg:province":"NM",
    "sg:tags":[
        "automotive"
    ],
    "wof:name":"Auto Specialty Auto",
    "wof:placetype":"venue"
},
  "geometry": {"coordinates":[-106.680846,35.046247],"type":"Point"}
}