{
  "type": "Feature",
  "properties": {
    "addr:full":"5051 Apache Trl Las Cruces NM 88012",
    "addr:housenumber":"5051",
    "addr:postcode":"88012",
    "addr:street":"Apache Trl",
    "iso:country":"US",
    "sg:address":"5051 Apache Trl",
    "sg:city":"Las Cruces",
    "sg:classifiers":[
        {
            "category":"Retail",
            "subcategory":"Repair Shop",
            "type":"Services"
        }
    ],
    "sg:phone":"+1 505 621 3682",
    "sg:postcode":"88012",
    "sg:province":"NM",
    "sg:tags":[
        "bathtub",
        "sink",
        "refinishing"
    ],
    "wof:name":"Miracle Method",
    "wof:placetype":"venue"
},
  "geometry": {"coordinates":[-106.788258,32.384847],"type":"Point"}
}