{
  "type": "Feature",
  "properties": {
    "addr:full":"6 Ave de Garcia Santa Fe NM 87507",
    "addr:postcode":"87507",
    "addr:street":"6 Ave De Garcia",
    "iso:country":"US",
    "sg:address":"6 Ave de Garcia",
    "sg:city":"Santa Fe",
    "sg:classifiers":[
        {
            "category":"Building & Trades",
            "subcategory":"Construction",
            "type":"Services"
        }
    ],
    "sg:phone":"+1 505 473 4537",
    "sg:postcode":"87507",
    "sg:province":"NM",
    "sg:tags":[
        "general",
        "contractor"
    ],
    "wof:name":"Marcials Construction Inc",
    "wof:placetype":"venue"
},
  "geometry": {"coordinates":[-106.107314,35.582526],"type":"Point"}
}