{
  "type": "Feature",
  "properties": {
    "addr:full":"7401 Menaul Blvd NE Albuquerque NM 87110",
    "addr:housenumber":"7401",
    "addr:postcode":"87110",
    "addr:street":"Menaul Blvd Ne",
    "iso:country":"US",
    "sg:address":"7401 Menaul Blvd NE",
    "sg:city":"Albuquerque",
    "sg:classifiers":[
        {
            "category":"Shopping",
            "subcategory":"Bicycles & Sporting Goods",
            "type":"Retail Goods"
        }
    ],
    "sg:phone":"+1 505 883 4342",
    "sg:postcode":"87110",
    "sg:province":"NM",
    "sg:tags":[
        "gun",
        "gunsmith"
    ],
    "wof:name":"Precision Arms Of NM Inc",
    "wof:placetype":"venue"
},
  "geometry": {"coordinates":[-106.561137,35.10919],"type":"Point"}
}