{
  "type": "Feature",
  "properties": {
    "addr:full":"131 Bookout Rd Tularosa NM 88352",
    "addr:housenumber":"131",
    "addr:postcode":"88352",
    "addr:street":"Bookout Rd",
    "iso:country":"US",
    "sg:address":"131 Bookout Rd",
    "sg:city":"Tularosa",
    "sg:classifiers":[
        {
            "category":"Travel",
            "subcategory":"Travel Agent",
            "type":"Entertainment"
        }
    ],
    "sg:phone":"+1 505 585 3522",
    "sg:postcode":"88352",
    "sg:province":"NM",
    "sg:tags":[
        "agency",
        "bureau"
    ],
    "wof:name":"Tularosa Travel Ctr",
    "wof:placetype":"venue"
},
  "geometry": {"coordinates":[-106.01073,33.071329],"type":"Point"}
}