{
  "type": "Feature",
  "properties": {
    "iso:country":"US",
    "sg:address":"1102 Sudderth Dr",
    "sg:city":"Ruidoso",
    "sg:classifiers":[
        {
            "category":"Home & Garden",
            "subcategory":"Furniture",
            "type":"Retail Goods"
        }
    ],
    "sg:phone":"+1 505 257 5094",
    "sg:postcode":"88345",
    "sg:province":"NM",
    "sg:tags":[
        "mattress"
    ],
    "wof:name":"Sierra Wholesale Mattress",
    "wof:placetype":"venue"
},
  "geometry": {"coordinates":[-105.659103,33.325698],"type":"Point"}
}