{
  "type": "Feature",
  "properties": {
    "iso:country":"US",
    "sg:address":"3709 General Patch St NE",
    "sg:city":"Albuquerque",
    "sg:classifiers":[
        {
            "category":"Arts & Performance",
            "subcategory":"Theater",
            "type":"Entertainment"
        }
    ],
    "sg:phone":"+1 505 299 8487",
    "sg:postcode":"87111",
    "sg:province":"NM",
    "sg:tags":[
        "group"
    ],
    "wof:name":"Adkins Entertainment Inc",
    "wof:placetype":"venue"
},
  "geometry": {"coordinates":[-106.545175,35.1257],"type":"Point"}
}