{
  "type": "Feature",
  "properties": {
    "iso:country":"US",
    "sg:address":"100 Court St",
    "sg:city":"Clayton",
    "sg:classifiers":[
        {
            "category":"Health Services",
            "subcategory":"Doctor",
            "type":"Services"
        }
    ],
    "sg:phone":"+1 505 374 8393",
    "sg:postcode":"88415",
    "sg:province":"NM",
    "sg:tags":[
        "clinic"
    ],
    "wof:name":"Family Planning Svc",
    "wof:placetype":"venue"
},
  "geometry": {"coordinates":[-103.18736199999999,36.450064],"type":"Point"}
}