{
  "type": "Feature",
  "properties": {
    "iso:country":"US",
    "sg:address":"314 S 2nd St",
    "sg:city":"Tucumcari",
    "sg:classifiers":[
        {
            "category":"Professional",
            "subcategory":"Accounting & Tax Preparation",
            "type":"Services"
        }
    ],
    "sg:phone":"+1 505 461 1195",
    "sg:postcode":"88401",
    "sg:province":"NM",
    "sg:tags":[
        "accountant"
    ],
    "wof:name":"R Kelly Mc Farland CPA",
    "wof:placetype":"venue"
},
  "geometry": {"coordinates":[-103.72602999999999,35.176847],"type":"Point"}
}