{
  "type": "Feature",
  "properties": {
    "addr:full":"902 Green Valley Rd NW Albuquerque NM 87107",
    "addr:housenumber":"902",
    "addr:postcode":"87107",
    "addr:street":"Green Valley Rd Nw",
    "iso:country":"US",
    "sg:address":"902 Green Valley Rd NW",
    "sg:city":"Albuquerque",
    "sg:classifiers":[
        {
            "category":"Food & Beverages",
            "subcategory":"Specialty",
            "type":"Retail Goods"
        }
    ],
    "sg:phone":"+1 505 343 0499",
    "sg:postcode":"87107",
    "sg:province":"NM",
    "wof:name":"Anthony Van Dyke-Nutrition",
    "wof:placetype":"venue"
},
  "geometry": {"coordinates":[-106.645619,35.15942],"type":"Point"}
}