{
  "type": "Feature",
  "properties": {
    "iso:country":"US",
    "sg:address":"35 George Ct",
    "sg:city":"Edgewood",
    "sg:classifiers":[
        {
            "category":"Professional",
            "type":"Services"
        }
    ],
    "sg:phone":"+1 505 832 9222",
    "sg:postcode":"87015",
    "sg:province":"NM",
    "sg:tags":[
        "establishment"
    ],
    "wof:name":"Us Southwest Soaring Musuem",
    "wof:placetype":"venue"
},
  "geometry": {"coordinates":[-106.19858600000001,35.065396],"type":"Point"}
}