{
  "type": "Feature",
  "properties": {
    "iso:country":"US",
    "sg:address":"113 Barranca Rd",
    "sg:city":"Santa Fe",
    "sg:classifiers":[
        {
            "category":"Shopping",
            "subcategory":"Computers & Home Electronics",
            "type":"Retail Goods"
        }
    ],
    "sg:phone":"+1 505 986 0094",
    "sg:postcode":"87501",
    "sg:province":"NM",
    "sg:tags":[
        "software"
    ],
    "wof:name":"Arterial Inc",
    "wof:placetype":"venue"
},
  "geometry": {"coordinates":[-105.917263,35.712011],"type":"Point"}
}