{
  "type": "Feature",
  "properties": {
    "addr:full":"602 W Main St Farmington NM 87401",
    "addr:housenumber":"602",
    "addr:postcode":"87401",
    "addr:street":"W Main St",
    "iso:country":"US",
    "sg:address":"602 W Main St",
    "sg:city":"Farmington",
    "sg:classifiers":[
        {
            "category":"Wholesale",
            "subcategory":"Construction Materials",
            "type":"Manufacturing & Wholesale Goods"
        }
    ],
    "sg:phone":"+1 505 327 9677",
    "sg:postcode":"87401",
    "sg:province":"NM",
    "sg:tags":[
        "h"
    ],
    "wof:name":"Sun Glass LLC",
    "wof:placetype":"venue"
},
  "geometry": {"coordinates":[-108.211843,36.729094],"type":"Point"}
}