{
  "type": "Feature",
  "properties": {
    "addr:full":"5820 Warren Ln SW Albuquerque NM 87105",
    "addr:housenumber":"5820",
    "addr:postcode":"87105",
    "addr:street":"Warren Ln Sw",
    "iso:country":"US",
    "sg:address":"5820 Warren Ln SW",
    "sg:city":"Albuquerque",
    "sg:classifiers":[
        {
            "category":"Building & Trades",
            "subcategory":"Construction",
            "type":"Services"
        }
    ],
    "sg:phone":"+1 505 296 3648",
    "sg:postcode":"87105",
    "sg:province":"NM",
    "sg:tags":[
        "general",
        "contractor"
    ],
    "wof:name":"New Traditions Bldrs Ltd Lblty",
    "wof:placetype":"venue"
},
  "geometry": {"coordinates":[-106.702529,34.994947],"type":"Point"}
}