{
  "type": "Feature",
  "properties": {
    "addr:full":"3108 San Mateo Blvd NE Albuquerque NM 87110",
    "addr:housenumber":"3108",
    "addr:postcode":"87110",
    "addr:street":"San Mateo Blvd Ne",
    "iso:country":"US",
    "sg:address":"3108 San Mateo Blvd NE",
    "sg:city":"Albuquerque",
    "sg:classifiers":[
        {
            "category":"Personal",
            "type":"Services"
        }
    ],
    "sg:phone":"+1 505 385 0139",
    "sg:postcode":"87110",
    "sg:province":"NM",
    "sg:tags":[
        "therapist",
        "massage"
    ],
    "wof:name":"De Medicina Therapeutic Mssg",
    "wof:placetype":"venue"
},
  "geometry": {"coordinates":[-106.58634000000001,35.119745],"type":"Point"}
}