{
  "type": "Feature",
  "properties": {
    "iso:country":"US",
    "sg:address":"3232 Cerrillos Rd",
    "sg:city":"Santa Fe",
    "sg:classifiers":[
        {
            "category":"Shopping",
            "subcategory":"Florist",
            "type":"Retail Goods"
        }
    ],
    "sg:phone":"+1 505 471 1191",
    "sg:postcode":"87507",
    "sg:province":"NM",
    "sg:tags":[
        "equipment"
    ],
    "wof:name":"Carpenter & Co",
    "wof:placetype":"venue"
},
  "geometry": {"coordinates":[-105.998966,35.650802],"type":"Point"}
}