{
  "type": "Feature",
  "properties": {
    "iso:country":"US",
    "sg:address":"805 Nikanda Rd NE",
    "sg:city":"Albuquerque",
    "sg:classifiers":[
        {
            "category":"Professional",
            "subcategory":"Management & Consulting",
            "type":"Services"
        }
    ],
    "sg:phone":"+1 505 980 5010",
    "sg:postcode":"87107",
    "sg:province":"NM",
    "wof:name":"Cls Consulting",
    "wof:placetype":"venue"
},
  "geometry": {"coordinates":[-106.625545,35.131564],"type":"Point"}
}