{
  "type": "Feature",
  "properties": {
    "iso:country":"US",
    "sg:address":"1501 S 4th St",
    "sg:city":"Raton",
    "sg:classifiers":[
        {
            "category":"Organizations",
            "subcategory":"Religious Organization",
            "type":"Services"
        }
    ],
    "sg:phone":"+1 505 445 3262",
    "sg:postcode":"87740",
    "sg:province":"NM",
    "wof:name":"First United Methodist Church",
    "wof:placetype":"venue"
},
  "geometry": {"coordinates":[-104.44981,36.888246],"type":"Point"}
}