{
  "type": "Feature",
  "properties": {
    "iso:country":"US",
    "sg:address":"6711 Academy Rd NE",
    "sg:city":"Albuquerque",
    "sg:classifiers":[
        {
            "category":"Banks & Credit Unions",
            "subcategory":"Bank",
            "type":"Services"
        }
    ],
    "sg:phone":"+1 505 292 7200",
    "sg:postcode":"87109",
    "sg:province":"NM",
    "sg:tags":[
        "loan",
        "real estate"
    ],
    "wof:name":"Charter Funding",
    "wof:placetype":"venue"
},
  "geometry": {"coordinates":[-106.57218,35.145422],"type":"Point"}
}