{
  "type": "Feature",
  "properties": {
    "iso:country":"US",
    "sg:address":"1301 Oregon Ave",
    "sg:city":"Alamogordo",
    "sg:classifiers":[
        {
            "category":"Health Services",
            "subcategory":"Doctor",
            "type":"Services"
        }
    ],
    "sg:phone":"+1 505 437 0667",
    "sg:postcode":"88310",
    "sg:province":"NM",
    "sg:tags":[
        "medical"
    ],
    "wof:name":"Back In Line Chiropractic Ctr",
    "wof:placetype":"venue"
},
  "geometry": {"coordinates":[-105.944586,32.905071],"type":"Point"}
}