{
  "type": "Feature",
  "properties": {
    "iso:country":"US",
    "sg:address":"575 S Alameda Blvd",
    "sg:city":"Las Cruces",
    "sg:classifiers":[
        {
            "category":"Building & Trades",
            "subcategory":"Construction",
            "type":"Services"
        }
    ],
    "sg:phone":"+1 505 528 3333",
    "sg:postcode":"88005",
    "sg:province":"NM",
    "sg:tags":[
        "marking",
        "maintenance",
        "parking"
    ],
    "sg:website":"www.las-cruces.org",
    "wof:name":"Las Cruces Public Works",
    "wof:placetype":"venue"
},
  "geometry": {"coordinates":[-106.780131,32.305586],"type":"Point"}
}