{
  "type": "Feature",
  "properties": {
    "addr:full":"363 S Espina St Las Cruces NM 88001",
    "addr:housenumber":"363",
    "addr:postcode":"88001",
    "addr:street":"S Espina St",
    "iso:country":"US",
    "sg:address":"363 S Espina St",
    "sg:city":"Las Cruces",
    "sg:classifiers":[
        {
            "category":"Cafe",
            "type":"Food & Drink"
        }
    ],
    "sg:menulink":"http://www.allmenus.com/nm/las-cruces/5509-el-sombrero-patio-cafe/menu/",
    "sg:phone":"+1 505 524 9911",
    "sg:postcode":"88001",
    "sg:province":"NM",
    "sg:tags":[
        "mexican"
    ],
    "wof:name":"El Sombrero Patio Cafe",
    "wof:placetype":"venue"
},
  "geometry": {"coordinates":[-106.770309,32.313856],"type":"Point"}
}