{
  "type": "Feature",
  "properties": {
    "iso:country":"US",
    "sg:address":"224 W Center St",
    "sg:city":"Tucumcari",
    "sg:classifiers":[
        {
            "category":"Retail",
            "subcategory":"Repair Shop",
            "type":"Services"
        }
    ],
    "sg:phone":"+1 505 461 3040",
    "sg:postcode":"88401",
    "sg:province":"NM",
    "sg:tags":[
        "welding"
    ],
    "wof:name":"Peterson's Welding",
    "wof:placetype":"venue"
},
  "geometry": {"coordinates":[-103.728335,35.177947],"type":"Point"}
}