{
  "type": "Feature",
  "properties": {
    "iso:country":"US",
    "sg:address":"613 E Corbett St",
    "sg:city":"Hobbs",
    "sg:classifiers":[
        {
            "category":"Real Estate",
            "subcategory":"Real Estate Agent",
            "type":"Services"
        }
    ],
    "sg:phone":"+1 505 397 1510",
    "sg:postcode":"88240",
    "sg:province":"NM",
    "wof:name":"TGS Properties",
    "wof:placetype":"venue"
},
  "geometry": {"coordinates":[-103.129909,32.710137],"type":"Point"}
}