{
  "type": "Feature",
  "properties": {
    "iso:country":"US",
    "sg:address":"400 W 7th St",
    "sg:city":"Clovis",
    "sg:classifiers":[
        {
            "category":"Retail",
            "subcategory":"Car Wash",
            "type":"Services"
        }
    ],
    "sg:phone":"+1 505 769 8875",
    "sg:postcode":"88101",
    "sg:province":"NM",
    "sg:tags":[
        "automobile",
        "detail",
        "clean"
    ],
    "wof:name":"Willie's Detail",
    "wof:placetype":"venue"
},
  "geometry": {"coordinates":[-103.21048,34.40472],"type":"Point"}
}