{
  "type": "Feature",
  "properties": {
    "iso:country":"US",
    "sg:address":"3624 Central Ave SE",
    "sg:city":"Albuquerque",
    "sg:classifiers":[
        {
            "category":"Restaurant",
            "type":"Food & Drink"
        }
    ],
    "sg:phone":"+1 505 232 2787",
    "sg:postcode":"87108",
    "sg:province":"NM",
    "wof:name":"Buster's 66 Coffeeshop",
    "wof:placetype":"venue"
},
  "geometry": {"coordinates":[-106.603582,35.079617],"type":"Point"}
}