{
  "type": "Feature",
  "properties": {
    "iso:country":"US",
    "sg:address":"13223 Desert Rose Ave NE",
    "sg:city":"Albuquerque",
    "sg:classifiers":[
        {
            "category":"Real Estate",
            "subcategory":"Real Estate Agent",
            "type":"Services"
        }
    ],
    "sg:phone":"+1 505 828 0675",
    "sg:postcode":"87111",
    "sg:province":"NM",
    "sg:tags":[
        "appraiser"
    ],
    "wof:name":"Judy A Roberts Appraisals",
    "wof:placetype":"venue"
},
  "geometry": {"coordinates":[-106.48792400000001,35.155814],"type":"Point"}
}