{
  "type": "Feature",
  "properties": {
    "iso:country":"US",
    "sg:address":"10820 Comanche Rd NE",
    "sg:city":"Albuquerque",
    "sg:classifiers":[
        {
            "category":"Health Services",
            "subcategory":"Doctor",
            "type":"Services"
        }
    ],
    "sg:phone":"+1 505 296 0761",
    "sg:postcode":"87111",
    "sg:province":"NM",
    "sg:tags":[
        "dentist"
    ],
    "sg:website":"www.jkeortho.com",
    "wof:name":"James K Economides LTD",
    "wof:placetype":"venue"
},
  "geometry": {"coordinates":[-106.519385,35.123455],"type":"Point"}
}