{
  "type": "Feature",
  "properties": {
    "iso:country":"US",
    "sg:address":"2122 Valley Rd SW",
    "sg:city":"Albuquerque",
    "sg:classifiers":[
        {
            "category":"Building & Trades",
            "subcategory":"Plumbing",
            "type":"Services"
        }
    ],
    "sg:phone":"+1 505 804 1559",
    "sg:postcode":"87105",
    "sg:province":"NM",
    "sg:tags":[
        "conditioning",
        "air",
        "system",
        "contractor"
    ],
    "wof:name":"F M Mechanical",
    "wof:placetype":"venue"
},
  "geometry": {"coordinates":[-106.689373,35.040751],"type":"Point"}
}