{
  "type": "Feature",
  "properties": {
    "addr:full":"9205 Galaxia Way NE Albuquerque NM 87111",
    "addr:housenumber":"9205",
    "addr:postcode":"87111",
    "addr:street":"Galaxia Way Ne",
    "iso:country":"US",
    "sg:address":"9205 Galaxia Way NE",
    "sg:city":"Albuquerque",
    "sg:classifiers":[
        {
            "category":"Professional",
            "subcategory":"Employment Agencies",
            "type":"Services"
        }
    ],
    "sg:phone":"+1 505 856 9480",
    "sg:postcode":"87111",
    "sg:province":"NM",
    "sg:tags":[
        "help",
        "contractor"
    ],
    "wof:name":"Images",
    "wof:placetype":"venue"
},
  "geometry": {"coordinates":[-106.541343,35.143848],"type":"Point"}
}