{
  "type": "Feature",
  "properties": {
    "iso:country":"US",
    "sg:address":"4009 Skyline Dr",
    "sg:city":"Farmington",
    "sg:classifiers":[
        {
            "category":"Health Services",
            "subcategory":"Doctor",
            "type":"Services"
        }
    ],
    "sg:phone":"+1 505 327 7922",
    "sg:postcode":"87401",
    "sg:province":"NM",
    "sg:tags":[
        "medical"
    ],
    "wof:name":"Lynne Bliss MD",
    "wof:placetype":"venue"
},
  "geometry": {"coordinates":[-108.202467,36.765006],"type":"Point"}
}