{
  "type": "Feature",
  "properties": {
    "addr:full":"180 Apache Cir Gallup NM 87301",
    "addr:housenumber":"180",
    "addr:postcode":"87301",
    "addr:street":"Apache Cir",
    "iso:country":"US",
    "sg:address":"180 Apache Cir",
    "sg:city":"Gallup",
    "sg:classifiers":[
        {
            "category":"Wholesale",
            "subcategory":"Hardware",
            "type":"Manufacturing & Wholesale Goods"
        }
    ],
    "sg:phone":"+1 505 863 9584",
    "sg:postcode":"87301",
    "sg:province":"NM",
    "sg:tags":[
        "beverage",
        "dispensing"
    ],
    "wof:name":"Pepsi-Cola Co",
    "wof:placetype":"venue"
},
  "geometry": {"coordinates":[-108.737796,35.518242],"type":"Point"}
}