{
  "type": "Feature",
  "properties": {
    "addr:full":"14 Millers End Santa Fe NM 87508",
    "addr:housenumber":"14",
    "addr:postcode":"87508",
    "addr:street":"Millers End",
    "iso:country":"US",
    "sg:address":"14 Millers End",
    "sg:city":"Santa Fe",
    "sg:classifiers":[
        {
            "category":"Shopping",
            "subcategory":"Florist",
            "type":"Retail Goods"
        }
    ],
    "sg:phone":"+1 505 577 6098",
    "sg:postcode":"87508",
    "sg:province":"NM",
    "wof:name":"Blumen Kenner",
    "wof:placetype":"venue"
},
  "geometry": {"coordinates":[-105.943031,35.604673],"type":"Point"}
}