{
  "type": "Feature",
  "properties": {
    "iso:country":"US",
    "sg:address":"1100 E Lincoln Rd",
    "sg:city":"Hobbs",
    "sg:classifiers":[
        {
            "category":"Professional",
            "type":"Services"
        }
    ],
    "sg:phone":"+1 505 393 6113",
    "sg:postcode":"88240",
    "sg:province":"NM",
    "sg:tags":[
        "establishment"
    ],
    "wof:name":"V & J Enterprises Inc",
    "wof:placetype":"venue"
},
  "geometry": {"coordinates":[-103.12326299999999,32.719789],"type":"Point"}
}