{
  "type": "Feature",
  "properties": {
    "addr:full":"10208 Karen Ave NE Albuquerque NM 87111",
    "addr:housenumber":"10208",
    "addr:postcode":"87111",
    "addr:street":"Karen Ave Ne",
    "iso:country":"US",
    "sg:address":"10208 Karen Ave NE",
    "sg:city":"Albuquerque",
    "sg:classifiers":[
        {
            "category":"Restaurant",
            "type":"Food & Drink"
        },
        {
            "category":"Food & Beverages",
            "subcategory":"Groceries & Convenience Stores",
            "type":"Retail Goods"
        }
    ],
    "sg:phone":"+1 505 892 5892",
    "sg:postcode":"87111",
    "sg:province":"NM",
    "sg:tags":[
        "shop",
        "sandwich"
    ],
    "wof:name":"Sub Zero Refrgrtn",
    "wof:placetype":"venue"
},
  "geometry": {"coordinates":[-106.52739099999999,35.127441],"type":"Point"}
}