{
  "type": "Feature",
  "properties": {
    "addr:full":"117 W Lime St Portales NM 88130",
    "addr:housenumber":"117",
    "addr:postcode":"88130",
    "addr:street":"W Lime St",
    "iso:country":"US",
    "sg:address":"117 W Lime St",
    "sg:city":"Portales",
    "sg:classifiers":[
        {
            "category":"Freight",
            "type":"Transportation"
        }
    ],
    "sg:phone":"+1 505 356 8374",
    "sg:postcode":"88130",
    "sg:province":"NM",
    "sg:tags":[
        "operator",
        "local",
        "trucking"
    ],
    "wof:name":"Wish Trucking Inc",
    "wof:placetype":"venue"
},
  "geometry": {"coordinates":[-103.3407,34.193361],"type":"Point"}
}