{
  "type": "Feature",
  "properties": {
    "iso:country":"US",
    "sg:address":"1205 Main St",
    "sg:city":"Eunice",
    "sg:classifiers":[
        {
            "category":"Retail",
            "subcategory":"Auto Repair",
            "type":"Services"
        }
    ],
    "sg:phone":"+1 505 394 2742",
    "sg:postcode":"88231",
    "sg:province":"NM",
    "sg:tags":[
        "wrecker"
    ],
    "wof:name":"J D's Wrecker & Svc Ctr",
    "wof:placetype":"venue"
},
  "geometry": {"coordinates":[-103.159498,32.440559],"type":"Point"}
}