{
  "type": "Feature",
  "properties": {
    "iso:country":"US",
    "sg:address":"425 Edmon Rd NE",
    "sg:city":"Albuquerque",
    "sg:classifiers":[
        {
            "category":"Manufacturing",
            "subcategory":"Buildings",
            "type":"Manufacturing & Wholesale Goods"
        },
        {
            "category":"Building & Trades",
            "subcategory":"Construction",
            "type":"Services"
        }
    ],
    "sg:phone":"+1 505 345 2854",
    "sg:postcode":"87107",
    "sg:province":"NM",
    "sg:tags":[
        "industrial",
        "system",
        "specialty",
        "builder",
        "heating",
        "contractor",
        "contractors-commercial",
        "home",
        "air conditioning"
    ],
    "sg:website":"http://www.wilger.com",
    "wof:name":"Wilger Enterprises, Inc.",
    "wof:placetype":"venue"
},
  "geometry": {"coordinates":[-106.625167,35.136834],"type":"Point"}
}