{
  "type": "Feature",
  "properties": {
    "iso:country":"US",
    "sg:address":"420 Columbus Rd",
    "sg:city":"Deming",
    "sg:classifiers":[
        {
            "category":"Personal",
            "subcategory":"Beauty Salon",
            "type":"Services"
        }
    ],
    "sg:phone":"+1 505 546 0075",
    "sg:postcode":"88030",
    "sg:province":"NM",
    "sg:tags":[
        "shop"
    ],
    "wof:name":"Today's Hair Beauty Salon",
    "wof:placetype":"venue"
},
  "geometry": {"coordinates":[-107.75827700000001,32.265386],"type":"Point"}
}