{
  "type": "Feature",
  "properties": {
    "iso:country":"US",
    "sg:address":"2012 Eubank Blvd NE",
    "sg:city":"Albuquerque",
    "sg:classifiers":[
        {
            "category":"Real Estate",
            "subcategory":"Real Estate Agent",
            "type":"Services"
        }
    ],
    "sg:phone":"+1 505 271 8728",
    "sg:postcode":"87112",
    "sg:province":"NM",
    "wof:name":"Sentinel Real Estate Corp",
    "wof:placetype":"venue"
},
  "geometry": {"coordinates":[-106.532915,35.103791],"type":"Point"}
}