{
  "type": "Feature",
  "properties": {
    "iso:country":"US",
    "sg:address":"3804 National Parks Hwy",
    "sg:city":"Carlsbad",
    "sg:classifiers":[
        {
            "category":"Professional",
            "subcategory":"Business Services",
            "type":"Services"
        }
    ],
    "sg:phone":"+1 505 887 5535",
    "sg:postcode":"88220",
    "sg:province":"NM",
    "sg:tags":[
        "reservation",
        "motel",
        "hotel"
    ],
    "wof:name":"Great Western Inn & Suites",
    "wof:placetype":"venue"
},
  "geometry": {"coordinates":[-104.228736,32.375923],"type":"Point"}
}