{
  "type": "Feature",
  "properties": {
    "addr:full":"13133 Cam del Norte NE Albuquerque NM 87123",
    "addr:housenumber":"13133",
    "addr:postcode":"87123",
    "addr:street":"Cam Del Norte Ne",
    "iso:country":"US",
    "sg:address":"13133 Cam del Norte NE",
    "sg:city":"Albuquerque",
    "sg:classifiers":[
        {
            "category":"Manufacturing",
            "subcategory":"Retail Goods",
            "type":"Manufacturing & Wholesale Goods"
        }
    ],
    "sg:phone":"+1 505 292 7023",
    "sg:postcode":"87123",
    "sg:province":"NM",
    "sg:tags":[
        "product",
        "mfg"
    ],
    "wof:name":"Barely Bears & Friends",
    "wof:placetype":"venue"
},
  "geometry": {"coordinates":[-106.50255300000001,35.080743],"type":"Point"}
}