{
  "type": "Feature",
  "properties": {
    "iso:country":"US",
    "sg:address":"2311 Cottage San Rd",
    "sg:city":"Silver City",
    "sg:classifiers":[
        {
            "category":"Building & Trades",
            "subcategory":"Construction",
            "type":"Services"
        }
    ],
    "sg:phone":"+1 505 538 0518",
    "sg:postcode":"88061",
    "sg:province":"NM",
    "sg:tags":[
        "general",
        "contractor"
    ],
    "wof:name":"Mc Arthur General Contracting",
    "wof:placetype":"venue"
},
  "geometry": {"coordinates":[-108.306817,32.823459],"type":"Point"}
}