{
  "type": "Feature",
  "properties": {
    "iso:country":"US",
    "sg:address":"6715 Pryor Ln",
    "sg:city":"Farmington",
    "sg:classifiers":[
        {
            "category":"Wholesale",
            "subcategory":"Non-durable Goods",
            "type":"Manufacturing & Wholesale Goods"
        }
    ],
    "sg:phone":"+1 505 325 3447",
    "sg:postcode":"87402",
    "sg:province":"NM",
    "sg:tags":[
        "export",
        "merchandise",
        "general"
    ],
    "wof:name":"Dimmick Carbajal",
    "wof:placetype":"venue"
},
  "geometry": {"coordinates":[-108.12437,36.77313],"type":"Point"}
}