{
  "type": "Feature",
  "properties": {
    "iso:country":"US",
    "sg:address":"1120 W Santa Fe Ave",
    "sg:city":"Grants",
    "sg:classifiers":[
        {
            "category":"Real Estate",
            "subcategory":"Real Estate Agent",
            "type":"Services"
        }
    ],
    "sg:phone":"+1 505 287 7110",
    "sg:postcode":"87020",
    "sg:province":"NM",
    "wof:name":"Remax Elegance",
    "wof:placetype":"venue"
},
  "geometry": {"coordinates":[-107.860309,35.154433],"type":"Point"}
}