{
  "type": "Feature",
  "properties": {
    "iso:country":"US",
    "sg:address":"521 S Canal St",
    "sg:city":"Carlsbad",
    "sg:classifiers":[
        {
            "category":"Retail",
            "subcategory":"Self-service Laundry",
            "type":"Services"
        }
    ],
    "sg:phone":"+1 505 885 1183",
    "sg:postcode":"88220",
    "sg:province":"NM",
    "wof:name":"Clean Corner Laundry",
    "wof:placetype":"venue"
},
  "geometry": {"coordinates":[-104.229113,32.415356],"type":"Point"}
}