{
  "type": "Feature",
  "properties": {
    "iso:country":"US",
    "sg:address":"2729 Dallas St NE",
    "sg:city":"Albuquerque",
    "sg:classifiers":[
        {
            "category":"Wholesale",
            "subcategory":"Auto Parts",
            "type":"Manufacturing & Wholesale Goods"
        }
    ],
    "sg:phone":"+1 720 206 0136",
    "sg:postcode":"87110",
    "sg:province":"NM",
    "sg:tags":[
        "new",
        "vehicle",
        "motor",
        "supply"
    ],
    "wof:name":"Ewi Inc",
    "wof:placetype":"venue"
},
  "geometry": {"coordinates":[-106.561213,35.112319],"type":"Point"}
}