{
  "type": "Feature",
  "properties": {
    "iso:country":"US",
    "sg:address":"2009 Botulph Rd",
    "sg:city":"Santa Fe",
    "sg:classifiers":[
        {
            "category":"Professional",
            "subcategory":"Lawyer & Legal Services",
            "type":"Services"
        }
    ],
    "sg:phone":"+1 505 988 9646",
    "sg:postcode":"87505",
    "sg:province":"NM",
    "sg:tags":[
        "attorney"
    ],
    "wof:name":"Gerber & Bateman",
    "wof:placetype":"venue"
},
  "geometry": {"coordinates":[-105.948102,35.654069],"type":"Point"}
}