{
  "type": "Feature",
  "properties": {
    "iso:country":"US",
    "sg:address":"2500 N Main St",
    "sg:city":"Las Cruces",
    "sg:classifiers":[
        {
            "category":"Shopping",
            "subcategory":"Discount & Variety Stores",
            "type":"Retail Goods"
        },
        {
            "category":"Shopping",
            "subcategory":"Department Store",
            "type":"Retail Goods"
        }
    ],
    "sg:phone":"+1 505 541 0447",
    "sg:postcode":"88001",
    "sg:province":"NM",
    "wof:name":"99 Cents Store",
    "wof:placetype":"venue"
},
  "geometry": {"coordinates":[-106.78294,32.331359],"type":"Point"}
}