{
  "type": "Feature",
  "properties": {
    "iso:country":"US",
    "sg:address":"16 Rd 5482",
    "sg:city":"Farmington",
    "sg:classifiers":[
        {
            "category":"Building & Trades",
            "subcategory":"Construction",
            "type":"Services"
        }
    ],
    "sg:phone":"+1 505 632 7517",
    "sg:postcode":"87401",
    "sg:province":"NM",
    "sg:tags":[
        "plastering",
        "contractor"
    ],
    "wof:name":"Clayton Enterprises",
    "wof:placetype":"venue"
},
  "geometry": {"coordinates":[-108.091477,36.693046],"type":"Point"}
}