{
  "type": "Feature",
  "properties": {
    "iso:country":"US",
    "sg:address":"600 Fairview Ln",
    "sg:city":"Espanola",
    "sg:classifiers":[
        {
            "category":"Banks & Credit Unions",
            "subcategory":"Investment Brokerage",
            "type":"Services"
        }
    ],
    "sg:phone":"+1 505 753 0343",
    "sg:postcode":"87532",
    "sg:province":"NM",
    "sg:tags":[
        "security"
    ],
    "wof:name":"Northern Hill Inc",
    "wof:placetype":"venue"
},
  "geometry": {"coordinates":[-106.063698,36.008047],"type":"Point"}
}