{
  "type": "Feature",
  "properties": {
    "iso:country":"US",
    "sg:address":"7807 Maple Ct SE",
    "sg:city":"Albuquerque",
    "sg:classifiers":[
        {
            "category":"Professional",
            "subcategory":"Business Services",
            "type":"Services"
        }
    ],
    "sg:phone":"+1 505 254 4707",
    "sg:postcode":"87116",
    "sg:province":"NM",
    "sg:tags":[
        "consulting",
        "health"
    ],
    "wof:name":"Nutrisha Consulting",
    "wof:placetype":"venue"
},
  "geometry": {"coordinates":[-106.560583,35.059949],"type":"Point"}
}