{
  "type": "Feature",
  "properties": {
    "iso:country":"US",
    "sg:address":"416 Yale Blvd SE",
    "sg:city":"Albuquerque",
    "sg:classifiers":[
        {
            "category":"Restaurant",
            "type":"Food & Drink"
        }
    ],
    "sg:phone":"+1 505 255 5519",
    "sg:postcode":"87106",
    "sg:province":"NM",
    "wof:name":"Marta's Camino Real",
    "wof:placetype":"venue"
},
  "geometry": {"coordinates":[-106.62204800000001,35.074934],"type":"Point"}
}