{
  "type": "Feature",
  "properties": {
    "iso:country":"US",
    "sg:address":"415 Roma Ave NW",
    "sg:city":"Albuquerque",
    "sg:classifiers":[
        {
            "category":"Government",
            "subcategory":"Jail",
            "type":"Public Place"
        }
    ],
    "sg:phone":"+1 505 764 3501",
    "sg:postcode":"87102",
    "sg:province":"NM",
    "sg:tags":[
        "detention",
        "facility"
    ],
    "wof:name":"Bernalillo Cnty Detention Ctr",
    "wof:placetype":"venue"
},
  "geometry": {"coordinates":[-106.65181,35.089371],"type":"Point"}
}