{
  "type": "Feature",
  "properties": {
    "iso:country":"US",
    "sg:address":"6102 Central Ave SW",
    "sg:city":"Albuquerque",
    "sg:classifiers":[
        {
            "category":"Professional",
            "type":"Services"
        }
    ],
    "sg:phone":"+1 505 833 0270",
    "sg:postcode":"87105",
    "sg:province":"NM",
    "sg:tags":[
        "establishment"
    ],
    "wof:name":"Amars Orange Camel",
    "wof:placetype":"venue"
},
  "geometry": {"coordinates":[-106.70680900000001,35.08072],"type":"Point"}
}