{
  "type": "Feature",
  "properties": {
    "iso:country":"US",
    "sg:address":"221 Hwy 165",
    "sg:city":"Placitas",
    "sg:classifiers":[
        {
            "category":"Restaurant",
            "type":"Food & Drink"
        }
    ],
    "sg:phone":"+1 505 771 1700",
    "sg:postcode":"87043",
    "sg:province":"NM",
    "sg:tags":[
        "eating"
    ],
    "wof:name":"Pinon Cafe",
    "wof:placetype":"venue"
},
  "geometry": {"coordinates":[-106.49930999999999,35.310776],"type":"Point"}
}