{
  "type": "Feature",
  "properties": {
    "iso:country":"US",
    "sg:address":"3600 Rodeo Ln",
    "sg:city":"Santa Fe",
    "sg:classifiers":[
        {
            "category":"Banks & Credit Unions",
            "subcategory":"Bank",
            "type":"Services"
        }
    ],
    "sg:phone":"+1 505 473 5626",
    "sg:postcode":"87507",
    "sg:province":"NM",
    "sg:tags":[
        "loan",
        "real estate"
    ],
    "wof:name":"Premier Mortgage Solutions",
    "wof:placetype":"venue"
},
  "geometry": {"coordinates":[-106.006066,35.638495],"type":"Point"}
}