{
  "type": "Feature",
  "properties": {
    "addr:full":"15 Jill St Clovis NM 88101",
    "addr:housenumber":"15",
    "addr:postcode":"88101",
    "addr:street":"Jill St",
    "iso:country":"US",
    "sg:address":"15 Jill St",
    "sg:city":"Clovis",
    "sg:classifiers":[
        {
            "category":"Professional",
            "subcategory":"Detective & Security Services",
            "type":"Services"
        }
    ],
    "sg:phone":"+1 505 791 5688",
    "sg:postcode":"88101",
    "sg:province":"NM",
    "wof:name":"Spear Investigations",
    "wof:placetype":"venue"
},
  "geometry": {"coordinates":[-103.314931,34.411459],"type":"Point"}
}