{
  "type": "Feature",
  "properties": {
    "iso:country":"US",
    "sg:address":"5119 Hwy 4",
    "sg:city":"Jemez Pueblo",
    "sg:classifiers":[
        {
            "category":"Government",
            "subcategory":"Office",
            "type":"Public Place"
        }
    ],
    "sg:phone":"+1 505 834 1005",
    "sg:postcode":"87024",
    "sg:province":"NM",
    "wof:name":"Jemez Pueblo Indian Office",
    "wof:placetype":"venue"
},
  "geometry": {"coordinates":[-106.724766,35.611475],"type":"Point"}
}