{
  "type": "Feature",
  "properties": {
    "iso:country":"US",
    "sg:address":"1836 Cerrillos Rd",
    "sg:city":"Santa Fe",
    "sg:classifiers":[
        {
            "category":"Home & Garden",
            "subcategory":"Household Appliances",
            "type":"Retail Goods"
        },
        {
            "category":"Wholesale",
            "subcategory":"Electrical",
            "type":"Manufacturing & Wholesale Goods"
        }
    ],
    "sg:phone":"+1 505 471 0481",
    "sg:postcode":"87505",
    "sg:province":"NM",
    "sg:tags":[
        "parts"
    ],
    "wof:name":"All Appliance Parts & Service",
    "wof:placetype":"venue"
},
  "geometry": {"coordinates":[-105.973777,35.664323],"type":"Point"}
}