{
  "type": "Feature",
  "properties": {
    "iso:country":"US",
    "sg:address":"4231 Grandview Rd",
    "sg:city":"Silver City",
    "sg:classifiers":[
        {
            "category":"Organizations",
            "subcategory":"Religious Organization",
            "type":"Services"
        }
    ],
    "sg:phone":"+1 505 538 2454",
    "sg:postcode":"88061",
    "sg:province":"NM",
    "wof:name":"Shiloh Ministries",
    "wof:placetype":"venue"
},
  "geometry": {"coordinates":[-108.268739,32.811912],"type":"Point"}
}