{
  "type": "Feature",
  "properties": {
    "iso:country":"US",
    "sg:address":"3121 San Mateo Blvd NE",
    "sg:city":"Albuquerque",
    "sg:classifiers":[
        {
            "category":"Shopping",
            "subcategory":"Florist",
            "type":"Retail Goods"
        }
    ],
    "sg:phone":"+1 505 265 8182",
    "sg:postcode":"87110",
    "sg:province":"NM",
    "wof:name":"Casa De Flores Flower Shop",
    "wof:placetype":"venue"
},
  "geometry": {"coordinates":[-106.58649,35.119585],"type":"Point"}
}