{
  "type": "Feature",
  "properties": {
    "iso:country":"US",
    "sg:address":"59 Balsa Rd",
    "sg:city":"Santa Fe",
    "sg:classifiers":[
        {
            "category":"Real Estate",
            "subcategory":"Architect",
            "type":"Services"
        }
    ],
    "sg:phone":"+1 505 466 6940",
    "sg:postcode":"87508",
    "sg:province":"NM",
    "sg:tags":[
        "architectural"
    ],
    "wof:name":"Reidy Thomas & Assoc PC",
    "wof:placetype":"venue"
},
  "geometry": {"coordinates":[-105.953464,35.535386],"type":"Point"}
}