{
  "type": "Feature",
  "properties": {
    "addr:full":"4601 E Main St Farmington NM 87402",
    "addr:housenumber":"4601",
    "addr:postcode":"87402",
    "addr:street":"E Main St",
    "iso:country":"US",
    "sg:address":"4601 E Main St",
    "sg:city":"Farmington",
    "sg:classifiers":[
        {
            "category":"Restaurant",
            "type":"Food & Drink"
        }
    ],
    "sg:menulink":"http://www.allmenus.com/nm/farmington/208513-taco-bell/menu/",
    "sg:phone":"+1 505 327 3350",
    "sg:postcode":"87402",
    "sg:province":"NM",
    "sg:tags":[
        "mexican"
    ],
    "wof:name":"Taco Bell",
    "wof:placetype":"venue"
},
  "geometry": {"coordinates":[-108.152429,36.7648],"type":"Point"}
}