{
  "type": "Feature",
  "properties": {
    "addr:full":"2309 Animas Ct NE Rio Rancho NM 87144",
    "addr:housenumber":"2309",
    "addr:postcode":"87144",
    "addr:street":"Animas Ct Ne",
    "iso:country":"US",
    "sg:address":"2309 Animas Ct NE",
    "sg:city":"Rio Rancho",
    "sg:classifiers":[
        {
            "category":"Insurance",
            "subcategory":"Insurance Agent",
            "type":"Services"
        }
    ],
    "sg:phone":"+1 505 896 0202",
    "sg:postcode":"87144",
    "sg:province":"NM",
    "sg:tags":[
        "building",
        "maintenance"
    ],
    "wof:name":"Action Realty",
    "wof:placetype":"venue"
},
  "geometry": {"coordinates":[-106.589618,35.295338],"type":"Point"}
}