{
  "type": "Feature",
  "properties": {
    "iso:country":"US",
    "sg:address":"100 E 38th St",
    "sg:city":"Farmington",
    "sg:classifiers":[
        {
            "category":"Real Estate",
            "subcategory":"Real Estate Agent",
            "type":"Services"
        }
    ],
    "sg:phone":"+1 505 327 4746",
    "sg:postcode":"87401",
    "sg:province":"NM",
    "sg:tags":[
        "business"
    ],
    "wof:name":"DC Appraisal Services",
    "wof:placetype":"venue"
},
  "geometry": {"coordinates":[-108.202527,36.762314],"type":"Point"}
}