{
  "type": "Feature",
  "properties": {
    "iso:country":"US",
    "sg:address":"2500 N Jefferson St",
    "sg:city":"Hobbs",
    "sg:classifiers":[
        {
            "category":"Organizations",
            "subcategory":"Religious Organization",
            "type":"Services"
        }
    ],
    "sg:phone":"+1 505 392 6016",
    "sg:postcode":"88240",
    "sg:province":"NM",
    "sg:tags":[
        "church"
    ],
    "wof:name":"First Missionary Baptist Chr",
    "wof:placetype":"venue"
},
  "geometry": {"coordinates":[-103.123237,32.729498],"type":"Point"}
}