{
  "type": "Feature",
  "properties": {
    "iso:country":"US",
    "sg:address":"8401 Spain Rd NE",
    "sg:city":"Albuquerque",
    "sg:classifiers":[
        {
            "category":"Banks & Credit Unions",
            "subcategory":"Investment Brokerage",
            "type":"Services"
        },
        {
            "category":"Real Estate",
            "subcategory":"Developer",
            "type":"Services"
        }
    ],
    "sg:phone":"+1 505 828 0551",
    "sg:postcode":"87111",
    "sg:province":"NM",
    "sg:tags":[
        "investing"
    ],
    "wof:name":"Two K Investments",
    "wof:placetype":"venue"
},
  "geometry": {"coordinates":[-106.54843099999999,35.13995],"type":"Point"}
}