{
  "type": "Feature",
  "properties": {
    "iso:country":"US",
    "sg:address":"1620 Adelita Dr NE",
    "sg:city":"Albuquerque",
    "sg:classifiers":[
        {
            "category":"Professional",
            "type":"Services"
        }
    ],
    "sg:phone":"+1 505 553 4418",
    "sg:postcode":"87112",
    "sg:province":"NM",
    "sg:tags":[
        "scientist"
    ],
    "wof:name":"Defiant Technologies Inc",
    "wof:placetype":"venue"
},
  "geometry": {"coordinates":[-106.4832,35.098399],"type":"Point"}
}