{
  "type": "Feature",
  "properties": {
    "iso:country":"US",
    "sg:address":"7027 Montgomery Blvd NE",
    "sg:city":"Albuquerque",
    "sg:classifiers":[
        {
            "category":"Insurance",
            "subcategory":"Insurance Agent",
            "type":"Services"
        }
    ],
    "sg:phone":"+1 505 888 0999",
    "sg:postcode":"87109",
    "sg:province":"NM",
    "wof:name":"Allstate",
    "wof:placetype":"venue"
},
  "geometry": {"coordinates":[-106.567279,35.130825],"type":"Point"}
}