{
  "type": "Feature",
  "properties": {
    "addr:full":"323 S 5th St Clayton NM 88415",
    "addr:housenumber":"323",
    "addr:postcode":"88415",
    "addr:street":"S 5Th St",
    "iso:country":"US",
    "sg:address":"323 S 5th St",
    "sg:city":"Clayton",
    "sg:classifiers":[
        {
            "category":"Education",
            "subcategory":"School",
            "type":"Public Place"
        }
    ],
    "sg:phone":"+1 505 374 9313",
    "sg:postcode":"88415",
    "sg:province":"NM",
    "wof:name":"Alvis Elementary Special Ed",
    "wof:placetype":"venue"
},
  "geometry": {"coordinates":[-103.17812499999999,36.45122],"type":"Point"}
}