{
  "type": "Feature",
  "properties": {
    "iso:country":"US",
    "sg:address":"400 E Spruce St",
    "sg:city":"Deming",
    "sg:classifiers":[
        {
            "category":"Autos & Motor Vehicles",
            "subcategory":"Automobile Sales",
            "type":"Retail Goods"
        }
    ],
    "sg:phone":"+1 505 544 4047",
    "sg:postcode":"88030",
    "sg:province":"NM",
    "sg:tags":[
        "car",
        "used",
        "dealer"
    ],
    "wof:name":"Gordo's Auto Sales",
    "wof:placetype":"venue"
},
  "geometry": {"coordinates":[-107.75349,32.26822],"type":"Point"}
}