{
  "type": "Feature",
  "properties": {
    "addr:full":"101 E Fairground Rd Artesia NM 88210",
    "addr:housenumber":"101",
    "addr:postcode":"88210",
    "addr:street":"E Fairground Rd",
    "iso:country":"US",
    "sg:address":"101 E Fairground Rd",
    "sg:city":"Artesia",
    "sg:classifiers":[
        {
            "category":"Professional",
            "subcategory":"Management & Consulting",
            "type":"Services"
        }
    ],
    "sg:phone":"+1 505 748 6660",
    "sg:postcode":"88210",
    "sg:province":"NM",
    "sg:tags":[
        "consultant",
        "safety"
    ],
    "wof:name":"American Safety Svc Inc",
    "wof:placetype":"venue"
},
  "geometry": {"coordinates":[-104.39553100000001,32.798903],"type":"Point"}
}