{
  "type": "Feature",
  "properties": {
    "iso:country":"US",
    "sg:address":"418 W Broadway Ave",
    "sg:city":"Farmington",
    "sg:classifiers":[
        {
            "category":"Professional",
            "subcategory":"Lawyer & Legal Services",
            "type":"Services"
        }
    ],
    "sg:phone":"+1 505 327 4757",
    "sg:postcode":"87401",
    "sg:province":"NM",
    "sg:tags":[
        "attorney"
    ],
    "wof:name":"Richard G Boren",
    "wof:placetype":"venue"
},
  "geometry": {"coordinates":[-108.210391,36.728126],"type":"Point"}
}