{
  "type": "Feature",
  "properties": {
    "iso:country":"US",
    "sg:address":"307 S Behrend Ave",
    "sg:city":"Farmington",
    "sg:classifiers":[
        {
            "category":"Home & Garden",
            "subcategory":"Building Materials",
            "type":"Retail Goods"
        }
    ],
    "sg:phone":"+1 505 793 2281",
    "sg:postcode":"87401",
    "sg:province":"NM",
    "sg:tags":[
        "glass",
        "window",
        "plate"
    ],
    "wof:name":"Finish Line Auto Glass",
    "wof:placetype":"venue"
},
  "geometry": {"coordinates":[-108.208054,36.727142],"type":"Point"}
}