{
  "type": "Feature",
  "properties": {
    "addr:full":"218 Curry Ave Jal NM 88252",
    "addr:housenumber":"218",
    "addr:postcode":"88252",
    "addr:street":"Curry Ave",
    "iso:country":"US",
    "sg:address":"218 Curry Ave",
    "sg:city":"Jal",
    "sg:classifiers":[
        {
            "category":"Shopping",
            "subcategory":"Florist",
            "type":"Retail Goods"
        }
    ],
    "sg:phone":"+1 505 395 2204",
    "sg:postcode":"88252",
    "sg:province":"NM",
    "wof:name":"R & L Flowers Barber Shop",
    "wof:placetype":"venue"
},
  "geometry": {"coordinates":[-103.19513499999999,32.113166],"type":"Point"}
}