{
  "type": "Feature",
  "properties": {
    "iso:country":"US",
    "sg:address":"2861 Cll Princesa Juana",
    "sg:city":"Santa Fe",
    "sg:classifiers":[
        {
            "category":"Retail",
            "subcategory":"Auto Repair",
            "type":"Services"
        }
    ],
    "sg:phone":"+1 505 471 2967",
    "sg:postcode":"87507",
    "sg:province":"NM",
    "sg:tags":[
        "automotive"
    ],
    "wof:name":"Aawesome Towing Inc",
    "wof:placetype":"venue"
},
  "geometry": {"coordinates":[-105.98465,35.643737],"type":"Point"}
}