{
  "type": "Feature",
  "properties": {
    "iso:country":"US",
    "sg:address":"131 US Hwy 70",
    "sg:city":"Ruidoso",
    "sg:classifiers":[
        {
            "category":"Utilities",
            "subcategory":"Mobile Phone",
            "type":"Services"
        }
    ],
    "sg:phone":"+1 505 378 1986",
    "sg:postcode":"88345",
    "sg:province":"NM",
    "sg:tags":[
        "telephone",
        "cellular"
    ],
    "wof:name":"Ruidoso Wireless",
    "wof:placetype":"venue"
},
  "geometry": {"coordinates":[-105.62483,33.324686],"type":"Point"}
}