{
  "type": "Feature",
  "properties": {
    "iso:country":"US",
    "sg:address":"4205 Hannett Ave NE",
    "sg:city":"Albuquerque",
    "sg:classifiers":[
        {
            "category":"Professional",
            "subcategory":"Research",
            "type":"Services"
        }
    ],
    "sg:phone":"+1 505 254 1168",
    "sg:postcode":"87110",
    "sg:province":"NM",
    "sg:tags":[
        "biologist",
        "consulting"
    ],
    "wof:name":"American Southwest Ichthyologi",
    "wof:placetype":"venue"
},
  "geometry": {"coordinates":[-106.598612,35.098869],"type":"Point"}
}