{
  "type": "Feature",
  "properties": {
    "iso:country":"US",
    "sg:address":"9802 Samar Rd NE",
    "sg:city":"Albuquerque",
    "sg:classifiers":[
        {
            "category":"Manufacturing",
            "subcategory":"Leather Goods",
            "type":"Manufacturing & Wholesale Goods"
        }
    ],
    "sg:phone":"+1 505 823 1165",
    "sg:postcode":"87122",
    "sg:province":"NM",
    "sg:tags":[
        "mfg"
    ],
    "wof:name":"Carmen Azu",
    "wof:placetype":"venue"
},
  "geometry": {"coordinates":[-106.53012099999999,35.163009],"type":"Point"}
}