{
  "type": "Feature",
  "properties": {
    "iso:country":"US",
    "sg:address":"5001 Montgomery Blvd NE",
    "sg:city":"Albuquerque",
    "sg:classifiers":[
        {
            "category":"Wholesale",
            "subcategory":"Apparel",
            "type":"Manufacturing & Wholesale Goods"
        }
    ],
    "sg:phone":"+1 505 856 2693",
    "sg:postcode":"87109",
    "sg:province":"NM",
    "sg:tags":[
        "clothing"
    ],
    "wof:name":"Southwest Baby LLC",
    "wof:placetype":"venue"
},
  "geometry": {"coordinates":[-106.589147,35.131031],"type":"Point"}
}