{
  "type": "Feature",
  "properties": {
    "addr:full":"1502 W Stevens St Carlsbad NM 88220",
    "addr:housenumber":"1502",
    "addr:postcode":"88220",
    "addr:street":"W Stevens St",
    "iso:country":"US",
    "sg:address":"1502 W Stevens St",
    "sg:city":"Carlsbad",
    "sg:classifiers":[
        {
            "category":"Utilities",
            "subcategory":"Water",
            "type":"Services"
        }
    ],
    "sg:phone":"+1 505 887 1191",
    "sg:postcode":"88220",
    "sg:province":"NM",
    "sg:tags":[
        "company",
        "sewage"
    ],
    "wof:name":"City Of Carlsbad Water System",
    "wof:placetype":"venue"
},
  "geometry": {"coordinates":[-104.246155,32.421742],"type":"Point"}
}