{
  "type": "Feature",
  "properties": {
    "iso:country":"US",
    "sg:address":"10701 Montgomery Blvd NE",
    "sg:city":"Albuquerque",
    "sg:classifiers":[
        {
            "category":"Personal",
            "subcategory":"Beauty Salon",
            "type":"Services"
        }
    ],
    "sg:phone":"+1 505 271 0402",
    "sg:postcode":"87111",
    "sg:province":"NM",
    "sg:tags":[
        "shop"
    ],
    "wof:name":"Blondie's Salon",
    "wof:placetype":"venue"
},
  "geometry": {"coordinates":[-106.521241,35.130761],"type":"Point"}
}