{
  "type": "Feature",
  "properties": {
    "addr:full":"19381 State Hwy 314 Belen NM 87002",
    "addr:housenumber":"19381",
    "addr:postcode":"87002",
    "addr:street":"State Hwy 314",
    "iso:country":"US",
    "sg:address":"19381 State Hwy 314",
    "sg:city":"Belen",
    "sg:classifiers":[
        {
            "category":"Organizations",
            "subcategory":"Religious Organization",
            "type":"Services"
        }
    ],
    "sg:phone":"+1 505 864 6611",
    "sg:postcode":"87002",
    "sg:province":"NM",
    "sg:tags":[
        "church"
    ],
    "wof:name":"Calvary Chapel Rio Grande Vly",
    "wof:placetype":"venue"
},
  "geometry": {"coordinates":[-106.76785599999999,34.686878],"type":"Point"}
}