{
  "type": "Feature",
  "properties": {
    "addr:full":"913 Vuelta del Sur Santa Fe NM 87507",
    "addr:housenumber":"913",
    "addr:postcode":"87507",
    "addr:street":"Vuelta Del",
    "iso:country":"US",
    "sg:address":"913 Vuelta del Sur",
    "sg:city":"Santa Fe",
    "sg:classifiers":[
        {
            "category":"Building & Trades",
            "subcategory":"Landscaping Services",
            "type":"Services"
        }
    ],
    "sg:phone":"+1 505 474 8330",
    "sg:postcode":"87507",
    "sg:province":"NM",
    "sg:tags":[
        "landscape"
    ],
    "wof:name":"Pecos Landscaping",
    "wof:placetype":"venue"
},
  "geometry": {"coordinates":[-106.026961,35.652955],"type":"Point"}
}