{
  "type": "Feature",
  "properties": {
    "addr:full":"1309 S Bloomfield Blvd Bloomfield NM 87413",
    "addr:housenumber":"1309",
    "addr:postcode":"87413",
    "addr:street":"S Bloomfield Blvd",
    "iso:country":"US",
    "sg:address":"1309 S Bloomfield Blvd",
    "sg:city":"Bloomfield",
    "sg:classifiers":[
        {
            "category":"Retail",
            "subcategory":"Auto Repair",
            "type":"Services"
        }
    ],
    "sg:phone":"+1 505 632 3168",
    "sg:postcode":"87413",
    "sg:province":"NM",
    "sg:tags":[
        "truck"
    ],
    "wof:name":"Mc Coy Equipment & Fabrication",
    "wof:placetype":"venue"
},
  "geometry": {"coordinates":[-107.9877,36.694319],"type":"Point"}
}