{
  "type": "Feature",
  "properties": {
    "addr:full":"929 US Hwy 66 Santa Rosa NM 88435",
    "addr:housenumber":"929",
    "addr:postcode":"88435",
    "addr:street":"Us Hwy 66",
    "iso:country":"US",
    "sg:address":"929 US Hwy 66",
    "sg:city":"Santa Rosa",
    "sg:classifiers":[
        {
            "category":"Travel",
            "subcategory":"Hotels & Motels",
            "type":"Entertainment"
        }
    ],
    "sg:phone":"+1 505 472 3762",
    "sg:postcode":"88435",
    "sg:province":"NM",
    "wof:name":"Sunset Motel",
    "wof:placetype":"venue"
},
  "geometry": {"coordinates":[-104.679979,34.944335],"type":"Point"}
}