{
  "type": "Feature",
  "properties": {
    "iso:country":"US",
    "sg:address":"730 Saint Michaels Dr",
    "sg:city":"Santa Fe",
    "sg:classifiers":[
        {
            "category":"Personal",
            "subcategory":"Beauty Salon",
            "type":"Services"
        }
    ],
    "sg:phone":"+1 505 471 6349",
    "sg:postcode":"87505",
    "sg:province":"NM",
    "wof:name":"Virginia's Hair Gallery",
    "wof:placetype":"venue"
},
  "geometry": {"coordinates":[-105.960989,35.659373],"type":"Point"}
}