{
  "type": "Feature",
  "properties": {
    "addr:full":"445 S 2nd St Raton NM 87740",
    "addr:housenumber":"445",
    "addr:postcode":"87740",
    "addr:street":"S 2Nd St",
    "iso:country":"US",
    "sg:address":"445 S 2nd St",
    "sg:city":"Raton",
    "sg:classifiers":[
        {
            "category":"Shopping",
            "subcategory":"Computers & Home Electronics",
            "type":"Retail Goods"
        }
    ],
    "sg:phone":"+1 505 445 2544",
    "sg:postcode":"87740",
    "sg:province":"NM",
    "sg:tags":[
        "equipment",
        "satellite",
        "system"
    ],
    "wof:name":"G K Communications",
    "wof:placetype":"venue"
},
  "geometry": {"coordinates":[-104.440206,36.898386],"type":"Point"}
}