{
  "type": "Feature",
  "properties": {
    "iso:country":"US",
    "sg:address":"2201 Will Rogers Dr",
    "sg:city":"Santa Rosa",
    "sg:classifiers":[
        {
            "category":"Building & Trades",
            "subcategory":"Construction",
            "type":"Services"
        }
    ],
    "sg:phone":"+1 505 472 3106",
    "sg:postcode":"88435",
    "sg:province":"NM",
    "sg:tags":[
        "general",
        "contractor"
    ],
    "wof:name":"Jim Sena Construction Co Inc",
    "wof:placetype":"venue"
},
  "geometry": {"coordinates":[-104.6647,34.945209],"type":"Point"}
}