{
  "type": "Feature",
  "properties": {
    "iso:country":"US",
    "sg:address":"3600 State Hwy 528",
    "sg:city":"Albuquerque",
    "sg:classifiers":[
        {
            "category":"Restaurant",
            "type":"Food & Drink"
        }
    ],
    "sg:phone":"+1 505 899 6900",
    "sg:postcode":"87114",
    "sg:province":"NM",
    "wof:name":"Bombay Grill",
    "wof:placetype":"venue"
},
  "geometry": {"coordinates":[-106.652055,35.207989],"type":"Point"}
}