{
  "type": "Feature",
  "properties": {
    "addr:full":"1901 C\ufffd\ufffdr del Monte NE Albuquerque NM 87112",
    "addr:housenumber":"1901",
    "addr:postcode":"87112",
    "addr:street":"C\ufffd\ufffdR Del;Ne",
    "iso:country":"US",
    "sg:address":"1901 C\ufffd\ufffdr del Monte NE",
    "sg:city":"Albuquerque",
    "sg:classifiers":[
        {
            "category":"Real Estate",
            "subcategory":"Real Estate Agent",
            "type":"Services"
        }
    ],
    "sg:phone":"+1 505 296 8543",
    "sg:postcode":"87112",
    "sg:province":"NM",
    "wof:name":"Joyce Giles Real Estate",
    "wof:placetype":"venue"
},
  "geometry": {"coordinates":[-106.491433,35.103272],"type":"Point"}
}