{
  "type": "Feature",
  "properties": {
    "iso:country":"US",
    "sg:address":"1212 N 1st St",
    "sg:city":"Artesia",
    "sg:classifiers":[
        {
            "category":"Retail",
            "subcategory":"Repair Shop",
            "type":"Services"
        }
    ],
    "sg:phone":"+1 505 748 2752",
    "sg:postcode":"88210",
    "sg:province":"NM",
    "wof:name":"AB Enterprises Inc",
    "wof:placetype":"venue"
},
  "geometry": {"coordinates":[-104.398371,32.853932],"type":"Point"}
}