{
  "type": "Feature",
  "properties": {
    "iso:country":"US",
    "sg:address":"3500 Comanche Rd NE",
    "sg:city":"Albuquerque",
    "sg:classifiers":[
        {
            "category":"Professional",
            "subcategory":"Lawyer & Legal Services",
            "type":"Services"
        }
    ],
    "sg:phone":"+1 505 881 9060",
    "sg:postcode":"87107",
    "sg:province":"NM",
    "sg:tags":[
        "attorney"
    ],
    "wof:name":"Budagher & Assoc",
    "wof:placetype":"venue"
},
  "geometry": {"coordinates":[-106.605183,35.12368],"type":"Point"}
}