{
  "type": "Feature",
  "properties": {
    "iso:country":"US",
    "sg:address":"1048 Pso de Peralta",
    "sg:city":"Santa Fe",
    "sg:classifiers":[
        {
            "category":"Wholesale",
            "subcategory":"Non-durable Goods",
            "type":"Manufacturing & Wholesale Goods"
        }
    ],
    "sg:phone":"+1 505 992 0441",
    "sg:postcode":"87501",
    "sg:province":"NM",
    "wof:name":"Shush Yaz Trading Co",
    "wof:placetype":"venue"
},
  "geometry": {"coordinates":[-105.934392,35.681963],"type":"Point"}
}