{
  "type": "Feature",
  "properties": {
    "iso:country":"US",
    "sg:address":"800 Municipal Dr",
    "sg:city":"Farmington",
    "sg:classifiers":[
        {
            "category":"Government",
            "subcategory":"Office",
            "type":"Public Place"
        }
    ],
    "sg:phone":"+1 505 599 1132",
    "sg:postcode":"87401",
    "sg:province":"NM",
    "sg:tags":[
        "village"
    ],
    "wof:name":"Farmington Personnel Dept",
    "wof:placetype":"venue"
},
  "geometry": {"coordinates":[-108.218712,36.736947],"type":"Point"}
}