{
  "type": "Feature",
  "properties": {
    "addr:full":"1235 S 2nd St Raton NM 87740",
    "addr:housenumber":"1235",
    "addr:postcode":"87740",
    "addr:street":"S 2Nd St",
    "iso:country":"US",
    "sg:address":"1235 S 2nd St",
    "sg:city":"Raton",
    "sg:classifiers":[
        {
            "category":"Shopping",
            "subcategory":"Department Store",
            "type":"Retail Goods"
        }
    ],
    "sg:phone":"+1 505 454 5588",
    "sg:postcode":"87740",
    "sg:province":"NM",
    "sg:website":"www.kmart.com",
    "wof:name":"Kmart",
    "wof:placetype":"venue"
},
  "geometry": {"coordinates":[-104.43987799999999,36.882671],"type":"Point"}
}