{
  "type": "Feature",
  "properties": {
    "iso:country":"US",
    "sg:address":"4141 Pinnacle St",
    "sg:city":"El Paso",
    "sg:classifiers":[
        {
            "category":"Professional",
            "subcategory":"Lawyer & Legal Services",
            "type":"Services"
        }
    ],
    "sg:phone":"+1 915 541 1221",
    "sg:postcode":"79902",
    "sg:province":"TX",
    "sg:tags":[
        "firm",
        "specializing",
        "law",
        "plan",
        "retirement"
    ],
    "wof:name":"Zaboroski & Zaboroski",
    "wof:placetype":"venue"
},
  "geometry": {"coordinates":[-106.51443999999999,31.794468],"type":"Point"}
}