{
  "type": "Feature",
  "properties": {
    "addr:full":"1120 E 2nd St Roswell NM 88201",
    "addr:housenumber":"1120",
    "addr:postcode":"88201",
    "addr:street":"E 2Nd St",
    "iso:country":"US",
    "sg:address":"1120 E 2nd St",
    "sg:city":"Roswell",
    "sg:classifiers":[
        {
            "category":"Restaurant",
            "type":"Food & Drink"
        }
    ],
    "sg:phone":"+1 505 622 6363",
    "sg:postcode":"88201",
    "sg:province":"NM",
    "wof:name":"Cowboy Cafe",
    "wof:placetype":"venue"
},
  "geometry": {"coordinates":[-104.508368,33.394098],"type":"Point"}
}