{
  "type": "Feature",
  "properties": {
    "addr:full":"156 Juan Tabo Blvd NE Albuquerque NM 87123",
    "addr:housenumber":"156",
    "addr:postcode":"87123",
    "addr:street":"Juan Tabo Blvd Ne",
    "iso:country":"US",
    "sg:address":"156 Juan Tabo Blvd NE",
    "sg:city":"Albuquerque",
    "sg:classifiers":[
        {
            "category":"Wholesale",
            "subcategory":"Scrap",
            "type":"Manufacturing & Wholesale Goods"
        }
    ],
    "sg:phone":"+1 505 345 2404",
    "sg:postcode":"87123",
    "sg:province":"NM",
    "sg:tags":[
        "recycling",
        "center"
    ],
    "wof:name":"Wise Recycling LLC",
    "wof:placetype":"venue"
},
  "geometry": {"coordinates":[-106.5151,35.070538],"type":"Point"}
}