{
  "type": "Feature",
  "properties": {
    "iso:country":"US",
    "sg:address":"2442 Cerrillos Rd",
    "sg:city":"Santa Fe",
    "sg:classifiers":[
        {
            "category":"Manufacturing",
            "subcategory":"Lumber",
            "type":"Manufacturing & Wholesale Goods"
        }
    ],
    "sg:phone":"+1 505 699 6789",
    "sg:postcode":"87505",
    "sg:province":"NM",
    "sg:tags":[
        "forestry"
    ],
    "wof:name":"Brothers Industries Inc",
    "wof:placetype":"venue"
},
  "geometry": {"coordinates":[-105.982187,35.660021],"type":"Point"}
}