{
  "type": "Feature",
  "properties": {
    "iso:country":"US",
    "sg:address":"6431 US Hwy 550",
    "sg:city":"Cuba",
    "sg:classifiers":[
        {
            "category":"Home & Garden",
            "subcategory":"Hardware",
            "type":"Retail Goods"
        }
    ],
    "sg:phone":"+1 505 289 3705",
    "sg:postcode":"87037",
    "sg:province":"NM",
    "wof:name":"Richard's True Value",
    "wof:placetype":"venue"
},
  "geometry": {"coordinates":[-107.74118,36.266084],"type":"Point"}
}