{
  "type": "Feature",
  "properties": {
    "iso:country":"US",
    "sg:address":"2300 Buena Vista Dr SE",
    "sg:city":"Albuquerque",
    "sg:classifiers":[
        {
            "category":"Restaurant",
            "type":"Food & Drink"
        }
    ],
    "sg:phone":"+1 505 247 9359",
    "sg:postcode":"87106",
    "sg:province":"NM",
    "wof:name":"Sandwich Co",
    "wof:placetype":"venue"
},
  "geometry": {"coordinates":[-106.624349,35.053706],"type":"Point"}
}