{
  "type": "Feature",
  "properties": {
    "iso:country":"US",
    "sg:address":"1033 Agua Fria St",
    "sg:city":"Santa Fe",
    "sg:classifiers":[
        {
            "category":"Personal",
            "type":"Services"
        }
    ],
    "sg:phone":"+1 505 983 6884",
    "sg:postcode":"87501",
    "sg:province":"NM",
    "sg:tags":[
        "electrolysis"
    ],
    "wof:name":"Donna L Baerwald's Skin Care",
    "wof:placetype":"venue"
},
  "geometry": {"coordinates":[-105.957585,35.683434],"type":"Point"}
}