{
  "type": "Feature",
  "properties": {
    "iso:country":"US",
    "sg:address":"311 Delaware Ave",
    "sg:city":"Alamogordo",
    "sg:classifiers":[
        {
            "category":"Organizations",
            "subcategory":"Community Association",
            "type":"Services"
        }
    ],
    "sg:phone":"+1 505 434 3772",
    "sg:postcode":"88310",
    "sg:province":"NM",
    "wof:name":"Prince Hall Masonic Temple",
    "wof:placetype":"venue"
},
  "geometry": {"coordinates":[-105.95805,32.893773],"type":"Point"}
}