{
  "type": "Feature",
  "properties": {
    "iso:country":"US",
    "sg:address":"221 Hwy 165",
    "sg:city":"Placitas",
    "sg:classifiers":[
        {
            "category":"Retail",
            "subcategory":"Laundry & Dry Cleaning",
            "type":"Services"
        }
    ],
    "sg:phone":"+1 505 867 9950",
    "sg:postcode":"87043",
    "sg:province":"NM",
    "sg:tags":[
        "cleaners"
    ],
    "wof:name":"Buttons & Bows Drycleaners",
    "wof:placetype":"venue"
},
  "geometry": {"coordinates":[-106.49930999999999,35.310776],"type":"Point"}
}