{
  "type": "Feature",
  "properties": {
    "iso:country":"US",
    "sg:address":"122 Bryn Mawr Dr SE",
    "sg:city":"Albuquerque",
    "sg:classifiers":[
        {
            "category":"Personal",
            "type":"Services"
        }
    ],
    "sg:phone":"+1 505 920 8730",
    "sg:postcode":"87106",
    "sg:province":"NM",
    "sg:tags":[
        "therapist",
        "massage"
    ],
    "wof:name":"Lydie K Spezza Massage Therpst",
    "wof:placetype":"venue"
},
  "geometry": {"coordinates":[-106.609438,35.079386],"type":"Point"}
}