{
  "type": "Feature",
  "properties": {
    "addr:full":"7201 Luella Anne Dr NE Albuquerque NM 87109",
    "addr:housenumber":"7201",
    "addr:postcode":"87109",
    "addr:street":"Luella Anne Dr Ne",
    "iso:country":"US",
    "sg:address":"7201 Luella Anne Dr NE",
    "sg:city":"Albuquerque",
    "sg:classifiers":[
        {
            "category":"Health Services",
            "subcategory":"Health Practitioner",
            "type":"Services"
        }
    ],
    "sg:phone":"+1 505 828 9531",
    "sg:postcode":"87109",
    "sg:province":"NM",
    "sg:tags":[
        "pathologist",
        "speech-language"
    ],
    "wof:name":"Gina Fresquezripley",
    "wof:placetype":"venue"
},
  "geometry": {"coordinates":[-106.565201,35.15625],"type":"Point"}
}