{
  "type": "Feature",
  "properties": {
    "iso:country":"US",
    "sg:address":"9104 James Ave NE",
    "sg:city":"Albuquerque",
    "sg:classifiers":[
        {
            "category":"Professional",
            "type":"Services"
        }
    ],
    "sg:phone":"+1 505 237 2336",
    "sg:postcode":"87111",
    "sg:province":"NM",
    "wof:name":"Glensen Art",
    "wof:placetype":"venue"
},
  "geometry": {"coordinates":[-106.54044,35.126585],"type":"Point"}
}