{
  "type": "Feature",
  "properties": {
    "addr:full":"1305 W Historic Highway 66 Gallup NM 87301",
    "addr:housenumber":"1305",
    "addr:postcode":"87301",
    "addr:street":"W Historic Highway 66",
    "iso:country":"US",
    "sg:address":"1305 W Historic Highway 66",
    "sg:city":"Gallup",
    "sg:classifiers":[
        {
            "category":"Travel",
            "subcategory":"Bed & Breakfast",
            "type":"Entertainment"
        }
    ],
    "sg:phone":"+1 505 863 3012",
    "sg:postcode":"87301",
    "sg:province":"NM",
    "sg:tags":[
        "inn"
    ],
    "wof:name":"Gardnia Inn",
    "wof:placetype":"venue"
},
  "geometry": {"coordinates":[-108.840034,35.504042],"type":"Point"}
}