{
  "type": "Feature",
  "properties": {
    "addr:full":"7520 Montgomery Blvd NE Bldg E4 Albuquerque NM 87109",
    "addr:housenumber":"7520",
    "addr:postcode":"87109",
    "addr:street":"Montgomery Blvd Ne Bldg E4",
    "iso:country":"US",
    "sg:address":"7520 Montgomery Blvd NE Bldg E4",
    "sg:city":"Albuquerque",
    "sg:classifiers":[
        {
            "category":"Health Services",
            "subcategory":"Doctor",
            "type":"Services"
        },
        {
            "category":"Health Services",
            "subcategory":"Dentist",
            "type":"Services"
        }
    ],
    "sg:phone":"+1 505 883 6111",
    "sg:postcode":"87109",
    "sg:province":"NM",
    "sg:tags":[
        "physician",
        "product",
        "surgeons",
        "whitening",
        "teeth",
        "surgery",
        "oral"
    ],
    "wof:name":"Rick Davison, DDS",
    "wof:placetype":"venue"
},
  "geometry": {"coordinates":[-106.561414,35.130676],"type":"Point"}
}