{
  "type": "Feature",
  "properties": {
    "iso:country":"US",
    "sg:address":"1590 Saint Michaels Dr",
    "sg:city":"Santa Fe",
    "sg:classifiers":[
        {
            "category":"Personal",
            "subcategory":"Beauty Salon",
            "type":"Services"
        }
    ],
    "sg:phone":"+1 505 471 4814",
    "sg:postcode":"87505",
    "sg:province":"NM",
    "wof:name":"Cuttery",
    "wof:placetype":"venue"
},
  "geometry": {"coordinates":[-105.975904,35.660588],"type":"Point"}
}