{
  "type": "Feature",
  "properties": {
    "addr:full":"4012 4th St NW Albuquerque NM 87107",
    "addr:housenumber":"4012",
    "addr:postcode":"87107",
    "addr:street":"4Th St Nw",
    "iso:country":"US",
    "sg:address":"4012 4th St NW",
    "sg:city":"Albuquerque",
    "sg:classifiers":[
        {
            "category":"Local Transit",
            "type":"Transportation"
        }
    ],
    "sg:phone":"+1 505 761 8200",
    "sg:postcode":"87107",
    "sg:province":"NM",
    "sg:tags":[
        "ambulance"
    ],
    "wof:name":"Albuquerque Ambulance",
    "wof:placetype":"venue"
},
  "geometry": {"coordinates":[-106.643778,35.124981],"type":"Point"}
}