{
  "type": "Feature",
  "properties": {
    "iso:country":"US",
    "sg:address":"6580 Hwy 518",
    "sg:city":"Ranchos De Taos",
    "sg:classifiers":[
        {
            "category":"Education",
            "subcategory":"College",
            "type":"Public Place"
        }
    ],
    "sg:phone":"+1 505 758 7180",
    "sg:postcode":"87557",
    "sg:province":"NM",
    "sg:tags":[
        "academic",
        "school"
    ],
    "wof:name":"Fort BURGWIN-Smu-In Taos",
    "wof:placetype":"venue"
},
  "geometry": {"coordinates":[-105.57631600000001,36.274872],"type":"Point"}
}