{
  "type": "Feature",
  "properties": {
    "iso:country":"US",
    "sg:address":"710 N Elm St",
    "sg:city":"Truth Or Cnsqncs",
    "sg:classifiers":[
        {
            "category":"Recreation",
            "type":"Entertainment"
        }
    ],
    "sg:phone":"+1 505 894 7222",
    "sg:postcode":"87901",
    "sg:province":"NM",
    "sg:tags":[
        "center"
    ],
    "wof:name":"Community Playhouse",
    "wof:placetype":"venue"
},
  "geometry": {"coordinates":[-107.243621,33.137989],"type":"Point"}
}