{
  "type": "Feature",
  "properties": {
    "addr:full":"2012 7th St NW Albuquerque NM 87102",
    "addr:housenumber":"2012",
    "addr:postcode":"87102",
    "addr:street":"7Th St Nw",
    "iso:country":"US",
    "sg:address":"2012 7th St NW",
    "sg:city":"Albuquerque",
    "sg:classifiers":[
        {
            "category":"Autos & Motor Vehicles",
            "subcategory":"Fuel & Gas Station",
            "type":"Retail Goods"
        }
    ],
    "sg:phone":"+1 505 243 6789",
    "sg:postcode":"87102",
    "sg:province":"NM",
    "sg:tags":[
        "oil"
    ],
    "wof:name":"Rio Grande Oil Co",
    "wof:placetype":"venue"
},
  "geometry": {"coordinates":[-106.65235,35.106525],"type":"Point"}
}