{
  "type": "Feature",
  "properties": {
    "iso:country":"US",
    "sg:address":"8701 Golf Course Rd NW",
    "sg:city":"Albuquerque",
    "sg:classifiers":[
        {
            "category":"Organizations",
            "subcategory":"Religious Organization",
            "type":"Services"
        }
    ],
    "sg:phone":"+1 505 898 8205",
    "sg:postcode":"87114",
    "sg:province":"NM",
    "sg:tags":[
        "church"
    ],
    "sg:website":"www.riovistachurch.org",
    "wof:name":"Rio Vista Church of Nazarene",
    "wof:placetype":"venue"
},
  "geometry": {"coordinates":[-106.687771,35.180847],"type":"Point"}
}