{
  "type": "Feature",
  "properties": {
    "iso:country":"US",
    "sg:address":"85 Moya Rd",
    "sg:city":"Santa Fe",
    "sg:classifiers":[
        {
            "category":"Social Services",
            "subcategory":"Child Care",
            "type":"Services"
        }
    ],
    "sg:phone":"+1 505 466 4610",
    "sg:postcode":"87508",
    "sg:province":"NM",
    "wof:name":"Wee Wonders Learning Ctr",
    "wof:placetype":"venue"
},
  "geometry": {"coordinates":[-105.911932,35.54391],"type":"Point"}
}