{
  "type": "Feature",
  "properties": {
    "iso:country":"US",
    "sg:address":"11001 Lexington Ave NE",
    "sg:city":"Albuquerque",
    "sg:classifiers":[
        {
            "category":"Building & Trades",
            "subcategory":"Construction",
            "type":"Services"
        }
    ],
    "sg:phone":"+1 505 296 7221",
    "sg:postcode":"87112",
    "sg:province":"NM",
    "sg:tags":[
        "house"
    ],
    "wof:name":"Can-Do",
    "wof:placetype":"venue"
},
  "geometry": {"coordinates":[-106.518493,35.114155],"type":"Point"}
}