{
  "type": "Feature",
  "properties": {
    "iso:country":"US",
    "sg:address":"2359 Moreland St",
    "sg:city":"Las Vegas",
    "sg:classifiers":[
        {
            "category":"Real Estate",
            "subcategory":"Real Estate Operator",
            "type":"Services"
        }
    ],
    "sg:phone":"+1 505 425 6585",
    "sg:postcode":"87701",
    "sg:province":"NM",
    "sg:tags":[
        "building",
        "apartment"
    ],
    "wof:name":"Kristin Park Apartments",
    "wof:placetype":"venue"
},
  "geometry": {"coordinates":[-105.220923,35.618029],"type":"Point"}
}