{
  "type": "Feature",
  "properties": {
    "addr:full":"401 W 4th St Portales NM 88130",
    "addr:housenumber":"401",
    "addr:postcode":"88130",
    "addr:street":"W 4Th St",
    "iso:country":"US",
    "sg:address":"401 W 4th St",
    "sg:city":"Portales",
    "sg:classifiers":[
        {
            "category":"Professional",
            "subcategory":"Lawyer & Legal Services",
            "type":"Services"
        }
    ],
    "sg:phone":"+1 505 356 5000",
    "sg:postcode":"88130",
    "sg:province":"NM",
    "wof:name":"Griffin Law Offc-Nttie Griffin",
    "wof:placetype":"venue"
},
  "geometry": {"coordinates":[-103.33759000000001,34.182444],"type":"Point"}
}