{
  "type": "Feature",
  "properties": {
    "iso:country":"US",
    "sg:address":"117 S Canyon St",
    "sg:city":"Carlsbad",
    "sg:classifiers":[
        {
            "category":"Shopping",
            "subcategory":"Clothing, Apparel, & Fashions",
            "type":"Retail Goods"
        }
    ],
    "sg:phone":"+1 505 887 5697",
    "sg:postcode":"88220",
    "sg:province":"NM",
    "sg:tags":[
        "accessory",
        "wear",
        "shoes"
    ],
    "wof:name":"Choices Fashions",
    "wof:placetype":"venue"
},
  "geometry": {"coordinates":[-104.227761,32.420124],"type":"Point"}
}