{
  "type": "Feature",
  "properties": {
    "iso:country":"US",
    "sg:address":"1216 N Pso de Onate",
    "sg:city":"Espanola",
    "sg:classifiers":[
        {
            "category":"Banks & Credit Unions",
            "subcategory":"Bank",
            "type":"Services"
        }
    ],
    "sg:phone":"+1 505 753 5228",
    "sg:postcode":"87532",
    "sg:province":"NM",
    "wof:name":"Del Norte Credit Union",
    "wof:placetype":"venue"
},
  "geometry": {"coordinates":[-106.088155,36.009444],"type":"Point"}
}