{
  "type": "Feature",
  "properties": {
    "iso:country":"US",
    "sg:address":"2626 San Pedro Dr NE",
    "sg:city":"Albuquerque",
    "sg:classifiers":[
        {
            "category":"Personal",
            "subcategory":"Beauty Salon",
            "type":"Services"
        }
    ],
    "sg:phone":"+1 505 872 4247",
    "sg:postcode":"87110",
    "sg:province":"NM",
    "sg:website":"www.greatclips.com",
    "wof:name":"Great Clips",
    "wof:placetype":"venue"
},
  "geometry": {"coordinates":[-106.577461,35.110434],"type":"Point"}
}