{
  "type": "Feature",
  "properties": {
    "addr:full":"5010 Olsen Pl NW Albuquerque NM 87114",
    "addr:housenumber":"5010",
    "addr:postcode":"87114",
    "addr:street":"Olsen Pl Nw",
    "iso:country":"US",
    "sg:address":"5010 Olsen Pl NW",
    "sg:city":"Albuquerque",
    "sg:classifiers":[
        {
            "category":"Real Estate",
            "subcategory":"Real Estate Agent",
            "type":"Services"
        }
    ],
    "sg:phone":"+1 505 898 7572",
    "sg:postcode":"87114",
    "sg:province":"NM",
    "wof:name":"Clara Lee Realty",
    "wof:placetype":"venue"
},
  "geometry": {"coordinates":[-106.688748,35.196673],"type":"Point"}
}