{
  "type": "Feature",
  "properties": {
    "addr:full":"329 N Bergin Ln Bloomfield NM 87413",
    "addr:housenumber":"329",
    "addr:postcode":"87413",
    "addr:street":"N Bergin Ln",
    "iso:country":"US",
    "sg:address":"329 N Bergin Ln",
    "sg:city":"Bloomfield",
    "sg:classifiers":[
        {
            "category":"Education",
            "subcategory":"School",
            "type":"Public Place"
        }
    ],
    "sg:phone":"+1 505 632 8021",
    "sg:postcode":"87413",
    "sg:province":"NM",
    "wof:name":"Mesa Alta Jr High School",
    "wof:placetype":"venue"
},
  "geometry": {"coordinates":[-108.00159600000001,36.714648],"type":"Point"}
}