{
  "type": "Feature",
  "properties": {
    "addr:full":"9906 Indian School Rd NE Albuquerque NM 87112",
    "addr:housenumber":"9906",
    "addr:postcode":"87112",
    "addr:street":"Indian School Rd Ne",
    "iso:country":"US",
    "sg:address":"9906 Indian School Rd NE",
    "sg:city":"Albuquerque",
    "sg:classifiers":[
        {
            "category":"Home & Garden",
            "subcategory":"Building Materials",
            "type":"Retail Goods"
        }
    ],
    "sg:phone":"+1 505 294 2500",
    "sg:postcode":"87112",
    "sg:province":"NM",
    "sg:tags":[
        "glass",
        "window",
        "plate"
    ],
    "wof:name":"Glass Emporium",
    "wof:placetype":"venue"
},
  "geometry": {"coordinates":[-106.533027,35.101641],"type":"Point"}
}