{
  "type": "Feature",
  "properties": {
    "iso:country":"US",
    "sg:address":"3020 N Main St",
    "sg:city":"Roswell",
    "sg:classifiers":[
        {
            "category":"Autos & Motor Vehicles",
            "subcategory":"Fuel & Gas Station",
            "type":"Retail Goods"
        }
    ],
    "sg:phone":"+1 505 623 3173",
    "sg:postcode":"88201",
    "sg:province":"NM",
    "sg:tags":[
        "oil"
    ],
    "wof:name":"Bell Gas Co",
    "wof:placetype":"venue"
},
  "geometry": {"coordinates":[-104.523117,33.435574],"type":"Point"}
}