{
  "type": "Feature",
  "properties": {
    "iso:country":"US",
    "sg:address":"24 Bouquet Ln",
    "sg:city":"Santa Fe",
    "sg:classifiers":[
        {
            "category":"Travel",
            "subcategory":"Travel Agent",
            "type":"Entertainment"
        }
    ],
    "sg:phone":"+1 505 455 9200",
    "sg:postcode":"87506",
    "sg:province":"NM",
    "sg:tags":[
        "agency",
        "bureau"
    ],
    "wof:name":"Travel Group",
    "wof:placetype":"venue"
},
  "geometry": {"coordinates":[-106.01829600000001,35.902483],"type":"Point"}
}