{
  "type": "Feature",
  "properties": {
    "addr:full":"5603 S Main St Mesilla Park NM 88047",
    "addr:housenumber":"5603",
    "addr:postcode":"88047",
    "addr:street":"S Main St;Park",
    "iso:country":"US",
    "sg:address":"5603 S Main St",
    "sg:city":"Mesilla Park",
    "sg:classifiers":[
        {
            "category":"Manufacturing",
            "subcategory":"Glass & Minerals",
            "type":"Manufacturing & Wholesale Goods"
        }
    ],
    "sg:phone":"+1 505 523 2777",
    "sg:postcode":"88047",
    "sg:province":"NM",
    "sg:tags":[
        "tile"
    ],
    "wof:name":"Casa Mexicana Tile",
    "wof:placetype":"venue"
},
  "geometry": {"coordinates":[-106.742239,32.236849],"type":"Point"}
}