{
  "type": "Feature",
  "properties": {
    "iso:country":"US",
    "sg:address":"2 Chamisa Cove",
    "sg:city":"Los Lunas",
    "sg:classifiers":[
        {
            "category":"Professional",
            "subcategory":"Computer Services",
            "type":"Services"
        }
    ],
    "sg:phone":"+1 505 869 9064",
    "sg:postcode":"87031",
    "sg:province":"NM",
    "sg:tags":[
        "datum"
    ],
    "wof:name":"Data Techniques",
    "wof:placetype":"venue"
},
  "geometry": {"coordinates":[-106.66935700000001,34.728952],"type":"Point"}
}