{
  "type": "Feature",
  "properties": {
    "iso:country":"US",
    "sg:address":"1600 Sudderth Dr",
    "sg:city":"Ruidoso",
    "sg:classifiers":[
        {
            "category":"Shopping",
            "subcategory":"Used Merchandise",
            "type":"Retail Goods"
        }
    ],
    "sg:phone":"+1 505 257 7609",
    "sg:postcode":"88345",
    "sg:province":"NM",
    "sg:tags":[
        "antique"
    ],
    "wof:name":"Keepsakes",
    "wof:placetype":"venue"
},
  "geometry": {"coordinates":[-105.661913,33.327988],"type":"Point"}
}