{
  "type": "Feature",
  "properties": {
    "addr:full":"4410 Central Ave SW Albuquerque NM 87105",
    "addr:housenumber":"4410",
    "addr:postcode":"87105",
    "addr:street":"Central Ave Sw",
    "iso:country":"US",
    "sg:address":"4410 Central Ave SW",
    "sg:city":"Albuquerque",
    "sg:classifiers":[
        {
            "category":"Banks & Credit Unions",
            "subcategory":"Financial Services",
            "type":"Services"
        }
    ],
    "sg:phone":"+1 505 352 5555",
    "sg:postcode":"87105",
    "sg:province":"NM",
    "sg:tags":[
        "cashing",
        "loan",
        "payday",
        "alternative",
        "check"
    ],
    "sg:website":"http://www.acecashexpress.com",
    "wof:name":"ACE Cash Express",
    "wof:placetype":"venue"
},
  "geometry": {"coordinates":[-106.687354,35.08508],"type":"Point"}
}