{
  "type": "Feature",
  "properties": {
    "addr:full":"1460 Trinity Dr Los Alamos NM 87544",
    "addr:housenumber":"1460",
    "addr:postcode":"87544",
    "addr:street":"Trinity Dr",
    "iso:country":"US",
    "sg:address":"1460 Trinity Dr",
    "sg:city":"Los Alamos",
    "sg:classifiers":[
        {
            "category":"Professional",
            "subcategory":"Management & Consulting",
            "type":"Services"
        }
    ],
    "sg:phone":"+1 505 661 7033",
    "sg:postcode":"87544",
    "sg:province":"NM",
    "sg:tags":[
        "consultant",
        "business"
    ],
    "wof:name":"Time Solutions Corp",
    "wof:placetype":"venue"
},
  "geometry": {"coordinates":[-106.298636,35.879857],"type":"Point"}
}