{
  "type": "Feature",
  "properties": {
    "iso:country":"US",
    "sg:address":"4565 San Mateo Blvd NE",
    "sg:city":"Albuquerque",
    "sg:classifiers":[
        {
            "category":"Professional",
            "type":"Services"
        }
    ],
    "sg:phone":"+1 505 872 4294",
    "sg:postcode":"87109",
    "sg:province":"NM",
    "sg:tags":[
        "establishment"
    ],
    "wof:name":"Goodman Reality Group",
    "wof:placetype":"venue"
},
  "geometry": {"coordinates":[-106.58655,35.131524],"type":"Point"}
}