{
  "type": "Feature",
  "properties": {
    "iso:country":"US",
    "sg:address":"2805 Palo Verde Dr NE",
    "sg:city":"Albuquerque",
    "sg:classifiers":[
        {
            "category":"Building & Trades",
            "subcategory":"Construction",
            "type":"Services"
        }
    ],
    "sg:phone":"+1 505 298 8355",
    "sg:postcode":"87112",
    "sg:province":"NM",
    "sg:tags":[
        "contractor"
    ],
    "wof:name":"Casa Cornice",
    "wof:placetype":"venue"
},
  "geometry": {"coordinates":[-106.496522,35.114042],"type":"Point"}
}