{
  "type": "Feature",
  "properties": {
    "iso:country":"US",
    "sg:address":"414 S White Sands Blvd",
    "sg:city":"Alamogordo",
    "sg:classifiers":[
        {
            "category":"Restaurant",
            "type":"Food & Drink"
        }
    ],
    "sg:phone":"+1 505 437 6400",
    "sg:postcode":"88310",
    "sg:province":"NM",
    "sg:tags":[
        "eating"
    ],
    "wof:name":"Hi-D-Ho Drive In",
    "wof:placetype":"venue"
},
  "geometry": {"coordinates":[-105.96044,32.886845],"type":"Point"}
}