{
  "type": "Feature",
  "properties": {
    "addr:full":"556 E Garcia St Santa Fe NM 87505",
    "addr:housenumber":"556",
    "addr:postcode":"87505",
    "addr:street":"E Garcia St",
    "iso:country":"US",
    "sg:address":"556 E Garcia St",
    "sg:city":"Santa Fe",
    "sg:classifiers":[
        {
            "category":"Organizations",
            "subcategory":"Membership Organization",
            "type":"Services"
        }
    ],
    "sg:phone":"+1 505 820 2826",
    "sg:postcode":"87505",
    "sg:province":"NM",
    "wof:name":"Arnold Condominiums Assn",
    "wof:placetype":"venue"
},
  "geometry": {"coordinates":[-105.933431,35.679958],"type":"Point"}
}