{
  "type": "Feature",
  "properties": {
    "iso:country":"US",
    "sg:address":"5012 Summersville Dr NW",
    "sg:city":"Albuquerque",
    "sg:classifiers":[
        {
            "category":"Wholesale",
            "subcategory":"Vending Machines",
            "type":"Manufacturing & Wholesale Goods"
        }
    ],
    "sg:phone":"+1 505 890 5712",
    "sg:postcode":"87120",
    "sg:province":"NM",
    "sg:tags":[
        "operator"
    ],
    "wof:name":"Snacks Unlimited",
    "wof:placetype":"venue"
},
  "geometry": {"coordinates":[-106.693437,35.176162],"type":"Point"}
}