{
  "type": "Feature",
  "properties": {
    "addr:full":"1305 Tungsten St Truth Or Cnsqncs NM 87901",
    "addr:housenumber":"1305",
    "addr:postcode":"87901",
    "addr:street":"Tungsten St",
    "iso:country":"US",
    "sg:address":"1305 Tungsten St",
    "sg:city":"Truth Or Cnsqncs",
    "sg:classifiers":[
        {
            "category":"Retail",
            "subcategory":"Laundry & Dry Cleaning",
            "type":"Services"
        }
    ],
    "sg:phone":"+1 505 894 3117",
    "sg:postcode":"87901",
    "sg:province":"NM",
    "sg:tags":[
        "cleaners",
        "rug",
        "carpet"
    ],
    "wof:name":"Blue Ribbon Carpet Cleaning",
    "wof:placetype":"venue"
},
  "geometry": {"coordinates":[-107.27713900000001,33.120158],"type":"Point"}
}