{
  "type": "Feature",
  "properties": {
    "addr:full":"233 S New York Ave Alamogordo NM 88310",
    "addr:housenumber":"233",
    "addr:postcode":"88310",
    "addr:street":"S New York Ave",
    "iso:country":"US",
    "sg:address":"233 S New York Ave",
    "sg:city":"Alamogordo",
    "sg:classifiers":[
        {
            "category":"Autos & Motor Vehicles",
            "subcategory":"Fuel & Gas Station",
            "type":"Retail Goods"
        }
    ],
    "sg:phone":"+1 505 443 2406",
    "sg:postcode":"88310",
    "sg:province":"NM",
    "sg:tags":[
        "oil"
    ],
    "wof:name":"Mirastar",
    "wof:placetype":"venue"
},
  "geometry": {"coordinates":[-105.95948799999999,32.887645],"type":"Point"}
}