{
  "type": "Feature",
  "properties": {
    "iso:country":"US",
    "sg:address":"5924 Osuna Rd NE",
    "sg:city":"Albuquerque",
    "sg:classifiers":[
        {
            "category":"Personal",
            "type":"Services"
        }
    ],
    "sg:phone":"+1 505 620 2171",
    "sg:postcode":"87109",
    "sg:province":"NM",
    "sg:tags":[
        "therapist",
        "massage"
    ],
    "wof:name":"Massage MAJIC",
    "wof:placetype":"venue"
},
  "geometry": {"coordinates":[-106.581304,35.144678],"type":"Point"}
}