{
  "type": "Feature",
  "properties": {
    "iso:country":"US",
    "sg:address":"121 S Main Ave",
    "sg:city":"Aztec",
    "sg:classifiers":[
        {
            "category":"Organizations",
            "subcategory":"Community Association",
            "type":"Services"
        }
    ],
    "sg:phone":"+1 505 334 2970",
    "sg:postcode":"87410",
    "sg:province":"NM",
    "sg:tags":[
        "military"
    ],
    "wof:name":"American Legion",
    "wof:placetype":"venue"
},
  "geometry": {"coordinates":[-107.995206,36.822232],"type":"Point"}
}