{
  "type": "Feature",
  "properties": {
    "iso:country":"US",
    "sg:address":"604 N Richardson Ave",
    "sg:city":"Roswell",
    "sg:classifiers":[
        {
            "category":"Professional",
            "subcategory":"Lawyer & Legal Services",
            "type":"Services"
        }
    ],
    "sg:phone":"+1 505 624 2463",
    "sg:postcode":"88201",
    "sg:province":"NM",
    "sg:tags":[
        "attorney"
    ],
    "wof:name":"Hennighausen & Olsen",
    "wof:placetype":"venue"
},
  "geometry": {"coordinates":[-104.524485,33.39986],"type":"Point"}
}