{
  "type": "Feature",
  "properties": {
    "iso:country":"US",
    "sg:address":"2721 San Mateo Blvd NE",
    "sg:city":"Albuquerque",
    "sg:classifiers":[
        {
            "category":"Personal",
            "subcategory":"Beauty Salon",
            "type":"Services"
        }
    ],
    "sg:phone":"+1 505 881 7833",
    "sg:postcode":"87110",
    "sg:province":"NM",
    "sg:tags":[
        "shop"
    ],
    "wof:name":"Cosmos Hair & Nail Concepts",
    "wof:placetype":"venue"
},
  "geometry": {"coordinates":[-106.586414,35.112448],"type":"Point"}
}