{
  "type": "Feature",
  "properties": {
    "iso:country":"US",
    "sg:address":"330 W Coal Ave",
    "sg:city":"Hobbs",
    "sg:classifiers":[
        {
            "category":"Personal",
            "subcategory":"Beauty Salon",
            "type":"Services"
        }
    ],
    "sg:phone":"+1 505 392 2253",
    "sg:postcode":"88240",
    "sg:province":"NM",
    "sg:tags":[
        "manicuring"
    ],
    "wof:name":"South West Nail & Salon",
    "wof:placetype":"venue"
},
  "geometry": {"coordinates":[-103.13971600000001,32.732567],"type":"Point"}
}