{
  "type": "Feature",
  "properties": {
    "iso:country":"US",
    "sg:address":"1212 Cll de Comercio",
    "sg:city":"Santa Fe",
    "sg:classifiers":[
        {
            "category":"Retail",
            "subcategory":"Auto Repair",
            "type":"Services"
        }
    ],
    "sg:phone":"+1 505 471 5577",
    "sg:postcode":"87507",
    "sg:province":"NM",
    "sg:tags":[
        "repairing",
        "automobile"
    ],
    "wof:name":"Need A Lift Automotive",
    "wof:placetype":"venue"
},
  "geometry": {"coordinates":[-105.989699,35.661991],"type":"Point"}
}