{
  "type": "Feature",
  "properties": {
    "addr:full":"8804 Cam Osito NE Albuquerque NM 87111",
    "addr:housenumber":"8804",
    "addr:postcode":"87111",
    "addr:street":"Cam Osito Ne",
    "iso:country":"US",
    "sg:address":"8804 Cam Osito NE",
    "sg:city":"Albuquerque",
    "sg:classifiers":[
        {
            "category":"Banks & Credit Unions",
            "subcategory":"Financial Services",
            "type":"Services"
        }
    ],
    "sg:phone":"+1 505 828 0702",
    "sg:postcode":"87111",
    "sg:province":"NM",
    "sg:tags":[
        "trust",
        "investment",
        "real estate"
    ],
    "wof:name":"Tegwar Assoc",
    "wof:placetype":"venue"
},
  "geometry": {"coordinates":[-106.54539800000001,35.139235],"type":"Point"}
}