{
  "type": "Feature",
  "properties": {
    "iso:country":"US",
    "sg:address":"1300 W Navajo St",
    "sg:city":"Farmington",
    "sg:classifiers":[
        {
            "category":"Airport",
            "type":"Transportation"
        }
    ],
    "sg:phone":"+1 505 599 1395",
    "sg:postcode":"87401",
    "sg:province":"NM",
    "wof:name":"Four Corners Regional Airport",
    "wof:placetype":"venue"
},
  "geometry": {"coordinates":[-108.22721799999999,36.738611],"type":"Point"}
}