{
  "type": "Feature",
  "properties": {
    "iso:country":"US",
    "sg:address":"5501 Montgomery Blvd NE",
    "sg:city":"Albuquerque",
    "sg:classifiers":[
        {
            "category":"Utilities",
            "subcategory":"Mobile Phone",
            "type":"Services"
        },
        {
            "category":"Coffee & Tea",
            "type":"Food & Drink"
        }
    ],
    "sg:phone":"+1 505 881 2795",
    "sg:postcode":"87109",
    "sg:province":"NM",
    "sg:tags":[
        "shop",
        "wi-fi",
        "espresso",
        "hotspot",
        "restaurant"
    ],
    "sg:website":"http://www.starbuckscoffee.com",
    "wof:name":"Starbucks Coffee",
    "wof:placetype":"venue"
},
  "geometry": {"coordinates":[-106.580709,35.130966],"type":"Point"}
}