{
  "type": "Feature",
  "properties": {
    "iso:country":"US",
    "sg:address":"2442 Cerrillos Rd",
    "sg:city":"Santa Fe",
    "sg:classifiers":[
        {
            "category":"Professional",
            "subcategory":"Detective & Security Services",
            "type":"Services"
        }
    ],
    "sg:phone":"+1 505 466 2809",
    "sg:postcode":"87505",
    "sg:province":"NM",
    "sg:tags":[
        "engineering",
        "design",
        "system"
    ],
    "wof:name":"Myers Integrated Tech L L C",
    "wof:placetype":"venue"
},
  "geometry": {"coordinates":[-105.982187,35.660021],"type":"Point"}
}