{
  "type": "Feature",
  "properties": {
    "iso:country":"US",
    "sg:address":"1515 E Sanger St",
    "sg:city":"Hobbs",
    "sg:classifiers":[
        {
            "category":"Education",
            "subcategory":"School",
            "type":"Public Place"
        }
    ],
    "sg:phone":"+1 505 433 0100",
    "sg:postcode":"88240",
    "sg:province":"NM",
    "sg:website":"www.hobbsschools.net",
    "wof:name":"Hobbs Municipal School Dist",
    "wof:placetype":"venue"
},
  "geometry": {"coordinates":[-103.118394,32.711105],"type":"Point"}
}