{
  "type": "Feature",
  "properties": {
    "iso:country":"US",
    "sg:address":"1000 W Spruce St",
    "sg:city":"Deming",
    "sg:classifiers":[
        {
            "category":"Shopping",
            "subcategory":"Used Merchandise",
            "type":"Retail Goods"
        }
    ],
    "sg:phone":"+1 505 546 2447",
    "sg:postcode":"88030",
    "sg:province":"NM",
    "sg:tags":[
        "furniture"
    ],
    "wof:name":"L & R New & Used Furniture",
    "wof:placetype":"venue"
},
  "geometry": {"coordinates":[-107.76996,32.26636],"type":"Point"}
}