{
  "type": "Feature",
  "properties": {
    "iso:country":"US",
    "sg:address":"2603 Boyd Ave",
    "sg:city":"Gallup",
    "sg:classifiers":[
        {
            "category":"Banks & Credit Unions",
            "subcategory":"Investment Brokerage",
            "type":"Services"
        }
    ],
    "sg:phone":"+1 505 863 2033",
    "sg:postcode":"87301",
    "sg:province":"NM",
    "sg:tags":[
        "repair",
        "industrial",
        "mfg",
        "automotive",
        "trade",
        "machinery"
    ],
    "wof:name":"Peterson Welding & Mch Work",
    "wof:placetype":"venue"
},
  "geometry": {"coordinates":[-108.701802,35.525269],"type":"Point"}
}