{
  "type": "Feature",
  "properties": {
    "iso:country":"US",
    "sg:address":"2609 W Marland St",
    "sg:city":"Hobbs",
    "sg:classifiers":[
        {
            "category":"Utilities",
            "subcategory":"Fuel Oil & Lpg",
            "type":"Services"
        }
    ],
    "sg:phone":"+1 505 393 0685",
    "sg:postcode":"88240",
    "sg:province":"NM",
    "sg:tags":[
        "propane",
        "gas"
    ],
    "wof:name":"Taylor Propane Gas",
    "wof:placetype":"venue"
},
  "geometry": {"coordinates":[-103.168174,32.696538],"type":"Point"}
}