{
  "type": "Feature",
  "properties": {
    "addr:full":"2093 Cll Lorca Santa Fe NM 87505",
    "addr:postcode":"2093;87505",
    "addr:street":"Cll Lorca",
    "iso:country":"US",
    "sg:address":"2093 Cll Lorca",
    "sg:city":"Santa Fe",
    "sg:classifiers":[
        {
            "category":"Building & Trades",
            "subcategory":"Electrical",
            "type":"Services"
        }
    ],
    "sg:phone":"+1 505 471 8697",
    "sg:postcode":"87505",
    "sg:province":"NM",
    "sg:tags":[
        "electric",
        "contractor"
    ],
    "wof:name":"PRS Electric",
    "wof:placetype":"venue"
},
  "geometry": {"coordinates":[-105.96392,35.654569],"type":"Point"}
}