{
  "type": "Feature",
  "properties": {
    "iso:country":"US",
    "sg:address":"145 Lincoln Ave",
    "sg:city":"Santa Fe",
    "sg:classifiers":[
        {
            "category":"Shopping",
            "subcategory":"Jewelry",
            "type":"Retail Goods"
        }
    ],
    "sg:phone":"+1 505 986 1955",
    "sg:postcode":"87501",
    "sg:province":"NM",
    "wof:name":"James Kallas Jewelers Inc",
    "wof:placetype":"venue"
},
  "geometry": {"coordinates":[-105.93842100000001,35.688487],"type":"Point"}
}