{
  "type": "Feature",
  "properties": {
    "iso:country":"US",
    "sg:address":"186 E Troy Ave",
    "sg:city":"Raton",
    "sg:classifiers":[
        {
            "category":"Bus Charters",
            "type":"Transportation"
        }
    ],
    "sg:phone":"+1 505 445 9510",
    "sg:postcode":"87740",
    "sg:province":"NM",
    "sg:tags":[
        "rental"
    ],
    "sg:website":"www.durhamschoolservices.com",
    "wof:name":"Durham School Svc",
    "wof:placetype":"venue"
},
  "geometry": {"coordinates":[-104.438759,36.888306],"type":"Point"}
}