{
  "type": "Feature",
  "properties": {
    "iso:country":"US",
    "sg:address":"1424 2nd St",
    "sg:city":"Santa Fe",
    "sg:classifiers":[
        {
            "category":"Health Services",
            "subcategory":"Doctor",
            "type":"Services"
        }
    ],
    "sg:phone":"+1 505 984 2774",
    "sg:postcode":"87505",
    "sg:province":"NM",
    "sg:tags":[
        "dentist"
    ],
    "wof:name":"Comprehensive Dental Care",
    "wof:placetype":"venue"
},
  "geometry": {"coordinates":[-105.969155,35.666343],"type":"Point"}
}