{
  "type": "Feature",
  "properties": {
    "iso:country":"US",
    "sg:address":"426 S Broadway St",
    "sg:city":"Truth Or Cnsqncs",
    "sg:classifiers":[
        {
            "category":"Restaurant",
            "type":"Food & Drink"
        }
    ],
    "sg:phone":"+1 505 894 7878",
    "sg:postcode":"87901",
    "sg:province":"NM",
    "wof:name":"Cuchillo Cafe",
    "wof:placetype":"venue"
},
  "geometry": {"coordinates":[-107.260191,33.127617],"type":"Point"}
}