{
  "type": "Feature",
  "properties": {
    "iso:country":"US",
    "sg:address":"4915 Pso del Norte NE",
    "sg:city":"Albuquerque",
    "sg:classifiers":[
        {
            "category":"Building & Trades",
            "subcategory":"Landscaping Services",
            "type":"Services"
        }
    ],
    "sg:phone":"+1 505 884 4433",
    "sg:postcode":"87113",
    "sg:province":"NM",
    "sg:tags":[
        "lawn",
        "maintenance",
        "grounds"
    ],
    "wof:name":"Lawn Doctor Inc",
    "wof:placetype":"venue"
},
  "geometry": {"coordinates":[-106.59463700000001,35.174508],"type":"Point"}
}