{
  "type": "Feature",
  "properties": {
    "iso:country":"US",
    "sg:address":"139 Madison St NE",
    "sg:city":"Albuquerque",
    "sg:classifiers":[
        {
            "category":"Real Estate",
            "subcategory":"Real Estate Agent",
            "type":"Services"
        }
    ],
    "sg:phone":"+1 505 830 9808",
    "sg:postcode":"87108",
    "sg:province":"NM",
    "sg:tags":[
        "management"
    ],
    "wof:name":"Mac Management Inc",
    "wof:placetype":"venue"
},
  "geometry": {"coordinates":[-106.592402,35.079484],"type":"Point"}
}