{
  "type": "Feature",
  "properties": {
    "iso:country":"US",
    "sg:address":"438 N Cam del Pueblo",
    "sg:city":"Bernalillo",
    "sg:classifiers":[
        {
            "category":"Organizations",
            "subcategory":"Religious Organization",
            "type":"Services"
        }
    ],
    "sg:phone":"+1 505 867 3880",
    "sg:postcode":"87004",
    "sg:province":"NM",
    "sg:tags":[
        "church"
    ],
    "wof:name":"Harvest Time Christian Church",
    "wof:placetype":"venue"
},
  "geometry": {"coordinates":[-106.538325,35.324617],"type":"Point"}
}