{
  "type": "Feature",
  "properties": {
    "iso:country":"US",
    "sg:address":"420 S Manzanita St",
    "sg:city":"Las Cruces",
    "sg:classifiers":[
        {
            "category":"Retail",
            "subcategory":"Self-service Laundry",
            "type":"Services"
        }
    ],
    "sg:phone":"+1 505 525 0090",
    "sg:postcode":"88001",
    "sg:province":"NM",
    "wof:name":"Manzanita's Laundry",
    "wof:placetype":"venue"
},
  "geometry": {"coordinates":[-106.771552,32.307604],"type":"Point"}
}