{
  "type": "Feature",
  "properties": {
    "addr:full":"4001 Oleta Dr Las Cruces NM 88001",
    "addr:housenumber":"4001",
    "addr:postcode":"88001",
    "addr:street":"Oleta Dr",
    "iso:country":"US",
    "sg:address":"4001 Oleta Dr",
    "sg:city":"Las Cruces",
    "sg:classifiers":[
        {
            "category":"Restaurant",
            "type":"Food & Drink"
        }
    ],
    "sg:phone":"+1 505 526 9588",
    "sg:postcode":"88001",
    "sg:province":"NM",
    "sg:tags":[
        "eating"
    ],
    "wof:name":"J W Flours",
    "wof:placetype":"venue"
},
  "geometry": {"coordinates":[-106.75302000000001,32.266529],"type":"Point"}
}