{
  "type": "Feature",
  "properties": {
    "iso:country":"US",
    "sg:address":"27 Vis Grande",
    "sg:city":"Cedar Crest",
    "sg:classifiers":[
        {
            "category":"Education",
            "subcategory":"Special Training",
            "type":"Public Place"
        }
    ],
    "sg:phone":"+1 505 281 1221",
    "sg:postcode":"87008",
    "sg:province":"NM",
    "sg:tags":[
        "aid",
        "instruction",
        "first"
    ],
    "wof:name":"Learn What To Do Cpr",
    "wof:placetype":"venue"
},
  "geometry": {"coordinates":[-106.38255599999999,35.101108],"type":"Point"}
}