{
  "type": "Feature",
  "properties": {
    "addr:full":"1748 Fairway Ter Clovis NM 88101",
    "addr:housenumber":"1748",
    "addr:postcode":"88101",
    "addr:street":"Fairway Ter",
    "iso:country":"US",
    "sg:address":"1748 Fairway Ter",
    "sg:city":"Clovis",
    "sg:classifiers":[
        {
            "category":"Travel",
            "subcategory":"Travel Agent",
            "type":"Entertainment"
        }
    ],
    "sg:phone":"+1 505 762 3721",
    "sg:postcode":"88101",
    "sg:province":"NM",
    "sg:tags":[
        "cruise"
    ],
    "wof:name":"Carlson Travel Network-Holiday",
    "wof:placetype":"venue"
},
  "geometry": {"coordinates":[-103.184415,34.436714],"type":"Point"}
}