{
  "type": "Feature",
  "properties": {
    "iso:country":"US",
    "sg:address":"3111 Glenwood Dr NW",
    "sg:city":"Albuquerque",
    "sg:classifiers":[
        {
            "category":"Retail",
            "subcategory":"Repair Shop",
            "type":"Services"
        }
    ],
    "sg:phone":"+1 505 344 8071",
    "sg:postcode":"87107",
    "sg:province":"NM",
    "wof:name":"Optical Services Company",
    "wof:placetype":"venue"
},
  "geometry": {"coordinates":[-106.677359,35.127639],"type":"Point"}
}