{
  "type": "Feature",
  "properties": {
    "iso:country":"US",
    "sg:address":"2701 Carlisle Blvd NE",
    "sg:city":"Albuquerque",
    "sg:classifiers":[
        {
            "category":"Professional",
            "type":"Services"
        }
    ],
    "sg:phone":"+1 505 830 6927",
    "sg:postcode":"87110",
    "sg:province":"NM",
    "sg:tags":[
        "establishment"
    ],
    "wof:name":"Humana",
    "wof:placetype":"venue"
},
  "geometry": {"coordinates":[-106.604182,35.112935],"type":"Point"}
}