{
  "type": "Feature",
  "properties": {
    "addr:full":"2701 Carlisle Blvd NE Albuquerque NM 87110",
    "addr:housenumber":"2701",
    "addr:postcode":"87110",
    "addr:street":"Carlisle Blvd Ne",
    "iso:country":"US",
    "sg:address":"2701 Carlisle Blvd NE",
    "sg:city":"Albuquerque",
    "sg:classifiers":[
        {
            "category":"Professional",
            "type":"Services"
        }
    ],
    "sg:phone":"+1 505 830 6927",
    "sg:postcode":"87110",
    "sg:province":"NM",
    "sg:tags":[
        "establishment"
    ],
    "wof:name":"Humana",
    "wof:placetype":"venue"
},
  "geometry": {"coordinates":[-106.60418199999999,35.112935],"type":"Point"}
}