{
  "type": "Feature",
  "properties": {
    "iso:country":"US",
    "sg:address":"1906 Saturn Ct NE",
    "sg:city":"Albuquerque",
    "sg:classifiers":[
        {
            "category":"Professional",
            "subcategory":"Business Services",
            "type":"Services"
        }
    ],
    "sg:phone":"+1 505 271 1836",
    "sg:postcode":"87112",
    "sg:province":"NM",
    "wof:name":"Translations LA Rosa",
    "wof:placetype":"venue"
},
  "geometry": {"coordinates":[-106.509668,35.104894],"type":"Point"}
}