{
  "type": "Feature",
  "properties": {
    "addr:full":"11030 Menaul Blvd NE Albuquerque NM 87112",
    "addr:housenumber":"11030",
    "addr:postcode":"87112",
    "addr:street":"Menaul Blvd Ne",
    "iso:country":"US",
    "sg:address":"11030 Menaul Blvd NE",
    "sg:city":"Albuquerque",
    "sg:classifiers":[
        {
            "category":"Shopping",
            "subcategory":"Florist",
            "type":"Retail Goods"
        }
    ],
    "sg:phone":"+1 505 293 7677",
    "sg:postcode":"87112",
    "sg:province":"NM",
    "wof:name":"Flower Co Florist",
    "wof:placetype":"venue"
},
  "geometry": {"coordinates":[-106.516713,35.108816],"type":"Point"}
}