{
  "type": "Feature",
  "properties": {
    "iso:country":"US",
    "sg:address":"320 Gold Ave SE",
    "sg:city":"Albuquerque",
    "sg:classifiers":[
        {
            "category":"Professional",
            "subcategory":"Lawyer & Legal Services",
            "type":"Services"
        }
    ],
    "sg:phone":"+1 505 244 0700",
    "sg:postcode":"87102",
    "sg:province":"NM",
    "wof:name":"David L Skinner PC",
    "wof:placetype":"venue"
},
  "geometry": {"coordinates":[-106.644214,35.082522],"type":"Point"}
}