{
  "type": "Feature",
  "properties": {
    "addr:full":"134 Yakima Rd Dexter NM 88230",
    "addr:housenumber":"134",
    "addr:postcode":"88230",
    "addr:street":"Yakima Rd",
    "iso:country":"US",
    "sg:address":"134 Yakima Rd",
    "sg:city":"Dexter",
    "sg:classifiers":[
        {
            "category":"Organizations",
            "subcategory":"Religious Organization",
            "type":"Services"
        }
    ],
    "sg:phone":"+1 505 347 2909",
    "sg:postcode":"88230",
    "sg:province":"NM",
    "sg:tags":[
        "church"
    ],
    "wof:name":"Midway Baptist Church",
    "wof:placetype":"venue"
},
  "geometry": {"coordinates":[-104.45379,33.296352],"type":"Point"}
}