{
  "type": "Feature",
  "properties": {
    "iso:country":"US",
    "sg:address":"6116 Agate Ave NW",
    "sg:city":"Albuquerque",
    "sg:classifiers":[
        {
            "category":"Professional",
            "subcategory":"Business Services",
            "type":"Services"
        }
    ],
    "sg:phone":"+1 505 839 9300",
    "sg:postcode":"87120",
    "sg:province":"NM",
    "wof:name":"Diversified Office Systems",
    "wof:placetype":"venue"
},
  "geometry": {"coordinates":[-106.709621,35.159676],"type":"Point"}
}