{
  "type": "Feature",
  "properties": {
    "iso:country":"US",
    "sg:address":"214 Grand Ave",
    "sg:city":"Las Vegas",
    "sg:classifiers":[
        {
            "category":"Professional",
            "subcategory":"Lawyer & Legal Services",
            "type":"Services"
        }
    ],
    "sg:phone":"+1 505 425 3514",
    "sg:postcode":"87701",
    "sg:province":"NM",
    "sg:tags":[
        "attorney"
    ],
    "wof:name":"New Mexico Legal Aid",
    "wof:placetype":"venue"
},
  "geometry": {"coordinates":[-105.215319,35.590923],"type":"Point"}
}