{
  "type": "Feature",
  "properties": {
    "iso:country":"US",
    "sg:address":"4309 Altura Ave NE",
    "sg:city":"Albuquerque",
    "sg:classifiers":[
        {
            "category":"Building & Trades",
            "subcategory":"Construction",
            "type":"Services"
        }
    ],
    "sg:phone":"+1 505 265 6113",
    "sg:postcode":"87110",
    "sg:province":"NM",
    "sg:tags":[
        "builder",
        "operative"
    ],
    "wof:name":"Eric Development",
    "wof:placetype":"venue"
},
  "geometry": {"coordinates":[-106.595366,35.095952],"type":"Point"}
}