{
  "type": "Feature",
  "properties": {
    "iso:country":"US",
    "sg:address":"10600 Teal Rd SW",
    "sg:city":"Albuquerque",
    "sg:classifiers":[
        {
            "category":"Retail",
            "subcategory":"Repair Shop",
            "type":"Services"
        }
    ],
    "sg:phone":"+1 505 604 3848",
    "sg:postcode":"87121",
    "sg:province":"NM",
    "wof:name":"Top Gun Mobile Wash",
    "wof:placetype":"venue"
},
  "geometry": {"coordinates":[-106.75175299999999,35.05656],"type":"Point"}
}