{
  "type": "Feature",
  "properties": {
    "iso:country":"US",
    "sg:address":"3917 West Rd",
    "sg:city":"Los Alamos",
    "sg:classifiers":[
        {
            "category":"Shopping",
            "subcategory":"Gifts & Souvenirs",
            "type":"Retail Goods"
        }
    ],
    "sg:phone":"+1 505 662 2555",
    "sg:postcode":"87544",
    "sg:province":"NM",
    "wof:name":"Lobby Shop",
    "wof:placetype":"venue"
},
  "geometry": {"coordinates":[-106.319976,35.882304],"type":"Point"}
}