{
  "type": "Feature",
  "properties": {
    "iso:country":"US",
    "sg:address":"2091 Cam Lado",
    "sg:city":"Santa Fe",
    "sg:classifiers":[
        {
            "category":"Banks & Credit Unions",
            "subcategory":"Financial Services",
            "type":"Services"
        }
    ],
    "sg:phone":"+1 505 471 8009",
    "sg:postcode":"87505",
    "sg:province":"NM",
    "sg:tags":[
        "trust",
        "management"
    ],
    "wof:name":"Charles Cocoa Maxwell Jr",
    "wof:placetype":"venue"
},
  "geometry": {"coordinates":[-105.96588,35.652617],"type":"Point"}
}