{
  "type": "Feature",
  "properties": {
    "iso:country":"US",
    "sg:address":"132 Monte Rey Dr",
    "sg:city":"Los Alamos",
    "sg:classifiers":[
        {
            "category":"Building & Trades",
            "subcategory":"Construction",
            "type":"Services"
        }
    ],
    "sg:phone":"+1 505 470 1512",
    "sg:postcode":"87544",
    "sg:province":"NM",
    "sg:tags":[
        "general",
        "contractor"
    ],
    "wof:name":"Confidence Builders",
    "wof:placetype":"venue"
},
  "geometry": {"coordinates":[-106.213955,35.804973],"type":"Point"}
}