{
  "type": "Feature",
  "properties": {
    "addr:full":"1866 Candela St Santa Fe NM 87505",
    "addr:housenumber":"1866",
    "addr:postcode":"87505",
    "addr:street":"Candela St",
    "iso:country":"US",
    "sg:address":"1866 Candela St",
    "sg:city":"Santa Fe",
    "sg:classifiers":[
        {
            "category":"Organizations",
            "subcategory":"Religious Organization",
            "type":"Services"
        }
    ],
    "sg:phone":"+1 505 473 7779",
    "sg:postcode":"87505",
    "sg:province":"NM",
    "wof:name":"St Juliana of Lazarevo",
    "wof:placetype":"venue"
},
  "geometry": {"coordinates":[-105.963472,35.64704],"type":"Point"}
}