{
  "type": "Feature",
  "properties": {
    "addr:full":"3229 Industrial Dr Hobbs NM 88240",
    "addr:housenumber":"3229",
    "addr:postcode":"88240",
    "addr:street":"Industrial Dr",
    "iso:country":"US",
    "sg:address":"3229 Industrial Dr",
    "sg:city":"Hobbs",
    "sg:classifiers":[
        {
            "category":"Wholesale",
            "subcategory":"Machinery & Supplies",
            "type":"Manufacturing & Wholesale Goods"
        }
    ],
    "sg:phone":"+1 505 392 2973",
    "sg:postcode":"88240",
    "sg:province":"NM",
    "sg:tags":[
        "equipment",
        "safety",
        "clothing"
    ],
    "wof:name":"Callaway Safety Equipment Inc",
    "wof:placetype":"venue"
},
  "geometry": {"coordinates":[-103.157014,32.735054],"type":"Point"}
}