{
  "type": "Feature",
  "properties": {
    "addr:full":"3393 Pan American Fwy Albuquerque NM 87107",
    "addr:housenumber":"3393",
    "addr:postcode":"87107",
    "addr:street":"Pan American Fwy",
    "iso:country":"US",
    "sg:address":"3393 Pan American Fwy",
    "sg:city":"Albuquerque",
    "sg:classifiers":[
        {
            "category":"Building & Trades",
            "subcategory":"Construction",
            "type":"Services"
        }
    ],
    "sg:phone":"+1 505 841 4334",
    "sg:postcode":"87107",
    "sg:province":"NM",
    "wof:name":"Transportation New Mexico Dept",
    "wof:placetype":"venue"
},
  "geometry": {"coordinates":[-106.62473300000001,35.117613],"type":"Point"}
}