{
  "type": "Feature",
  "properties": {
    "iso:country":"US",
    "sg:address":"8200 Carmel Ave NE",
    "sg:city":"Albuquerque",
    "sg:classifiers":[
        {
            "category":"Health Services",
            "subcategory":"Clinic",
            "type":"Services"
        }
    ],
    "sg:phone":"+1 505 828 4431",
    "sg:postcode":"87122",
    "sg:province":"NM",
    "sg:tags":[
        "information",
        "dentist",
        "bureau"
    ],
    "wof:name":"Dental Emergency",
    "wof:placetype":"venue"
},
  "geometry": {"coordinates":[-106.554585,35.175653],"type":"Point"}
}