{
  "type": "Feature",
  "properties": {
    "addr:full":"4601 Quartz Dr NE Rio Rancho NM 87124",
    "addr:housenumber":"4601",
    "addr:postcode":"87124",
    "addr:street":"Quartz Dr Ne",
    "iso:country":"US",
    "sg:address":"4601 Quartz Dr NE",
    "sg:city":"Rio Rancho",
    "sg:classifiers":[
        {
            "category":"Organizations",
            "subcategory":"Religious Organization",
            "type":"Services"
        }
    ],
    "sg:phone":"+1 505 891 1643",
    "sg:postcode":"87124",
    "sg:province":"NM",
    "wof:name":"John D De Jesus",
    "wof:placetype":"venue"
},
  "geometry": {"coordinates":[-106.648894,35.265438],"type":"Point"}
}