{
  "type": "Feature",
  "properties": {
    "iso:country":"US",
    "sg:address":"1966 Cerrillos Rd",
    "sg:city":"Santa Fe",
    "sg:classifiers":[
        {
            "category":"Shopping",
            "subcategory":"Computers & Home Electronics",
            "type":"Retail Goods"
        }
    ],
    "sg:phone":"+1 505 982 2289",
    "sg:postcode":"87505",
    "sg:province":"NM",
    "wof:name":"Super Sound",
    "wof:placetype":"venue"
},
  "geometry": {"coordinates":[-105.976106,35.663128],"type":"Point"}
}