{
  "type": "Feature",
  "properties": {
    "iso:country":"US",
    "sg:address":"3 Abanico Rd",
    "sg:city":"Santa Fe",
    "sg:classifiers":[
        {
            "category":"Organizations",
            "subcategory":"Religious Organization",
            "type":"Services"
        }
    ],
    "sg:phone":"+1 505 466 6314",
    "sg:postcode":"87508",
    "sg:province":"NM",
    "wof:name":"Foundation In Light",
    "wof:placetype":"venue"
},
  "geometry": {"coordinates":[-105.937533,35.5452],"type":"Point"}
}