{
  "type": "Feature",
  "properties": {
    "iso:country":"US",
    "sg:address":"237 Don Gaspar Ave",
    "sg:city":"Santa Fe",
    "sg:classifiers":[
        {
            "category":"Government",
            "subcategory":"Office",
            "type":"Public Place"
        }
    ],
    "sg:phone":"+1 505 827 4906",
    "sg:postcode":"87501",
    "sg:province":"NM",
    "wof:name":"Honorable Michael Vigil",
    "wof:placetype":"venue"
},
  "geometry": {"coordinates":[-105.940349,35.68445],"type":"Point"}
}