{
  "type": "Feature",
  "properties": {
    "addr:full":"2015 Menaul Blvd NE Albuquerque NM 87107",
    "addr:housenumber":"2015",
    "addr:postcode":"87107",
    "addr:street":"Menaul Blvd Ne",
    "iso:country":"US",
    "sg:address":"2015 Menaul Blvd NE",
    "sg:city":"Albuquerque",
    "sg:classifiers":[
        {
            "category":"Travel",
            "subcategory":"Hotels & Motels",
            "type":"Entertainment"
        }
    ],
    "sg:phone":"+1 505 881 3210",
    "sg:postcode":"87107",
    "sg:province":"NM",
    "wof:name":"Comfort Inn Midtown",
    "wof:placetype":"venue"
},
  "geometry": {"coordinates":[-106.622061,35.109235],"type":"Point"}
}