{
  "type": "Feature",
  "properties": {
    "addr:full":"103 Industrial Park Loop NE Rio Rancho NM 87124",
    "addr:housenumber":"103",
    "addr:postcode":"87124",
    "addr:street":"Industrial Park Loop Ne",
    "iso:country":"US",
    "sg:address":"103 Industrial Park Loop NE",
    "sg:city":"Rio Rancho",
    "sg:classifiers":[
        {
            "category":"Home & Garden",
            "subcategory":"Building Materials",
            "type":"Retail Goods"
        }
    ],
    "sg:phone":"+1 505 891 0400",
    "sg:postcode":"87124",
    "sg:province":"NM",
    "wof:name":"New Mexico Builders Supply",
    "wof:placetype":"venue"
},
  "geometry": {"coordinates":[-106.631309,35.260519],"type":"Point"}
}