{
  "type": "Feature",
  "properties": {
    "addr:full":"131 Bookout Rd Tularosa NM 88352",
    "addr:housenumber":"131",
    "addr:postcode":"88352",
    "addr:street":"Bookout Rd",
    "iso:country":"US",
    "sg:address":"131 Bookout Rd",
    "sg:city":"Tularosa",
    "sg:classifiers":[
        {
            "category":"Farming",
            "subcategory":"Farm",
            "type":"Manufacturing & Wholesale Goods"
        }
    ],
    "sg:phone":"+1 505 585 2815",
    "sg:postcode":"88352",
    "sg:province":"NM",
    "wof:name":"Glover Farms",
    "wof:placetype":"venue"
},
  "geometry": {"coordinates":[-106.01073,33.071329],"type":"Point"}
}