{
  "type": "Feature",
  "properties": {
    "iso:country":"US",
    "sg:address":"7500 Bluewater Rd NW",
    "sg:city":"Albuquerque",
    "sg:classifiers":[
        {
            "category":"Social Services",
            "subcategory":"Job Training",
            "type":"Services"
        }
    ],
    "sg:phone":"+1 505 839 3249",
    "sg:postcode":"87121",
    "sg:province":"NM",
    "sg:tags":[
        "jewelry"
    ],
    "wof:name":"Santa Fe Symposium",
    "wof:placetype":"venue"
},
  "geometry": {"coordinates":[-106.71727199999999,35.085366],"type":"Point"}
}