{
  "type": "Feature",
  "properties": {
    "addr:full":"403 W Quay Ave Artesia NM 88210",
    "addr:housenumber":"403",
    "addr:postcode":"88210",
    "addr:street":"W Quay Ave",
    "iso:country":"US",
    "sg:address":"403 W Quay Ave",
    "sg:city":"Artesia",
    "sg:classifiers":[
        {
            "category":"Shopping",
            "subcategory":"Department Store",
            "type":"Retail Goods"
        }
    ],
    "sg:phone":"+1 505 746 4508",
    "sg:postcode":"88210",
    "sg:province":"NM",
    "wof:name":"Family Dollar Store",
    "wof:placetype":"venue"
},
  "geometry": {"coordinates":[-104.402287,32.841033],"type":"Point"}
}