{
  "type": "Feature",
  "properties": {
    "iso:country":"US",
    "sg:address":"415 Solar Rd NW",
    "sg:city":"Albuquerque",
    "sg:classifiers":[
        {
            "category":"Professional",
            "subcategory":"Business Services",
            "type":"Services"
        }
    ],
    "sg:phone":"+1 505 710 7944",
    "sg:postcode":"87107",
    "sg:province":"NM",
    "sg:tags":[
        "artist"
    ],
    "wof:name":"Miguel Gandert Photography",
    "wof:placetype":"venue"
},
  "geometry": {"coordinates":[-106.640767,35.147951],"type":"Point"}
}