{
  "type": "Feature",
  "properties": {
    "iso:country":"US",
    "sg:address":"2711 Karsten Ct SE",
    "sg:city":"Albuquerque",
    "sg:classifiers":[
        {
            "category":"Professional",
            "subcategory":"Business Services",
            "type":"Services"
        }
    ],
    "sg:phone":"+1 505 842 9500",
    "sg:postcode":"87102",
    "sg:province":"NM",
    "sg:tags":[
        "machine",
        "specialize",
        "cutting",
        "sh"
    ],
    "wof:name":"Waterjet Cutting Inc",
    "wof:placetype":"venue"
},
  "geometry": {"coordinates":[-106.64214800000001,35.053507],"type":"Point"}
}