{
  "type": "Feature",
  "properties": {
    "addr:full":"201 Galisteo St Santa Fe NM 87501",
    "addr:housenumber":"201",
    "addr:postcode":"87501",
    "addr:street":"Galisteo St",
    "iso:country":"US",
    "sg:address":"201 Galisteo St",
    "sg:city":"Santa Fe",
    "sg:classifiers":[
        {
            "category":"Home & Garden",
            "subcategory":"Furniture",
            "type":"Retail Goods"
        }
    ],
    "sg:phone":"+1 505 982 7000",
    "sg:postcode":"87501",
    "sg:province":"NM",
    "wof:name":"Sequia Collections",
    "wof:placetype":"venue"
},
  "geometry": {"coordinates":[-105.941479,35.685693],"type":"Point"}
}