{
  "type": "Feature",
  "properties": {
    "iso:country":"US",
    "sg:address":"3 Homesteads Rd",
    "sg:city":"Placitas",
    "sg:classifiers":[
        {
            "category":"Professional",
            "subcategory":"Lawyer & Legal Services",
            "type":"Services"
        }
    ],
    "sg:phone":"+1 505 897 1156",
    "sg:postcode":"87043",
    "sg:province":"NM",
    "sg:tags":[
        "attorney"
    ],
    "wof:name":"Lisa Brown Attorney",
    "wof:placetype":"venue"
},
  "geometry": {"coordinates":[-106.49123899999999,35.308259],"type":"Point"}
}