{
  "type": "Feature",
  "properties": {
    "addr:full":"7950 Doniphan Dr Anthony NM 79821",
    "addr:housenumber":"7950",
    "addr:postcode":"79821",
    "addr:street":"Doniphan Dr",
    "iso:country":"US",
    "sg:address":"7950 Doniphan Dr",
    "sg:city":"Anthony",
    "sg:classifiers":[
        {
            "category":"Recreation",
            "type":"Entertainment"
        }
    ],
    "sg:phone":"+1 915 886 4936",
    "sg:postcode":"79821",
    "sg:province":"NM",
    "sg:tags":[
        "martial",
        "arts",
        "instruction"
    ],
    "wof:name":"X E N Martial Arts",
    "wof:placetype":"venue"
},
  "geometry": {"coordinates":[-106.60348,31.957112],"type":"Point"}
}