{
  "type": "Feature",
  "properties": {
    "addr:full":"101 W Greene St Carlsbad NM 88220",
    "addr:housenumber":"101",
    "addr:postcode":"88220",
    "addr:street":"W Greene St",
    "iso:country":"US",
    "sg:address":"101 W Greene St",
    "sg:city":"Carlsbad",
    "sg:classifiers":[
        {
            "category":"Government",
            "subcategory":"Office",
            "type":"Public Place"
        }
    ],
    "sg:phone":"+1 505 887 4820",
    "sg:postcode":"88220",
    "sg:province":"NM",
    "wof:name":"Eddy County Purchasing",
    "wof:placetype":"venue"
},
  "geometry": {"coordinates":[-104.22708799999999,32.417978],"type":"Point"}
}