{
  "type": "Feature",
  "properties": {
    "iso:country":"US",
    "sg:address":"2800 San Mateo Blvd NE # 1",
    "sg:city":"Albuquerque",
    "sg:classifiers":[
        {
            "category":"Communications",
            "subcategory":"Newspaper",
            "type":"Services"
        }
    ],
    "sg:phone":"+1 505 298 0151",
    "sg:postcode":"87110",
    "sg:province":"NM",
    "wof:name":"Pueblo Journal",
    "wof:placetype":"venue"
},
  "geometry": {"coordinates":[-106.586342,35.112789],"type":"Point"}
}