{
  "type": "Feature",
  "properties": {
    "iso:country":"US",
    "sg:address":"70 Meikle Rd",
    "sg:city":"Tijeras",
    "sg:classifiers":[
        {
            "category":"Building & Trades",
            "subcategory":"Construction",
            "type":"Services"
        }
    ],
    "sg:phone":"+1 505 286 3976",
    "sg:postcode":"87059",
    "sg:province":"NM",
    "sg:tags":[
        "general",
        "contractor"
    ],
    "wof:name":"Blaze Builders",
    "wof:placetype":"venue"
},
  "geometry": {"coordinates":[-106.30511,34.958147],"type":"Point"}
}