{
  "type": "Feature",
  "properties": {
    "iso:country":"US",
    "sg:address":"2120 Ryan Pl NW",
    "sg:city":"Albuquerque",
    "sg:classifiers":[
        {
            "category":"Building & Trades",
            "subcategory":"Pest Control",
            "type":"Services"
        }
    ],
    "sg:phone":"+1 505 344 2525",
    "sg:postcode":"87107",
    "sg:province":"NM",
    "wof:name":"Albuquerque Pest Control",
    "wof:placetype":"venue"
},
  "geometry": {"coordinates":[-106.669687,35.123181],"type":"Point"}
}