{
  "type": "Feature",
  "properties": {
    "addr:full":"106 E Idaho Ave Las Cruces NM 88005",
    "addr:housenumber":"106",
    "addr:postcode":"88005",
    "addr:street":"E Idaho Ave",
    "iso:country":"US",
    "sg:address":"106 E Idaho Ave",
    "sg:city":"Las Cruces",
    "sg:classifiers":[
        {
            "category":"Professional",
            "subcategory":"Engineering",
            "type":"Services"
        }
    ],
    "sg:phone":"+1 505 524 2007",
    "sg:postcode":"88005",
    "sg:province":"NM",
    "sg:tags":[
        "engineer"
    ],
    "wof:name":"Engineers Inc",
    "wof:placetype":"venue"
},
  "geometry": {"coordinates":[-106.779223,32.296707],"type":"Point"}
}