{
  "type": "Feature",
  "properties": {
    "addr:full":"100 Alameda Rd NW Albuquerque NM 87114",
    "addr:housenumber":"100",
    "addr:postcode":"87114",
    "addr:street":"Alameda Rd Nw",
    "iso:country":"US",
    "sg:address":"100 Alameda Rd NW",
    "sg:city":"Albuquerque",
    "sg:classifiers":[
        {
            "category":"Manufacturing",
            "subcategory":"Building Materials",
            "type":"Manufacturing & Wholesale Goods"
        }
    ],
    "sg:phone":"+1 505 898 6770",
    "sg:postcode":"87114",
    "sg:province":"NM",
    "sg:tags":[
        "molding"
    ],
    "sg:website":"www.bestmoulding.com/",
    "wof:name":"Best Moulding Corp",
    "wof:placetype":"venue"
},
  "geometry": {"coordinates":[-106.611974,35.194289],"type":"Point"}
}