{
  "type": "Feature",
  "properties": {
    "iso:country":"US",
    "sg:address":"8100 Wyoming Blvd NE",
    "sg:city":"Albuquerque",
    "sg:classifiers":[
        {
            "category":"Restaurant",
            "type":"Food & Drink"
        }
    ],
    "sg:menulink":"http://www.allmenus.com/nm/albuquerque/156948-whataburger/menu/",
    "sg:phone":"+1 505 798 0330",
    "sg:postcode":"87113",
    "sg:province":"NM",
    "sg:tags":[
        "burger",
        "american"
    ],
    "wof:name":"Whataburger",
    "wof:placetype":"venue"
},
  "geometry": {"coordinates":[-106.55978,35.175323],"type":"Point"}
}