{
  "type": "Feature",
  "properties": {
    "iso:country":"US",
    "sg:address":"551 W Cordova Rd",
    "sg:city":"Santa Fe",
    "sg:classifiers":[
        {
            "category":"Organizations",
            "subcategory":"Community Association",
            "type":"Services"
        }
    ],
    "sg:phone":"+1 505 989 7342",
    "sg:postcode":"87505",
    "sg:province":"NM",
    "sg:tags":[
        "environmental",
        "org"
    ],
    "sg:website":"www.nukewatch.org",
    "wof:name":"Nuclear Watch Of New Mexico",
    "wof:placetype":"venue"
},
  "geometry": {"coordinates":[-105.949597,35.672445],"type":"Point"}
}