{
  "type": "Feature",
  "properties": {
    "addr:full":"1212 Columbus Rd Deming NM 88030",
    "addr:housenumber":"1212",
    "addr:postcode":"88030",
    "addr:street":"Columbus Rd",
    "iso:country":"US",
    "sg:address":"1212 Columbus Rd",
    "sg:city":"Deming",
    "sg:classifiers":[
        {
            "category":"Food & Beverages",
            "subcategory":"Specialty",
            "type":"Retail Goods"
        }
    ],
    "sg:phone":"+1 505 546 6226",
    "sg:postcode":"88030",
    "sg:province":"NM",
    "sg:tags":[
        "health",
        "diet"
    ],
    "wof:name":"Better Bodies Health",
    "wof:placetype":"venue"
},
  "geometry": {"coordinates":[-107.75166400000001,32.256953],"type":"Point"}
}