{
  "type": "Feature",
  "properties": {
    "iso:country":"US",
    "sg:address":"125 Lincoln Ave",
    "sg:city":"Santa Fe",
    "sg:classifiers":[
        {
            "category":"Professional",
            "type":"Services"
        }
    ],
    "sg:phone":"+1 505 982 9814",
    "sg:postcode":"87501",
    "sg:province":"NM",
    "wof:name":"Jim Kassube",
    "wof:placetype":"venue"
},
  "geometry": {"coordinates":[-105.93834200000001,35.688719],"type":"Point"}
}