{
  "type": "Feature",
  "properties": {
    "iso:country":"US",
    "sg:address":"609 N Ash St",
    "sg:city":"Carlsbad",
    "sg:classifiers":[
        {
            "category":"Wholesale",
            "subcategory":"Construction Materials",
            "type":"Manufacturing & Wholesale Goods"
        }
    ],
    "sg:phone":"+1 505 885 1820",
    "sg:postcode":"88220",
    "sg:province":"NM",
    "wof:name":"Westfall Concrete Products",
    "wof:placetype":"venue"
},
  "geometry": {"coordinates":[-104.23802000000001,32.428594],"type":"Point"}
}