{
  "type": "Feature",
  "properties": {
    "iso:country":"US",
    "sg:address":"2155 Dona Ana Rd",
    "sg:city":"Las Cruces",
    "sg:classifiers":[
        {
            "category":"Retail",
            "subcategory":"Repair Shop",
            "type":"Services"
        },
        {
            "category":"Building & Trades",
            "subcategory":"Plumbing",
            "type":"Services"
        }
    ],
    "sg:phone":"+1 505 526 5442",
    "sg:postcode":"88007",
    "sg:province":"NM",
    "sg:tags":[
        "installation",
        "tank",
        "cleaning",
        "septic"
    ],
    "sg:website":"www.johnnysseptic.com",
    "wof:name":"Johnny's Septic Tank Co",
    "wof:placetype":"venue"
},
  "geometry": {"coordinates":[-106.792102,32.331241],"type":"Point"}
}