{
  "type": "Feature",
  "properties": {
    "addr:full":"1523 S 1st St Artesia NM 88210",
    "addr:housenumber":"1523",
    "addr:postcode":"88210",
    "addr:street":"S 1St St",
    "iso:country":"US",
    "sg:address":"1523 S 1st St",
    "sg:city":"Artesia",
    "sg:classifiers":[
        {
            "category":"Retail",
            "subcategory":"Auto Repair",
            "type":"Services"
        }
    ],
    "sg:phone":"+1 505 748 3223",
    "sg:postcode":"88210",
    "sg:province":"NM",
    "sg:tags":[
        "body",
        "glass",
        "towing"
    ],
    "wof:name":"Southwest Glass",
    "wof:placetype":"venue"
},
  "geometry": {"coordinates":[-104.395437,32.82718],"type":"Point"}
}