{
  "type": "Feature",
  "properties": {
    "addr:full":"2425 N McKinley St Hobbs NM 88240",
    "addr:housenumber":"2425",
    "addr:postcode":"88240",
    "addr:street":"N Mckinley St",
    "iso:country":"US",
    "sg:address":"2425 N McKinley St",
    "sg:city":"Hobbs",
    "sg:classifiers":[
        {
            "category":"Social Services",
            "subcategory":"Child Care",
            "type":"Services"
        }
    ],
    "sg:phone":"+1 505 392 8634",
    "sg:postcode":"88240",
    "sg:province":"NM",
    "sg:tags":[
        "kindergarten",
        "academic",
        "school"
    ],
    "wof:name":"Head Start Child & Family Svc",
    "wof:placetype":"venue"
},
  "geometry": {"coordinates":[-103.13462,32.729075],"type":"Point"}
}