{
  "type": "Feature",
  "properties": {
    "addr:full":"4917 Chisholm Trl NW Albuquerque NM 87120",
    "addr:housenumber":"4917",
    "addr:postcode":"87120",
    "addr:street":"Chisholm Trl Nw",
    "iso:country":"US",
    "sg:address":"4917 Chisholm Trl NW",
    "sg:city":"Albuquerque",
    "sg:classifiers":[
        {
            "category":"Shopping",
            "subcategory":"Hobbies, Toys, & Games",
            "type":"Retail Goods"
        }
    ],
    "sg:phone":"+1 505 681 9053",
    "sg:postcode":"87120",
    "sg:province":"NM",
    "sg:tags":[
        "craft"
    ],
    "wof:name":"H & H Custom Beading",
    "wof:placetype":"venue"
},
  "geometry": {"coordinates":[-106.695745,35.165872],"type":"Point"}
}