{
  "type": "Feature",
  "properties": {
    "addr:full":"4008 Stephanie NE Albuquerque NM 87111",
    "addr:housenumber":"4008",
    "addr:postcode":"87111",
    "addr:street":"Stephanie Ne",
    "iso:country":"US",
    "sg:address":"4008 Stephanie NE",
    "sg:city":"Albuquerque",
    "sg:classifiers":[
        {
            "category":"Professional",
            "subcategory":"Computer Services",
            "type":"Services"
        }
    ],
    "sg:phone":"+1 505 296 8512",
    "sg:postcode":"87111",
    "sg:province":"NM",
    "sg:tags":[
        "repair"
    ],
    "wof:name":"Azar's Computer Sales & Svc",
    "wof:placetype":"venue"
},
  "geometry": {"coordinates":[-106.50682,35.128454],"type":"Point"}
}