{
  "type": "Feature",
  "properties": {
    "addr:full":"1460 Trinity Dr Los Alamos NM 87544",
    "addr:housenumber":"1460",
    "addr:postcode":"87544",
    "addr:street":"Trinity Dr",
    "iso:country":"US",
    "sg:address":"1460 Trinity Dr",
    "sg:city":"Los Alamos",
    "sg:classifiers":[
        {
            "category":"Health Services",
            "subcategory":"Health Practitioner",
            "type":"Services"
        }
    ],
    "sg:phone":"+1 505 661 1144",
    "sg:postcode":"87544",
    "sg:province":"NM",
    "sg:tags":[
        "acupuncture"
    ],
    "wof:name":"Acupuncture",
    "wof:placetype":"venue"
},
  "geometry": {"coordinates":[-106.298636,35.879857],"type":"Point"}
}