{
  "type": "Feature",
  "properties": {
    "iso:country":"US",
    "sg:address":"6401 Isleta Blvd SW",
    "sg:city":"Albuquerque",
    "sg:phone":"+1 505 873 4696",
    "sg:postcode":"87105",
    "sg:province":"NM",
    "sg:tags":[
        "farm",
        "crop",
        "general"
    ],
    "wof:name":"Ortiz Farms Inc",
    "wof:placetype":"venue"
},
  "geometry": {"coordinates":[-106.696729,34.976395],"type":"Point"}
}