{
  "type": "Feature",
  "properties": {
    "addr:full":"6208 E Main St Farmington NM 87402",
    "addr:housenumber":"6208",
    "addr:postcode":"87402",
    "addr:street":"E Main St",
    "iso:country":"US",
    "sg:address":"6208 E Main St",
    "sg:city":"Farmington",
    "sg:classifiers":[
        {
            "category":"Home & Garden",
            "subcategory":"Furniture",
            "type":"Retail Goods"
        }
    ],
    "sg:phone":"+1 505 327 6533",
    "sg:postcode":"87402",
    "sg:province":"NM",
    "wof:name":"Freight Direct Furniture",
    "wof:placetype":"venue"
},
  "geometry": {"coordinates":[-108.128636,36.776804],"type":"Point"}
}