{
  "type": "Feature",
  "properties": {
    "iso:country":"US",
    "sg:address":"2912 2nd St NW",
    "sg:city":"Albuquerque",
    "sg:classifiers":[
        {
            "category":"Autos & Motor Vehicles",
            "subcategory":"Automobile Sales",
            "type":"Retail Goods"
        },
        {
            "category":"Wholesale",
            "subcategory":"Scrap",
            "type":"Manufacturing & Wholesale Goods"
        }
    ],
    "sg:phone":"+1 505 269 7098",
    "sg:postcode":"87107",
    "sg:province":"NM",
    "sg:tags":[
        "wrecking",
        "car",
        "truck",
        "new",
        "salvage"
    ],
    "wof:name":"Cabellos Auto Sls & Salvage",
    "wof:placetype":"venue"
},
  "geometry": {"coordinates":[-106.643586,35.113423],"type":"Point"}
}