{
  "type": "Feature",
  "properties": {
    "addr:full":"10254 Coors Byp NW Albuquerque NM 87114",
    "addr:housenumber":"10254",
    "addr:postcode":"87114",
    "addr:street":"Coors Byp Nw",
    "iso:country":"US",
    "sg:address":"10254 Coors Byp NW",
    "sg:city":"Albuquerque",
    "sg:classifiers":[
        {
            "category":"Restaurant",
            "type":"Food & Drink"
        }
    ],
    "sg:menulink":"http://www.allmenus.com/nm/albuquerque/121835-keva-juice/menu/",
    "sg:phone":"+1 505 792 0200",
    "sg:postcode":"87114",
    "sg:province":"NM",
    "sg:tags":[
        "smoothy",
        "juice",
        "american"
    ],
    "wof:name":"Keva Juice",
    "wof:placetype":"venue"
},
  "geometry": {"coordinates":[-106.65959700000001,35.203483],"type":"Point"}
}