{
  "type": "Feature",
  "properties": {
    "addr:full":"925 San Pedro Dr NE Albuquerque NM 87108",
    "addr:housenumber":"925",
    "addr:postcode":"87108",
    "addr:street":"San Pedro Dr Ne",
    "iso:country":"US",
    "sg:address":"925 San Pedro Dr NE",
    "sg:city":"Albuquerque",
    "sg:classifiers":[
        {
            "category":"Restaurant",
            "type":"Food & Drink"
        }
    ],
    "sg:menulink":"http://www.allmenus.com/nm/albuquerque/196373-mcdonalds/menu/",
    "sg:postcode":"87108",
    "sg:province":"NM",
    "sg:tags":[
        "burger",
        "american"
    ],
    "wof:name":"McDonald's",
    "wof:placetype":"venue"
},
  "geometry": {"coordinates":[-106.577459,35.086932],"type":"Point"}
}