{
  "type": "Feature",
  "properties": {
    "iso:country":"US",
    "sg:address":"1819 E 20th St",
    "sg:city":"Farmington",
    "sg:classifiers":[
        {
            "category":"Restaurant",
            "type":"Food & Drink"
        }
    ],
    "sg:phone":"+1 505 324 0001",
    "sg:postcode":"87401",
    "sg:province":"NM",
    "sg:tags":[
        "eating"
    ],
    "wof:name":"Diner Blue Moon",
    "wof:placetype":"venue"
},
  "geometry": {"coordinates":[-108.18225,36.748158],"type":"Point"}
}