{
  "type": "Feature",
  "properties": {
    "iso:country":"US",
    "sg:address":"1021 Mechem Dr",
    "sg:city":"Ruidoso",
    "sg:classifiers":[
        {
            "category":"Retail",
            "subcategory":"Auto Repair",
            "type":"Services"
        }
    ],
    "sg:phone":"+1 505 258 5533",
    "sg:postcode":"88345",
    "sg:province":"NM",
    "sg:tags":[
        "automobile",
        "diagnostic"
    ],
    "wof:name":"Dan Fender Auto Sales",
    "wof:placetype":"venue"
},
  "geometry": {"coordinates":[-105.673109,33.352431],"type":"Point"}
}