{
  "type": "Feature",
  "properties": {
    "iso:country":"US",
    "sg:address":"3918 W Rodeo Rd",
    "sg:city":"Santa Fe",
    "sg:classifiers":[
        {
            "category":"Shopping",
            "subcategory":"Clothing, Apparel, & Fashions",
            "type":"Retail Goods"
        }
    ],
    "sg:phone":"+1 505 424 9330",
    "sg:postcode":"87507",
    "sg:province":"NM",
    "wof:name":"Clint Mortenson",
    "wof:placetype":"venue"
},
  "geometry": {"coordinates":[-106.011447,35.638489],"type":"Point"}
}