{
  "type": "Feature",
  "properties": {
    "iso:country":"US",
    "sg:address":"107 Cll Galisteo",
    "sg:city":"Santa Fe",
    "sg:classifiers":[
        {
            "category":"Education",
            "subcategory":"Special Training",
            "type":"Public Place"
        }
    ],
    "sg:phone":"+1 505 982 1980",
    "sg:postcode":"87508",
    "sg:province":"NM",
    "sg:tags":[
        "self",
        "motivational",
        "improvement"
    ],
    "wof:name":"Life Design Intl",
    "wof:placetype":"venue"
},
  "geometry": {"coordinates":[-106.04386599999999,35.52293],"type":"Point"}
}