{
  "type": "Feature",
  "properties": {
    "iso:country":"US",
    "sg:address":"2825 Candelaria Rd NW",
    "sg:city":"Albuquerque",
    "sg:classifiers":[
        {
            "category":"Professional",
            "subcategory":"Lawyer & Legal Services",
            "type":"Services"
        }
    ],
    "sg:phone":"+1 505 344 1176",
    "sg:postcode":"87107",
    "sg:province":"NM",
    "wof:name":"Jane Marx Attorney At Law PC",
    "wof:placetype":"venue"
},
  "geometry": {"coordinates":[-106.68465,35.129013],"type":"Point"}
}