{
  "type": "Feature",
  "properties": {
    "addr:full":"2403 San Mateo Blvd NE Albuquerque NM 87110",
    "addr:housenumber":"2403",
    "addr:postcode":"87110",
    "addr:street":"San Mateo Blvd Ne",
    "iso:country":"US",
    "sg:address":"2403 San Mateo Blvd NE",
    "sg:city":"Albuquerque",
    "sg:classifiers":[
        {
            "category":"Building & Trades",
            "subcategory":"Electrical",
            "type":"Services"
        }
    ],
    "sg:phone":"+1 505 888 7077",
    "sg:postcode":"87110",
    "sg:province":"NM",
    "sg:tags":[
        "electrical",
        "contractor"
    ],
    "wof:name":"New Mexico Electric Switch",
    "wof:placetype":"venue"
},
  "geometry": {"coordinates":[-106.58725099999999,35.106995],"type":"Point"}
}