{
  "type": "Feature",
  "properties": {
    "iso:country":"US",
    "sg:address":"131 W Walnut St",
    "sg:city":"Roswell",
    "sg:classifiers":[
        {
            "category":"Organizations",
            "subcategory":"Religious Organization",
            "type":"Services"
        }
    ],
    "sg:phone":"+1 505 625 1298",
    "sg:postcode":"88203",
    "sg:province":"NM",
    "wof:name":"Sister Brenda's Ministries Inc",
    "wof:placetype":"venue"
},
  "geometry": {"coordinates":[-104.52396299999999,33.39207],"type":"Point"}
}