{
  "type": "Feature",
  "properties": {
    "iso:country":"US",
    "sg:address":"2529 San Mateo Blvd NE",
    "sg:city":"Albuquerque",
    "sg:classifiers":[
        {
            "category":"Professional",
            "type":"Services"
        }
    ],
    "sg:phone":"+1 505 888 9644",
    "sg:postcode":"87110",
    "sg:province":"NM",
    "sg:tags":[
        "establishment"
    ],
    "wof:name":"Voicestream",
    "wof:placetype":"venue"
},
  "geometry": {"coordinates":[-106.58677,35.107578],"type":"Point"}
}