{
  "type": "Feature",
  "properties": {
    "addr:full":"1925 Aspen Dr Santa Fe NM 87505",
    "addr:housenumber":"1925",
    "addr:postcode":"87505",
    "addr:street":"Aspen Dr",
    "iso:country":"US",
    "sg:address":"1925 Aspen Dr",
    "sg:city":"Santa Fe",
    "sg:classifiers":[
        {
            "category":"Professional",
            "subcategory":"Management & Consulting",
            "type":"Services"
        }
    ],
    "sg:phone":"+1 505 988 3962",
    "sg:postcode":"87505",
    "sg:province":"NM",
    "sg:tags":[
        "financial"
    ],
    "wof:name":"Patrick Flanagan Cfp",
    "wof:placetype":"venue"
},
  "geometry": {"coordinates":[-105.97068899999999,35.655309],"type":"Point"}
}