{
  "type": "Feature",
  "properties": {
    "iso:country":"US",
    "sg:address":"10701 Ranchitos Rd NE",
    "sg:city":"Albuquerque",
    "sg:classifiers":[
        {
            "category":"Building & Trades",
            "subcategory":"Construction",
            "type":"Services"
        }
    ],
    "sg:phone":"+1 505 883 3666",
    "sg:postcode":"87122",
    "sg:province":"NM",
    "sg:tags":[
        "general",
        "contractor"
    ],
    "wof:name":"JAMES BARB CONSTRUCTION",
    "wof:placetype":"venue"
},
  "geometry": {"coordinates":[-106.521929,35.169912],"type":"Point"}
}