{
  "type": "Feature",
  "properties": {
    "addr:full":"1535 Airway Rd SW Albuquerque NM 87105",
    "addr:housenumber":"1535",
    "addr:postcode":"87105",
    "addr:street":"Airway Rd Sw",
    "iso:country":"US",
    "sg:address":"1535 Airway Rd SW",
    "sg:city":"Albuquerque",
    "sg:classifiers":[
        {
            "category":"Building & Trades",
            "subcategory":"Electrical",
            "type":"Services"
        }
    ],
    "sg:phone":"+1 505 242 6787",
    "sg:postcode":"87105",
    "sg:province":"NM",
    "sg:tags":[
        "electric",
        "contractor"
    ],
    "wof:name":"Before Daylite Electric",
    "wof:placetype":"venue"
},
  "geometry": {"coordinates":[-106.679231,35.070256],"type":"Point"}
}