{
  "type": "Feature",
  "properties": {
    "iso:country":"US",
    "sg:address":"401 Conchas St SE",
    "sg:city":"Albuquerque",
    "sg:classifiers":[
        {
            "category":"Autos & Motor Vehicles",
            "subcategory":"Automobile Sales",
            "type":"Retail Goods"
        }
    ],
    "sg:phone":"+1 505 299 8725",
    "sg:postcode":"87123",
    "sg:province":"NM",
    "sg:tags":[
        "wrecker"
    ],
    "wof:name":"East Central Auto Wrecking",
    "wof:placetype":"venue"
},
  "geometry": {"coordinates":[-106.535475,35.068478],"type":"Point"}
}