{
  "type": "Feature",
  "properties": {
    "addr:full":"518 E 2nd St Portales NM 88130",
    "addr:housenumber":"518",
    "addr:postcode":"88130",
    "addr:street":"E 2Nd St",
    "iso:country":"US",
    "sg:address":"518 E 2nd St",
    "sg:city":"Portales",
    "sg:classifiers":[
        {
            "category":"Shopping",
            "subcategory":"Clothing, Apparel, & Fashions",
            "type":"Retail Goods"
        }
    ],
    "sg:phone":"+1 505 356 2680",
    "sg:postcode":"88130",
    "sg:province":"NM",
    "sg:tags":[
        "sportswear"
    ],
    "wof:name":"LA Frontera",
    "wof:placetype":"venue"
},
  "geometry": {"coordinates":[-103.333788,34.187219],"type":"Point"}
}