{
  "type": "Feature",
  "properties": {
    "iso:country":"US",
    "sg:address":"404 Live Oak Loop NE",
    "sg:city":"Albuquerque",
    "sg:classifiers":[
        {
            "category":"Travel",
            "subcategory":"Travel Agent",
            "type":"Entertainment"
        }
    ],
    "sg:phone":"+1 505 856 5050",
    "sg:postcode":"87122",
    "sg:province":"NM",
    "sg:tags":[
        "agency"
    ],
    "wof:name":"Ahrens Travel",
    "wof:placetype":"venue"
},
  "geometry": {"coordinates":[-106.487576,35.176662],"type":"Point"}
}