{
  "type": "Feature",
  "properties": {
    "iso:country":"US",
    "sg:address":"208 N Main St",
    "sg:city":"Roswell",
    "sg:classifiers":[
        {
            "category":"Autos & Motor Vehicles",
            "subcategory":"Auto Supplies",
            "type":"Retail Goods"
        }
    ],
    "sg:phone":"+1 505 625 2205",
    "sg:postcode":"88201",
    "sg:province":"NM",
    "wof:name":"Main Street Market",
    "wof:placetype":"venue"
},
  "geometry": {"coordinates":[-104.522825,33.395291],"type":"Point"}
}