{
  "type": "Feature",
  "properties": {
    "iso:country":"US",
    "sg:address":"5343 Wyoming Blvd NE",
    "sg:city":"Albuquerque",
    "sg:classifiers":[
        {
            "category":"Health Services",
            "subcategory":"Doctor",
            "type":"Services"
        }
    ],
    "sg:phone":"+1 505 822 8777",
    "sg:postcode":"87109",
    "sg:province":"NM",
    "sg:tags":[
        "dentist"
    ],
    "wof:name":"Derek Lines DDS",
    "wof:placetype":"venue"
},
  "geometry": {"coordinates":[-106.551147,35.1407],"type":"Point"}
}