{
  "type": "Feature",
  "properties": {
    "iso:country":"US",
    "sg:address":"3800 N Mesa St",
    "sg:city":"El Paso",
    "sg:classifiers":[
        {
            "category":"Shopping",
            "subcategory":"Bicycles & Sporting Goods",
            "type":"Retail Goods"
        }
    ],
    "sg:phone":"+1 915 542 4949",
    "sg:postcode":"79902",
    "sg:province":"TX",
    "wof:name":"Simply Aerobics",
    "wof:placetype":"venue"
},
  "geometry": {"coordinates":[-106.507609,31.789871],"type":"Point"}
}