{
  "type": "Feature",
  "properties": {
    "iso:country":"US",
    "sg:address":"1808 Axtell St",
    "sg:city":"Clovis",
    "sg:classifiers":[
        {
            "category":"Mining & Drilling",
            "type":"Manufacturing & Wholesale Goods"
        }
    ],
    "sg:phone":"+1 505 769 3462",
    "sg:postcode":"88101",
    "sg:province":"NM",
    "sg:tags":[
        "general",
        "contractor"
    ],
    "wof:name":"Curry Equipment & Services",
    "wof:placetype":"venue"
},
  "geometry": {"coordinates":[-103.20160300000001,34.416275],"type":"Point"}
}