{
  "type": "Feature",
  "properties": {
    "iso:country":"US",
    "sg:address":"711 Maxwell Ave",
    "sg:city":"Springer",
    "sg:classifiers":[
        {
            "category":"Food & Beverages",
            "subcategory":"Liquor & Beverages",
            "type":"Retail Goods"
        }
    ],
    "sg:phone":"+1 505 483 2749",
    "sg:postcode":"87747",
    "sg:province":"NM",
    "wof:name":"Skychief Liquors",
    "wof:placetype":"venue"
},
  "geometry": {"coordinates":[-104.595875,36.364936],"type":"Point"}
}