{
  "type": "Feature",
  "properties": {
    "addr:full":"215 Locust St NE Albuquerque NM 87102",
    "addr:housenumber":"215",
    "addr:postcode":"87102",
    "addr:street":"Locust St Ne",
    "iso:country":"US",
    "sg:address":"215 Locust St NE",
    "sg:city":"Albuquerque",
    "sg:classifiers":[
        {
            "category":"Organizations",
            "subcategory":"Religious Organization",
            "type":"Services"
        }
    ],
    "sg:phone":"+1 505 764 2900",
    "sg:postcode":"87102",
    "sg:province":"NM",
    "sg:tags":[
        "child",
        "day",
        "care"
    ],
    "sg:website":"www.firstpresabq.org",
    "wof:name":"First Presbyterian Church",
    "wof:placetype":"venue"
},
  "geometry": {"coordinates":[-106.63711000000001,35.08428],"type":"Point"}
}