{
  "type": "Feature",
  "properties": {
    "iso:country":"US",
    "sg:address":"1103 S 2nd St",
    "sg:city":"Raton",
    "sg:classifiers":[
        {
            "category":"Banks & Credit Unions",
            "subcategory":"Bank",
            "type":"Services"
        }
    ],
    "sg:phone":"+1 505 445 2713",
    "sg:postcode":"87740",
    "sg:province":"NM",
    "sg:tags":[
        "national",
        "commercial"
    ],
    "wof:name":"Wells Fargo",
    "wof:placetype":"venue"
},
  "geometry": {"coordinates":[-104.440161,36.887396],"type":"Point"}
}