{
  "type": "Feature",
  "properties": {
    "addr:full":"417 Menaul Blvd NW Albuquerque NM 87107",
    "addr:housenumber":"417",
    "addr:postcode":"87107",
    "addr:street":"Menaul Blvd Nw",
    "iso:country":"US",
    "sg:address":"417 Menaul Blvd NW",
    "sg:city":"Albuquerque",
    "sg:classifiers":[
        {
            "category":"Retail",
            "subcategory":"Auto Repair",
            "type":"Services"
        }
    ],
    "sg:phone":"+1 505 344 4260",
    "sg:postcode":"87107",
    "sg:province":"NM",
    "sg:tags":[
        "body",
        "automobile",
        "painting"
    ],
    "wof:name":"Rightway Collision",
    "wof:placetype":"venue"
},
  "geometry": {"coordinates":[-106.647436,35.111133],"type":"Point"}
}