{
  "type": "Feature",
  "properties": {
    "addr:full":"1614 Pso de Peralta Santa Fe NM 87501",
    "addr:housenumber":"1614",
    "addr:postcode":"87501",
    "addr:street":"Pso De Peralta",
    "iso:country":"US",
    "sg:address":"1614 Pso de Peralta",
    "sg:city":"Santa Fe",
    "sg:classifiers":[
        {
            "category":"Museum",
            "type":"Entertainment"
        }
    ],
    "sg:phone":"+1 505 989 4423",
    "sg:postcode":"87501",
    "sg:province":"NM",
    "sg:tags":[
        "arts",
        "center"
    ],
    "wof:name":"Warehouse 21",
    "wof:placetype":"venue"
},
  "geometry": {"coordinates":[-105.948499,35.681774],"type":"Point"}
}