{
  "type": "Feature",
  "properties": {
    "iso:country":"US",
    "sg:address":"435 Saint Michaels Dr",
    "sg:city":"Santa Fe",
    "sg:classifiers":[
        {
            "category":"Health Services",
            "subcategory":"Optometrist",
            "type":"Services"
        }
    ],
    "sg:phone":"+1 505 983 6613",
    "sg:postcode":"87505",
    "sg:province":"NM",
    "wof:name":"Jason H Juba OD",
    "wof:placetype":"venue"
},
  "geometry": {"coordinates":[-105.943349,35.656454],"type":"Point"}
}