{
  "type": "Feature",
  "properties": {
    "iso:country":"US",
    "sg:address":"1418 US Hwy 180 E",
    "sg:city":"Silver City",
    "sg:classifiers":[
        {
            "category":"Restaurant",
            "type":"Food & Drink"
        }
    ],
    "sg:phone":"+1 505 534 1955",
    "sg:postcode":"88061",
    "sg:province":"NM",
    "sg:tags":[
        "eating"
    ],
    "wof:name":"Burger King",
    "wof:placetype":"venue"
},
  "geometry": {"coordinates":[-108.26558900000001,32.783209],"type":"Point"}
}