{
  "type": "Feature",
  "properties": {
    "iso:country":"US",
    "sg:address":"700 Dawn Loop",
    "sg:city":"Clovis",
    "sg:classifiers":[
        {
            "category":"Freight",
            "type":"Transportation"
        }
    ],
    "sg:phone":"+1 505 762 0132",
    "sg:postcode":"88101",
    "sg:province":"NM",
    "sg:tags":[
        "delivery",
        "package"
    ],
    "wof:name":"Fedex",
    "wof:placetype":"venue"
},
  "geometry": {"coordinates":[-103.200005,34.386635],"type":"Point"}
}