{
  "type": "Feature",
  "properties": {
    "iso:country":"US",
    "sg:address":"1200 W 2nd St",
    "sg:city":"Roswell",
    "sg:classifiers":[
        {
            "category":"Autos & Motor Vehicles",
            "subcategory":"Auto Supplies",
            "type":"Retail Goods"
        }
    ],
    "sg:phone":"+1 505 622 7791",
    "sg:postcode":"88201",
    "sg:province":"NM",
    "sg:tags":[
        "automobile",
        "stereo",
        "radio"
    ],
    "wof:name":"Car Tunes & Tint",
    "wof:placetype":"venue"
},
  "geometry": {"coordinates":[-104.540395,33.394197],"type":"Point"}
}