{
  "type": "Feature",
  "properties": {
    "iso:country":"US",
    "sg:address":"2929 Barcelona Rd SW",
    "sg:city":"Albuquerque",
    "sg:classifiers":[
        {
            "category":"Social Services",
            "type":"Services"
        }
    ],
    "sg:phone":"+1 505 877 0371",
    "sg:postcode":"87105",
    "sg:province":"NM",
    "wof:name":"Amistatad Crisis Shelter",
    "wof:placetype":"venue"
},
  "geometry": {"coordinates":[-106.7014,35.030639],"type":"Point"}
}