{
  "type": "Feature",
  "properties": {
    "addr:full":"7605 Eagle Ave NW Albuquerque NM 87114",
    "addr:housenumber":"7605",
    "addr:postcode":"87114",
    "addr:street":"Eagle Ave Nw",
    "iso:country":"US",
    "sg:address":"7605 Eagle Ave NW",
    "sg:city":"Albuquerque",
    "sg:classifiers":[
        {
            "category":"Social Services",
            "subcategory":"Child Care",
            "type":"Services"
        }
    ],
    "sg:phone":"+1 505 440 7472",
    "sg:postcode":"87114",
    "sg:province":"NM",
    "wof:name":"Jennifer A Gutierrez Child Cr",
    "wof:placetype":"venue"
},
  "geometry": {"coordinates":[-106.743287,35.197584],"type":"Point"}
}