{
  "type": "Feature",
  "properties": {
    "addr:full":"3502 McNutt Rd Sunland Park NM 88063",
    "addr:housenumber":"3502",
    "addr:postcode":"88063",
    "addr:street":"Mcnutt Rd",
    "iso:country":"US",
    "sg:address":"3502 McNutt Rd",
    "sg:city":"Sunland Park",
    "sg:classifiers":[
        {
            "category":"Social Services",
            "type":"Services"
        }
    ],
    "sg:phone":"+1 505 589 1653",
    "sg:postcode":"88063",
    "sg:province":"NM",
    "sg:tags":[
        "youth",
        "organization",
        "center",
        "welfare"
    ],
    "wof:name":"Families & Youth Inc Child",
    "wof:placetype":"venue"
},
  "geometry": {"coordinates":[-106.544648,31.800982],"type":"Point"}
}