{
  "type": "Feature",
  "properties": {
    "iso:country":"US",
    "sg:address":"610 Central Ave",
    "sg:city":"Los Alamos",
    "sg:classifiers":[
        {
            "category":"Autos & Motor Vehicles",
            "subcategory":"Auto Supplies",
            "type":"Retail Goods"
        }
    ],
    "sg:phone":"+1 505 663 0903",
    "sg:postcode":"87544",
    "sg:province":"NM",
    "sg:tags":[
        "automobile",
        "parts"
    ],
    "wof:name":"Autozone",
    "wof:placetype":"venue"
},
  "geometry": {"coordinates":[-106.295103,35.881314],"type":"Point"}
}