{
  "type": "Feature",
  "properties": {
    "iso:country":"US",
    "sg:address":"2109 Malpais Rd SW",
    "sg:city":"Albuquerque",
    "sg:classifiers":[
        {
            "category":"Retail",
            "subcategory":"Repair Shop",
            "type":"Services"
        },
        {
            "category":"Building & Trades",
            "subcategory":"Plumbing",
            "type":"Services"
        }
    ],
    "sg:phone":"+1 505 877 4907",
    "sg:postcode":"87105",
    "sg:province":"NM",
    "sg:tags":[
        "septic"
    ],
    "wof:name":"Castillos Septic Tank Cleaning",
    "wof:placetype":"venue"
},
  "geometry": {"coordinates":[-106.69931099999999,34.951058],"type":"Point"}
}