{
  "type": "Feature",
  "properties": {
    "iso:country":"US",
    "sg:address":"2400 Central Ave SE",
    "sg:city":"Albuquerque",
    "sg:classifiers":[
        {
            "category":"Restaurant",
            "type":"Food & Drink"
        }
    ],
    "sg:phone":"+1 505 266 0550",
    "sg:postcode":"87106",
    "sg:province":"NM",
    "sg:tags":[
        "eating"
    ],
    "sg:website":"www.frontierrestaurant.com",
    "wof:name":"Frontier Restaurant",
    "wof:placetype":"venue"
},
  "geometry": {"coordinates":[-106.618269,35.08099],"type":"Point"}
}