{
  "type": "Feature",
  "properties": {
    "addr:full":"3815 S Main St Mesilla Park NM 88047",
    "addr:housenumber":"3815",
    "addr:postcode":"88047",
    "addr:street":"S Main St;Park",
    "iso:country":"US",
    "sg:address":"3815 S Main St",
    "sg:city":"Mesilla Park",
    "sg:classifiers":[
        {
            "category":"Real Estate",
            "subcategory":"Developer",
            "type":"Services"
        }
    ],
    "sg:phone":"+1 505 524 2037",
    "sg:postcode":"88047",
    "sg:province":"NM",
    "sg:tags":[
        "mobile",
        "home"
    ],
    "wof:name":"Dove Canyon",
    "wof:placetype":"venue"
},
  "geometry": {"coordinates":[-106.76282999999999,32.269521],"type":"Point"}
}