{
  "type": "Feature",
  "properties": {
    "iso:country":"US",
    "sg:address":"5 Bayou Ct",
    "sg:city":"Roswell",
    "sg:classifiers":[
        {
            "category":"Shopping",
            "subcategory":"Computers & Home Electronics",
            "type":"Retail Goods"
        }
    ],
    "sg:phone":"+1 505 625 9327",
    "sg:postcode":"88201",
    "sg:province":"NM",
    "sg:tags":[
        "publishing"
    ],
    "wof:name":"Mbar Publishing",
    "wof:placetype":"venue"
},
  "geometry": {"coordinates":[-104.535653,33.436846],"type":"Point"}
}