{
  "type": "Feature",
  "properties": {
    "iso:country":"US",
    "sg:address":"2501 E Aztec Ave",
    "sg:city":"Gallup",
    "sg:classifiers":[
        {
            "category":"Retail",
            "subcategory":"Auto Repair",
            "type":"Services"
        }
    ],
    "sg:phone":"+1 505 722 5162",
    "sg:postcode":"87301",
    "sg:province":"NM",
    "sg:tags":[
        "repairing",
        "automobile"
    ],
    "wof:name":"Gallup Transmissions",
    "wof:placetype":"venue"
},
  "geometry": {"coordinates":[-108.70396,35.527744],"type":"Point"}
}