{
  "type": "Feature",
  "properties": {
    "iso:country":"US",
    "sg:address":"806 Alvarado Ave",
    "sg:city":"Artesia",
    "sg:classifiers":[
        {
            "category":"Building & Trades",
            "subcategory":"Construction",
            "type":"Services"
        }
    ],
    "sg:phone":"+1 505 746 3114",
    "sg:postcode":"88210",
    "sg:province":"NM",
    "sg:tags":[
        "concrete",
        "contractor"
    ],
    "wof:name":"Rogo Concrete Construction",
    "wof:placetype":"venue"
},
  "geometry": {"coordinates":[-104.407574,32.854012],"type":"Point"}
}