{
  "type": "Feature",
  "properties": {
    "addr:full":"2624 Dakota St NE Albuquerque NM 87110",
    "addr:housenumber":"2624",
    "addr:postcode":"87110",
    "addr:street":"Dakota St Ne",
    "iso:country":"US",
    "sg:address":"2624 Dakota St NE",
    "sg:city":"Albuquerque",
    "sg:classifiers":[
        {
            "category":"Building & Trades",
            "subcategory":"Equipment Rental",
            "type":"Services"
        }
    ],
    "sg:phone":"+1 505 205 1185",
    "sg:postcode":"87110",
    "sg:province":"NM",
    "sg:tags":[
        "party",
        "supply"
    ],
    "wof:name":"Skorpion Jumpers",
    "wof:placetype":"venue"
},
  "geometry": {"coordinates":[-106.574162,35.110501],"type":"Point"}
}