{
  "type": "Feature",
  "properties": {
    "iso:country":"US",
    "sg:address":"1408 N Hudson St",
    "sg:city":"Silver City",
    "sg:classifiers":[
        {
            "category":"Shopping",
            "subcategory":"Tobacco",
            "type":"Retail Goods"
        }
    ],
    "sg:phone":"+1 505 388 5575",
    "sg:postcode":"88061",
    "sg:province":"NM",
    "sg:tags":[
        "product"
    ],
    "wof:name":"Smoke Shop",
    "wof:placetype":"venue"
},
  "geometry": {"coordinates":[-108.273307,32.781262],"type":"Point"}
}