{
  "type": "Feature",
  "properties": {
    "iso:country":"US",
    "sg:address":"9633 Montgomery Blvd NE",
    "sg:city":"Albuquerque",
    "sg:classifiers":[
        {
            "category":"Autos & Motor Vehicles",
            "subcategory":"Fuel & Gas Station",
            "type":"Retail Goods"
        }
    ],
    "sg:phone":"+1 505 292 3868",
    "sg:postcode":"87111",
    "sg:province":"NM",
    "sg:tags":[
        "oil"
    ],
    "wof:name":"M & E Chevron Redi-Mart",
    "wof:placetype":"venue"
},
  "geometry": {"coordinates":[-106.533664,35.130721],"type":"Point"}
}