{
  "type": "Feature",
  "properties": {
    "iso:country":"US",
    "sg:address":"9108 Woodland Ave NE",
    "sg:city":"Albuquerque",
    "sg:classifiers":[
        {
            "category":"Social Services",
            "subcategory":"Child Care",
            "type":"Services"
        }
    ],
    "sg:phone":"+1 505 296 2880",
    "sg:postcode":"87112",
    "sg:province":"NM",
    "sg:tags":[
        "day"
    ],
    "wof:name":"Childrens Choice Child",
    "wof:placetype":"venue"
},
  "geometry": {"coordinates":[-106.53936,35.109996],"type":"Point"}
}