{
  "type": "Feature",
  "properties": {
    "iso:country":"US",
    "sg:address":"11825 US Hwy 180 E",
    "sg:city":"Arenas Valley",
    "sg:classifiers":[
        {
            "category":"Retail",
            "subcategory":"Auto Repair",
            "type":"Services"
        }
    ],
    "sg:phone":"+1 505 538 5482",
    "sg:postcode":"88022",
    "sg:province":"NM",
    "sg:tags":[
        "body",
        "automobile",
        "painting"
    ],
    "wof:name":"Vern's Body Shop",
    "wof:placetype":"venue"
},
  "geometry": {"coordinates":[-108.189538,32.780729],"type":"Point"}
}