{
  "type": "Feature",
  "properties": {
    "iso:country":"US",
    "sg:address":"188 Airport Rd",
    "sg:city":"Hurley",
    "sg:classifiers":[
        {
            "category":"Airport",
            "type":"Transportation"
        }
    ],
    "sg:phone":"+1 505 388 4554",
    "sg:postcode":"88043",
    "sg:province":"NM",
    "wof:name":"Grant County Airport",
    "wof:placetype":"venue"
},
  "geometry": {"coordinates":[-108.15821699999999,32.630089],"type":"Point"}
}