{
  "type": "Feature",
  "properties": {
    "iso:country":"US",
    "sg:address":"3281 Cerrillos Rd",
    "sg:city":"Santa Fe",
    "sg:classifiers":[
        {
            "category":"Autos & Motor Vehicles",
            "subcategory":"Automobile Sales",
            "type":"Retail Goods"
        }
    ],
    "sg:phone":"+1 505 473 4852",
    "sg:postcode":"87507",
    "sg:province":"NM",
    "sg:tags":[
        "car",
        "dealer"
    ],
    "wof:name":"Best Used Cars",
    "wof:placetype":"venue"
},
  "geometry": {"coordinates":[-105.997577,35.651807],"type":"Point"}
}