{
  "type": "Feature",
  "properties": {
    "iso:country":"US",
    "sg:address":"131 W San Francisco St",
    "sg:city":"Santa Fe",
    "sg:classifiers":[
        {
            "category":"Shopping",
            "type":"Retail Goods"
        }
    ],
    "sg:phone":"+1 505 982 5328",
    "sg:postcode":"87501",
    "sg:province":"NM",
    "sg:tags":[
        "art",
        "gallery",
        "dealer"
    ],
    "sg:website":"www.clinefineart.com",
    "wof:name":"Cline Fine Art",
    "wof:placetype":"venue"
},
  "geometry": {"coordinates":[-105.94175,35.687935],"type":"Point"}
}