{
  "type": "Feature",
  "properties": {
    "iso:country":"US",
    "sg:address":"4583 Corrales Rd",
    "sg:city":"Corrales",
    "sg:classifiers":[
        {
            "category":"Professional",
            "subcategory":"Management & Consulting",
            "type":"Services"
        }
    ],
    "sg:phone":"+1 505 343 8770",
    "sg:postcode":"87048",
    "sg:province":"NM",
    "sg:tags":[
        "marketing",
        "consultant"
    ],
    "wof:name":"Third Moon Gallery",
    "wof:placetype":"venue"
},
  "geometry": {"coordinates":[-106.61411699999999,35.226072],"type":"Point"}
}