{
  "type": "Feature",
  "properties": {
    "iso:country":"US",
    "sg:address":"721 7th St",
    "sg:city":"Las Vegas",
    "sg:classifiers":[
        {
            "category":"Health Services",
            "subcategory":"Clinic",
            "type":"Services"
        }
    ],
    "sg:phone":"+1 505 387 2620",
    "sg:postcode":"87701",
    "sg:province":"NM",
    "sg:tags":[
        "hypnotherapy"
    ],
    "wof:name":"Hilary Bennet",
    "wof:placetype":"venue"
},
  "geometry": {"coordinates":[-105.217119,35.595722],"type":"Point"}
}