{
  "type": "Feature",
  "properties": {
    "addr:full":"38 Isabelita Rd Tijeras NM 87059",
    "addr:housenumber":"38",
    "addr:postcode":"87059",
    "addr:street":"Isabelita Rd",
    "iso:country":"US",
    "sg:address":"38 Isabelita Rd",
    "sg:city":"Tijeras",
    "sg:classifiers":[
        {
            "category":"Building & Trades",
            "subcategory":"Construction",
            "type":"Services"
        }
    ],
    "sg:phone":"+1 505 286 0806",
    "sg:postcode":"87059",
    "sg:province":"NM",
    "sg:tags":[
        "house"
    ],
    "wof:name":"Decosta Construction",
    "wof:placetype":"venue"
},
  "geometry": {"coordinates":[-106.279875,34.960804],"type":"Point"}
}