{
  "type": "Feature",
  "properties": {
    "iso:country":"US",
    "sg:address":"3 Torneo Ct",
    "sg:city":"Santa Fe",
    "sg:classifiers":[
        {
            "category":"Professional",
            "subcategory":"Business Services",
            "type":"Services"
        }
    ],
    "sg:phone":"+1 505 466 2586",
    "sg:postcode":"87508",
    "sg:province":"NM",
    "wof:name":"Sylvias Business Services",
    "wof:placetype":"venue"
},
  "geometry": {"coordinates":[-105.90688900000001,35.546957],"type":"Point"}
}