{
  "type": "Feature",
  "properties": {
    "iso:country":"US",
    "sg:address":"1313 E University Ave",
    "sg:city":"Las Cruces",
    "sg:classifiers":[
        {
            "category":"Organizations",
            "subcategory":"Religious Organization",
            "type":"Services"
        }
    ],
    "sg:phone":"+1 505 522 7370",
    "sg:postcode":"88001",
    "sg:province":"NM",
    "sg:tags":[
        "church"
    ],
    "wof:name":"Baptist Student Union Inc",
    "wof:placetype":"venue"
},
  "geometry": {"coordinates":[-106.751468,32.2851],"type":"Point"}
}