{
  "type": "Feature",
  "properties": {
    "addr:full":"8215 William Moyers Ave NE Albuquerque NM 87122",
    "addr:housenumber":"8215",
    "addr:postcode":"87122",
    "addr:street":"William Moyers Ave Ne",
    "iso:country":"US",
    "sg:address":"8215 William Moyers Ave NE",
    "sg:city":"Albuquerque",
    "sg:classifiers":[
        {
            "category":"Personal",
            "subcategory":"Beauty Salon",
            "type":"Services"
        }
    ],
    "sg:phone":"+1 505 823 4420",
    "sg:postcode":"87122",
    "sg:province":"NM",
    "sg:tags":[
        "shop"
    ],
    "wof:name":"Classic Touch",
    "wof:placetype":"venue"
},
  "geometry": {"coordinates":[-106.55374500000001,35.18501],"type":"Point"}
}