{
  "type": "Feature",
  "properties": {
    "addr:full":"192 Pso de la Tierra Santa Fe NM 87506",
    "addr:housenumber":"192",
    "addr:postcode":"87506",
    "addr:street":"Pso De La Tierra",
    "iso:country":"US",
    "sg:address":"192 Pso de la Tierra",
    "sg:city":"Santa Fe",
    "sg:classifiers":[
        {
            "category":"Professional",
            "type":"Services"
        }
    ],
    "sg:phone":"+1 505 984 2996",
    "sg:postcode":"87506",
    "sg:province":"NM",
    "wof:name":"Centava",
    "wof:placetype":"venue"
},
  "geometry": {"coordinates":[-106.027092,35.722026],"type":"Point"}
}