{
  "type": "Feature",
  "properties": {
    "iso:country":"US",
    "sg:address":"1500 S Main St",
    "sg:city":"Roswell",
    "sg:classifiers":[
        {
            "category":"Organizations",
            "subcategory":"Religious Organization",
            "type":"Services"
        }
    ],
    "sg:phone":"+1 505 623 1182",
    "sg:postcode":"88203",
    "sg:province":"NM",
    "sg:tags":[
        "preschool",
        "church"
    ],
    "wof:name":"Child Garden School",
    "wof:placetype":"venue"
},
  "geometry": {"coordinates":[-104.52296699999999,33.376388],"type":"Point"}
}