{
  "type": "Feature",
  "properties": {
    "iso:country":"US",
    "sg:address":"5120 Pastura Pl NW",
    "sg:city":"Albuquerque",
    "sg:classifiers":[
        {
            "category":"Personal",
            "subcategory":"Beauty Salon",
            "type":"Services"
        }
    ],
    "sg:phone":"+1 505 344 9468",
    "sg:postcode":"87107",
    "sg:province":"NM",
    "sg:tags":[
        "shop"
    ],
    "wof:name":"Brandis Hair Designs",
    "wof:placetype":"venue"
},
  "geometry": {"coordinates":[-106.64940900000001,35.134134],"type":"Point"}
}