{
  "type": "Feature",
  "properties": {
    "iso:country":"US",
    "sg:address":"149 E Alameda St",
    "sg:city":"Santa Fe",
    "sg:classifiers":[
        {
            "category":"Professional",
            "subcategory":"Business Services",
            "type":"Services"
        }
    ],
    "sg:phone":"+1 505 984 8399",
    "sg:postcode":"87501",
    "sg:province":"NM",
    "sg:tags":[
        "appraiser"
    ],
    "wof:name":"Leslie Trilling Appraiser",
    "wof:placetype":"venue"
},
  "geometry": {"coordinates":[-105.937923,35.684971],"type":"Point"}
}