{
  "type": "Feature",
  "properties": {
    "iso:country":"US",
    "sg:address":"1001 S Chicago Ave",
    "sg:city":"Portales",
    "sg:classifiers":[
        {
            "category":"Manufacturing",
            "subcategory":"Toys & Sporting Goods",
            "type":"Manufacturing & Wholesale Goods"
        }
    ],
    "sg:phone":"+1 505 356 5504",
    "sg:postcode":"88130",
    "sg:province":"NM",
    "sg:tags":[
        "mfg"
    ],
    "wof:name":"Agape Toys & Furniture",
    "wof:placetype":"venue"
},
  "geometry": {"coordinates":[-103.327417,34.181961],"type":"Point"}
}