{
  "type": "Feature",
  "properties": {
    "iso:country":"US",
    "sg:address":"2633 Dakota St NE",
    "sg:city":"Albuquerque",
    "sg:classifiers":[
        {
            "category":"Organizations",
            "subcategory":"Religious Organization",
            "type":"Services"
        }
    ],
    "sg:phone":"+1 505 881 4517",
    "sg:postcode":"87110",
    "sg:province":"NM",
    "sg:tags":[
        "church"
    ],
    "wof:name":"Dakota Street Church Of God",
    "wof:placetype":"venue"
},
  "geometry": {"coordinates":[-106.57431200000001,35.110349],"type":"Point"}
}