{
  "type": "Feature",
  "properties": {
    "iso:country":"US",
    "sg:address":"700 S Telshor Blvd",
    "sg:city":"Las Cruces",
    "sg:classifiers":[
        {
            "category":"Shopping",
            "type":"Retail Goods"
        }
    ],
    "sg:phone":"+1 505 522 7387",
    "sg:postcode":"88011",
    "sg:province":"NM",
    "sg:tags":[
        "pet",
        "shop",
        "merchandise"
    ],
    "wof:name":"Jerry's Perfect Pet Shop",
    "wof:placetype":"venue"
},
  "geometry": {"coordinates":[-106.740977,32.310818],"type":"Point"}
}