{
  "type": "Feature",
  "properties": {
    "iso:country":"US",
    "sg:address":"101 S 4th St",
    "sg:city":"Jal",
    "sg:classifiers":[
        {
            "category":"Utilities",
            "subcategory":"Natural Gas",
            "type":"Services"
        }
    ],
    "sg:phone":"+1 505 395 2141",
    "sg:postcode":"88252",
    "sg:province":"NM",
    "sg:tags":[
        "company"
    ],
    "wof:name":"Zia Gas Co",
    "wof:placetype":"venue"
},
  "geometry": {"coordinates":[-103.194544,32.115874],"type":"Point"}
}