{
  "type": "Feature",
  "properties": {
    "iso:country":"US",
    "sg:address":"2600 W Main St",
    "sg:city":"Farmington",
    "sg:classifiers":[
        {
            "category":"Building & Trades",
            "subcategory":"Construction",
            "type":"Services"
        }
    ],
    "sg:phone":"+1 505 325 7568",
    "sg:postcode":"87401",
    "sg:province":"NM",
    "wof:name":"Essco Pipe & Supply",
    "wof:placetype":"venue"
},
  "geometry": {"coordinates":[-108.243776,36.733163],"type":"Point"}
}