{
  "type": "Feature",
  "properties": {
    "addr:full":"822 Clayton Rd Raton NM 87740",
    "addr:housenumber":"822",
    "addr:postcode":"87740",
    "addr:street":"Clayton Rd",
    "iso:country":"US",
    "sg:address":"822 Clayton Rd",
    "sg:city":"Raton",
    "sg:phone":"+1 505 445 9182",
    "sg:postcode":"87740",
    "sg:province":"NM",
    "sg:tags":[
        "petroleum",
        "product",
        "station",
        "gasoline"
    ],
    "sg:website":"www.wilsoncorp.com",
    "wof:name":"Wilson Corp",
    "wof:placetype":"venue"
},
  "geometry": {"coordinates":[-104.426334,36.884931],"type":"Point"}
}