{
  "type": "Feature",
  "properties": {
    "iso:country":"US",
    "sg:address":"407 Cam del Bosque NW",
    "sg:city":"Albuquerque",
    "sg:classifiers":[
        {
            "category":"Sports & Exercise",
            "subcategory":"Bowling",
            "type":"Entertainment"
        }
    ],
    "sg:phone":"+1 505 897 0177",
    "sg:postcode":"87114",
    "sg:province":"NM",
    "sg:tags":[
        "center"
    ],
    "wof:name":"Lucky 66 Bowl Inc",
    "wof:placetype":"venue"
},
  "geometry": {"coordinates":[-106.622818,35.202813],"type":"Point"}
}