{
  "type": "Feature",
  "properties": {
    "iso:country":"US",
    "sg:address":"3204 Mercantile Ct",
    "sg:city":"Santa Fe",
    "sg:classifiers":[
        {
            "category":"Social Services",
            "type":"Services"
        }
    ],
    "sg:phone":"+1 505 424 1800",
    "sg:postcode":"87507",
    "sg:province":"NM",
    "sg:tags":[
        "organization",
        "welfare"
    ],
    "wof:name":"Gerard's House",
    "wof:placetype":"venue"
},
  "geometry": {"coordinates":[-105.999504,35.655999],"type":"Point"}
}