{
  "type": "Feature",
  "properties": {
    "iso:country":"US",
    "sg:address":"4 Rd 6351",
    "sg:city":"Kirtland",
    "sg:classifiers":[
        {
            "category":"Building & Trades",
            "subcategory":"Construction",
            "type":"Services"
        }
    ],
    "sg:phone":"+1 505 598 4112",
    "sg:postcode":"87417",
    "sg:province":"NM",
    "sg:tags":[
        "hanging",
        "contractor"
    ],
    "wof:name":"Intermountain Painting Inc",
    "wof:placetype":"venue"
},
  "geometry": {"coordinates":[-108.353431,36.735285],"type":"Point"}
}