{
  "type": "Feature",
  "properties": {
    "iso:country":"US",
    "sg:address":"225 Wheeler Ave",
    "sg:city":"Texico",
    "sg:classifiers":[
        {
            "category":"Food & Beverages",
            "subcategory":"Groceries & Convenience Stores",
            "type":"Retail Goods"
        }
    ],
    "sg:phone":"+1 505 482 9313",
    "sg:postcode":"88135",
    "sg:province":"NM",
    "wof:name":"Town & Country Food Store 150",
    "wof:placetype":"venue"
},
  "geometry": {"coordinates":[-103.059974,34.388765],"type":"Point"}
}