{
  "type": "Feature",
  "properties": {
    "iso:country":"US",
    "sg:address":"2901 Juan Tabo Blvd NE",
    "sg:city":"Albuquerque",
    "sg:classifiers":[
        {
            "category":"Banks & Credit Unions",
            "subcategory":"Bank",
            "type":"Services"
        }
    ],
    "sg:phone":"+1 505 292 4900",
    "sg:postcode":"87112",
    "sg:province":"NM",
    "sg:tags":[
        "loan",
        "mortgage",
        "real estate"
    ],
    "wof:name":"New Century Mortgage Corp",
    "wof:placetype":"venue"
},
  "geometry": {"coordinates":[-106.515756,35.114938],"type":"Point"}
}