{
  "type": "Feature",
  "properties": {
    "iso:country":"US",
    "sg:address":"4600 E Main St",
    "sg:city":"Farmington",
    "sg:classifiers":[
        {
            "category":"Utilities",
            "subcategory":"Mobile Phone",
            "type":"Services"
        }
    ],
    "sg:phone":"+1 505 566 4620",
    "sg:postcode":"87402",
    "sg:province":"NM",
    "sg:tags":[
        "communication",
        "radiotelephone"
    ],
    "wof:name":"Hooked Up Cellular",
    "wof:placetype":"venue"
},
  "geometry": {"coordinates":[-108.15313500000001,36.764701],"type":"Point"}
}