{
  "type": "Feature",
  "properties": {
    "iso:country":"US",
    "sg:address":"1920 Cerrillos Rd",
    "sg:city":"Santa Fe",
    "sg:classifiers":[
        {
            "category":"Government",
            "subcategory":"Office",
            "type":"Public Place"
        }
    ],
    "sg:phone":"+1 505 955 2700",
    "sg:postcode":"87505",
    "sg:province":"NM",
    "sg:tags":[
        "village"
    ],
    "wof:name":"Santa Fe Animal Control",
    "wof:placetype":"venue"
},
  "geometry": {"coordinates":[-105.974865,35.663767],"type":"Point"}
}