{
  "type": "Feature",
  "properties": {
    "addr:full":"1015 Rio Grande Blvd NW Albuquerque NM 87104",
    "addr:housenumber":"1015",
    "addr:postcode":"87104",
    "addr:street":"Rio Grande Blvd Nw",
    "iso:country":"US",
    "sg:address":"1015 Rio Grande Blvd NW",
    "sg:city":"Albuquerque",
    "sg:classifiers":[
        {
            "category":"Travel",
            "subcategory":"Hotels & Motels",
            "type":"Entertainment"
        }
    ],
    "sg:phone":"+1 505 843 9500",
    "sg:postcode":"87104",
    "sg:province":"NM",
    "sg:tags":[
        "operation"
    ],
    "wof:name":"Best Western",
    "wof:placetype":"venue"
},
  "geometry": {"coordinates":[-106.670748,35.103508],"type":"Point"}
}