{
  "type": "Feature",
  "properties": {
    "iso:country":"US",
    "sg:address":"17502 Hwy 4",
    "sg:city":"Jemez Springs",
    "sg:classifiers":[
        {
            "category":"Shopping",
            "type":"Retail Goods"
        },
        {
            "category":"Shopping",
            "subcategory":"Gifts & Souvenirs",
            "type":"Retail Goods"
        }
    ],
    "sg:phone":"+1 505 829 3956",
    "sg:postcode":"87025",
    "sg:province":"NM",
    "sg:tags":[
        "shop",
        "merchandise"
    ],
    "wof:name":"Jemez Mountain Trading Company",
    "wof:placetype":"venue"
},
  "geometry": {"coordinates":[-106.69172399999999,35.769541],"type":"Point"}
}