{
  "type": "Feature",
  "properties": {
    "iso:country":"US",
    "sg:address":"6020 Silver Leaf Trl NE",
    "sg:city":"Albuquerque",
    "sg:classifiers":[
        {
            "category":"Building & Trades",
            "subcategory":"Electrical",
            "type":"Services"
        }
    ],
    "sg:phone":"+1 505 890 0320",
    "sg:postcode":"87111",
    "sg:province":"NM",
    "sg:tags":[
        "electrical",
        "contractor"
    ],
    "wof:name":"Whitaker Electric",
    "wof:placetype":"venue"
},
  "geometry": {"coordinates":[-106.496194,35.149145],"type":"Point"}
}