{
  "type": "Feature",
  "properties": {
    "iso:country":"US",
    "sg:address":"425 S Telshor Blvd",
    "sg:city":"Las Cruces",
    "sg:classifiers":[
        {
            "category":"Banks & Credit Unions",
            "subcategory":"Bank",
            "type":"Services"
        }
    ],
    "sg:phone":"+1 505 521 6883",
    "sg:postcode":"88011",
    "sg:province":"NM",
    "wof:name":"Wells Fargo Bank",
    "wof:placetype":"venue"
},
  "geometry": {"coordinates":[-106.747893,32.317285],"type":"Point"}
}