{
  "type": "Feature",
  "properties": {
    "iso:country":"US",
    "sg:address":"11012 Prospect Ave NE",
    "sg:city":"Albuquerque",
    "sg:classifiers":[
        {
            "category":"Building & Trades",
            "subcategory":"Construction",
            "type":"Services"
        }
    ],
    "sg:phone":"+1 505 401 4186",
    "sg:postcode":"87112",
    "sg:province":"NM",
    "sg:tags":[
        "general",
        "contractor"
    ],
    "wof:name":"High Mesa Enterprises",
    "wof:placetype":"venue"
},
  "geometry": {"coordinates":[-106.518772,35.107169],"type":"Point"}
}