{
  "type": "Feature",
  "properties": {
    "iso:country":"US",
    "sg:address":"6125 4th St NW",
    "sg:city":"Albuquerque",
    "sg:classifiers":[
        {
            "category":"Professional",
            "subcategory":"Accounting & Tax Preparation",
            "type":"Services"
        }
    ],
    "sg:phone":"+1 505 765 9157",
    "sg:postcode":"87107",
    "sg:province":"NM",
    "sg:tags":[
        "accountant"
    ],
    "wof:name":"Diviersified Captial Inc",
    "wof:placetype":"venue"
},
  "geometry": {"coordinates":[-106.640128,35.145185],"type":"Point"}
}