{
  "type": "Feature",
  "properties": {
    "addr:full":"1301 Luisa St Santa Fe NM 87505",
    "addr:housenumber":"1301",
    "addr:postcode":"87505",
    "addr:street":"Luisa St",
    "iso:country":"US",
    "sg:address":"1301 Luisa St",
    "sg:city":"Santa Fe",
    "sg:classifiers":[
        {
            "category":"Health Services",
            "subcategory":"Health Practitioner",
            "type":"Services"
        }
    ],
    "sg:phone":"+1 505 992 0436",
    "sg:postcode":"87505",
    "sg:province":"NM",
    "sg:tags":[
        "acupuncture"
    ],
    "wof:name":"3 Treasures Medicine",
    "wof:placetype":"venue"
},
  "geometry": {"coordinates":[-105.950748,35.670002],"type":"Point"}
}