{
  "type": "Feature",
  "properties": {
    "iso:country":"US",
    "sg:address":"102 Mountain Park Pl NW",
    "sg:city":"Albuquerque",
    "sg:classifiers":[
        {
            "category":"Manufacturing",
            "subcategory":"Tools & Machinery",
            "type":"Manufacturing & Wholesale Goods"
        }
    ],
    "sg:phone":"+1 505 792 0277",
    "sg:postcode":"87114",
    "sg:province":"NM",
    "sg:tags":[
        "p",
        "lab",
        "mfg"
    ],
    "wof:name":"Wwwoptisourcellccom",
    "wof:placetype":"venue"
},
  "geometry": {"coordinates":[-106.607708,35.19484],"type":"Point"}
}