{
  "type": "Feature",
  "properties": {
    "addr:full":"1300 Luisa St Santa Fe NM 87505",
    "addr:housenumber":"1300",
    "addr:postcode":"87505",
    "addr:street":"Luisa St",
    "iso:country":"US",
    "sg:address":"1300 Luisa St",
    "sg:city":"Santa Fe",
    "sg:classifiers":[
        {
            "category":"Professional",
            "subcategory":"Engineering",
            "type":"Services"
        }
    ],
    "sg:phone":"+1 505 983 5557",
    "sg:postcode":"87505",
    "sg:province":"NM",
    "sg:tags":[
        "engineer"
    ],
    "wof:name":"Delapp & Assoc",
    "wof:placetype":"venue"
},
  "geometry": {"coordinates":[-105.950748,35.670002],"type":"Point"}
}