{
  "type": "Feature",
  "properties": {
    "addr:full":"5811 Valerian Pl NE Albuquerque NM 87111",
    "addr:housenumber":"5811",
    "addr:postcode":"87111",
    "addr:street":"Valerian Pl Ne",
    "iso:country":"US",
    "sg:address":"5811 Valerian Pl NE",
    "sg:city":"Albuquerque",
    "sg:classifiers":[
        {
            "category":"Banks & Credit Unions",
            "subcategory":"Bank",
            "type":"Services"
        }
    ],
    "sg:phone":"+1 505 856 0855",
    "sg:postcode":"87111",
    "sg:province":"NM",
    "sg:tags":[
        "personal",
        "institution"
    ],
    "wof:name":"Access Financial",
    "wof:placetype":"venue"
},
  "geometry": {"coordinates":[-106.49181400000001,35.146541],"type":"Point"}
}