{
  "type": "Feature",
  "properties": {
    "iso:country":"US",
    "sg:address":"240 Sunnyslope St SW",
    "sg:city":"Albuquerque",
    "sg:classifiers":[
        {
            "category":"Arts & Performance",
            "subcategory":"Theater",
            "type":"Entertainment"
        }
    ],
    "sg:phone":"+1 505 877 3806",
    "sg:postcode":"87105",
    "sg:province":"NM",
    "sg:tags":[
        "entertainer",
        "group",
        "business"
    ],
    "wof:name":"Mariachi Nuevo Mexico",
    "wof:placetype":"venue"
},
  "geometry": {"coordinates":[-106.671009,35.009685],"type":"Point"}
}