{
  "type": "Feature",
  "properties": {
    "iso:country":"US",
    "sg:address":"105 S 1st St",
    "sg:city":"Tucumcari",
    "sg:classifiers":[
        {
            "category":"Retail",
            "subcategory":"Repair Shop",
            "type":"Services"
        }
    ],
    "sg:phone":"+1 505 461 1114",
    "sg:postcode":"88401",
    "sg:province":"NM",
    "sg:tags":[
        "lock",
        "locksmith"
    ],
    "wof:name":"Rix Security Svc",
    "wof:placetype":"venue"
},
  "geometry": {"coordinates":[-103.72492,35.178998],"type":"Point"}
}