{
  "type": "Feature",
  "properties": {
    "addr:full":"222 Galisteo St Santa Fe NM 87501",
    "addr:housenumber":"222",
    "addr:postcode":"87501",
    "addr:street":"Galisteo St",
    "iso:country":"US",
    "sg:address":"222 Galisteo St",
    "sg:city":"Santa Fe",
    "sg:classifiers":[
        {
            "category":"Home & Garden",
            "subcategory":"Hardware",
            "type":"Retail Goods"
        }
    ],
    "sg:phone":"+1 505 983 1743",
    "sg:postcode":"87501",
    "sg:province":"NM",
    "wof:name":"Artesanos Imports Co",
    "wof:placetype":"venue"
},
  "geometry": {"coordinates":[-105.941402,35.685971],"type":"Point"}
}