{
  "type": "Feature",
  "properties": {
    "addr:full":"12104 Genoa St NE Albuquerque NM 87111",
    "addr:housenumber":"12104",
    "addr:postcode":"87111",
    "addr:street":"Genoa St Ne",
    "iso:country":"US",
    "sg:address":"12104 Genoa St NE",
    "sg:city":"Albuquerque",
    "sg:classifiers":[
        {
            "category":"Professional",
            "type":"Services"
        }
    ],
    "sg:phone":"+1 505 332 8256",
    "sg:postcode":"87111",
    "sg:province":"NM",
    "wof:name":"ACC Educational Service",
    "wof:placetype":"venue"
},
  "geometry": {"coordinates":[-106.501971,35.13695],"type":"Point"}
}