{
  "type": "Feature",
  "properties": {
    "addr:full":"308 S Motel Blvd Las Cruces NM 88007",
    "addr:housenumber":"308",
    "addr:postcode":"88007",
    "addr:street":"Blvd",
    "iso:country":"US",
    "sg:address":"308 S Motel Blvd",
    "sg:city":"Las Cruces",
    "sg:classifiers":[
        {
            "category":"Freight",
            "type":"Transportation"
        }
    ],
    "sg:phone":"+1 505 523 5606",
    "sg:postcode":"88007",
    "sg:province":"NM",
    "sg:tags":[
        "broker",
        "trucking"
    ],
    "wof:name":"Mosley's Truck Brokerage Co",
    "wof:placetype":"venue"
},
  "geometry": {"coordinates":[-106.80970000000001,32.293829],"type":"Point"}
}