{
  "type": "Feature",
  "properties": {
    "iso:country":"US",
    "sg:address":"2 Cll Medico",
    "sg:city":"Santa Fe",
    "sg:classifiers":[
        {
            "category":"Professional",
            "subcategory":"Management & Consulting",
            "type":"Services"
        },
        {
            "category":"Building & Trades",
            "subcategory":"Landscaping Services",
            "type":"Services"
        }
    ],
    "sg:phone":"+1 505 988 8939",
    "sg:postcode":"87505",
    "sg:province":"NM",
    "sg:tags":[
        "designer",
        "business",
        "landscape"
    ],
    "wof:name":"Santa Fe Design Associates",
    "wof:placetype":"venue"
},
  "geometry": {"coordinates":[-105.940891,35.657499],"type":"Point"}
}