{
  "type": "Feature",
  "properties": {
    "addr:full":"2400 Louisiana Blvd NE Albuquerque NM 87110",
    "addr:housenumber":"2400",
    "addr:postcode":"87110",
    "addr:street":"Louisiana Blvd Ne",
    "iso:country":"US",
    "sg:address":"2400 Louisiana Blvd NE",
    "sg:city":"Albuquerque",
    "sg:classifiers":[
        {
            "category":"Government",
            "subcategory":"Office",
            "type":"Public Place"
        }
    ],
    "sg:phone":"+1 505 346 2768",
    "sg:postcode":"87110",
    "sg:province":"NM",
    "sg:tags":[
        "federal"
    ],
    "sg:website":"www.doi.gov",
    "wof:name":"US Interior Dept",
    "wof:placetype":"venue"
},
  "geometry": {"coordinates":[-106.56883500000001,35.106702],"type":"Point"}
}