{
  "type": "Feature",
  "properties": {
    "addr:full":"1104 W River Rd Bloomfield NM 87413",
    "addr:housenumber":"1104",
    "addr:postcode":"87413",
    "addr:street":"W River Rd",
    "iso:country":"US",
    "sg:address":"1104 W River Rd",
    "sg:city":"Bloomfield",
    "sg:classifiers":[
        {
            "category":"Building & Trades",
            "subcategory":"Construction",
            "type":"Services"
        }
    ],
    "sg:phone":"+1 505 632 3847",
    "sg:postcode":"87413",
    "sg:province":"NM",
    "sg:tags":[
        "hanging",
        "contractor"
    ],
    "wof:name":"Rodneys Painting Drywall",
    "wof:placetype":"venue"
},
  "geometry": {"coordinates":[-107.99337800000001,36.697034],"type":"Point"}
}