{
  "type": "Feature",
  "properties": {
    "addr:full":"812 Canterbury Arc Las Cruces NM 88005",
    "addr:housenumber":"812",
    "addr:postcode":"88005",
    "addr:street":"Canterbury Arc",
    "iso:country":"US",
    "sg:address":"812 Canterbury Arc",
    "sg:city":"Las Cruces",
    "sg:classifiers":[
        {
            "category":"Building & Trades",
            "subcategory":"Construction",
            "type":"Services"
        }
    ],
    "sg:phone":"+1 505 644 3526",
    "sg:postcode":"88005",
    "sg:province":"NM",
    "sg:tags":[
        "house"
    ],
    "wof:name":"Gall Properties and Developing",
    "wof:placetype":"venue"
},
  "geometry": {"coordinates":[-106.77627,32.275567],"type":"Point"}
}