{
  "type": "Feature",
  "properties": {
    "iso:country":"US",
    "sg:address":"2215 Stoneham Pl NW",
    "sg:city":"Albuquerque",
    "sg:classifiers":[
        {
            "category":"Building & Trades",
            "subcategory":"Construction",
            "type":"Services"
        }
    ],
    "sg:phone":"+1 505 836 6128",
    "sg:postcode":"87120",
    "sg:province":"NM",
    "sg:tags":[
        "house"
    ],
    "wof:name":"Tcb Construction LLC",
    "wof:placetype":"venue"
},
  "geometry": {"coordinates":[-106.719891,35.110623],"type":"Point"}
}