{
  "type": "Feature",
  "properties": {
    "iso:country":"US",
    "sg:address":"100 Industrial Ave NE",
    "sg:city":"Albuquerque",
    "sg:classifiers":[
        {
            "category":"Professional",
            "type":"Services"
        }
    ],
    "sg:phone":"+1 505 341 9869",
    "sg:postcode":"87107",
    "sg:province":"NM",
    "sg:tags":[
        "establishment"
    ],
    "wof:name":"Fema",
    "wof:placetype":"venue"
},
  "geometry": {"coordinates":[-106.633535,35.12291],"type":"Point"}
}