{
  "type": "Feature",
  "properties": {
    "addr:full":"5115 Homestead Cir NW Albuquerque NM 87120",
    "addr:housenumber":"5115",
    "addr:postcode":"87120",
    "addr:street":"Homestead Cir Nw",
    "iso:country":"US",
    "sg:address":"5115 Homestead Cir NW",
    "sg:city":"Albuquerque",
    "sg:classifiers":[
        {
            "category":"Food & Beverages",
            "subcategory":"Groceries & Convenience Stores",
            "type":"Retail Goods"
        }
    ],
    "sg:phone":"+1 505 344 2943",
    "sg:postcode":"87120",
    "sg:province":"NM",
    "sg:tags":[
        "grocer"
    ],
    "sg:website":"www.allsups.com",
    "wof:name":"Allsup's Convenience Store",
    "wof:placetype":"venue"
},
  "geometry": {"coordinates":[-106.695909,35.162803],"type":"Point"}
}