{
  "type": "Feature",
  "properties": {
    "addr:full":"5814 Gibson Blvd SE Albuquerque NM 87108",
    "addr:housenumber":"5814",
    "addr:postcode":"87108",
    "addr:street":"Gibson Blvd Se",
    "iso:country":"US",
    "sg:address":"5814 Gibson Blvd SE",
    "sg:city":"Albuquerque",
    "sg:classifiers":[
        {
            "category":"Restaurant",
            "type":"Food & Drink"
        }
    ],
    "sg:phone":"+1 505 256 1893",
    "sg:postcode":"87108",
    "sg:province":"NM",
    "sg:tags":[
        "eating"
    ],
    "wof:name":"Sirloin Stockade",
    "wof:placetype":"venue"
},
  "geometry": {"coordinates":[-106.57668200000001,35.058173],"type":"Point"}
}