{
  "type": "Feature",
  "properties": {
    "iso:country":"US",
    "sg:address":"5555 Zuni Rd SE",
    "sg:city":"Albuquerque",
    "sg:classifiers":[
        {
            "category":"Insurance",
            "subcategory":"Insurance Agent",
            "type":"Services"
        }
    ],
    "sg:phone":"+1 505 268 7925",
    "sg:postcode":"87108",
    "sg:province":"NM",
    "wof:name":"Titan Auto Insurance",
    "wof:placetype":"venue"
},
  "geometry": {"coordinates":[-106.583827,35.072909],"type":"Point"}
}