{
  "type": "Feature",
  "properties": {
    "iso:country":"US",
    "sg:address":"2510 N Telshor Blvd",
    "sg:city":"Las Cruces",
    "sg:classifiers":[
        {
            "category":"Government",
            "subcategory":"Office",
            "type":"Public Place"
        }
    ],
    "sg:phone":"+1 505 521 8348",
    "sg:postcode":"88011",
    "sg:province":"NM",
    "sg:tags":[
        "federal",
        "planning",
        "dev"
    ],
    "wof:name":"USDA Rural Development",
    "wof:placetype":"venue"
},
  "geometry": {"coordinates":[-106.76550899999999,32.346534],"type":"Point"}
}