{
  "type": "Feature",
  "properties": {
    "iso:country":"US",
    "sg:address":"175 Chavez Rd",
    "sg:city":"Moriarty",
    "sg:classifiers":[
        {
            "category":"Building & Trades",
            "subcategory":"Landscaping Services",
            "type":"Services"
        }
    ],
    "sg:phone":"+1 505 832 4061",
    "sg:postcode":"87035",
    "sg:province":"NM",
    "wof:name":"Better Business Maintenance",
    "wof:placetype":"venue"
},
  "geometry": {"coordinates":[-106.10417,34.982369],"type":"Point"}
}