{
  "type": "Feature",
  "properties": {
    "addr:full":"3824 Corrales Rd Corrales NM 87048",
    "addr:housenumber":"3824",
    "addr:postcode":"87048",
    "addr:street":"Corrales Rd",
    "iso:country":"US",
    "sg:address":"3824 Corrales Rd",
    "sg:city":"Corrales",
    "sg:classifiers":[
        {
            "category":"Food & Beverages",
            "subcategory":"Specialty",
            "type":"Retail Goods"
        }
    ],
    "sg:phone":"+1 505 792 8300",
    "sg:postcode":"87048",
    "sg:province":"NM",
    "sg:tags":[
        "health",
        "diet"
    ],
    "wof:name":"Whole World Botanicals",
    "wof:placetype":"venue"
},
  "geometry": {"coordinates":[-106.622709,35.217932],"type":"Point"}
}