{
  "type": "Feature",
  "properties": {
    "iso:country":"US",
    "sg:address":"6600 Menaul Blvd NE",
    "sg:city":"Albuquerque",
    "sg:classifiers":[
        {
            "category":"Shopping",
            "subcategory":"Gifts & Souvenirs",
            "type":"Retail Goods"
        }
    ],
    "sg:phone":"+1 505 883 1405",
    "sg:postcode":"87110",
    "sg:province":"NM",
    "sg:tags":[
        "shop"
    ],
    "sg:website":"www.crabtree-evelyn.com",
    "wof:name":"Crabtree & Evelyn",
    "wof:placetype":"venue"
},
  "geometry": {"coordinates":[-106.56990999999999,35.109124],"type":"Point"}
}