{
  "type": "Feature",
  "properties": {
    "addr:full":"104 W 4th St Roswell NM 88201",
    "addr:housenumber":"104",
    "addr:postcode":"88201",
    "addr:street":"W 4Th St",
    "iso:country":"US",
    "sg:address":"104 W 4th St",
    "sg:city":"Roswell",
    "sg:classifiers":[
        {
            "category":"Shopping",
            "type":"Retail Goods"
        }
    ],
    "sg:phone":"+1 505 623 0753",
    "sg:postcode":"88201",
    "sg:province":"NM",
    "sg:tags":[
        "picture",
        "frame"
    ],
    "wof:name":"Frame Shop",
    "wof:placetype":"venue"
},
  "geometry": {"coordinates":[-104.524349,33.396375],"type":"Point"}
}