{
  "type": "Feature",
  "properties": {
    "addr:full":"5 Santa Ana Trl N Corrales NM 87048",
    "addr:housenumber":"5",
    "addr:postcode":"87048",
    "addr:street":"Santa Ana Trl N",
    "iso:country":"US",
    "sg:address":"5 Santa Ana Trl N",
    "sg:city":"Corrales",
    "sg:classifiers":[
        {
            "category":"Professional",
            "subcategory":"Computer Services",
            "type":"Services"
        }
    ],
    "sg:phone":"+1 505 898 1235",
    "sg:postcode":"87048",
    "sg:province":"NM",
    "sg:tags":[
        "consultant",
        "designer"
    ],
    "wof:name":"Paul Mansfield",
    "wof:placetype":"venue"
},
  "geometry": {"coordinates":[-106.651073,35.22145],"type":"Point"}
}