{
  "type": "Feature",
  "properties": {
    "iso:country":"US",
    "sg:address":"5700 Menaul Blvd NE",
    "sg:city":"Albuquerque",
    "sg:classifiers":[
        {
            "category":"Autos & Motor Vehicles",
            "subcategory":"Automobile Sales",
            "type":"Retail Goods"
        }
    ],
    "sg:phone":"+1 505 255 7500",
    "sg:postcode":"87110",
    "sg:province":"NM",
    "sg:tags":[
        "car",
        "dealer"
    ],
    "wof:name":"R B's Auto Sales",
    "wof:placetype":"venue"
},
  "geometry": {"coordinates":[-106.579787,35.109103],"type":"Point"}
}