{
  "type": "Feature",
  "properties": {
    "iso:country":"US",
    "sg:address":"361 Vinton Rd",
    "sg:city":"Anthony",
    "sg:classifiers":[
        {
            "category":"Health Services",
            "subcategory":"Doctor",
            "type":"Services"
        }
    ],
    "sg:phone":"+1 915 886 9000",
    "sg:postcode":"88021",
    "sg:province":"NM",
    "sg:tags":[
        "obstetrician",
        "gynecologist"
    ],
    "wof:name":"Desert Mountain Obstetrics & Gynecology",
    "wof:placetype":"venue"
},
  "geometry": {"coordinates":[-106.64299800000001,31.9562],"type":"Point"}
}