{
  "type": "Feature",
  "properties": {
    "iso:country":"US",
    "sg:address":"1416 San Pedro Dr NE",
    "sg:city":"Albuquerque",
    "sg:classifiers":[
        {
            "category":"Health Services",
            "subcategory":"Chiropractor",
            "type":"Services"
        }
    ],
    "sg:phone":"+1 505 255 2300",
    "sg:postcode":"87110",
    "sg:province":"NM",
    "wof:name":"Family Chiropractic",
    "wof:placetype":"venue"
},
  "geometry": {"coordinates":[-106.57749,35.092736],"type":"Point"}
}