{
  "type": "Feature",
  "properties": {
    "iso:country":"US",
    "sg:address":"5850 Eubank Blvd NE",
    "sg:city":"Albuquerque",
    "sg:classifiers":[
        {
            "category":"Insurance",
            "subcategory":"Insurance Agent",
            "type":"Services"
        }
    ],
    "sg:phone":"+1 505 294 2009",
    "sg:postcode":"87111",
    "sg:province":"NM",
    "wof:name":"Christian Slayton Insur Agcy",
    "wof:placetype":"venue"
},
  "geometry": {"coordinates":[-106.530677,35.143853],"type":"Point"}
}