{
  "type": "Feature",
  "properties": {
    "iso:country":"US",
    "sg:address":"1313 Cam Sol",
    "sg:city":"Farmington",
    "sg:classifiers":[
        {
            "category":"Professional",
            "subcategory":"Art Services",
            "type":"Services"
        }
    ],
    "sg:phone":"+1 505 325 6423",
    "sg:postcode":"87401",
    "sg:province":"NM",
    "sg:tags":[
        "photography",
        "commercial"
    ],
    "wof:name":"Wedding Photographer",
    "wof:placetype":"venue"
},
  "geometry": {"coordinates":[-108.186672,36.716933],"type":"Point"}
}