{
  "type": "Feature",
  "properties": {
    "iso:country":"US",
    "sg:address":"26 Ave B",
    "sg:city":"Hachita",
    "sg:classifiers":[
        {
            "category":"Government",
            "subcategory":"Post Office",
            "type":"Public Place"
        }
    ],
    "sg:phone":"+1 505 436 2220",
    "sg:postcode":"88040",
    "sg:province":"NM",
    "wof:name":"US Post Office",
    "wof:placetype":"venue"
},
  "geometry": {"coordinates":[-108.321764,31.916257],"type":"Point"}
}