{
  "type": "Feature",
  "properties": {
    "iso:country":"US",
    "sg:address":"10900 Menaul Blvd NE",
    "sg:city":"Albuquerque",
    "sg:classifiers":[
        {
            "category":"Food & Beverages",
            "subcategory":"Bakery",
            "type":"Retail Goods"
        }
    ],
    "sg:phone":"+1 505 293 9356",
    "sg:postcode":"87112",
    "sg:province":"NM",
    "sg:tags":[
        "baker"
    ],
    "wof:name":"Cakes By Nadine",
    "wof:placetype":"venue"
},
  "geometry": {"coordinates":[-106.515567,35.108868],"type":"Point"}
}