{
  "type": "Feature",
  "properties": {
    "addr:full":"6 Ver Mesita Santa Fe NM 87508",
    "addr:housenumber":"6",
    "addr:postcode":"87508",
    "addr:street":"Ver Mesita",
    "iso:country":"US",
    "sg:address":"6 Ver Mesita",
    "sg:city":"Santa Fe",
    "sg:classifiers":[
        {
            "category":"Utilities",
            "subcategory":"Water",
            "type":"Services"
        }
    ],
    "sg:phone":"+1 505 466 9090",
    "sg:postcode":"87508",
    "sg:province":"NM",
    "sg:tags":[
        "supply"
    ],
    "wof:name":"Rainharvest LLC",
    "wof:placetype":"venue"
},
  "geometry": {"coordinates":[-105.833304,35.523189],"type":"Point"}
}