{
  "type": "Feature",
  "properties": {
    "iso:country":"US",
    "sg:address":"7043 US Hwy 70",
    "sg:city":"Alamogordo",
    "sg:classifiers":[
        {
            "category":"Building & Trades",
            "subcategory":"Construction",
            "type":"Services"
        }
    ],
    "sg:phone":"+1 505 437 6657",
    "sg:postcode":"88310",
    "sg:province":"NM",
    "sg:tags":[
        "contractor"
    ],
    "wof:name":"Jack Wayte Construction Co Inc",
    "wof:placetype":"venue"
},
  "geometry": {"coordinates":[-105.979518,32.972174],"type":"Point"}
}