{
  "type": "Feature",
  "properties": {
    "addr:full":"2170 E Lohman Ave Las Cruces NM 88001",
    "addr:housenumber":"2170",
    "addr:postcode":"88001",
    "addr:street":"E Lohman Ave",
    "iso:country":"US",
    "sg:address":"2170 E Lohman Ave",
    "sg:city":"Las Cruces",
    "sg:classifiers":[
        {
            "category":"Health Services",
            "subcategory":"Doctor",
            "type":"Services"
        }
    ],
    "sg:phone":"+1 505 524 8888",
    "sg:postcode":"88001",
    "sg:province":"NM",
    "sg:tags":[
        "physician",
        "surgeon"
    ],
    "wof:name":"Occu Care",
    "wof:placetype":"venue"
},
  "geometry": {"coordinates":[-106.753484,32.312423],"type":"Point"}
}