{
  "type": "Feature",
  "properties": {
    "iso:country":"US",
    "sg:address":"2370 Aztec Rd NE",
    "sg:city":"Albuquerque",
    "sg:classifiers":[
        {
            "category":"Retail",
            "subcategory":"Auto Repair",
            "type":"Services"
        }
    ],
    "sg:phone":"+1 505 878 9510",
    "sg:postcode":"87107",
    "sg:province":"NM",
    "sg:tags":[
        "general",
        "supply"
    ],
    "wof:name":"Albuqerque Auto Bdy Fleet Svcs",
    "wof:placetype":"venue"
},
  "geometry": {"coordinates":[-106.619565,35.120128],"type":"Point"}
}