{
  "type": "Feature",
  "properties": {
    "iso:country":"US",
    "sg:address":"303 Pso de Peralta",
    "sg:city":"Santa Fe",
    "sg:classifiers":[
        {
            "category":"Professional",
            "subcategory":"Lawyer & Legal Services",
            "type":"Services"
        }
    ],
    "sg:phone":"+1 505 983 6497",
    "sg:postcode":"87501",
    "sg:province":"NM",
    "sg:tags":[
        "attorney"
    ],
    "sg:website":"www.cwlaw.com",
    "wof:name":"Conner & Winters",
    "wof:placetype":"venue"
},
  "geometry": {"coordinates":[-105.941103,35.692612],"type":"Point"}
}