{
  "type": "Feature",
  "properties": {
    "addr:full":"605 W Main St Artesia NM 88210",
    "addr:housenumber":"605",
    "addr:postcode":"88210",
    "addr:street":"W Main St",
    "iso:country":"US",
    "sg:address":"605 W Main St",
    "sg:city":"Artesia",
    "sg:classifiers":[
        {
            "category":"Mining & Drilling",
            "type":"Manufacturing & Wholesale Goods"
        }
    ],
    "sg:phone":"+1 505 746 9613",
    "sg:postcode":"88210",
    "sg:province":"NM",
    "sg:tags":[
        "field",
        "oil"
    ],
    "wof:name":"Alliance Flow",
    "wof:placetype":"venue"
},
  "geometry": {"coordinates":[-104.403595,32.842128],"type":"Point"}
}