{
  "type": "Feature",
  "properties": {
    "addr:full":"2555 Airport Rd Santa Teresa NM 88008",
    "addr:housenumber":"2555",
    "addr:postcode":"88008",
    "addr:street":"Airport Rd",
    "iso:country":"US",
    "sg:address":"2555 Airport Rd",
    "sg:city":"Santa Teresa",
    "sg:classifiers":[
        {
            "category":"Utilities",
            "subcategory":"Telephone",
            "type":"Services"
        }
    ],
    "sg:phone":"+1 505 589 3532",
    "sg:postcode":"88008",
    "sg:province":"NM",
    "sg:tags":[
        "telecommunication"
    ],
    "wof:name":"Qwest",
    "wof:placetype":"venue"
},
  "geometry": {"coordinates":[-106.694108,31.86617],"type":"Point"}
}