{
  "type": "Feature",
  "properties": {
    "addr:full":"2116 W Bender Blvd Hobbs NM 88240",
    "addr:housenumber":"2116",
    "addr:postcode":"88240",
    "addr:street":"W Bender Blvd",
    "iso:country":"US",
    "sg:address":"2116 W Bender Blvd",
    "sg:city":"Hobbs",
    "sg:classifiers":[
        {
            "category":"Building & Trades",
            "subcategory":"Construction",
            "type":"Services"
        }
    ],
    "sg:phone":"+1 505 397 5995",
    "sg:postcode":"88240",
    "sg:province":"NM",
    "sg:tags":[
        "utility",
        "contractor"
    ],
    "wof:name":"Henkel's & Mccoy",
    "wof:placetype":"venue"
},
  "geometry": {"coordinates":[-103.164181,32.725752],"type":"Point"}
}