{
  "type": "Feature",
  "properties": {
    "addr:full":"1001 Tramway Blvd NE Albuquerque NM 87112",
    "addr:housenumber":"1001",
    "addr:postcode":"87112",
    "addr:street":"Tramway Blvd Ne",
    "iso:country":"US",
    "sg:address":"1001 Tramway Blvd NE",
    "sg:city":"Albuquerque",
    "sg:classifiers":[
        {
            "category":"Professional",
            "subcategory":"Business Services",
            "type":"Services"
        }
    ],
    "sg:phone":"+1 505 275 4149",
    "sg:postcode":"87112",
    "sg:province":"NM",
    "sg:tags":[
        "transcribing",
        "disc"
    ],
    "wof:name":"BDR Transcription",
    "wof:placetype":"venue"
},
  "geometry": {"coordinates":[-106.497714,35.09383],"type":"Point"}
}