{
  "type": "Feature",
  "properties": {
    "iso:country":"US",
    "sg:address":"331 Academy Dr",
    "sg:city":"Corrales",
    "sg:classifiers":[
        {
            "category":"Shopping",
            "type":"Retail Goods"
        }
    ],
    "sg:phone":"+1 505 828 1337",
    "sg:postcode":"87048",
    "sg:province":"NM",
    "sg:tags":[
        "merchandise"
    ],
    "wof:name":"Furniture First",
    "wof:placetype":"venue"
},
  "geometry": {"coordinates":[-106.606512,35.247312],"type":"Point"}
}