{
  "type": "Feature",
  "properties": {
    "iso:country":"US",
    "sg:address":"7100 Jefferson St NE",
    "sg:city":"Albuquerque",
    "sg:classifiers":[
        {
            "category":"Retail",
            "subcategory":"Auto Repair",
            "type":"Services"
        }
    ],
    "sg:phone":"+1 505 344 3464",
    "sg:postcode":"87109",
    "sg:province":"NM",
    "sg:tags":[
        "body"
    ],
    "wof:name":"International Dent Inc",
    "wof:placetype":"venue"
},
  "geometry": {"coordinates":[-106.59317299999999,35.159752],"type":"Point"}
}