{
  "type": "Feature",
  "properties": {
    "addr:full":"1300 W Hadley Ave Las Cruces NM 88005",
    "addr:housenumber":"1300",
    "addr:postcode":"88005",
    "addr:street":"W Hadley Ave",
    "iso:country":"US",
    "sg:address":"1300 W Hadley Ave",
    "sg:city":"Las Cruces",
    "sg:classifiers":[
        {
            "category":"Retail",
            "subcategory":"Auto Repair",
            "type":"Services"
        }
    ],
    "sg:phone":"+1 505 526 4869",
    "sg:postcode":"88005",
    "sg:province":"NM",
    "sg:tags":[
        "automotive"
    ],
    "wof:name":"Discount Towing & Recovery",
    "wof:placetype":"venue"
},
  "geometry": {"coordinates":[-106.79559,32.30934],"type":"Point"}
}