{
  "type": "Feature",
  "properties": {
    "addr:full":"1865 S Valley Dr Las Cruces NM 88005",
    "addr:housenumber":"1865",
    "addr:postcode":"88005",
    "addr:street":"S Valley Dr",
    "iso:country":"US",
    "sg:address":"1865 S Valley Dr",
    "sg:city":"Las Cruces",
    "sg:classifiers":[
        {
            "category":"Retail",
            "subcategory":"Auto Repair",
            "type":"Services"
        }
    ],
    "sg:phone":"+1 505 526 4068",
    "sg:postcode":"88005",
    "sg:province":"NM",
    "sg:tags":[
        "muffler",
        "exhaust",
        "system"
    ],
    "wof:name":"J & J Muffler Shop",
    "wof:placetype":"venue"
},
  "geometry": {"coordinates":[-106.77928,32.286658],"type":"Point"}
}