{
  "type": "Feature",
  "properties": {
    "iso:country":"US",
    "sg:address":"437 Godfrey Ave",
    "sg:city":"Belen",
    "sg:classifiers":[
        {
            "category":"Shopping",
            "subcategory":"Gifts & Souvenirs",
            "type":"Retail Goods"
        }
    ],
    "sg:phone":"+1 505 864 2130",
    "sg:postcode":"87002",
    "sg:province":"NM",
    "sg:tags":[
        "shop"
    ],
    "wof:name":"Shirley's Gift & Things",
    "wof:placetype":"venue"
},
  "geometry": {"coordinates":[-106.716229,34.647524],"type":"Point"}
}