{
  "type": "Feature",
  "properties": {
    "iso:country":"US",
    "sg:address":"734 Center St",
    "sg:city":"Ruidoso",
    "sg:classifiers":[
        {
            "category":"Building & Trades",
            "subcategory":"Construction",
            "type":"Services"
        }
    ],
    "sg:phone":"+1 505 257 4130",
    "sg:postcode":"88345",
    "sg:province":"NM",
    "sg:tags":[
        "home",
        "general",
        "family",
        "contractor"
    ],
    "wof:name":"Noel Bowley Construction",
    "wof:placetype":"venue"
},
  "geometry": {"coordinates":[-105.671738,33.326029],"type":"Point"}
}