{
  "type": "Feature",
  "properties": {
    "iso:country":"US",
    "sg:address":"413 Romero St NW",
    "sg:city":"Albuquerque",
    "sg:classifiers":[
        {
            "category":"Museum",
            "type":"Entertainment"
        },
        {
            "category":"Shopping",
            "subcategory":"Jewelry",
            "type":"Retail Goods"
        }
    ],
    "sg:phone":"+1 505 242 4080",
    "sg:postcode":"87104",
    "sg:province":"NM",
    "sg:tags":[
        "gallery",
        "jeweler"
    ],
    "wof:name":"Shiprock Trading Co Inc",
    "wof:placetype":"venue"
},
  "geometry": {"coordinates":[-106.670437,35.098011],"type":"Point"}
}