{
  "type": "Feature",
  "properties": {
    "iso:country":"US",
    "sg:address":"223 Pso del Pueblo Sur",
    "sg:city":"Taos",
    "sg:classifiers":[
        {
            "category":"Building & Trades",
            "subcategory":"Construction",
            "type":"Services"
        }
    ],
    "sg:phone":"+1 505 737 5164",
    "sg:postcode":"87571",
    "sg:province":"NM",
    "sg:tags":[
        "home",
        "improvement"
    ],
    "wof:name":"L & G Interiors",
    "wof:placetype":"venue"
},
  "geometry": {"coordinates":[-105.574138,36.404348],"type":"Point"}
}