{
  "type": "Feature",
  "properties": {
    "iso:country":"US",
    "sg:address":"3504 Montgomery Blvd NE",
    "sg:city":"Albuquerque",
    "sg:classifiers":[
        {
            "category":"Professional",
            "subcategory":"Accounting & Tax Preparation",
            "type":"Services"
        }
    ],
    "sg:phone":"+1 505 883 3192",
    "sg:postcode":"87107",
    "sg:province":"NM",
    "sg:tags":[
        "consulting",
        "return",
        "accountant",
        "business"
    ],
    "wof:name":"B & R Tax & Accounting",
    "wof:placetype":"venue"
},
  "geometry": {"coordinates":[-106.606183,35.130948],"type":"Point"}
}