{
  "type": "Feature",
  "properties": {
    "iso:country":"US",
    "sg:address":"1011 Pso de Peralta",
    "sg:city":"Santa Fe",
    "sg:classifiers":[
        {
            "category":"Real Estate",
            "subcategory":"Real Estate Agent",
            "type":"Services"
        }
    ],
    "sg:phone":"+1 505 983 4239",
    "sg:postcode":"87501",
    "sg:province":"NM",
    "wof:name":"Clem Gunn Real Estate",
    "wof:placetype":"venue"
},
  "geometry": {"coordinates":[-105.93477,35.681114],"type":"Point"}
}