{
  "type": "Feature",
  "properties": {
    "addr:full":"1708 Hendola Dr NE Albuquerque NM 87110",
    "addr:housenumber":"1708",
    "addr:postcode":"87110",
    "addr:street":"Hendola Dr Ne",
    "iso:country":"US",
    "sg:address":"1708 Hendola Dr NE",
    "sg:city":"Albuquerque",
    "sg:classifiers":[
        {
            "category":"Personal",
            "type":"Services"
        }
    ],
    "sg:phone":"+1 505 271 8709",
    "sg:postcode":"87110",
    "sg:province":"NM",
    "wof:name":"Charles V Fenolio",
    "wof:placetype":"venue"
},
  "geometry": {"coordinates":[-106.555999,35.100294],"type":"Point"}
}