{
  "type": "Feature",
  "properties": {
    "iso:country":"US",
    "sg:address":"1703 N Garden Ave",
    "sg:city":"Roswell",
    "sg:classifiers":[
        {
            "category":"Sports & Exercise",
            "subcategory":"Race Track",
            "type":"Entertainment"
        }
    ],
    "sg:phone":"+1 505 420 8722",
    "sg:postcode":"88201",
    "sg:province":"NM",
    "sg:tags":[
        "operation"
    ],
    "wof:name":"Roswell Dragway LLC",
    "wof:placetype":"venue"
},
  "geometry": {"coordinates":[-104.514317,33.412699],"type":"Point"}
}