{
  "type": "Feature",
  "properties": {
    "addr:full":"712 N Prince St Clovis NM 88101",
    "addr:housenumber":"712",
    "addr:postcode":"88101",
    "addr:street":"N Prince St",
    "iso:country":"US",
    "sg:address":"712 N Prince St",
    "sg:city":"Clovis",
    "sg:classifiers":[
        {
            "category":"Banks & Credit Unions",
            "subcategory":"Bank",
            "type":"Services"
        }
    ],
    "sg:phone":"+1 505 769 9196",
    "sg:postcode":"88101",
    "sg:province":"NM",
    "sg:tags":[
        "loan"
    ],
    "wof:name":"K P Car Lot & Loans",
    "wof:placetype":"venue"
},
  "geometry": {"coordinates":[-103.196585,34.405617],"type":"Point"}
}