{
  "type": "Feature",
  "properties": {
    "iso:country":"US",
    "sg:address":"1601 W Murray Dr",
    "sg:city":"Farmington",
    "sg:classifiers":[
        {
            "category":"Wholesale",
            "subcategory":"Machinery & Supplies",
            "type":"Manufacturing & Wholesale Goods"
        }
    ],
    "sg:phone":"+1 505 327 1398",
    "sg:postcode":"87401",
    "sg:province":"NM",
    "sg:tags":[
        "equipment"
    ],
    "wof:name":"Harbison-Fischer",
    "wof:placetype":"venue"
},
  "geometry": {"coordinates":[-108.230494,36.729065],"type":"Point"}
}