{
  "type": "Feature",
  "properties": {
    "addr:full":"5021 San Mateo Ln NE Albuquerque NM 87109",
    "addr:housenumber":"5021",
    "addr:postcode":"87109",
    "addr:street":"San Mateo Ln Ne",
    "iso:country":"US",
    "sg:address":"5021 San Mateo Ln NE",
    "sg:city":"Albuquerque",
    "sg:classifiers":[
        {
            "category":"Real Estate",
            "subcategory":"Real Estate Operator",
            "type":"Services"
        }
    ],
    "sg:phone":"+1 505 883 6494",
    "sg:postcode":"87109",
    "sg:province":"NM",
    "sg:tags":[
        "apartment"
    ],
    "wof:name":"Briarwood Park Apartments",
    "wof:placetype":"venue"
},
  "geometry": {"coordinates":[-106.581973,35.137868],"type":"Point"}
}