{
  "type": "Feature",
  "properties": {
    "addr:full":"304 Catron St Santa Fe NM 87501",
    "addr:housenumber":"304",
    "addr:postcode":"87501",
    "addr:street":"Catron St",
    "iso:country":"US",
    "sg:address":"304 Catron St",
    "sg:city":"Santa Fe",
    "sg:classifiers":[
        {
            "category":"Shopping",
            "subcategory":"Used Merchandise",
            "type":"Retail Goods"
        }
    ],
    "sg:phone":"+1 505 984 0207",
    "sg:postcode":"87501",
    "sg:province":"NM",
    "sg:tags":[
        "antique"
    ],
    "wof:name":"Bedroom The Antique Linen",
    "wof:placetype":"venue"
},
  "geometry": {"coordinates":[-105.94327699999999,35.691193],"type":"Point"}
}