{
  "type": "Feature",
  "properties": {
    "iso:country":"US",
    "sg:address":"12242 State Rte 14 Scn",
    "sg:city":"Cedar Crest",
    "sg:classifiers":[
        {
            "category":"Organizations",
            "subcategory":"Religious Organization",
            "type":"Services"
        }
    ],
    "sg:phone":"+1 505 281 3313",
    "sg:postcode":"87008",
    "sg:province":"NM",
    "sg:tags":[
        "church"
    ],
    "wof:name":"Mountain Christian Church",
    "wof:placetype":"venue"
},
  "geometry": {"coordinates":[-106.366307,35.13231],"type":"Point"}
}