{
  "type": "Feature",
  "properties": {
    "iso:country":"US",
    "sg:address":"3120 Blake Rd SW",
    "sg:city":"Albuquerque",
    "sg:classifiers":[
        {
            "category":"Building & Trades",
            "subcategory":"Equipment Rental",
            "type":"Services"
        }
    ],
    "sg:phone":"+1 505 877 7587",
    "sg:postcode":"87105",
    "sg:province":"NM",
    "sg:tags":[
        "audio",
        "leasing"
    ],
    "wof:name":"Elliott Location Equipment",
    "wof:placetype":"venue"
},
  "geometry": {"coordinates":[-106.704801,35.035858],"type":"Point"}
}