{
  "type": "Feature",
  "properties": {
    "iso:country":"US",
    "sg:address":"1301 Rio Grande Blvd NW",
    "sg:city":"Albuquerque",
    "sg:classifiers":[
        {
            "category":"Wholesale",
            "subcategory":"Durable Goods & Equipment",
            "type":"Manufacturing & Wholesale Goods"
        }
    ],
    "sg:phone":"+1 505 247 1598",
    "sg:postcode":"87104",
    "sg:province":"NM",
    "sg:tags":[
        "representative",
        "manufacturer"
    ],
    "sg:website":"www.gorman-co.com",
    "wof:name":"Gorman Co",
    "wof:placetype":"venue"
},
  "geometry": {"coordinates":[-106.67168599999999,35.108582],"type":"Point"}
}