{
  "type": "Feature",
  "properties": {
    "iso:country":"US",
    "sg:address":"475 Mission Rd",
    "sg:city":"Jemez Pueblo",
    "sg:classifiers":[
        {
            "category":"Organizations",
            "subcategory":"Religious Organization",
            "type":"Services"
        }
    ],
    "sg:phone":"+1 505 834 7300",
    "sg:postcode":"87024",
    "sg:province":"NM",
    "sg:tags":[
        "church"
    ],
    "wof:name":"San Diego Mission",
    "wof:placetype":"venue"
},
  "geometry": {"coordinates":[-106.731155,35.614294],"type":"Point"}
}