{
  "type": "Feature",
  "properties": {
    "iso:country":"US",
    "sg:address":"72 E San Francisco St",
    "sg:city":"Santa Fe",
    "sg:classifiers":[
        {
            "category":"Shopping",
            "subcategory":"Clothing, Apparel, & Fashions",
            "type":"Retail Goods"
        }
    ],
    "sg:phone":"+1 505 988 3100",
    "sg:postcode":"87501",
    "sg:province":"NM",
    "sg:tags":[
        "home",
        "furniture",
        "woman",
        "man",
        "accessory"
    ],
    "wof:name":"Simply Santa Fe",
    "wof:placetype":"venue"
},
  "geometry": {"coordinates":[-105.938703,35.687093],"type":"Point"}
}