{
  "type": "Feature",
  "properties": {
    "iso:country":"US",
    "sg:address":"514 W Main St",
    "sg:city":"Artesia",
    "sg:classifiers":[
        {
            "category":"Manufacturing",
            "subcategory":"Printing",
            "type":"Manufacturing & Wholesale Goods"
        }
    ],
    "sg:phone":"+1 505 748 3536",
    "sg:postcode":"88210",
    "sg:province":"NM",
    "sg:tags":[
        "commercial"
    ],
    "wof:name":"Incredible Printing",
    "wof:placetype":"venue"
},
  "geometry": {"coordinates":[-104.403403,32.842278],"type":"Point"}
}