{
  "type": "Feature",
  "properties": {
    "addr:full":"11208 Cochiti Rd SE Albuquerque NM 87123",
    "addr:postcode":"11208;87123",
    "addr:street":"Cochiti Rd Se",
    "iso:country":"US",
    "sg:address":"11208 Cochiti Rd SE",
    "sg:city":"Albuquerque",
    "sg:classifiers":[
        {
            "category":"Professional",
            "subcategory":"Research",
            "type":"Services"
        }
    ],
    "sg:phone":"+1 505 346 1688",
    "sg:postcode":"87123",
    "sg:province":"NM",
    "sg:tags":[
        "development",
        "laboratory"
    ],
    "wof:name":"Adherent Technology Inc",
    "wof:placetype":"venue"
},
  "geometry": {"coordinates":[-106.52356,35.069892],"type":"Point"}
}