{
  "type": "Feature",
  "properties": {
    "iso:country":"US",
    "sg:address":"6 Maplewood Ct",
    "sg:city":"Edgewood",
    "sg:classifiers":[
        {
            "category":"Professional",
            "subcategory":"Management & Consulting",
            "type":"Services"
        }
    ],
    "sg:phone":"+1 505 286 4447",
    "sg:postcode":"87015",
    "sg:province":"NM",
    "wof:name":"Administrative Management Svc",
    "wof:placetype":"venue"
},
  "geometry": {"coordinates":[-106.24565699999999,35.141927],"type":"Point"}
}