{
  "type": "Feature",
  "properties": {
    "addr:full":"515 Slate Ave NW Albuquerque NM 87102",
    "addr:housenumber":"515",
    "addr:postcode":"87102",
    "addr:street":"Slate Ave Nw",
    "iso:country":"US",
    "sg:address":"515 Slate Ave NW",
    "sg:city":"Albuquerque",
    "sg:classifiers":[
        {
            "category":"Cafe",
            "type":"Food & Drink"
        },
        {
            "category":"Restaurant",
            "type":"Food & Drink"
        }
    ],
    "sg:menulink":"http://www.allmenus.com/nm/albuquerque/283400-slate-street-cafe/menu/",
    "sg:phone":"+1 505 243 2210",
    "sg:postcode":"87102",
    "sg:province":"NM",
    "sg:tags":[
        "new",
        "american"
    ],
    "wof:name":"Slate Street Cafe",
    "wof:placetype":"venue"
},
  "geometry": {"coordinates":[-106.652091,35.09264],"type":"Point"}
}