{
  "type": "Feature",
  "properties": {
    "addr:full":"518 W Pear St Deming NM 88030",
    "addr:housenumber":"518",
    "addr:postcode":"88030",
    "addr:street":"W Pear St",
    "iso:country":"US",
    "sg:address":"518 W Pear St",
    "sg:city":"Deming",
    "sg:classifiers":[
        {
            "category":"Health Services",
            "subcategory":"Chiropractor",
            "type":"Services"
        }
    ],
    "sg:phone":"+1 505 546 6465",
    "sg:postcode":"88030",
    "sg:province":"NM",
    "wof:name":"Johnson Chiropractic Health",
    "wof:placetype":"venue"
},
  "geometry": {"coordinates":[-107.76297700000001,32.246905],"type":"Point"}
}