{
  "type": "Feature",
  "properties": {
    "iso:country":"US",
    "sg:address":"3301 Southern Blvd SE",
    "sg:city":"Rio Rancho",
    "sg:classifiers":[
        {
            "category":"Restaurant",
            "type":"Food & Drink"
        }
    ],
    "sg:phone":"+1 505 994 4300",
    "sg:postcode":"87124",
    "sg:province":"NM",
    "sg:tags":[
        "eating",
        "caterer"
    ],
    "wof:name":"Your Place or Mine Catering",
    "wof:placetype":"venue"
},
  "geometry": {"coordinates":[-106.669215,35.241575],"type":"Point"}
}