{
  "type": "Feature",
  "properties": {
    "iso:country":"US",
    "sg:address":"4004 Carlisle Blvd NE",
    "sg:city":"Albuquerque",
    "sg:classifiers":[
        {
            "category":"Insurance",
            "subcategory":"Insurance Agent",
            "type":"Services"
        }
    ],
    "sg:phone":"+1 505 888 4472",
    "sg:postcode":"87107",
    "sg:province":"NM",
    "wof:name":"Carpenter Insurance",
    "wof:placetype":"venue"
},
  "geometry": {"coordinates":[-106.604058,35.127066],"type":"Point"}
}