{
  "type": "Feature",
  "properties": {
    "iso:country":"US",
    "sg:address":"1315 N Main St",
    "sg:city":"Las Cruces",
    "sg:classifiers":[
        {
            "category":"Utilities",
            "subcategory":"Fuel Oil & Lpg",
            "type":"Services"
        }
    ],
    "sg:phone":"+1 505 523 4642",
    "sg:postcode":"88001",
    "sg:province":"NM",
    "sg:tags":[
        "liquefied",
        "gas",
        "petroleum"
    ],
    "wof:name":"One Oak",
    "wof:placetype":"venue"
},
  "geometry": {"coordinates":[-106.782193,32.322056],"type":"Point"}
}