{
  "type": "Feature",
  "properties": {
    "iso:country":"US",
    "sg:address":"7200 4th St NW",
    "sg:city":"Albuquerque",
    "sg:classifiers":[
        {
            "category":"Wholesale",
            "subcategory":"Jewelry",
            "type":"Manufacturing & Wholesale Goods"
        }
    ],
    "sg:phone":"+1 505 897 9967",
    "sg:postcode":"87107",
    "sg:province":"NM",
    "sg:tags":[
        "jeweler"
    ],
    "wof:name":"Tambrian Limited",
    "wof:placetype":"venue"
},
  "geometry": {"coordinates":[-106.635515,35.168403],"type":"Point"}
}