{
  "type": "Feature",
  "properties": {
    "addr:full":"526 S Alameda Blvd Las Cruces NM 88005",
    "addr:housenumber":"526",
    "addr:postcode":"88005",
    "addr:street":"S Alameda Blvd",
    "iso:country":"US",
    "sg:address":"526 S Alameda Blvd",
    "sg:city":"Las Cruces",
    "sg:classifiers":[
        {
            "category":"Real Estate",
            "subcategory":"Real Estate Services",
            "type":"Services"
        }
    ],
    "sg:phone":"+1 505 527 1600",
    "sg:postcode":"88005",
    "sg:province":"NM",
    "sg:tags":[
        "company",
        "title"
    ],
    "sg:website":"www.sierratitle.com",
    "wof:name":"Sierra Title Co Of Nm Inc",
    "wof:placetype":"venue"
},
  "geometry": {"coordinates":[-106.780006,32.305051],"type":"Point"}
}