{
  "type": "Feature",
  "properties": {
    "addr:full":"2006 S 9th St Tucumcari NM 88401",
    "addr:housenumber":"2006",
    "addr:postcode":"88401",
    "addr:street":"S 9Th St",
    "iso:country":"US",
    "sg:address":"2006 S 9th St",
    "sg:city":"Tucumcari",
    "sg:classifiers":[
        {
            "category":"Building & Trades",
            "subcategory":"Construction",
            "type":"Services"
        }
    ],
    "sg:phone":"+1 505 461 2406",
    "sg:postcode":"88401",
    "sg:province":"NM",
    "sg:tags":[
        "concrete",
        "contractor"
    ],
    "wof:name":"Pavestone Co",
    "wof:placetype":"venue"
},
  "geometry": {"coordinates":[-103.734933,35.159859],"type":"Point"}
}