{
  "type": "Feature",
  "properties": {
    "iso:country":"US",
    "sg:address":"3428 US Hwy 64",
    "sg:city":"Waterflow",
    "sg:classifiers":[
        {
            "category":"Government",
            "subcategory":"Post Office",
            "type":"Public Place"
        }
    ],
    "sg:phone":"+1 505 598 6338",
    "sg:postcode":"87421",
    "sg:province":"NM",
    "wof:name":"US Post Office",
    "wof:placetype":"venue"
},
  "geometry": {"coordinates":[-108.49342,36.760298],"type":"Point"}
}