{
  "type": "Feature",
  "properties": {
    "iso:country":"US",
    "sg:address":"260 S Riverside Dr",
    "sg:city":"Espanola",
    "sg:classifiers":[
        {
            "category":"Retail",
            "subcategory":"Auto Repair",
            "type":"Services"
        }
    ],
    "sg:phone":"+1 505 747 2461",
    "sg:postcode":"87532",
    "sg:province":"NM",
    "sg:tags":[
        "wrecker"
    ],
    "wof:name":"American Towing",
    "wof:placetype":"venue"
},
  "geometry": {"coordinates":[-106.067703,35.991206],"type":"Point"}
}