{
  "type": "Feature",
  "properties": {
    "addr:full":"2412 San Mateo Pl NE Albuquerque NM 87110",
    "addr:housenumber":"2412",
    "addr:postcode":"87110",
    "addr:street":"San Mateo Pl Ne",
    "iso:country":"US",
    "sg:address":"2412 San Mateo Pl NE",
    "sg:city":"Albuquerque",
    "sg:classifiers":[
        {
            "category":"Real Estate",
            "subcategory":"Real Estate Agent",
            "type":"Services"
        }
    ],
    "sg:phone":"+1 505 872 8000",
    "sg:postcode":"87110",
    "sg:province":"NM",
    "wof:name":"MVP Real Estate",
    "wof:placetype":"venue"
},
  "geometry": {"coordinates":[-106.58632799999999,35.10671],"type":"Point"}
}