{
  "type": "Feature",
  "properties": {
    "iso:country":"US",
    "sg:address":"243 N Cam del Pueblo",
    "sg:city":"Bernalillo",
    "sg:classifiers":[
        {
            "category":"Organizations",
            "subcategory":"Professional Association",
            "type":"Services"
        }
    ],
    "sg:phone":"+1 505 867 1185",
    "sg:postcode":"87004",
    "sg:province":"NM",
    "sg:tags":[
        "chambers",
        "commerce"
    ],
    "wof:name":"Bernalillo Chamber Of Commerce",
    "wof:placetype":"venue"
},
  "geometry": {"coordinates":[-106.542776,35.322417],"type":"Point"}
}