{
  "type": "Feature",
  "properties": {
    "addr:full":"2600 N Silver St Tyrone NM 88061",
    "addr:housenumber":"2600",
    "addr:postcode":"88061",
    "addr:street":"N Silver St",
    "iso:country":"US",
    "sg:address":"2600 N Silver St",
    "sg:city":"Tyrone",
    "sg:classifiers":[
        {
            "category":"Government",
            "subcategory":"Office",
            "type":"Public Place"
        }
    ],
    "sg:phone":"+1 505 388 3241",
    "sg:postcode":"88061",
    "sg:province":"NM",
    "sg:tags":[
        "armed",
        "force",
        "recruiting"
    ],
    "wof:name":"US Marine Corps Recruiting",
    "wof:placetype":"venue"
},
  "geometry": {"coordinates":[-108.267151,32.795197],"type":"Point"}
}