{
  "type": "Feature",
  "properties": {
    "iso:country":"US",
    "sg:address":"1829 Cam de la Canada",
    "sg:city":"Santa Fe",
    "sg:classifiers":[
        {
            "category":"Professional",
            "subcategory":"Accounting & Tax Preparation",
            "type":"Services"
        }
    ],
    "sg:phone":"+1 505 982 4025",
    "sg:postcode":"87501",
    "sg:province":"NM",
    "sg:tags":[
        "accountant"
    ],
    "wof:name":"John A Ulibarri CPA",
    "wof:placetype":"venue"
},
  "geometry": {"coordinates":[-105.971011,35.678418],"type":"Point"}
}