{
  "type": "Feature",
  "properties": {
    "addr:full":"6626 4th St NW Albuquerque NM 87107",
    "addr:housenumber":"6626",
    "addr:postcode":"87107",
    "addr:street":"4Th St Nw",
    "iso:country":"US",
    "sg:address":"6626 4th St NW",
    "sg:city":"Albuquerque",
    "sg:classifiers":[
        {
            "category":"Autos & Motor Vehicles",
            "subcategory":"Auto Supplies",
            "type":"Retail Goods"
        },
        {
            "category":"Wholesale",
            "subcategory":"Electrical",
            "type":"Manufacturing & Wholesale Goods"
        }
    ],
    "sg:phone":"+1 505 341 1258",
    "sg:postcode":"87107",
    "sg:province":"NM",
    "sg:tags":[
        "battery",
        "automobile",
        "part",
        "batteries-storage",
        "accessory"
    ],
    "sg:website":"http://www.autozone.com",
    "wof:name":"AutoZone",
    "wof:placetype":"venue"
},
  "geometry": {"coordinates":[-106.63821,35.154563],"type":"Point"}
}