{
  "type": "Feature",
  "properties": {
    "addr:full":"2603 Columbia Rd Roswell NM 88201",
    "addr:housenumber":"2603",
    "addr:postcode":"88201",
    "addr:street":"Columbia Rd",
    "iso:country":"US",
    "sg:address":"2603 Columbia Rd",
    "sg:city":"Roswell",
    "sg:classifiers":[
        {
            "category":"Professional",
            "subcategory":"Accounting & Tax Preparation",
            "type":"Services"
        }
    ],
    "sg:phone":"+1 505 625 2537",
    "sg:postcode":"88201",
    "sg:province":"NM",
    "wof:name":"Pats Bookkeeping Service",
    "wof:placetype":"venue"
},
  "geometry": {"coordinates":[-104.485484,33.442607],"type":"Point"}
}