{
  "type": "Feature",
  "properties": {
    "iso:country":"US",
    "sg:address":"6301 Indian School Rd NE",
    "sg:city":"Albuquerque",
    "sg:classifiers":[
        {
            "category":"Insurance",
            "subcategory":"Insurance Agent",
            "type":"Services"
        }
    ],
    "sg:phone":"+1 505 883 0007",
    "sg:postcode":"87110",
    "sg:province":"NM",
    "wof:name":"United Concordia",
    "wof:placetype":"venue"
},
  "geometry": {"coordinates":[-106.573225,35.101951],"type":"Point"}
}