{
  "type": "Feature",
  "properties": {
    "addr:full":"1113 S Jackson St Tucumcari NM 88401",
    "addr:housenumber":"1113",
    "addr:postcode":"88401",
    "addr:street":"S Jackson St",
    "iso:country":"US",
    "sg:address":"1113 S Jackson St",
    "sg:city":"Tucumcari",
    "sg:classifiers":[
        {
            "category":"Government",
            "subcategory":"Office",
            "type":"Public Place"
        }
    ],
    "sg:phone":"+1 505 461 9803",
    "sg:postcode":"88401",
    "sg:province":"NM",
    "sg:tags":[
        "state",
        "program"
    ],
    "wof:name":"Construction Industries Div",
    "wof:placetype":"venue"
},
  "geometry": {"coordinates":[-103.72107099999999,35.16872],"type":"Point"}
}