{
  "type": "Feature",
  "properties": {
    "iso:country":"US",
    "sg:address":"3900 Central Ave SE",
    "sg:city":"Albuquerque",
    "sg:classifiers":[
        {
            "category":"Retail",
            "subcategory":"Laundry & Dry Cleaning",
            "type":"Services"
        }
    ],
    "sg:phone":"+1 505 268 8774",
    "sg:postcode":"87108",
    "sg:province":"NM",
    "wof:name":"Grande Laundry",
    "wof:placetype":"venue"
},
  "geometry": {"coordinates":[-106.599869,35.079232],"type":"Point"}
}