{
  "type": "Feature",
  "properties": {
    "iso:country":"US",
    "sg:address":"59 Rd 2391",
    "sg:city":"Aztec",
    "sg:classifiers":[
        {
            "category":"Building & Trades",
            "subcategory":"Construction",
            "type":"Services"
        }
    ],
    "sg:phone":"+1 505 334 7221",
    "sg:postcode":"87410",
    "sg:province":"NM",
    "sg:tags":[
        "concrete",
        "contractor"
    ],
    "wof:name":"Gunn Enterprises",
    "wof:placetype":"venue"
},
  "geometry": {"coordinates":[-107.898191,36.923166],"type":"Point"}
}