{
  "type": "Feature",
  "properties": {
    "addr:full":"1750 Central Ave Tularosa NM 88352",
    "addr:housenumber":"1750",
    "addr:postcode":"88352",
    "addr:street":"Central Ave",
    "iso:country":"US",
    "sg:address":"1750 Central Ave",
    "sg:city":"Tularosa",
    "sg:classifiers":[
        {
            "category":"Sports & Exercise",
            "subcategory":"Race Track",
            "type":"Entertainment"
        }
    ],
    "sg:phone":"+1 505 585 9077",
    "sg:postcode":"88352",
    "sg:province":"NM",
    "sg:tags":[
        "operation",
        "racing",
        "or"
    ],
    "wof:name":"Marr Training Stable",
    "wof:placetype":"venue"
},
  "geometry": {"coordinates":[-105.988815,33.081552],"type":"Point"}
}