{
  "type": "Feature",
  "properties": {
    "iso:country":"US",
    "sg:address":"809 San Mateo Blvd NE",
    "sg:city":"Albuquerque",
    "sg:classifiers":[
        {
            "category":"Health Services",
            "subcategory":"Chiropractor",
            "type":"Services"
        }
    ],
    "sg:phone":"+1 505 884 1240",
    "sg:postcode":"87108",
    "sg:province":"NM",
    "wof:name":"L D Schmidt DC",
    "wof:placetype":"venue"
},
  "geometry": {"coordinates":[-106.586275,35.085446],"type":"Point"}
}