{
  "type": "Feature",
  "properties": {
    "addr:full":"1712 N Grimes St Hobbs NM 88240",
    "addr:housenumber":"1712",
    "addr:postcode":"88240",
    "addr:street":"N Grimes St",
    "iso:country":"US",
    "sg:address":"1712 N Grimes St",
    "sg:city":"Hobbs",
    "sg:classifiers":[
        {
            "category":"Retail",
            "subcategory":"Auto Repair",
            "type":"Services"
        }
    ],
    "sg:phone":"+1 505 391 9161",
    "sg:postcode":"88240",
    "sg:province":"NM",
    "sg:tags":[
        "repairing",
        "automobile"
    ],
    "wof:name":"Automotive",
    "wof:placetype":"venue"
},
  "geometry": {"coordinates":[-103.144766,32.719358],"type":"Point"}
}