{
  "type": "Feature",
  "properties": {
    "addr:full":"220 Gold Ave SW Albuquerque NM 87102",
    "addr:housenumber":"220",
    "addr:postcode":"87102",
    "addr:street":"Gold Ave Sw",
    "iso:country":"US",
    "sg:address":"220 Gold Ave SW",
    "sg:city":"Albuquerque",
    "sg:classifiers":[
        {
            "category":"Real Estate",
            "subcategory":"Architect",
            "type":"Services"
        }
    ],
    "sg:phone":"+1 505 842 1278",
    "sg:postcode":"87102",
    "sg:province":"NM",
    "sg:tags":[
        "firm",
        "architectural"
    ],
    "wof:name":"Cherry & See Architects",
    "wof:placetype":"venue"
},
  "geometry": {"coordinates":[-106.650408,35.0833],"type":"Point"}
}