{
  "type": "Feature",
  "properties": {
    "iso:country":"US",
    "sg:address":"314 W Motel Dr",
    "sg:city":"Lordsburg",
    "sg:classifiers":[
        {
            "category":"Retail",
            "subcategory":"Auto Repair",
            "type":"Services"
        }
    ],
    "sg:phone":"+1 505 542 8171",
    "sg:postcode":"88045",
    "sg:province":"NM",
    "sg:tags":[
        "wrecker"
    ],
    "wof:name":"TLB Towing & Repairs",
    "wof:placetype":"venue"
},
  "geometry": {"coordinates":[-108.71127,32.350748],"type":"Point"}
}