{
  "type": "Feature",
  "properties": {
    "iso:country":"US",
    "sg:address":"940 S 2nd St",
    "sg:city":"Raton",
    "sg:classifiers":[
        {
            "category":"Government",
            "subcategory":"Office",
            "type":"Public Place"
        }
    ],
    "sg:phone":"+1 505 445 9130",
    "sg:postcode":"87740",
    "sg:province":"NM",
    "sg:tags":[
        "village"
    ],
    "wof:name":"Raton City Warehouse",
    "wof:placetype":"venue"
},
  "geometry": {"coordinates":[-104.44141,36.892788],"type":"Point"}
}