{
  "type": "Feature",
  "properties": {
    "addr:full":"2401 N Fowler St Hobbs NM 88240",
    "addr:housenumber":"2401",
    "addr:postcode":"88240",
    "addr:street":"N Fowler St",
    "iso:country":"US",
    "sg:address":"2401 N Fowler St",
    "sg:city":"Hobbs",
    "sg:classifiers":[
        {
            "category":"Organizations",
            "subcategory":"Membership Organization",
            "type":"Services"
        }
    ],
    "sg:phone":"+1 505 392 1441",
    "sg:postcode":"88240",
    "sg:province":"NM",
    "wof:name":"Snell Memorial Foundation",
    "wof:placetype":"venue"
},
  "geometry": {"coordinates":[-103.136245,32.727936],"type":"Point"}
}