{
  "type": "Feature",
  "properties": {
    "iso:country":"US",
    "sg:address":"2520 Jefferson St NE",
    "sg:city":"Albuquerque",
    "sg:classifiers":[
        {
            "category":"Wholesale",
            "subcategory":"Electrical",
            "type":"Manufacturing & Wholesale Goods"
        }
    ],
    "sg:phone":"+1 505 888 4000",
    "sg:postcode":"87110",
    "sg:province":"NM",
    "sg:tags":[
        "equipment",
        "alarm",
        "burglar",
        "system",
        "contractor"
    ],
    "sg:website":"www.security-supply.com",
    "wof:name":"Security Supply",
    "wof:placetype":"venue"
},
  "geometry": {"coordinates":[-106.593155,35.107882],"type":"Point"}
}