{
  "type": "Feature",
  "properties": {
    "iso:country":"US",
    "sg:address":"2305 Saturn Pl NE",
    "sg:city":"Albuquerque",
    "sg:classifiers":[
        {
            "category":"Building & Trades",
            "subcategory":"Construction",
            "type":"Services"
        }
    ],
    "sg:phone":"+1 505 298 8929",
    "sg:postcode":"87112",
    "sg:province":"NM",
    "sg:tags":[
        "home"
    ],
    "wof:name":"Hartland Homes By Gene Austin",
    "wof:placetype":"venue"
},
  "geometry": {"coordinates":[-106.509289,35.107644],"type":"Point"}
}