{
  "type": "Feature",
  "properties": {
    "addr:full":"700 1st St Alamogordo NM 88310",
    "addr:housenumber":"700",
    "addr:postcode":"88310",
    "addr:street":"1St St",
    "iso:country":"US",
    "sg:address":"700 1st St",
    "sg:city":"Alamogordo",
    "sg:classifiers":[
        {
            "category":"Professional",
            "type":"Services"
        }
    ],
    "sg:phone":"+1 505 434 4795",
    "sg:postcode":"88310",
    "sg:province":"NM",
    "wof:name":"LA Vida Institute",
    "wof:placetype":"venue"
},
  "geometry": {"coordinates":[-105.95909,32.89015],"type":"Point"}
}