{
  "type": "Feature",
  "properties": {
    "iso:country":"US",
    "sg:address":"3027 Hughes Rd SW",
    "sg:city":"Albuquerque",
    "sg:classifiers":[
        {
            "category":"Building & Trades",
            "subcategory":"Construction",
            "type":"Services"
        }
    ],
    "sg:phone":"+1 505 839 9178",
    "sg:postcode":"87105",
    "sg:province":"NM",
    "sg:tags":[
        "marking",
        "maintenance",
        "parking"
    ],
    "wof:name":"G & C Striping",
    "wof:placetype":"venue"
},
  "geometry": {"coordinates":[-106.709481,35.031825],"type":"Point"}
}