{
  "type": "Feature",
  "properties": {
    "iso:country":"US",
    "sg:address":"1516 San Pedro Dr NE",
    "sg:city":"Albuquerque",
    "sg:classifiers":[
        {
            "category":"Professional",
            "subcategory":"Lawyer & Legal Services",
            "type":"Services"
        }
    ],
    "sg:phone":"+1 505 880 8737",
    "sg:postcode":"87110",
    "sg:province":"NM",
    "sg:tags":[
        "attorney"
    ],
    "sg:website":"www.standridgelawfirm.com",
    "wof:name":"Standridge Law Firm PC",
    "wof:placetype":"venue"
},
  "geometry": {"coordinates":[-106.577466,35.091605],"type":"Point"}
}