{
  "type": "Feature",
  "properties": {
    "iso:country":"US",
    "sg:address":"1710 Muscatel Ave",
    "sg:city":"Carlsbad",
    "sg:classifiers":[
        {
            "category":"Wholesale",
            "subcategory":"Sporting Goods",
            "type":"Manufacturing & Wholesale Goods"
        }
    ],
    "sg:phone":"+1 505 885 1600",
    "sg:postcode":"88220",
    "sg:province":"NM",
    "sg:tags":[
        "course",
        "golf",
        "equipment"
    ],
    "wof:name":"Forestore Storage",
    "wof:placetype":"venue"
},
  "geometry": {"coordinates":[-104.220579,32.452079],"type":"Point"}
}