{
  "type": "Feature",
  "properties": {
    "addr:full":"294 N Cam del Pueblo Bernalillo NM 87004",
    "addr:housenumber":"294",
    "addr:postcode":"87004",
    "addr:street":"N Cam Del Pueblo",
    "iso:country":"US",
    "sg:address":"294 N Cam del Pueblo",
    "sg:city":"Bernalillo",
    "sg:classifiers":[
        {
            "category":"Home & Garden",
            "subcategory":"Furniture",
            "type":"Retail Goods"
        }
    ],
    "sg:phone":"+1 505 867 4440",
    "sg:postcode":"87004",
    "sg:province":"NM",
    "sg:tags":[
        "cabinet"
    ],
    "wof:name":"Rombin & Marshall Co",
    "wof:placetype":"venue"
},
  "geometry": {"coordinates":[-106.541382,35.323218],"type":"Point"}
}