{
  "type": "Feature",
  "properties": {
    "addr:full":"9500 Constitution Ave NE Albuquerque NM 87112",
    "addr:housenumber":"9500",
    "addr:postcode":"87112",
    "addr:street":"Constitution Ave Ne",
    "iso:country":"US",
    "sg:address":"9500 Constitution Ave NE",
    "sg:city":"Albuquerque",
    "sg:classifiers":[
        {
            "category":"Organizations",
            "subcategory":"Religious Organization",
            "type":"Services"
        }
    ],
    "sg:phone":"+1 505 298 5596",
    "sg:postcode":"87112",
    "sg:province":"NM",
    "sg:tags":[
        "church"
    ],
    "wof:name":"St Pauls United Methdst Church",
    "wof:placetype":"venue"
},
  "geometry": {"coordinates":[-106.539693,35.094531],"type":"Point"}
}