{
  "type": "Feature",
  "properties": {
    "iso:country":"US",
    "sg:address":"1105 E 23rd St",
    "sg:city":"Farmington",
    "sg:classifiers":[
        {
            "category":"Shopping",
            "subcategory":"Department Store",
            "type":"Retail Goods"
        }
    ],
    "sg:phone":"+1 505 326 3693",
    "sg:postcode":"87401",
    "sg:province":"NM",
    "sg:tags":[
        "shop"
    ],
    "wof:name":"Sweet By Design",
    "wof:placetype":"venue"
},
  "geometry": {"coordinates":[-108.19349200000001,36.750923],"type":"Point"}
}