{
  "type": "Feature",
  "properties": {
    "addr:full":"100 Phillips Rd Farmington NM 87401",
    "addr:housenumber":"100",
    "addr:postcode":"87401",
    "addr:street":"Phillips Rd",
    "iso:country":"US",
    "sg:address":"100 Phillips Rd",
    "sg:city":"Farmington",
    "sg:classifiers":[
        {
            "category":"Restaurant",
            "type":"Food & Drink"
        }
    ],
    "sg:phone":"+1 505 326 1979",
    "sg:postcode":"87401",
    "sg:province":"NM",
    "sg:website":"www.subway.com",
    "wof:name":"Subway Sandwiches & Salads",
    "wof:placetype":"venue"
},
  "geometry": {"coordinates":[-108.233287,36.733619],"type":"Point"}
}