{
  "type": "Feature",
  "properties": {
    "iso:country":"US",
    "sg:address":"4001 Office Ct",
    "sg:city":"Santa Fe",
    "sg:classifiers":[
        {
            "category":"Manufacturing",
            "subcategory":"Glass & Minerals",
            "type":"Manufacturing & Wholesale Goods"
        }
    ],
    "sg:phone":"+1 505 474 6161",
    "sg:postcode":"87507",
    "sg:province":"NM",
    "sg:tags":[
        "treated",
        "or"
    ],
    "wof:name":"Strathmore Minerals Corp",
    "wof:placetype":"venue"
},
  "geometry": {"coordinates":[-106.015951,35.63296],"type":"Point"}
}