{
  "type": "Feature",
  "properties": {
    "iso:country":"US",
    "sg:address":"1200 W Summit St",
    "sg:city":"Roswell",
    "sg:classifiers":[
        {
            "category":"Professional",
            "subcategory":"Business Services",
            "type":"Services"
        }
    ],
    "sg:phone":"+1 505 625 2454",
    "sg:postcode":"88203",
    "sg:province":"NM",
    "sg:tags":[
        "water",
        "treatment"
    ],
    "wof:name":"Aqua Pro",
    "wof:placetype":"venue"
},
  "geometry": {"coordinates":[-104.538966,33.383668],"type":"Point"}
}