{
  "type": "Feature",
  "properties": {
    "iso:country":"US",
    "sg:address":"850 Salida Sandia SW",
    "sg:city":"Albuquerque",
    "sg:classifiers":[
        {
            "category":"Retail",
            "subcategory":"Animal Services",
            "type":"Services"
        }
    ],
    "sg:phone":"+1 505 873 9043",
    "sg:postcode":"87105",
    "sg:province":"NM",
    "sg:tags":[
        "breeder",
        "horse"
    ],
    "wof:name":"Horses Unlimited",
    "wof:placetype":"venue"
},
  "geometry": {"coordinates":[-106.66886599999999,34.971283],"type":"Point"}
}