{
  "type": "Feature",
  "properties": {
    "iso:country":"US",
    "sg:address":"333 S Campo St",
    "sg:city":"Las Cruces",
    "sg:classifiers":[
        {
            "category":"Professional",
            "subcategory":"Lawyer & Legal Services",
            "type":"Services"
        }
    ],
    "sg:phone":"+1 505 527 1660",
    "sg:postcode":"88001",
    "sg:province":"NM",
    "wof:name":"Winchester & Assciates",
    "wof:placetype":"venue"
},
  "geometry": {"coordinates":[-106.77578699999999,32.307877],"type":"Point"}
}