{
  "type": "Feature",
  "properties": {
    "iso:country":"US",
    "sg:address":"1120 NW County Rd",
    "sg:city":"Hobbs",
    "sg:classifiers":[
        {
            "category":"Insurance",
            "subcategory":"Insurance Agent",
            "type":"Services"
        }
    ],
    "sg:phone":"+1 505 397 3561",
    "sg:postcode":"88240",
    "sg:province":"NM",
    "wof:name":"Holly Peden",
    "wof:placetype":"venue"
},
  "geometry": {"coordinates":[-103.175002,32.718163],"type":"Point"}
}