{
  "type": "Feature",
  "properties": {
    "iso:country":"US",
    "sg:address":"403 E Lohman Ave",
    "sg:city":"Las Cruces",
    "sg:classifiers":[
        {
            "category":"Banks & Credit Unions",
            "subcategory":"Bank",
            "type":"Services"
        }
    ],
    "sg:phone":"+1 505 527 8228",
    "sg:postcode":"88001",
    "sg:province":"NM",
    "sg:tags":[
        "loan"
    ],
    "wof:name":"Your Credit Inc",
    "wof:placetype":"venue"
},
  "geometry": {"coordinates":[-106.77334500000001,32.307118],"type":"Point"}
}