{
  "type": "Feature",
  "properties": {
    "addr:full":"408 Granado St Tularosa NM 88352",
    "addr:housenumber":"408",
    "addr:postcode":"88352",
    "addr:street":"Granado St",
    "iso:country":"US",
    "sg:address":"408 Granado St",
    "sg:city":"Tularosa",
    "sg:classifiers":[
        {
            "category":"Professional",
            "subcategory":"Accounting & Tax Preparation",
            "type":"Services"
        }
    ],
    "sg:phone":"+1 505 585 6558",
    "sg:postcode":"88352",
    "sg:province":"NM",
    "sg:tags":[
        "bookkeeping",
        "general"
    ],
    "wof:name":"Accurate Bookkeeping",
    "wof:placetype":"venue"
},
  "geometry": {"coordinates":[-106.017752,33.072454],"type":"Point"}
}