{
  "type": "Feature",
  "properties": {
    "iso:country":"US",
    "sg:address":"802 S Solano Dr",
    "sg:city":"Las Cruces",
    "sg:classifiers":[
        {
            "category":"Building & Trades",
            "subcategory":"Equipment Rental",
            "type":"Services"
        }
    ],
    "sg:phone":"+1 505 647 3100",
    "sg:postcode":"88001",
    "sg:province":"NM",
    "sg:tags":[
        "leasing",
        "furniture"
    ],
    "wof:name":"Casa Rentals",
    "wof:placetype":"venue"
},
  "geometry": {"coordinates":[-106.763759,32.304116],"type":"Point"}
}