{
  "type": "Feature",
  "properties": {
    "iso:country":"US",
    "sg:address":"2752 N Roadrunner Pkwy",
    "sg:city":"Las Cruces",
    "sg:classifiers":[
        {
            "category":"Organizations",
            "subcategory":"Religious Organization",
            "type":"Services"
        }
    ],
    "sg:phone":"+1 505 522 0465",
    "sg:postcode":"88011",
    "sg:province":"NM",
    "wof:name":"Mission Lutheran Church",
    "wof:placetype":"venue"
},
  "geometry": {"coordinates":[-106.75049,32.3515],"type":"Point"}
}