{
  "type": "Feature",
  "properties": {
    "iso:country":"US",
    "sg:address":"4551 Highway 64",
    "sg:city":"Farmington",
    "sg:classifiers":[
        {
            "category":"Autos & Motor Vehicles",
            "subcategory":"Automobile Sales",
            "type":"Retail Goods"
        },
        {
            "category":"Autos & Motor Vehicles",
            "subcategory":"Auto Supplies",
            "type":"Retail Goods"
        }
    ],
    "sg:phone":"+1 505 516 0834",
    "sg:postcode":"87401",
    "sg:province":"NM",
    "sg:tags":[
        "part",
        "salvage"
    ],
    "wof:name":"Highway 64 Truck & Auto Salvage",
    "wof:placetype":"venue"
},
  "geometry": {"coordinates":[-108.315991,36.731032],"type":"Point"}
}