{
  "type": "Feature",
  "properties": {
    "iso:country":"US",
    "sg:address":"417 Tramway Blvd NE",
    "sg:city":"Albuquerque",
    "sg:classifiers":[
        {
            "category":"Retail",
            "subcategory":"Self-service Laundry",
            "type":"Services"
        }
    ],
    "sg:phone":"+1 505 237 9600",
    "sg:postcode":"87123",
    "sg:province":"NM",
    "wof:name":"Spincycle Coin Laundry",
    "wof:placetype":"venue"
},
  "geometry": {"coordinates":[-106.49597,35.072318],"type":"Point"}
}