{
  "type": "Feature",
  "properties": {
    "iso:country":"US",
    "sg:address":"10500 4th St NW",
    "sg:city":"Albuquerque",
    "sg:classifiers":[
        {
            "category":"Restaurant",
            "type":"Food & Drink"
        }
    ],
    "sg:menulink":"http://www.allmenus.com/nm/albuquerque/27015-el-pinto-restaurant/menu/",
    "sg:phone":"+1 505 898 1771",
    "sg:postcode":"87114",
    "sg:province":"NM",
    "sg:tags":[
        "mexican"
    ],
    "wof:name":"El Pinto Restaurant",
    "wof:placetype":"venue"
},
  "geometry": {"coordinates":[-106.612481,35.206871],"type":"Point"}
}