{
  "type": "Feature",
  "properties": {
    "addr:full":"1155 S 2nd St Raton NM 87740",
    "addr:housenumber":"1155",
    "addr:postcode":"87740",
    "addr:street":"S 2Nd St",
    "iso:country":"US",
    "sg:address":"1155 S 2nd St",
    "sg:city":"Raton",
    "sg:classifiers":[
        {
            "category":"Restaurant",
            "type":"Food & Drink"
        }
    ],
    "sg:phone":"+1 505 445 2933",
    "sg:postcode":"87740",
    "sg:province":"NM",
    "sg:tags":[
        "eating"
    ],
    "wof:name":"Shanghai Restaurant Inc",
    "wof:placetype":"venue"
},
  "geometry": {"coordinates":[-104.440146,36.885771],"type":"Point"}
}