{
  "type": "Feature",
  "properties": {
    "iso:country":"US",
    "sg:address":"2929 Carlisle Blvd NE",
    "sg:city":"Albuquerque",
    "sg:classifiers":[
        {
            "category":"Restaurant",
            "type":"Food & Drink"
        }
    ],
    "sg:menulink":"http://www.allmenus.com/nm/albuquerque/164144-wienerschnitzel/menu/",
    "sg:phone":"+1 505 883 9994",
    "sg:postcode":"87110",
    "sg:province":"NM",
    "sg:tags":[
        "sandwich",
        "dog",
        "burger",
        "hot",
        "wrap",
        "american"
    ],
    "wof:name":"Wienerschnitzel",
    "wof:placetype":"venue"
},
  "geometry": {"coordinates":[-106.604344,35.115291],"type":"Point"}
}