{
  "type": "Feature",
  "properties": {
    "iso:country":"US",
    "sg:address":"1301 Eubank Blvd NE",
    "sg:city":"Albuquerque",
    "sg:classifiers":[
        {
            "category":"Restaurant",
            "type":"Food & Drink"
        }
    ],
    "sg:phone":"+1 505 291 9713",
    "sg:postcode":"87112",
    "sg:province":"NM",
    "wof:name":"Dona Pepa Mexican Restaurant",
    "wof:placetype":"venue"
},
  "geometry": {"coordinates":[-106.532712,35.094526],"type":"Point"}
}