{
  "type": "Feature",
  "properties": {
    "addr:full":"2351 S Main St Las Cruces NM 88005",
    "addr:housenumber":"2351",
    "addr:postcode":"88005",
    "addr:street":"S Main St",
    "iso:country":"US",
    "sg:address":"2351 S Main St",
    "sg:city":"Las Cruces",
    "sg:classifiers":[
        {
            "category":"Shopping",
            "subcategory":"Pharmacy",
            "type":"Retail Goods"
        }
    ],
    "sg:phone":"+1 505 865 2089",
    "sg:postcode":"88005",
    "sg:province":"NM",
    "wof:name":"Sav-On Drugs",
    "wof:placetype":"venue"
},
  "geometry": {"coordinates":[-106.77318,32.285791],"type":"Point"}
}