{
  "type": "Feature",
  "properties": {
    "addr:full":"2423 Willow Rd Los Lunas NM 87031",
    "addr:housenumber":"2423",
    "addr:postcode":"87031",
    "addr:street":"Willow Rd",
    "iso:country":"US",
    "sg:address":"2423 Willow Rd",
    "sg:city":"Los Lunas",
    "sg:classifiers":[
        {
            "category":"Home & Garden",
            "subcategory":"Mobile Homes",
            "type":"Retail Goods"
        }
    ],
    "sg:phone":"+1 505 865 1881",
    "sg:postcode":"87031",
    "sg:province":"NM",
    "sg:tags":[
        "repair"
    ],
    "wof:name":"Star Light",
    "wof:placetype":"venue"
},
  "geometry": {"coordinates":[-106.728184,34.835137],"type":"Point"}
}