{
  "type": "Feature",
  "properties": {
    "addr:full":"200 N Indio Ave Portales NM 88130",
    "addr:housenumber":"200",
    "addr:postcode":"88130",
    "addr:street":"N Indio Ave",
    "iso:country":"US",
    "sg:address":"200 N Indio Ave",
    "sg:city":"Portales",
    "sg:classifiers":[
        {
            "category":"Professional",
            "type":"Services"
        }
    ],
    "sg:phone":"+1 505 356 0489",
    "sg:postcode":"88130",
    "sg:province":"NM",
    "sg:tags":[
        "establishment"
    ],
    "wof:name":"Iglesia Bautista Bethel",
    "wof:placetype":"venue"
},
  "geometry": {"coordinates":[-103.32437899999999,34.19075],"type":"Point"}
}