{
  "type": "Feature",
  "properties": {
    "iso:country":"US",
    "sg:address":"7511 Cerrillos Rd",
    "sg:city":"Santa Fe",
    "sg:classifiers":[
        {
            "category":"Home & Garden",
            "subcategory":"Mobile Homes",
            "type":"Retail Goods"
        }
    ],
    "sg:phone":"+1 505 473 3483",
    "sg:postcode":"87507",
    "sg:province":"NM",
    "wof:name":"Homes Of America",
    "wof:placetype":"venue"
},
  "geometry": {"coordinates":[-106.02802,35.621989],"type":"Point"}
}