{
  "type": "Feature",
  "properties": {
    "addr:full":"2900 Willow Creek Ln Las Cruces NM 88007",
    "addr:housenumber":"2900",
    "addr:postcode":"88007",
    "addr:street":"Willow Creek Ln",
    "iso:country":"US",
    "sg:address":"2900 Willow Creek Ln",
    "sg:city":"Las Cruces",
    "sg:classifiers":[
        {
            "category":"Farming",
            "subcategory":"Crops",
            "type":"Manufacturing & Wholesale Goods"
        }
    ],
    "sg:phone":"+1 505 526 5715",
    "sg:postcode":"88007",
    "sg:province":"NM",
    "sg:tags":[
        "grove",
        "nut",
        "tree"
    ],
    "wof:name":"Hoffman Farm",
    "wof:placetype":"venue"
},
  "geometry": {"coordinates":[-106.83432000000001,32.341969],"type":"Point"}
}