{
  "type": "Feature",
  "properties": {
    "iso:country":"US",
    "sg:address":"1137 Maple St",
    "sg:city":"Bernalillo",
    "sg:classifiers":[
        {
            "category":"Building & Trades",
            "subcategory":"Cleaning & Sanitation",
            "type":"Services"
        }
    ],
    "sg:phone":"+1 505 867 5765",
    "sg:postcode":"87004",
    "sg:province":"NM",
    "sg:tags":[
        "maintenance"
    ],
    "wof:name":"White Glove Janitorial",
    "wof:placetype":"venue"
},
  "geometry": {"coordinates":[-106.557382,35.302021],"type":"Point"}
}