{
  "type": "Feature",
  "properties": {
    "addr:full":"88 Vis del Oro Cerrillos NM 87010",
    "addr:postcode":"87010",
    "addr:street":"Del Oro",
    "iso:country":"US",
    "sg:address":"88 Vis del Oro",
    "sg:city":"Cerrillos",
    "sg:classifiers":[
        {
            "category":"Professional",
            "subcategory":"Business Services",
            "type":"Services"
        }
    ],
    "sg:phone":"+1 505 438 3080",
    "sg:postcode":"87010",
    "sg:province":"NM",
    "wof:name":"Janis Group Inc",
    "wof:placetype":"venue"
},
  "geometry": {"coordinates":[-106.13504500000001,35.363618],"type":"Point"}
}