{
  "type": "Feature",
  "properties": {
    "iso:country":"US",
    "sg:address":"509 Ida Pl NE",
    "sg:city":"Albuquerque",
    "sg:classifiers":[
        {
            "category":"Professional",
            "subcategory":"Art Services",
            "type":"Services"
        }
    ],
    "sg:phone":"+1 505 299 0713",
    "sg:postcode":"87123",
    "sg:province":"NM",
    "sg:tags":[
        "graphic",
        "designer"
    ],
    "wof:name":"Graphic Bliss Graphic Design",
    "wof:placetype":"venue"
},
  "geometry": {"coordinates":[-106.522761,35.074896],"type":"Point"}
}