{
  "type": "Feature",
  "properties": {
    "iso:country":"US",
    "sg:address":"420 Central Ave SW",
    "sg:city":"Albuquerque",
    "sg:classifiers":[
        {
            "category":"Professional",
            "subcategory":"Engineering",
            "type":"Services"
        }
    ],
    "sg:phone":"+1 505 242 2280",
    "sg:postcode":"87102",
    "sg:province":"NM",
    "sg:tags":[
        "engineer"
    ],
    "wof:name":"Bandi Engineering",
    "wof:placetype":"venue"
},
  "geometry": {"coordinates":[-106.652593,35.08477],"type":"Point"}
}