{
  "type": "Feature",
  "properties": {
    "addr:full":"2112 Moon St NE Albuquerque NM 87112",
    "addr:housenumber":"2112",
    "addr:postcode":"87112",
    "addr:street":"Moon St Ne",
    "iso:country":"US",
    "sg:address":"2112 Moon St NE",
    "sg:city":"Albuquerque",
    "sg:classifiers":[
        {
            "category":"Real Estate",
            "subcategory":"Real Estate Operator",
            "type":"Services"
        }
    ],
    "sg:phone":"+1 505 298 9330",
    "sg:postcode":"87112",
    "sg:province":"NM",
    "sg:tags":[
        "building",
        "apartment"
    ],
    "wof:name":"Executive East Apartments",
    "wof:placetype":"venue"
},
  "geometry": {"coordinates":[-106.54192999999999,35.108965],"type":"Point"}
}