{
  "type": "Feature",
  "properties": {
    "addr:full":"83 Upper San Pedro Rd Espanola NM 87532",
    "addr:housenumber":"83",
    "addr:postcode":"87532",
    "addr:street":"Upper San Pedro Rd",
    "iso:country":"US",
    "sg:address":"83 Upper San Pedro Rd",
    "sg:city":"Espanola",
    "sg:classifiers":[
        {
            "category":"Professional",
            "subcategory":"Accounting & Tax Preparation",
            "type":"Services"
        }
    ],
    "sg:phone":"+1 505 753 4300",
    "sg:postcode":"87532",
    "sg:province":"NM",
    "sg:tags":[
        "accountant"
    ],
    "wof:name":"Jose M Montoya Tax Svc",
    "wof:placetype":"venue"
},
  "geometry": {"coordinates":[-106.066472,35.977929],"type":"Point"}
}