{
  "type": "Feature",
  "properties": {
    "iso:country":"US",
    "sg:address":"2187 McNutt Rd",
    "sg:city":"Sunland Park",
    "sg:classifiers":[
        {
            "category":"Shopping",
            "subcategory":"Books",
            "type":"Retail Goods"
        }
    ],
    "sg:phone":"+1 505 589 1300",
    "sg:postcode":"88063",
    "sg:province":"NM",
    "sg:tags":[
        "dealer"
    ],
    "wof:name":"Angel Emmanuel Christian Book",
    "wof:placetype":"venue"
},
  "geometry": {"coordinates":[-106.577263,31.799403],"type":"Point"}
}