{
  "type": "Feature",
  "properties": {
    "iso:country":"US",
    "sg:address":"1819 N Turner St",
    "sg:city":"Hobbs",
    "sg:classifiers":[
        {
            "category":"Banks & Credit Unions",
            "subcategory":"Investment Brokerage",
            "type":"Services"
        }
    ],
    "sg:phone":"+1 505 393 2274",
    "sg:postcode":"88240",
    "sg:province":"NM",
    "sg:tags":[
        "advisory",
        "financial"
    ],
    "wof:name":"Farm Bureau Financial Svc",
    "wof:placetype":"venue"
},
  "geometry": {"coordinates":[-103.143449,32.721726],"type":"Point"}
}