{
  "type": "Feature",
  "properties": {
    "iso:country":"US",
    "sg:address":"1820 S 1st St",
    "sg:city":"Artesia",
    "sg:classifiers":[
        {
            "category":"Travel",
            "subcategory":"Hotels & Motels",
            "type":"Entertainment"
        }
    ],
    "sg:phone":"+1 505 746 9801",
    "sg:postcode":"88210",
    "sg:province":"NM",
    "sg:tags":[
        "operation"
    ],
    "wof:name":"Artesia Inn",
    "wof:placetype":"venue"
},
  "geometry": {"coordinates":[-104.395714,32.822023],"type":"Point"}
}