{
  "type": "Feature",
  "properties": {
    "iso:country":"US",
    "sg:address":"500 S 3rd St",
    "sg:city":"Raton",
    "sg:classifiers":[
        {
            "category":"Education",
            "subcategory":"School",
            "type":"Public Place"
        }
    ],
    "sg:phone":"+1 505 445 9881",
    "sg:postcode":"87740",
    "sg:province":"NM",
    "sg:tags":[
        "middle"
    ],
    "wof:name":"Raton Middle School",
    "wof:placetype":"venue"
},
  "geometry": {"coordinates":[-104.441928,36.897013],"type":"Point"}
}