{
  "type": "Feature",
  "properties": {
    "iso:country":"US",
    "sg:address":"110 E 11th St",
    "sg:city":"Silver City",
    "sg:classifiers":[
        {
            "category":"Shopping",
            "subcategory":"Clothing, Apparel, & Fashions",
            "type":"Retail Goods"
        }
    ],
    "sg:phone":"+1 505 534 4463",
    "sg:postcode":"88061",
    "sg:province":"NM",
    "sg:tags":[
        "shop",
        "bridal"
    ],
    "wof:name":"Jessica's Bridal Boutique",
    "wof:placetype":"venue"
},
  "geometry": {"coordinates":[-108.27490299999999,32.776417],"type":"Point"}
}