{
  "type": "Feature",
  "properties": {
    "iso:country":"US",
    "sg:address":"9010 Cordova Ave NE",
    "sg:city":"Albuquerque",
    "sg:classifiers":[
        {
            "category":"Building & Trades",
            "subcategory":"Plumbing",
            "type":"Services"
        }
    ],
    "sg:phone":"+1 505 292 4497",
    "sg:postcode":"87112",
    "sg:province":"NM",
    "sg:tags":[
        "cooling",
        "heating",
        "contractor"
    ],
    "wof:name":"G & A Heating & Cooling",
    "wof:placetype":"venue"
},
  "geometry": {"coordinates":[-106.539345,35.110236],"type":"Point"}
}