{
  "type": "Feature",
  "properties": {
    "addr:full":"701 Dalies Ave Belen NM 87002",
    "addr:housenumber":"701",
    "addr:postcode":"87002",
    "addr:street":"Dalies Ave",
    "iso:country":"US",
    "sg:address":"701 Dalies Ave",
    "sg:city":"Belen",
    "sg:classifiers":[
        {
            "category":"Wholesale",
            "subcategory":"Medical Equipment & Supplies",
            "type":"Manufacturing & Wholesale Goods"
        }
    ],
    "sg:phone":"+1 505 864 1109",
    "sg:postcode":"87002",
    "sg:province":"NM",
    "sg:tags":[
        "physician",
        "surgeon"
    ],
    "sg:website":"www.sharencarepharmacy.com",
    "wof:name":"Share 'n Care Pharmacy & Med",
    "wof:placetype":"venue"
},
  "geometry": {"coordinates":[-106.775403,34.661001],"type":"Point"}
}