{
  "type": "Feature",
  "properties": {
    "addr:full":"800 N Miranda St Las Cruces NM 88005",
    "addr:housenumber":"800",
    "addr:postcode":"88005",
    "addr:street":"N Miranda St",
    "iso:country":"US",
    "sg:address":"800 N Miranda St",
    "sg:city":"Las Cruces",
    "sg:classifiers":[
        {
            "category":"Organizations",
            "subcategory":"Religious Organization",
            "type":"Services"
        }
    ],
    "sg:phone":"+1 505 526 6442",
    "sg:postcode":"88005",
    "sg:province":"NM",
    "wof:name":"Church Of Christ",
    "wof:placetype":"venue"
},
  "geometry": {"coordinates":[-106.78708,32.315349],"type":"Point"}
}