{
  "type": "Feature",
  "properties": {
    "addr:full":"2300 Candelaria Rd NE Albuquerque NM 87107",
    "addr:housenumber":"2300",
    "addr:postcode":"87107",
    "addr:street":"Candelaria Rd Ne",
    "iso:country":"US",
    "sg:address":"2300 Candelaria Rd NE",
    "sg:city":"Albuquerque",
    "sg:classifiers":[
        {
            "category":"Building & Trades",
            "subcategory":"Electrical",
            "type":"Services"
        }
    ],
    "sg:phone":"+1 505 830 9007",
    "sg:postcode":"87107",
    "sg:province":"NM",
    "sg:tags":[
        "electronic",
        "contractor"
    ],
    "wof:name":"Digital Electrical Contg LLC",
    "wof:placetype":"venue"
},
  "geometry": {"coordinates":[-106.619208,35.114794],"type":"Point"}
}