{
  "type": "Feature",
  "properties": {
    "iso:country":"US",
    "sg:address":"10918 Cochiti Rd SE",
    "sg:city":"Albuquerque",
    "sg:classifiers":[
        {
            "category":"Manufacturing",
            "subcategory":"Jewelry",
            "type":"Manufacturing & Wholesale Goods"
        }
    ],
    "sg:phone":"+1 505 298 3096",
    "sg:postcode":"87123",
    "sg:province":"NM",
    "wof:name":"Blue Canyon Jewelry",
    "wof:placetype":"venue"
},
  "geometry": {"coordinates":[-106.526802,35.070266],"type":"Point"}
}