{
  "type": "Feature",
  "properties": {
    "addr:full":"2805 Bright Star Dr NW Albuquerque NM 87120",
    "addr:housenumber":"2805",
    "addr:postcode":"87120",
    "addr:street":"Bright Star Dr Nw",
    "iso:country":"US",
    "sg:address":"2805 Bright Star Dr NW",
    "sg:city":"Albuquerque",
    "sg:classifiers":[
        {
            "category":"Wholesale",
            "subcategory":"Groceries",
            "type":"Manufacturing & Wholesale Goods"
        }
    ],
    "sg:phone":"+1 505 833 1673",
    "sg:postcode":"87120",
    "sg:province":"NM",
    "sg:tags":[
        "organization",
        "religious"
    ],
    "wof:name":"David Oller",
    "wof:placetype":"venue"
},
  "geometry": {"coordinates":[-106.70496300000001,35.115483],"type":"Point"}
}