{
  "type": "Feature",
  "properties": {
    "iso:country":"US",
    "sg:address":"300 Unser Blvd SE",
    "sg:city":"Rio Rancho",
    "sg:classifiers":[
        {
            "category":"Bars & Pubs",
            "type":"Food & Drink"
        }
    ],
    "sg:phone":"+1 505 892 1211",
    "sg:postcode":"87124",
    "sg:province":"NM",
    "sg:tags":[
        "lounge",
        "bar"
    ],
    "wof:name":"Anchor Inn",
    "wof:placetype":"venue"
},
  "geometry": {"coordinates":[-106.696821,35.254331],"type":"Point"}
}