{
  "type": "Feature",
  "properties": {
    "iso:country":"US",
    "sg:address":"101 Nymeyer Rd",
    "sg:city":"Loving",
    "sg:classifiers":[
        {
            "category":"Freight",
            "type":"Transportation"
        }
    ],
    "sg:phone":"+1 505 745 3741",
    "sg:postcode":"88256",
    "sg:province":"NM",
    "sg:tags":[
        "operator",
        "local",
        "trucking"
    ],
    "wof:name":"Kimberly Ballard",
    "wof:placetype":"venue"
},
  "geometry": {"coordinates":[-104.083871,32.298012],"type":"Point"}
}