{
  "type": "Feature",
  "properties": {
    "addr:full":"1203 Coal Ave SE Ste A Albuquerque NM 87106",
    "addr:housenumber":"1203",
    "addr:postcode":"87106",
    "addr:street":"Coal Ave Se Ste A",
    "iso:country":"US",
    "sg:address":"1203 Coal Ave SE Ste A",
    "sg:city":"Albuquerque",
    "sg:classifiers":[
        {
            "category":"Health Services",
            "subcategory":"Doctor",
            "type":"Services"
        }
    ],
    "sg:phone":"+1 505 244 9040",
    "sg:postcode":"87106",
    "sg:province":"NM",
    "sg:tags":[
        "medicine",
        "physician",
        "surgeon",
        "internal",
        "surgeons"
    ],
    "wof:name":"Patricia Morrow Md",
    "wof:placetype":"venue"
},
  "geometry": {"coordinates":[-106.63458799999999,35.078335],"type":"Point"}
}