{
  "type": "Feature",
  "properties": {
    "iso:country":"US",
    "sg:address":"508 N Main St",
    "sg:city":"Clovis",
    "sg:classifiers":[
        {
            "category":"Real Estate",
            "subcategory":"Real Estate Services",
            "type":"Services"
        }
    ],
    "sg:phone":"+1 505 762 1063",
    "sg:postcode":"88101",
    "sg:province":"NM",
    "sg:tags":[
        "company",
        "title"
    ],
    "wof:name":"Aztec Abstract & Title Ins Inc",
    "wof:placetype":"venue"
},
  "geometry": {"coordinates":[-103.20543499999999,34.403822],"type":"Point"}
}