{
  "type": "Feature",
  "properties": {
    "iso:country":"US",
    "sg:address":"314 el Pueblo Rd NW",
    "sg:city":"Albuquerque",
    "sg:classifiers":[
        {
            "category":"Wholesale",
            "subcategory":"Construction Materials",
            "type":"Manufacturing & Wholesale Goods"
        },
        {
            "category":"Home & Garden",
            "subcategory":"Building Materials",
            "type":"Retail Goods"
        }
    ],
    "sg:phone":"+1 505 897 9985",
    "sg:postcode":"87114",
    "sg:province":"NM",
    "sg:tags":[
        "windows"
    ],
    "sg:website":"www.pinonwindow.com",
    "wof:name":"Pinon Window & Door Co",
    "wof:placetype":"venue"
},
  "geometry": {"coordinates":[-106.626432,35.176992],"type":"Point"}
}