{
  "type": "Feature",
  "properties": {
    "iso:country":"US",
    "sg:address":"369 Montezuma Ave",
    "sg:city":"Santa Fe",
    "sg:classifiers":[
        {
            "category":"Professional",
            "subcategory":"Business Services",
            "type":"Services"
        }
    ],
    "sg:phone":"+1 505 474 8686",
    "sg:postcode":"87501",
    "sg:province":"NM",
    "sg:tags":[
        "design"
    ],
    "wof:name":"Verde Design Group LLC",
    "wof:placetype":"venue"
},
  "geometry": {"coordinates":[-105.944181,35.684633],"type":"Point"}
}