{
  "type": "Feature",
  "properties": {
    "iso:country":"US",
    "sg:address":"2861 Cerrillos Rd",
    "sg:city":"Santa Fe",
    "sg:classifiers":[
        {
            "category":"Restaurant",
            "type":"Food & Drink"
        }
    ],
    "sg:phone":"+1 505 471 1750",
    "sg:postcode":"87507",
    "sg:province":"NM",
    "sg:tags":[
        "eating"
    ],
    "sg:website":"www.sonic.com",
    "wof:name":"Sonic Drive-In",
    "wof:placetype":"venue"
},
  "geometry": {"coordinates":[-105.987971,35.657293],"type":"Point"}
}