{
  "type": "Feature",
  "properties": {
    "iso:country":"US",
    "sg:address":"711 Cam del Pueblo",
    "sg:city":"Bernalillo",
    "sg:classifiers":[
        {
            "category":"Government",
            "subcategory":"Office",
            "type":"Public Place"
        }
    ],
    "sg:phone":"+1 505 867 7500",
    "sg:postcode":"87004",
    "sg:province":"NM",
    "wof:name":"Sandoval County Community Svc",
    "wof:placetype":"venue"
},
  "geometry": {"coordinates":[-106.548181,35.306298],"type":"Point"}
}