{
  "type": "Feature",
  "properties": {
    "iso:country":"US",
    "sg:address":"1110 N Main St",
    "sg:city":"Roswell",
    "sg:classifiers":[
        {
            "category":"Banks & Credit Unions",
            "subcategory":"Bank",
            "type":"Services"
        }
    ],
    "sg:phone":"+1 505 623 9685",
    "sg:postcode":"88201",
    "sg:province":"NM",
    "sg:tags":[
        "machine",
        "teller",
        "automated"
    ],
    "wof:name":"Atm USA",
    "wof:placetype":"venue"
},
  "geometry": {"coordinates":[-104.52284299999999,33.40563],"type":"Point"}
}