{
  "type": "Feature",
  "properties": {
    "addr:full":"10732 Pueblo Pl NW Albuquerque NM 87114",
    "addr:housenumber":"10732",
    "addr:postcode":"87114",
    "addr:street":"Pueblo Pl Nw",
    "iso:country":"US",
    "sg:address":"10732 Pueblo Pl NW",
    "sg:city":"Albuquerque",
    "sg:classifiers":[
        {
            "category":"Professional",
            "subcategory":"Engineering",
            "type":"Services"
        }
    ],
    "sg:phone":"+1 505 930 5150",
    "sg:postcode":"87114",
    "sg:province":"NM",
    "sg:tags":[
        "engineer"
    ],
    "wof:name":"GSL Network Consulting",
    "wof:placetype":"venue"
},
  "geometry": {"coordinates":[-106.666726,35.210429],"type":"Point"}
}