{
  "type": "Feature",
  "properties": {
    "addr:full":"1091 W Murray Dr Farmington NM 87401",
    "addr:housenumber":"1091",
    "addr:postcode":"87401",
    "addr:street":"W Murray Dr",
    "iso:country":"US",
    "sg:address":"1091 W Murray Dr",
    "sg:city":"Farmington",
    "sg:classifiers":[
        {
            "category":"Social Services",
            "subcategory":"Adult Care",
            "type":"Services"
        }
    ],
    "sg:phone":"+1 505 324 6200",
    "sg:postcode":"87401",
    "sg:province":"NM",
    "sg:tags":[
        "home",
        "residential"
    ],
    "sg:website":"www.lcca.com",
    "wof:name":"Bridge At Life Care Ctr",
    "wof:placetype":"venue"
},
  "geometry": {"coordinates":[-108.223568,36.726019],"type":"Point"}
}