{
  "type": "Feature",
  "properties": {
    "addr:full":"305 S Ruby St Deming NM 88030",
    "addr:housenumber":"305",
    "addr:postcode":"88030",
    "addr:street":"S Ruby St",
    "iso:country":"US",
    "sg:address":"305 S Ruby St",
    "sg:city":"Deming",
    "sg:classifiers":[
        {
            "category":"Food & Beverages",
            "subcategory":"Bakery",
            "type":"Retail Goods"
        }
    ],
    "sg:phone":"+1 505 546 9714",
    "sg:postcode":"88030",
    "sg:province":"NM",
    "wof:name":"Deming Pastry Shop",
    "wof:placetype":"venue"
},
  "geometry": {"coordinates":[-107.753249,32.267212],"type":"Point"}
}