{
  "type": "Feature",
  "properties": {
    "addr:full":"440 Cerrillos Rd Santa Fe NM 87501",
    "addr:housenumber":"440",
    "addr:postcode":"87501",
    "addr:street":"Cerrillos Rd",
    "iso:country":"US",
    "sg:address":"440 Cerrillos Rd",
    "sg:city":"Santa Fe",
    "sg:classifiers":[
        {
            "category":"Professional",
            "subcategory":"Lawyer & Legal Services",
            "type":"Services"
        }
    ],
    "sg:phone":"+1 505 983 6956",
    "sg:postcode":"87501",
    "sg:province":"NM",
    "sg:tags":[
        "attorney"
    ],
    "wof:name":"Serra Garrity & Masiowski",
    "wof:placetype":"venue"
},
  "geometry": {"coordinates":[-105.94381799999999,35.683496],"type":"Point"}
}