{
  "type": "Feature",
  "properties": {
    "addr:full":"205 Colorado Mountain Rd NE Rio Rancho NM 87124",
    "addr:housenumber":"205",
    "addr:postcode":"87124",
    "addr:street":"Mountain Rd Ne",
    "iso:country":"US",
    "sg:address":"205 Colorado Mountain Rd NE",
    "sg:city":"Rio Rancho",
    "sg:classifiers":[
        {
            "category":"Professional",
            "subcategory":"Management & Consulting",
            "type":"Services"
        }
    ],
    "sg:phone":"+1 505 994 0192",
    "sg:postcode":"87124",
    "sg:province":"NM",
    "sg:tags":[
        "consultant"
    ],
    "wof:name":"Athletic Field Consulting",
    "wof:placetype":"venue"
},
  "geometry": {"coordinates":[-106.695099,35.262286],"type":"Point"}
}