{
  "type": "Feature",
  "properties": {
    "addr:full":"2595 Missouri Ave Las Cruces NM 88011",
    "addr:housenumber":"2595",
    "addr:postcode":"88011",
    "addr:street":"Missouri Ave",
    "iso:country":"US",
    "sg:address":"2595 Missouri Ave",
    "sg:city":"Las Cruces",
    "sg:classifiers":[
        {
            "category":"Shopping",
            "subcategory":"Clothing, Apparel, & Fashions",
            "type":"Retail Goods"
        }
    ],
    "sg:phone":"+1 505 521 3400",
    "sg:postcode":"88011",
    "sg:province":"NM",
    "sg:tags":[
        "uniform"
    ],
    "wof:name":"Scrub Fashions",
    "wof:placetype":"venue"
},
  "geometry": {"coordinates":[-106.741671,32.299],"type":"Point"}
}