{
  "type": "Feature",
  "properties": {
    "iso:country":"US",
    "sg:address":"3311 May Cir SE",
    "sg:city":"Rio Rancho",
    "sg:classifiers":[
        {
            "category":"Professional",
            "subcategory":"Business Services",
            "type":"Services"
        }
    ],
    "sg:phone":"+1 505 459 8220",
    "sg:postcode":"87124",
    "sg:province":"NM",
    "sg:tags":[
        "fund",
        "promotion",
        "raising"
    ],
    "wof:name":"KISC Promotions Publications",
    "wof:placetype":"venue"
},
  "geometry": {"coordinates":[-106.669303,35.241276],"type":"Point"}
}