{
  "type": "Feature",
  "properties": {
    "iso:country":"US",
    "sg:address":"818 Pso del Pueblo Sur",
    "sg:city":"Taos",
    "sg:classifiers":[
        {
            "category":"Wholesale",
            "subcategory":"Non-durable Goods",
            "type":"Manufacturing & Wholesale Goods"
        }
    ],
    "sg:phone":"+1 505 758 7731",
    "sg:postcode":"87571",
    "sg:province":"NM",
    "sg:tags":[
        "import",
        "paper",
        "handmade",
        "asian"
    ],
    "wof:name":"Passages International Inc",
    "wof:placetype":"venue"
},
  "geometry": {"coordinates":[-105.583775,36.388518],"type":"Point"}
}