{
  "type": "Feature",
  "properties": {
    "iso:country":"US",
    "sg:address":"1269 E River Rd",
    "sg:city":"Belen",
    "sg:classifiers":[
        {
            "category":"Building & Trades",
            "subcategory":"Construction",
            "type":"Services"
        }
    ],
    "sg:phone":"+1 505 472 3892",
    "sg:postcode":"87002",
    "sg:province":"NM",
    "sg:tags":[
        "company"
    ],
    "wof:name":"Rivers Construction Inc",
    "wof:placetype":"venue"
},
  "geometry": {"coordinates":[-106.74897799999999,34.654659],"type":"Point"}
}