{
  "type": "Feature",
  "properties": {
    "addr:full":"6409 Whiteman Dr NW Albuquerque NM 87120",
    "addr:postcode":"6409;87120",
    "addr:street":"Whiteman Dr Nw",
    "iso:country":"US",
    "sg:address":"6409 Whiteman Dr NW",
    "sg:city":"Albuquerque",
    "sg:classifiers":[
        {
            "category":"Professional",
            "subcategory":"Management & Consulting",
            "type":"Services"
        },
        {
            "category":"Professional",
            "subcategory":"Engineering",
            "type":"Services"
        }
    ],
    "sg:phone":"+1 505 922 6488",
    "sg:postcode":"87120",
    "sg:province":"NM",
    "sg:tags":[
        "science",
        "consultant",
        "engineer",
        "academic"
    ],
    "wof:name":"Mccormack Consultants Inc",
    "wof:placetype":"venue"
},
  "geometry": {"coordinates":[-106.712481,35.15693],"type":"Point"}
}