{
  "type": "Feature",
  "properties": {
    "iso:country":"US",
    "sg:address":"725 University Blvd SE",
    "sg:city":"Albuquerque",
    "sg:classifiers":[
        {
            "category":"Health Services",
            "subcategory":"Doctor",
            "type":"Services"
        }
    ],
    "sg:phone":"+1 505 843 9557",
    "sg:postcode":"87106",
    "sg:province":"NM",
    "sg:tags":[
        "clinic"
    ],
    "wof:name":"Concentra Medical Systems",
    "wof:placetype":"venue"
},
  "geometry": {"coordinates":[-106.629173,35.074173],"type":"Point"}
}