{
  "type": "Feature",
  "properties": {
    "addr:full":"2516 San Mateo Pl NE Albuquerque NM 87110",
    "addr:housenumber":"2516",
    "addr:postcode":"87110",
    "addr:street":"San Mateo Pl Ne",
    "iso:country":"US",
    "sg:address":"2516 San Mateo Pl NE",
    "sg:city":"Albuquerque",
    "sg:classifiers":[
        {
            "category":"Health Services",
            "subcategory":"Medical Lab",
            "type":"Services"
        }
    ],
    "sg:phone":"+1 505 883 8683",
    "sg:postcode":"87110",
    "sg:province":"NM",
    "sg:tags":[
        "laboratory",
        "dental"
    ],
    "wof:name":"Alpha Omega Dental Lab",
    "wof:placetype":"venue"
},
  "geometry": {"coordinates":[-106.58640200000001,35.107814],"type":"Point"}
}