{
  "type": "Feature",
  "properties": {
    "iso:country":"US",
    "sg:address":"4305 Mesa Grande Pl SE",
    "sg:city":"Albuquerque",
    "sg:classifiers":[
        {
            "category":"Organizations",
            "subcategory":"Membership Organization",
            "type":"Services"
        }
    ],
    "sg:phone":"+1 505 265 5526",
    "sg:postcode":"87108",
    "sg:province":"NM",
    "sg:tags":[
        "hospital",
        "specialty"
    ],
    "wof:name":"Desert Club Inc",
    "wof:placetype":"venue"
},
  "geometry": {"coordinates":[-106.59608900000001,35.07713],"type":"Point"}
}