{
  "type": "Feature",
  "properties": {
    "iso:country":"US",
    "sg:address":"1304 W Aspen Ave",
    "sg:city":"Lovington",
    "sg:classifiers":[
        {
            "category":"Building & Trades",
            "subcategory":"Construction",
            "type":"Services"
        }
    ],
    "sg:phone":"+1 505 396 6440",
    "sg:postcode":"88260",
    "sg:province":"NM",
    "sg:tags":[
        "water",
        "well",
        "drilling"
    ],
    "wof:name":"Jack's Waterwell Svc",
    "wof:placetype":"venue"
},
  "geometry": {"coordinates":[-103.366619,32.959127],"type":"Point"}
}