{
  "type": "Feature",
  "properties": {
    "addr:full":"229 Nizhoni Blvd Gallup NM 87301",
    "addr:housenumber":"229",
    "addr:postcode":"87301",
    "addr:street":"Nizhoni Blvd",
    "iso:country":"US",
    "sg:address":"229 Nizhoni Blvd",
    "sg:city":"Gallup",
    "sg:classifiers":[
        {
            "category":"Social Services",
            "type":"Services"
        }
    ],
    "sg:phone":"+1 505 863 6254",
    "sg:postcode":"87301",
    "sg:province":"NM",
    "sg:tags":[
        "probation"
    ],
    "wof:name":"Adult Probation",
    "wof:placetype":"venue"
},
  "geometry": {"coordinates":[-108.737685,35.508325],"type":"Point"}
}