{
  "type": "Feature",
  "properties": {
    "iso:country":"US",
    "sg:address":"348 Country Club Dr",
    "sg:city":"Ruidoso",
    "sg:classifiers":[
        {
            "category":"Building & Trades",
            "subcategory":"Pest Control",
            "type":"Services"
        }
    ],
    "sg:phone":"+1 505 257 9857",
    "sg:postcode":"88345",
    "sg:province":"NM",
    "wof:name":"Mac's Pest Control",
    "wof:placetype":"venue"
},
  "geometry": {"coordinates":[-105.673753,33.347229],"type":"Point"}
}