{
  "type": "Feature",
  "properties": {
    "addr:full":"320 W Broadway St Hobbs NM 88240",
    "addr:housenumber":"320",
    "addr:postcode":"88240",
    "addr:street":"W Broadway St",
    "iso:country":"US",
    "sg:address":"320 W Broadway St",
    "sg:city":"Hobbs",
    "sg:classifiers":[
        {
            "category":"Shopping",
            "subcategory":"Musical Instruments",
            "type":"Retail Goods"
        }
    ],
    "sg:phone":"+1 505 397 0989",
    "sg:postcode":"88240",
    "sg:province":"NM",
    "sg:tags":[
        "music",
        "dealer"
    ],
    "wof:name":"Q Systems Music & Sound",
    "wof:placetype":"venue"
},
  "geometry": {"coordinates":[-103.13972200000001,32.700883],"type":"Point"}
}