{
  "type": "Feature",
  "properties": {
    "addr:full":"2810 N Telshor Blvd Las Cruces NM 88011",
    "addr:housenumber":"2810",
    "addr:postcode":"88011",
    "addr:street":"N Telshor Blvd",
    "iso:country":"US",
    "sg:address":"2810 N Telshor Blvd",
    "sg:city":"Las Cruces",
    "sg:classifiers":[
        {
            "category":"Health Services",
            "subcategory":"Doctor",
            "type":"Services"
        }
    ],
    "sg:phone":"+1 505 522 2088",
    "sg:postcode":"88011",
    "sg:province":"NM",
    "sg:tags":[
        "physician",
        "surgeon"
    ],
    "wof:name":"Friedman David J PC",
    "wof:placetype":"venue"
},
  "geometry": {"coordinates":[-106.763738,32.35049],"type":"Point"}
}