{
  "type": "Feature",
  "properties": {
    "iso:country":"US",
    "sg:address":"9417 Regal Ridge Dr NE",
    "sg:city":"Albuquerque",
    "sg:classifiers":[
        {
            "category":"Education",
            "subcategory":"Vocational School",
            "type":"Public Place"
        }
    ],
    "sg:phone":"+1 505 856 6473",
    "sg:postcode":"87111",
    "sg:province":"NM",
    "wof:name":"Writing & Training Services",
    "wof:placetype":"venue"
},
  "geometry": {"coordinates":[-106.538979,35.146344],"type":"Point"}
}