{
  "type": "Feature",
  "properties": {
    "iso:country":"US",
    "sg:address":"121 W San Francisco St",
    "sg:city":"Santa Fe",
    "sg:classifiers":[
        {
            "category":"Shopping",
            "subcategory":"Clothing, Apparel, & Fashions",
            "type":"Retail Goods"
        }
    ],
    "sg:phone":"+1 505 983 9298",
    "sg:postcode":"87501",
    "sg:province":"NM",
    "sg:tags":[
        "shoes"
    ],
    "wof:name":"Parts Unknown",
    "wof:placetype":"venue"
},
  "geometry": {"coordinates":[-105.940603,35.68761],"type":"Point"}
}