{
  "type": "Feature",
  "properties": {
    "addr:full":"2211 N Mesquite St Las Cruces NM 88001",
    "addr:housenumber":"2211",
    "addr:postcode":"88001",
    "addr:street":"N Mesquite St",
    "iso:country":"US",
    "sg:address":"2211 N Mesquite St",
    "sg:city":"Las Cruces",
    "sg:classifiers":[
        {
            "category":"Building & Trades",
            "subcategory":"Landscaping Services",
            "type":"Services"
        }
    ],
    "sg:phone":"+1 505 524 0592",
    "sg:postcode":"88001",
    "sg:province":"NM",
    "sg:tags":[
        "landscape",
        "contractor"
    ],
    "wof:name":"Green Thumb",
    "wof:placetype":"venue"
},
  "geometry": {"coordinates":[-106.78024000000001,32.32656],"type":"Point"}
}