{
  "type": "Feature",
  "properties": {
    "iso:country":"US",
    "sg:address":"150 Whitetail Rd NE",
    "sg:city":"Albuquerque",
    "sg:classifiers":[
        {
            "category":"Professional",
            "subcategory":"Business Services",
            "type":"Services"
        }
    ],
    "sg:phone":"+1 505 856 3667",
    "sg:postcode":"87122",
    "sg:province":"NM",
    "sg:tags":[
        "personal",
        "assistant"
    ],
    "sg:website":"http://andersonorganizing.com",
    "wof:name":"Anderson Organizing Systems",
    "wof:placetype":"venue"
},
  "geometry": {"coordinates":[-106.484668,35.179324],"type":"Point"}
}