{
  "type": "Feature",
  "properties": {
    "iso:country":"US",
    "sg:address":"311 S Ash St",
    "sg:city":"Aztec",
    "sg:classifiers":[
        {
            "category":"Social Services",
            "type":"Services"
        }
    ],
    "sg:phone":"+1 505 334 8861",
    "sg:postcode":"87410",
    "sg:province":"NM",
    "sg:tags":[
        "youth",
        "organization",
        "center"
    ],
    "wof:name":"Boys & Girls Club Of Aztec",
    "wof:placetype":"venue"
},
  "geometry": {"coordinates":[-107.998318,36.820931],"type":"Point"}
}