{
  "type": "Feature",
  "properties": {
    "addr:full":"8517 Trumbull Ave SE Albuquerque NM 87108",
    "addr:housenumber":"8517",
    "addr:postcode":"87108",
    "addr:street":"Trumbull Ave Se",
    "iso:country":"US",
    "sg:address":"8517 Trumbull Ave SE",
    "sg:city":"Albuquerque",
    "sg:classifiers":[
        {
            "category":"Shopping",
            "type":"Retail Goods"
        }
    ],
    "sg:phone":"+1 505 268 7616",
    "sg:postcode":"87108",
    "sg:province":"NM",
    "sg:tags":[
        "art",
        "gallery",
        "dealer"
    ],
    "wof:name":"Rare Prints & Maps",
    "wof:placetype":"venue"
},
  "geometry": {"coordinates":[-106.550595,35.069144],"type":"Point"}
}