{
  "type": "Feature",
  "properties": {
    "iso:country":"US",
    "sg:address":"1117 N Main St",
    "sg:city":"Clovis",
    "sg:classifiers":[
        {
            "category":"Organizations",
            "subcategory":"Religious Organization",
            "type":"Services"
        }
    ],
    "sg:phone":"+1 505 763 4638",
    "sg:postcode":"88101",
    "sg:province":"NM",
    "sg:tags":[
        "church"
    ],
    "wof:name":"St James Episcopal Church",
    "wof:placetype":"venue"
},
  "geometry": {"coordinates":[-103.205293,34.409764],"type":"Point"}
}