{
  "type": "Feature",
  "properties": {
    "addr:full":"300 N Turner St Hobbs NM 88240",
    "addr:housenumber":"300",
    "addr:postcode":"88240",
    "addr:street":"N Turner St",
    "iso:country":"US",
    "sg:address":"300 N Turner St",
    "sg:city":"Hobbs",
    "sg:classifiers":[
        {
            "category":"Government",
            "subcategory":"Office",
            "type":"Public Place"
        }
    ],
    "sg:phone":"+1 505 397 9231",
    "sg:postcode":"88240",
    "sg:province":"NM",
    "sg:tags":[
        "civil",
        "defense",
        "agency"
    ],
    "wof:name":"Hobbs Emergency Mgmt Safety",
    "wof:placetype":"venue"
},
  "geometry": {"coordinates":[-103.136208,32.703969],"type":"Point"}
}