{
  "type": "Feature",
  "properties": {
    "iso:country":"US",
    "sg:address":"1141 Juan Tabo Blvd NE",
    "sg:city":"Albuquerque",
    "sg:classifiers":[
        {
            "category":"Autos & Motor Vehicles",
            "subcategory":"Auto Supplies",
            "type":"Retail Goods"
        }
    ],
    "sg:phone":"+1 505 293 2966",
    "sg:postcode":"87112",
    "sg:province":"NM",
    "sg:tags":[
        "repair",
        "part",
        "tune",
        "automotive"
    ],
    "sg:website":"http://www.bigotires.com",
    "wof:name":"Big O Tires",
    "wof:placetype":"venue"
},
  "geometry": {"coordinates":[-106.515343,35.09201],"type":"Point"}
}