{
  "type": "Feature",
  "properties": {
    "addr:full":"405 W Main St Farmington NM 87401",
    "addr:housenumber":"405",
    "addr:postcode":"87401",
    "addr:street":"W Main St",
    "iso:country":"US",
    "sg:address":"405 W Main St",
    "sg:city":"Farmington",
    "sg:classifiers":[
        {
            "category":"Banks & Credit Unions",
            "subcategory":"Bank",
            "type":"Services"
        }
    ],
    "sg:phone":"+1 505 324 8119",
    "sg:postcode":"87401",
    "sg:province":"NM",
    "sg:tags":[
        "loan"
    ],
    "wof:name":"Sun Loan Co",
    "wof:placetype":"venue"
},
  "geometry": {"coordinates":[-108.209335,36.728964],"type":"Point"}
}