{
  "type": "Feature",
  "properties": {
    "iso:country":"US",
    "sg:address":"9 Bear Claw Trl",
    "sg:city":"Tijeras",
    "sg:classifiers":[
        {
            "category":"Professional",
            "subcategory":"Business Services",
            "type":"Services"
        }
    ],
    "sg:phone":"+1 505 281 3621",
    "sg:postcode":"87059",
    "sg:province":"NM",
    "wof:name":"Mq Enterprises",
    "wof:placetype":"venue"
},
  "geometry": {"coordinates":[-106.39108299999999,35.087503],"type":"Point"}
}