{
  "type": "Feature",
  "properties": {
    "iso:country":"US",
    "sg:address":"39 S Vis Estrellas",
    "sg:city":"Lamy",
    "sg:classifiers":[
        {
            "category":"Professional",
            "subcategory":"Management & Consulting",
            "type":"Services"
        }
    ],
    "sg:phone":"+1 505 466 1167",
    "sg:postcode":"87540",
    "sg:province":"NM",
    "sg:tags":[
        "marketing",
        "program"
    ],
    "sg:website":"www.pamelayellen.com",
    "wof:name":"Prospecting & Marketing Inst",
    "wof:placetype":"venue"
},
  "geometry": {"coordinates":[-105.92958400000001,35.501645],"type":"Point"}
}