{
  "type": "Feature",
  "properties": {
    "iso:country":"US",
    "sg:address":"904 SW 10th St",
    "sg:city":"Seminole",
    "sg:classifiers":[
        {
            "category":"Farming",
            "subcategory":"Farm",
            "type":"Manufacturing & Wholesale Goods"
        }
    ],
    "sg:phone":"+1 432 758 3187",
    "sg:postcode":"79360",
    "sg:province":"NM",
    "sg:tags":[
        "crop",
        "general"
    ],
    "wof:name":"Oliver Farland",
    "wof:placetype":"venue"
},
  "geometry": {"coordinates":[-102.656297,32.708119],"type":"Point"}
}