{
  "type": "Feature",
  "properties": {
    "iso:country":"US",
    "sg:address":"1730 Montano Rd NW",
    "sg:city":"Albuquerque",
    "sg:classifiers":[
        {
            "category":"Professional",
            "type":"Services"
        }
    ],
    "sg:phone":"+1 505 341 4790",
    "sg:postcode":"87107",
    "sg:province":"NM",
    "sg:tags":[
        "establishment"
    ],
    "wof:name":"Samba",
    "wof:placetype":"venue"
},
  "geometry": {"coordinates":[-106.662912,35.142346],"type":"Point"}
}