{
  "type": "Feature",
  "properties": {
    "addr:full":"1300 el Paseo Rd Las Cruces NM 88001",
    "addr:housenumber":"1300",
    "addr:postcode":"88001",
    "addr:street":"El Paseo Rd",
    "iso:country":"US",
    "sg:address":"1300 el Paseo Rd",
    "sg:city":"Las Cruces",
    "sg:classifiers":[
        {
            "category":"Shopping",
            "subcategory":"Pharmacy",
            "type":"Retail Goods"
        }
    ],
    "sg:phone":"+1 505 525 8708",
    "sg:postcode":"88001",
    "sg:province":"NM",
    "sg:website":"www.walgreens.com",
    "wof:name":"Walgreens",
    "wof:placetype":"venue"
},
  "geometry": {"coordinates":[-106.77095,32.296859],"type":"Point"}
}