{
  "type": "Feature",
  "properties": {
    "iso:country":"US",
    "sg:address":"201 3rd St SW",
    "sg:city":"Albuquerque",
    "sg:classifiers":[
        {
            "category":"Professional",
            "subcategory":"Lawyer & Legal Services",
            "type":"Services"
        }
    ],
    "sg:phone":"+1 505 248 1300",
    "sg:postcode":"87102",
    "sg:province":"NM",
    "wof:name":"Barlow & Wilcox PA",
    "wof:placetype":"venue"
},
  "geometry": {"coordinates":[-106.650788,35.082415],"type":"Point"}
}