{
  "type": "Feature",
  "properties": {
    "iso:country":"US",
    "sg:address":"1401 Pennsylvania St NE",
    "sg:city":"Albuquerque",
    "sg:classifiers":[
        {
            "category":"Professional",
            "subcategory":"Management & Consulting",
            "type":"Services"
        }
    ],
    "sg:phone":"+1 505 328 0254",
    "sg:postcode":"87110",
    "sg:province":"NM",
    "sg:tags":[
        "arts",
        "fine"
    ],
    "wof:name":"Norman D Chavez Jr",
    "wof:placetype":"venue"
},
  "geometry": {"coordinates":[-106.559695,35.096275],"type":"Point"}
}