{
  "type": "Feature",
  "properties": {
    "addr:full":"2916 Hopi Trl Alamogordo NM 88310",
    "addr:housenumber":"2916",
    "addr:postcode":"88310",
    "addr:street":"Hopi Trl",
    "iso:country":"US",
    "sg:address":"2916 Hopi Trl",
    "sg:city":"Alamogordo",
    "sg:classifiers":[
        {
            "category":"Shopping",
            "subcategory":"Hobbies, Toys, & Games",
            "type":"Retail Goods"
        }
    ],
    "sg:phone":"+1 505 437 1146",
    "sg:postcode":"88310",
    "sg:province":"NM",
    "wof:name":"Carols Craft & Gift Shoppe",
    "wof:placetype":"venue"
},
  "geometry": {"coordinates":[-105.92619999999999,32.89981],"type":"Point"}
}