{
  "type": "Feature",
  "properties": {
    "iso:country":"US",
    "sg:address":"2001 Chamisa St",
    "sg:city":"Santa Fe",
    "sg:classifiers":[
        {
            "category":"Shopping",
            "subcategory":"Musical Instruments",
            "type":"Retail Goods"
        }
    ],
    "sg:phone":"+1 505 982 2608",
    "sg:postcode":"87505",
    "sg:province":"NM",
    "wof:name":"Santa Fe Band Instruments",
    "wof:placetype":"venue"
},
  "geometry": {"coordinates":[-105.976842,35.661975],"type":"Point"}
}