{
  "type": "Feature",
  "properties": {
    "addr:full":"2605 Pajarito Rd SW Albuquerque NM 87105",
    "addr:postcode":"2605;87105",
    "addr:street":"Pajarito Rd Sw",
    "iso:country":"US",
    "sg:address":"2605 Pajarito Rd SW",
    "sg:city":"Albuquerque",
    "sg:classifiers":[
        {
            "category":"Building & Trades",
            "subcategory":"Construction",
            "type":"Services"
        }
    ],
    "sg:phone":"+1 505 877 4143",
    "sg:postcode":"87105",
    "sg:province":"NM",
    "sg:tags":[
        "general",
        "contractor"
    ],
    "wof:name":"Hoefler Construction Inc",
    "wof:placetype":"venue"
},
  "geometry": {"coordinates":[-106.712666,34.990358],"type":"Point"}
}