{
  "type": "Feature",
  "properties": {
    "iso:country":"US",
    "sg:address":"460 Saint Michaels Dr",
    "sg:city":"Santa Fe",
    "sg:classifiers":[
        {
            "category":"Banks & Credit Unions",
            "subcategory":"Investment Brokerage",
            "type":"Services"
        }
    ],
    "sg:phone":"+1 505 984 8232",
    "sg:postcode":"87505",
    "sg:province":"NM",
    "sg:tags":[
        "security"
    ],
    "wof:name":"Raymond James",
    "wof:placetype":"venue"
},
  "geometry": {"coordinates":[-105.951774,35.658666],"type":"Point"}
}