{
  "type": "Feature",
  "properties": {
    "addr:full":"2632 Pennsylvania St NE Albuquerque NM 87110",
    "addr:housenumber":"2632",
    "addr:postcode":"87110",
    "addr:street":"Pennsylvania St Ne",
    "iso:country":"US",
    "sg:address":"2632 Pennsylvania St NE",
    "sg:city":"Albuquerque",
    "sg:classifiers":[
        {
            "category":"Retail",
            "subcategory":"Veterinary Services",
            "type":"Services"
        }
    ],
    "sg:phone":"+1 505 271 2287",
    "sg:postcode":"87110",
    "sg:province":"NM",
    "sg:tags":[
        "veterinarian"
    ],
    "wof:name":"Uptown Cat Hospital",
    "wof:placetype":"venue"
},
  "geometry": {"coordinates":[-106.55979499999999,35.110423],"type":"Point"}
}