{
  "type": "Feature",
  "properties": {
    "iso:country":"US",
    "sg:address":"2443 N Main St",
    "sg:city":"Las Cruces",
    "sg:classifiers":[
        {
            "category":"Professional",
            "type":"Services"
        }
    ],
    "sg:phone":"+1 505 647 8842",
    "sg:postcode":"88001",
    "sg:province":"NM",
    "sg:tags":[
        "establishment"
    ],
    "wof:name":"Lamaker & Co Inc",
    "wof:placetype":"venue"
},
  "geometry": {"coordinates":[-106.783851,32.328379],"type":"Point"}
}