{
  "type": "Feature",
  "properties": {
    "iso:country":"US",
    "sg:address":"4 Swinson Ave",
    "sg:city":"Alamogordo",
    "sg:classifiers":[
        {
            "category":"Retail",
            "subcategory":"Car Wash",
            "type":"Services"
        }
    ],
    "sg:phone":"+1 505 437 5270",
    "sg:postcode":"88310",
    "sg:province":"NM",
    "sg:tags":[
        "truck",
        "cleaning"
    ],
    "wof:name":"S & C Glass & Window Tint",
    "wof:placetype":"venue"
},
  "geometry": {"coordinates":[-105.987471,32.901939],"type":"Point"}
}