{
  "type": "Feature",
  "properties": {
    "iso:country":"US",
    "sg:address":"1402 S 22nd St",
    "sg:city":"Artesia",
    "sg:classifiers":[
        {
            "category":"Building & Trades",
            "subcategory":"Construction",
            "type":"Services"
        }
    ],
    "sg:phone":"+1 505 746 4034",
    "sg:postcode":"88210",
    "sg:province":"NM",
    "sg:tags":[
        "general",
        "contractor"
    ],
    "wof:name":"New Look Construction",
    "wof:placetype":"venue"
},
  "geometry": {"coordinates":[-104.42347100000001,32.828764],"type":"Point"}
}