{
  "type": "Feature",
  "properties": {
    "iso:country":"US",
    "sg:address":"2068 Cll Contento",
    "sg:city":"Santa Fe",
    "sg:classifiers":[
        {
            "category":"Health Services",
            "subcategory":"Health Practitioner",
            "type":"Services"
        }
    ],
    "sg:phone":"+1 505 470 1690",
    "sg:postcode":"87505",
    "sg:province":"NM",
    "sg:tags":[
        "midwife"
    ],
    "wof:name":"Family Tree Midwifery",
    "wof:placetype":"venue"
},
  "geometry": {"coordinates":[-105.96149200000001,35.654472],"type":"Point"}
}