{
  "type": "Feature",
  "properties": {
    "iso:country":"US",
    "sg:address":"8019 Saddlebrook Ave NW",
    "sg:city":"Albuquerque",
    "sg:classifiers":[
        {
            "category":"Retail",
            "subcategory":"Repair Shop",
            "type":"Services"
        }
    ],
    "sg:phone":"+1 505 839 2650",
    "sg:postcode":"87120",
    "sg:province":"NM",
    "wof:name":"Akers Beverage & Vend Mch Repr",
    "wof:placetype":"venue"
},
  "geometry": {"coordinates":[-106.731704,35.112657],"type":"Point"}
}