{
  "type": "Feature",
  "properties": {
    "addr:full":"333 Becker Ave Belen NM 87002",
    "addr:housenumber":"333",
    "addr:postcode":"87002",
    "addr:street":"Becker Ave",
    "iso:country":"US",
    "sg:address":"333 Becker Ave",
    "sg:city":"Belen",
    "sg:classifiers":[
        {
            "category":"Organizations",
            "subcategory":"Non-profit Organization",
            "type":"Services"
        }
    ],
    "sg:phone":"+1 505 864 3511",
    "sg:postcode":"87002",
    "sg:province":"NM",
    "wof:name":"Valencia County Literacy Counc",
    "wof:placetype":"venue"
},
  "geometry": {"coordinates":[-106.771513,34.659938],"type":"Point"}
}