{
  "type": "Feature",
  "properties": {
    "iso:country":"US",
    "sg:address":"5301 Central Ave SE",
    "sg:city":"Albuquerque",
    "sg:classifiers":[
        {
            "category":"Utilities",
            "subcategory":"Telephone",
            "type":"Services"
        }
    ],
    "sg:phone":"+1 505 268 3710",
    "sg:postcode":"87108",
    "sg:province":"NM",
    "sg:tags":[
        "communications"
    ],
    "wof:name":"Valor Telecom Southwest LLC",
    "wof:placetype":"venue"
},
  "geometry": {"coordinates":[-106.584431,35.077571],"type":"Point"}
}