{
  "type": "Feature",
  "properties": {
    "addr:full":"101 W 6th St Roswell NM 88201",
    "addr:housenumber":"101",
    "addr:postcode":"88201",
    "addr:street":"W 6Th St",
    "iso:country":"US",
    "sg:address":"101 W 6th St",
    "sg:city":"Roswell",
    "sg:classifiers":[
        {
            "category":"Shopping",
            "subcategory":"Musical Instruments",
            "type":"Retail Goods"
        }
    ],
    "sg:phone":"+1 505 623 0200",
    "sg:postcode":"88201",
    "sg:province":"NM",
    "wof:name":"Fat Dog Sound & Light",
    "wof:placetype":"venue"
},
  "geometry": {"coordinates":[-104.522829,33.398784],"type":"Point"}
}