{
  "type": "Feature",
  "properties": {
    "iso:country":"US",
    "sg:address":"12713 Summer Ave NE",
    "sg:city":"Albuquerque",
    "sg:classifiers":[
        {
            "category":"Travel",
            "subcategory":"Travel Agent",
            "type":"Entertainment"
        }
    ],
    "sg:phone":"+1 505 262 3730",
    "sg:postcode":"87112",
    "sg:province":"NM",
    "sg:tags":[
        "agency"
    ],
    "wof:name":"Sandia Travel Services",
    "wof:placetype":"venue"
},
  "geometry": {"coordinates":[-106.50527,35.092855],"type":"Point"}
}