{
  "type": "Feature",
  "properties": {
    "addr:full":"2212 Primrose St Carlsbad NM 88220",
    "addr:housenumber":"2212",
    "addr:postcode":"88220",
    "addr:street":"Primrose St",
    "iso:country":"US",
    "sg:address":"2212 Primrose St",
    "sg:city":"Carlsbad",
    "sg:classifiers":[
        {
            "category":"Education",
            "subcategory":"School",
            "type":"Public Place"
        }
    ],
    "sg:phone":"+1 505 234 3311",
    "sg:postcode":"88220",
    "sg:province":"NM",
    "wof:name":"Puckett Elementary School",
    "wof:placetype":"venue"
},
  "geometry": {"coordinates":[-104.21524700000001,32.397492],"type":"Point"}
}