{
  "type": "Feature",
  "properties": {
    "iso:country":"US",
    "sg:address":"5300 Eubank Blvd NE",
    "sg:city":"Albuquerque",
    "sg:classifiers":[
        {
            "category":"Professional",
            "type":"Services"
        }
    ],
    "sg:phone":"+1 505 385 2319",
    "sg:postcode":"87111",
    "sg:province":"NM",
    "wof:name":"Austin Communications",
    "wof:placetype":"venue"
},
  "geometry": {"coordinates":[-106.533188,35.140086],"type":"Point"}
}