{
  "type": "Feature",
  "properties": {
    "iso:country":"US",
    "sg:address":"4400 Lead Ave SE",
    "sg:city":"Albuquerque",
    "sg:classifiers":[
        {
            "category":"Health Services",
            "subcategory":"Health Practitioner",
            "type":"Services"
        }
    ],
    "sg:phone":"+1 505 266 3655",
    "sg:postcode":"87108",
    "sg:province":"NM",
    "sg:tags":[
        "specialty",
        "outpatient"
    ],
    "wof:name":"Langford Physical Therapy",
    "wof:placetype":"venue"
},
  "geometry": {"coordinates":[-106.595361,35.074977],"type":"Point"}
}