{
  "type": "Feature",
  "properties": {
    "addr:full":"219 Paloma Blanca Dr Chaparral NM 88081",
    "addr:housenumber":"219",
    "addr:postcode":"88081",
    "addr:street":"Paloma Blanca Dr",
    "iso:country":"US",
    "sg:address":"219 Paloma Blanca Dr",
    "sg:city":"Chaparral",
    "sg:classifiers":[
        {
            "category":"Building & Trades",
            "subcategory":"Electrical",
            "type":"Services"
        }
    ],
    "sg:phone":"+1 575 621 1123",
    "sg:postcode":"88081",
    "sg:province":"NM",
    "sg:tags":[
        "electrician"
    ],
    "wof:name":"J&F Electric",
    "wof:placetype":"venue"
},
  "geometry": {"coordinates":[-106.418145,32.027489],"type":"Point"}
}