{
  "type": "Feature",
  "properties": {
    "iso:country":"US",
    "sg:address":"2431 San Pedro Dr NE",
    "sg:city":"Albuquerque",
    "sg:classifiers":[
        {
            "category":"Insurance",
            "subcategory":"Insurance Agent",
            "type":"Services"
        }
    ],
    "sg:phone":"+1 505 884 6000",
    "sg:postcode":"87110",
    "sg:province":"NM",
    "sg:tags":[
        "agency"
    ],
    "wof:name":"J A Sunderland Agency Inc",
    "wof:placetype":"venue"
},
  "geometry": {"coordinates":[-106.577651,35.106734],"type":"Point"}
}