{
  "type": "Feature",
  "properties": {
    "iso:country":"US",
    "sg:address":"1721 Rio Rancho Dr SE",
    "sg:city":"Rio Rancho",
    "sg:classifiers":[
        {
            "category":"Health Services",
            "subcategory":"Doctor",
            "type":"Services"
        }
    ],
    "sg:phone":"+1 505 727 2600",
    "sg:postcode":"87124",
    "sg:province":"NM",
    "sg:tags":[
        "physician",
        "surgeon"
    ],
    "wof:name":"St Joseph Health Care",
    "wof:placetype":"venue"
},
  "geometry": {"coordinates":[-106.659991,35.22751],"type":"Point"}
}