{
  "type": "Feature",
  "properties": {
    "addr:full":"1010 Spring St Socorro NM 87801",
    "addr:housenumber":"1010",
    "addr:postcode":"87801",
    "addr:street":"Spring St",
    "iso:country":"US",
    "sg:address":"1010 Spring St",
    "sg:city":"Socorro",
    "sg:classifiers":[
        {
            "category":"Retail",
            "subcategory":"Animal Services",
            "type":"Services"
        }
    ],
    "sg:phone":"+1 505 838 0347",
    "sg:postcode":"87801",
    "sg:province":"NM",
    "wof:name":"Holzheu of Animals",
    "wof:placetype":"venue"
},
  "geometry": {"coordinates":[-106.90710300000001,34.051508],"type":"Point"}
}