{
  "type": "Feature",
  "properties": {
    "iso:country":"US",
    "sg:address":"4402 2nd St NW",
    "sg:city":"Albuquerque",
    "sg:classifiers":[
        {
            "category":"Wholesale",
            "subcategory":"Metals & Minerals",
            "type":"Manufacturing & Wholesale Goods"
        }
    ],
    "sg:phone":"+1 505 343 1101",
    "sg:postcode":"87107",
    "sg:province":"NM",
    "sg:tags":[
        "pipe"
    ],
    "sg:website":"www.101pipe.com",
    "wof:name":"101 Pipe & Casing",
    "wof:placetype":"venue"
},
  "geometry": {"coordinates":[-106.639582,35.129091],"type":"Point"}
}