{
  "type": "Feature",
  "properties": {
    "addr:full":"9 Lee Rd Gila NM 88061",
    "addr:housenumber":"9",
    "addr:postcode":"88061",
    "addr:street":"Lee Rd",
    "iso:country":"US",
    "sg:address":"9 Lee Rd",
    "sg:city":"Gila",
    "sg:classifiers":[
        {
            "category":"Real Estate",
            "subcategory":"Real Estate Agent",
            "type":"Services"
        }
    ],
    "sg:phone":"+1 505 535 2361",
    "sg:postcode":"88061",
    "sg:province":"NM",
    "wof:name":"Jackson Real Estate",
    "wof:placetype":"venue"
},
  "geometry": {"coordinates":[-108.57187999999999,32.971601],"type":"Point"}
}