{
  "type": "Feature",
  "properties": {
    "addr:full":"4252 Kiva Trl Los Lunas NM 87031",
    "addr:housenumber":"4252",
    "addr:postcode":"87031",
    "addr:street":"Kiva Trl",
    "iso:country":"US",
    "sg:address":"4252 Kiva Trl",
    "sg:city":"Los Lunas",
    "sg:classifiers":[
        {
            "category":"Freight",
            "type":"Transportation"
        },
        {
            "category":"Retail",
            "subcategory":"Auto Repair",
            "type":"Services"
        }
    ],
    "sg:phone":"+1 505 865 0862",
    "sg:postcode":"87031",
    "sg:province":"NM",
    "sg:tags":[
        "co",
        "automobile",
        "drive",
        "broker",
        "operator",
        "transporter",
        "trucking"
    ],
    "wof:name":"Heartland Transport Inc",
    "wof:placetype":"venue"
},
  "geometry": {"coordinates":[-106.75767,34.76057],"type":"Point"}
}