{
  "type": "Feature",
  "properties": {
    "iso:country":"US",
    "sg:address":"6601 Leta Rd NE",
    "sg:city":"Albuquerque",
    "sg:classifiers":[
        {
            "category":"Organizations",
            "subcategory":"Religious Organization",
            "type":"Services"
        }
    ],
    "sg:phone":"+1 505 344 3773",
    "sg:postcode":"87113",
    "sg:province":"NM",
    "wof:name":"First Free Will Baptist Church",
    "wof:placetype":"venue"
},
  "geometry": {"coordinates":[-106.620599,35.153072],"type":"Point"}
}