{
  "type": "Feature",
  "properties": {
    "iso:country":"US",
    "sg:address":"1908 Edith Blvd SE",
    "sg:city":"Albuquerque",
    "sg:classifiers":[
        {
            "category":"Retail",
            "subcategory":"Repair Shop",
            "type":"Services"
        }
    ],
    "sg:phone":"+1 505 843 7223",
    "sg:postcode":"87102",
    "sg:province":"NM",
    "wof:name":"R&S General Cleaning",
    "wof:placetype":"venue"
},
  "geometry": {"coordinates":[-106.64281,35.063082],"type":"Point"}
}