{
  "type": "Feature",
  "properties": {
    "iso:country":"US",
    "sg:address":"1716 W Hadley Ave",
    "sg:city":"Las Cruces",
    "sg:classifiers":[
        {
            "category":"Wholesale",
            "subcategory":"Medical Equipment & Supplies",
            "type":"Manufacturing & Wholesale Goods"
        }
    ],
    "sg:phone":"+1 505 647 1128",
    "sg:postcode":"88005",
    "sg:province":"NM",
    "sg:tags":[
        "physician",
        "surgeon"
    ],
    "wof:name":"Patient Care Svc",
    "wof:placetype":"venue"
},
  "geometry": {"coordinates":[-106.800734,32.309167],"type":"Point"}
}