{
  "type": "Feature",
  "properties": {
    "iso:country":"US",
    "sg:address":"10147 2nd St NW",
    "sg:city":"Albuquerque",
    "sg:classifiers":[
        {
            "category":"Home & Garden",
            "subcategory":"Garden Supply",
            "type":"Retail Goods"
        }
    ],
    "sg:phone":"+1 505 898 5227",
    "sg:postcode":"87114",
    "sg:province":"NM",
    "sg:tags":[
        "nurseryman"
    ],
    "wof:name":"Helen's Native Plants Furn",
    "wof:placetype":"venue"
},
  "geometry": {"coordinates":[-106.61149500000001,35.196569],"type":"Point"}
}