{
  "type": "Feature",
  "properties": {
    "iso:country":"US",
    "sg:address":"608 E 15th St",
    "sg:city":"Farmington",
    "sg:classifiers":[
        {
            "category":"Building & Trades",
            "subcategory":"Construction",
            "type":"Services"
        }
    ],
    "sg:phone":"+1 505 326 2336",
    "sg:postcode":"87401",
    "sg:province":"NM",
    "sg:tags":[
        "house"
    ],
    "wof:name":"Agape Builders Inc",
    "wof:placetype":"venue"
},
  "geometry": {"coordinates":[-108.19895200000001,36.745026],"type":"Point"}
}