{
  "type": "Feature",
  "properties": {
    "addr:full":"1511 Cll Angelina Santa Fe NM 87507",
    "addr:housenumber":"1511",
    "addr:postcode":"87507",
    "addr:street":"Cll Angelina",
    "iso:country":"US",
    "sg:address":"1511 Cll Angelina",
    "sg:city":"Santa Fe",
    "sg:classifiers":[
        {
            "category":"Real Estate",
            "subcategory":"Real Estate Agent",
            "type":"Services"
        }
    ],
    "sg:phone":"+1 505 466 6690",
    "sg:postcode":"87507",
    "sg:province":"NM",
    "wof:name":"Bob Di Janni Fine Home Realty",
    "wof:placetype":"venue"
},
  "geometry": {"coordinates":[-105.989075,35.667109],"type":"Point"}
}