{
  "type": "Feature",
  "properties": {
    "addr:full":"11 Wright Rd Mimbres NM 88049",
    "addr:housenumber":"11",
    "addr:postcode":"88049",
    "addr:street":"Wright Rd",
    "iso:country":"US",
    "sg:address":"11 Wright Rd",
    "sg:city":"Mimbres",
    "sg:classifiers":[
        {
            "category":"Professional",
            "subcategory":"Accounting & Tax Preparation",
            "type":"Services"
        }
    ],
    "sg:phone":"+1 505 536 9492",
    "sg:postcode":"88049",
    "sg:province":"NM",
    "sg:tags":[
        "return",
        "filing"
    ],
    "wof:name":"Joann's Tax Svc",
    "wof:placetype":"venue"
},
  "geometry": {"coordinates":[-107.94981,32.831962],"type":"Point"}
}