{
  "type": "Feature",
  "properties": {
    "addr:full":"3 Debonaire Dr Los Lunas NM 87031",
    "addr:housenumber":"3",
    "addr:postcode":"87031",
    "addr:street":"Debonaire Dr",
    "iso:country":"US",
    "sg:address":"3 Debonaire Dr",
    "sg:city":"Los Lunas",
    "sg:classifiers":[
        {
            "category":"Building & Trades",
            "subcategory":"Electrical",
            "type":"Services"
        }
    ],
    "sg:phone":"+1 505 866 0839",
    "sg:postcode":"87031",
    "sg:province":"NM",
    "sg:tags":[
        "electrical",
        "contractor"
    ],
    "wof:name":"Love Electric",
    "wof:placetype":"venue"
},
  "geometry": {"coordinates":[-106.739965,34.766474],"type":"Point"}
}