{
  "type": "Feature",
  "properties": {
    "addr:full":"145 Wisconsin St NE Albuquerque NM 87108",
    "addr:housenumber":"145",
    "addr:postcode":"87108",
    "addr:street":"Wisconsin St Ne",
    "iso:country":"US",
    "sg:address":"145 Wisconsin St NE",
    "sg:city":"Albuquerque",
    "sg:classifiers":[
        {
            "category":"Retail",
            "subcategory":"Auto Repair",
            "type":"Services"
        }
    ],
    "sg:phone":"+1 505 255 9862",
    "sg:postcode":"87108",
    "sg:province":"NM",
    "sg:tags":[
        "automobile",
        "electric"
    ],
    "wof:name":"East Mesa Auto Electric",
    "wof:placetype":"venue"
},
  "geometry": {"coordinates":[-106.551649,35.075284],"type":"Point"}
}