{
  "type": "Feature",
  "properties": {
    "iso:country":"US",
    "sg:address":"3419 Agua Fria St",
    "sg:city":"Santa Fe",
    "sg:classifiers":[
        {
            "category":"Building & Trades",
            "subcategory":"Construction",
            "type":"Services"
        },
        {
            "category":"Manufacturing",
            "subcategory":"Rubber & Plastics",
            "type":"Manufacturing & Wholesale Goods"
        }
    ],
    "sg:phone":"+1 505 471 2140",
    "sg:postcode":"87507",
    "sg:province":"NM",
    "sg:tags":[
        "product",
        "remodeling",
        "contractor"
    ],
    "sg:website":"www.santafedesigns.com",
    "wof:name":"Beautiful Woods",
    "wof:placetype":"venue"
},
  "geometry": {"coordinates":[-106.009212,35.659438],"type":"Point"}
}