{
  "type": "Feature",
  "properties": {
    "addr:full":"3700 Rio Grande Blvd NW Albuquerque NM 87107",
    "addr:housenumber":"3700",
    "addr:postcode":"87107",
    "addr:street":"Rio Grande Blvd Nw",
    "iso:country":"US",
    "sg:address":"3700 Rio Grande Blvd NW",
    "sg:city":"Albuquerque",
    "sg:classifiers":[
        {
            "category":"Wholesale",
            "subcategory":"Stationery",
            "type":"Manufacturing & Wholesale Goods"
        }
    ],
    "sg:phone":"+1 505 344 2345",
    "sg:postcode":"87107",
    "sg:province":"NM",
    "sg:tags":[
        "mapping"
    ],
    "sg:website":"www.ebert.com",
    "wof:name":"Ebert & Assoc",
    "wof:placetype":"venue"
},
  "geometry": {"coordinates":[-106.670565,35.133684],"type":"Point"}
}