{
  "type": "Feature",
  "properties": {
    "iso:country":"US",
    "sg:address":"1698 Galisteo St",
    "sg:city":"Santa Fe",
    "sg:classifiers":[
        {
            "category":"Travel",
            "subcategory":"Hotels & Motels",
            "type":"Entertainment"
        }
    ],
    "sg:phone":"+1 505 988 7300",
    "sg:postcode":"87505",
    "sg:province":"NM",
    "sg:tags":[
        "operation"
    ],
    "wof:name":"Residence Inn By Marriott",
    "wof:placetype":"venue"
},
  "geometry": {"coordinates":[-105.947649,35.665648],"type":"Point"}
}