{
  "type": "Feature",
  "properties": {
    "addr:full":"147 Cll del Presidente Bernalillo NM 87004",
    "addr:housenumber":"147",
    "addr:postcode":"87004",
    "addr:street":"Cll Del Presidente",
    "iso:country":"US",
    "sg:address":"147 Cll del Presidente",
    "sg:city":"Bernalillo",
    "sg:classifiers":[
        {
            "category":"Government",
            "subcategory":"Post Office",
            "type":"Public Place"
        }
    ],
    "sg:phone":"+1 505 867 5526",
    "sg:postcode":"87004",
    "sg:province":"NM",
    "wof:name":"US Post Office",
    "wof:placetype":"venue"
},
  "geometry": {"coordinates":[-106.547663,35.305638],"type":"Point"}
}