{
  "type": "Feature",
  "properties": {
    "iso:country":"US",
    "sg:address":"806 Yucca St",
    "sg:city":"Truth Or Cnsqncs",
    "sg:classifiers":[
        {
            "category":"Building & Trades",
            "subcategory":"Construction",
            "type":"Services"
        }
    ],
    "sg:phone":"+1 505 894 7468",
    "sg:postcode":"87901",
    "sg:province":"NM",
    "sg:tags":[
        "marking",
        "maintenance",
        "parking"
    ],
    "wof:name":"Hot Shot Cleaning & Striping",
    "wof:placetype":"venue"
},
  "geometry": {"coordinates":[-107.263411,33.13819],"type":"Point"}
}