{
  "type": "Feature",
  "properties": {
    "iso:country":"US",
    "sg:address":"6122 4th St NW",
    "sg:city":"Albuquerque",
    "sg:classifiers":[
        {
            "category":"Restaurant",
            "type":"Food & Drink"
        }
    ],
    "sg:phone":"+1 505 345 5975",
    "sg:postcode":"87107",
    "sg:province":"NM",
    "sg:tags":[
        "eating"
    ],
    "wof:name":"Four Joys Chinese Restaurant",
    "wof:placetype":"venue"
},
  "geometry": {"coordinates":[-106.64,35.14489],"type":"Point"}
}