{
  "type": "Feature",
  "properties": {
    "iso:country":"US",
    "sg:address":"2601 W Main St",
    "sg:city":"Artesia",
    "sg:classifiers":[
        {
            "category":"Food & Beverages",
            "subcategory":"Groceries & Convenience Stores",
            "type":"Retail Goods"
        }
    ],
    "sg:phone":"+1 505 746 6669",
    "sg:postcode":"88210",
    "sg:province":"NM",
    "wof:name":"Little Giant Convenience Store",
    "wof:placetype":"venue"
},
  "geometry": {"coordinates":[-104.435427,32.842625],"type":"Point"}
}