{
  "type": "Feature",
  "properties": {
    "addr:full":"3601 34th Cir SE Rio Rancho NM 87124",
    "addr:housenumber":"3601",
    "addr:postcode":"87124",
    "addr:street":"34Th Cir Se",
    "iso:country":"US",
    "sg:address":"3601 34th Cir SE",
    "sg:city":"Rio Rancho",
    "sg:classifiers":[
        {
            "category":"Wholesale",
            "subcategory":"Vending Machines",
            "type":"Manufacturing & Wholesale Goods"
        }
    ],
    "sg:phone":"+1 505 896 3007",
    "sg:postcode":"87124",
    "sg:province":"NM",
    "wof:name":"Ben's Reliable Vending",
    "wof:placetype":"venue"
},
  "geometry": {"coordinates":[-106.661858,35.236884],"type":"Point"}
}