{
  "type": "Feature",
  "properties": {
    "iso:country":"US",
    "sg:address":"2011 Mountain Rd NW",
    "sg:city":"Albuquerque",
    "sg:classifiers":[
        {
            "category":"Restaurant",
            "type":"Food & Drink"
        }
    ],
    "sg:menulink":"http://www.allmenus.com/nm/albuquerque/91279-melting-pot/menu/",
    "sg:phone":"+1 505 843 6358",
    "sg:postcode":"87104",
    "sg:province":"NM",
    "sg:tags":[
        "new",
        "american"
    ],
    "wof:name":"Melting Pot",
    "wof:placetype":"venue"
},
  "geometry": {"coordinates":[-106.66845499999999,35.098416],"type":"Point"}
}