{
  "type": "Feature",
  "properties": {
    "iso:country":"US",
    "sg:address":"3807 Academy Pkwy S NE",
    "sg:city":"Albuquerque",
    "sg:classifiers":[
        {
            "category":"Shopping",
            "subcategory":"Pharmacy",
            "type":"Retail Goods"
        }
    ],
    "sg:phone":"+1 505 345 9299",
    "sg:postcode":"87109",
    "sg:province":"NM",
    "wof:name":"Pharmacare Health Svc",
    "wof:placetype":"venue"
},
  "geometry": {"coordinates":[-106.602901,35.156084],"type":"Point"}
}