{
  "type": "Feature",
  "properties": {
    "addr:full":"107 Granite Dr Ruidoso NM 88345",
    "addr:housenumber":"107",
    "addr:postcode":"88345",
    "addr:street":"Granite Dr",
    "iso:country":"US",
    "sg:address":"107 Granite Dr",
    "sg:city":"Ruidoso",
    "sg:classifiers":[
        {
            "category":"Building & Trades",
            "subcategory":"Plumbing",
            "type":"Services"
        }
    ],
    "sg:phone":"+1 505 258 4122",
    "sg:postcode":"88345",
    "sg:province":"NM",
    "sg:tags":[
        "plumbing",
        "contractor"
    ],
    "wof:name":"Welch Plumbing",
    "wof:placetype":"venue"
},
  "geometry": {"coordinates":[-105.656527,33.366017],"type":"Point"}
}