{
  "type": "Feature",
  "properties": {
    "iso:country":"US",
    "sg:address":"5617 Menaul Blvd NE",
    "sg:city":"Albuquerque",
    "sg:classifiers":[
        {
            "category":"Wholesale",
            "subcategory":"Medical Equipment & Supplies",
            "type":"Manufacturing & Wholesale Goods"
        }
    ],
    "sg:phone":"+1 505 242 1552",
    "sg:postcode":"87110",
    "sg:province":"NM",
    "sg:tags":[
        "physician",
        "surgeon"
    ],
    "wof:name":"Choice Medical",
    "wof:placetype":"venue"
},
  "geometry": {"coordinates":[-106.581012,35.109179],"type":"Point"}
}