{
  "type": "Feature",
  "properties": {
    "addr:full":"509 Roma Ave NW Albuquerque NM 87102",
    "addr:housenumber":"509",
    "addr:postcode":"87102",
    "addr:street":"Roma Ave Nw",
    "iso:country":"US",
    "sg:address":"509 Roma Ave NW",
    "sg:city":"Albuquerque",
    "sg:classifiers":[
        {
            "category":"Professional",
            "subcategory":"Lawyer & Legal Services",
            "type":"Services"
        }
    ],
    "sg:phone":"+1 505 243 8656",
    "sg:postcode":"87102",
    "sg:province":"NM",
    "wof:name":"Campos Mguel P Attorney At Law",
    "wof:placetype":"venue"
},
  "geometry": {"coordinates":[-106.653054,35.089549],"type":"Point"}
}