{
  "type": "Feature",
  "properties": {
    "addr:full":"2405 N Dal Paso St Hobbs NM 88240",
    "addr:housenumber":"2405",
    "addr:postcode":"88240",
    "addr:street":"N Dal Paso St",
    "iso:country":"US",
    "sg:address":"2405 N Dal Paso St",
    "sg:city":"Hobbs",
    "sg:classifiers":[
        {
            "category":"Food & Beverages",
            "subcategory":"Groceries & Convenience Stores",
            "type":"Retail Goods"
        }
    ],
    "sg:phone":"+1 505 392 4738",
    "sg:postcode":"88240",
    "sg:province":"NM",
    "wof:name":"Town & Country Food Store 90",
    "wof:placetype":"venue"
},
  "geometry": {"coordinates":[-103.127706,32.727939],"type":"Point"}
}