{
  "type": "Feature",
  "properties": {
    "iso:country":"US",
    "sg:address":"105 E Marcy Ave",
    "sg:city":"Santa Fe",
    "sg:classifiers":[
        {
            "category":"Restaurant",
            "type":"Food & Drink"
        }
    ],
    "sg:phone":"+1 505 995 9887",
    "sg:postcode":"87501",
    "sg:province":"NM",
    "wof:name":"Lynn's Web-Epicurean Delight",
    "wof:placetype":"venue"
},
  "geometry": {"coordinates":[-105.935233,35.688622],"type":"Point"}
}