{
  "type": "Feature",
  "properties": {
    "iso:country":"US",
    "sg:address":"211 W Reinken Ave",
    "sg:city":"Belen",
    "sg:classifiers":[
        {
            "category":"Retail",
            "subcategory":"Portrait Studio",
            "type":"Services"
        }
    ],
    "sg:phone":"+1 505 864 7454",
    "sg:postcode":"87002",
    "sg:province":"NM",
    "sg:tags":[
        "photo"
    ],
    "wof:name":"Black & White Photographs",
    "wof:placetype":"venue"
},
  "geometry": {"coordinates":[-106.778116,34.663049],"type":"Point"}
}