{
  "type": "Feature",
  "properties": {
    "iso:country":"US",
    "sg:address":"1902 Hubbard Dr",
    "sg:city":"Alamogordo",
    "sg:classifiers":[
        {
            "category":"Retail",
            "subcategory":"Repair Shop",
            "type":"Services"
        }
    ],
    "sg:phone":"+1 505 437 5113",
    "sg:postcode":"88310",
    "sg:province":"NM",
    "sg:tags":[
        "clocks",
        "electrical",
        "parts"
    ],
    "wof:name":"Thompson Electronics Service",
    "wof:placetype":"venue"
},
  "geometry": {"coordinates":[-105.941096,32.913814],"type":"Point"}
}