{
  "type": "Feature",
  "properties": {
    "iso:country":"US",
    "sg:address":"6005 Central Ave NW",
    "sg:city":"Albuquerque",
    "sg:classifiers":[
        {
            "category":"Personal",
            "subcategory":"Beauty Salon",
            "type":"Services"
        }
    ],
    "sg:phone":"+1 505 839 8373",
    "sg:postcode":"87105",
    "sg:province":"NM",
    "wof:name":"Xtremely Hot Creations-Teresa",
    "wof:placetype":"venue"
},
  "geometry": {"coordinates":[-106.704829,35.081295],"type":"Point"}
}