{
  "type": "Feature",
  "properties": {
    "iso:country":"US",
    "sg:address":"5620 Wyoming Blvd NE",
    "sg:city":"Albuquerque",
    "sg:classifiers":[
        {
            "category":"Arena",
            "subcategory":"Sports Club",
            "type":"Entertainment"
        }
    ],
    "sg:phone":"+1 505 837 2300",
    "sg:postcode":"87109",
    "sg:province":"NM",
    "wof:name":"Nike New Mexico Classic",
    "wof:placetype":"venue"
},
  "geometry": {"coordinates":[-106.55328,35.145262],"type":"Point"}
}