{
  "type": "Feature",
  "properties": {
    "addr:full":"1240 Cll de Comercio Santa Fe NM 87507",
    "addr:housenumber":"1240",
    "addr:postcode":"87507",
    "addr:street":"Cll De Comercio",
    "iso:country":"US",
    "sg:address":"1240 Cll de Comercio",
    "sg:city":"Santa Fe",
    "sg:classifiers":[
        {
            "category":"Retail",
            "subcategory":"Auto Repair",
            "type":"Services"
        }
    ],
    "sg:phone":"+1 505 473 0778",
    "sg:postcode":"87507",
    "sg:province":"NM",
    "sg:tags":[
        "repairing",
        "automobile"
    ],
    "wof:name":"European Automotive Svc",
    "wof:placetype":"venue"
},
  "geometry": {"coordinates":[-105.989473,35.661153],"type":"Point"}
}