{
  "type": "Feature",
  "properties": {
    "iso:country":"US",
    "sg:address":"701 N Florida Ave",
    "sg:city":"Alamogordo",
    "sg:classifiers":[
        {
            "category":"Retail",
            "subcategory":"Repair Shop",
            "type":"Services"
        }
    ],
    "sg:phone":"+1 505 434 0038",
    "sg:postcode":"88310",
    "sg:province":"NM",
    "sg:tags":[
        "cleaners",
        "parts",
        "vacuum"
    ],
    "wof:name":"L J Vacuum Svc",
    "wof:placetype":"venue"
},
  "geometry": {"coordinates":[-105.952977,32.897968],"type":"Point"}
}