{
  "type": "Feature",
  "properties": {
    "iso:country":"US",
    "sg:address":"1206 E 8th St",
    "sg:city":"Alamogordo",
    "sg:classifiers":[
        {
            "category":"Shopping",
            "type":"Retail Goods"
        }
    ],
    "sg:phone":"+1 505 434 2852",
    "sg:postcode":"88310",
    "sg:province":"NM",
    "sg:tags":[
        "merchandise"
    ],
    "wof:name":"Woods & Wax",
    "wof:placetype":"venue"
},
  "geometry": {"coordinates":[-105.947481,32.897873],"type":"Point"}
}