{
  "type": "Feature",
  "properties": {
    "iso:country":"US",
    "sg:address":"9308 Susan Ave SE",
    "sg:city":"Albuquerque",
    "sg:classifiers":[
        {
            "category":"Professional",
            "subcategory":"Lawyer & Legal Services",
            "type":"Services"
        }
    ],
    "sg:phone":"+1 505 262 0757",
    "sg:postcode":"87123",
    "sg:province":"NM",
    "sg:tags":[
        "attorney"
    ],
    "wof:name":"John T Fitzpatrick",
    "wof:placetype":"venue"
},
  "geometry": {"coordinates":[-106.54357,35.067674],"type":"Point"}
}