{
  "type": "Feature",
  "properties": {
    "addr:full":"2500 Candelaria Rd NE Albuquerque NM 87107",
    "addr:housenumber":"2500",
    "addr:postcode":"87107",
    "addr:street":"Candelaria Rd Ne",
    "iso:country":"US",
    "sg:address":"2500 Candelaria Rd NE",
    "sg:city":"Albuquerque",
    "sg:classifiers":[
        {
            "category":"Organizations",
            "subcategory":"Non-profit Organization",
            "type":"Services"
        }
    ],
    "sg:phone":"+1 505 884 0220",
    "sg:postcode":"87107",
    "sg:province":"NM",
    "wof:name":"Solo Club Inc",
    "wof:placetype":"venue"
},
  "geometry": {"coordinates":[-106.61520400000001,35.115946],"type":"Point"}
}