{
  "type": "Feature",
  "properties": {
    "iso:country":"US",
    "sg:address":"150 N Alameda Blvd",
    "sg:city":"Las Cruces",
    "sg:classifiers":[
        {
            "category":"Education",
            "subcategory":"School",
            "type":"Public Place"
        }
    ],
    "sg:phone":"+1 505 527 9496",
    "sg:postcode":"88005",
    "sg:province":"NM",
    "sg:website":"www.lcps.com",
    "wof:name":"Central Elementary School",
    "wof:placetype":"venue"
},
  "geometry": {"coordinates":[-106.78122399999999,32.309449],"type":"Point"}
}