{
  "type": "Feature",
  "properties": {
    "iso:country":"US",
    "sg:address":"3901 Donald Rd SW",
    "sg:city":"Albuquerque",
    "sg:classifiers":[
        {
            "category":"Education",
            "subcategory":"Dance Studio",
            "type":"Public Place"
        }
    ],
    "sg:phone":"+1 505 877 4954",
    "sg:postcode":"87105",
    "sg:province":"NM",
    "wof:name":"Reginas Dance Studio",
    "wof:placetype":"venue"
},
  "geometry": {"coordinates":[-106.688478,35.019428],"type":"Point"}
}