{
  "type": "Feature",
  "properties": {
    "iso:country":"US",
    "sg:address":"520 Chama St NE",
    "sg:city":"Albuquerque",
    "sg:classifiers":[
        {
            "category":"Insurance",
            "subcategory":"Insurance Agent",
            "type":"Services"
        }
    ],
    "sg:phone":"+1 505 266 2373",
    "sg:postcode":"87108",
    "sg:province":"NM",
    "wof:name":"Allen Agency",
    "wof:placetype":"venue"
},
  "geometry": {"coordinates":[-106.56629,35.085039],"type":"Point"}
}