{
  "type": "Feature",
  "properties": {
    "iso:country":"US",
    "sg:address":"133 Eubank Blvd NE",
    "sg:city":"Albuquerque",
    "sg:classifiers":[
        {
            "category":"Building & Trades",
            "subcategory":"Cleaning & Sanitation",
            "type":"Services"
        }
    ],
    "sg:phone":"+1 505 263 2545",
    "sg:postcode":"87123",
    "sg:province":"NM",
    "sg:tags":[
        "window"
    ],
    "wof:name":"K/D Window Cleaning",
    "wof:placetype":"venue"
},
  "geometry": {"coordinates":[-106.53244599999999,35.073704],"type":"Point"}
}