{
  "type": "Feature",
  "properties": {
    "addr:full":"510 Anglada Ln Taos NM 87571",
    "addr:housenumber":"510",
    "addr:postcode":"87571",
    "addr:street":"Anglada Ln",
    "iso:country":"US",
    "sg:address":"510 Anglada Ln",
    "sg:city":"Taos",
    "sg:classifiers":[
        {
            "category":"Shopping",
            "subcategory":"Beauty & Cosmetics",
            "type":"Retail Goods"
        }
    ],
    "sg:phone":"+1 505 737 5404",
    "sg:postcode":"87571",
    "sg:province":"NM",
    "sg:tags":[
        "merchandise"
    ],
    "wof:name":"HMS Crown Inc",
    "wof:placetype":"venue"
},
  "geometry": {"coordinates":[-105.558684,36.387752],"type":"Point"}
}