{
  "type": "Feature",
  "properties": {
    "iso:country":"US",
    "sg:address":"3000 E 20th St",
    "sg:city":"Farmington",
    "sg:classifiers":[
        {
            "category":"Shopping",
            "subcategory":"Hobbies, Toys, & Games",
            "type":"Retail Goods"
        }
    ],
    "sg:phone":"+1 505 325 4464",
    "sg:postcode":"87401",
    "sg:province":"NM",
    "sg:tags":[
        "material",
        "craft",
        "supply"
    ],
    "wof:name":"Hobby Lobby Creative Center",
    "wof:placetype":"venue"
},
  "geometry": {"coordinates":[-108.166257,36.748113],"type":"Point"}
}