{
  "type": "Feature",
  "properties": {
    "addr:full":"2204 Sudderth Dr Ruidoso NM 88345",
    "addr:housenumber":"2204",
    "addr:postcode":"88345",
    "addr:street":"Sudderth Dr",
    "iso:country":"US",
    "sg:address":"2204 Sudderth Dr",
    "sg:city":"Ruidoso",
    "sg:classifiers":[
        {
            "category":"Shopping",
            "subcategory":"Gifts & Souvenirs",
            "type":"Retail Goods"
        }
    ],
    "sg:phone":"+1 505 257 4417",
    "sg:postcode":"88345",
    "sg:province":"NM",
    "sg:tags":[
        "balloon",
        "artist"
    ],
    "wof:name":"Something Special",
    "wof:placetype":"venue"
},
  "geometry": {"coordinates":[-105.66802800000001,33.331044],"type":"Point"}
}