{
  "type": "Feature",
  "properties": {
    "iso:country":"US",
    "sg:address":"1150 Bosque Farms Blvd",
    "sg:city":"Bosque Farms",
    "sg:classifiers":[
        {
            "category":"Restaurant",
            "type":"Food & Drink"
        }
    ],
    "sg:phone":"+1 505 869 3878",
    "sg:postcode":"87068",
    "sg:province":"NM",
    "wof:name":"Burritos Alinstante",
    "wof:placetype":"venue"
},
  "geometry": {"coordinates":[-106.690555,34.85785],"type":"Point"}
}