{
  "type": "Feature",
  "properties": {
    "addr:full":"2211 N Main St Roswell NM 88201",
    "addr:housenumber":"2211",
    "addr:postcode":"88201",
    "addr:street":"N Main St",
    "iso:country":"US",
    "sg:address":"2211 N Main St",
    "sg:city":"Roswell",
    "sg:classifiers":[
        {
            "category":"Banks & Credit Unions",
            "subcategory":"Bank",
            "type":"Services"
        }
    ],
    "sg:phone":"+1 505 627 3000",
    "sg:postcode":"88201",
    "sg:province":"NM",
    "wof:name":"Otero Federal Credit Union",
    "wof:placetype":"venue"
},
  "geometry": {"coordinates":[-104.522977,33.419483],"type":"Point"}
}