{
  "type": "Feature",
  "properties": {
    "iso:country":"US",
    "sg:address":"2244 Wyoming Blvd NE",
    "sg:city":"Albuquerque",
    "sg:classifiers":[
        {
            "category":"Real Estate",
            "subcategory":"Real Estate Agent",
            "type":"Services"
        }
    ],
    "sg:phone":"+1 505 237 0001",
    "sg:postcode":"87112",
    "sg:province":"NM",
    "sg:tags":[
        "investment"
    ],
    "wof:name":"Weingarten Realty",
    "wof:placetype":"venue"
},
  "geometry": {"coordinates":[-106.55082,35.108853],"type":"Point"}
}