{
  "type": "Feature",
  "properties": {
    "iso:country":"US",
    "sg:address":"4108 Dietz Ct NW",
    "sg:city":"Albuquerque",
    "sg:classifiers":[
        {
            "category":"Education",
            "subcategory":"Special Training",
            "type":"Public Place"
        }
    ],
    "sg:phone":"+1 505 341 9321",
    "sg:postcode":"87107",
    "sg:province":"NM",
    "sg:tags":[
        "center"
    ],
    "wof:name":"Hemophilla Foundation-Nm",
    "wof:placetype":"venue"
},
  "geometry": {"coordinates":[-106.66468999999999,35.138761],"type":"Point"}
}