{
  "type": "Feature",
  "properties": {
    "addr:full":"1120 Hst Rte 66 Gallup NM 87301",
    "addr:housenumber":"1120",
    "addr:postcode":"87301",
    "addr:street":"Hst Rte 66",
    "iso:country":"US",
    "sg:address":"1120 Hst Rte 66",
    "sg:city":"Gallup",
    "sg:classifiers":[
        {
            "category":"Food & Beverages",
            "subcategory":"Liquor & Beverages",
            "type":"Retail Goods"
        }
    ],
    "sg:phone":"+1 505 722 3227",
    "sg:postcode":"87301",
    "sg:province":"NM",
    "wof:name":"California Liquors Uptown",
    "wof:placetype":"venue"
},
  "geometry": {"coordinates":[-108.754029,35.524234],"type":"Point"}
}