{
  "type": "Feature",
  "properties": {
    "iso:country":"US",
    "sg:address":"2512 E Lohman Ave",
    "sg:city":"Las Cruces",
    "sg:classifiers":[
        {
            "category":"Autos & Motor Vehicles",
            "subcategory":"Fuel & Gas Station",
            "type":"Retail Goods"
        }
    ],
    "sg:phone":"+1 505 532 0348",
    "sg:postcode":"88011",
    "sg:province":"NM",
    "sg:tags":[
        "station",
        "gasoline"
    ],
    "wof:name":"Nacho Station",
    "wof:placetype":"venue"
},
  "geometry": {"coordinates":[-106.744753,32.314943],"type":"Point"}
}