{
  "type": "Feature",
  "properties": {
    "iso:country":"US",
    "sg:address":"1426 S Roosevelt Rd Ar",
    "sg:city":"Elida",
    "sg:classifiers":[
        {
            "category":"Building & Trades",
            "subcategory":"Construction",
            "type":"Services"
        }
    ],
    "sg:phone":"+1 505 274 6249",
    "sg:postcode":"88116",
    "sg:province":"NM",
    "sg:tags":[
        "fence"
    ],
    "wof:name":"Lynn Beard",
    "wof:placetype":"venue"
},
  "geometry": {"coordinates":[-103.77001,33.868703],"type":"Point"}
}