{
  "type": "Feature",
  "properties": {
    "addr:full":"933 San Pedro Dr NE Albuquerque NM 87108",
    "addr:housenumber":"933",
    "addr:postcode":"87108",
    "addr:street":"San Pedro Dr Ne",
    "iso:country":"US",
    "sg:address":"933 San Pedro Dr NE",
    "sg:city":"Albuquerque",
    "sg:classifiers":[
        {
            "category":"Professional",
            "subcategory":"Business Services",
            "type":"Services"
        }
    ],
    "sg:phone":"+1 505 265 2511",
    "sg:postcode":"87108",
    "sg:province":"NM",
    "sg:tags":[
        "recording",
        "studio"
    ],
    "sg:website":"www.santafecenterstudios.com",
    "wof:name":"Santa Fe Center Studios",
    "wof:placetype":"venue"
},
  "geometry": {"coordinates":[-106.577549,35.086905],"type":"Point"}
}