{
  "type": "Feature",
  "properties": {
    "addr:full":"4513 Topaz Ave NW Albuquerque NM 87114",
    "addr:housenumber":"4513",
    "addr:postcode":"87114",
    "addr:street":"Topaz Ave Nw",
    "iso:country":"US",
    "sg:address":"4513 Topaz Ave NW",
    "sg:city":"Albuquerque",
    "sg:classifiers":[
        {
            "category":"Retail",
            "subcategory":"Laundry & Dry Cleaning",
            "type":"Services"
        }
    ],
    "sg:phone":"+1 505 792 0880",
    "sg:postcode":"87114",
    "sg:province":"NM",
    "sg:tags":[
        "cleaners",
        "rug",
        "carpet"
    ],
    "wof:name":"Richard's Floor Care",
    "wof:placetype":"venue"
},
  "geometry": {"coordinates":[-106.67596500000001,35.209154],"type":"Point"}
}