{
  "type": "Feature",
  "properties": {
    "addr:full":"5001 Central Ave NW Albuquerque NM 87105",
    "addr:housenumber":"5001",
    "addr:postcode":"87105",
    "addr:street":"Central Ave Nw",
    "iso:country":"US",
    "sg:address":"5001 Central Ave NW",
    "sg:city":"Albuquerque",
    "sg:classifiers":[
        {
            "category":"Building & Trades",
            "subcategory":"Construction",
            "type":"Services"
        }
    ],
    "sg:phone":"+1 505 883 4887",
    "sg:postcode":"87105",
    "sg:province":"NM",
    "sg:tags":[
        "restoration",
        "cleaning",
        "contractor"
    ],
    "wof:name":"Rico Restoration LLC",
    "wof:placetype":"venue"
},
  "geometry": {"coordinates":[-106.694468,35.083586],"type":"Point"}
}