{
  "type": "Feature",
  "properties": {
    "iso:country":"US",
    "sg:address":"1212 Arvilla Ave NW",
    "sg:city":"Albuquerque",
    "sg:classifiers":[
        {
            "category":"Wholesale",
            "subcategory":"Construction Materials",
            "type":"Manufacturing & Wholesale Goods"
        }
    ],
    "sg:phone":"+1 505 243 2550",
    "sg:postcode":"87107",
    "sg:province":"NM",
    "sg:tags":[
        "entrance",
        "retail",
        "automatic"
    ],
    "wof:name":"Aluminum Door Service Inc",
    "wof:placetype":"venue"
},
  "geometry": {"coordinates":[-106.656486,35.12405],"type":"Point"}
}