{
  "type": "Feature",
  "properties": {
    "iso:country":"US",
    "sg:address":"829 San Lorenzo Ave NW",
    "sg:city":"Albuquerque",
    "sg:classifiers":[
        {
            "category":"Communications",
            "subcategory":"Film & Video Production",
            "type":"Services"
        }
    ],
    "sg:phone":"+1 505 341 2246",
    "sg:postcode":"87107",
    "sg:province":"NM",
    "sg:tags":[
        "motion"
    ],
    "wof:name":"ME & Pete Familiar Production",
    "wof:placetype":"venue"
},
  "geometry": {"coordinates":[-106.648906,35.127426],"type":"Point"}
}