{
  "type": "Feature",
  "properties": {
    "iso:country":"US",
    "sg:address":"206 N Summit Ave",
    "sg:city":"Mountainair",
    "sg:classifiers":[
        {
            "category":"Retail",
            "subcategory":"Auto Rental",
            "type":"Services"
        }
    ],
    "sg:phone":"+1 505 847 0077",
    "sg:postcode":"87036",
    "sg:province":"NM",
    "sg:tags":[
        "renting",
        "truck",
        "leasing"
    ],
    "wof:name":"U-Haul Co",
    "wof:placetype":"venue"
},
  "geometry": {"coordinates":[-106.240635,34.522406],"type":"Point"}
}