{
  "type": "Feature",
  "properties": {
    "iso:country":"US",
    "sg:address":"9401 Montara Ct NW",
    "sg:city":"Albuquerque",
    "sg:classifiers":[
        {
            "category":"Professional",
            "subcategory":"Management & Consulting",
            "type":"Services"
        }
    ],
    "sg:phone":"+1 505 922 6360",
    "sg:postcode":"87114",
    "sg:province":"NM",
    "sg:tags":[
        "retail",
        "direct",
        "sales"
    ],
    "wof:name":"Jerome Pearson",
    "wof:placetype":"venue"
},
  "geometry": {"coordinates":[-106.734675,35.189326],"type":"Point"}
}