{
  "type": "Feature",
  "properties": {
    "iso:country":"US",
    "sg:address":"2624 N Main St",
    "sg:city":"Roswell",
    "sg:classifiers":[
        {
            "category":"Bakery",
            "type":"Food & Drink"
        }
    ],
    "sg:menulink":"http://www.allmenus.com/nm/roswell/100140-golden-corral/menu/",
    "sg:phone":"+1 505 622 5102",
    "sg:postcode":"88201",
    "sg:province":"NM",
    "sg:tags":[
        "american",
        "pastry"
    ],
    "wof:name":"Golden Corral",
    "wof:placetype":"venue"
},
  "geometry": {"coordinates":[-104.523094,33.426198],"type":"Point"}
}