{
  "type": "Feature",
  "properties": {
    "iso:country":"US",
    "sg:address":"826 Mullen Rd NW",
    "sg:city":"Albuquerque",
    "sg:classifiers":[
        {
            "category":"Travel",
            "subcategory":"Travel Agent",
            "type":"Entertainment"
        }
    ],
    "sg:phone":"+1 505 343 9400",
    "sg:postcode":"87107",
    "sg:province":"NM",
    "sg:tags":[
        "tours",
        "promoter"
    ],
    "sg:website":"www.farhorizon.com",
    "wof:name":"Far Horizons Archaeological",
    "wof:placetype":"venue"
},
  "geometry": {"coordinates":[-106.646835,35.151523],"type":"Point"}
}