{
  "type": "Feature",
  "properties": {
    "iso:country":"US",
    "sg:address":"2009 W Pierce St",
    "sg:city":"Carlsbad",
    "sg:classifiers":[
        {
            "category":"Restaurant",
            "type":"Food & Drink"
        }
    ],
    "sg:phone":"+1 505 234 1393",
    "sg:postcode":"88220",
    "sg:province":"NM",
    "sg:tags":[
        "eating"
    ],
    "wof:name":"Subway",
    "wof:placetype":"venue"
},
  "geometry": {"coordinates":[-104.252319,32.437871],"type":"Point"}
}