{
  "type": "Feature",
  "properties": {
    "iso:country":"US",
    "sg:address":"3050 Rockhound Rd SW",
    "sg:city":"Deming",
    "sg:classifiers":[
        {
            "category":"Wholesale",
            "subcategory":"Construction Materials",
            "type":"Manufacturing & Wholesale Goods"
        }
    ],
    "sg:phone":"+1 505 546 8366",
    "sg:postcode":"88030",
    "sg:province":"NM",
    "sg:tags":[
        "sand",
        "gravel"
    ],
    "wof:name":"O'Kelley Sand & Gravel",
    "wof:placetype":"venue"
},
  "geometry": {"coordinates":[-107.791431,32.195825],"type":"Point"}
}