{
  "type": "Feature",
  "properties": {
    "iso:country":"US",
    "sg:address":"2897 Trades West Rd",
    "sg:city":"Santa Fe",
    "sg:classifiers":[
        {
            "category":"Retail",
            "subcategory":"Auto Repair",
            "type":"Services"
        }
    ],
    "sg:phone":"+1 505 471 0796",
    "sg:postcode":"87507",
    "sg:province":"NM",
    "sg:tags":[
        "wrecker"
    ],
    "wof:name":"Professional A Towing",
    "wof:placetype":"venue"
},
  "geometry": {"coordinates":[-105.991251,35.661464],"type":"Point"}
}