{
  "type": "Feature",
  "properties": {
    "iso:country":"US",
    "sg:address":"12621 Lomas Blvd NE",
    "sg:city":"Albuquerque",
    "sg:classifiers":[
        {
            "category":"Real Estate",
            "subcategory":"Real Estate Operator",
            "type":"Services"
        }
    ],
    "sg:phone":"+1 505 292 0075",
    "sg:postcode":"87112",
    "sg:province":"NM",
    "sg:tags":[
        "apartment"
    ],
    "wof:name":"Townhouse Apartments",
    "wof:placetype":"venue"
},
  "geometry": {"coordinates":[-106.50786100000001,35.086654],"type":"Point"}
}