{
  "type": "Feature",
  "properties": {
    "addr:full":"8001 Pennsylvania Cir NE Albuquerque NM 87110",
    "addr:housenumber":"8001",
    "addr:postcode":"87110",
    "addr:street":"Pennsylvania Cir Ne",
    "iso:country":"US",
    "sg:address":"8001 Pennsylvania Cir NE",
    "sg:city":"Albuquerque",
    "sg:classifiers":[
        {
            "category":"Insurance",
            "subcategory":"Insurance Agent",
            "type":"Services"
        }
    ],
    "sg:phone":"+1 505 262 1000",
    "sg:postcode":"87110",
    "sg:province":"NM",
    "wof:name":"Insurance Exchange",
    "wof:placetype":"venue"
},
  "geometry": {"coordinates":[-106.558195,35.089659],"type":"Point"}
}