{
  "type": "Feature",
  "properties": {
    "iso:country":"US",
    "sg:address":"1882 S Espina St",
    "sg:city":"Las Cruces",
    "sg:classifiers":[
        {
            "category":"Professional",
            "subcategory":"Engineering",
            "type":"Services"
        }
    ],
    "sg:phone":"+1 505 524 3542",
    "sg:postcode":"88001",
    "sg:province":"NM",
    "sg:tags":[
        "engineer"
    ],
    "wof:name":"Advanced Logistics Support Crp",
    "wof:placetype":"venue"
},
  "geometry": {"coordinates":[-106.76066899999999,32.29119],"type":"Point"}
}