{
  "type": "Feature",
  "properties": {
    "iso:country":"US",
    "sg:address":"1031 Cam Santander",
    "sg:city":"Santa Fe",
    "sg:classifiers":[
        {
            "category":"Building & Trades",
            "subcategory":"Construction",
            "type":"Services"
        }
    ],
    "sg:phone":"+1 505 988 5393",
    "sg:postcode":"87505",
    "sg:province":"NM",
    "sg:tags":[
        "contractor"
    ],
    "wof:name":"Simis Tile Co",
    "wof:placetype":"venue"
},
  "geometry": {"coordinates":[-105.918049,35.674443],"type":"Point"}
}