{
  "type": "Feature",
  "properties": {
    "addr:full":"1309 Parsifal St NE Albuquerque NM 87112",
    "addr:housenumber":"1309",
    "addr:postcode":"87112",
    "addr:street":"Parsifal St Ne",
    "iso:country":"US",
    "sg:address":"1309 Parsifal St NE",
    "sg:city":"Albuquerque",
    "sg:classifiers":[
        {
            "category":"Recreation",
            "type":"Entertainment"
        }
    ],
    "sg:phone":"+1 505 299 9462",
    "sg:postcode":"87112",
    "sg:province":"NM",
    "sg:tags":[
        "amusement"
    ],
    "wof:name":"Sortz Fun",
    "wof:placetype":"venue"
},
  "geometry": {"coordinates":[-106.53702800000001,35.092999],"type":"Point"}
}