{
  "type": "Feature",
  "properties": {
    "iso:country":"US",
    "sg:address":"1309 Parsifal St NE",
    "sg:city":"Albuquerque",
    "sg:classifiers":[
        {
            "category":"Recreation",
            "type":"Entertainment"
        }
    ],
    "sg:phone":"+1 505 299 9462",
    "sg:postcode":"87112",
    "sg:province":"NM",
    "sg:tags":[
        "amusement"
    ],
    "wof:name":"Sortz Fun",
    "wof:placetype":"venue"
},
  "geometry": {"coordinates":[-106.537028,35.092999],"type":"Point"}
}