{
  "type": "Feature",
  "properties": {
    "addr:full":"1704 Rio Rancho Blvd NE Albuquerque NM 87124",
    "addr:housenumber":"1704",
    "addr:postcode":"87124",
    "addr:street":"Rio Rancho Blvd Ne",
    "iso:country":"US",
    "sg:address":"1704 Rio Rancho Blvd NE",
    "sg:city":"Albuquerque",
    "sg:classifiers":[
        {
            "category":"Banks & Credit Unions",
            "subcategory":"Bank",
            "type":"Services"
        }
    ],
    "sg:phone":"+1 505 765 2001",
    "sg:postcode":"87124",
    "sg:province":"NM",
    "sg:tags":[
        "national",
        "commercial"
    ],
    "wof:name":"Bank Of America",
    "wof:placetype":"venue"
},
  "geometry": {"coordinates":[-106.604699,35.287282],"type":"Point"}
}