{
  "type": "Feature",
  "properties": {
    "addr:full":"10900 Central Park Dr NE Albuquerque NM 87123",
    "addr:postcode":"10900;87123",
    "addr:street":"Central Park Dr Ne",
    "iso:country":"US",
    "sg:address":"10900 Central Park Dr NE",
    "sg:city":"Albuquerque",
    "sg:classifiers":[
        {
            "category":"Real Estate",
            "subcategory":"Developer",
            "type":"Services"
        }
    ],
    "sg:phone":"+1 505 332 9370",
    "sg:postcode":"87123",
    "sg:province":"NM",
    "wof:name":"Viva",
    "wof:placetype":"venue"
},
  "geometry": {"coordinates":[-106.52636699999999,35.07539],"type":"Point"}
}