{
  "type": "Feature",
  "properties": {
    "iso:country":"US",
    "sg:address":"4 Everest Ct",
    "sg:city":"Cedar Crest",
    "sg:classifiers":[
        {
            "category":"Farming",
            "subcategory":"Livestock Farm",
            "type":"Manufacturing & Wholesale Goods"
        }
    ],
    "sg:phone":"+1 505 252 1043",
    "sg:postcode":"87008",
    "sg:province":"NM",
    "sg:tags":[
        "trainer",
        "horse"
    ],
    "wof:name":"Mark W Harper Horse Trainer",
    "wof:placetype":"venue"
},
  "geometry": {"coordinates":[-106.378936,35.089413],"type":"Point"}
}