{
  "type": "Feature",
  "properties": {
    "iso:country":"US",
    "sg:address":"2418 Miles Rd SE",
    "sg:city":"Albuquerque",
    "sg:classifiers":[
        {
            "category":"Social Services",
            "type":"Services"
        }
    ],
    "sg:phone":"+1 505 246 9972",
    "sg:postcode":"87106",
    "sg:province":"NM",
    "sg:tags":[
        "counselor",
        "marriage",
        "family"
    ],
    "wof:name":"Rosario Romero",
    "wof:placetype":"venue"
},
  "geometry": {"coordinates":[-106.620012,35.057044],"type":"Point"}
}