{
  "type": "Feature",
  "properties": {
    "addr:full":"8101 Harper Rd NE Albuquerque NM 87111",
    "addr:housenumber":"8101",
    "addr:postcode":"87111",
    "addr:street":"Harper Rd Ne",
    "iso:country":"US",
    "sg:address":"8101 Harper Rd NE",
    "sg:city":"Albuquerque",
    "sg:classifiers":[
        {
            "category":"Autos & Motor Vehicles",
            "subcategory":"Fuel & Gas Station",
            "type":"Retail Goods"
        }
    ],
    "sg:phone":"+1 505 797 8301",
    "sg:postcode":"87111",
    "sg:province":"NM",
    "sg:tags":[
        "oil"
    ],
    "wof:name":"Shell",
    "wof:placetype":"venue"
},
  "geometry": {"coordinates":[-106.557929,35.158904],"type":"Point"}
}