{
  "type": "Feature",
  "properties": {
    "iso:country":"US",
    "sg:address":"1624 Goff Blvd SW",
    "sg:city":"Albuquerque",
    "sg:classifiers":[
        {
            "category":"Food & Beverages",
            "subcategory":"Specialty",
            "type":"Retail Goods"
        }
    ],
    "sg:phone":"+1 505 452 0853",
    "sg:postcode":"87105",
    "sg:province":"NM",
    "sg:tags":[
        "water",
        "bulk",
        "company"
    ],
    "wof:name":"Water Store",
    "wof:placetype":"venue"
},
  "geometry": {"coordinates":[-106.677869,35.054783],"type":"Point"}
}