{
  "type": "Feature",
  "properties": {
    "iso:country":"US",
    "sg:address":"20 Quedo Rd",
    "sg:city":"Santa Fe",
    "sg:classifiers":[
        {
            "category":"Shopping",
            "type":"Retail Goods"
        }
    ],
    "sg:phone":"+1 505 466 6054",
    "sg:postcode":"87508",
    "sg:province":"NM",
    "sg:tags":[
        "merchandise"
    ],
    "wof:name":"Gatherings",
    "wof:placetype":"venue"
},
  "geometry": {"coordinates":[-105.957165,35.520033],"type":"Point"}
}