{
  "type": "Feature",
  "properties": {
    "iso:country":"US",
    "sg:address":"223 Shirley Ln",
    "sg:city":"Anthony",
    "sg:classifiers":[
        {
            "category":"Building & Trades",
            "subcategory":"Pest Control",
            "type":"Services"
        }
    ],
    "sg:phone":"+1 505 824 0530",
    "sg:postcode":"88081",
    "sg:province":"NM",
    "wof:name":"Ambush Exterminating",
    "wof:placetype":"venue"
},
  "geometry": {"coordinates":[-106.443336,32.025422],"type":"Point"}
}