{
  "type": "Feature",
  "properties": {
    "addr:full":"300 E Motel Dr Lordsburg NM 88045",
    "addr:housenumber":"300",
    "addr:postcode":"88045",
    "addr:street":"Dr",
    "iso:country":"US",
    "sg:address":"300 E Motel Dr",
    "sg:city":"Lordsburg",
    "sg:classifiers":[
        {
            "category":"Home & Garden",
            "subcategory":"Building Materials",
            "type":"Retail Goods"
        },
        {
            "category":"Home & Garden",
            "subcategory":"Furniture",
            "type":"Retail Goods"
        }
    ],
    "sg:phone":"+1 505 542 3340",
    "sg:postcode":"88045",
    "sg:province":"NM",
    "sg:tags":[
        "paint",
        "merchandise",
        "general"
    ],
    "wof:name":"Home Town Supply",
    "wof:placetype":"venue"
},
  "geometry": {"coordinates":[-108.706852,32.349677],"type":"Point"}
}