{
  "type": "Feature",
  "properties": {
    "iso:country":"US",
    "sg:address":"531 Pso del Pueblo Sur",
    "sg:city":"Taos",
    "sg:classifiers":[
        {
            "category":"Home & Garden",
            "subcategory":"Home Furnishings",
            "type":"Retail Goods"
        }
    ],
    "sg:phone":"+1 505 758 3183",
    "sg:postcode":"87571",
    "sg:province":"NM",
    "sg:tags":[
        "curtain",
        "made",
        "drapery"
    ],
    "wof:name":"Spivey's Decorating",
    "wof:placetype":"venue"
},
  "geometry": {"coordinates":[-105.5779,36.397885],"type":"Point"}
}