{
  "type": "Feature",
  "properties": {
    "iso:country":"US",
    "sg:address":"2800 W Marland St",
    "sg:city":"Hobbs",
    "sg:classifiers":[
        {
            "category":"Professional",
            "subcategory":"Management & Consulting",
            "type":"Services"
        }
    ],
    "sg:phone":"+1 505 393 8830",
    "sg:postcode":"88240",
    "sg:province":"NM",
    "sg:tags":[
        "consultant",
        "safety"
    ],
    "wof:name":"American Safety Svc Inc",
    "wof:placetype":"venue"
},
  "geometry": {"coordinates":[-103.172755,32.696506],"type":"Point"}
}