{
  "type": "Feature",
  "properties": {
    "iso:country":"US",
    "sg:address":"1564 Navajo Dr",
    "sg:city":"Santa Fe",
    "sg:classifiers":[
        {
            "category":"Real Estate",
            "subcategory":"Real Estate Agent",
            "type":"Services"
        }
    ],
    "sg:phone":"+1 505 982 3520",
    "sg:postcode":"87505",
    "sg:province":"NM",
    "sg:tags":[
        "management"
    ],
    "wof:name":"Morris Property Management",
    "wof:placetype":"venue"
},
  "geometry": {"coordinates":[-105.965751,35.666607],"type":"Point"}
}