{
  "type": "Feature",
  "properties": {
    "addr:full":"1600 S Ave D Portales NM 88130",
    "addr:housenumber":"1600",
    "addr:postcode":"88130",
    "addr:street":"S Ave D",
    "iso:country":"US",
    "sg:address":"1600 S Ave D",
    "sg:city":"Portales",
    "sg:classifiers":[
        {
            "category":"Restaurant",
            "type":"Food & Drink"
        }
    ],
    "sg:phone":"+1 505 356 5587",
    "sg:postcode":"88130",
    "sg:province":"NM",
    "sg:tags":[
        "eating"
    ],
    "wof:name":"Cattle Baron Restaurant 1",
    "wof:placetype":"venue"
},
  "geometry": {"coordinates":[-103.33472399999999,34.17442],"type":"Point"}
}