{
  "type": "Feature",
  "properties": {
    "addr:full":"4624 Hilltop Pl NE Albuquerque NM 87111",
    "addr:housenumber":"4624",
    "addr:postcode":"87111",
    "addr:street":"Hilltop Pl Ne",
    "iso:country":"US",
    "sg:address":"4624 Hilltop Pl NE",
    "sg:city":"Albuquerque",
    "sg:classifiers":[
        {
            "category":"Professional",
            "subcategory":"Management & Consulting",
            "type":"Services"
        }
    ],
    "sg:phone":"+1 505 323 4144",
    "sg:postcode":"87111",
    "sg:province":"NM",
    "sg:tags":[
        "business"
    ],
    "wof:name":"Hilltop Consulting Services",
    "wof:placetype":"venue"
},
  "geometry": {"coordinates":[-106.49407100000001,35.133767],"type":"Point"}
}