{
  "type": "Feature",
  "properties": {
    "iso:country":"US",
    "sg:address":"312 Utter Ln",
    "sg:city":"Tularosa",
    "sg:classifiers":[
        {
            "category":"Wholesale",
            "subcategory":"Hardware",
            "type":"Manufacturing & Wholesale Goods"
        }
    ],
    "sg:phone":"+1 505 585 9828",
    "sg:postcode":"88352",
    "sg:province":"NM",
    "sg:tags":[
        "refrigerating"
    ],
    "wof:name":"Sainz Refrigeration",
    "wof:placetype":"venue"
},
  "geometry": {"coordinates":[-106.01467100000001,33.075703],"type":"Point"}
}