{
  "type": "Feature",
  "properties": {
    "iso:country":"US",
    "sg:address":"7201 Jefferson St NE",
    "sg:city":"Albuquerque",
    "sg:classifiers":[
        {
            "category":"Wholesale",
            "subcategory":"Machinery & Supplies",
            "type":"Manufacturing & Wholesale Goods"
        }
    ],
    "sg:phone":"+1 505 761 0123",
    "sg:postcode":"87109",
    "sg:province":"NM",
    "sg:tags":[
        "equipment",
        "conveyor",
        "conveying"
    ],
    "wof:name":"Conveyors & Equipment",
    "wof:placetype":"venue"
},
  "geometry": {"coordinates":[-106.593323,35.1618],"type":"Point"}
}