{
  "type": "Feature",
  "properties": {
    "addr:full":"24 Garcia Dr Bernalillo NM 87004",
    "addr:housenumber":"24",
    "addr:postcode":"87004",
    "addr:street":"Garcia Dr",
    "iso:country":"US",
    "sg:address":"24 Garcia Dr",
    "sg:city":"Bernalillo",
    "sg:classifiers":[
        {
            "category":"Building & Trades",
            "subcategory":"Plumbing",
            "type":"Services"
        }
    ],
    "sg:phone":"+1 505 771 0941",
    "sg:postcode":"87004",
    "sg:province":"NM",
    "sg:tags":[
        "contractor"
    ],
    "wof:name":"Warrior Mechanical",
    "wof:placetype":"venue"
},
  "geometry": {"coordinates":[-106.526257,35.341646],"type":"Point"}
}