{
  "type": "Feature",
  "properties": {
    "iso:country":"US",
    "sg:address":"1300 Luisa St",
    "sg:city":"Santa Fe",
    "sg:classifiers":[
        {
            "category":"Professional",
            "subcategory":"Engineering",
            "type":"Services"
        }
    ],
    "sg:phone":"+1 505 983 4992",
    "sg:postcode":"87505",
    "sg:province":"NM",
    "wof:name":"Druc Engineering LLC",
    "wof:placetype":"venue"
},
  "geometry": {"coordinates":[-105.950748,35.670002],"type":"Point"}
}