{
  "type": "Feature",
  "properties": {
    "iso:country":"US",
    "sg:address":"1110 Bellamah Dr",
    "sg:city":"Alamogordo",
    "sg:classifiers":[
        {
            "category":"Building & Trades",
            "subcategory":"Construction",
            "type":"Services"
        }
    ],
    "sg:phone":"+1 505 434 8630",
    "sg:postcode":"88310",
    "sg:province":"NM",
    "sg:tags":[
        "builder",
        "operative"
    ],
    "wof:name":"Eagle Mountain Inc",
    "wof:placetype":"venue"
},
  "geometry": {"coordinates":[-105.930747,32.900739],"type":"Point"}
}