{
  "type": "Feature",
  "properties": {
    "iso:country":"US",
    "sg:address":"2726 Candelaria Rd NW",
    "sg:city":"Albuquerque",
    "sg:classifiers":[
        {
            "category":"Real Estate",
            "subcategory":"Architect",
            "type":"Services"
        }
    ],
    "sg:phone":"+1 505 344 6746",
    "sg:postcode":"87107",
    "sg:province":"NM",
    "sg:tags":[
        "architectural"
    ],
    "wof:name":"Siegel Design",
    "wof:placetype":"venue"
},
  "geometry": {"coordinates":[-106.67967299999999,35.126831],"type":"Point"}
}