{
  "type": "Feature",
  "properties": {
    "addr:full":"5120 4th St NW Albuquerque NM 87107",
    "addr:housenumber":"5120",
    "addr:postcode":"87107",
    "addr:street":"4Th St Nw",
    "iso:country":"US",
    "sg:address":"5120 4th St NW",
    "sg:city":"Albuquerque",
    "sg:classifiers":[
        {
            "category":"Wholesale",
            "subcategory":"Construction Materials",
            "type":"Manufacturing & Wholesale Goods"
        },
        {
            "category":"Building & Trades",
            "subcategory":"Construction",
            "type":"Services"
        }
    ],
    "sg:phone":"+1 505 344 9636",
    "sg:postcode":"87107",
    "sg:province":"NM",
    "sg:tags":[
        "gate",
        "accessory",
        "fence",
        "contractor"
    ],
    "sg:website":"http://www.alamedagates.com",
    "wof:name":"Alameda Fence Co Inc",
    "wof:placetype":"venue"
},
  "geometry": {"coordinates":[-106.642065,35.134406],"type":"Point"}
}