{
  "type": "Feature",
  "properties": {
    "iso:country":"US",
    "sg:address":"202 S Light Plant Rd",
    "sg:city":"Aztec",
    "sg:classifiers":[
        {
            "category":"Government",
            "subcategory":"Office",
            "type":"Public Place"
        }
    ],
    "sg:phone":"+1 505 334 0259",
    "sg:postcode":"87410",
    "sg:province":"NM",
    "sg:tags":[
        "village"
    ],
    "wof:name":"Aztec City Electrical Dept",
    "wof:placetype":"venue"
},
  "geometry": {"coordinates":[-108.00940900000001,36.825183],"type":"Point"}
}