{
  "type": "Feature",
  "properties": {
    "iso:country":"US",
    "sg:address":"822 Pso del Pueblo Sur",
    "sg:city":"Taos",
    "sg:classifiers":[
        {
            "category":"Home & Garden",
            "subcategory":"Building Materials",
            "type":"Retail Goods"
        }
    ],
    "sg:phone":"+1 505 758 8089",
    "sg:postcode":"87571",
    "sg:province":"NM",
    "sg:tags":[
        "glass",
        "window",
        "plate"
    ],
    "wof:name":"Glasco",
    "wof:placetype":"venue"
},
  "geometry": {"coordinates":[-105.58391899999999,36.388388],"type":"Point"}
}