{
  "type": "Feature",
  "properties": {
    "iso:country":"US",
    "sg:address":"7408 Yarwood St NE",
    "sg:city":"Albuquerque",
    "sg:classifiers":[
        {
            "category":"Health Services",
            "subcategory":"Hospital",
            "type":"Services"
        }
    ],
    "sg:phone":"+1 505 293 7553",
    "sg:postcode":"87109",
    "sg:province":"NM",
    "sg:tags":[
        "mental"
    ],
    "wof:name":"New Life Homes Inc",
    "wof:placetype":"venue"
},
  "geometry": {"coordinates":[-106.563462,35.154527],"type":"Point"}
}