{
  "type": "Feature",
  "properties": {
    "iso:country":"US",
    "sg:address":"7338 US Hwy 70",
    "sg:city":"Alamogordo",
    "sg:classifiers":[
        {
            "category":"Shopping",
            "subcategory":"Discount & Variety Stores",
            "type":"Retail Goods"
        }
    ],
    "sg:phone":"+1 505 437 6020",
    "sg:postcode":"88310",
    "sg:province":"NM",
    "sg:tags":[
        "merchandise",
        "general"
    ],
    "wof:name":"Mc Ginn's Vounty Store",
    "wof:placetype":"venue"
},
  "geometry": {"coordinates":[-105.988547,32.994439],"type":"Point"}
}