{
  "type": "Feature",
  "properties": {
    "iso:country":"US",
    "sg:address":"420 River Rd",
    "sg:city":"Santa Rosa",
    "sg:classifiers":[
        {
            "category":"Social Services",
            "type":"Services"
        }
    ],
    "sg:phone":"+1 505 472 5377",
    "sg:postcode":"88435",
    "sg:province":"NM",
    "wof:name":"Eastern Plains Caa Inc",
    "wof:placetype":"venue"
},
  "geometry": {"coordinates":[-104.691695,34.93508],"type":"Point"}
}