{
  "type": "Feature",
  "properties": {
    "iso:country":"US",
    "sg:address":"200 Cam Colores",
    "sg:city":"Santa Fe",
    "sg:classifiers":[
        {
            "category":"Recreation",
            "type":"Entertainment"
        }
    ],
    "sg:phone":"+1 505 473 0905",
    "sg:postcode":"87507",
    "sg:province":"NM",
    "sg:tags":[
        "stable"
    ],
    "wof:name":"Santa Fe Reiners & Terry Berg",
    "wof:placetype":"venue"
},
  "geometry": {"coordinates":[-106.083527,35.591435],"type":"Point"}
}