{
  "type": "Feature",
  "properties": {
    "addr:full":"2603 W Main St Farmington NM 87401",
    "addr:housenumber":"2603",
    "addr:postcode":"87401",
    "addr:street":"W Main St",
    "iso:country":"US",
    "sg:address":"2603 W Main St",
    "sg:city":"Farmington",
    "sg:classifiers":[
        {
            "category":"Organizations",
            "subcategory":"Professional Association",
            "type":"Services"
        }
    ],
    "sg:phone":"+1 505 326 2591",
    "sg:postcode":"87401",
    "sg:province":"NM",
    "sg:tags":[
        "business"
    ],
    "wof:name":"UPS",
    "wof:placetype":"venue"
},
  "geometry": {"coordinates":[-108.243814,36.733016],"type":"Point"}
}