{
  "type": "Feature",
  "properties": {
    "iso:country":"US",
    "sg:address":"62 Midway Rd",
    "sg:city":"Lemitar",
    "sg:classifiers":[
        {
            "category":"Autos & Motor Vehicles",
            "subcategory":"Automobile Sales",
            "type":"Retail Goods"
        }
    ],
    "sg:phone":"+1 505 835 2460",
    "sg:postcode":"87823",
    "sg:province":"NM",
    "sg:tags":[
        "aircraft"
    ],
    "wof:name":"Haines Aviation Consultants",
    "wof:placetype":"venue"
},
  "geometry": {"coordinates":[-106.921716,34.176494],"type":"Point"}
}