{
  "type": "Feature",
  "properties": {
    "iso:country":"US",
    "sg:address":"1325 Washington St",
    "sg:city":"Anthony",
    "sg:classifiers":[
        {
            "category":"Education",
            "subcategory":"School",
            "type":"Public Place"
        }
    ],
    "sg:phone":"+1 505 882 6200",
    "sg:postcode":"88021",
    "sg:province":"NM",
    "wof:name":"Gadsden School District Adm",
    "wof:placetype":"venue"
},
  "geometry": {"coordinates":[-106.623368,31.999814],"type":"Point"}
}