{
  "type": "Feature",
  "properties": {
    "addr:full":"750 N Valley Dr Las Cruces NM 88005",
    "addr:housenumber":"750",
    "addr:postcode":"88005",
    "addr:street":"N Valley Dr",
    "iso:country":"US",
    "sg:address":"750 N Valley Dr",
    "sg:city":"Las Cruces",
    "sg:classifiers":[
        {
            "category":"Autos & Motor Vehicles",
            "subcategory":"Auto Supplies",
            "type":"Retail Goods"
        }
    ],
    "sg:phone":"+1 505 523 9337",
    "sg:postcode":"88005",
    "sg:province":"NM",
    "sg:tags":[
        "automotive",
        "used",
        "towing",
        "parts"
    ],
    "wof:name":"Action Auto Parts",
    "wof:placetype":"venue"
},
  "geometry": {"coordinates":[-106.796221,32.311372],"type":"Point"}
}