{
  "type": "Feature",
  "properties": {
    "iso:country":"US",
    "sg:address":"1102 Kachina Dr",
    "sg:city":"Roswell",
    "sg:classifiers":[
        {
            "category":"Building & Trades",
            "subcategory":"Construction",
            "type":"Services"
        }
    ],
    "sg:phone":"+1 505 622 9850",
    "sg:postcode":"88201",
    "sg:province":"NM",
    "sg:tags":[
        "general",
        "contractor"
    ],
    "wof:name":"JDL Construction Co",
    "wof:placetype":"venue"
},
  "geometry": {"coordinates":[-104.509951,33.433057],"type":"Point"}
}