{
  "type": "Feature",
  "properties": {
    "iso:country":"US",
    "sg:address":"612 E Tucumcari Blvd",
    "sg:city":"Tucumcari",
    "sg:classifiers":[
        {
            "category":"Home & Garden",
            "subcategory":"Building Materials",
            "type":"Retail Goods"
        }
    ],
    "sg:phone":"+1 505 461 1241",
    "sg:postcode":"88401",
    "sg:province":"NM",
    "sg:tags":[
        "lumber"
    ],
    "wof:name":"Burns Lumber & Hardware",
    "wof:placetype":"venue"
},
  "geometry": {"coordinates":[-103.719624,35.171656],"type":"Point"}
}