{
  "type": "Feature",
  "properties": {
    "iso:country":"US",
    "sg:address":"2701 Mary Ellen St NE",
    "sg:city":"Albuquerque",
    "sg:classifiers":[
        {
            "category":"Retail",
            "subcategory":"Repair Shop",
            "type":"Services"
        }
    ],
    "sg:phone":"+1 505 323 5205",
    "sg:postcode":"87112",
    "sg:province":"NM",
    "sg:tags":[
        "upholsterer"
    ],
    "wof:name":"Casa De Decor",
    "wof:placetype":"venue"
},
  "geometry": {"coordinates":[-106.53228900000001,35.113346],"type":"Point"}
}