{
  "type": "Feature",
  "properties": {
    "iso:country":"US",
    "sg:address":"4505 Shadow Ave NW",
    "sg:city":"Albuquerque",
    "sg:classifiers":[
        {
            "category":"Travel",
            "subcategory":"Travel Agent",
            "type":"Entertainment"
        }
    ],
    "sg:phone":"+1 505 328 3444",
    "sg:postcode":"87114",
    "sg:province":"NM",
    "sg:tags":[
        "tours",
        "promoter"
    ],
    "wof:name":"Sand To Salt Tours Outfitters",
    "wof:placetype":"venue"
},
  "geometry": {"coordinates":[-106.676014,35.210104],"type":"Point"}
}