{
  "type": "Feature",
  "properties": {
    "addr:full":"1600 Mountain Rd NW Albuquerque NM 87104",
    "addr:housenumber":"1600",
    "addr:postcode":"87104",
    "addr:street":"Mountain Rd Nw",
    "iso:country":"US",
    "sg:address":"1600 Mountain Rd NW",
    "sg:city":"Albuquerque",
    "sg:classifiers":[
        {
            "category":"Real Estate",
            "subcategory":"Real Estate Operator",
            "type":"Services"
        }
    ],
    "sg:phone":"+1 505 883 5030",
    "sg:postcode":"87104",
    "sg:province":"NM",
    "sg:tags":[
        "property",
        "management"
    ],
    "wof:name":"Mountain Road Eductl Partnr",
    "wof:placetype":"venue"
},
  "geometry": {"coordinates":[-106.665105,35.097059],"type":"Point"}
}