{
  "type": "Feature",
  "properties": {
    "iso:country":"US",
    "sg:address":"4517 Central Ave NW",
    "sg:city":"Albuquerque",
    "sg:classifiers":[
        {
            "category":"Restaurant",
            "type":"Food & Drink"
        }
    ],
    "sg:menulink":"http://www.allmenus.com/nm/albuquerque/208512-taco-bell/menu/",
    "sg:phone":"+1 505 836 0159",
    "sg:postcode":"87105",
    "sg:province":"NM",
    "sg:tags":[
        "mexican"
    ],
    "wof:name":"Taco Bell",
    "wof:placetype":"venue"
},
  "geometry": {"coordinates":[-106.689035,35.085212],"type":"Point"}
}