{
  "type": "Feature",
  "properties": {
    "iso:country":"US",
    "sg:address":"604 N 26th St",
    "sg:city":"Artesia",
    "sg:classifiers":[
        {
            "category":"Health Services",
            "subcategory":"Optometrist",
            "type":"Services"
        }
    ],
    "sg:phone":"+1 505 748 2015",
    "sg:postcode":"88210",
    "sg:province":"NM",
    "wof:name":"J R Davis OD Optometrist",
    "wof:placetype":"venue"
},
  "geometry": {"coordinates":[-104.42965,32.943916],"type":"Point"}
}