{
  "type": "Feature",
  "properties": {
    "addr:full":"5109 Coors Blvd NW Albuquerque NM 87120",
    "addr:housenumber":"5109",
    "addr:postcode":"87120",
    "addr:street":"Coors Blvd Nw",
    "iso:country":"US",
    "sg:address":"5109 Coors Blvd NW",
    "sg:city":"Albuquerque",
    "sg:classifiers":[
        {
            "category":"Restaurant",
            "type":"Food & Drink"
        }
    ],
    "sg:menulink":"http://www.allmenus.com/nm/albuquerque/26851-dominos-pizza/menu/",
    "sg:phone":"+1 505 836 7500",
    "sg:postcode":"87120",
    "sg:province":"NM",
    "sg:tags":[
        "american",
        "wing",
        "pizza"
    ],
    "wof:name":"Domino's Pizza",
    "wof:placetype":"venue"
},
  "geometry": {"coordinates":[-106.69418899999999,35.144217],"type":"Point"}
}