{
  "type": "Feature",
  "properties": {
    "addr:full":"950 Zuni Dr Alamogordo NM 88310",
    "addr:housenumber":"950",
    "addr:postcode":"88310",
    "addr:street":"Zuni Dr",
    "iso:country":"US",
    "sg:address":"950 Zuni Dr",
    "sg:city":"Alamogordo",
    "sg:classifiers":[
        {
            "category":"Retail",
            "subcategory":"Animal Services",
            "type":"Services"
        }
    ],
    "sg:phone":"+1 505 434 0555",
    "sg:postcode":"88310",
    "sg:province":"NM",
    "wof:name":"Woof Woof World & Meow Manor",
    "wof:placetype":"venue"
},
  "geometry": {"coordinates":[-105.977328,32.876161],"type":"Point"}
}