{
  "type": "Feature",
  "properties": {
    "iso:country":"US",
    "sg:address":"5507 Broadway Blvd SE",
    "sg:city":"Albuquerque",
    "sg:classifiers":[
        {
            "category":"Retail",
            "subcategory":"Auto Repair",
            "type":"Services"
        }
    ],
    "sg:phone":"+1 505 873 3233",
    "sg:postcode":"87105",
    "sg:province":"NM",
    "sg:tags":[
        "wrecker"
    ],
    "wof:name":"Broadway Industries",
    "wof:placetype":"venue"
},
  "geometry": {"coordinates":[-106.65339400000001,34.994962],"type":"Point"}
}