{
  "type": "Feature",
  "properties": {
    "iso:country":"US",
    "sg:address":"6741 Kelly Ann Rd NE",
    "sg:city":"Albuquerque",
    "sg:classifiers":[
        {
            "category":"Building & Trades",
            "subcategory":"Construction",
            "type":"Services"
        }
    ],
    "sg:phone":"+1 505 934 0220",
    "sg:postcode":"87109",
    "sg:province":"NM",
    "sg:tags":[
        "house"
    ],
    "wof:name":"Next Level Builders Ltd",
    "wof:placetype":"venue"
},
  "geometry": {"coordinates":[-106.57089,35.147237],"type":"Point"}
}