{
  "type": "Feature",
  "properties": {
    "iso:country":"US",
    "sg:address":"1239 Delamar Ave NW",
    "sg:city":"Albuquerque",
    "sg:classifiers":[
        {
            "category":"Building & Trades",
            "subcategory":"Equipment Rental",
            "type":"Services"
        }
    ],
    "sg:phone":"+1 505 247 2731",
    "sg:postcode":"87107",
    "sg:province":"NM",
    "wof:name":"Avhq Rental Services",
    "wof:placetype":"venue"
},
  "geometry": {"coordinates":[-106.651904,35.136354],"type":"Point"}
}