{
  "type": "Feature",
  "properties": {
    "addr:full":"4228 Chavez Rd Las Cruces NM 88007",
    "addr:housenumber":"4228",
    "addr:postcode":"88007",
    "addr:street":"Chavez Rd",
    "iso:country":"US",
    "sg:address":"4228 Chavez Rd",
    "sg:city":"Las Cruces",
    "sg:classifiers":[
        {
            "category":"Health Services",
            "subcategory":"Health Practitioner",
            "type":"Services"
        }
    ],
    "sg:phone":"+1 505 524 4674",
    "sg:postcode":"88007",
    "sg:province":"NM",
    "wof:name":"Lil Brown Therapy Center",
    "wof:placetype":"venue"
},
  "geometry": {"coordinates":[-106.851482,32.348019],"type":"Point"}
}