{
  "type": "Feature",
  "properties": {
    "addr:full":"8201 Golf Course Rd NW Albuquerque NM 87120",
    "addr:housenumber":"8201",
    "addr:postcode":"87120",
    "addr:street":"Golf Course Rd Nw",
    "iso:country":"US",
    "sg:address":"8201 Golf Course Rd NW",
    "sg:city":"Albuquerque",
    "sg:classifiers":[
        {
            "category":"Health Services",
            "subcategory":"Chiropractor",
            "type":"Services"
        }
    ],
    "sg:phone":"+1 505 792 3311",
    "sg:postcode":"87120",
    "sg:province":"NM",
    "wof:name":"Health Plex Chiropractic",
    "wof:placetype":"venue"
},
  "geometry": {"coordinates":[-106.687814,35.176978],"type":"Point"}
}