{
  "type": "Feature",
  "properties": {
    "iso:country":"US",
    "sg:address":"8220 Louisiana Blvd NE",
    "sg:city":"Albuquerque",
    "sg:classifiers":[
        {
            "category":"Professional",
            "subcategory":"Research",
            "type":"Services"
        }
    ],
    "sg:phone":"+1 505 266 6611",
    "sg:postcode":"87113",
    "sg:province":"NM",
    "sg:tags":[
        "environmental",
        "ecological"
    ],
    "sg:website":"www.enservice.com",
    "wof:name":"Environmental Services Inc",
    "wof:placetype":"venue"
},
  "geometry": {"coordinates":[-106.56870499999999,35.173978],"type":"Point"}
}