{
  "type": "Feature",
  "properties": {
    "addr:full":"1404 N Kentucky Ave Roswell NM 88201",
    "addr:housenumber":"1404",
    "addr:postcode":"88201",
    "addr:street":"N Kentucky Ave",
    "iso:country":"US",
    "sg:address":"1404 N Kentucky Ave",
    "sg:city":"Roswell",
    "sg:classifiers":[
        {
            "category":"Organizations",
            "subcategory":"Membership Organization",
            "type":"Services"
        }
    ],
    "sg:phone":"+1 505 623 5777",
    "sg:postcode":"88201",
    "sg:province":"NM",
    "sg:tags":[
        "athletic"
    ],
    "wof:name":"New Mexico Senior Olympic's",
    "wof:placetype":"venue"
},
  "geometry": {"coordinates":[-104.52752700000001,33.408738],"type":"Point"}
}