{
  "type": "Feature",
  "properties": {
    "addr:full":"1816 E 25th St Farmington NM 87401",
    "addr:housenumber":"1816",
    "addr:postcode":"87401",
    "addr:street":"E 25Th St",
    "iso:country":"US",
    "sg:address":"1816 E 25th St",
    "sg:city":"Farmington",
    "sg:classifiers":[
        {
            "category":"Wholesale",
            "subcategory":"Chemicals & Plastics",
            "type":"Manufacturing & Wholesale Goods"
        }
    ],
    "sg:phone":"+1 505 325 5457",
    "sg:postcode":"87401",
    "sg:province":"NM",
    "sg:tags":[
        "cleaning",
        "compound"
    ],
    "sg:website":"www.fuller.com",
    "wof:name":"Fuller Brush Co",
    "wof:placetype":"venue"
},
  "geometry": {"coordinates":[-108.18211599999999,36.753074],"type":"Point"}
}