{
  "type": "Feature",
  "properties": {
    "addr:full":"2317 State Hwy 469 San Jon NM 88434",
    "addr:housenumber":"2317",
    "addr:postcode":"88434",
    "addr:street":"State Hwy 469",
    "iso:country":"US",
    "sg:address":"2317 State Hwy 469",
    "sg:city":"San Jon",
    "sg:classifiers":[
        {
            "category":"Sports & Exercise",
            "subcategory":"Bowling",
            "type":"Entertainment"
        }
    ],
    "sg:phone":"+1 505 576 2402",
    "sg:postcode":"88434",
    "sg:province":"NM",
    "sg:tags":[
        "center"
    ],
    "wof:name":"Womens International Bowl",
    "wof:placetype":"venue"
},
  "geometry": {"coordinates":[-103.331357,35.088479],"type":"Point"}
}