{
  "type": "Feature",
  "properties": {
    "iso:country":"US",
    "sg:address":"813 W Arrington St",
    "sg:city":"Farmington",
    "sg:classifiers":[
        {
            "category":"Wholesale",
            "subcategory":"Construction Materials",
            "type":"Manufacturing & Wholesale Goods"
        },
        {
            "category":"Manufacturing",
            "subcategory":"Chemicals & Compounds",
            "type":"Manufacturing & Wholesale Goods"
        }
    ],
    "sg:phone":"+1 505 326 5924",
    "sg:postcode":"87401",
    "sg:province":"NM",
    "sg:tags":[
        "glass",
        "product",
        "mfg"
    ],
    "wof:name":"P P G Industries Inc",
    "wof:placetype":"venue"
},
  "geometry": {"coordinates":[-108.218208,36.730257],"type":"Point"}
}