{
  "type": "Feature",
  "properties": {
    "addr:full":"1901 Macbeth Ct NE Albuquerque NM 87112",
    "addr:housenumber":"1901",
    "addr:postcode":"87112",
    "addr:street":"Macbeth Ct Ne",
    "iso:country":"US",
    "sg:address":"1901 Macbeth Ct NE",
    "sg:city":"Albuquerque",
    "sg:classifiers":[
        {
            "category":"Personal",
            "type":"Services"
        }
    ],
    "sg:phone":"+1 505 291 9036",
    "sg:postcode":"87112",
    "sg:province":"NM",
    "wof:name":"A Peaceful Healing Massage",
    "wof:placetype":"venue"
},
  "geometry": {"coordinates":[-106.50815,35.104918],"type":"Point"}
}