{
  "type": "Feature",
  "properties": {
    "iso:country":"US",
    "sg:address":"2709 Compa Ct NE",
    "sg:city":"Albuquerque",
    "sg:classifiers":[
        {
            "category":"Government",
            "subcategory":"Police Station",
            "type":"Public Place"
        }
    ],
    "sg:phone":"+1 505 332 4285",
    "sg:postcode":"87112",
    "sg:province":"NM",
    "sg:tags":[
        "department"
    ],
    "wof:name":"Albuquerque Police Department",
    "wof:placetype":"venue"
},
  "geometry": {"coordinates":[-106.503579,35.113547],"type":"Point"}
}