{
  "type": "Feature",
  "properties": {
    "iso:country":"US",
    "sg:address":"115 E 19th St",
    "sg:city":"Roswell",
    "sg:classifiers":[
        {
            "category":"Health Services",
            "subcategory":"Health Practitioner",
            "type":"Services"
        }
    ],
    "sg:phone":"+1 505 627 7767",
    "sg:postcode":"88201",
    "sg:province":"NM",
    "sg:tags":[
        "therapist",
        "physical"
    ],
    "wof:name":"Sports Care Of Roswell",
    "wof:placetype":"venue"
},
  "geometry": {"coordinates":[-104.522733,33.416025],"type":"Point"}
}