{
  "type": "Feature",
  "properties": {
    "iso:country":"US",
    "sg:address":"103 Chuckwagon Rd",
    "sg:city":"Carlsbad",
    "sg:classifiers":[
        {
            "category":"Shopping",
            "subcategory":"Gifts & Souvenirs",
            "type":"Retail Goods"
        }
    ],
    "sg:phone":"+1 505 885 1522",
    "sg:postcode":"88220",
    "sg:province":"NM",
    "sg:tags":[
        "basket",
        "parcel"
    ],
    "wof:name":"Desert Country Gift Baskets",
    "wof:placetype":"venue"
},
  "geometry": {"coordinates":[-104.22229,32.314961],"type":"Point"}
}