{
  "type": "Feature",
  "properties": {
    "iso:country":"US",
    "sg:address":"13 Lockheed Dr",
    "sg:city":"Alamogordo",
    "sg:classifiers":[
        {
            "category":"Arts & Performance",
            "subcategory":"Theater",
            "type":"Entertainment"
        }
    ],
    "sg:phone":"+1 505 437 4535",
    "sg:postcode":"88310",
    "sg:province":"NM",
    "sg:tags":[
        "group"
    ],
    "wof:name":"A & D Sound Syst",
    "wof:placetype":"venue"
},
  "geometry": {"coordinates":[-105.959154,32.9444],"type":"Point"}
}