{
  "type": "Feature",
  "properties": {
    "iso:country":"US",
    "sg:address":"4010 Carlisle Blvd NE",
    "sg:city":"Albuquerque",
    "sg:classifiers":[
        {
            "category":"Organizations",
            "subcategory":"Professional Association",
            "type":"Services"
        }
    ],
    "sg:phone":"+1 505 888 1812",
    "sg:postcode":"87107",
    "sg:province":"NM",
    "sg:tags":[
        "business"
    ],
    "wof:name":"New Mexico Grocers Association",
    "wof:placetype":"venue"
},
  "geometry": {"coordinates":[-106.60405799999999,35.127011],"type":"Point"}
}