{
  "type": "Feature",
  "properties": {
    "iso:country":"US",
    "sg:address":"202 Central Ave SE",
    "sg:city":"Albuquerque",
    "sg:classifiers":[
        {
            "category":"Building & Trades",
            "subcategory":"Construction",
            "type":"Services"
        }
    ],
    "sg:phone":"+1 505 243 1354",
    "sg:postcode":"87102",
    "sg:province":"NM",
    "sg:tags":[
        "contractor"
    ],
    "wof:name":"KCC Contractor",
    "wof:placetype":"venue"
},
  "geometry": {"coordinates":[-106.643401,35.083423],"type":"Point"}
}