{
  "type": "Feature",
  "properties": {
    "iso:country":"US",
    "sg:address":"520 N Main St",
    "sg:city":"Belen",
    "sg:classifiers":[
        {
            "category":"Education",
            "subcategory":"School",
            "type":"Public Place"
        }
    ],
    "sg:phone":"+1 505 864 4466",
    "sg:postcode":"87002",
    "sg:province":"NM",
    "sg:website":"www.belen.k12.nm.us",
    "wof:name":"Belen Schools",
    "wof:placetype":"venue"
},
  "geometry": {"coordinates":[-106.774931,34.665496],"type":"Point"}
}