{
  "type": "Feature",
  "properties": {
    "addr:full":"5700 Manzanillo Loop NE Albuquerque NM 87111",
    "addr:housenumber":"5700",
    "addr:postcode":"87111",
    "addr:street":"Manzanillo Loop Ne",
    "iso:country":"US",
    "sg:address":"5700 Manzanillo Loop NE",
    "sg:city":"Albuquerque",
    "sg:classifiers":[
        {
            "category":"Professional",
            "subcategory":"Business Services",
            "type":"Services"
        }
    ],
    "sg:phone":"+1 505 872 9447",
    "sg:postcode":"87111",
    "sg:province":"NM",
    "wof:name":"Genistar Technologies Inc",
    "wof:placetype":"venue"
},
  "geometry": {"coordinates":[-106.52191000000001,35.146129],"type":"Point"}
}