{
  "type": "Feature",
  "properties": {
    "iso:country":"US",
    "sg:address":"10117 Mesa Arriba Ave NE",
    "sg:city":"Albuquerque",
    "sg:classifiers":[
        {
            "category":"Building & Trades",
            "subcategory":"Plumbing",
            "type":"Services"
        }
    ],
    "sg:phone":"+1 505 298 8560",
    "sg:postcode":"87111",
    "sg:province":"NM",
    "sg:tags":[
        "heating",
        "contractor"
    ],
    "wof:name":"Gallipoli Radiant LLC",
    "wof:placetype":"venue"
},
  "geometry": {"coordinates":[-106.527616,35.12037],"type":"Point"}
}