{
  "type": "Feature",
  "properties": {
    "iso:country":"US",
    "sg:address":"210 Truman St NE",
    "sg:city":"Albuquerque",
    "sg:classifiers":[
        {
            "category":"Social Services",
            "type":"Services"
        }
    ],
    "sg:phone":"+1 505 254 9947",
    "sg:postcode":"87108",
    "sg:province":"NM",
    "sg:tags":[
        "child",
        "referral",
        "care"
    ],
    "sg:website":"www.ywca.org",
    "wof:name":"Pan Child Care Food Program",
    "wof:placetype":"venue"
},
  "geometry": {"coordinates":[-106.587354,35.081616],"type":"Point"}
}