{
  "type": "Feature",
  "properties": {
    "addr:full":"11515 Menaul Blvd NE Albuquerque NM 87112",
    "addr:housenumber":"11515",
    "addr:postcode":"87112",
    "addr:street":"Menaul Blvd Ne",
    "iso:country":"US",
    "sg:address":"11515 Menaul Blvd NE",
    "sg:city":"Albuquerque",
    "sg:classifiers":[
        {
            "category":"Retail",
            "subcategory":"Car Wash",
            "type":"Services"
        }
    ],
    "sg:phone":"+1 505 271 6496",
    "sg:postcode":"87112",
    "sg:province":"NM",
    "sg:tags":[
        "operated",
        "polishing",
        "washing"
    ],
    "wof:name":"High Desert Car Wash",
    "wof:placetype":"venue"
},
  "geometry": {"coordinates":[-106.512179,35.108822],"type":"Point"}
}