{
  "type": "Feature",
  "properties": {
    "addr:full":"115 E Alicante Rd Santa Fe NM 87505",
    "addr:housenumber":"115",
    "addr:postcode":"87505",
    "addr:street":"E Alicante Rd",
    "iso:country":"US",
    "sg:address":"115 E Alicante Rd",
    "sg:city":"Santa Fe",
    "sg:classifiers":[
        {
            "category":"Personal",
            "subcategory":"Beauty Salon",
            "type":"Services"
        }
    ],
    "sg:phone":"+1 505 204 1388",
    "sg:postcode":"87505",
    "sg:province":"NM",
    "sg:tags":[
        "treatment",
        "skin"
    ],
    "wof:name":"Sara Malmar",
    "wof:placetype":"venue"
},
  "geometry": {"coordinates":[-105.941215,35.665401],"type":"Point"}
}