{
  "type": "Feature",
  "properties": {
    "iso:country":"US",
    "sg:address":"4124 Broadway Blvd SE",
    "sg:city":"Albuquerque",
    "sg:classifiers":[
        {
            "category":"Retail",
            "subcategory":"Animal Services",
            "type":"Services"
        }
    ],
    "sg:phone":"+1 505 877 6789",
    "sg:postcode":"87105",
    "sg:province":"NM",
    "wof:name":"Tejas Industries",
    "wof:placetype":"venue"
},
  "geometry": {"coordinates":[-106.646653,35.023899],"type":"Point"}
}