{
  "type": "Feature",
  "properties": {
    "iso:country":"US",
    "sg:address":"1500 S 8th St",
    "sg:city":"Deming",
    "sg:classifiers":[
        {
            "category":"Local Transit",
            "type":"Transportation"
        }
    ],
    "sg:phone":"+1 505 544 4241",
    "sg:postcode":"88030",
    "sg:province":"NM",
    "sg:tags":[
        "ambulance"
    ],
    "wof:name":"Elite Medical Transport LLC",
    "wof:placetype":"venue"
},
  "geometry": {"coordinates":[-107.76867,32.254109],"type":"Point"}
}