{
  "type": "Feature",
  "properties": {
    "iso:country":"US",
    "sg:address":"1008 Pso de la Cuma",
    "sg:city":"Santa Fe",
    "sg:classifiers":[
        {
            "category":"Real Estate",
            "subcategory":"Developer",
            "type":"Services"
        }
    ],
    "sg:phone":"+1 505 995 0655",
    "sg:postcode":"87501",
    "sg:province":"NM",
    "wof:name":"DIV",
    "wof:placetype":"venue"
},
  "geometry": {"coordinates":[-105.938507,35.703273],"type":"Point"}
}