{
  "type": "Feature",
  "properties": {
    "addr:full":"8200 Tina Dr NE Albuquerque NM 87109",
    "addr:housenumber":"8200",
    "addr:postcode":"87109",
    "addr:street":"Tina Dr Ne",
    "iso:country":"US",
    "sg:address":"8200 Tina Dr NE",
    "sg:city":"Albuquerque",
    "sg:classifiers":[
        {
            "category":"Personal",
            "subcategory":"Nail Salon",
            "type":"Services"
        }
    ],
    "sg:phone":"+1 505 450 2874",
    "sg:postcode":"87109",
    "sg:province":"NM",
    "wof:name":"Nails By Michelle",
    "wof:placetype":"venue"
},
  "geometry": {"coordinates":[-106.553917,35.168549],"type":"Point"}
}