{
  "type": "Feature",
  "properties": {
    "iso:country":"US",
    "sg:address":"311 E 14th St",
    "sg:city":"Silver City",
    "sg:classifiers":[
        {
            "category":"Health Services",
            "subcategory":"Doctor",
            "type":"Services"
        }
    ],
    "sg:phone":"+1 505 388 2528",
    "sg:postcode":"88061",
    "sg:province":"NM",
    "sg:tags":[
        "dentist"
    ],
    "wof:name":"Eric York DDS",
    "wof:placetype":"venue"
},
  "geometry": {"coordinates":[-108.273587,32.779428],"type":"Point"}
}