{
  "type": "Feature",
  "properties": {
    "iso:country":"US",
    "sg:address":"2800 E 7th St",
    "sg:city":"Clovis",
    "sg:classifiers":[
        {
            "category":"Wholesale",
            "subcategory":"Electrical",
            "type":"Manufacturing & Wholesale Goods"
        }
    ],
    "sg:phone":"+1 505 762 3244",
    "sg:postcode":"88101",
    "sg:province":"NM",
    "sg:tags":[
        "alarm",
        "burglar",
        "system"
    ],
    "wof:name":"First Alarm",
    "wof:placetype":"venue"
},
  "geometry": {"coordinates":[-103.17178699999999,34.404948],"type":"Point"}
}