{
  "type": "Feature",
  "properties": {
    "iso:country":"US",
    "sg:address":"6 Industrial Park Ln",
    "sg:city":"Belen",
    "sg:classifiers":[
        {
            "category":"Home & Garden",
            "subcategory":"Furniture",
            "type":"Retail Goods"
        }
    ],
    "sg:phone":"+1 505 864 6556",
    "sg:postcode":"87002",
    "sg:province":"NM",
    "sg:tags":[
        "cabinet"
    ],
    "wof:name":"Dan's Cabinets & Counter Tops",
    "wof:placetype":"venue"
},
  "geometry": {"coordinates":[-106.783942,34.706928],"type":"Point"}
}