{
  "type": "Feature",
  "properties": {
    "iso:country":"US",
    "sg:address":"4501 W Picacho Ave",
    "sg:city":"Las Cruces",
    "sg:classifiers":[
        {
            "category":"Education",
            "subcategory":"School",
            "type":"Public Place"
        }
    ],
    "sg:phone":"+1 505 527 9606",
    "sg:postcode":"88007",
    "sg:province":"NM",
    "wof:name":"Fairacres Elementary School",
    "wof:placetype":"venue"
},
  "geometry": {"coordinates":[-106.846032,32.303982],"type":"Point"}
}