{
  "type": "Feature",
  "properties": {
    "iso:country":"US",
    "sg:address":"798 Terrace Ave",
    "sg:city":"Chama",
    "sg:classifiers":[
        {
            "category":"Shopping",
            "subcategory":"Crafts & Fabrics",
            "type":"Retail Goods"
        }
    ],
    "sg:phone":"+1 505 756 1412",
    "sg:postcode":"87520",
    "sg:province":"NM",
    "sg:tags":[
        "material",
        "quilting",
        "supply"
    ],
    "sg:website":"www.littlefoot.net",
    "wof:name":"Little Foot LTD",
    "wof:placetype":"venue"
},
  "geometry": {"coordinates":[-106.581484,36.899888],"type":"Point"}
}