{
  "type": "Feature",
  "properties": {
    "addr:full":"4410 Prospect Ave NE Albuquerque NM 87110",
    "addr:housenumber":"4410",
    "addr:postcode":"87110",
    "addr:street":"Prospect Ave Ne",
    "iso:country":"US",
    "sg:address":"4410 Prospect Ave NE",
    "sg:city":"Albuquerque",
    "sg:classifiers":[
        {
            "category":"Retail",
            "subcategory":"Auto Repair",
            "type":"Services"
        }
    ],
    "sg:phone":"+1 505 872 4410",
    "sg:postcode":"87110",
    "sg:province":"NM",
    "sg:tags":[
        "repairing",
        "automobile",
        "general"
    ],
    "wof:name":"Dave's Garage",
    "wof:placetype":"venue"
},
  "geometry": {"coordinates":[-106.59562699999999,35.107383],"type":"Point"}
}