{
  "type": "Feature",
  "properties": {
    "iso:country":"US",
    "sg:address":"710 S 3rd St",
    "sg:city":"Gallup",
    "sg:classifiers":[
        {
            "category":"Banks & Credit Unions",
            "subcategory":"Bank",
            "type":"Services"
        }
    ],
    "sg:phone":"+1 505 863 9381",
    "sg:postcode":"87301",
    "sg:province":"NM",
    "wof:name":"First American CREDIT Union",
    "wof:placetype":"venue"
},
  "geometry": {"coordinates":[-108.742092,35.522331],"type":"Point"}
}