{
  "type": "Feature",
  "properties": {
    "iso:country":"US",
    "sg:address":"2108 Isleta Blvd SW",
    "sg:city":"Albuquerque",
    "sg:classifiers":[
        {
            "category":"Professional",
            "subcategory":"Advertising",
            "type":"Services"
        }
    ],
    "sg:phone":"+1 505 250 7987",
    "sg:postcode":"87105",
    "sg:province":"NM",
    "sg:tags":[
        "distribution"
    ],
    "wof:name":"Pena's Distributing",
    "wof:placetype":"venue"
},
  "geometry": {"coordinates":[-106.679272,35.043908],"type":"Point"}
}