{
  "type": "Feature",
  "properties": {
    "iso:country":"US",
    "sg:address":"1404 Luisa St",
    "sg:city":"Santa Fe",
    "sg:classifiers":[
        {
            "category":"Shopping",
            "subcategory":"Tobacco",
            "type":"Retail Goods"
        }
    ],
    "sg:phone":"+1 505 995 1173",
    "sg:postcode":"87505",
    "sg:province":"NM",
    "sg:tags":[
        "cigarette",
        "cigar",
        "dealer"
    ],
    "wof:name":"Purofino Cigars Intl Inc",
    "wof:placetype":"venue"
},
  "geometry": {"coordinates":[-105.951812,35.668463],"type":"Point"}
}