{
  "type": "Feature",
  "properties": {
    "iso:country":"US",
    "sg:address":"10520 Connemara Ave SW",
    "sg:city":"Albuquerque",
    "sg:classifiers":[
        {
            "category":"Restaurant",
            "type":"Food & Drink"
        }
    ],
    "sg:phone":"+1 505 831 5981",
    "sg:postcode":"87121",
    "sg:province":"NM",
    "sg:tags":[
        "parlor",
        "ice",
        "cream"
    ],
    "wof:name":"Alaska Ice Cream",
    "wof:placetype":"venue"
},
  "geometry": {"coordinates":[-106.750067,35.06092],"type":"Point"}
}