{
  "type": "Feature",
  "properties": {
    "addr:full":"4019 Old River Rd Las Cruces NM 88005",
    "addr:housenumber":"4019",
    "addr:postcode":"88005",
    "addr:street":"Old River Rd",
    "iso:country":"US",
    "sg:address":"4019 Old River Rd",
    "sg:city":"Las Cruces",
    "sg:classifiers":[
        {
            "category":"Professional",
            "type":"Services"
        }
    ],
    "sg:phone":"+1 505 647 3574",
    "sg:postcode":"88005",
    "sg:province":"NM",
    "sg:tags":[
        "establishment"
    ],
    "wof:name":"I C",
    "wof:placetype":"venue"
},
  "geometry": {"coordinates":[-106.766836,32.260237],"type":"Point"}
}