{
  "type": "Feature",
  "properties": {
    "iso:country":"US",
    "sg:address":"690 Hayride Rd",
    "sg:city":"Las Cruces",
    "sg:classifiers":[
        {
            "category":"Building & Trades",
            "subcategory":"Construction",
            "type":"Services"
        }
    ],
    "sg:phone":"+1 505 526 6199",
    "sg:postcode":"88007",
    "sg:province":"NM",
    "sg:tags":[
        "excavation",
        "contractor"
    ],
    "wof:name":"Tractor For Hire",
    "wof:placetype":"venue"
},
  "geometry": {"coordinates":[-106.90096,32.471929],"type":"Point"}
}