{
  "type": "Feature",
  "properties": {
    "iso:country":"US",
    "sg:address":"838 Don Diego Ave",
    "sg:city":"Santa Fe",
    "sg:classifiers":[
        {
            "category":"Autos & Motor Vehicles",
            "subcategory":"Auto Supplies",
            "type":"Retail Goods"
        }
    ],
    "sg:phone":"+1 505 490 1519",
    "sg:postcode":"87505",
    "sg:province":"NM",
    "sg:tags":[
        "automobile",
        "accessory"
    ],
    "wof:name":"Touchstone",
    "wof:placetype":"venue"
},
  "geometry": {"coordinates":[-105.94812899999999,35.678327],"type":"Point"}
}