{
  "type": "Feature",
  "properties": {
    "addr:full":"7100 Louisiana Blvd NE Albuquerque NM 87109",
    "addr:housenumber":"7100",
    "addr:postcode":"87109",
    "addr:street":"Louisiana Blvd Ne",
    "iso:country":"US",
    "sg:address":"7100 Louisiana Blvd NE",
    "sg:city":"Albuquerque",
    "sg:classifiers":[
        {
            "category":"Professional",
            "subcategory":"Computer Services",
            "type":"Services"
        }
    ],
    "sg:phone":"+1 505 797 7910",
    "sg:postcode":"87109",
    "sg:province":"NM",
    "sg:tags":[
        "website",
        "design"
    ],
    "wof:name":"Urban Development Group",
    "wof:placetype":"venue"
},
  "geometry": {"coordinates":[-106.568713,35.160184],"type":"Point"}
}