{
  "type": "Feature",
  "properties": {
    "iso:country":"US",
    "sg:address":"205 W San Francisco St",
    "sg:city":"Santa Fe",
    "sg:classifiers":[
        {
            "category":"Shopping",
            "subcategory":"Gifts & Souvenirs",
            "type":"Retail Goods"
        }
    ],
    "sg:phone":"+1 505 986 9265",
    "sg:postcode":"87501",
    "sg:province":"NM",
    "sg:tags":[
        "shop"
    ],
    "sg:website":"www.santafemoxie.com",
    "wof:name":"Moxie",
    "wof:placetype":"venue"
},
  "geometry": {"coordinates":[-105.943136,35.688262],"type":"Point"}
}