{
  "type": "Feature",
  "properties": {
    "iso:country":"US",
    "sg:address":"320 Garfield St",
    "sg:city":"Santa Fe",
    "sg:classifiers":[
        {
            "category":"Health Services",
            "subcategory":"Health Practitioner",
            "type":"Services"
        }
    ],
    "sg:phone":"+1 505 984 1143",
    "sg:postcode":"87501",
    "sg:province":"NM",
    "sg:tags":[
        "psychologist"
    ],
    "wof:name":"Molly Hunt",
    "wof:placetype":"venue"
},
  "geometry": {"coordinates":[-105.945326,35.683984],"type":"Point"}
}