{
  "type": "Feature",
  "properties": {
    "addr:full":"5821 Midway Park Blvd NE Albuquerque NM 87109",
    "addr:housenumber":"5821",
    "addr:postcode":"87109",
    "addr:street":"Midway Park Blvd Ne",
    "iso:country":"US",
    "sg:address":"5821 Midway Park Blvd NE",
    "sg:city":"Albuquerque",
    "sg:classifiers":[
        {
            "category":"Government",
            "subcategory":"Office",
            "type":"Public Place"
        }
    ],
    "sg:phone":"+1 505 761 4615",
    "sg:postcode":"87109",
    "sg:province":"NM",
    "sg:tags":[
        "resource",
        "federal",
        "testing",
        "water",
        "which",
        "measure",
        "laboratory"
    ],
    "wof:name":"US Dept Geological Survey",
    "wof:placetype":"venue"
},
  "geometry": {"coordinates":[-106.603604,35.147734],"type":"Point"}
}