{
  "type": "Feature",
  "properties": {
    "iso:country":"US",
    "sg:address":"1616 Brian Ave SW",
    "sg:city":"Albuquerque",
    "sg:classifiers":[
        {
            "category":"Professional",
            "subcategory":"Computer Services",
            "type":"Services"
        }
    ],
    "sg:phone":"+1 505 720 7337",
    "sg:postcode":"87121",
    "sg:province":"NM",
    "wof:name":"ASR Computers",
    "wof:placetype":"venue"
},
  "geometry": {"coordinates":[-106.72798899999999,35.046964],"type":"Point"}
}