{
  "type": "Feature",
  "properties": {
    "iso:country":"US",
    "sg:address":"10 Proctor Dr",
    "sg:city":"Peralta",
    "sg:classifiers":[
        {
            "category":"Building & Trades",
            "subcategory":"Construction",
            "type":"Services"
        }
    ],
    "sg:phone":"+1 505 869 3980",
    "sg:postcode":"87042",
    "sg:province":"NM",
    "sg:tags":[
        "concrete",
        "contractor"
    ],
    "wof:name":"S Cg Concrete Inc",
    "wof:placetype":"venue"
},
  "geometry": {"coordinates":[-106.68348,34.838602],"type":"Point"}
}