{
  "type": "Feature",
  "properties": {
    "iso:country":"US",
    "sg:address":"430 W Manhattan Ave",
    "sg:city":"Santa Fe",
    "sg:classifiers":[
        {
            "category":"Professional",
            "type":"Services"
        }
    ],
    "sg:phone":"+1 505 989 1155",
    "sg:postcode":"87501",
    "sg:province":"NM",
    "wof:name":"Brett Chomer Studio",
    "wof:placetype":"venue"
},
  "geometry": {"coordinates":[-105.946585,35.683529],"type":"Point"}
}