{
  "type": "Feature",
  "properties": {
    "addr:full":"715 N Turner St Hobbs NM 88240",
    "addr:housenumber":"715",
    "addr:postcode":"88240",
    "addr:street":"N Turner St",
    "iso:country":"US",
    "sg:address":"715 N Turner St",
    "sg:city":"Hobbs",
    "sg:classifiers":[
        {
            "category":"Shopping",
            "subcategory":"Florist",
            "type":"Retail Goods"
        }
    ],
    "sg:phone":"+1 505 393 2188",
    "sg:postcode":"88240",
    "sg:province":"NM",
    "wof:name":"Hobbs Floral",
    "wof:placetype":"venue"
},
  "geometry": {"coordinates":[-103.136292,32.707987],"type":"Point"}
}