{
  "type": "Feature",
  "properties": {
    "addr:full":"327 Georgia St SE Albuquerque NM 87108",
    "addr:housenumber":"327",
    "addr:postcode":"87108",
    "addr:street":"Georgia St Se",
    "iso:country":"US",
    "sg:address":"327 Georgia St SE",
    "sg:city":"Albuquerque",
    "sg:classifiers":[
        {
            "category":"Organizations",
            "subcategory":"Religious Organization",
            "type":"Services"
        }
    ],
    "sg:phone":"+1 505 260 4844",
    "sg:postcode":"87108",
    "sg:province":"NM",
    "wof:name":"Vietnamese Buddhist Congregatn",
    "wof:placetype":"venue"
},
  "geometry": {"coordinates":[-106.57194,35.07308],"type":"Point"}
}