{
  "type": "Feature",
  "properties": {
    "addr:full":"230 Ledoux St Taos NM 87571",
    "addr:housenumber":"230",
    "addr:postcode":"87571",
    "addr:street":"Ledoux St",
    "iso:country":"US",
    "sg:address":"230 Ledoux St",
    "sg:city":"Taos",
    "sg:classifiers":[
        {
            "category":"Shopping",
            "type":"Retail Goods"
        }
    ],
    "sg:phone":"+1 505 758 0484",
    "sg:postcode":"87571",
    "sg:province":"NM",
    "sg:tags":[
        "art",
        "gallery",
        "dealer"
    ],
    "wof:name":"Carol Savid Gallery",
    "wof:placetype":"venue"
},
  "geometry": {"coordinates":[-105.575287,36.406285],"type":"Point"}
}