{
  "type": "Feature",
  "properties": {
    "addr:full":"301 Johnson St Santa Fe NM 87501",
    "addr:housenumber":"301",
    "addr:postcode":"87501",
    "addr:street":"Johnson St",
    "iso:country":"US",
    "sg:address":"301 Johnson St",
    "sg:city":"Santa Fe",
    "sg:classifiers":[
        {
            "category":"Health Services",
            "subcategory":"Health Practitioner",
            "type":"Services"
        }
    ],
    "sg:phone":"+1 505 982 4957",
    "sg:postcode":"87501",
    "sg:province":"NM",
    "wof:name":"Psychology Consultants",
    "wof:placetype":"venue"
},
  "geometry": {"coordinates":[-105.943516,35.689316],"type":"Point"}
}