{
  "type": "Feature",
  "properties": {
    "addr:full":"424 53rd St SW Albuquerque NM 87105",
    "addr:housenumber":"424",
    "addr:postcode":"87105",
    "addr:street":"53Rd St Sw",
    "iso:country":"US",
    "sg:address":"424 53rd St SW",
    "sg:city":"Albuquerque",
    "sg:classifiers":[
        {
            "category":"Shopping",
            "type":"Retail Goods"
        }
    ],
    "sg:phone":"+1 505 836 4445",
    "sg:postcode":"87105",
    "sg:province":"NM",
    "sg:tags":[
        "art",
        "gallery",
        "dealer"
    ],
    "wof:name":"Art By Ike",
    "wof:placetype":"venue"
},
  "geometry": {"coordinates":[-106.695635,35.080038],"type":"Point"}
}