{
  "type": "Feature",
  "properties": {
    "addr:full":"5313 Sweetwater Dr NW Albuquerque NM 87120",
    "addr:housenumber":"5313",
    "addr:postcode":"87120",
    "addr:street":"Sweetwater Dr Nw",
    "iso:country":"US",
    "sg:address":"5313 Sweetwater Dr NW",
    "sg:city":"Albuquerque",
    "sg:classifiers":[
        {
            "category":"Building & Trades",
            "subcategory":"Plumbing",
            "type":"Services"
        }
    ],
    "sg:phone":"+1 505 899 8944",
    "sg:postcode":"87120",
    "sg:province":"NM",
    "sg:tags":[
        "plumbing",
        "contractor"
    ],
    "wof:name":"Kan Du Plumbing",
    "wof:placetype":"venue"
},
  "geometry": {"coordinates":[-106.707335,35.146248],"type":"Point"}
}