{
  "type": "Feature",
  "properties": {
    "addr:full":"1605 Chaco Ave Grants NM 87020",
    "addr:postcode":"1605;87020",
    "addr:street":"Chaco Ave",
    "iso:country":"US",
    "sg:address":"1605 Chaco Ave",
    "sg:city":"Grants",
    "sg:classifiers":[
        {
            "category":"Building & Trades",
            "subcategory":"Plumbing",
            "type":"Services"
        }
    ],
    "sg:phone":"+1 505 287 2388",
    "sg:postcode":"87020",
    "sg:province":"NM",
    "sg:tags":[
        "plumbing",
        "contractor"
    ],
    "wof:name":"Sprunk's Plumbing & Heating",
    "wof:placetype":"venue"
},
  "geometry": {"coordinates":[-107.824585,35.168037],"type":"Point"}
}