{
  "type": "Feature",
  "properties": {
    "addr:full":"1500 W 7th St Clovis NM 88101",
    "addr:housenumber":"1500",
    "addr:postcode":"88101",
    "addr:street":"W 7Th St",
    "iso:country":"US",
    "sg:address":"1500 W 7th St",
    "sg:city":"Clovis",
    "sg:classifiers":[
        {
            "category":"Personal",
            "subcategory":"Beauty Salon",
            "type":"Services"
        }
    ],
    "sg:phone":"+1 505 763 3991",
    "sg:postcode":"88101",
    "sg:province":"NM",
    "sg:tags":[
        "shop",
        "operation",
        "trailer"
    ],
    "wof:name":"La Petite Beauty & Style Salon",
    "wof:placetype":"venue"
},
  "geometry": {"coordinates":[-103.22326200000001,34.404692],"type":"Point"}
}