{
  "type": "Feature",
  "properties": {
    "addr:full":"9724 Guadalupe Trl NW Albuquerque NM 87114",
    "addr:housenumber":"9724",
    "addr:postcode":"87114",
    "addr:street":"Guadalupe Trl Nw",
    "iso:country":"US",
    "sg:address":"9724 Guadalupe Trl NW",
    "sg:city":"Albuquerque",
    "sg:classifiers":[
        {
            "category":"Building & Trades",
            "subcategory":"Construction",
            "type":"Services"
        }
    ],
    "sg:phone":"+1 505 323 2069",
    "sg:postcode":"87114",
    "sg:province":"NM",
    "sg:tags":[
        "general",
        "contractor"
    ],
    "wof:name":"P - S Construction Inc",
    "wof:placetype":"venue"
},
  "geometry": {"coordinates":[-106.626054,35.193664],"type":"Point"}
}