{
  "type": "Feature",
  "properties": {
    "iso:country":"US",
    "sg:address":"13032 Central Ave SE",
    "sg:city":"Albuquerque",
    "sg:classifiers":[
        {
            "category":"Autos & Motor Vehicles",
            "subcategory":"Recreational Vehicle Sales",
            "type":"Retail Goods"
        }
    ],
    "sg:phone":"+1 505 271 8700",
    "sg:postcode":"87123",
    "sg:province":"NM",
    "wof:name":"E Z TRUCK & Rv Sales",
    "wof:placetype":"venue"
},
  "geometry": {"coordinates":[-106.498558,35.068257],"type":"Point"}
}