{
  "type": "Feature",
  "properties": {
    "addr:full":"1105 N Main St Las Cruces NM 88001",
    "addr:housenumber":"1105",
    "addr:postcode":"88001",
    "addr:street":"N Main St",
    "iso:country":"US",
    "sg:address":"1105 N Main St",
    "sg:city":"Las Cruces",
    "sg:classifiers":[
        {
            "category":"Food & Beverages",
            "subcategory":"Specialty",
            "type":"Retail Goods"
        }
    ],
    "sg:phone":"+1 505 524 8382",
    "sg:postcode":"88001",
    "sg:province":"NM",
    "sg:tags":[
        "herb"
    ],
    "wof:name":"Bee Healthy",
    "wof:placetype":"venue"
},
  "geometry": {"coordinates":[-106.781425,32.319249],"type":"Point"}
}