{
  "type": "Feature",
  "properties": {
    "addr:full":"301 N Solano Dr Las Cruces NM 88001",
    "addr:housenumber":"301",
    "addr:postcode":"88001",
    "addr:street":"N Solano Dr",
    "iso:country":"US",
    "sg:address":"301 N Solano Dr",
    "sg:city":"Las Cruces",
    "sg:classifiers":[
        {
            "category":"Organizations",
            "subcategory":"Religious Organization",
            "type":"Services"
        }
    ],
    "sg:phone":"+1 505 373 0297",
    "sg:postcode":"88001",
    "sg:province":"NM",
    "sg:tags":[
        "church"
    ],
    "wof:name":"Mountain View Baptist Church",
    "wof:placetype":"venue"
},
  "geometry": {"coordinates":[-106.76672000000001,32.315599],"type":"Point"}
}