{
  "type": "Feature",
  "properties": {
    "iso:country":"US",
    "sg:address":"2930 Hillrise Dr",
    "sg:city":"Las Cruces",
    "sg:classifiers":[
        {
            "category":"Health Services",
            "subcategory":"Podiatrist",
            "type":"Services"
        }
    ],
    "sg:phone":"+1 505 522 3330",
    "sg:postcode":"88011",
    "sg:province":"NM",
    "wof:name":"Mesilla Valley Foot Care",
    "wof:placetype":"venue"
},
  "geometry": {"coordinates":[-106.737767,32.304182],"type":"Point"}
}