{
  "type": "Feature",
  "properties": {
    "addr:full":"2930 Hillrise Dr Las Cruces NM 88011",
    "addr:housenumber":"2930",
    "addr:postcode":"88011",
    "addr:street":"Hillrise Dr",
    "iso:country":"US",
    "sg:address":"2930 Hillrise Dr",
    "sg:city":"Las Cruces",
    "sg:classifiers":[
        {
            "category":"Health Services",
            "subcategory":"Podiatrist",
            "type":"Services"
        }
    ],
    "sg:phone":"+1 505 522 3330",
    "sg:postcode":"88011",
    "sg:province":"NM",
    "wof:name":"Mesilla Valley Foot Care",
    "wof:placetype":"venue"
},
  "geometry": {"coordinates":[-106.73776700000001,32.304182],"type":"Point"}
}