{
  "type": "Feature",
  "properties": {
    "iso:country":"US",
    "sg:address":"827 Cam del Monte Sol",
    "sg:city":"Santa Fe",
    "sg:classifiers":[
        {
            "category":"Retail",
            "subcategory":"Auto Repair",
            "type":"Services"
        }
    ],
    "sg:phone":"+1 505 989 8025",
    "sg:postcode":"87501",
    "sg:province":"NM",
    "sg:tags":[
        "general"
    ],
    "wof:name":"Capital Automotive & Alignment",
    "wof:placetype":"venue"
},
  "geometry": {"coordinates":[-105.922261,35.669988],"type":"Point"}
}