{
  "type": "Feature",
  "properties": {
    "iso:country":"US",
    "sg:address":"1233 Siler Rd",
    "sg:city":"Santa Fe",
    "sg:classifiers":[
        {
            "category":"Manufacturing",
            "subcategory":"Printing",
            "type":"Manufacturing & Wholesale Goods"
        }
    ],
    "sg:phone":"+1 505 474 5858",
    "sg:postcode":"87507",
    "sg:province":"NM",
    "sg:tags":[
        "printer"
    ],
    "sg:website":"www.rollerprinting.com",
    "wof:name":"Roller Printing",
    "wof:placetype":"venue"
},
  "geometry": {"coordinates":[-105.993191,35.658899],"type":"Point"}
}