{
  "type": "Feature",
  "properties": {
    "iso:country":"US",
    "sg:address":"104 E Linda Vista Blvd",
    "sg:city":"Roswell",
    "sg:classifiers":[
        {
            "category":"Professional",
            "subcategory":"Advertising",
            "type":"Services"
        }
    ],
    "sg:phone":"+1 505 317 1127",
    "sg:postcode":"88201",
    "sg:province":"NM",
    "sg:tags":[
        "counselor"
    ],
    "wof:name":"Image Group Marketing",
    "wof:placetype":"venue"
},
  "geometry": {"coordinates":[-104.522986,33.436252],"type":"Point"}
}