{
  "type": "Feature",
  "properties": {
    "iso:country":"US",
    "sg:address":"84 S Bear Creek Rd",
    "sg:city":"Gila",
    "sg:classifiers":[
        {
            "category":"Wholesale",
            "subcategory":"Construction Materials",
            "type":"Manufacturing & Wholesale Goods"
        }
    ],
    "sg:phone":"+1 505 535 2042",
    "sg:postcode":"88061",
    "sg:province":"NM",
    "sg:tags":[
        "sand",
        "gravel"
    ],
    "wof:name":"Bear Creek Sand & Gravel",
    "wof:placetype":"venue"
},
  "geometry": {"coordinates":[-108.569834,32.951353],"type":"Point"}
}