{
  "type": "Feature",
  "properties": {
    "iso:country":"US",
    "sg:address":"4505 Andrew Dr NE",
    "sg:city":"Albuquerque",
    "sg:classifiers":[
        {
            "category":"Professional",
            "subcategory":"Employment Agencies",
            "type":"Services"
        }
    ],
    "sg:phone":"+1 505 884 8218",
    "sg:postcode":"87109",
    "sg:province":"NM",
    "wof:name":"Virtual Hr Associates",
    "wof:placetype":"venue"
},
  "geometry": {"coordinates":[-106.572621,35.137328],"type":"Point"}
}