{
  "type": "Feature",
  "properties": {
    "addr:full":"1903 Central Ave Los Alamos NM 87544",
    "addr:housenumber":"1903",
    "addr:postcode":"87544",
    "addr:street":"Central Ave",
    "iso:country":"US",
    "sg:address":"1903 Central Ave",
    "sg:city":"Los Alamos",
    "sg:classifiers":[
        {
            "category":"Banks & Credit Unions",
            "subcategory":"Bank",
            "type":"Services"
        }
    ],
    "sg:phone":"+1 505 662 5254",
    "sg:postcode":"87544",
    "sg:province":"NM",
    "sg:tags":[
        "national",
        "commercial"
    ],
    "wof:name":"Bank of America",
    "wof:placetype":"venue"
},
  "geometry": {"coordinates":[-106.301654,35.881415],"type":"Point"}
}