{
  "type": "Feature",
  "properties": {
    "iso:country":"US",
    "sg:address":"618 W Picacho Ave",
    "sg:city":"Las Cruces",
    "sg:classifiers":[
        {
            "category":"Professional",
            "subcategory":"Management & Consulting",
            "type":"Services"
        }
    ],
    "sg:phone":"+1 505 527 0059",
    "sg:postcode":"88005",
    "sg:province":"NM",
    "sg:tags":[
        "consultant"
    ],
    "wof:name":"Pearl Consultants",
    "wof:placetype":"venue"
},
  "geometry": {"coordinates":[-106.788267,32.315156],"type":"Point"}
}