{
  "type": "Feature",
  "properties": {
    "addr:full":"783 Pso de la Cuma Santa Fe NM 87501",
    "addr:housenumber":"783",
    "addr:postcode":"87501",
    "addr:street":"Pso De La Cuma",
    "iso:country":"US",
    "sg:address":"783 Pso de la Cuma",
    "sg:city":"Santa Fe",
    "sg:classifiers":[
        {
            "category":"Health Services",
            "subcategory":"Doctor",
            "type":"Services"
        }
    ],
    "sg:phone":"+1 505 989 4302",
    "sg:postcode":"87501",
    "sg:province":"NM",
    "wof:name":"William L Cloud",
    "wof:placetype":"venue"
},
  "geometry": {"coordinates":[-105.939165,35.695572],"type":"Point"}
}