{
  "type": "Feature",
  "properties": {
    "iso:country":"US",
    "sg:address":"507 Wyoming Blvd NE",
    "sg:city":"Albuquerque",
    "sg:classifiers":[
        {
            "category":"Retail",
            "subcategory":"Repair Shop",
            "type":"Services"
        }
    ],
    "sg:phone":"+1 505 266 0054",
    "sg:postcode":"87123",
    "sg:province":"NM",
    "sg:tags":[
        "sewing",
        "upholsterer"
    ],
    "wof:name":"Los Altos Upholstery",
    "wof:placetype":"venue"
},
  "geometry": {"coordinates":[-106.550465,35.083554],"type":"Point"}
}