{
  "type": "Feature",
  "properties": {
    "iso:country":"US",
    "sg:address":"104 W San Francisco St",
    "sg:city":"Santa Fe",
    "sg:classifiers":[
        {
            "category":"Home & Garden",
            "subcategory":"Home Furnishings",
            "type":"Retail Goods"
        }
    ],
    "sg:phone":"+1 505 988 3574",
    "sg:postcode":"87501",
    "sg:province":"NM",
    "sg:tags":[
        "cookware",
        "mills",
        "store",
        "for"
    ],
    "wof:name":"Nambe Mills Showroom",
    "wof:placetype":"venue"
},
  "geometry": {"coordinates":[-105.940926,35.687538],"type":"Point"}
}