{
  "type": "Feature",
  "properties": {
    "iso:country":"US",
    "sg:address":"2413 Valencia Dr NE",
    "sg:city":"Albuquerque",
    "sg:classifiers":[
        {
            "category":"Building & Trades",
            "subcategory":"Construction",
            "type":"Services"
        }
    ],
    "sg:phone":"+1 505 883 7132",
    "sg:postcode":"87110",
    "sg:province":"NM",
    "sg:tags":[
        "house",
        "nonresidential",
        "general",
        "contractor"
    ],
    "wof:name":"Strong Arm Stucco & Constr",
    "wof:placetype":"venue"
},
  "geometry": {"coordinates":[-106.58098699999999,35.107082],"type":"Point"}
}