{
  "type": "Feature",
  "properties": {
    "addr:full":"10744 Four Mile Rd SW Albuquerque NM 87121",
    "addr:housenumber":"10744",
    "addr:postcode":"87121",
    "addr:street":"Four Mile Rd Sw",
    "iso:country":"US",
    "sg:address":"10744 Four Mile Rd SW",
    "sg:city":"Albuquerque",
    "sg:classifiers":[
        {
            "category":"Personal",
            "subcategory":"Nail Salon",
            "type":"Services"
        }
    ],
    "sg:phone":"+1 505 610 1193",
    "sg:postcode":"87121",
    "sg:province":"NM",
    "wof:name":"Nails By Jeannie",
    "wof:placetype":"venue"
},
  "geometry": {"coordinates":[-106.75179300000001,35.040279],"type":"Point"}
}