{
  "type": "Feature",
  "properties": {
    "iso:country":"US",
    "sg:address":"4803 Rio Grande Blvd NW",
    "sg:city":"Albuquerque",
    "sg:classifiers":[
        {
            "category":"Shopping",
            "type":"Retail Goods"
        }
    ],
    "sg:phone":"+1 505 245 8700",
    "sg:postcode":"87107",
    "sg:province":"NM",
    "sg:tags":[
        "art",
        "gallery",
        "dealer"
    ],
    "sg:website":"www.maximo.com",
    "wof:name":"Maximo Art & Design Research",
    "wof:placetype":"venue"
},
  "geometry": {"coordinates":[-106.664852,35.147548],"type":"Point"}
}