{
  "type": "Feature",
  "properties": {
    "iso:country":"US",
    "sg:address":"3816 Cll del Monte NE",
    "sg:city":"Albuquerque",
    "sg:classifiers":[
        {
            "category":"Professional",
            "subcategory":"Management & Consulting",
            "type":"Services"
        }
    ],
    "sg:phone":"+1 505 265 1136",
    "sg:postcode":"87110",
    "sg:province":"NM",
    "wof:name":"Maize Homes",
    "wof:placetype":"venue"
},
  "geometry": {"coordinates":[-106.601112,35.091628],"type":"Point"}
}