{
  "type": "Feature",
  "properties": {
    "addr:full":"40 First Plaza Center NW Albuquerque NM 87102",
    "addr:housenumber":"40",
    "addr:postcode":"87102",
    "addr:street":"First;Nw",
    "iso:country":"US",
    "sg:address":"40 First Plaza Center NW",
    "sg:city":"Albuquerque",
    "sg:classifiers":[
        {
            "category":"Sports & Exercise",
            "subcategory":"Gym",
            "type":"Entertainment"
        }
    ],
    "sg:phone":"+1 505 242 1500",
    "sg:postcode":"87102",
    "sg:province":"NM",
    "sg:tags":[
        "club",
        "health",
        "studio",
        "gymnasium"
    ],
    "sg:website":"www.nmsw.com",
    "wof:name":"Downtown Sports & Wellness",
    "wof:placetype":"venue"
},
  "geometry": {"coordinates":[-106.649247,35.085804],"type":"Point"}
}