{
  "type": "Feature",
  "properties": {
    "addr:full":"313 Cree Meadows Dr Ruidoso NM 88345",
    "addr:housenumber":"313",
    "addr:postcode":"88345",
    "addr:street":"Cree Meadows Dr",
    "iso:country":"US",
    "sg:address":"313 Cree Meadows Dr",
    "sg:city":"Ruidoso",
    "sg:classifiers":[
        {
            "category":"Professional",
            "subcategory":"Business Services",
            "type":"Services"
        }
    ],
    "sg:phone":"+1 505 258 4014",
    "sg:postcode":"88345",
    "sg:province":"NM",
    "wof:name":"Building Inspector",
    "wof:placetype":"venue"
},
  "geometry": {"coordinates":[-105.663347,33.349215],"type":"Point"}
}