{
  "type": "Feature",
  "properties": {
    "addr:full":"215 Altez St SE Albuquerque NM 87123",
    "addr:housenumber":"215",
    "addr:postcode":"87123",
    "addr:street":"Altez St Se",
    "iso:country":"US",
    "sg:address":"215 Altez St SE",
    "sg:city":"Albuquerque",
    "sg:classifiers":[
        {
            "category":"Retail",
            "subcategory":"Laundry & Dry Cleaning",
            "type":"Services"
        }
    ],
    "sg:phone":"+1 505 298 1882",
    "sg:postcode":"87123",
    "sg:province":"NM",
    "sg:tags":[
        "launderer",
        "industrial",
        "clothing",
        "linen",
        "sup"
    ],
    "wof:name":"Unifirst",
    "wof:placetype":"venue"
},
  "geometry": {"coordinates":[-106.539537,35.070802],"type":"Point"}
}