{
  "type": "Feature",
  "properties": {
    "iso:country":"US",
    "sg:address":"150 Salgado Rd",
    "sg:city":"Anthony",
    "sg:classifiers":[
        {
            "category":"Building & Trades",
            "subcategory":"Equipment Rental",
            "type":"Services"
        }
    ],
    "sg:phone":"+1 575 874 0504",
    "sg:postcode":"88021",
    "sg:province":"NM",
    "sg:tags":[
        "yard",
        "leasing",
        "store"
    ],
    "wof:name":"Ivy S Party Rentals Etc",
    "wof:placetype":"venue"
},
  "geometry": {"coordinates":[-106.651149,31.929784],"type":"Point"}
}