{
  "type": "Feature",
  "properties": {
    "iso:country":"US",
    "sg:address":"1216 W Summit St",
    "sg:city":"Roswell",
    "sg:classifiers":[
        {
            "category":"Manufacturing",
            "subcategory":"Lumber",
            "type":"Manufacturing & Wholesale Goods"
        }
    ],
    "sg:phone":"+1 505 623 0287",
    "sg:postcode":"88203",
    "sg:province":"NM",
    "sg:tags":[
        "fire",
        "equipment",
        "suppression"
    ],
    "wof:name":"Don J Ford",
    "wof:placetype":"venue"
},
  "geometry": {"coordinates":[-104.53917300000001,33.383594],"type":"Point"}
}