{
  "type": "Feature",
  "properties": {
    "iso:country":"US",
    "sg:address":"322 Muriel St NE",
    "sg:city":"Albuquerque",
    "sg:classifiers":[
        {
            "category":"Wholesale",
            "subcategory":"Jewelry",
            "type":"Manufacturing & Wholesale Goods"
        }
    ],
    "sg:phone":"+1 505 237 1325",
    "sg:postcode":"87123",
    "sg:province":"NM",
    "sg:tags":[
        "stone"
    ],
    "wof:name":"Op Silver Mfg",
    "wof:placetype":"venue"
},
  "geometry": {"coordinates":[-106.516266,35.074983],"type":"Point"}
}