{
  "type": "Feature",
  "properties": {
    "iso:country":"US",
    "sg:address":"13500 Central Ave SW",
    "sg:city":"Albuquerque",
    "sg:classifiers":[
        {
            "category":"Travel",
            "subcategory":"Campground",
            "type":"Entertainment"
        }
    ],
    "sg:phone":"+1 505 831 3545",
    "sg:postcode":"87121",
    "sg:province":"NM",
    "sg:tags":[
        "recreational",
        "parks",
        "vehicle"
    ],
    "sg:website":"www.americanrvpark.com",
    "wof:name":"American RV Park",
    "wof:placetype":"venue"
},
  "geometry": {"coordinates":[-106.77610199999999,35.065039],"type":"Point"}
}