{
  "type": "Feature",
  "properties": {
    "iso:country":"US",
    "sg:address":"2301 Central Ave NW",
    "sg:city":"Albuquerque",
    "sg:classifiers":[
        {
            "category":"Restaurant",
            "type":"Food & Drink"
        }
    ],
    "sg:phone":"+1 505 277 9585",
    "sg:postcode":"87104",
    "sg:province":"NM",
    "sg:tags":[
        "shop",
        "coffee"
    ],
    "wof:name":"Starbucks",
    "wof:placetype":"venue"
},
  "geometry": {"coordinates":[-106.67511399999999,35.095501],"type":"Point"}
}