{
  "type": "Feature",
  "properties": {
    "iso:country":"US",
    "sg:address":"1851 Calle Los Vecinos NW",
    "sg:city":"Albuquerque",
    "sg:classifiers":[
        {
            "category":"Professional",
            "subcategory":"Art Services",
            "type":"Services"
        }
    ],
    "sg:phone":"+1 505 345 4780",
    "sg:postcode":"87107",
    "sg:province":"NM",
    "sg:tags":[
        "sculptor"
    ],
    "wof:name":"Reynaldo Rivera Sculptor Inc",
    "wof:placetype":"venue"
},
  "geometry": {"coordinates":[-106.667888,35.13068],"type":"Point"}
}