{
  "type": "Feature",
  "properties": {
    "iso:country":"US",
    "sg:address":"721 W Apache St",
    "sg:city":"Farmington",
    "sg:classifiers":[
        {
            "category":"Retail",
            "subcategory":"Veterinary Services",
            "type":"Services"
        }
    ],
    "sg:phone":"+1 505 325 0323",
    "sg:postcode":"87401",
    "sg:province":"NM",
    "sg:tags":[
        "merchandise"
    ],
    "wof:name":"Oldfield Barney Dvm",
    "wof:placetype":"venue"
},
  "geometry": {"coordinates":[-108.215532,36.733909],"type":"Point"}
}