{
  "type": "Feature",
  "properties": {
    "iso:country":"US",
    "sg:address":"300 Frontage Rd NE",
    "sg:city":"Rio Rancho",
    "sg:classifiers":[
        {
            "category":"Manufacturing",
            "subcategory":"Retail Goods",
            "type":"Manufacturing & Wholesale Goods"
        }
    ],
    "sg:phone":"+1 505 896 0101",
    "sg:postcode":"87124",
    "sg:province":"NM",
    "sg:tags":[
        "assembly",
        "fabricating"
    ],
    "wof:name":"Team Specialty Products Corp",
    "wof:placetype":"venue"
},
  "geometry": {"coordinates":[-106.635363,35.260604],"type":"Point"}
}