{
  "type": "Feature",
  "properties": {
    "iso:country":"US",
    "sg:address":"819 Apache Ave NW",
    "sg:city":"Albuquerque",
    "sg:classifiers":[
        {
            "category":"Building & Trades",
            "subcategory":"Electrical",
            "type":"Services"
        }
    ],
    "sg:phone":"+1 505 842 9946",
    "sg:postcode":"87102",
    "sg:province":"NM",
    "sg:tags":[
        "electrical",
        "contractor"
    ],
    "wof:name":"Gutierrez Ray",
    "wof:placetype":"venue"
},
  "geometry": {"coordinates":[-106.650414,35.109081],"type":"Point"}
}