{
  "type": "Feature",
  "properties": {
    "addr:full":"1207 Mitchell St Clovis NM 88101",
    "addr:housenumber":"1207",
    "addr:postcode":"88101",
    "addr:street":"Mitchell St",
    "iso:country":"US",
    "sg:address":"1207 Mitchell St",
    "sg:city":"Clovis",
    "sg:classifiers":[
        {
            "category":"Shopping",
            "subcategory":"Gifts & Souvenirs",
            "type":"Retail Goods"
        }
    ],
    "sg:phone":"+1 505 763 1280",
    "sg:postcode":"88101",
    "sg:province":"NM",
    "wof:name":"Rainee Day Gifts & Gallery",
    "wof:placetype":"venue"
},
  "geometry": {"coordinates":[-103.20668000000001,34.410922],"type":"Point"}
}