{
  "type": "Feature",
  "properties": {
    "addr:full":"10000 Coors Byp NW Albuquerque NM 87114",
    "addr:housenumber":"10000",
    "addr:postcode":"87114",
    "addr:street":"Coors Byp Nw",
    "iso:country":"US",
    "sg:address":"10000 Coors Byp NW",
    "sg:city":"Albuquerque",
    "sg:classifiers":[
        {
            "category":"Home & Garden",
            "subcategory":"Furniture",
            "type":"Retail Goods"
        }
    ],
    "sg:phone":"+1 505 922 1320",
    "sg:postcode":"87114",
    "sg:province":"NM",
    "sg:tags":[
        "bed"
    ],
    "wof:name":"Comfort Zone Southwest",
    "wof:placetype":"venue"
},
  "geometry": {"coordinates":[-106.65981499999999,35.196994],"type":"Point"}
}