{
  "type": "Feature",
  "properties": {
    "addr:full":"19 Cirquela Rd Cedar Crest NM 87008",
    "addr:housenumber":"19",
    "addr:postcode":"87008",
    "addr:street":"Cirquela Rd",
    "iso:country":"US",
    "sg:address":"19 Cirquela Rd",
    "sg:city":"Cedar Crest",
    "sg:classifiers":[
        {
            "category":"Health Services",
            "subcategory":"Hospital",
            "type":"Services"
        }
    ],
    "sg:phone":"+1 505 281 3609",
    "sg:postcode":"87008",
    "sg:province":"NM",
    "sg:tags":[
        "mental"
    ],
    "sg:website":"www.villasantamaria.org",
    "wof:name":"Villa Santa Maria",
    "wof:placetype":"venue"
},
  "geometry": {"coordinates":[-106.37767100000001,35.102008],"type":"Point"}
}