{
  "type": "Feature",
  "properties": {
    "iso:country":"US",
    "sg:address":"4605 Periwinkle Ct NW",
    "sg:city":"Albuquerque",
    "sg:classifiers":[
        {
            "category":"Communications",
            "type":"Services"
        }
    ],
    "sg:phone":"+1 505 250 8686",
    "sg:postcode":"87120",
    "sg:province":"NM",
    "wof:name":"J V Communications",
    "wof:placetype":"venue"
},
  "geometry": {"coordinates":[-106.692739,35.154238],"type":"Point"}
}