{
  "type": "Feature",
  "properties": {
    "addr:full":"321 Columbia St Las Vegas NM 87701",
    "addr:housenumber":"321",
    "addr:postcode":"87701",
    "addr:street":"Columbia St",
    "iso:country":"US",
    "sg:address":"321 Columbia St",
    "sg:city":"Las Vegas",
    "sg:classifiers":[
        {
            "category":"Autos & Motor Vehicles",
            "subcategory":"Auto Supplies",
            "type":"Retail Goods"
        }
    ],
    "sg:phone":"+1 505 425 5659",
    "sg:postcode":"87701",
    "sg:province":"NM",
    "sg:tags":[
        "automobile",
        "parts"
    ],
    "wof:name":"Amigo Auto",
    "wof:placetype":"venue"
},
  "geometry": {"coordinates":[-105.213843,35.5993],"type":"Point"}
}