{
  "type": "Feature",
  "properties": {
    "iso:country":"US",
    "sg:address":"3801 Isleta Blvd SW",
    "sg:city":"Albuquerque",
    "sg:classifiers":[
        {
            "category":"Banks & Credit Unions",
            "subcategory":"Bank",
            "type":"Services"
        }
    ],
    "sg:phone":"+1 505 873 7333",
    "sg:postcode":"87105",
    "sg:province":"NM",
    "wof:name":"Ranchers Banks",
    "wof:placetype":"venue"
},
  "geometry": {"coordinates":[-106.68303299999999,35.020026],"type":"Point"}
}