{
  "type": "Feature",
  "properties": {
    "iso:country":"US",
    "sg:address":"601 S Espanola St",
    "sg:city":"Las Cruces",
    "sg:classifiers":[
        {
            "category":"Recreation",
            "type":"Entertainment"
        }
    ],
    "sg:phone":"+1 505 527 9113",
    "sg:postcode":"88001",
    "sg:province":"NM",
    "sg:tags":[
        "instruction",
        "gymnastic"
    ],
    "wof:name":"Cruces Gymnastics Academy",
    "wof:placetype":"venue"
},
  "geometry": {"coordinates":[-106.76351,32.3072],"type":"Point"}
}