{
  "type": "Feature",
  "properties": {
    "addr:full":"600 S White Sands Blvd Alamogordo NM 88310",
    "addr:housenumber":"600",
    "addr:postcode":"88310",
    "addr:street":"S White Sands Blvd",
    "iso:country":"US",
    "sg:address":"600 S White Sands Blvd",
    "sg:city":"Alamogordo",
    "sg:classifiers":[
        {
            "category":"Restaurant",
            "type":"Food & Drink"
        }
    ],
    "sg:phone":"+1 505 434 5811",
    "sg:postcode":"88310",
    "sg:province":"NM",
    "sg:tags":[
        "pizzeria"
    ],
    "wof:name":"Mazzios Pizza",
    "wof:placetype":"venue"
},
  "geometry": {"coordinates":[-105.960346,32.885441],"type":"Point"}
}