{
  "type": "Feature",
  "properties": {
    "iso:country":"US",
    "sg:address":"1630 Hickory Loop",
    "sg:city":"Las Cruces",
    "sg:classifiers":[
        {
            "category":"Wholesale",
            "subcategory":"Medical Equipment & Supplies",
            "type":"Manufacturing & Wholesale Goods"
        }
    ],
    "sg:phone":"+1 505 526 9933",
    "sg:postcode":"88005",
    "sg:province":"NM",
    "sg:tags":[
        "physician",
        "surgeon"
    ],
    "wof:name":"J Carlton Enterprises LLC",
    "wof:placetype":"venue"
},
  "geometry": {"coordinates":[-106.793229,32.29336],"type":"Point"}
}