{
  "type": "Feature",
  "properties": {
    "addr:full":"10001 Coors Byp NW Albuquerque NM 87114",
    "addr:housenumber":"10001",
    "addr:postcode":"87114",
    "addr:street":"Coors Byp Nw",
    "iso:country":"US",
    "sg:address":"10001 Coors Byp NW",
    "sg:city":"Albuquerque",
    "sg:classifiers":[
        {
            "category":"Food & Beverages",
            "subcategory":"Specialty",
            "type":"Retail Goods"
        }
    ],
    "sg:phone":"+1 505 792 5517",
    "sg:postcode":"87114",
    "sg:province":"NM",
    "wof:name":"Shaklee",
    "wof:placetype":"venue"
},
  "geometry": {"coordinates":[-106.65991699999999,35.196884],"type":"Point"}
}