{
  "type": "Feature",
  "properties": {
    "iso:country":"US",
    "sg:address":"321 W Pine St",
    "sg:city":"Deming",
    "sg:classifiers":[
        {
            "category":"Autos & Motor Vehicles",
            "subcategory":"Fuel & Gas Station",
            "type":"Retail Goods"
        }
    ],
    "sg:phone":"+1 505 546 7318",
    "sg:postcode":"88030",
    "sg:province":"NM",
    "sg:tags":[
        "oil"
    ],
    "wof:name":"Sav-O-Mat Inc",
    "wof:placetype":"venue"
},
  "geometry": {"coordinates":[-107.761476,32.268404],"type":"Point"}
}