{
  "type": "Feature",
  "properties": {
    "addr:full":"801 US Hwy 666 Gallup NM 87301",
    "addr:housenumber":"801",
    "addr:postcode":"87301",
    "addr:street":"Us Hwy 666",
    "iso:country":"US",
    "sg:address":"801 US Hwy 666",
    "sg:city":"Gallup",
    "sg:classifiers":[
        {
            "category":"Restaurant",
            "type":"Food & Drink"
        }
    ],
    "sg:phone":"+1 505 722 6140",
    "sg:postcode":"87301",
    "sg:province":"NM",
    "wof:name":"Burger King",
    "wof:placetype":"venue"
},
  "geometry": {"coordinates":[-108.758764,35.536961],"type":"Point"}
}