{
  "type": "Feature",
  "properties": {
    "iso:country":"US",
    "sg:address":"1515 W Cll Sur",
    "sg:city":"Hobbs",
    "sg:classifiers":[
        {
            "category":"Banks & Credit Unions",
            "subcategory":"Bank",
            "type":"Services"
        }
    ],
    "sg:phone":"+1 505 392 3319",
    "sg:postcode":"88240",
    "sg:province":"NM",
    "sg:tags":[
        "state"
    ],
    "wof:name":"Western Commerce Bank",
    "wof:placetype":"venue"
},
  "geometry": {"coordinates":[-103.155467,32.743343],"type":"Point"}
}