{
  "type": "Feature",
  "properties": {
    "iso:country":"US",
    "sg:address":"400 N Pennsylvania Ave",
    "sg:city":"Roswell",
    "sg:classifiers":[
        {
            "category":"Professional",
            "subcategory":"Accounting & Tax Preparation",
            "type":"Services"
        }
    ],
    "sg:phone":"+1 505 622 4667",
    "sg:postcode":"88201",
    "sg:province":"NM",
    "sg:tags":[
        "accountant"
    ],
    "wof:name":"Ronald L Miller CPA",
    "wof:placetype":"venue"
},
  "geometry": {"coordinates":[-104.526045,33.397661],"type":"Point"}
}