{
  "type": "Feature",
  "properties": {
    "addr:full":"4591 San Mateo Blvd NE Albuquerque NM 87109",
    "addr:housenumber":"4591",
    "addr:postcode":"87109",
    "addr:street":"San Mateo Blvd Ne",
    "iso:country":"US",
    "sg:address":"4591 San Mateo Blvd NE",
    "sg:city":"Albuquerque",
    "sg:classifiers":[
        {
            "category":"Cinema",
            "subcategory":"Movie Theater",
            "type":"Entertainment"
        }
    ],
    "sg:phone":"+1 505 888 4773",
    "sg:postcode":"87109",
    "sg:province":"NM",
    "sg:tags":[
        "motion",
        "picture"
    ],
    "wof:name":"Cinemark Movies 8",
    "wof:placetype":"venue"
},
  "geometry": {"coordinates":[-106.58655400000001,35.13107],"type":"Point"}
}