{
  "type": "Feature",
  "properties": {
    "iso:country":"US",
    "sg:address":"5427 Timberline Ave NW",
    "sg:city":"Albuquerque",
    "sg:classifiers":[
        {
            "category":"Social Services",
            "subcategory":"Child Care",
            "type":"Services"
        }
    ],
    "sg:phone":"+1 505 898 0518",
    "sg:postcode":"87120",
    "sg:province":"NM",
    "sg:tags":[
        "day"
    ],
    "wof:name":"Aunties Home Child Care",
    "wof:placetype":"venue"
},
  "geometry": {"coordinates":[-106.700222,35.158659],"type":"Point"}
}