{
  "type": "Feature",
  "properties": {
    "iso:country":"US",
    "sg:address":"2400 Menaul Blvd NE",
    "sg:city":"Albuquerque",
    "sg:classifiers":[
        {
            "category":"Wholesale",
            "subcategory":"Stationery",
            "type":"Manufacturing & Wholesale Goods"
        }
    ],
    "sg:phone":"+1 505 888 4894",
    "sg:postcode":"87107",
    "sg:province":"NM",
    "sg:tags":[
        "business",
        "form",
        "system"
    ],
    "sg:website":"www.aurorapublishing.com",
    "wof:name":"Aurora Publishing",
    "wof:placetype":"venue"
},
  "geometry": {"coordinates":[-106.618827,35.109116],"type":"Point"}
}