{
  "type": "Feature",
  "properties": {
    "iso:country":"US",
    "sg:address":"3724 Eubank Blvd NE",
    "sg:city":"Albuquerque",
    "sg:classifiers":[
        {
            "category":"Education",
            "subcategory":"Junior College",
            "type":"Public Place"
        }
    ],
    "sg:phone":"+1 505 292 4180",
    "sg:postcode":"87111",
    "sg:province":"NM",
    "sg:tags":[
        "technical",
        "institute"
    ],
    "sg:website":"www.trinityls.com",
    "wof:name":"Bartending Academy",
    "wof:placetype":"venue"
},
  "geometry": {"coordinates":[-106.533216,35.123575],"type":"Point"}
}