{
  "type": "Feature",
  "properties": {
    "addr:full":"400 Delaware Ave Alamogordo NM 88310",
    "addr:housenumber":"400",
    "addr:postcode":"88310",
    "addr:street":"Delaware Ave",
    "iso:country":"US",
    "sg:address":"400 Delaware Ave",
    "sg:city":"Alamogordo",
    "sg:classifiers":[
        {
            "category":"Organizations",
            "subcategory":"Religious Organization",
            "type":"Services"
        }
    ],
    "sg:phone":"+1 505 437 0988",
    "sg:postcode":"88310",
    "sg:province":"NM",
    "sg:tags":[
        "church"
    ],
    "wof:name":"Corinth Baptist Church",
    "wof:placetype":"venue"
},
  "geometry": {"coordinates":[-105.958054,32.894897],"type":"Point"}
}