{
  "type": "Feature",
  "properties": {
    "iso:country":"US",
    "sg:address":"199 S Butler Ave",
    "sg:city":"Farmington",
    "sg:classifiers":[
        {
            "category":"Autos & Motor Vehicles",
            "subcategory":"Automobile Sales",
            "type":"Retail Goods"
        }
    ],
    "sg:phone":"+1 505 327 3300",
    "sg:postcode":"87401",
    "sg:province":"NM",
    "sg:tags":[
        "used"
    ],
    "wof:name":"Trucksmart Inc",
    "wof:placetype":"venue"
},
  "geometry": {"coordinates":[-108.197579,36.729251],"type":"Point"}
}