{
  "type": "Feature",
  "properties": {
    "iso:country":"US",
    "sg:address":"2423 Chelwood Park Blvd NE",
    "sg:city":"Albuquerque",
    "sg:classifiers":[
        {
            "category":"Personal",
            "subcategory":"Beauty Salon",
            "type":"Services"
        }
    ],
    "sg:phone":"+1 505 292 6885",
    "sg:postcode":"87112",
    "sg:province":"NM",
    "sg:tags":[
        "shop"
    ],
    "wof:name":"Al Fanso Russo Phographer",
    "wof:placetype":"venue"
},
  "geometry": {"coordinates":[-106.50658799999999,35.111173],"type":"Point"}
}