{
  "type": "Feature",
  "properties": {
    "iso:country":"US",
    "sg:address":"8400 Menaul Blvd NE",
    "sg:city":"Albuquerque",
    "sg:classifiers":[
        {
            "category":"Ice Cream",
            "type":"Food & Drink"
        }
    ],
    "sg:menulink":"http://www.allmenus.com/nm/albuquerque/243443-baskin-robbins/menu/",
    "sg:phone":"+1 505 294 3101",
    "sg:postcode":"87112",
    "sg:province":"NM",
    "sg:tags":[
        "american"
    ],
    "wof:name":"Baskin-Robbins",
    "wof:placetype":"venue"
},
  "geometry": {"coordinates":[-106.55023,35.108712],"type":"Point"}
}