{
  "type": "Feature",
  "properties": {
    "iso:country":"US",
    "sg:address":"1251 W Apache St",
    "sg:city":"Farmington",
    "sg:classifiers":[
        {
            "category":"Shopping",
            "subcategory":"Jewelry",
            "type":"Retail Goods"
        }
    ],
    "sg:phone":"+1 505 327 3857",
    "sg:postcode":"87401",
    "sg:province":"NM",
    "sg:tags":[
        "personal",
        "merchandise"
    ],
    "wof:name":"Bola Tys & Butterflys",
    "wof:placetype":"venue"
},
  "geometry": {"coordinates":[-108.228409,36.733696],"type":"Point"}
}