{
  "type": "Feature",
  "properties": {
    "iso:country":"US",
    "sg:address":"2117 N French Dr",
    "sg:city":"Hobbs",
    "sg:classifiers":[
        {
            "category":"Wholesale",
            "subcategory":"Machinery & Supplies",
            "type":"Manufacturing & Wholesale Goods"
        }
    ],
    "sg:phone":"+1 505 391 9811",
    "sg:postcode":"88240",
    "sg:province":"NM",
    "sg:tags":[
        "field",
        "oil",
        "equipment"
    ],
    "wof:name":"Weatherford",
    "wof:placetype":"venue"
},
  "geometry": {"coordinates":[-103.16211300000001,32.725428],"type":"Point"}
}