{
  "type": "Feature",
  "properties": {
    "iso:country":"US",
    "sg:address":"2605 W Main St",
    "sg:city":"Artesia",
    "sg:classifiers":[
        {
            "category":"Utilities",
            "subcategory":"Natural Gas",
            "type":"Services"
        }
    ],
    "sg:phone":"+1 505 746 2755",
    "sg:postcode":"88210",
    "sg:province":"NM",
    "sg:tags":[
        "distribution"
    ],
    "wof:name":"Enron Energy Services Inc",
    "wof:placetype":"venue"
},
  "geometry": {"coordinates":[-104.435389,32.84255],"type":"Point"}
}