{
  "type": "Feature",
  "properties": {
    "addr:full":"205 W Boutz Rd Las Cruces NM 88005",
    "addr:housenumber":"205",
    "addr:postcode":"88005",
    "addr:street":"W Boutz Rd",
    "iso:country":"US",
    "sg:address":"205 W Boutz Rd",
    "sg:city":"Las Cruces",
    "sg:classifiers":[
        {
            "category":"Health Services",
            "subcategory":"Hospital",
            "type":"Services"
        }
    ],
    "sg:phone":"+1 505 647 3945",
    "sg:postcode":"88005",
    "sg:province":"NM",
    "sg:tags":[
        "mental"
    ],
    "wof:name":"Alliance Behavioral Health",
    "wof:placetype":"venue"
},
  "geometry": {"coordinates":[-106.781853,32.288148],"type":"Point"}
}