{
  "type": "Feature",
  "properties": {
    "iso:country":"US",
    "sg:address":"11101 Arvada Ave NE",
    "sg:city":"Albuquerque",
    "sg:classifiers":[
        {
            "category":"Professional",
            "subcategory":"Business Services",
            "type":"Services"
        }
    ],
    "sg:phone":"+1 505 294 5444",
    "sg:postcode":"87112",
    "sg:province":"NM",
    "wof:name":"Your Happy Helper",
    "wof:placetype":"venue"
},
  "geometry": {"coordinates":[-106.516784,35.104396],"type":"Point"}
}