{
  "type": "Feature",
  "properties": {
    "iso:country":"US",
    "sg:address":"157 Cll Don Jose",
    "sg:city":"Santa Fe",
    "sg:classifiers":[
        {
            "category":"Real Estate",
            "subcategory":"Real Estate Agent",
            "type":"Services"
        }
    ],
    "sg:phone":"+1 505 820 0443",
    "sg:postcode":"87501",
    "sg:province":"NM",
    "wof:name":"Debra S Anderson",
    "wof:placetype":"venue"
},
  "geometry": {"coordinates":[-105.980427,35.67637],"type":"Point"}
}