{
  "type": "Feature",
  "properties": {
    "addr:full":"600 Central Ave SW Albuquerque NM 87102",
    "addr:housenumber":"600",
    "addr:postcode":"87102",
    "addr:street":"Central Ave Sw",
    "iso:country":"US",
    "sg:address":"600 Central Ave SW",
    "sg:city":"Albuquerque",
    "sg:classifiers":[
        {
            "category":"Professional",
            "subcategory":"Engineering",
            "type":"Services"
        }
    ],
    "sg:phone":"+1 505 842 5504",
    "sg:postcode":"87102",
    "sg:province":"NM",
    "sg:tags":[
        "engineer"
    ],
    "wof:name":"Bandi Engineering Co",
    "wof:placetype":"venue"
},
  "geometry": {"coordinates":[-106.655163,35.085028],"type":"Point"}
}