{
  "type": "Feature",
  "properties": {
    "addr:full":"920 N Turner St Hobbs NM 88240",
    "addr:housenumber":"920",
    "addr:postcode":"88240",
    "addr:street":"N Turner St",
    "iso:country":"US",
    "sg:address":"920 N Turner St",
    "sg:city":"Hobbs",
    "sg:classifiers":[
        {
            "category":"Social Services",
            "type":"Services"
        }
    ],
    "sg:phone":"+1 505 397 4398",
    "sg:postcode":"88240",
    "sg:province":"NM",
    "sg:tags":[
        "organization",
        "welfare"
    ],
    "wof:name":"Habitat For Humanity",
    "wof:placetype":"venue"
},
  "geometry": {"coordinates":[-103.13614699999999,32.709997],"type":"Point"}
}