{
  "type": "Feature",
  "properties": {
    "iso:country":"US",
    "sg:address":"1612 N Main St",
    "sg:city":"Clovis",
    "sg:classifiers":[
        {
            "category":"Shopping",
            "subcategory":"Used Merchandise",
            "type":"Retail Goods"
        },
        {
            "category":"Shopping",
            "subcategory":"Clothing, Apparel, & Fashions",
            "type":"Retail Goods"
        }
    ],
    "sg:phone":"+1 505 769 0308",
    "sg:postcode":"88101",
    "sg:province":"NM",
    "sg:tags":[
        "second",
        "store",
        "hand"
    ],
    "wof:name":"Mother Hubbard Inc",
    "wof:placetype":"venue"
},
  "geometry": {"coordinates":[-103.205462,34.413889],"type":"Point"}
}