{
  "type": "Feature",
  "properties": {
    "iso:country":"US",
    "sg:address":"5235 Hwy 28",
    "sg:city":"Anthony",
    "sg:classifiers":[
        {
            "category":"Education",
            "subcategory":"School",
            "type":"Public Place"
        }
    ],
    "sg:phone":"+1 505 882 0142",
    "sg:postcode":"88021",
    "sg:province":"NM",
    "wof:name":"Desert Pride Academy",
    "wof:placetype":"venue"
},
  "geometry": {"coordinates":[-106.650293,31.984731],"type":"Point"}
}