{
  "type": "Feature",
  "properties": {
    "addr:full":"419 S California St Socorro NM 87801",
    "addr:housenumber":"419",
    "addr:postcode":"87801",
    "addr:street":"S California St",
    "iso:country":"US",
    "sg:address":"419 S California St",
    "sg:city":"Socorro",
    "sg:classifiers":[
        {
            "category":"Cinema",
            "subcategory":"Movie Rental",
            "type":"Entertainment"
        }
    ],
    "sg:phone":"+1 505 835 3913",
    "sg:postcode":"87801",
    "sg:province":"NM",
    "sg:tags":[
        "product",
        "leasing",
        "tobacco",
        "disc",
        "video",
        "tape"
    ],
    "wof:name":"Video Shack",
    "wof:placetype":"venue"
},
  "geometry": {"coordinates":[-106.891153,34.0545],"type":"Point"}
}