{
  "type": "Feature",
  "properties": {
    "addr:full":"225 Virginia Ave Roswell NM 88203",
    "addr:housenumber":"225",
    "addr:postcode":"88203",
    "addr:street":"Virginia Ave",
    "iso:country":"US",
    "sg:address":"225 Virginia Ave",
    "sg:city":"Roswell",
    "sg:classifiers":[
        {
            "category":"Retail",
            "subcategory":"Auto Repair",
            "type":"Services"
        }
    ],
    "sg:phone":"+1 505 622 0891",
    "sg:postcode":"88203",
    "sg:province":"NM",
    "sg:tags":[
        "general"
    ],
    "wof:name":"Auto Aid",
    "wof:placetype":"venue"
},
  "geometry": {"coordinates":[-104.5204,33.372711],"type":"Point"}
}