{
  "type": "Feature",
  "properties": {
    "iso:country":"US",
    "sg:address":"200 W Railroad Ave",
    "sg:city":"Tucumcari",
    "sg:classifiers":[
        {
            "category":"Railroad",
            "type":"Transportation"
        }
    ],
    "sg:phone":"+1 505 461 3116",
    "sg:postcode":"88401",
    "sg:province":"NM",
    "sg:tags":[
        "operator",
        "line"
    ],
    "wof:name":"Union Pacific Railroad Company",
    "wof:placetype":"venue"
},
  "geometry": {"coordinates":[-103.72733599999999,35.179553],"type":"Point"}
}