{
  "type": "Feature",
  "properties": {
    "addr:full":"703 E 2nd St Portales NM 88130",
    "addr:housenumber":"703",
    "addr:postcode":"88130",
    "addr:street":"E 2Nd St",
    "iso:country":"US",
    "sg:address":"703 E 2nd St",
    "sg:city":"Portales",
    "sg:classifiers":[
        {
            "category":"Retail",
            "subcategory":"Auto Repair",
            "type":"Services"
        }
    ],
    "sg:phone":"+1 505 760 9895",
    "sg:postcode":"88130",
    "sg:province":"NM",
    "sg:tags":[
        "repairing",
        "automobile"
    ],
    "wof:name":"Sam's Accessories & Auto",
    "wof:placetype":"venue"
},
  "geometry": {"coordinates":[-103.33183200000001,34.187292],"type":"Point"}
}