{
  "type": "Feature",
  "properties": {
    "iso:country":"US",
    "sg:address":"373 N Cam del Pueblo",
    "sg:city":"Bernalillo",
    "sg:classifiers":[
        {
            "category":"Shopping",
            "type":"Retail Goods"
        }
    ],
    "sg:phone":"+1 505 867 8666",
    "sg:postcode":"87004",
    "sg:province":"NM",
    "sg:tags":[
        "art",
        "gallery",
        "dealer"
    ],
    "wof:name":"Art Gallery 66",
    "wof:placetype":"venue"
},
  "geometry": {"coordinates":[-106.539906,35.324057],"type":"Point"}
}