{
  "type": "Feature",
  "properties": {
    "addr:full":"5401 Purcell Dr NE Albuquerque NM 87111",
    "addr:housenumber":"5401",
    "addr:postcode":"87111",
    "addr:street":"Purcell Dr Ne",
    "iso:country":"US",
    "sg:address":"5401 Purcell Dr NE",
    "sg:city":"Albuquerque",
    "sg:classifiers":[
        {
            "category":"Insurance",
            "subcategory":"Insurance Agent",
            "type":"Services"
        }
    ],
    "sg:phone":"+1 505 292 8397",
    "sg:postcode":"87111",
    "sg:province":"NM",
    "wof:name":"Louise E Malherbe Agency",
    "wof:placetype":"venue"
},
  "geometry": {"coordinates":[-106.52221900000001,35.142128],"type":"Point"}
}