{
  "type": "Feature",
  "properties": {
    "iso:country":"US",
    "sg:address":"813 Tangigoot",
    "sg:city":"Aztec",
    "sg:classifiers":[
        {
            "category":"Building & Trades",
            "subcategory":"Construction",
            "type":"Services"
        }
    ],
    "sg:phone":"+1 505 334 9467",
    "sg:postcode":"87410",
    "sg:province":"NM",
    "sg:tags":[
        "contractor"
    ],
    "wof:name":"Aero Construction Co",
    "wof:placetype":"venue"
},
  "geometry": {"coordinates":[-107.976382,36.824382],"type":"Point"}
}