{
  "type": "Feature",
  "properties": {
    "addr:full":"8501 Zuni Rd SE Albuquerque NM 87108",
    "addr:housenumber":"8501",
    "addr:postcode":"87108",
    "addr:street":"Zuni Rd Se",
    "iso:country":"US",
    "sg:address":"8501 Zuni Rd SE",
    "sg:city":"Albuquerque",
    "sg:classifiers":[
        {
            "category":"Restaurant",
            "type":"Food & Drink"
        }
    ],
    "sg:phone":"+1 505 265 1481",
    "sg:postcode":"87108",
    "sg:province":"NM",
    "wof:name":"Bea's Central Office",
    "wof:placetype":"venue"
},
  "geometry": {"coordinates":[-106.55373,35.072786],"type":"Point"}
}