{
  "type": "Feature",
  "properties": {
    "addr:full":"1021 Alvarado Dr SE Albuquerque NM 87108",
    "addr:housenumber":"1021",
    "addr:postcode":"87108",
    "addr:street":"Alvarado Dr Se",
    "iso:country":"US",
    "sg:address":"1021 Alvarado Dr SE",
    "sg:city":"Albuquerque",
    "sg:classifiers":[
        {
            "category":"Building & Trades",
            "subcategory":"Construction",
            "type":"Services"
        }
    ],
    "sg:phone":"+1 505 620 2530",
    "sg:postcode":"87108",
    "sg:province":"NM",
    "sg:tags":[
        "painter"
    ],
    "wof:name":"Dr Painting Co",
    "wof:placetype":"venue"
},
  "geometry": {"coordinates":[-106.582095,35.062308],"type":"Point"}
}