{
  "type": "Feature",
  "properties": {
    "iso:country":"US",
    "sg:address":"4504 Barrett Ave NW",
    "sg:city":"Albuquerque",
    "sg:classifiers":[
        {
            "category":"Organizations",
            "subcategory":"Religious Organization",
            "type":"Services"
        }
    ],
    "sg:phone":"+1 505 898 1199",
    "sg:postcode":"87114",
    "sg:province":"NM",
    "wof:name":"Wisdom Ministries",
    "wof:placetype":"venue"
},
  "geometry": {"coordinates":[-106.67389900000001,35.202768],"type":"Point"}
}