{
  "type": "Feature",
  "properties": {
    "iso:country":"US",
    "sg:address":"201 E Broadway St",
    "sg:city":"Hobbs",
    "sg:classifiers":[
        {
            "category":"Wholesale",
            "subcategory":"Machinery & Supplies",
            "type":"Manufacturing & Wholesale Goods"
        }
    ],
    "sg:phone":"+1 505 391 6665",
    "sg:postcode":"88240",
    "sg:province":"NM",
    "sg:tags":[
        "equipment",
        "safety",
        "clothing"
    ],
    "wof:name":"Mobile Med One",
    "wof:placetype":"venue"
},
  "geometry": {"coordinates":[-103.134963,32.700798],"type":"Point"}
}