{
  "type": "Feature",
  "properties": {
    "iso:country":"US",
    "sg:address":"2050 W Amador Ave",
    "sg:city":"Las Cruces",
    "sg:classifiers":[
        {
            "category":"Wholesale",
            "subcategory":"Hardware",
            "type":"Manufacturing & Wholesale Goods"
        }
    ],
    "sg:phone":"+1 505 523 8898",
    "sg:postcode":"88005",
    "sg:province":"NM",
    "sg:tags":[
        "air",
        "parts",
        "conditioning",
        "supply"
    ],
    "sg:website":"www.johnstonesupply.com",
    "wof:name":"Johnstone Supply",
    "wof:placetype":"venue"
},
  "geometry": {"coordinates":[-106.804175,32.299767],"type":"Point"}
}