{
  "type": "Feature",
  "properties": {
    "addr:full":"4222 Rio Grande Blvd NW Albuquerque NM 87107",
    "addr:housenumber":"4222",
    "addr:postcode":"87107",
    "addr:street":"Rio Grande Blvd Nw",
    "iso:country":"US",
    "sg:address":"4222 Rio Grande Blvd NW",
    "sg:city":"Albuquerque",
    "sg:classifiers":[
        {
            "category":"Shopping",
            "subcategory":"Florist",
            "type":"Retail Goods"
        }
    ],
    "sg:phone":"+1 505 345 3666",
    "sg:postcode":"87107",
    "sg:province":"NM",
    "wof:name":"Wildflower Wrangler",
    "wof:placetype":"venue"
},
  "geometry": {"coordinates":[-106.66711599999999,35.141504],"type":"Point"}
}