{
  "type": "Feature",
  "properties": {
    "iso:country":"US",
    "sg:address":"2133 Ryan Pl NW",
    "sg:city":"Albuquerque",
    "sg:classifiers":[
        {
            "category":"Professional",
            "subcategory":"Art Services",
            "type":"Services"
        }
    ],
    "sg:phone":"+1 505 345 3994",
    "sg:postcode":"87107",
    "sg:province":"NM",
    "sg:tags":[
        "commercial",
        "design"
    ],
    "wof:name":"Zocoloco Studios",
    "wof:placetype":"venue"
},
  "geometry": {"coordinates":[-106.66989100000001,35.123115],"type":"Point"}
}