{
  "type": "Feature",
  "properties": {
    "addr:full":"11109 Hackamore Ave SW Albuquerque NM 87121",
    "addr:housenumber":"11109",
    "addr:postcode":"87121",
    "addr:street":"Hackamore Ave Sw",
    "iso:country":"US",
    "sg:address":"11109 Hackamore Ave SW",
    "sg:city":"Albuquerque",
    "sg:classifiers":[
        {
            "category":"Shopping",
            "subcategory":"Bicycles & Sporting Goods",
            "type":"Retail Goods"
        }
    ],
    "sg:phone":"+1 505 836 1575",
    "sg:postcode":"87121",
    "sg:province":"NM",
    "sg:tags":[
        "gun",
        "gunsmith"
    ],
    "wof:name":"Smitty's Handguns & Knives",
    "wof:placetype":"venue"
},
  "geometry": {"coordinates":[-106.754887,35.060325],"type":"Point"}
}