{
  "type": "Feature",
  "properties": {
    "iso:country":"US",
    "sg:address":"6535 Edith Blvd NE",
    "sg:city":"Albuquerque",
    "sg:classifiers":[
        {
            "category":"Home & Garden",
            "subcategory":"Garden Supply",
            "type":"Retail Goods"
        }
    ],
    "sg:phone":"+1 505 345 1300",
    "sg:postcode":"87107",
    "sg:province":"NM",
    "sg:tags":[
        "fountain",
        "display"
    ],
    "wof:name":"Southwest Fountains Waterfalls",
    "wof:placetype":"venue"
},
  "geometry": {"coordinates":[-106.623648,35.150583],"type":"Point"}
}