{
  "type": "Feature",
  "properties": {
    "addr:full":"1431 San Mateo Blvd SE Albuquerque NM 87108",
    "addr:housenumber":"1431",
    "addr:postcode":"87108",
    "addr:street":"San Mateo Blvd Se",
    "iso:country":"US",
    "sg:address":"1431 San Mateo Blvd SE",
    "sg:city":"Albuquerque",
    "sg:classifiers":[
        {
            "category":"Personal",
            "subcategory":"Beauty Salon",
            "type":"Services"
        }
    ],
    "sg:phone":"+1 505 256 7244",
    "sg:postcode":"87108",
    "sg:province":"NM",
    "sg:tags":[
        "shop"
    ],
    "wof:name":"Pro Nails",
    "wof:placetype":"venue"
},
  "geometry": {"coordinates":[-106.586533,35.058917],"type":"Point"}
}