{
  "type": "Feature",
  "properties": {
    "addr:full":"8100 Constitution Pl NE Albuquerque NM 87110",
    "addr:housenumber":"8100",
    "addr:postcode":"87110",
    "addr:street":"Constitution Pl Ne",
    "iso:country":"US",
    "sg:address":"8100 Constitution Pl NE",
    "sg:city":"Albuquerque",
    "sg:classifiers":[
        {
            "category":"Health Services",
            "subcategory":"Doctor",
            "type":"Services"
        }
    ],
    "sg:phone":"+1 505 291 2222",
    "sg:postcode":"87110",
    "sg:province":"NM",
    "sg:tags":[
        "medical",
        "clinic"
    ],
    "wof:name":"New Mexico Arthritis Clinic",
    "wof:placetype":"venue"
},
  "geometry": {"coordinates":[-106.555762,35.093397],"type":"Point"}
}