{
  "type": "Feature",
  "properties": {
    "iso:country":"US",
    "sg:address":"230 W Coal Ave",
    "sg:city":"Gallup",
    "sg:classifiers":[
        {
            "category":"Personal",
            "subcategory":"Shoe Repair & Shine",
            "type":"Services"
        }
    ],
    "sg:phone":"+1 505 863 5252",
    "sg:postcode":"87301",
    "sg:province":"NM",
    "sg:tags":[
        "tack",
        "shoes"
    ],
    "wof:name":"City Electric Shoe Shop",
    "wof:placetype":"venue"
},
  "geometry": {"coordinates":[-108.74280400000001,35.527058],"type":"Point"}
}