{
  "type": "Feature",
  "properties": {
    "iso:country":"US",
    "sg:address":"1301 Yale Blvd SE",
    "sg:city":"Albuquerque",
    "sg:classifiers":[
        {
            "category":"Wholesale",
            "subcategory":"Vending Machines",
            "type":"Manufacturing & Wholesale Goods"
        }
    ],
    "sg:phone":"+1 505 242 0102",
    "sg:postcode":"87106",
    "sg:province":"NM",
    "sg:tags":[
        "product",
        "sales"
    ],
    "wof:name":"Clear Waters",
    "wof:placetype":"venue"
},
  "geometry": {"coordinates":[-106.622131,35.066805],"type":"Point"}
}