{
  "type": "Feature",
  "properties": {
    "iso:country":"US",
    "sg:address":"3323 Hoyle Rd NE",
    "sg:city":"Albuquerque",
    "sg:classifiers":[
        {
            "category":"Building & Trades",
            "subcategory":"Construction",
            "type":"Services"
        }
    ],
    "sg:phone":"+1 505 881 6722",
    "sg:postcode":"87110",
    "sg:province":"NM",
    "sg:tags":[
        "general",
        "contractor"
    ],
    "wof:name":"S R G Construction Inc",
    "wof:placetype":"venue"
},
  "geometry": {"coordinates":[-106.59930300000001,35.118513],"type":"Point"}
}