{
  "type": "Feature",
  "properties": {
    "addr:full":"79 Summer Winds Dr NE Rio Rancho NM 87124",
    "addr:housenumber":"79",
    "addr:postcode":"87124",
    "addr:street":"Summer Winds Dr Ne",
    "iso:country":"US",
    "sg:address":"79 Summer Winds Dr NE",
    "sg:city":"Rio Rancho",
    "sg:classifiers":[
        {
            "category":"Organizations",
            "subcategory":"Community Association",
            "type":"Services"
        }
    ],
    "sg:phone":"+1 505 892 4144",
    "sg:postcode":"87124",
    "sg:province":"NM",
    "wof:name":"Gold Wing Road Riders Assn",
    "wof:placetype":"venue"
},
  "geometry": {"coordinates":[-106.695195,35.258462],"type":"Point"}
}