{
  "type": "Feature",
  "properties": {
    "iso:country":"US",
    "sg:address":"1715 Girard Blvd NE",
    "sg:city":"Albuquerque",
    "sg:classifiers":[
        {
            "category":"Shopping",
            "subcategory":"Bicycles & Sporting Goods",
            "type":"Retail Goods"
        }
    ],
    "sg:phone":"+1 505 255 3400",
    "sg:postcode":"87106",
    "sg:province":"NM",
    "sg:tags":[
        "personal",
        "equipment",
        "training",
        "physical",
        "fitness"
    ],
    "wof:name":"Discount Fitness Equipment",
    "wof:placetype":"venue"
},
  "geometry": {"coordinates":[-106.613953,35.103322],"type":"Point"}
}