{
  "type": "Feature",
  "properties": {
    "iso:country":"US",
    "sg:address":"755 N Riverside Dr",
    "sg:city":"Espanola",
    "sg:classifiers":[
        {
            "category":"Retail",
            "subcategory":"Auto Repair",
            "type":"Services"
        }
    ],
    "sg:phone":"+1 505 753 2480",
    "sg:postcode":"87532",
    "sg:province":"NM",
    "sg:tags":[
        "automobile",
        "lubrication"
    ],
    "wof:name":"Swift Lube",
    "wof:placetype":"venue"
},
  "geometry": {"coordinates":[-106.060852,35.987897],"type":"Point"}
}