{
  "type": "Feature",
  "properties": {
    "addr:full":"627 Cam de la Luz Santa Fe NM 87505",
    "addr:housenumber":"627",
    "addr:postcode":"87505",
    "addr:street":"Cam De La Luz",
    "iso:country":"US",
    "sg:address":"627 Cam de la Luz",
    "sg:city":"Santa Fe",
    "sg:classifiers":[
        {
            "category":"Organizations",
            "subcategory":"Membership Organization",
            "type":"Services"
        }
    ],
    "sg:phone":"+1 505 983 1790",
    "sg:postcode":"87505",
    "sg:province":"NM",
    "wof:name":"Margaret Lfranc Art Foundation",
    "wof:placetype":"venue"
},
  "geometry": {"coordinates":[-105.915589,35.675262],"type":"Point"}
}