{
  "type": "Feature",
  "properties": {
    "iso:country":"US",
    "sg:address":"105 4th St SW",
    "sg:city":"Albuquerque",
    "sg:classifiers":[
        {
            "category":"Shopping",
            "type":"Retail Goods"
        }
    ],
    "sg:phone":"+1 505 242 1983",
    "sg:postcode":"87102",
    "sg:province":"NM",
    "sg:tags":[
        "art",
        "gallery",
        "dealer"
    ],
    "wof:name":"Downtown Contemporary Art Ctr",
    "wof:placetype":"venue"
},
  "geometry": {"coordinates":[-106.651866,35.083613],"type":"Point"}
}