{
  "type": "Feature",
  "properties": {
    "iso:country":"US",
    "sg:address":"10 Valle Vista Ct",
    "sg:city":"Santa Fe",
    "sg:classifiers":[
        {
            "category":"Professional",
            "subcategory":"Business Services",
            "type":"Services"
        }
    ],
    "sg:phone":"+1 505 473 2033",
    "sg:postcode":"87508",
    "sg:province":"NM",
    "wof:name":"Mario Reynolds",
    "wof:placetype":"venue"
},
  "geometry": {"coordinates":[-106.06128699999999,35.583059],"type":"Point"}
}