{
  "type": "Feature",
  "properties": {
    "iso:country":"US",
    "sg:address":"10 W 1st St",
    "sg:city":"Tatum",
    "sg:classifiers":[
        {
            "category":"Shopping",
            "type":"Retail Goods"
        }
    ],
    "sg:phone":"+1 505 398 2212",
    "sg:postcode":"88267",
    "sg:province":"NM",
    "sg:tags":[
        "equipment",
        "telephone",
        "supply"
    ],
    "wof:name":"Leaco",
    "wof:placetype":"venue"
},
  "geometry": {"coordinates":[-103.318817,33.255987],"type":"Point"}
}