{
  "type": "Feature",
  "properties": {
    "iso:country":"US",
    "sg:address":"3 Rd 5219",
    "sg:city":"Bloomfield",
    "sg:classifiers":[
        {
            "category":"Building & Trades",
            "subcategory":"Construction",
            "type":"Services"
        }
    ],
    "sg:phone":"+1 505 632 7171",
    "sg:postcode":"87413",
    "sg:province":"NM",
    "sg:tags":[
        "concrete",
        "contractor"
    ],
    "wof:name":"Quality Concrete",
    "wof:placetype":"venue"
},
  "geometry": {"coordinates":[-108.041867,36.675975],"type":"Point"}
}