{
  "type": "Feature",
  "properties": {
    "iso:country":"US",
    "sg:address":"3632 State Hwy 47",
    "sg:city":"Peralta",
    "sg:classifiers":[
        {
            "category":"Communications",
            "type":"Services"
        }
    ],
    "sg:phone":"+1 505 869 6056",
    "sg:postcode":"87042",
    "sg:province":"NM",
    "wof:name":"Lu Jans Communications",
    "wof:placetype":"venue"
},
  "geometry": {"coordinates":[-106.690535,34.830359],"type":"Point"}
}