{
  "type": "Feature",
  "properties": {
    "iso:country":"US",
    "sg:address":"2333 Raymac Rd SW",
    "sg:city":"Albuquerque",
    "sg:classifiers":[
        {
            "category":"Autos & Motor Vehicles",
            "subcategory":"Auto Supplies",
            "type":"Retail Goods"
        }
    ],
    "sg:phone":"+1 505 363 3252",
    "sg:postcode":"87105",
    "sg:province":"NM",
    "sg:tags":[
        "equipment",
        "racing",
        "car",
        "automobile"
    ],
    "wof:name":"Cusotm Coating",
    "wof:placetype":"venue"
},
  "geometry": {"coordinates":[-106.707309,34.979233],"type":"Point"}
}