{
  "type": "Feature",
  "properties": {
    "iso:country":"US",
    "sg:address":"2125 S Valley Dr",
    "sg:city":"Las Cruces",
    "sg:classifiers":[
        {
            "category":"Retail",
            "subcategory":"Repair Shop",
            "type":"Services"
        }
    ],
    "sg:phone":"+1 505 524 3626",
    "sg:postcode":"88005",
    "sg:province":"NM",
    "sg:tags":[
        "scooter",
        "motorcycle",
        "motor"
    ],
    "sg:website":"www.lcmotorsports.com",
    "wof:name":"Las Cruces Motorsports",
    "wof:placetype":"venue"
},
  "geometry": {"coordinates":[-106.776977,32.285788],"type":"Point"}
}