{
  "type": "Feature",
  "properties": {
    "iso:country":"US",
    "sg:address":"301 Tigris Rd NE",
    "sg:city":"Rio Rancho",
    "sg:classifiers":[
        {
            "category":"Shopping",
            "subcategory":"Books",
            "type":"Retail Goods"
        }
    ],
    "sg:phone":"+1 505 896 0506",
    "sg:postcode":"87124",
    "sg:province":"NM",
    "sg:tags":[
        "reseller"
    ],
    "wof:name":"Hackett JC",
    "wof:placetype":"venue"
},
  "geometry": {"coordinates":[-106.654584,35.260869],"type":"Point"}
}