{
  "type": "Feature",
  "properties": {
    "iso:country":"US",
    "sg:address":"5600 Wyoming Blvd NE",
    "sg:city":"Albuquerque",
    "sg:classifiers":[
        {
            "category":"Real Estate",
            "subcategory":"Developer",
            "type":"Services"
        }
    ],
    "sg:phone":"+1 505 857 9566",
    "sg:postcode":"87109",
    "sg:province":"NM",
    "wof:name":"T S C",
    "wof:placetype":"venue"
},
  "geometry": {"coordinates":[-106.551681,35.142935],"type":"Point"}
}