{
  "type": "Feature",
  "properties": {
    "iso:country":"US",
    "sg:address":"3020 Majestic Ridge",
    "sg:city":"Las Cruces",
    "sg:classifiers":[
        {
            "category":"Shopping",
            "subcategory":"Catalog Store",
            "type":"Retail Goods"
        }
    ],
    "sg:phone":"+1 505 522 3721",
    "sg:postcode":"88011",
    "sg:province":"NM",
    "sg:tags":[
        "house",
        "mail"
    ],
    "wof:name":"Dons Collectibles",
    "wof:placetype":"venue"
},
  "geometry": {"coordinates":[-106.73567,32.30935],"type":"Point"}
}