{
  "type": "Feature",
  "properties": {
    "iso:country":"US",
    "sg:address":"2508 Sudderth Dr",
    "sg:city":"Ruidoso",
    "sg:classifiers":[
        {
            "category":"Shopping",
            "subcategory":"Clothing, Apparel, & Fashions",
            "type":"Retail Goods"
        }
    ],
    "sg:phone":"+1 505 257 3132",
    "sg:postcode":"88345",
    "sg:province":"NM",
    "wof:name":"The T Shirt Outlet",
    "wof:placetype":"venue"
},
  "geometry": {"coordinates":[-105.672785,33.331759],"type":"Point"}
}