{
  "type": "Feature",
  "properties": {
    "iso:country":"US",
    "sg:address":"517 Swoose Ct SW",
    "sg:city":"Albuquerque",
    "sg:classifiers":[
        {
            "category":"Real Estate",
            "subcategory":"Real Estate Agent",
            "type":"Services"
        }
    ],
    "sg:phone":"+1 505 265 1832",
    "sg:postcode":"87105",
    "sg:province":"NM",
    "wof:name":"Sunrise Properties",
    "wof:placetype":"venue"
},
  "geometry": {"coordinates":[-106.676316,34.9923],"type":"Point"}
}