{
  "type": "Feature",
  "properties": {
    "iso:country":"US",
    "sg:address":"8116 Corte del Viento NW",
    "sg:city":"Albuquerque",
    "sg:classifiers":[
        {
            "category":"Building & Trades",
            "subcategory":"Construction",
            "type":"Services"
        }
    ],
    "sg:phone":"+1 505 280 2400",
    "sg:postcode":"87120",
    "sg:province":"NM",
    "sg:tags":[
        "general",
        "contractor"
    ],
    "wof:name":"Christian Contractors",
    "wof:placetype":"venue"
},
  "geometry": {"coordinates":[-106.734874,35.105994],"type":"Point"}
}