{
  "type": "Feature",
  "properties": {
    "iso:country":"US",
    "sg:address":"1789 Central Ave",
    "sg:city":"Los Alamos",
    "sg:classifiers":[
        {
            "category":"Coffee & Tea",
            "type":"Food & Drink"
        }
    ],
    "sg:menulink":"http://www.allmenus.com/nm/los-alamos/124943-starbucks-coffee/menu/",
    "sg:phone":"+1 505 661 0100",
    "sg:postcode":"87544",
    "sg:province":"NM",
    "sg:tags":[
        "american"
    ],
    "wof:name":"Starbucks Coffee",
    "wof:placetype":"venue"
},
  "geometry": {"coordinates":[-106.30267499999999,35.881658],"type":"Point"}
}