{
  "type": "Feature",
  "properties": {
    "iso:country":"US",
    "sg:address":"7555 Old Aztec Hwy",
    "sg:city":"Flora Vista",
    "sg:classifiers":[
        {
            "category":"Manufacturing",
            "subcategory":"Retail Goods",
            "type":"Manufacturing & Wholesale Goods"
        }
    ],
    "sg:phone":"+1 505 215 3078",
    "sg:postcode":"87415",
    "sg:province":"NM",
    "sg:tags":[
        "product",
        "mfg"
    ],
    "wof:name":"Martini Industries",
    "wof:placetype":"venue"
},
  "geometry": {"coordinates":[-108.101163,36.788354],"type":"Point"}
}