{
  "type": "Feature",
  "properties": {
    "iso:country":"US",
    "sg:address":"251 Sagebrush Dr",
    "sg:city":"Corrales",
    "sg:classifiers":[
        {
            "category":"Professional",
            "subcategory":"Art Services",
            "type":"Services"
        }
    ],
    "sg:phone":"+1 505 898 6630",
    "sg:postcode":"87048",
    "sg:province":"NM",
    "sg:tags":[
        "commercial",
        "design"
    ],
    "wof:name":"Dezinz By U Inc",
    "wof:placetype":"venue"
},
  "geometry": {"coordinates":[-106.614434,35.24089],"type":"Point"}
}