{
  "type": "Feature",
  "properties": {
    "iso:country":"US",
    "sg:address":"1907 Buena Vista Dr SE",
    "sg:city":"Albuquerque",
    "sg:classifiers":[
        {
            "category":"Building & Trades",
            "subcategory":"Cleaning & Sanitation",
            "type":"Services"
        }
    ],
    "sg:phone":"+1 505 848 9316",
    "sg:postcode":"87106",
    "sg:province":"NM",
    "sg:tags":[
        "janitor"
    ],
    "wof:name":"Fresh Start",
    "wof:placetype":"venue"
},
  "geometry": {"coordinates":[-106.624281,35.05852],"type":"Point"}
}