{
  "type": "Feature",
  "properties": {
    "iso:country":"US",
    "sg:address":"1864 Amis Ave",
    "sg:city":"Las Cruces",
    "sg:classifiers":[
        {
            "category":"Professional",
            "subcategory":"Art Services",
            "type":"Services"
        }
    ],
    "sg:phone":"+1 505 524 0092",
    "sg:postcode":"88005",
    "sg:province":"NM",
    "sg:tags":[
        "photo",
        "photography",
        "commercial",
        "studio",
        "portrait"
    ],
    "wof:name":"Jack Diven Photography",
    "wof:placetype":"venue"
},
  "geometry": {"coordinates":[-106.790997,32.325154],"type":"Point"}
}