{
  "type": "Feature",
  "properties": {
    "addr:full":"121 S Alameda St Jal NM 88252",
    "addr:housenumber":"121",
    "addr:postcode":"88252",
    "addr:street":"S Alameda St",
    "iso:country":"US",
    "sg:address":"121 S Alameda St",
    "sg:city":"Jal",
    "sg:classifiers":[
        {
            "category":"Organizations",
            "subcategory":"Religious Organization",
            "type":"Services"
        }
    ],
    "sg:phone":"+1 505 395 2446",
    "sg:postcode":"88252",
    "sg:province":"NM",
    "sg:tags":[
        "church"
    ],
    "wof:name":"Church Of God",
    "wof:placetype":"venue"
},
  "geometry": {"coordinates":[-103.19539,32.115507],"type":"Point"}
}