{
  "type": "Feature",
  "properties": {
    "iso:country":"US",
    "sg:address":"1000 Rio Grande Blvd NW",
    "sg:city":"Albuquerque",
    "sg:classifiers":[
        {
            "category":"Autos & Motor Vehicles",
            "subcategory":"Automobile Sales",
            "type":"Retail Goods"
        }
    ],
    "sg:phone":"+1 505 247 3742",
    "sg:postcode":"87104",
    "sg:province":"NM",
    "sg:tags":[
        "station",
        "gasoline"
    ],
    "wof:name":"Old Town Cheveron",
    "wof:placetype":"venue"
},
  "geometry": {"coordinates":[-106.670732,35.104206],"type":"Point"}
}