{
  "type": "Feature",
  "properties": {
    "iso:country":"US",
    "sg:address":"531 W Cordova Rd",
    "sg:city":"Santa Fe",
    "sg:classifiers":[
        {
            "category":"Shopping",
            "subcategory":"Clothing, Apparel, & Fashions",
            "type":"Retail Goods"
        }
    ],
    "sg:phone":"+1 505 988 3782",
    "sg:postcode":"87505",
    "sg:province":"NM",
    "sg:tags":[
        "uniform"
    ],
    "wof:name":"Capital City Uniforms",
    "wof:placetype":"venue"
},
  "geometry": {"coordinates":[-105.94981799999999,35.672542],"type":"Point"}
}