{
  "type": "Feature",
  "properties": {
    "iso:country":"US",
    "sg:address":"3417 State Rte 434",
    "sg:city":"Angel Fire",
    "sg:classifiers":[
        {
            "category":"Real Estate",
            "subcategory":"Real Estate Agent",
            "type":"Services"
        }
    ],
    "sg:phone":"+1 505 377 2639",
    "sg:postcode":"87710",
    "sg:province":"NM",
    "wof:name":"Colfax County Appraisers",
    "wof:placetype":"venue"
},
  "geometry": {"coordinates":[-105.28628399999999,36.394885],"type":"Point"}
}