{
  "type": "Feature",
  "properties": {
    "addr:full":"721 E Broadway St Hobbs NM 88240",
    "addr:housenumber":"721",
    "addr:postcode":"88240",
    "addr:street":"E Broadway St",
    "iso:country":"US",
    "sg:address":"721 E Broadway St",
    "sg:city":"Hobbs",
    "sg:classifiers":[
        {
            "category":"Insurance",
            "subcategory":"Hazard Insurance",
            "type":"Services"
        },
        {
            "category":"Professional",
            "subcategory":"Business Services",
            "type":"Services"
        }
    ],
    "sg:phone":"+1 505 391 7722",
    "sg:postcode":"88240",
    "sg:province":"NM",
    "sg:tags":[
        "bond"
    ],
    "wof:name":"A-Action Bail Bonds",
    "wof:placetype":"venue"
},
  "geometry": {"coordinates":[-103.127768,32.700712],"type":"Point"}
}