{
  "type": "Feature",
  "properties": {
    "iso:country":"US",
    "sg:address":"3104 Highland Rd",
    "sg:city":"Roswell",
    "sg:classifiers":[
        {
            "category":"Shopping",
            "subcategory":"Pharmacy",
            "type":"Retail Goods"
        }
    ],
    "sg:phone":"+1 505 623 8056",
    "sg:postcode":"88201",
    "sg:province":"NM",
    "wof:name":"Ricks Good Neighbor Pharmacy",
    "wof:placetype":"venue"
},
  "geometry": {"coordinates":[-104.568619,33.397054],"type":"Point"}
}