{
  "type": "Feature",
  "properties": {
    "iso:country":"US",
    "sg:address":"2200 Sunport Blvd SE",
    "sg:city":"Albuquerque",
    "sg:classifiers":[
        {
            "category":"Restaurant",
            "type":"Food & Drink"
        }
    ],
    "sg:phone":"+1 505 842 4305",
    "sg:postcode":"87106",
    "sg:province":"NM",
    "wof:name":"Black Mesa Coffee Co",
    "wof:placetype":"venue"
},
  "geometry": {"coordinates":[-106.618173,35.049665],"type":"Point"}
}