{
  "type": "Feature",
  "properties": {
    "iso:country":"US",
    "sg:address":"2555 Lakeside Dr",
    "sg:city":"Las Cruces",
    "sg:classifiers":[
        {
            "category":"Farming",
            "subcategory":"Farm",
            "type":"Manufacturing & Wholesale Goods"
        }
    ],
    "sg:phone":"+1 505 525 1524",
    "sg:postcode":"88007",
    "sg:province":"NM",
    "wof:name":"Mesilla Valley Pecan Co",
    "wof:placetype":"venue"
},
  "geometry": {"coordinates":[-106.806091,32.291183],"type":"Point"}
}