{
  "type": "Feature",
  "properties": {
    "iso:country":"US",
    "sg:address":"97 Meador Ln",
    "sg:city":"Santa Fe",
    "sg:classifiers":[
        {
            "category":"Retail",
            "subcategory":"Repair Shop",
            "type":"Services"
        }
    ],
    "sg:phone":"+1 505 474 7800",
    "sg:postcode":"87508",
    "sg:province":"NM",
    "sg:tags":[
        "scooter",
        "motorcycle",
        "motor"
    ],
    "wof:name":"High Desert Custom V Twins",
    "wof:placetype":"venue"
},
  "geometry": {"coordinates":[-105.995007,35.609633],"type":"Point"}
}