{
  "type": "Feature",
  "properties": {
    "iso:country":"US",
    "sg:address":"100 W Franklin St",
    "sg:city":"Grady",
    "sg:classifiers":[
        {
            "category":"Education",
            "subcategory":"School",
            "type":"Public Place"
        }
    ],
    "sg:phone":"+1 505 357 2192",
    "sg:postcode":"88120",
    "sg:province":"NM",
    "wof:name":"Grady School District",
    "wof:placetype":"venue"
},
  "geometry": {"coordinates":[-103.316208,34.822491],"type":"Point"}
}