{
  "type": "Feature",
  "properties": {
    "iso:country":"US",
    "sg:address":"1004 Hickox St",
    "sg:city":"Santa Fe",
    "sg:classifiers":[
        {
            "category":"Building & Trades",
            "subcategory":"Construction",
            "type":"Services"
        }
    ],
    "sg:phone":"+1 505 982 4566",
    "sg:postcode":"87505",
    "sg:province":"NM",
    "sg:tags":[
        "hanging",
        "contractor"
    ],
    "wof:name":"Santa Fe Painting and Dctg",
    "wof:placetype":"venue"
},
  "geometry": {"coordinates":[-105.956543,35.681425],"type":"Point"}
}