{
  "type": "Feature",
  "properties": {
    "iso:country":"US",
    "sg:address":"2841 San Mateo Blvd NE",
    "sg:city":"Albuquerque",
    "sg:classifiers":[
        {
            "category":"Personal",
            "subcategory":"Beauty Salon",
            "type":"Services"
        }
    ],
    "sg:phone":"+1 505 881 0818",
    "sg:postcode":"87110",
    "sg:province":"NM",
    "wof:name":"Hair Fashions-Beauty Salon",
    "wof:placetype":"venue"
},
  "geometry": {"coordinates":[-106.58642399999999,35.113908],"type":"Point"}
}