{
  "type": "Feature",
  "properties": {
    "iso:country":"US",
    "sg:address":"5811 Signal Ave NE",
    "sg:city":"Albuquerque",
    "sg:phone":"+1 800 424 6423",
    "sg:postcode":"87113",
    "sg:province":"NM",
    "sg:website":"http://www.comfortinn.com/hotel-albuquerque-new_mexico-NM417?promo=yplocal",
    "wof:name":"Comfort Inn & Suites North Albuquerque",
    "wof:placetype":"venue"
},
  "geometry": {"coordinates":[-106.579144,35.182964],"type":"Point"}
}