{
  "type": "Feature",
  "properties": {
    "iso:country":"US",
    "sg:address":"901 Rio Grande Blvd NW",
    "sg:city":"Albuquerque",
    "sg:classifiers":[
        {
            "category":"Wholesale",
            "subcategory":"Machinery & Supplies",
            "type":"Manufacturing & Wholesale Goods"
        }
    ],
    "sg:phone":"+1 505 243 2866",
    "sg:postcode":"87104",
    "sg:province":"NM",
    "sg:tags":[
        "equipment",
        "industrial"
    ],
    "wof:name":"Zia Elevator Co Inc",
    "wof:placetype":"venue"
},
  "geometry": {"coordinates":[-106.670748,35.103508],"type":"Point"}
}