{
  "type": "Feature",
  "properties": {
    "iso:country":"US",
    "sg:address":"2908 Indian Farm Ln NW",
    "sg:city":"Albuquerque",
    "sg:classifiers":[
        {
            "category":"Professional",
            "type":"Services"
        }
    ],
    "sg:phone":"+1 505 345 4203",
    "sg:postcode":"87107",
    "sg:province":"NM",
    "sg:tags":[
        "establishment"
    ],
    "wof:name":"Casa De Carino",
    "wof:placetype":"venue"
},
  "geometry": {"coordinates":[-106.66819599999999,35.122086],"type":"Point"}
}