{
  "type": "Feature",
  "properties": {
    "iso:country":"US",
    "sg:address":"4113 Comanche Rd NE",
    "sg:city":"Albuquerque",
    "sg:classifiers":[
        {
            "category":"Shopping",
            "subcategory":"Hobbies, Toys, & Games",
            "type":"Retail Goods"
        }
    ],
    "sg:phone":"+1 505 883 6146",
    "sg:postcode":"87110",
    "sg:province":"NM",
    "wof:name":"Fiesta SW",
    "wof:placetype":"venue"
},
  "geometry": {"coordinates":[-106.597078,35.123371],"type":"Point"}
}