{
  "type": "Feature",
  "properties": {
    "addr:full":"721 E Organ Rd Mesilla Park NM 88047",
    "addr:housenumber":"721",
    "addr:postcode":"88047",
    "addr:street":"E Organ Rd",
    "iso:country":"US",
    "sg:address":"721 E Organ Rd",
    "sg:city":"Mesilla Park",
    "sg:classifiers":[
        {
            "category":"Shopping",
            "subcategory":"Computers & Home Electronics",
            "type":"Retail Goods"
        }
    ],
    "sg:phone":"+1 505 525 1302",
    "sg:postcode":"88047",
    "sg:province":"NM",
    "sg:tags":[
        "television",
        "radio"
    ],
    "wof:name":"HMC Electronic",
    "wof:placetype":"venue"
},
  "geometry": {"coordinates":[-106.711643,32.208845],"type":"Point"}
}