{
  "type": "Feature",
  "properties": {
    "iso:country":"US",
    "sg:address":"520 W Cordova Rd",
    "sg:city":"Santa Fe",
    "sg:classifiers":[
        {
            "category":"Shopping",
            "subcategory":"Books",
            "type":"Retail Goods"
        }
    ],
    "sg:phone":"+1 505 982 9371",
    "sg:postcode":"87505",
    "sg:province":"NM",
    "sg:tags":[
        "store"
    ],
    "wof:name":"Books West",
    "wof:placetype":"venue"
},
  "geometry": {"coordinates":[-105.94805,35.672045],"type":"Point"}
}