{
  "type": "Feature",
  "properties": {
    "addr:full":"500 Cruz Alta Rd Taos NM 87571",
    "addr:housenumber":"500",
    "addr:postcode":"87571",
    "addr:street":"Cruz Alta Rd",
    "iso:country":"US",
    "sg:address":"500 Cruz Alta Rd",
    "sg:city":"Taos",
    "sg:classifiers":[
        {
            "category":"Professional",
            "subcategory":"Management & Consulting",
            "type":"Services"
        }
    ],
    "sg:phone":"+1 505 751 0450",
    "sg:postcode":"87571",
    "sg:province":"NM",
    "sg:tags":[
        "business"
    ],
    "wof:name":"Brody & White Consulting Inc",
    "wof:placetype":"venue"
},
  "geometry": {"coordinates":[-105.572412,36.38398],"type":"Point"}
}