{
  "type": "Feature",
  "properties": {
    "iso:country":"US",
    "sg:address":"57 Rd 1305",
    "sg:city":"La Plata",
    "sg:classifiers":[
        {
            "category":"Personal",
            "subcategory":"Beauty Salon",
            "type":"Services"
        }
    ],
    "sg:phone":"+1 505 330 8254",
    "sg:postcode":"87418",
    "sg:province":"NM",
    "sg:tags":[
        "shop"
    ],
    "wof:name":"New Creations Inc",
    "wof:placetype":"venue"
},
  "geometry": {"coordinates":[-108.177217,36.941105],"type":"Point"}
}