{
  "type": "Feature",
  "properties": {
    "iso:country":"US",
    "sg:address":"1216 Mechem Dr",
    "sg:city":"Ruidoso",
    "sg:classifiers":[
        {
            "category":"Government",
            "subcategory":"Office",
            "type":"Public Place"
        }
    ],
    "sg:phone":"+1 505 258 3272",
    "sg:postcode":"88345",
    "sg:province":"NM",
    "sg:tags":[
        "state",
        "program"
    ],
    "sg:website":"www.nmenv.state.nm.us",
    "wof:name":"Environment Dept",
    "wof:placetype":"venue"
},
  "geometry": {"coordinates":[-105.667379,33.36839],"type":"Point"}
}