{
  "type": "Feature",
  "properties": {
    "iso:country":"US",
    "sg:address":"8109 Waverly Dr NW",
    "sg:city":"Albuquerque",
    "sg:classifiers":[
        {
            "category":"Professional",
            "subcategory":"Business Services",
            "type":"Services"
        }
    ],
    "sg:phone":"+1 505 450 7869",
    "sg:postcode":"87120",
    "sg:province":"NM",
    "sg:tags":[
        "life",
        "personal",
        "assistant",
        "environmental",
        "survey",
        "wild"
    ],
    "sg:website":"http://www.envirologicalservices.com",
    "wof:name":"Envirological Services, Inc",
    "wof:placetype":"venue"
},
  "geometry": {"coordinates":[-106.695116,35.174685],"type":"Point"}
}