{
  "type": "Feature",
  "properties": {
    "addr:full":"5720 Industry Way SE Albuquerque NM 87105",
    "addr:housenumber":"5720",
    "addr:postcode":"87105",
    "addr:street":"Industry Way Se",
    "iso:country":"US",
    "sg:address":"5720 Industry Way SE",
    "sg:city":"Albuquerque",
    "sg:classifiers":[
        {
            "category":"Building & Trades",
            "subcategory":"Plumbing",
            "type":"Services"
        }
    ],
    "sg:phone":"+1 505 877 2897",
    "sg:postcode":"87105",
    "sg:province":"NM",
    "sg:tags":[
        "contractor"
    ],
    "wof:name":"A & S Plumbing Inc",
    "wof:placetype":"venue"
},
  "geometry": {"coordinates":[-106.65471700000001,34.997785],"type":"Point"}
}