{
  "type": "Feature",
  "properties": {
    "iso:country":"US",
    "sg:address":"2350 Fox Rd",
    "sg:city":"Santa Fe",
    "sg:classifiers":[
        {
            "category":"Building & Trades",
            "subcategory":"Equipment Rental",
            "type":"Services"
        }
    ],
    "sg:phone":"+1 505 473 1566",
    "sg:postcode":"87507",
    "sg:province":"NM",
    "sg:tags":[
        "audio",
        "leasing"
    ],
    "wof:name":"Serious Grippage and Light Co",
    "wof:placetype":"venue"
},
  "geometry": {"coordinates":[-106.00464100000001,35.64749],"type":"Point"}
}