{
  "type": "Feature",
  "properties": {
    "iso:country":"US",
    "sg:address":"42437 US Hwy 70",
    "sg:city":"Portales",
    "sg:classifiers":[
        {
            "category":"Communications",
            "subcategory":"Radio Station",
            "type":"Services"
        }
    ],
    "sg:phone":"+1 505 359 2100",
    "sg:postcode":"88130",
    "sg:province":"NM",
    "sg:tags":[
        "company",
        "broadcasting"
    ],
    "wof:name":"KSEL",
    "wof:placetype":"venue"
},
  "geometry": {"coordinates":[-103.323275,34.198383],"type":"Point"}
}