{
  "type": "Feature",
  "properties": {
    "iso:country":"US",
    "sg:address":"12129 State Rte 14 Scn",
    "sg:city":"Cedar Crest",
    "sg:classifiers":[
        {
            "category":"Shopping",
            "type":"Retail Goods"
        }
    ],
    "sg:phone":"+1 505 286 7952",
    "sg:postcode":"87008",
    "sg:province":"NM",
    "sg:tags":[
        "ice"
    ],
    "wof:name":"Waterboys II At Cedar Crest",
    "wof:placetype":"venue"
},
  "geometry": {"coordinates":[-106.371403,35.11845],"type":"Point"}
}