{
  "type": "Feature",
  "properties": {
    "addr:full":"9910 Tanoan Dr NE Albuquerque NM 87111",
    "addr:postcode":"9910;87111",
    "addr:street":"Tanoan Dr Ne",
    "iso:country":"US",
    "sg:address":"9910 Tanoan Dr NE",
    "sg:city":"Albuquerque",
    "sg:classifiers":[
        {
            "category":"Professional",
            "subcategory":"Business Services",
            "type":"Services"
        }
    ],
    "sg:phone":"+1 505 821 3096",
    "sg:postcode":"87111",
    "sg:province":"NM",
    "wof:name":"Invention Finders Inc",
    "wof:placetype":"venue"
},
  "geometry": {"coordinates":[-106.530337,35.158242],"type":"Point"}
}