{
  "type": "Feature",
  "properties": {
    "iso:country":"US",
    "sg:address":"9924 Menaul Blvd NE",
    "sg:city":"Albuquerque",
    "sg:classifiers":[
        {
            "category":"Social Services",
            "type":"Services"
        }
    ],
    "sg:phone":"+1 505 332 1816",
    "sg:postcode":"87112",
    "sg:province":"NM",
    "sg:tags":[
        "youth",
        "organization",
        "center"
    ],
    "sg:website":"www.ydinm.org",
    "wof:name":"Youth Development Inc",
    "wof:placetype":"venue"
},
  "geometry": {"coordinates":[-106.52935600000001,35.108889],"type":"Point"}
}