{
  "type": "Feature",
  "properties": {
    "iso:country":"US",
    "sg:address":"101 E Joy Dr",
    "sg:city":"Anthony",
    "sg:classifiers":[
        {
            "category":"Education",
            "subcategory":"Special Training",
            "type":"Public Place"
        }
    ],
    "sg:phone":"+1 505 233 4080",
    "sg:postcode":"88021",
    "sg:province":"NM",
    "sg:tags":[
        "center"
    ],
    "wof:name":"Texas Migrant Council Inc",
    "wof:placetype":"venue"
},
  "geometry": {"coordinates":[-106.62159,32.03936],"type":"Point"}
}