{
  "type": "Feature",
  "properties": {
    "iso:country":"US",
    "sg:address":"1 Stone Ridge Rd",
    "sg:city":"Santa Fe",
    "sg:classifiers":[
        {
            "category":"Professional",
            "subcategory":"Business Services",
            "type":"Services"
        }
    ],
    "sg:phone":"+1 505 577 9597",
    "sg:postcode":"87505",
    "sg:province":"NM",
    "wof:name":"Global Troop Technologies LLC",
    "wof:placetype":"venue"
},
  "geometry": {"coordinates":[-105.894369,35.615726],"type":"Point"}
}