{
  "type": "Feature",
  "properties": {
    "addr:full":"3200 Pan American Fwy Albuquerque NM 87107",
    "addr:housenumber":"3200",
    "addr:postcode":"87107",
    "addr:street":"Pan American Fwy",
    "iso:country":"US",
    "sg:address":"3200 Pan American Fwy",
    "sg:city":"Albuquerque",
    "sg:classifiers":[
        {
            "category":"Freight",
            "type":"Transportation"
        }
    ],
    "sg:phone":"+1 505 884 2115",
    "sg:postcode":"87107",
    "sg:province":"NM",
    "sg:tags":[
        "distance",
        "long",
        "trucking"
    ],
    "wof:name":"White Cloud Co Inc",
    "wof:placetype":"venue"
},
  "geometry": {"coordinates":[-106.623431,35.120416],"type":"Point"}
}