{
  "type": "Feature",
  "properties": {
    "iso:country":"US",
    "sg:address":"532 US Hwy 180 W",
    "sg:city":"Silver City",
    "sg:classifiers":[
        {
            "category":"Government",
            "subcategory":"Office",
            "type":"Public Place"
        }
    ],
    "sg:phone":"+1 505 538 9730",
    "sg:postcode":"88061",
    "sg:province":"NM",
    "sg:tags":[
        "state"
    ],
    "wof:name":"Land Office",
    "wof:placetype":"venue"
},
  "geometry": {"coordinates":[-108.281373,32.780844],"type":"Point"}
}