{
  "type": "Feature",
  "properties": {
    "iso:country":"US",
    "sg:address":"801 E Bender Blvd",
    "sg:city":"Hobbs",
    "sg:classifiers":[
        {
            "category":"Professional",
            "subcategory":"Advertising",
            "type":"Services"
        },
        {
            "category":"Communications",
            "subcategory":"Newspaper",
            "type":"Services"
        },
        {
            "category":"Wholesale",
            "subcategory":"Books, Periodicals, & Newspapers",
            "type":"Manufacturing & Wholesale Goods"
        }
    ],
    "sg:phone":"+1 575 393 5991",
    "sg:postcode":"88240",
    "sg:province":"NM",
    "sg:tags":[
        "print",
        "publisher",
        "book"
    ],
    "wof:name":"Thrifty Nickel",
    "wof:placetype":"venue"
},
  "geometry": {"coordinates":[-103.127617,32.725739],"type":"Point"}
}