{
  "type": "Feature",
  "properties": {
    "addr:full":"2406 Cerrillos Rd Santa Fe NM 87505",
    "addr:housenumber":"2406",
    "addr:postcode":"87505",
    "addr:street":"Cerrillos Rd",
    "iso:country":"US",
    "sg:address":"2406 Cerrillos Rd",
    "sg:city":"Santa Fe",
    "sg:classifiers":[
        {
            "category":"Personal",
            "type":"Services"
        }
    ],
    "sg:phone":"+1 505 438 3788",
    "sg:postcode":"87505",
    "sg:province":"NM",
    "sg:tags":[
        "consultant",
        "program",
        "health",
        "fitness"
    ],
    "wof:name":"Jenny Craig Weight Loss Ctr",
    "wof:placetype":"venue"
},
  "geometry": {"coordinates":[-105.982467,35.659863],"type":"Point"}
}