{
  "type": "Feature",
  "properties": {
    "iso:country":"US",
    "sg:address":"3101 Vassar Dr NE",
    "sg:city":"Albuquerque",
    "sg:classifiers":[
        {
            "category":"Wholesale",
            "subcategory":"Machinery & Supplies",
            "type":"Manufacturing & Wholesale Goods"
        }
    ],
    "sg:phone":"+1 505 883 8500",
    "sg:postcode":"87107",
    "sg:province":"NM",
    "sg:tags":[
        "equipment",
        "irrigation",
        "system"
    ],
    "wof:name":"Sierra Irrigation Inc",
    "wof:placetype":"venue"
},
  "geometry": {"coordinates":[-106.615275,35.114868],"type":"Point"}
}