{
  "type": "Feature",
  "properties": {
    "iso:country":"US",
    "sg:address":"3579 Cerrillos Rd",
    "sg:city":"Santa Fe",
    "sg:classifiers":[
        {
            "category":"Shopping",
            "subcategory":"Computers & Home Electronics",
            "type":"Retail Goods"
        }
    ],
    "sg:phone":"+1 505 471 3116",
    "sg:postcode":"87507",
    "sg:province":"NM",
    "sg:tags":[
        "high",
        "fidelity",
        "stereophonic"
    ],
    "wof:name":"Sonido Accessories Macias",
    "wof:placetype":"venue"
},
  "geometry": {"coordinates":[-106.00428100000001,35.647671],"type":"Point"}
}