{
  "type": "Feature",
  "properties": {
    "iso:country":"US",
    "sg:address":"1631 Eubank Blvd NE",
    "sg:city":"Albuquerque",
    "sg:classifiers":[
        {
            "category":"Professional",
            "subcategory":"Printing & Photocopies",
            "type":"Services"
        }
    ],
    "sg:phone":"+1 505 881 0164",
    "sg:postcode":"87112",
    "sg:province":"NM",
    "sg:tags":[
        "duplicating",
        "copying"
    ],
    "wof:name":"State Wide Printing",
    "wof:placetype":"venue"
},
  "geometry": {"coordinates":[-106.532943,35.100377],"type":"Point"}
}