{
  "type": "Feature",
  "properties": {
    "addr:full":"820 Scenic Dr Alamogordo NM 88310",
    "addr:housenumber":"820",
    "addr:postcode":"88310",
    "addr:street":"Scenic Dr",
    "iso:country":"US",
    "sg:address":"820 Scenic Dr",
    "sg:city":"Alamogordo",
    "sg:classifiers":[
        {
            "category":"Building & Trades",
            "subcategory":"Construction",
            "type":"Services"
        }
    ],
    "sg:phone":"+1 505 437 4790",
    "sg:postcode":"88310",
    "sg:province":"NM",
    "sg:tags":[
        "general",
        "contractor"
    ],
    "wof:name":"Home Service Contractors",
    "wof:placetype":"venue"
},
  "geometry": {"coordinates":[-105.930032,32.895518],"type":"Point"}
}