{
  "type": "Feature",
  "properties": {
    "addr:full":"811 N Prince St Clovis NM 88101",
    "addr:housenumber":"811",
    "addr:postcode":"88101",
    "addr:street":"N Prince St",
    "iso:country":"US",
    "sg:address":"811 N Prince St",
    "sg:city":"Clovis",
    "sg:classifiers":[
        {
            "category":"Retail",
            "subcategory":"Repair Shop",
            "type":"Services"
        }
    ],
    "sg:phone":"+1 505 762 0260",
    "sg:postcode":"88101",
    "sg:province":"NM",
    "sg:tags":[
        "appliance"
    ],
    "wof:name":"AAA Appliance Svc & Parts",
    "wof:placetype":"venue"
},
  "geometry": {"coordinates":[-103.196442,34.406702],"type":"Point"}
}