{
  "type": "Feature",
  "properties": {
    "iso:country":"US",
    "sg:address":"1500 Wyoming Blvd NE",
    "sg:city":"Albuquerque",
    "sg:classifiers":[
        {
            "category":"Shopping",
            "type":"Retail Goods"
        }
    ],
    "sg:phone":"+1 505 298 3323",
    "sg:postcode":"87112",
    "sg:province":"NM",
    "sg:tags":[
        "trophy",
        "medal",
        "award"
    ],
    "wof:name":"Trophy Case",
    "wof:placetype":"venue"
},
  "geometry": {"coordinates":[-106.550748,35.098011],"type":"Point"}
}