{
  "type": "Feature",
  "properties": {
    "iso:country":"US",
    "sg:address":"1608 Blue Quail Ct NE",
    "sg:city":"Rio Rancho",
    "sg:classifiers":[
        {
            "category":"Retail",
            "subcategory":"Auto Repair",
            "type":"Services"
        }
    ],
    "sg:phone":"+1 505 892 7926",
    "sg:postcode":"87144",
    "sg:province":"NM",
    "sg:tags":[
        "body"
    ],
    "wof:name":"Coyote Auto Restoration",
    "wof:placetype":"venue"
},
  "geometry": {"coordinates":[-106.603579,35.282219],"type":"Point"}
}