{
  "type": "Feature",
  "properties": {
    "iso:country":"US",
    "sg:address":"2749 N Florida Ave",
    "sg:city":"Alamogordo",
    "sg:classifiers":[
        {
            "category":"Autos & Motor Vehicles",
            "subcategory":"Auto Supplies",
            "type":"Retail Goods"
        }
    ],
    "sg:phone":"+1 505 439 5467",
    "sg:postcode":"88310",
    "sg:province":"NM",
    "sg:tags":[
        "automobile",
        "accessory"
    ],
    "wof:name":"Playhard Offroad & Accessories",
    "wof:placetype":"venue"
},
  "geometry": {"coordinates":[-105.9524,32.924966],"type":"Point"}
}