{
  "type": "Feature",
  "properties": {
    "addr:full":"7400 Montgomery Blvd NE Ste 10 Albuquerque NM 87109",
    "addr:housenumber":"7400",
    "addr:postcode":"87109",
    "addr:street":"Montgomery Blvd Ne Ste 10",
    "iso:country":"US",
    "sg:address":"7400 Montgomery Blvd NE Ste 10",
    "sg:city":"Albuquerque",
    "sg:classifiers":[
        {
            "category":"Personal",
            "subcategory":"Nail Salon",
            "type":"Services"
        }
    ],
    "sg:phone":"+1 505 881 3320",
    "sg:postcode":"87109",
    "sg:province":"NM",
    "wof:name":"A Touch of Zen",
    "wof:placetype":"venue"
},
  "geometry": {"coordinates":[-106.56385,35.130669],"type":"Point"}
}