{
  "type": "Feature",
  "properties": {
    "iso:country":"US",
    "sg:address":"6805 Ladrillo Pl NE",
    "sg:city":"Albuquerque",
    "sg:classifiers":[
        {
            "category":"Shopping",
            "subcategory":"Crafts & Fabrics",
            "type":"Retail Goods"
        },
        {
            "category":"Professional",
            "subcategory":"Art Services",
            "type":"Services"
        }
    ],
    "sg:phone":"+1 206 239 8470",
    "sg:postcode":"87113",
    "sg:province":"NM",
    "sg:tags":[
        "picture",
        "frame"
    ],
    "wof:name":"New Ocean Companies",
    "wof:placetype":"venue"
},
  "geometry": {"coordinates":[-106.57125000000001,35.176159],"type":"Point"}
}