{
  "type": "Feature",
  "properties": {
    "addr:full":"10331 Cielito Lindo NE Albuquerque NM 87111",
    "addr:housenumber":"10331",
    "addr:postcode":"87111",
    "addr:street":"Cielito",
    "iso:country":"US",
    "sg:address":"10331 Cielito Lindo NE",
    "sg:city":"Albuquerque",
    "sg:classifiers":[
        {
            "category":"Building & Trades",
            "subcategory":"Construction",
            "type":"Services"
        }
    ],
    "sg:phone":"+1 505 294 7245",
    "sg:postcode":"87111",
    "sg:province":"NM",
    "sg:tags":[
        "hanging",
        "contractor"
    ],
    "wof:name":"Dick Harting Painting",
    "wof:placetype":"venue"
},
  "geometry": {"coordinates":[-106.52498,35.127485],"type":"Point"}
}