{
  "type": "Feature",
  "properties": {
    "iso:country":"US",
    "sg:address":"2679 Louisiana Blvd NE",
    "sg:city":"Albuquerque",
    "sg:classifiers":[
        {
            "category":"Restaurant",
            "type":"Food & Drink"
        }
    ],
    "sg:phone":"+1 505 883 1226",
    "sg:postcode":"87110",
    "sg:province":"NM",
    "wof:name":"Cheese & Coffee",
    "wof:placetype":"venue"
},
  "geometry": {"coordinates":[-106.568927,35.109511],"type":"Point"}
}