{
  "type": "Feature",
  "properties": {
    "addr:full":"945 Sagebrush Dr Corrales NM 87048",
    "addr:housenumber":"945",
    "addr:postcode":"87048",
    "addr:street":"Sagebrush Dr",
    "iso:country":"US",
    "sg:address":"945 Sagebrush Dr",
    "sg:city":"Corrales",
    "sg:classifiers":[
        {
            "category":"Shopping",
            "subcategory":"Bicycles & Sporting Goods",
            "type":"Retail Goods"
        }
    ],
    "sg:phone":"+1 505 897 5131",
    "sg:postcode":"87048",
    "sg:province":"NM",
    "sg:tags":[
        "horse",
        "furnishing"
    ],
    "wof:name":"High Desert",
    "wof:placetype":"venue"
},
  "geometry": {"coordinates":[-106.62679300000001,35.245906],"type":"Point"}
}