{
  "type": "Feature",
  "properties": {
    "iso:country":"US",
    "sg:address":"505 E 3rd Ave",
    "sg:city":"Truth Or Cnsqncs",
    "sg:classifiers":[
        {
            "category":"Travel",
            "subcategory":"Campground",
            "type":"Entertainment"
        }
    ],
    "sg:phone":"+1 505 894 2182",
    "sg:postcode":"87901",
    "sg:province":"NM",
    "wof:name":"Cottonwood Rv Park",
    "wof:placetype":"venue"
},
  "geometry": {"coordinates":[-107.24557,33.133078],"type":"Point"}
}