{
  "type": "Feature",
  "properties": {
    "iso:country":"US",
    "sg:address":"1303 Clemente Pl SW",
    "sg:city":"Albuquerque",
    "sg:classifiers":[
        {
            "category":"Building & Trades",
            "subcategory":"Construction",
            "type":"Services"
        }
    ],
    "sg:phone":"+1 505 480 2608",
    "sg:postcode":"87121",
    "sg:province":"NM",
    "sg:tags":[
        "general",
        "contractor"
    ],
    "wof:name":"Ultimate Labor Force",
    "wof:placetype":"venue"
},
  "geometry": {"coordinates":[-106.75151700000001,35.051734],"type":"Point"}
}