{
  "type": "Feature",
  "properties": {
    "iso:country":"US",
    "sg:address":"1323 N Main St",
    "sg:city":"Las Cruces",
    "sg:classifiers":[
        {
            "category":"Shopping",
            "subcategory":"Gifts & Souvenirs",
            "type":"Retail Goods"
        }
    ],
    "sg:phone":"+1 505 527 0209",
    "sg:postcode":"88001",
    "sg:province":"NM",
    "sg:tags":[
        "shop"
    ],
    "wof:name":"Patron's Upolstery & Gift",
    "wof:placetype":"venue"
},
  "geometry": {"coordinates":[-106.78217100000001,32.321956],"type":"Point"}
}