{
  "type": "Feature",
  "properties": {
    "iso:country":"US",
    "sg:address":"1021 Tierra Dr",
    "sg:city":"Santa Fe",
    "sg:classifiers":[
        {
            "category":"Real Estate",
            "subcategory":"Real Estate Agent",
            "type":"Services"
        }
    ],
    "sg:phone":"+1 505 471 5205",
    "sg:postcode":"87505",
    "sg:province":"NM",
    "sg:tags":[
        "appraiser"
    ],
    "wof:name":"Cornell Appraisal",
    "wof:placetype":"venue"
},
  "geometry": {"coordinates":[-105.983115,35.651703],"type":"Point"}
}