{
  "type": "Feature",
  "properties": {
    "iso:country":"US",
    "sg:address":"3804 San Medina Ave",
    "sg:city":"Farmington",
    "sg:classifiers":[
        {
            "category":"Professional",
            "subcategory":"Business Services",
            "type":"Services"
        }
    ],
    "sg:phone":"+1 505 326 5748",
    "sg:postcode":"87401",
    "sg:province":"NM",
    "sg:tags":[
        "lecture",
        "bureau",
        "seminar"
    ],
    "wof:name":"Creative Visions",
    "wof:placetype":"venue"
},
  "geometry": {"coordinates":[-108.19419600000001,36.761873],"type":"Point"}
}