{
  "type": "Feature",
  "properties": {
    "addr:full":"401 S 2nd St Tucumcari NM 88401",
    "addr:housenumber":"401",
    "addr:postcode":"88401",
    "addr:street":"S 2Nd St",
    "iso:country":"US",
    "sg:address":"401 S 2nd St",
    "sg:city":"Tucumcari",
    "sg:classifiers":[
        {
            "category":"Building & Trades",
            "subcategory":"Plumbing",
            "type":"Services"
        }
    ],
    "sg:phone":"+1 505 461 1454",
    "sg:postcode":"88401",
    "sg:province":"NM",
    "sg:tags":[
        "air",
        "heating",
        "conditioning",
        "contractor"
    ],
    "wof:name":"N A Heating and Cooling",
    "wof:placetype":"venue"
},
  "geometry": {"coordinates":[-103.726108,35.175951],"type":"Point"}
}