{
  "type": "Feature",
  "properties": {
    "iso:country":"US",
    "sg:address":"800 W Picacho Ave",
    "sg:city":"Las Cruces",
    "sg:classifiers":[
        {
            "category":"Professional",
            "subcategory":"Computer Services",
            "type":"Services"
        }
    ],
    "sg:phone":"+1 505 541 9766",
    "sg:postcode":"88005",
    "sg:province":"NM",
    "sg:tags":[
        "repair"
    ],
    "wof:name":"PC Fix",
    "wof:placetype":"venue"
},
  "geometry": {"coordinates":[-106.79126,32.314479],"type":"Point"}
}