{
  "type": "Feature",
  "properties": {
    "iso:country":"US",
    "sg:address":"1 Drifter Ct",
    "sg:city":"Los Lunas",
    "sg:classifiers":[
        {
            "category":"Wholesale",
            "subcategory":"Non-durable Goods",
            "type":"Manufacturing & Wholesale Goods"
        }
    ],
    "sg:phone":"+1 505 865 6706",
    "sg:postcode":"87031",
    "sg:province":"NM",
    "wof:name":"Dutton Trading Co",
    "wof:placetype":"venue"
},
  "geometry": {"coordinates":[-106.71259,34.777598],"type":"Point"}
}