{
  "type": "Feature",
  "properties": {
    "addr:full":"816 NW County Rd Hobbs NM 88240",
    "addr:housenumber":"816",
    "addr:postcode":"88240",
    "addr:street":"Nw County Rd",
    "iso:country":"US",
    "sg:address":"816 NW County Rd",
    "sg:city":"Hobbs",
    "sg:classifiers":[
        {
            "category":"Manufacturing",
            "subcategory":"Tools & Machinery",
            "type":"Manufacturing & Wholesale Goods"
        }
    ],
    "sg:phone":"+1 505 393 3913",
    "sg:postcode":"88240",
    "sg:province":"NM",
    "sg:tags":[
        "machine",
        "shop"
    ],
    "wof:name":"Curtis Machines Inc",
    "wof:placetype":"venue"
},
  "geometry": {"coordinates":[-103.175736,32.708184],"type":"Point"}
}