{
  "type": "Feature",
  "properties": {
    "addr:full":"1011 W Picacho Ave Las Cruces NM 88005",
    "addr:housenumber":"1011",
    "addr:postcode":"88005",
    "addr:street":"W Picacho Ave",
    "iso:country":"US",
    "sg:address":"1011 W Picacho Ave",
    "sg:city":"Las Cruces",
    "sg:classifiers":[
        {
            "category":"Personal",
            "subcategory":"Beauty Salon",
            "type":"Services"
        }
    ],
    "sg:phone":"+1 505 541 8746",
    "sg:postcode":"88005",
    "sg:province":"NM",
    "sg:tags":[
        "shop"
    ],
    "wof:name":"Zia Hair Salon",
    "wof:placetype":"venue"
},
  "geometry": {"coordinates":[-106.793404,32.313914],"type":"Point"}
}