{
  "type": "Feature",
  "properties": {
    "addr:full":"4800 Menaul Blvd NE Albuquerque NM 87110",
    "addr:housenumber":"4800",
    "addr:postcode":"87110",
    "addr:street":"Menaul Blvd Ne",
    "iso:country":"US",
    "sg:address":"4800 Menaul Blvd NE",
    "sg:city":"Albuquerque",
    "sg:classifiers":[
        {
            "category":"Restaurant",
            "type":"Food & Drink"
        }
    ],
    "sg:menulink":"http://www.allmenus.com/nm/albuquerque/181792-wendys/menu/",
    "sg:phone":"+1 505 884 4850",
    "sg:postcode":"87110",
    "sg:province":"NM",
    "sg:tags":[
        "burger",
        "american",
        "soup"
    ],
    "wof:name":"Wendy's",
    "wof:placetype":"venue"
},
  "geometry": {"coordinates":[-106.590788,35.109117],"type":"Point"}
}