{
  "type": "Feature",
  "properties": {
    "addr:full":"10705 Cochiti Rd SE Albuquerque NM 87123",
    "addr:housenumber":"10705",
    "addr:postcode":"87123",
    "addr:street":"Cochiti Rd Se",
    "iso:country":"US",
    "sg:address":"10705 Cochiti Rd SE",
    "sg:city":"Albuquerque",
    "sg:classifiers":[
        {
            "category":"Real Estate",
            "subcategory":"Developer",
            "type":"Services"
        }
    ],
    "sg:phone":"+1 505 459 3072",
    "sg:postcode":"87123",
    "sg:province":"NM",
    "sg:tags":[
        "mobile",
        "home"
    ],
    "wof:name":"El Sueno Communities",
    "wof:placetype":"venue"
},
  "geometry": {"coordinates":[-106.52486,35.070155],"type":"Point"}
}