{
  "type": "Feature",
  "properties": {
    "iso:country":"US",
    "sg:address":"1741 Singletary Dr NE",
    "sg:city":"Albuquerque",
    "sg:classifiers":[
        {
            "category":"Professional",
            "subcategory":"Management & Consulting",
            "type":"Services"
        }
    ],
    "sg:phone":"+1 505 275 1811",
    "sg:postcode":"87112",
    "sg:province":"NM",
    "sg:tags":[
        "consultant",
        "business"
    ],
    "wof:name":"Healthcare Management Conslnt",
    "wof:placetype":"venue"
},
  "geometry": {"coordinates":[-106.492312,35.09959],"type":"Point"}
}