{
  "type": "Feature",
  "properties": {
    "iso:country":"US",
    "sg:address":"3023 Cll Princesa Juana",
    "sg:city":"Santa Fe",
    "sg:classifiers":[
        {
            "category":"Building & Trades",
            "subcategory":"Plumbing",
            "type":"Services"
        }
    ],
    "sg:phone":"+1 505 471 4646",
    "sg:postcode":"87507",
    "sg:province":"NM",
    "sg:tags":[
        "contractor"
    ],
    "wof:name":"Blea Enterprises Plbg & Htg",
    "wof:placetype":"venue"
},
  "geometry": {"coordinates":[-105.98863299999999,35.644881],"type":"Point"}
}