{
  "type": "Feature",
  "properties": {
    "iso:country":"US",
    "sg:address":"22 Riverside Rd",
    "sg:city":"Peralta",
    "sg:classifiers":[
        {
            "category":"Manufacturing",
            "subcategory":"Retail Goods",
            "type":"Manufacturing & Wholesale Goods"
        }
    ],
    "sg:phone":"+1 505 869 6193",
    "sg:postcode":"87042",
    "sg:province":"NM",
    "sg:tags":[
        "lead",
        "mfg"
    ],
    "wof:name":"Figleaf Studio",
    "wof:placetype":"venue"
},
  "geometry": {"coordinates":[-106.709051,34.825525],"type":"Point"}
}