{
  "type": "Feature",
  "properties": {
    "addr:full":"8810 Sonya Ave SW Albuquerque NM 87121",
    "addr:housenumber":"8810",
    "addr:postcode":"87121",
    "addr:street":"Sonya Ave Sw",
    "iso:country":"US",
    "sg:address":"8810 Sonya Ave SW",
    "sg:city":"Albuquerque",
    "sg:classifiers":[
        {
            "category":"Recreation",
            "type":"Entertainment"
        }
    ],
    "sg:phone":"+1 505 836 3554",
    "sg:postcode":"87121",
    "sg:province":"NM",
    "sg:tags":[
        "club",
        "baseball"
    ],
    "wof:name":"West Gate Little League",
    "wof:placetype":"venue"
},
  "geometry": {"coordinates":[-106.73289,35.054012],"type":"Point"}
}