{
  "type": "Feature",
  "properties": {
    "iso:country":"US",
    "sg:address":"5150 Ellison St NE",
    "sg:city":"Albuquerque",
    "sg:classifiers":[
        {
            "category":"Autos & Motor Vehicles",
            "subcategory":"Automobile Sales",
            "type":"Retail Goods"
        }
    ],
    "sg:phone":"+1 505 761 1900",
    "sg:postcode":"87109",
    "sg:province":"NM",
    "sg:tags":[
        "car",
        "dealer"
    ],
    "wof:name":"University Volkswagen Mazda",
    "wof:placetype":"venue"
},
  "geometry": {"coordinates":[-106.58990300000001,35.160736],"type":"Point"}
}