{
  "type": "Feature",
  "properties": {
    "iso:country":"US",
    "sg:address":"1421 San Carlos Rd SW",
    "sg:city":"Albuquerque",
    "sg:classifiers":[
        {
            "category":"Professional",
            "type":"Services"
        }
    ],
    "sg:phone":"+1 505 242 5427",
    "sg:postcode":"87104",
    "sg:province":"NM",
    "wof:name":"Edmund Dover",
    "wof:placetype":"venue"
},
  "geometry": {"coordinates":[-106.66506800000001,35.083334],"type":"Point"}
}