{
  "type": "Feature",
  "properties": {
    "iso:country":"US",
    "sg:address":"2050 N Butler Ave",
    "sg:city":"Farmington",
    "sg:classifiers":[
        {
            "category":"Health Services",
            "subcategory":"Doctor",
            "type":"Services"
        }
    ],
    "sg:phone":"+1 505 327 5057",
    "sg:postcode":"87401",
    "sg:province":"NM",
    "wof:name":"Kenneth R Dunston DDS",
    "wof:placetype":"venue"
},
  "geometry": {"coordinates":[-108.197595,36.748876],"type":"Point"}
}