{
  "type": "Feature",
  "properties": {
    "iso:country":"US",
    "sg:address":"309 S 4th St",
    "sg:city":"Logan",
    "sg:classifiers":[
        {
            "category":"Real Estate",
            "subcategory":"Real Estate Operator",
            "type":"Services"
        }
    ],
    "sg:phone":"+1 505 487 2552",
    "sg:postcode":"88426",
    "sg:province":"NM",
    "sg:tags":[
        "mobile",
        "home",
        "community"
    ],
    "wof:name":"Sunshine Mobile Home",
    "wof:placetype":"venue"
},
  "geometry": {"coordinates":[-103.098472,35.604362],"type":"Point"}
}