{
  "type": "Feature",
  "properties": {
    "iso:country":"US",
    "sg:address":"102 Navajo Dr",
    "sg:city":"Santa Fe",
    "sg:classifiers":[
        {
            "category":"Personal",
            "subcategory":"Beauty Salon",
            "type":"Services"
        }
    ],
    "sg:phone":"+1 505 820 2424",
    "sg:postcode":"87505",
    "sg:province":"NM",
    "wof:name":"Olivia's Hair Design",
    "wof:placetype":"venue"
},
  "geometry": {"coordinates":[-105.96629799999999,35.668364],"type":"Point"}
}