{
  "type": "Feature",
  "properties": {
    "iso:country":"US",
    "sg:address":"928 Cerrito Dr",
    "sg:city":"Gallup",
    "sg:classifiers":[
        {
            "category":"Social Services",
            "subcategory":"Child Care",
            "type":"Services"
        }
    ],
    "sg:phone":"+1 505 722 7654",
    "sg:postcode":"87301",
    "sg:province":"NM",
    "sg:tags":[
        "day"
    ],
    "wof:name":"Casias Donna Sue Day Care",
    "wof:placetype":"venue"
},
  "geometry": {"coordinates":[-108.725686,35.520346],"type":"Point"}
}