{
  "type": "Feature",
  "properties": {
    "addr:full":"10521 Espira Ct NW Albuquerque NM 87114",
    "addr:housenumber":"10521",
    "addr:postcode":"87114",
    "addr:street":"Espira Ct Nw",
    "iso:country":"US",
    "sg:address":"10521 Espira Ct NW",
    "sg:city":"Albuquerque",
    "sg:classifiers":[
        {
            "category":"Shopping",
            "subcategory":"Computers & Home Electronics",
            "type":"Retail Goods"
        }
    ],
    "sg:phone":"+1 505 898 6818",
    "sg:postcode":"87114",
    "sg:province":"NM",
    "wof:name":"Antennas West",
    "wof:placetype":"venue"
},
  "geometry": {"coordinates":[-106.673293,35.209587],"type":"Point"}
}