{
  "type": "Feature",
  "properties": {
    "iso:country":"US",
    "sg:address":"4201 Central Ave NW",
    "sg:city":"Albuquerque",
    "sg:classifiers":[
        {
            "category":"Shopping",
            "subcategory":"Discount & Variety Stores",
            "type":"Retail Goods"
        },
        {
            "category":"Shopping",
            "subcategory":"Department Store",
            "type":"Retail Goods"
        }
    ],
    "sg:phone":"+1 505 839 4319",
    "sg:postcode":"87105",
    "sg:province":"NM",
    "wof:name":"Family Dollar Stores",
    "wof:placetype":"venue"
},
  "geometry": {"coordinates":[-106.687566,35.085193],"type":"Point"}
}