{
  "type": "Feature",
  "properties": {
    "addr:full":"1504 Wyoming Blvd NE Albuquerque NM 87112",
    "addr:housenumber":"1504",
    "addr:postcode":"87112",
    "addr:street":"Wyoming;Ne",
    "iso:country":"US",
    "sg:address":"1504 Wyoming Blvd NE",
    "sg:city":"Albuquerque",
    "sg:classifiers":[
        {
            "category":"Shopping",
            "subcategory":"Computers & Home Electronics",
            "type":"Retail Goods"
        }
    ],
    "sg:phone":"+1 505 332 0717",
    "sg:postcode":"87112",
    "sg:province":"NM",
    "sg:tags":[
        "game",
        "video"
    ],
    "wof:name":"Gamers Anonymous",
    "wof:placetype":"venue"
},
  "geometry": {"coordinates":[-106.55067200000001,35.097956],"type":"Point"}
}