{
  "type": "Feature",
  "properties": {
    "iso:country":"US",
    "sg:address":"6436 Glen Oak NE",
    "sg:city":"Albuquerque",
    "sg:classifiers":[
        {
            "category":"Professional",
            "subcategory":"Lawyer & Legal Services",
            "type":"Services"
        }
    ],
    "sg:phone":"+1 505 298 8128",
    "sg:postcode":"87111",
    "sg:province":"NM",
    "sg:tags":[
        "attorney"
    ],
    "wof:name":"Patricia M Monaghan",
    "wof:placetype":"venue"
},
  "geometry": {"coordinates":[-106.511538,35.152612],"type":"Point"}
}