{
  "type": "Feature",
  "properties": {
    "iso:country":"US",
    "sg:address":"17 Rd 4904",
    "sg:city":"Bloomfield",
    "sg:classifiers":[
        {
            "category":"Building & Trades",
            "subcategory":"Plumbing",
            "type":"Services"
        }
    ],
    "sg:phone":"+1 505 632 9494",
    "sg:postcode":"87413",
    "sg:province":"NM",
    "sg:tags":[
        "septic"
    ],
    "wof:name":"Serrano's Inc",
    "wof:placetype":"venue"
},
  "geometry": {"coordinates":[-107.928687,36.710931],"type":"Point"}
}