{
  "type": "Feature",
  "properties": {
    "addr:full":"1300 W Navajo St Farmington NM 87401",
    "addr:housenumber":"1300",
    "addr:postcode":"87401",
    "addr:street":"W Navajo St",
    "iso:country":"US",
    "sg:address":"1300 W Navajo St",
    "sg:city":"Farmington",
    "sg:classifiers":[
        {
            "category":"Airline",
            "type":"Transportation"
        }
    ],
    "sg:phone":"+1 505 326 3216",
    "sg:postcode":"87401",
    "sg:province":"NM",
    "sg:tags":[
        "scheduled",
        "air"
    ],
    "wof:name":"Great Lakes Airlines",
    "wof:placetype":"venue"
},
  "geometry": {"coordinates":[-108.22721799999999,36.738611],"type":"Point"}
}