{
  "type": "Feature",
  "properties": {
    "addr:full":"9217 Orlando Pl NE Albuquerque NM 87111",
    "addr:housenumber":"9217",
    "addr:postcode":"87111",
    "addr:street":"Orlando Pl Ne",
    "iso:country":"US",
    "sg:address":"9217 Orlando Pl NE",
    "sg:city":"Albuquerque",
    "sg:classifiers":[
        {
            "category":"Shopping",
            "subcategory":"Computers & Home Electronics",
            "type":"Retail Goods"
        }
    ],
    "sg:phone":"+1 505 292 3272",
    "sg:postcode":"87111",
    "sg:province":"NM",
    "sg:tags":[
        "software"
    ],
    "wof:name":"MDM Assoc",
    "wof:placetype":"venue"
},
  "geometry": {"coordinates":[-106.539466,35.124974],"type":"Point"}
}