{
  "type": "Feature",
  "properties": {
    "iso:country":"US",
    "sg:address":"529 E Palace Ave",
    "sg:city":"Santa Fe",
    "sg:classifiers":[
        {
            "category":"Travel",
            "subcategory":"Hotels & Motels",
            "type":"Entertainment"
        }
    ],
    "sg:phone":"+1 505 986 1431",
    "sg:postcode":"87501",
    "sg:province":"NM",
    "sg:tags":[
        "breakfast",
        "operation",
        "bed",
        "accommodation"
    ],
    "wof:name":"Alexander's Inn",
    "wof:placetype":"venue"
},
  "geometry": {"coordinates":[-105.927603,35.684872],"type":"Point"}
}