{
  "type": "Feature",
  "properties": {
    "iso:country":"US",
    "sg:address":"200 Aggie Rd",
    "sg:city":"Santa Fe",
    "sg:classifiers":[
        {
            "category":"Building & Trades",
            "subcategory":"Construction",
            "type":"Services"
        }
    ],
    "sg:phone":"+1 505 473 3018",
    "sg:postcode":"87507",
    "sg:province":"NM",
    "sg:tags":[
        "excavating",
        "contractor"
    ],
    "wof:name":"Vigil's Excavation",
    "wof:placetype":"venue"
},
  "geometry": {"coordinates":[-106.011432,35.644985],"type":"Point"}
}