{
  "type": "Feature",
  "properties": {
    "iso:country":"US",
    "sg:address":"930 el Paseo Rd",
    "sg:city":"Las Cruces",
    "sg:classifiers":[
        {
            "category":"Restaurant",
            "type":"Food & Drink"
        }
    ],
    "sg:phone":"+1 505 525 0404",
    "sg:postcode":"88001",
    "sg:province":"NM",
    "wof:name":"E 2 Restaurant",
    "wof:placetype":"venue"
},
  "geometry": {"coordinates":[-106.77678400000001,32.302121],"type":"Point"}
}