{
  "type": "Feature",
  "properties": {
    "iso:country":"US",
    "sg:address":"91 Little Glorieta Ave",
    "sg:city":"Cloudcroft",
    "sg:classifiers":[
        {
            "category":"Food & Beverages",
            "subcategory":"Specialty",
            "type":"Retail Goods"
        }
    ],
    "sg:phone":"+1 505 682 5000",
    "sg:postcode":"88317",
    "sg:province":"NM",
    "sg:tags":[
        "health",
        "diet"
    ],
    "wof:name":"Farside Food & Health",
    "wof:placetype":"venue"
},
  "geometry": {"coordinates":[-105.744356,32.958559],"type":"Point"}
}