{
  "type": "Feature",
  "properties": {
    "addr:full":"637 Pso del Pueblo Norte Taos NM 87571",
    "addr:housenumber":"637",
    "addr:postcode":"87571",
    "addr:street":"Pso Del Pueblo Norte",
    "iso:country":"US",
    "sg:address":"637 Pso del Pueblo Norte",
    "sg:city":"Taos",
    "sg:classifiers":[
        {
            "category":"Organizations",
            "subcategory":"Labor Organization",
            "type":"Services"
        }
    ],
    "sg:phone":"+1 505 751 0129",
    "sg:postcode":"87571",
    "sg:province":"NM",
    "wof:name":"Horse Fly Lc",
    "wof:placetype":"venue"
},
  "geometry": {"coordinates":[-105.579542,36.395111],"type":"Point"}
}