{
  "type": "Feature",
  "properties": {
    "iso:country":"US",
    "sg:address":"7401 E Main St",
    "sg:city":"Farmington",
    "sg:classifiers":[
        {
            "category":"Home & Garden",
            "subcategory":"Garden Supply",
            "type":"Retail Goods"
        }
    ],
    "sg:phone":"+1 505 325 8883",
    "sg:postcode":"87402",
    "sg:province":"NM",
    "sg:tags":[
        "nurseryman"
    ],
    "wof:name":"Evergreen Nurseries",
    "wof:placetype":"venue"
},
  "geometry": {"coordinates":[-108.11046,36.786183],"type":"Point"}
}