{
  "type": "Feature",
  "properties": {
    "addr:full":"2791 State Rte 108 Texico NM 88135",
    "addr:housenumber":"2791",
    "addr:postcode":"88135",
    "addr:street":"State Rte 108",
    "iso:country":"US",
    "sg:address":"2791 State Rte 108",
    "sg:city":"Texico",
    "sg:phone":"+1 505 389 5311",
    "sg:postcode":"88135",
    "sg:province":"NM",
    "sg:tags":[
        "farm",
        "wheat",
        "corn",
        "grain",
        "cash"
    ],
    "wof:name":"Crest Agro Inc",
    "wof:placetype":"venue"
},
  "geometry": {"coordinates":[-103.055955,34.660514],"type":"Point"}
}