{
  "type": "Feature",
  "properties": {
    "iso:country":"US",
    "sg:address":"110 W Clinton St",
    "sg:city":"Hobbs",
    "sg:classifiers":[
        {
            "category":"Building & Trades",
            "subcategory":"Plumbing",
            "type":"Services"
        }
    ],
    "sg:phone":"+1 505 393 4212",
    "sg:postcode":"88240",
    "sg:province":"NM",
    "sg:tags":[
        "plumbing",
        "contractor"
    ],
    "wof:name":"Cottrell Construction & Plbg",
    "wof:placetype":"venue"
},
  "geometry": {"coordinates":[-103.13735699999999,32.707176],"type":"Point"}
}