{
  "type": "Feature",
  "properties": {
    "addr:full":"156 Wyatt Dr Las Cruces NM 88005",
    "addr:housenumber":"156",
    "addr:postcode":"88005",
    "addr:street":"Wyatt Dr",
    "iso:country":"US",
    "sg:address":"156 Wyatt Dr",
    "sg:city":"Las Cruces",
    "sg:classifiers":[
        {
            "category":"Insurance",
            "subcategory":"Insurance Agent",
            "type":"Services"
        }
    ],
    "sg:phone":"+1 505 523 1100",
    "sg:postcode":"88005",
    "sg:province":"NM",
    "wof:name":"Rio Valley Insurance Group",
    "wof:placetype":"venue"
},
  "geometry": {"coordinates":[-106.777992,32.299221],"type":"Point"}
}