{
  "type": "Feature",
  "properties": {
    "addr:full":"4511 N Main St Roswell NM 88201",
    "addr:housenumber":"4511",
    "addr:postcode":"88201",
    "addr:street":"N Main St",
    "iso:country":"US",
    "sg:address":"4511 N Main St",
    "sg:city":"Roswell",
    "sg:classifiers":[
        {
            "category":"Banks & Credit Unions",
            "subcategory":"Bank",
            "type":"Services"
        }
    ],
    "sg:phone":"+1 505 622 3415",
    "sg:postcode":"88201",
    "sg:province":"NM",
    "sg:tags":[
        "loan"
    ],
    "wof:name":"Allied Cash Advance",
    "wof:placetype":"venue"
},
  "geometry": {"coordinates":[-104.52314800000001,33.450258],"type":"Point"}
}