{
  "type": "Feature",
  "properties": {
    "iso:country":"US",
    "sg:address":"307 Pso del Pueblo Sur",
    "sg:city":"Taos",
    "sg:classifiers":[
        {
            "category":"Insurance",
            "subcategory":"Insurance Agent",
            "type":"Services"
        }
    ],
    "sg:phone":"+1 505 758 8106",
    "sg:postcode":"87571",
    "sg:province":"NM",
    "wof:name":"Beaudry Insurance",
    "wof:placetype":"venue"
},
  "geometry": {"coordinates":[-105.574788,36.402447],"type":"Point"}
}