{
  "type": "Feature",
  "properties": {
    "iso:country":"US",
    "sg:address":"7 Hwy 344",
    "sg:city":"Edgewood",
    "sg:classifiers":[
        {
            "category":"Shopping",
            "subcategory":"Gifts & Souvenirs",
            "type":"Retail Goods"
        }
    ],
    "sg:phone":"+1 505 281 3877",
    "sg:postcode":"87015",
    "sg:province":"NM",
    "sg:tags":[
        "shop"
    ],
    "wof:name":"Edgewood Travel Ctr-Diamond",
    "wof:placetype":"venue"
},
  "geometry": {"coordinates":[-106.19145899999999,35.062367],"type":"Point"}
}