{
  "type": "Feature",
  "properties": {
    "iso:country":"US",
    "sg:address":"2402 W Pierce St",
    "sg:city":"Carlsbad",
    "sg:classifiers":[
        {
            "category":"Health Services",
            "subcategory":"Doctor",
            "type":"Services"
        }
    ],
    "sg:phone":"+1 505 887 5325",
    "sg:postcode":"88220",
    "sg:province":"NM",
    "sg:tags":[
        "physician",
        "medical",
        "surgeon"
    ],
    "wof:name":"Lim Michael G MD",
    "wof:placetype":"venue"
},
  "geometry": {"coordinates":[-104.257609,32.440999],"type":"Point"}
}