{
  "type": "Feature",
  "properties": {
    "iso:country":"US",
    "sg:address":"4 Peach Blossom Rd",
    "sg:city":"Los Lunas",
    "sg:classifiers":[
        {
            "category":"Professional",
            "type":"Services"
        }
    ],
    "sg:phone":"+1 505 865 9119",
    "sg:postcode":"87031",
    "sg:province":"NM",
    "sg:tags":[
        "establishment"
    ],
    "wof:name":"Stencil Artisan's League Inc",
    "wof:placetype":"venue"
},
  "geometry": {"coordinates":[-106.711789,34.807127],"type":"Point"}
}