{
  "type": "Feature",
  "properties": {
    "iso:country":"US",
    "sg:address":"534 Ridgecrest Ave",
    "sg:city":"Los Alamos",
    "sg:classifiers":[
        {
            "category":"Professional",
            "subcategory":"Business Services",
            "type":"Services"
        }
    ],
    "sg:phone":"+1 505 667 9333",
    "sg:postcode":"87544",
    "sg:province":"NM",
    "wof:name":"Asm Los Alamos Chapter",
    "wof:placetype":"venue"
},
  "geometry": {"coordinates":[-106.194001,35.820985],"type":"Point"}
}