{
  "type": "Feature",
  "properties": {
    "addr:full":"7611 Menaul Blvd NE Albuquerque NM 87110",
    "addr:housenumber":"7611",
    "addr:postcode":"87110",
    "addr:street":"Menaul Blvd Ne",
    "iso:country":"US",
    "sg:address":"7611 Menaul Blvd NE",
    "sg:city":"Albuquerque",
    "sg:classifiers":[
        {
            "category":"Shopping",
            "subcategory":"Computers & Home Electronics",
            "type":"Retail Goods"
        }
    ],
    "sg:phone":"+1 505 296 6978",
    "sg:postcode":"87110",
    "sg:province":"NM",
    "sg:tags":[
        "equipment",
        "electronic",
        "supply"
    ],
    "wof:name":"Hudson's Home Entertainment",
    "wof:placetype":"venue"
},
  "geometry": {"coordinates":[-106.558814,35.10925],"type":"Point"}
}