{
  "type": "Feature",
  "properties": {
    "addr:full":"171 Pso de Peralta Santa Fe NM 87501",
    "addr:housenumber":"171",
    "addr:postcode":"87501",
    "addr:street":"Pso De Peralta",
    "iso:country":"US",
    "sg:address":"171 Pso de Peralta",
    "sg:city":"Santa Fe",
    "sg:classifiers":[
        {
            "category":"Shopping",
            "subcategory":"Jewelry",
            "type":"Retail Goods"
        }
    ],
    "sg:phone":"+1 505 988 8009",
    "sg:postcode":"87501",
    "sg:province":"NM",
    "wof:name":"Chavez Fine Jewelers",
    "wof:placetype":"venue"
},
  "geometry": {"coordinates":[-105.950816,35.691346],"type":"Point"}
}