{
  "type": "Feature",
  "properties": {
    "iso:country":"US",
    "sg:address":"45 Meadow Dr",
    "sg:city":"Tijeras",
    "sg:classifiers":[
        {
            "category":"Restaurant",
            "type":"Food & Drink"
        }
    ],
    "sg:phone":"+1 505 281 5404",
    "sg:postcode":"87059",
    "sg:province":"NM",
    "sg:tags":[
        "eating"
    ],
    "wof:name":"Have Utensils Will Travel",
    "wof:placetype":"venue"
},
  "geometry": {"coordinates":[-106.303387,35.127686],"type":"Point"}
}