{
  "type": "Feature",
  "properties": {
    "addr:full":"4119 Elaine Dr Los Lunas NM 87031",
    "addr:housenumber":"4119",
    "addr:postcode":"87031",
    "addr:street":"Elaine Dr",
    "iso:country":"US",
    "sg:address":"4119 Elaine Dr",
    "sg:city":"Los Lunas",
    "sg:classifiers":[
        {
            "category":"Airport",
            "type":"Transportation"
        }
    ],
    "sg:phone":"+1 505 565 4081",
    "sg:postcode":"87031",
    "sg:province":"NM",
    "sg:tags":[
        "aircraft",
        "maintenance"
    ],
    "wof:name":"Morgan Aviation Enterprises",
    "wof:placetype":"venue"
},
  "geometry": {"coordinates":[-106.745729,34.755058],"type":"Point"}
}