{
  "type": "Feature",
  "properties": {
    "addr:full":"465 Saint Michaels Dr Santa Fe NM 87505",
    "addr:housenumber":"465",
    "addr:postcode":"87505",
    "addr:street":"Saint Michaels Dr",
    "iso:country":"US",
    "sg:address":"465 Saint Michaels Dr",
    "sg:city":"Santa Fe",
    "sg:classifiers":[
        {
            "category":"Health Services",
            "subcategory":"Doctor",
            "type":"Services"
        }
    ],
    "sg:phone":"+1 505 983 6651",
    "sg:postcode":"87505",
    "sg:province":"NM",
    "sg:tags":[
        "medical"
    ],
    "wof:name":"Cheryl A Ewing MD PC Facs",
    "wof:placetype":"venue"
},
  "geometry": {"coordinates":[-105.951633,35.658724],"type":"Point"}
}