{
  "type": "Feature",
  "properties": {
    "iso:country":"US",
    "sg:address":"3703 W Pine Lodge Rd",
    "sg:city":"Roswell",
    "sg:classifiers":[
        {
            "category":"Professional",
            "subcategory":"Detective & Security Services",
            "type":"Services"
        }
    ],
    "sg:phone":"+1 505 623 1986",
    "sg:postcode":"88201",
    "sg:province":"NM",
    "wof:name":"Maurice Catano",
    "wof:placetype":"venue"
},
  "geometry": {"coordinates":[-104.581962,33.452271],"type":"Point"}
}