{
  "type": "Feature",
  "properties": {
    "addr:full":"114 Kit Carson Rd Taos NM 87571",
    "addr:housenumber":"114",
    "addr:postcode":"87571",
    "addr:street":"Kit Carson Rd",
    "iso:country":"US",
    "sg:address":"114 Kit Carson Rd",
    "sg:city":"Taos",
    "sg:classifiers":[
        {
            "category":"Travel",
            "subcategory":"Hotels & Motels",
            "type":"Entertainment"
        }
    ],
    "sg:phone":"+1 505 758 4874",
    "sg:postcode":"87571",
    "sg:province":"NM",
    "sg:tags":[
        "breakfast",
        "accommodation",
        "bed"
    ],
    "sg:website":"www.ladonaluz.com",
    "wof:name":"LA Dona Luz Inn B & B",
    "wof:placetype":"venue"
},
  "geometry": {"coordinates":[-105.573194,36.407103],"type":"Point"}
}