{
  "type": "Feature",
  "properties": {
    "addr:full":"5011 Montgomery Blvd NE Albuquerque NM 87109",
    "addr:housenumber":"5011",
    "addr:postcode":"87109",
    "addr:street":"Montgomery Blvd Ne",
    "iso:country":"US",
    "sg:address":"5011 Montgomery Blvd NE",
    "sg:city":"Albuquerque",
    "sg:classifiers":[
        {
            "category":"Shopping",
            "subcategory":"Clothing, Apparel, & Fashions",
            "type":"Retail Goods"
        }
    ],
    "sg:phone":"+1 505 883 8179",
    "sg:postcode":"87109",
    "sg:province":"NM",
    "wof:name":"Anchor Blue",
    "wof:placetype":"venue"
},
  "geometry": {"coordinates":[-106.589223,35.13103],"type":"Point"}
}