{
  "type": "Feature",
  "properties": {
    "addr:full":"2115 Menaul Blvd NE Albuquerque NM 87107",
    "addr:housenumber":"2115",
    "addr:postcode":"87107",
    "addr:street":"Menaul Blvd Ne",
    "iso:country":"US",
    "sg:address":"2115 Menaul Blvd NE",
    "sg:city":"Albuquerque",
    "sg:classifiers":[
        {
            "category":"Building & Trades",
            "subcategory":"Construction",
            "type":"Services"
        }
    ],
    "sg:phone":"+1 505 884 1109",
    "sg:postcode":"87107",
    "sg:province":"NM",
    "sg:tags":[
        "restoration",
        "cleaning",
        "patio",
        "deck"
    ],
    "wof:name":"Citation Cleaning Systems",
    "wof:placetype":"venue"
},
  "geometry": {"coordinates":[-106.620574,35.109255],"type":"Point"}
}