{
  "type": "Feature",
  "properties": {
    "iso:country":"US",
    "sg:address":"7608 Old Santa Fe Trl",
    "sg:city":"Santa Fe",
    "sg:classifiers":[
        {
            "category":"Health Services",
            "subcategory":"Clinic",
            "type":"Services"
        }
    ],
    "sg:phone":"+1 505 989 4610",
    "sg:postcode":"87505",
    "sg:province":"NM",
    "sg:tags":[
        "holistic",
        "practitioner"
    ],
    "wof:name":"Light Harmonics Inc",
    "wof:placetype":"venue"
},
  "geometry": {"coordinates":[-105.883174,35.598295],"type":"Point"}
}