{
  "type": "Feature",
  "properties": {
    "addr:full":"5616 Dustin Ct NW Albuquerque NM 87120",
    "addr:housenumber":"5616",
    "addr:postcode":"87120",
    "addr:street":"Dustin Ct Nw",
    "iso:country":"US",
    "sg:address":"5616 Dustin Ct NW",
    "sg:city":"Albuquerque",
    "sg:classifiers":[
        {
            "category":"Communications",
            "subcategory":"Film & Video Production",
            "type":"Services"
        }
    ],
    "sg:phone":"+1 505 307 1321",
    "sg:postcode":"87120",
    "sg:province":"NM",
    "sg:tags":[
        "motion"
    ],
    "wof:name":"Brothers Production",
    "wof:placetype":"venue"
},
  "geometry": {"coordinates":[-106.703232,35.159789],"type":"Point"}
}