{
  "type": "Feature",
  "properties": {
    "iso:country":"US",
    "sg:address":"3484 Lopez Ln",
    "sg:city":"Santa Fe",
    "sg:classifiers":[
        {
            "category":"Retail",
            "subcategory":"Auto Repair",
            "type":"Services"
        }
    ],
    "sg:phone":"+1 505 473 7900",
    "sg:postcode":"87507",
    "sg:province":"NM",
    "sg:tags":[
        "repairing",
        "automobile"
    ],
    "wof:name":"Precise Automotive",
    "wof:placetype":"venue"
},
  "geometry": {"coordinates":[-106.01957,35.64033],"type":"Point"}
}