{
  "type": "Feature",
  "properties": {
    "iso:country":"US",
    "sg:address":"1521 36th Cir SE",
    "sg:city":"Rio Rancho",
    "sg:classifiers":[
        {
            "category":"Building & Trades",
            "subcategory":"Construction",
            "type":"Services"
        }
    ],
    "sg:phone":"+1 505 892 4910",
    "sg:postcode":"87124",
    "sg:province":"NM",
    "sg:tags":[
        "general"
    ],
    "wof:name":"Grand River Construction",
    "wof:placetype":"venue"
},
  "geometry": {"coordinates":[-106.664826,35.230528],"type":"Point"}
}