{
  "type": "Feature",
  "properties": {
    "addr:full":"8010 Menaul Blvd NE Albuquerque NM 87110",
    "addr:housenumber":"8010",
    "addr:postcode":"87110",
    "addr:street":"Menaul Blvd Ne",
    "iso:country":"US",
    "sg:address":"8010 Menaul Blvd NE",
    "sg:city":"Albuquerque",
    "sg:classifiers":[
        {
            "category":"Professional",
            "subcategory":"Lawyer & Legal Services",
            "type":"Services"
        }
    ],
    "sg:phone":"+1 505 299 8999",
    "sg:postcode":"87110",
    "sg:province":"NM",
    "wof:name":"Law Offices",
    "wof:placetype":"venue"
},
  "geometry": {"coordinates":[-106.555654,35.10913],"type":"Point"}
}