{
  "type": "Feature",
  "properties": {
    "iso:country":"US",
    "sg:address":"3542 Zafarano Dr",
    "sg:city":"Santa Fe",
    "sg:classifiers":[
        {
            "category":"Coffee & Tea",
            "type":"Food & Drink"
        }
    ],
    "sg:menulink":"http://www.allmenus.com/nm/santa-fe/124949-starbucks-coffee/menu/",
    "sg:phone":"+1 505 471 9028",
    "sg:postcode":"87507",
    "sg:province":"NM",
    "sg:tags":[
        "american"
    ],
    "wof:name":"Starbucks Coffee",
    "wof:placetype":"venue"
},
  "geometry": {"coordinates":[-106.011702,35.64018],"type":"Point"}
}