{
  "type": "Feature",
  "properties": {
    "addr:full":"1248 Vallecita Dr Santa Fe NM 87501",
    "addr:housenumber":"1248",
    "addr:postcode":"87501",
    "addr:street":"Vallecita Dr",
    "iso:country":"US",
    "sg:address":"1248 Vallecita Dr",
    "sg:city":"Santa Fe",
    "sg:classifiers":[
        {
            "category":"Professional",
            "subcategory":"Management & Consulting",
            "type":"Services"
        }
    ],
    "sg:phone":"+1 505 988 8981",
    "sg:postcode":"87501",
    "sg:province":"NM",
    "sg:tags":[
        "business"
    ],
    "wof:name":"Piedra Consulting Inc",
    "wof:placetype":"venue"
},
  "geometry": {"coordinates":[-105.920867,35.700748],"type":"Point"}
}