{
  "type": "Feature",
  "properties": {
    "iso:country":"US",
    "sg:address":"1711 Elm St",
    "sg:city":"Aztec",
    "sg:classifiers":[
        {
            "category":"Real Estate",
            "subcategory":"Developer",
            "type":"Services"
        }
    ],
    "sg:phone":"+1 505 334 8368",
    "sg:postcode":"87410",
    "sg:province":"NM",
    "sg:tags":[
        "mobile",
        "home"
    ],
    "wof:name":"Cottonwood Mobile Home Park",
    "wof:placetype":"venue"
},
  "geometry": {"coordinates":[-108.01541,36.825935],"type":"Point"}
}