{
  "type": "Feature",
  "properties": {
    "iso:country":"US",
    "sg:address":"2455 Bosque Farms Blvd",
    "sg:city":"Bosque Farms",
    "sg:classifiers":[
        {
            "category":"Real Estate",
            "subcategory":"Real Estate Agent",
            "type":"Services"
        }
    ],
    "sg:phone":"+1 505 869 2631",
    "sg:postcode":"87068",
    "sg:province":"NM",
    "wof:name":"Camco Realty Of Valencia Cnty",
    "wof:placetype":"venue"
},
  "geometry": {"coordinates":[-106.691451,34.839694],"type":"Point"}
}