{
  "type": "Feature",
  "properties": {
    "addr:full":"2401 San Juan Blvd Farmington NM 87401",
    "addr:housenumber":"2401",
    "addr:postcode":"87401",
    "addr:street":"San Juan Blvd",
    "iso:country":"US",
    "sg:address":"2401 San Juan Blvd",
    "sg:city":"Farmington",
    "sg:classifiers":[
        {
            "category":"Building & Trades",
            "subcategory":"Cleaning & Sanitation",
            "type":"Services"
        }
    ],
    "sg:phone":"+1 505 330 7669",
    "sg:postcode":"87401",
    "sg:province":"NM",
    "sg:tags":[
        "janitor"
    ],
    "wof:name":"Crystal Vision Window Cleaning",
    "wof:placetype":"venue"
},
  "geometry": {"coordinates":[-108.174851,36.73814],"type":"Point"}
}