{
  "type": "Feature",
  "properties": {
    "addr:full":"7329 Niquel Pl NW Albuquerque NM 87120",
    "addr:housenumber":"7329",
    "addr:postcode":"87120",
    "addr:street":"Niquel Pl Nw",
    "iso:country":"US",
    "sg:address":"7329 Niquel Pl NW",
    "sg:city":"Albuquerque",
    "sg:classifiers":[
        {
            "category":"Arts & Performance",
            "subcategory":"Theater",
            "type":"Entertainment"
        }
    ],
    "sg:phone":"+1 505 833 1986",
    "sg:postcode":"87120",
    "sg:province":"NM",
    "sg:tags":[
        "live",
        "music"
    ],
    "wof:name":"DJBK Voice Of The Southwest",
    "wof:placetype":"venue"
},
  "geometry": {"coordinates":[-106.719076,35.115943],"type":"Point"}
}