{
  "type": "Feature",
  "properties": {
    "addr:full":"630 Saratoga Dr NE Rio Rancho NM 87124",
    "addr:housenumber":"630",
    "addr:postcode":"87124",
    "addr:street":"Saratoga Dr Ne",
    "iso:country":"US",
    "sg:address":"630 Saratoga Dr NE",
    "sg:city":"Rio Rancho",
    "sg:classifiers":[
        {
            "category":"Retail",
            "subcategory":"Repair Shop",
            "type":"Services"
        }
    ],
    "sg:phone":"+1 505 892 2330",
    "sg:postcode":"87124",
    "sg:province":"NM",
    "sg:tags":[
        "lock",
        "locksmith"
    ],
    "wof:name":"West Mesa Lock & Key Co",
    "wof:placetype":"venue"
},
  "geometry": {"coordinates":[-106.638119,35.26814],"type":"Point"}
}