{
  "type": "Feature",
  "properties": {
    "iso:country":"US",
    "sg:address":"6904 Bogart Ct NW",
    "sg:city":"Albuquerque",
    "sg:classifiers":[
        {
            "category":"Wholesale",
            "subcategory":"Vending Machines",
            "type":"Manufacturing & Wholesale Goods"
        }
    ],
    "sg:phone":"+1 505 899 9233",
    "sg:postcode":"87120",
    "sg:province":"NM",
    "wof:name":"E & W Vending",
    "wof:placetype":"venue"
},
  "geometry": {"coordinates":[-106.71798099999999,35.150217],"type":"Point"}
}