{
  "type": "Feature",
  "properties": {
    "addr:full":"505 National Ave Las Vegas NM 87701",
    "addr:housenumber":"505",
    "addr:postcode":"87701",
    "addr:street":"National Ave",
    "iso:country":"US",
    "sg:address":"505 National Ave",
    "sg:city":"Las Vegas",
    "sg:classifiers":[
        {
            "category":"Professional",
            "subcategory":"Lawyer & Legal Services",
            "type":"Services"
        }
    ],
    "sg:phone":"+1 505 426 8316",
    "sg:postcode":"87701",
    "sg:province":"NM",
    "sg:tags":[
        "attorney"
    ],
    "wof:name":"Baber Silva & Grano Law Firm",
    "wof:placetype":"venue"
},
  "geometry": {"coordinates":[-105.215255,35.597374],"type":"Point"}
}