{
  "type": "Feature",
  "properties": {
    "iso:country":"US",
    "sg:address":"720 W 7th St",
    "sg:city":"Clovis",
    "sg:classifiers":[
        {
            "category":"Fast Food",
            "type":"Food & Drink"
        },
        {
            "category":"Restaurant",
            "type":"Food & Drink"
        },
        {
            "category":"Professional",
            "type":"Services"
        }
    ],
    "sg:phone":"+1 575 763 7995",
    "sg:postcode":"88101",
    "sg:province":"NM",
    "sg:tags":[
        "delivery",
        "take",
        "french"
    ],
    "wof:name":"Foxy Drive-In",
    "wof:placetype":"venue"
},
  "geometry": {"coordinates":[-103.213166,34.404703],"type":"Point"}
}