{
  "type": "Feature",
  "properties": {
    "iso:country":"US",
    "sg:address":"2883 State Hwy 14 N",
    "sg:city":"Cerrillos",
    "sg:classifiers":[
        {
            "category":"Real Estate",
            "subcategory":"Real Estate Agent",
            "type":"Services"
        }
    ],
    "sg:phone":"+1 505 438 7330",
    "sg:postcode":"87010",
    "sg:province":"NM",
    "sg:website":"www.madridnewmexico.com",
    "wof:name":"Sea Properties LTD",
    "wof:placetype":"venue"
},
  "geometry": {"coordinates":[-106.142746,35.41234],"type":"Point"}
}