{
  "type": "Feature",
  "properties": {
    "addr:full":"5404 Overlook Dr NE Albuquerque NM 87111",
    "addr:housenumber":"5404",
    "addr:postcode":"87111",
    "addr:street":"Overlook Dr Ne",
    "iso:country":"US",
    "sg:address":"5404 Overlook Dr NE",
    "sg:city":"Albuquerque",
    "sg:classifiers":[
        {
            "category":"Retail",
            "subcategory":"Portrait Studio",
            "type":"Services"
        }
    ],
    "sg:phone":"+1 505 332 2036",
    "sg:postcode":"87111",
    "sg:province":"NM",
    "sg:tags":[
        "photo"
    ],
    "wof:name":"Art Scene",
    "wof:placetype":"venue"
},
  "geometry": {"coordinates":[-106.514883,35.14288],"type":"Point"}
}