{
  "type": "Feature",
  "properties": {
    "addr:full":"3505 Lafayette Dr NE Albuquerque NM 87107",
    "addr:housenumber":"3505",
    "addr:postcode":"87107",
    "addr:street":"Lafayette Dr Ne",
    "iso:country":"US",
    "sg:address":"3505 Lafayette Dr NE",
    "sg:city":"Albuquerque",
    "sg:classifiers":[
        {
            "category":"Professional",
            "subcategory":"Management & Consulting",
            "type":"Services"
        }
    ],
    "sg:phone":"+1 505 830 9880",
    "sg:postcode":"87107",
    "sg:province":"NM",
    "sg:tags":[
        "business"
    ],
    "wof:name":"Forth First",
    "wof:placetype":"venue"
},
  "geometry": {"coordinates":[-106.60862400000001,35.122825],"type":"Point"}
}