{
  "type": "Feature",
  "properties": {
    "addr:full":"10211 Carraro Ct NW Albuquerque NM 87114",
    "addr:housenumber":"10211",
    "addr:postcode":"87114",
    "addr:street":"Carraro Ct Nw",
    "iso:country":"US",
    "sg:address":"10211 Carraro Ct NW",
    "sg:city":"Albuquerque",
    "sg:classifiers":[
        {
            "category":"Manufacturing",
            "subcategory":"Apparel",
            "type":"Manufacturing & Wholesale Goods"
        }
    ],
    "sg:phone":"+1 505 897 7122",
    "sg:postcode":"87114",
    "sg:province":"NM",
    "sg:tags":[
        "commercial",
        "furnishing"
    ],
    "wof:name":"Diva Design Lines",
    "wof:placetype":"venue"
},
  "geometry": {"coordinates":[-106.690122,35.201425],"type":"Point"}
}