{
  "type": "Feature",
  "properties": {
    "iso:country":"US",
    "sg:address":"705 W Riverside Dr",
    "sg:city":"Carlsbad",
    "sg:classifiers":[
        {
            "category":"Professional",
            "subcategory":"Engineering",
            "type":"Services"
        }
    ],
    "sg:phone":"+1 505 885 6891",
    "sg:postcode":"88220",
    "sg:province":"NM",
    "sg:tags":[
        "engineer"
    ],
    "wof:name":"William N Stanley PE",
    "wof:placetype":"venue"
},
  "geometry": {"coordinates":[-104.236498,32.438219],"type":"Point"}
}