{
  "type": "Feature",
  "properties": {
    "iso:country":"US",
    "sg:address":"211 Sudderth Dr",
    "sg:city":"Ruidoso",
    "sg:classifiers":[
        {
            "category":"Professional",
            "subcategory":"Computer Services",
            "type":"Services"
        }
    ],
    "sg:phone":"+1 505 257 9297",
    "sg:postcode":"88345",
    "sg:province":"NM",
    "sg:tags":[
        "scanning"
    ],
    "wof:name":"Alliance Imaging",
    "wof:placetype":"venue"
},
  "geometry": {"coordinates":[-105.630611,33.323],"type":"Point"}
}