{
  "type": "Feature",
  "properties": {
    "addr:full":"5636 Moon St NE Albuquerque NM 87111",
    "addr:housenumber":"5636",
    "addr:postcode":"87111",
    "addr:street":"Moon St Ne",
    "iso:country":"US",
    "sg:address":"5636 Moon St NE",
    "sg:city":"Albuquerque",
    "sg:classifiers":[
        {
            "category":"Banks & Credit Unions",
            "subcategory":"Bank",
            "type":"Services"
        }
    ],
    "sg:phone":"+1 505 332 7000",
    "sg:postcode":"87111",
    "sg:province":"NM",
    "sg:tags":[
        "loan",
        "real estate"
    ],
    "wof:name":"Homestead Mortgage Co",
    "wof:placetype":"venue"
},
  "geometry": {"coordinates":[-106.543859,35.142749],"type":"Point"}
}