{
  "type": "Feature",
  "properties": {
    "iso:country":"US",
    "sg:address":"405 Trujillo Ln",
    "sg:city":"Taos",
    "sg:classifiers":[
        {
            "category":"Real Estate",
            "subcategory":"Architect",
            "type":"Services"
        }
    ],
    "sg:phone":"+1 505 751 1479",
    "sg:postcode":"87571",
    "sg:province":"NM",
    "wof:name":"DWH Architects Inc",
    "wof:placetype":"venue"
},
  "geometry": {"coordinates":[-105.581518,36.409552],"type":"Point"}
}