{
  "type": "Feature",
  "properties": {
    "iso:country":"US",
    "sg:address":"2774 Agua Fria St",
    "sg:city":"Santa Fe",
    "sg:classifiers":[
        {
            "category":"Building & Trades",
            "subcategory":"Plumbing",
            "type":"Services"
        }
    ],
    "sg:phone":"+1 505 473 2275",
    "sg:postcode":"87507",
    "sg:province":"NM",
    "sg:tags":[
        "plumbing",
        "contractor"
    ],
    "wof:name":"Sierra Mesa Plumbing & Heating",
    "wof:placetype":"venue"
},
  "geometry": {"coordinates":[-105.993341,35.665267],"type":"Point"}
}