{
  "type": "Feature",
  "properties": {
    "iso:country":"US",
    "sg:address":"1839 Wilmoore Dr SE",
    "sg:city":"Albuquerque",
    "sg:classifiers":[
        {
            "category":"Retail",
            "subcategory":"Auto Repair",
            "type":"Services"
        }
    ],
    "sg:phone":"+1 505 217 9579",
    "sg:postcode":"87106",
    "sg:province":"NM",
    "sg:tags":[
        "body",
        "automobile",
        "painting",
        "repairing"
    ],
    "wof:name":"Black Bear Auto Body",
    "wof:placetype":"venue"
},
  "geometry": {"coordinates":[-106.623195,35.061986],"type":"Point"}
}