{
  "type": "Feature",
  "properties": {
    "addr:full":"12008 Gazelle Pl NE Albuquerque NM 87111",
    "addr:housenumber":"12008",
    "addr:postcode":"87111",
    "addr:street":"Gazelle Pl Ne",
    "iso:country":"US",
    "sg:address":"12008 Gazelle Pl NE",
    "sg:city":"Albuquerque",
    "sg:classifiers":[
        {
            "category":"Building & Trades",
            "subcategory":"Construction",
            "type":"Services"
        }
    ],
    "sg:phone":"+1 505 237 2965",
    "sg:postcode":"87111",
    "sg:province":"NM",
    "sg:tags":[
        "house"
    ],
    "wof:name":"Arch Development Corp",
    "wof:placetype":"venue"
},
  "geometry": {"coordinates":[-106.50107300000001,35.152734],"type":"Point"}
}