{
  "type": "Feature",
  "properties": {
    "iso:country":"US",
    "sg:address":"909 S Main St",
    "sg:city":"Belen",
    "sg:classifiers":[
        {
            "category":"Shopping",
            "type":"Retail Goods"
        }
    ],
    "sg:phone":"+1 505 864 8767",
    "sg:postcode":"87002",
    "sg:province":"NM",
    "sg:tags":[
        "candle"
    ],
    "wof:name":"Scents Enchantment",
    "wof:placetype":"venue"
},
  "geometry": {"coordinates":[-106.779518,34.651475],"type":"Point"}
}