{
  "type": "Feature",
  "properties": {
    "iso:country":"US",
    "sg:address":"500 N Guadalupe St",
    "sg:city":"Santa Fe",
    "sg:classifiers":[
        {
            "category":"Health Services",
            "subcategory":"Doctor",
            "type":"Services"
        }
    ],
    "sg:phone":"+1 505 982 2400",
    "sg:postcode":"87501",
    "sg:province":"NM",
    "sg:tags":[
        "osteopathic"
    ],
    "wof:name":"North Texas Headache Clinic",
    "wof:placetype":"venue"
},
  "geometry": {"coordinates":[-105.947821,35.6926],"type":"Point"}
}