{
  "type": "Feature",
  "properties": {
    "addr:full":"3411 Candelaria Rd NE Albuquerque NM 87107",
    "addr:housenumber":"3411",
    "addr:postcode":"87107",
    "addr:street":"Candelaria Rd Ne",
    "iso:country":"US",
    "sg:address":"3411 Candelaria Rd NE",
    "sg:city":"Albuquerque",
    "sg:classifiers":[
        {
            "category":"Organizations",
            "subcategory":"Professional Association",
            "type":"Services"
        }
    ],
    "sg:phone":"+1 505 830 6040",
    "sg:postcode":"87107",
    "sg:province":"NM",
    "sg:website":"www.lls.org",
    "wof:name":"Leukemia & Lymphoma Society",
    "wof:placetype":"venue"
},
  "geometry": {"coordinates":[-106.60536399999999,35.116604],"type":"Point"}
}