{
  "type": "Feature",
  "properties": {
    "iso:country":"US",
    "sg:address":"2742 Manzano St NE",
    "sg:city":"Albuquerque",
    "sg:classifiers":[
        {
            "category":"Freight",
            "type":"Transportation"
        }
    ],
    "sg:phone":"+1 505 888 3065",
    "sg:postcode":"87110",
    "sg:province":"NM",
    "sg:tags":[
        "trucking"
    ],
    "wof:name":"Jerry Kennedy Trucking",
    "wof:placetype":"venue"
},
  "geometry": {"coordinates":[-106.588453,35.112065],"type":"Point"}
}