{
  "type": "Feature",
  "properties": {
    "iso:country":"US",
    "sg:address":"118 Main St",
    "sg:city":"Clayton",
    "sg:classifiers":[
        {
            "category":"Shopping",
            "subcategory":"Stationery & Office Supplies",
            "type":"Retail Goods"
        }
    ],
    "sg:phone":"+1 505 374 8270",
    "sg:postcode":"88415",
    "sg:province":"NM",
    "wof:name":"Clayton Office Supply",
    "wof:placetype":"venue"
},
  "geometry": {"coordinates":[-103.18320199999999,36.452012],"type":"Point"}
}