{
  "type": "Feature",
  "properties": {
    "iso:country":"US",
    "sg:address":"4800 San Mateo Ln NE",
    "sg:city":"Albuquerque",
    "sg:classifiers":[
        {
            "category":"Food & Beverages",
            "subcategory":"Liquor & Beverages",
            "type":"Retail Goods"
        }
    ],
    "sg:phone":"+1 505 881 9353",
    "sg:postcode":"87109",
    "sg:province":"NM",
    "sg:tags":[
        "alcoholic"
    ],
    "wof:name":"ABC Liquor 2 3 4",
    "wof:placetype":"venue"
},
  "geometry": {"coordinates":[-106.585064,35.134647],"type":"Point"}
}