{
  "type": "Feature",
  "properties": {
    "iso:country":"US",
    "sg:address":"2417 San Pedro Dr NE",
    "sg:city":"Albuquerque",
    "sg:classifiers":[
        {
            "category":"Home & Garden",
            "subcategory":"Home Furnishings",
            "type":"Retail Goods"
        }
    ],
    "sg:phone":"+1 505 883 5267",
    "sg:postcode":"87110",
    "sg:province":"NM",
    "sg:tags":[
        "lamp",
        "shades"
    ],
    "wof:name":"Uptown Lamps & Shades LLC",
    "wof:placetype":"venue"
},
  "geometry": {"coordinates":[-106.577653,35.106994],"type":"Point"}
}