{
  "type": "Feature",
  "properties": {
    "iso:country":"US",
    "sg:address":"1817 Central Ave NW",
    "sg:city":"Albuquerque",
    "sg:classifiers":[
        {
            "category":"Health Services",
            "subcategory":"Doctor",
            "type":"Services"
        }
    ],
    "sg:phone":"+1 505 243 7839",
    "sg:postcode":"87104",
    "sg:province":"NM",
    "sg:tags":[
        "osteopathic"
    ],
    "wof:name":"Medical Services Ltd",
    "wof:placetype":"venue"
},
  "geometry": {"coordinates":[-106.66565799999999,35.091028],"type":"Point"}
}