{
  "type": "Feature",
  "properties": {
    "addr:full":"1625 Rio Bravo Blvd SW Albuquerque NM 87105",
    "addr:housenumber":"1625",
    "addr:postcode":"87105",
    "addr:street":"Rio Bravo Blvd Sw",
    "iso:country":"US",
    "sg:address":"1625 Rio Bravo Blvd SW",
    "sg:city":"Albuquerque",
    "sg:classifiers":[
        {
            "category":"Food & Beverages",
            "subcategory":"Specialty",
            "type":"Retail Goods"
        }
    ],
    "sg:phone":"+1 505 452 1820",
    "sg:postcode":"87105",
    "sg:province":"NM",
    "sg:tags":[
        "health",
        "diet"
    ],
    "sg:website":"www.gnc.com",
    "wof:name":"GNC",
    "wof:placetype":"venue"
},
  "geometry": {"coordinates":[-106.68530800000001,35.0268],"type":"Point"}
}