{
  "type": "Feature",
  "properties": {
    "addr:full":"40 Paige Ct Los Alamos NM 87544",
    "addr:housenumber":"40",
    "addr:postcode":"87544",
    "addr:street":"Paige Ct",
    "iso:country":"US",
    "sg:address":"40 Paige Ct",
    "sg:city":"Los Alamos",
    "sg:classifiers":[
        {
            "category":"Education",
            "subcategory":"Dance Studio",
            "type":"Public Place"
        }
    ],
    "sg:phone":"+1 505 672 9035",
    "sg:postcode":"87544",
    "sg:province":"NM",
    "wof:name":"Pajarito Ballet Theatre I",
    "wof:placetype":"venue"
},
  "geometry": {"coordinates":[-106.19256900000001,35.823622],"type":"Point"}
}