{
  "type": "Feature",
  "properties": {
    "addr:full":"2701 Sandigale Dr Las Cruces NM 88011",
    "addr:housenumber":"2701",
    "addr:postcode":"88011",
    "addr:street":"Sandigale Dr",
    "iso:country":"US",
    "sg:address":"2701 Sandigale Dr",
    "sg:city":"Las Cruces",
    "sg:classifiers":[
        {
            "category":"Professional",
            "type":"Services"
        }
    ],
    "sg:phone":"+1 505 532 5037",
    "sg:postcode":"88011",
    "sg:province":"NM",
    "wof:name":"Tomasita Rodriguez",
    "wof:placetype":"venue"
},
  "geometry": {"coordinates":[-106.7405,32.303378],"type":"Point"}
}