{
  "type": "Feature",
  "properties": {
    "addr:full":"1114 S Espanola St Las Cruces NM 88001",
    "addr:housenumber":"1114",
    "addr:postcode":"88001",
    "addr:street":"S Espanola St",
    "iso:country":"US",
    "sg:address":"1114 S Espanola St",
    "sg:city":"Las Cruces",
    "sg:classifiers":[
        {
            "category":"Manufacturing",
            "subcategory":"Printing",
            "type":"Manufacturing & Wholesale Goods"
        }
    ],
    "sg:phone":"+1 505 647 3424",
    "sg:postcode":"88001",
    "sg:province":"NM",
    "sg:tags":[
        "printer"
    ],
    "wof:name":"Print Shop",
    "wof:placetype":"venue"
},
  "geometry": {"coordinates":[-106.761746,32.30094],"type":"Point"}
}