{
  "type": "Feature",
  "properties": {
    "iso:country":"US",
    "sg:address":"205 Central Ave",
    "sg:city":"Tularosa",
    "sg:classifiers":[
        {
            "category":"Utilities",
            "subcategory":"Telephone",
            "type":"Services"
        }
    ],
    "sg:phone":"+1 505 585 2892",
    "sg:postcode":"88352",
    "sg:province":"NM",
    "sg:tags":[
        "company"
    ],
    "wof:name":"National Telephone Co LLC",
    "wof:placetype":"venue"
},
  "geometry": {"coordinates":[-106.017492,33.079172],"type":"Point"}
}