{
  "type": "Feature",
  "properties": {
    "addr:full":"1550 Academy Rd Santa Fe NM 87507",
    "addr:housenumber":"1550",
    "addr:postcode":"87507",
    "addr:street":"Academy Rd",
    "iso:country":"US",
    "sg:address":"1550 Academy Rd",
    "sg:city":"Santa Fe",
    "sg:classifiers":[
        {
            "category":"Freight",
            "type":"Transportation"
        }
    ],
    "sg:phone":"+1 505 438 3115",
    "sg:postcode":"87507",
    "sg:province":"NM",
    "sg:tags":[
        "commercial",
        "storage",
        "special",
        "general"
    ],
    "wof:name":"Academy Storage LLC",
    "wof:placetype":"venue"
},
  "geometry": {"coordinates":[-106.031493,35.637556],"type":"Point"}
}