{
  "type": "Feature",
  "properties": {
    "iso:country":"US",
    "sg:address":"3810 State Hwy 14",
    "sg:city":"Santa Fe",
    "sg:classifiers":[
        {
            "category":"Restaurant",
            "type":"Food & Drink"
        }
    ],
    "sg:phone":"+1 505 471 9194",
    "sg:postcode":"87508",
    "sg:province":"NM",
    "wof:name":"Blue Sky Cafe",
    "wof:placetype":"venue"
},
  "geometry": {"coordinates":[-106.06647,35.48903],"type":"Point"}
}