{
  "type": "Feature",
  "properties": {
    "iso:country":"US",
    "sg:address":"130 Bridge St",
    "sg:city":"Las Vegas",
    "sg:classifiers":[
        {
            "category":"Professional",
            "subcategory":"Employment Agencies",
            "type":"Services"
        }
    ],
    "sg:phone":"+1 505 425 5814",
    "sg:postcode":"87701",
    "sg:province":"NM",
    "sg:tags":[
        "help",
        "contractor"
    ],
    "wof:name":"Personnel Management Svc",
    "wof:placetype":"venue"
},
  "geometry": {"coordinates":[-105.22441000000001,35.59363],"type":"Point"}
}