{
  "type": "Feature",
  "properties": {
    "iso:country":"US",
    "sg:address":"4901 Pan American Pl NE",
    "sg:city":"Albuquerque",
    "sg:classifiers":[
        {
            "category":"Cinema",
            "subcategory":"Movie Theater",
            "type":"Entertainment"
        }
    ],
    "sg:phone":"+1 505 342 2424",
    "sg:postcode":"87109",
    "sg:province":"NM",
    "sg:tags":[
        "motion",
        "picture"
    ],
    "wof:name":"Century 10",
    "wof:placetype":"venue"
},
  "geometry": {"coordinates":[-106.589245,35.157499],"type":"Point"}
}