{
  "type": "Feature",
  "properties": {
    "addr:full":"311 E Palace Ave Santa Fe NM 87501",
    "addr:housenumber":"311",
    "addr:postcode":"87501",
    "addr:street":"E Palace Ave",
    "iso:country":"US",
    "sg:address":"311 E Palace Ave",
    "sg:city":"Santa Fe",
    "sg:classifiers":[
        {
            "category":"Organizations",
            "subcategory":"Religious Organization",
            "type":"Services"
        }
    ],
    "sg:phone":"+1 505 982 4447",
    "sg:postcode":"87501",
    "sg:province":"NM",
    "sg:tags":[
        "church"
    ],
    "wof:name":"Episcopal Church-Holy Faith",
    "wof:placetype":"venue"
},
  "geometry": {"coordinates":[-105.933122,35.686539],"type":"Point"}
}