{
  "type": "Feature",
  "properties": {
    "iso:country":"US",
    "sg:address":"6201 Cochiti Dr NW",
    "sg:city":"Albuquerque",
    "sg:classifiers":[
        {
            "category":"Professional",
            "type":"Services"
        }
    ],
    "sg:phone":"+1 505 890 0671",
    "sg:postcode":"87120",
    "sg:province":"NM",
    "sg:tags":[
        "psychological"
    ],
    "wof:name":"Oklahoma Cunseling Diagnostics",
    "wof:placetype":"venue"
},
  "geometry": {"coordinates":[-106.70736100000001,35.153738],"type":"Point"}
}