{
  "type": "Feature",
  "properties": {
    "iso:country":"US",
    "sg:address":"8501 Volcano Rd NW",
    "sg:city":"Albuquerque",
    "sg:classifiers":[
        {
            "category":"Government",
            "subcategory":"Office",
            "type":"Public Place"
        }
    ],
    "sg:phone":"+1 505 831 6327",
    "sg:postcode":"87121",
    "sg:province":"NM",
    "sg:tags":[
        "transportation"
    ],
    "wof:name":"Transportation New Mexico Dept",
    "wof:placetype":"venue"
},
  "geometry": {"coordinates":[-106.73138299999999,35.076434],"type":"Point"}
}