{
  "type": "Feature",
  "properties": {
    "iso:country":"US",
    "sg:address":"7300 Lomas Blvd NE",
    "sg:city":"Albuquerque",
    "sg:classifiers":[
        {
            "category":"Autos & Motor Vehicles",
            "subcategory":"Automobile Sales",
            "type":"Retail Goods"
        }
    ],
    "sg:phone":"+1 505 268 5900",
    "sg:postcode":"87110",
    "sg:province":"NM",
    "sg:tags":[
        "car",
        "dealer"
    ],
    "wof:name":"Lincoln Mercury Used Car Sales",
    "wof:placetype":"venue"
},
  "geometry": {"coordinates":[-106.56196300000001,35.087263],"type":"Point"}
}