{
  "type": "Feature",
  "properties": {
    "iso:country":"US",
    "sg:address":"2709 Wyoming Blvd NE",
    "sg:city":"Albuquerque",
    "sg:classifiers":[
        {
            "category":"Health Services",
            "subcategory":"Health Practitioner",
            "type":"Services"
        }
    ],
    "sg:phone":"+1 505 294 5486",
    "sg:postcode":"87111",
    "sg:province":"NM",
    "wof:name":"Wu Jane",
    "wof:placetype":"venue"
},
  "geometry": {"coordinates":[-106.550932,35.118233],"type":"Point"}
}