{
  "type": "Feature",
  "properties": {
    "iso:country":"US",
    "sg:address":"1303 N Garden Ave",
    "sg:city":"Roswell",
    "sg:classifiers":[
        {
            "category":"Professional",
            "subcategory":"Business Services",
            "type":"Services"
        }
    ],
    "sg:phone":"+1 505 623 4682",
    "sg:postcode":"88201",
    "sg:province":"NM",
    "sg:tags":[
        "water",
        "treatment"
    ],
    "wof:name":"Water Quality Svc Inc",
    "wof:placetype":"venue"
},
  "geometry": {"coordinates":[-104.51428,33.406561],"type":"Point"}
}