{
  "type": "Feature",
  "properties": {
    "iso:country":"US",
    "sg:address":"1909 Leonard St SE",
    "sg:city":"Rio Rancho",
    "sg:classifiers":[
        {
            "category":"Professional",
            "subcategory":"Computer Services",
            "type":"Services"
        }
    ],
    "sg:phone":"+1 505 896 3359",
    "sg:postcode":"87124",
    "sg:province":"NM",
    "wof:name":"Star Computer Services",
    "wof:placetype":"venue"
},
  "geometry": {"coordinates":[-106.664571,35.223662],"type":"Point"}
}