{
  "type": "Feature",
  "properties": {
    "iso:country":"US",
    "sg:address":"121 Broadway",
    "sg:city":"Mountainair",
    "sg:classifiers":[
        {
            "category":"Government",
            "subcategory":"Office",
            "type":"Public Place"
        }
    ],
    "sg:phone":"+1 505 847 2941",
    "sg:postcode":"87036",
    "sg:province":"NM",
    "wof:name":"Natural Resource Conservation",
    "wof:placetype":"venue"
},
  "geometry": {"coordinates":[-106.241606,34.520284],"type":"Point"}
}