{
  "type": "Feature",
  "properties": {
    "addr:full":"10120 N Hwy 478 Mesquite NM 88048",
    "addr:housenumber":"10120",
    "addr:postcode":"88048",
    "addr:street":"N Hwy 478",
    "iso:country":"US",
    "sg:address":"10120 N Hwy 478",
    "sg:city":"Mesquite",
    "sg:classifiers":[
        {
            "category":"Autos & Motor Vehicles",
            "subcategory":"Auto Supplies",
            "type":"Retail Goods"
        }
    ],
    "sg:phone":"+1 505 233 3077",
    "sg:postcode":"88048",
    "sg:province":"NM",
    "wof:name":"El Valle Auto Parts",
    "wof:placetype":"venue"
},
  "geometry": {"coordinates":[-106.674969,32.130561],"type":"Point"}
}