{
  "type": "Feature",
  "properties": {
    "iso:country":"US",
    "sg:address":"800 E 30th St",
    "sg:city":"Farmington",
    "sg:classifiers":[
        {
            "category":"Insurance",
            "subcategory":"Insurance Agent",
            "type":"Services"
        }
    ],
    "sg:phone":"+1 505 327 0448",
    "sg:postcode":"87401",
    "sg:province":"NM",
    "sg:tags":[
        "real estate"
    ],
    "wof:name":"James & Jacqueline Sheppeck",
    "wof:placetype":"venue"
},
  "geometry": {"coordinates":[-108.194993,36.755396],"type":"Point"}
}