{
  "type": "Feature",
  "properties": {
    "addr:full":"36 Bisbee Ct Santa Fe NM 87508",
    "addr:housenumber":"36",
    "addr:postcode":"87508",
    "addr:street":"Bisbee Ct",
    "iso:country":"US",
    "sg:address":"36 Bisbee Ct",
    "sg:city":"Santa Fe",
    "sg:classifiers":[
        {
            "category":"Wholesale",
            "subcategory":"Home Furnishings",
            "type":"Manufacturing & Wholesale Goods"
        },
        {
            "category":"Manufacturing",
            "subcategory":"Lumber",
            "type":"Manufacturing & Wholesale Goods"
        }
    ],
    "sg:phone":"+1 505 424 1818",
    "sg:postcode":"87508",
    "sg:province":"NM",
    "sg:tags":[
        "hardwood",
        "flooring"
    ],
    "wof:name":"Hamel Hardwoods Ltd",
    "wof:placetype":"venue"
},
  "geometry": {"coordinates":[-106.041003,35.593605],"type":"Point"}
}