{
  "type": "Feature",
  "properties": {
    "addr:full":"183 New Mexico 467 Portales NM 88130",
    "addr:housenumber":"183;467",
    "addr:postcode":"88130",
    "addr:street":"New Mexico",
    "iso:country":"US",
    "sg:address":"183 New Mexico 467",
    "sg:city":"Portales",
    "sg:classifiers":[
        {
            "category":"Home & Garden",
            "subcategory":"Building Materials",
            "type":"Retail Goods"
        }
    ],
    "sg:phone":"+1 505 356 4976",
    "sg:postcode":"88130",
    "sg:province":"NM",
    "sg:tags":[
        "truss"
    ],
    "wof:name":"Nixon Trusses",
    "wof:placetype":"venue"
},
  "geometry": {"coordinates":[-103.317588,34.224983],"type":"Point"}
}