{
  "type": "Feature",
  "properties": {
    "iso:country":"US",
    "sg:address":"1202 E Poplar St",
    "sg:city":"Deming",
    "sg:classifiers":[
        {
            "category":"Manufacturing",
            "subcategory":"Food",
            "type":"Manufacturing & Wholesale Goods"
        }
    ],
    "sg:phone":"+1 505 546 6841",
    "sg:postcode":"88030",
    "sg:province":"NM",
    "sg:tags":[
        "mfg",
        "packaged",
        "direct",
        "sales",
        "preparation",
        "retail"
    ],
    "wof:name":"Amigos Mexican Foods Inc",
    "wof:placetype":"venue"
},
  "geometry": {"coordinates":[-107.74684999999999,32.261359],"type":"Point"}
}