{
  "type": "Feature",
  "properties": {
    "iso:country":"US",
    "sg:address":"6111 Sunray Rd NW",
    "sg:city":"Albuquerque",
    "sg:classifiers":[
        {
            "category":"Shopping",
            "subcategory":"Stationery & Office Supplies",
            "type":"Retail Goods"
        },
        {
            "category":"Manufacturing",
            "subcategory":"Paper Products",
            "type":"Manufacturing & Wholesale Goods"
        }
    ],
    "sg:phone":"+1 505 839 2904",
    "sg:postcode":"87120",
    "sg:province":"NM",
    "sg:tags":[
        "equipment",
        "stationery-wholesale",
        "manufacturer"
    ],
    "wof:name":"Ubiquity Distributing",
    "wof:placetype":"venue"
},
  "geometry": {"coordinates":[-106.708845,35.10896],"type":"Point"}
}