{
  "type": "Feature",
  "properties": {
    "iso:country":"US",
    "sg:address":"4775 Indian School Rd NE",
    "sg:city":"Albuquerque",
    "sg:classifiers":[
        {
            "category":"Health Services",
            "subcategory":"Doctor",
            "type":"Services"
        }
    ],
    "sg:phone":"+1 505 265 0123",
    "sg:postcode":"87110",
    "sg:province":"NM",
    "sg:tags":[
        "dentist"
    ],
    "wof:name":"Daniel L De Fazio DDS",
    "wof:placetype":"venue"
},
  "geometry": {"coordinates":[-106.590411,35.101986],"type":"Point"}
}