{
  "type": "Feature",
  "properties": {
    "addr:full":"1495 Bosque Farms Blvd Bosque Farms NM 87068",
    "addr:housenumber":"1495",
    "addr:postcode":"87068",
    "addr:street":"Bosque Farms Blvd",
    "iso:country":"US",
    "sg:address":"1495 Bosque Farms Blvd",
    "sg:city":"Bosque Farms",
    "sg:classifiers":[
        {
            "category":"Shopping",
            "subcategory":"Clothing, Apparel, & Fashions",
            "type":"Retail Goods"
        }
    ],
    "sg:phone":"+1 505 869 3656",
    "sg:postcode":"87068",
    "sg:province":"NM",
    "wof:name":"Tatiana's Fashions",
    "wof:placetype":"venue"
},
  "geometry": {"coordinates":[-106.69115600000001,34.852861],"type":"Point"}
}