{
  "type": "Feature",
  "properties": {
    "addr:full":"145 Central Park Sq Los Alamos NM 87544",
    "addr:housenumber":"145",
    "addr:postcode":"87544",
    "addr:street":"Central Park Sq",
    "iso:country":"US",
    "sg:address":"145 Central Park Sq",
    "sg:city":"Los Alamos",
    "sg:classifiers":[
        {
            "category":"Communications",
            "subcategory":"Radio Station",
            "type":"Services"
        }
    ],
    "sg:phone":"+1 505 663 1490",
    "sg:postcode":"87544",
    "sg:province":"NM",
    "sg:tags":[
        "company",
        "broadcasting"
    ],
    "wof:name":"KRSN AM 1490",
    "wof:placetype":"venue"
},
  "geometry": {"coordinates":[-106.300484,35.882812],"type":"Point"}
}