{
  "type": "Feature",
  "properties": {
    "addr:full":"216 W Lupita Rd Santa Fe NM 87505",
    "addr:housenumber":"216",
    "addr:postcode":"87505",
    "addr:street":"W Lupita Rd",
    "iso:country":"US",
    "sg:address":"216 W Lupita Rd",
    "sg:city":"Santa Fe",
    "sg:classifiers":[
        {
            "category":"Organizations",
            "subcategory":"Religious Organization",
            "type":"Services"
        }
    ],
    "sg:phone":"+1 505 820 2991",
    "sg:postcode":"87505",
    "sg:province":"NM",
    "sg:tags":[
        "synagogue"
    ],
    "wof:name":"Congregation Beit Tlkva",
    "wof:placetype":"venue"
},
  "geometry": {"coordinates":[-105.94797199999999,35.662359],"type":"Point"}
}