{
  "type": "Feature",
  "properties": {
    "iso:country":"US",
    "sg:address":"1720 Bridge Blvd SW",
    "sg:city":"Albuquerque",
    "sg:classifiers":[
        {
            "category":"Building & Trades",
            "subcategory":"Equipment Rental",
            "type":"Services"
        }
    ],
    "sg:phone":"+1 505 842 0505",
    "sg:postcode":"87105",
    "sg:province":"NM",
    "sg:tags":[
        "yard"
    ],
    "wof:name":"Midtown Rentals",
    "wof:placetype":"venue"
},
  "geometry": {"coordinates":[-106.683032,35.065008],"type":"Point"}
}