{
  "type": "Feature",
  "properties": {
    "iso:country":"US",
    "sg:address":"919 S Main St",
    "sg:city":"Anthony",
    "sg:classifiers":[
        {
            "category":"Retail",
            "subcategory":"Repair Shop",
            "type":"Services"
        }
    ],
    "sg:phone":"+1 915 886 2706",
    "sg:postcode":"79821",
    "sg:province":"NM",
    "sg:tags":[
        "television",
        "radio"
    ],
    "wof:name":"Anthony TV Clinic",
    "wof:placetype":"venue"
},
  "geometry": {"coordinates":[-106.605525,31.991882],"type":"Point"}
}