{
  "type": "Feature",
  "properties": {
    "iso:country":"US",
    "sg:address":"418 Montezuma Ave",
    "sg:city":"Santa Fe",
    "sg:classifiers":[
        {
            "category":"Manufacturing",
            "subcategory":"Building Materials",
            "type":"Manufacturing & Wholesale Goods"
        }
    ],
    "sg:phone":"+1 505 988 3328",
    "sg:postcode":"87501",
    "sg:province":"NM",
    "sg:tags":[
        "door"
    ],
    "wof:name":"Santa Fe Heritage Door Co",
    "wof:placetype":"venue"
},
  "geometry": {"coordinates":[-105.94647999999999,35.685076],"type":"Point"}
}