{
  "type": "Feature",
  "properties": {
    "addr:full":"2359 State Hwy 47 Belen NM 87002",
    "addr:housenumber":"2359",
    "addr:postcode":"87002",
    "addr:street":"State Hwy 47",
    "iso:country":"US",
    "sg:address":"2359 State Hwy 47",
    "sg:city":"Belen",
    "sg:classifiers":[
        {
            "category":"Personal",
            "type":"Services"
        },
        {
            "category":"Health Services",
            "subcategory":"Health Practitioner",
            "type":"Services"
        }
    ],
    "sg:phone":"+1 505 864 0601",
    "sg:postcode":"87002",
    "sg:province":"NM",
    "sg:tags":[
        "therapist",
        "massage"
    ],
    "wof:name":"Healing Touch Lic",
    "wof:placetype":"venue"
},
  "geometry": {"coordinates":[-106.73691700000001,34.658472],"type":"Point"}
}