{
  "type": "Feature",
  "properties": {
    "iso:country":"US",
    "sg:address":"9821 Lona Ln NE",
    "sg:city":"Albuquerque",
    "sg:classifiers":[
        {
            "category":"Building & Trades",
            "subcategory":"Construction",
            "type":"Services"
        }
    ],
    "sg:phone":"+1 505 293 5590",
    "sg:postcode":"87111",
    "sg:province":"NM",
    "sg:tags":[
        "carpentry",
        "contractor"
    ],
    "wof:name":"Mitchcraft Enterprises",
    "wof:placetype":"venue"
},
  "geometry": {"coordinates":[-106.536739,35.140499],"type":"Point"}
}