{
  "type": "Feature",
  "properties": {
    "iso:country":"US",
    "sg:address":"1815 4th St NW",
    "sg:city":"Albuquerque",
    "sg:classifiers":[
        {
            "category":"Retail",
            "subcategory":"Auto Repair",
            "type":"Services"
        }
    ],
    "sg:phone":"+1 505 242 2155",
    "sg:postcode":"87102",
    "sg:province":"NM",
    "sg:tags":[
        "automobile",
        "top",
        "upholstery"
    ],
    "wof:name":"Venegas & Sons Auto Upholstery",
    "wof:placetype":"venue"
},
  "geometry": {"coordinates":[-106.64828799999999,35.102292],"type":"Point"}
}