{
  "type": "Feature",
  "properties": {
    "iso:country":"US",
    "sg:address":"1072 Village Way",
    "sg:city":"Santa Fe",
    "sg:classifiers":[
        {
            "category":"Building & Trades",
            "subcategory":"Construction",
            "type":"Services"
        }
    ],
    "sg:phone":"+1 505 471 3389",
    "sg:postcode":"87507",
    "sg:province":"NM",
    "sg:tags":[
        "contractor"
    ],
    "wof:name":"Tile Works",
    "wof:placetype":"venue"
},
  "geometry": {"coordinates":[-106.04469400000001,35.643324],"type":"Point"}
}