{
  "type": "Feature",
  "properties": {
    "iso:country":"US",
    "sg:address":"510 Alto St",
    "sg:city":"Santa Fe",
    "sg:classifiers":[
        {
            "category":"Recreation",
            "type":"Entertainment"
        }
    ],
    "sg:phone":"+1 505 984 3077",
    "sg:postcode":"87501",
    "sg:province":"NM",
    "wof:name":"Bradbury Reid Ltd",
    "wof:placetype":"venue"
},
  "geometry": {"coordinates":[-105.946782,35.687839],"type":"Point"}
}