{
  "type": "Feature",
  "properties": {
    "iso:country":"US",
    "sg:address":"2101 N Main St",
    "sg:city":"Roswell",
    "sg:classifiers":[
        {
            "category":"Travel",
            "subcategory":"Hotels & Motels",
            "type":"Entertainment"
        }
    ],
    "sg:phone":"+1 505 623 6050",
    "sg:postcode":"88201",
    "sg:province":"NM",
    "sg:tags":[
        "operator",
        "apartment"
    ],
    "wof:name":"Budget Inn North",
    "wof:placetype":"venue"
},
  "geometry": {"coordinates":[-104.523045,33.418641],"type":"Point"}
}