{
  "type": "Feature",
  "properties": {
    "iso:country":"US",
    "sg:address":"6004 Rio Salado Loop NE",
    "sg:city":"Rio Rancho",
    "sg:classifiers":[
        {
            "category":"Building & Trades",
            "subcategory":"Construction",
            "type":"Services"
        }
    ],
    "sg:phone":"+1 505 891 3181",
    "sg:postcode":"87144",
    "sg:province":"NM",
    "sg:tags":[
        "residential"
    ],
    "wof:name":"Iliff Construction Inc",
    "wof:placetype":"venue"
},
  "geometry": {"coordinates":[-106.61597399999999,35.269934],"type":"Point"}
}