{
  "type": "Feature",
  "properties": {
    "iso:country":"US",
    "sg:address":"9469 Coors Blvd NW",
    "sg:city":"Albuquerque",
    "sg:classifiers":[
        {
            "category":"Shopping",
            "type":"Retail Goods"
        }
    ],
    "sg:phone":"+1 505 898 4659",
    "sg:postcode":"87114",
    "sg:province":"NM",
    "sg:tags":[
        "religious",
        "merchandise"
    ],
    "wof:name":"Holy Family Religious Supplies",
    "wof:placetype":"venue"
},
  "geometry": {"coordinates":[-106.661576,35.187144],"type":"Point"}
}