{
  "type": "Feature",
  "properties": {
    "iso:country":"US",
    "sg:address":"1017 E McGaffey St",
    "sg:city":"Roswell",
    "sg:classifiers":[
        {
            "category":"Retail",
            "subcategory":"Repair Shop",
            "type":"Services"
        }
    ],
    "sg:phone":"+1 505 627 9365",
    "sg:postcode":"88203",
    "sg:province":"NM",
    "sg:tags":[
        "welding"
    ],
    "wof:name":"Custom Wrought Iron & Welding",
    "wof:placetype":"venue"
},
  "geometry": {"coordinates":[-104.50859699999999,33.379833],"type":"Point"}
}