{
  "type": "Feature",
  "properties": {
    "addr:full":"2621 Coors Blvd NW Albuquerque NM 87120",
    "addr:housenumber":"2621",
    "addr:postcode":"87120",
    "addr:street":"Coors Blvd Nw",
    "iso:country":"US",
    "sg:address":"2621 Coors Blvd NW",
    "sg:city":"Albuquerque",
    "sg:classifiers":[
        {
            "category":"Utilities",
            "subcategory":"Mobile Phone",
            "type":"Services"
        }
    ],
    "sg:phone":"+1 505 352 5580",
    "sg:postcode":"87120",
    "sg:province":"NM",
    "sg:tags":[
        "telephone",
        "cellular"
    ],
    "wof:name":"Go Wireless",
    "wof:placetype":"venue"
},
  "geometry": {"coordinates":[-106.701821,35.114483],"type":"Point"}
}