{
  "type": "Feature",
  "properties": {
    "iso:country":"US",
    "sg:address":"107 N Riverside Dr",
    "sg:city":"Espanola",
    "sg:classifiers":[
        {
            "category":"Food & Beverages",
            "subcategory":"Bakery",
            "type":"Retail Goods"
        }
    ],
    "sg:phone":"+1 505 753 5461",
    "sg:postcode":"87532",
    "sg:province":"NM",
    "sg:tags":[
        "baker"
    ],
    "wof:name":"Lovin Oven Bakery",
    "wof:placetype":"venue"
},
  "geometry": {"coordinates":[-106.060895,35.987825],"type":"Point"}
}