{
  "type": "Feature",
  "properties": {
    "iso:country":"US",
    "sg:address":"619 N Turner St",
    "sg:city":"Hobbs",
    "sg:classifiers":[
        {
            "category":"Communications",
            "subcategory":"Radio Station",
            "type":"Services"
        }
    ],
    "sg:phone":"+1 505 397 4969",
    "sg:postcode":"88240",
    "sg:province":"NM",
    "sg:tags":[
        "am",
        "fm"
    ],
    "wof:name":"Kykk-Am/Kzor-fm",
    "wof:placetype":"venue"
},
  "geometry": {"coordinates":[-103.136287,32.7069],"type":"Point"}
}