{
  "type": "Feature",
  "properties": {
    "iso:country":"US",
    "sg:address":"8 Homesteads Rd",
    "sg:city":"Placitas",
    "sg:classifiers":[
        {
            "category":"Wholesale",
            "subcategory":"Non-durable Goods",
            "type":"Manufacturing & Wholesale Goods"
        }
    ],
    "sg:phone":"+1 505 867 4657",
    "sg:postcode":"87043",
    "sg:province":"NM",
    "wof:name":"Lynnie Bug Studios",
    "wof:placetype":"venue"
},
  "geometry": {"coordinates":[-106.491342,35.30784],"type":"Point"}
}