{
  "type": "Feature",
  "properties": {
    "addr:full":"2200 Cleopatra Pl NE Albuquerque NM 87112",
    "addr:housenumber":"2200",
    "addr:postcode":"87112",
    "addr:street":"Cleopatra Pl Ne",
    "iso:country":"US",
    "sg:address":"2200 Cleopatra Pl NE",
    "sg:city":"Albuquerque",
    "sg:classifiers":[
        {
            "category":"Education",
            "subcategory":"Special Training",
            "type":"Public Place"
        }
    ],
    "sg:phone":"+1 505 296 4686",
    "sg:postcode":"87112",
    "sg:province":"NM",
    "sg:tags":[
        "piano",
        "lesson",
        "keyboard"
    ],
    "wof:name":"Steven P Oberg",
    "wof:placetype":"venue"
},
  "geometry": {"coordinates":[-106.50752900000001,35.107585],"type":"Point"}
}