{
  "type": "Feature",
  "properties": {
    "iso:country":"US",
    "sg:address":"514 Carmony Rd NE",
    "sg:city":"Albuquerque",
    "sg:classifiers":[
        {
            "category":"Wholesale",
            "subcategory":"Office Equipment",
            "type":"Manufacturing & Wholesale Goods"
        }
    ],
    "sg:phone":"+1 505 345 7575",
    "sg:postcode":"87107",
    "sg:province":"NM",
    "sg:tags":[
        "bank",
        "supply"
    ],
    "sg:website":"www.redhawkindustries.com",
    "wof:name":"Fi Source Inc",
    "wof:placetype":"venue"
},
  "geometry": {"coordinates":[-106.627894,35.128741],"type":"Point"}
}