{
  "type": "Feature",
  "properties": {
    "addr:full":"9301 Candelaria Rd NE Albuquerque NM 87112",
    "addr:housenumber":"9301",
    "addr:postcode":"87112",
    "addr:street":"Candelaria Rd Ne",
    "iso:country":"US",
    "sg:address":"9301 Candelaria Rd NE",
    "sg:city":"Albuquerque",
    "sg:classifiers":[
        {
            "category":"Personal",
            "subcategory":"Beauty Salon",
            "type":"Services"
        }
    ],
    "sg:phone":"+1 505 323 6883",
    "sg:postcode":"87112",
    "sg:province":"NM",
    "wof:name":"C'Elaine Hair Images",
    "wof:placetype":"venue"
},
  "geometry": {"coordinates":[-106.538634,35.116332],"type":"Point"}
}