{
  "type": "Feature",
  "properties": {
    "iso:country":"US",
    "sg:address":"19650 State Hwy 314",
    "sg:city":"Belen",
    "sg:classifiers":[
        {
            "category":"Wholesale",
            "subcategory":"Machinery & Supplies",
            "type":"Manufacturing & Wholesale Goods"
        }
    ],
    "sg:phone":"+1 505 861 1500",
    "sg:postcode":"87002",
    "sg:province":"NM",
    "sg:tags":[
        "tractor"
    ],
    "wof:name":"New Mexico Tractor Sales",
    "wof:placetype":"venue"
},
  "geometry": {"coordinates":[-106.757441,34.719589],"type":"Point"}
}