{
  "type": "Feature",
  "properties": {
    "addr:full":"109 Maple St Clovis NM 88101",
    "addr:housenumber":"109",
    "addr:postcode":"88101",
    "addr:street":"Maple St",
    "iso:country":"US",
    "sg:address":"109 Maple St",
    "sg:city":"Clovis",
    "sg:classifiers":[
        {
            "category":"Autos & Motor Vehicles",
            "subcategory":"Automobile Sales",
            "type":"Retail Goods"
        }
    ],
    "sg:phone":"+1 505 762 3836",
    "sg:postcode":"88101",
    "sg:province":"NM",
    "sg:tags":[
        "used"
    ],
    "wof:name":"Auto World",
    "wof:placetype":"venue"
},
  "geometry": {"coordinates":[-103.19263599999999,34.399608],"type":"Point"}
}