{
  "type": "Feature",
  "properties": {
    "iso:country":"US",
    "sg:address":"2007 Turrentine Dr",
    "sg:city":"Las Cruces",
    "sg:classifiers":[
        {
            "category":"Professional",
            "subcategory":"Management & Consulting",
            "type":"Services"
        }
    ],
    "sg:phone":"+1 505 523 1571",
    "sg:postcode":"88005",
    "sg:province":"NM",
    "sg:tags":[
        "business"
    ],
    "wof:name":"Bjp Consulting Inc",
    "wof:placetype":"venue"
},
  "geometry": {"coordinates":[-106.766448,32.285338],"type":"Point"}
}