{
  "type": "Feature",
  "properties": {
    "iso:country":"US",
    "sg:address":"68 Anaya Rd",
    "sg:city":"Tijeras",
    "sg:classifiers":[
        {
            "category":"Building & Trades",
            "subcategory":"Construction",
            "type":"Services"
        }
    ],
    "sg:phone":"+1 505 286 3570",
    "sg:postcode":"87059",
    "sg:province":"NM",
    "sg:tags":[
        "excavating",
        "contractor"
    ],
    "wof:name":"Bayless Trucking & Excavating",
    "wof:placetype":"venue"
},
  "geometry": {"coordinates":[-106.296098,34.974704],"type":"Point"}
}