{
  "type": "Feature",
  "properties": {
    "iso:country":"US",
    "sg:address":"1135 Emerson St",
    "sg:city":"Raton",
    "sg:classifiers":[
        {
            "category":"Retail",
            "subcategory":"Auto Rental",
            "type":"Services"
        }
    ],
    "sg:phone":"+1 505 445 3314",
    "sg:postcode":"87740",
    "sg:province":"NM",
    "sg:tags":[
        "truck",
        "rent",
        "lease"
    ],
    "wof:name":"U-Haul",
    "wof:placetype":"venue"
},
  "geometry": {"coordinates":[-104.437487,36.88636],"type":"Point"}
}