{
  "type": "Feature",
  "properties": {
    "iso:country":"US",
    "sg:address":"1 Farrell St",
    "sg:city":"Ranchos De Taos",
    "sg:classifiers":[
        {
            "category":"Government",
            "subcategory":"Office",
            "type":"Public Place"
        }
    ],
    "sg:phone":"+1 505 751 9375",
    "sg:postcode":"87571",
    "sg:province":"NM",
    "sg:tags":[
        "state",
        "inspection"
    ],
    "wof:name":"Electrical Inspector",
    "wof:placetype":"venue"
},
  "geometry": {"coordinates":[-105.580264,36.28183],"type":"Point"}
}