{
  "type": "Feature",
  "properties": {
    "iso:country":"US",
    "sg:address":"401 Roma Ave NW",
    "sg:city":"Albuquerque",
    "sg:classifiers":[
        {
            "category":"Government",
            "subcategory":"Office",
            "type":"Public Place"
        }
    ],
    "sg:phone":"+1 505 841 8263",
    "sg:postcode":"87102",
    "sg:province":"NM",
    "wof:name":"Honorable Denise B Sheperd",
    "wof:placetype":"venue"
},
  "geometry": {"coordinates":[-106.651961,35.089315],"type":"Point"}
}