{
  "type": "Feature",
  "properties": {
    "iso:country":"US",
    "sg:address":"319 Sudderth Dr",
    "sg:city":"Ruidoso",
    "sg:classifiers":[
        {
            "category":"Wholesale",
            "subcategory":"Groceries",
            "type":"Manufacturing & Wholesale Goods"
        }
    ],
    "sg:phone":"+1 505 257 5040",
    "sg:postcode":"88345",
    "sg:province":"NM",
    "sg:tags":[
        "food",
        "product",
        "mexican"
    ],
    "wof:name":"Ole Taco",
    "wof:placetype":"venue"
},
  "geometry": {"coordinates":[-105.636948,33.322635],"type":"Point"}
}