{
  "type": "Feature",
  "properties": {
    "iso:country":"US",
    "sg:address":"3321 James Ave",
    "sg:city":"Santa Fe",
    "sg:classifiers":[
        {
            "category":"Shopping",
            "subcategory":"Beauty & Cosmetics",
            "type":"Retail Goods"
        }
    ],
    "sg:phone":"+1 505 471 1302",
    "sg:postcode":"87507",
    "sg:province":"NM",
    "sg:tags":[
        "merchandise"
    ],
    "wof:name":"Mary Kay Comestics",
    "wof:placetype":"venue"
},
  "geometry": {"coordinates":[-106.00129,35.646807],"type":"Point"}
}