{
  "type": "Feature",
  "properties": {
    "iso:country":"US",
    "sg:address":"1401 Pso del Pueblo Sur",
    "sg:city":"Taos",
    "sg:classifiers":[
        {
            "category":"Restaurant",
            "type":"Food & Drink"
        }
    ],
    "sg:phone":"+1 505 758 8777",
    "sg:postcode":"87571",
    "sg:province":"NM",
    "wof:name":"Tequilas",
    "wof:placetype":"venue"
},
  "geometry": {"coordinates":[-105.595534,36.371288],"type":"Point"}
}