{
  "type": "Feature",
  "properties": {
    "iso:country":"US",
    "sg:address":"104 Calhoun St",
    "sg:city":"Clovis",
    "sg:classifiers":[
        {
            "category":"Organizations",
            "subcategory":"Religious Organization",
            "type":"Services"
        }
    ],
    "sg:phone":"+1 505 762 6717",
    "sg:postcode":"88101",
    "sg:province":"NM",
    "wof:name":"Jerusalem Dist Missionary",
    "wof:placetype":"venue"
},
  "geometry": {"coordinates":[-103.21301800000001,34.39967],"type":"Point"}
}