{
  "type": "Feature",
  "properties": {
    "iso:country":"US",
    "sg:address":"850 W Florida St",
    "sg:city":"Deming",
    "sg:classifiers":[
        {
            "category":"Health Services",
            "subcategory":"Doctor",
            "type":"Services"
        }
    ],
    "sg:phone":"+1 505 546 6548",
    "sg:postcode":"88030",
    "sg:province":"NM",
    "sg:tags":[
        "physician",
        "practice",
        "general",
        "obstetrician"
    ],
    "wof:name":"Florida Medical Center",
    "wof:placetype":"venue"
},
  "geometry": {"coordinates":[-107.766836,32.254034],"type":"Point"}
}