{
  "type": "Feature",
  "properties": {
    "addr:full":"35 W Orchard Park Rd Dexter NM 88230",
    "addr:housenumber":"35",
    "addr:postcode":"88230",
    "addr:street":"W Orchard Park Rd",
    "iso:country":"US",
    "sg:address":"35 W Orchard Park Rd",
    "sg:city":"Dexter",
    "sg:classifiers":[
        {
            "category":"Professional",
            "subcategory":"Management & Consulting",
            "type":"Services"
        }
    ],
    "sg:phone":"+1 505 347 2924",
    "sg:postcode":"88230",
    "sg:province":"NM",
    "wof:name":"J & J Pressure Wash",
    "wof:placetype":"venue"
},
  "geometry": {"coordinates":[-104.46833599999999,33.255882],"type":"Point"}
}