{
  "type": "Feature",
  "properties": {
    "iso:country":"US",
    "sg:address":"700 1st St",
    "sg:city":"Alamogordo",
    "sg:classifiers":[
        {
            "category":"Shopping",
            "subcategory":"Clothing, Apparel, & Fashions",
            "type":"Retail Goods"
        }
    ],
    "sg:phone":"+1 505 437 4230",
    "sg:postcode":"88310",
    "sg:province":"NM",
    "sg:tags":[
        "furnishing"
    ],
    "wof:name":"J & C Men's Apparel",
    "wof:placetype":"venue"
},
  "geometry": {"coordinates":[-105.95909,32.89015],"type":"Point"}
}