{
  "type": "Feature",
  "properties": {
    "iso:country":"US",
    "sg:address":"218 S Ave B",
    "sg:city":"Portales",
    "sg:classifiers":[
        {
            "category":"Education",
            "subcategory":"Library",
            "type":"Public Place"
        }
    ],
    "sg:phone":"+1 505 356 3940",
    "sg:postcode":"88130",
    "sg:province":"NM",
    "wof:name":"Portales Public Library",
    "wof:placetype":"venue"
},
  "geometry": {"coordinates":[-103.340207,34.18626],"type":"Point"}
}