{
  "type": "Feature",
  "properties": {
    "iso:country":"US",
    "sg:address":"2904 W 2nd St",
    "sg:city":"Roswell",
    "sg:classifiers":[
        {
            "category":"Professional",
            "subcategory":"Engineering",
            "type":"Services"
        }
    ],
    "sg:phone":"+1 505 624 2420",
    "sg:postcode":"88201",
    "sg:province":"NM",
    "sg:tags":[
        "engineer"
    ],
    "wof:name":"Atkins Engineering Associates",
    "wof:placetype":"venue"
},
  "geometry": {"coordinates":[-104.56552000000001,33.394122],"type":"Point"}
}