{
  "type": "Feature",
  "properties": {
    "iso:country":"US",
    "sg:address":"2503 Cll de Rincon Bonito",
    "sg:city":"Santa Fe",
    "sg:classifiers":[
        {
            "category":"Recreation",
            "type":"Entertainment"
        }
    ],
    "sg:phone":"+1 505 438 8905",
    "sg:postcode":"87505",
    "sg:province":"NM",
    "wof:name":"Patricia Flasch & Assoc",
    "wof:placetype":"venue"
},
  "geometry": {"coordinates":[-105.959542,35.643225],"type":"Point"}
}