{
  "type": "Feature",
  "properties": {
    "iso:country":"US",
    "sg:address":"826 Gibson Blvd SE",
    "sg:city":"Albuquerque",
    "sg:classifiers":[
        {
            "category":"Manufacturing",
            "subcategory":"Metals",
            "type":"Manufacturing & Wholesale Goods"
        }
    ],
    "sg:phone":"+1 505 720 3050",
    "sg:postcode":"87102",
    "sg:province":"NM",
    "sg:tags":[
        "ornamental",
        "work"
    ],
    "wof:name":"David's Wrought Iron Mfg",
    "wof:placetype":"venue"
},
  "geometry": {"coordinates":[-106.64108400000001,35.060354],"type":"Point"}
}