{
  "type": "Feature",
  "properties": {
    "iso:country":"US",
    "sg:address":"7200 Montgomery Blvd NE",
    "sg:city":"Albuquerque",
    "sg:classifiers":[
        {
            "category":"Wholesale",
            "subcategory":"Medical Equipment & Supplies",
            "type":"Manufacturing & Wholesale Goods"
        }
    ],
    "sg:phone":"+1 505 797 1321",
    "sg:postcode":"87109",
    "sg:province":"NM",
    "sg:tags":[
        "dental"
    ],
    "wof:name":"Hayes Handpiece",
    "wof:placetype":"venue"
},
  "geometry": {"coordinates":[-106.563849,35.130743],"type":"Point"}
}