{
  "type": "Feature",
  "properties": {
    "iso:country":"US",
    "sg:address":"105 W 3rd St",
    "sg:city":"Roswell",
    "sg:classifiers":[
        {
            "category":"Mining & Drilling",
            "type":"Manufacturing & Wholesale Goods"
        }
    ],
    "sg:phone":"+1 505 622 3200",
    "sg:postcode":"88201",
    "sg:province":"NM",
    "sg:tags":[
        "oil",
        "gas",
        "producer"
    ],
    "wof:name":"Mc Clellan Oil Corp",
    "wof:placetype":"venue"
},
  "geometry": {"coordinates":[-104.52434100000001,33.395452],"type":"Point"}
}