{
  "type": "Feature",
  "properties": {
    "iso:country":"US",
    "sg:address":"1801 Espinacitas St",
    "sg:city":"Santa Fe",
    "sg:classifiers":[
        {
            "category":"Shopping",
            "subcategory":"Clothing, Apparel, & Fashions",
            "type":"Retail Goods"
        }
    ],
    "sg:phone":"+1 505 820 1530",
    "sg:postcode":"87505",
    "sg:province":"NM",
    "sg:tags":[
        "item",
        "boutique"
    ],
    "wof:name":"Biancas Boutique",
    "wof:placetype":"venue"
},
  "geometry": {"coordinates":[-105.96745799999999,35.661508],"type":"Point"}
}