{
  "type": "Feature",
  "properties": {
    "addr:full":"3214 Los Arboles Ave NE Albuquerque NM 87107",
    "addr:housenumber":"3214",
    "addr:postcode":"87107",
    "addr:street":"Los Arboles Ave Ne",
    "iso:country":"US",
    "sg:address":"3214 Los Arboles Ave NE",
    "sg:city":"Albuquerque",
    "sg:classifiers":[
        {
            "category":"Professional",
            "type":"Services"
        }
    ],
    "sg:phone":"+1 505 884 4642",
    "sg:postcode":"87107",
    "sg:province":"NM",
    "sg:tags":[
        "establishment"
    ],
    "wof:name":"Sanicare",
    "wof:placetype":"venue"
},
  "geometry": {"coordinates":[-106.608181,35.114026],"type":"Point"}
}