{
  "type": "Feature",
  "properties": {
    "addr:full":"727 W Animas St Farmington NM 87401",
    "addr:housenumber":"727",
    "addr:postcode":"87401",
    "addr:street":"W Animas St",
    "iso:country":"US",
    "sg:address":"727 W Animas St",
    "sg:city":"Farmington",
    "sg:classifiers":[
        {
            "category":"Health Services",
            "subcategory":"Health Practitioner",
            "type":"Services"
        }
    ],
    "sg:phone":"+1 505 564 8563",
    "sg:postcode":"87401",
    "sg:province":"NM",
    "sg:tags":[
        "therapist",
        "physical"
    ],
    "wof:name":"San Juan Regional Medical Ctr",
    "wof:placetype":"venue"
},
  "geometry": {"coordinates":[-108.216221,36.727026],"type":"Point"}
}