{
  "type": "Feature",
  "properties": {
    "iso:country":"US",
    "sg:address":"1612 Georgia St NE",
    "sg:city":"Albuquerque",
    "sg:classifiers":[
        {
            "category":"Building & Trades",
            "subcategory":"Construction",
            "type":"Services"
        }
    ],
    "sg:phone":"+1 505 265 4510",
    "sg:postcode":"87110",
    "sg:province":"NM",
    "sg:tags":[
        "general",
        "contractor"
    ],
    "wof:name":"Reardon Homes Inc",
    "wof:placetype":"venue"
},
  "geometry": {"coordinates":[-106.571893,35.094479],"type":"Point"}
}