{
  "type": "Feature",
  "properties": {
    "addr:full":"8801 Horizon Blvd Albuquerque NM 87113",
    "addr:housenumber":"8801",
    "addr:postcode":"87113",
    "addr:street":"Horizon Blvd",
    "iso:country":"US",
    "sg:address":"8801 Horizon Blvd",
    "sg:city":"Albuquerque",
    "sg:classifiers":[
        {
            "category":"Professional",
            "subcategory":"Accounting & Tax Preparation",
            "type":"Services"
        }
    ],
    "sg:phone":"+1 505 338 1500",
    "sg:postcode":"87113",
    "sg:province":"NM",
    "sg:tags":[
        "firm",
        "public",
        "certified"
    ],
    "sg:website":"www.pulakos.com",
    "wof:name":"Pulakos & Alongi LTD",
    "wof:placetype":"venue"
},
  "geometry": {"coordinates":[-106.600939,35.184565],"type":"Point"}
}