{
  "type": "Feature",
  "properties": {
    "iso:country":"US",
    "sg:address":"401 N 26th St",
    "sg:city":"Artesia",
    "sg:classifiers":[
        {
            "category":"Personal",
            "type":"Services"
        }
    ],
    "sg:phone":"+1 505 746 4334",
    "sg:postcode":"88210",
    "sg:province":"NM",
    "sg:tags":[
        "therapist",
        "massage"
    ],
    "wof:name":"Pecos Valley Pro Massage & Spa",
    "wof:placetype":"venue"
},
  "geometry": {"coordinates":[-104.429875,32.897189],"type":"Point"}
}