{
  "type": "Feature",
  "properties": {
    "iso:country":"US",
    "sg:address":"2331 Sudderth Dr",
    "sg:city":"Ruidoso",
    "sg:classifiers":[
        {
            "category":"Restaurant",
            "type":"Food & Drink"
        }
    ],
    "sg:phone":"+1 505 257 6666",
    "sg:postcode":"88345",
    "sg:province":"NM",
    "sg:tags":[
        "eating"
    ],
    "wof:name":"Pasta Cafe Italian Bistro",
    "wof:placetype":"venue"
},
  "geometry": {"coordinates":[-105.66948600000001,33.331257],"type":"Point"}
}