{
  "type": "Feature",
  "properties": {
    "iso:country":"US",
    "sg:address":"3 Juan de Dios Rd",
    "sg:city":"Arroyo Seco",
    "sg:classifiers":[
        {
            "category":"Organizations",
            "subcategory":"Non-profit Organization",
            "type":"Services"
        }
    ],
    "sg:phone":"+1 505 776 8309",
    "sg:postcode":"87514",
    "sg:province":"NM",
    "wof:name":"Taos Ice Tigers High School",
    "wof:placetype":"venue"
},
  "geometry": {"coordinates":[-105.55323,36.51974],"type":"Point"}
}