{
  "type": "Feature",
  "properties": {
    "iso:country":"US",
    "sg:address":"104 State Hwy 371",
    "sg:city":"Thoreau",
    "sg:classifiers":[
        {
            "category":"Cinema",
            "subcategory":"Movie Rental",
            "type":"Entertainment"
        }
    ],
    "sg:phone":"+1 505 862 7006",
    "sg:postcode":"87323",
    "sg:province":"NM",
    "sg:tags":[
        "leasing",
        "video",
        "disc",
        "tape"
    ],
    "wof:name":"Gabe's Movie Time",
    "wof:placetype":"venue"
},
  "geometry": {"coordinates":[-108.209676,35.407834],"type":"Point"}
}