{
  "type": "Feature",
  "properties": {
    "iso:country":"US",
    "sg:address":"509 Apache Ct",
    "sg:city":"Gallup",
    "sg:classifiers":[
        {
            "category":"Building & Trades",
            "subcategory":"Plumbing",
            "type":"Services"
        }
    ],
    "sg:phone":"+1 505 722 4756",
    "sg:postcode":"87301",
    "sg:province":"NM",
    "sg:tags":[
        "plumbing",
        "contractor"
    ],
    "wof:name":"Capital Plumbing",
    "wof:placetype":"venue"
},
  "geometry": {"coordinates":[-108.676743,35.524476],"type":"Point"}
}