{
  "type": "Feature",
  "properties": {
    "addr:full":"706 N Main St Belen NM 87002",
    "addr:housenumber":"706",
    "addr:postcode":"87002",
    "addr:street":"N Main St",
    "iso:country":"US",
    "sg:address":"706 N Main St",
    "sg:city":"Belen",
    "sg:classifiers":[
        {
            "category":"Restaurant",
            "type":"Food & Drink"
        }
    ],
    "sg:phone":"+1 505 861 0953",
    "sg:postcode":"87002",
    "sg:province":"NM",
    "sg:website":"www.subway.com",
    "wof:name":"Subway Sandwiches & Salads",
    "wof:placetype":"venue"
},
  "geometry": {"coordinates":[-106.774253,34.669171],"type":"Point"}
}