{
  "type": "Feature",
  "properties": {
    "addr:full":"9708 Lagrima de Oro Rd NE Albuquerque NM 87111",
    "addr:housenumber":"9708",
    "addr:postcode":"87111",
    "addr:street":"Lagrima De Oro Rd Ne",
    "iso:country":"US",
    "sg:address":"9708 Lagrima de Oro Rd NE",
    "sg:city":"Albuquerque",
    "sg:classifiers":[
        {
            "category":"Shopping",
            "subcategory":"Books",
            "type":"Retail Goods"
        },
        {
            "category":"Wholesale",
            "subcategory":"Books, Periodicals, & Newspapers",
            "type":"Manufacturing & Wholesale Goods"
        }
    ],
    "sg:phone":"+1 505 266 5952",
    "sg:postcode":"87111",
    "sg:province":"NM",
    "sg:tags":[
        "books-wholesale",
        "store",
        "manufacturer"
    ],
    "wof:name":"Neuma Books",
    "wof:placetype":"venue"
},
  "geometry": {"coordinates":[-106.53294200000001,35.132552],"type":"Point"}
}