{
  "type": "Feature",
  "properties": {
    "iso:country":"US",
    "sg:address":"2021 Pinon St",
    "sg:city":"Santa Fe",
    "sg:classifiers":[
        {
            "category":"Organizations",
            "subcategory":"Membership Organization",
            "type":"Services"
        },
        {
            "category":"Professional",
            "subcategory":"Business Services",
            "type":"Services"
        }
    ],
    "sg:phone":"+1 505 820 7426",
    "sg:postcode":"87505",
    "sg:province":"NM",
    "sg:tags":[
        "arbitration",
        "meditation",
        "instruction"
    ],
    "wof:name":"Sidda Yoga Meditation Ctr",
    "wof:placetype":"venue"
},
  "geometry": {"coordinates":[-105.975677,35.661842],"type":"Point"}
}