{
  "type": "Feature",
  "properties": {
    "iso:country":"US",
    "sg:address":"5326 Vicksburg Dr NW",
    "sg:city":"Albuquerque",
    "sg:classifiers":[
        {
            "category":"Social Services",
            "subcategory":"Child Care",
            "type":"Services"
        }
    ],
    "sg:phone":"+1 505 890 6757",
    "sg:postcode":"87120",
    "sg:province":"NM",
    "sg:tags":[
        "day"
    ],
    "wof:name":"Barbara Meyer",
    "wof:placetype":"venue"
},
  "geometry": {"coordinates":[-106.69911999999999,35.168167],"type":"Point"}
}