{
  "type": "Feature",
  "properties": {
    "iso:country":"US",
    "sg:address":"3905 San Mateo Blvd NE",
    "sg:city":"Albuquerque",
    "sg:classifiers":[
        {
            "category":"Food & Beverages",
            "subcategory":"Bakery",
            "type":"Retail Goods"
        }
    ],
    "sg:phone":"+1 505 889 3810",
    "sg:postcode":"87110",
    "sg:province":"NM",
    "wof:name":"French Corner Bakery",
    "wof:placetype":"venue"
},
  "geometry": {"coordinates":[-106.586568,35.127415],"type":"Point"}
}