{
  "type": "Feature",
  "properties": {
    "addr:full":"5816 Irving Blvd NW Albuquerque NM 87114",
    "addr:housenumber":"5816",
    "addr:postcode":"87114",
    "addr:street":"Irving Blvd Nw",
    "iso:country":"US",
    "sg:address":"5816 Irving Blvd NW",
    "sg:city":"Albuquerque",
    "sg:classifiers":[
        {
            "category":"Recreation",
            "type":"Entertainment"
        }
    ],
    "sg:phone":"+1 505 379 9963",
    "sg:postcode":"87114",
    "sg:province":"NM",
    "sg:tags":[
        "diving",
        "instruction"
    ],
    "wof:name":"Shark Bite Scuba Instruction",
    "wof:placetype":"venue"
},
  "geometry": {"coordinates":[-106.714242,35.203893],"type":"Point"}
}