{
  "type": "Feature",
  "properties": {
    "addr:full":"1240 Pennsylvania St NE Albuquerque NM 87110",
    "addr:housenumber":"1240",
    "addr:postcode":"87110",
    "addr:street":"Pennsylvania St Ne",
    "iso:country":"US",
    "sg:address":"1240 Pennsylvania St NE",
    "sg:city":"Albuquerque",
    "sg:classifiers":[
        {
            "category":"Banks & Credit Unions",
            "subcategory":"Bank",
            "type":"Services"
        }
    ],
    "sg:phone":"+1 505 889 7700",
    "sg:postcode":"87110",
    "sg:province":"NM",
    "sg:tags":[
        "loan",
        "real estate"
    ],
    "sg:website":"www.knr-mortgage.com",
    "wof:name":"KNR Mortgage",
    "wof:placetype":"venue"
},
  "geometry": {"coordinates":[-106.559428,35.091371],"type":"Point"}
}