{
  "type": "Feature",
  "properties": {
    "addr:full":"10410 Comanche Rd NE Albuquerque NM 87111",
    "addr:housenumber":"10410",
    "addr:postcode":"87111",
    "addr:street":"Comanche Rd Ne",
    "iso:country":"US",
    "sg:address":"10410 Comanche Rd NE",
    "sg:city":"Albuquerque",
    "sg:classifiers":[
        {
            "category":"Education",
            "subcategory":"Dance Studio",
            "type":"Public Place"
        }
    ],
    "sg:phone":"+1 505 298 5551",
    "sg:postcode":"87111",
    "sg:province":"NM",
    "sg:tags":[
        "instruction",
        "dancing"
    ],
    "wof:name":"Alwin School Of The Dance",
    "wof:placetype":"venue"
},
  "geometry": {"coordinates":[-106.522953,35.123436],"type":"Point"}
}