{
  "type": "Feature",
  "properties": {
    "addr:full":"3211 University Blvd SE Albuquerque NM 87106",
    "addr:housenumber":"3211",
    "addr:postcode":"87106",
    "addr:street":"University Blvd Se",
    "iso:country":"US",
    "sg:address":"3211 University Blvd SE",
    "sg:city":"Albuquerque",
    "sg:classifiers":[
        {
            "category":"Freight",
            "type":"Transportation"
        }
    ],
    "sg:phone":"+1 505 244 0487",
    "sg:postcode":"87106",
    "sg:province":"NM",
    "sg:tags":[
        "forwarder"
    ],
    "wof:name":"Kintetsu World Express USA",
    "wof:placetype":"venue"
},
  "geometry": {"coordinates":[-106.63090800000001,35.05021],"type":"Point"}
}