{
  "type": "Feature",
  "properties": {
    "addr:full":"3019 Isleta Blvd SW Albuquerque NM 87105",
    "addr:housenumber":"3019",
    "addr:postcode":"87105",
    "addr:street":"Isleta Blvd Sw",
    "iso:country":"US",
    "sg:address":"3019 Isleta Blvd SW",
    "sg:city":"Albuquerque",
    "sg:classifiers":[
        {
            "category":"Shopping",
            "type":"Retail Goods"
        }
    ],
    "sg:phone":"+1 505 842 7329",
    "sg:postcode":"87105",
    "sg:province":"NM",
    "sg:tags":[
        "wedding",
        "supply"
    ],
    "wof:name":"Celebrations",
    "wof:placetype":"venue"
},
  "geometry": {"coordinates":[-106.679681,35.030868],"type":"Point"}
}