{
  "type": "Feature",
  "properties": {
    "iso:country":"US",
    "sg:address":"823 S 1st St",
    "sg:city":"Tucumcari",
    "sg:classifiers":[
        {
            "category":"Organizations",
            "subcategory":"Religious Organization",
            "type":"Services"
        }
    ],
    "sg:phone":"+1 505 461 3106",
    "sg:postcode":"88401",
    "sg:province":"NM",
    "sg:tags":[
        "church"
    ],
    "wof:name":"Trinity Baptist Church Inc",
    "wof:placetype":"venue"
},
  "geometry": {"coordinates":[-103.724985,35.171531],"type":"Point"}
}