{
  "type": "Feature",
  "properties": {
    "addr:full":"11725 Rosemont Ave NE Albuquerque NM 87112",
    "addr:housenumber":"11725",
    "addr:postcode":"87112",
    "addr:street":"Rosemont Ave Ne",
    "iso:country":"US",
    "sg:address":"11725 Rosemont Ave NE",
    "sg:city":"Albuquerque",
    "sg:classifiers":[
        {
            "category":"Education",
            "subcategory":"Vocational School",
            "type":"Public Place"
        }
    ],
    "sg:phone":"+1 505 298 1379",
    "sg:postcode":"87112",
    "sg:province":"NM",
    "wof:name":"Christian Health Seminars",
    "wof:placetype":"venue"
},
  "geometry": {"coordinates":[-106.518198,35.090871],"type":"Point"}
}