{
  "type": "Feature",
  "properties": {
    "iso:country":"US",
    "sg:address":"51 E Therma St",
    "sg:city":"Eagle Nest",
    "sg:classifiers":[
        {
            "category":"Real Estate",
            "subcategory":"Real Estate Agent",
            "type":"Services"
        }
    ],
    "sg:phone":"+1 505 377 2222",
    "sg:postcode":"87718",
    "sg:province":"NM",
    "wof:name":"Eagle Nest Realty",
    "wof:placetype":"venue"
},
  "geometry": {"coordinates":[-105.263226,36.553988],"type":"Point"}
}