{
  "type": "Feature",
  "properties": {
    "iso:country":"US",
    "sg:address":"2724 Washington St NE",
    "sg:city":"Albuquerque",
    "sg:classifiers":[
        {
            "category":"Retail",
            "subcategory":"Repair Shop",
            "type":"Services"
        }
    ],
    "sg:phone":"+1 505 888 4194",
    "sg:postcode":"87110",
    "sg:province":"NM",
    "sg:tags":[
        "plumbing",
        "drain",
        "cleaning",
        "sewer"
    ],
    "wof:name":"Leo's Sewer Svc",
    "wof:placetype":"venue"
},
  "geometry": {"coordinates":[-106.594741,35.11244],"type":"Point"}
}