{
  "type": "Feature",
  "properties": {
    "iso:country":"US",
    "sg:address":"200 Mechem Dr",
    "sg:city":"Ruidoso",
    "sg:classifiers":[
        {
            "category":"Personal",
            "subcategory":"Beauty Salon",
            "type":"Services"
        }
    ],
    "sg:phone":"+1 505 257 8982",
    "sg:postcode":"88345",
    "sg:province":"NM",
    "sg:tags":[
        "spa",
        "day"
    ],
    "wof:name":"Sevilla's Day Spa",
    "wof:placetype":"venue"
},
  "geometry": {"coordinates":[-105.681304,33.33428],"type":"Point"}
}