{
  "type": "Feature",
  "properties": {
    "iso:country":"US",
    "sg:address":"3925 Clinton Blvd SW",
    "sg:city":"Albuquerque",
    "sg:classifiers":[
        {
            "category":"Freight",
            "type":"Transportation"
        }
    ],
    "sg:phone":"+1 505 452 1312",
    "sg:postcode":"87105",
    "sg:province":"NM",
    "sg:tags":[
        "dump",
        "truck",
        "hauling",
        "tractor"
    ],
    "wof:name":"C&R Hauling",
    "wof:placetype":"venue"
},
  "geometry": {"coordinates":[-106.69098,35.020505],"type":"Point"}
}