{
  "type": "Feature",
  "properties": {
    "iso:country":"US",
    "sg:address":"8309 Ville Ct NE",
    "sg:city":"Albuquerque",
    "sg:classifiers":[
        {
            "category":"Autos & Motor Vehicles",
            "subcategory":"Recreational Vehicle Sales",
            "type":"Retail Goods"
        }
    ],
    "sg:phone":"+1 505 480 8597",
    "sg:postcode":"87113",
    "sg:province":"NM",
    "wof:name":"Rvs Plus",
    "wof:placetype":"venue"
},
  "geometry": {"coordinates":[-106.573892,35.176741],"type":"Point"}
}