{
  "type": "Feature",
  "properties": {
    "addr:full":"600 Charles St Truth Or Cnsqncs NM 87901",
    "addr:housenumber":"600",
    "addr:postcode":"87901",
    "addr:street":"Charles St",
    "iso:country":"US",
    "sg:address":"600 Charles St",
    "sg:city":"Truth Or Cnsqncs",
    "sg:classifiers":[
        {
            "category":"Freight",
            "type":"Transportation"
        }
    ],
    "sg:phone":"+1 505 894 7640",
    "sg:postcode":"87901",
    "sg:province":"NM",
    "sg:tags":[
        "commercial",
        "storage"
    ],
    "wof:name":"Home Town Self Storage",
    "wof:placetype":"venue"
},
  "geometry": {"coordinates":[-107.258618,33.125019],"type":"Point"}
}