{
  "type": "Feature",
  "properties": {
    "addr:full":"6639 Charwood Rd NW Albuquerque NM 87114",
    "addr:housenumber":"6639",
    "addr:postcode":"87114",
    "addr:street":"Charwood Rd Nw",
    "iso:country":"US",
    "sg:address":"6639 Charwood Rd NW",
    "sg:city":"Albuquerque",
    "sg:classifiers":[
        {
            "category":"Professional",
            "subcategory":"Management & Consulting",
            "type":"Services"
        }
    ],
    "sg:phone":"+1 505 221 5061",
    "sg:postcode":"87114",
    "sg:province":"NM",
    "wof:name":"Dmu Consulting",
    "wof:placetype":"venue"
},
  "geometry": {"coordinates":[-106.72915,35.200133],"type":"Point"}
}