{
  "type": "Feature",
  "properties": {
    "iso:country":"US",
    "sg:address":"275 Coyote Trl",
    "sg:city":"Corrales",
    "sg:classifiers":[
        {
            "category":"Professional",
            "subcategory":"Business Services",
            "type":"Services"
        }
    ],
    "sg:phone":"+1 505 843 6433",
    "sg:postcode":"87114",
    "sg:province":"NM",
    "sg:tags":[
        "interior",
        "consultant",
        "design",
        "decorator"
    ],
    "wof:name":"Jan Bernson Interior Designers",
    "wof:placetype":"venue"
},
  "geometry": {"coordinates":[-106.64299,35.21578],"type":"Point"}
}