{
  "type": "Feature",
  "properties": {
    "iso:country":"US",
    "sg:address":"278 Dp Rd",
    "sg:city":"Los Alamos",
    "sg:classifiers":[
        {
            "category":"Home & Garden",
            "subcategory":"Furniture",
            "type":"Retail Goods"
        }
    ],
    "sg:phone":"+1 505 661 6211",
    "sg:postcode":"87544",
    "sg:province":"NM",
    "sg:tags":[
        "cabinet"
    ],
    "wof:name":"C R Cabinets",
    "wof:placetype":"venue"
},
  "geometry": {"coordinates":[-106.27724499999999,35.877974],"type":"Point"}
}