{
  "type": "Feature",
  "properties": {
    "addr:full":"209 Vassar Dr SE Albuquerque NM 87106",
    "addr:housenumber":"209",
    "addr:postcode":"87106",
    "addr:street":"Vassar Dr Se",
    "iso:country":"US",
    "sg:address":"209 Vassar Dr SE",
    "sg:city":"Albuquerque",
    "sg:classifiers":[
        {
            "category":"Building & Trades",
            "subcategory":"Construction",
            "type":"Services"
        }
    ],
    "sg:phone":"+1 505 255 2258",
    "sg:postcode":"87106",
    "sg:province":"NM",
    "sg:tags":[
        "handyman"
    ],
    "wof:name":"Jim's Fix It",
    "wof:placetype":"venue"
},
  "geometry": {"coordinates":[-106.61463999999999,35.077465],"type":"Point"}
}