{
  "type": "Feature",
  "properties": {
    "iso:country":"US",
    "sg:address":"312 Staab St",
    "sg:city":"Santa Fe",
    "sg:classifiers":[
        {
            "category":"Professional",
            "subcategory":"Accounting & Tax Preparation",
            "type":"Services"
        }
    ],
    "sg:phone":"+1 505 986 0886",
    "sg:postcode":"87501",
    "sg:province":"NM",
    "wof:name":"Michael P Sherry CPA",
    "wof:placetype":"venue"
},
  "geometry": {"coordinates":[-105.943241,35.69051],"type":"Point"}
}