{
  "type": "Feature",
  "properties": {
    "iso:country":"US",
    "sg:address":"2706 Crestview Dr",
    "sg:city":"Las Cruces",
    "sg:classifiers":[
        {
            "category":"Real Estate",
            "subcategory":"Surveying",
            "type":"Services"
        }
    ],
    "sg:phone":"+1 505 522 1681",
    "sg:postcode":"88011",
    "sg:province":"NM",
    "wof:name":"Frank Harder Surveying Inc",
    "wof:placetype":"venue"
},
  "geometry": {"coordinates":[-106.74029899999999,32.302408],"type":"Point"}
}