{
  "type": "Feature",
  "properties": {
    "iso:country":"US",
    "sg:address":"600 Montana Ave",
    "sg:city":"Las Cruces",
    "sg:classifiers":[
        {
            "category":"Professional",
            "subcategory":"Accounting & Tax Preparation",
            "type":"Services"
        }
    ],
    "sg:phone":"+1 505 524 0068",
    "sg:postcode":"88001",
    "sg:province":"NM",
    "wof:name":"Scott K Fowler CPA PA",
    "wof:placetype":"venue"
},
  "geometry": {"coordinates":[-106.767403,32.295247],"type":"Point"}
}