{
  "type": "Feature",
  "properties": {
    "addr:full":"1504 Bridge Blvd SW Albuquerque NM 87105",
    "addr:housenumber":"1504",
    "addr:postcode":"87105",
    "addr:street":"Bridge Blvd Sw",
    "iso:country":"US",
    "sg:address":"1504 Bridge Blvd SW",
    "sg:city":"Albuquerque",
    "sg:classifiers":[
        {
            "category":"Shopping",
            "subcategory":"Clothing, Apparel, & Fashions",
            "type":"Retail Goods"
        }
    ],
    "sg:phone":"+1 505 242 4799",
    "sg:postcode":"87105",
    "sg:province":"NM",
    "sg:tags":[
        "item",
        "boutique"
    ],
    "wof:name":"Alexis Boutique",
    "wof:placetype":"venue"
},
  "geometry": {"coordinates":[-106.678572,35.065518],"type":"Point"}
}