{
  "type": "Feature",
  "properties": {
    "iso:country":"US",
    "sg:address":"908 S Michigan Ave",
    "sg:city":"Roswell",
    "sg:classifiers":[
        {
            "category":"Building & Trades",
            "subcategory":"Construction",
            "type":"Services"
        }
    ],
    "sg:phone":"+1 505 627 1992",
    "sg:postcode":"88203",
    "sg:province":"NM",
    "sg:tags":[
        "contractor"
    ],
    "wof:name":"Professional Business Systems",
    "wof:placetype":"venue"
},
  "geometry": {"coordinates":[-104.533245,33.384581],"type":"Point"}
}