{
  "type": "Feature",
  "properties": {
    "iso:country":"US",
    "sg:address":"123 E Tucumcari Blvd",
    "sg:city":"Tucumcari",
    "sg:classifiers":[
        {
            "category":"Autos & Motor Vehicles",
            "subcategory":"Fuel & Gas Station",
            "type":"Retail Goods"
        }
    ],
    "sg:phone":"+1 505 461 2366",
    "sg:postcode":"88401",
    "sg:province":"NM",
    "sg:tags":[
        "oil"
    ],
    "wof:name":"Rigdon Texaco",
    "wof:placetype":"venue"
},
  "geometry": {"coordinates":[-103.725866,35.171812],"type":"Point"}
}