{
  "type": "Feature",
  "properties": {
    "iso:country":"US",
    "sg:address":"7150 Vineyard Rd",
    "sg:city":"Dexter",
    "sg:classifiers":[
        {
            "category":"Farming",
            "subcategory":"Dairy Farm",
            "type":"Manufacturing & Wholesale Goods"
        }
    ],
    "sg:phone":"+1 505 734 6338",
    "sg:postcode":"88230",
    "sg:province":"NM",
    "wof:name":"Breedy K Dairy",
    "wof:placetype":"venue"
},
  "geometry": {"coordinates":[-104.405591,33.190744],"type":"Point"}
}