{
  "type": "Feature",
  "properties": {
    "iso:country":"US",
    "sg:address":"6604 Christy Ave NE",
    "sg:city":"Albuquerque",
    "sg:classifiers":[
        {
            "category":"Retail",
            "subcategory":"Veterinary Services",
            "type":"Services"
        }
    ],
    "sg:phone":"+1 505 877 3311",
    "sg:postcode":"87109",
    "sg:province":"NM",
    "sg:tags":[
        "veterinarian"
    ],
    "wof:name":"Jobyco PC",
    "wof:placetype":"venue"
},
  "geometry": {"coordinates":[-106.568781,35.154105],"type":"Point"}
}