{
  "type": "Feature",
  "properties": {
    "addr:full":"1415 S Jackson St Tucumcari NM 88401",
    "addr:housenumber":"1415",
    "addr:postcode":"88401",
    "addr:street":"S Jackson St",
    "iso:country":"US",
    "sg:address":"1415 S Jackson St",
    "sg:city":"Tucumcari",
    "sg:classifiers":[
        {
            "category":"Freight",
            "type":"Transportation"
        },
        {
            "category":"Manufacturing",
            "subcategory":"Glass & Minerals",
            "type":"Manufacturing & Wholesale Goods"
        }
    ],
    "sg:phone":"+1 505 461 4221",
    "sg:postcode":"88401",
    "sg:province":"NM",
    "sg:tags":[
        "ready",
        "concrete",
        "mfg",
        "local",
        "trucking"
    ],
    "wof:name":"Hayes Trucking & Concrete Inc",
    "wof:placetype":"venue"
},
  "geometry": {"coordinates":[-103.721075,35.165722],"type":"Point"}
}