{
  "type": "Feature",
  "properties": {
    "iso:country":"US",
    "sg:address":"1301 N Pershing St",
    "sg:city":"Truth Or Cnsqncs",
    "sg:classifiers":[
        {
            "category":"Professional",
            "subcategory":"Employment Agencies",
            "type":"Services"
        }
    ],
    "sg:phone":"+1 505 894 1263",
    "sg:postcode":"87901",
    "sg:province":"NM",
    "sg:tags":[
        "co",
        "fraternal"
    ],
    "wof:name":"New Mexico Dept Of Labor",
    "wof:placetype":"venue"
},
  "geometry": {"coordinates":[-107.25166900000001,33.143271],"type":"Point"}
}