{
  "type": "Feature",
  "properties": {
    "addr:full":"1706 Southern Blvd SE Rio Rancho NM 87124",
    "addr:housenumber":"1706",
    "addr:postcode":"87124",
    "addr:street":"Southern Blvd Se",
    "iso:country":"US",
    "sg:address":"1706 Southern Blvd SE",
    "sg:city":"Rio Rancho",
    "sg:classifiers":[
        {
            "category":"Restaurant",
            "type":"Food & Drink"
        }
    ],
    "sg:phone":"+1 505 892 5454",
    "sg:postcode":"87124",
    "sg:province":"NM",
    "sg:tags":[
        "eating"
    ],
    "wof:name":"Sal-E-Boys Pizzeria Inc",
    "wof:placetype":"venue"
},
  "geometry": {"coordinates":[-106.70269999999999,35.241473],"type":"Point"}
}