{
  "type": "Feature",
  "properties": {
    "iso:country":"US",
    "sg:address":"1107 N Coleman St",
    "sg:city":"Hobbs",
    "sg:classifiers":[
        {
            "category":"Shopping",
            "subcategory":"Gifts & Souvenirs",
            "type":"Retail Goods"
        }
    ],
    "sg:phone":"+1 505 397 0581",
    "sg:postcode":"88240",
    "sg:province":"NM",
    "wof:name":"M & M Gift Shop",
    "wof:placetype":"venue"
},
  "geometry": {"coordinates":[-103.147538,32.712534],"type":"Point"}
}