{
  "type": "Feature",
  "properties": {
    "iso:country":"US",
    "sg:address":"209 N Auburn Ave",
    "sg:city":"Farmington",
    "sg:classifiers":[
        {
            "category":"Social Services",
            "subcategory":"Child Care",
            "type":"Services"
        }
    ],
    "sg:phone":"+1 505 325 3166",
    "sg:postcode":"87401",
    "sg:province":"NM",
    "sg:tags":[
        "day"
    ],
    "wof:name":"School Of Montessori",
    "wof:placetype":"venue"
},
  "geometry": {"coordinates":[-108.210723,36.731558],"type":"Point"}
}