{
  "type": "Feature",
  "properties": {
    "iso:country":"US",
    "sg:address":"397 Alameda Blvd NW",
    "sg:city":"Albuquerque",
    "sg:classifiers":[
        {
            "category":"Food & Beverages",
            "subcategory":"Groceries & Convenience Stores",
            "type":"Retail Goods"
        }
    ],
    "sg:phone":"+1 505 898 6492",
    "sg:postcode":"87114",
    "sg:province":"NM",
    "sg:tags":[
        "station",
        "gas"
    ],
    "wof:name":"Circle K",
    "wof:placetype":"venue"
},
  "geometry": {"coordinates":[-106.617107,35.189101],"type":"Point"}
}