{
  "type": "Feature",
  "properties": {
    "addr:full":"2545 S Espina St Las Cruces NM 88001",
    "addr:housenumber":"2545",
    "addr:postcode":"88001",
    "addr:street":"S Espina St",
    "iso:country":"US",
    "sg:address":"2545 S Espina St",
    "sg:city":"Las Cruces",
    "sg:classifiers":[
        {
            "category":"Organizations",
            "subcategory":"Community Association",
            "type":"Services"
        }
    ],
    "sg:phone":"+1 505 522 6020",
    "sg:postcode":"88001",
    "sg:province":"NM",
    "wof:name":"Alpha Gama RHO",
    "wof:placetype":"venue"
},
  "geometry": {"coordinates":[-106.75700500000001,32.285239],"type":"Point"}
}