{
  "type": "Feature",
  "properties": {
    "addr:full":"6955 Cam Nuevo Mejico Las Cruces NM 88007",
    "addr:housenumber":"6955",
    "addr:postcode":"88007",
    "addr:street":"Cam Nuevo Mejico",
    "iso:country":"US",
    "sg:address":"6955 Cam Nuevo Mejico",
    "sg:city":"Las Cruces",
    "sg:classifiers":[
        {
            "category":"Banks & Credit Unions",
            "subcategory":"Investment Brokerage",
            "type":"Services"
        }
    ],
    "sg:phone":"+1 505 526 8810",
    "sg:postcode":"88007",
    "sg:province":"NM",
    "wof:name":"Blanco Investment",
    "wof:placetype":"venue"
},
  "geometry": {"coordinates":[-106.870451,32.310445],"type":"Point"}
}