{
  "type": "Feature",
  "properties": {
    "addr:full":"120 Llano St Aztec NM 87410",
    "addr:housenumber":"120",
    "addr:postcode":"87410",
    "addr:street":"Llano St",
    "iso:country":"US",
    "sg:address":"120 Llano St",
    "sg:city":"Aztec",
    "sg:classifiers":[
        {
            "category":"Sports & Exercise",
            "subcategory":"Gym",
            "type":"Entertainment"
        }
    ],
    "sg:phone":"+1 505 333 2611",
    "sg:postcode":"87410",
    "sg:province":"NM",
    "sg:tags":[
        "club",
        "health",
        "studio",
        "gymnasium"
    ],
    "wof:name":"Curves For Women",
    "wof:placetype":"venue"
},
  "geometry": {"coordinates":[-107.99677699999999,36.819423],"type":"Point"}
}