{
  "type": "Feature",
  "properties": {
    "iso:country":"US",
    "sg:address":"3600 Menaul Blvd NE",
    "sg:city":"Albuquerque",
    "sg:classifiers":[
        {
            "category":"Shopping",
            "type":"Retail Goods"
        }
    ],
    "sg:phone":"+1 505 888 6500",
    "sg:postcode":"87110",
    "sg:province":"NM",
    "sg:tags":[
        "equipment",
        "care",
        "health",
        "home"
    ],
    "wof:name":"Hme Specialists LLC",
    "wof:placetype":"venue"
},
  "geometry": {"coordinates":[-106.601958,35.109214],"type":"Point"}
}