{
  "type": "Feature",
  "properties": {
    "iso:country":"US",
    "sg:address":"2291 State Hwy 304",
    "sg:city":"Belen",
    "sg:classifiers":[
        {
            "category":"Real Estate",
            "subcategory":"Real Estate Operator",
            "type":"Services"
        }
    ],
    "sg:phone":"+1 505 864 9558",
    "sg:postcode":"87002",
    "sg:province":"NM",
    "sg:tags":[
        "building",
        "apartment"
    ],
    "wof:name":"Rio Verde Apts",
    "wof:placetype":"venue"
},
  "geometry": {"coordinates":[-106.734148,34.649851],"type":"Point"}
}