{
  "type": "Feature",
  "properties": {
    "iso:country":"US",
    "sg:address":"116 W Center St",
    "sg:city":"Tucumcari",
    "sg:classifiers":[
        {
            "category":"Home & Garden",
            "subcategory":"Furniture",
            "type":"Retail Goods"
        }
    ],
    "sg:phone":"+1 505 461 9930",
    "sg:postcode":"88401",
    "sg:province":"NM",
    "wof:name":"Furniture Depot Plus",
    "wof:placetype":"venue"
},
  "geometry": {"coordinates":[-103.727206,35.177956],"type":"Point"}
}