{
  "type": "Feature",
  "properties": {
    "iso:country":"US",
    "sg:address":"423 Chama St NE",
    "sg:city":"Albuquerque",
    "sg:classifiers":[
        {
            "category":"Building & Trades",
            "subcategory":"Landscaping Services",
            "type":"Services"
        }
    ],
    "sg:phone":"+1 505 256 0310",
    "sg:postcode":"87108",
    "sg:province":"NM",
    "wof:name":"Santa Fe Tree Service",
    "wof:placetype":"venue"
},
  "geometry": {"coordinates":[-106.566435,35.083181],"type":"Point"}
}