{
  "type": "Feature",
  "properties": {
    "addr:full":"1605 W Terrace Dr Grants NM 87020",
    "addr:housenumber":"1605",
    "addr:postcode":"87020",
    "addr:street":"W Terrace Dr",
    "iso:country":"US",
    "sg:address":"1605 W Terrace Dr",
    "sg:city":"Grants",
    "sg:classifiers":[
        {
            "category":"Farming",
            "subcategory":"Livestock Farm",
            "type":"Manufacturing & Wholesale Goods"
        }
    ],
    "sg:phone":"+1 505 290 1655",
    "sg:postcode":"87020",
    "sg:province":"NM",
    "sg:tags":[
        "animal",
        "general"
    ],
    "wof:name":"Hamilton Ranch",
    "wof:placetype":"venue"
},
  "geometry": {"coordinates":[-107.832166,35.171409],"type":"Point"}
}