{
  "type": "Feature",
  "properties": {
    "addr:full":"305 S Lake St Carlsbad NM 88220",
    "addr:housenumber":"305",
    "addr:postcode":"88220",
    "addr:street":"S Lake St",
    "iso:country":"US",
    "sg:address":"305 S Lake St",
    "sg:city":"Carlsbad",
    "sg:classifiers":[
        {
            "category":"Professional",
            "subcategory":"Business Services",
            "type":"Services"
        }
    ],
    "sg:phone":"+1 505 885 1400",
    "sg:postcode":"88220",
    "sg:province":"NM",
    "wof:name":"Carlsbad Answering Service",
    "wof:placetype":"venue"
},
  "geometry": {"coordinates":[-104.23557099999999,32.417967],"type":"Point"}
}