{
  "type": "Feature",
  "properties": {
    "addr:full":"112 Cree Meadows Dr Ruidoso NM 88345",
    "addr:housenumber":"112",
    "addr:postcode":"88345",
    "addr:street":"Cree Meadows Dr",
    "iso:country":"US",
    "sg:address":"112 Cree Meadows Dr",
    "sg:city":"Ruidoso",
    "sg:classifiers":[
        {
            "category":"Real Estate",
            "subcategory":"Real Estate Agent",
            "type":"Services"
        }
    ],
    "sg:phone":"+1 505 257 0106",
    "sg:postcode":"88345",
    "sg:province":"NM",
    "wof:name":"Sibley Properties",
    "wof:placetype":"venue"
},
  "geometry": {"coordinates":[-105.67205300000001,33.348075],"type":"Point"}
}