{
  "type": "Feature",
  "properties": {
    "iso:country":"US",
    "sg:address":"9201 Montgomery Blvd NE",
    "sg:city":"Albuquerque",
    "sg:classifiers":[
        {
            "category":"Real Estate",
            "subcategory":"Real Estate Agent",
            "type":"Services"
        }
    ],
    "sg:phone":"+1 505 299 2307",
    "sg:postcode":"87111",
    "sg:province":"NM",
    "wof:name":"Kenneth McCalvey LLC",
    "wof:placetype":"venue"
},
  "geometry": {"coordinates":[-106.538999,35.130673],"type":"Point"}
}