{
  "type": "Feature",
  "properties": {
    "iso:country":"US",
    "sg:address":"4406 el Llano Rd",
    "sg:city":"Las Vegas",
    "sg:classifiers":[
        {
            "category":"Retail",
            "subcategory":"Auto Repair",
            "type":"Services"
        }
    ],
    "sg:phone":"+1 505 454 0997",
    "sg:postcode":"87701",
    "sg:province":"NM",
    "sg:tags":[
        "truck"
    ],
    "wof:name":"Greer's Diesel Repair Shop",
    "wof:placetype":"venue"
},
  "geometry": {"coordinates":[-105.24907399999999,35.629554],"type":"Point"}
}