{
  "type": "Feature",
  "properties": {
    "iso:country":"US",
    "sg:address":"416 W Coal Ave",
    "sg:city":"Gallup",
    "sg:classifiers":[
        {
            "category":"Autos & Motor Vehicles",
            "subcategory":"Automobile Sales",
            "type":"Retail Goods"
        }
    ],
    "sg:phone":"+1 505 863 5089",
    "sg:postcode":"87301",
    "sg:province":"NM",
    "sg:tags":[
        "car",
        "dealer"
    ],
    "wof:name":"John's Used Cars",
    "wof:placetype":"venue"
},
  "geometry": {"coordinates":[-108.745074,35.526322],"type":"Point"}
}