{
  "type": "Feature",
  "properties": {
    "iso:country":"US",
    "sg:address":"500 Granado St",
    "sg:city":"Tularosa",
    "sg:classifiers":[
        {
            "category":"Organizations",
            "subcategory":"Religious Organization",
            "type":"Services"
        }
    ],
    "sg:phone":"+1 505 585 9864",
    "sg:postcode":"88352",
    "sg:province":"NM",
    "sg:tags":[
        "church"
    ],
    "wof:name":"First Baptist Church-Tularosa",
    "wof:placetype":"venue"
},
  "geometry": {"coordinates":[-106.018587,33.072054],"type":"Point"}
}