{
  "type": "Feature",
  "properties": {
    "iso:country":"US",
    "sg:address":"3530 Pan American Fwy",
    "sg:city":"Albuquerque",
    "sg:classifiers":[
        {
            "category":"Health Services",
            "subcategory":"Clinic",
            "type":"Services"
        }
    ],
    "sg:phone":"+1 505 888 4325",
    "sg:postcode":"87107",
    "sg:province":"NM",
    "sg:tags":[
        "home",
        "care",
        "merchandise",
        "med"
    ],
    "wof:name":"Option Care Inc (del)",
    "wof:placetype":"venue"
},
  "geometry": {"coordinates":[-106.621707,35.123662],"type":"Point"}
}