{
  "type": "Feature",
  "properties": {
    "iso:country":"US",
    "sg:address":"3309 May Cir SE",
    "sg:city":"Rio Rancho",
    "sg:classifiers":[
        {
            "category":"Personal",
            "type":"Services"
        }
    ],
    "sg:phone":"+1 505 892 4183",
    "sg:postcode":"87124",
    "sg:province":"NM",
    "sg:tags":[
        "miscellaneous"
    ],
    "wof:name":"Bevens Enterprises New Mexico",
    "wof:placetype":"venue"
},
  "geometry": {"coordinates":[-106.669299,35.241337],"type":"Point"}
}