{
  "type": "Feature",
  "properties": {
    "iso:country":"US",
    "sg:address":"2370 US Hwy 180 E",
    "sg:city":"Silver City",
    "sg:classifiers":[
        {
            "category":"Restaurant",
            "type":"Food & Drink"
        }
    ],
    "sg:phone":"+1 505 388 5426",
    "sg:postcode":"88061",
    "sg:province":"NM",
    "sg:tags":[
        "eating"
    ],
    "wof:name":"Subway 1004",
    "wof:placetype":"venue"
},
  "geometry": {"coordinates":[-108.255227,32.787053],"type":"Point"}
}