{
  "type": "Feature",
  "properties": {
    "iso:country":"US",
    "sg:address":"1461 US Hwy 70",
    "sg:city":"Ruidoso Downs",
    "sg:classifiers":[
        {
            "category":"Wholesale",
            "subcategory":"Farm Supplies",
            "type":"Manufacturing & Wholesale Goods"
        }
    ],
    "sg:phone":"+1 505 378 1036",
    "sg:postcode":"88346",
    "sg:province":"NM",
    "sg:tags":[
        "feed"
    ],
    "wof:name":"Hawkinson Feed & Supply",
    "wof:placetype":"venue"
},
  "geometry": {"coordinates":[-105.59934199999999,33.330782],"type":"Point"}
}