{
  "type": "Feature",
  "properties": {
    "iso:country":"US",
    "sg:address":"2116 Cam Maria Felez",
    "sg:city":"Santa Fe",
    "sg:classifiers":[
        {
            "category":"Home & Garden",
            "subcategory":"Home Furnishings",
            "type":"Retail Goods"
        }
    ],
    "sg:phone":"+1 505 471 2900",
    "sg:postcode":"87507",
    "sg:province":"NM",
    "sg:tags":[
        "repair"
    ],
    "wof:name":"Dannys Upholstery",
    "wof:placetype":"venue"
},
  "geometry": {"coordinates":[-106.010373,35.655077],"type":"Point"}
}