{
  "type": "Feature",
  "properties": {
    "iso:country":"US",
    "sg:address":"118 Old Santa Fe Trl",
    "sg:city":"Santa Fe",
    "sg:classifiers":[
        {
            "category":"Shopping",
            "subcategory":"Gifts & Souvenirs",
            "type":"Retail Goods"
        }
    ],
    "sg:phone":"+1 505 984 1914",
    "sg:postcode":"87501",
    "sg:province":"NM",
    "sg:tags":[
        "shop"
    ],
    "wof:name":"Sumac Design",
    "wof:placetype":"venue"
},
  "geometry": {"coordinates":[-105.93835,35.686256],"type":"Point"}
}