{
  "type": "Feature",
  "properties": {
    "addr:full":"500 N Orchard Ave Farmington NM 87401",
    "addr:housenumber":"500",
    "addr:postcode":"87401",
    "addr:street":"N Orchard Ave",
    "iso:country":"US",
    "sg:address":"500 N Orchard Ave",
    "sg:city":"Farmington",
    "sg:classifiers":[
        {
            "category":"Banks & Credit Unions",
            "subcategory":"Bank",
            "type":"Services"
        }
    ],
    "sg:phone":"+1 505 325 0176",
    "sg:postcode":"87401",
    "sg:province":"NM",
    "sg:tags":[
        "federal",
        "agency"
    ],
    "wof:name":"Outsource",
    "wof:placetype":"venue"
},
  "geometry": {"coordinates":[-108.205215,36.735213],"type":"Point"}
}