{
  "type": "Feature",
  "properties": {
    "iso:country":"US",
    "sg:address":"607 Deer Park Dr",
    "sg:city":"Alto",
    "sg:classifiers":[
        {
            "category":"Building & Trades",
            "subcategory":"Electrical",
            "type":"Services"
        }
    ],
    "sg:phone":"+1 505 336 1527",
    "sg:postcode":"88345",
    "sg:province":"NM",
    "sg:tags":[
        "electric",
        "contractor"
    ],
    "wof:name":"Alto Lakes Electrical Svc",
    "wof:placetype":"venue"
},
  "geometry": {"coordinates":[-105.65647300000001,33.40278],"type":"Point"}
}