{
  "type": "Feature",
  "properties": {
    "iso:country":"US",
    "sg:address":"7520 Corona Ave NE",
    "sg:city":"Albuquerque",
    "sg:classifiers":[
        {
            "category":"Government",
            "subcategory":"Police Station",
            "type":"Public Place"
        }
    ],
    "sg:phone":"+1 505 857 8421",
    "sg:postcode":"87113",
    "sg:province":"NM",
    "sg:tags":[
        "department"
    ],
    "sg:website":"www.cabq.gov",
    "wof:name":"Albuquerque Police Dept",
    "wof:placetype":"venue"
},
  "geometry": {"coordinates":[-106.559927,35.18011],"type":"Point"}
}