{
  "type": "Feature",
  "properties": {
    "addr:full":"49 Brentwood Rd Roswell NM 88201",
    "addr:housenumber":"49",
    "addr:postcode":"88201",
    "addr:street":"Brentwood Rd",
    "iso:country":"US",
    "sg:address":"49 Brentwood Rd",
    "sg:city":"Roswell",
    "sg:classifiers":[
        {
            "category":"Professional",
            "subcategory":"Business Services",
            "type":"Services"
        }
    ],
    "sg:phone":"+1 505 624 7907",
    "sg:postcode":"88201",
    "sg:province":"NM",
    "wof:name":"Van Rheenen Enterprises",
    "wof:placetype":"venue"
},
  "geometry": {"coordinates":[-104.490499,33.421781],"type":"Point"}
}