{
  "type": "Feature",
  "properties": {
    "iso:country":"US",
    "sg:address":"549 Cam Sin Pasada",
    "sg:city":"Corrales",
    "sg:classifiers":[
        {
            "category":"Professional",
            "subcategory":"Business Services",
            "type":"Services"
        }
    ],
    "sg:phone":"+1 505 897 4266",
    "sg:postcode":"87048",
    "sg:province":"NM",
    "sg:tags":[
        "drafting"
    ],
    "wof:name":"Handley Residential Drafting",
    "wof:placetype":"venue"
},
  "geometry": {"coordinates":[-106.61562499999999,35.247278],"type":"Point"}
}