{
  "type": "Feature",
  "properties": {
    "iso:country":"US",
    "sg:address":"7612 Rio Penasco Ct NW",
    "sg:city":"Albuquerque",
    "sg:classifiers":[
        {
            "category":"Health Services",
            "subcategory":"Clinic",
            "type":"Services"
        }
    ],
    "sg:phone":"+1 505 270 9989",
    "sg:postcode":"87120",
    "sg:province":"NM",
    "wof:name":"R & G Healthcare Properties",
    "wof:placetype":"venue"
},
  "geometry": {"coordinates":[-106.683486,35.172967],"type":"Point"}
}