{
  "type": "Feature",
  "properties": {
    "addr:full":"4320 Pso del Norte NE Albuquerque NM 87113",
    "addr:housenumber":"4320",
    "addr:postcode":"87113",
    "addr:street":"Pso Del Norte Ne",
    "iso:country":"US",
    "sg:address":"4320 Pso del Norte NE",
    "sg:city":"Albuquerque",
    "sg:classifiers":[
        {
            "category":"Insurance",
            "subcategory":"Insurance Agent",
            "type":"Services"
        }
    ],
    "sg:phone":"+1 505 857 0243",
    "sg:postcode":"87113",
    "sg:province":"NM",
    "wof:name":"Insurance & Professional Svc",
    "wof:placetype":"venue"
},
  "geometry": {"coordinates":[-106.599304,35.174403],"type":"Point"}
}