{
  "type": "Feature",
  "properties": {
    "iso:country":"US",
    "sg:address":"4250 E Main St",
    "sg:city":"Farmington",
    "sg:classifiers":[
        {
            "category":"Professional",
            "type":"Services"
        }
    ],
    "sg:phone":"+1 505 324 2118",
    "sg:postcode":"87402",
    "sg:province":"NM",
    "sg:tags":[
        "establishment"
    ],
    "wof:name":"Alamo PCS",
    "wof:placetype":"venue"
},
  "geometry": {"coordinates":[-108.15595500000001,36.759783],"type":"Point"}
}