{
  "type": "Feature",
  "properties": {
    "iso:country":"US",
    "sg:address":"3110 National Parks Hwy",
    "sg:city":"Carlsbad",
    "sg:classifiers":[
        {
            "category":"Wholesale",
            "subcategory":"Electrical",
            "type":"Manufacturing & Wholesale Goods"
        }
    ],
    "sg:phone":"+1 505 885 2666",
    "sg:postcode":"88220",
    "sg:province":"NM",
    "sg:tags":[
        "radio"
    ],
    "wof:name":"Caprock Communications",
    "wof:placetype":"venue"
},
  "geometry": {"coordinates":[-104.22128499999999,32.386843],"type":"Point"}
}