{
  "type": "Feature",
  "properties": {
    "iso:country":"US",
    "sg:address":"1415 E Pine St",
    "sg:city":"Deming",
    "sg:classifiers":[
        {
            "category":"Retail",
            "subcategory":"Auto Repair",
            "type":"Services"
        }
    ],
    "sg:phone":"+1 505 546 9315",
    "sg:postcode":"88030",
    "sg:province":"NM",
    "sg:tags":[
        "truck"
    ],
    "wof:name":"E & M Auto Repair",
    "wof:placetype":"venue"
},
  "geometry": {"coordinates":[-107.742712,32.268787],"type":"Point"}
}