{
  "type": "Feature",
  "properties": {
    "iso:country":"US",
    "sg:address":"501 Mountain Rd NE",
    "sg:city":"Albuquerque",
    "sg:classifiers":[
        {
            "category":"Government",
            "subcategory":"Office",
            "type":"Public Place"
        }
    ],
    "sg:phone":"+1 505 841 8983",
    "sg:postcode":"87102",
    "sg:province":"NM",
    "sg:tags":[
        "state",
        "inspection"
    ],
    "wof:name":"Labor & Industrial Div",
    "wof:placetype":"venue"
},
  "geometry": {"coordinates":[-106.639665,35.094187],"type":"Point"}
}