{
  "type": "Feature",
  "properties": {
    "addr:full":"620 E Greene St Carlsbad NM 88220",
    "addr:housenumber":"620",
    "addr:postcode":"88220",
    "addr:street":"E Greene St",
    "iso:country":"US",
    "sg:address":"620 E Greene St",
    "sg:city":"Carlsbad",
    "sg:classifiers":[
        {
            "category":"Professional",
            "subcategory":"Management & Consulting",
            "type":"Services"
        }
    ],
    "sg:phone":"+1 505 628 3471",
    "sg:postcode":"88220",
    "sg:province":"NM",
    "sg:tags":[
        "fuel"
    ],
    "wof:name":"Bureau Of Land Management",
    "wof:placetype":"venue"
},
  "geometry": {"coordinates":[-104.218345,32.418929],"type":"Point"}
}