{
  "type": "Feature",
  "properties": {
    "addr:full":"111 N Date St Truth Or Cnsqncs NM 87901",
    "addr:housenumber":"111",
    "addr:postcode":"87901",
    "addr:street":"N Date St",
    "iso:country":"US",
    "sg:address":"111 N Date St",
    "sg:city":"Truth Or Cnsqncs",
    "sg:classifiers":[
        {
            "category":"Personal",
            "subcategory":"Tattoo Parlor",
            "type":"Services"
        }
    ],
    "sg:phone":"+1 505 894 1687",
    "sg:postcode":"87901",
    "sg:province":"NM",
    "sg:tags":[
        "tattooing"
    ],
    "wof:name":"Tattoos By Leroy",
    "wof:placetype":"venue"
},
  "geometry": {"coordinates":[-107.250435,33.132046],"type":"Point"}
}