{
  "type": "Feature",
  "properties": {
    "addr:full":"109 N Allen Ave Farmington NM 87401",
    "addr:housenumber":"109",
    "addr:postcode":"87401",
    "addr:street":"N Allen Ave",
    "iso:country":"US",
    "sg:address":"109 N Allen Ave",
    "sg:city":"Farmington",
    "sg:classifiers":[
        {
            "category":"Building & Trades",
            "subcategory":"Equipment Rental",
            "type":"Services"
        }
    ],
    "sg:phone":"+1 505 325 0013",
    "sg:postcode":"87401",
    "sg:province":"NM",
    "sg:tags":[
        "leasing",
        "furniture"
    ],
    "wof:name":"Furniture Outlet",
    "wof:placetype":"venue"
},
  "geometry": {"coordinates":[-108.20671900000001,36.730204],"type":"Point"}
}