{
  "type": "Feature",
  "properties": {
    "addr:full":"6800 Beck Dr NE Albuquerque NM 87109",
    "addr:housenumber":"6800",
    "addr:postcode":"87109",
    "addr:street":"Beck Dr Ne",
    "iso:country":"US",
    "sg:address":"6800 Beck Dr NE",
    "sg:city":"Albuquerque",
    "sg:classifiers":[
        {
            "category":"Professional",
            "subcategory":"Management & Consulting",
            "type":"Services"
        }
    ],
    "sg:phone":"+1 505 821 2633",
    "sg:postcode":"87109",
    "sg:province":"NM",
    "sg:tags":[
        "consultant"
    ],
    "wof:name":"Axxant Corp",
    "wof:placetype":"venue"
},
  "geometry": {"coordinates":[-106.568376,35.152376],"type":"Point"}
}