{
  "type": "Feature",
  "properties": {
    "addr:full":"207 W Broadway St Farmington NM 87401",
    "addr:housenumber":"207",
    "addr:postcode":"87401",
    "addr:street":"W Broadway St",
    "iso:country":"US",
    "sg:address":"207 W Broadway St",
    "sg:city":"Farmington",
    "sg:classifiers":[
        {
            "category":"Personal",
            "subcategory":"Beauty Salon",
            "type":"Services"
        }
    ],
    "sg:phone":"+1 505 326 6311",
    "sg:postcode":"87401",
    "sg:province":"NM",
    "sg:tags":[
        "shop"
    ],
    "wof:name":"Hair Razors",
    "wof:placetype":"venue"
},
  "geometry": {"coordinates":[-108.206636,36.728002],"type":"Point"}
}