{
  "type": "Feature",
  "properties": {
    "addr:full":"9910 Trumbull Ave SE Albuquerque NM 87123",
    "addr:housenumber":"9910",
    "addr:postcode":"87123",
    "addr:street":"Trumbull Ave Se",
    "iso:country":"US",
    "sg:address":"9910 Trumbull Ave SE",
    "sg:city":"Albuquerque",
    "sg:classifiers":[
        {
            "category":"Professional",
            "subcategory":"Art Services",
            "type":"Services"
        }
    ],
    "sg:phone":"+1 505 271 0111",
    "sg:postcode":"87123",
    "sg:province":"NM",
    "sg:tags":[
        "commercial",
        "printing",
        "design"
    ],
    "wof:name":"Print Professionals",
    "wof:placetype":"venue"
},
  "geometry": {"coordinates":[-106.535883,35.06846],"type":"Point"}
}