{
  "type": "Feature",
  "properties": {
    "addr:full":"1401 General Somervell St NE Albuquerque NM 87112",
    "addr:housenumber":"1401",
    "addr:postcode":"87112",
    "addr:street":"General Somervell St Ne",
    "iso:country":"US",
    "sg:address":"1401 General Somervell St NE",
    "sg:city":"Albuquerque",
    "sg:classifiers":[
        {
            "category":"Shopping",
            "type":"Retail Goods"
        }
    ],
    "sg:phone":"+1 505 450 6857",
    "sg:postcode":"87112",
    "sg:province":"NM",
    "sg:tags":[
        "merchandise"
    ],
    "wof:name":"Hung Nguyen Cell Phone Access",
    "wof:placetype":"venue"
},
  "geometry": {"coordinates":[-106.542648,35.095072],"type":"Point"}
}