{
  "type": "Feature",
  "properties": {
    "iso:country":"US",
    "sg:address":"7 Ave Vista Grande",
    "sg:city":"Santa Fe",
    "sg:classifiers":[
        {
            "category":"Social Services",
            "type":"Services"
        }
    ],
    "sg:phone":"+1 505 466 7459",
    "sg:postcode":"87508",
    "sg:province":"NM",
    "sg:tags":[
        "organization",
        "welfare"
    ],
    "sg:website":"www.theranches.org",
    "wof:name":"New Mexico Girls Ranch",
    "wof:placetype":"venue"
},
  "geometry": {"coordinates":[-105.886952,35.536815],"type":"Point"}
}