{
  "type": "Feature",
  "properties": {
    "iso:country":"US",
    "sg:address":"107 Quesnel",
    "sg:city":"Taos",
    "sg:classifiers":[
        {
            "category":"Professional",
            "subcategory":"Art Services",
            "type":"Services"
        }
    ],
    "sg:phone":"+1 505 758 4047",
    "sg:postcode":"87571",
    "sg:province":"NM",
    "sg:tags":[
        "graphic",
        "designer"
    ],
    "wof:name":"Digerati Design",
    "wof:placetype":"venue"
},
  "geometry": {"coordinates":[-105.573689,36.405644],"type":"Point"}
}