{
  "type": "Feature",
  "properties": {
    "iso:country":"US",
    "sg:address":"303 Colbert Ave",
    "sg:city":"Springer",
    "sg:classifiers":[
        {
            "category":"Wholesale",
            "subcategory":"Farm Supplies",
            "type":"Manufacturing & Wholesale Goods"
        }
    ],
    "sg:phone":"+1 505 483 2608",
    "sg:postcode":"87747",
    "sg:province":"NM",
    "sg:tags":[
        "equipment",
        "livestock"
    ],
    "wof:name":"Ranchers Supply",
    "wof:placetype":"venue"
},
  "geometry": {"coordinates":[-104.597084,36.359929],"type":"Point"}
}