{
  "type": "Feature",
  "properties": {
    "iso:country":"US",
    "sg:address":"11901 Palm Springs Ave NE",
    "sg:city":"Albuquerque",
    "sg:classifiers":[
        {
            "category":"Organizations",
            "subcategory":"Religious Organization",
            "type":"Services"
        }
    ],
    "sg:phone":"+1 505 237 8057",
    "sg:postcode":"87111",
    "sg:province":"NM",
    "wof:name":"Elijah Ministries Inc",
    "wof:placetype":"venue"
},
  "geometry": {"coordinates":[-106.507313,35.116866],"type":"Point"}
}