{
  "type": "Feature",
  "properties": {
    "addr:full":"109 N Silver Ave Deming NM 88030",
    "addr:housenumber":"109",
    "addr:postcode":"88030",
    "addr:street":"N Silver Ave",
    "iso:country":"US",
    "sg:address":"109 N Silver Ave",
    "sg:city":"Deming",
    "sg:classifiers":[
        {
            "category":"Utilities",
            "subcategory":"Cable",
            "type":"Services"
        }
    ],
    "sg:phone":"+1 505 546 0417",
    "sg:postcode":"88030",
    "sg:province":"NM",
    "sg:tags":[
        "television"
    ],
    "wof:name":"Comcast Cable",
    "wof:placetype":"venue"
},
  "geometry": {"coordinates":[-107.7576,32.269927],"type":"Point"}
}