{
  "type": "Feature",
  "properties": {
    "iso:country":"US",
    "sg:address":"10207 Corona Ave NE",
    "sg:city":"Albuquerque",
    "sg:classifiers":[
        {
            "category":"Building & Trades",
            "subcategory":"Electrical",
            "type":"Services"
        }
    ],
    "sg:phone":"+1 888 663 9262",
    "sg:postcode":"87122",
    "sg:province":"NM",
    "sg:tags":[
        "fiber",
        "optic"
    ],
    "wof:name":"R M S Inc",
    "wof:placetype":"venue"
},
  "geometry": {"coordinates":[-106.530097,35.180132],"type":"Point"}
}