{
  "type": "Feature",
  "properties": {
    "iso:country":"US",
    "sg:address":"1601 S Main St",
    "sg:city":"Roswell",
    "sg:classifiers":[
        {
            "category":"Health Services",
            "subcategory":"Nursing And Care Facility",
            "type":"Services"
        }
    ],
    "sg:phone":"+1 505 623 6008",
    "sg:postcode":"88203",
    "sg:province":"NM",
    "sg:tags":[
        "home",
        "skilled",
        "convalescent"
    ],
    "wof:name":"Casa Maria Health Care Center",
    "wof:placetype":"venue"
},
  "geometry": {"coordinates":[-104.523079,33.374488],"type":"Point"}
}