{
  "type": "Feature",
  "properties": {
    "iso:country":"US",
    "sg:address":"3250 Southside River Rd",
    "sg:city":"Farmington",
    "sg:classifiers":[
        {
            "category":"Mining & Drilling",
            "type":"Manufacturing & Wholesale Goods"
        }
    ],
    "sg:phone":"+1 505 327 6222",
    "sg:postcode":"87401",
    "sg:province":"NM",
    "sg:tags":[
        "field",
        "oil"
    ],
    "sg:website":"www.bjservices.com",
    "wof:name":"B J SVC Co USA",
    "wof:placetype":"venue"
},
  "geometry": {"coordinates":[-108.162998,36.726468],"type":"Point"}
}