{
  "type": "Feature",
  "properties": {
    "iso:country":"US",
    "sg:address":"5009 Hallmarc Dr",
    "sg:city":"Farmington",
    "sg:classifiers":[
        {
            "category":"Building & Trades",
            "subcategory":"Landscaping Services",
            "type":"Services"
        }
    ],
    "sg:phone":"+1 505 599 9440",
    "sg:postcode":"87402",
    "sg:province":"NM",
    "sg:tags":[
        "machinery"
    ],
    "wof:name":"Premier Lawncare Co",
    "wof:placetype":"venue"
},
  "geometry": {"coordinates":[-108.124692,36.77335],"type":"Point"}
}