{
  "type": "Feature",
  "properties": {
    "iso:country":"US",
    "sg:address":"620 Dekalb Rd",
    "sg:city":"Farmington",
    "sg:classifiers":[
        {
            "category":"Professional",
            "type":"Services"
        }
    ],
    "sg:phone":"+1 505 325 5773",
    "sg:postcode":"87401",
    "sg:province":"NM",
    "sg:tags":[
        "establishment"
    ],
    "sg:website":"www.mosaicinfo.org",
    "wof:name":"Mosaic",
    "wof:placetype":"venue"
},
  "geometry": {"coordinates":[-108.1845,36.725741],"type":"Point"}
}