{
  "type": "Feature",
  "properties": {
    "iso:country":"US",
    "sg:address":"2204 N Clayton Ave",
    "sg:city":"Farmington",
    "sg:classifiers":[
        {
            "category":"Education",
            "subcategory":"Special Training",
            "type":"Public Place"
        }
    ],
    "sg:phone":"+1 505 325 3283",
    "sg:postcode":"87402",
    "sg:province":"NM",
    "wof:name":"Tutoring With Zane",
    "wof:placetype":"venue"
},
  "geometry": {"coordinates":[-108.166237,36.750956],"type":"Point"}
}