{
  "type": "Feature",
  "properties": {
    "addr:full":"3015 Central Ave SE Albuquerque NM 87106",
    "addr:housenumber":"3015",
    "addr:postcode":"87106",
    "addr:street":"Central Ave Se",
    "iso:country":"US",
    "sg:address":"3015 Central Ave SE",
    "sg:city":"Albuquerque",
    "sg:classifiers":[
        {
            "category":"Restaurant",
            "type":"Food & Drink"
        }
    ],
    "sg:phone":"+1 505 232 3474",
    "sg:postcode":"87106",
    "sg:province":"NM",
    "wof:name":"Crazy Fish Restaurant",
    "wof:placetype":"venue"
},
  "geometry": {"coordinates":[-106.61095,35.080726],"type":"Point"}
}