{
  "type": "Feature",
  "properties": {
    "iso:country":"US",
    "sg:address":"7008 2nd St NW",
    "sg:city":"Albuquerque",
    "sg:classifiers":[
        {
            "category":"Retail",
            "subcategory":"Auto Repair",
            "type":"Services"
        }
    ],
    "sg:phone":"+1 505 344 5693",
    "sg:postcode":"87107",
    "sg:province":"NM",
    "sg:tags":[
        "automobile",
        "electric"
    ],
    "wof:name":"H & C Truck Electrical Svc Inc",
    "wof:placetype":"venue"
},
  "geometry": {"coordinates":[-106.630584,35.158348],"type":"Point"}
}