{
  "type": "Feature",
  "properties": {
    "addr:full":"1913 Patricia Ct Las Cruces NM 88001",
    "addr:housenumber":"1913",
    "addr:postcode":"88001",
    "addr:street":"Patricia Ct",
    "iso:country":"US",
    "sg:address":"1913 Patricia Ct",
    "sg:city":"Las Cruces",
    "sg:classifiers":[
        {
            "category":"Building & Trades",
            "subcategory":"Construction",
            "type":"Services"
        }
    ],
    "sg:phone":"+1 505 525 2984",
    "sg:postcode":"88001",
    "sg:province":"NM",
    "sg:tags":[
        "general",
        "contractor"
    ],
    "wof:name":"Jeans Maintenance Services",
    "wof:placetype":"venue"
},
  "geometry": {"coordinates":[-106.761257,32.330765],"type":"Point"}
}