{
  "type": "Feature",
  "properties": {
    "addr:full":"605 W Coal Ave Gallup NM 87301",
    "addr:housenumber":"605",
    "addr:postcode":"87301",
    "addr:street":"W Coal Ave",
    "iso:country":"US",
    "sg:address":"605 W Coal Ave",
    "sg:city":"Gallup",
    "sg:classifiers":[
        {
            "category":"Professional",
            "subcategory":"Business Services",
            "type":"Services"
        }
    ],
    "sg:phone":"+1 505 863 3982",
    "sg:postcode":"87301",
    "sg:province":"NM",
    "sg:tags":[
        "recording",
        "studio"
    ],
    "wof:name":"Tohatchi Area Of Opportunity",
    "wof:placetype":"venue"
},
  "geometry": {"coordinates":[-108.747319,35.525426],"type":"Point"}
}