{
  "type": "Feature",
  "properties": {
    "iso:country":"US",
    "sg:address":"3734 Hawkins St NE",
    "sg:city":"Albuquerque",
    "sg:classifiers":[
        {
            "category":"Building & Trades",
            "subcategory":"Construction",
            "type":"Services"
        }
    ],
    "sg:phone":"+1 505 761 7162",
    "sg:postcode":"87109",
    "sg:province":"NM",
    "sg:tags":[
        "contractor"
    ],
    "sg:website":"www.solarindustriesinc.com",
    "wof:name":"Solar Industries",
    "wof:placetype":"venue"
},
  "geometry": {"coordinates":[-106.602704,35.162664],"type":"Point"}
}