{
  "type": "Feature",
  "properties": {
    "iso:country":"US",
    "sg:address":"306 Burro Ave",
    "sg:city":"Cloudcroft",
    "sg:classifiers":[
        {
            "category":"Real Estate",
            "subcategory":"Real Estate Agent",
            "type":"Services"
        }
    ],
    "sg:phone":"+1 505 682 3343",
    "sg:postcode":"88317",
    "sg:province":"NM",
    "wof:name":"Mack Gary Real Estate",
    "wof:placetype":"venue"
},
  "geometry": {"coordinates":[-105.744339,32.958537],"type":"Point"}
}