{
  "type": "Feature",
  "properties": {
    "iso:country":"US",
    "sg:address":"120 W Main St",
    "sg:city":"Farmington",
    "sg:classifiers":[
        {
            "category":"Shopping",
            "subcategory":"Books",
            "type":"Retail Goods"
        }
    ],
    "sg:phone":"+1 505 325 2541",
    "sg:postcode":"87401",
    "sg:province":"NM",
    "sg:tags":[
        "organization",
        "membership",
        "religious",
        "dealer"
    ],
    "wof:name":"Christian Science Reading Room",
    "wof:placetype":"venue"
},
  "geometry": {"coordinates":[-108.205573,36.729166],"type":"Point"}
}