{
  "type": "Feature",
  "properties": {
    "iso:country":"US",
    "sg:address":"2801 Yale Blvd SE",
    "sg:city":"Albuquerque",
    "sg:classifiers":[
        {
            "category":"Parking",
            "type":"Transportation"
        }
    ],
    "sg:phone":"+1 505 242 5181",
    "sg:postcode":"87106",
    "sg:province":"NM",
    "sg:tags":[
        "personal",
        "automobile"
    ],
    "sg:website":"www.airportfastpark.com",
    "wof:name":"Airport Fast Park",
    "wof:placetype":"venue"
},
  "geometry": {"coordinates":[-106.62215,35.050025],"type":"Point"}
}