{
  "type": "Feature",
  "properties": {
    "iso:country":"US",
    "sg:address":"219 Delgado St",
    "sg:city":"Santa Fe",
    "sg:classifiers":[
        {
            "category":"Shopping",
            "type":"Retail Goods"
        }
    ],
    "sg:phone":"+1 505 983 6537",
    "sg:postcode":"87501",
    "sg:province":"NM",
    "sg:tags":[
        "material",
        "artist",
        "supply"
    ],
    "wof:name":"In Art",
    "wof:placetype":"venue"
},
  "geometry": {"coordinates":[-105.931187,35.683848],"type":"Point"}
}