{
  "type": "Feature",
  "properties": {
    "addr:full":"1309 W 15th St Clovis NM 88101",
    "addr:housenumber":"1309",
    "addr:postcode":"88101",
    "addr:street":"W 15Th St",
    "iso:country":"US",
    "sg:address":"1309 W 15th St",
    "sg:city":"Clovis",
    "sg:classifiers":[
        {
            "category":"Real Estate",
            "subcategory":"Real Estate Agent",
            "type":"Services"
        }
    ],
    "sg:phone":"+1 505 769 1995",
    "sg:postcode":"88101",
    "sg:province":"NM",
    "sg:tags":[
        "building",
        "operator",
        "apartment"
    ],
    "wof:name":"Gatewood Village",
    "wof:placetype":"venue"
},
  "geometry": {"coordinates":[-103.220586,34.41271],"type":"Point"}
}