{
  "type": "Feature",
  "properties": {
    "iso:country":"US",
    "sg:address":"609 N Elm St",
    "sg:city":"Carlsbad",
    "sg:classifiers":[
        {
            "category":"Organizations",
            "subcategory":"Non-profit Organization",
            "type":"Services"
        }
    ],
    "sg:phone":"+1 505 234 9658",
    "sg:postcode":"88220",
    "sg:province":"NM",
    "sg:tags":[
        "social"
    ],
    "wof:name":"David Travis",
    "wof:placetype":"venue"
},
  "geometry": {"coordinates":[-104.23974800000001,32.428452],"type":"Point"}
}