{
  "type": "Feature",
  "properties": {
    "iso:country":"US",
    "sg:address":"123 W 12th St",
    "sg:city":"Silver City",
    "sg:classifiers":[
        {
            "category":"Food & Beverages",
            "subcategory":"Groceries & Convenience Stores",
            "type":"Retail Goods"
        }
    ],
    "sg:phone":"+1 505 538 9772",
    "sg:postcode":"88061",
    "sg:province":"NM",
    "wof:name":"Snappy Mart Stores Inc",
    "wof:placetype":"venue"
},
  "geometry": {"coordinates":[-108.27700400000001,32.777657],"type":"Point"}
}