{
  "type": "Feature",
  "properties": {
    "iso:country":"US",
    "sg:address":"326 N Bolton Rd",
    "sg:city":"Artesia",
    "sg:phone":"+1 505 746 3725",
    "sg:postcode":"88210",
    "sg:province":"NM",
    "sg:tags":[
        "farm",
        "field",
        "crop",
        "cotton"
    ],
    "wof:name":"Horner Farms Inc",
    "wof:placetype":"venue"
},
  "geometry": {"coordinates":[-104.377955,32.892496],"type":"Point"}
}