{
  "type": "Feature",
  "properties": {
    "addr:full":"7000 Prospect Pl NE Albuquerque NM 87110",
    "addr:housenumber":"7000",
    "addr:postcode":"87110",
    "addr:street":"Prospect Pl Ne",
    "iso:country":"US",
    "sg:address":"7000 Prospect Pl NE",
    "sg:city":"Albuquerque",
    "sg:classifiers":[
        {
            "category":"Banks & Credit Unions",
            "subcategory":"Bank",
            "type":"Services"
        },
        {
            "category":"Banks & Credit Unions",
            "subcategory":"Financial Services",
            "type":"Services"
        }
    ],
    "sg:phone":"+1 505 349 2325",
    "sg:postcode":"87110",
    "sg:province":"NM",
    "sg:tags":[
        "saving",
        "loan",
        "commercial"
    ],
    "wof:name":"Chase",
    "wof:placetype":"venue"
},
  "geometry": {"coordinates":[-106.56665,35.10767],"type":"Point"}
}