{
  "type": "Feature",
  "properties": {
    "iso:country":"US",
    "sg:address":"805 Arnold St",
    "sg:city":"Lordsburg",
    "sg:classifiers":[
        {
            "category":"Professional",
            "subcategory":"Business Services",
            "type":"Services"
        }
    ],
    "sg:phone":"+1 505 542 3757",
    "sg:postcode":"88045",
    "sg:province":"NM",
    "wof:name":"National Education Assoc",
    "wof:placetype":"venue"
},
  "geometry": {"coordinates":[-108.702024,32.343678],"type":"Point"}
}