{
  "type": "Feature",
  "properties": {
    "iso:country":"US",
    "sg:address":"175 E Thorpe Rd",
    "sg:city":"Las Cruces",
    "sg:classifiers":[
        {
            "category":"Building & Trades",
            "subcategory":"Construction",
            "type":"Services"
        }
    ],
    "sg:phone":"+1 505 523 2027",
    "sg:postcode":"88007",
    "sg:province":"NM",
    "wof:name":"Del Rey Builders",
    "wof:placetype":"venue"
},
  "geometry": {"coordinates":[-106.81537,32.389724],"type":"Point"}
}