{
  "type": "Feature",
  "properties": {
    "iso:country":"US",
    "sg:address":"302 W Main St",
    "sg:city":"Artesia",
    "sg:classifiers":[
        {
            "category":"Home & Garden",
            "subcategory":"Furniture",
            "type":"Retail Goods"
        }
    ],
    "sg:phone":"+1 505 746 9402",
    "sg:postcode":"88210",
    "sg:province":"NM",
    "wof:name":"Ken-Mar Furniture",
    "wof:placetype":"venue"
},
  "geometry": {"coordinates":[-104.399925,32.84228],"type":"Point"}
}