{
  "type": "Feature",
  "properties": {
    "iso:country":"US",
    "sg:address":"704 S Orchard Ave",
    "sg:city":"Farmington",
    "sg:classifiers":[
        {
            "category":"Building & Trades",
            "subcategory":"Construction",
            "type":"Services"
        }
    ],
    "sg:phone":"+1 505 324 0700",
    "sg:postcode":"87401",
    "sg:province":"NM",
    "sg:tags":[
        "steel",
        "house",
        "erect",
        "structural"
    ],
    "wof:name":"Liberty Construction Co",
    "wof:placetype":"venue"
},
  "geometry": {"coordinates":[-108.20550799999999,36.723068],"type":"Point"}
}