{
  "type": "Feature",
  "properties": {
    "iso:country":"US",
    "sg:address":"203 Wellesley Dr SE",
    "sg:city":"Albuquerque",
    "sg:classifiers":[
        {
            "category":"Personal",
            "subcategory":"Beauty Salon",
            "type":"Services"
        }
    ],
    "sg:phone":"+1 505 254 4820",
    "sg:postcode":"87106",
    "sg:province":"NM",
    "wof:name":"Kowlix",
    "wof:placetype":"venue"
},
  "geometry": {"coordinates":[-106.60837600000001,35.077295],"type":"Point"}
}