{
  "type": "Feature",
  "properties": {
    "iso:country":"US",
    "sg:address":"811 6th St",
    "sg:city":"Las Vegas",
    "sg:classifiers":[
        {
            "category":"Shopping",
            "subcategory":"Clothing, Apparel, & Fashions",
            "type":"Retail Goods"
        }
    ],
    "sg:phone":"+1 505 425 6991",
    "sg:postcode":"87701",
    "sg:province":"NM",
    "sg:tags":[
        "organization",
        "religious"
    ],
    "wof:name":"Catholic Ladies Altar Soc",
    "wof:placetype":"venue"
},
  "geometry": {"coordinates":[-105.217046,35.597869],"type":"Point"}
}