{
  "type": "Feature",
  "properties": {
    "iso:country":"US",
    "sg:address":"808 N Hudson St",
    "sg:city":"Silver City",
    "sg:classifiers":[
        {
            "category":"Autos & Motor Vehicles",
            "subcategory":"Automobile Sales",
            "type":"Retail Goods"
        }
    ],
    "sg:phone":"+1 505 388 4848",
    "sg:postcode":"88061",
    "sg:province":"NM",
    "sg:tags":[
        "car",
        "dealer"
    ],
    "wof:name":"Taylor Truck & Auto",
    "wof:placetype":"venue"
},
  "geometry": {"coordinates":[-108.274378,32.774336],"type":"Point"}
}