{
  "type": "Feature",
  "properties": {
    "addr:full":"651 State Hwy 314 NW Los Lunas NM 87031",
    "addr:housenumber":"651",
    "addr:postcode":"87031",
    "addr:street":"State Hwy 314 Nw",
    "iso:country":"US",
    "sg:address":"651 State Hwy 314 NW",
    "sg:city":"Los Lunas",
    "sg:classifiers":[
        {
            "category":"Professional",
            "subcategory":"Lawyer & Legal Services",
            "type":"Services"
        }
    ],
    "sg:phone":"+1 505 865 9696",
    "sg:postcode":"87031",
    "sg:province":"NM",
    "sg:tags":[
        "attorney"
    ],
    "wof:name":"David C Chavez Law Office",
    "wof:placetype":"venue"
},
  "geometry": {"coordinates":[-106.733536,34.818021],"type":"Point"}
}