{
  "type": "Feature",
  "properties": {
    "addr:full":"315 E Spruce St Deming NM 88030",
    "addr:housenumber":"315",
    "addr:postcode":"88030",
    "addr:street":"E Spruce St",
    "iso:country":"US",
    "sg:address":"315 E Spruce St",
    "sg:city":"Deming",
    "sg:classifiers":[
        {
            "category":"Personal",
            "subcategory":"Beauty Salon",
            "type":"Services"
        }
    ],
    "sg:phone":"+1 505 544 3345",
    "sg:postcode":"88030",
    "sg:province":"NM",
    "sg:tags":[
        "shop"
    ],
    "wof:name":"Hair We Are",
    "wof:placetype":"venue"
},
  "geometry": {"coordinates":[-107.754886,32.268119],"type":"Point"}
}