{
  "type": "Feature",
  "properties": {
    "iso:country":"US",
    "sg:address":"5248 2nd St NW",
    "sg:city":"Albuquerque",
    "sg:classifiers":[
        {
            "category":"Shopping",
            "subcategory":"Discount & Variety Stores",
            "type":"Retail Goods"
        }
    ],
    "sg:phone":"+1 505 259 4002",
    "sg:postcode":"87107",
    "sg:province":"NM",
    "sg:tags":[
        "merchandise",
        "general"
    ],
    "wof:name":"Hensonjim Sales Inc",
    "wof:placetype":"venue"
},
  "geometry": {"coordinates":[-106.636743,35.137796],"type":"Point"}
}