{
  "type": "Feature",
  "properties": {
    "iso:country":"US",
    "sg:address":"441 Monroe St NE",
    "sg:city":"Albuquerque",
    "sg:classifiers":[
        {
            "category":"Organizations",
            "subcategory":"Non-profit Organization",
            "type":"Services"
        }
    ],
    "sg:phone":"+1 505 260 6106",
    "sg:postcode":"87108",
    "sg:province":"NM",
    "wof:name":"Family Focus Ctr",
    "wof:placetype":"venue"
},
  "geometry": {"coordinates":[-106.590874,35.084859],"type":"Point"}
}