{
  "type": "Feature",
  "properties": {
    "addr:full":"3199 N White Sands Blvd Alamogordo NM 88310",
    "addr:housenumber":"3199",
    "addr:postcode":"88310",
    "addr:street":"N White Sands Blvd",
    "iso:country":"US",
    "sg:address":"3199 N White Sands Blvd",
    "sg:city":"Alamogordo",
    "sg:classifiers":[
        {
            "category":"Shopping",
            "subcategory":"Jewelry",
            "type":"Retail Goods"
        }
    ],
    "sg:phone":"+1 505 434 3270",
    "sg:postcode":"88310",
    "sg:province":"NM",
    "sg:tags":[
        "jeweler"
    ],
    "wof:name":"Zales The Diamond Store",
    "wof:placetype":"venue"
},
  "geometry": {"coordinates":[-105.96339,32.932468],"type":"Point"}
}