{
  "type": "Feature",
  "properties": {
    "addr:full":"3 Kirkland Rd Silver City NM 88061",
    "addr:housenumber":"3",
    "addr:postcode":"88061",
    "addr:street":"Kirkland Rd",
    "iso:country":"US",
    "sg:address":"3 Kirkland Rd",
    "sg:city":"Silver City",
    "sg:classifiers":[
        {
            "category":"Building & Trades",
            "subcategory":"Construction",
            "type":"Services"
        }
    ],
    "sg:phone":"+1 505 388 9213",
    "sg:postcode":"88061",
    "sg:province":"NM",
    "sg:tags":[
        "excavating",
        "contractor"
    ],
    "wof:name":"Brewer Backhoe & Excavation",
    "wof:placetype":"venue"
},
  "geometry": {"coordinates":[-108.209219,32.783499],"type":"Point"}
}