{
  "type": "Feature",
  "properties": {
    "addr:full":"616 Amherst Dr SE Albuquerque NM 87106",
    "addr:housenumber":"616",
    "addr:postcode":"87106",
    "addr:street":"Amherst Dr Se",
    "iso:country":"US",
    "sg:address":"616 Amherst Dr SE",
    "sg:city":"Albuquerque",
    "sg:classifiers":[
        {
            "category":"Building & Trades",
            "subcategory":"Construction",
            "type":"Services"
        }
    ],
    "sg:phone":"+1 505 265 5794",
    "sg:postcode":"87106",
    "sg:province":"NM",
    "sg:tags":[
        "contractor"
    ],
    "wof:name":"Nob Hill Painting",
    "wof:placetype":"venue"
},
  "geometry": {"coordinates":[-106.605513,35.070316],"type":"Point"}
}