{
  "type": "Feature",
  "properties": {
    "iso:country":"US",
    "sg:address":"8300 Wyoming Blvd NE",
    "sg:city":"Albuquerque",
    "sg:classifiers":[
        {
            "category":"Real Estate",
            "subcategory":"Real Estate Operator",
            "type":"Services"
        }
    ],
    "sg:phone":"+1 505 821 6262",
    "sg:postcode":"87113",
    "sg:province":"NM",
    "sg:tags":[
        "building",
        "apartment"
    ],
    "wof:name":"Pinnacle Estates Apts",
    "wof:placetype":"venue"
},
  "geometry": {"coordinates":[-106.559937,35.178115],"type":"Point"}
}