{
  "type": "Feature",
  "properties": {
    "iso:country":"US",
    "sg:address":"714 N Beech Ave",
    "sg:city":"Roswell",
    "sg:classifiers":[
        {
            "category":"Real Estate",
            "subcategory":"Real Estate Agent",
            "type":"Services"
        }
    ],
    "sg:phone":"+1 505 622 4841",
    "sg:postcode":"88201",
    "sg:province":"NM",
    "wof:name":"Ogas Appraisals",
    "wof:placetype":"venue"
},
  "geometry": {"coordinates":[-104.509111,33.399839],"type":"Point"}
}