{
  "type": "Feature",
  "properties": {
    "iso:country":"US",
    "sg:address":"2879 Trades West Rd",
    "sg:city":"Santa Fe",
    "sg:classifiers":[
        {
            "category":"Manufacturing",
            "subcategory":"Tools & Machinery",
            "type":"Manufacturing & Wholesale Goods"
        },
        {
            "category":"Retail",
            "subcategory":"Auto Repair",
            "type":"Services"
        }
    ],
    "sg:phone":"+1 505 474 0059",
    "sg:postcode":"87507",
    "sg:province":"NM",
    "sg:tags":[
        "shop",
        "automobile",
        "machine",
        "industrial",
        "mfg"
    ],
    "wof:name":"J & R Machine Shop",
    "wof:placetype":"venue"
},
  "geometry": {"coordinates":[-105.99202099999999,35.661234],"type":"Point"}
}