{
  "type": "Feature",
  "properties": {
    "iso:country":"US",
    "sg:address":"1010 Zuni Dr",
    "sg:city":"Alamogordo",
    "sg:classifiers":[
        {
            "category":"Manufacturing",
            "subcategory":"Building Materials",
            "type":"Manufacturing & Wholesale Goods"
        }
    ],
    "sg:phone":"+1 505 437 7134",
    "sg:postcode":"88310",
    "sg:province":"NM",
    "sg:tags":[
        "machine",
        "wood",
        "structural"
    ],
    "wof:name":"French Brothers Inc",
    "wof:placetype":"venue"
},
  "geometry": {"coordinates":[-105.987503,32.876142],"type":"Point"}
}