{
  "type": "Feature",
  "properties": {
    "iso:country":"US",
    "sg:address":"1042 S Main St",
    "sg:city":"Las Cruces",
    "sg:classifiers":[
        {
            "category":"Real Estate",
            "subcategory":"Architect",
            "type":"Services"
        }
    ],
    "sg:phone":"+1 505 525 2000",
    "sg:postcode":"88005",
    "sg:province":"NM",
    "sg:tags":[
        "planning",
        "architectural",
        "land"
    ],
    "wof:name":"Newby Steve Architects & Assoc",
    "wof:placetype":"venue"
},
  "geometry": {"coordinates":[-106.778887,32.299841],"type":"Point"}
}