{
  "type": "Feature",
  "properties": {
    "addr:full":"244 N 1st St Raton NM 87740",
    "addr:housenumber":"244",
    "addr:postcode":"87740",
    "addr:street":"N 1St St",
    "iso:country":"US",
    "sg:address":"244 N 1st St",
    "sg:city":"Raton",
    "sg:classifiers":[
        {
            "category":"Retail",
            "subcategory":"Funeral Services",
            "type":"Services"
        }
    ],
    "sg:phone":"+1 505 445 3757",
    "sg:postcode":"87740",
    "sg:province":"NM",
    "sg:tags":[
        "director"
    ],
    "wof:name":"Alderette-Pomeroy Funeral Home",
    "wof:placetype":"venue"
},
  "geometry": {"coordinates":[-104.437904,36.903753],"type":"Point"}
}