{
  "type": "Feature",
  "properties": {
    "addr:full":"104 E Aztec Ave Gallup NM 87301",
    "addr:housenumber":"104",
    "addr:postcode":"87301",
    "addr:street":"E Aztec Ave",
    "iso:country":"US",
    "sg:address":"104 E Aztec Ave",
    "sg:city":"Gallup",
    "sg:classifiers":[
        {
            "category":"Professional",
            "subcategory":"Lawyer & Legal Services",
            "type":"Services"
        }
    ],
    "sg:phone":"+1 505 722 4463",
    "sg:postcode":"87301",
    "sg:province":"NM",
    "sg:tags":[
        "attorney"
    ],
    "wof:name":"Mason Issacson & Macik",
    "wof:placetype":"venue"
},
  "geometry": {"coordinates":[-108.739645,35.52703],"type":"Point"}
}