{
  "type": "Feature",
  "properties": {
    "iso:country":"US",
    "sg:address":"505 Burro Ave",
    "sg:city":"Cloudcroft",
    "sg:classifiers":[
        {
            "category":"Real Estate",
            "subcategory":"Architect",
            "type":"Services"
        }
    ],
    "sg:phone":"+1 505 682 1589",
    "sg:postcode":"88317",
    "sg:province":"NM",
    "wof:name":"Imaginit Architectural Plng",
    "wof:placetype":"venue"
},
  "geometry": {"coordinates":[-105.742818,32.958687],"type":"Point"}
}