{
  "type": "Feature",
  "properties": {
    "iso:country":"US",
    "sg:address":"520 Central Ave SE",
    "sg:city":"Albuquerque",
    "sg:classifiers":[
        {
            "category":"Recreation",
            "type":"Entertainment"
        }
    ],
    "sg:phone":"+1 505 842 1080",
    "sg:postcode":"87102",
    "sg:province":"NM",
    "sg:tags":[
        "instruction",
        "yoga"
    ],
    "wof:name":"Bhaza Yoga Studio",
    "wof:placetype":"venue"
},
  "geometry": {"coordinates":[-106.64001,35.082972],"type":"Point"}
}