{
  "type": "Feature",
  "properties": {
    "iso:country":"US",
    "sg:address":"1570 Center Ct",
    "sg:city":"Santa Fe",
    "sg:classifiers":[
        {
            "category":"Retail",
            "subcategory":"Car Wash",
            "type":"Services"
        }
    ],
    "sg:phone":"+1 505 438 3951",
    "sg:postcode":"87507",
    "sg:province":"NM",
    "sg:tags":[
        "automobile",
        "detail",
        "clean"
    ],
    "wof:name":"Bob Ladd Auto Detail",
    "wof:placetype":"venue"
},
  "geometry": {"coordinates":[-106.024145,35.636267],"type":"Point"}
}